Workbook
Name a: [1]ISICrev3.1!$E:$F
Name Calculated_Relationship_HS12___HS07: '[2]Correlation HS2012-HS2007'!#REF!
Name CAP_CT: #REF!
Name CAP_CT: #REF!
Name CAP_GFCF: #REF!
Name CAP_GFCF: #REF!
Name CAP_IT: #REF!
Name CAP_IT: #REF!
Name CAP_OCon: #REF!
Name CAP_OCon: #REF!
Name CAP_OMach: #REF!
Name CAP_OMach: #REF!
Name CAP_Other: #REF!
Name CAP_Other: #REF!
Name CAP_QI: #REF!
Name CAP_QI: #REF!
Name CAP_RStruc: #REF!
Name CAP_RStruc: #REF!
Name CAP_Soft: #REF!
Name CAP_Soft: #REF!
Name CAP_TraEq: #REF!
Name CAP_TraEq: #REF!
Name CAPIT: #REF!
Name CAPIT: #REF!
Name CAPIT_QI: #REF!
Name CAPIT_QI: #REF!
Name capit_qph: #REF!
Name capit_qph: #REF!
Name CAPNIT: #REF!
Name CAPNIT: #REF!
Name CAPNIT_QI: #REF!
Name CAPNIT_QI: #REF!
Name capnit_qph: #REF!
Name capnit_qph: #REF!
Name FLAPPIE: #REF!
Name FLAPPIE: #REF!
Name go_level_top1: OFFSET('[3]35-sector'!$E$36,MATCH(#REF!,'[3]35-sector'!$E$37:$E$71,0),2,1,8)
Name HS: '[4]HS02_CPC1.1_SITC3_ISIC3.1 (2)'!#REF!
Name ISIC05: '[5]CNH EXIOBASE Output'!$D$4
Name ISIC06: '[5]CNH EXIOBASE Output'!$E$4
Name ISIC20: 'KOR WIOD IO-tables'!#REF!
Name ISIC21: 'KOR WIOD IO-tables'!#REF!
Name ISIC231: '[5]CNH EXIOBASE Output'!$N$4
Name ISIC239: '[5]CNH EXIOBASE Output'!$O$4
Name ISIC241: '[5]CNH EXIOBASE Output'!$P$4
Name ISIC242: '[5]CNH EXIOBASE Output'!$Q$4
Name ISIC351: '[5]CNH EXIOBASE Output'!$Y$4
Name ISIC352T353: '[5]CNH EXIOBASE Output'!$Z$4
Name M1_stone: '[3]2000'!$E$1382:$BV$1451
Name M2_stone: '[3]2000'!$E$1524:$BV$1593
Name M3_stone: '[3]2000'!$E$1737:$BV$1806
Name Matrix1: #REF!
Name rca_trad_2010: '[6]13-sector VAX_G_2010'!$C$141:$P$203
Name rca_trad_2011: '[6]13-sector VAX_G_2011'!$C$141:$P$203
Name rca_trad_2012: '[6]13-sector VAX_G_2012'!$C$141:$P$203
Name rca_trad_2013: '[6]13-sector VAX_G_2013'!$C$141:$P$203
Name rca_trad_2014: '[6]13-sector VAX_G_2014'!$C$141:$P$203
Name rca_trad_2015: '[6]13-sector VAX_G_2015'!$C$141:$P$203
Name rca_trad_2016: '[6]13-sector VAX_G_2016'!$C$141:$P$203
Name rca_trad_2017: '[6]13-sector VAX_G_2017'!$C$141:$P$203

Sheet About
A1: GaHEbIC Government and Household Expenditures by ISIC Code
A3: Source: | B3: Most Industries
B4: OECD
B5: 2015, 2018, 2020
B6: Input-Output Tables 2018, 2021, 2023 Editions (ISIC Rev. 4)
B7: https://stats.oecd.org/Index.aspx?DataSetCode=IOTSI4_2018
B8: https://stats.oecd.org/Index.aspx?DataSetCode=IOTS_2021
B9: https://www.oecd.org/sti/ind/input-outputtables.htm
B10: Variable: TTL
B13: Split for Chemicals/Pharmaceuticals and Coal/Petroleum Extraction Industries
B14: World Input-Output Database
B15: 2016
B16: National IO Tables
B17: http://www.wiod.org/database/niots16
B18: KOR NIOT, 2014
B20: Split for All Other ISIC Codes
B21: Exiobase
B22: 2019
B23: Exiobase 3rx, 2016
B24: https://zenodo.org/record/2654460#.YEFjHmhKg2w
B25: KOR, Final Demand Matrix
A27: Notes
A29: We use WIOD (chem/pharma) and EXIOBASE (all others) to make splits between the ISIC code sectors.
A31: We convert USD using the following conversion factors
A32: 0.96868157 | B32: 2012 USD per 2015 USD
A33: 0.91 | B33: 2012 USD per 2018 USD
A34: 0.88711067 | B34: 2012 USD per 2020 USD

Sheet OECD TTL - 2018
A2: Dataset: Input-Output Tables 2018 edition
A3: Variable | C3: TTL: Total
A4: Country | C4: KOR: Korea
A5: Time | C5: 2015
A6: Unit | C6: US Dollar, Millions
A7: To: (sector in column) | C7: D01T03: Agriculture, forestry and fishing | D7: D05T06: Mining and extraction of energy producing products | E7: D07T08: Mining and quarrying of non-energy producing products | F7: D09: Mining support service activities | G7: D10T12: Food products, beverages and tobacco | H7: D13T15: Textiles, wearing apparel, leather and related products | I7: D16: Wood and products of wood and cork | J7: D17T18: Paper products and printing | K7: D19: Coke and refined petroleum products | L7: D20T21: Chemicals and pharmaceutical products | M7: D22: Rubber and plastic products | N7: D23: Other non-metallic mineral products | O7: D24: Basic metals | P7: D25: Fabricated metal products | Q7: D26: Computer, electronic and optical products | R7: D27: Electrical equipment | S7: D28: Machinery and equipment, nec | T7: D29: Motor vehicles, trailers and semi-trailers | U7: D30: Other transport equipment | V7: D31T33: Other manufacturing; repair and installation of machinery and equipment | W7: D35T39: Electricity, gas, water supply, sewerage, waste and remediation services | X7: D41T43: Construction | Y7: D45T47: Wholesale and retail trade; repair of motor vehicles | Z7: D49T53: Transportation and storage | AA7: D55T56: Accomodation and food services | AB7: D58T60: Publishing, audiovisual and broadcasting activities | AC7: D61: Telecommunications | AD7: D62T63: IT and other information services | AE7: D64T66: Financial and insurance activities | AF7: D68: Real estate activities | AG7: D69T82: Other business sector services | AH7: D84: Public admin. and defence; compulsory social security | AI7: D85: Education | AJ7: D86T88: Human health and social work | AK7: D90T96: Arts, entertainment, recreation and other service activities | AL7: D97T98: Private households with employed persons | AM7: HFCE: Final consumption expenditure of households | AN7: NPISH: Final consumption expenditure of non-profit institutions serving households | AO7: GGFC: Final consumption expenditure of general government | AP7: GFCF: Gross Fixed Capital Formation | AQ7: INVNT: Changes in inventories | AR7: CONS_ABR: Direct purchases abroad by residents (imports) | AS7: CONS_NONRES: Direct purchases by non-residents (exports) | AT7: EXPO: Exports (cross border) | AU7: IMPO: Imports (cross border) | AV7: Households and orgs serving households
A8: From: (sector in row)
A9: TTL_01T03: Agriculture, forestry and fishing | C9: 4722.3 | D9: 8.4 | E9: 3.5 | F9: 0 | G9: 27898.7 | H9: 1366.4 | I9: 939.5 | J9: 502.4 | K9: 65.5 | L9: 1671.1 | M9: 591.8 | N9: 16.5 | O9: 77.9 | P9: 31.8 | Q9: 21.2 | R9: 21.4 | S9: 30.1 | T9: 19 | U9: 34.1 | V9: 124.8 | W9: 123.7 | X9: 313.8 | Y9: 1580.4 | Z9: 146.3 | AA9: 3624.3 | AB9: 30.5 | AC9: 3.1 | AD9: 14 | AE9: 24 | AF9: 41.4 | AG9: 422.6 | AH9: 367.4 | AI9: 279.4 | AJ9: 265.5 | AK9: 265.4 | AL9: 0 | AM9: 11293.8 | AN9: 17.3 | AO9: 761.7 | AP9: 382.6 | AQ9: -6.7 | AR9: 157.9 | AS9: 118.2 | AT9: 827.1 | AU9: -8239 | AV9: =AM9+AN9 -> 11311.1
A10: TTL_05T06: Mining and extraction of energy producing products | C10: 73 | D10: 51.2 | E10: 6.7 | F10: 0.7 | G10: 164.9 | H10: 52 | I10: 11.1 | J10: 143.1 | K10: 53282.7 | L10: 4330.4 | M10: 235.5 | N10: 439.2 | O10: 3659.1 | P10: 80.2 | Q10: 38.4 | R10: 49.2 | S10: 140.5 | T10: 180.3 | U10: 148.7 | V10: 28.3 | W10: 12265.4 | X10: 132.8 | Y10: 337 | Z10: 293 | AA10: 260.5 | AB10: 12.6 | AC10: 22.3 | AD10: 7.2 | AE10: 43.9 | AF10: 64.3 | AG10: 150.5 | AH10: 98.7 | AI10: 164.1 | AJ10: 235.1 | AK10: 254.5 | AL10: 0 | AM10: 450.9 | AN10: 0.5 | AO10: 15.1 | AP10: 699.2 | AQ10: -17 | AR10: 5.3 | AS10: 1.4 | AT10: 5.1 | AU10: -77242.4 | AV10: =AM10+AN10 -> 451.4
A11: TTL_07T08: Mining and quarrying of non-energy producing products | C11: 13.4 | D11: 1.7 | E11: 34 | F11: 0 | G11: 14.9 | H11: 6.7 | I11: 2.1 | J11: 25.5 | K11: 515.3 | L11: 654.9 | M11: 18.5 | N11: 751.6 | O11: 9125.7 | P11: 449.9 | Q11: 142.6 | R11: 287 | S11: 211.1 | T11: 79.2 | U11: 77.1 | V11: 72.1 | W11: 115.3 | X11: 814.1 | Y11: 38.6 | Z11: 13.9 | AA11: 7.7 | AB11: 0.8 | AC11: 1.9 | AD11: 1.4 | AE11: 2.2 | AF11: 20.7 | AG11: 11.2 | AH11: 18.5 | AI11: 3.1 | AJ11: 4.2 | AK11: 10.2 | AL11: 0 | AM11: 48 | AN11: 0 | AO11: 2.7 | AP11: 64.2 | AQ11: -2.9 | AR11: 2.8 | AS11: 0.2 | AT11: 343.1 | AU11: -11225.8 | AV11: =AM11+AN11 -> 48
A12: TTL_09: Mining support service activities | C12: 9.4 | D12: 0.9 | E12: 1.9 | F12: 0 | G12: 1.3 | H12: 0.1 | I12: 0.1 | J12: 0.7 | K12: 6.6 | L12: 1.9 | M12: 2.1 | N12: 0.9 | O12: 2.9 | P12: 0.5 | Q12: 0.4 | R12: 0.2 | S12: 1.5 | T12: 0.3 | U12: 0.3 | V12: 0.3 | W12: 8.6 | X12: 16.8 | Y12: 0.3 | Z12: 1.2 | AA12: 0.2 | AB12: 0 | AC12: 0 | AD12: 0.1 | AE12: 0.1 | AF12: 0 | AG12: 0.6 | AH12: 1.3 | AI12: 0.7 | AJ12: 0.1 | AK12: 0.1 | AL12: 0 | AM12: 0.8 | AN12: 0 | AO12: 6.1 | AP12: 0.7 | AQ12: 0.1 | AR12: 0.5 | AS12: 0 | AT12: 17 | AU12: -39.9 | AV12: =AM12+AN12 -> 0.8
A13: TTL_10T12: Food products, beverages and tobacco | C13: 5960.6 | D13: 1 | E13: 2 | F13: 0 | G13: 24001.4 | H13: 917.8 | I13: 36.3 | J13: 265.5 | K13: 179.4 | L13: 3028.4 | M13: 200.2 | N13: 85.8 | O13: 87.3 | P13: 69.1 | Q13: 127.1 | R13: 52.3 | S13: 87.2 | T13: 68.9 | U13: 104.1 | V13: 74.1 | W13: 247.6 | X13: 352.2 | Y13: 3094.6 | Z13: 228.5 | AA13: 23070.1 | AB13: 69.9 | AC13: 18.8 | AD13: 49.5 | AE13: 120.9 | AF13: 78.8 | AG13: 599.5 | AH13: 1579.9 | AI13: 1285 | AJ13: 2670.7 | AK13: 1467.3 | AL13: 0 | AM13: 38819.1 | AN13: 148.3 | AO13: 925.2 | AP13: 162.7 | AQ13: 12.3 | AR13: 650.4 | AS13: 467.4 | AT13: 4654.7 | AU13: -15825 | AV13: =AM13+AN13 -> 38967.4
A14: TTL_13T15: Textiles, wearing apparel, leather and related products | C14: 322.9 | D14: 12 | E14: 17.5 | F14: 0.1 | G14: 278.5 | H14: 27189 | I14: 123 | J14: 437.2 | K14: 170.3 | L14: 1612.4 | M14: 1806.9 | N14: 300.9 | O14: 255.3 | P14: 435.8 | Q14: 820.1 | R14: 374.7 | S14: 535.9 | T14: 1843.1 | U14: 2469.4 | V14: 1606.6 | W14: 495 | X14: 1275.7 | Y14: 3146.4 | Z14: 791.9 | AA14: 808.3 | AB14: 420.7 | AC14: 97.4 | AD14: 130.7 | AE14: 591.9 | AF14: 85.6 | AG14: 1311.4 | AH14: 1765.6 | AI14: 659.3 | AJ14: 3399.6 | AK14: 1749.9 | AL14: 0 | AM14: 17460.7 | AN14: 61.6 | AO14: 400.9 | AP14: 867.2 | AQ14: 22.2 | AR14: 293.1 | AS14: 271.3 | AT14: 12707.8 | AU14: -19347.7 | AV14: =AM14+AN14 -> 17522.3
A15: TTL_16: Wood and of products of wood and cork (except furniture) | C15: 42.8 | D15: 6.6 | E15: 4.7 | F15: 0 | G15: 52.2 | H15: 57.3 | I15: 1278.1 | J15: 222.2 | K15: 26 | L15: 204.3 | M15: 131.1 | N15: 126.1 | O15: 46.1 | P15: 178.3 | Q15: 136.9 | R15: 82.6 | S15: 127.5 | T15: 219.5 | U15: 434.7 | V15: 1193.9 | W15: 136.1 | X15: 3074.2 | Y15: 252.4 | Z15: 47.8 | AA15: 60.3 | AB15: 26 | AC15: 8.4 | AD15: 19.2 | AE15: 16.7 | AF15: 389.6 | AG15: 126.2 | AH15: 40.7 | AI15: 60.6 | AJ15: 27.2 | AK15: 135.6 | AL15: 0 | AM15: 166.8 | AN15: 0.5 | AO15: 9.7 | AP15: 600.1 | AQ15: -17.5 | AR15: 21.4 | AS15: 13.6 | AT15: 195.1 | AU15: -2195.2 | AV15: =AM15+AN15 -> 167.3
A16: TTL_17T18: Paper products and printing | C16: 89.5 | D16: 3.1 | E16: 11.7 | F16: 0 | G16: 1141.9 | H16: 458.8 | I16: 131.3 | J16: 7691.1 | K16: 122.3 | L16: 1390.9 | M16: 753.4 | N16: 493.6 | O16: 185.6 | P16: 338.6 | Q16: 791.7 | R16: 389 | S16: 435.9 | T16: 402.3 | U16: 114.1 | V16: 318.6 | W16: 438.4 | X16: 408.2 | Y16: 2304.7 | Z16: 291.7 | AA16: 517.9 | AB16: 1578.3 | AC16: 200.1 | AD16: 491.4 | AE16: 1217.7 | AF16: 160.9 | AG16: 1635.3 | AH16: 853.8 | AI16: 1287.1 | AJ16: 650.4 | AK16: 787.2 | AL16: 0 | AM16: 708.5 | AN16: 1.2 | AO16: 143 | AP16: 154.7 | AQ16: 6.5 | AR16: 87 | AS16: 47 | AT16: 3024.8 | AU16: -3513.2 | AV16: =AM16+AN16 -> 709.7
A17: TTL_19: Coke and refined petroleum products | C17: 1199.3 | D17: 37.1 | E17: 119.3 | F17: 0.4 | G17: 510.8 | H17: 736.2 | I17: 151.4 | J17: 489.6 | K17: 7323.9 | L17: 11920.6 | M17: 2363.2 | N17: 1309.3 | O17: 3549.6 | P17: 706.1 | Q17: 779.8 | R17: 556.5 | S17: 620 | T17: 572.5 | U17: 555.4 | V17: 315.2 | W17: 3445.8 | X17: 3137 | Y17: 2691.4 | Z17: 11014.4 | AA17: 466.4 | AB17: 120.9 | AC17: 147.5 | AD17: 233 | AE17: 641.7 | AF17: 352.5 | AG17: 1209.6 | AH17: 1157.8 | AI17: 651.3 | AJ17: 802.1 | AK17: 753.9 | AL17: 0 | AM17: 15806.1 | AN17: 0.9 | AO17: 124.6 | AP17: 35.8 | AQ17: 123.4 | AR17: 195.6 | AS17: 117.1 | AT17: 29136 | AU17: -14914.9 | AV17: =AM17+AN17 -> 15807
A18: TTL_20T21: Chemicals and pharmaceutical products | C18: 1643.4 | D18: 37.7 | E18: 77 | F18: 0.2 | G18: 893.6 | H18: 3513.1 | I18: 391.9 | J18: 1570 | K18: 4502 | L18: 37902.9 | M18: 14139 | N18: 1744 | O18: 4124.3 | P18: 1753.4 | Q18: 3086.6 | R18: 1817.2 | S18: 1344.8 | T18: 1810.3 | U18: 1924.2 | V18: 864.8 | W18: 1370.6 | X18: 2899.6 | Y18: 1560.8 | Z18: 2190.5 | AA18: 445.8 | AB18: 199.9 | AC18: 65 | AD18: 113.6 | AE18: 243.5 | AF18: 494.9 | AG18: 1451.9 | AH18: 719.1 | AI18: 671 | AJ18: 6513.4 | AK18: 1273.7 | AL18: 0 | AM18: 6981.6 | AN18: 1.9 | AO18: 7981.3 | AP18: 787.1 | AQ18: -175.2 | AR18: 163.1 | AS18: 118.3 | AT18: 50152.2 | AU18: -29213.9 | AV18: =AM18+AN18 -> 6983.5
A19: TTL_22: Rubber and plastics products | C19: 242.8 | D19: 30.4 | E19: 43.1 | F19: 0.1 | G19: 1866.4 | H19: 1204.3 | I19: 194.9 | J19: 780.9 | K19: 352.2 | L19: 3373.7 | M19: 10678.7 | N19: 1064.7 | O19: 1220.8 | P19: 1643 | Q19: 5169.6 | R19: 3001.6 | S19: 3307.7 | T19: 6608.9 | U19: 2076.2 | V19: 1252.3 | W19: 513.7 | X19: 7556.3 | Y19: 3051.6 | Z19: 1292.1 | AA19: 629.7 | AB19: 116.4 | AC19: 225.6 | AD19: 162.9 | AE19: 243.6 | AF19: 345.5 | AG19: 893 | AH19: 399.1 | AI19: 301.3 | AJ19: 675.7 | AK19: 508.8 | AL19: 0 | AM19: 703.5 | AN19: 0.4 | AO19: 76.2 | AP19: 853.3 | AQ19: -35.2 | AR19: 6.5 | AS19: 9.4 | AT19: 13095.7 | AU19: -7737.9 | AV19: =AM19+AN19 -> 703.9
A20: TTL_23: Other non-metallic mineral products | C20: 100.1 | D20: 4.5 | E20: 51.3 | F20: 0.1 | G20: 471 | H20: 158.1 | I20: 129 | J20: 63.2 | K20: 123.3 | L20: 908.7 | M20: 560.7 | N20: 6495.8 | O20: 1094.7 | P20: 796.1 | Q20: 2122.4 | R20: 683.3 | S20: 688.1 | T20: 1092.1 | U20: 766.3 | V20: 227.3 | W20: 288.9 | X20: 22013.4 | Y20: 707.3 | Z20: 191.4 | AA20: 260.5 | AB20: 24.3 | AC20: 39.7 | AD20: 39.2 | AE20: 71 | AF20: 527.5 | AG20: 307.8 | AH20: 200.9 | AI20: 220.9 | AJ20: 232.2 | AK20: 201.8 | AL20: 0 | AM20: 485.2 | AN20: 0.5 | AO20: 27.3 | AP20: 617.7 | AQ20: -37.6 | AR20: 2.7 | AS20: 3.7 | AT20: 3087.2 | AU20: -10504.6 | AV20: =AM20+AN20 -> 485.7
... A49: OUTPUT: Output at basic prices | C49: 50961.4 | D49: 1375.4 | E49: 2779.4 | F49: 48.2 | G49: 100296.9 | H49: 70078.1 | I49: 7786.1 | J49: 28746.3 | K49: 91266 | L49: 140150 | M49: 67999.5 | N49: 35545.1 | O49: 117545.9 | P49: 87559 | Q49: 274943.1 | R49: 78041.6 | S49: 109026.7 | T49: 166943.4 | U49: 68352.9 | V49: 22743.1 | W49: 97381.1 | X49: 182430.4 | Y49: 206730.9 | Z49: 121466.2 | AA49: 84906.8 | AB49: 23398 | AC49: 38570.3 | AD49: 47167.7 | AE49: 130918 | AF49: 121953.2 | AG49: 165585.8 | AH49: 127986.3 | AI49: 93872.1 | AJ49: 105025.5 | AK49: 65390.2 | AL49: 1812.9 | AM49: 0 | AN49: 0 | AO49: 0 | AP49: 0 | AQ49: 0 | AR49: 0 | AS49: 0 | AT49: 0 | AU49: 0 | AV49: =AM49+AN49 -> 0
A50: Data extracted on 20 May 2021 13:18 UTC (GMT) from OECD.Stat | AV50: =AM50+AN50 -> 0

Sheet OECD TTL - 2021
A1: =DotStatQuery(B1) -> #NAME? | B1: Sorry, the query is too large to fit into the Excel cell. You will not be able to update your table with the .Stat Populator.
A2: Dataset: Input-Output Tables (IOTs) 2021 ed.
A3: Variable | C3: TTL: Total
A4: Country | C4: KOR: Korea
A5: Time | C5: 2018
A6: Unit | C6: US Dollar, Millions
A7: To industry / sector | C7: D01T02: Agriculture, hunting, forestry | D7: D03: Fishing and aquaculture | E7: D05T06: Mining and quarrying, energy producing products | F7: D07T08: Mining and quarrying, non-energy producing products | G7: D09: Mining support service activities | H7: D10T12: Food products, beverages and tobacco | I7: D13T15: Textiles, textile products, leather and footwear | J7: D16: Wood and products of wood and cork | K7: D17T18: Paper products and printing | L7: D19: Coke and refined petroleum products | M7: D20: Chemical and chemical products | N7: D21: Pharmaceuticals, medicinal chemical and botanical products | O7: D22: Rubber and plastics products | P7: D23: Other non-metallic mineral products | Q7: D24: Basic metals | R7: D25: Fabricated metal products | S7: D26: Computer, electronic and optical equipment | T7: D27: Electrical equipment | U7: D28: Machinery and equipment, nec | V7: D29: Motor vehicles, trailers and semi-trailers | W7: D30: Other transport equipment | X7: D31T33: Manufacturing nec; repair and installation of machinery and equipment | Y7: D35: Electricity, gas, steam and air conditioning supply | Z7: D36T39: Water supply; sewerage, waste management and remediation activities | AA7: D41T43: Construction | AB7: D45T47: Wholesale and retail trade; repair of motor vehicles | AC7: D49: Land transport and transport via pipelines | AD7: D50: Water transport | AE7: D51: Air transport | AF7: D52: Warehousing and support activities for transportation | AG7: D53: Postal and courier activities | AH7: D55T56: Accommodation and food service activities | AI7: D58T60: Publishing, audiovisual and broadcasting activities | AJ7: D61: Telecommunications | AK7: D62T63: IT and other information services | AL7: D64T66: Financial and insurance activities | AM7: D68: Real estate activities | AN7: D69T75: Professional, scientific and technical activities | AO7: D77T82: Administrative and support services | AP7: D84: Public administration and defence; compulsory social security | AQ7: D85: Education | AR7: D86T88: Human health and social work activities | AS7: D90T93: Arts, entertainment and recreation | AT7: D94T96: Other service activities | AU7: D97T98: Activities of households as employers; undifferentiated goods- and services-producing activities of households for own use | AV7: HFCE: Final consumption expenditure of households | AW7: NPISH: Final consumption expenditure of non-profit institutions serving households | AX7: GGFC: Final consumption expenditure of general government | AY7: GFCF: Gross Fixed Capital Formation | AZ7: INVNT: Changes in inventories | BA7: CONS_ABR: Direct purchases abroad by residents (imports) | BB7: CONS_NONRES: Direct purchases by non-residents (exports) | BC7: EXPO: Exports (cross border) | BD7: IMPO: Imports (cross border)
A8: From industry / sector
A9: TTL_01T02: Agriculture, hunting, forestry | C9: 2572 | D9: 85.4 | E9: 0.8 | F9: 4.1 | G9: 0 | H9: 27287 | I9: 552.7 | J9: 687 | K9: 14.8 | L9: 13.1 | M9: 156.3 | N9: 313.2 | O9: 543.2 | P9: 14.5 | Q9: 40.3 | R9: 35.2 | S9: 104 | T9: 33.1 | U9: 55 | V9: 45.9 | W9: 29.1 | X9: 34.3 | Y9: 11.5 | Z9: 5.3 | AA9: 511.2 | AB9: 99 | AC9: 5.8 | AD9: 2 | AE9: 12.7 | AF9: 16.6 | AG9: 1.1 | AH9: 5850.2 | AI9: 16.1 | AJ9: 10.5 | AK9: 4.6 | AL9: 40.5 | AM9: 10.4 | AN9: 144.9 | AO9: 16.1 | AP9: 253.4 | AQ9: 408.3 | AR9: 1074.7 | AS9: 139.7 | AT9: 65.4 | AU9: 0 | AV9: 14327.7 | AW9: 56.4 | AX9: 1.6 | AY9: 412.3 | AZ9: -287 | BA9: 315.9 | BB9: 160.3 | BC9: 643.1 | BD9: -7669.9
A10: TTL_03: Fishing and aquaculture | C10: 7.2 | D10: 173.9 | E10: 0 | F10: 0.2 | G10: 0 | H10: 2269.2 | I10: 7.4 | J10: 0.5 | K10: 1.3 | L10: 0.7 | M10: 8.9 | N10: 3.2 | O10: 4.2 | P10: 1.6 | Q10: 5.3 | R10: 4.7 | S10: 15.2 | T10: 5 | U10: 7.3 | V10: 4.8 | W10: 4.7 | X10: 10.1 | Y10: 1 | Z10: 0.7 | AA10: 4.2 | AB10: 11.2 | AC10: 0.8 | AD10: 0.5 | AE10: 0.4 | AF10: 0.5 | AG10: 0.1 | AH10: 2552.2 | AI10: 1.4 | AJ10: 1.4 | AK10: 0.7 | AL10: 2.2 | AM10: 2.7 | AN10: 22.2 | AO10: 1.6 | AP10: 79.8 | AQ10: 188.3 | AR10: 189.8 | AS10: 20.5 | AT10: 6.9 | AU10: 0 | AV10: 2933.6 | AW10: 3.8 | AX10: 0.3 | AY10: 1.5 | AZ10: 7.1 | BA10: 23.3 | BB10: 12.1 | BC10: 270.4 | BD10: -939.2
A11: TTL_05T06: Mining and quarrying, energy producing products | C11: 4.2 | D11: 5.8 | E11: 0 | F11: 1.6 | G11: 0.3 | H11: 7.6 | I11: 13.1 | J11: 0.7 | K11: 3.4 | L11: 77279.8 | M11: 8972.8 | N11: 3 | O11: 14.7 | P11: 85.8 | Q11: 1655.4 | R11: 20.3 | S11: 15.9 | T11: 6.4 | U11: 10.8 | V11: 9.7 | W11: 6.2 | X11: 2.3 | Y11: 23522.5 | Z11: 425.1 | AA11: 23.9 | AB11: 68.4 | AC11: 80.5 | AD11: 15.9 | AE11: 39.2 | AF11: 4.6 | AG11: 6.6 | AH11: 14.1 | AI11: 1.9 | AJ11: 1.9 | AK11: 1.1 | AL11: 4.1 | AM11: 12.5 | AN11: 27.3 | AO11: 5.6 | AP11: 13.6 | AQ11: 15 | AR11: 19 | AS11: 4 | AT11: 6.9 | AU11: 0 | AV11: 103.5 | AW11: 0.3 | AX11: 0.5 | AY11: 14.1 | AZ11: 4752.3 | BA11: 12.7 | BB11: 0.1 | BC11: 9.2 | BD11: -116874.9
A12: TTL_07T08: Mining and quarrying, non-energy producing products | C12: 2.3 | D12: 0.4 | E12: 0 | F12: 4.9 | G12: 0.1 | H12: 27.2 | I12: 11.3 | J12: 0.7 | K12: 22.2 | L12: 13.6 | M12: 615.8 | N12: 5.9 | O12: 41.4 | P12: 2553.6 | Q12: 11523.1 | R12: 29.1 | S12: 46.5 | T12: 13.5 | U12: 21.8 | V12: 16.5 | W12: 4.3 | X12: 7.2 | Y12: 44 | Z12: 10.4 | AA12: 285.4 | AB12: 3.2 | AC12: 1.2 | AD12: 1.6 | AE12: 0.7 | AF12: 0.6 | AG12: 0.1 | AH12: 6.8 | AI12: 0.5 | AJ12: 0.6 | AK12: 0.3 | AL12: 0.9 | AM12: 1 | AN12: 8.5 | AO12: 4.2 | AP12: 6.3 | AQ12: 1.4 | AR12: 8.1 | AS12: 1.6 | AT12: 3.6 | AU12: 0 | AV12: 24.9 | AW12: 0.2 | AX12: 0.3 | AY12: 6.9 | AZ12: 1.8 | BA12: 6.2 | BB12: 0.3 | BC12: 138.2 | BD12: -11898.4
A13: TTL_09: Mining support service activities | C13: 0.2 | D13: 0.1 | E13: 0.1 | F13: 1.5 | G13: 0 | H13: 0.5 | I13: 0.2 | J13: 0 | K13: 0.4 | L13: 8.8 | M13: 2.3 | N13: 0.1 | O13: 0.6 | P13: 2.3 | Q13: 5.5 | R13: 0.4 | S13: 0.8 | T13: 0.3 | U13: 0.6 | V13: 0.4 | W13: 0.2 | X13: 0.1 | Y13: 3.9 | Z13: 0.1 | AA13: 13.9 | AB13: 0.5 | AC13: 0.4 | AD13: 0.1 | AE13: 0.1 | AF13: 0.1 | AG13: 0 | AH13: 0.3 | AI13: 0.1 | AJ13: 0.1 | AK13: 0.1 | AL13: 0.2 | AM13: 0.4 | AN13: 0.7 | AO13: 0.2 | AP13: 0.3 | AQ13: 0.1 | AR13: 0.3 | AS13: 0.1 | AT13: 0.1 | AU13: 0 | AV13: 1.1 | AW13: 0 | AX13: 0.1 | AY13: 2.7 | AZ13: 0.6 | BA13: 0.8 | BB13: 0 | BC13: 17.5 | BD13: -48.2
A14: TTL_10T12: Food products, beverages and tobacco | C14: 6360.4 | D14: 324.6 | E14: 1.5 | F14: 12.2 | G14: 0 | H14: 19121.6 | I14: 1090.1 | J14: 33.2 | K14: 117.5 | L14: 76.9 | M14: 1165.7 | N14: 281.8 | O14: 246.4 | P14: 96.9 | Q14: 284 | R14: 287.8 | S14: 695.9 | T14: 222.4 | U14: 422.9 | V14: 264.2 | W14: 204.8 | X14: 93.9 | Y14: 78.3 | Z14: 24.4 | AA14: 222.3 | AB14: 1064.6 | AC14: 40 | AD14: 38.8 | AE14: 56.7 | AF14: 134.9 | AG14: 7.8 | AH14: 34180.5 | AI14: 112.9 | AJ14: 66.1 | AK14: 51.8 | AL14: 254.8 | AM14: 42.6 | AN14: 1071.4 | AO14: 246.8 | AP14: 787 | AQ14: 1903 | AR14: 2441.8 | AS14: 1541.6 | AT14: 386.1 | AU14: 0 | AV14: 47148.3 | AW14: 184.6 | AX14: 781.3 | AY14: 122.4 | AZ14: 700.4 | BA14: 1330.8 | BB14: 653.2 | BC14: 6634.3 | BD14: -20594.8
A15: TTL_13T15: Textiles, textile products, leather and footwear | C15: 204.3 | D15: 678.9 | E15: 3.1 | F15: 23 | G15: 0.1 | H15: 563.4 | I15: 21919.4 | J15: 86.4 | K15: 526.1 | L15: 84.2 | M15: 511.8 | N15: 149.6 | O15: 2289.5 | P15: 315.7 | Q15: 729.1 | R15: 855.6 | S15: 1867.2 | T15: 661.4 | U15: 950.6 | V15: 1599.6 | W15: 682.3 | X15: 1923.2 | Y15: 176.2 | Z15: 159.4 | AA15: 643.8 | AB15: 1983.4 | AC15: 393 | AD15: 40.6 | AE15: 7.8 | AF15: 841.9 | AG15: 66.3 | AH15: 1151.3 | AI15: 144.2 | AJ15: 91.9 | AK15: 34.2 | AL15: 407.7 | AM15: 145.3 | AN15: 751.3 | AO15: 739.4 | AP15: 902.8 | AQ15: 322.5 | AR15: 1155.7 | AS15: 571.1 | AT15: 856.3 | AU15: 0 | AV15: 30964.5 | AW15: 50.5 | AX15: 2.5 | AY15: 309.5 | AZ15: -80.5 | BA15: 811.5 | BB15: 482.6 | BC15: 10267.8 | BD15: -20685.6
A16: TTL_16: Wood and products of wood and cork | C16: 38 | D16: 169.4 | E16: 1.4 | F16: 3.1 | G16: 0 | H16: 98.2 | I16: 80.4 | J16: 1533.5 | K16: 54.2 | L16: 11.3 | M16: 60.4 | N16: 6.4 | O16: 51.3 | P16: 113.3 | Q16: 157.3 | R16: 215.3 | S16: 101.7 | T16: 86.6 | U16: 175.1 | V16: 104.8 | W16: 39.4 | X16: 1381.4 | Y16: 305 | Z16: 7.6 | AA16: 4331.9 | AB16: 136.1 | AC16: 6.4 | AD16: 2 | AE16: 0.3 | AF16: 453 | AG16: 1.4 | AH16: 212.8 | AI16: 5.1 | AJ16: 2.3 | AK16: 2.7 | AL16: 3 | AM16: 3.1 | AN16: 13.9 | AO16: 27.8 | AP16: 4.5 | AQ16: 39.9 | AR16: 55.9 | AS16: 27.6 | AT16: 30.2 | AU16: 0 | AV16: 130.2 | AW16: 2 | AX16: 0.5 | AY16: 18 | AZ16: 170.7 | BA16: 57.3 | BB16: 27 | BC16: 151.5 | BD16: -2783.3
A17: TTL_17T18: Paper products and printing | C17: 282.2 | D17: 19.8 | E17: 0.7 | F17: 8.6 | G17: 0 | H17: 2249.7 | I17: 811.7 | J17: 127.1 | K17: 10939.8 | L17: 87.2 | M17: 868.6 | N17: 365.9 | O17: 555.1 | P17: 345.3 | Q17: 266.5 | R17: 592.8 | S17: 828.9 | T17: 715.3 | U17: 418.6 | V17: 285.9 | W17: 98.9 | X17: 402.4 | Y17: 52.8 | Z17: 39.2 | AA17: 603.6 | AB17: 2387.8 | AC17: 55 | AD17: 19.8 | AE17: 6.6 | AF17: 316.3 | AG17: 157.4 | AH17: 788.4 | AI17: 1269.2 | AJ17: 181.6 | AK17: 248 | AL17: 1397.7 | AM17: 174.7 | AN17: 3022.5 | AO17: 352.1 | AP17: 669.9 | AQ17: 656.4 | AR17: 595.1 | AS17: 391.1 | AT17: 491.9 | AU17: 0 | AV17: 1111.2 | AW17: 19 | AX17: 1 | AY17: 72.1 | AZ17: 542.5 | BA17: 156 | BB17: 79.4 | BC17: 3518 | BD17: -4120.6
A18: TTL_19: Coke and refined petroleum products | C18: 628.7 | D18: 686.7 | E18: 0.8 | F18: 124 | G18: 0.5 | H18: 465.1 | I18: 644.5 | J18: 71.4 | K18: 377.9 | L18: 7012.1 | M18: 19337.4 | N18: 246.2 | O18: 1830.3 | P18: 1710.4 | Q18: 890.8 | R18: 878.1 | S18: 1654.2 | T18: 678.9 | U18: 631 | V18: 737.6 | W18: 402.6 | X18: 204.6 | Y18: 4004.7 | Z18: 314.7 | AA18: 2231.7 | AB18: 5094.5 | AC18: 9611.3 | AD18: 1876.1 | AE18: 4680.8 | AF18: 517.9 | AG18: 811 | AH18: 1541.1 | AI18: 210.8 | AJ18: 187.7 | AK18: 114.9 | AL18: 364.1 | AM18: 819.7 | AN18: 2646.3 | AO18: 584.5 | AP18: 1633.1 | AQ18: 1620.9 | AR18: 2033.1 | AS18: 458.7 | AT18: 939.5 | AU18: 0 | AV18: 12483.2 | AW18: 35.3 | AX18: 4 | AY18: 62.8 | AZ18: 1297.1 | BA18: 587.1 | BB18: 322.4 | BC18: 52580.3 | BD18: -26881.9
A19: TTL_20: Chemical and chemical products | C19: 2795.1 | D19: 49.1 | E19: 3.4 | F19: 92.7 | G19: 0.3 | H19: 818.1 | I19: 4213.3 | J19: 520.7 | K19: 1569.9 | L19: 1644.9 | M19: 38536.9 | N19: 1621.7 | O19: 16882.8 | P19: 1454.6 | Q19: 1785.1 | R19: 2913.8 | S19: 12206.1 | T19: 3896.1 | U19: 1573.4 | V19: 2339.8 | W19: 629.4 | X19: 1010.8 | Y19: 2085.5 | Z19: 340.8 | AA19: 2451.8 | AB19: 1246.9 | AC19: 480.6 | AD19: 84.9 | AE19: 140.8 | AF19: 176.5 | AG19: 29.3 | AH19: 916.8 | AI19: 394.5 | AJ19: 69 | AK19: 78 | AL19: 169.9 | AM19: 151.2 | AN19: 2714 | AO19: 868.2 | AP19: 416.2 | AQ19: 411.2 | AR19: 2154.9 | AS19: 529.7 | AT19: 2536.9 | AU19: 0 | AV19: 9661.4 | AW19: 34 | AX19: 21.2 | AY19: 259.1 | AZ19: 1808.9 | BA19: 208.8 | BB19: 127.4 | BC19: 67713.8 | BD19: -38176.5
A20: TTL_21: Pharmaceuticals, medicinal chemical and botanical products | C20: 73.8 | D20: 15.4 | E20: 0.5 | F20: 1.9 | G20: 0 | H20: 165.3 | I20: 187 | J20: 9.4 | K20: 24 | L20: 15.1 | M20: 132.6 | N20: 1327.7 | O20: 78.9 | P20: 22 | Q20: 69.8 | R20: 75.5 | S20: 225.3 | T20: 62.6 | U20: 111.2 | V20: 73.7 | W20: 64.7 | X20: 30.5 | Y20: 16.3 | Z20: 20.9 | AA20: 34.5 | AB20: 58.2 | AC20: 5.5 | AD20: 3 | AE20: 6.1 | AF20: 6.3 | AG20: 1.4 | AH20: 53.6 | AI20: 6.7 | AJ20: 11 | AK20: 4.9 | AL20: 14.1 | AM20: 13.5 | AN20: 406 | AO20: 23.8 | AP20: 157.3 | AQ20: 70.7 | AR20: 15666.7 | AS20: 15 | AT20: 22.9 | AU20: 0 | AV20: 1313.2 | AW20: 33.1 | AX20: 1177.2 | AY20: 352.5 | AZ20: 572.8 | BA20: 166.4 | BB20: 82.1 | BC20: 3194.6 | BD20: -5846.3
... A58: OUTPUT: Output at basic prices | C58: 49280.8 | D58: 7937.6 | E58: 451.6 | F58: 3632.9 | G58: 22 | H58: 113119.4 | I58: 70332.9 | J58: 7929 | K58: 35526.7 | L58: 122001.1 | M58: 156663.6 | N58: 20431 | O58: 75665 | P58: 39861.4 | Q58: 137411.8 | R58: 92387.2 | S58: 315223.2 | T58: 90071.3 | U58: 134106.7 | V58: 179400 | W58: 42141.3 | X58: 32086.3 | Y58: 88817.4 | Z58: 18818.6 | AA58: 234149.1 | AB58: 240708.8 | AC58: 56342.5 | AD58: 19462.9 | AE58: 19964.5 | AF58: 36476.9 | AG58: 8256.8 | AH58: 133326.4 | AI58: 50668 | AJ58: 39108.6 | AK58: 45512.2 | AL58: 164084.7 | AM58: 177037.3 | AN58: 197776.9 | AO58: 84187 | AP58: 140188.4 | AQ58: 119266.1 | AR58: 139569.3 | AS58: 34208.4 | AT58: 47784 | AU58: 2012.3 | AV58: 0 | AW58: 0 | AX58: 0 | AY58: 0 | AZ58: 0 | BA58: 0 | BB58: 0 | BC58: 0 | BD58: 0
A59: Data extracted on 25 Feb 2022 22:25 UTC (GMT) from OECD.Stat

Sheet OECD TTL - 2023
A1: =DotStatQuery(B1) -> #NAME? | B1: Sorry, the query is too large to fit into the Excel cell. You will not be able to update your table with the .Stat Populator.
A2: Dataset: Input-Output Tables (IOTs) 2021 ed.
A3: Variable | C3: TTL: Total
A4: Country | C4: KOR: Korea
A5: Time | C5: 2020
A6: Unit | C6: US Dollar, Millions
A7: To industry / sector | C7: D01T02: Agriculture, hunting, forestry | D7: D03: Fishing and aquaculture | E7: D05T06: Mining and quarrying, energy producing products | F7: D07T08: Mining and quarrying, non-energy producing products | G7: D09: Mining support service activities | H7: D10T12: Food products, beverages and tobacco | I7: D13T15: Textiles, textile products, leather and footwear | J7: D16: Wood and products of wood and cork | K7: D17T18: Paper products and printing | L7: D19: Coke and refined petroleum products | M7: D20: Chemical and chemical products | N7: D21: Pharmaceuticals, medicinal chemical and botanical products | O7: D22: Rubber and plastics products | P7: D23: Other non-metallic mineral products | Q7: D24: Basic metals | R7: D25: Fabricated metal products | S7: D26: Computer, electronic and optical equipment | T7: D27: Electrical equipment | U7: D28: Machinery and equipment, nec | V7: D29: Motor vehicles, trailers and semi-trailers | W7: D30: Other transport equipment | X7: D31T33: Manufacturing nec; repair and installation of machinery and equipment | Y7: D35: Electricity, gas, steam and air conditioning supply | Z7: D36T39: Water supply; sewerage, waste management and remediation activities | AA7: D41T43: Construction | AB7: D45T47: Wholesale and retail trade; repair of motor vehicles | AC7: D49: Land transport and transport via pipelines | AD7: D50: Water transport | AE7: D51: Air transport | AF7: D52: Warehousing and support activities for transportation | AG7: D53: Postal and courier activities | AH7: D55T56: Accommodation and food service activities | AI7: D58T60: Publishing, audiovisual and broadcasting activities | AJ7: D61: Telecommunications | AK7: D62T63: IT and other information services | AL7: D64T66: Financial and insurance activities | AM7: D68: Real estate activities | AN7: D69T75: Professional, scientific and technical activities | AO7: D77T82: Administrative and support services | AP7: D84: Public administration and defence; compulsory social security | AQ7: D85: Education | AR7: D86T88: Human health and social work activities | AS7: D90T93: Arts, entertainment and recreation | AT7: D94T96: Other service activities | AU7: D97T98: Activities of households as employers; undifferentiated goods- and services-producing activities of households for own use | AV7: HFCE: Final consumption expenditure of households | AW7: NPISH: Final consumption expenditure of non-profit institutions serving households | AX7: GGFC: Final consumption expenditure of general government | AY7: GFCF: Gross Fixed Capital Formation | AZ7: INVNT: Changes in inventories | BA7: CONS_ABR: Direct purchases abroad by residents (imports) | BB7: CONS_NONRES: Direct purchases by non-residents (exports) | BC7: EXPO: Exports (cross border) | BD7: IMPO: Imports (cross border)
A8: From industry / sector
A9: TTL_01T02: Agriculture, hunting, forestry | C9: 2633.3 | D9: 100.6 | E9: 0.4 | F9: 4.1 | G9: 0 | H9: 24080 | I9: 453.1 | J9: 599.1 | K9: 13.2 | L9: 15 | M9: 146.4 | N9: 248.9 | O9: 470.4 | P9: 12.4 | Q9: 33.8 | R9: 30.1 | S9: 67 | T9: 29.2 | U9: 43 | V9: 31.8 | W9: 31.1 | X9: 26.4 | Y9: 9.8 | Z9: 4.5 | AA9: 369.3 | AB9: 118 | AC9: 5.2 | AD9: 3.6 | AE9: 10.2 | AF9: 15.5 | AG9: 1.2 | AH9: 5028.6 | AI9: 13.7 | AJ9: 7 | AK9: 4.1 | AL9: 37.6 | AM9: 8.2 | AN9: 161.5 | AO9: 17 | AP9: 234.7 | AQ9: 355 | AR9: 1016.7 | AS9: 108.4 | AT9: 52.8 | AU9: 0 | AV9: 13393.9 | AW9: 77.1 | AX9: 1.5 | AY9: 342.8 | AZ9: 298 | BA9: 102.7 | BB9: 54.1 | BC9: 435.8 | BD9: -6524.3
A10: TTL_03: Fishing and aquaculture | C10: 7.7 | D10: 153.6 | E10: 0 | F10: 0.2 | G10: 0 | H10: 1747.5 | I10: 5.6 | J10: 0.4 | K10: 1.1 | L10: 1.4 | M10: 7.5 | N10: 2.6 | O10: 3.4 | P10: 1.2 | Q10: 3.8 | R10: 3.5 | S10: 8.5 | T10: 3.8 | U10: 4.9 | V10: 3.5 | W10: 4.1 | X10: 6.6 | Y10: 1 | Z10: 0.6 | AA10: 3.2 | AB10: 11.1 | AC10: 0.7 | AD10: 1 | AE10: 0.5 | AF10: 0.6 | AG10: 0.1 | AH10: 2280.8 | AI10: 1.2 | AJ10: 0.9 | AK10: 0.6 | AL10: 2 | AM10: 1.5 | AN10: 19 | AO10: 2 | AP10: 71.2 | AQ10: 165.3 | AR10: 179.4 | AS10: 16.6 | AT10: 5.6 | AU10: 0 | AV10: 2579.5 | AW10: 14.9 | AX10: 0.5 | AY10: 3 | AZ10: 41.7 | BA10: 7.2 | BB10: 4.2 | BC10: 273.8 | BD10: -685.8
A11: TTL_05T06: Mining and quarrying, energy producing products | C11: 3.8 | D11: 5.4 | E11: 0 | F11: 3 | G11: 0.1 | H11: 5.4 | I11: 7.1 | J11: 0.5 | K11: 2.5 | L11: 42473.3 | M11: 2496.6 | N11: 1.6 | O11: 8.4 | P11: 147.3 | Q11: 3197.6 | R11: 10.6 | S11: 7.9 | T11: 6.5 | U11: 15.3 | V11: 7.6 | W11: 6.1 | X11: 1.8 | Y11: 20179.6 | Z11: 167.3 | AA11: 19.3 | AB11: 60.5 | AC11: 77.7 | AD11: 18 | AE11: 37.9 | AF11: 4.5 | AG11: 7.2 | AH11: 12.8 | AI11: 1.7 | AJ11: 1.3 | AK11: 1 | AL11: 3.3 | AM11: 6 | AN11: 29.6 | AO11: 5.2 | AP11: 15.5 | AQ11: 14.4 | AR11: 17.2 | AS11: 3.4 | AT11: 5.9 | AU11: 0 | AV11: 112.5 | AW11: 0.1 | AX11: 0.3 | AY11: 25.6 | AZ11: 290.4 | BA11: 6.2 | BB11: 0 | BC11: 12.1 | BD11: -69225.3
A12: TTL_07T08: Mining and quarrying, non-energy producing products | C12: 3.9 | D12: 0.4 | E12: 0 | F12: 4.4 | G12: 0.3 | H12: 23.7 | I12: 10 | J12: 0.8 | K12: 21.1 | L12: 36.9 | M12: 595.4 | N12: 6.4 | O12: 43.3 | P12: 2103.9 | Q12: 12564.7 | R12: 42.7 | S12: 37.5 | T12: 23.1 | U12: 26.6 | V12: 25 | W12: 9.1 | X12: 7.5 | Y12: 47.6 | Z12: 11.2 | AA12: 247.1 | AB12: 7.7 | AC12: 1 | AD12: 0.8 | AE12: 0.6 | AF12: 0.9 | AG12: 0.1 | AH12: 7 | AI12: 0.9 | AJ12: 1.6 | AK12: 0.4 | AL12: 1.4 | AM12: 1.1 | AN12: 10.1 | AO12: 4.8 | AP12: 6.5 | AQ12: 1.5 | AR12: 9.3 | AS12: 1.8 | AT12: 4.2 | AU12: 0 | AV12: 30.8 | AW12: 0.2 | AX12: 0.3 | AY12: 13.3 | AZ12: 78.9 | BA12: 12.1 | BB12: 0.1 | BC12: 61.5 | BD12: -12871.8
A13: TTL_09: Mining support service activities | C13: 0.2 | D13: 0.2 | E13: 0 | F13: 0.9 | G13: 0 | H13: 0.7 | I13: 0.2 | J13: 0.1 | K13: 0.3 | L13: 42.8 | M13: 4.1 | N13: 0.1 | O13: 0.5 | P13: 1.8 | Q13: 3.7 | R13: 1.4 | S13: 0.9 | T13: 0.5 | U13: 1.2 | V13: 1 | W13: 0.5 | X13: 0.2 | Y13: 7.6 | Z13: 0.2 | AA13: 4.6 | AB13: 2.4 | AC13: 1 | AD13: 0.8 | AE13: 0.5 | AF13: 0.4 | AG13: 0.1 | AH13: 0.5 | AI13: 0.2 | AJ13: 0.1 | AK13: 0.1 | AL13: 0.4 | AM13: 0.3 | AN13: 1 | AO13: 0.5 | AP13: 0.5 | AQ13: 0.2 | AR13: 0.4 | AS13: 0.1 | AT13: 0.2 | AU13: 0 | AV13: 2.8 | AW13: 0 | AX13: 0.1 | AY13: 1.9 | AZ13: 0.3 | BA13: 1.2 | BB13: 0 | BC13: 14.8 | BD13: -79.7
A14: TTL_10T12: Food products, beverages and tobacco | C14: 6482.1 | D14: 346.6 | E14: 0.8 | F14: 11.3 | G14: 0 | H14: 16822.9 | I14: 943.8 | J14: 26.2 | K14: 101.3 | L14: 140.3 | M14: 962.6 | N14: 230.4 | O14: 203.5 | P14: 76.3 | Q14: 229.6 | R14: 226.8 | S14: 395.5 | T14: 175.9 | U14: 301.8 | V14: 201.6 | W14: 170.3 | X14: 70.7 | Y14: 69.1 | Z14: 22.5 | AA14: 160.9 | AB14: 1208.7 | AC14: 33.2 | AD14: 35.9 | AE14: 40.8 | AF14: 122.7 | AG14: 7.5 | AH14: 31844.3 | AI14: 99.4 | AJ14: 48.2 | AK14: 43 | AL14: 233.9 | AM14: 26.6 | AN14: 1019.9 | AO14: 244.4 | AP14: 744.3 | AQ14: 1698.9 | AR14: 2345.4 | AS14: 1375.5 | AT14: 338.9 | AU14: 0 | AV14: 45646.5 | AW14: 190.1 | AX14: 1107.7 | AY14: 121.3 | AZ14: 661 | BA14: 370 | BB14: 203.2 | BC14: 4754.4 | BD14: -17183.5
A15: TTL_13T15: Textiles, textile products, leather and footwear | C15: 188 | D15: 474.8 | E15: 1.9 | F15: 21.3 | G15: 0.1 | H15: 488.8 | I15: 16691.1 | J15: 70.8 | K15: 456 | L15: 191 | M15: 470.4 | N15: 125.9 | O15: 1645 | P15: 273.9 | Q15: 624.1 | R15: 739.5 | S15: 1107.6 | T15: 526.6 | U15: 710.5 | V15: 1223.9 | W15: 608.3 | X15: 1428.4 | Y15: 180.9 | Z15: 128.3 | AA15: 457.9 | AB15: 2374.3 | AC15: 405.9 | AD15: 45.6 | AE15: 4.8 | AF15: 819.7 | AG15: 70.4 | AH15: 994.2 | AI15: 158.1 | AJ15: 74 | AK15: 30 | AL15: 451.4 | AM15: 106.4 | AN15: 769.3 | AO15: 741 | AP15: 1061.5 | AQ15: 329.6 | AR15: 1296.7 | AS15: 547.1 | AT15: 816.7 | AU15: 0 | AV15: 30535.2 | AW15: 83.6 | AX15: 2 | AY15: 263.5 | AZ15: 454.8 | BA15: 166.4 | BB15: 138.8 | BC15: 7446.2 | BD15: -17717.6
A16: TTL_16: Wood and products of wood and cork | C16: 46.1 | D16: 177.6 | E16: 0.7 | F16: 2.9 | G16: 0 | H16: 89.2 | I16: 56.3 | J16: 1260.4 | K16: 47.9 | L16: 23.9 | M16: 50.7 | N16: 5.5 | O16: 41 | P16: 99.7 | Q16: 134.3 | R16: 183.2 | S16: 57.5 | T16: 74.3 | U16: 128.3 | V16: 86.5 | W16: 32.3 | X16: 1051.7 | Y16: 266.5 | Z16: 7.4 | AA16: 3545.7 | AB16: 225.7 | AC16: 6.4 | AD16: 2 | AE16: 0.4 | AF16: 489.4 | AG16: 1.5 | AH16: 194.6 | AI16: 4.6 | AJ16: 3.1 | AK16: 2.2 | AL16: 2.8 | AM16: 2.2 | AN16: 14.1 | AO16: 28.6 | AP16: 5.5 | AQ16: 40.5 | AR16: 55.8 | AS16: 25 | AT16: 24.7 | AU16: 0 | AV16: 179.8 | AW16: 14.1 | AX16: 0.3 | AY16: 26.3 | AZ16: 53.2 | BA16: 16.9 | BB16: 7.5 | BC16: 80.5 | BD16: -2064.9
A17: TTL_17T18: Paper products and printing | C17: 284.5 | D17: 18.9 | E17: 0.3 | F17: 7.3 | G17: 0 | H17: 1984.2 | I17: 668.4 | J17: 101.2 | K17: 9072.3 | L17: 178.5 | M17: 783 | N17: 302.1 | O17: 470.2 | P17: 282.1 | Q17: 210 | R17: 489.5 | S17: 508.7 | T17: 575.6 | U17: 297.8 | V17: 219.5 | W17: 86.6 | X17: 288.2 | Y17: 39.1 | Z17: 35.7 | AA17: 443.7 | AB17: 3411.3 | AC17: 48.6 | AD17: 18.9 | AE17: 4.9 | AF17: 293.4 | AG17: 159.6 | AH17: 633.8 | AI17: 1210.5 | AJ17: 116.8 | AK17: 215.8 | AL17: 1257.6 | AM17: 98.8 | AN17: 2876.3 | AO17: 314.9 | AP17: 673.6 | AQ17: 631.1 | AR17: 583 | AS17: 331.9 | AT17: 426.8 | AU17: 0 | AV17: 1121.5 | AW17: 30.8 | AX17: 1 | AY17: 86.2 | AZ17: 178.7 | BA17: 45.8 | BB17: 28.9 | BC17: 2781 | BD17: -3001
A18: TTL_19: Coke and refined petroleum products | C18: 537.8 | D18: 537.4 | E18: 0.6 | F18: 105 | G18: 0.8 | H18: 325.6 | I18: 458.6 | J18: 50.7 | K18: 234.7 | L18: 13290.5 | M18: 16401.2 | N18: 180.8 | O18: 1502.7 | P18: 1318.1 | Q18: 634.3 | R18: 663.1 | S18: 946 | T18: 503.8 | U18: 403 | V18: 529.1 | W18: 362.9 | X18: 133.9 | Y18: 2929 | Z18: 244.3 | AA18: 1531.9 | AB18: 4985.1 | AC18: 7817.1 | AD18: 1491.7 | AE18: 3798 | AF18: 409.3 | AG18: 725.6 | AH18: 1253.6 | AI18: 160.4 | AJ18: 104.1 | AK18: 78.8 | AL18: 267.6 | AM18: 412.9 | AN18: 2172.3 | AO18: 471.6 | AP18: 1482 | AQ18: 1323.5 | AR18: 1695.1 | AS18: 339.3 | AT18: 714.8 | AU18: 0 | AV18: 11406 | AW18: 3.6 | AX18: 0.8 | AY18: 51.1 | AZ18: 591.8 | BA18: 127.6 | BB18: 95 | BC18: 35254.2 | BD18: -17591.7
A19: TTL_20: Chemical and chemical products | C19: 2628.7 | D19: 49.3 | E19: 1.8 | F19: 90.3 | G19: 0.5 | H19: 720.2 | I19: 3232.2 | J19: 404 | K19: 1330.5 | L19: 3697.5 | M19: 34652.7 | N19: 1272.3 | O19: 13964.6 | P19: 1204 | Q19: 1486.6 | R19: 2360.9 | S19: 7609.9 | T19: 2888.7 | U19: 1170.4 | V19: 1913.8 | W19: 534.2 | X19: 717.6 | Y19: 1933.8 | Z19: 318.1 | AA19: 1885.6 | AB19: 1173.2 | AC19: 499.7 | AD19: 88.8 | AE19: 146.7 | AF19: 163.6 | AG19: 33.3 | AH19: 687.3 | AI19: 353 | AJ19: 49.1 | AK19: 62.8 | AL19: 145.7 | AM19: 84.3 | AN19: 2486 | AO19: 906.2 | AP19: 410.1 | AQ19: 371.3 | AR19: 2076.4 | AS19: 447.1 | AT19: 2113.5 | AU19: 0 | AV19: 10366 | AW19: 46.1 | AX19: 19.8 | AY19: 193.6 | AZ19: 742.1 | BA19: 51.1 | BB19: 35.4 | BC19: 51808.1 | BD19: -28171.8
A20: TTL_21: Pharmaceuticals, medicinal chemical and botanical products | C20: 71.9 | D20: 15.3 | E20: 0.3 | F20: 2 | G20: 0 | H20: 152.5 | I20: 188 | J20: 9.3 | K20: 26.3 | L20: 33.9 | M20: 151.9 | N20: 1248 | O20: 85.2 | P20: 21.7 | Q20: 70.3 | R20: 74 | S20: 167.2 | T20: 62.1 | U20: 100.5 | V20: 69.7 | W20: 63.4 | X20: 28.3 | Y20: 17.2 | Z20: 19.7 | AA20: 33.7 | AB20: 355.8 | AC20: 5.1 | AD20: 3.3 | AE20: 4.8 | AF20: 6 | AG20: 1.5 | AH20: 51.6 | AI20: 6.3 | AJ20: 12.2 | AK20: 4.6 | AL20: 13.1 | AM20: 7.8 | AN20: 493.5 | AO20: 23.8 | AP20: 162.1 | AQ20: 69 | AR20: 15395.7 | AS20: 13.3 | AT20: 22.4 | AU20: 0 | AV20: 1479.4 | AW20: 39.6 | AX20: 1655.4 | AY20: 244.1 | AZ20: 114.3 | BA20: 38.7 | BB20: 23.6 | BC20: 2571 | BD20: -4996.2
... A58: OUTPUT: Output at basic prices | C58: 44833.7 | D58: 6974.9 | E58: 319.6 | F58: 3279.8 | G58: 24.7 | H58: 105755.1 | I58: 61304.9 | J58: 6912.3 | K58: 31927.6 | L58: 103466.9 | M58: 133456.9 | N58: 20534.2 | O58: 68896.7 | P58: 34680.9 | Q58: 120595.5 | R58: 84741.5 | S58: 251355.4 | T58: 84807.2 | U58: 118826.3 | V58: 167278.8 | W58: 40978 | X58: 28670.1 | Y58: 78519.2 | Z58: 17621.6 | AA58: 220313.5 | AB58: 325300.9 | AC58: 51643.3 | AD58: 18285.3 | AE58: 17951.3 | AF58: 35203.2 | AG58: 8231.4 | AH58: 123751.1 | AI58: 46146 | AJ58: 34591.9 | AK58: 44052.9 | AL58: 149316.5 | AM58: 163638 | AN58: 199544.5 | AO58: 80230.7 | AP58: 143703.3 | AQ58: 110832.4 | AR58: 139040.2 | AS58: 30180.2 | AT58: 43824.2 | AU58: 1838 | AV58: 0 | AW58: 0 | AX58: 0 | AY58: 0 | AZ58: 0 | BA58: 0 | BB58: 0 | BC58: 0 | BD58: 0
A59: Data extracted on 25 Feb 2022 22:25 UTC (GMT) from OECD.Stat

Sheet ISIC Crosswalk
A2: ISIC 05 | B2: 05 | C2: Mining of coal and lignite
B3: 051 | C3: Mining of hard coal | I3: OECD Version | J3: OECD ISIC
B4: 052 | C4: Mining of lignite | I4: 2023 | J4: TTL_01T02: Agriculture, hunting, forestry
A5: ISIC 06 | B5: 06 | C5: Extraction of crude petroleum & natural gas | I5: 2018 | J5: TTL_01T03: Agriculture, forestry and fishing | K5: ISIC 01T03
B6: 061 | C6: Extraction of crude petroleum | I6: 2023 | J6: TTL_03: Fishing and aquaculture
B7: 062 | C7: Extraction of natural gas | I7: 2018 | J7: TTL_05T06: Mining and extraction of energy producing products
A8: ISIC 07T08 | B8: 07 | C8: Mining of metal ores | I8: 2023 | J8: TTL_05T06: Mining and quarrying, energy producing products
B9: 071 | C9: Mining of iron ores | I9: 2018 | J9: TTL_07T08: Mining and quarrying of non-energy producing products
B10: 072 | C10: Mining of non-ferrous metal ores | I10: 2023 | J10: TTL_07T08: Mining and quarrying, non-energy producing products | K10: ISIC 07T08
A11: ISIC 07T08 | B11: 08 | C11: Other mining and quarrying | I11: 2023 | J11: TTL_09: Mining support service activities | K11: ISIC 09
B12: 081 | C12: Quarrying of stone, sand and clay | I12: 2023 | J12: TTL_10T12: Food products, beverages and tobacco | K12: ISIC 10T12
B13: 089 | C13: Mining and quarrying n.e.c. | I13: 2023 | J13: TTL_13T15: Textiles, textile products, leather and footwear | K13: ISIC 13T15
A14: ISIC 09 | B14: 09 | C14: Mining support service activities | I14: 2018 | J14: TTL_13T15: Textiles, wearing apparel, leather and related products
B15: 091 | C15: Support activities for petroleum | I15: 2018 | J15: TTL_16: Wood and of products of wood and cork (except furniture)
B16: 099 | C16: Support activities for other mining, quarrying | I16: 2023 | J16: TTL_16: Wood and products of wood and cork | K16: ISIC 16
B17: 0B | C17: Mining and quarrying | I17: 2023 | J17: TTL_17T18: Paper products and printing | K17: ISIC 17T18
B18: 35 | C18: Electricity, gas, steam & air conditioning | I18: 2023 | J18: TTL_19: Coke and refined petroleum products | K18: ISIC 19
A19: ISIC 351 | B19: 351 | C19: Electric power generation, transmission | I19: 2023 | J19: TTL_20: Chemical and chemical products | K19: ISIC 20
A20: ISIC 352T353 | B20: 352 | C20: Manufacture of gas | I20: 2018 | J20: TTL_20T21: Chemicals and pharmaceutical products
A21: ISIC 352T353 | B21: 353 | C21: Steam and air conditioning supply | I21: 2023 | J21: TTL_21: Pharmaceuticals, medicinal chemical and botanical products | K21: ISIC 21
B22: 35D | C22: Electricity, gas, steam & air conditioning | I22: 2023 | J22: TTL_22: Rubber and plastics products | K22: ISIC 22
A23: ISIC 36T39 | B23: 36 | C23: Water collection, treatment and supply | I23: 2023 | J23: TTL_23: Other non-metallic mineral products
B24: 360 | C24: Water collection, treatment and supply | I24: 2023 | J24: TTL_24: Basic metals
A25: ISIC 36T39 | B25: 37 | C25: Sewerage | I25: 2018 | J25: TTL_24: Manufacture of basic metals
B26: 370 | C26: Sewerage | I26: 2023 | J26: TTL_25: Fabricated metal products | K26: ISIC 25
A27: ISIC 36T39 | B27: 38 | C27: Waste collection,treatment,disposal activities | I27: 2018 | J27: TTL_25: Fabricated metal products, except machinery and equipment
B28: 381 | C28: Waste collection | I28: 2023 | J28: TTL_26: Computer, electronic and optical equipment | K28: ISIC 26
B29: 382 | C29: Waste treatment and disposal | I29: 2018 | J29: TTL_26: Computer, electronic and optical products
B30: 383 | C30: Materials recovery | I30: 2023 | J30: TTL_27: Electrical equipment | K30: ISIC 27
A31: ISIC 36T39 | B31: 39 | C31: Remediation activities | I31: 2018 | J31: TTL_28: Machinery and equipment n.e.c.
B32: 390 | C32: Remediation activities | I32: 2023 | J32: TTL_28: Machinery and equipment, nec | K32: ISIC 28
A33: ISIC 36T39 | B33: 39E | C33: Water supply;sewerage,waste management | I33: 2023 | J33: TTL_29: Motor vehicles, trailers and semi-trailers | K33: ISIC 29
A34: ISIC 10T12 | B34: 1010 | C34: Processing/preserving of meat | I34: 2023 | J34: TTL_30: Other transport equipment | K34: ISIC 30
A35: ISIC 10T12 | B35: 1020 | C35: Processing/preserving of fish, etc. | I35: 2023 | J35: TTL_31T33: Manufacturing nec; repair and installation of machinery and equipment | K35: ISIC 31T33
A36: ISIC 10T12 | B36: 1030 | C36: Processing/preserving of fruit,vegetables | I36: 2018 | J36: TTL_31T33: Other manufacturing; repair and installation of machinery and equipment
A37: ISIC 10T12 | B37: 1040 | C37: Vegetable and animal oils and fats | I37: 2023 | J37: TTL_35: Electricity, gas, steam and air conditioning supply
A38: ISIC 10T12 | B38: 1050 | C38: Dairy products | I38: 2018 | J38: TTL_35T39: Electricity, gas, water supply, sewerage, waste and remediation services
A39: ISIC 10T12 | B39: 106 | C39: Grain mill products,starches and starch products | I39: 2023 | J39: TTL_36T39: Water supply; sewerage, waste management and remediation activities | K39: ISIC 36T39
B40: 1061 | C40: Grain mill products | I40: 2023 | J40: TTL_41T43: Construction | K40: ISIC 41T43
B41: 1062 | C41: Starches and starch products | I41: 2023 | J41: TTL_45T47: Wholesale and retail trade; repair of motor vehicles | K41: ISIC 45T47
A42: ISIC 10T12 | B42: 107 | C42: Other food products | I42: 2023 | J42: TTL_49: Land transport and transport via pipelines
B43: 1071 | C43: Bakery products | I43: 2018 | J43: TTL_49T53: Transportation and storage | K43: ISIC 49T53
B44: 1072 | C44: Sugar | I44: 2023 | J44: TTL_50: Water transport
B45: 1073 | C45: Cocoa, chocolate and sugar confectionery | I45: 2023 | J45: TTL_51: Air transport
B46: 1074 | C46: Macaroni, noodles, couscous, etc. | I46: 2023 | J46: TTL_52: Warehousing and support activities for transportation
B47: 1075 | C47: Prepared meals and dishes | I47: 2023 | J47: TTL_53: Postal and courier activities
B48: 1079 | C48: Other food products n.e.c. | I48: 2023 | J48: TTL_55T56: Accommodation and food service activities | K48: ISIC 55T56
A49: ISIC 10T12 | B49: 1080 | C49: Prepared animal feeds | I49: 2018 | J49: TTL_55T56: Accomodation and food services
A50: ISIC 10T12 | B50: 110 | C50: Beverages | I50: 2023 | J50: TTL_58T60: Publishing, audiovisual and broadcasting activities | K50: ISIC 58T60
B51: 1101 | C51: Distilling, rectifying and blending of spirits | I51: 2023 | J51: TTL_61: Telecommunications | K51: ISIC 61
B52: 1102 | C52: Wines | I52: 2023 | J52: TTL_62T63: IT and other information services | K52: ISIC 62T63
B53: 1103 | C53: Malt liquors and malt | I53: 2023 | J53: TTL_64T66: Financial and insurance activities | K53: ISIC 64T66
B54: 1104 | C54: Soft drinks,mineral waters,other bottled waters | I54: 2023 | J54: TTL_68: Real estate activities | K54: ISIC 68
A55: ISIC 10T12 | B55: 1200 | C55: Tobacco products | I55: 2023 | J55: TTL_69T75: Professional, scientific and technical activities
A56: ISIC 13T15 | B56: 131 | C56: Spinning, weaving and finishing of textiles | I56: 2018 | J56: TTL_69T82: Other business sector services | K56: ISIC 69T82
B57: 1311 | C57: Preparation and spinning of textile fibres | I57: 2023 | J57: TTL_77T82: Administrative and support services
B58: 1312 | C58: Weaving of textiles | I58: 2023 | J58: TTL_84: Public administration and defence; compulsory social security | K58: ISIC 84
B59: 1313 | C59: Finishing of textiles | I59: 2023 | J59: TTL_85: Education | K59: ISIC 85
A60: ISIC 13T15 | B60: 139 | C60: Other textiles | I60: 2018 | J60: TTL_86T88: Human health and social work
B61: 1391 | C61: Knitted and crocheted fabrics | I61: 2023 | J61: TTL_86T88: Human health and social work activities | K61: ISIC 86T88
B62: 1392 | C62: Made-up textile articles, except apparel | I62: 2023 | J62: TTL_90T93: Arts, entertainment and recreation
B63: 1393 | C63: Carpets and rugs | I63: 2018 | J63: TTL_90T96: Arts, entertainment, recreation and other service activities | K63: ISIC 90T96
B64: 1394 | C64: Cordage, rope, twine and netting | I64: 2023 | J64: TTL_94T96: Other service activities
B65: 1399 | C65: Other textiles n.e.c. | I65: 2023 | J65: TTL_97T98: Activities of households as employers; undifferentiated goods- and services-producing activities of households for own use | K65: ISIC 97T98
A66: ISIC 13T15 | B66: 1410 | C66: Wearing apparel, except fur apparel | I66: 2018 | J66: TTL_97T98: Private households with employed persons
A67: ISIC 13T15 | B67: 1420 | C67: Articles of fur
A68: ISIC 13T15 | B68: 1430 | C68: Knitted and crocheted apparel
A69: ISIC 13T15 | B69: 151 | C69: Leather;luggage,handbags,saddlery,harness;fur
B70: 1511 | C70: Tanning/dressing of leather; dressing of fur
B71: 1512 | C71: Luggage,handbags,etc.;saddlery/harness
A72: ISIC 13T15 | B72: 1520 | C72: Footwear
A73: ISIC 16 | B73: 1610 | C73: Sawmilling and planing of wood
A74: ISIC 16 | B74: 162 | C74: Wood products, cork, straw, plaiting materials
B75: 1621 | C75: Veneer sheets and wood-based panels
B76: 1622 | C76: Builders' carpentry and joinery
B77: 1623 | C77: Wooden containers
B78: 1629 | C78: Other wood products;articles of cork,straw
A79: ISIC 17T18 | B79: 170 | C79: Paper and paper products
B80: 1701 | C80: Pulp, paper and paperboard
B81: 1702 | C81: Corrugated paper and paperboard
B82: 1709 | C82: Other articles of paper and paperboard
A83: ISIC 17T18 | B83: 181 | C83: Printing and service activities related to printing
B84: 1811 | C84: Printing
B85: 1812 | C85: Service activities related to printing
A86: ISIC 17T18 | B86: 1820 | C86: Reproduction of recorded media
A87: ISIC 19 | B87: 1910 | C87: Coke oven products
A88: ISIC 19 | B88: 1920 | C88: Refined petroleum products
A89: ISIC 20 | B89: 201 | C89: Basic chemicals,fertilizers, etc.
B90: 2011 | C90: Basic chemicals
B91: 2012 | C91: Fertilizers and nitrogen compounds
B92: 2013 | C92: Plastics and synthetic rubber in primary forms
A93: ISIC 20 | B93: 202 | C93: Other chemical products
B94: 2021 | C94: Pesticides and other agrochemical products
B95: 2022 | C95: Paints,varnishes;printing ink and mastics
B96: 2023 | C96: Soap,cleaning and cosmetic preparations
B97: 2029 | C97: Other chemical products n.e.c.
B98: 2030 | C98: Man-made fibres
A99: ISIC 21 | B99: 2100 | C99: Pharmaceuticals,medicinal chemicals, etc.
A100: ISIC 22 | B100: 221 | C100: Rubber products
B101: 2211 | C101: Rubber tyres and tubes
...

Sheet EXIOBASE final demand matrix
A1: Sector | B1: ISIC code | C1: Sector ID | D1: Final consumption expenditure by households | E1: Final consumption expenditure by non-profit organisations serving households (NPISH) | F1: Final consumption expenditure by government | G1: Gross fixed capital formation | H1: Changes in inventories | I1: Changes in valuables | J1: Exports: Total (fob) | K1: Households and organizations serving households | L1: % households
A2: Paddy rice | B2: =VLOOKUP(A2, 'ISIC Code Mapping'!$A$2:$C$201, 3, FALSE) -> ISIC 01T03 | C2: 1 | D2: 0 | E2: 0 | F2: 0 | G2: 0 | H2: 153.80468 | I2: 0 | J2: 0.066205081 | K2: =D2+E2 -> 0 | L2: =IF(K2>0, D2/K2, "N/A") -> N/A
A3: Wheat | B3: =VLOOKUP(A3, 'ISIC Code Mapping'!$A$2:$C$201, 3, FALSE) -> ISIC 01T03 | C3: 2 | D3: 0 | E3: 0 | F3: 0 | G3: 0 | H3: 8.0469878 | I3: 0 | J3: 0.03552528 | K3: =D3+E3 -> 0 | L3: =IF(K3>0, D3/K3, "N/A") -> N/A
A4: Cereal grains nec | B4: =VLOOKUP(A4, 'ISIC Code Mapping'!$A$2:$C$201, 3, FALSE) -> ISIC 01T03 | C4: 3 | D4: 0 | E4: 0 | F4: 0 | G4: 0 | H4: 18.286038 | I4: 0 | J4: 0.58681183 | K4: =D4+E4 -> 0 | L4: =IF(K4>0, D4/K4, "N/A") -> N/A
A5: Vegetables, fruit, nuts | B5: =VLOOKUP(A5, 'ISIC Code Mapping'!$A$2:$C$201, 3, FALSE) -> ISIC 01T03 | C5: 4 | D5: 7667.2109 | E5: 0 | F5: 0 | G5: 58.06951 | H5: 154.7706 | I5: 0 | J5: 292.25767 | K5: =D5+E5 -> 7667.2109 | L5: =IF(K5>0, D5/K5, "N/A") -> 1
A6: Oil seeds | B6: =VLOOKUP(A6, 'ISIC Code Mapping'!$A$2:$C$201, 3, FALSE) -> ISIC 01T03 | C6: 5 | D6: 14.871594 | E6: 0 | F6: 0 | G6: 0 | H6: 17.91034 | I6: 0 | J6: 5.328702 | K6: =D6+E6 -> 14.871594 | L6: =IF(K6>0, D6/K6, "N/A") -> 1
A7: Sugar cane, sugar beet | B7: =VLOOKUP(A7, 'ISIC Code Mapping'!$A$2:$C$201, 3, FALSE) -> ISIC 01T03 | C7: 6 | D7: 0 | E7: 0 | F7: 0 | G7: 0 | H7: 0 | I7: 0 | J7: 0 | K7: =D7+E7 -> 0 | L7: =IF(K7>0, D7/K7, "N/A") -> N/A
A8: Plant-based fibers | B8: =VLOOKUP(A8, 'ISIC Code Mapping'!$A$2:$C$201, 3, FALSE) -> ISIC 01T03 | C8: 7 | D8: 0.0051085358 | E8: 0 | F8: 0 | G8: 0 | H8: 0.0032662311 | I8: 0 | J8: 0.00062780236 | K8: =D8+E8 -> 0.0051085358 | L8: =IF(K8>0, D8/K8, "N/A") -> 1
A9: Crops nec | B9: =VLOOKUP(A9, 'ISIC Code Mapping'!$A$2:$C$201, 3, FALSE) -> ISIC 01T03 | C9: 8 | D9: 325.64682 | E9: 0 | F9: 0 | G9: 4.4115765 | H9: 7.0174465 | I9: 0 | J9: 214.60162 | K9: =D9+E9 -> 325.64682 | L9: =IF(K9>0, D9/K9, "N/A") -> 1
A10: Cattle | B10: =VLOOKUP(A10, 'ISIC Code Mapping'!$A$2:$C$201, 3, FALSE) -> ISIC 01T03 | C10: 9 | D10: 0 | E10: 0 | F10: 0 | G10: 0 | H10: 3152.2546 | I10: 0 | J10: 0 | K10: =D10+E10 -> 0 | L10: =IF(K10>0, D10/K10, "N/A") -> N/A
A11: Pigs | B11: =VLOOKUP(A11, 'ISIC Code Mapping'!$A$2:$C$201, 3, FALSE) -> ISIC 01T03 | C11: 10 | D11: 0 | E11: 0 | F11: 0 | G11: 0 | H11: 17.761078 | I11: 0 | J11: 0 | K11: =D11+E11 -> 0 | L11: =IF(K11>0, D11/K11, "N/A") -> N/A
A12: Poultry | B12: =VLOOKUP(A12, 'ISIC Code Mapping'!$A$2:$C$201, 3, FALSE) -> ISIC 01T03 | C12: 11 | D12: 0 | E12: 0 | F12: 0 | G12: 0 | H12: 122.2567 | I12: 0 | J12: 0 | K12: =D12+E12 -> 0 | L12: =IF(K12>0, D12/K12, "N/A") -> N/A
A13: Meat animals nec | B13: =VLOOKUP(A13, 'ISIC Code Mapping'!$A$2:$C$201, 3, FALSE) -> ISIC 01T03 | C13: 12 | D13: 0 | E13: 0 | F13: 0 | G13: 0 | H13: 103.52509 | I13: 0 | J13: 1.1839165 | K13: =D13+E13 -> 0 | L13: =IF(K13>0, D13/K13, "N/A") -> N/A
... A201: Extra-territorial organizations and bodies | B201: =VLOOKUP(A201, 'ISIC Code Mapping'!$A$2:$C$201, 3, FALSE) -> 0 | C201: 200 | D201: 0 | E201: 0 | F201: 0 | G201: 0 | H201: 0 | I201: 0 | J201: 0 | K201: =D201+E201 -> 0 | L201: =IF(K201>0, D201/K201, "N/A") -> N/A

Sheet ISIC Code Mapping
A1: Label | B1: Exiobase Sector Code | C1: ISIC Code
A2: Paddy rice | B2: 1 | C2: ISIC 01T03
A3: Wheat | B3: 2 | C3: ISIC 01T03
A4: Cereal grains nec | B4: 3 | C4: ISIC 01T03
A5: Vegetables, fruit, nuts | B5: 4 | C5: ISIC 01T03
A6: Oil seeds | B6: 5 | C6: ISIC 01T03
A7: Sugar cane, sugar beet | B7: 6 | C7: ISIC 01T03
A8: Plant-based fibers | B8: 7 | C8: ISIC 01T03
A9: Crops nec | B9: 8 | C9: ISIC 01T03
A10: Cattle | B10: 9 | C10: ISIC 01T03
A11: Pigs | B11: 10 | C11: ISIC 01T03
A12: Poultry | B12: 11 | C12: ISIC 01T03
A13: Meat animals nec | B13: 12 | C13: ISIC 01T03
... A200: Private households with employed persons (95) | B200: 199 | C200: ISIC 97T98
A201: Extra-territorial organizations and bodies | B201: 200

Sheet KOR WIOD IO-tables
A1: Source: World Input-Output Database
E2: A01 | F2: A02 | G2: A03 | H2: B | I2: C10-C12 | J2: C13-C15 | K2: C16 | L2: C17 | M2: C18 | N2: C19 | O2: C20 | P2: C21 | Q2: C22 | R2: C23 | S2: C24 | T2: C25 | U2: C26 | V2: C27 | W2: C28 | X2: C29 | Y2: C30 | Z2: C31_C32 | AA2: C33 | AB2: D35 | AC2: E36 | AD2: E37-E39 | AE2: F | AF2: G45 | AG2: G46 | AH2: G47 | AI2: H49 | AJ2: H50 | AK2: H51 | AL2: H52 | AM2: H53 | AN2: I | AO2: J58 | AP2: J59_J60 | AQ2: J61 | AR2: J62_J63 | AS2: K64 | AT2: K65 | AU2: K66 | AV2: L68 | AW2: M69_M70 | AX2: M71 | AY2: M72 | AZ2: M73 | BA2: M74_M75 | BB2: N | BC2: O84 | BD2: P85 | BE2: Q | BF2: R_S | BG2: T | BH2: U | BI2: CONS_h | BJ2: CONS_np | BK2: CONS_g | BL2: GFCF | BM2: INVEN | BN2: EXP | BO2: GO
A3: Year | B3: Code | C3: Description | D3: Origin | E3: Crop and animal production, hunting and related service activities | F3: Forestry and logging | G3: Fishing and aquaculture | H3: Mining and quarrying | I3: Manufacture of food products, beverages and tobacco products | J3: Manufacture of textiles, wearing apparel and leather products | K3: Manufacture of wood and of products of wood and cork, except furniture; manufacture of articles of straw and plaiting materials | L3: Manufacture of paper and paper products | M3: Printing and reproduction of recorded media | N3: Manufacture of coke and refined petroleum products | O3: Manufacture of chemicals and chemical products | P3: Manufacture of basic pharmaceutical products and pharmaceutical preparations | Q3: Manufacture of rubber and plastic products | R3: Manufacture of other non-metallic mineral products | S3: Manufacture of basic metals | T3: Manufacture of fabricated metal products, except machinery and equipment | U3: Manufacture of computer, electronic and optical products | V3: Manufacture of electrical equipment | W3: Manufacture of machinery and equipment n.e.c. | X3: Manufacture of motor vehicles, trailers and semi-trailers | Y3: Manufacture of other transport equipment | Z3: Manufacture of furniture; other manufacturing | AA3: Repair and installation of machinery and equipment | AB3: Electricity, gas, steam and air conditioning supply | AC3: Water collection, treatment and supply | AD3: Sewerage; waste collection, treatment and disposal activities; materials recovery; remediation activities and other waste management services | AE3: Construction | AF3: Wholesale and retail trade and repair of motor vehicles and motorcycles | AG3: Wholesale trade, except of motor vehicles and motorcycles | AH3: Retail trade, except of motor vehicles and motorcycles | AI3: Land transport and transport via pipelines | AJ3: Water transport | AK3: Air transport | AL3: Warehousing and support activities for transportation | AM3: Postal and courier activities | AN3: Accommodation and food service activities | AO3: Publishing activities | AP3: Motion picture, video and television programme production, sound recording and music publishing activities; programming and broadcasting activities | AQ3: Telecommunications | AR3: Computer programming, consultancy and related activities; information service activities | AS3: Financial service activities, except insurance and pension funding | AT3: Insurance, reinsurance and pension funding, except compulsory social security | AU3: Activities auxiliary to financial services and insurance activities | AV3: Real estate activities | AW3: Legal and accounting activities; activities of head offices; management consultancy activities | AX3: Architectural and engineering activities; technical testing and analysis | AY3: Scientific research and development | AZ3: Advertising and market research | BA3: Other professional, scientific and technical activities; veterinary activities | BB3: Administrative and support service activities | BC3: Public administration and defence; compulsory social security | BD3: Education | BE3: Human health and social work activities | BF3: Other service activities | BG3: Activities of households as employers; undifferentiated goods- and services-producing activities of households for own use | BH3: Activities of extraterritorial organizations and bodies | BI3: Final consumption expenditure by households | BJ3: Final consumption expenditure by non-profit organisations serving households (NPISH) | BK3: Final consumption expenditure by government | BL3: Gross fixed capital formation | BM3: Changes in inventories and valuables | BN3: Exports | BO3: Total output | BQ3: Final consumption expenditure by households and orgs serving households
A4: 2014 | B4: A01 | C4: Crop and animal production, hunting and related service activities | D4: Domestic | E4: 2375.8662 | F4: 423.38433 | G4: 57.422173 | H4: 0.36671585 | I4: 26723.8 | J4: 569.33077 | K4: 0.36448055 | L4: 1.5170069 | M4: 1.9803197 | N4: 3.0901806 | O4: 84.079269 | P4: 866.3993 | Q4: 400.15552 | R4: 1.3785865 | S4: 7.1841145 | T4: 4.6550551 | U4: 15.735263 | V4: 3.3145958 | W4: 7.5865767 | X4: 12.405886 | Y4: 3.2903294 | Z4: 5.8572838 | AA4: 0 | AB4: 2.0941513 | AC4: 2.9312599 | AD4: 2.6771131 | AE4: 766.94268 | AF4: 3.917867 | AG4: 24.617969 | AH4: 34.366649 | AI4: 3.6209252 | AJ4: 0.5908776 | AK4: 0.2873582 | AL4: 13.057635 | AM4: 0.2692843 | AN4: 1772.0367 | AO4: 5.6277376 | AP4: 4.9923011 | AQ4: 2.0951126 | AR4: 9.2068302 | AS4: 23.154172 | AT4: 4.0985106 | AU4: 2.7454442 | AV4: 3.0472708 | AW4: 4.0476463 | AX4: 11.112646 | AY4: 47.216027 | AZ4: 0.025521093 | BA4: 7.1343845 | BB4: 17.526693 | BC4: 69.780243 | BD4: 432.30832 | BE4: 713.47637 | BF4: 97.112352 | BG4: 0 | BH4: 0 | BI4: 10716.412 | BJ4: 0 | BK4: 0.04410552 | BL4: 290.74291 | BM4: 289.01019 | BN4: 406.80609 | BO4: 47354.297
A5: 2014 | B5: A02 | C5: Forestry and logging | D5: Domestic | E5: 71.700954 | F5: 251.61852 | G5: 7.4254035 | H5: 3.5939201 | I5: 618.11177 | J5: 1.5655722 | K5: 946.62106 | L5: 1.5674854 | M5: 0.027816388 | N5: 0.096488172 | O5: 22.808921 | P5: 26.353876 | Q5: 1.0683278 | R5: 0.074614789 | S5: 0.12502897 | T5: 0.61579892 | U5: 0.53960168 | V5: 0.25379875 | W5: 0.24538813 | X5: 0.27134451 | Y5: 0.12984142 | Z5: 6.4490293 | AA5: 0 | AB5: 0.036097841 | AC5: 1.6775788 | AD5: 0.027326365 | AE5: 79.176758 | AF5: 0.034793693 | AG5: 0.21971498 | AH5: 0.30653414 | AI5: 0.082402767 | AJ5: 0.0089506849 | AK5: 0.0015507644 | AL5: 0.053805096 | AM5: 0.0022745969 | AN5: 210.00092 | AO5: 0.043343663 | AP5: 0.070707894 | AQ5: 0.063999875 | AR5: 0.038498081 | AS5: 0.071436073 | AT5: 0.013463826 | AU5: 0.010402949 | AV5: 0.050233112 | AW5: 0.063149838 | AX5: 0.039295227 | AY5: 1.5557981 | AZ5: 0.00079425806 | BA5: 0.028131598 | BB5: 0.24551939 | BC5: 0.97675735 | BD5: 29.294845 | BE5: 28.366379 | BF5: 1.7587602 | BG5: 0 | BH5: 0 | BI5: 632.12915 | BJ5: 0 | BK5: 0 | BL5: 287.39783 | BM5: 123.5807 | BN5: 32.850656 | BO5: 3391.5431
A6: 2014 | B6: A03 | C6: Fishing and aquaculture | D6: Domestic | E6: 0.153176 | F6: 0.0011743354 | G6: 116.10146 | H6: 0.0037492956 | I6: 2510.2868 | J6: 0.21280081 | K6: 0.0076002733 | L6: 0.035283739 | M6: 0.023579685 | N6: 0.051779091 | O6: 2.0314047 | P6: 0.38520339 | Q6: 0.040192631 | R6: 0.022160607 | S6: 0.074033834 | T6: 1.0857077 | U6: 0.28725826 | V6: 0.14454029 | W6: 0.13434072 | X6: 0.16586032 | Y6: 0.081666228 | Z6: 6.1262377 | AA6: 0 | AB6: 0.022920079 | AC6: 0.014233501 | AD6: 0.012050586 | AE6: 0.16526042 | AF6: 0.19916766 | AG6: 1.2521264 | AH6: 1.7478539 | AI6: 0.12586614 | AJ6: 0.0057802954 | AK6: 0.0015611819 | AL6: 0.038485848 | AM6: 0.0013607188 | AN6: 876.65545 | AO6: 0.029245662 | AP6: 0.30455646 | AQ6: 0.043913317 | AR6: 0.023302797 | AS6: 0.049005233 | AT6: 0.011560884 | AU6: 0.015415566 | AV6: 0.38512262 | AW6: 0.086296011 | AX6: 0.020941545 | AY6: 19.830665 | AZ6: 0.00067951796 | BA6: 0.0446523 | BB6: 1.4372324 | BC6: 0.036466318 | BD6: 144.91752 | BE6: 137.40531 | BF6: 21.600233 | BG6: 0 | BH6: 0 | BI6: 1178.3223 | BJ6: 0 | BK6: 0 | BL6: 0.36117162 | BM6: 21.943442 | BN6: 200.24733 | BO6: 5244.8145
A7: 2014 | B7: B | C7: Mining and quarrying | D7: Domestic | E7: 0.66397976 | F7: 0.02342087 | G7: 0.072499982 | H7: 0.066068677 | I7: 6.3094564 | J7: 6.7586119 | K7: 0.21863153 | L7: 1.6883186 | M7: 0.32282228 | N7: 2823.0183 | O7: 29.773745 | P7: 3.2061842 | Q7: 0.85470987 | R7: 37.012293 | S7: 676.231 | T7: 4.1784235 | U7: 32.249432 | V7: 4.8280035 | W7: 5.6570082 | X7: 8.1574984 | Y7: 6.4866268 | Z7: 2.8069531 | AA7: 0 | AB7: 1033.7074 | AC7: 0.55619448 | AD7: 0.81979205 | AE7: 68.76046 | AF7: 0.14268771 | AG7: 0.91260546 | AH7: 1.2712328 | AI7: 1.077402 | AJ7: 0.14328137 | AK7: 0.06900229 | AL7: 0.65854958 | AM7: 0.040600158 | AN7: 2.3133925 | AO7: 0.51105218 | AP7: 0.41223544 | AQ7: 0.92752048 | AR7: 0.35619622 | AS7: 0.66055289 | AT7: 0.18059115 | AU7: 0.18937852 | AV7: 0.29356568 | AW7: 0.25043314 | AX7: 0.37943549 | AY7: 0.82566433 | AZ7: 0.010315966 | BA7: 0.20407192 | BB7: 0.65508061 | BC7: 0.88416519 | BD7: 1.6553966 | BE7: 2.1027373 | BF7: 1.574976 | BG7: 0 | BH7: 0 | BI7: 42.297223 | BJ7: 0 | BK7: 0 | BL7: 7.7949102 | BM7: -792.26588 | BN7: 271.36732 | BO7: 4302.3236
A8: 2014 | B8: C10-C12 | C8: Manufacture of food products, beverages and tobacco products | D8: Domestic | E8: 8588.1288 | F8: 1.6416271 | G8: 195.59589 | H8: 6.1262874 | I8: 19842.917 | J8: 963.6938 | K8: 9.2170614 | L8: 78.43199 | M8: 20.987381 | N8: 45.03965 | O8: 1402.4137 | P8: 606.60591 | Q8: 37.500734 | R8: 26.768992 | S8: 144.94615 | T8: 114.98726 | U8: 508.70189 | V8: 100.85284 | W8: 191.14705 | X8: 296.51655 | Y8: 240.5871 | Z8: 97.491068 | AA8: 0 | AB8: 32.728959 | AC8: 26.615443 | AD8: 35.3317 | AE8: 148.4817 | AF8: 39.22812 | AG8: 246.55587 | AH8: 344.18034 | AI8: 39.843674 | AJ8: 6.029992 | AK8: 3.7532009 | AL8: 189.6089 | AM8: 3.4917441 | AN8: 14277.321 | AO8: 51.375996 | AP8: 53.648039 | AQ8: 26.504745 | AR8: 93.523895 | AS8: 163.3337 | AT8: 41.255877 | AU8: 31.196937 | AV8: 36.878217 | AW8: 34.554001 | AX8: 121.04931 | AY8: 345.27895 | AZ8: 0.27428677 | BA8: 79.282994 | BB8: 485.41246 | BC8: 207.98767 | BD8: 2157.1266 | BE8: 1500.2663 | BF8: 1489.6791 | BG8: 0 | BH8: 0 | BI8: 40454.491 | BJ8: 0 | BK8: 1.1125698 | BL8: 104.52648 | BM8: 694.77482 | BN8: 6585.8251 | BO8: 103672.83
A9: 2014 | B9: C13-C15 | C9: Manufacture of textiles, wearing apparel and leather products | D9: Domestic | E9: 181.71237 | F9: 7.0508001 | G9: 133.8888 | H9: 10.519164 | I9: 413.00446 | J9: 22204.05 | K9: 28.513065 | L9: 365.72511 | M9: 54.684818 | N9: 88.609921 | O9: 733.33629 | P9: 160.43104 | Q9: 510.8001 | R9: 94.606347 | S9: 497.00273 | T9: 441.97868 | U9: 1899.9498 | V9: 359.96102 | W9: 573.44001 | X9: 1377.7683 | Y9: 959.95006 | Z9: 1967.6967 | AA9: 0 | AB9: 175.10792 | AC9: 119.72236 | AD9: 408.1805 | AE9: 886.52374 | AF9: 81.020672 | AG9: 509.19401 | AH9: 710.81693 | AI9: 375.45101 | AJ9: 24.514459 | AK9: 7.1924652 | AL9: 998.11479 | AM9: 33.840139 | AN9: 324.239 | AO9: 50.226416 | AP9: 128.79915 | AQ9: 41.541184 | AR9: 43.406001 | AS9: 267.75633 | AT9: 91.326337 | AU9: 78.130686 | AV9: 70.360796 | AW9: 25.776082 | AX9: 80.104817 | AY9: 141.3956 | AZ9: 0.33632675 | BA9: 133.35671 | BB9: 683.91768 | BC9: 576.43152 | BD9: 276.2506 | BE9: 575.69516 | BF9: 928.89044 | BG9: 0 | BH9: 0 | BI9: 11825.814 | BJ9: 0 | BK9: 0.14601378 | BL9: 431.81527 | BM9: 635.51933 | BN9: 26182.705 | BO9: 80988.299
A10: 2014 | B10: C16 | C10: Manufacture of wood and of products of wood and cork, except furniture; manufacture of articles of straw and plaiting materials | D10: Domestic | E10: 32.196511 | F10: 1.853963 | G10: 69.063513 | H10: 4.647851 | I10: 55.061001 | J10: 35.690136 | K10: 867.85917 | L10: 78.503152 | M10: 2.2955963 | N10: 8.4893676 | O10: 59.400795 | P10: 5.0580171 | Q10: 9.5490073 | R10: 48.178705 | S10: 126.66051 | T10: 163.36337 | U10: 92.467763 | V10: 75.816005 | W10: 97.498143 | X10: 169.62145 | Y10: 179.06427 | Z10: 992.3766 | AA10: 0 | AB10: 66.684535 | AC10: 1.6764386 | AD10: 18.166056 | AE10: 1779.7854 | AF10: 4.4860906 | AG10: 28.198477 | AH10: 39.363296 | AI10: 9.2667512 | AJ10: 0.62935747 | AK10: 0.2134084 | AL10: 284.09213 | AM10: 0.11877576 | AN10: 54.208667 | AO10: 1.8069708 | AP10: 5.0969803 | AQ10: 0.87429344 | AR10: 0.60765694 | AS10: 1.8987782 | AT10: 0.4608295 | AU10: 0.30283455 | AV10: 1.6065644 | AW10: 0.35618745 | AX10: 71.353706 | AY10: 4.4364393 | AZ10: 0.029809572 | BA10: 8.8624928 | BB10: 2.8501061 | BC10: 7.9954277 | BD10: 30.198253 | BE10: 24.888831 | BF10: 60.533833 | BG10: 0 | BH10: 0 | BI10: 86.147426 | BJ10: 0 | BK10: 0.0080997209 | BL10: 11.006103 | BM10: 2.8497834 | BN10: 166.7923 | BO10: 5952.568
A11: 2014 | B11: C17 | C11: Manufacture of paper and paper products | D11: Domestic | E11: 161.76971 | F11: 0.54302279 | G11: 3.3273901 | H11: 1.9526515 | I11: 1296.2086 | J11: 481.14985 | K11: 27.467533 | L11: 5069.0809 | M11: 1560.1276 | N11: 30.673969 | O11: 509.87888 | P11: 567.10126 | Q11: 89.872947 | R11: 111.9386 | S11: 114.56699 | T11: 206.54182 | U11: 652.08546 | V11: 473.53608 | W11: 185.82965 | X11: 179.01989 | Y11: 116.64545 | Z11: 207.62971 | AA11: 0 | AB11: 21.000571 | AC11: 12.846209 | AD11: 140.90716 | AE11: 326.23185 | AF11: 95.286504 | AG11: 598.72523 | AH11: 835.82106 | AI11: 46.819106 | AJ11: 3.2989824 | AK11: 1.2368335 | AL11: 161.89858 | AM11: 51.132503 | AN11: 205.11956 | AO11: 2046.5046 | AP11: 29.232243 | AQ11: 13.380042 | AR11: 97.942971 | AS11: 136.34971 | AT11: 37.438873 | AU11: 25.901674 | AV11: 25.822571 | AW11: 47.686316 | AX11: 126.88882 | AY11: 99.843294 | AZ11: 0.1259069 | BA11: 61.942984 | BB11: 91.249708 | BC11: 89.472224 | BD11: 254.23531 | BE11: 69.277755 | BF11: 135.21108 | BG11: 0 | BH11: 0 | BI11: 492.52652 | BJ11: 0 | BK11: 0.0022419656 | BL11: 24.824539 | BM11: -1352.9867 | BN11: 3448.3845 | BO11: 20548.529
A12: 2014 | B12: C18 | C12: Printing and reproduction of recorded media | D12: Domestic | E12: 8.9431355 | F12: 0.016962624 | G12: 0.32129329 | H12: 0.91543185 | I12: 196.81321 | J12: 148.25117 | K12: 2.2936708 | L12: 176.39756 | M12: 1414.2566 | N12: 128.19591 | O12: 153.3424 | P12: 266.32132 | Q12: 49.613804 | R12: 13.487036 | S12: 44.521278 | T12: 57.268779 | U12: 351.49006 | V12: 57.991825 | W12: 51.275521 | X12: 61.333348 | Y12: 29.545046 | Z12: 34.183906 | AA12: 0 | AB12: 21.810779 | AC12: 96.611893 | AD12: 21.340056 | AE12: 36.348353 | AF12: 24.317317 | AG12: 152.79349 | AH12: 213.30029 | AI12: 87.568836 | AJ12: 3.7081777 | AK12: 1.0019255 | AL12: 187.09648 | AM12: 155.94277 | AN12: 21.843018 | AO12: 1061.3749 | AP12: 61.918993 | AQ12: 35.270784 | AR12: 102.26642 | AS12: 1021.4452 | AT12: 133.01152 | AU12: 51.752236 | AV12: 18.972305 | AW12: 195.73074 | AX12: 220.5203 | AY12: 224.63133 | AZ12: 0.72988015 | BA12: 56.984405 | BB12: 81.250179 | BC12: 950.78898 | BD12: 731.22835 | BE12: 398.77135 | BF12: 461.91472 | BG12: 0 | BH12: 0 | BI12: 79.814733 | BJ12: 0 | BK12: 0.16803533 | BL12: 8.6662057 | BM12: -83.194463 | BN12: 207.20701 | BO12: 10291.687
A13: 2014 | B13: C19 | C13: Manufacture of coke and refined petroleum products | D13: Domestic | E13: 729.07057 | F13: 48.561447 | G13: 338.02254 | H13: 133.80155 | I13: 482.03195 | J13: 675.19919 | K13: 42.545028 | L13: 293.80343 | M13: 92.183411 | N13: 6509.4687 | O13: 27023.01 | P13: 420.79472 | Q13: 410.16664 | R13: 780.05098 | S13: 1244.3691 | T13: 810.69366 | U13: 980.54541 | V13: 464.37275 | W13: 591.86334 | X13: 601.94145 | Y13: 537.7052 | Z13: 142.95694 | AA13: 0 | AB13: 3398.8529 | AC13: 349.8312 | AD13: 302.91747 | AE13: 2417.7225 | AF13: 134.28616 | AG13: 843.82476 | AH13: 1177.9719 | AI13: 8570.8549 | AJ13: 2137.5984 | AK13: 2271.7095 | AL13: 662.53857 | AM13: 116.19578 | AN13: 864.59038 | AO13: 113.07869 | AP13: 155.94053 | AQ13: 47.221039 | AR13: 81.814502 | AS13: 201.27974 | AT13: 33.292722 | AU13: 19.67793 | AV13: 270.36279 | AW13: 237.83506 | AX13: 347.50718 | AY13: 137.68432 | AZ13: 0.47095512 | BA13: 156.5876 | BB13: 429.41818 | BC13: 739.60681 | BD13: 1300.6352 | BE13: 597.90559 | BF13: 939.98726 | BG13: 0 | BH13: 0 | BI13: 3280.1819 | BJ13: 0 | BK13: 0.05995792 | BL13: 28.65426 | BM13: 450.77737 | BN13: 56677.021 | BO13: 132849.05
A14: 2014 | B14: C20 | C14: Manufacture of chemicals and chemical products | D14: Domestic | E14: 2380.3294 | F14: 200.92162 | G14: 34.291769 | H14: 100.49147 | I14: 1096.037 | J14: 6468.8046 | K14: 321.18378 | L14: 1264.3066 | M14: 762.80046 | N14: 3719.1377 | O14: 58504.948 | P14: 4753.6404 | Q14: 6395.6298 | R14: 906.06131 | S14: 2062.9936 | T14: 2770.8719 | U14: 12828.404 | V14: 3197.432 | W14: 1479.2527 | X14: 2200.0642 | Y14: 1553.9522 | Z14: 1093.8944 | AA14: 0 | AB14: 2275.8346 | AC14: 981.15411 | AD14: 575.94578 | AE14: 3234.7026 | AF14: 30.504575 | AG14: 191.78065 | AH14: 267.70744 | AI14: 795.31884 | AJ14: 64.868627 | AK14: 54.60935 | AL14: 320.2974 | AM14: 10.305053 | AN14: 294.8424 | AO14: 687.9631 | AP14: 250.08749 | AQ14: 17.788366 | AR14: 49.679763 | AS14: 50.250855 | AT14: 19.235858 | AU14: 18.559152 | AV14: 58.564037 | AW14: 34.701898 | AX14: 277.20132 | AY14: 1218.3422 | AZ14: 0.49969797 | BA14: 396.3673 | BB14: 2015.1446 | BC14: 261.73172 | BD14: 305.0121 | BE14: 1550.9212 | BF14: 2365.8698 | BG14: 0 | BH14: 0 | BI14: 4152.0453 | BJ14: 0 | BK14: 0.009432764 | BL14: 187.92968 | BM14: -2962.6478 | BN14: 66739.526 | BO14: 200888.1
A15: 2014 | B15: C21 | C15: Manufacture of basic pharmaceutical products and pharmaceutical preparations | D15: Domestic | E15: 194.67675 | F15: 0.50378163 | G15: 16.708611 | H15: 2.147035 | I15: 764.9693 | J15: 174.27683 | K15: 5.2549203 | L15: 20.948455 | M15: 4.8900291 | N15: 30.665191 | O15: 274.50002 | P15: 8655.2548 | Q15: 21.868823 | R15: 10.796034 | S15: 60.434723 | T15: 62.552654 | U15: 331.25227 | V15: 61.345756 | W15: 96.793549 | X15: 167.01143 | Y15: 139.28254 | Z15: 58.59541 | AA15: 0 | AB15: 23.164084 | AC15: 46.176147 | AD15: 71.188687 | AE15: 80.791666 | AF15: 2.6337942 | AG15: 16.724257 | AH15: 23.316904 | AI15: 20.408337 | AJ15: 3.0854742 | AK15: 46.394681 | AL15: 60.000743 | AM15: 1.4968321 | AN15: 79.233028 | AO15: 8.3432076 | AP15: 11.672343 | AQ15: 14.883908 | AR15: 15.403994 | AS15: 51.804191 | AT15: 37.47544 | AU15: 35.941931 | AV15: 4.5517218 | AW15: 9.0490317 | AX15: 17.934818 | AY15: 341.63469 | AZ15: 0.12272826 | BA15: 6.2777622 | BB15: 162.25412 | BC15: 510.41851 | BD15: 107.10741 | BE15: 19564.47 | BF15: 125.51491 | BG15: 0 | BH15: 0 | BI15: 3355.1431 | BJ15: 0 | BK15: 0 | BL15: 102.35842 | BM15: 69.358154 | BN15: 2256.1532 | BO15: 38437.217
... A123: 2014 | B123: GO | C123: Output at basic prices | D123: TOT | E123: 47354.297 | F123: 3391.5431 | G123: 5244.8145 | H123: 4302.3236 | I123: 103672.83 | J123: 80988.299 | K123: 5952.568 | L123: 20548.529 | M123: 10291.687 | N123: 132849.05 | O123: 200888.1 | P123: 38437.217 | Q123: 22422.064 | R123: 16179.696 | S123: 149666.64 | T123: 94002.044 | U123: 312095 | V123: 81461.773 | W123: 114490.22 | X123: 148282.29 | Y123: 106735.61 | Z123: 21108.228 | AA123: 0 | AB123: 104005.54 | AC123: 19275 | AD123: 20158.545 | AE123: 189724.11 | AF123: 11937.556 | AG123: 79110.503 | AH123: 102405.36 | AI123: 65024.348 | AJ123: 12937.012 | AK123: 13906.976 | AL123: 37774.181 | AM123: 5157.3785 | AN123: 69508.467 | AO123: 24435.07 | AP123: 52781.724 | AQ123: 15002.626 | AR123: 21455.767 | AS123: 95310.828 | AT123: 25556.582 | AU123: 17326.758 | AV123: 126619.58 | AW123: 18373.793 | AX123: 30644.449 | AY123: 42942.029 | AZ123: 2312.5229 | BA123: 19138.876 | BB123: 50389.382 | BC123: 132526.19 | BD123: 99773.726 | BE123: 106532.95 | BF123: 71441.735 | BG123: 0 | BH123: 0 | BI123: 0 | BJ123: 0 | BK123: 0 | BL123: 0 | BM123: 0 | BN123: 0 | BO123: 0

Sheet KOR Data for ISIC Splits
B1: Unit | C1: Coal mining | D1: Oil and gas extraction | E1: Chemicals | F1: Pharmaceuticals | G1: Glass | H1: Cement and Other Nometallic Minerals | I1: Iron and steel | J1: Other metals | K1: Electricity generation and distribution | L1: Energy pipelines and gas processing | M1: Water and waste
C2: ISIC 05 | D2: ISIC 06 | E2: ISIC 20 | F2: ISIC 21 | G2: ISIC 231 | H2: ISIC 239 | I2: ISIC 241 | J2: ISIC 242 | K2: ISIC 351 | L2: ISIC 352T353 | M2: ISIC 36T39
A3: Government | B3: M.EUR | C3: =SUMIF('EXIOBASE final demand matrix'!$B:$B, 'KOR Data for ISIC Splits'!C$2, 'EXIOBASE final demand matrix'!$F:$F) -> 0 | D3: =SUMIF('EXIOBASE final demand matrix'!$B:$B, 'KOR Data for ISIC Splits'!D$2, 'EXIOBASE final demand matrix'!$F:$F) -> 0 | E3: ='KOR WIOD IO-tables'!BK14 -> 0.009432764 | F3: ='KOR WIOD IO-tables'!BK15 -> 0 | G3: =SUMIF('EXIOBASE final demand matrix'!$B:$B, 'KOR Data for ISIC Splits'!G$2, 'EXIOBASE final demand matrix'!$F:$F) -> 0 | H3: =SUMIF('EXIOBASE final demand matrix'!$B:$B, 'KOR Data for ISIC Splits'!H$2, 'EXIOBASE final demand matrix'!$F:$F) -> 0 | I3: =SUMIF('EXIOBASE final demand matrix'!$B:$B, 'KOR Data for ISIC Splits'!I$2, 'EXIOBASE final demand matrix'!$F:$F) -> 0 | J3: =SUMIF('EXIOBASE final demand matrix'!$B:$B, 'KOR Data for ISIC Splits'!J$2, 'EXIOBASE final demand matrix'!$F:$F) -> 0 | K3: =SUMIF('EXIOBASE final demand matrix'!$B:$B, 'KOR Data for ISIC Splits'!K$2, 'EXIOBASE final demand matrix'!$F:$F) -> 0 | L3: =SUMIF('EXIOBASE final demand matrix'!$B:$B, 'KOR Data for ISIC Splits'!L$2, 'EXIOBASE final demand matrix'!$F:$F) -> 0 | M3: =SUMIF('EXIOBASE final demand matrix'!$B:$B, 'KOR Data for ISIC Splits'!M$2, 'EXIOBASE final demand matrix'!$F:$F) -> 2824.2866
A4: Households | B4: M.EUR | C4: =SUMIF('EXIOBASE final demand matrix'!$B:$B, 'KOR Data for ISIC Splits'!C$2, 'EXIOBASE final demand matrix'!$K:$K) -> 0 | D4: =SUMIF('EXIOBASE final demand matrix'!$B:$B, 'KOR Data for ISIC Splits'!D$2, 'EXIOBASE final demand matrix'!$K:$K) -> 0 | E4: ='KOR WIOD IO-tables'!BQ14 -> 0 | F4: ='KOR WIOD IO-tables'!BQ15 -> 0 | G4: =SUMIF('EXIOBASE final demand matrix'!$B:$B, 'KOR Data for ISIC Splits'!G$2, 'EXIOBASE final demand matrix'!$K:$K) -> 0 | H4: =SUMIF('EXIOBASE final demand matrix'!$B:$B, 'KOR Data for ISIC Splits'!H$2, 'EXIOBASE final demand matrix'!$K:$K) -> 245.05448 | I4: =SUMIF('EXIOBASE final demand matrix'!$B:$B, 'KOR Data for ISIC Splits'!I$2, 'EXIOBASE final demand matrix'!$K:$K) -> 0 | J4: =SUMIF('EXIOBASE final demand matrix'!$B:$B, 'KOR Data for ISIC Splits'!J$2, 'EXIOBASE final demand matrix'!$K:$K) -> 0.68594751 | K4: =SUMIF('EXIOBASE final demand matrix'!$B:$B, 'KOR Data for ISIC Splits'!K$2, 'EXIOBASE final demand matrix'!$K:$K) -> 6491.9867 | L4: =SUMIF('EXIOBASE final demand matrix'!$B:$B, 'KOR Data for ISIC Splits'!L$2, 'EXIOBASE final demand matrix'!$K:$K) -> 3092.6702 | M4: =SUMIF('EXIOBASE final demand matrix'!$B:$B, 'KOR Data for ISIC Splits'!M$2, 'EXIOBASE final demand matrix'!$K:$K) -> 7003.1026
A6: Government | B6: percent | C6: =IF(ISERROR(C3/SUM($C3:$D3)),0.5,C3/SUM($C3:$D3)) -> 0.5 | D6: =IF(ISERROR(D3/SUM($C3:$D3)),0.5,D3/SUM($C3:$D3)) -> 0.5 | E6: =IF(ISERROR(E3/SUM($E3:$F3)), 0.5, E3/SUM($E3:$F3)) -> 1 | F6: =IF(ISERROR(F3/SUM($E3:$F3)), 0.5, F3/SUM($E3:$F3)) -> 0 | G6: =IF(ISERROR(G3/SUM($G3:$H3)), 0.5, G3/SUM($G3:$H3)) -> 0.5 | H6: =IF(ISERROR(H3/SUM($G3:$H3)), 0.5, H3/SUM($G3:$H3)) -> 0.5 | I6: =IF(ISERROR(I3/SUM($I3:$J3)),0.5,I3/SUM($I3:$J3)) -> 0.5 | J6: =IF(ISERROR(J3/SUM($I3:$J3)),0.5,J3/SUM($I3:$J3)) -> 0.5 | K6: =IF(ISERROR(K3/SUM($K3:$M3)),1/3,K3/SUM($K3:$M3)) -> 0 | L6: =IF(ISERROR(L3/SUM($K3:$M3)),1/3,L3/SUM($K3:$M3)) -> 0 | M6: =IF(ISERROR(M3/SUM($K3:$M3)),1/3,M3/SUM($K3:$M3)) -> 1
A7: Households | B7: percent | C7: =IF(ISERROR(C4/SUM($C4:$D4)),0.5,C4/SUM($C4:$D4)) -> 0.5 | D7: =IF(ISERROR(D4/SUM($C4:$D4)),0.5,D4/SUM($C4:$D4)) -> 0.5 | E7: =IF(ISERROR(E4/SUM($E4:$F4)), 0.5, E4/SUM($E4:$F4)) -> 0.5 | F7: =IF(ISERROR(F4/SUM($E4:$F4)), 0.5, F4/SUM($E4:$F4)) -> 0.5 | G7: =IF(ISERROR(G4/SUM($G4:$H4)), 0.5, G4/SUM($G4:$H4)) -> 0 | H7: =IF(ISERROR(H4/SUM($G4:$H4)), 0.5, H4/SUM($G4:$H4)) -> 1 | I7: =IF(ISERROR(I4/SUM($I4:$J4)),0.5,I4/SUM($I4:$J4)) -> 0 | J7: =IF(ISERROR(J4/SUM($I4:$J4)),0.5,J4/SUM($I4:$J4)) -> 1 | K7: =IF(ISERROR(K4/SUM($K4:$M4)),1/3,K4/SUM($K4:$M4)) -> 0.39137213 | L7: =IF(ISERROR(L4/SUM($K4:$M4)),1/3,L4/SUM($K4:$M4)) -> 0.18644291 | M7: =IF(ISERROR(M4/SUM($K4:$M4)),1/3,M4/SUM($K4:$M4)) -> 0.42218496
E8: Data from WIOD; units NOT M.EUR

Sheet BObIC
A1: Unit: USD | B1: ISIC 01T03 | C1: ISIC 05 | D1: ISIC 06 | E1: ISIC 07T08 | F1: ISIC 09 | G1: ISIC 10T12 | H1: ISIC 13T15 | I1: ISIC 16 | J1: ISIC 17T18 | K1: ISIC 19 | L1: ISIC 20 | M1: ISIC 21 | N1: ISIC 22 | O1: ISIC 231 | P1: ISIC 239 | Q1: ISIC 241 | R1: ISIC 242 | S1: ISIC 25 | T1: ISIC 26 | U1: ISIC 27 | V1: ISIC 28 | W1: ISIC 29 | X1: ISIC 30 | Y1: ISIC 31T33 | Z1: ISIC 351 | AA1: ISIC 352T353 | AB1: ISIC 36T39 | AC1: ISIC 41T43 | AD1: ISIC 45T47 | AE1: ISIC 49T53 | AF1: ISIC 55T56 | AG1: ISIC 58T60 | AH1: ISIC 61 | AI1: ISIC 62T63 | AJ1: ISIC 64T66 | AK1: ISIC 68 | AL1: ISIC 69T82 | AM1: ISIC 84 | AN1: ISIC 85 | AO1: ISIC 86T88 | AP1: ISIC 90T96 | AQ1: ISIC 97T98
A2: Output | B2: =INDEX(INDIRECT(CONCATENATE("'","OECD TTL - ",INDEX('[7]ISIC Crosswalk'!$I$2:$I$71,MATCH(B$1,'[7]ISIC Crosswalk'!$K$2:$K$71,0),1),"'!","$C$7:$BD$58")),MATCH("OUTPUT: Output at basic prices",INDIRECT(CONCATENATE("'","OECD TTL - ",INDEX('[7]ISIC Crosswalk'!$I$2:$I$71,MATCH(B$1,'[7]ISIC Crosswalk'!$K$2:$K$71,0),1),"'!","$A$7:$A$58")),0),MATCH(INDEX('[7]ISIC Crosswalk'!$J$2:$J$71,MATCH(B1,'[7]ISIC Crosswalk'!$K$2:$K$71,0),1),INDIRECT(CONCATENATE("'","OECD TTL - ",INDEX('[7]ISIC Crosswalk'!$I$2:$I$71,MATCH(B$1,'[7]ISIC Crosswalk'!$K$2:$K$71,0),1),"'!","$C$7:$BD$7")),0))*1000000*IF(INDEX('[7]ISIC Crosswalk'!$I$2:$I$71,MATCH(B$1,'[7]ISIC Crosswalk'!$K$2:$K$71,0),1)=2021,[7]About!$A$26,[7]About!$A$25) -> 44846032000 | C2: ='[7]OECD TTL - 2021'!E58*10^6*'[7]KOR EXIOBASE Output'!C7*[7]About!$A$26 -> 2.6230038e+08 | D2: ='[7]OECD TTL - 2021'!E58*10^6*'[7]KOR EXIOBASE Output'!D7*[7]About!$A$26 -> 1.4865562e+08 | E2: =INDEX(INDIRECT(CONCATENATE("'","OECD TTL - ",INDEX('[7]ISIC Crosswalk'!$I$2:$I$71,MATCH(E$1,'[7]ISIC Crosswalk'!$K$2:$K$71,0),1),"'!","$C$7:$BD$58")),MATCH("OUTPUT: Output at basic prices",INDIRECT(CONCATENATE("'","OECD TTL - ",INDEX('[7]ISIC Crosswalk'!$I$2:$I$71,MATCH(E$1,'[7]ISIC Crosswalk'!$K$2:$K$71,0),1),"'!","$A$7:$A$58")),0),MATCH(INDEX('[7]ISIC Crosswalk'!$J$2:$J$71,MATCH(E1,'[7]ISIC Crosswalk'!$K$2:$K$71,0),1),INDIRECT(CONCATENATE("'","OECD TTL - ",INDEX('[7]ISIC Crosswalk'!$I$2:$I$71,MATCH(E$1,'[7]ISIC Crosswalk'!$K$2:$K$71,0),1),"'!","$C$7:$BD$7")),0))*1000000*IF(INDEX('[7]ISIC Crosswalk'!$I$2:$I$71,MATCH(E$1,'[7]ISIC Crosswalk'!$K$2:$K$71,0),1)=2021,[7]About!$A$26,[7]About!$A$25) -> 3305939000 | F2: =INDEX(INDIRECT(CONCATENATE("'","OECD TTL - ",INDEX('[7]ISIC Crosswalk'!$I$2:$I$71,MATCH(F$1,'[7]ISIC Crosswalk'!$K$2:$K$71,0),1),"'!","$C$7:$BD$58")),MATCH("OUTPUT: Output at basic prices",INDIRECT(CONCATENATE("'","OECD TTL - ",INDEX('[7]ISIC Crosswalk'!$I$2:$I$71,MATCH(F$1,'[7]ISIC Crosswalk'!$K$2:$K$71,0),1),"'!","$A$7:$A$58")),0),MATCH(INDEX('[7]ISIC Crosswalk'!$J$2:$J$71,MATCH(F1,'[7]ISIC Crosswalk'!$K$2:$K$71,0),1),INDIRECT(CONCATENATE("'","OECD TTL - ",INDEX('[7]ISIC Crosswalk'!$I$2:$I$71,MATCH(F$1,'[7]ISIC Crosswalk'!$K$2:$K$71,0),1),"'!","$C$7:$BD$7")),0))*1000000*IF(INDEX('[7]ISIC Crosswalk'!$I$2:$I$71,MATCH(F$1,'[7]ISIC Crosswalk'!$K$2:$K$71,0),1)=2021,[7]About!$A$26,[7]About!$A$25) -> 20020000 | G2: =INDEX(INDIRECT(CONCATENATE("'","OECD TTL - ",INDEX('[7]ISIC Crosswalk'!$I$2:$I$71,MATCH(G$1,'[7]ISIC Crosswalk'!$K$2:$K$71,0),1),"'!","$C$7:$BD$58")),MATCH("OUTPUT: Output at basic prices",INDIRECT(CONCATENATE("'","OECD TTL - ",INDEX('[7]ISIC Crosswalk'!$I$2:$I$71,MATCH(G$1,'[7]ISIC Crosswalk'!$K$2:$K$71,0),1),"'!","$A$7:$A$58")),0),MATCH(INDEX('[7]ISIC Crosswalk'!$J$2:$J$71,MATCH(G1,'[7]ISIC Crosswalk'!$K$2:$K$71,0),1),INDIRECT(CONCATENATE("'","OECD TTL - ",INDEX('[7]ISIC Crosswalk'!$I$2:$I$71,MATCH(G$1,'[7]ISIC Crosswalk'!$K$2:$K$71,0),1),"'!","$C$7:$BD$7")),0))*1000000*IF(INDEX('[7]ISIC Crosswalk'!$I$2:$I$71,MATCH(G$1,'[7]ISIC Crosswalk'!$K$2:$K$71,0),1)=2021,[7]About!$A$26,[7]About!$A$25) -> 102938654000 | H2: =INDEX(INDIRECT(CONCATENATE("'","OECD TTL - ",INDEX('[7]ISIC Crosswalk'!$I$2:$I$71,MATCH(H$1,'[7]ISIC Crosswalk'!$K$2:$K$71,0),1),"'!","$C$7:$BD$58")),MATCH("OUTPUT: Output at basic prices",INDIRECT(CONCATENATE("'","OECD TTL - ",INDEX('[7]ISIC Crosswalk'!$I$2:$I$71,MATCH(H$1,'[7]ISIC Crosswalk'!$K$2:$K$71,0),1),"'!","$A$7:$A$58")),0),MATCH(INDEX('[7]ISIC Crosswalk'!$J$2:$J$71,MATCH(H1,'[7]ISIC Crosswalk'!$K$2:$K$71,0),1),INDIRECT(CONCATENATE("'","OECD TTL - ",INDEX('[7]ISIC Crosswalk'!$I$2:$I$71,MATCH(H$1,'[7]ISIC Crosswalk'!$K$2:$K$71,0),1),"'!","$C$7:$BD$7")),0))*1000000*IF(INDEX('[7]ISIC Crosswalk'!$I$2:$I$71,MATCH(H$1,'[7]ISIC Crosswalk'!$K$2:$K$71,0),1)=2021,[7]About!$A$26,[7]About!$A$25) -> 64002939000 | I2: =INDEX(INDIRECT(CONCATENATE("'","OECD TTL - ",INDEX('[7]ISIC Crosswalk'!$I$2:$I$71,MATCH(I$1,'[7]ISIC Crosswalk'!$K$2:$K$71,0),1),"'!","$C$7:$BD$58")),MATCH("OUTPUT: Output at basic prices",INDIRECT(CONCATENATE("'","OECD TTL - ",INDEX('[7]ISIC Crosswalk'!$I$2:$I$71,MATCH(I$1,'[7]ISIC Crosswalk'!$K$2:$K$71,0),1),"'!","$A$7:$A$58")),0),MATCH(INDEX('[7]ISIC Crosswalk'!$J$2:$J$71,MATCH(I1,'[7]ISIC Crosswalk'!$K$2:$K$71,0),1),INDIRECT(CONCATENATE("'","OECD TTL - ",INDEX('[7]ISIC Crosswalk'!$I$2:$I$71,MATCH(I$1,'[7]ISIC Crosswalk'!$K$2:$K$71,0),1),"'!","$C$7:$BD$7")),0))*1000000*IF(INDEX('[7]ISIC Crosswalk'!$I$2:$I$71,MATCH(I$1,'[7]ISIC Crosswalk'!$K$2:$K$71,0),1)=2021,[7]About!$A$26,[7]About!$A$25) -> 7215390000 | J2: =INDEX(INDIRECT(CONCATENATE("'","OECD TTL - ",INDEX('[7]ISIC Crosswalk'!$I$2:$I$71,MATCH(J$1,'[7]ISIC Crosswalk'!$K$2:$K$71,0),1),"'!","$C$7:$BD$58")),MATCH("OUTPUT: Output at basic prices",INDIRECT(CONCATENATE("'","OECD TTL - ",INDEX('[7]ISIC Crosswalk'!$I$2:$I$71,MATCH(J$1,'[7]ISIC Crosswalk'!$K$2:$K$71,0),1),"'!","$A$7:$A$58")),0),MATCH(INDEX('[7]ISIC Crosswalk'!$J$2:$J$71,MATCH(J1,'[7]ISIC Crosswalk'!$K$2:$K$71,0),1),INDIRECT(CONCATENATE("'","OECD TTL - ",INDEX('[7]ISIC Crosswalk'!$I$2:$I$71,MATCH(J$1,'[7]ISIC Crosswalk'!$K$2:$K$71,0),1),"'!","$C$7:$BD$7")),0))*1000000*IF(INDEX('[7]ISIC Crosswalk'!$I$2:$I$71,MATCH(J$1,'[7]ISIC Crosswalk'!$K$2:$K$71,0),1)=2021,[7]About!$A$26,[7]About!$A$25) -> 32329297000 | K2: =INDEX(INDIRECT(CONCATENATE("'","OECD TTL - ",INDEX('[7]ISIC Crosswalk'!$I$2:$I$71,MATCH(K$1,'[7]ISIC Crosswalk'!$K$2:$K$71,0),1),"'!","$C$7:$BD$58")),MATCH("OUTPUT: Output at basic prices",INDIRECT(CONCATENATE("'","OECD TTL - ",INDEX('[7]ISIC Crosswalk'!$I$2:$I$71,MATCH(K$1,'[7]ISIC Crosswalk'!$K$2:$K$71,0),1),"'!","$A$7:$A$58")),0),MATCH(INDEX('[7]ISIC Crosswalk'!$J$2:$J$71,MATCH(K1,'[7]ISIC Crosswalk'!$K$2:$K$71,0),1),INDIRECT(CONCATENATE("'","OECD TTL - ",INDEX('[7]ISIC Crosswalk'!$I$2:$I$71,MATCH(K$1,'[7]ISIC Crosswalk'!$K$2:$K$71,0),1),"'!","$C$7:$BD$7")),0))*1000000*IF(INDEX('[7]ISIC Crosswalk'!$I$2:$I$71,MATCH(K$1,'[7]ISIC Crosswalk'!$K$2:$K$71,0),1)=2021,[7]About!$A$26,[7]About!$A$25) -> 111021001000 | L2: =INDEX(INDIRECT(CONCATENATE("'","OECD TTL - ",INDEX('[7]ISIC Crosswalk'!$I$2:$I$71,MATCH(L$1,'[7]ISIC Crosswalk'!$K$2:$K$71,0),1),"'!","$C$7:$BD$58")),MATCH("OUTPUT: Output at basic prices",INDIRECT(CONCATENATE("'","OECD TTL - ",INDEX('[7]ISIC Crosswalk'!$I$2:$I$71,MATCH(L$1,'[7]ISIC Crosswalk'!$K$2:$K$71,0),1),"'!","$A$7:$A$58")),0),MATCH(INDEX('[7]ISIC Crosswalk'!$J$2:$J$71,MATCH(L1,'[7]ISIC Crosswalk'!$K$2:$K$71,0),1),INDIRECT(CONCATENATE("'","OECD TTL - ",INDEX('[7]ISIC Crosswalk'!$I$2:$I$71,MATCH(L$1,'[7]ISIC Crosswalk'!$K$2:$K$71,0),1),"'!","$C$7:$BD$7")),0))*1000000*IF(INDEX('[7]ISIC Crosswalk'!$I$2:$I$71,MATCH(L$1,'[7]ISIC Crosswalk'!$K$2:$K$71,0),1)=2021,[7]About!$A$26,[7]About!$A$25) -> 142563876000 | ... N2: =INDEX(INDIRECT(CONCATENATE("'","OECD TTL - ",INDEX('[7]ISIC Crosswalk'!$I$2:$I$71,MATCH(N$1,'[7]ISIC Crosswalk'!$K$2:$K$71,0),1),"'!","$C$7:$BD$58")),MATCH("OUTPUT: Output at basic prices",INDIRECT(CONCATENATE("'","OECD TTL - ",INDEX('[7]ISIC Crosswalk'!$I$2:$I$71,MATCH(N$1,'[7]ISIC Crosswalk'!$K$2:$K$71,0),1),"'!","$A$7:$A$58")),0),MATCH(INDEX('[7]ISIC Crosswalk'!$J$2:$J$71,MATCH(N1,'[7]ISIC Crosswalk'!$K$2:$K$71,0),1),INDIRECT(CONCATENATE("'","OECD TTL - ",INDEX('[7]ISIC Crosswalk'!$I$2:$I$71,MATCH(N$1,'[7]ISIC Crosswalk'!$K$2:$K$71,0),1),"'!","$C$7:$BD$7")),0))*1000000*IF(INDEX('[7]ISIC Crosswalk'!$I$2:$I$71,MATCH(N$1,'[7]ISIC Crosswalk'!$K$2:$K$71,0),1)=2021,[7]About!$A$26,[7]About!$A$25) -> 59839560000 | O2: ='[7]OECD TTL - 2021'!P58*10^6*'[7]KOR EXIOBASE Output'!E7*[7]About!$A$26 -> 1.1808344e+10 | P2: ='[7]OECD TTL - 2021'!P58*10^6*'[7]KOR EXIOBASE Output'!F7*[7]About!$A$26 -> 2.446553e+10 | Q2: ='[7]OECD TTL - 2021'!Q58*10^6*'[7]KOR EXIOBASE Output'!G7*[7]About!$A$26 -> 9.8234755e+10 | R2: ='[7]OECD TTL - 2021'!Q58*10^6*'[7]KOR EXIOBASE Output'!H7*[7]About!$A$26 -> 2.6809983e+10 | S2: =INDEX(INDIRECT(CONCATENATE("'","OECD TTL - ",INDEX('[7]ISIC Crosswalk'!$I$2:$I$71,MATCH(S$1,'[7]ISIC Crosswalk'!$K$2:$K$71,0),1),"'!","$C$7:$BD$58")),MATCH("OUTPUT: Output at basic prices",INDIRECT(CONCATENATE("'","OECD TTL - ",INDEX('[7]ISIC Crosswalk'!$I$2:$I$71,MATCH(S$1,'[7]ISIC Crosswalk'!$K$2:$K$71,0),1),"'!","$A$7:$A$58")),0),MATCH(INDEX('[7]ISIC Crosswalk'!$J$2:$J$71,MATCH(S1,'[7]ISIC Crosswalk'!$K$2:$K$71,0),1),INDIRECT(CONCATENATE("'","OECD TTL - ",INDEX('[7]ISIC Crosswalk'!$I$2:$I$71,MATCH(S$1,'[7]ISIC Crosswalk'!$K$2:$K$71,0),1),"'!","$C$7:$BD$7")),0))*1000000*IF(INDEX('[7]ISIC Crosswalk'!$I$2:$I$71,MATCH(S$1,'[7]ISIC Crosswalk'!$K$2:$K$71,0),1)=2021,[7]About!$A$26,[7]About!$A$25) -> 84072352000 | T2: =INDEX(INDIRECT(CONCATENATE("'","OECD TTL - ",INDEX('[7]ISIC Crosswalk'!$I$2:$I$71,MATCH(T$1,'[7]ISIC Crosswalk'!$K$2:$K$71,0),1),"'!","$C$7:$BD$58")),MATCH("OUTPUT: Output at basic prices",INDIRECT(CONCATENATE("'","OECD TTL - ",INDEX('[7]ISIC Crosswalk'!$I$2:$I$71,MATCH(T$1,'[7]ISIC Crosswalk'!$K$2:$K$71,0),1),"'!","$A$7:$A$58")),0),MATCH(INDEX('[7]ISIC Crosswalk'!$J$2:$J$71,MATCH(T1,'[7]ISIC Crosswalk'!$K$2:$K$71,0),1),INDIRECT(CONCATENATE("'","OECD TTL - ",INDEX('[7]ISIC Crosswalk'!$I$2:$I$71,MATCH(T$1,'[7]ISIC Crosswalk'!$K$2:$K$71,0),1),"'!","$C$7:$BD$7")),0))*1000000*IF(INDEX('[7]ISIC Crosswalk'!$I$2:$I$71,MATCH(T$1,'[7]ISIC Crosswalk'!$K$2:$K$71,0),1)=2021,[7]About!$A$26,[7]About!$A$25) -> 286853112000 | U2: =INDEX(INDIRECT(CONCATENATE("'","OECD TTL - ",INDEX('[7]ISIC Crosswalk'!$I$2:$I$71,MATCH(U$1,'[7]ISIC Crosswalk'!$K$2:$K$71,0),1),"'!","$C$7:$BD$58")),MATCH("OUTPUT: Output at basic prices",INDIRECT(CONCATENATE("'","OECD TTL - ",INDEX('[7]ISIC Crosswalk'!$I$2:$I$71,MATCH(U$1,'[7]ISIC Crosswalk'!$K$2:$K$71,0),1),"'!","$A$7:$A$58")),0),MATCH(INDEX('[7]ISIC Crosswalk'!$J$2:$J$71,MATCH(U1,'[7]ISIC Crosswalk'!$K$2:$K$71,0),1),INDIRECT(CONCATENATE("'","OECD TTL - ",INDEX('[7]ISIC Crosswalk'!$I$2:$I$71,MATCH(U$1,'[7]ISIC Crosswalk'!$K$2:$K$71,0),1),"'!","$C$7:$BD$7")),0))*1000000*IF(INDEX('[7]ISIC Crosswalk'!$I$2:$I$71,MATCH(U$1,'[7]ISIC Crosswalk'!$K$2:$K$71,0),1)=2021,[7]About!$A$26,[7]About!$A$25) -> 81964883000 | V2: =INDEX(INDIRECT(CONCATENATE("'","OECD TTL - ",INDEX('[7]ISIC Crosswalk'!$I$2:$I$71,MATCH(V$1,'[7]ISIC Crosswalk'!$K$2:$K$71,0),1),"'!","$C$7:$BD$58")),MATCH("OUTPUT: Output at basic prices",INDIRECT(CONCATENATE("'","OECD TTL - ",INDEX('[7]ISIC Crosswalk'!$I$2:$I$71,MATCH(V$1,'[7]ISIC Crosswalk'!$K$2:$K$71,0),1),"'!","$A$7:$A$58")),0),MATCH(INDEX('[7]ISIC Crosswalk'!$J$2:$J$71,MATCH(V1,'[7]ISIC Crosswalk'!$K$2:$K$71,0),1),INDIRECT(CONCATENATE("'","OECD TTL - ",INDEX('[7]ISIC Crosswalk'!$I$2:$I$71,MATCH(V$1,'[7]ISIC Crosswalk'!$K$2:$K$71,0),1),"'!","$C$7:$BD$7")),0))*1000000*IF(INDEX('[7]ISIC Crosswalk'!$I$2:$I$71,MATCH(V$1,'[7]ISIC Crosswalk'!$K$2:$K$71,0),1)=2021,[7]About!$A$26,[7]About!$A$25) -> 1.220371e+11 | W2: =INDEX(INDIRECT(CONCATENATE("'","OECD TTL - ",INDEX('[7]ISIC Crosswalk'!$I$2:$I$71,MATCH(W$1,'[7]ISIC Crosswalk'!$K$2:$K$71,0),1),"'!","$C$7:$BD$58")),MATCH("OUTPUT: Output at basic prices",INDIRECT(CONCATENATE("'","OECD TTL - ",INDEX('[7]ISIC Crosswalk'!$I$2:$I$71,MATCH(W$1,'[7]ISIC Crosswalk'!$K$2:$K$71,0),1),"'!","$A$7:$A$58")),0),MATCH(INDEX('[7]ISIC Crosswalk'!$J$2:$J$71,MATCH(W1,'[7]ISIC Crosswalk'!$K$2:$K$71,0),1),INDIRECT(CONCATENATE("'","OECD TTL - ",INDEX('[7]ISIC Crosswalk'!$I$2:$I$71,MATCH(W$1,'[7]ISIC Crosswalk'!$K$2:$K$71,0),1),"'!","$C$7:$BD$7")),0))*1000000*IF(INDEX('[7]ISIC Crosswalk'!$I$2:$I$71,MATCH(W$1,'[7]ISIC Crosswalk'!$K$2:$K$71,0),1)=2021,[7]About!$A$26,[7]About!$A$25) -> 163254000000 | X2: =INDEX(INDIRECT(CONCATENATE("'","OECD TTL - ",INDEX('[7]ISIC Crosswalk'!$I$2:$I$71,MATCH(X$1,'[7]ISIC Crosswalk'!$K$2:$K$71,0),1),"'!","$C$7:$BD$58")),MATCH("OUTPUT: Output at basic prices",INDIRECT(CONCATENATE("'","OECD TTL - ",INDEX('[7]ISIC Crosswalk'!$I$2:$I$71,MATCH(X$1,'[7]ISIC Crosswalk'!$K$2:$K$71,0),1),"'!","$A$7:$A$58")),0),MATCH(INDEX('[7]ISIC Crosswalk'!$J$2:$J$71,MATCH(X1,'[7]ISIC Crosswalk'!$K$2:$K$71,0),1),INDIRECT(CONCATENATE("'","OECD TTL - ",INDEX('[7]ISIC Crosswalk'!$I$2:$I$71,MATCH(X$1,'[7]ISIC Crosswalk'!$K$2:$K$71,0),1),"'!","$C$7:$BD$7")),0))*1000000*IF(INDEX('[7]ISIC Crosswalk'!$I$2:$I$71,MATCH(X$1,'[7]ISIC Crosswalk'!$K$2:$K$71,0),1)=2021,[7]About!$A$26,[7]About!$A$25) -> 38348583000 | Y2: =INDEX(INDIRECT(CONCATENATE("'","OECD TTL - ",INDEX('[7]ISIC Crosswalk'!$I$2:$I$71,MATCH(Y$1,'[7]ISIC Crosswalk'!$K$2:$K$71,0),1),"'!","$C$7:$BD$58")),MATCH("OUTPUT: Output at basic prices",INDIRECT(CONCATENATE("'","OECD TTL - ",INDEX('[7]ISIC Crosswalk'!$I$2:$I$71,MATCH(Y$1,'[7]ISIC Crosswalk'!$K$2:$K$71,0),1),"'!","$A$7:$A$58")),0),MATCH(INDEX('[7]ISIC Crosswalk'!$J$2:$J$71,MATCH(Y1,'[7]ISIC Crosswalk'!$K$2:$K$71,0),1),INDIRECT(CONCATENATE("'","OECD TTL - ",INDEX('[7]ISIC Crosswalk'!$I$2:$I$71,MATCH(Y$1,'[7]ISIC Crosswalk'!$K$2:$K$71,0),1),"'!","$C$7:$BD$7")),0))*1000000*IF(INDEX('[7]ISIC Crosswalk'!$I$2:$I$71,MATCH(Y$1,'[7]ISIC Crosswalk'!$K$2:$K$71,0),1)=2021,[7]About!$A$26,[7]About!$A$25) -> 29198533000 | Z2: ='[7]OECD TTL - 2021'!Y58*10^6*'[7]KOR EXIOBASE Output'!I7*[7]About!$A$26 -> 3.6868341e+10 | AA2: ='[7]OECD TTL - 2021'!Y58*10^6*'[7]KOR EXIOBASE Output'!J7*[7]About!$A$26 -> 1.2129536e+10 | AB2: =INDEX(INDIRECT(CONCATENATE("'","OECD TTL - ",INDEX('[7]ISIC Crosswalk'!$I$2:$I$71,MATCH(AB$1,'[7]ISIC Crosswalk'!$K$2:$K$71,0),1),"'!","$C$7:$BD$58")),MATCH("OUTPUT: Output at basic prices",INDIRECT(CONCATENATE("'","OECD TTL - ",INDEX('[7]ISIC Crosswalk'!$I$2:$I$71,MATCH(AB$1,'[7]ISIC Crosswalk'!$K$2:$K$71,0),1),"'!","$A$7:$A$58")),0),MATCH(INDEX('[7]ISIC Crosswalk'!$J$2:$J$71,MATCH(AB1,'[7]ISIC Crosswalk'!$K$2:$K$71,0),1),INDIRECT(CONCATENATE("'","OECD TTL - ",INDEX('[7]ISIC Crosswalk'!$I$2:$I$71,MATCH(AB$1,'[7]ISIC Crosswalk'!$K$2:$K$71,0),1),"'!","$C$7:$BD$7")),0))*1000000*IF(INDEX('[7]ISIC Crosswalk'!$I$2:$I$71,MATCH(AB$1,'[7]ISIC Crosswalk'!$K$2:$K$71,0),1)=2021,[7]About!$A$26,[7]About!$A$25) -> 17124926000 | AC2: =INDEX(INDIRECT(CONCATENATE("'","OECD TTL - ",INDEX('[7]ISIC Crosswalk'!$I$2:$I$71,MATCH(AC$1,'[7]ISIC Crosswalk'!$K$2:$K$71,0),1),"'!","$C$7:$BD$58")),MATCH("OUTPUT: Output at basic prices",INDIRECT(CONCATENATE("'","OECD TTL - ",INDEX('[7]ISIC Crosswalk'!$I$2:$I$71,MATCH(AC$1,'[7]ISIC Crosswalk'!$K$2:$K$71,0),1),"'!","$A$7:$A$58")),0),MATCH(INDEX('[7]ISIC Crosswalk'!$J$2:$J$71,MATCH(AC1,'[7]ISIC Crosswalk'!$K$2:$K$71,0),1),INDIRECT(CONCATENATE("'","OECD TTL - ",INDEX('[7]ISIC Crosswalk'!$I$2:$I$71,MATCH(AC$1,'[7]ISIC Crosswalk'!$K$2:$K$71,0),1),"'!","$C$7:$BD$7")),0))*1000000*IF(INDEX('[7]ISIC Crosswalk'!$I$2:$I$71,MATCH(AC$1,'[7]ISIC Crosswalk'!$K$2:$K$71,0),1)=2021,[7]About!$A$26,[7]About!$A$25) -> 213075681000 | AD2: =INDEX(INDIRECT(CONCATENATE("'","OECD TTL - ",INDEX('[7]ISIC Crosswalk'!$I$2:$I$71,MATCH(AD$1,'[7]ISIC Crosswalk'!$K$2:$K$71,0),1),"'!","$C$7:$BD$58")),MATCH("OUTPUT: Output at basic prices",INDIRECT(CONCATENATE("'","OECD TTL - ",INDEX('[7]ISIC Crosswalk'!$I$2:$I$71,MATCH(AD$1,'[7]ISIC Crosswalk'!$K$2:$K$71,0),1),"'!","$A$7:$A$58")),0),MATCH(INDEX('[7]ISIC Crosswalk'!$J$2:$J$71,MATCH(AD1,'[7]ISIC Crosswalk'!$K$2:$K$71,0),1),INDIRECT(CONCATENATE("'","OECD TTL - ",INDEX('[7]ISIC Crosswalk'!$I$2:$I$71,MATCH(AD$1,'[7]ISIC Crosswalk'!$K$2:$K$71,0),1),"'!","$C$7:$BD$7")),0))*1000000*IF(INDEX('[7]ISIC Crosswalk'!$I$2:$I$71,MATCH(AD$1,'[7]ISIC Crosswalk'!$K$2:$K$71,0),1)=2021,[7]About!$A$26,[7]About!$A$25) -> 219045008000 | AE2: =INDEX(INDIRECT(CONCATENATE("'","OECD TTL - ",INDEX('[7]ISIC Crosswalk'!$I$2:$I$71,MATCH(AE$1,'[7]ISIC Crosswalk'!$K$2:$K$71,0),1),"'!","$C$7:$BD$58")),MATCH("OUTPUT: Output at basic prices",INDIRECT(CONCATENATE("'","OECD TTL - ",INDEX('[7]ISIC Crosswalk'!$I$2:$I$71,MATCH(AE$1,'[7]ISIC Crosswalk'!$K$2:$K$71,0),1),"'!","$A$7:$A$58")),0),MATCH(INDEX('[7]ISIC Crosswalk'!$J$2:$J$71,MATCH(AE1,'[7]ISIC Crosswalk'!$K$2:$K$71,0),1),INDIRECT(CONCATENATE("'","OECD TTL - ",INDEX('[7]ISIC Crosswalk'!$I$2:$I$71,MATCH(AE$1,'[7]ISIC Crosswalk'!$K$2:$K$71,0),1),"'!","$C$7:$BD$7")),0))*1000000*IF(INDEX('[7]ISIC Crosswalk'!$I$2:$I$71,MATCH(AE$1,'[7]ISIC Crosswalk'!$K$2:$K$71,0),1)=2021,[7]About!$A$26,[7]About!$A$25) -> 106890256000 | AF2: =INDEX(INDIRECT(CONCATENATE("'","OECD TTL - ",INDEX('[7]ISIC Crosswalk'!$I$2:$I$71,MATCH(AF$1,'[7]ISIC Crosswalk'!$K$2:$K$71,0),1),"'!","$C$7:$BD$58")),MATCH("OUTPUT: Output at basic prices",INDIRECT(CONCATENATE("'","OECD TTL - ",INDEX('[7]ISIC Crosswalk'!$I$2:$I$71,MATCH(AF$1,'[7]ISIC Crosswalk'!$K$2:$K$71,0),1),"'!","$A$7:$A$58")),0),MATCH(INDEX('[7]ISIC Crosswalk'!$J$2:$J$71,MATCH(AF1,'[7]ISIC Crosswalk'!$K$2:$K$71,0),1),INDIRECT(CONCATENATE("'","OECD TTL - ",INDEX('[7]ISIC Crosswalk'!$I$2:$I$71,MATCH(AF$1,'[7]ISIC Crosswalk'!$K$2:$K$71,0),1),"'!","$C$7:$BD$7")),0))*1000000*IF(INDEX('[7]ISIC Crosswalk'!$I$2:$I$71,MATCH(AF$1,'[7]ISIC Crosswalk'!$K$2:$K$71,0),1)=2021,[7]About!$A$26,[7]About!$A$25) -> 121327024000 | AG2: =INDEX(INDIRECT(CONCATENATE("'","OECD TTL - ",INDEX('[7]ISIC Crosswalk'!$I$2:$I$71,MATCH(AG$1,'[7]ISIC Crosswalk'!$K$2:$K$71,0),1),"'!","$C$7:$BD$58")),MATCH("OUTPUT: Output at basic prices",INDIRECT(CONCATENATE("'","OECD TTL - ",INDEX('[7]ISIC Crosswalk'!$I$2:$I$71,MATCH(AG$1,'[7]ISIC Crosswalk'!$K$2:$K$71,0),1),"'!","$A$7:$A$58")),0),MATCH(INDEX('[7]ISIC Crosswalk'!$J$2:$J$71,MATCH(AG1,'[7]ISIC Crosswalk'!$K$2:$K$71,0),1),INDIRECT(CONCATENATE("'","OECD TTL - ",INDEX('[7]ISIC Crosswalk'!$I$2:$I$71,MATCH(AG$1,'[7]ISIC Crosswalk'!$K$2:$K$71,0),1),"'!","$C$7:$BD$7")),0))*1000000*IF(INDEX('[7]ISIC Crosswalk'!$I$2:$I$71,MATCH(AG$1,'[7]ISIC Crosswalk'!$K$2:$K$71,0),1)=2021,[7]About!$A$26,[7]About!$A$25) -> 46107880000 | AH2: =INDEX(INDIRECT(CONCATENATE("'","OECD TTL - ",INDEX('[7]ISIC Crosswalk'!$I$2:$I$71,MATCH(AH$1,'[7]ISIC Crosswalk'!$K$2:$K$71,0),1),"'!","$C$7:$BD$58")),MATCH("OUTPUT: Output at basic prices",INDIRECT(CONCATENATE("'","OECD TTL - ",INDEX('[7]ISIC Crosswalk'!$I$2:$I$71,MATCH(AH$1,'[7]ISIC Crosswalk'!$K$2:$K$71,0),1),"'!","$A$7:$A$58")),0),MATCH(INDEX('[7]ISIC Crosswalk'!$J$2:$J$71,MATCH(AH1,'[7]ISIC Crosswalk'!$K$2:$K$71,0),1),INDIRECT(CONCATENATE("'","OECD TTL - ",INDEX('[7]ISIC Crosswalk'!$I$2:$I$71,MATCH(AH$1,'[7]ISIC Crosswalk'!$K$2:$K$71,0),1),"'!","$C$7:$BD$7")),0))*1000000*IF(INDEX('[7]ISIC Crosswalk'!$I$2:$I$71,MATCH(AH$1,'[7]ISIC Crosswalk'!$K$2:$K$71,0),1)=2021,[7]About!$A$26,[7]About!$A$25) -> 35588826000 | AI2: =INDEX(INDIRECT(CONCATENATE("'","OECD TTL - ",INDEX('[7]ISIC Crosswalk'!$I$2:$I$71,MATCH(AI$1,'[7]ISIC Crosswalk'!$K$2:$K$71,0),1),"'!","$C$7:$BD$58")),MATCH("OUTPUT: Output at basic prices",INDIRECT(CONCATENATE("'","OECD TTL - ",INDEX('[7]ISIC Crosswalk'!$I$2:$I$71,MATCH(AI$1,'[7]ISIC Crosswalk'!$K$2:$K$71,0),1),"'!","$A$7:$A$58")),0),MATCH(INDEX('[7]ISIC Crosswalk'!$J$2:$J$71,MATCH(AI1,'[7]ISIC Crosswalk'!$K$2:$K$71,0),1),INDIRECT(CONCATENATE("'","OECD TTL - ",INDEX('[7]ISIC Crosswalk'!$I$2:$I$71,MATCH(AI$1,'[7]ISIC Crosswalk'!$K$2:$K$71,0),1),"'!","$C$7:$BD$7")),0))*1000000*IF(INDEX('[7]ISIC Crosswalk'!$I$2:$I$71,MATCH(AI$1,'[7]ISIC Crosswalk'!$K$2:$K$71,0),1)=2021,[7]About!$A$26,[7]About!$A$25) -> 41416102000 | ... AQ2: =INDEX(INDIRECT(CONCATENATE("'","OECD TTL - ",INDEX('[7]ISIC Crosswalk'!$I$2:$I$71,MATCH(AQ$1,'[7]ISIC Crosswalk'!$K$2:$K$71,0),1),"'!","$C$7:$BD$58")),MATCH("OUTPUT: Output at basic prices",INDIRECT(CONCATENATE("'","OECD TTL - ",INDEX('[7]ISIC Crosswalk'!$I$2:$I$71,MATCH(AQ$1,'[7]ISIC Crosswalk'!$K$2:$K$71,0),1),"'!","$A$7:$A$58")),0),MATCH(INDEX('[7]ISIC Crosswalk'!$J$2:$J$71,MATCH(AQ1,'[7]ISIC Crosswalk'!$K$2:$K$71,0),1),INDIRECT(CONCATENATE("'","OECD TTL - ",INDEX('[7]ISIC Crosswalk'!$I$2:$I$71,MATCH(AQ$1,'[7]ISIC Crosswalk'!$K$2:$K$71,0),1),"'!","$C$7:$BD$7")),0))*1000000*IF(INDEX('[7]ISIC Crosswalk'!$I$2:$I$71,MATCH(AQ$1,'[7]ISIC Crosswalk'!$K$2:$K$71,0),1)=2021,[7]About!$A$26,[7]About!$A$25) -> 1831193000

Sheet GaHEbIC-government
A1: Unit: USD | B1: ISIC 01T03 | C1: ISIC 05 | D1: ISIC 06 | E1: ISIC 07T08 | F1: ISIC 09 | G1: ISIC 10T12 | H1: ISIC 13T15 | I1: ISIC 16 | J1: ISIC 17T18 | K1: ISIC 19 | L1: ISIC 20 | M1: ISIC 21 | N1: ISIC 22 | O1: ISIC 231 | P1: ISIC 239 | Q1: ISIC 241 | R1: ISIC 242 | S1: ISIC 25 | T1: ISIC 26 | U1: ISIC 27 | V1: ISIC 28 | W1: ISIC 29 | X1: ISIC 30 | Y1: ISIC 31T33 | Z1: ISIC 351 | AA1: ISIC 352T353 | AB1: ISIC 36T39 | AC1: ISIC 41T43 | AD1: ISIC 45T47 | AE1: ISIC 49T53 | AF1: ISIC 55T56 | AG1: ISIC 58T60 | AH1: ISIC 61 | AI1: ISIC 62T63 | AJ1: ISIC 64T66 | AK1: ISIC 68 | AL1: ISIC 69T82 | AM1: ISIC 84 | AN1: ISIC 85 | AO1: ISIC 86T88 | AP1: ISIC 90T96 | AQ1: ISIC 97T98
A2: Government Expenditures | B2: =INDEX(INDIRECT(CONCATENATE("'","OECD TTL - ",INDEX('ISIC Crosswalk'!$I$2:$I$71,MATCH(B$1,'ISIC Crosswalk'!$K$2:$K$71,0),1),"'!","$Ao$9:$Ax$58")),MATCH(INDEX('ISIC Crosswalk'!$J$2:$J$71,MATCH(B$1,'ISIC Crosswalk'!$K$2:$K$71,0),1),INDIRECT(CONCATENATE("'","OECD TTL - ",INDEX('ISIC Crosswalk'!$I$2:$I$71,MATCH(B$1,'ISIC Crosswalk'!$K$2:$K$71,0),1),"'!","$a$9:$a$58")),0),MATCH("GGFC: Final consumption expenditure of general government",INDIRECT(CONCATENATE("'","OECD TTL - ",INDEX('ISIC Crosswalk'!$I$2:$I$71,MATCH(B$1,'ISIC Crosswalk'!$K$2:$K$71,0),1),"'!","$Ao$7:$Ax$7")),0))*1000000*IF(INDEX('ISIC Crosswalk'!$I$2:$I$71,MATCH(B$1,'ISIC Crosswalk'!$K$2:$K$71,0),1)=2023,About!$A$34,About!$A$32) -> 7.3784475e+08 | C2: =('OECD TTL - 2023'!$AX$11*BObIC!C2/SUM(BObIC!$C$2:$D$2)*1000000)*(About!$A$34) -> 169864.51 | D2: =('OECD TTL - 2023'!$AX$11*BObIC!D2/SUM(BObIC!$C$2:$D$2)*1000000)*(About!$A$34) -> 96268.693 | E2: =INDEX(INDIRECT(CONCATENATE("'","OECD TTL - ",INDEX('ISIC Crosswalk'!$I$2:$I$71,MATCH(E$1,'ISIC Crosswalk'!$K$2:$K$71,0),1),"'!","$Ao$9:$Ax$58")),MATCH(INDEX('ISIC Crosswalk'!$J$2:$J$71,MATCH(E$1,'ISIC Crosswalk'!$K$2:$K$71,0),1),INDIRECT(CONCATENATE("'","OECD TTL - ",INDEX('ISIC Crosswalk'!$I$2:$I$71,MATCH(E$1,'ISIC Crosswalk'!$K$2:$K$71,0),1),"'!","$a$9:$a$58")),0),MATCH("GGFC: Final consumption expenditure of general government",INDIRECT(CONCATENATE("'","OECD TTL - ",INDEX('ISIC Crosswalk'!$I$2:$I$71,MATCH(E$1,'ISIC Crosswalk'!$K$2:$K$71,0),1),"'!","$Ao$7:$Ax$7")),0))*1000000*IF(INDEX('ISIC Crosswalk'!$I$2:$I$71,MATCH(E$1,'ISIC Crosswalk'!$K$2:$K$71,0),1)=2023,About!$A$34,About!$A$32) -> 266133.2 | F2: =INDEX(INDIRECT(CONCATENATE("'","OECD TTL - ",INDEX('ISIC Crosswalk'!$I$2:$I$71,MATCH(F$1,'ISIC Crosswalk'!$K$2:$K$71,0),1),"'!","$Ao$9:$Ax$58")),MATCH(INDEX('ISIC Crosswalk'!$J$2:$J$71,MATCH(F$1,'ISIC Crosswalk'!$K$2:$K$71,0),1),INDIRECT(CONCATENATE("'","OECD TTL - ",INDEX('ISIC Crosswalk'!$I$2:$I$71,MATCH(F$1,'ISIC Crosswalk'!$K$2:$K$71,0),1),"'!","$a$9:$a$58")),0),MATCH("GGFC: Final consumption expenditure of general government",INDIRECT(CONCATENATE("'","OECD TTL - ",INDEX('ISIC Crosswalk'!$I$2:$I$71,MATCH(F$1,'ISIC Crosswalk'!$K$2:$K$71,0),1),"'!","$Ao$7:$Ax$7")),0))*1000000*IF(INDEX('ISIC Crosswalk'!$I$2:$I$71,MATCH(F$1,'ISIC Crosswalk'!$K$2:$K$71,0),1)=2023,About!$A$34,About!$A$32) -> 88711.067 | G2: =INDEX(INDIRECT(CONCATENATE("'","OECD TTL - ",INDEX('ISIC Crosswalk'!$I$2:$I$71,MATCH(G$1,'ISIC Crosswalk'!$K$2:$K$71,0),1),"'!","$Ao$9:$Ax$58")),MATCH(INDEX('ISIC Crosswalk'!$J$2:$J$71,MATCH(G$1,'ISIC Crosswalk'!$K$2:$K$71,0),1),INDIRECT(CONCATENATE("'","OECD TTL - ",INDEX('ISIC Crosswalk'!$I$2:$I$71,MATCH(G$1,'ISIC Crosswalk'!$K$2:$K$71,0),1),"'!","$a$9:$a$58")),0),MATCH("GGFC: Final consumption expenditure of general government",INDIRECT(CONCATENATE("'","OECD TTL - ",INDEX('ISIC Crosswalk'!$I$2:$I$71,MATCH(G$1,'ISIC Crosswalk'!$K$2:$K$71,0),1),"'!","$Ao$7:$Ax$7")),0))*1000000*IF(INDEX('ISIC Crosswalk'!$I$2:$I$71,MATCH(G$1,'ISIC Crosswalk'!$K$2:$K$71,0),1)=2023,About!$A$34,About!$A$32) -> 9.8265249e+08 | H2: =INDEX(INDIRECT(CONCATENATE("'","OECD TTL - ",INDEX('ISIC Crosswalk'!$I$2:$I$71,MATCH(H$1,'ISIC Crosswalk'!$K$2:$K$71,0),1),"'!","$Ao$9:$Ax$58")),MATCH(INDEX('ISIC Crosswalk'!$J$2:$J$71,MATCH(H$1,'ISIC Crosswalk'!$K$2:$K$71,0),1),INDIRECT(CONCATENATE("'","OECD TTL - ",INDEX('ISIC Crosswalk'!$I$2:$I$71,MATCH(H$1,'ISIC Crosswalk'!$K$2:$K$71,0),1),"'!","$a$9:$a$58")),0),MATCH("GGFC: Final consumption expenditure of general government",INDIRECT(CONCATENATE("'","OECD TTL - ",INDEX('ISIC Crosswalk'!$I$2:$I$71,MATCH(H$1,'ISIC Crosswalk'!$K$2:$K$71,0),1),"'!","$Ao$7:$Ax$7")),0))*1000000*IF(INDEX('ISIC Crosswalk'!$I$2:$I$71,MATCH(H$1,'ISIC Crosswalk'!$K$2:$K$71,0),1)=2023,About!$A$34,About!$A$32) -> 1774221.3 | I2: =INDEX(INDIRECT(CONCATENATE("'","OECD TTL - ",INDEX('ISIC Crosswalk'!$I$2:$I$71,MATCH(I$1,'ISIC Crosswalk'!$K$2:$K$71,0),1),"'!","$Ao$9:$Ax$58")),MATCH(INDEX('ISIC Crosswalk'!$J$2:$J$71,MATCH(I$1,'ISIC Crosswalk'!$K$2:$K$71,0),1),INDIRECT(CONCATENATE("'","OECD TTL - ",INDEX('ISIC Crosswalk'!$I$2:$I$71,MATCH(I$1,'ISIC Crosswalk'!$K$2:$K$71,0),1),"'!","$a$9:$a$58")),0),MATCH("GGFC: Final consumption expenditure of general government",INDIRECT(CONCATENATE("'","OECD TTL - ",INDEX('ISIC Crosswalk'!$I$2:$I$71,MATCH(I$1,'ISIC Crosswalk'!$K$2:$K$71,0),1),"'!","$Ao$7:$Ax$7")),0))*1000000*IF(INDEX('ISIC Crosswalk'!$I$2:$I$71,MATCH(I$1,'ISIC Crosswalk'!$K$2:$K$71,0),1)=2023,About!$A$34,About!$A$32) -> 266133.2 | J2: =INDEX(INDIRECT(CONCATENATE("'","OECD TTL - ",INDEX('ISIC Crosswalk'!$I$2:$I$71,MATCH(J$1,'ISIC Crosswalk'!$K$2:$K$71,0),1),"'!","$Ao$9:$Ax$58")),MATCH(INDEX('ISIC Crosswalk'!$J$2:$J$71,MATCH(J$1,'ISIC Crosswalk'!$K$2:$K$71,0),1),INDIRECT(CONCATENATE("'","OECD TTL - ",INDEX('ISIC Crosswalk'!$I$2:$I$71,MATCH(J$1,'ISIC Crosswalk'!$K$2:$K$71,0),1),"'!","$a$9:$a$58")),0),MATCH("GGFC: Final consumption expenditure of general government",INDIRECT(CONCATENATE("'","OECD TTL - ",INDEX('ISIC Crosswalk'!$I$2:$I$71,MATCH(J$1,'ISIC Crosswalk'!$K$2:$K$71,0),1),"'!","$Ao$7:$Ax$7")),0))*1000000*IF(INDEX('ISIC Crosswalk'!$I$2:$I$71,MATCH(J$1,'ISIC Crosswalk'!$K$2:$K$71,0),1)=2023,About!$A$34,About!$A$32) -> 887110.67 | K2: =INDEX(INDIRECT(CONCATENATE("'","OECD TTL - ",INDEX('ISIC Crosswalk'!$I$2:$I$71,MATCH(K$1,'ISIC Crosswalk'!$K$2:$K$71,0),1),"'!","$Ao$9:$Ax$58")),MATCH(INDEX('ISIC Crosswalk'!$J$2:$J$71,MATCH(K$1,'ISIC Crosswalk'!$K$2:$K$71,0),1),INDIRECT(CONCATENATE("'","OECD TTL - ",INDEX('ISIC Crosswalk'!$I$2:$I$71,MATCH(K$1,'ISIC Crosswalk'!$K$2:$K$71,0),1),"'!","$a$9:$a$58")),0),MATCH("GGFC: Final consumption expenditure of general government",INDIRECT(CONCATENATE("'","OECD TTL - ",INDEX('ISIC Crosswalk'!$I$2:$I$71,MATCH(K$1,'ISIC Crosswalk'!$K$2:$K$71,0),1),"'!","$Ao$7:$Ax$7")),0))*1000000*IF(INDEX('ISIC Crosswalk'!$I$2:$I$71,MATCH(K$1,'ISIC Crosswalk'!$K$2:$K$71,0),1)=2023,About!$A$34,About!$A$32) -> 709688.54 | L2: =INDEX(INDIRECT(CONCATENATE("'","OECD TTL - ",INDEX('ISIC Crosswalk'!$I$2:$I$71,MATCH(L$1,'ISIC Crosswalk'!$K$2:$K$71,0),1),"'!","$Ao$9:$Ax$58")),MATCH(INDEX('ISIC Crosswalk'!$J$2:$J$71,MATCH(L$1,'ISIC Crosswalk'!$K$2:$K$71,0),1),INDIRECT(CONCATENATE("'","OECD TTL - ",INDEX('ISIC Crosswalk'!$I$2:$I$71,MATCH(L$1,'ISIC Crosswalk'!$K$2:$K$71,0),1),"'!","$a$9:$a$58")),0),MATCH("GGFC: Final consumption expenditure of general government",INDIRECT(CONCATENATE("'","OECD TTL - ",INDEX('ISIC Crosswalk'!$I$2:$I$71,MATCH(L$1,'ISIC Crosswalk'!$K$2:$K$71,0),1),"'!","$Ao$7:$Ax$7")),0))*1000000*IF(INDEX('ISIC Crosswalk'!$I$2:$I$71,MATCH(L$1,'ISIC Crosswalk'!$K$2:$K$71,0),1)=2023,About!$A$34,About!$A$32) -> 17564791 | ... N2: =INDEX(INDIRECT(CONCATENATE("'","OECD TTL - ",INDEX('ISIC Crosswalk'!$I$2:$I$71,MATCH(N$1,'ISIC Crosswalk'!$K$2:$K$71,0),1),"'!","$Ao$9:$Ax$58")),MATCH(INDEX('ISIC Crosswalk'!$J$2:$J$71,MATCH(N$1,'ISIC Crosswalk'!$K$2:$K$71,0),1),INDIRECT(CONCATENATE("'","OECD TTL - ",INDEX('ISIC Crosswalk'!$I$2:$I$71,MATCH(N$1,'ISIC Crosswalk'!$K$2:$K$71,0),1),"'!","$a$9:$a$58")),0),MATCH("GGFC: Final consumption expenditure of general government",INDIRECT(CONCATENATE("'","OECD TTL - ",INDEX('ISIC Crosswalk'!$I$2:$I$71,MATCH(N$1,'ISIC Crosswalk'!$K$2:$K$71,0),1),"'!","$Ao$7:$Ax$7")),0))*1000000*IF(INDEX('ISIC Crosswalk'!$I$2:$I$71,MATCH(N$1,'ISIC Crosswalk'!$K$2:$K$71,0),1)=2023,About!$A$34,About!$A$32) -> 2306487.7 | O2: =('OECD TTL - 2023'!$AX22*BObIC!O2/SUM(BObIC!$O$2:$P$2)*1000000)*(About!$A$34) -> 490932.48 | P2: =('OECD TTL - 2023'!$AX22*BObIC!P2/SUM(BObIC!$O$2:$P$2)*1000000)*(About!$A$34) -> 1017155.7 | Q2: =('OECD TTL - 2023'!$AX23*BObIC!Q2/SUM(BObIC!$Q$2:$R$2)*1000000)*(About!$A$34) -> 766602.5 | R2: =('OECD TTL - 2023'!$AX23*BObIC!R2/SUM(BObIC!$Q$2:$R$2)*1000000)*(About!$A$34) -> 209219.23 | S2: =INDEX(INDIRECT(CONCATENATE("'","OECD TTL - ",INDEX('ISIC Crosswalk'!$I$2:$I$71,MATCH(S$1,'ISIC Crosswalk'!$K$2:$K$71,0),1),"'!","$Ao$9:$Ax$58")),MATCH(INDEX('ISIC Crosswalk'!$J$2:$J$71,MATCH(S$1,'ISIC Crosswalk'!$K$2:$K$71,0),1),INDIRECT(CONCATENATE("'","OECD TTL - ",INDEX('ISIC Crosswalk'!$I$2:$I$71,MATCH(S$1,'ISIC Crosswalk'!$K$2:$K$71,0),1),"'!","$a$9:$a$58")),0),MATCH("GGFC: Final consumption expenditure of general government",INDIRECT(CONCATENATE("'","OECD TTL - ",INDEX('ISIC Crosswalk'!$I$2:$I$71,MATCH(S$1,'ISIC Crosswalk'!$K$2:$K$71,0),1),"'!","$Ao$7:$Ax$7")),0))*1000000*IF(INDEX('ISIC Crosswalk'!$I$2:$I$71,MATCH(S$1,'ISIC Crosswalk'!$K$2:$K$71,0),1)=2023,About!$A$34,About!$A$32) -> 2750043.1 | T2: =INDEX(INDIRECT(CONCATENATE("'","OECD TTL - ",INDEX('ISIC Crosswalk'!$I$2:$I$71,MATCH(T$1,'ISIC Crosswalk'!$K$2:$K$71,0),1),"'!","$Ao$9:$Ax$58")),MATCH(INDEX('ISIC Crosswalk'!$J$2:$J$71,MATCH(T$1,'ISIC Crosswalk'!$K$2:$K$71,0),1),INDIRECT(CONCATENATE("'","OECD TTL - ",INDEX('ISIC Crosswalk'!$I$2:$I$71,MATCH(T$1,'ISIC Crosswalk'!$K$2:$K$71,0),1),"'!","$a$9:$a$58")),0),MATCH("GGFC: Final consumption expenditure of general government",INDIRECT(CONCATENATE("'","OECD TTL - ",INDEX('ISIC Crosswalk'!$I$2:$I$71,MATCH(T$1,'ISIC Crosswalk'!$K$2:$K$71,0),1),"'!","$Ao$7:$Ax$7")),0))*1000000*IF(INDEX('ISIC Crosswalk'!$I$2:$I$71,MATCH(T$1,'ISIC Crosswalk'!$K$2:$K$71,0),1)=2023,About!$A$34,About!$A$32) -> 29274652 | U2: =INDEX(INDIRECT(CONCATENATE("'","OECD TTL - ",INDEX('ISIC Crosswalk'!$I$2:$I$71,MATCH(U$1,'ISIC Crosswalk'!$K$2:$K$71,0),1),"'!","$Ao$9:$Ax$58")),MATCH(INDEX('ISIC Crosswalk'!$J$2:$J$71,MATCH(U$1,'ISIC Crosswalk'!$K$2:$K$71,0),1),INDIRECT(CONCATENATE("'","OECD TTL - ",INDEX('ISIC Crosswalk'!$I$2:$I$71,MATCH(U$1,'ISIC Crosswalk'!$K$2:$K$71,0),1),"'!","$a$9:$a$58")),0),MATCH("GGFC: Final consumption expenditure of general government",INDIRECT(CONCATENATE("'","OECD TTL - ",INDEX('ISIC Crosswalk'!$I$2:$I$71,MATCH(U$1,'ISIC Crosswalk'!$K$2:$K$71,0),1),"'!","$Ao$7:$Ax$7")),0))*1000000*IF(INDEX('ISIC Crosswalk'!$I$2:$I$71,MATCH(U$1,'ISIC Crosswalk'!$K$2:$K$71,0),1)=2023,About!$A$34,About!$A$32) -> 2572620.9 | V2: =INDEX(INDIRECT(CONCATENATE("'","OECD TTL - ",INDEX('ISIC Crosswalk'!$I$2:$I$71,MATCH(V$1,'ISIC Crosswalk'!$K$2:$K$71,0),1),"'!","$Ao$9:$Ax$58")),MATCH(INDEX('ISIC Crosswalk'!$J$2:$J$71,MATCH(V$1,'ISIC Crosswalk'!$K$2:$K$71,0),1),INDIRECT(CONCATENATE("'","OECD TTL - ",INDEX('ISIC Crosswalk'!$I$2:$I$71,MATCH(V$1,'ISIC Crosswalk'!$K$2:$K$71,0),1),"'!","$a$9:$a$58")),0),MATCH("GGFC: Final consumption expenditure of general government",INDIRECT(CONCATENATE("'","OECD TTL - ",INDEX('ISIC Crosswalk'!$I$2:$I$71,MATCH(V$1,'ISIC Crosswalk'!$K$2:$K$71,0),1),"'!","$Ao$7:$Ax$7")),0))*1000000*IF(INDEX('ISIC Crosswalk'!$I$2:$I$71,MATCH(V$1,'ISIC Crosswalk'!$K$2:$K$71,0),1)=2023,About!$A$34,About!$A$32) -> 5588797.2 | W2: =INDEX(INDIRECT(CONCATENATE("'","OECD TTL - ",INDEX('ISIC Crosswalk'!$I$2:$I$71,MATCH(W$1,'ISIC Crosswalk'!$K$2:$K$71,0),1),"'!","$Ao$9:$Ax$58")),MATCH(INDEX('ISIC Crosswalk'!$J$2:$J$71,MATCH(W$1,'ISIC Crosswalk'!$K$2:$K$71,0),1),INDIRECT(CONCATENATE("'","OECD TTL - ",INDEX('ISIC Crosswalk'!$I$2:$I$71,MATCH(W$1,'ISIC Crosswalk'!$K$2:$K$71,0),1),"'!","$a$9:$a$58")),0),MATCH("GGFC: Final consumption expenditure of general government",INDIRECT(CONCATENATE("'","OECD TTL - ",INDEX('ISIC Crosswalk'!$I$2:$I$71,MATCH(W$1,'ISIC Crosswalk'!$K$2:$K$71,0),1),"'!","$Ao$7:$Ax$7")),0))*1000000*IF(INDEX('ISIC Crosswalk'!$I$2:$I$71,MATCH(W$1,'ISIC Crosswalk'!$K$2:$K$71,0),1)=2023,About!$A$34,About!$A$32) -> 8427551.4 | X2: =INDEX(INDIRECT(CONCATENATE("'","OECD TTL - ",INDEX('ISIC Crosswalk'!$I$2:$I$71,MATCH(X$1,'ISIC Crosswalk'!$K$2:$K$71,0),1),"'!","$Ao$9:$Ax$58")),MATCH(INDEX('ISIC Crosswalk'!$J$2:$J$71,MATCH(X$1,'ISIC Crosswalk'!$K$2:$K$71,0),1),INDIRECT(CONCATENATE("'","OECD TTL - ",INDEX('ISIC Crosswalk'!$I$2:$I$71,MATCH(X$1,'ISIC Crosswalk'!$K$2:$K$71,0),1),"'!","$a$9:$a$58")),0),MATCH("GGFC: Final consumption expenditure of general government",INDIRECT(CONCATENATE("'","OECD TTL - ",INDEX('ISIC Crosswalk'!$I$2:$I$71,MATCH(X$1,'ISIC Crosswalk'!$K$2:$K$71,0),1),"'!","$Ao$7:$Ax$7")),0))*1000000*IF(INDEX('ISIC Crosswalk'!$I$2:$I$71,MATCH(X$1,'ISIC Crosswalk'!$K$2:$K$71,0),1)=2023,About!$A$34,About!$A$32) -> 443555.34 | Y2: =INDEX(INDIRECT(CONCATENATE("'","OECD TTL - ",INDEX('ISIC Crosswalk'!$I$2:$I$71,MATCH(Y$1,'ISIC Crosswalk'!$K$2:$K$71,0),1),"'!","$Ao$9:$Ax$58")),MATCH(INDEX('ISIC Crosswalk'!$J$2:$J$71,MATCH(Y$1,'ISIC Crosswalk'!$K$2:$K$71,0),1),INDIRECT(CONCATENATE("'","OECD TTL - ",INDEX('ISIC Crosswalk'!$I$2:$I$71,MATCH(Y$1,'ISIC Crosswalk'!$K$2:$K$71,0),1),"'!","$a$9:$a$58")),0),MATCH("GGFC: Final consumption expenditure of general government",INDIRECT(CONCATENATE("'","OECD TTL - ",INDEX('ISIC Crosswalk'!$I$2:$I$71,MATCH(Y$1,'ISIC Crosswalk'!$K$2:$K$71,0),1),"'!","$Ao$7:$Ax$7")),0))*1000000*IF(INDEX('ISIC Crosswalk'!$I$2:$I$71,MATCH(Y$1,'ISIC Crosswalk'!$K$2:$K$71,0),1)=2023,About!$A$34,About!$A$32) -> 3104887.4 | Z2: =('OECD TTL - 2023'!$AX31*BObIC!Z2/SUM(BObIC!$Z$2:$AA$2)*1000000)*(About!$A$34) -> 801005.28 | AA2: =('OECD TTL - 2023'!$AX31*BObIC!AA2/SUM(BObIC!$Z$2:$AA$2)*1000000)*(About!$A$34) -> 263527.53 | AB2: =INDEX(INDIRECT(CONCATENATE("'","OECD TTL - ",INDEX('ISIC Crosswalk'!$I$2:$I$71,MATCH(AB$1,'ISIC Crosswalk'!$K$2:$K$71,0),1),"'!","$Ao$9:$Ax$58")),MATCH(INDEX('ISIC Crosswalk'!$J$2:$J$71,MATCH(AB$1,'ISIC Crosswalk'!$K$2:$K$71,0),1),INDIRECT(CONCATENATE("'","OECD TTL - ",INDEX('ISIC Crosswalk'!$I$2:$I$71,MATCH(AB$1,'ISIC Crosswalk'!$K$2:$K$71,0),1),"'!","$a$9:$a$58")),0),MATCH("GGFC: Final consumption expenditure of general government",INDIRECT(CONCATENATE("'","OECD TTL - ",INDEX('ISIC Crosswalk'!$I$2:$I$71,MATCH(AB$1,'ISIC Crosswalk'!$K$2:$K$71,0),1),"'!","$Ao$7:$Ax$7")),0))*1000000*IF(INDEX('ISIC Crosswalk'!$I$2:$I$71,MATCH(AB$1,'ISIC Crosswalk'!$K$2:$K$71,0),1)=2023,About!$A$34,About!$A$32) -> 7.7968157e+08 | AC2: =INDEX(INDIRECT(CONCATENATE("'","OECD TTL - ",INDEX('ISIC Crosswalk'!$I$2:$I$71,MATCH(AC$1,'ISIC Crosswalk'!$K$2:$K$71,0),1),"'!","$Ao$9:$Ax$58")),MATCH(INDEX('ISIC Crosswalk'!$J$2:$J$71,MATCH(AC$1,'ISIC Crosswalk'!$K$2:$K$71,0),1),INDIRECT(CONCATENATE("'","OECD TTL - ",INDEX('ISIC Crosswalk'!$I$2:$I$71,MATCH(AC$1,'ISIC Crosswalk'!$K$2:$K$71,0),1),"'!","$a$9:$a$58")),0),MATCH("GGFC: Final consumption expenditure of general government",INDIRECT(CONCATENATE("'","OECD TTL - ",INDEX('ISIC Crosswalk'!$I$2:$I$71,MATCH(AC$1,'ISIC Crosswalk'!$K$2:$K$71,0),1),"'!","$Ao$7:$Ax$7")),0))*1000000*IF(INDEX('ISIC Crosswalk'!$I$2:$I$71,MATCH(AC$1,'ISIC Crosswalk'!$K$2:$K$71,0),1)=2023,About!$A$34,About!$A$32) -> 3637153.8 | AD2: =INDEX(INDIRECT(CONCATENATE("'","OECD TTL - ",INDEX('ISIC Crosswalk'!$I$2:$I$71,MATCH(AD$1,'ISIC Crosswalk'!$K$2:$K$71,0),1),"'!","$Ao$9:$Ax$58")),MATCH(INDEX('ISIC Crosswalk'!$J$2:$J$71,MATCH(AD$1,'ISIC Crosswalk'!$K$2:$K$71,0),1),INDIRECT(CONCATENATE("'","OECD TTL - ",INDEX('ISIC Crosswalk'!$I$2:$I$71,MATCH(AD$1,'ISIC Crosswalk'!$K$2:$K$71,0),1),"'!","$a$9:$a$58")),0),MATCH("GGFC: Final consumption expenditure of general government",INDIRECT(CONCATENATE("'","OECD TTL - ",INDEX('ISIC Crosswalk'!$I$2:$I$71,MATCH(AD$1,'ISIC Crosswalk'!$K$2:$K$71,0),1),"'!","$Ao$7:$Ax$7")),0))*1000000*IF(INDEX('ISIC Crosswalk'!$I$2:$I$71,MATCH(AD$1,'ISIC Crosswalk'!$K$2:$K$71,0),1)=2023,About!$A$34,About!$A$32) -> 1.0214192e+09 | AE2: =INDEX(INDIRECT(CONCATENATE("'","OECD TTL - ",INDEX('ISIC Crosswalk'!$I$2:$I$71,MATCH(AE$1,'ISIC Crosswalk'!$K$2:$K$71,0),1),"'!","$Ao$9:$Ax$58")),MATCH(INDEX('ISIC Crosswalk'!$J$2:$J$71,MATCH(AE$1,'ISIC Crosswalk'!$K$2:$K$71,0),1),INDIRECT(CONCATENATE("'","OECD TTL - ",INDEX('ISIC Crosswalk'!$I$2:$I$71,MATCH(AE$1,'ISIC Crosswalk'!$K$2:$K$71,0),1),"'!","$a$9:$a$58")),0),MATCH("GGFC: Final consumption expenditure of general government",INDIRECT(CONCATENATE("'","OECD TTL - ",INDEX('ISIC Crosswalk'!$I$2:$I$71,MATCH(AE$1,'ISIC Crosswalk'!$K$2:$K$71,0),1),"'!","$Ao$7:$Ax$7")),0))*1000000*IF(INDEX('ISIC Crosswalk'!$I$2:$I$71,MATCH(AE$1,'ISIC Crosswalk'!$K$2:$K$71,0),1)=2023,About!$A$34,About!$A$32) -> 4.8900014e+09 | AF2: =INDEX(INDIRECT(CONCATENATE("'","OECD TTL - ",INDEX('ISIC Crosswalk'!$I$2:$I$71,MATCH(AF$1,'ISIC Crosswalk'!$K$2:$K$71,0),1),"'!","$Ao$9:$Ax$58")),MATCH(INDEX('ISIC Crosswalk'!$J$2:$J$71,MATCH(AF$1,'ISIC Crosswalk'!$K$2:$K$71,0),1),INDIRECT(CONCATENATE("'","OECD TTL - ",INDEX('ISIC Crosswalk'!$I$2:$I$71,MATCH(AF$1,'ISIC Crosswalk'!$K$2:$K$71,0),1),"'!","$a$9:$a$58")),0),MATCH("GGFC: Final consumption expenditure of general government",INDIRECT(CONCATENATE("'","OECD TTL - ",INDEX('ISIC Crosswalk'!$I$2:$I$71,MATCH(AF$1,'ISIC Crosswalk'!$K$2:$K$71,0),1),"'!","$Ao$7:$Ax$7")),0))*1000000*IF(INDEX('ISIC Crosswalk'!$I$2:$I$71,MATCH(AF$1,'ISIC Crosswalk'!$K$2:$K$71,0),1)=2023,About!$A$34,About!$A$32) -> 2.1017426e+09 | AG2: =INDEX(INDIRECT(CONCATENATE("'","OECD TTL - ",INDEX('ISIC Crosswalk'!$I$2:$I$71,MATCH(AG$1,'ISIC Crosswalk'!$K$2:$K$71,0),1),"'!","$Ao$9:$Ax$58")),MATCH(INDEX('ISIC Crosswalk'!$J$2:$J$71,MATCH(AG$1,'ISIC Crosswalk'!$K$2:$K$71,0),1),INDIRECT(CONCATENATE("'","OECD TTL - ",INDEX('ISIC Crosswalk'!$I$2:$I$71,MATCH(AG$1,'ISIC Crosswalk'!$K$2:$K$71,0),1),"'!","$a$9:$a$58")),0),MATCH("GGFC: Final consumption expenditure of general government",INDIRECT(CONCATENATE("'","OECD TTL - ",INDEX('ISIC Crosswalk'!$I$2:$I$71,MATCH(AG$1,'ISIC Crosswalk'!$K$2:$K$71,0),1),"'!","$Ao$7:$Ax$7")),0))*1000000*IF(INDEX('ISIC Crosswalk'!$I$2:$I$71,MATCH(AG$1,'ISIC Crosswalk'!$K$2:$K$71,0),1)=2023,About!$A$34,About!$A$32) -> 17476080 | AH2: =INDEX(INDIRECT(CONCATENATE("'","OECD TTL - ",INDEX('ISIC Crosswalk'!$I$2:$I$71,MATCH(AH$1,'ISIC Crosswalk'!$K$2:$K$71,0),1),"'!","$Ao$9:$Ax$58")),MATCH(INDEX('ISIC Crosswalk'!$J$2:$J$71,MATCH(AH$1,'ISIC Crosswalk'!$K$2:$K$71,0),1),INDIRECT(CONCATENATE("'","OECD TTL - ",INDEX('ISIC Crosswalk'!$I$2:$I$71,MATCH(AH$1,'ISIC Crosswalk'!$K$2:$K$71,0),1),"'!","$a$9:$a$58")),0),MATCH("GGFC: Final consumption expenditure of general government",INDIRECT(CONCATENATE("'","OECD TTL - ",INDEX('ISIC Crosswalk'!$I$2:$I$71,MATCH(AH$1,'ISIC Crosswalk'!$K$2:$K$71,0),1),"'!","$Ao$7:$Ax$7")),0))*1000000*IF(INDEX('ISIC Crosswalk'!$I$2:$I$71,MATCH(AH$1,'ISIC Crosswalk'!$K$2:$K$71,0),1)=2023,About!$A$34,About!$A$32) -> 887110.67 | AI2: =INDEX(INDIRECT(CONCATENATE("'","OECD TTL - ",INDEX('ISIC Crosswalk'!$I$2:$I$71,MATCH(AI$1,'ISIC Crosswalk'!$K$2:$K$71,0),1),"'!","$Ao$9:$Ax$58")),MATCH(INDEX('ISIC Crosswalk'!$J$2:$J$71,MATCH(AI$1,'ISIC Crosswalk'!$K$2:$K$71,0),1),INDIRECT(CONCATENATE("'","OECD TTL - ",INDEX('ISIC Crosswalk'!$I$2:$I$71,MATCH(AI$1,'ISIC Crosswalk'!$K$2:$K$71,0),1),"'!","$a$9:$a$58")),0),MATCH("GGFC: Final consumption expenditure of general government",INDIRECT(CONCATENATE("'","OECD TTL - ",INDEX('ISIC Crosswalk'!$I$2:$I$71,MATCH(AI$1,'ISIC Crosswalk'!$K$2:$K$71,0),1),"'!","$Ao$7:$Ax$7")),0))*1000000*IF(INDEX('ISIC Crosswalk'!$I$2:$I$71,MATCH(AI$1,'ISIC Crosswalk'!$K$2:$K$71,0),1)=2023,About!$A$34,About!$A$32) -> 11443728 | ... AQ2: =INDEX(INDIRECT(CONCATENATE("'","OECD TTL - ",INDEX('ISIC Crosswalk'!$I$2:$I$71,MATCH(AQ$1,'ISIC Crosswalk'!$K$2:$K$71,0),1),"'!","$Ao$9:$Ax$58")),MATCH(INDEX('ISIC Crosswalk'!$J$2:$J$71,MATCH(AQ$1,'ISIC Crosswalk'!$K$2:$K$71,0),1),INDIRECT(CONCATENATE("'","OECD TTL - ",INDEX('ISIC Crosswalk'!$I$2:$I$71,MATCH(AQ$1,'ISIC Crosswalk'!$K$2:$K$71,0),1),"'!","$a$9:$a$58")),0),MATCH("GGFC: Final consumption expenditure of general government",INDIRECT(CONCATENATE("'","OECD TTL - ",INDEX('ISIC Crosswalk'!$I$2:$I$71,MATCH(AQ$1,'ISIC Crosswalk'!$K$2:$K$71,0),1),"'!","$Ao$7:$Ax$7")),0))*1000000*IF(INDEX('ISIC Crosswalk'!$I$2:$I$71,MATCH(AQ$1,'ISIC Crosswalk'!$K$2:$K$71,0),1)=2023,About!$A$34,About!$A$32) -> 0

Sheet GaHEbIC-household
A1: Unit: USD | B1: ISIC 01T03 | C1: ISIC 05 | D1: ISIC 06 | E1: ISIC 07T08 | F1: ISIC 09 | G1: ISIC 10T12 | H1: ISIC 13T15 | I1: ISIC 16 | J1: ISIC 17T18 | K1: ISIC 19 | L1: ISIC 20 | M1: ISIC 21 | N1: ISIC 22 | O1: ISIC 231 | P1: ISIC 239 | Q1: ISIC 241 | R1: ISIC 242 | S1: ISIC 25 | T1: ISIC 26 | U1: ISIC 27 | V1: ISIC 28 | W1: ISIC 29 | X1: ISIC 30 | Y1: ISIC 31T33 | Z1: ISIC 351 | AA1: ISIC 352T353 | AB1: ISIC 36T39 | AC1: ISIC 41T43 | AD1: ISIC 45T47 | AE1: ISIC 49T53 | AF1: ISIC 55T56 | AG1: ISIC 58T60 | AH1: ISIC 61 | AI1: ISIC 62T63 | AJ1: ISIC 64T66 | AK1: ISIC 68 | AL1: ISIC 69T82 | AM1: ISIC 84 | AN1: ISIC 85 | AO1: ISIC 86T88 | AP1: ISIC 90T96 | AQ1: ISIC 97T98
A2: Household Expenditures | B2: =INDEX(INDIRECT(CONCATENATE("'","OECD TTL - ",INDEX('ISIC Crosswalk'!$I$2:$I$71,MATCH(B$1,'ISIC Crosswalk'!$K$2:$K$71,0),1),"'!","$AM$9:$AV$58")),MATCH(INDEX('ISIC Crosswalk'!$J$2:$J$71,MATCH(B$1,'ISIC Crosswalk'!$K$2:$K$71,0),1),INDIRECT(CONCATENATE("'","OECD TTL - ",INDEX('ISIC Crosswalk'!$I$2:$I$71,MATCH(B$1,'ISIC Crosswalk'!$K$2:$K$71,0),1),"'!","$a$9:$a$58")),0),MATCH("HFCE: Final consumption expenditure of households",INDIRECT(CONCATENATE("'","OECD TTL - ",INDEX('ISIC Crosswalk'!$I$2:$I$71,MATCH(B$1,'ISIC Crosswalk'!$K$2:$K$71,0),1),"'!","$Am$7:$Av$7")),0))*1000000*IF(INDEX('ISIC Crosswalk'!$I$2:$I$71,MATCH(B$1,'ISIC Crosswalk'!$K$2:$K$71,0),1)=2023,About!$A$34,About!$A$32) -> 1.0940096e+10 | C2: =('OECD TTL - 2023'!$AV$11*BObIC!C2/SUM(BObIC!$C$2:$D$2)*1000000)*(About!$A$34) -> 63699191 | D2: =('OECD TTL - 2023'!$AV$11*BObIC!D2/SUM(BObIC!$C$2:$D$2)*1000000)*(About!$A$34) -> 36100760 | E2: =INDEX(INDIRECT(CONCATENATE("'","OECD TTL - ",INDEX('ISIC Crosswalk'!$I$2:$I$71,MATCH(E$1,'ISIC Crosswalk'!$K$2:$K$71,0),1),"'!","$AM$9:$AV$58")),MATCH(INDEX('ISIC Crosswalk'!$J$2:$J$71,MATCH(E$1,'ISIC Crosswalk'!$K$2:$K$71,0),1),INDIRECT(CONCATENATE("'","OECD TTL - ",INDEX('ISIC Crosswalk'!$I$2:$I$71,MATCH(E$1,'ISIC Crosswalk'!$K$2:$K$71,0),1),"'!","$a$9:$a$58")),0),MATCH("HFCE: Final consumption expenditure of households",INDIRECT(CONCATENATE("'","OECD TTL - ",INDEX('ISIC Crosswalk'!$I$2:$I$71,MATCH(E$1,'ISIC Crosswalk'!$K$2:$K$71,0),1),"'!","$Am$7:$Av$7")),0))*1000000*IF(INDEX('ISIC Crosswalk'!$I$2:$I$71,MATCH(E$1,'ISIC Crosswalk'!$K$2:$K$71,0),1)=2023,About!$A$34,About!$A$32) -> 27323009 | F2: =INDEX(INDIRECT(CONCATENATE("'","OECD TTL - ",INDEX('ISIC Crosswalk'!$I$2:$I$71,MATCH(F$1,'ISIC Crosswalk'!$K$2:$K$71,0),1),"'!","$AM$9:$AV$58")),MATCH(INDEX('ISIC Crosswalk'!$J$2:$J$71,MATCH(F$1,'ISIC Crosswalk'!$K$2:$K$71,0),1),INDIRECT(CONCATENATE("'","OECD TTL - ",INDEX('ISIC Crosswalk'!$I$2:$I$71,MATCH(F$1,'ISIC Crosswalk'!$K$2:$K$71,0),1),"'!","$a$9:$a$58")),0),MATCH("HFCE: Final consumption expenditure of households",INDIRECT(CONCATENATE("'","OECD TTL - ",INDEX('ISIC Crosswalk'!$I$2:$I$71,MATCH(F$1,'ISIC Crosswalk'!$K$2:$K$71,0),1),"'!","$Am$7:$Av$7")),0))*1000000*IF(INDEX('ISIC Crosswalk'!$I$2:$I$71,MATCH(F$1,'ISIC Crosswalk'!$K$2:$K$71,0),1)=2023,About!$A$34,About!$A$32) -> 2483909.9 | G2: =INDEX(INDIRECT(CONCATENATE("'","OECD TTL - ",INDEX('ISIC Crosswalk'!$I$2:$I$71,MATCH(G$1,'ISIC Crosswalk'!$K$2:$K$71,0),1),"'!","$AM$9:$AV$58")),MATCH(INDEX('ISIC Crosswalk'!$J$2:$J$71,MATCH(G$1,'ISIC Crosswalk'!$K$2:$K$71,0),1),INDIRECT(CONCATENATE("'","OECD TTL - ",INDEX('ISIC Crosswalk'!$I$2:$I$71,MATCH(G$1,'ISIC Crosswalk'!$K$2:$K$71,0),1),"'!","$a$9:$a$58")),0),MATCH("HFCE: Final consumption expenditure of households",INDIRECT(CONCATENATE("'","OECD TTL - ",INDEX('ISIC Crosswalk'!$I$2:$I$71,MATCH(G$1,'ISIC Crosswalk'!$K$2:$K$71,0),1),"'!","$Am$7:$Av$7")),0))*1000000*IF(INDEX('ISIC Crosswalk'!$I$2:$I$71,MATCH(G$1,'ISIC Crosswalk'!$K$2:$K$71,0),1)=2023,About!$A$34,About!$A$32) -> 4.0493497e+10 | H2: =INDEX(INDIRECT(CONCATENATE("'","OECD TTL - ",INDEX('ISIC Crosswalk'!$I$2:$I$71,MATCH(H$1,'ISIC Crosswalk'!$K$2:$K$71,0),1),"'!","$AM$9:$AV$58")),MATCH(INDEX('ISIC Crosswalk'!$J$2:$J$71,MATCH(H$1,'ISIC Crosswalk'!$K$2:$K$71,0),1),INDIRECT(CONCATENATE("'","OECD TTL - ",INDEX('ISIC Crosswalk'!$I$2:$I$71,MATCH(H$1,'ISIC Crosswalk'!$K$2:$K$71,0),1),"'!","$a$9:$a$58")),0),MATCH("HFCE: Final consumption expenditure of households",INDIRECT(CONCATENATE("'","OECD TTL - ",INDEX('ISIC Crosswalk'!$I$2:$I$71,MATCH(H$1,'ISIC Crosswalk'!$K$2:$K$71,0),1),"'!","$Am$7:$Av$7")),0))*1000000*IF(INDEX('ISIC Crosswalk'!$I$2:$I$71,MATCH(H$1,'ISIC Crosswalk'!$K$2:$K$71,0),1)=2023,About!$A$34,About!$A$32) -> 2.7088102e+10 | I2: =INDEX(INDIRECT(CONCATENATE("'","OECD TTL - ",INDEX('ISIC Crosswalk'!$I$2:$I$71,MATCH(I$1,'ISIC Crosswalk'!$K$2:$K$71,0),1),"'!","$AM$9:$AV$58")),MATCH(INDEX('ISIC Crosswalk'!$J$2:$J$71,MATCH(I$1,'ISIC Crosswalk'!$K$2:$K$71,0),1),INDIRECT(CONCATENATE("'","OECD TTL - ",INDEX('ISIC Crosswalk'!$I$2:$I$71,MATCH(I$1,'ISIC Crosswalk'!$K$2:$K$71,0),1),"'!","$a$9:$a$58")),0),MATCH("HFCE: Final consumption expenditure of households",INDIRECT(CONCATENATE("'","OECD TTL - ",INDEX('ISIC Crosswalk'!$I$2:$I$71,MATCH(I$1,'ISIC Crosswalk'!$K$2:$K$71,0),1),"'!","$Am$7:$Av$7")),0))*1000000*IF(INDEX('ISIC Crosswalk'!$I$2:$I$71,MATCH(I$1,'ISIC Crosswalk'!$K$2:$K$71,0),1)=2023,About!$A$34,About!$A$32) -> 1.595025e+08 | J2: =INDEX(INDIRECT(CONCATENATE("'","OECD TTL - ",INDEX('ISIC Crosswalk'!$I$2:$I$71,MATCH(J$1,'ISIC Crosswalk'!$K$2:$K$71,0),1),"'!","$AM$9:$AV$58")),MATCH(INDEX('ISIC Crosswalk'!$J$2:$J$71,MATCH(J$1,'ISIC Crosswalk'!$K$2:$K$71,0),1),INDIRECT(CONCATENATE("'","OECD TTL - ",INDEX('ISIC Crosswalk'!$I$2:$I$71,MATCH(J$1,'ISIC Crosswalk'!$K$2:$K$71,0),1),"'!","$a$9:$a$58")),0),MATCH("HFCE: Final consumption expenditure of households",INDIRECT(CONCATENATE("'","OECD TTL - ",INDEX('ISIC Crosswalk'!$I$2:$I$71,MATCH(J$1,'ISIC Crosswalk'!$K$2:$K$71,0),1),"'!","$Am$7:$Av$7")),0))*1000000*IF(INDEX('ISIC Crosswalk'!$I$2:$I$71,MATCH(J$1,'ISIC Crosswalk'!$K$2:$K$71,0),1)=2023,About!$A$34,About!$A$32) -> 9.9489462e+08 | K2: =INDEX(INDIRECT(CONCATENATE("'","OECD TTL - ",INDEX('ISIC Crosswalk'!$I$2:$I$71,MATCH(K$1,'ISIC Crosswalk'!$K$2:$K$71,0),1),"'!","$AM$9:$AV$58")),MATCH(INDEX('ISIC Crosswalk'!$J$2:$J$71,MATCH(K$1,'ISIC Crosswalk'!$K$2:$K$71,0),1),INDIRECT(CONCATENATE("'","OECD TTL - ",INDEX('ISIC Crosswalk'!$I$2:$I$71,MATCH(K$1,'ISIC Crosswalk'!$K$2:$K$71,0),1),"'!","$a$9:$a$58")),0),MATCH("HFCE: Final consumption expenditure of households",INDIRECT(CONCATENATE("'","OECD TTL - ",INDEX('ISIC Crosswalk'!$I$2:$I$71,MATCH(K$1,'ISIC Crosswalk'!$K$2:$K$71,0),1),"'!","$Am$7:$Av$7")),0))*1000000*IF(INDEX('ISIC Crosswalk'!$I$2:$I$71,MATCH(K$1,'ISIC Crosswalk'!$K$2:$K$71,0),1)=2023,About!$A$34,About!$A$32) -> 1.0118384e+10 | L2: =INDEX(INDIRECT(CONCATENATE("'","OECD TTL - ",INDEX('ISIC Crosswalk'!$I$2:$I$71,MATCH(L$1,'ISIC Crosswalk'!$K$2:$K$71,0),1),"'!","$AM$9:$AV$58")),MATCH(INDEX('ISIC Crosswalk'!$J$2:$J$71,MATCH(L$1,'ISIC Crosswalk'!$K$2:$K$71,0),1),INDIRECT(CONCATENATE("'","OECD TTL - ",INDEX('ISIC Crosswalk'!$I$2:$I$71,MATCH(L$1,'ISIC Crosswalk'!$K$2:$K$71,0),1),"'!","$a$9:$a$58")),0),MATCH("HFCE: Final consumption expenditure of households",INDIRECT(CONCATENATE("'","OECD TTL - ",INDEX('ISIC Crosswalk'!$I$2:$I$71,MATCH(L$1,'ISIC Crosswalk'!$K$2:$K$71,0),1),"'!","$Am$7:$Av$7")),0))*1000000*IF(INDEX('ISIC Crosswalk'!$I$2:$I$71,MATCH(L$1,'ISIC Crosswalk'!$K$2:$K$71,0),1)=2023,About!$A$34,About!$A$32) -> 9.1957892e+09 | ... N2: =INDEX(INDIRECT(CONCATENATE("'","OECD TTL - ",INDEX('ISIC Crosswalk'!$I$2:$I$71,MATCH(N$1,'ISIC Crosswalk'!$K$2:$K$71,0),1),"'!","$AM$9:$AV$58")),MATCH(INDEX('ISIC Crosswalk'!$J$2:$J$71,MATCH(N$1,'ISIC Crosswalk'!$K$2:$K$71,0),1),INDIRECT(CONCATENATE("'","OECD TTL - ",INDEX('ISIC Crosswalk'!$I$2:$I$71,MATCH(N$1,'ISIC Crosswalk'!$K$2:$K$71,0),1),"'!","$a$9:$a$58")),0),MATCH("HFCE: Final consumption expenditure of households",INDIRECT(CONCATENATE("'","OECD TTL - ",INDEX('ISIC Crosswalk'!$I$2:$I$71,MATCH(N$1,'ISIC Crosswalk'!$K$2:$K$71,0),1),"'!","$Am$7:$Av$7")),0))*1000000*IF(INDEX('ISIC Crosswalk'!$I$2:$I$71,MATCH(N$1,'ISIC Crosswalk'!$K$2:$K$71,0),1)=2023,About!$A$34,About!$A$32) -> 7.2902755e+08 | O2: =('OECD TTL - 2023'!$AV22*BObIC!O2/SUM(BObIC!$O$2:$P$2)*1000000)*(About!$A$34) -> 58161060 | P2: =('OECD TTL - 2023'!$AV22*BObIC!P2/SUM(BObIC!$O$2:$P$2)*1000000)*(About!$A$34) -> 1.2050303e+08 | Q2: =('OECD TTL - 2023'!$AV23*BObIC!Q2/SUM(BObIC!$Q$2:$R$2)*1000000)*(About!$A$34) -> 5.3599453e+08 | R2: =('OECD TTL - 2023'!$AV23*BObIC!R2/SUM(BObIC!$Q$2:$R$2)*1000000)*(About!$A$34) -> 1.4628228e+08 | S2: =INDEX(INDIRECT(CONCATENATE("'","OECD TTL - ",INDEX('ISIC Crosswalk'!$I$2:$I$71,MATCH(S$1,'ISIC Crosswalk'!$K$2:$K$71,0),1),"'!","$AM$9:$AV$58")),MATCH(INDEX('ISIC Crosswalk'!$J$2:$J$71,MATCH(S$1,'ISIC Crosswalk'!$K$2:$K$71,0),1),INDIRECT(CONCATENATE("'","OECD TTL - ",INDEX('ISIC Crosswalk'!$I$2:$I$71,MATCH(S$1,'ISIC Crosswalk'!$K$2:$K$71,0),1),"'!","$a$9:$a$58")),0),MATCH("HFCE: Final consumption expenditure of households",INDIRECT(CONCATENATE("'","OECD TTL - ",INDEX('ISIC Crosswalk'!$I$2:$I$71,MATCH(S$1,'ISIC Crosswalk'!$K$2:$K$71,0),1),"'!","$Am$7:$Av$7")),0))*1000000*IF(INDEX('ISIC Crosswalk'!$I$2:$I$71,MATCH(S$1,'ISIC Crosswalk'!$K$2:$K$71,0),1)=2023,About!$A$34,About!$A$32) -> 1.2868427e+09 | T2: =INDEX(INDIRECT(CONCATENATE("'","OECD TTL - ",INDEX('ISIC Crosswalk'!$I$2:$I$71,MATCH(T$1,'ISIC Crosswalk'!$K$2:$K$71,0),1),"'!","$AM$9:$AV$58")),MATCH(INDEX('ISIC Crosswalk'!$J$2:$J$71,MATCH(T$1,'ISIC Crosswalk'!$K$2:$K$71,0),1),INDIRECT(CONCATENATE("'","OECD TTL - ",INDEX('ISIC Crosswalk'!$I$2:$I$71,MATCH(T$1,'ISIC Crosswalk'!$K$2:$K$71,0),1),"'!","$a$9:$a$58")),0),MATCH("HFCE: Final consumption expenditure of households",INDIRECT(CONCATENATE("'","OECD TTL - ",INDEX('ISIC Crosswalk'!$I$2:$I$71,MATCH(T$1,'ISIC Crosswalk'!$K$2:$K$71,0),1),"'!","$Am$7:$Av$7")),0))*1000000*IF(INDEX('ISIC Crosswalk'!$I$2:$I$71,MATCH(T$1,'ISIC Crosswalk'!$K$2:$K$71,0),1)=2023,About!$A$34,About!$A$32) -> 2.0963135e+10 | U2: =INDEX(INDIRECT(CONCATENATE("'","OECD TTL - ",INDEX('ISIC Crosswalk'!$I$2:$I$71,MATCH(U$1,'ISIC Crosswalk'!$K$2:$K$71,0),1),"'!","$AM$9:$AV$58")),MATCH(INDEX('ISIC Crosswalk'!$J$2:$J$71,MATCH(U$1,'ISIC Crosswalk'!$K$2:$K$71,0),1),INDIRECT(CONCATENATE("'","OECD TTL - ",INDEX('ISIC Crosswalk'!$I$2:$I$71,MATCH(U$1,'ISIC Crosswalk'!$K$2:$K$71,0),1),"'!","$a$9:$a$58")),0),MATCH("HFCE: Final consumption expenditure of households",INDIRECT(CONCATENATE("'","OECD TTL - ",INDEX('ISIC Crosswalk'!$I$2:$I$71,MATCH(U$1,'ISIC Crosswalk'!$K$2:$K$71,0),1),"'!","$Am$7:$Av$7")),0))*1000000*IF(INDEX('ISIC Crosswalk'!$I$2:$I$71,MATCH(U$1,'ISIC Crosswalk'!$K$2:$K$71,0),1)=2023,About!$A$34,About!$A$32) -> 6.4014793e+09 | V2: =INDEX(INDIRECT(CONCATENATE("'","OECD TTL - ",INDEX('ISIC Crosswalk'!$I$2:$I$71,MATCH(V$1,'ISIC Crosswalk'!$K$2:$K$71,0),1),"'!","$AM$9:$AV$58")),MATCH(INDEX('ISIC Crosswalk'!$J$2:$J$71,MATCH(V$1,'ISIC Crosswalk'!$K$2:$K$71,0),1),INDIRECT(CONCATENATE("'","OECD TTL - ",INDEX('ISIC Crosswalk'!$I$2:$I$71,MATCH(V$1,'ISIC Crosswalk'!$K$2:$K$71,0),1),"'!","$a$9:$a$58")),0),MATCH("HFCE: Final consumption expenditure of households",INDIRECT(CONCATENATE("'","OECD TTL - ",INDEX('ISIC Crosswalk'!$I$2:$I$71,MATCH(V$1,'ISIC Crosswalk'!$K$2:$K$71,0),1),"'!","$Am$7:$Av$7")),0))*1000000*IF(INDEX('ISIC Crosswalk'!$I$2:$I$71,MATCH(V$1,'ISIC Crosswalk'!$K$2:$K$71,0),1)=2023,About!$A$34,About!$A$32) -> 2.5444108e+09 | W2: =INDEX(INDIRECT(CONCATENATE("'","OECD TTL - ",INDEX('ISIC Crosswalk'!$I$2:$I$71,MATCH(W$1,'ISIC Crosswalk'!$K$2:$K$71,0),1),"'!","$AM$9:$AV$58")),MATCH(INDEX('ISIC Crosswalk'!$J$2:$J$71,MATCH(W$1,'ISIC Crosswalk'!$K$2:$K$71,0),1),INDIRECT(CONCATENATE("'","OECD TTL - ",INDEX('ISIC Crosswalk'!$I$2:$I$71,MATCH(W$1,'ISIC Crosswalk'!$K$2:$K$71,0),1),"'!","$a$9:$a$58")),0),MATCH("HFCE: Final consumption expenditure of households",INDIRECT(CONCATENATE("'","OECD TTL - ",INDEX('ISIC Crosswalk'!$I$2:$I$71,MATCH(W$1,'ISIC Crosswalk'!$K$2:$K$71,0),1),"'!","$Am$7:$Av$7")),0))*1000000*IF(INDEX('ISIC Crosswalk'!$I$2:$I$71,MATCH(W$1,'ISIC Crosswalk'!$K$2:$K$71,0),1)=2023,About!$A$34,About!$A$32) -> 2.297457e+10 | X2: =INDEX(INDIRECT(CONCATENATE("'","OECD TTL - ",INDEX('ISIC Crosswalk'!$I$2:$I$71,MATCH(X$1,'ISIC Crosswalk'!$K$2:$K$71,0),1),"'!","$AM$9:$AV$58")),MATCH(INDEX('ISIC Crosswalk'!$J$2:$J$71,MATCH(X$1,'ISIC Crosswalk'!$K$2:$K$71,0),1),INDIRECT(CONCATENATE("'","OECD TTL - ",INDEX('ISIC Crosswalk'!$I$2:$I$71,MATCH(X$1,'ISIC Crosswalk'!$K$2:$K$71,0),1),"'!","$a$9:$a$58")),0),MATCH("HFCE: Final consumption expenditure of households",INDIRECT(CONCATENATE("'","OECD TTL - ",INDEX('ISIC Crosswalk'!$I$2:$I$71,MATCH(X$1,'ISIC Crosswalk'!$K$2:$K$71,0),1),"'!","$Am$7:$Av$7")),0))*1000000*IF(INDEX('ISIC Crosswalk'!$I$2:$I$71,MATCH(X$1,'ISIC Crosswalk'!$K$2:$K$71,0),1)=2023,About!$A$34,About!$A$32) -> 5.1212899e+08 | Y2: =INDEX(INDIRECT(CONCATENATE("'","OECD TTL - ",INDEX('ISIC Crosswalk'!$I$2:$I$71,MATCH(Y$1,'ISIC Crosswalk'!$K$2:$K$71,0),1),"'!","$AM$9:$AV$58")),MATCH(INDEX('ISIC Crosswalk'!$J$2:$J$71,MATCH(Y$1,'ISIC Crosswalk'!$K$2:$K$71,0),1),INDIRECT(CONCATENATE("'","OECD TTL - ",INDEX('ISIC Crosswalk'!$I$2:$I$71,MATCH(Y$1,'ISIC Crosswalk'!$K$2:$K$71,0),1),"'!","$a$9:$a$58")),0),MATCH("HFCE: Final consumption expenditure of households",INDIRECT(CONCATENATE("'","OECD TTL - ",INDEX('ISIC Crosswalk'!$I$2:$I$71,MATCH(Y$1,'ISIC Crosswalk'!$K$2:$K$71,0),1),"'!","$Am$7:$Av$7")),0))*1000000*IF(INDEX('ISIC Crosswalk'!$I$2:$I$71,MATCH(Y$1,'ISIC Crosswalk'!$K$2:$K$71,0),1)=2023,About!$A$34,About!$A$32) -> 6.619265e+09 | Z2: =('OECD TTL - 2023'!$AX31*BObIC!Z2/SUM(BObIC!$Z$2:$AA$2)*1000000)*(About!$A$34) -> 801005.28 | AA2: =('OECD TTL - 2023'!$AX31*BObIC!AA2/SUM(BObIC!$Z$2:$AA$2)*1000000)*(About!$A$34) -> 263527.53 | AB2: =INDEX(INDIRECT(CONCATENATE("'","OECD TTL - ",INDEX('ISIC Crosswalk'!$I$2:$I$71,MATCH(AB$1,'ISIC Crosswalk'!$K$2:$K$71,0),1),"'!","$AM$9:$AV$58")),MATCH(INDEX('ISIC Crosswalk'!$J$2:$J$71,MATCH(AB$1,'ISIC Crosswalk'!$K$2:$K$71,0),1),INDIRECT(CONCATENATE("'","OECD TTL - ",INDEX('ISIC Crosswalk'!$I$2:$I$71,MATCH(AB$1,'ISIC Crosswalk'!$K$2:$K$71,0),1),"'!","$a$9:$a$58")),0),MATCH("HFCE: Final consumption expenditure of households",INDIRECT(CONCATENATE("'","OECD TTL - ",INDEX('ISIC Crosswalk'!$I$2:$I$71,MATCH(AB$1,'ISIC Crosswalk'!$K$2:$K$71,0),1),"'!","$Am$7:$Av$7")),0))*1000000*IF(INDEX('ISIC Crosswalk'!$I$2:$I$71,MATCH(AB$1,'ISIC Crosswalk'!$K$2:$K$71,0),1)=2023,About!$A$34,About!$A$32) -> 3.1357588e+09 | AC2: =INDEX(INDIRECT(CONCATENATE("'","OECD TTL - ",INDEX('ISIC Crosswalk'!$I$2:$I$71,MATCH(AC$1,'ISIC Crosswalk'!$K$2:$K$71,0),1),"'!","$AM$9:$AV$58")),MATCH(INDEX('ISIC Crosswalk'!$J$2:$J$71,MATCH(AC$1,'ISIC Crosswalk'!$K$2:$K$71,0),1),INDIRECT(CONCATENATE("'","OECD TTL - ",INDEX('ISIC Crosswalk'!$I$2:$I$71,MATCH(AC$1,'ISIC Crosswalk'!$K$2:$K$71,0),1),"'!","$a$9:$a$58")),0),MATCH("HFCE: Final consumption expenditure of households",INDIRECT(CONCATENATE("'","OECD TTL - ",INDEX('ISIC Crosswalk'!$I$2:$I$71,MATCH(AC$1,'ISIC Crosswalk'!$K$2:$K$71,0),1),"'!","$Am$7:$Av$7")),0))*1000000*IF(INDEX('ISIC Crosswalk'!$I$2:$I$71,MATCH(AC$1,'ISIC Crosswalk'!$K$2:$K$71,0),1)=2023,About!$A$34,About!$A$32) -> 2.8981906e+08 | AD2: =INDEX(INDIRECT(CONCATENATE("'","OECD TTL - ",INDEX('ISIC Crosswalk'!$I$2:$I$71,MATCH(AD$1,'ISIC Crosswalk'!$K$2:$K$71,0),1),"'!","$AM$9:$AV$58")),MATCH(INDEX('ISIC Crosswalk'!$J$2:$J$71,MATCH(AD$1,'ISIC Crosswalk'!$K$2:$K$71,0),1),INDIRECT(CONCATENATE("'","OECD TTL - ",INDEX('ISIC Crosswalk'!$I$2:$I$71,MATCH(AD$1,'ISIC Crosswalk'!$K$2:$K$71,0),1),"'!","$a$9:$a$58")),0),MATCH("HFCE: Final consumption expenditure of households",INDIRECT(CONCATENATE("'","OECD TTL - ",INDEX('ISIC Crosswalk'!$I$2:$I$71,MATCH(AD$1,'ISIC Crosswalk'!$K$2:$K$71,0),1),"'!","$Am$7:$Av$7")),0))*1000000*IF(INDEX('ISIC Crosswalk'!$I$2:$I$71,MATCH(AD$1,'ISIC Crosswalk'!$K$2:$K$71,0),1)=2023,About!$A$34,About!$A$32) -> 4.9098382e+10 | AE2: =INDEX(INDIRECT(CONCATENATE("'","OECD TTL - ",INDEX('ISIC Crosswalk'!$I$2:$I$71,MATCH(AE$1,'ISIC Crosswalk'!$K$2:$K$71,0),1),"'!","$AM$9:$AV$58")),MATCH(INDEX('ISIC Crosswalk'!$J$2:$J$71,MATCH(AE$1,'ISIC Crosswalk'!$K$2:$K$71,0),1),INDIRECT(CONCATENATE("'","OECD TTL - ",INDEX('ISIC Crosswalk'!$I$2:$I$71,MATCH(AE$1,'ISIC Crosswalk'!$K$2:$K$71,0),1),"'!","$a$9:$a$58")),0),MATCH("HFCE: Final consumption expenditure of households",INDIRECT(CONCATENATE("'","OECD TTL - ",INDEX('ISIC Crosswalk'!$I$2:$I$71,MATCH(AE$1,'ISIC Crosswalk'!$K$2:$K$71,0),1),"'!","$Am$7:$Av$7")),0))*1000000*IF(INDEX('ISIC Crosswalk'!$I$2:$I$71,MATCH(AE$1,'ISIC Crosswalk'!$K$2:$K$71,0),1)=2023,About!$A$34,About!$A$32) -> 3.060036e+10 | AF2: =INDEX(INDIRECT(CONCATENATE("'","OECD TTL - ",INDEX('ISIC Crosswalk'!$I$2:$I$71,MATCH(AF$1,'ISIC Crosswalk'!$K$2:$K$71,0),1),"'!","$AM$9:$AV$58")),MATCH(INDEX('ISIC Crosswalk'!$J$2:$J$71,MATCH(AF$1,'ISIC Crosswalk'!$K$2:$K$71,0),1),INDIRECT(CONCATENATE("'","OECD TTL - ",INDEX('ISIC Crosswalk'!$I$2:$I$71,MATCH(AF$1,'ISIC Crosswalk'!$K$2:$K$71,0),1),"'!","$a$9:$a$58")),0),MATCH("HFCE: Final consumption expenditure of households",INDIRECT(CONCATENATE("'","OECD TTL - ",INDEX('ISIC Crosswalk'!$I$2:$I$71,MATCH(AF$1,'ISIC Crosswalk'!$K$2:$K$71,0),1),"'!","$Am$7:$Av$7")),0))*1000000*IF(INDEX('ISIC Crosswalk'!$I$2:$I$71,MATCH(AF$1,'ISIC Crosswalk'!$K$2:$K$71,0),1)=2023,About!$A$34,About!$A$32) -> 5.625701e+10 | AG2: =INDEX(INDIRECT(CONCATENATE("'","OECD TTL - ",INDEX('ISIC Crosswalk'!$I$2:$I$71,MATCH(AG$1,'ISIC Crosswalk'!$K$2:$K$71,0),1),"'!","$AM$9:$AV$58")),MATCH(INDEX('ISIC Crosswalk'!$J$2:$J$71,MATCH(AG$1,'ISIC Crosswalk'!$K$2:$K$71,0),1),INDIRECT(CONCATENATE("'","OECD TTL - ",INDEX('ISIC Crosswalk'!$I$2:$I$71,MATCH(AG$1,'ISIC Crosswalk'!$K$2:$K$71,0),1),"'!","$a$9:$a$58")),0),MATCH("HFCE: Final consumption expenditure of households",INDIRECT(CONCATENATE("'","OECD TTL - ",INDEX('ISIC Crosswalk'!$I$2:$I$71,MATCH(AG$1,'ISIC Crosswalk'!$K$2:$K$71,0),1),"'!","$Am$7:$Av$7")),0))*1000000*IF(INDEX('ISIC Crosswalk'!$I$2:$I$71,MATCH(AG$1,'ISIC Crosswalk'!$K$2:$K$71,0),1)=2023,About!$A$34,About!$A$32) -> 7.5149806e+09 | AH2: =INDEX(INDIRECT(CONCATENATE("'","OECD TTL - ",INDEX('ISIC Crosswalk'!$I$2:$I$71,MATCH(AH$1,'ISIC Crosswalk'!$K$2:$K$71,0),1),"'!","$AM$9:$AV$58")),MATCH(INDEX('ISIC Crosswalk'!$J$2:$J$71,MATCH(AH$1,'ISIC Crosswalk'!$K$2:$K$71,0),1),INDIRECT(CONCATENATE("'","OECD TTL - ",INDEX('ISIC Crosswalk'!$I$2:$I$71,MATCH(AH$1,'ISIC Crosswalk'!$K$2:$K$71,0),1),"'!","$a$9:$a$58")),0),MATCH("HFCE: Final consumption expenditure of households",INDIRECT(CONCATENATE("'","OECD TTL - ",INDEX('ISIC Crosswalk'!$I$2:$I$71,MATCH(AH$1,'ISIC Crosswalk'!$K$2:$K$71,0),1),"'!","$Am$7:$Av$7")),0))*1000000*IF(INDEX('ISIC Crosswalk'!$I$2:$I$71,MATCH(AH$1,'ISIC Crosswalk'!$K$2:$K$71,0),1)=2023,About!$A$34,About!$A$32) -> 8.5646987e+09 | AI2: =INDEX(INDIRECT(CONCATENATE("'","OECD TTL - ",INDEX('ISIC Crosswalk'!$I$2:$I$71,MATCH(AI$1,'ISIC Crosswalk'!$K$2:$K$71,0),1),"'!","$AM$9:$AV$58")),MATCH(INDEX('ISIC Crosswalk'!$J$2:$J$71,MATCH(AI$1,'ISIC Crosswalk'!$K$2:$K$71,0),1),INDIRECT(CONCATENATE("'","OECD TTL - ",INDEX('ISIC Crosswalk'!$I$2:$I$71,MATCH(AI$1,'ISIC Crosswalk'!$K$2:$K$71,0),1),"'!","$a$9:$a$58")),0),MATCH("HFCE: Final consumption expenditure of households",INDIRECT(CONCATENATE("'","OECD TTL - ",INDEX('ISIC Crosswalk'!$I$2:$I$71,MATCH(AI$1,'ISIC Crosswalk'!$K$2:$K$71,0),1),"'!","$Am$7:$Av$7")),0))*1000000*IF(INDEX('ISIC Crosswalk'!$I$2:$I$71,MATCH(AI$1,'ISIC Crosswalk'!$K$2:$K$71,0),1)=2023,About!$A$34,About!$A$32) -> 6.6048938e+09 | ... AQ2: =INDEX(INDIRECT(CONCATENATE("'","OECD TTL - ",INDEX('ISIC Crosswalk'!$I$2:$I$71,MATCH(AQ$1,'ISIC Crosswalk'!$K$2:$K$71,0),1),"'!","$AM$9:$AV$58")),MATCH(INDEX('ISIC Crosswalk'!$J$2:$J$71,MATCH(AQ$1,'ISIC Crosswalk'!$K$2:$K$71,0),1),INDIRECT(CONCATENATE("'","OECD TTL - ",INDEX('ISIC Crosswalk'!$I$2:$I$71,MATCH(AQ$1,'ISIC Crosswalk'!$K$2:$K$71,0),1),"'!","$a$9:$a$58")),0),MATCH("HFCE: Final consumption expenditure of households",INDIRECT(CONCATENATE("'","OECD TTL - ",INDEX('ISIC Crosswalk'!$I$2:$I$71,MATCH(AQ$1,'ISIC Crosswalk'!$K$2:$K$71,0),1),"'!","$Am$7:$Av$7")),0))*1000000*IF(INDEX('ISIC Crosswalk'!$I$2:$I$71,MATCH(AQ$1,'ISIC Crosswalk'!$K$2:$K$71,0),1)=2023,About!$A$34,About!$A$32) -> 1.6305094e+09
