Workbook

Sheet About
A1: BRESaC Percent Energy Savings from Retrofitting by Component
A2: BRESaC Retrofitting Cost per Unit Energy Saved
A4: Source: | B4: Residential Buildings, Single Family
B5: Lawrence Berkeley National Laboratory
B6: 2014
B7: A Meta-Analysis of Single-Family Deep Energy Retrofit Performance in the U.S.
B8: https://www.osti.gov/servlets/purl/1129577
B9: Tables 11 and 15
B11: Residential Buildings, Multifamily
B12: Building Energy Exchange
B13: 2015
B14: Evaluating New York City’s Multifamily Building Energy Data for Savings Opportunities: Retrofitting Affordability
B15: https://be-exchange.org/wp-content/uploads/2017/11/BEEx_Retrofitting_Affordability_Update_Nov2015-1.pdf
B16: Table 3, Table 13, Figure 6
B18: Commercial Buildings Deep Retrofit Measures
B19: PNNL
B20: 2011
B21: Advanced Energy Retrofit Guides OFFICE BUILDINGS
B22: https://www.pnnl.gov/main/publications/external/technical_reports/PNNL-20761.pdf
B23: Table 5.3 and Appendix
B25: Commercial Buildings Statistics
B26: EIA
B27: 2015
B28: Commercial Building Energy Consumption Survey 2012
B29: https://www.eia.gov/consumption/commercial/data/2012/index.php?view=characteristics
B30: Tables B5, B10, and C4
B32: US County Climate Zones
B33: PNNL and ORNL
B34: 2010
B35: Guide to Determining Climate Regions by County
B36: https://www1.eere.energy.gov/buildings/publications/pdfs/building_america/ba_climateguide_7_1.pdf
B37: Tables B5, B10, and C4
A39: Notes
A40: This variable helps control the building retrofitting policy, whose effects are cumulative with other
A41: policies affecting the energy use of building components.
A43: Therefore, for energy savings, this variable should contain the percentage of energy savings from
A44: retrofitting in a scenario where retrofitting is the only enabled policy. For example, you should
A45: incorporate any effects from future improvement of building codes that is part of the BAU case,
A46: but you should not incorporate any effects from future improvement of building codes above
A47: and beyond the improvement in the BAU case (caused by the building energy efficiency standards
A48: policy lever).

Sheet Residential
A1: Single Family
C2: Source
A3: Average project costs ($) | B3: 40420 | C3: Table 15
A4: Average project costs ($/SF) | B4: 22.11 | C4: Table 15
A5: Average site energy reduction (MMBtu) | B5: 74.5 | C5: Table 11
A6: Average cost per energy reduction ($/btu) | B6: =B3/(B5*10^6) -> 0.00054255034
A7: Average percent reduction in energy use | B7: 0.47 | C7: Table 11
A10: Multi Family
A11: Removing non-heating/cooling/envelope related retrofit costs and savings
A12: Building Type | B12: Removed Tech | C12: Frequency of Rec | D12: Total Removed Source Savings (GBTU) | E12: Measure cost ($/SF) | F12: Frequency adjusted measure costs ($/SF-rec)
A13: post war gas low | B13: separate dhw from heating | C13: 0.44 | D13: 1000 | E13: 0.3 | F13: =E13*C13 -> 0.132
A14: post war gas low | B14: install low flow aerators | C14: 0.29 | D14: 500 | E14: 0.08 | F14: =E14*C14 -> 0.0232
A15: post war gas low | B15: replace boiler | C15: 0.04 | D15: 240 | E15: 0.71 | F15: =E15*C15 -> 0.0284
A16: post war oil | B16: seprrate dhw from heating | C16: 0.24 | D16: 570 | E16: 0.6 | F16: =E16*C16 -> 0.144
A17: post war gas mid | B17: separate dhw from heating | C17: 0.17 | D17: 190 | E17: 0.6 | F17: =E17*C17 -> 0.102
A18: post war gas mid | B18: upgrade boiler | C18: 0.12 | D18: 180 | E18: 1.28 | F18: =E18*C18 -> 0.1536
A19: pre war gas low | B19: separate dhw from heating | C19: 0.33 | D19: 340 | E19: 0.48 | F19: =E19*C19 -> 0.1584
A20: pre war gas low | B20: install low flow showerheads | C20: 0.06 | D20: 210 | E20: 0.04 | F20: =E20*C20 -> 0.0024
A21: pre war gas low | B21: installe low flow aerators | C21: 0.27 | D21: 190 | E21: 0.06 | F21: =E21*C21 -> 0.0162
A22: pre war oil mid | B22: separate dhw from heating | C22: 0.38 | D22: 260 | E22: 0.55 | F22: =E22*C22 -> 0.209
A23: pre war oil mid | B23: #2 oil to natural gas | C23: 0.08 | D23: 200 | E23: 2.19 | F23: =E23*C23 -> 0.1752
A24: pre war oil mid | B24: #6 oil or #4 oil to natural gas | C24: 0.36 | D24: 110 | E24: 2.05 | F24: =E24*C24 -> 0.738
... A35: pre war gas mid | B35: install low flow aerators | C35: 0.29 | D35: 40 | E35: 0.05 | F35: =E35*C35 -> 0.0145
A37: Adjusted Savings by Building Type after Removing Uncovered Costs
B38: Area (million SF) | C38: Total Source Savings (TBTU) | D38: Retrofit cost (millions) | E38: Adjusted Source Savings (TBTU) | F38: Adjusted Costs ($) | G38: Cost per BTU Saved | H38: Source Energy Use | I38: Percent Reduction
A39: post war gas low | B39: 270 | C39: 4.9 | D39: 230 | E39: =C39-SUMIF($A$13:$A$35,A39,$D$13:$D$35)/10^3 -> 3.16 | F39: =D39*10^6-SUMIF($A$13:$A$35,A39,$F$13:$F$35)*B39*10^6 -> 180428000 | G39: =F39/(E39*10^12) -> 5.7097468e-05 | H39: 31 | I39: =1-(H39-E39)/H39 -> 0.10193548
A40: post war oil | B40: 200 | C40: 3.7 | D40: 430 | E40: =C40-SUMIF($A$13:$A$35,A40,$D$13:$D$35)/10^3 -> 3.13 | F40: =D40*10^6-SUMIF($A$13:$A$35,A40,$F$13:$F$35)*B40*10^6 -> 401200000 | G40: =F40/(E40*10^12) -> 0.00012817891 | H40: 26 | I40: =1-(H40-E40)/H40 -> 0.12038462
A41: post war gas mid | B41: 220 | C41: 2.7 | D41: 220 | E41: =C41-SUMIF($A$13:$A$35,A41,$D$13:$D$35)/10^3 -> 2.33 | F41: =D41*10^6-SUMIF($A$13:$A$35,A41,$F$13:$F$35)*B41*10^6 -> 163768000 | G41: =F41/(E41*10^12) -> 7.0286695e-05 | H41: 26 | I41: =1-(H41-E41)/H41 -> 0.089615385
A42: pre war gas low | B42: 160 | C42: 2.3 | D42: 180 | E42: =C42-SUMIF($A$13:$A$35,A42,$D$13:$D$35)/10^3 -> 1.56 | F42: =D42*10^6-SUMIF($A$13:$A$35,A42,$F$13:$F$35)*B42*10^6 -> 151680000 | G42: =F42/(E42*10^12) -> 9.7230769e-05 | H42: 17 | I42: =1-(H42-E42)/H42 -> 0.091764706
A43: pre war oil mid | B43: 110 | C43: 1.7 | D43: 240 | E43: =C43-SUMIF($A$13:$A$35,A43,$D$13:$D$35)/10^3 -> 1.02 | F43: =D43*10^6-SUMIF($A$13:$A$35,A43,$F$13:$F$35)*B43*10^6 -> 1.14094e+08 | G43: =F43/(E43*10^12) -> 0.00011185686 | H43: 12 | I43: =1-(H43-E43)/H43 -> 0.085
A44: post war gas high | B44: 220 | C44: 1.7 | D44: 40 | E44: =C44-SUMIF($A$13:$A$35,A44,$D$13:$D$35)/10^3 -> 1.21 | F44: =D44*10^6-SUMIF($A$13:$A$35,A44,$F$13:$F$35)*B44*10^6 -> 20486000 | G44: =F44/(E44*10^12) -> 1.6930579e-05 | H44: 35 | I44: =1-(H44-E44)/H44 -> 0.034571429
A45: pre war oil low | B45: 110 | C45: 1.7 | D45: 280 | E45: =C45-SUMIF($A$13:$A$35,A45,$D$13:$D$35)/10^3 -> 1.33 | F45: =D45*10^6-SUMIF($A$13:$A$35,A45,$F$13:$F$35)*B45*10^6 -> 259056000 | G45: =F45/(E45*10^12) -> 0.00019477895 | H45: 13 | I45: =1-(H45-E45)/H45 -> 0.10230769
A46: all electric | B46: 80 | C46: 1.2 | D46: 500 | E46: =C46-SUMIF($A$13:$A$35,A46,$D$13:$D$35)/10^3 -> 0.73 | F46: =D46*10^6-SUMIF($A$13:$A$35,A46,$F$13:$F$35)*B46*10^6 -> 473968000 | G46: =F46/(E46*10^12) -> 0.00064927123 | H46: 8 | I46: =1-(H46-E46)/H46 -> 0.09125
A47: all district steam | B47: 100 | C47: 0.7 | D47: 50 | E47: =C47-SUMIF($A$13:$A$35,A47,$D$13:$D$35)/10^3 -> 0.49 | F47: =D47*10^6-SUMIF($A$13:$A$35,A47,$F$13:$F$35)*B47*10^6 -> 49800000 | G47: =F47/(E47*10^12) -> 0.00010163265 | H47: 15 | I47: =1-(H47-E47)/H47 -> 0.032666667
A48: pre war gas mid | B48: 60 | C48: 0.3 | D48: 10 | E48: =C48-SUMIF($A$13:$A$35,A48,$D$13:$D$35)/10^3 -> 0.2 | F48: =D48*10^6-SUMIF($A$13:$A$35,A48,$F$13:$F$35)*B48*10^6 -> 2290000 | G48: =F48/(E48*10^12) -> 1.145e-05 | H48: 6 | I48: =1-(H48-E48)/H48 -> 0.033333333
A50: Floor area weighted cost per unit saved ($) | C50: =SUMPRODUCT(B39:B48,G39:G48)/SUM(B39:B48) -> 0.00011262662
A51: Floor area weighted average percent reduction in energy consumption | C51: =SUMPRODUCT(B39:B48,I39:I48)/SUM(B39:B48) -> 0.082858476
A53: Average Costs ($/BTU saved) | B53: =(B6*'AEO 2019_Table 4'!C17+C50*'AEO 2019_Table 4'!C18)/SUM('AEO 2019_Table 4'!C17:C18) -> 0.0004247967
A54: Average reduction in building energy use (%) | B54: =(B7*'AEO 2019_Table 4'!C17+C51*'AEO 2019_Table 4'!C18)/SUM('AEO 2019_Table 4'!C17:C18) -> 0.36396416
A55: Share of residential bldg energy use for space heating and cooling (ignoring non-appliance plug loads and "other") | B55: =SUM('AEO 2019_Table 4'!D77:D78,'AEO 2019_Table 4'!D89)/SUM('AEO 2019_Table 4'!D77:D86) -> 0.69537069
A56: Perc reduction heating and cooling energy use | B56: =B54/B55 -> 0.52341027

Sheet Commercial
A1: Climate | B1: Measure | C1: Savings as % of Total Site Energy | D1: Remaining Site Energy Use | E1: Cost | F1: Include? | I1: Floorspace allocation | J1: Average Energy Consumption per Building (MMBtu) | K1: Total Reductions | L1: Average Building Sqaure Footage | M1: Total Cost | N1: Cost per BTU Saved
A2: Hot & Humid | B2: E7 Add AEDG roof insulation | C2: 0.001 | D2: =MIN(1,1-C2) -> 0.999 | E2: 312358 | F2: 0 | H2: Cold | I2: ='County Climates'!L28 -> 0.41667828 | J2: ='CBECS_Table C4'!B61 -> 1352 | K2: {=SUMPRODUCT(IF(A2:A56=H2,C2:C56),IF(A2:A56=H2,F2:F56))} -> 0.238 | L2: ='CBECS_Table B10'!H26*10^3/'CBECS_Table B10'!B26 -> 15762.846 | M2: {=SUMPRODUCT(IF(A2:A56=H2,E2:E56),IF(A2:A56=H2,F2:F56))} -> 1238255 | N2: =M2/(J2*10^6*K2) -> 0.0038481894
A3: Hot & Dry | B3: E7 Add AEDG roof insulation | C3: 0.009 | D3: =MIN(1,1-C3) -> 0.991 | E3: 376577 | F3: 1 | H3: Hot & Dry | I3: ='County Climates'!L29+'County Climates'!L32 -> 0.067288166 | J3: ='CBECS_Table C4'!B63 -> 960 | K3: {=SUMPRODUCT(IF(A3:A57=H3,C3:C57),IF(A3:A57=H3,F3:F57))} -> 0.382 | L3: =L2 -> 15762.846 | M3: {=SUMPRODUCT(IF(A3:A57=H3,E3:E57),IF(A3:A57=H3,F3:F57))} -> 1353942 | N3: =M3/(J3*10^6*K3) -> 0.0036920321
A4: Marine | B4: E7 Add AEDG roof insulation | C4: 0.013 | D4: =MIN(1,1-C4) -> 0.987 | E4: 390000 | F4: 1 | H4: Hot & Humid | I4: ='County Climates'!L30+'County Climates'!L33 -> 0.42559458 | J4: ='CBECS_Table C4'!B64 -> 1185 | K4: {=SUMPRODUCT(IF(A4:A58=H4,C4:C58),IF(A4:A58=H4,F4:F58))} -> 0.352 | L4: =L3 -> 15762.846 | M4: {=SUMPRODUCT(IF(A4:A58=H4,E4:E58),IF(A4:A58=H4,F4:F58))} -> 857498 | N4: =M4/(J4*10^6*K4) -> 0.0020557585
A5: Cold | B5: E7 Add AEDG roof insulation | C5: 0.016 | D5: =MIN(1,1-C5) -> 0.984 | E5: 369120 | F5: 1 | H5: Marine | I5: ='County Climates'!L31 -> 0.046834572 | J5: ='CBECS_Table C4'!B65 -> 1337 | K5: {=SUMPRODUCT(IF(A5:A59=H5,C5:C59),IF(A5:A59=H5,F5:F59))} -> 0.257 | L5: =L4 -> 15762.846 | M5: {=SUMPRODUCT(IF(A5:A59=H5,E5:E59),IF(A5:A59=H5,F5:F59))} -> 827853 | N5: =M5/(J5*10^6*K5) -> 0.0024092879
A6: Very Cold | B6: E7 Add AEDG roof insulation | C6: 0.022 | D6: =MIN(1,1-C6) -> 0.978 | E6: 412876 | F6: 1 | H6: Very Cold | I6: ='County Climates'!L35+'County Climates'!L34 -> 0.043604409 | J6: ='CBECS_Table C4'!B61 -> 1352 | K6: {=SUMPRODUCT(IF(A6:A60=H6,C6:C60),IF(A6:A60=H6,F6:F60))} -> 0.224 | L6: =L5 -> 15762.846 | M6: {=SUMPRODUCT(IF(A6:A60=H6,E6:E60),IF(A6:A60=H6,F6:F60))} -> 1225959 | N6: =M6/(J6*10^6*K6) -> 0.0040481
A7: Hot & Humid | B7: HA13 Widen Zone Temperature Deadband, Add Conference Room Standby Control (Upgrade To DDC Zone Control) | C7: 0.093 | D7: =MIN(1,1-C7) -> 0.907 | E7: 213808 | F7: 1
A8: Hot & Dry | B8: HA13 Widen Zone Temperature Deadband, Add Conference Room Standby Control (Upgrade To DDC Zone Control) | C8: 0.103 | D8: =MIN(1,1-C8) -> 0.897 | E8: 215730 | F8: 1 | J8: Cost per BTU Saved | K8: =SUMPRODUCT(I2:I6,N2:N6) -> 0.0030161597
A9: Marine | B9: HA13 Widen Zone Temperature Deadband, Add Conference Room Standby Control (Upgrade To DDC Zone Control) | C9: 0.106 | D9: =MIN(1,1-C9) -> 0.894 | E9: 223420 | F9: 1 | J9: Average reduction in building energy use (%) | K9: =SUMPRODUCT(I2:I6,K2:K6) -> 0.29648667
A10: Cold | B10: HA13 Widen Zone Temperature Deadband, Add Conference Room Standby Control (Upgrade To DDC Zone Control) | C10: 0.091 | D10: =MIN(1,1-C10) -> 0.909 | E10: 211458 | F10: 1 | J10: Share of commercial bldg energy use for space heating and cooling (ignoring non-appliance plug loads and "other") | K10: =SUM('AEO 2019_Table 5'!D61:D62,'AEO 2019_Table 5'!D64)/SUM('AEO 2019_Table 5'!D61:D67) -> 0.58842711
A11: Very Cold | B11: HA13 Widen Zone Temperature Deadband, Add Conference Room Standby Control (Upgrade To DDC Zone Control) | C11: 0.079 | D11: =MIN(1,1-C11) -> 0.921 | E11: 210604 | F11: 1 | J11: Perc reduction heating and cooling energy use | K11: =K9/K10 -> 0.50386304
A12: Hot & Humid | B12: HA14 Lower VAV Box Minimum Flow Setpoints, Reset Duct Static Pressure (Upgrade to DDC Zone Control) | C12: 0.117 | D12: =MIN(1,1-C12) -> 0.883 | E12: 226887 | F12: 1
A13: Hot & Dry | B13: HA14 Lower VAV Box Minimum Flow Setpoints, Reset Duct Static Pressure (Upgrade to DDC Zone Control) | C13: 0.131 | D13: =MIN(1,1-C13) -> 0.869 | E13: 228917 | F13: 1
A14: Marine | B14: HA14 Lower VAV Box Minimum Flow Setpoints, Reset Duct Static Pressure (Upgrade to DDC Zone Control) | C14: 0.119 | D14: =MIN(1,1-C14) -> 0.881 | E14: 237086 | F14: 1
A15: Cold | B15: HA14 Lower VAV Box Minimum Flow Setpoints, Reset Duct Static Pressure (Upgrade to DDC Zone Control) | C15: 0.1 | D15: =MIN(1,1-C15) -> 0.9 | E15: 224393 | F15: 1
A16: Very Cold | B16: HA14 Lower VAV Box Minimum Flow Setpoints, Reset Duct Static Pressure (Upgrade to DDC Zone Control) | C16: 0.085 | D16: =MIN(1,1-C16) -> 0.915 | E16: 223487 | F16: 1
A17: Hot & Humid | B17: HA15 Add Demand Controlled Ventilation | C17: 0.006 | D17: =MIN(1,1-C17) -> 0.994 | E17: 233036 | F17: 1
A18: Hot & Dry | B18: HA15 Add Demand Controlled Ventilation | C18: 0.006 | D18: =MIN(1,1-C18) -> 0.994 | E18: 300659 | F18: 1
A19: Marine | B19: HA15 Add Demand Controlled Ventilation | C19: 0 | D19: =MIN(1,1-C19) -> 1 | E19: 285784 | F19: 1
A20: Cold | B20: HA15 Add Demand Controlled Ventilation | C20: 0.002 | D20: =MIN(1,1-C20) -> 0.998 | E20: 345387 | F20: 1
A21: Very Cold | B21: HA15 Add Demand Controlled Ventilation | C21: 0.007 | D21: =MIN(1,1-C21) -> 0.993 | E21: 300332 | F21: 1
A22: Hot & Humid | B22: HA16 Replace Supply Fan Motor and VFD | C22: 0.027 | D22: =MIN(1,1-C22) -> 0.973 | E22: 42490 | F22: 1
A23: Hot & Dry | B23: HA16 Replace Supply Fan Motor and VFD | C23: 0.034 | D23: =MIN(1,1-C23) -> 0.966 | E23: 45189 | F23: 1
... A56: Very Cold | B56: HW15 Replace Boiler Burners with Modulating Burners | C56: 0.004 | D56: =MIN(1,1-C56) -> 0.996 | E56: 48119 | F56: 1

Sheet County Climates
A1: State Abbrev | B1: State | C1: County | D1: Climate | E1: Division | F1: Total Floor Space (million) | K1: Count of County | L1: Column Labels
A2: AL | B2: Alabama | C2: Autauga | D2: Hot-Humid | E2: =INDEX('State Codes'!$E$7:$E$70,MATCH(INDEX('State Codes'!$C$7:$C$70,MATCH('County Climates'!B2,'State Codes'!$D$7:$D$70,0),1),'State Codes'!$C$7:$C$70,0),1) -> East South Central Division | F2: =INDEX('CBECS_Table B5'!$C$6:$K$6,1,MATCH('County Climates'!E2,'CBECS_Table B5'!$C$1:$K$1,0)) -> 4904 | K2: Row Labels | L2: Cold | M2: Hot-Dry | N2: Hot-Humid | O2: Marine | P2: Mixed-Dry | Q2: Mixed-Humid | R2: Subarctic | S2: Very Cold | U2: Total Floor Area
A3: AL | B3: Alabama | C3: Baldwin | D3: Hot-Humid | E3: =INDEX('State Codes'!$E$7:$E$70,MATCH(INDEX('State Codes'!$C$7:$C$70,MATCH('County Climates'!B3,'State Codes'!$D$7:$D$70,0),1),'State Codes'!$C$7:$C$70,0),1) -> East South Central Division | F3: =INDEX('CBECS_Table B5'!$C$6:$K$6,1,MATCH('County Climates'!E3,'CBECS_Table B5'!$C$1:$K$1,0)) -> 4904 | K3: East North Central Division | L3: 0.76659039 | M3: 0 | N3: 0 | O3: 0 | P3: 0 | Q3: 0.17620137 | R3: 0 | S3: 0.057208238 | U3: =INDEX('CBECS_Table B5'!$C$6:$K$6,1,MATCH('County Climates'!K3,'CBECS_Table B5'!$C$1:$K$1,0)) -> 12742
A4: AL | B4: Alabama | C4: Barbour | D4: Hot-Humid | E4: =INDEX('State Codes'!$E$7:$E$70,MATCH(INDEX('State Codes'!$C$7:$C$70,MATCH('County Climates'!B4,'State Codes'!$D$7:$D$70,0),1),'State Codes'!$C$7:$C$70,0),1) -> East South Central Division | F4: =INDEX('CBECS_Table B5'!$C$6:$K$6,1,MATCH('County Climates'!E4,'CBECS_Table B5'!$C$1:$K$1,0)) -> 4904 | K4: East South Central Division | L4: 0 | M4: 0 | N4: 0.1510989 | O4: 0 | P4: 0 | Q4: 0.8489011 | R4: 0 | S4: 0 | U4: =INDEX('CBECS_Table B5'!$C$6:$K$6,1,MATCH('County Climates'!K4,'CBECS_Table B5'!$C$1:$K$1,0)) -> 4904
A5: AL | B5: Alabama | C5: Bibb | D5: Mixed-Humid | E5: =INDEX('State Codes'!$E$7:$E$70,MATCH(INDEX('State Codes'!$C$7:$C$70,MATCH('County Climates'!B5,'State Codes'!$D$7:$D$70,0),1),'State Codes'!$C$7:$C$70,0),1) -> East South Central Division | F5: =INDEX('CBECS_Table B5'!$C$6:$K$6,1,MATCH('County Climates'!E5,'CBECS_Table B5'!$C$1:$K$1,0)) -> 4904 | K5: Middle Atlantic Division | L5: 0.82 | M5: 0 | N5: 0 | O5: 0 | P5: 0 | Q5: 0.18 | R5: 0 | S5: 0 | U5: =INDEX('CBECS_Table B5'!$C$6:$K$6,1,MATCH('County Climates'!K5,'CBECS_Table B5'!$C$1:$K$1,0)) -> 11232
A6: AL | B6: Alabama | C6: Blount | D6: Mixed-Humid | E6: =INDEX('State Codes'!$E$7:$E$70,MATCH(INDEX('State Codes'!$C$7:$C$70,MATCH('County Climates'!B6,'State Codes'!$D$7:$D$70,0),1),'State Codes'!$C$7:$C$70,0),1) -> East South Central Division | F6: =INDEX('CBECS_Table B5'!$C$6:$K$6,1,MATCH('County Climates'!E6,'CBECS_Table B5'!$C$1:$K$1,0)) -> 4904 | K6: Mountain Division | L6: 0.81494662 | M6: 0.067615658 | N6: 0 | O6: 0 | P6: 0.060498221 | Q6: 0 | R6: 0 | S6: 0.056939502 | U6: =INDEX('CBECS_Table B5'!$C$6:$K$6,1,MATCH('County Climates'!K6,'CBECS_Table B5'!$C$1:$K$1,0)) -> 4981
A7: AL | B7: Alabama | C7: Bullock | D7: Hot-Humid | E7: =INDEX('State Codes'!$E$7:$E$70,MATCH(INDEX('State Codes'!$C$7:$C$70,MATCH('County Climates'!B7,'State Codes'!$D$7:$D$70,0),1),'State Codes'!$C$7:$C$70,0),1) -> East South Central Division | F7: =INDEX('CBECS_Table B5'!$C$6:$K$6,1,MATCH('County Climates'!E7,'CBECS_Table B5'!$C$1:$K$1,0)) -> 4904 | K7: New England Division | L7: 0.98507463 | M7: 0 | N7: 0 | O7: 0 | P7: 0 | Q7: 0 | R7: 0 | S7: 0.014925373 | U7: =INDEX('CBECS_Table B5'!$C$6:$K$6,1,MATCH('County Climates'!K7,'CBECS_Table B5'!$C$1:$K$1,0)) -> 4302
A8: AL | B8: Alabama | C8: Butler | D8: Hot-Humid | E8: =INDEX('State Codes'!$E$7:$E$70,MATCH(INDEX('State Codes'!$C$7:$C$70,MATCH('County Climates'!B8,'State Codes'!$D$7:$D$70,0),1),'State Codes'!$C$7:$C$70,0),1) -> East South Central Division | F8: =INDEX('CBECS_Table B5'!$C$6:$K$6,1,MATCH('County Climates'!E8,'CBECS_Table B5'!$C$1:$K$1,0)) -> 4904 | K8: Pacific Division | L8: 0.29878049 | M8: 0.15853659 | N8: 0.030487805 | O8: 0.30487805 | P8: 0.048780488 | Q8: 0 | R8: 0.054878049 | S8: 0.10365854 | U8: =INDEX('CBECS_Table B5'!$C$6:$K$6,1,MATCH('County Climates'!K8,'CBECS_Table B5'!$C$1:$K$1,0)) -> 13379
A9: AL | B9: Alabama | C9: Calhoun | D9: Mixed-Humid | E9: =INDEX('State Codes'!$E$7:$E$70,MATCH(INDEX('State Codes'!$C$7:$C$70,MATCH('County Climates'!B9,'State Codes'!$D$7:$D$70,0),1),'State Codes'!$C$7:$C$70,0),1) -> East South Central Division | F9: =INDEX('CBECS_Table B5'!$C$6:$K$6,1,MATCH('County Climates'!E9,'CBECS_Table B5'!$C$1:$K$1,0)) -> 4904 | K9: South Atlantic Division | L9: 0.05942275 | M9: 0 | N9: 0.27504244 | O9: 0 | P9: 0 | Q9: 0.6655348 | R9: 0 | S9: 0 | U9: =INDEX('CBECS_Table B5'!$C$6:$K$6,1,MATCH('County Climates'!K9,'CBECS_Table B5'!$C$1:$K$1,0)) -> 17981
A10: AL | B10: Alabama | C10: Chambers | D10: Mixed-Humid | E10: =INDEX('State Codes'!$E$7:$E$70,MATCH(INDEX('State Codes'!$C$7:$C$70,MATCH('County Climates'!B10,'State Codes'!$D$7:$D$70,0),1),'State Codes'!$C$7:$C$70,0),1) -> East South Central Division | F10: =INDEX('CBECS_Table B5'!$C$6:$K$6,1,MATCH('County Climates'!E10,'CBECS_Table B5'!$C$1:$K$1,0)) -> 4904 | K10: West North Central Division | L10: 0.63915858 | M10: 0 | N10: 0 | O10: 0 | P10: 0 | Q10: 0.26375405 | R10: 0 | S10: 0.097087379 | U10: =INDEX('CBECS_Table B5'!$C$6:$K$6,1,MATCH('County Climates'!K10,'CBECS_Table B5'!$C$1:$K$1,0)) -> 6178
A11: AL | B11: Alabama | C11: Cherokee | D11: Mixed-Humid | E11: =INDEX('State Codes'!$E$7:$E$70,MATCH(INDEX('State Codes'!$C$7:$C$70,MATCH('County Climates'!B11,'State Codes'!$D$7:$D$70,0),1),'State Codes'!$C$7:$C$70,0),1) -> East South Central Division | F11: =INDEX('CBECS_Table B5'!$C$6:$K$6,1,MATCH('County Climates'!E11,'CBECS_Table B5'!$C$1:$K$1,0)) -> 4904 | K11: West South Central Division | L11: 0 | M11: 0.14893617 | N11: 0.44468085 | O11: 0 | P11: 0.065957447 | Q11: 0.34042553 | R11: 0 | S11: 0 | U11: =INDEX('CBECS_Table B5'!$C$6:$K$6,1,MATCH('County Climates'!K11,'CBECS_Table B5'!$C$1:$K$1,0)) -> 11394
A12: AL | B12: Alabama | C12: Chilton | D12: Mixed-Humid | E12: =INDEX('State Codes'!$E$7:$E$70,MATCH(INDEX('State Codes'!$C$7:$C$70,MATCH('County Climates'!B12,'State Codes'!$D$7:$D$70,0),1),'State Codes'!$C$7:$C$70,0),1) -> East South Central Division | F12: =INDEX('CBECS_Table B5'!$C$6:$K$6,1,MATCH('County Climates'!E12,'CBECS_Table B5'!$C$1:$K$1,0)) -> 4904
A13: AL | B13: Alabama | C13: Choctaw | D13: Hot-Humid | E13: =INDEX('State Codes'!$E$7:$E$70,MATCH(INDEX('State Codes'!$C$7:$C$70,MATCH('County Climates'!B13,'State Codes'!$D$7:$D$70,0),1),'State Codes'!$C$7:$C$70,0),1) -> East South Central Division | F13: =INDEX('CBECS_Table B5'!$C$6:$K$6,1,MATCH('County Climates'!E13,'CBECS_Table B5'!$C$1:$K$1,0)) -> 4904
A14: AL | B14: Alabama | C14: Clarke | D14: Hot-Humid | E14: =INDEX('State Codes'!$E$7:$E$70,MATCH(INDEX('State Codes'!$C$7:$C$70,MATCH('County Climates'!B14,'State Codes'!$D$7:$D$70,0),1),'State Codes'!$C$7:$C$70,0),1) -> East South Central Division | F14: =INDEX('CBECS_Table B5'!$C$6:$K$6,1,MATCH('County Climates'!E14,'CBECS_Table B5'!$C$1:$K$1,0)) -> 4904 | K14: Region | L14: Total Floor Area
A15: AL | B15: Alabama | C15: Clay | D15: Mixed-Humid | E15: =INDEX('State Codes'!$E$7:$E$70,MATCH(INDEX('State Codes'!$C$7:$C$70,MATCH('County Climates'!B15,'State Codes'!$D$7:$D$70,0),1),'State Codes'!$C$7:$C$70,0),1) -> East South Central Division | F15: =INDEX('CBECS_Table B5'!$C$6:$K$6,1,MATCH('County Climates'!E15,'CBECS_Table B5'!$C$1:$K$1,0)) -> 4904 | L15: Cold | M15: Hot-Dry | N15: Hot-Humid | O15: Marine | P15: Mixed-Dry | Q15: Mixed-Humid | R15: Subarctic | S15: Very Cold
A16: AL | B16: Alabama | C16: Cleburne | D16: Mixed-Humid | E16: =INDEX('State Codes'!$E$7:$E$70,MATCH(INDEX('State Codes'!$C$7:$C$70,MATCH('County Climates'!B16,'State Codes'!$D$7:$D$70,0),1),'State Codes'!$C$7:$C$70,0),1) -> East South Central Division | F16: =INDEX('CBECS_Table B5'!$C$6:$K$6,1,MATCH('County Climates'!E16,'CBECS_Table B5'!$C$1:$K$1,0)) -> 4904 | K16: East North Central Division | L16: =L3*$U3*10^6 -> 9.7678947e+09 | M16: =M3*$U3*10^6 -> 0 | N16: =N3*$U3*10^6 -> 0 | O16: =O3*$U3*10^6 -> 0 | P16: =P3*$U3*10^6 -> 0 | Q16: =Q3*$U3*10^6 -> 2.2451579e+09 | R16: =R3*$U3*10^6 -> 0 | S16: =S3*$U3*10^6 -> 7.2894737e+08
A17: AL | B17: Alabama | C17: Coffee | D17: Hot-Humid | E17: =INDEX('State Codes'!$E$7:$E$70,MATCH(INDEX('State Codes'!$C$7:$C$70,MATCH('County Climates'!B17,'State Codes'!$D$7:$D$70,0),1),'State Codes'!$C$7:$C$70,0),1) -> East South Central Division | F17: =INDEX('CBECS_Table B5'!$C$6:$K$6,1,MATCH('County Climates'!E17,'CBECS_Table B5'!$C$1:$K$1,0)) -> 4904 | K17: East South Central Division | L17: =L4*$U4*10^6 -> 0 | M17: =M4*$U4*10^6 -> 0 | N17: =N4*$U4*10^6 -> 7.4098901e+08 | O17: =O4*$U4*10^6 -> 0 | P17: =P4*$U4*10^6 -> 0 | Q17: =Q4*$U4*10^6 -> 4.163011e+09 | R17: =R4*$U4*10^6 -> 0 | S17: =S4*$U4*10^6 -> 0
A18: AL | B18: Alabama | C18: Colbert | D18: Mixed-Humid | E18: =INDEX('State Codes'!$E$7:$E$70,MATCH(INDEX('State Codes'!$C$7:$C$70,MATCH('County Climates'!B18,'State Codes'!$D$7:$D$70,0),1),'State Codes'!$C$7:$C$70,0),1) -> East South Central Division | F18: =INDEX('CBECS_Table B5'!$C$6:$K$6,1,MATCH('County Climates'!E18,'CBECS_Table B5'!$C$1:$K$1,0)) -> 4904 | K18: Middle Atlantic Division | L18: =L5*$U5*10^6 -> 9210240000 | M18: =M5*$U5*10^6 -> 0 | N18: =N5*$U5*10^6 -> 0 | O18: =O5*$U5*10^6 -> 0 | P18: =P5*$U5*10^6 -> 0 | Q18: =Q5*$U5*10^6 -> 2021760000 | R18: =R5*$U5*10^6 -> 0 | S18: =S5*$U5*10^6 -> 0
A19: AL | B19: Alabama | C19: Conecuh | D19: Hot-Humid | E19: =INDEX('State Codes'!$E$7:$E$70,MATCH(INDEX('State Codes'!$C$7:$C$70,MATCH('County Climates'!B19,'State Codes'!$D$7:$D$70,0),1),'State Codes'!$C$7:$C$70,0),1) -> East South Central Division | F19: =INDEX('CBECS_Table B5'!$C$6:$K$6,1,MATCH('County Climates'!E19,'CBECS_Table B5'!$C$1:$K$1,0)) -> 4904 | K19: Mountain Division | L19: =L6*$U6*10^6 -> 4.0592491e+09 | M19: =M6*$U6*10^6 -> 3.3679359e+08 | N19: =N6*$U6*10^6 -> 0 | O19: =O6*$U6*10^6 -> 0 | P19: =P6*$U6*10^6 -> 3.0134164e+08 | Q19: =Q6*$U6*10^6 -> 0 | R19: =R6*$U6*10^6 -> 0 | S19: =S6*$U6*10^6 -> 2.8361566e+08
A20: AL | B20: Alabama | C20: Coosa | D20: Mixed-Humid | E20: =INDEX('State Codes'!$E$7:$E$70,MATCH(INDEX('State Codes'!$C$7:$C$70,MATCH('County Climates'!B20,'State Codes'!$D$7:$D$70,0),1),'State Codes'!$C$7:$C$70,0),1) -> East South Central Division | F20: =INDEX('CBECS_Table B5'!$C$6:$K$6,1,MATCH('County Climates'!E20,'CBECS_Table B5'!$C$1:$K$1,0)) -> 4904 | K20: New England Division | L20: =L7*$U7*10^6 -> 4.237791e+09 | M20: =M7*$U7*10^6 -> 0 | N20: =N7*$U7*10^6 -> 0 | O20: =O7*$U7*10^6 -> 0 | P20: =P7*$U7*10^6 -> 0 | Q20: =Q7*$U7*10^6 -> 0 | R20: =R7*$U7*10^6 -> 0 | S20: =S7*$U7*10^6 -> 64208955
A21: AL | B21: Alabama | C21: Covington | D21: Hot-Humid | E21: =INDEX('State Codes'!$E$7:$E$70,MATCH(INDEX('State Codes'!$C$7:$C$70,MATCH('County Climates'!B21,'State Codes'!$D$7:$D$70,0),1),'State Codes'!$C$7:$C$70,0),1) -> East South Central Division | F21: =INDEX('CBECS_Table B5'!$C$6:$K$6,1,MATCH('County Climates'!E21,'CBECS_Table B5'!$C$1:$K$1,0)) -> 4904 | K21: Pacific Division | L21: =L8*$U8*10^6 -> 3.9973841e+09 | M21: =M8*$U8*10^6 -> 2.121061e+09 | N21: =N8*$U8*10^6 -> 4.0789634e+08 | O21: =O8*$U8*10^6 -> 4.0789634e+09 | P21: =P8*$U8*10^6 -> 6.5263415e+08 | Q21: =Q8*$U8*10^6 -> 0 | R21: =R8*$U8*10^6 -> 7.3421341e+08 | S21: =S8*$U8*10^6 -> 1.3868476e+09
A22: AL | B22: Alabama | C22: Crenshaw | D22: Hot-Humid | E22: =INDEX('State Codes'!$E$7:$E$70,MATCH(INDEX('State Codes'!$C$7:$C$70,MATCH('County Climates'!B22,'State Codes'!$D$7:$D$70,0),1),'State Codes'!$C$7:$C$70,0),1) -> East South Central Division | F22: =INDEX('CBECS_Table B5'!$C$6:$K$6,1,MATCH('County Climates'!E22,'CBECS_Table B5'!$C$1:$K$1,0)) -> 4904 | K22: South Atlantic Division | L22: =L9*$U9*10^6 -> 1.0684805e+09 | M22: =M9*$U9*10^6 -> 0 | N22: =N9*$U9*10^6 -> 4.9455382e+09 | O22: =O9*$U9*10^6 -> 0 | P22: =P9*$U9*10^6 -> 0 | Q22: =Q9*$U9*10^6 -> 1.1966981e+10 | R22: =R9*$U9*10^6 -> 0 | S22: =S9*$U9*10^6 -> 0
A23: AL | B23: Alabama | C23: Cullman | D23: Mixed-Humid | E23: =INDEX('State Codes'!$E$7:$E$70,MATCH(INDEX('State Codes'!$C$7:$C$70,MATCH('County Climates'!B23,'State Codes'!$D$7:$D$70,0),1),'State Codes'!$C$7:$C$70,0),1) -> East South Central Division | F23: =INDEX('CBECS_Table B5'!$C$6:$K$6,1,MATCH('County Climates'!E23,'CBECS_Table B5'!$C$1:$K$1,0)) -> 4904 | K23: West North Central Division | L23: =L10*$U10*10^6 -> 3.9487217e+09 | M23: =M10*$U10*10^6 -> 0 | N23: =N10*$U10*10^6 -> 0 | O23: =O10*$U10*10^6 -> 0 | P23: =P10*$U10*10^6 -> 0 | Q23: =Q10*$U10*10^6 -> 1.6294725e+09 | R23: =R10*$U10*10^6 -> 0 | S23: =S10*$U10*10^6 -> 5.9980583e+08
A24: AL | B24: Alabama | C24: Dale | D24: Hot-Humid | E24: =INDEX('State Codes'!$E$7:$E$70,MATCH(INDEX('State Codes'!$C$7:$C$70,MATCH('County Climates'!B24,'State Codes'!$D$7:$D$70,0),1),'State Codes'!$C$7:$C$70,0),1) -> East South Central Division | F24: =INDEX('CBECS_Table B5'!$C$6:$K$6,1,MATCH('County Climates'!E24,'CBECS_Table B5'!$C$1:$K$1,0)) -> 4904 | K24: West South Central Division | L24: =L11*$U11*10^6 -> 0 | M24: =M11*$U11*10^6 -> 1.6969787e+09 | N24: =N11*$U11*10^6 -> 5.0666936e+09 | O24: =O11*$U11*10^6 -> 0 | P24: =P11*$U11*10^6 -> 7.5151915e+08 | Q24: =Q11*$U11*10^6 -> 3.8788085e+09 | R24: =R11*$U11*10^6 -> 0 | S24: =S11*$U11*10^6 -> 0
A25: AL | B25: Alabama | C25: Dallas | D25: Hot-Humid | E25: =INDEX('State Codes'!$E$7:$E$70,MATCH(INDEX('State Codes'!$C$7:$C$70,MATCH('County Climates'!B25,'State Codes'!$D$7:$D$70,0),1),'State Codes'!$C$7:$C$70,0),1) -> East South Central Division | F25: =INDEX('CBECS_Table B5'!$C$6:$K$6,1,MATCH('County Climates'!E25,'CBECS_Table B5'!$C$1:$K$1,0)) -> 4904 | K25: Total | L25: =SUM(L16:L24) -> 3.6289761e+10 | M25: =SUM(M16:M24) -> 4.1548333e+09 | N25: =SUM(N16:N24) -> 1.1161117e+10 | O25: =SUM(O16:O24) -> 4.0789634e+09 | P25: =SUM(P16:P24) -> 1.7054949e+09 | Q25: =SUM(Q16:Q24) -> 2.5905191e+10 | R25: =SUM(R16:R24) -> 7.3421341e+08 | S25: =SUM(S16:S24) -> 3.0634254e+09
A26: AL | B26: Alabama | C26: DeKalb | D26: Mixed-Humid | E26: =INDEX('State Codes'!$E$7:$E$70,MATCH(INDEX('State Codes'!$C$7:$C$70,MATCH('County Climates'!B26,'State Codes'!$D$7:$D$70,0),1),'State Codes'!$C$7:$C$70,0),1) -> East South Central Division | F26: =INDEX('CBECS_Table B5'!$C$6:$K$6,1,MATCH('County Climates'!E26,'CBECS_Table B5'!$C$1:$K$1,0)) -> 4904
A27: AL | B27: Alabama | C27: Elmore | D27: Hot-Humid | E27: =INDEX('State Codes'!$E$7:$E$70,MATCH(INDEX('State Codes'!$C$7:$C$70,MATCH('County Climates'!B27,'State Codes'!$D$7:$D$70,0),1),'State Codes'!$C$7:$C$70,0),1) -> East South Central Division | F27: =INDEX('CBECS_Table B5'!$C$6:$K$6,1,MATCH('County Climates'!E27,'CBECS_Table B5'!$C$1:$K$1,0)) -> 4904 | L27: Share of Floorspace
A28: AL | B28: Alabama | C28: Escambia | D28: Hot-Humid | E28: =INDEX('State Codes'!$E$7:$E$70,MATCH(INDEX('State Codes'!$C$7:$C$70,MATCH('County Climates'!B28,'State Codes'!$D$7:$D$70,0),1),'State Codes'!$C$7:$C$70,0),1) -> East South Central Division | F28: =INDEX('CBECS_Table B5'!$C$6:$K$6,1,MATCH('County Climates'!E28,'CBECS_Table B5'!$C$1:$K$1,0)) -> 4904 | K28: Cold | L28: =SUMIF($L$15:$S$15,K28,$L$25:$S$25)/SUM($L$25:$S$25) -> 0.41667828
A29: AL | B29: Alabama | C29: Etowah | D29: Mixed-Humid | E29: =INDEX('State Codes'!$E$7:$E$70,MATCH(INDEX('State Codes'!$C$7:$C$70,MATCH('County Climates'!B29,'State Codes'!$D$7:$D$70,0),1),'State Codes'!$C$7:$C$70,0),1) -> East South Central Division | F29: =INDEX('CBECS_Table B5'!$C$6:$K$6,1,MATCH('County Climates'!E29,'CBECS_Table B5'!$C$1:$K$1,0)) -> 4904 | K29: Hot-Dry | L29: =SUMIF($L$15:$S$15,K29,$L$25:$S$25)/SUM($L$25:$S$25) -> 0.047705709
A30: AL | B30: Alabama | C30: Fayette | D30: Mixed-Humid | E30: =INDEX('State Codes'!$E$7:$E$70,MATCH(INDEX('State Codes'!$C$7:$C$70,MATCH('County Climates'!B30,'State Codes'!$D$7:$D$70,0),1),'State Codes'!$C$7:$C$70,0),1) -> East South Central Division | F30: =INDEX('CBECS_Table B5'!$C$6:$K$6,1,MATCH('County Climates'!E30,'CBECS_Table B5'!$C$1:$K$1,0)) -> 4904 | K30: Hot-Humid | L30: =SUMIF($L$15:$S$15,K30,$L$25:$S$25)/SUM($L$25:$S$25) -> 0.12815171
A31: AL | B31: Alabama | C31: Franklin | D31: Mixed-Humid | E31: =INDEX('State Codes'!$E$7:$E$70,MATCH(INDEX('State Codes'!$C$7:$C$70,MATCH('County Climates'!B31,'State Codes'!$D$7:$D$70,0),1),'State Codes'!$C$7:$C$70,0),1) -> East South Central Division | F31: =INDEX('CBECS_Table B5'!$C$6:$K$6,1,MATCH('County Climates'!E31,'CBECS_Table B5'!$C$1:$K$1,0)) -> 4904 | K31: Marine | L31: =SUMIF($L$15:$S$15,K31,$L$25:$S$25)/SUM($L$25:$S$25) -> 0.046834572
A32: AL | B32: Alabama | C32: Geneva | D32: Hot-Humid | E32: =INDEX('State Codes'!$E$7:$E$70,MATCH(INDEX('State Codes'!$C$7:$C$70,MATCH('County Climates'!B32,'State Codes'!$D$7:$D$70,0),1),'State Codes'!$C$7:$C$70,0),1) -> East South Central Division | F32: =INDEX('CBECS_Table B5'!$C$6:$K$6,1,MATCH('County Climates'!E32,'CBECS_Table B5'!$C$1:$K$1,0)) -> 4904 | K32: Mixed-Dry | L32: =SUMIF($L$15:$S$15,K32,$L$25:$S$25)/SUM($L$25:$S$25) -> 0.019582457
A33: AL | B33: Alabama | C33: Greene | D33: Mixed-Humid | E33: =INDEX('State Codes'!$E$7:$E$70,MATCH(INDEX('State Codes'!$C$7:$C$70,MATCH('County Climates'!B33,'State Codes'!$D$7:$D$70,0),1),'State Codes'!$C$7:$C$70,0),1) -> East South Central Division | F33: =INDEX('CBECS_Table B5'!$C$6:$K$6,1,MATCH('County Climates'!E33,'CBECS_Table B5'!$C$1:$K$1,0)) -> 4904 | K33: Mixed-Humid | L33: =SUMIF($L$15:$S$15,K33,$L$25:$S$25)/SUM($L$25:$S$25) -> 0.29744286
A34: AL | B34: Alabama | C34: Hale | D34: Mixed-Humid | E34: =INDEX('State Codes'!$E$7:$E$70,MATCH(INDEX('State Codes'!$C$7:$C$70,MATCH('County Climates'!B34,'State Codes'!$D$7:$D$70,0),1),'State Codes'!$C$7:$C$70,0),1) -> East South Central Division | F34: =INDEX('CBECS_Table B5'!$C$6:$K$6,1,MATCH('County Climates'!E34,'CBECS_Table B5'!$C$1:$K$1,0)) -> 4904 | K34: Subarctic | L34: =SUMIF($L$15:$S$15,K34,$L$25:$S$25)/SUM($L$25:$S$25) -> 0.008430223
A35: AL | B35: Alabama | C35: Henry | D35: Hot-Humid | E35: =INDEX('State Codes'!$E$7:$E$70,MATCH(INDEX('State Codes'!$C$7:$C$70,MATCH('County Climates'!B35,'State Codes'!$D$7:$D$70,0),1),'State Codes'!$C$7:$C$70,0),1) -> East South Central Division | F35: =INDEX('CBECS_Table B5'!$C$6:$K$6,1,MATCH('County Climates'!E35,'CBECS_Table B5'!$C$1:$K$1,0)) -> 4904 | K35: Very Cold | L35: =SUMIF($L$15:$S$15,K35,$L$25:$S$25)/SUM($L$25:$S$25) -> 0.035174186
A36: AL | B36: Alabama | C36: Houston | D36: Hot-Humid | E36: =INDEX('State Codes'!$E$7:$E$70,MATCH(INDEX('State Codes'!$C$7:$C$70,MATCH('County Climates'!B36,'State Codes'!$D$7:$D$70,0),1),'State Codes'!$C$7:$C$70,0),1) -> East South Central Division | F36: =INDEX('CBECS_Table B5'!$C$6:$K$6,1,MATCH('County Climates'!E36,'CBECS_Table B5'!$C$1:$K$1,0)) -> 4904
A37: AL | B37: Alabama | C37: Jackson | D37: Mixed-Humid | E37: =INDEX('State Codes'!$E$7:$E$70,MATCH(INDEX('State Codes'!$C$7:$C$70,MATCH('County Climates'!B37,'State Codes'!$D$7:$D$70,0),1),'State Codes'!$C$7:$C$70,0),1) -> East South Central Division | F37: =INDEX('CBECS_Table B5'!$C$6:$K$6,1,MATCH('County Climates'!E37,'CBECS_Table B5'!$C$1:$K$1,0)) -> 4904
A38: AL | B38: Alabama | C38: Jefferson | D38: Mixed-Humid | E38: =INDEX('State Codes'!$E$7:$E$70,MATCH(INDEX('State Codes'!$C$7:$C$70,MATCH('County Climates'!B38,'State Codes'!$D$7:$D$70,0),1),'State Codes'!$C$7:$C$70,0),1) -> East South Central Division | F38: =INDEX('CBECS_Table B5'!$C$6:$K$6,1,MATCH('County Climates'!E38,'CBECS_Table B5'!$C$1:$K$1,0)) -> 4904
A39: AL | B39: Alabama | C39: Lamar | D39: Mixed-Humid | E39: =INDEX('State Codes'!$E$7:$E$70,MATCH(INDEX('State Codes'!$C$7:$C$70,MATCH('County Climates'!B39,'State Codes'!$D$7:$D$70,0),1),'State Codes'!$C$7:$C$70,0),1) -> East South Central Division | F39: =INDEX('CBECS_Table B5'!$C$6:$K$6,1,MATCH('County Climates'!E39,'CBECS_Table B5'!$C$1:$K$1,0)) -> 4904
A40: AL | B40: Alabama | C40: Lauderdale | D40: Mixed-Humid | E40: =INDEX('State Codes'!$E$7:$E$70,MATCH(INDEX('State Codes'!$C$7:$C$70,MATCH('County Climates'!B40,'State Codes'!$D$7:$D$70,0),1),'State Codes'!$C$7:$C$70,0),1) -> East South Central Division | F40: =INDEX('CBECS_Table B5'!$C$6:$K$6,1,MATCH('County Climates'!E40,'CBECS_Table B5'!$C$1:$K$1,0)) -> 4904
A41: AL | B41: Alabama | C41: Lawrence | D41: Mixed-Humid | E41: =INDEX('State Codes'!$E$7:$E$70,MATCH(INDEX('State Codes'!$C$7:$C$70,MATCH('County Climates'!B41,'State Codes'!$D$7:$D$70,0),1),'State Codes'!$C$7:$C$70,0),1) -> East South Central Division | F41: =INDEX('CBECS_Table B5'!$C$6:$K$6,1,MATCH('County Climates'!E41,'CBECS_Table B5'!$C$1:$K$1,0)) -> 4904
A42: AL | B42: Alabama | C42: Lee | D42: Mixed-Humid | E42: =INDEX('State Codes'!$E$7:$E$70,MATCH(INDEX('State Codes'!$C$7:$C$70,MATCH('County Climates'!B42,'State Codes'!$D$7:$D$70,0),1),'State Codes'!$C$7:$C$70,0),1) -> East South Central Division | F42: =INDEX('CBECS_Table B5'!$C$6:$K$6,1,MATCH('County Climates'!E42,'CBECS_Table B5'!$C$1:$K$1,0)) -> 4904
A43: AL | B43: Alabama | C43: Limestone | D43: Mixed-Humid | E43: =INDEX('State Codes'!$E$7:$E$70,MATCH(INDEX('State Codes'!$C$7:$C$70,MATCH('County Climates'!B43,'State Codes'!$D$7:$D$70,0),1),'State Codes'!$C$7:$C$70,0),1) -> East South Central Division | F43: =INDEX('CBECS_Table B5'!$C$6:$K$6,1,MATCH('County Climates'!E43,'CBECS_Table B5'!$C$1:$K$1,0)) -> 4904
A44: AL | B44: Alabama | C44: Lowndes | D44: Hot-Humid | E44: =INDEX('State Codes'!$E$7:$E$70,MATCH(INDEX('State Codes'!$C$7:$C$70,MATCH('County Climates'!B44,'State Codes'!$D$7:$D$70,0),1),'State Codes'!$C$7:$C$70,0),1) -> East South Central Division | F44: =INDEX('CBECS_Table B5'!$C$6:$K$6,1,MATCH('County Climates'!E44,'CBECS_Table B5'!$C$1:$K$1,0)) -> 4904
A45: AL | B45: Alabama | C45: Macon | D45: Hot-Humid | E45: =INDEX('State Codes'!$E$7:$E$70,MATCH(INDEX('State Codes'!$C$7:$C$70,MATCH('County Climates'!B45,'State Codes'!$D$7:$D$70,0),1),'State Codes'!$C$7:$C$70,0),1) -> East South Central Division | F45: =INDEX('CBECS_Table B5'!$C$6:$K$6,1,MATCH('County Climates'!E45,'CBECS_Table B5'!$C$1:$K$1,0)) -> 4904
A46: AL | B46: Alabama | C46: Madison | D46: Mixed-Humid | E46: =INDEX('State Codes'!$E$7:$E$70,MATCH(INDEX('State Codes'!$C$7:$C$70,MATCH('County Climates'!B46,'State Codes'!$D$7:$D$70,0),1),'State Codes'!$C$7:$C$70,0),1) -> East South Central Division | F46: =INDEX('CBECS_Table B5'!$C$6:$K$6,1,MATCH('County Climates'!E46,'CBECS_Table B5'!$C$1:$K$1,0)) -> 4904
A47: AL | B47: Alabama | C47: Marengo | D47: Hot-Humid | E47: =INDEX('State Codes'!$E$7:$E$70,MATCH(INDEX('State Codes'!$C$7:$C$70,MATCH('County Climates'!B47,'State Codes'!$D$7:$D$70,0),1),'State Codes'!$C$7:$C$70,0),1) -> East South Central Division | F47: =INDEX('CBECS_Table B5'!$C$6:$K$6,1,MATCH('County Climates'!E47,'CBECS_Table B5'!$C$1:$K$1,0)) -> 4904
... A3141: WI | B3141: Wisconsin | C3141: Winnebago | D3141: Cold | E3141: =INDEX('State Codes'!$E$7:$E$70,MATCH(INDEX('State Codes'!$C$7:$C$70,MATCH('County Climates'!B3141,'State Codes'!$D$7:$D$70,0),1),'State Codes'!$C$7:$C$70,0),1) -> East North Central Division | F3141: =INDEX('CBECS_Table B5'!$C$6:$K$6,1,MATCH('County Climates'!E3141,'CBECS_Table B5'!$C$1:$K$1,0)) -> 12742

Sheet CBECS_Table B5
A1: Release date: February 2015 Revised date: May 2016 | C1: =C5&" Division" -> New England Division | D1: =D5&" Division" -> Middle Atlantic Division | E1: =E5&" Division" -> East North Central Division | F1: =F5&" Division" -> West North Central Division | G1: =G5&" Division" -> South Atlantic Division | H1: =H5&" Division" -> East South Central Division | I1: =I5&" Division" -> West South Central Division | J1: =J5&" Division" -> mountain Division | K1: =K5&" Division" -> Pacific Division
A2: Table B5. Census region and division, floorspace, 2012
B3: Total floorspace (million square feet)
C4: Northeast | E4: Midwest | G4: South | J4: West
B5: All buildings | C5: New England | D5: Middle Atlantic | E5: East North Central | F5: West North Central | G5: South Atlantic | H5: East South Central | I5: West South Central | J5: mountain | K5: Pacific
A6: All buildings | B6: 87093 | C6: 4302 | D6: 11232 | E6: 12742 | F6: 6178 | G6: 17981 | H6: 4904 | I6: 11394 | J6: 4981 | K6: 13379
A7: Building floorspace (square feet)
A8: 1,001 to 5,000 | B8: 8041 | C8: 405 | D8: 652 | E8: 1066 | F8: 792 | G8: 1564 | H8: 613 | I8: 1206 | J8: 528 | K8: 1216
A9: 5,001 to 10,000 | B9: 8900 | C9: 541 | D9: 707 | E9: 1062 | F9: 810 | G9: 1764 | H9: 606 | I9: 1164 | J9: 504 | K9: 1741
A10: 10,001 to 25,000 | B10: 14105 | C10: 901 | D10: 1507 | E10: 1823 | F10: 1065 | G10: 2709 | H10: 769 | I10: 1732 | J10: 990 | K10: 2609
A11: 25,001 to 50,000 | B11: 11917 | C11: 642 | D11: 1002 | E11: 2040 | F11: 989 | G11: 2273 | H11: 501 | I11: 1755 | J11: 467 | K11: 2249
A12: 50,001 to 100,000 | B12: 13918 | C12: 598 | D12: 2078 | E12: 1809 | F12: 920 | G12: 3049 | H12: 1002 | I12: 2088 | J12: 725 | K12: 1648
A13: 100,001 to 200,000 | B13: 12415 | C13: 418 | D13: 2124 | E13: 1771 | F13: 628 | G13: 2817 | H13: 578 | I13: 1756 | J13: 447 | K13: 1875
A14: 200,001 to 500,000 | B14: 10724 | C14: 597 | D14: 1636 | E14: 2129 | F14: 597 | G14: 2089 | H14: 503 | I14: 1089 | J14: 774 | K14: 1310
A15: Over 500,000 | B15: 7074 | C15: Q | D15: 1526 | E15: 1042 | F15: 376 | G15: 1715 | H15: Q | I15: 604 | J15: 546 | K15: 731
A16: Principal building activity
A17: Education | B17: 12239 | C17: 642 | D17: 1414 | E17: 2205 | F17: 968 | G17: 2840 | H17: 469 | I17: 1853 | J17: 783 | K17: 1065
A18: Food sales | B18: 1252 | C18: Q | D18: Q | E18: Q | F18: Q | G18: 188 | H18: Q | I18: Q | J18: Q | K18: 304
A19: Food service | B19: 1819 | C19: Q | D19: 162 | E19: 217 | F19: 153 | G19: 396 | H19: 150 | I19: 225 | J19: 104 | K19: 282
A20: Health care | B20: 4155 | C20: 274 | D20: 792 | E20: 549 | F20: 313 | G20: 662 | H20: 271 | I20: 508 | J20: 289 | K20: 497
A21: Inpatient | B21: 2374 | C21: 169 | D21: 369 | E21: 359 | F21: 137 | G21: 405 | H21: 184 | I21: 304 | J21: 132 | K21: 315
A22: Outpatient | B22: 1781 | C22: Q | D22: 423 | E22: 190 | F22: 176 | G22: 257 | H22: Q | I22: 204 | J22: 157 | K22: 182
A23: Lodging | B23: 5826 | C23: Q | D23: 800 | E23: 673 | F23: 384 | G23: 1217 | H23: 486 | I23: 599 | J23: 519 | K23: 940
A24: Mercantile | B24: 11330 | C24: 463 | D24: 1190 | E24: 1488 | F24: 644 | G24: 2746 | H24: 736 | I24: 1247 | J24: 727 | K24: 2088
A25: Retail (other than mall) | B25: 5439 | C25: Q | D25: 672 | E25: 748 | F25: 394 | G25: 1052 | H25: Q | I25: 693 | J25: 307 | K25: 1030
A26: Enclosed and strip malls | B26: 5890 | C26: Q | D26: 518 | E26: 740 | F26: 250 | G26: 1694 | H26: Q | I26: 554 | J26: 420 | K26: 1058
A27: Office | B27: 15952 | C27: 738 | D27: 2965 | E27: 2430 | F27: 904 | G27: 3183 | H27: 694 | I27: 1625 | J27: 852 | K27: 2562
A28: Public assembly | B28: 5559 | C28: 350 | D28: 603 | E28: 1196 | F28: 390 | G28: 904 | H28: 330 | I28: 769 | J28: 321 | K28: 697
A29: Public order and safety | B29: 1440 | C29: Q | D29: Q | E29: Q | F29: Q | G29: Q | H29: Q | I29: Q | J29: Q | K29: Q
A30: Religious worship | B30: 4557 | C30: Q | D30: 613 | E30: 547 | F30: 378 | G30: 857 | H30: 614 | I30: 540 | J30: 214 | K30: 511
A31: Service | B31: 4630 | C31: 255 | D31: 568 | E31: 847 | F31: 625 | G31: 741 | H31: 318 | I31: 583 | J31: Q | K31: 578
A32: Warehouse and storage | B32: 13077 | C32: 521 | D32: 1240 | E32: 1570 | F32: 960 | G32: 2832 | H32: Q | I32: 1919 | J32: 591 | K32: 2938
A33: Other | B33: 2002 | C33: Q | D33: Q | E33: Q | F33: Q | G33: 568 | H33: Q | I33: Q | J33: Q | K33: 345
A34: Vacant | B34: 3256 | C34: Q | D34: Q | E34: 345 | F34: 191 | G34: 546 | H34: Q | I34: 934 | J34: Q | K34: 396
A35: Year constructed
A36: Before 1920 | B36: 3983 | C36: 692 | D36: 940 | E36: 642 | F36: 398 | G36: 425 | H36: 278 | I36: 279 | J36: Q | K36: 225
A37: 1920 to 1945 | B37: 6025 | C37: 428 | D37: 1530 | E37: 1373 | F37: 396 | G37: 690 | H37: 219 | I37: 593 | J37: 144 | K37: 651
A38: 1946 to 1959 | B38: 7381 | C38: 349 | D38: 1233 | E38: 1154 | F38: 508 | G38: 1515 | H38: 268 | I38: 850 | J38: 325 | K38: 1179
A39: 1960 to 1969 | B39: 10362 | C39: 481 | D39: 1759 | E39: 1488 | F39: 1198 | G39: 1699 | H39: 699 | I39: 1101 | J39: 406 | K39: 1532
A40: 1970 to 1979 | B40: 10846 | C40: 502 | D40: 1450 | E40: 1865 | F40: 754 | G40: 1703 | H40: 555 | I40: 1435 | J40: 802 | K40: 1780
A41: 1980 to 1989 | B41: 15230 | C41: 572 | D41: 1170 | E41: 1655 | F41: 962 | G41: 3584 | H41: 940 | I41: 2419 | J41: 981 | K41: 2948
A42: 1990 to 1999 | B42: 13803 | C42: 485 | D42: 1560 | E42: 1942 | F42: 856 | G42: 2798 | H42: 1213 | I42: 2161 | J42: 804 | K42: 1984
A43: 2000 to 2003 | B43: 7215 | C43: 343 | D43: 637 | E43: 1090 | F43: 405 | G43: 1919 | H43: 208 | I43: 1187 | J43: 419 | K43: 1007
A44: 2004 to 2007 | B44: 6524 | C44: Q | D44: 267 | E44: 860 | F44: 375 | G44: 1923 | H44: 312 | I44: 605 | J44: 667 | K44: Q
A45: 2008 to 2012 | B45: 5723 | C45: 217 | D45: 685 | E45: 672 | F45: 325 | G45: 1725 | H45: 212 | I45: 765 | J45: 329 | K45: 793
A46: Number of floors
A47: One | B47: 39809 | C47: 1083 | D47: 2782 | E47: 4975 | F47: 2677 | G47: 9191 | H47: 2639 | I47: 6702 | J47: 2575 | K47: 7186
A48: Two | B48: 20206 | C48: 1281 | D48: 2816 | E48: 3206 | F48: 1661 | G48: 3825 | H48: 1084 | I48: 2063 | J48: 1153 | K48: 3116
A49: Three | B49: 8140 | C49: 965 | D49: 1456 | E49: 1708 | F49: 899 | G49: 992 | H49: 344 | I49: 692 | J49: 274 | K49: 809
A50: Four to nine | B50: 13535 | C50: 782 | D50: 2626 | E50: 2085 | F50: 829 | G50: 2913 | H50: 705 | I50: 1396 | J50: 498 | K50: 1700
A51: Ten or more | B51: 5404 | C51: Q | D51: 1552 | E51: 767 | F51: Q | G51: 1061 | H51: Q | I51: 541 | J51: Q | K51: 568
A52: Elevators and escalators (more than one may apply)
A53: Any elevators | B53: 32120 | C53: 1857 | D53: 6054 | E53: 5439 | F53: 2115 | G53: 6484 | H53: 1236 | I53: 3302 | J53: 1700 | K53: 3932
A54: Number of elevators
A55: One | B55: 11158 | C55: 944 | D55: 1636 | E55: 2252 | F55: 968 | G55: 1948 | H55: 440 | I55: 1277 | J55: 486 | K55: 1207
A56: Two to five | B56: 12817 | C56: 713 | D56: 2432 | E56: 1993 | F56: 788 | G56: 2839 | H56: 476 | I56: 1295 | J56: 563 | K56: 1718
A57: Six or more | B57: 8145 | C57: 200 | D57: 1986 | E57: 1195 | F57: 359 | G57: 1697 | H57: 320 | I57: 730 | J57: 651 | K57: 1007
A58: Any escalators | B58: 3654 | C58: Q | D58: 785 | E58: 731 | F58: Q | G58: 646 | H58: Q | I58: 283 | J58: Q | K58: 461
A59: Number of workers (main shift)
A60: Fewer than 5 | B60: 17751 | C60: 1017 | D60: 1675 | E60: 2663 | F60: 1623 | G60: 3033 | H60: 1266 | I60: 3037 | J60: 968 | K60: 2470
A61: 5 to 9 | B61: 8973 | C61: 496 | D61: 786 | E61: 1110 | F61: 800 | G61: 1751 | H61: 491 | I61: 1312 | J61: 565 | K61: 1662
A62: 10 to 19 | B62: 9623 | C62: 439 | D62: 951 | E62: 1232 | F62: 648 | G62: 1935 | H62: 573 | I62: 1307 | J62: 560 | K62: 1978
A63: 20 to 49 | B63: 14514 | C63: 546 | D63: 1358 | E63: 2270 | F63: 1102 | G63: 3001 | H63: 964 | I63: 1646 | J63: 858 | K63: 2771
A64: 50 to 99 | B64: 13476 | C64: 657 | D64: 1728 | E64: 2147 | F64: 614 | G64: 3490 | H64: 764 | I64: 1821 | J64: 597 | K64: 1657
A65: 100 to 249 | B65: 10941 | C65: 686 | D65: 1843 | E65: 1548 | F65: 766 | G65: 2622 | H65: 447 | I65: 1094 | J65: 689 | K65: 1246
A66: 250 or more | B66: 11815 | C66: 460 | D66: 2892 | E66: 1771 | F66: 626 | G66: 2150 | H66: 399 | I66: 1178 | J66: 745 | K66: 1595
A67: Weekly operating hours
A68: Fewer than 40 | B68: 8220 | C68: 392 | D68: 781 | E68: 1329 | F68: 697 | G68: 1161 | H68: 698 | I68: 1648 | J68: 564 | K68: 950
A69: 40 to 48 | B69: 15828 | C69: 830 | D69: 1531 | E69: 1988 | F69: 1060 | G69: 2901 | H69: 1269 | I69: 2618 | J69: 896 | K69: 2734
A70: 49 to 60 | B70: 20529 | C70: 910 | D70: 2435 | E70: 2736 | F70: 1636 | G70: 5097 | H70: 876 | I70: 2522 | J70: 1161 | K70: 3158
A71: 61 to 84 | B71: 15867 | C71: 984 | D71: 2329 | E71: 2591 | F71: 1037 | G71: 3459 | H71: 476 | I71: 1339 | J71: 807 | K71: 2844
A72: 85 to 167 | B72: 9395 | C72: 530 | D72: 1351 | E72: 1606 | F72: 821 | G72: 1846 | H72: 503 | I72: 789 | J72: 409 | K72: 1539
A73: Open continuously | B73: 17253 | C73: 655 | D73: 2806 | E73: 2491 | F73: 927 | G73: 3518 | H73: 1082 | I73: 2477 | J73: 1144 | K73: 2155
A74: Ownership and occupancy
A75: Nongovernment owned | B75: 67550 | C75: 3314 | D75: 8599 | E75: 9494 | F75: 4683 | G75: 14128 | H75: 3498 | I75: 8815 | J75: 3633 | K75: 11386
A76: Owner occupied | B76: 30637 | C76: 1499 | D76: 3954 | E76: 4649 | F76: 2690 | G76: 5746 | H76: 1975 | I76: 4397 | J76: 1539 | K76: 4187
A77: Leased to tenant(s) | B77: 26115 | C77: 1111 | D77: 3319 | E77: 3356 | F77: 1364 | G77: 5971 | H77: 1111 | I77: 3023 | J77: 1394 | K77: 5466
A78: Owner occupied and leased | B78: 8873 | C78: 604 | D78: 1182 | E78: 1246 | F78: 521 | G78: 2071 | H78: 330 | I78: 840 | J78: 532 | K78: 1546
A79: Unoccupied | B79: 1925 | C79: Q | D79: Q | E79: Q | F79: Q | G79: 338 | H79: Q | I79: 555 | J79: Q | K79: 187
A80: Government owned | B80: 19543 | C80: 988 | D80: 2634 | E80: 3247 | F80: 1495 | G80: 3853 | H80: 1406 | I80: 2580 | J80: 1348 | K80: 1993
A81: Federal | B81: 1573 | C81: Q | D81: Q | E81: Q | F81: Q | G81: 666 | H81: Q | I81: Q | J81: Q | K81: Q
A82: State | B82: 5539 | C82: Q | D82: 948 | E82: 780 | F82: Q | G82: 715 | H82: Q | I82: 660 | J82: 502 | K82: 620
A83: Local | B83: 12431 | C83: 752 | D83: 1461 | E83: 2262 | F83: 1048 | G83: 2472 | H83: 580 | I83: 1840 | J83: 766 | K83: 1249
A84: Party responsible for operation and maintenance of energy systems
A85: Building owner | B85: 73702 | C85: 3625 | D85: 9679 | E85: 11275 | F85: 5539 | G85: 14565 | H85: 4191 | I85: 10015 | J85: 4277 | K85: 10534
A86: Business owner or tenant | B86: 11309 | C86: 528 | D86: 1291 | E86: 1205 | F86: 518 | G86: 2840 | H86: 546 | I86: 1154 | J86: 625 | K86: 2600
A87: Property management | B87: 1250 | C87: Q | D87: Q | E87: Q | F87: Q | G87: 377 | H87: Q | I87: Q | J87: Q | K87: Q
A88: Other | B88: 832 | C88: Q | D88: Q | E88: Q | F88: Q | G88: Q | H88: Q | I88: Q | J88: Q | K88: Q
A89: Provider of direct input on energy- related equipment purchases
A90: Building owner | B90: 76271 | C90: 3714 | D90: 9853 | E90: 11466 | F90: 5693 | G90: 15171 | H90: 4330 | I90: 10301 | J90: 4490 | K90: 11252
A91: Business owner or tenant | B91: 8256 | C91: 429 | D91: 965 | E91: 917 | F91: 357 | G91: 2088 | H91: 384 | I91: 854 | J91: 394 | K91: 1869
A92: Property management | B92: 880 | C92: Q | D92: Q | E92: Q | F92: Q | G92: 215 | H92: Q | I92: Q | J92: Q | K92: Q
A93: Other | B93: 1686 | C93: Q | D93: Q | E93: Q | F93: Q | G93: 507 | H93: Q | I93: Q | J93: Q | K93: Q
A94: Number of establishments
A95: One | B95: 54994 | C95: 2724 | D95: 6803 | E95: 8202 | F95: 4301 | G95: 10895 | H95: 3293 | I95: 7554 | J95: 2972 | K95: 8250
A96: 2 to 5 | B96: 17756 | C96: 916 | D96: 2389 | E96: 2890 | F96: 1317 | G96: 3711 | H96: 1014 | I96: 1777 | J96: 1096 | K96: 2646
A97: 6 to 10 | B97: 4425 | C97: Q | D97: 611 | E97: 583 | F97: Q | G97: 1007 | H97: Q | I97: 551 | J97: Q | K97: 879
A98: 11 to 20 | B98: 3704 | C98: Q | D98: 572 | E98: 369 | F98: Q | G98: 1025 | H98: Q | I98: 397 | J98: 243 | K98: 574
A99: More than 20 | B99: 3821 | C99: Q | D99: 701 | E99: 435 | F99: Q | G99: 992 | H99: Q | I99: 316 | J99: Q | K99: 778
A100: Currently unoccupied | B100: 2393 | C100: Q | D100: Q | E100: Q | F100: Q | G100: 350 | H100: Q | I100: 798 | J100: Q | K100: 252
...

Sheet CBECS_Table B10
A1: Release date: February 2015 Revised date: May 2016
A2: Table B10. Number of floors, number of buildings and floorspace, 2012
B3: Number of buildings (thousand) | H3: Total floorspace (million square feet)
B4: All buildings | C4: One floor | D4: Two floors | E4: Three floors | F4: Four to nine floors | G4: Ten or more floors | H4: All buildings | I4: One floor | J4: Two floors | K4: Three floors | L4: Four to nine floors | M4: Ten or more floors
A5: All buildings | B5: 5557 | C5: 3836 | D5: 1158 | E5: 374 | F5: 177 | G5: 13 | H5: 87093 | I5: 39809 | J5: 20206 | K5: 8140 | L5: 13535 | M5: 5404
A6: Building floorspace (square feet)
A7: 1,001 to 5,000 | B7: 2777 | C7: 2195 | D7: 423 | E7: 137 | F7: Q | G7: N | H7: 8041 | I7: 6244 | J7: 1315 | K7: 416 | L7: Q | M7: N
A8: 5,001 to 10,000 | B8: 1229 | C8: 836 | D8: 301 | E8: 74 | F8: Q | G8: N | H8: 8900 | I8: 6044 | J8: 2181 | K8: 536 | L8: Q | M8: N
A9: 10,001 to 25,000 | B9: 884 | C9: 519 | D9: 254 | E9: 78 | F9: 32 | G9: N | H9: 14105 | I9: 8129 | J9: 4162 | K9: 1234 | L9: 581 | M9: N
A10: 25,001 to 50,000 | B10: 332 | C10: 161 | D10: 100 | E10: 46 | F10: 24 | G10: Q | H10: 11917 | I10: 5761 | J10: 3584 | K10: 1655 | L10: 906 | M10: Q
A11: 50,001 to 100,000 | B11: 199 | C11: 81 | D11: 54 | E11: 24 | F11: 39 | G11: Q | H11: 13918 | I11: 5643 | J11: 3882 | K11: 1624 | L11: 2708 | M11: Q
A12: 100,001 to 200,000 | B12: 90 | C12: 32 | D12: 18 | E12: 12 | F12: 26 | G12: 3 | H12: 12415 | I12: 4355 | J12: 2538 | K12: 1537 | L12: 3552 | M12: 433
A13: 200,001 to 500,000 | B13: 38 | C13: 10 | D13: 7 | E13: 3 | F13: 12 | G13: 6 | H13: 10724 | I13: 2630 | J13: 1915 | K13: 918 | L13: 3466 | M13: 1795
A14: Over 500,000 | B14: 8 | C14: 1 | D14: 1 | E14: Q | F14: 2 | G14: 3 | H14: 7074 | I14: 1004 | J14: 630 | K14: Q | L14: 2116 | M14: 3104
A15: Principal building activity
A16: Education | B16: 389 | C16: 266 | D16: 66 | E16: 36 | F16: 19 | G16: Q | H16: 12239 | I16: 4419 | J16: 3765 | K16: 1967 | L16: 1987 | M16: Q
A17: Food sales | B17: 177 | C17: 140 | D17: 23 | E17: Q | F17: N | G17: N | H17: 1252 | I17: 949 | J17: 223 | K17: Q | L17: N | M17: N
A18: Food service | B18: 380 | C18: 284 | D18: 60 | E18: 29 | F18: Q | G18: N | H18: 1819 | I18: 1205 | J18: 388 | K18: 162 | L18: Q | M18: N
A19: Health care | B19: 157 | C19: 92 | D19: 48 | E19: 10 | F19: 7 | G19: 1 | H19: 4155 | I19: 740 | J19: 662 | K19: 400 | L19: 1780 | M19: 574
A20: Inpatient | B20: 10 | C20: Q | D20: Q | E20: 1 | F20: 4 | G20: 1 | H20: 2374 | I20: Q | J20: Q | K20: 104 | L20: 1486 | M20: 534
A21: Outpatient | B21: 147 | C21: 89 | D21: 46 | E21: Q | F21: 2 | G21: Q | H21: 1781 | I21: 627 | J21: 523 | K21: Q | L21: 294 | M21: Q
A22: Lodging | B22: 158 | C22: 49 | D22: 53 | E22: 23 | F22: 30 | G22: 3 | H22: 5826 | I22: 697 | J22: 912 | K22: 817 | L22: 2194 | M22: 1206
A23: Mercantile | B23: 602 | C23: 441 | D23: 116 | E23: 32 | F23: Q | G23: Q | H23: 11330 | I23: 8616 | J23: 1986 | K23: 349 | L23: Q | M23: Q
A24: Retail (other than mall) | B24: 438 | C24: 303 | D24: 91 | E24: 32 | F24: Q | G24: Q | H24: 5439 | I24: 3951 | J24: 991 | K24: 279 | L24: Q | M24: Q
A25: Enclosed and strip malls | B25: 164 | C25: 138 | D25: 26 | E25: Q | F25: Q | G25: Q | H25: 5890 | I25: 4665 | J25: 995 | K25: Q | L25: Q | M25: Q
A26: Office | B26: 1012 | C26: 554 | D26: 277 | E26: 118 | F26: 56 | G26: 7 | H26: 15952 | I26: 3644 | J26: 3577 | K26: 1877 | L26: 3949 | M26: 2904
A27: Public assembly | B27: 352 | C27: 223 | D27: 87 | E27: 24 | F27: 18 | G27: Q | H27: 5559 | I27: 2097 | J27: 1209 | K27: 594 | L27: 1605 | M27: Q
A28: Public order and safety | B28: 84 | C28: 59 | D28: 17 | E28: Q | F28: Q | G28: Q | H28: 1440 | I28: 509 | J28: 293 | K28: Q | L28: Q | M28: Q
A29: Religious worship | B29: 412 | C29: 261 | D29: 125 | E29: 21 | F29: Q | G29: N | H29: 4557 | I29: 1916 | J29: 2030 | K29: 426 | L29: Q | M29: N
A30: Service | B30: 619 | C30: 495 | D30: 94 | E30: 24 | F30: Q | G30: Q | H30: 4630 | I30: 2996 | J30: 1157 | K30: 236 | L30: Q | M30: Q
A31: Warehouse and storage | B31: 796 | C31: 661 | D31: 114 | E31: 15 | F31: Q | G31: N | H31: 13077 | I31: 9153 | J31: 2925 | K31: 683 | L31: Q | M31: N
A32: Other | B32: 125 | C32: 94 | D32: 24 | E32: Q | F32: Q | G32: Q | H32: 2002 | I32: 1086 | J32: 407 | K32: Q | L32: Q | M32: Q
A33: Vacant | B33: 296 | C33: 217 | D33: 50 | E33: Q | F33: 8 | G33: Q | H33: 3256 | I33: 1782 | J33: 672 | K33: Q | L33: 544 | M33: Q
A34: Year constructed
A35: Before 1920 | B35: 362 | C35: 77 | D35: 126 | E35: 106 | F35: 51 | G35: Q | H35: 3983 | I35: 530 | J35: 856 | K35: 902 | L35: 1552 | M35: Q
A36: 1920 to 1945 | B36: 488 | C36: 240 | D36: 125 | E36: 91 | F36: 29 | G36: 2 | H36: 6025 | I36: 1550 | J36: 860 | K36: 1244 | L36: 1527 | M36: 845
A37: 1946 to 1959 | B37: 599 | C37: 419 | D37: 130 | E37: 32 | F37: 18 | G37: 1 | H37: 7381 | I37: 3194 | J37: 1926 | K37: 642 | L37: 1404 | M37: 215
A38: 1960 to 1969 | B38: 639 | C38: 423 | D38: 170 | E38: 27 | F38: 18 | G38: 2 | H38: 10362 | I38: 3969 | J38: 3192 | K38: 1070 | L38: 1364 | M38: 767
A39: 1970 to 1979 | B39: 684 | C39: 515 | D39: 136 | E39: 20 | F39: 11 | G39: 2 | H39: 10846 | I39: 4970 | J39: 3000 | K39: 700 | L39: 1332 | M39: 844
A40: 1980 to 1989 | B40: 915 | C40: 699 | D40: 171 | E40: 27 | F40: 15 | G40: 3 | H40: 15230 | I40: 7897 | J40: 3135 | K40: 996 | L40: 1899 | M40: 1303
A41: 1990 to 1999 | B41: 845 | C41: 690 | D41: 109 | E41: 31 | F41: 13 | G41: 1 | H41: 13803 | I41: 7756 | J41: 2866 | K41: 827 | L41: 1708 | M41: 646
A42: 2000 to 2003 | B42: 375 | C42: 280 | D42: 76 | E42: 14 | F42: 5 | G42: Q | H42: 7215 | I42: 3517 | J42: 1734 | K42: 656 | L42: 1150 | M42: Q
A43: 2004 to 2007 | B43: 347 | C43: 258 | D43: 74 | E43: 10 | F43: 5 | G43: Q | H43: 6524 | I43: 3505 | J43: 1500 | K43: 436 | L43: 729 | M43: Q
A44: 2008 to 2012 | B44: 303 | C44: 235 | D44: 41 | E44: 15 | F44: 11 | G44: Q | H44: 5723 | I44: 2921 | J44: 1137 | K44: 667 | L44: 871 | M44: Q
A45: Census region
A46: Northeast | B46: 805 | C46: 360 | D46: 236 | E46: 147 | F46: 60 | G46: 4 | H46: 15534 | I46: 3865 | J46: 4098 | K46: 2421 | L46: 3409 | M46: 1742
A47: Midwest | B47: 1237 | C47: 785 | D47: 296 | E47: 121 | F47: 33 | G47: 2 | H47: 18919 | I47: 7652 | J47: 4867 | K47: 2607 | L47: 2915 | M47: 879
A48: South | B48: 2247 | C48: 1737 | D48: 377 | E48: 63 | F48: 64 | G48: 5 | H48: 34279 | I48: 18532 | J48: 6972 | K48: 2028 | L48: 5013 | M48: 1734
A49: West | B49: 1267 | C49: 954 | D49: 248 | E49: 43 | F49: 21 | G49: 2 | H49: 18360 | I49: 9760 | J49: 4269 | K49: 1083 | L49: 2198 | M49: 1049
A50: Climate region1
A51: Very cold/Cold | B51: 2031 | C51: 1200 | D51: 523 | E51: 227 | F51: 76 | G51: 4 | H51: 31898 | I51: 12175 | J51: 8343 | K51: 4460 | L51: 5340 | M51: 1580
A52: Mixed-humid | B52: 1743 | C52: 1222 | D52: 339 | E52: 106 | F52: 70 | G52: 6 | H52: 27873 | I52: 12382 | J52: 6124 | K52: 2292 | L52: 4616 | M52: 2459
A53: Mixed-dry/Hot-dry | B53: 837 | C53: 664 | D53: 134 | E53: 23 | F53: 16 | G53: 1 | H53: 12037 | I53: 6815 | J53: 2492 | K53: 697 | L53: 1577 | M53: 455
A54: Hot-humid | B54: 799 | C54: 646 | D54: 128 | E54: 11 | F54: 12 | G54: 2 | H54: 12831 | I54: 7485 | J54: 2556 | K54: 527 | L54: 1581 | M54: 682
A55: Marine | B55: 147 | C55: 103 | D55: 34 | E55: Q | F55: 3 | G55: Q | H55: 2454 | I55: 952 | J55: 690 | K55: Q | L55: 420 | M55: Q
A56: Elevators and escalators (more than one may apply)
A57: Any elevators | B57: 405 | C57: N | D57: 167 | E57: 105 | F57: 121 | G57: 13 | H57: 32120 | I57: N | J57: 8548 | K57: 5654 | L57: 12514 | M57: 5404
A58: Number of elevators
A59: One | B59: 272 | C59: N | D59: 144 | E59: 75 | F59: 53 | G59: Q | H59: 11158 | I59: N | J59: 6069 | K59: 2771 | L59: 2305 | M59: Q
A60: Two to five | B60: 118 | C60: N | D60: 22 | E60: 29 | F60: 61 | G60: 5 | H60: 12817 | I60: N | J60: 2335 | K60: 2579 | L60: 7010 | M60: 893
A61: Six or more | B61: 16 | C61: N | D61: Q | E61: 1 | F61: 7 | G61: 8 | H61: 8145 | I61: N | J61: Q | K61: 304 | L61: 3199 | M61: 4498
A62: Any escalators | B62: 10 | C62: N | D62: Q | E62: Q | F62: 4 | G62: 2 | H62: 3654 | I62: N | J62: 333 | K62: Q | L62: 1372 | M62: 1813
A63: Number of workers (main shift)
A64: Fewer than 5 | B64: 2892 | C64: 2191 | D64: 494 | E64: 164 | F64: 42 | G64: Q | H64: 17751 | I64: 11548 | J64: 3555 | K64: 1547 | L64: 1002 | M64: Q
A65: 5 to 9 | B65: 1085 | C65: 767 | D65: 220 | E65: 77 | F65: 21 | G65: Q | H65: 8973 | I65: 5638 | J65: 2234 | K65: 715 | L65: 379 | M65: Q
A66: 10 to 19 | B66: 731 | C66: 475 | D66: 197 | E66: 42 | F66: 16 | G66: Q | H66: 9623 | I66: 5709 | J66: 2560 | K66: 710 | L66: 597 | M66: Q
A67: 20 to 49 | B67: 513 | C67: 282 | D67: 152 | E67: 55 | F67: 24 | G67: Q | H67: 14514 | I67: 6907 | J67: 4279 | K67: 1764 | L67: 1442 | M67: Q
A68: 50 to 99 | B68: 206 | C68: 87 | D68: 65 | E68: 21 | F68: 31 | G68: 1 | H68: 13476 | I68: 5841 | J68: 3670 | K68: 1372 | L68: 2290 | M68: 303
A69: 100 to 249 | B69: 93 | C69: 31 | D69: 24 | E69: 11 | F69: 27 | G69: 2 | H69: 10941 | I69: 3289 | J69: 2711 | K69: 1240 | L69: 3289 | M69: 412
A70: 250 or more | B70: 37 | C70: 3 | D70: 6 | E70: 4 | F70: 15 | G70: 8 | H70: 11815 | I70: 876 | J70: 1196 | K70: 792 | L70: 4535 | M70: 4415
A71: Weekly operating hours
A72: Fewer than 40 | B72: 1149 | C72: 846 | D72: 229 | E72: 58 | F72: 16 | G72: Q | H72: 8220 | I72: 4998 | J72: 1974 | K72: 587 | L72: 617 | M72: Q
A73: 40 to 48 | B73: 1346 | C73: 933 | D73: 284 | E73: 95 | F73: 34 | G73: Q | H73: 15828 | I73: 8264 | J73: 4018 | K73: 1479 | L73: 1836 | M73: Q
A74: 49 to 60 | B74: 1244 | C74: 830 | D74: 295 | E74: 69 | F74: 45 | G74: 4 | H74: 20529 | I74: 9541 | J74: 5074 | K74: 1806 | L74: 2783 | M74: 1326
A75: 61 to 84 | B75: 764 | C75: 510 | D75: 160 | E75: 67 | F75: 26 | G75: 2 | H75: 15867 | I75: 7516 | J75: 4016 | K75: 1669 | L75: 1711 | M75: 955
A76: 85 to 167 | B76: 479 | C76: 355 | D76: 80 | E76: 33 | F76: 11 | G76: Q | H76: 9395 | I76: 4788 | J76: 2281 | K76: 970 | L76: 1296 | M76: Q
A77: Open continuously | B77: 575 | C77: 363 | D77: 110 | E77: 52 | F77: 45 | G77: 6 | H77: 17253 | I77: 4702 | J77: 2844 | K77: 1629 | L77: 5291 | M77: 2788
A78: Ownership and occupancy
A79: Nongovernment owned | B79: 4781 | C79: 3290 | D79: 1010 | E79: 328 | F79: 142 | G79: 11 | H79: 67550 | I79: 32751 | J79: 15005 | K79: 5929 | L79: 9454 | M79: 4410
A80: Owner occupied | B80: 2466 | C80: 1651 | D80: 552 | E80: 191 | F80: 70 | G80: 2 | H80: 30637 | I80: 13707 | J80: 7954 | K80: 3564 | L80: 4439 | M80: 973
A81: Leased to tenant(s) | B81: 1745 | C81: 1288 | D81: 321 | E81: 84 | F81: 46 | G81: 5 | H81: 26115 | I81: 14937 | J81: 4864 | K81: 1284 | L81: 2830 | M81: 2199
A82: Owner occupied and leased | B82: 349 | C82: 183 | D82: 98 | E82: 42 | F82: 23 | G82: 3 | H82: 8873 | I82: 2885 | J82: 1805 | K82: 975 | L82: 2015 | M82: 1193
A83: Unoccupied | B83: 221 | C83: 169 | D83: 38 | E83: Q | F83: Q | G83: Q | H83: 1925 | I83: 1221 | J83: 382 | K83: Q | L83: Q | M83: Q
A84: Government owned | B84: 776 | C84: 546 | D84: 148 | E84: 46 | F84: 35 | G84: 2 | H84: 19543 | I84: 7058 | J84: 5201 | K84: 2210 | L84: 4081 | M84: 993
A85: Federal | B85: 33 | C85: 21 | D85: Q | E85: Q | F85: 1 | G85: 1 | H85: 1573 | I85: 323 | J85: Q | K85: Q | L85: 469 | M85: 496
A86: State | B86: 185 | C86: 112 | D86: 48 | E86: 10 | F86: 14 | G86: 1 | H86: 5539 | I86: 1530 | J86: 1682 | K86: 655 | L86: 1473 | M86: 199
A87: Local | B87: 558 | C87: 413 | D87: 90 | E87: 35 | F87: 20 | G87: Q | H87: 12431 | I87: 5205 | J87: 3336 | K87: 1454 | L87: 2139 | M87: Q
A88: Party responsible for operation and maintenance of energy systems
A89: Building owner | B89: 4715 | C89: 3223 | D89: 992 | E89: 329 | F89: 159 | G89: 12 | H89: 73702 | I89: 31061 | J89: 17556 | K89: 7461 | L89: 12524 | M89: 5099
A90: Business owner or tenant | B90: 724 | C90: 537 | D90: 137 | E90: 38 | F90: 12 | G90: Q | H90: 11309 | I90: 7944 | J90: 2193 | K90: 507 | L90: 612 | M90: Q
A91: Property management | B91: 54 | C91: 41 | D91: 8 | E91: Q | F91: Q | G91: Q | H91: 1250 | I91: 438 | J91: 176 | K91: Q | L91: Q | M91: Q
A92: Other | B92: 64 | C92: 35 | D92: Q | E92: Q | F92: Q | G92: Q | H92: 832 | I92: 366 | J92: Q | K92: Q | L92: Q | M92: Q
A93: Provider of direct input on energy-related equipment purchases
A94: Building owner | B94: 4876 | C94: 3347 | D94: 1013 | E94: 343 | F94: 161 | G94: 12 | H94: 76271 | I94: 32776 | J94: 18070 | K94: 7744 | L94: 12529 | M94: 5151
A95: Business owner or tenant | B95: 540 | C95: 394 | D95: 114 | E95: 22 | F95: 10 | G95: Q | H95: 8256 | I95: 5688 | J95: 1655 | K95: 250 | L95: 610 | M95: Q
A96: Property management | B96: 35 | C96: 26 | D96: Q | E96: Q | F96: Q | G96: Q | H96: 880 | I96: 378 | J96: Q | K96: Q | L96: Q | M96: Q
A97: Other | B97: 106 | C97: 70 | D97: 26 | E97: Q | F97: Q | G97: Q | H97: 1686 | I97: 967 | J97: 360 | K97: Q | L97: Q | M97: Q
A98: Number of establishments
A99: One | B99: 4205 | C99: 2997 | D99: 833 | E99: 259 | F99: 112 | G99: 4 | H99: 54994 | I99: 25686 | J99: 14210 | K99: 5591 | L99: 7895 | M99: 1613
A100: 2 to 5 | B100: 862 | C100: 510 | D100: 224 | E100: 87 | F100: 39 | G100: 3 | H100: 17756 | I100: 7605 | J100: 3755 | K100: 1810 | L100: 3323 | M100: 1263
...

Sheet CBECS_Table C4
A1: Release date: May 2016 Revised date: December 2016
A2: Table C4. Sum of major fuel consumption and expenditure gross energy intensities , 2012
B3: Sum of major fuel consumption | H3: Sum of major fuel expenditures
B4: per building (million Btu) | C4: per square foot (thousand Btu) | D4: per worker (million Btu) | E4: Distribution of building-level intensities (thousand Btu/square foot) | H4: per building (thousand dollars) | I4: per square foot (dollars) | J4: per million Btu (dollars)
E5: 25th per- centile | F5: Median | G5: 75th per- centile
A6: All buildings | B6: 1253 | C6: 80 | D6: 79 | E6: 18.9 | F6: 45.9 | G6: 89 | H6: 26.8 | I6: 1.71 | J6: 21.41
A7: Building floorspace (square feet)
A8: 1,001 to 5,000 | B8: 260 | C8: 89.9 | D8: 70.6 | E8: 17.6 | F8: 46.4 | G8: 100 | H8: 5.9 | I8: 2.03 | J8: 22.62
A9: 5,001 to 10,000 | B9: 526 | C9: 72.6 | D9: 70 | E9: 18.3 | F9: 40.1 | G9: 74.3 | H9: 11.6 | I9: 1.6 | J9: 22.02
A10: 10,001 to 25,000 | B10: 992 | C10: 62.1 | D10: 61.8 | E10: 18.7 | F10: 43.8 | G10: 81.5 | H10: 22.5 | I10: 1.41 | J10: 22.73
A11: 25,001 to 50,000 | B11: 2478 | C11: 69 | D11: 72.6 | E11: 24.6 | F11: 48.8 | G11: 88.8 | H11: 52.1 | I11: 1.45 | J11: 21.03
A12: 50,001 to 100,000 | B12: 5359 | C12: 76.7 | D12: 86.5 | E12: 33.7 | F12: 58.2 | G12: 93.4 | H12: 113.1 | I12: 1.62 | J12: 21.1
A13: 100,001 to 200,000 | B13: 11497 | C13: 83.4 | D13: 91.5 | E13: 39 | F13: 66.2 | G13: 101.1 | H13: 243.4 | I13: 1.76 | J13: 21.17
A14: 200,001 to 500,000 | B14: 27198 | C14: 95.7 | D14: 99.1 | E14: 47.4 | F14: 77.1 | G14: 114.8 | H14: 553.4 | I14: 1.95 | J14: 20.35
A15: Over 500,000 | B15: 95959 | C15: 108.4 | D15: 83.4 | E15: 42.9 | F15: 71.2 | G15: 124.3 | H15: 1996.3 | I15: 2.26 | J15: 20.8
A16: Principal building activity
A17: Education | B17: 2166 | C17: 68.8 | D17: 77.3 | E17: 31.1 | F17: 50.8 | G17: 81.1 | H17: 43.3 | I17: 1.37 | J17: 19.98
A18: Food sales | B18: 1483 | C18: 209.5 | D18: 223.6 | E18: 128.1 | F18: 222.8 | G18: 321.6 | H18: 34.9 | I18: 4.93 | J18: 23.52
A19: Food service | B19: 1355 | C19: 282.7 | D19: 149.9 | E19: 94.4 | F19: 241.1 | G19: 449 | H19: 26.2 | I19: 5.47 | J19: 19.36
A20: Health care | B20: 4578 | C20: 172.7 | D20: 94.2 | E20: 42.4 | F20: 63.2 | G20: 90.9 | H20: 83.4 | I20: 3.15 | J20: 18.22
A21: Inpatient | B21: 57281 | C21: 231.1 | D21: 128.2 | E21: 163.8 | F21: 205.7 | G21: 272.6 | H21: 978.6 | I21: 3.95 | J21: 17.08
A22: Outpatient | B22: 1147 | C22: 94.8 | D22: 50.7 | E22: 33.5 | F22: 61.7 | G22: 82.1 | H22: 25.1 | I22: 2.08 | J22: 21.91
A23: Lodging | B23: 3574 | C23: 96.9 | D23: 184.1 | E23: 48.1 | F23: 69.1 | G23: 119.1 | H23: 69.6 | I23: 1.89 | J23: 19.48
A24: Mercantile | B24: 1673 | C24: 88.9 | D24: 110.5 | E24: 33.4 | F24: 63.6 | G24: 107.6 | H24: 37.7 | I24: 2 | J24: 22.53
A25: Retail (other than mall) | B25: 830 | C25: 66.9 | D25: 90.4 | E25: 25.6 | F25: 52.2 | G25: 88.3 | H25: 20.5 | I25: 1.65 | J25: 24.69
A26: Enclosed and strip malls | B26: 3924 | C26: 109.3 | D26: 126.4 | E26: 59 | F26: 100.8 | G26: 177.3 | H26: 83.6 | I26: 2.33 | J26: 21.31
A27: Office | B27: 1226 | C27: 77.8 | D27: 36.8 | E27: 32.6 | F27: 52.7 | G27: 80.2 | H27: 30.4 | I27: 1.93 | J27: 24.8
A28: Public assembly | B28: 1363 | C28: 86.3 | D28: 154.4 | E28: 22.2 | F28: 49.3 | G28: 82.5 | H28: 29 | I28: 1.84 | J28: 21.29
... A34: Vacant | B34: 140 | C34: 12.7 | D34: 176 | E34: 0 | F34: 0 | G34: 6.4 | H34: 3.3 | I34: 0.3 | J34: 23.46
A35: Year constructed
A36: Before 1920 | B36: 658 | C36: 59.8 | D36: 72 | E36: 16.4 | F36: 39 | G36: 81.8 | H36: 14.4 | I36: 1.3 | J36: 21.81
A37: 1920 to 1945 | B37: 857 | C37: 69.4 | D37: 69.7 | E37: 16.8 | F37: 46 | G37: 84 | H37: 19.9 | I37: 1.61 | J37: 23.19
A38: 1946 to 1959 | B38: 896 | C38: 72.7 | D38: 81.8 | E38: 20.2 | F38: 44.1 | G38: 85.9 | H38: 18.4 | I38: 1.49 | J38: 20.52
A39: 1960 to 1969 | B39: 1412 | C39: 87 | D39: 91.5 | E39: 28.4 | F39: 53.8 | G39: 107 | H39: 28.8 | I39: 1.77 | J39: 20.39
A40: 1970 to 1979 | B40: 1479 | C40: 93.3 | D40: 80.7 | E40: 18.8 | F40: 52.5 | G40: 104 | H40: 30.1 | I40: 1.9 | J40: 20.36
A41: 1980 to 1989 | B41: 1272 | C41: 76.4 | D41: 66.6 | E41: 17.6 | F41: 44.3 | G41: 82.5 | H41: 28.6 | I41: 1.72 | J41: 22.49
A42: 1990 to 1999 | B42: 1304 | C42: 79.8 | D42: 82 | E42: 16.8 | F42: 45 | G42: 87.2 | H42: 28.1 | I42: 1.72 | J42: 21.56
A43: 2000 to 2003 | B43: 1542 | C43: 80.2 | D43: 77.5 | E43: 22.6 | F43: 48.1 | G43: 100.3 | H43: 33.6 | I43: 1.75 | J43: 21.77
A44: 2004 to 2007 | B44: 1522 | C44: 80.9 | D44: 88.1 | E44: 18.6 | F44: 48.3 | G44: 82.1 | H44: 32.6 | I44: 1.73 | J44: 21.42
A45: 2008 to 2012 | B45: 1598 | C45: 84.5 | D45: 87.1 | E45: 16.9 | F45: 35.8 | G45: 79.8 | H45: 34.1 | I45: 1.8 | J45: 21.33
A46: Census region and division
A47: Northeast | B47: 1812 | C47: 93.9 | D47: 82.1 | E47: 24.7 | F47: 54.8 | G47: 104.6 | H47: 43.3 | I47: 2.25 | J47: 23.93
A48: New England | B48: 1219 | C48: 85.5 | D48: 88.3 | E48: 18.3 | F48: 43.7 | G48: 92.4 | H48: 30.9 | I48: 2.17 | J48: 25.34
A49: Middle Atlantic | B49: 2167 | C49: 97.2 | D49: 80.2 | E49: 30.9 | F49: 61.5 | G49: 119.6 | H49: 50.8 | I49: 2.28 | J49: 23.45
A50: Midwest | B50: 1265 | C50: 82.8 | D50: 90.7 | E50: 23.5 | F50: 50.8 | G50: 93.7 | H50: 22.1 | I50: 1.45 | J50: 17.49
A51: East North Central | B51: 1538 | C51: 88.7 | D51: 94.8 | E51: 32.3 | F51: 61.7 | G51: 109.2 | H51: 26.8 | I51: 1.55 | J51: 17.44
A52: West North Central | B52: 866 | C52: 70.4 | D52: 81.6 | E52: 11.9 | F52: 35.1 | G52: 70 | H52: 15.3 | I52: 1.24 | J52: 17.62
A53: South | B53: 1142 | C53: 74.9 | D53: 78.6 | E53: 17 | F53: 43.6 | G53: 85.7 | H53: 24.4 | I53: 1.6 | J53: 21.35
A54: South Atlantic | B54: 1244 | C54: 75.5 | D54: 75 | E54: 18.4 | F54: 43.2 | G54: 94.2 | H54: 28.7 | I54: 1.74 | J54: 23.03
A55: East South Central | B55: 999 | C55: 75.3 | D55: 86 | E55: 21.2 | F55: 51 | G55: 82.5 | H55: 20.2 | I55: 1.52 | J55: 20.26
A56: West South Central | B56: 1068 | C56: 73.6 | D56: 81.7 | E56: 12.5 | F56: 39.2 | G56: 80.2 | H56: 20.4 | I56: 1.41 | J56: 19.09
A57: West | B57: 1082 | C57: 74.7 | D57: 67 | E57: 17.5 | F57: 41.9 | G57: 79.6 | H57: 25.2 | I57: 1.74 | J57: 23.31
A58: Mountain | B58: 1233 | C58: 83.8 | D58: 90.7 | E58: 20.4 | F58: 56.7 | G58: 90.6 | H58: 22.7 | I58: 1.54 | J58: 18.43
A59: Pacific | B59: 1027 | C59: 71.3 | D59: 60.1 | E59: 16.8 | F59: 37 | G59: 75.6 | H59: 26.1 | I59: 1.82 | J59: 25.45
A60: Climate region1
A61: Very cold/Cold | B61: 1352 | C61: 86.1 | D61: 89.3 | E61: 22.6 | F61: 54 | G61: 98.7 | H61: 25.9 | I61: 1.65 | J61: 19.15
A62: Mixed-humid | B62: 1302 | C62: 81.4 | D62: 79.1 | E62: 21.5 | F62: 45.6 | G62: 90.3 | H62: 28.4 | I62: 1.77 | J62: 21.78
A63: Mixed-dry/Hot-dry | B63: 960 | C63: 66.8 | D63: 61.6 | E63: 15 | F63: 31.6 | G63: 68.2 | H63: 24.5 | I63: 1.7 | J63: 25.48
A64: Hot-humid | B64: 1185 | C64: 73.8 | D64: 75.5 | E64: 16.7 | F64: 44.4 | G64: 86.6 | H64: 27.4 | I64: 1.71 | J64: 23.11
A65: Marine | B65: 1337 | C65: 80.2 | D65: 62.7 | E65: 21.2 | F65: 44.1 | G65: 92.1 | H65: 31.8 | I65: 1.91 | J65: 23.78
A66: Number of floors
A67: One | B67: 738 | C67: 71.1 | D67: 80.8 | E67: 16.4 | F67: 42.2 | G67: 88.7 | H67: 16.3 | I67: 1.57 | J67: 22.05
A68: Two | B68: 1261 | C68: 72.3 | D68: 74 | E68: 23.2 | F68: 49.6 | G68: 85.5 | H68: 26.8 | I68: 1.54 | J68: 21.27
A69: Three | B69: 1787 | C69: 82.1 | D69: 85.4 | E69: 32.5 | F69: 56.4 | G69: 96 | H69: 37.6 | I69: 1.73 | J69: 21.03
A70: Four to nine | B70: 8102 | C70: 105.8 | D70: 88.1 | E70: 42.4 | F70: 66.8 | G70: 102.4 | H70: 160.2 | I70: 2.09 | J70: 19.77
A71: Ten or more | B71: 45392 | C71: 105.8 | D71: 61.2 | E71: 58.3 | F71: 82 | G71: 116.1 | H71: 1048.2 | I71: 2.44 | J71: 23.09
A72: Elevators and escalators (more than one may apply)
A73: Any elevators | B73: 7855 | C73: 99.1 | D73: 79.6 | E73: 43.7 | F73: 69.9 | G73: 106.3 | H73: 163 | I73: 2.06 | J73: 20.76
A74: Number of elevators
A75: One | B75: 3253 | C75: 79.2 | D75: 77.9 | E75: 40.5 | F75: 65.7 | G75: 99.2 | H75: 65.7 | I75: 1.6 | J75: 20.21
A76: Two to five | B76: 10565 | C76: 96.9 | D76: 80.2 | E76: 51.5 | F76: 75.8 | G76: 115.7 | H76: 222.1 | I76: 2.04 | J76: 21.02
A77: Six or more | B77: 65801 | C77: 129.8 | D77: 80.5 | E77: 67.5 | F77: 96.9 | G77: 166.2 | H77: 1375.4 | I77: 2.71 | J77: 20.9
A78: Any escalators | B78: 38936 | C78: 103.1 | D78: 78.2 | E78: 65.7 | F78: 66.8 | G78: 115.4 | H78: 838.2 | I78: 2.22 | J78: 21.53
A79: Number of workers (main shift)
A80: Fewer than 5 | B80: 261 | C80: 42.6 | D80: 149.3 | E80: 8.6 | F80: 32.1 | G80: 71.7 | H80: 5.8 | I80: 0.95 | J80: 22.33
A81: 5 to 9 | B81: 551 | C81: 66.6 | D81: 85.2 | E81: 26.3 | F81: 48.7 | G81: 94.1 | H81: 12.6 | I81: 1.52 | J81: 22.8
A82: 10 to 19 | B82: 1056 | C82: 80.3 | D82: 81.5 | E82: 36.4 | F82: 63.3 | G82: 119 | H82: 22.4 | I82: 1.7 | J82: 21.18
A83: 20 to 49 | B83: 2316 | C83: 81.8 | D83: 79.8 | E83: 37.3 | F83: 63 | G83: 113.2 | H83: 49.6 | I83: 1.75 | J83: 21.39
A84: 50 to 99 | B84: 5594 | C84: 85.3 | D84: 85.6 | E84: 48.1 | F84: 69.9 | G84: 112.2 | H84: 116.7 | I84: 1.78 | J84: 20.85
A85: 100 to 249 | B85: 11330 | C85: 96.7 | D85: 79.2 | E85: 57.9 | F85: 89 | G85: 127 | H85: 232.8 | I85: 1.99 | J85: 20.54
A86: 250 or more | B86: 38827 | C86: 122 | D86: 57.7 | E86: 62.3 | F86: 86.4 | G86: 151 | H86: 836.8 | I86: 2.63 | J86: 21.55
A87: Weekly operating hours
A88: Fewer than 40 | B88: 199 | C88: 27.8 | D88: 69.5 | E88: 2.4 | F88: 16.8 | G88: 42.4 | H88: 4.2 | I88: 0.58 | J88: 20.97
A89: 40 to 48 | B89: 618 | C89: 52.6 | D89: 47.4 | E89: 22.5 | F89: 42.9 | G89: 69 | H89: 14.2 | I89: 1.21 | J89: 23.05
A90: 49 to 60 | B90: 1011 | C90: 61.3 | D90: 50.6 | E90: 25 | F90: 48.1 | G90: 83.2 | H90: 23.3 | I90: 1.41 | J90: 22.99
A91: 61 to 84 | B91: 1792 | C91: 86.3 | D91: 82.1 | E91: 35.5 | F91: 72.4 | G91: 143.7 | H91: 39.4 | I91: 1.9 | J91: 21.95
A92: 85 to 167 | B92: 2294 | C92: 116.9 | D92: 135.8 | E92: 59 | F92: 124.7 | G92: 265.2 | H92: 47.8 | I92: 2.43 | J92: 20.83
A93: Open continuously | B93: 3783 | C93: 126.2 | D93: 122.7 | E93: 18.6 | F93: 62.7 | G93: 138.5 | H93: 75.1 | I93: 2.51 | J93: 19.86
A94: Ownership and occupancy
A95: Nongovernment owned | B95: 1124 | C95: 79.6 | D95: 78.5 | E95: 17.4 | F95: 44.5 | G95: 89.3 | H95: 24.4 | I95: 1.73 | J95: 21.7
A96: Owner occupied | B96: 1060 | C96: 85.4 | D96: 101.1 | E96: 19.8 | F96: 45 | G96: 93.7 | H96: 21.6 | I96: 1.74 | J96: 20.37
A97: Leased to tenant(s) | B97: 1170 | C97: 78.2 | D97: 63.7 | E97: 22.3 | F97: 51.3 | G97: 102.2 | H97: 27.2 | I97: 1.82 | J97: 23.25
A98: Owner occupied and leased | B98: 2032 | C98: 79.9 | D98: 66.9 | E98: 21.3 | F98: 42.6 | G98: 75.8 | H98: 44.9 | I98: 1.77 | J98: 22.11
A99: Unoccupied | B99: 47 | C99: 5.4 | E99: 0 | F99: 0 | G99: 2.8 | H99: 1.1 | I99: 0.12 | J99: 22.65
A100: Government owned | B100: 2046 | C100: 81.2 | D100: 80.7 | E100: 28.2 | F100: 53.4 | G100: 87.6 | H100: 41.8 | I100: 1.66 | J100: 20.41
A101: Federal | B101: 4164 | C101: 87.3 | D101: 64.3 | E101: 32.7 | F101: 58.3 | G101: 67.5 | H101: 94 | I101: 1.97 | J101: 22.56
A102: State | B102: 3001 | C102: 100.1 | D102: 99.4 | E102: 35 | F102: 58.2 | G102: 88.8 | H102: 57.6 | I102: 1.92 | J102: 19.2
A103: Local | B103: 1605 | C103: 72.1 | D103: 74.9 | E103: 26.2 | F103: 52.3 | G103: 86.2 | H103: 33.4 | I103: 1.5 | J103: 20.83
A104: Party responsible for operation and maintenance of energy systems
A105: Building owner | B105: 1232 | C105: 78.8 | D105: 78 | E105: 18.2 | F105: 44.4 | G105: 84.7 | H105: 26.1 | I105: 1.67 | J105: 21.21
...

Sheet State Codes
A1: Census Bureau Region and Division Codes and Federal Information Processing System (FIPS) Codes for States
A3: Source: U.S. Census Bureau, Population Division
A4: Internet Release Date: May 2017
A6: Region | B6: Division | C6: State (FIPS) | D6: Name | E6: Division
A7: 1 | B7: 0 | C7: 0 | D7: Northeast Region | E7: =IF(B7=0,"",IF(COUNTIF($B$7:B7,B7)=1,D7,E6))
A8: 1 | B8: 1 | C8: 0 | D8: New England Division | E8: =IF(B8=0,"",IF(COUNTIF($B$7:B8,B8)=1,D8,E7)) -> New England Division
A9: 1 | B9: 1 | C9: 9 | D9: Connecticut | E9: =IF(B9=0,"",IF(COUNTIF($B$7:B9,B9)=1,D9,E8)) -> New England Division
A10: 1 | B10: 1 | C10: 23 | D10: Maine | E10: =IF(B10=0,"",IF(COUNTIF($B$7:B10,B10)=1,D10,E9)) -> New England Division
A11: 1 | B11: 1 | C11: 25 | D11: Massachusetts | E11: =IF(B11=0,"",IF(COUNTIF($B$7:B11,B11)=1,D11,E10)) -> New England Division
A12: 1 | B12: 1 | C12: 33 | D12: New Hampshire | E12: =IF(B12=0,"",IF(COUNTIF($B$7:B12,B12)=1,D12,E11)) -> New England Division
A13: 1 | B13: 1 | C13: 44 | D13: Rhode Island | E13: =IF(B13=0,"",IF(COUNTIF($B$7:B13,B13)=1,D13,E12)) -> New England Division
A14: 1 | B14: 1 | C14: 50 | D14: Vermont | E14: =IF(B14=0,"",IF(COUNTIF($B$7:B14,B14)=1,D14,E13)) -> New England Division
A15: 1 | B15: 2 | C15: 0 | D15: Middle Atlantic Division | E15: =IF(B15=0,"",IF(COUNTIF($B$7:B15,B15)=1,D15,E14)) -> Middle Atlantic Division
A16: 1 | B16: 2 | C16: 34 | D16: New Jersey | E16: =IF(B16=0,"",IF(COUNTIF($B$7:B16,B16)=1,D16,E15)) -> Middle Atlantic Division
A17: 1 | B17: 2 | C17: 36 | D17: New York | E17: =IF(B17=0,"",IF(COUNTIF($B$7:B17,B17)=1,D17,E16)) -> Middle Atlantic Division
A18: 1 | B18: 2 | C18: 42 | D18: Pennsylvania | E18: =IF(B18=0,"",IF(COUNTIF($B$7:B18,B18)=1,D18,E17)) -> Middle Atlantic Division
A19: 2 | B19: 0 | C19: 0 | D19: Midwest Region | E19: =IF(B19=0,"",IF(COUNTIF($B$7:B19,B19)=1,D19,E18)) -> Middle Atlantic Division
... A70: 4 | B70: 9 | C70: 53 | D70: Washington | E70: =IF(B70=0,"",IF(COUNTIF($B$7:B70,B70)=1,D70,E69)) -> Pacific Division

Sheet AEO 2019_Table 4
B1: highogs.d120120a | C1: 2020 | D1: 2021 | E1: 2022 | F1: 2023 | G1: 2024 | H1: 2025 | I1: 2026 | J1: 2027 | K1: 2028 | L1: 2029 | M1: 2030 | N1: 2031 | O1: 2032 | P1: 2033 | Q1: 2034 | R1: 2035 | S1: 2036 | T1: 2037 | U1: 2038 | V1: 2039 | W1: 2040 | X1: 2041 | Y1: 2042 | Z1: 2043 | AA1: 2044 | AB1: 2045 | AC1: 2046 | AD1: 2047 | AE1: 2048 | AF1: 2049 | AG1: 2050
C3: Report | D3: Annual Energy Outlook 2021
C4: Scenario | D4: ref2021 | G4: Reference case
C5: Datekey | D5: d113020a
C6: Release Date | E6: January 2021
A10: RKI000 | B10: 4. Residential Sector Key Indicators and Consumption | AH10: Compound
B11: (quadrillion Btu, unless otherwise noted) | AH11: Growth
AH12: 2020-2050
B13: Key Indicators and Consumption | C13: 2020 | D13: 2021 | E13: 2022 | F13: 2023 | G13: 2024 | H13: 2025 | I13: 2026 | J13: 2027 | K13: 2028 | L13: 2029 | M13: 2030 | N13: 2031 | O13: 2032 | P13: 2033 | Q13: 2034 | R13: 2035 | S13: 2036 | T13: 2037 | U13: 2038 | V13: 2039 | W13: 2040 | X13: 2041 | Y13: 2042 | Z13: 2043 | AA13: 2044 | AB13: 2045 | AC13: 2046 | AD13: 2047 | AE13: 2048 | AF13: 2049 | AG13: 2050 | AH13: (percent)
B15: Key Indicators
B16: Households (millions)
A17: RKI000:ba_Single-Family | B17: Single-Family | C17: 84.750443 | D17: 85.593651 | E17: 86.439354 | F17: 87.273476 | G17: 88.112289 | H17: 88.984467 | I17: 89.856285 | J17: 90.700256 | K17: 91.51667 | L17: 92.31514 | M17: 93.093277 | N17: 93.847504 | O17: 94.588799 | P17: 95.310699 | Q17: 96.006424 | R17: 96.697853 | S17: 97.37767 | T17: 98.047127 | U17: 98.708321 | V17: 99.360046 | W17: 100.01558 | X17: 100.67042 | Y17: 101.32133 | Z17: 101.97403 | AA17: 102.632 | AB17: 103.29288 | AC17: 103.95903 | AD17: 104.62138 | AE17: 105.2791 | AF17: 105.93704 | AG17: 106.59597 | AH17: 0.007674
A18: RKI000:ba_Multifamily | B18: Multifamily | C18: 31.968704 | D18: 32.227837 | E18: 32.484608 | F18: 32.738888 | G18: 33.007179 | H18: 33.292564 | I18: 33.572525 | J18: 33.83012 | K18: 34.072906 | L18: 34.306412 | M18: 34.532425 | N18: 34.747349 | O18: 34.956161 | P18: 35.154221 | Q18: 35.343121 | R18: 35.533417 | S18: 35.72086 | T18: 35.907597 | U18: 36.095905 | V18: 36.288265 | W18: 36.482738 | X18: 36.677246 | Y18: 36.872318 | Z18: 37.067024 | AA18: 37.256569 | AB18: 37.445789 | AC18: 37.632339 | AD18: 37.817364 | AE18: 38.004612 | AF18: 38.195267 | AG18: 38.390739 | AH18: 0.006121
A19: RKI000:ba_MobileHomes | B19: Mobile Homes | C19: 6.663464 | D19: 6.648326 | E19: 6.634981 | F19: 6.627098 | G19: 6.630111 | H19: 6.643839 | I19: 6.664732 | J19: 6.675515 | K19: 6.675215 | L19: 6.664383 | M19: 6.643749 | N19: 6.616388 | O19: 6.58721 | P19: 6.557878 | Q19: 6.529199 | R19: 6.505653 | S19: 6.485949 | T19: 6.466928 | U19: 6.447885 | V19: 6.43115 | W19: 6.419676 | X19: 6.411514 | Y19: 6.40536 | Z19: 6.400518 | AA19: 6.396067 | AB19: 6.392113 | AC19: 6.388073 | AD19: 6.381184 | AE19: 6.37248 | AF19: 6.363905 | AG19: 6.35391 | AH19: -0.001584
A20: RKI000:ba_Total | B20: Total | C20: 123.38261 | D20: 124.46981 | E20: 125.55894 | F20: 126.63946 | G20: 127.74958 | H20: 128.92087 | I20: 130.09354 | J20: 131.2059 | K20: 132.26479 | L20: 133.28593 | M20: 134.26945 | N20: 135.21124 | O20: 136.13216 | P20: 137.0228 | Q20: 137.87875 | R20: 138.73691 | S20: 139.58447 | T20: 140.42166 | U20: 141.25212 | V20: 142.07947 | W20: 142.918 | X20: 143.75919 | Y20: 144.59901 | Z20: 145.44156 | AA20: 146.28465 | AB20: 147.1308 | AC20: 147.97945 | AD20: 148.81992 | AE20: 149.65619 | AF20: 150.49622 | AG20: 151.34062 | AH20: 0.006831
A22: RKI000:ca_AverageHouseS | B22: Average House Square Footage | C22: 1789.3104 | D22: 1795.358 | E22: 1801.3766 | F22: 1807.3268 | G22: 1813.0863 | H22: 1818.6857 | I22: 1824.2563 | J22: 1829.9603 | K22: 1835.7445 | L22: 1841.579 | M22: 1847.4465 | N22: 1853.3517 | O22: 1859.2565 | P22: 1865.1763 | Q22: 1871.0797 | R22: 1876.913 | S22: 1882.7009 | T22: 1888.4429 | U22: 1894.134 | V22: 1899.7411 | W22: 1905.2928 | X22: 1910.8062 | Y22: 1916.274 | Z22: 1921.7234 | AA22: 1927.2003 | AB22: 1932.6646 | AC22: 1938.1436 | AD22: 1943.6198 | AE22: 1949.0584 | AF22: 1954.4558 | AG22: 1959.8108 | AH22: 0.003039
B24: Energy Intensity
B25: (million Btu per household)
A26: RKI000:da_DeliveredEner | B26: Gross End-use Consumption 1/ | C26: 92.738052 | D26: 91.586494 | E26: 91.932487 | F26: 91.31826 | G26: 90.823273 | H26: 90.223351 | I26: 89.61335 | J26: 88.99015 | K26: 88.42942 | L26: 87.893829 | M26: 87.318878 | N26: 86.789642 | O26: 86.329742 | P26: 85.926926 | Q26: 85.607529 | R26: 85.342171 | S26: 85.099846 | T26: 84.88208 | U26: 84.683701 | V26: 84.499214 | W26: 84.319466 | X26: 84.135582 | Y26: 83.962128 | Z26: 83.800156 | AA26: 83.656654 | AB26: 83.525162 | AC26: 83.412842 | AD26: 83.307243 | AE26: 83.24379 | AF26: 83.194534 | AG26: 83.15329 | AH26: -0.00363
A27: RKI000:da_TotalEnergyCo | B27: Delivered Energy Consumption | C27: 92.104782 | D27: 90.867767 | E27: 91.143921 | F27: 90.463226 | G27: 89.904442 | H27: 89.241905 | I27: 88.56897 | J27: 87.883224 | K27: 87.260002 | L27: 86.662102 | M27: 86.023964 | N27: 85.430344 | O27: 84.905266 | P27: 84.436523 | Q27: 84.050179 | R27: 83.717567 | S27: 83.407295 | T27: 83.12088 | U27: 82.852921 | V27: 82.598061 | W27: 82.347038 | X27: 82.090897 | Y27: 81.843887 | Z27: 81.606949 | AA27: 81.386993 | AB27: 81.177185 | AC27: 80.98513 | AD27: 80.798256 | AE27: 80.651489 | AF27: 80.517357 | AG27: 80.389618 | AH27: -0.004524
B28: (thousand Btu per square foot)
A29: RKI000:ea_DeliveredEner | B29: Gross End-use Consumption 1/ | C29: 51.828938 | D29: 51.012939 | E29: 51.034573 | F29: 50.526699 | G29: 50.093189 | H29: 49.609097 | I29: 49.123222 | J29: 48.629551 | K29: 48.170876 | L29: 47.727428 | M29: 47.264633 | N29: 46.82848 | O29: 46.432404 | P29: 46.069065 | Q29: 45.75301 | R29: 45.469433 | S29: 45.200935 | T29: 44.948185 | U29: 44.708401 | V29: 44.479332 | W29: 44.255383 | X29: 44.03146 | Y29: 43.815304 | Z29: 43.606773 | AA29: 43.408386 | AB29: 43.217617 | AC29: 43.037495 | AD29: 42.861904 | AE29: 42.709747 | AF29: 42.566597 | AG29: 42.429241 | AH29: -0.006648
A30: RKI000:ea_TotalEnergyCo | B30: Delivered Energy Consumption | C30: 51.475014 | D30: 50.612617 | E30: 50.596817 | F30: 50.053608 | G30: 49.586411 | H30: 49.06945 | I30: 48.550724 | J30: 48.024662 | K30: 47.533848 | L30: 47.058586 | M30: 46.563709 | N30: 46.095051 | O30: 45.666248 | P30: 45.269997 | Q30: 44.920685 | R30: 44.603863 | S30: 44.301933 | T30: 44.015564 | U30: 43.741848 | V30: 43.478588 | W30: 43.220146 | X30: 42.961391 | Y30: 42.709908 | Z30: 42.4655 | AA30: 42.230686 | AB30: 42.002731 | AC30: 41.784897 | AD30: 41.571022 | AE30: 41.379719 | AF30: 41.196815 | AG30: 41.01907 | AH30: -0.00754
B32: Energy Consumption by Fuel
B33: Electricity 1/
A34: RKI000:fa_SpaceHeating | B34: Space Heating | C34: 0.648984 | D34: 0.698291 | E34: 0.706468 | F34: 0.702827 | G34: 0.701007 | H34: 0.69955 | I34: 0.697172 | J34: 0.693818 | K34: 0.690231 | L34: 0.68634 | M34: 0.68221 | N34: 0.677813 | O34: 0.673331 | P34: 0.669098 | Q34: 0.665025 | R34: 0.661573 | S34: 0.658052 | T34: 0.654504 | U34: 0.650834 | V34: 0.647063 | W34: 0.643497 | X34: 0.639746 | Y34: 0.635992 | Z34: 0.63249 | AA34: 0.628953 | AB34: 0.625267 | AC34: 0.621895 | AD34: 0.618506 | AE34: 0.615298 | AF34: 0.61255 | AG34: 0.609983 | AH34: -0.002064
A35: RKI000:fa_SpaceCooling | B35: Space Cooling | C35: 0.805383 | D35: 0.7663 | E35: 0.862066 | F35: 0.87731 | G35: 0.893665 | H35: 0.910851 | I35: 0.927645 | J35: 0.943833 | K35: 0.959908 | L35: 0.975957 | M35: 0.991661 | N35: 1.00764 | O35: 1.024417 | P35: 1.041983 | Q35: 1.060664 | R35: 1.0811 | S35: 1.10211 | T35: 1.124333 | U35: 1.146319 | V35: 1.168238 | W35: 1.190837 | X35: 1.213056 | Y35: 1.236301 | Z35: 1.259563 | AA35: 1.283829 | AB35: 1.307854 | AC35: 1.33271 | AD35: 1.357816 | AE35: 1.384607 | AF35: 1.411898 | AG35: 1.440232 | AH35: 0.019564
A36: RKI000:fa_WaterHeating | B36: Water Heating | C36: 0.607547 | D36: 0.610144 | E36: 0.613074 | F36: 0.61509 | G36: 0.617846 | H36: 0.620172 | I36: 0.621656 | J36: 0.622656 | K36: 0.623322 | L36: 0.6239 | M36: 0.624483 | N36: 0.625003 | O36: 0.625859 | P36: 0.627114 | Q36: 0.628819 | R36: 0.631185 | S36: 0.633851 | T36: 0.636678 | U36: 0.639551 | V36: 0.642161 | W36: 0.644696 | X36: 0.647135 | Y36: 0.649634 | Z36: 0.65233 | AA36: 0.655174 | AB36: 0.658088 | AC36: 0.661325 | AD36: 0.664806 | AE36: 0.668643 | AF36: 0.672985 | AG36: 0.677571 | AH36: 0.003643
A37: RKI000:fa_Refrigeration | B37: Refrigeration | C37: 0.297571 | D37: 0.295346 | E37: 0.293794 | F37: 0.292089 | G37: 0.290616 | H37: 0.289474 | I37: 0.288541 | J37: 0.287696 | K37: 0.286959 | L37: 0.286376 | M37: 0.28598 | N37: 0.285826 | O37: 0.285965 | P37: 0.286393 | Q37: 0.287106 | R37: 0.288174 | S37: 0.289567 | T37: 0.291258 | U37: 0.293256 | V37: 0.295533 | W37: 0.298126 | X37: 0.301018 | Y37: 0.30418 | Z37: 0.307324 | AA37: 0.31044 | AB37: 0.31352 | AC37: 0.316558 | AD37: 0.319522 | AE37: 0.322411 | AF37: 0.325241 | AG37: 0.328011 | AH37: 0.003252
A38: RKI000:fa_Cooking | B38: Cooking | C38: 0.055007 | D38: 0.055161 | E38: 0.05546 | F38: 0.05575 | G38: 0.056045 | H38: 0.056357 | I38: 0.056663 | J38: 0.056938 | K38: 0.057183 | L38: 0.057389 | M38: 0.057556 | N38: 0.057676 | O38: 0.057755 | P38: 0.057841 | Q38: 0.057947 | R38: 0.058089 | S38: 0.058269 | T38: 0.058488 | U38: 0.058698 | V38: 0.058899 | W38: 0.059098 | X38: 0.05929 | Y38: 0.059473 | Z38: 0.059649 | AA38: 0.059818 | AB38: 0.05998 | AC38: 0.060139 | AD38: 0.06029 | AE38: 0.06044 | AF38: 0.060595 | AG38: 0.060756 | AH38: 0.003319
A39: RKI000:fa_ClothesDryers | B39: Clothes Dryers | C39: 0.21642 | D39: 0.220336 | E39: 0.224132 | F39: 0.227692 | G39: 0.231622 | H39: 0.235607 | I39: 0.239343 | J39: 0.242757 | K39: 0.246061 | L39: 0.249326 | M39: 0.252545 | N39: 0.255598 | O39: 0.258678 | P39: 0.261852 | Q39: 0.265235 | R39: 0.268841 | S39: 0.27257 | T39: 0.276244 | U39: 0.279829 | V39: 0.283363 | W39: 0.286891 | X39: 0.29037 | Y39: 0.293837 | Z39: 0.29735 | AA39: 0.300874 | AB39: 0.304347 | AC39: 0.307894 | AD39: 0.311491 | AE39: 0.315186 | AF39: 0.319055 | AG39: 0.322998 | AH39: 0.013437
A40: RKI000:fa_Freezers | B40: Freezers | C40: 0.069181 | D40: 0.068847 | E40: 0.068698 | F40: 0.068526 | G40: 0.06834 | H40: 0.068157 | I40: 0.067953 | J40: 0.067707 | K40: 0.067461 | L40: 0.067224 | M40: 0.066995 | N40: 0.066774 | O40: 0.06657 | P40: 0.066383 | Q40: 0.066214 | R40: 0.066077 | S40: 0.065975 | T40: 0.065902 | U40: 0.065862 | V40: 0.065855 | W40: 0.065888 | X40: 0.065966 | Y40: 0.066082 | Z40: 0.066247 | AA40: 0.066465 | AB40: 0.066737 | AC40: 0.067063 | AD40: 0.067429 | AE40: 0.06779 | AF40: 0.068152 | AG40: 0.068514 | AH40: -0.000323
A41: RKI000:fa_Lighting | B41: Lighting | C41: 0.211245 | D41: 0.204658 | E41: 0.202521 | F41: 0.20193 | G41: 0.202401 | H41: 0.201491 | I41: 0.200873 | J41: 0.200838 | K41: 0.201379 | L41: 0.202196 | M41: 0.200463 | N41: 0.199204 | O41: 0.198392 | P41: 0.197965 | Q41: 0.197945 | R41: 0.198286 | S41: 0.198748 | T41: 0.199251 | U41: 0.199757 | V41: 0.200288 | W41: 0.197496 | X41: 0.195328 | Y41: 0.193641 | Z41: 0.192433 | AA41: 0.191624 | AB41: 0.191038 | AC41: 0.190629 | AD41: 0.190303 | AE41: 0.190083 | AF41: 0.190014 | AG41: 0.190188 | AH41: -0.003494
A42: RKI000:fa_ClothesWasher | B42: Clothes Washers 2/ | C42: 0.036779 | D42: 0.037026 | E42: 0.037375 | F42: 0.037721 | G42: 0.038075 | H42: 0.038449 | I42: 0.038824 | J42: 0.03918 | K42: 0.039523 | L42: 0.039855 | M42: 0.040193 | N42: 0.040519 | O42: 0.040839 | P42: 0.041152 | Q42: 0.041455 | R42: 0.041759 | S42: 0.04206 | T42: 0.042358 | U42: 0.042653 | V42: 0.042945 | W42: 0.04324 | X42: 0.043535 | Y42: 0.043829 | Z42: 0.044122 | AA42: 0.044416 | AB42: 0.044709 | AC42: 0.045004 | AD42: 0.045295 | AE42: 0.045585 | AF42: 0.045875 | AG42: 0.046168 | AH42: 0.007607
A43: RKI000:fa_Dishwashers | B43: Dishwashers 2/ | C43: 0.026617 | D43: 0.026992 | E43: 0.027431 | F43: 0.027859 | G43: 0.028283 | H43: 0.028709 | I43: 0.029123 | J43: 0.029508 | K43: 0.029918 | L43: 0.03036 | M43: 0.03083 | N43: 0.03133 | O43: 0.031868 | P43: 0.032445 | Q43: 0.033062 | R43: 0.033677 | S43: 0.034289 | T43: 0.034896 | U43: 0.035501 | V43: 0.036103 | W43: 0.036706 | X43: 0.037309 | Y43: 0.03791 | Z43: 0.03851 | AA43: 0.03911 | AB43: 0.03971 | AC43: 0.040309 | AD43: 0.040905 | AE43: 0.041499 | AF43: 0.042093 | AG43: 0.042686 | AH43: 0.01587
A44: RKI000:fa_ColorTelevisi | B44: Televisions and Related Equipment 3/ | C44: 0.20913 | D44: 0.205162 | E44: 0.202737 | F44: 0.200828 | G44: 0.199926 | H44: 0.199812 | I44: 0.20026 | J44: 0.201233 | K44: 0.20279 | L44: 0.20499 | M44: 0.207745 | N44: 0.210879 | O44: 0.214516 | P44: 0.218628 | Q44: 0.223129 | R44: 0.228027 | S44: 0.233134 | T44: 0.23827 | U44: 0.243305 | V44: 0.248126 | W44: 0.252637 | X44: 0.256616 | Y44: 0.260069 | Z44: 0.263242 | AA44: 0.266345 | AB44: 0.26934 | AC44: 0.272296 | AD44: 0.275205 | AE44: 0.27813 | AF44: 0.281099 | AG44: 0.284057 | AH44: 0.01026
A45: RKI000:fa_PersonalCompu | B45: Computers and Related Equipment 4/ | C45: 0.086663 | D45: 0.083815 | E45: 0.081571 | F45: 0.079481 | G45: 0.077709 | H45: 0.076122 | I45: 0.074639 | J45: 0.073224 | K45: 0.071899 | L45: 0.07067 | M45: 0.069487 | N45: 0.068284 | O45: 0.0671 | P45: 0.06591 | Q45: 0.064687 | R45: 0.063421 | S45: 0.062059 | T45: 0.060712 | U45: 0.059373 | V45: 0.058027 | W45: 0.056675 | X45: 0.055295 | Y45: 0.053887 | Z45: 0.052461 | AA45: 0.051003 | AB45: 0.049484 | AC45: 0.047905 | AD45: 0.046248 | AE45: 0.044522 | AF45: 0.042687 | AG45: 0.040729 | AH45: -0.024855
... A50: RKI000:fa_PurchasedElec | B50: Purchased Electricity | C50: 5.052812 | D50: 5.085637 | E50: 5.095811 | F50: 5.116436 | G50: 5.142391 | H50: 5.170817 | I50: 5.205887 | J50: 5.237628 | K50: 5.270442 | L50: 5.303538 | M50: 5.333761 | N50: 5.36293 | O50: 5.394765 | P50: 5.428938 | Q50: 5.470158 | R50: 5.515707 | S50: 5.562729 | T50: 5.610796 | U50: 5.65801 | V50: 5.705455 | W50: 5.750833 | X50: 5.795556 | Y50: 5.841669 | Z50: 5.888741 | AA50: 5.936951 | AB50: 5.985407 | AC50: 6.035119 | AD50: 6.084916 | AE50: 6.139284 | AF50: 6.195721 | AG50: 6.253851 | AH50: 0.007134
B52: Natural Gas
A53: RKI000:ga_SpaceHeating | B53: Space Heating | C53: 3.527198 | D53: 3.406817 | E53: 3.538172 | F53: 3.535602 | G53: 3.539818 | H53: 3.535704 | I53: 3.522943 | J53: 3.505328 | K53: 3.488243 | L53: 3.469637 | M53: 3.44763 | N53: 3.428068 | O53: 3.411065 | P53: 3.395152 | Q53: 3.380025 | R53: 3.367227 | S53: 3.35518 | T53: 3.343377 | U53: 3.333029 | V53: 3.323643 | W53: 3.315649 | X53: 3.307149 | Y53: 3.298006 | Z53: 3.288577 | AA53: 3.279139 | AB53: 3.269643 | AC53: 3.260687 | AD53: 3.251623 | AE53: 3.243194 | AF53: 3.234245 | AG53: 3.224808 | AH53: -0.002983
A54: RKI000:ga_SpaceCooling | B54: Space Cooling | C54: 0.058618 | D54: 0.055422 | E54: 0.060292 | F54: 0.060192 | G54: 0.060163 | H54: 0.060023 | I54: 0.059796 | J54: 0.059542 | K54: 0.059324 | L54: 0.059101 | M54: 0.05881 | N54: 0.058535 | O54: 0.058282 | P54: 0.058023 | Q54: 0.057819 | R54: 0.057719 | S54: 0.057717 | T54: 0.05785 | U54: 0.058006 | V54: 0.058187 | W54: 0.058388 | X54: 0.058543 | Y54: 0.058715 | Z54: 0.058861 | AA54: 0.059042 | AB54: 0.059194 | AC54: 0.059373 | AD54: 0.059533 | AE54: 0.059739 | AF54: 0.05993 | AG54: 0.060134 | AH54: 0.000852
A55: RKI000:ga_WaterHeating | B55: Water Heating | C55: 1.007279 | D55: 1.004169 | E55: 1.007347 | F55: 1.014073 | G55: 1.023789 | H55: 1.033103 | I55: 1.041576 | J55: 1.049033 | K55: 1.056876 | L55: 1.064852 | M55: 1.070652 | N55: 1.076483 | O55: 1.082882 | P55: 1.089521 | Q55: 1.095863 | R55: 1.10233 | S55: 1.108471 | T55: 1.114128 | U55: 1.119485 | V55: 1.124763 | W55: 1.130038 | X55: 1.135069 | Y55: 1.139977 | Z55: 1.145107 | AA55: 1.150508 | AB55: 1.156279 | AC55: 1.16249 | AD55: 1.168953 | AE55: 1.175813 | AF55: 1.18275 | AG55: 1.189524 | AH55: 0.005559
A56: RKI000:ga_Cooking | B56: Cooking | C56: 0.103456 | D56: 0.103327 | E56: 0.103488 | F56: 0.103641 | G56: 0.103815 | H56: 0.10403 | I56: 0.10424 | J56: 0.104418 | K56: 0.104596 | L56: 0.104837 | M56: 0.105138 | N56: 0.105513 | O56: 0.105978 | P56: 0.10654 | Q56: 0.107144 | R56: 0.10781 | S56: 0.108522 | T56: 0.109274 | U56: 0.110047 | V56: 0.110843 | W56: 0.11167 | X56: 0.112526 | Y56: 0.113409 | Z56: 0.114322 | AA56: 0.115263 | AB56: 0.116226 | AC56: 0.117205 | AD56: 0.118188 | AE56: 0.119165 | AF56: 0.120132 | AG56: 0.121081 | AH56: 0.005257
A57: RKI000:ga_ClothesDryers | B57: Clothes Dryers | C57: 0.039427 | D57: 0.039794 | E57: 0.040383 | F57: 0.041098 | G57: 0.041912 | H57: 0.042688 | I57: 0.043422 | J57: 0.044122 | K57: 0.044799 | L57: 0.04545 | M57: 0.045976 | N57: 0.046544 | O57: 0.047158 | P57: 0.047801 | Q57: 0.048443 | R57: 0.049087 | S57: 0.049716 | T57: 0.050362 | U57: 0.051031 | V57: 0.051721 | W57: 0.052427 | X57: 0.053131 | Y57: 0.053831 | Z57: 0.054534 | AA57: 0.055235 | AB57: 0.055935 | AC57: 0.056636 | AD57: 0.057333 | AE57: 0.058035 | AF57: 0.058729 | AG57: 0.059408 | AH57: 0.01376
A58: RKI000:ga_OtherNatGas | B58: Other Uses 6/ | C58: 0.233372 | D58: 0.231855 | E58: 0.231502 | F58: 0.231786 | G58: 0.232411 | H58: 0.232655 | I58: 0.232517 | J58: 0.232038 | K58: 0.231477 | L58: 0.23081 | M58: 0.229433 | N58: 0.228332 | O58: 0.227513 | P58: 0.226939 | Q58: 0.22645 | R58: 0.226059 | S58: 0.225705 | T58: 0.225355 | U58: 0.225028 | V58: 0.224728 | W58: 0.224433 | X58: 0.224098 | Y58: 0.223732 | Z58: 0.223368 | AA58: 0.223001 | AB58: 0.222637 | AC58: 0.222293 | AD58: 0.221954 | AE58: 0.22166 | AF58: 0.221362 | AG58: 0.221026 | AH58: -0.00181
A59: RKI000:ga_DeliveredEner | B59: Delivered Energy | C59: 4.96935 | D59: 4.841384 | E59: 4.981184 | F59: 4.986392 | G59: 5.001907 | H59: 5.008203 | I59: 5.004495 | J59: 4.99448 | K59: 4.985316 | L59: 4.974687 | M59: 4.95764 | N59: 4.943475 | O59: 4.932878 | P59: 4.923977 | Q59: 4.915745 | R59: 4.910232 | S59: 4.905311 | T59: 4.900348 | U59: 4.896626 | V59: 4.893885 | W59: 4.892605 | X59: 4.890516 | Y59: 4.88767 | Z59: 4.884768 | AA59: 4.882187 | AB59: 4.879915 | AC59: 4.878683 | AD59: 4.877585 | AE59: 4.877605 | AF59: 4.877148 | AG59: 4.87598 | AH59: -0.000632
B61: Distillate Fuel Oil 7/
A62: RKI000:ha_SpaceHeating | B62: Space Heating | C62: 0.372664 | D62: 0.399955 | E62: 0.399688 | F62: 0.389283 | G62: 0.379513 | H62: 0.371232 | I62: 0.363199 | J62: 0.355843 | K62: 0.349209 | L62: 0.343014 | M62: 0.337038 | N62: 0.331464 | O62: 0.326065 | P62: 0.320905 | Q62: 0.315898 | R62: 0.311373 | S62: 0.307099 | T62: 0.302775 | U62: 0.298363 | V62: 0.294289 | W62: 0.290039 | X62: 0.285819 | Y62: 0.281613 | Z62: 0.277426 | AA62: 0.273195 | AB62: 0.268874 | AC62: 0.264632 | AD62: 0.260426 | AE62: 0.256324 | AF62: 0.252154 | AG62: 0.247963 | AH62: -0.013488
A63: RKI000:ha_WaterHeating | B63: Water Heating | C63: 0.048759 | D63: 0.047108 | E63: 0.045228 | F63: 0.043108 | G63: 0.041235 | H63: 0.039721 | I63: 0.038404 | J63: 0.037331 | K63: 0.036495 | L63: 0.035866 | M63: 0.035412 | N63: 0.034932 | O63: 0.034422 | P63: 0.033898 | Q63: 0.03336 | R63: 0.032838 | S63: 0.032329 | T63: 0.031798 | U63: 0.031244 | V63: 0.030722 | W63: 0.030176 | X63: 0.029644 | Y63: 0.029136 | Z63: 0.028658 | AA63: 0.028199 | AB63: 0.02775 | AC63: 0.02733 | AD63: 0.026935 | AE63: 0.026564 | AF63: 0.026194 | AG63: 0.025829 | AH63: -0.020957
A64: RKI000:Other_ha_ha | B64: Other Uses 8/ | C64: 0.007851 | D64: 0.007902 | E64: 0.007891 | F64: 0.007813 | G64: 0.007739 | H64: 0.007688 | I64: 0.00764 | J64: 0.007599 | K64: 0.007566 | L64: 0.007536 | M64: 0.007505 | N64: 0.007479 | O64: 0.007454 | P64: 0.00743 | Q64: 0.007408 | R64: 0.007392 | S64: 0.00738 | T64: 0.007363 | U64: 0.007342 | V64: 0.007326 | W64: 0.007302 | X64: 0.007279 | Y64: 0.007256 | Z64: 0.007236 | AA64: 0.007214 | AB64: 0.00719 | AC64: 0.007168 | AD64: 0.007148 | AE64: 0.007131 | AF64: 0.007112 | AG64: 0.007092 | AH64: -0.00338
A65: RKI000:ha_DeliveredEner | B65: Delivered Energy | C65: 0.429274 | D65: 0.454966 | E65: 0.452806 | F65: 0.440204 | G65: 0.428487 | H65: 0.418641 | I65: 0.409243 | J65: 0.400773 | K65: 0.39327 | L65: 0.386416 | M65: 0.379955 | N65: 0.373876 | O65: 0.367941 | P65: 0.362233 | Q65: 0.356666 | R65: 0.351603 | S65: 0.346807 | T65: 0.341936 | U65: 0.336949 | V65: 0.332337 | W65: 0.327518 | X65: 0.322742 | Y65: 0.318006 | Z65: 0.313319 | AA65: 0.308608 | AB65: 0.303814 | AC65: 0.299129 | AD65: 0.294509 | AE65: 0.290019 | AF65: 0.28546 | AG65: 0.280897 | AH65: -0.014037
B67: Propane
A68: RKI000:ia_SpaceHeating | B68: Space Heating | C68: 0.300826 | D68: 0.319245 | E68: 0.316427 | F68: 0.313786 | G68: 0.311282 | H68: 0.308732 | I68: 0.306312 | J68: 0.303989 | K68: 0.301527 | L68: 0.298858 | M68: 0.295637 | N68: 0.292482 | O68: 0.289513 | P68: 0.28679 | Q68: 0.284197 | R68: 0.281868 | S68: 0.27961 | T68: 0.277262 | U68: 0.274919 | V68: 0.272692 | W68: 0.270642 | X68: 0.268655 | Y68: 0.266657 | Z68: 0.26476 | AA68: 0.262848 | AB68: 0.260929 | AC68: 0.258979 | AD68: 0.25697 | AE68: 0.254948 | AF68: 0.252907 | AG68: 0.250867 | AH68: -0.006035
A69: RKI000:ia_WaterHeating | B69: Water Heating | C69: 0.065346 | D69: 0.063722 | E69: 0.062055 | F69: 0.060465 | G69: 0.059105 | H69: 0.057937 | I69: 0.056967 | J69: 0.056138 | K69: 0.055393 | L69: 0.054729 | M69: 0.054049 | N69: 0.053271 | O69: 0.052457 | P69: 0.051632 | Q69: 0.050781 | R69: 0.049942 | S69: 0.049103 | T69: 0.048235 | U69: 0.047364 | V69: 0.046527 | W69: 0.045739 | X69: 0.044994 | Y69: 0.044292 | Z69: 0.043656 | AA69: 0.043064 | AB69: 0.042516 | AC69: 0.041997 | AD69: 0.041497 | AE69: 0.041015 | AF69: 0.040548 | AG69: 0.040094 | AH69: -0.01615
A70: RKI000:ia_Cooking | B70: Cooking | C70: 0.017067 | D70: 0.016859 | E70: 0.016696 | F70: 0.016528 | G70: 0.016358 | H70: 0.016189 | I70: 0.01601 | J70: 0.015815 | K70: 0.015609 | L70: 0.015392 | M70: 0.015163 | N70: 0.014927 | O70: 0.014685 | P70: 0.01448 | Q70: 0.014313 | R70: 0.014186 | S70: 0.014101 | T70: 0.014056 | U70: 0.014005 | V70: 0.01395 | W70: 0.01389 | X70: 0.013826 | Y70: 0.013758 | Z70: 0.013687 | AA70: 0.013616 | AB70: 0.013546 | AC70: 0.01348 | AD70: 0.013417 | AE70: 0.013359 | AF70: 0.013304 | AG70: 0.01325 | AH70: -0.008401
A71: RKI000:ia_OtherUses | B71: Other Uses 9/ | C71: 0.071942 | D71: 0.074219 | E71: 0.076272 | F71: 0.078184 | G71: 0.080132 | H71: 0.082117 | I71: 0.08416 | J71: 0.086215 | K71: 0.088203 | L71: 0.090113 | M71: 0.091786 | N71: 0.093445 | O71: 0.095152 | P71: 0.096924 | Q71: 0.098706 | R71: 0.100542 | S71: 0.102393 | T71: 0.104196 | U71: 0.105976 | V71: 0.107785 | W71: 0.109637 | X71: 0.11151 | Y71: 0.113397 | Z71: 0.115342 | AA71: 0.117306 | AB71: 0.119287 | AC71: 0.121262 | AD71: 0.123226 | AE71: 0.125186 | AF71: 0.127143 | AG71: 0.129101 | AH71: 0.019682
A72: RKI000:ia_DeliveredEner | B72: Delivered Energy | C72: 0.45518 | D72: 0.474045 | E72: 0.47145 | F72: 0.468962 | G72: 0.466877 | H72: 0.464974 | I72: 0.46345 | J72: 0.462157 | K72: 0.460731 | L72: 0.459092 | M72: 0.456636 | N72: 0.454125 | O72: 0.451806 | P72: 0.449826 | Q72: 0.447996 | R72: 0.446539 | S72: 0.445206 | T72: 0.443749 | U72: 0.442264 | V72: 0.440953 | W72: 0.439908 | X72: 0.438985 | Y72: 0.438105 | Z72: 0.437445 | AA72: 0.436834 | AB72: 0.436278 | AC72: 0.435718 | AD72: 0.435111 | AE72: 0.434508 | AF72: 0.433901 | AG72: 0.433312 | AH72: -0.00164
A74: RKI000:ja_MarketedRenew | B74: Marketed Renewables (wood) 10/ | C74: 0.457513 | D74: 0.454262 | E74: 0.442685 | F74: 0.44422 | G74: 0.445592 | H74: 0.442511 | I74: 0.439175 | J74: 0.43576 | K74: 0.431667 | L74: 0.427109 | M74: 0.422399 | N74: 0.416737 | O74: 0.410947 | P74: 0.404757 | Q74: 0.398165 | R74: 0.390633 | S74: 0.38231 | T74: 0.375142 | U74: 0.369302 | V74: 0.362859 | W74: 0.358009 | X74: 0.353523 | Y74: 0.349097 | Z74: 0.344771 | AA74: 0.341088 | AB74: 0.33825 | AC74: 0.335486 | AD74: 0.332267 | AE74: 0.328579 | AF74: 0.325327 | AG74: 0.322186 | AH74: -0.011621
B76: Energy Consumption by End Use 1/
A77: RKI000:ka_SpaceHeating | B77: Space Heating | C77: 5.307185 | D77: 5.27857 | E77: 5.40344 | F77: 5.385718 | G77: 5.377212 | H77: 5.357728 | I77: 5.328801 | J77: 5.294736 | K77: 5.260876 | L77: 5.224958 | M77: 5.184915 | N77: 5.146564 | O77: 5.110921 | P77: 5.076702 | Q77: 5.043309 | R77: 5.012675 | S77: 4.982251 | T77: 4.95306 | U77: 4.926447 | V77: 4.900547 | W77: 4.877836 | X77: 4.854891 | Y77: 4.831365 | Z77: 4.808023 | AA77: 4.785222 | AB77: 4.762963 | AC77: 4.741679 | AD77: 4.719794 | AE77: 4.698342 | AF77: 4.677184 | AG77: 4.655806 | AH77: -0.004355
A78: RKI000:ka_SpaceCooling | B78: Space Cooling | C78: 0.864001 | D78: 0.821723 | E78: 0.922358 | F78: 0.937503 | G78: 0.953828 | H78: 0.970874 | I78: 0.987441 | J78: 1.003375 | K78: 1.019232 | L78: 1.035058 | M78: 1.050471 | N78: 1.066175 | O78: 1.082699 | P78: 1.100006 | Q78: 1.118483 | R78: 1.138818 | S78: 1.159827 | T78: 1.182183 | U78: 1.204325 | V78: 1.226425 | W78: 1.249226 | X78: 1.271599 | Y78: 1.295016 | Z78: 1.318424 | AA78: 1.342871 | AB78: 1.367048 | AC78: 1.392083 | AD78: 1.417349 | AE78: 1.444345 | AF78: 1.471828 | AG78: 1.500366 | AH78: 0.018567
A79: RKI000:ka_WaterHeating | B79: Water Heating | C79: 1.728931 | D79: 1.725143 | E79: 1.727704 | F79: 1.732736 | G79: 1.741975 | H79: 1.750933 | I79: 1.758603 | J79: 1.765158 | K79: 1.772085 | L79: 1.779346 | M79: 1.784596 | N79: 1.789688 | O79: 1.79562 | P79: 1.802165 | Q79: 1.808823 | R79: 1.816295 | S79: 1.823754 | T79: 1.830839 | U79: 1.837644 | V79: 1.844173 | W79: 1.850649 | X79: 1.856842 | Y79: 1.863041 | Z79: 1.86975 | AA79: 1.876945 | AB79: 1.884634 | AC79: 1.893142 | AD79: 1.902191 | AE79: 1.912034 | AF79: 1.922478 | AG79: 1.933017 | AH79: 0.003726
A80: RKI000:ka_Refrigeration | B80: Refrigeration | C80: 0.297571 | D80: 0.295346 | E80: 0.293794 | F80: 0.292089 | G80: 0.290616 | H80: 0.289474 | I80: 0.288541 | J80: 0.287696 | K80: 0.286959 | L80: 0.286376 | M80: 0.28598 | N80: 0.285826 | O80: 0.285965 | P80: 0.286393 | Q80: 0.287106 | R80: 0.288174 | S80: 0.289567 | T80: 0.291258 | U80: 0.293256 | V80: 0.295533 | W80: 0.298126 | X80: 0.301018 | Y80: 0.30418 | Z80: 0.307324 | AA80: 0.31044 | AB80: 0.31352 | AC80: 0.316558 | AD80: 0.319522 | AE80: 0.322411 | AF80: 0.325241 | AG80: 0.328011 | AH80: 0.003252
A81: RKI000:ka_Cooking | B81: Cooking | C81: 0.17553 | D81: 0.175348 | E81: 0.175644 | F81: 0.175919 | G81: 0.176218 | H81: 0.176576 | I81: 0.176914 | J81: 0.177171 | K81: 0.177388 | L81: 0.177618 | M81: 0.177857 | N81: 0.178115 | O81: 0.178418 | P81: 0.178861 | Q81: 0.179404 | R81: 0.180086 | S81: 0.180891 | T81: 0.181818 | U81: 0.18275 | V81: 0.183692 | W81: 0.184658 | X81: 0.185641 | Y81: 0.18664 | Z81: 0.187659 | AA81: 0.188696 | AB81: 0.189752 | AC81: 0.190824 | AD81: 0.191895 | AE81: 0.192964 | AF81: 0.19403 | AG81: 0.195087 | AH81: 0.003528
A82: RKI000:ka_ClothesDryers | B82: Clothes Dryers | C82: 0.255846 | D82: 0.26013 | E82: 0.264514 | F82: 0.26879 | G82: 0.273535 | H82: 0.278295 | I82: 0.282766 | J82: 0.28688 | K82: 0.290861 | L82: 0.294776 | M82: 0.298522 | N82: 0.302141 | O82: 0.305836 | P82: 0.309653 | Q82: 0.313678 | R82: 0.317928 | S82: 0.322286 | T82: 0.326606 | U82: 0.33086 | V82: 0.335084 | W82: 0.339318 | X82: 0.343501 | Y82: 0.347668 | Z82: 0.351884 | AA82: 0.356109 | AB82: 0.360281 | AC82: 0.36453 | AD82: 0.368824 | AE82: 0.373221 | AF82: 0.377784 | AG82: 0.382406 | AH82: 0.013487
A83: RKI000:ka_Freezers | B83: Freezers | C83: 0.069181 | D83: 0.068847 | E83: 0.068698 | F83: 0.068526 | G83: 0.06834 | H83: 0.068157 | I83: 0.067953 | J83: 0.067707 | K83: 0.067461 | L83: 0.067224 | M83: 0.066995 | N83: 0.066774 | O83: 0.06657 | P83: 0.066383 | Q83: 0.066214 | R83: 0.066077 | S83: 0.065975 | T83: 0.065902 | U83: 0.065862 | V83: 0.065855 | W83: 0.065888 | X83: 0.065966 | Y83: 0.066082 | Z83: 0.066247 | AA83: 0.066465 | AB83: 0.066737 | AC83: 0.067063 | AD83: 0.067429 | AE83: 0.06779 | AF83: 0.068152 | AG83: 0.068514 | AH83: -0.000323
A84: RKI000:ka_Lighting | B84: Lighting | C84: 0.211245 | D84: 0.204658 | E84: 0.202521 | F84: 0.20193 | G84: 0.202401 | H84: 0.201491 | I84: 0.200873 | J84: 0.200838 | K84: 0.201379 | L84: 0.202196 | M84: 0.200463 | N84: 0.199204 | O84: 0.198392 | P84: 0.197965 | Q84: 0.197945 | R84: 0.198286 | S84: 0.198748 | T84: 0.199251 | U84: 0.199757 | V84: 0.200288 | W84: 0.197496 | X84: 0.195328 | Y84: 0.193641 | Z84: 0.192433 | AA84: 0.191624 | AB84: 0.191038 | AC84: 0.190629 | AD84: 0.190303 | AE84: 0.190083 | AF84: 0.190014 | AG84: 0.190188 | AH84: -0.003494
A85: RKI000:ka_ClothesWasher | B85: Clothes Washers 2/ | C85: 0.036779 | D85: 0.037026 | E85: 0.037375 | F85: 0.037721 | G85: 0.038075 | H85: 0.038449 | I85: 0.038824 | J85: 0.03918 | K85: 0.039523 | L85: 0.039855 | M85: 0.040193 | N85: 0.040519 | O85: 0.040839 | P85: 0.041152 | Q85: 0.041455 | R85: 0.041759 | S85: 0.04206 | T85: 0.042358 | U85: 0.042653 | V85: 0.042945 | W85: 0.04324 | X85: 0.043535 | Y85: 0.043829 | Z85: 0.044122 | AA85: 0.044416 | AB85: 0.044709 | AC85: 0.045004 | AD85: 0.045295 | AE85: 0.045585 | AF85: 0.045875 | AG85: 0.046168 | AH85: 0.007607
A86: RKI000:ka_Dishwashers | B86: Dishwashers 2/ | C86: 0.026617 | D86: 0.026992 | E86: 0.027431 | F86: 0.027859 | G86: 0.028283 | H86: 0.028709 | I86: 0.029123 | J86: 0.029508 | K86: 0.029918 | L86: 0.03036 | M86: 0.03083 | N86: 0.03133 | O86: 0.031868 | P86: 0.032445 | Q86: 0.033062 | R86: 0.033677 | S86: 0.034289 | T86: 0.034896 | U86: 0.035501 | V86: 0.036103 | W86: 0.036706 | X86: 0.037309 | Y86: 0.03791 | Z86: 0.03851 | AA86: 0.03911 | AB86: 0.03971 | AC86: 0.040309 | AD86: 0.040905 | AE86: 0.041499 | AF86: 0.042093 | AG86: 0.042686 | AH86: 0.01587
A87: RKI000:ka_ColorTelevisi | B87: Televisions and Related Equipment 3/ | C87: 0.20913 | D87: 0.205162 | E87: 0.202737 | F87: 0.200828 | G87: 0.199926 | H87: 0.199812 | I87: 0.20026 | J87: 0.201233 | K87: 0.20279 | L87: 0.20499 | M87: 0.207745 | N87: 0.210879 | O87: 0.214516 | P87: 0.218628 | Q87: 0.223129 | R87: 0.228027 | S87: 0.233134 | T87: 0.23827 | U87: 0.243305 | V87: 0.248126 | W87: 0.252637 | X87: 0.256616 | Y87: 0.260069 | Z87: 0.263242 | AA87: 0.266345 | AB87: 0.26934 | AC87: 0.272296 | AD87: 0.275205 | AE87: 0.27813 | AF87: 0.281099 | AG87: 0.284057 | AH87: 0.01026
A88: RKI000:ka_PersonalCompu | B88: Computers and Related Equipment 4/ | C88: 0.086663 | D88: 0.083815 | E88: 0.081571 | F88: 0.079481 | G88: 0.077709 | H88: 0.076122 | I88: 0.074639 | J88: 0.073224 | K88: 0.071899 | L88: 0.07067 | M88: 0.069487 | N88: 0.068284 | O88: 0.0671 | P88: 0.06591 | Q88: 0.064687 | R88: 0.063421 | S88: 0.062059 | T88: 0.060712 | U88: 0.059373 | V88: 0.058027 | W88: 0.056675 | X88: 0.055295 | Y88: 0.053887 | Z88: 0.052461 | AA88: 0.051003 | AB88: 0.049484 | AC88: 0.047905 | AD88: 0.046248 | AE88: 0.044522 | AF88: 0.042687 | AG88: 0.040729 | AH88: -0.024855
... A95: RKI000:la_ElectricityRe | B95: Electricity Related Losses | C95: 9.423895 | D95: 9.476621 | E95: 9.489174 | F95: 9.257663 | G95: 9.044497 | H95: 8.781025 | I95: 8.504918 | J95: 8.31342 | K95: 8.230984 | L95: 8.17648 | M95: 8.19232 | N95: 8.185059 | O95: 8.164425 | P95: 8.170115 | Q95: 8.173469 | R95: 8.198778 | S95: 8.224853 | T95: 8.23952 | U95: 8.258127 | V95: 8.292449 | W95: 8.330718 | X95: 8.36727 | Y95: 8.40609 | Z95: 8.423908 | AA95: 8.409726 | AB95: 8.439298 | AC95: 8.472725 | AD95: 8.503682 | AE95: 8.533015 | AF95: 8.585814 | AG95: 8.639295 | AH95: -0.002893
B97: Total Energy Consumption by End Use 1/
A98: RKI000:ma_SpaceHeating | B98: Space Heating | C98: 6.51761 | D98: 6.579794 | E98: 6.719017 | F98: 6.657437 | G98: 6.610179 | H98: 6.545724 | I98: 6.467808 | J98: 6.396029 | K98: 6.338858 | L98: 6.283124 | M98: 6.23278 | N98: 6.181098 | O98: 6.129976 | P98: 6.083678 | Q98: 6.037023 | R98: 5.996106 | S98: 5.955264 | T98: 5.914248 | U98: 5.876412 | V98: 5.841048 | W98: 5.810057 | X98: 5.778563 | Y98: 5.746598 | Z98: 5.712856 | AA98: 5.676187 | AB98: 5.644627 | AC98: 5.614811 | AD98: 5.584211 | AE98: 5.553601 | AF98: 5.526089 | AG98: 5.498514 | AH98: -0.005652
A99: RKI000:ma_SpaceCooling | B99: Space Cooling | C99: 2.366128 | D99: 2.249679 | E99: 2.527688 | F99: 2.524938 | G99: 2.525652 | H99: 2.517709 | I99: 2.502984 | J99: 2.501515 | K99: 2.518388 | L99: 2.53974 | M99: 2.573649 | N99: 2.604116 | O99: 2.633105 | P99: 2.668165 | Q99: 2.703381 | R99: 2.745875 | S99: 2.789436 | T99: 2.833351 | U99: 2.877506 | V99: 2.924451 | W99: 2.97437 | X99: 3.023025 | Y99: 3.074131 | Z99: 3.12034 | AA99: 3.161524 | AB99: 3.2112 | AC99: 3.26319 | AD99: 3.315017 | AE99: 3.368937 | AF99: 3.428514 | AG99: 3.490087 | AH99: 0.01304
A100: RKI000:ma_WaterHeating | B100: Water Heating | C100: 2.862072 | D100: 2.862111 | E100: 2.869363 | F100: 2.845701 | G100: 2.828674 | H100: 2.804127 | I100: 2.774236 | J100: 2.753495 | K100: 2.745571 | L100: 2.741243 | M100: 2.743793 | N100: 2.743618 | O100: 2.742828 | P100: 2.745957 | Q100: 2.748435 | R100: 2.754554 | S100: 2.760983 | T100: 2.76585 | U100: 2.771141 | V100: 2.77755 | W100: 2.784608 | X100: 2.791183 | Y100: 2.797906 | Z100: 2.802966 | AA100: 2.805055 | AB100: 2.812578 | AC100: 2.821633 | AD100: 2.831316 | AE100: 2.841442 | AF100: 2.855138 | AG100: 2.8691 | AH100: 8.2e-05
A101: RKI000:ma_Refrigeration | B101: Refrigeration | C101: 0.852572 | D101: 0.845705 | E101: 0.840893 | F101: 0.820605 | G101: 0.801767 | H101: 0.781067 | I101: 0.759946 | J101: 0.744354 | K101: 0.735123 | L101: 0.727896 | M101: 0.725242 | N101: 0.722077 | O101: 0.71876 | P101: 0.717409 | Q101: 0.716114 | R101: 0.716546 | S101: 0.717728 | T101: 0.718993 | U101: 0.721295 | V101: 0.725087 | W101: 0.730016 | X101: 0.735631 | Y101: 0.741915 | Z101: 0.746978 | AA101: 0.750205 | AB101: 0.755602 | AC101: 0.761002 | AD101: 0.766082 | AE101: 0.77056 | AF101: 0.775979 | AG101: 0.781167 | AH101: -0.002911
A102: RKI000:ma_Cooking | B102: Cooking | C102: 0.278124 | D102: 0.278138 | E102: 0.278921 | F102: 0.276796 | G102: 0.274794 | H102: 0.272284 | I102: 0.269488 | J102: 0.267548 | K102: 0.266694 | L102: 0.266098 | M102: 0.266262 | N102: 0.266145 | O102: 0.265827 | P102: 0.265911 | Q102: 0.265992 | R102: 0.266436 | S102: 0.267049 | T102: 0.267712 | U102: 0.268426 | V102: 0.269301 | W102: 0.270272 | X102: 0.271245 | Y102: 0.272225 | Z102: 0.272992 | AA102: 0.273433 | AB102: 0.274328 | AC102: 0.275257 | AD102: 0.276157 | AE102: 0.276976 | AF102: 0.278005 | AG102: 0.279024 | AH102: 0.000108
A103: RKI000:ma_ClothesDryers | B103: Clothes Dryers | C103: 0.659492 | D103: 0.670714 | E103: 0.68189 | F103: 0.680783 | G103: 0.680924 | H103: 0.67841 | I103: 0.673794 | J103: 0.672206 | K103: 0.675152 | L103: 0.679175 | M103: 0.686429 | N103: 0.692255 | O103: 0.697333 | P103: 0.703734 | Q103: 0.710006 | R103: 0.717561 | S103: 0.725316 | T103: 0.73229 | U103: 0.739302 | V103: 0.74695 | W103: 0.754931 | X103: 0.76274 | Y103: 0.770518 | Z103: 0.77727 | AA103: 0.782322 | AB103: 0.789428 | AC103: 0.79681 | AD103: 0.80416 | AE103: 0.811327 | AF103: 0.819947 | AG103: 0.828637 | AH103: 0.007639
A104: RKI000:ma_Freezers | B104: Freezers | C104: 0.198212 | D104: 0.197138 | E104: 0.196626 | F104: 0.192518 | G104: 0.188539 | H104: 0.183903 | I104: 0.178972 | J104: 0.175177 | K104: 0.172821 | L104: 0.170865 | M104: 0.169898 | N104: 0.16869 | O104: 0.167319 | P104: 0.166287 | Q104: 0.165155 | R104: 0.164302 | S104: 0.163528 | T104: 0.162685 | U104: 0.161996 | V104: 0.161575 | W104: 0.161339 | X104: 0.161208 | Y104: 0.161178 | Z104: 0.161019 | AA104: 0.160618 | AB104: 0.16084 | AC104: 0.161218 | AD104: 0.161666 | AE104: 0.162018 | AF104: 0.162601 | AG104: 0.163167 | AH104: -0.006464
A105: RKI000:ma_Lighting | B105: Lighting | C105: 0.605238 | D105: 0.586025 | E105: 0.579653 | F105: 0.56731 | G105: 0.558393 | H105: 0.543669 | I105: 0.529051 | J105: 0.519626 | K105: 0.515887 | L105: 0.513932 | M105: 0.508372 | N105: 0.503246 | O105: 0.498649 | P105: 0.495897 | Q105: 0.493726 | R105: 0.493039 | S105: 0.492623 | T105: 0.491866 | U105: 0.491324 | V105: 0.491405 | W105: 0.483605 | X105: 0.477345 | Y105: 0.472304 | Z105: 0.467726 | AA105: 0.463076 | AB105: 0.460413 | AC105: 0.458271 | AD105: 0.456269 | AE105: 0.454297 | AF105: 0.453345 | AG105: 0.452938 | AH105: -0.009616
A106: RKI000:ma_ClothesWasher | B106: Clothes Washers 2/ | C106: 0.105377 | D106: 0.106022 | E106: 0.106973 | F106: 0.105974 | G106: 0.105045 | H106: 0.103745 | I106: 0.102253 | J106: 0.101371 | K106: 0.101248 | L106: 0.101302 | M106: 0.101929 | N106: 0.102362 | O106: 0.102648 | P106: 0.103085 | Q106: 0.1034 | R106: 0.103835 | S106: 0.104252 | T106: 0.104564 | U106: 0.104909 | V106: 0.105366 | W106: 0.105882 | X106: 0.106392 | Y106: 0.106901 | Z106: 0.107243 | AA106: 0.107334 | AB106: 0.107752 | AC106: 0.108188 | AD106: 0.108599 | AE106: 0.108947 | AF106: 0.109452 | AG106: 0.109949 | AH106: 0.001417
A107: RKI000:ma_Dishwashers | B107: Dishwashers 2/ | C107: 0.076259 | D107: 0.077291 | E107: 0.078512 | F107: 0.078269 | G107: 0.078028 | H107: 0.077464 | I107: 0.076702 | J107: 0.076345 | K107: 0.076644 | L107: 0.077167 | M107: 0.078184 | N107: 0.079149 | O107: 0.0801 | P107: 0.081274 | Q107: 0.082464 | R107: 0.083738 | S107: 0.084989 | T107: 0.086144 | U107: 0.087318 | V107: 0.088578 | W107: 0.089883 | X107: 0.091177 | Y107: 0.092465 | Z107: 0.093603 | AA107: 0.094513 | AB107: 0.095703 | AC107: 0.096902 | AD107: 0.098074 | AE107: 0.099183 | AF107: 0.100428 | AG107: 0.101659 | AH107: 0.009629
A108: RKI000:ma_ColorTelevisi | B108: Televisions and Related Equipment 3/ | C108: 0.59918 | D108: 0.587468 | E108: 0.58027 | F108: 0.564214 | G108: 0.551567 | H108: 0.539138 | I108: 0.527435 | J108: 0.520648 | K108: 0.5195 | L108: 0.521034 | M108: 0.52684 | N108: 0.532739 | O108: 0.539176 | P108: 0.547658 | Q108: 0.556541 | R108: 0.566991 | S108: 0.577853 | T108: 0.588187 | U108: 0.598436 | V108: 0.608776 | W108: 0.618627 | X108: 0.627121 | Y108: 0.634326 | Z108: 0.639832 | AA108: 0.643646 | AB108: 0.649126 | AC108: 0.654596 | AD108: 0.659827 | AE108: 0.664728 | AF108: 0.670661 | AG108: 0.67649 | AH108: 0.004053
A109: RKI000:ma_PersonalCompu | B109: Computers and Related Equipment 4/ | C109: 0.248299 | D109: 0.239998 | E109: 0.233472 | F109: 0.223297 | G109: 0.214388 | H109: 0.205396 | I109: 0.19658 | J109: 0.189453 | K109: 0.184189 | L109: 0.179624 | M109: 0.176218 | N109: 0.172504 | O109: 0.168653 | P109: 0.165104 | Q109: 0.161346 | R109: 0.157697 | S109: 0.153821 | T109: 0.149873 | U109: 0.146035 | V109: 0.142369 | W109: 0.138778 | X109: 0.135132 | Y109: 0.131433 | Z109: 0.127512 | AA109: 0.123253 | AB109: 0.119258 | AC109: 0.115164 | AD109: 0.110884 | AE109: 0.106407 | AF109: 0.101846 | AG109: 0.096998 | AH109: -0.030846
... A114: RKI000:ma_TtllOwnUseGen | B114: Total Net Own-use Generation | C114: 20.933901 | D114: 20.953787 | E114: 21.11767 | F114: 20.91 | G114: 20.73641 | H114: 20.501259 | I114: 20.249361 | J114: 20.074984 | K114: 20.014212 | L114: 19.980686 | M114: 20.010036 | N114: 20.016998 | O114: 20.016539 | P114: 20.047495 | Q114: 20.083374 | R114: 20.148874 | S114: 20.216898 | T114: 20.275047 | U114: 20.339113 | V114: 20.42094 | W114: 20.508375 | X114: 20.59341 | Y114: 20.681854 | Z114: 20.749743 | AA114: 20.786196 | AB114: 20.870569 | AC114: 20.96175 | AD114: 21.050432 | AE114: 21.142799 | AF114: 21.262299 | AG114: 21.383919 | AH114: 0.000709
B116: Nonmarketed Renewables 12/
A117: RKI000:na_GeothermalHea | B117: Geothermal Heat Pumps | C117: 0.013036 | D117: 0.015201 | E117: 0.017725 | F117: 0.018765 | G117: 0.020128 | H117: 0.020978 | I117: 0.022219 | J117: 0.02329 | K117: 0.024472 | L117: 0.025659 | M117: 0.02686 | N117: 0.027926 | O117: 0.028994 | P117: 0.030059 | Q117: 0.031076 | R117: 0.032084 | S117: 0.0331 | T117: 0.034097 | U117: 0.035104 | V117: 0.03615 | W117: 0.037255 | X117: 0.038368 | Y117: 0.039507 | Z117: 0.040661 | AA117: 0.041816 | AB117: 0.043009 | AC117: 0.044202 | AD117: 0.045451 | AE117: 0.046683 | AF117: 0.047979 | AG117: 0.049258 | AH117: 0.04531
A118: RKI000:na_SolarHotWater | B118: Solar Hot Water Heating | C118: 0.041923 | D118: 0.0459 | E118: 0.045856 | F118: 0.045132 | G118: 0.044743 | H118: 0.043871 | I118: 0.043569 | J118: 0.043343 | K118: 0.043447 | L118: 0.043559 | M118: 0.044141 | N118: 0.044365 | O118: 0.044488 | P118: 0.044635 | Q118: 0.044823 | R118: 0.044966 | S118: 0.045067 | T118: 0.045217 | U118: 0.045376 | V118: 0.045571 | W118: 0.045716 | X118: 0.04592 | Y118: 0.046134 | Z118: 0.046332 | AA118: 0.046519 | AB118: 0.046729 | AC118: 0.046861 | AD118: 0.046873 | AE118: 0.046947 | AF118: 0.047069 | AG118: 0.046927 | AH118: 0.003766
A119: RKI000:na_SolarPhotovol | B119: Solar Photovoltaic | C119: 0.225073 | D119: 0.259677 | E119: 0.288641 | F119: 0.312461 | G119: 0.337018 | H119: 0.359239 | I119: 0.383723 | J119: 0.409686 | K119: 0.436777 | L119: 0.46326 | M119: 0.496 | N119: 0.523722 | O119: 0.55119 | P119: 0.579765 | Q119: 0.609985 | R119: 0.640008 | S119: 0.669855 | T119: 0.700877 | U119: 0.731649 | V119: 0.764556 | W119: 0.797295 | X119: 0.831853 | Y119: 0.867645 | Z119: 0.903495 | AA119: 0.940947 | AB119: 0.980271 | AC119: 1.018873 | AD119: 1.055044 | AE119: 1.093461 | AF119: 1.133643 | AG119: 1.168608 | AH119: 0.05644
A120: RKI000:na_WindHuffPuff | B120: Wind | C120: 0.000173 | D120: 0.000174 | E120: 0.000173 | F120: 0.000169 | G120: 0.000167 | H120: 0.000162 | I120: 0.00016 | J120: 0.000159 | K120: 0.000158 | L120: 0.000158 | M120: 0.000158 | N120: 0.000158 | O120: 0.000157 | P120: 0.000157 | Q120: 0.000157 | R120: 0.000156 | S120: 0.000156 | T120: 0.000156 | U120: 0.000155 | V120: 0.000155 | W120: 0.000156 | X120: 0.000158 | Y120: 0.00016 | Z120: 0.000161 | AA120: 0.000163 | AB120: 0.000165 | AC120: 0.000166 | AD120: 0.000168 | AE120: 0.000169 | AF120: 0.000171 | AG120: 0.000173 | AH120: 1.6e-05
A121: RKI000:na_Total | B121: Total | C121: 0.280204 | D121: 0.320951 | E121: 0.352396 | F121: 0.376527 | G121: 0.402057 | H121: 0.42425 | I121: 0.449671 | J121: 0.476478 | K121: 0.504854 | L121: 0.532635 | M121: 0.56716 | N121: 0.59617 | O121: 0.62483 | P121: 0.654616 | Q121: 0.686041 | R121: 0.717214 | S121: 0.748178 | T121: 0.780346 | U121: 0.812283 | V121: 0.846432 | W121: 0.880422 | X121: 0.916299 | Y121: 0.953445 | Z121: 0.990649 | AA121: 1.029446 | AB121: 1.070174 | AC121: 1.110102 | AD121: 1.147535 | AE121: 1.18726 | AF121: 1.228862 | AG121: 1.264965 | AH121: 0.051526
B123: Heating Degree Days
A124: RKI000:hdd_NewEngland | B124: New England | C124: 5958 | D124: 6244 | E124: 6198 | F124: 6187 | G124: 6176 | H124: 6165 | I124: 6153 | J124: 6142 | K124: 6130 | L124: 6118 | M124: 6107 | N124: 6095 | O124: 6083 | P124: 6071 | Q124: 6059 | R124: 6048 | S124: 6036 | T124: 6024 | U124: 6012 | V124: 6000 | W124: 5988 | X124: 5976 | Y124: 5964 | Z124: 5952 | AA124: 5940 | AB124: 5929 | AC124: 5917 | AD124: 5905 | AE124: 5893 | AF124: 5881 | AG124: 5869 | AH124: -0.000502
A125: RKI000:hdd_MiddleAtlant | B125: Middle Atlantic | C125: 5371 | D125: 5595 | E125: 5569 | F125: 5558 | G125: 5548 | H125: 5538 | I125: 5528 | J125: 5517 | K125: 5507 | L125: 5497 | M125: 5487 | N125: 5477 | O125: 5467 | P125: 5457 | Q125: 5446 | R125: 5436 | S125: 5426 | T125: 5416 | U125: 5406 | V125: 5396 | W125: 5386 | X125: 5376 | Y125: 5366 | Z125: 5355 | AA125: 5345 | AB125: 5335 | AC125: 5325 | AD125: 5315 | AE125: 5305 | AF125: 5295 | AG125: 5285 | AH125: -0.000538
A126: RKI000:hdd_EastNorthCen | B126: East North Central | C126: 6000 | D126: 6217 | E126: 6172 | F126: 6167 | G126: 6163 | H126: 6159 | I126: 6155 | J126: 6151 | K126: 6147 | L126: 6143 | M126: 6138 | N126: 6134 | O126: 6130 | P126: 6126 | Q126: 6122 | R126: 6118 | S126: 6114 | T126: 6109 | U126: 6105 | V126: 6101 | W126: 6097 | X126: 6093 | Y126: 6089 | Z126: 6084 | AA126: 6080 | AB126: 6076 | AC126: 6072 | AD126: 6068 | AE126: 6064 | AF126: 6059 | AG126: 6055 | AH126: 0.000304
A127: RKI000:hdd_WestNorthCen | B127: West North Central | C127: 6410 | D127: 6529 | E127: 6490 | F127: 6489 | G127: 6487 | H127: 6485 | I127: 6483 | J127: 6481 | K127: 6479 | L127: 6477 | M127: 6474 | N127: 6472 | O127: 6470 | P127: 6467 | Q127: 6465 | R127: 6462 | S127: 6459 | T127: 6457 | U127: 6454 | V127: 6451 | W127: 6449 | X127: 6446 | Y127: 6443 | Z127: 6440 | AA127: 6437 | AB127: 6434 | AC127: 6431 | AD127: 6428 | AE127: 6426 | AF127: 6423 | AG127: 6420 | AH127: 5.2e-05
A128: RKI000:hdd_SouthAtlantc | B128: South Atlantic | C128: 2335 | D128: 2486 | E128: 2520 | F128: 2511 | G128: 2503 | H128: 2495 | I128: 2487 | J128: 2479 | K128: 2471 | L128: 2463 | M128: 2455 | N128: 2448 | O128: 2440 | P128: 2432 | Q128: 2424 | R128: 2417 | S128: 2409 | T128: 2401 | U128: 2393 | V128: 2385 | W128: 2378 | X128: 2370 | Y128: 2362 | Z128: 2355 | AA128: 2347 | AB128: 2339 | AC128: 2332 | AD128: 2324 | AE128: 2316 | AF128: 2309 | AG128: 2301 | AH128: -0.000489
A129: RKI000:hdd_EastSouthCen | B129: East South Central | C129: 3119 | D129: 3304 | E129: 3319 | F129: 3314 | G129: 3310 | H129: 3306 | I129: 3302 | J129: 3297 | K129: 3293 | L129: 3288 | M129: 3284 | N129: 3280 | O129: 3275 | P129: 3271 | Q129: 3266 | R129: 3262 | S129: 3257 | T129: 3252 | U129: 3248 | V129: 3243 | W129: 3238 | X129: 3234 | Y129: 3229 | Z129: 3224 | AA129: 3220 | AB129: 3215 | AC129: 3210 | AD129: 3206 | AE129: 3201 | AF129: 3196 | AG129: 3191 | AH129: 0.000761
A130: RKI000:hdd_WestSouthCen | B130: West South Central | C130: 1829 | D130: 1910 | E130: 2015 | F130: 2009 | G130: 2004 | H130: 1999 | I130: 1994 | J130: 1988 | K130: 1983 | L130: 1978 | M130: 1973 | N130: 1967 | O130: 1962 | P130: 1957 | Q130: 1952 | R130: 1947 | S130: 1942 | T130: 1937 | U130: 1932 | V130: 1927 | W130: 1922 | X130: 1917 | Y130: 1912 | Z130: 1907 | AA130: 1902 | AB130: 1897 | AC130: 1892 | AD130: 1887 | AE130: 1882 | AF130: 1877 | AG130: 1873 | AH130: 0.000793
...

Sheet AEO 2019_Table 5
B1: highogs.d120120a | C1: 2020 | D1: 2021 | E1: 2022 | F1: 2023 | G1: 2024 | H1: 2025 | I1: 2026 | J1: 2027 | K1: 2028 | L1: 2029 | M1: 2030 | N1: 2031 | O1: 2032 | P1: 2033 | Q1: 2034 | R1: 2035 | S1: 2036 | T1: 2037 | U1: 2038 | V1: 2039 | W1: 2040 | X1: 2041 | Y1: 2042 | Z1: 2043 | AA1: 2044 | AB1: 2045 | AC1: 2046 | AD1: 2047 | AE1: 2048 | AF1: 2049 | AG1: 2050
C3: Report | D3: Annual Energy Outlook 2021
C4: Scenario | D4: ref2021 | G4: Reference case
C5: Datekey | D5: d113020a
C6: Release Date | E6: January 2021
A10: CKI000 | B10: 5. Commercial Sector Key Indicators and Consumption | AH10: Compound
B11: (quadrillion Btu, unless otherwise noted) | AH11: Growth
AH12: 2020-2050
B13: Key Indicators and Consumption | C13: 2020 | D13: 2021 | E13: 2022 | F13: 2023 | G13: 2024 | H13: 2025 | I13: 2026 | J13: 2027 | K13: 2028 | L13: 2029 | M13: 2030 | N13: 2031 | O13: 2032 | P13: 2033 | Q13: 2034 | R13: 2035 | S13: 2036 | T13: 2037 | U13: 2038 | V13: 2039 | W13: 2040 | X13: 2041 | Y13: 2042 | Z13: 2043 | AA13: 2044 | AB13: 2045 | AC13: 2046 | AD13: 2047 | AE13: 2048 | AF13: 2049 | AG13: 2050 | AH13: (percent)
B15: Key Indicators
B17: Total Floorspace (billion square feet)
A18: CKI000:da_Surviving | B18: Surviving | C18: 91.743568 | D18: 92.493767 | E18: 93.426628 | F18: 94.241493 | G18: 95.189041 | H18: 96.214439 | I18: 97.251869 | J18: 98.274696 | K18: 99.282448 | L18: 100.27715 | M18: 101.25889 | N18: 102.24216 | O18: 103.24239 | P18: 104.26911 | Q18: 105.31145 | R18: 106.36074 | S18: 107.40666 | T18: 108.43839 | U18: 109.44685 | V18: 110.44609 | W18: 111.44925 | X18: 112.47022 | Y18: 113.50256 | Z18: 114.54393 | AA18: 115.59248 | AB18: 116.6426 | AC18: 117.70586 | AD18: 118.77532 | AE18: 119.83874 | AF18: 120.90787 | AG18: 121.97993 | AH18: 0.009541
A19: CKI000:da_NewAdditions | B19: New Additions | C19: 1.838832 | D19: 2.029895 | E19: 1.920078 | F19: 2.061501 | G19: 2.148808 | H19: 2.170696 | I19: 2.166135 | J19: 2.161175 | K19: 2.158285 | L19: 2.155443 | M19: 2.167129 | N19: 2.194356 | O19: 2.231306 | P19: 2.257577 | Q19: 2.275329 | R19: 2.28282 | S19: 2.279454 | T19: 2.26694 | U19: 2.268399 | V19: 2.282958 | W19: 2.311536 | X19: 2.333751 | Y19: 2.353738 | Z19: 2.371938 | AA19: 2.384594 | AB19: 2.408923 | AC19: 2.426404 | AD19: 2.431646 | AE19: 2.448693 | AF19: 2.46304 | AG19: 2.474073 | AH19: 0.00994
A20: CKI000:da_Total | B20: Total | C20: 93.582397 | D20: 94.523659 | E20: 95.34671 | F20: 96.302994 | G20: 97.337845 | H20: 98.385132 | I20: 99.418007 | J20: 100.43587 | K20: 101.44074 | L20: 102.43259 | M20: 103.42602 | N20: 104.43652 | O20: 105.4737 | P20: 106.52669 | Q20: 107.58678 | R20: 108.64356 | S20: 109.68612 | T20: 110.70533 | U20: 111.71525 | V20: 112.72905 | W20: 113.76079 | X20: 114.80397 | Y20: 115.85629 | Z20: 116.91587 | AA20: 117.97708 | AB20: 119.05152 | AC20: 120.13227 | AD20: 121.20697 | AE20: 122.28743 | AF20: 123.37091 | AG20: 124.454 | AH20: 0.009548
B22: Energy Consumption Intensity
B23: (thousand Btu per square foot)
A24: CKI000:ea_DeliveredEner | B24: Gross End-use Consumption 1/ | C24: 92.874619 | D24: 94.294548 | E24: 94.450386 | F24: 95.745605 | G24: 96.57914 | H24: 97.300018 | I24: 96.721397 | J24: 96.050079 | K24: 95.358665 | L24: 94.638687 | M24: 93.739624 | N24: 92.984718 | O24: 92.321533 | P24: 91.710487 | Q24: 91.153137 | R24: 90.682869 | S24: 90.265137 | T24: 89.870987 | U24: 89.506485 | V24: 89.175758 | W24: 88.824623 | X24: 88.516159 | Y24: 88.219269 | Z24: 87.951149 | AA24: 87.70002 | AB24: 87.469574 | AC24: 87.278946 | AD24: 87.134293 | AE24: 87.040024 | AF24: 86.972649 | AG24: 86.917885 | AH24: -0.002207
A25: CKI000:ea_ElectricityRe | B25: Delivered Energy Consumption | C25: 91.926216 | D25: 93.2285 | E25: 93.30925 | F25: 94.569321 | G25: 95.378639 | H25: 96.045639 | I25: 95.439926 | J25: 94.708832 | K25: 93.98455 | L25: 93.232414 | M25: 92.306175 | N25: 91.506004 | O25: 90.829536 | P25: 90.18959 | Q25: 89.60585 | R25: 89.103523 | S25: 88.633148 | T25: 88.210899 | U25: 87.809647 | V25: 87.444687 | W25: 87.057007 | X25: 86.716454 | Y25: 86.387978 | Z25: 86.089035 | AA25: 85.813766 | AB25: 85.553154 | AC25: 85.314499 | AD25: 85.154808 | AE25: 85.049713 | AF25: 84.980927 | AG25: 84.917252 | AH25: -0.00264
B27: Energy Consumption by Fuel
B28: Electricity 1/
A29: CKI000:ga_SpaceHeating | B29: Space Heating 2/ | C29: 0.113108 | D29: 0.115901 | E29: 0.114781 | F29: 0.114161 | G29: 0.113685 | H29: 0.113128 | I29: 0.112423 | J29: 0.111519 | K29: 0.110527 | L29: 0.109465 | M29: 0.108322 | N29: 0.107237 | O29: 0.106139 | P29: 0.105024 | Q29: 0.103927 | R29: 0.102731 | S29: 0.101536 | T29: 0.10032 | U29: 0.099072 | V29: 0.097779 | W29: 0.096483 | X29: 0.095223 | Y29: 0.09393 | Z29: 0.092609 | AA29: 0.091305 | AB29: 0.089989 | AC29: 0.088691 | AD29: 0.08739 | AE29: 0.086103 | AF29: 0.08483 | AG29: 0.083563 | AH29: -0.010041
A30: CKI000:ga_SpaceCooling | B30: Space Cooling 2/ | C30: 0.530484 | D30: 0.499401 | E30: 0.54127 | F30: 0.545801 | G30: 0.551193 | H30: 0.55642 | I30: 0.560966 | J30: 0.565015 | K30: 0.568864 | L30: 0.572538 | M30: 0.575713 | N30: 0.579738 | O30: 0.584247 | P30: 0.589036 | Q30: 0.594343 | R30: 0.600357 | S30: 0.606459 | T30: 0.612681 | U30: 0.618844 | V30: 0.625016 | W30: 0.631119 | X30: 0.637669 | Y30: 0.644832 | Z30: 0.652012 | AA30: 0.659692 | AB30: 0.667424 | AC30: 0.675522 | AD30: 0.683842 | AE30: 0.692972 | AF30: 0.702404 | AG30: 0.712138 | AH30: 0.009864
A31: CKI000:ga_WaterHeating | B31: Water Heating 2/ | C31: 0.025259 | D31: 0.024811 | E31: 0.024422 | F31: 0.024157 | G31: 0.023959 | H31: 0.023758 | I31: 0.023536 | J31: 0.02329 | K31: 0.023034 | L31: 0.022773 | M31: 0.022514 | N31: 0.022267 | O31: 0.022035 | P31: 0.021814 | Q31: 0.021606 | R31: 0.02141 | S31: 0.021221 | T31: 0.021029 | U31: 0.02083 | V31: 0.020631 | W31: 0.020436 | X31: 0.020262 | Y31: 0.020094 | Z31: 0.01993 | AA31: 0.01977 | AB31: 0.019612 | AC31: 0.019457 | AD31: 0.019306 | AE31: 0.019164 | AF31: 0.019032 | AG31: 0.0189 | AH31: -0.00962
A32: CKI000:ga_Ventilation | B32: Ventilation | C32: 0.505827 | D32: 0.501606 | E32: 0.498216 | F32: 0.497024 | G32: 0.497277 | H32: 0.497199 | I32: 0.488625 | J32: 0.480246 | K32: 0.472302 | L32: 0.464968 | M32: 0.457587 | N32: 0.450991 | O32: 0.445115 | P32: 0.439769 | Q32: 0.435185 | R32: 0.431223 | S32: 0.427859 | T32: 0.424901 | U32: 0.422213 | V32: 0.419847 | W32: 0.416772 | X32: 0.414367 | Y32: 0.412405 | Z32: 0.410821 | AA32: 0.409666 | AB32: 0.40885 | AC32: 0.40842 | AD32: 0.408362 | AE32: 0.408748 | AF32: 0.409595 | AG32: 0.410734 | AH32: -0.006918
A33: CKI000:ga_Cooking | B33: Cooking | C33: 0.084765 | D33: 0.08411 | E33: 0.083669 | F33: 0.083581 | G33: 0.083671 | H33: 0.083723 | I33: 0.083681 | J33: 0.083544 | K33: 0.083345 | L33: 0.083091 | M33: 0.082788 | N33: 0.082505 | O33: 0.082243 | P33: 0.081996 | Q33: 0.081771 | R33: 0.081555 | S33: 0.08133 | T33: 0.081078 | U33: 0.080789 | V33: 0.080484 | W33: 0.08018 | X33: 0.079951 | Y33: 0.079723 | Z33: 0.079502 | AA33: 0.079275 | AB33: 0.079035 | AC33: 0.078794 | AD33: 0.078551 | AE33: 0.078322 | AF33: 0.078112 | AG33: 0.07789 | AH33: -0.002816
A34: CKI000:ga_Lighting | B34: Lighting | C34: 0.534773 | D34: 0.518426 | E34: 0.505123 | F34: 0.495132 | G34: 0.487166 | H34: 0.480211 | I34: 0.474199 | J34: 0.468797 | K34: 0.461557 | L34: 0.454545 | M34: 0.440337 | N34: 0.428149 | O34: 0.417524 | P34: 0.408416 | Q34: 0.400732 | R34: 0.394175 | S34: 0.388692 | T34: 0.383917 | U34: 0.379658 | V34: 0.375877 | W34: 0.370444 | X34: 0.366245 | Y34: 0.362688 | Z34: 0.359474 | AA34: 0.356838 | AB34: 0.35471 | AC34: 0.353074 | AD34: 0.351922 | AE34: 0.351265 | AF34: 0.351075 | AG34: 0.351211 | AH34: -0.013917
A35: CKI000:ga_Refrigeration | B35: Refrigeration | C35: 0.652675 | D35: 0.648219 | E35: 0.644071 | F35: 0.642537 | G35: 0.642707 | H35: 0.643651 | I35: 0.644886 | J35: 0.646186 | K35: 0.647552 | L35: 0.649011 | M35: 0.648711 | N35: 0.649393 | O35: 0.650647 | P35: 0.652299 | Q35: 0.654344 | R35: 0.656709 | S35: 0.659267 | T35: 0.661808 | U35: 0.664277 | V35: 0.666836 | W35: 0.669189 | X35: 0.672484 | Y35: 0.675959 | Z35: 0.679569 | AA35: 0.68328 | AB35: 0.687102 | AC35: 0.691051 | AD35: 0.69504 | AE35: 0.699162 | AF35: 0.703397 | AG35: 0.707571 | AH35: 0.002696
A36: CKI000:ga_OfficeEquipme | B36: Computing | C36: 0.330159 | D36: 0.325755 | E36: 0.321981 | F36: 0.319435 | G36: 0.317918 | H36: 0.317215 | I36: 0.316841 | J36: 0.317254 | K36: 0.318512 | L36: 0.320179 | M36: 0.321813 | N36: 0.324377 | O36: 0.327493 | P36: 0.330646 | Q36: 0.33386 | R36: 0.337607 | S36: 0.341369 | T36: 0.345087 | U36: 0.34878 | V36: 0.351958 | W36: 0.355182 | X36: 0.358437 | Y36: 0.360651 | Z36: 0.362867 | AA36: 0.36399 | AB36: 0.364547 | AC36: 0.364524 | AD36: 0.363883 | AE36: 0.361507 | AF36: 0.358495 | AG36: 0.353638 | AH36: 0.002293
A37: CKI000:ha_OfficeEquipme | B37: Office Equipment | C37: 0.435086 | D37: 0.455255 | E37: 0.474626 | F37: 0.493633 | G37: 0.512342 | H37: 0.53011 | I37: 0.546927 | J37: 0.562448 | K37: 0.576945 | L37: 0.590697 | M37: 0.603772 | N37: 0.616219 | O37: 0.62873 | P37: 0.640668 | Q37: 0.652534 | R37: 0.664258 | S37: 0.67603 | T37: 0.687462 | U37: 0.699179 | V37: 0.711024 | W37: 0.723714 | X37: 0.736914 | Y37: 0.750903 | Z37: 0.765677 | AA37: 0.781526 | AB37: 0.798532 | AC37: 0.816726 | AD37: 0.83668 | AE37: 0.858232 | AF37: 0.881412 | AG37: 0.906807 | AH37: 0.024782
A38: CKI000:ha_OtherUses | B38: Other Uses 3/ | C38: 1.212048 | D38: 1.322887 | E38: 1.39411 | F38: 1.464612 | G38: 1.536923 | H38: 1.60941 | I38: 1.625645 | J38: 1.643251 | K38: 1.661111 | L38: 1.679179 | M38: 1.697602 | N38: 1.716557 | O38: 1.736895 | P38: 1.758069 | Q38: 1.780321 | R38: 1.803553 | S38: 1.827615 | T38: 1.852653 | U38: 1.878494 | V38: 1.90567 | W38: 1.934408 | X38: 1.96481 | Y38: 1.996669 | Z38: 2.030749 | AA38: 2.066134 | AB38: 2.103584 | AC38: 2.142973 | AD38: 2.184314 | AE38: 2.228035 | AF38: 2.274116 | AG38: 2.322687 | AH38: 0.021917
A39: CKI000:ha_ElecSubtotal | B39: Electricity Subtotal | C39: 4.424184 | D39: 4.496373 | E39: 4.602268 | F39: 4.680073 | G39: 4.76684 | H39: 4.854825 | I39: 4.877728 | J39: 4.90155 | K39: 4.923748 | L39: 4.946447 | M39: 4.959159 | N39: 4.977432 | O39: 5.001067 | P39: 5.027737 | Q39: 5.058623 | R39: 5.093579 | S39: 5.131377 | T39: 5.170936 | U39: 5.212136 | V39: 5.255121 | W39: 5.297927 | X39: 5.346361 | Y39: 5.397854 | Z39: 5.45321 | AA39: 5.511477 | AB39: 5.573385 | AC39: 5.639232 | AD39: 5.70929 | AE39: 5.783511 | AF39: 5.862469 | AG39: 5.945138 | AH39: 0.009898
A40: CKI000:ha_OwnGeneration | B40: Onsite Generation for Own Use | C40: 0.088754 | D40: 0.100767 | E40: 0.108803 | F40: 0.11328 | G40: 0.116855 | H40: 0.123412 | I40: 0.127401 | J40: 0.13471 | K40: 0.139391 | L40: 0.144049 | M40: 0.148256 | N40: 0.154432 | O40: 0.157366 | P40: 0.162016 | Q40: 0.166467 | R40: 0.171586 | S40: 0.179007 | T40: 0.183781 | U40: 0.189563 | V40: 0.195143 | W40: 0.201085 | X40: 0.206613 | Y40: 0.212167 | Z40: 0.21771 | AA40: 0.222534 | AB40: 0.228152 | AC40: 0.235994 | AD40: 0.239927 | AE40: 0.24339 | AF40: 0.24572 | AG40: 0.248986 | AH40: 0.034982
A41: CKI000:ha_PurchasedElec | B41: Purchased Electricity | C41: 4.33543 | D41: 4.395605 | E41: 4.493466 | F41: 4.566792 | G41: 4.649986 | H41: 4.731413 | I41: 4.750327 | J41: 4.766841 | K41: 4.784356 | L41: 4.802398 | M41: 4.810903 | N41: 4.823 | O41: 4.8437 | P41: 4.865721 | Q41: 4.892156 | R41: 4.921993 | S41: 4.952371 | T41: 4.987155 | U41: 5.022573 | V41: 5.059978 | W41: 5.096842 | X41: 5.139748 | Y41: 5.185687 | Z41: 5.2355 | AA41: 5.288943 | AB41: 5.345232 | AC41: 5.403239 | AD41: 5.469363 | AE41: 5.540121 | AF41: 5.616748 | AG41: 5.696152 | AH41: 0.00914
B43: Natural Gas
A44: CKI000:ia_SpaceHeating | B44: Space Heating 2/ | C44: 1.772856 | D44: 1.831843 | E44: 1.827382 | F44: 1.834553 | G44: 1.855115 | H44: 1.86914 | I44: 1.873803 | J44: 1.871754 | K44: 1.868644 | L44: 1.862351 | M44: 1.852769 | N44: 1.846887 | O44: 1.843503 | P44: 1.840334 | Q44: 1.837623 | R44: 1.836205 | S44: 1.834901 | T44: 1.83278 | U44: 1.830921 | V44: 1.829187 | W44: 1.827238 | X44: 1.824652 | Y44: 1.820829 | Z44: 1.816435 | AA44: 1.811472 | AB44: 1.80613 | AC44: 1.800939 | AD44: 1.795927 | AE44: 1.791825 | AF44: 1.786999 | AG44: 1.780834 | AH44: 0.00015
A45: CKI000:ia_SpaceCooling | B45: Space Cooling 2/ | C45: 0.027616 | D45: 0.023902 | E45: 0.026169 | F45: 0.026034 | G45: 0.026061 | H45: 0.026022 | I45: 0.025873 | J45: 0.025704 | K45: 0.025539 | L45: 0.025346 | M45: 0.025099 | N45: 0.02491 | O45: 0.024765 | P45: 0.024636 | Q45: 0.024524 | R45: 0.024442 | S45: 0.024374 | T45: 0.024314 | U45: 0.024268 | V45: 0.024244 | W45: 0.024221 | X45: 0.024191 | Y45: 0.024163 | Z45: 0.024128 | AA45: 0.024106 | AB45: 0.02409 | AC45: 0.024081 | AD45: 0.024089 | AE45: 0.024138 | AF45: 0.024176 | AG45: 0.024209 | AH45: -0.00438
A46: CKI000:ia_WaterHeating | B46: Water Heating 2/ | C46: 0.612486 | D46: 0.611184 | E46: 0.6105 | F46: 0.615428 | G46: 0.624619 | H46: 0.63198 | I46: 0.636733 | J46: 0.639746 | K46: 0.642558 | L46: 0.644514 | M46: 0.644026 | N46: 0.645122 | O46: 0.647698 | P46: 0.651031 | Q46: 0.654777 | R46: 0.659081 | S46: 0.663584 | T46: 0.667906 | U46: 0.672367 | V46: 0.67705 | W46: 0.68181 | X46: 0.686683 | Y46: 0.691272 | Z46: 0.695826 | AA46: 0.700267 | AB46: 0.704726 | AC46: 0.709345 | AD46: 0.714105 | AE46: 0.719327 | AF46: 0.724421 | AG46: 0.729048 | AH46: 0.005824
A47: CKI000:ia_Cooking | B47: Cooking | C47: 0.344411 | D47: 0.346069 | E47: 0.348805 | F47: 0.354585 | G47: 0.362601 | H47: 0.369714 | I47: 0.375491 | J47: 0.380341 | K47: 0.384956 | L47: 0.389017 | M47: 0.391078 | N47: 0.394165 | O47: 0.398085 | P47: 0.402538 | Q47: 0.407136 | R47: 0.411987 | S47: 0.416853 | T47: 0.421536 | U47: 0.426165 | V47: 0.430864 | W47: 0.435601 | X47: 0.440561 | Y47: 0.445352 | Z47: 0.45011 | AA47: 0.454769 | AB47: 0.459433 | AC47: 0.464175 | AD47: 0.468894 | AE47: 0.473821 | AF47: 0.47866 | AG47: 0.48319 | AH47: 0.01135
A48: CKI000:ia_OtherUses | B48: Other Uses 4/ | C48: 0.55567 | D48: 0.609088 | E48: 0.580644 | F48: 0.693526 | G48: 0.741611 | H48: 0.787225 | I48: 0.789477 | J48: 0.790011 | K48: 0.790203 | L48: 0.789708 | M48: 0.788681 | N48: 0.788469 | O48: 0.788847 | P48: 0.789711 | Q48: 0.790612 | R48: 0.792051 | S48: 0.793585 | T48: 0.795144 | U48: 0.796932 | V48: 0.798947 | W48: 0.80098 | X48: 0.802606 | Y48: 0.803938 | Z48: 0.805425 | AA48: 0.806672 | AB48: 0.807976 | AC48: 0.809443 | AD48: 0.810968 | AE48: 0.812839 | AF48: 0.814654 | AG48: 0.816157 | AH48: 0.012897
A49: CKI000:ia_DeliveredEner | B49: Delivered Energy | C49: 3.313039 | D49: 3.422087 | E49: 3.393499 | F49: 3.524127 | G49: 3.610008 | H49: 3.684081 | I49: 3.701378 | J49: 3.707556 | K49: 3.7119 | L49: 3.710937 | M49: 3.701653 | N49: 3.699553 | O49: 3.702897 | P49: 3.708249 | Q49: 3.714673 | R49: 3.723764 | S49: 3.733297 | T49: 3.74168 | U49: 3.750653 | V49: 3.760292 | W49: 3.76985 | X49: 3.778692 | Y49: 3.785554 | Z49: 3.791923 | AA49: 3.797285 | AB49: 3.802355 | AC49: 3.807984 | AD49: 3.813983 | AE49: 3.821949 | AF49: 3.828911 | AG49: 3.833438 | AH49: 0.004875
B51: Distillate Fuel Oil
A52: CKI000:ja_SpaceHeating | B52: Space Heating 2/ | C52: 0.216543 | D52: 0.229024 | E52: 0.22828 | F52: 0.225781 | G52: 0.223931 | H52: 0.223321 | I52: 0.222513 | J52: 0.220847 | K52: 0.218492 | L52: 0.215848 | M52: 0.213216 | N52: 0.21102 | O52: 0.208797 | P52: 0.206669 | Q52: 0.204562 | R52: 0.202782 | S52: 0.201278 | T52: 0.199415 | U52: 0.197208 | V52: 0.195288 | W52: 0.192921 | X52: 0.190644 | Y52: 0.188422 | Z52: 0.18626 | AA52: 0.184053 | AB52: 0.181699 | AC52: 0.179448 | AD52: 0.177269 | AE52: 0.175228 | AF52: 0.173049 | AG52: 0.170837 | AH52: -0.007872
A53: CKI000:ja_WaterHeating | B53: Water Heating 2/ | C53: 0.006524 | D53: 0.006581 | E53: 0.006587 | F53: 0.006542 | G53: 0.006527 | H53: 0.006554 | I53: 0.00657 | J53: 0.006555 | K53: 0.006513 | L53: 0.006461 | M53: 0.006406 | N53: 0.006363 | O53: 0.006324 | P53: 0.006291 | Q53: 0.006259 | R53: 0.006236 | S53: 0.006221 | T53: 0.006193 | U53: 0.006155 | V53: 0.006126 | W53: 0.006088 | X53: 0.006053 | Y53: 0.00602 | Z53: 0.005989 | AA53: 0.005956 | AB53: 0.005919 | AC53: 0.005885 | AD53: 0.005853 | AE53: 0.005827 | AF53: 0.005795 | AG53: 0.005763 | AH53: -0.004125
A54: CKI000:ja_OtherUses | B54: Other Uses 5/ | C54: 0.086303 | D54: 0.085565 | E54: 0.09808 | F54: 0.100283 | G54: 0.102809 | H54: 0.106009 | I54: 0.107263 | J54: 0.107885 | K54: 0.108032 | L54: 0.107989 | M54: 0.107421 | N54: 0.107156 | O54: 0.107033 | P54: 0.107168 | Q54: 0.107361 | R54: 0.107757 | S54: 0.108346 | T54: 0.108744 | U54: 0.108942 | V54: 0.109332 | W54: 0.109478 | X54: 0.109621 | Y54: 0.109806 | Z54: 0.110033 | AA54: 0.110218 | AB54: 0.110304 | AC54: 0.110468 | AD54: 0.110692 | AE54: 0.110995 | AF54: 0.111206 | AG54: 0.111432 | AH54: 0.008555
A55: CKI000:ja_DeliveredEner | B55: Delivered Energy | C55: 0.30937 | D55: 0.32117 | E55: 0.332947 | F55: 0.332606 | G55: 0.333267 | H55: 0.335884 | I55: 0.336347 | J55: 0.335287 | K55: 0.333038 | L55: 0.330298 | M55: 0.327043 | N55: 0.324539 | O55: 0.322154 | P55: 0.320127 | Q55: 0.318182 | R55: 0.316775 | S55: 0.315844 | T55: 0.314352 | U55: 0.312305 | V55: 0.310746 | W55: 0.308487 | X55: 0.306318 | Y55: 0.304248 | Z55: 0.302282 | AA55: 0.300228 | AB55: 0.297922 | AC55: 0.295801 | AD55: 0.293814 | AE55: 0.29205 | AF55: 0.29005 | AG55: 0.288032 | AH55: -0.002379
A57: CKI000:ka_MarketedRenew | B57: Marketed Renewables (biomass) | C57: 0.131216 | D57: 0.131216 | E57: 0.131216 | F57: 0.131216 | G57: 0.131216 | H57: 0.131216 | I57: 0.131216 | J57: 0.131216 | K57: 0.131216 | L57: 0.131216 | M57: 0.131216 | N57: 0.131216 | O57: 0.131216 | P57: 0.131216 | Q57: 0.131216 | R57: 0.131216 | S57: 0.131216 | T57: 0.131216 | U57: 0.131216 | V57: 0.131216 | W57: 0.131216 | X57: 0.131216 | Y57: 0.131216 | Z57: 0.131216 | AA57: 0.131216 | AB57: 0.131216 | AC57: 0.131216 | AD57: 0.131216 | AE57: 0.131216 | AF57: 0.131216 | AG57: 0.131216 | AH57: 0
A58: CKI000:ka_OtherFuels | B58: Other Fuels 6/ | C58: 0.51362 | D58: 0.542221 | E58: 0.545603 | F58: 0.552567 | G58: 0.559474 | H58: 0.566869 | I58: 0.569179 | J58: 0.571263 | K58: 0.573353 | L58: 0.575188 | M58: 0.576045 | N58: 0.57826 | O58: 0.580159 | P58: 0.582284 | Q58: 0.584179 | R58: 0.586774 | S58: 0.589098 | T58: 0.591013 | U58: 0.592929 | V58: 0.595323 | W58: 0.597279 | X58: 0.59942 | Y58: 0.601885 | Z58: 0.604254 | AA58: 0.606386 | AB58: 0.608507 | AC58: 0.610785 | AD58: 0.61298 | AE58: 0.615175 | AF58: 0.61725 | AG58: 0.619454 | AH58: 0.006265
B60: Energy Consumption by End Use 1/
A61: CKI000:la_SpaceHeating | B61: Space Heating 2/ | C61: 2.102507 | D61: 2.176769 | E61: 2.170443 | F61: 2.174495 | G61: 2.192731 | H61: 2.205589 | I61: 2.208739 | J61: 2.204119 | K61: 2.197663 | L61: 2.187665 | M61: 2.174307 | N61: 2.165144 | O61: 2.158438 | P61: 2.152026 | Q61: 2.146112 | R61: 2.141718 | S61: 2.137715 | T61: 2.132515 | U61: 2.127201 | V61: 2.122253 | W61: 2.116642 | X61: 2.110519 | Y61: 2.103181 | Z61: 2.095303 | AA61: 2.08683 | AB61: 2.077818 | AC61: 2.069078 | AD61: 2.060586 | AE61: 2.053157 | AF61: 2.044878 | AG61: 2.035234 | AH61: -0.001083
A62: CKI000:la_SpaceCooling | B62: Space Cooling 2/ | C62: 0.5581 | D62: 0.523304 | E62: 0.567438 | F62: 0.571835 | G62: 0.577254 | H62: 0.582442 | I62: 0.586839 | J62: 0.590719 | K62: 0.594403 | L62: 0.597884 | M62: 0.600812 | N62: 0.604647 | O62: 0.609012 | P62: 0.613672 | Q62: 0.618867 | R62: 0.624799 | S62: 0.630832 | T62: 0.636995 | U62: 0.643112 | V62: 0.64926 | W62: 0.655339 | X62: 0.661859 | Y62: 0.668995 | Z62: 0.67614 | AA62: 0.683797 | AB62: 0.691514 | AC62: 0.699603 | AD62: 0.707931 | AE62: 0.71711 | AF62: 0.72658 | AG62: 0.736347 | AH62: 0.009282
A63: CKI000:la_WaterHeating | B63: Water Heating 2/ | C63: 0.644268 | D63: 0.642577 | E63: 0.641509 | F63: 0.646127 | G63: 0.655105 | H63: 0.662292 | I63: 0.666839 | J63: 0.669591 | K63: 0.672105 | L63: 0.673748 | M63: 0.672946 | N63: 0.673752 | O63: 0.676058 | P63: 0.679135 | Q63: 0.682642 | R63: 0.686727 | S63: 0.691026 | T63: 0.695127 | U63: 0.699352 | V63: 0.703808 | W63: 0.708334 | X63: 0.712997 | Y63: 0.717386 | Z63: 0.721745 | AA63: 0.725994 | AB63: 0.730256 | AC63: 0.734687 | AD63: 0.739264 | AE63: 0.744318 | AF63: 0.749249 | AG63: 0.753712 | AH63: 0.005244
A64: CKI000:la_Ventilation | B64: Ventilation | C64: 0.505827 | D64: 0.501606 | E64: 0.498216 | F64: 0.497024 | G64: 0.497277 | H64: 0.497199 | I64: 0.488625 | J64: 0.480246 | K64: 0.472302 | L64: 0.464968 | M64: 0.457587 | N64: 0.450991 | O64: 0.445115 | P64: 0.439769 | Q64: 0.435185 | R64: 0.431223 | S64: 0.427859 | T64: 0.424901 | U64: 0.422213 | V64: 0.419847 | W64: 0.416772 | X64: 0.414367 | Y64: 0.412405 | Z64: 0.410821 | AA64: 0.409666 | AB64: 0.40885 | AC64: 0.40842 | AD64: 0.408362 | AE64: 0.408748 | AF64: 0.409595 | AG64: 0.410734 | AH64: -0.006918
A65: CKI000:la_Cooking | B65: Cooking | C65: 0.429176 | D65: 0.430179 | E65: 0.432474 | F65: 0.438166 | G65: 0.446272 | H65: 0.453437 | I65: 0.459172 | J65: 0.463885 | K65: 0.468301 | L65: 0.472109 | M65: 0.473866 | N65: 0.47667 | O65: 0.480327 | P65: 0.484534 | Q65: 0.488907 | R65: 0.493542 | S65: 0.498183 | T65: 0.502614 | U65: 0.506954 | V65: 0.511347 | W65: 0.515781 | X65: 0.520512 | Y65: 0.525076 | Z65: 0.529612 | AA65: 0.534044 | AB65: 0.538468 | AC65: 0.542969 | AD65: 0.547446 | AE65: 0.552143 | AF65: 0.556772 | AG65: 0.56108 | AH65: 0.008973
A66: CKI000:la_Lighting | B66: Lighting | C66: 0.534773 | D66: 0.518426 | E66: 0.505123 | F66: 0.495132 | G66: 0.487166 | H66: 0.480211 | I66: 0.474199 | J66: 0.468797 | K66: 0.461557 | L66: 0.454545 | M66: 0.440337 | N66: 0.428149 | O66: 0.417524 | P66: 0.408416 | Q66: 0.400732 | R66: 0.394175 | S66: 0.388692 | T66: 0.383917 | U66: 0.379658 | V66: 0.375877 | W66: 0.370444 | X66: 0.366245 | Y66: 0.362688 | Z66: 0.359474 | AA66: 0.356838 | AB66: 0.35471 | AC66: 0.353074 | AD66: 0.351922 | AE66: 0.351265 | AF66: 0.351075 | AG66: 0.351211 | AH66: -0.013917
A67: CKI000:la_Refrigeration | B67: Refrigeration | C67: 0.652675 | D67: 0.648219 | E67: 0.644071 | F67: 0.642537 | G67: 0.642707 | H67: 0.643651 | I67: 0.644886 | J67: 0.646186 | K67: 0.647552 | L67: 0.649011 | M67: 0.648711 | N67: 0.649393 | O67: 0.650647 | P67: 0.652299 | Q67: 0.654344 | R67: 0.656709 | S67: 0.659267 | T67: 0.661808 | U67: 0.664277 | V67: 0.666836 | W67: 0.669189 | X67: 0.672484 | Y67: 0.675959 | Z67: 0.679569 | AA67: 0.68328 | AB67: 0.687102 | AC67: 0.691051 | AD67: 0.69504 | AE67: 0.699162 | AF67: 0.703397 | AG67: 0.707571 | AH67: 0.002696
A68: CKI000:la_OfficeEquipme | B68: Computing | C68: 0.330159 | D68: 0.325755 | E68: 0.321981 | F68: 0.319435 | G68: 0.317918 | H68: 0.317215 | I68: 0.316841 | J68: 0.317254 | K68: 0.318512 | L68: 0.320179 | M68: 0.321813 | N68: 0.324377 | O68: 0.327493 | P68: 0.330646 | Q68: 0.33386 | R68: 0.337607 | S68: 0.341369 | T68: 0.345087 | U68: 0.34878 | V68: 0.351958 | W68: 0.355182 | X68: 0.358437 | Y68: 0.360651 | Z68: 0.362867 | AA68: 0.36399 | AB68: 0.364547 | AC68: 0.364524 | AD68: 0.363883 | AE68: 0.361507 | AF68: 0.358495 | AG68: 0.353638 | AH68: 0.002293
A69: CKI000:ma_OfficeEquipme | B69: Office Equipment | C69: 0.435086 | D69: 0.455255 | E69: 0.474626 | F69: 0.493633 | G69: 0.512342 | H69: 0.53011 | I69: 0.546927 | J69: 0.562448 | K69: 0.576945 | L69: 0.590697 | M69: 0.603772 | N69: 0.616219 | O69: 0.62873 | P69: 0.640668 | Q69: 0.652534 | R69: 0.664258 | S69: 0.67603 | T69: 0.687462 | U69: 0.699179 | V69: 0.711024 | W69: 0.723714 | X69: 0.736914 | Y69: 0.750903 | Z69: 0.765677 | AA69: 0.781526 | AB69: 0.798532 | AC69: 0.816726 | AD69: 0.83668 | AE69: 0.858232 | AF69: 0.881412 | AG69: 0.906807 | AH69: 0.024782
A70: CKI000:ma_OtherUses | B70: Other Uses 7/ | C70: 2.498857 | D70: 2.690977 | E70: 2.749653 | F70: 2.942204 | G70: 3.072034 | H70: 3.200728 | I70: 3.22278 | J70: 3.243628 | K70: 3.263915 | L70: 3.283282 | M70: 3.300965 | N70: 3.321659 | O70: 3.34415 | P70: 3.368448 | Q70: 3.39369 | R70: 3.421352 | S70: 3.44986 | T70: 3.478772 | U70: 3.508513 | V70: 3.540488 | W70: 3.573362 | X70: 3.607673 | Y70: 3.643514 | Z70: 3.681677 | AA70: 3.720626 | AB70: 3.761588 | AC70: 3.804886 | AD70: 3.85017 | AE70: 3.89826 | AF70: 3.948443 | AG70: 4.000947 | AH70: 0.015814
A71: CKI000:ma_GrsEndUseCons | B71: Gross End-use Consumption | C71: 8.691429 | D71: 8.913066 | E71: 9.005533 | F71: 9.220589 | G71: 9.400805 | H71: 9.572875 | I71: 9.615849 | J71: 9.646873 | K71: 9.673253 | L71: 9.694086 | M71: 9.695116 | N71: 9.711 | O71: 9.737494 | P71: 9.769614 | Q71: 9.806873 | R71: 9.85211 | S71: 9.900833 | T71: 9.949198 | U71: 9.999239 | V71: 10.052699 | W71: 10.104759 | X71: 10.162006 | Y71: 10.220757 | Z71: 10.282885 | AA71: 10.346592 | AB71: 10.413385 | AC71: 10.485018 | AD71: 10.561284 | AE71: 10.643901 | AF71: 10.729895 | AG71: 10.817279 | AH71: 0.00732
A72: CKI000:ma_OwnGeneration | B72: Onsite Generation for Own Use | C72: 0.088754 | D72: 0.100767 | E72: 0.108803 | F72: 0.11328 | G72: 0.116855 | H72: 0.123412 | I72: 0.127401 | J72: 0.13471 | K72: 0.139391 | L72: 0.144049 | M72: 0.148256 | N72: 0.154432 | O72: 0.157366 | P72: 0.162016 | Q72: 0.166467 | R72: 0.171586 | S72: 0.179007 | T72: 0.183781 | U72: 0.189563 | V72: 0.195143 | W72: 0.201085 | X72: 0.206613 | Y72: 0.212167 | Z72: 0.21771 | AA72: 0.222534 | AB72: 0.228152 | AC72: 0.235994 | AD72: 0.239927 | AE72: 0.24339 | AF72: 0.24572 | AG72: 0.248986 | AH72: 0.034982
... A75: CKI000:na_ElectricityRe | B75: Electricity Related Losses | C75: 8.086047 | D75: 8.190955 | E75: 8.36768 | F75: 8.263312 | G75: 8.178636 | H75: 8.035031 | I75: 7.760867 | J75: 7.566372 | K75: 7.472069 | L75: 7.404101 | M75: 7.389483 | N75: 7.361253 | O75: 7.330706 | P75: 7.322793 | Q75: 7.310106 | R75: 7.316556 | S75: 7.322708 | T75: 7.324018 | U75: 7.331012 | V75: 7.354646 | W75: 7.3837 | X75: 7.42083 | Y75: 7.46253 | Z75: 7.489846 | AA75: 7.492239 | AB75: 7.5371 | AC75: 7.586079 | AD75: 7.643915 | AE75: 7.700721 | AF75: 7.783999 | AG75: 7.869395 | AH75: -0.000905
B77: Total Energy Consumption by End Use
A78: CKI000:oa_SpaceHeating | B78: Space Heating 2/ | C78: 2.309234 | D78: 2.387904 | E78: 2.379134 | F78: 2.376062 | G78: 2.387784 | H78: 2.392822 | I78: 2.387613 | J78: 2.376268 | K78: 2.365394 | L78: 2.351518 | M78: 2.335714 | N78: 2.323739 | O78: 2.314019 | P78: 2.304991 | Q78: 2.296294 | R78: 2.289284 | S78: 2.282612 | T78: 2.274607 | U78: 2.266548 | V78: 2.259096 | W78: 2.25111 | X78: 2.24269 | Y78: 2.233038 | Z78: 2.222499 | AA78: 2.21095 | AB78: 2.199514 | AC78: 2.188387 | AD78: 2.17759 | AE78: 2.167802 | AF78: 2.157513 | AG78: 2.145844 | AH78: -0.002443
A79: CKI000:oa_SpaceCooling | B79: Space Cooling 2/ | C79: 1.527662 | D79: 1.433053 | E79: 1.551555 | F79: 1.535521 | G79: 1.522956 | H79: 1.503351 | I79: 1.479382 | J79: 1.462915 | K79: 1.457687 | L79: 1.454888 | M79: 1.458664 | N79: 1.462037 | O79: 1.465418 | P79: 1.471591 | Q79: 1.47774 | R79: 1.487168 | S79: 1.496276 | T79: 1.504786 | U79: 1.513533 | V79: 1.523981 | W79: 1.534927 | X79: 1.546953 | Y79: 1.560475 | Z79: 1.571662 | AA79: 1.580575 | AB79: 1.594097 | AC79: 1.608337 | AD79: 1.623496 | AE79: 1.6398 | AF79: 1.65921 | AG79: 1.678982 | AH79: 0.003153
A80: CKI000:oa_WaterHeating | B80: Water Heating 2/ | C80: 0.690434 | D80: 0.687775 | E80: 0.685912 | F80: 0.68878 | G80: 0.696212 | H80: 0.701613 | I80: 0.704286 | J80: 0.705543 | K80: 0.707061 | L80: 0.707836 | M80: 0.706493 | N80: 0.706683 | O80: 0.708357 | P80: 0.710906 | Q80: 0.713865 | R80: 0.717481 | S80: 0.72131 | T80: 0.724912 | U80: 0.72865 | V80: 0.732681 | W80: 0.736815 | X80: 0.741121 | Y80: 0.745165 | Z80: 0.749119 | AA80: 0.752869 | AB80: 0.756778 | AC80: 0.760862 | AD80: 0.765113 | AE80: 0.769835 | AF80: 0.774519 | AG80: 0.778729 | AH80: 0.004019
A81: CKI000:oa_Ventilation | B81: Ventilation | C81: 1.430322 | D81: 1.415373 | E81: 1.404056 | F81: 1.374589 | G81: 1.350473 | H81: 1.320094 | I81: 1.266066 | J81: 1.221587 | K81: 1.189046 | L81: 1.160957 | M81: 1.139424 | N81: 1.117973 | O81: 1.097577 | P81: 1.080284 | Q81: 1.064063 | R81: 1.050644 | S81: 1.038432 | T81: 1.026723 | U81: 1.016067 | V81: 1.007431 | W81: 0.997625 | X81: 0.989514 | Y81: 0.982556 | Z81: 0.975073 | AA81: 0.966561 | AB81: 0.961753 | AC81: 0.95784 | AD81: 0.9551 | AE81: 0.952994 | AF81: 0.953441 | AG81: 0.954409 | AH81: -0.013395
A82: CKI000:oa_Cooking | B82: Cooking | C82: 0.584101 | D82: 0.5834 | E82: 0.584597 | F82: 0.585739 | G82: 0.589829 | H82: 0.592003 | I82: 0.592316 | J82: 0.59285 | K82: 0.594782 | L82: 0.596484 | M82: 0.597226 | N82: 0.598688 | O82: 0.600881 | P82: 0.60396 | Q82: 0.607072 | R82: 0.61069 | S82: 0.614244 | T82: 0.617451 | U82: 0.620586 | V82: 0.623986 | W82: 0.627527 | X82: 0.631484 | Y82: 0.635293 | Z82: 0.638806 | AA82: 0.641809 | AB82: 0.645349 | AC82: 0.648965 | AD82: 0.652614 | AE82: 0.656428 | AF82: 0.660487 | AG82: 0.66418 | AH82: 0.004292
A83: CKI000:oa_Lighting | B83: Lighting | C83: 1.512173 | D83: 1.462832 | E83: 1.423519 | F83: 1.369356 | G83: 1.323014 | H83: 1.27499 | I83: 1.228689 | J83: 1.192466 | K83: 1.161996 | L83: 1.134932 | M83: 1.096468 | N83: 1.06135 | O83: 1.029542 | P83: 1.003265 | Q83: 0.97982 | R83: 0.960378 | S83: 0.943374 | T83: 0.927691 | U83: 0.913657 | V83: 0.901925 | W83: 0.886731 | X83: 0.874599 | Y83: 0.864105 | Z83: 0.853202 | AA83: 0.841919 | AB83: 0.834399 | AC83: 0.82804 | AD83: 0.823095 | AE83: 0.818974 | AF83: 0.81722 | AG83: 0.816097 | AH83: -0.020349
A84: CKI000:oa_Refrigeration | B84: Refrigeration | C84: 1.845564 | D84: 1.829066 | E84: 1.815097 | F84: 1.777025 | G84: 1.745421 | H84: 1.708934 | I84: 1.670952 | J84: 1.643683 | K84: 1.630249 | L84: 1.620485 | M84: 1.615333 | N84: 1.609798 | O84: 1.604383 | P84: 1.602359 | Q84: 1.599922 | R84: 1.600024 | S84: 1.60007 | T84: 1.59918 | U84: 1.598601 | V84: 1.600086 | W84: 1.601835 | X84: 1.605903 | Y84: 1.610472 | Z84: 1.612941 | AA84: 1.612124 | AB84: 1.616296 | AC84: 1.620676 | AD84: 1.625599 | AE84: 1.630093 | AF84: 1.637345 | AG84: 1.644161 | AH84: -0.003844
A85: CKI000:oa_OfficeEquipme | B85: Computing | C85: 0.933589 | D85: 0.919177 | E85: 0.907396 | F85: 0.883442 | G85: 0.863382 | H85: 0.842225 | I85: 0.820961 | J85: 0.806988 | K85: 0.801871 | L85: 0.799441 | M85: 0.801337 | N85: 0.804107 | O85: 0.807541 | P85: 0.812226 | Q85: 0.816314 | R85: 0.822555 | S85: 0.828517 | T85: 0.833862 | U85: 0.839349 | V85: 0.844529 | W85: 0.850198 | X85: 0.855954 | Y85: 0.85925 | Z85: 0.861257 | AA85: 0.858794 | AB85: 0.857538 | AC85: 0.854893 | AD85: 0.85107 | AE85: 0.842852 | AF85: 0.834494 | AG85: 0.821738 | AH85: -0.004245
A86: CKI000:pa_OfficeEquipme | B86: Office Equipment | C86: 1.230289 | D86: 1.284585 | E86: 1.337574 | F86: 1.36521 | G86: 1.391385 | H86: 1.407474 | I86: 1.417134 | J86: 1.430682 | K86: 1.452492 | L86: 1.474882 | M86: 1.503433 | N86: 1.52756 | O86: 1.55034 | P86: 1.573786 | Q86: 1.595497 | R86: 1.618416 | S86: 1.640756 | T86: 1.661169 | U86: 1.682593 | V86: 1.706116 | W86: 1.732352 | X86: 1.759761 | Y86: 1.789026 | Z86: 1.817314 | AA86: 1.843923 | AB86: 1.878418 | AC86: 1.915413 | AD86: 1.956873 | AE86: 2.000964 | AF86: 2.051724 | AG86: 2.107119 | AH86: 0.018098
A87: CKI000:pa_OtherUses | B87: Other Uses 7/ | C87: 4.714108 | D87: 5.100855 | E87: 5.284374 | F87: 5.528179 | G87: 5.708986 | H87: 5.8644 | I87: 5.809315 | J87: 5.780264 | K87: 5.784746 | L87: 5.796765 | M87: 5.830507 | N87: 5.860319 | O87: 5.890141 | P87: 5.929039 | Q87: 5.966394 | R87: 6.012025 | S87: 6.05795 | T87: 6.102835 | U87: 6.150667 | V87: 6.207512 | W87: 6.269339 | X87: 6.334858 | Y87: 6.403908 | Z87: 6.470859 | AA87: 6.529305 | AB87: 6.606344 | AC87: 6.687683 | AD87: 6.77465 | AE87: 6.86488 | AF87: 6.967942 | AG87: 7.075416 | AH87: 0.013628
A88: CKI000:pa_Total | B88: Total Gross End-use Consumption | C88: 16.777477 | D88: 17.104021 | E88: 17.373213 | F88: 17.483902 | G88: 17.579441 | H88: 17.607906 | I88: 17.376715 | J88: 17.213245 | K88: 17.145323 | L88: 17.098186 | M88: 17.084599 | N88: 17.072254 | O88: 17.068199 | P88: 17.092407 | Q88: 17.11698 | R88: 17.168667 | S88: 17.223541 | T88: 17.273216 | U88: 17.33025 | V88: 17.407345 | W88: 17.488461 | X88: 17.582836 | Y88: 17.683289 | Z88: 17.77273 | AA88: 17.838831 | AB88: 17.950485 | AC88: 18.071096 | AD88: 18.2052 | AE88: 18.344622 | AF88: 18.513893 | AG88: 18.686674 | AH88: 0.003599
A89: CKI000:pa_OwnGeneration | B89: Onsite Generation for Own Use | C89: 0.088754 | D89: 0.100767 | E89: 0.108803 | F89: 0.11328 | G89: 0.116855 | H89: 0.123412 | I89: 0.127401 | J89: 0.13471 | K89: 0.139391 | L89: 0.144049 | M89: 0.148256 | N89: 0.154432 | O89: 0.157366 | P89: 0.162016 | Q89: 0.166467 | R89: 0.171586 | S89: 0.179007 | T89: 0.183781 | U89: 0.189563 | V89: 0.195143 | W89: 0.201085 | X89: 0.206613 | Y89: 0.212167 | Z89: 0.21771 | AA89: 0.222534 | AB89: 0.228152 | AC89: 0.235994 | AD89: 0.239927 | AE89: 0.24339 | AF89: 0.24572 | AG89: 0.248986 | AH89: 0.034982
A90: CKI000:pa_TtllOwnUseGen | B90: Total Net Own-use Generation | C90: 16.688723 | D90: 17.003254 | E90: 17.26441 | F90: 17.370621 | G90: 17.462585 | H90: 17.484493 | I90: 17.249313 | J90: 17.078535 | K90: 17.005932 | L90: 16.954138 | M90: 16.936344 | N90: 16.917822 | O90: 16.910833 | P90: 16.930391 | Q90: 16.950512 | R90: 16.99708 | S90: 17.044535 | T90: 17.089436 | U90: 17.140688 | V90: 17.212202 | W90: 17.287374 | X90: 17.376223 | Y90: 17.471121 | Z90: 17.555021 | AA90: 17.616297 | AB90: 17.722332 | AC90: 17.835104 | AD90: 17.965271 | AE90: 18.101233 | AF90: 18.268173 | AG90: 18.437687 | AH90: 0.003328
B92: Nonmarketed Renewable Fuels 8/
A93: CKI000:qa_SolarThermal | B93: Solar Thermal | C93: 0.073802 | D93: 0.07482 | E93: 0.074536 | F93: 0.072862 | G93: 0.071973 | H93: 0.069906 | I93: 0.069271 | J93: 0.068682 | K93: 0.068536 | L93: 0.068331 | M93: 0.068702 | N93: 0.06847 | O93: 0.068218 | P93: 0.068077 | Q93: 0.067909 | R93: 0.067775 | S93: 0.067605 | T93: 0.067488 | U93: 0.06729 | V93: 0.067204 | W93: 0.067079 | X93: 0.067001 | Y93: 0.066944 | Z93: 0.066835 | AA93: 0.066729 | AB93: 0.066679 | AC93: 0.066538 | AD93: 0.066286 | AE93: 0.066062 | AF93: 0.06592 | AG93: 0.065509 | AH93: -0.003965
A94: CKI000:qa_SolarPhotovol | B94: Solar Photovoltaic | C94: 0.165692 | D94: 0.194457 | E94: 0.213234 | F94: 0.220475 | G94: 0.226622 | H94: 0.238787 | I94: 0.246037 | J94: 0.261795 | K94: 0.271675 | L94: 0.281913 | M94: 0.294567 | N94: 0.307668 | O94: 0.313624 | P94: 0.323249 | Q94: 0.333208 | R94: 0.344396 | S94: 0.360303 | T94: 0.370399 | U94: 0.382887 | V94: 0.395108 | W94: 0.407557 | X94: 0.41975 | Y94: 0.432264 | Z94: 0.44382 | AA94: 0.454485 | AB94: 0.467325 | AC94: 0.484232 | AD94: 0.490786 | AE94: 0.49689 | AF94: 0.500876 | AG94: 0.504236 | AH94: 0.037794
A95: CKI000:qa_EKnowitzWindy | B95: Wind | C95: 0.006898 | D95: 0.006984 | E95: 0.006952 | F95: 0.006809 | G95: 0.00675 | H95: 0.006575 | I95: 0.006501 | J95: 0.006458 | K95: 0.006448 | L95: 0.00643 | M95: 0.006444 | N95: 0.006428 | O95: 0.006407 | P95: 0.006425 | Q95: 0.006416 | R95: 0.006394 | S95: 0.006371 | T95: 0.006361 | U95: 0.006337 | V95: 0.006331 | W95: 0.00632 | X95: 0.006305 | Y95: 0.006296 | Z95: 0.006301 | AA95: 0.006285 | AB95: 0.006275 | AC95: 0.006256 | AD95: 0.006239 | AE95: 0.006214 | AF95: 0.006217 | AG95: 0.0062 | AH95: -0.00355
A96: CKI000:qa_TotalSolar | B96: Total | C96: 0.246392 | D96: 0.276261 | E96: 0.294722 | F96: 0.300146 | G96: 0.305345 | H96: 0.315268 | I96: 0.321809 | J96: 0.336935 | K96: 0.346659 | L96: 0.356674 | M96: 0.369713 | N96: 0.382566 | O96: 0.388249 | P96: 0.397751 | Q96: 0.407534 | R96: 0.418565 | S96: 0.434279 | T96: 0.444249 | U96: 0.456514 | V96: 0.468642 | W96: 0.480956 | X96: 0.493056 | Y96: 0.505504 | Z96: 0.516955 | AA96: 0.527499 | AB96: 0.540279 | AC96: 0.557027 | AD96: 0.563311 | AE96: 0.569166 | AF96: 0.573014 | AG96: 0.575945 | AH96: 0.028707
B98: Heating Degree Days
A99: CKI000:hdd_NewEngland | B99: New England | C99: 5958 | D99: 6244 | E99: 6198 | F99: 6187 | G99: 6176 | H99: 6165 | I99: 6153 | J99: 6142 | K99: 6130 | L99: 6118 | M99: 6107 | N99: 6095 | O99: 6083 | P99: 6071 | Q99: 6059 | R99: 6048 | S99: 6036 | T99: 6024 | U99: 6012 | V99: 6000 | W99: 5988 | X99: 5976 | Y99: 5964 | Z99: 5952 | AA99: 5940 | AB99: 5929 | AC99: 5917 | AD99: 5905 | AE99: 5893 | AF99: 5881 | AG99: 5869 | AH99: -0.000502
A100: CKI000:hdd_MiddleAtlant | B100: Middle Atlantic | C100: 5371 | D100: 5595 | E100: 5569 | F100: 5558 | G100: 5548 | H100: 5538 | I100: 5528 | J100: 5517 | K100: 5507 | L100: 5497 | M100: 5487 | N100: 5477 | O100: 5467 | P100: 5457 | Q100: 5446 | R100: 5436 | S100: 5426 | T100: 5416 | U100: 5406 | V100: 5396 | W100: 5386 | X100: 5376 | Y100: 5366 | Z100: 5355 | AA100: 5345 | AB100: 5335 | AC100: 5325 | AD100: 5315 | AE100: 5305 | AF100: 5295 | AG100: 5285 | AH100: -0.000538
A101: CKI000:hdd_EastNorthCen | B101: East North Central | C101: 6000 | D101: 6217 | E101: 6172 | F101: 6167 | G101: 6163 | H101: 6159 | I101: 6155 | J101: 6151 | K101: 6147 | L101: 6143 | M101: 6138 | N101: 6134 | O101: 6130 | P101: 6126 | Q101: 6122 | R101: 6118 | S101: 6114 | T101: 6109 | U101: 6105 | V101: 6101 | W101: 6097 | X101: 6093 | Y101: 6089 | Z101: 6084 | AA101: 6080 | AB101: 6076 | AC101: 6072 | AD101: 6068 | AE101: 6064 | AF101: 6059 | AG101: 6055 | AH101: 0.000304
A102: CKI000:hdd_WestNorthCen | B102: West North Central | C102: 6410 | D102: 6529 | E102: 6490 | F102: 6489 | G102: 6487 | H102: 6485 | I102: 6483 | J102: 6481 | K102: 6479 | L102: 6477 | M102: 6474 | N102: 6472 | O102: 6470 | P102: 6467 | Q102: 6465 | R102: 6462 | S102: 6459 | T102: 6457 | U102: 6454 | V102: 6451 | W102: 6449 | X102: 6446 | Y102: 6443 | Z102: 6440 | AA102: 6437 | AB102: 6434 | AC102: 6431 | AD102: 6428 | AE102: 6426 | AF102: 6423 | AG102: 6420 | AH102: 5.2e-05
A103: CKI000:hdd_SouthAtlantc | B103: South Atlantic | C103: 2335 | D103: 2486 | E103: 2520 | F103: 2511 | G103: 2503 | H103: 2495 | I103: 2487 | J103: 2479 | K103: 2471 | L103: 2463 | M103: 2455 | N103: 2448 | O103: 2440 | P103: 2432 | Q103: 2424 | R103: 2417 | S103: 2409 | T103: 2401 | U103: 2393 | V103: 2385 | W103: 2378 | X103: 2370 | Y103: 2362 | Z103: 2355 | AA103: 2347 | AB103: 2339 | AC103: 2332 | AD103: 2324 | AE103: 2316 | AF103: 2309 | AG103: 2301 | AH103: -0.000489
A104: CKI000:hdd_EastSouthCen | B104: East South Central | C104: 3119 | D104: 3304 | E104: 3319 | F104: 3314 | G104: 3310 | H104: 3306 | I104: 3302 | J104: 3297 | K104: 3293 | L104: 3288 | M104: 3284 | N104: 3280 | O104: 3275 | P104: 3271 | Q104: 3266 | R104: 3262 | S104: 3257 | T104: 3252 | U104: 3248 | V104: 3243 | W104: 3238 | X104: 3234 | Y104: 3229 | Z104: 3224 | AA104: 3220 | AB104: 3215 | AC104: 3210 | AD104: 3206 | AE104: 3201 | AF104: 3196 | AG104: 3191 | AH104: 0.000761
A105: CKI000:hdd_WestSouthCen | B105: West South Central | C105: 1829 | D105: 1910 | E105: 2015 | F105: 2009 | G105: 2004 | H105: 1999 | I105: 1994 | J105: 1988 | K105: 1983 | L105: 1978 | M105: 1973 | N105: 1967 | O105: 1962 | P105: 1957 | Q105: 1952 | R105: 1947 | S105: 1942 | T105: 1937 | U105: 1932 | V105: 1927 | W105: 1922 | X105: 1917 | Y105: 1912 | Z105: 1907 | AA105: 1902 | AB105: 1897 | AC105: 1892 | AD105: 1887 | AE105: 1882 | AF105: 1877 | AG105: 1873 | AH105: 0.000793
A106: CKI000:hdd_Mountain | B106: Mountain | C106: 4810 | D106: 4802 | E106: 4793 | F106: 4780 | G106: 4768 | H106: 4755 | I106: 4742 | J106: 4730 | K106: 4717 | L106: 4704 | M106: 4691 | N106: 4678 | O106: 4664 | P106: 4651 | Q106: 4638 | R106: 4624 | S106: 4611 | T106: 4597 | U106: 4584 | V106: 4570 | W106: 4557 | X106: 4543 | Y106: 4530 | Z106: 4517 | AA106: 4503 | AB106: 4490 | AC106: 4476 | AD106: 4463 | AE106: 4450 | AF106: 4436 | AG106: 4423 | AH106: -0.002792
A107: CKI000:hdd_Pacific | B107: Pacific | C107: 3335 | D107: 3363 | E107: 3253 | F107: 3243 | G107: 3232 | H107: 3222 | I107: 3212 | J107: 3201 | K107: 3191 | L107: 3180 | M107: 3169 | N107: 3159 | O107: 3148 | P107: 3137 | Q107: 3126 | R107: 3116 | S107: 3105 | T107: 3094 | U107: 3083 | V107: 3072 | W107: 3061 | X107: 3050 | Y107: 3039 | Z107: 3028 | AA107: 3017 | AB107: 3005 | AC107: 2994 | AD107: 2983 | AE107: 2972 | AF107: 2961 | AG107: 2950 | AH107: -0.004081
A108: CKI000:hdd_UnitedStates | B108: United States | C108: 3994.5471 | D108: 4123.4863 | E108: 4106.1538 | F108: 4092.9009 | G108: 4080.1919 | H108: 4067.6082 | I108: 4055.0151 | J108: 4042.1086 | K108: 4029.5825 | L108: 4016.8516 | M108: 4004.0332 | N108: 3991.6162 | O108: 3978.823 | P108: 3966.1135 | Q108: 3953.3047 | R108: 3940.9419 | S108: 3928.1753 | T108: 3915.2417 | U108: 3902.5 | V108: 3889.5938 | W108: 3877.0181 | X108: 3864.113 | Y108: 3851.2107 | Z108: 3838.2595 | AA108: 3825.2751 | AB108: 3812.176 | AC108: 3799.3579 | AD108: 3786.5342 | AE108: 3773.8267 | AF108: 3761.2253 | AG108: 3748.8479 | AH108: -0.002114
B110: Cooling Degree Days
A111: CKI000:cdd_NewEngland | B111: New England | C111: 652 | D111: 505 | E111: 579 | F111: 584 | G111: 590 | H111: 596 | I111: 602 | J111: 608 | K111: 614 | L111: 620 | M111: 626 | N111: 632 | O111: 638 | P111: 644 | Q111: 650 | R111: 656 | S111: 662 | T111: 668 | U111: 674 | V111: 680 | W111: 686 | X111: 692 | Y111: 698 | Z111: 704 | AA111: 710 | AB111: 716 | AC111: 723 | AD111: 729 | AE111: 735 | AF111: 741 | AG111: 747 | AH111: 0.004544
A112: CKI000:cdd_MiddleAtlant | B112: Middle Atlantic | C112: 840 | D112: 706 | E112: 826 | F112: 834 | G112: 842 | H112: 850 | I112: 858 | J112: 867 | K112: 875 | L112: 883 | M112: 891 | N112: 899 | O112: 907 | P112: 916 | Q112: 924 | R112: 932 | S112: 940 | T112: 948 | U112: 956 | V112: 965 | W112: 973 | X112: 981 | Y112: 989 | Z112: 997 | AA112: 1005 | AB112: 1014 | AC112: 1022 | AD112: 1030 | AE112: 1038 | AF112: 1046 | AG112: 1054 | AH112: 0.007594
A113: CKI000:cdd_EastNorthCen | B113: East North Central | C113: 831 | D113: 767 | E113: 857 | F113: 864 | G113: 870 | H113: 876 | I113: 882 | J113: 889 | K113: 895 | L113: 901 | M113: 907 | N113: 914 | O113: 920 | P113: 926 | Q113: 932 | R113: 939 | S113: 945 | T113: 951 | U113: 958 | V113: 964 | W113: 970 | X113: 976 | Y113: 983 | Z113: 989 | AA113: 995 | AB113: 1002 | AC113: 1008 | AD113: 1014 | AE113: 1021 | AF113: 1027 | AG113: 1033 | AH113: 0.00728
A114: CKI000:cdd_WestNorthCen | B114: West North Central | C114: 975 | D114: 956 | E114: 1035 | F114: 1040 | G114: 1046 | H114: 1051 | I114: 1057 | J114: 1062 | K114: 1068 | L114: 1074 | M114: 1079 | N114: 1085 | O114: 1091 | P114: 1096 | Q114: 1102 | R114: 1108 | S114: 1114 | T114: 1119 | U114: 1125 | V114: 1131 | W114: 1137 | X114: 1142 | Y114: 1148 | Z114: 1154 | AA114: 1160 | AB114: 1166 | AC114: 1171 | AD114: 1177 | AE114: 1183 | AF114: 1189 | AG114: 1195 | AH114: 0.006805
A115: CKI000:cdd_SouthAtlantc | B115: South Atlantic | C115: 2274 | D115: 2219 | E115: 2359 | F115: 2373 | G115: 2388 | H115: 2402 | I115: 2417 | J115: 2431 | K115: 2445 | L115: 2460 | M115: 2474 | N115: 2488 | O115: 2503 | P115: 2517 | Q115: 2531 | R115: 2546 | S115: 2560 | T115: 2575 | U115: 2589 | V115: 2603 | W115: 2618 | X115: 2632 | Y115: 2647 | Z115: 2661 | AA115: 2676 | AB115: 2690 | AC115: 2705 | AD115: 2719 | AE115: 2734 | AF115: 2748 | AG115: 2763 | AH115: 0.006514
A116: CKI000:cdd_EastSouthCen | B116: East South Central | C116: 1623 | D116: 1710 | E116: 1808 | F116: 1818 | G116: 1828 | H116: 1838 | I116: 1848 | J116: 1858 | K116: 1868 | L116: 1878 | M116: 1888 | N116: 1898 | O116: 1909 | P116: 1919 | Q116: 1929 | R116: 1939 | S116: 1949 | T116: 1959 | U116: 1969 | V116: 1980 | W116: 1990 | X116: 2000 | Y116: 2010 | Z116: 2020 | AA116: 2031 | AB116: 2041 | AC116: 2051 | AD116: 2061 | AE116: 2071 | AF116: 2082 | AG116: 2092 | AH116: 0.008497
A117: CKI000:cdd_WestSouthCen | B117: West South Central | C117: 2730 | D117: 2770 | E117: 2861 | F117: 2875 | G117: 2889 | H117: 2904 | I117: 2918 | J117: 2932 | K117: 2947 | L117: 2961 | M117: 2976 | N117: 2990 | O117: 3004 | P117: 3018 | Q117: 3033 | R117: 3047 | S117: 3061 | T117: 3076 | U117: 3090 | V117: 3104 | W117: 3119 | X117: 3133 | Y117: 3147 | Z117: 3161 | AA117: 3176 | AB117: 3190 | AC117: 3204 | AD117: 3218 | AE117: 3233 | AF117: 3247 | AG117: 3261 | AH117: 0.005942
A118: CKI000:cdd_Mountain | B118: Mountain | C118: 1639 | D118: 1471 | E118: 1560 | F118: 1568 | G118: 1577 | H118: 1586 | I118: 1595 | J118: 1604 | K118: 1613 | L118: 1622 | M118: 1631 | N118: 1641 | O118: 1650 | P118: 1659 | Q118: 1668 | R118: 1678 | S118: 1687 | T118: 1697 | U118: 1706 | V118: 1715 | W118: 1725 | X118: 1734 | Y118: 1744 | Z118: 1753 | AA118: 1763 | AB118: 1772 | AC118: 1782 | AD118: 1791 | AE118: 1801 | AF118: 1810 | AG118: 1820 | AH118: 0.003498
...

Sheet BRESaC-energy
A1: Percent energy saving (dimensionless) | B1: urban residential | C1: rural residential | D1: commercial
A2: heating | B2: =Residential!B56 -> 0.52341027 | C2: =$B2 -> 0.52341027 | D2: =Commercial!K11 -> 0.50386304
A3: cooling and ventilation | B3: =Residential!B56 -> 0.52341027 | C3: =$B3 -> 0.52341027 | D3: =Commercial!K11 -> 0.50386304
A4: envelope | B4: 0 | C4: =$B4 -> 0 | D4: 0
A5: lighting | B5: 0 | C5: =$B5 -> 0 | D5: 0
A6: appliances | B6: 0 | C6: =$B6 -> 0 | D6: 0
A7: other component | B7: 0 | C7: =$B7 -> 0 | D7: 0

Sheet BRESaC-cost
A1: $/BTU | B1: urban residential | C1: rural residential | D1: commercial
A2: heating | B2: =Residential!$B$53 -> 0.0004247967 | C2: =$B2 -> 0.0004247967 | D2: =Commercial!$K$8 -> 0.0030161597
A3: cooling and ventilation | B3: =Residential!$B$53 -> 0.0004247967 | C3: =$B3 -> 0.0004247967 | D3: =Commercial!$K$8 -> 0.0030161597
A4: envelope | B4: 0 | C4: =$B4 -> 0 | D4: 0
A5: lighting | B5: 0 | C5: =$B5 -> 0 | D5: 0
A6: appliances | B6: 0 | C6: =$B6 -> 0 | D6: 0
A7: other component | B7: 0 | C7: =$B7 -> 0 | D7: 0
