Workbook
Name cpi_2019_to_2012: About!$A$96

Sheet About
A1: CCaMC BAU Construction Cost per Unit Capacity
A2: CCaMC Annual Fixed O&M Cost per Unit Capacity
A3: CCaMC Variable O&M Cost per Unit Elec Output
A4: CCaMC BAU Soft Costs per Unit Capacity
A6: Sources: | B6: PV and Onshore wind Capital and O&M Costs
B7: Korea Energy Economics Institute
B8: 2020
B9: Medium-to-long-term levelized cost of electricity (LCOE) forecast (1/5)
B10: http://www.keei.re.kr/web_keei/d_results.nsf/0/A10FCB3438C55F4349258669004FC436/$file/%EA%B8%B0%EB%B3%B8%202020-21_%EC%9E%AC%EC%83%9D%EC%97%90%EB%84%88%EC%A7%80%20%EA%B3%B5%EA%B8%89%ED%99%95%EB%8C%80%EB%A5%BC%20%EC%9C%84%ED%95%9C%20%EC%A4%91%EC%9E%A5%EA%B8%B0%20%EB%B0%9C%EC%A0%84%EB%8B%A8%EA%B0%80(LCOE)%20%EC%A0%84%EB%A7%9D%20%EC%8B%9C%EC%8A%A4%ED%85%9C%20%EA%B5%AC%EC%B6%95%20%EB%B0%8F%20%EC%9A%B4%EC%98%81.pdf
B12: Gas and conventional power Capital and O&M Costs
B13: IEA
B14: 2020
B15: Levelised Cost of Electricity Calculator
B16: https://www.iea.org/articles/levelised-cost-of-electricity-calculator
B18: Conventional Power Capital and O&M Costs | D18: KEEI 발전원별 균등화 발전원가 최종보고서
B19: Korea Energy Economics Institute
B20: 2020
B21: KEEI Levelized cost of electricity by source
B22: http://www.alio.go.kr/informationResearchView.do?seq=2477139
B24: All Generator Capital and O&M Costs
B25: KPX
B26: 2018
B27: Power generation statistics
B28: https://www.kpx.or.kr/www/downloadBbsFile.do?atchmnflNo=29587
B30: Select Costs
B31: United States EPS version 3.3.1
B32: elec/CCaMC
A34: Notes:
A35: 2017 PPI | B35: 98.58
A36: 2012 PPI | B36: 103.31 | C36: =B35/B36 -> 0.95421547
A37: 2012 환율 | B37: 1126.88
A38: Exchate rate
A39: =B37*C36 -> 1075.2863
A41: For several plant types, we use US costs directly due to limited data availability (highlighted in yellow
A42: on the KRW tab.
A43: We were not able to identify soft cost data for renewable technologies, and therefore use the ratio
A44: of hard costs to soft costs from the US model.
A46: 2026-09-08: grid-connection (spur line) costs split out of the KEEI-based CAPEX for onshore wind, solar PV and offshore wind and placed in CCaMC-SLCCpUC (KRW tab rows 57-61, Calculation rows 110-119). KEEI's capex totals include 계통연계/한전계통비용, so before this change SLCCpUC = 0 was consistent but the spur line was invisible; now BCCpUC + SLCCpUC equals the previous BCCpUC for every year. Values (2020 KRW/kW): onshore 42,000; solar 23,000; offshore 324,000 (assumed half of KEEI's combined electrical-works-plus-connection figure). Thermal and nuclear connection costs remain inside their CAPEX (not itemized by KEEI). Source: KEEI 기본연구 24-22.
A48: 2026-09-08: CCaMC-BSCpUC year header repaired. The tab had 31 year columns labelled 2021, 2022, 2022, 2023 ... 2050: the data columns were aligned to the US tab's 2021-2050 (B..AE) but every label from column D onward was one year low, and a 32nd column referenced the US tab's empty column and read 0 as '2050'. So the exported soft costs were shifted a year late from 2023 and fell to 0 in 2050. Fixed by relabelling B..AE 2021-2050 and deleting the extra column; values unchanged otherwise. The exported CSV also carried a slightly older conversion (onshore 335,912 vs workbook 330,704 $/MW in 2021); the re-export brings the CSV to the workbook.

Sheet KRW
A2: CAPEX (KRW/kW) | B2: 2020 | C2: 2025 | D2: 2030 | G2: 기본데이터 | H2: 비고
A3: hard coal | B3: =1396000+42461 -> 1438461 | D3: =1920000+42451 -> 1962451 | G3: KEEI 발전원별 균등화 발전원가 최종보고서
A4: natural gas nonpeaker | B4: =924000+15879 -> 939879 | D4: =1009000+15879 -> 1024879 | G4: KEEI 발전원별 균등화 발전원가 최종보고서
A5: nuclear | B5: =2624000+124426+8946+2486042000000/1400000 -> 4533116.3 | D5: =3740000+124426+8946+2486042000000/1400000 -> 5649116.3 | G5: KEEI 발전원별 균등화 발전원가 최종보고서
A6: hydro | B6: 968700 | D6: 968700 | G6: KPX 발전 설비 현황
A7: onshore wind | B7: =2731000+5378 -> 2736378 | C7: =B7*0.95 -> 2599559.1 | D7: =B7*0.86 -> 2353285.1 | G7: 재생에너지 공급확대를 위한 중장기 발전단가 (LCOE)전망 시스템 구축 및 운영(3/5) | H7: 육상풍력 20MW 기준 설비비용 + 토지 임대비용 | J7: NREL ATB 2022~2030 변화율 참고
A8: solar PV | B8: =1355000+15174 -> 1370174 | C8: =B8 -> 1370174 | D8: =B8*0.82 -> 1123542.7 | G8: 재생에너지 공급확대를 위한 중장기 발전단가 (LCOE)전망 시스템 구축 및 운영(3/5) | H8: 태양광 지상 3MW 기준 설비비용 + 토지 임대비용 | J8: NREL ATB 2022~2030 변화율 참고
A9: solar thermal | B9: 0 | D9: 0
A10: biomass | B10: =(2980000+4666667)/2 -> 3823333.5 | D10: =B10 -> 3823333.5 | G10: KPX 발전 설비 현황
A11: geothermal | B11: =8208*About!A39 -> 8825950.2 | D11: =B11 -> 8825950.2 | G11: IEA 2020 Levelized cost of Electricity
A12: petroleum | B12: 1895634 | D12: =B12 -> 1895634 | G12: KPX 발전 설비 현황
A13: natural gas peaker | B13: =B4*0.7 -> 657915.3 | D13: =D4*0.7 -> 717415.3 | G13: =gas non peaker * 70%, assumed
A14: lignite | B14: =B3 -> 1438461 | D14: =D3 -> 1962451 | G14: KPX 발전 설비 현황
A15: offshore wind | B15: =6000000+5300 -> 6005300 | C15: =B15*0.93 -> 5584929 | D15: =B15*0.74 -> 4443922 | G15: 재생에너지 공급확대를 위한 중장기 발전단가 (LCOE)전망 시스템 구축 및 운영(3/5) | H15: 해상풍력 30~365MW 기준 평균값 + 토지 임대비용 | J15: NREL ATB 2022~2030 변화율 참고
A16: crude oil | B16: 1895634 | D16: =B16 -> 1895634 | G16: KPX 발전 설비 현황
A17: heavy or residual fuel oil | B17: 1895634 | D17: =B17 -> 1895634 | G17: KPX 발전 설비 현황
A18: municipal solid waste | B18: 4800000 | D18: =B18 -> 4800000 | G18: KPX 발전 설비 현황
A20: Fixed O&M (KRW/kW-yr)
A21: hard coal | B21: =5525*12+30.86*12 -> 66670.32 | D21: =5525*12+30.86*12 -> 66670.32 | G21: KEEI 발전원별 균등화 발전원가 최종보고서
A22: natural gas nonpeaker | B22: =3623*12+29.97*12 -> 43835.64 | D22: =3623*12+29.97*12 -> 43835.64 | G22: KEEI 발전원별 균등화 발전원가 최종보고서
A23: nuclear | B23: =12441*12+63.48*12+82*12+1325*12 -> 166937.76 | D23: =12441*12+63.48*12+82*12+1325*12 -> 166937.76 | G23: KEEI 발전원별 균등화 발전원가 최종보고서
A24: hydro | B24: =B6*0.025 -> 24217.5 | D24: =B24 -> 24217.5 | G24: 2.5% of construction cost, assumed
A25: onshore wind | B25: 51027 | C25: =B25 -> 51027 | D25: =B25 -> 51027 | G25: 재생에너지 공급확대를 위한 중장기 발전단가(LCOE)전망 시스템 구축(5/5) | H25: 육상풍력 20MW 기준 운영 및 유지비용
A26: solar PV | B26: 24871 | C26: =B26 -> 24871 | D26: =B26 -> 24871 | G26: 재생에너지 공급확대를 위한 중장기 발전단가 (LCOE)전망 시스템 구축 및 운영(3/5) | H26: 태양광 3MW 기준 운영 및 유지비용
A27: solar thermal | B27: =B9*0.025 -> 0 | D27: =B27 -> 0 | G27: 2.5% of construction cost, assumed
A28: biomass | B28: =B10*0.025 -> 95583.338 | D28: =B28 -> 95583.338 | G28: 2.5% of construction cost, assumed
A29: geothermal | B29: =B11*0.025 -> 220648.75 | D29: =B29 -> 220648.75 | G29: 2.5% of construction cost, assumed
A30: petroleum | B30: =B12*0.025 -> 47390.85 | D30: =B30 -> 47390.85 | G30: 2.5% of construction cost, assumed
A31: natural gas peaker | B31: =B13*0.025 -> 16447.882 | D31: =B31 -> 16447.882 | G31: 2.5% of construction cost, assumed
A32: lignite | B32: =B21 -> 66670.32 | D32: =D21 -> 66670.32 | G32: =hard coal
A33: offshore wind | B33: =122000 -> 122000 | C33: =122000 -> 122000 | D33: =B33 -> 122000 | G33: 재생에너지 공급확대를 위한 중장기 발전단가 (LCOE)전망 시스템 구축 및 운영(3/5) | H33: 해상풍력 30~365MW 기준 운영 및 유지비용
A34: crude oil | B34: =B16*0.025 -> 47390.85 | D34: =D16*0.025 -> 47390.85 | G34: 2.5% of construction cost, assumed
A35: heavy or residual fuel oil | B35: =B17*0.025 -> 47390.85 | D35: =D17*0.025 -> 47390.85 | G35: 2.5% of construction cost, assumed
A36: municipal solid waste | B36: =B18*0.025 -> 120000 | D36: =D18*0.025 -> 120000 | G36: 2.5% of construction cost, assumed
A38: Variable O&M (KRW/MWh)
A39: hard coal | B39: =880+300 -> 1180 | D39: =B39 -> 1180 | G39: KEEI 발전원별 균등화 발전원가 최종보고서
A40: natural gas nonpeaker | B40: =340+300 -> 640 | D40: =B40 -> 640 | G40: KEEI 발전원별 균등화 발전원가 최종보고서
A41: nuclear | B41: =990+1000 -> 1990 | D41: =B41 -> 1990 | G41: KEEI 발전원별 균등화 발전원가 최종보고서
A42: hydro | B42: 200 | D42: =B42 -> 200
A43: onshore wind | B43: 100 | D43: =B43 -> 100 | G43: KEEI 발전원별 균등화 발전원가 최종보고서
A44: solar PV | B44: 100 | D44: =B44 -> 100 | G44: KEEI 발전원별 균등화 발전원가 최종보고서
A45: solar thermal | D45: =B45 -> 0
A46: biomass | B46: 100 | D46: =B46 -> 100 | G46: other renewables
A47: geothermal | B47: 100 | D47: =B47 -> 100 | G47: other renewables
A48: petroleum | B48: 150 | D48: =B48 -> 150
A49: natural gas peaker | B49: =B40 -> 640 | D49: =B49 -> 640 | G49: = natural gas nonpeaker
A50: lignite | B50: =B39 -> 1180 | D50: =B50 -> 1180
A51: offshore wind | D51: =B51 -> 0 | G51: KEEI 발전원별 균등화 발전원가 최종보고서
A52: crude oil | B52: 150 | D52: =B52 -> 150
A53: heavy or residual fuel oil | B53: 150 | D53: =B53 -> 150
A54: municipal solid waste | B54: 100 | D54: =B54 -> 100 | G54: other renewables
A57: Grid connection (spur line) cost ALREADY INCLUDED in the KEEI CAPEX above, KRW/kW, 2020 basis (KEEI 기본연구 24-22, 재생에너지 LCOE 전망 시스템 5/5, Tables 3-6 / 3-11 / 3-13). Moved out of CCaMC-BCCpUC into CCaMC-SLCCpUC on 2026-09-08 so the total is unchanged.
A58: Technology | B58: KRW/kW | C58: Basis / note
A59: onshore wind | B59: 42000 | C59: 계통연계 row, 20 MW basis, 2020 (40,000 in 2024); 전기공사 (internal electrical works, 116,000) NOT included
A60: solar PV | B60: 23000 | C60: 한전계통비용 row, 3 MW ground-mount basis, 2020 (32,000 in 2024); the separate 변전소 (substation) row is left in CAPEX
A61: offshore wind | B61: 324000 | C61: ASSUMPTION: 50% of KEEI's combined 전기공사+계통연계 (mean of 5 Korean cases 432/740/581/389/1,096 M KRW/MW = 648,000 KRW/kW); KEEI does not split export cable/connection from array cabling. Total capex unaffected by the split.

Sheet NREL ATB
C2: 2022 | D2: 2023 | E2: 2024 | F2: 2025 | G2: 2026 | H2: 2027 | I2: 2028 | J2: 2029 | K2: 2030 | L2: 2031 | M2: 2032 | N2: 2033 | O2: 2034 | P2: 2035 | Q2: 2036 | R2: 2037 | S2: 2038 | T2: 2039 | U2: 2040 | V2: 2041 | W2: 2042 | X2: 2043 | Y2: 2044 | Z2: 2045 | AA2: 2046 | AB2: 2047 | AC2: 2048 | AD2: 2049 | AE2: 2050
A3: Utility PV - Class 1 | B3: Advanced | C3: 1482.6833 | D3: 1610.9047 | E3: 1533.5706 | F3: 1456.2366 | G3: 1378.9026 | H3: 1301.5686 | I3: 1224.2345 | J3: 1146.9005 | K3: 1069.5665 | L3: 992.23246 | M3: 914.89843 | N3: 837.56441 | O3: 760.23038 | P3: 682.89636 | Q3: 674.87452 | R3: 666.85267 | S3: 658.83083 | T3: 650.80899 | U3: 642.78715 | V3: 634.76531 | W3: 626.74347 | X3: 618.72163 | Y3: 610.69979 | Z3: 602.67795 | AA3: 594.65611 | AB3: 586.63427 | AC3: 578.61243 | AD3: 570.59059 | AE3: 562.56875
A4: Utility PV - Class 1 | B4: Moderate | C4: 1482.6833 | D4: 1610.9047 | E4: 1551.2727 | F4: 1491.6407 | G4: 1432.0088 | H4: 1372.3768 | I4: 1312.7449 | J4: 1253.1129 | K4: 1193.4809 | L4: 1133.849 | M4: 1074.217 | N4: 1014.5851 | O4: 954.9531 | P4: 895.32114 | Q4: 881.15949 | R4: 866.99784 | S4: 852.83619 | T4: 838.67453 | U4: 824.51288 | V4: 810.35123 | W4: 796.18958 | X4: 782.02792 | Y4: 767.86627 | Z4: 753.70462 | AA4: 739.54297 | AB4: 725.38131 | AC4: 711.21966 | AD4: 697.05801 | AE4: 682.89636
A5: Utility PV - Class 1 | B5: Conservative | C5: 1482.6833 | D5: 1610.9047 | E5: 1575.7665 | F5: 1540.6284 | G5: 1505.4903 | H5: 1470.3521 | I5: 1435.214 | J5: 1400.0759 | K5: 1364.9377 | L5: 1329.7996 | M5: 1294.6615 | N5: 1259.5234 | O5: 1224.3852 | P5: 1189.2471 | Q5: 1169.652 | R5: 1150.057 | S5: 1130.4619 | T5: 1110.8668 | U5: 1091.2718 | V5: 1071.6767 | W5: 1052.0816 | X5: 1032.4866 | Y5: 1012.8915 | Z5: 993.29646 | AA5: 973.7014 | AB5: 954.10633 | AC5: 934.51127 | AD5: 914.91621 | AE5: 895.32114
A6: Utility PV - Class 2 | B6: Advanced | C6: 1482.6833 | D6: 1610.9047 | E6: 1533.5706 | F6: 1456.2366 | G6: 1378.9026 | H6: 1301.5686 | I6: 1224.2345 | J6: 1146.9005 | K6: 1069.5665 | L6: 992.23246 | M6: 914.89843 | N6: 837.56441 | O6: 760.23038 | P6: 682.89636 | Q6: 674.87452 | R6: 666.85267 | S6: 658.83083 | T6: 650.80899 | U6: 642.78715 | V6: 634.76531 | W6: 626.74347 | X6: 618.72163 | Y6: 610.69979 | Z6: 602.67795 | AA6: 594.65611 | AB6: 586.63427 | AC6: 578.61243 | AD6: 570.59059 | AE6: 562.56875
A7: Utility PV - Class 2 | B7: Moderate | C7: 1482.6833 | D7: 1610.9047 | E7: 1551.2727 | F7: 1491.6407 | G7: 1432.0088 | H7: 1372.3768 | I7: 1312.7449 | J7: 1253.1129 | K7: 1193.4809 | L7: 1133.849 | M7: 1074.217 | N7: 1014.5851 | O7: 954.9531 | P7: 895.32114 | Q7: 881.15949 | R7: 866.99784 | S7: 852.83619 | T7: 838.67453 | U7: 824.51288 | V7: 810.35123 | W7: 796.18958 | X7: 782.02792 | Y7: 767.86627 | Z7: 753.70462 | AA7: 739.54297 | AB7: 725.38131 | AC7: 711.21966 | AD7: 697.05801 | AE7: 682.89636
A8: Utility PV - Class 2 | B8: Conservative | C8: 1482.6833 | D8: 1610.9047 | E8: 1575.7665 | F8: 1540.6284 | G8: 1505.4903 | H8: 1470.3521 | I8: 1435.214 | J8: 1400.0759 | K8: 1364.9377 | L8: 1329.7996 | M8: 1294.6615 | N8: 1259.5234 | O8: 1224.3852 | P8: 1189.2471 | Q8: 1169.652 | R8: 1150.057 | S8: 1130.4619 | T8: 1110.8668 | U8: 1091.2718 | V8: 1071.6767 | W8: 1052.0816 | X8: 1032.4866 | Y8: 1012.8915 | Z8: 993.29646 | AA8: 973.7014 | AB8: 954.10633 | AC8: 934.51127 | AD8: 914.91621 | AE8: 895.32114
A9: Utility PV - Class 3 | B9: Advanced | C9: 1482.6833 | D9: 1610.9047 | E9: 1533.5706 | F9: 1456.2366 | G9: 1378.9026 | H9: 1301.5686 | I9: 1224.2345 | J9: 1146.9005 | K9: 1069.5665 | L9: 992.23246 | M9: 914.89843 | N9: 837.56441 | O9: 760.23038 | P9: 682.89636 | Q9: 674.87452 | R9: 666.85267 | S9: 658.83083 | T9: 650.80899 | U9: 642.78715 | V9: 634.76531 | W9: 626.74347 | X9: 618.72163 | Y9: 610.69979 | Z9: 602.67795 | AA9: 594.65611 | AB9: 586.63427 | AC9: 578.61243 | AD9: 570.59059 | AE9: 562.56875
A10: Utility PV - Class 3 | B10: Moderate | C10: 1482.6833 | D10: 1610.9047 | E10: 1551.2727 | F10: 1491.6407 | G10: 1432.0088 | H10: 1372.3768 | I10: 1312.7449 | J10: 1253.1129 | K10: 1193.4809 | L10: 1133.849 | M10: 1074.217 | N10: 1014.5851 | O10: 954.9531 | P10: 895.32114 | Q10: 881.15949 | R10: 866.99784 | S10: 852.83619 | T10: 838.67453 | U10: 824.51288 | V10: 810.35123 | W10: 796.18958 | X10: 782.02792 | Y10: 767.86627 | Z10: 753.70462 | AA10: 739.54297 | AB10: 725.38131 | AC10: 711.21966 | AD10: 697.05801 | AE10: 682.89636
A11: Utility PV - Class 3 | B11: Conservative | C11: 1482.6833 | D11: 1610.9047 | E11: 1575.7665 | F11: 1540.6284 | G11: 1505.4903 | H11: 1470.3521 | I11: 1435.214 | J11: 1400.0759 | K11: 1364.9377 | L11: 1329.7996 | M11: 1294.6615 | N11: 1259.5234 | O11: 1224.3852 | P11: 1189.2471 | Q11: 1169.652 | R11: 1150.057 | S11: 1130.4619 | T11: 1110.8668 | U11: 1091.2718 | V11: 1071.6767 | W11: 1052.0816 | X11: 1032.4866 | Y11: 1012.8915 | Z11: 993.29646 | AA11: 973.7014 | AB11: 954.10633 | AC11: 934.51127 | AD11: 914.91621 | AE11: 895.32114
A12: Utility PV - Class 4 | B12: Advanced | C12: 1482.6833 | D12: 1610.9047 | E12: 1533.5706 | F12: 1456.2366 | G12: 1378.9026 | H12: 1301.5686 | I12: 1224.2345 | J12: 1146.9005 | K12: 1069.5665 | L12: 992.23246 | M12: 914.89843 | N12: 837.56441 | O12: 760.23038 | P12: 682.89636 | Q12: 674.87452 | R12: 666.85267 | S12: 658.83083 | T12: 650.80899 | U12: 642.78715 | V12: 634.76531 | W12: 626.74347 | X12: 618.72163 | Y12: 610.69979 | Z12: 602.67795 | AA12: 594.65611 | AB12: 586.63427 | AC12: 578.61243 | AD12: 570.59059 | AE12: 562.56875
A13: Utility PV - Class 4 | B13: Moderate | C13: 1482.6833 | D13: 1610.9047 | E13: 1551.2727 | F13: 1491.6407 | G13: 1432.0088 | H13: 1372.3768 | I13: 1312.7449 | J13: 1253.1129 | K13: 1193.4809 | L13: 1133.849 | M13: 1074.217 | N13: 1014.5851 | O13: 954.9531 | P13: 895.32114 | Q13: 881.15949 | R13: 866.99784 | S13: 852.83619 | T13: 838.67453 | U13: 824.51288 | V13: 810.35123 | W13: 796.18958 | X13: 782.02792 | Y13: 767.86627 | Z13: 753.70462 | AA13: 739.54297 | AB13: 725.38131 | AC13: 711.21966 | AD13: 697.05801 | AE13: 682.89636
A14: Utility PV - Class 4 | B14: Conservative | C14: 1482.6833 | D14: 1610.9047 | E14: 1575.7665 | F14: 1540.6284 | G14: 1505.4903 | H14: 1470.3521 | I14: 1435.214 | J14: 1400.0759 | K14: 1364.9377 | L14: 1329.7996 | M14: 1294.6615 | N14: 1259.5234 | O14: 1224.3852 | P14: 1189.2471 | Q14: 1169.652 | R14: 1150.057 | S14: 1130.4619 | T14: 1110.8668 | U14: 1091.2718 | V14: 1071.6767 | W14: 1052.0816 | X14: 1032.4866 | Y14: 1012.8915 | Z14: 993.29646 | AA14: 973.7014 | AB14: 954.10633 | AC14: 934.51127 | AD14: 914.91621 | AE14: 895.32114
... A32: Utility PV - Class 10 | B32: Conservative | C32: 1482.6833 | D32: 1610.9047 | E32: 1575.7665 | F32: 1540.6284 | G32: 1505.4903 | H32: 1470.3521 | I32: 1435.214 | J32: 1400.0759 | K32: 1364.9377 | L32: 1329.7996 | M32: 1294.6615 | N32: 1259.5234 | O32: 1224.3852 | P32: 1189.2471 | Q32: 1169.652 | R32: 1150.057 | S32: 1130.4619 | T32: 1110.8668 | U32: 1091.2718 | V32: 1071.6767 | W32: 1052.0816 | X32: 1032.4866 | Y32: 1012.8915 | Z32: 993.29646 | AA32: 973.7014 | AB32: 954.10633 | AC32: 934.51127 | AD32: 914.91621 | AE32: 895.32114
C34: =AVERAGE(C3:C32) -> 1482.6833 | F34: =AVERAGE(F3:F32) -> 1496.1686 | K34: =AVERAGE(K3:K32) -> 1209.3284
A35: 감소율 | F35: =F34/$C34 -> 1.0090952 | K35: =K34/$C34 -> 0.81563501
C38: 2022 | D38: 2023 | E38: 2024 | F38: 2025 | G38: 2026 | H38: 2027 | I38: 2028 | J38: 2029 | K38: 2030 | L38: 2031 | M38: 2032 | N38: 2033 | O38: 2034 | P38: 2035 | Q38: 2036 | R38: 2037 | S38: 2038 | T38: 2039 | U38: 2040 | V38: 2041 | W38: 2042 | X38: 2043 | Y38: 2044 | Z38: 2045 | AA38: 2046 | AB38: 2047 | AC38: 2048 | AD38: 2049 | AE38: 2050
A39: Land-Based Wind - Class 1 - Technology 1 | B39: Advanced | C39: 1665.7866 | D39: 1777.1999 | E39: 1658.6961 | F39: 1544.2437 | G39: 1503.7295 | H39: 1463.2152 | I39: 1422.7009 | J39: 1382.1866 | K39: 1341.6723 | L39: 1325.0977 | M39: 1308.5231 | N39: 1291.9485 | O39: 1275.3739 | P39: 1258.7993 | Q39: 1242.2246 | R39: 1225.65 | S39: 1209.0754 | T39: 1192.5008 | U39: 1175.9262 | V39: 1159.3516 | W39: 1142.777 | X39: 1126.2023 | Y39: 1109.6277 | Z39: 1093.0531 | AA39: 1076.4785 | AB39: 1059.9039 | AC39: 1043.3293 | AD39: 1026.7547 | AE39: 1010.18
A40: Land-Based Wind - Class 1 - Technology 1 | B40: Moderate | C40: 1665.7866 | D40: 1786.3136 | E40: 1676.0949 | F40: 1569.0991 | G40: 1536.8699 | H40: 1504.6407 | I40: 1472.4116 | J40: 1440.1824 | K40: 1407.9532 | L40: 1393.301 | M40: 1378.6487 | N40: 1363.9965 | O40: 1349.3442 | P40: 1334.692 | Q40: 1320.0397 | R40: 1305.3875 | S40: 1290.7352 | T40: 1276.083 | U40: 1261.4307 | V40: 1246.7785 | W40: 1232.1262 | X40: 1217.474 | Y40: 1202.8217 | Z40: 1188.1695 | AA40: 1173.5172 | AB40: 1158.865 | AC40: 1144.2127 | AD40: 1129.5605 | AE40: 1114.9082
A41: Land-Based Wind - Class 1 - Technology 1 | B41: Conservative | C41: 1665.7866 | D41: 1809.6114 | E41: 1720.5725 | F41: 1632.6385 | G41: 1621.5892 | H41: 1610.5398 | I41: 1599.4905 | J41: 1588.4411 | K41: 1577.3918 | L41: 1566.3437 | M41: 1555.2957 | N41: 1544.2476 | O41: 1533.1996 | P41: 1522.1515 | Q41: 1511.1035 | R41: 1500.0554 | S41: 1489.0074 | T41: 1477.9593 | U41: 1466.9113 | V41: 1455.8632 | W41: 1444.8151 | X41: 1433.7671 | Y41: 1422.719 | Z41: 1411.671 | AA41: 1400.6229 | AB41: 1389.5749 | AC41: 1378.5268 | AD41: 1367.4788 | AE41: 1356.4307
A42: Land-Based Wind - Class 2 - Technology 1 | B42: Advanced | C42: 1665.7866 | D42: 1777.1999 | E42: 1658.6961 | F42: 1544.2437 | G42: 1503.7295 | H42: 1463.2152 | I42: 1422.7009 | J42: 1382.1866 | K42: 1341.6723 | L42: 1325.0977 | M42: 1308.5231 | N42: 1291.9485 | O42: 1275.3739 | P42: 1258.7993 | Q42: 1242.2246 | R42: 1225.65 | S42: 1209.0754 | T42: 1192.5008 | U42: 1175.9262 | V42: 1159.3516 | W42: 1142.777 | X42: 1126.2023 | Y42: 1109.6277 | Z42: 1093.0531 | AA42: 1076.4785 | AB42: 1059.9039 | AC42: 1043.3293 | AD42: 1026.7547 | AE42: 1010.18
A43: Land-Based Wind - Class 2 - Technology 1 | B43: Moderate | C43: 1665.7866 | D43: 1786.3136 | E43: 1676.0949 | F43: 1569.0991 | G43: 1536.8699 | H43: 1504.6407 | I43: 1472.4116 | J43: 1440.1824 | K43: 1407.9532 | L43: 1393.301 | M43: 1378.6487 | N43: 1363.9965 | O43: 1349.3442 | P43: 1334.692 | Q43: 1320.0397 | R43: 1305.3875 | S43: 1290.7352 | T43: 1276.083 | U43: 1261.4307 | V43: 1246.7785 | W43: 1232.1262 | X43: 1217.474 | Y43: 1202.8217 | Z43: 1188.1695 | AA43: 1173.5172 | AB43: 1158.865 | AC43: 1144.2127 | AD43: 1129.5605 | AE43: 1114.9082
A44: Land-Based Wind - Class 2 - Technology 1 | B44: Conservative | C44: 1665.7866 | D44: 1809.6114 | E44: 1720.5725 | F44: 1632.6385 | G44: 1621.5892 | H44: 1610.5398 | I44: 1599.4905 | J44: 1588.4411 | K44: 1577.3918 | L44: 1566.3437 | M44: 1555.2957 | N44: 1544.2476 | O44: 1533.1996 | P44: 1522.1515 | Q44: 1511.1035 | R44: 1500.0554 | S44: 1489.0074 | T44: 1477.9593 | U44: 1466.9113 | V44: 1455.8632 | W44: 1444.8151 | X44: 1433.7671 | Y44: 1422.719 | Z44: 1411.671 | AA44: 1400.6229 | AB44: 1389.5749 | AC44: 1378.5268 | AD44: 1367.4788 | AE44: 1356.4307
A45: Land-Based Wind - Class 3 - Technology 1 | B45: Advanced | C45: 1665.7866 | D45: 1777.1999 | E45: 1658.6961 | F45: 1544.2437 | G45: 1503.7295 | H45: 1463.2152 | I45: 1422.7009 | J45: 1382.1866 | K45: 1341.6723 | L45: 1325.0977 | M45: 1308.5231 | N45: 1291.9485 | O45: 1275.3739 | P45: 1258.7993 | Q45: 1242.2246 | R45: 1225.65 | S45: 1209.0754 | T45: 1192.5008 | U45: 1175.9262 | V45: 1159.3516 | W45: 1142.777 | X45: 1126.2023 | Y45: 1109.6277 | Z45: 1093.0531 | AA45: 1076.4785 | AB45: 1059.9039 | AC45: 1043.3293 | AD45: 1026.7547 | AE45: 1010.18
A46: Land-Based Wind - Class 3 - Technology 1 | B46: Moderate | C46: 1665.7866 | D46: 1786.3136 | E46: 1676.0949 | F46: 1569.0991 | G46: 1536.8699 | H46: 1504.6407 | I46: 1472.4116 | J46: 1440.1824 | K46: 1407.9532 | L46: 1393.301 | M46: 1378.6487 | N46: 1363.9965 | O46: 1349.3442 | P46: 1334.692 | Q46: 1320.0397 | R46: 1305.3875 | S46: 1290.7352 | T46: 1276.083 | U46: 1261.4307 | V46: 1246.7785 | W46: 1232.1262 | X46: 1217.474 | Y46: 1202.8217 | Z46: 1188.1695 | AA46: 1173.5172 | AB46: 1158.865 | AC46: 1144.2127 | AD46: 1129.5605 | AE46: 1114.9082
A47: Land-Based Wind - Class 3 - Technology 1 | B47: Conservative | C47: 1665.7866 | D47: 1809.6114 | E47: 1720.5725 | F47: 1632.6385 | G47: 1621.5892 | H47: 1610.5398 | I47: 1599.4905 | J47: 1588.4411 | K47: 1577.3918 | L47: 1566.3437 | M47: 1555.2957 | N47: 1544.2476 | O47: 1533.1996 | P47: 1522.1515 | Q47: 1511.1035 | R47: 1500.0554 | S47: 1489.0074 | T47: 1477.9593 | U47: 1466.9113 | V47: 1455.8632 | W47: 1444.8151 | X47: 1433.7671 | Y47: 1422.719 | Z47: 1411.671 | AA47: 1400.6229 | AB47: 1389.5749 | AC47: 1378.5268 | AD47: 1367.4788 | AE47: 1356.4307
A48: Land-Based Wind - Class 4 - Technology 1 | B48: Advanced | C48: 1665.7866 | D48: 1777.1999 | E48: 1658.6961 | F48: 1544.2437 | G48: 1503.7295 | H48: 1463.2152 | I48: 1422.7009 | J48: 1382.1866 | K48: 1341.6723 | L48: 1325.0977 | M48: 1308.5231 | N48: 1291.9485 | O48: 1275.3739 | P48: 1258.7993 | Q48: 1242.2246 | R48: 1225.65 | S48: 1209.0754 | T48: 1192.5008 | U48: 1175.9262 | V48: 1159.3516 | W48: 1142.777 | X48: 1126.2023 | Y48: 1109.6277 | Z48: 1093.0531 | AA48: 1076.4785 | AB48: 1059.9039 | AC48: 1043.3293 | AD48: 1026.7547 | AE48: 1010.18
A49: Land-Based Wind - Class 4 - Technology 1 | B49: Moderate | C49: 1665.7866 | D49: 1786.3136 | E49: 1676.0949 | F49: 1569.0991 | G49: 1536.8699 | H49: 1504.6407 | I49: 1472.4116 | J49: 1440.1824 | K49: 1407.9532 | L49: 1393.301 | M49: 1378.6487 | N49: 1363.9965 | O49: 1349.3442 | P49: 1334.692 | Q49: 1320.0397 | R49: 1305.3875 | S49: 1290.7352 | T49: 1276.083 | U49: 1261.4307 | V49: 1246.7785 | W49: 1232.1262 | X49: 1217.474 | Y49: 1202.8217 | Z49: 1188.1695 | AA49: 1173.5172 | AB49: 1158.865 | AC49: 1144.2127 | AD49: 1129.5605 | AE49: 1114.9082
A50: Land-Based Wind - Class 4 - Technology 1 | B50: Conservative | C50: 1665.7866 | D50: 1809.6114 | E50: 1720.5725 | F50: 1632.6385 | G50: 1621.5892 | H50: 1610.5398 | I50: 1599.4905 | J50: 1588.4411 | K50: 1577.3918 | L50: 1566.3437 | M50: 1555.2957 | N50: 1544.2476 | O50: 1533.1996 | P50: 1522.1515 | Q50: 1511.1035 | R50: 1500.0554 | S50: 1489.0074 | T50: 1477.9593 | U50: 1466.9113 | V50: 1455.8632 | W50: 1444.8151 | X50: 1433.7671 | Y50: 1422.719 | Z50: 1411.671 | AA50: 1400.6229 | AB50: 1389.5749 | AC50: 1378.5268 | AD50: 1367.4788 | AE50: 1356.4307
... A68: Land-Based Wind - Class 10 - Technology 4 | B68: Conservative | C68: 2334.7859 | D68: 2534.5084 | E68: 2402.0177 | F68: 2271.6321 | G68: 2250.5808 | H68: 2229.5295 | I68: 2208.4782 | J68: 2187.427 | K68: 2166.3757 | L68: 2151.4337 | M68: 2136.4917 | N68: 2121.5497 | O68: 2106.6076 | P68: 2091.6656 | Q68: 2076.7236 | R68: 2061.7816 | S68: 2046.8396 | T68: 2031.8975 | U68: 2016.9555 | V68: 2002.0135 | W68: 1987.0715 | X68: 1972.1295 | Y68: 1957.1875 | Z68: 1942.2454 | AA68: 1927.3034 | AB68: 1912.3614 | AC68: 1897.4194 | AD68: 1882.4774 | AE68: 1867.5354
C69: =AVERAGE(C39:C68) -> 1753.3776 | F69: =AVERAGE(F39:F68) -> 1663.3109 | K69: =AVERAGE(K39:K68) -> 1513.1997
F70: =F69/$C$69 -> 0.94863245 | K70: =K69/$C$69 -> 0.86301988
C73: 2022 | D73: 2023 | E73: 2024 | F73: 2025 | G73: 2026 | H73: 2027 | I73: 2028 | J73: 2029 | K73: 2030 | L73: 2031 | M73: 2032 | N73: 2033 | O73: 2034 | P73: 2035 | Q73: 2036 | R73: 2037 | S73: 2038 | T73: 2039 | U73: 2040 | V73: 2041 | W73: 2042 | X73: 2043 | Y73: 2044 | Z73: 2045 | AA73: 2046 | AB73: 2047 | AC73: 2048 | AD73: 2049 | AE73: 2050
A74: Offshore Wind - Class 1 | B74: Advanced | C74: 5493.2473 | D74: 5086.3064 | E74: 4846.1825 | F74: 4678.5633 | G74: 4208.0104 | H74: 3763.8044 | I74: 3336.9353 | J74: 3264.6893 | K74: 3201.9438 | L74: 3117.8664 | M74: 3046.8906 | N74: 2985.673 | O74: 2931.9862 | P74: 2884.2751 | Q74: 2852.3719 | R74: 2822.7353 | S74: 2795.0836 | T74: 2769.1837 | U74: 2744.8404 | V74: 2721.8887 | W74: 2700.188 | X74: 2679.6173 | Y74: 2660.0725 | Z74: 2641.4625 | AA74: 2623.7074 | AB74: 2606.7375 | AC74: 2590.4907 | AD74: 2574.9118 | AE74: 2559.9516
A75: Offshore Wind - Class 1 | B75: Moderate | C75: 6252.4766 | D75: 6049.2989 | E75: 5905.0969 | F75: 5794.1397 | G75: 5704.413 | H75: 5629.3642 | I75: 5207.7543 | J75: 4794.3037 | K75: 4387.2589 | L75: 3954.965 | M75: 3534.0054 | N75: 3478.8168 | O75: 3430.208 | P75: 3386.8418 | Q75: 3357.7543 | R75: 3330.6676 | S75: 3305.3374 | T75: 3281.5609 | U75: 3259.1678 | V75: 3238.0139 | W75: 3217.9762 | X75: 3198.9487 | Y75: 3180.8394 | Z75: 3163.5686 | AA75: 3147.0659 | AB75: 3131.2694 | AC75: 3116.1242 | AD75: 3101.5817 | AE75: 3087.5982
A76: Offshore Wind - Class 1 | B76: Conservative | C76: 7592.293 | D76: 7555.2279 | E76: 7521.4576 | F76: 7490.4635 | G76: 7461.839 | H76: 7435.2599 | I76: 7410.4634 | J76: 7387.2341 | K76: 6844.3527 | L76: 6261.9671 | M76: 5688.5559 | N76: 5121.9004 | O76: 4560.5071 | P76: 4003.3242 | Q76: 3979.0053 | R76: 3956.3035 | S76: 3935.0248 | T76: 3915.0077 | U76: 3896.1162 | V76: 3878.2353 | W76: 3861.266 | X76: 3845.1236 | Y76: 3829.7341 | Z76: 3815.0329 | AA76: 3800.9637 | AB76: 3787.476 | AC76: 3774.526 | AD76: 3762.0737 | AE76: 3750.0838
A77: Offshore Wind - Class 2 | B77: Advanced | C77: 5340.258 | D77: 4944.6506 | E77: 4711.2142 | F77: 4548.2634 | G77: 4090.8156 | H77: 3658.9809 | I77: 3244.0004 | J77: 3173.7663 | K77: 3112.7685 | L77: 3031.0326 | M77: 2962.0335 | N77: 2902.5208 | O77: 2850.3292 | P77: 2803.9468 | Q77: 2772.9323 | R77: 2744.1211 | S77: 2717.2394 | T77: 2692.0609 | U77: 2668.3954 | V77: 2646.083 | W77: 2624.9866 | X77: 2604.9889 | Y77: 2585.9884 | Z77: 2567.8966 | AA77: 2550.6361 | AB77: 2534.1388 | AC77: 2518.3445 | AD77: 2503.1995 | AE77: 2488.6558
A78: Offshore Wind - Class 2 | B78: Moderate | C78: 6078.3426 | D78: 5880.8234 | E78: 5740.6376 | F78: 5632.7705 | G78: 5545.5427 | H78: 5472.584 | I78: 5062.7162 | J78: 4660.7804 | K78: 4265.0719 | L78: 3844.8175 | M78: 3435.5819 | N78: 3381.9304 | O78: 3334.6753 | P78: 3292.5168 | Q78: 3264.2394 | R78: 3237.9071 | S78: 3213.2824 | T78: 3190.1681 | U78: 3168.3987 | V78: 3147.8339 | W78: 3128.3543 | X78: 3109.8566 | Y78: 3092.2518 | Z78: 3075.4619 | AA78: 3059.4188 | AB78: 3044.0623 | AC78: 3029.339 | AD78: 3015.2014 | AE78: 3001.6073
A79: Offshore Wind - Class 2 | B79: Conservative | C79: 7380.8445 | D79: 7344.8116 | E79: 7311.982 | F79: 7281.8511 | G79: 7254.0237 | H79: 7228.1848 | I79: 7204.079 | J79: 7181.4966 | K79: 6653.7347 | L79: 6087.5687 | M79: 5530.1274 | N79: 4979.2534 | O79: 4433.4951 | P79: 3891.83 | Q79: 3868.1884 | R79: 3846.1187 | S79: 3825.4327 | T79: 3805.9731 | U79: 3787.6078 | V79: 3770.2248 | W79: 3753.7282 | X79: 3738.0353 | Y79: 3723.0743 | Z79: 3708.7828 | AA79: 3695.1052 | AB79: 3681.9932 | AC79: 3669.4039 | AD79: 3657.2983 | AE79: 3645.6425
A80: Offshore Wind - Class 3 | B80: Advanced | C80: 5571.8792 | D80: 5159.1133 | E80: 4915.5521 | F80: 4745.5338 | G80: 4268.2451 | H80: 3817.6806 | I80: 3384.7014 | J80: 3311.4211 | K80: 3247.7775 | L80: 3162.4966 | M80: 3090.5047 | N80: 3028.4109 | O80: 2973.9555 | P80: 2925.5615 | Q80: 2893.2018 | R80: 2863.1408 | S80: 2835.0933 | T80: 2808.8227 | U80: 2784.1308 | V80: 2760.8506 | W80: 2738.8393 | X80: 2717.9742 | Y80: 2698.1496 | Z80: 2679.2731 | AA80: 2661.264 | AB80: 2644.0512 | AC80: 2627.5717 | AD80: 2611.7698 | AE80: 2596.5955
A81: Offshore Wind - Class 3 | B81: Moderate | C81: 6341.9765 | D81: 6135.8904 | E81: 5989.6243 | F81: 5877.0787 | G81: 5786.0677 | H81: 5709.9446 | I81: 5282.2996 | J81: 4862.9309 | K81: 4450.0595 | L81: 4011.5775 | M81: 3584.5922 | N81: 3528.6136 | O81: 3479.3091 | P81: 3435.3221 | Q81: 3405.8182 | R81: 3378.3438 | S81: 3352.651 | T81: 3328.5342 | U81: 3305.8205 | V81: 3284.3638 | W81: 3264.0393 | X81: 3244.7394 | Y81: 3226.371 | Z81: 3208.8529 | AA81: 3192.114 | AB81: 3176.0914 | AC81: 3160.7295 | AD81: 3145.9788 | AE81: 3131.795
A82: Offshore Wind - Class 3 | B82: Conservative | C82: 7700.9713 | D82: 7663.3757 | E82: 7629.1221 | F82: 7597.6843 | G82: 7568.65 | H82: 7541.6905 | I82: 7516.5391 | J82: 7492.9772 | K82: 6942.3249 | L82: 6351.6028 | M82: 5769.9837 | N82: 5195.2169 | O82: 4625.7876 | P82: 4060.629 | Q82: 4035.962 | R82: 4012.9352 | S82: 3991.352 | T82: 3971.0482 | U82: 3951.8865 | V82: 3933.7495 | W82: 3916.5373 | X82: 3900.1639 | Y82: 3884.554 | Z82: 3869.6425 | AA82: 3855.3717 | AB82: 3841.6912 | AC82: 3828.5557 | AD82: 3815.9252 | AE82: 3803.7638
A83: Offshore Wind - Class 4 | B83: Advanced | C83: 5974.4515 | D83: 5531.8628 | E83: 5270.7043 | F83: 5088.4019 | G83: 4576.6288 | H83: 4093.5107 | I83: 3629.2484 | J83: 3550.6736 | K83: 3482.4317 | L83: 3390.9893 | M83: 3313.7959 | N83: 3247.2156 | O83: 3188.8258 | P83: 3136.9353 | Q83: 3102.2376 | R83: 3070.0048 | S83: 3039.9308 | T83: 3011.7621 | U83: 2985.2863 | V83: 2960.324 | W83: 2936.7223 | X83: 2914.3499 | Y83: 2893.0929 | Z83: 2872.8525 | AA83: 2853.5423 | AB83: 2835.0857 | AC83: 2817.4157 | AD83: 2800.4721 | AE83: 2784.2013
A84: Offshore Wind - Class 4 | B84: Moderate | C84: 6800.1887 | D84: 6579.2129 | E84: 6422.379 | F84: 6301.7019 | G84: 6204.1152 | H84: 6122.4921 | I84: 5663.9496 | J84: 5214.2811 | K84: 4771.5795 | L84: 4301.4168 | M84: 3843.5815 | N84: 3783.5585 | O84: 3730.6915 | P84: 3683.5265 | Q84: 3651.8909 | R84: 3622.4315 | S84: 3594.8824 | T84: 3569.0231 | U84: 3544.6684 | V84: 3521.6616 | W84: 3499.8685 | X84: 3479.1741 | Y84: 3459.4785 | Z84: 3440.6948 | AA84: 3422.7465 | AB84: 3405.5662 | AC84: 3389.0944 | AD84: 3373.2779 | AE84: 3358.0695
A85: Offshore Wind - Class 4 | B85: Conservative | C85: 8257.3721 | D85: 8217.0601 | E85: 8180.3316 | F85: 8146.6223 | G85: 8115.4904 | H85: 8086.5829 | I85: 8059.6143 | J85: 8034.3501 | K85: 7443.9128 | L85: 6810.5106 | M85: 6186.8692 | N85: 5570.575 | O85: 4960.0041 | P85: 4354.0124 | Q85: 4327.5631 | R85: 4302.8726 | S85: 4279.7299 | T85: 4257.9594 | U85: 4237.413 | V85: 4217.9657 | W85: 4199.5099 | X85: 4181.9534 | Y85: 4165.2158 | Z85: 4149.2269 | AA85: 4133.9251 | AB85: 4119.2561 | AC85: 4105.1715 | AD85: 4091.6285 | AE85: 4078.5883
... A94: Offshore Wind - Class 7 | B94: Conservative | C94: 8860.8681 | D94: 8817.6099 | E94: 8778.1971 | F94: 8742.0242 | G94: 8708.6169 | H94: 8677.5967 | I94: 8648.6572 | J94: 8621.5465 | K94: 7987.9565 | L94: 7308.2618 | M94: 6639.0408 | N94: 5977.7045 | O94: 5322.5096 | P94: 4672.2285 | Q94: 4643.8462 | R94: 4617.3512 | S94: 4592.5171 | T94: 4569.1553 | U94: 4547.1075 | V94: 4526.2388 | W94: 4506.4343 | X94: 4487.5946 | Y94: 4469.6336 | Z94: 4452.4762 | AA94: 4436.056 | AB94: 4420.3148 | AC94: 4405.201 | AD94: 4390.6681 | AE94: 4376.675
C95: =AVERAGE(C75:C93) -> 6866.6965 | F95: =AVERAGE(F75:F93) -> 6373.9253 | K95: =AVERAGE(K75:K93) -> 5100.1161
F96: =F95/$C$95 -> 0.92823753 | K96: =K95/$C$95 -> 0.74273213
C98: 2030 | D98: 2031 | E98: 2032 | F98: 2033 | G98: 2034 | H98: 2035 | I98: 2036 | J98: 2037 | K98: 2038 | L98: 2039 | M98: 2040 | N98: 2041 | O98: 2042 | P98: 2043 | Q98: 2044 | R98: 2045 | S98: 2046 | T98: 2047 | U98: 2048 | V98: 2049 | W98: 2050
A99: Offshore Wind - Class 8 | B99: Advanced | C99: 5512.0168 | D99: 4840.6977 | E99: 4462.9496 | F99: 4206.1042 | G99: 4014.2399 | H99: 3862.5383 | I99: 3531.5499 | J99: 3314.0578 | K99: 3154.6252 | L99: 3030.0698 | M99: 2928.6044 | N99: 2843.4615 | O99: 2770.4174 | P99: 2706.6685 | Q99: 2650.2653 | R99: 2599.7999 | S99: 2554.2255 | T99: 2512.7426 | U99: 2474.7288 | V99: 2439.69 | W99: 2407.2283
A100: Offshore Wind - Class 8 | B100: Moderate | C100: 7989.7278 | D100: 6864.2207 | E100: 6037.6043 | F100: 5758.7797 | G100: 5548.2481 | H100: 5380.344 | I100: 5009.2632 | J100: 4761.6045 | K100: 4577.9692 | L100: 4433.198 | M100: 4314.3731 | N100: 4214.02 | O100: 4127.4415 | P100: 4051.5028 | Q100: 3984.0121 | R100: 3923.3802 | S100: 3868.4194 | T100: 3818.2203 | U100: 3772.0717 | V100: 3729.4077 | W100: 3689.7707
A101: Offshore Wind - Class 8 | B101: Conservative | C101: 12503.108 | D101: 11187.199 | E101: 10160.049 | F101: 9256.4064 | G101: 8420.8779 | H101: 7628.2876 | I101: 7232.7582 | J101: 6964.6265 | K101: 6763.512 | L101: 6603.5082 | M101: 6471.1836 | N101: 6358.704 | O101: 6261.1139 | P101: 6175.0865 | Q101: 6098.2838 | R101: 6029.003 | S101: 5965.966 | T101: 5908.1907 | U101: 5854.9061 | V101: 5805.4968 | W101: 5759.4638
A102: Offshore Wind - Class 9 | B102: Advanced | C102: 5864.7201 | D102: 5150.4445 | E102: 4748.5251 | F102: 4475.2446 | G102: 4271.1033 | H102: 4109.6947 | I102: 3757.527 | J102: 3526.118 | K102: 3356.4836 | L102: 3223.9581 | M102: 3116.0002 | N102: 3025.4091 | O102: 2947.691 | P102: 2879.8629 | Q102: 2819.8505 | R102: 2766.1561 | S102: 2717.6653 | T102: 2673.5282 | U102: 2633.0819 | V102: 2595.8011 | W102: 2561.2622
A103: Offshore Wind - Class 9 | B103: Moderate | C103: 8500.9752 | D103: 7303.4489 | E103: 6423.9389 | F103: 6127.2729 | G103: 5903.2698 | H103: 5724.6219 | I103: 5329.7964 | J103: 5066.2905 | K103: 4870.9046 | L103: 4716.8698 | M103: 4590.4416 | N103: 4483.667 | O103: 4391.5485 | P103: 4310.7506 | Q103: 4238.9414 | R103: 4174.4297 | S103: 4115.9521 | T103: 4062.5409 | U103: 4013.4393 | V103: 3968.0454 | W103: 3925.872
A104: Offshore Wind - Class 9 | B104: Conservative | C104: 13303.158 | D104: 11903.047 | E104: 10810.171 | F104: 9848.7059 | G104: 8959.7135 | H104: 8116.4069 | I104: 7695.5684 | J104: 7410.2796 | K104: 7196.2961 | L104: 7026.0539 | M104: 6885.2622 | N104: 6765.5853 | O104: 6661.7505 | P104: 6570.2183 | Q104: 6488.5013 | R104: 6414.7872 | S104: 6347.7166 | T104: 6286.2443 | U104: 6229.5502 | V104: 6176.9793 | W104: 6128.0006
A105: Offshore Wind - Class 10 | B105: Advanced | C105: 6033.9596 | D105: 5299.0719 | E105: 4885.5543 | F105: 4604.3877 | G105: 4394.3554 | H105: 4228.2889 | I105: 3865.9587 | J105: 3627.8719 | K105: 3453.3424 | L105: 3316.9926 | M105: 3205.9193 | N105: 3112.7141 | O105: 3032.7531 | P105: 2962.9677 | Q105: 2901.2234 | R105: 2845.9797 | S105: 2796.0896 | T105: 2750.6787 | U105: 2709.0654 | V105: 2670.7087 | W105: 2635.1729
A106: Offshore Wind - Class 10 | B106: Moderate | C106: 8746.2895 | D106: 7514.206 | E106: 6609.3158 | F106: 6304.0889 | G106: 6073.6217 | H106: 5889.8185 | I106: 5483.5993 | J106: 5212.4894 | K106: 5011.4653 | L106: 4852.9855 | M106: 4722.9089 | N106: 4613.0531 | O106: 4518.2763 | P106: 4435.1467 | Q106: 4361.2654 | R106: 4294.8922 | S106: 4234.7271 | T106: 4179.7744 | U106: 4129.256 | V106: 4082.552 | W106: 4039.1616
A107: Offshore Wind - Class 10 | B107: Conservative | C107: 13687.05 | D107: 12246.535 | E107: 11122.122 | F107: 10132.912 | G107: 9218.2658 | H107: 8350.6238 | I107: 7917.6409 | J107: 7624.1195 | K107: 7403.9611 | L107: 7228.8061 | M107: 7083.9515 | N107: 6960.8211 | O107: 6853.99 | P107: 6759.8164 | Q107: 6675.7413 | R107: 6599.9 | S107: 6530.894 | T107: 6467.6478 | U107: 6409.3176 | V107: 6355.2296 | W107: 6304.8377
A108: Offshore Wind - Class 11 | B108: Advanced | C108: 6220.1358 | D108: 5462.5734 | E108: 5036.2968 | F108: 4746.4549 | G108: 4529.9421 | H108: 4358.7518 | I108: 3985.242 | J108: 3739.8089 | K108: 3559.8943 | L108: 3419.3375 | M108: 3304.837 | N108: 3208.7562 | O108: 3126.3279 | P108: 3054.3893 | Q108: 2990.7401 | R108: 2933.7917 | S108: 2882.3622 | T108: 2835.5501 | U108: 2792.6528 | V108: 2753.1127 | W108: 2716.4805
A109: Offshore Wind - Class 11 | B109: Moderate | C109: 9016.1541 | D109: 7746.0549 | E109: 6813.2446 | F109: 6498.5999 | G109: 6261.0218 | H109: 6071.5474 | I109: 5652.7944 | J109: 5373.3194 | K109: 5166.0929 | L109: 5002.7231 | M109: 4868.6331 | N109: 4755.3877 | O109: 4657.6866 | P109: 4571.9922 | Q109: 4495.8311 | R109: 4427.4099 | S109: 4365.3884 | T109: 4308.7402 | U109: 4256.6631 | V109: 4208.5181 | W109: 4163.7889
A110: Offshore Wind - Class 11 | B110: Conservative | C110: 14109.36 | D110: 12624.399 | E110: 11465.292 | F110: 10445.56 | G110: 9502.693 | H110: 8608.2801 | I110: 8161.9377 | J110: 7859.3597 | K110: 7632.4085 | L110: 7451.8491 | M110: 7302.5251 | N110: 7175.5954 | O110: 7065.4682 | P110: 6968.3889 | Q110: 6881.7196 | R110: 6803.5383 | S110: 6732.4031 | T110: 6667.2054 | U110: 6607.0754 | V110: 6551.3186 | W110: 6499.3719
... A119: Offshore Wind - Class 14 | B119: Conservative | C119: 17789.161 | D119: 15916.914 | E119: 14455.505 | F119: 13169.822 | G119: 11981.049 | H119: 10853.368 | I119: 10290.617 | J119: 9909.1254 | K119: 9622.9839 | L119: 9395.3337 | M119: 9207.065 | N119: 9047.0315 | O119: 8908.1823 | P119: 8785.7841 | Q119: 8676.5111 | R119: 8577.9397 | S119: 8488.2519 | T119: 8406.0504 | U119: 8330.2382 | V119: 8259.9396 | W119: 8194.4448

Sheet Calculation
A2: CAPEX (KRW/kW) | B2: 2020 | C2: 2021 | D2: 2022 | E2: 2023 | F2: 2024 | G2: 2025 | H2: 2026 | I2: 2027 | J2: 2028 | K2: 2029 | L2: 2030 | M2: 2031 | N2: 2032 | O2: 2033 | P2: 2034 | Q2: 2035 | R2: 2036 | S2: 2037 | T2: 2038 | U2: 2039 | V2: 2040 | W2: 2041 | X2: 2042 | Y2: 2043 | Z2: 2044 | AA2: 2045 | AB2: 2046 | AC2: 2047 | AD2: 2048 | AE2: 2049 | AF2: 2050
A3: hard coal | B3: =KRW!B3 -> 1438461 | C3: =B3+($L3-$B3)/($L$2-$B$2) -> 1490860 | D3: =C3+($L3-$B3)/($L$2-$B$2) -> 1543259 | E3: =D3+($L3-$B3)/($L$2-$B$2) -> 1595658 | F3: =E3+($L3-$B3)/($L$2-$B$2) -> 1648057 | G3: =F3+($L3-$B3)/($L$2-$B$2) -> 1700456 | H3: =G3+($L3-$B3)/($L$2-$B$2) -> 1752855 | I3: =H3+($L3-$B3)/($L$2-$B$2) -> 1805254 | J3: =I3+($L3-$B3)/($L$2-$B$2) -> 1857653 | K3: =J3+($L3-$B3)/($L$2-$B$2) -> 1910052 | L3: =KRW!D3 -> 1962451 | M3: {=TREND($B3:$L3,$B$2:$L$2,M$2)} -> 2014850 | N3: {=TREND($B3:$L3,$B$2:$L$2,N$2)} -> 2067249 | O3: {=TREND($B3:$L3,$B$2:$L$2,O$2)} -> 2119648 | P3: {=TREND($B3:$L3,$B$2:$L$2,P$2)} -> 2172047 | Q3: {=TREND($B3:$L3,$B$2:$L$2,Q$2)} -> 2224446 | R3: {=TREND($B3:$L3,$B$2:$L$2,R$2)} -> 2276845 | S3: {=TREND($B3:$L3,$B$2:$L$2,S$2)} -> 2329244 | T3: {=TREND($B3:$L3,$B$2:$L$2,T$2)} -> 2381643 | ... AF3: {=TREND($B3:$L3,$B$2:$L$2,AF$2)} -> 3010431
A4: natural gas nonpeaker | B4: =KRW!B4 -> 939879 | C4: =B4+($L4-$B4)/($L$2-$B$2) -> 948379 | D4: =C4+($L4-$B4)/($L$2-$B$2) -> 956879 | E4: =D4+($L4-$B4)/($L$2-$B$2) -> 965379 | F4: =E4+($L4-$B4)/($L$2-$B$2) -> 973879 | G4: =F4+($L4-$B4)/($L$2-$B$2) -> 982379 | H4: =G4+($L4-$B4)/($L$2-$B$2) -> 990879 | I4: =H4+($L4-$B4)/($L$2-$B$2) -> 999379 | J4: =I4+($L4-$B4)/($L$2-$B$2) -> 1007879 | K4: =J4+($L4-$B4)/($L$2-$B$2) -> 1016379 | L4: =KRW!D4 -> 1024879 | M4: {=TREND($B4:$L4,$B$2:$L$2,M$2)} -> 1033379 | N4: {=TREND($B4:$L4,$B$2:$L$2,N$2)} -> 1041879 | O4: {=TREND($B4:$L4,$B$2:$L$2,O$2)} -> 1050379 | P4: {=TREND($B4:$L4,$B$2:$L$2,P$2)} -> 1058879 | Q4: {=TREND($B4:$L4,$B$2:$L$2,Q$2)} -> 1067379 | R4: {=TREND($B4:$L4,$B$2:$L$2,R$2)} -> 1075879 | S4: {=TREND($B4:$L4,$B$2:$L$2,S$2)} -> 1084379 | T4: {=TREND($B4:$L4,$B$2:$L$2,T$2)} -> 1092879 | ... AF4: {=TREND($B4:$L4,$B$2:$L$2,AF$2)} -> 1194879
A5: nuclear | B5: =KRW!B5 -> 4533116.3 | C5: =B5+($L5-$B5)/($L$2-$B$2) -> 4644716.3 | D5: =C5+($L5-$B5)/($L$2-$B$2) -> 4756316.3 | E5: =D5+($L5-$B5)/($L$2-$B$2) -> 4867916.3 | F5: =E5+($L5-$B5)/($L$2-$B$2) -> 4979516.3 | G5: =F5+($L5-$B5)/($L$2-$B$2) -> 5091116.3 | H5: =G5+($L5-$B5)/($L$2-$B$2) -> 5202716.3 | I5: =H5+($L5-$B5)/($L$2-$B$2) -> 5314316.3 | J5: =I5+($L5-$B5)/($L$2-$B$2) -> 5425916.3 | K5: =J5+($L5-$B5)/($L$2-$B$2) -> 5537516.3 | L5: =KRW!D5 -> 5649116.3 | M5: {=TREND($B5:$L5,$B$2:$L$2,M$2)} -> 5760716.3 | N5: {=TREND($B5:$L5,$B$2:$L$2,N$2)} -> 5872316.3 | O5: {=TREND($B5:$L5,$B$2:$L$2,O$2)} -> 5983916.3 | P5: {=TREND($B5:$L5,$B$2:$L$2,P$2)} -> 6095516.3 | Q5: {=TREND($B5:$L5,$B$2:$L$2,Q$2)} -> 6207116.3 | R5: {=TREND($B5:$L5,$B$2:$L$2,R$2)} -> 6318716.3 | S5: {=TREND($B5:$L5,$B$2:$L$2,S$2)} -> 6430316.3 | T5: {=TREND($B5:$L5,$B$2:$L$2,T$2)} -> 6541916.3 | ... AF5: {=TREND($B5:$L5,$B$2:$L$2,AF$2)} -> 7881116.3
A6: hydro | B6: =KRW!B6 -> 968700 | C6: =B6+($L6-$B6)/($L$2-$B$2) -> 968700 | D6: =C6+($L6-$B6)/($L$2-$B$2) -> 968700 | E6: =D6+($L6-$B6)/($L$2-$B$2) -> 968700 | F6: =E6+($L6-$B6)/($L$2-$B$2) -> 968700 | G6: =F6+($L6-$B6)/($L$2-$B$2) -> 968700 | H6: =G6+($L6-$B6)/($L$2-$B$2) -> 968700 | I6: =H6+($L6-$B6)/($L$2-$B$2) -> 968700 | J6: =I6+($L6-$B6)/($L$2-$B$2) -> 968700 | K6: =J6+($L6-$B6)/($L$2-$B$2) -> 968700 | L6: =KRW!D6 -> 968700 | M6: {=TREND($B6:$L6,$B$2:$L$2,M$2)} -> 968700 | N6: {=TREND($B6:$L6,$B$2:$L$2,N$2)} -> 968700 | O6: {=TREND($B6:$L6,$B$2:$L$2,O$2)} -> 968700 | P6: {=TREND($B6:$L6,$B$2:$L$2,P$2)} -> 968700 | Q6: {=TREND($B6:$L6,$B$2:$L$2,Q$2)} -> 968700 | R6: {=TREND($B6:$L6,$B$2:$L$2,R$2)} -> 968700 | S6: {=TREND($B6:$L6,$B$2:$L$2,S$2)} -> 968700 | T6: {=TREND($B6:$L6,$B$2:$L$2,T$2)} -> 968700 | ... AF6: {=TREND($B6:$L6,$B$2:$L$2,AF$2)} -> 968700
A7: onshore wind | B7: =KRW!B7 -> 2736378 | C7: =B7+($G7-$B7)/($G$2-$B$2) -> 2709014.2 | D7: =C7+($G7-$B7)/($G$2-$B$2) -> 2681650.4 | E7: =D7+($G7-$B7)/($G$2-$B$2) -> 2654286.7 | F7: =E7+($G7-$B7)/($G$2-$B$2) -> 2626922.9 | G7: =KRW!C7 -> 2599559.1 | H7: =G7+($L7-$G7)/($L$2-$G$2) -> 2550304.3 | I7: =H7+($L7-$G7)/($L$2-$G$2) -> 2501049.5 | J7: =I7+($L7-$G7)/($L$2-$G$2) -> 2451794.7 | K7: =J7+($L7-$G7)/($L$2-$G$2) -> 2402539.9 | L7: =KRW!D7 -> 2353285.1 | M7: {=TREND($B7:$L7,$B$2:$L$2,M$2)} -> 2339852 | N7: {=TREND($B7:$L7,$B$2:$L$2,N$2)} -> 2301542.7 | O7: {=TREND($B7:$L7,$B$2:$L$2,O$2)} -> 2263233.4 | P7: {=TREND($B7:$L7,$B$2:$L$2,P$2)} -> 2224924.1 | Q7: {=TREND($B7:$L7,$B$2:$L$2,Q$2)} -> 2186614.8 | R7: {=TREND($B7:$L7,$B$2:$L$2,R$2)} -> 2148305.5 | S7: {=TREND($B7:$L7,$B$2:$L$2,S$2)} -> 2109996.2 | T7: {=TREND($B7:$L7,$B$2:$L$2,T$2)} -> 2071686.9 | ... AF7: {=TREND($B7:$L7,$B$2:$L$2,AF$2)} -> 1611975.4
A8: solar PV | B8: =KRW!B8 -> 1370174 | C8: =B8+($G8-$B8)/($G$2-$B$2) -> 1370174 | D8: =C8+($G8-$B8)/($G$2-$B$2) -> 1370174 | E8: =D8+($G8-$B8)/($G$2-$B$2) -> 1370174 | F8: =E8+($G8-$B8)/($G$2-$B$2) -> 1370174 | G8: =KRW!C8 -> 1370174 | H8: =G8+($L8-$G8)/($L$2-$G$2) -> 1320847.7 | I8: =H8+($L8-$G8)/($L$2-$G$2) -> 1271521.5 | J8: =I8+($L8-$G8)/($L$2-$G$2) -> 1222195.2 | K8: =J8+($L8-$G8)/($L$2-$G$2) -> 1172868.9 | L8: =KRW!D8 -> 1123542.7 | M8: {=TREND($B8:$L8,$B$2:$L$2,M$2)} -> 1154932.1 | N8: {=TREND($B8:$L8,$B$2:$L$2,N$2)} -> 1130269 | O8: {=TREND($B8:$L8,$B$2:$L$2,O$2)} -> 1105605.9 | P8: {=TREND($B8:$L8,$B$2:$L$2,P$2)} -> 1080942.7 | Q8: {=TREND($B8:$L8,$B$2:$L$2,Q$2)} -> 1056279.6 | R8: {=TREND($B8:$L8,$B$2:$L$2,R$2)} -> 1031616.5 | S8: {=TREND($B8:$L8,$B$2:$L$2,S$2)} -> 1006953.3 | T8: {=TREND($B8:$L8,$B$2:$L$2,T$2)} -> 982290.2 | ... AF8: {=TREND($B8:$L8,$B$2:$L$2,AF$2)} -> 686332.61
A9: solar thermal | B9: =KRW!B9 -> 0 | C9: =B9+($L9-$B9)/($L$2-$B$2) -> 0 | D9: =C9+($L9-$B9)/($L$2-$B$2) -> 0 | E9: =D9+($L9-$B9)/($L$2-$B$2) -> 0 | F9: =E9+($L9-$B9)/($L$2-$B$2) -> 0 | G9: =F9+($L9-$B9)/($L$2-$B$2) -> 0 | H9: =G9+($L9-$B9)/($L$2-$B$2) -> 0 | I9: =H9+($L9-$B9)/($L$2-$B$2) -> 0 | J9: =I9+($L9-$B9)/($L$2-$B$2) -> 0 | K9: =J9+($L9-$B9)/($L$2-$B$2) -> 0 | L9: =KRW!D9 -> 0 | M9: {=TREND($B9:$L9,$B$2:$L$2,M$2)} -> 0 | N9: {=TREND($B9:$L9,$B$2:$L$2,N$2)} -> 0 | O9: {=TREND($B9:$L9,$B$2:$L$2,O$2)} -> 0 | P9: {=TREND($B9:$L9,$B$2:$L$2,P$2)} -> 0 | Q9: {=TREND($B9:$L9,$B$2:$L$2,Q$2)} -> 0 | R9: {=TREND($B9:$L9,$B$2:$L$2,R$2)} -> 0 | S9: {=TREND($B9:$L9,$B$2:$L$2,S$2)} -> 0 | T9: {=TREND($B9:$L9,$B$2:$L$2,T$2)} -> 0 | ... AF9: {=TREND($B9:$L9,$B$2:$L$2,AF$2)} -> 0
A10: biomass | B10: =KRW!B10 -> 3823333.5 | C10: =B10+($L10-$B10)/($L$2-$B$2) -> 3823333.5 | D10: =C10+($L10-$B10)/($L$2-$B$2) -> 3823333.5 | E10: =D10+($L10-$B10)/($L$2-$B$2) -> 3823333.5 | F10: =E10+($L10-$B10)/($L$2-$B$2) -> 3823333.5 | G10: =F10+($L10-$B10)/($L$2-$B$2) -> 3823333.5 | H10: =G10+($L10-$B10)/($L$2-$B$2) -> 3823333.5 | I10: =H10+($L10-$B10)/($L$2-$B$2) -> 3823333.5 | J10: =I10+($L10-$B10)/($L$2-$B$2) -> 3823333.5 | K10: =J10+($L10-$B10)/($L$2-$B$2) -> 3823333.5 | L10: =KRW!D10 -> 3823333.5 | M10: {=TREND($B10:$L10,$B$2:$L$2,M$2)} -> 3823333.5 | N10: {=TREND($B10:$L10,$B$2:$L$2,N$2)} -> 3823333.5 | O10: {=TREND($B10:$L10,$B$2:$L$2,O$2)} -> 3823333.5 | P10: {=TREND($B10:$L10,$B$2:$L$2,P$2)} -> 3823333.5 | Q10: {=TREND($B10:$L10,$B$2:$L$2,Q$2)} -> 3823333.5 | R10: {=TREND($B10:$L10,$B$2:$L$2,R$2)} -> 3823333.5 | S10: {=TREND($B10:$L10,$B$2:$L$2,S$2)} -> 3823333.5 | T10: {=TREND($B10:$L10,$B$2:$L$2,T$2)} -> 3823333.5 | ... AF10: {=TREND($B10:$L10,$B$2:$L$2,AF$2)} -> 3823333.5
A11: geothermal | B11: =KRW!B11 -> 8825950.2 | C11: =B11+($L11-$B11)/($L$2-$B$2) -> 8825950.2 | D11: =C11+($L11-$B11)/($L$2-$B$2) -> 8825950.2 | E11: =D11+($L11-$B11)/($L$2-$B$2) -> 8825950.2 | F11: =E11+($L11-$B11)/($L$2-$B$2) -> 8825950.2 | G11: =F11+($L11-$B11)/($L$2-$B$2) -> 8825950.2 | H11: =G11+($L11-$B11)/($L$2-$B$2) -> 8825950.2 | I11: =H11+($L11-$B11)/($L$2-$B$2) -> 8825950.2 | J11: =I11+($L11-$B11)/($L$2-$B$2) -> 8825950.2 | K11: =J11+($L11-$B11)/($L$2-$B$2) -> 8825950.2 | L11: =KRW!D11 -> 8825950.2 | M11: {=TREND($B11:$L11,$B$2:$L$2,M$2)} -> 8825950.2 | N11: {=TREND($B11:$L11,$B$2:$L$2,N$2)} -> 8825950.2 | O11: {=TREND($B11:$L11,$B$2:$L$2,O$2)} -> 8825950.2 | P11: {=TREND($B11:$L11,$B$2:$L$2,P$2)} -> 8825950.2 | Q11: {=TREND($B11:$L11,$B$2:$L$2,Q$2)} -> 8825950.2 | R11: {=TREND($B11:$L11,$B$2:$L$2,R$2)} -> 8825950.2 | S11: {=TREND($B11:$L11,$B$2:$L$2,S$2)} -> 8825950.2 | T11: {=TREND($B11:$L11,$B$2:$L$2,T$2)} -> 8825950.2 | ... AF11: {=TREND($B11:$L11,$B$2:$L$2,AF$2)} -> 8825950.2
A12: petroleum | B12: =KRW!B12 -> 1895634 | C12: =B12+($L12-$B12)/($L$2-$B$2) -> 1895634 | D12: =C12+($L12-$B12)/($L$2-$B$2) -> 1895634 | E12: =D12+($L12-$B12)/($L$2-$B$2) -> 1895634 | F12: =E12+($L12-$B12)/($L$2-$B$2) -> 1895634 | G12: =F12+($L12-$B12)/($L$2-$B$2) -> 1895634 | H12: =G12+($L12-$B12)/($L$2-$B$2) -> 1895634 | I12: =H12+($L12-$B12)/($L$2-$B$2) -> 1895634 | J12: =I12+($L12-$B12)/($L$2-$B$2) -> 1895634 | K12: =J12+($L12-$B12)/($L$2-$B$2) -> 1895634 | L12: =KRW!D12 -> 1895634 | M12: {=TREND($B12:$L12,$B$2:$L$2,M$2)} -> 1895634 | N12: {=TREND($B12:$L12,$B$2:$L$2,N$2)} -> 1895634 | O12: {=TREND($B12:$L12,$B$2:$L$2,O$2)} -> 1895634 | P12: {=TREND($B12:$L12,$B$2:$L$2,P$2)} -> 1895634 | Q12: {=TREND($B12:$L12,$B$2:$L$2,Q$2)} -> 1895634 | R12: {=TREND($B12:$L12,$B$2:$L$2,R$2)} -> 1895634 | S12: {=TREND($B12:$L12,$B$2:$L$2,S$2)} -> 1895634 | T12: {=TREND($B12:$L12,$B$2:$L$2,T$2)} -> 1895634 | ... AF12: {=TREND($B12:$L12,$B$2:$L$2,AF$2)} -> 1895634
A13: natural gas peaker | B13: =KRW!B13 -> 657915.3 | C13: =B13+($L13-$B13)/($L$2-$B$2) -> 663865.3 | D13: =C13+($L13-$B13)/($L$2-$B$2) -> 669815.3 | E13: =D13+($L13-$B13)/($L$2-$B$2) -> 675765.3 | F13: =E13+($L13-$B13)/($L$2-$B$2) -> 681715.3 | G13: =F13+($L13-$B13)/($L$2-$B$2) -> 687665.3 | H13: =G13+($L13-$B13)/($L$2-$B$2) -> 693615.3 | I13: =H13+($L13-$B13)/($L$2-$B$2) -> 699565.3 | J13: =I13+($L13-$B13)/($L$2-$B$2) -> 705515.3 | K13: =J13+($L13-$B13)/($L$2-$B$2) -> 711465.3 | L13: =KRW!D13 -> 717415.3 | M13: {=TREND($B13:$L13,$B$2:$L$2,M$2)} -> 723365.3 | N13: {=TREND($B13:$L13,$B$2:$L$2,N$2)} -> 729315.3 | O13: {=TREND($B13:$L13,$B$2:$L$2,O$2)} -> 735265.3 | P13: {=TREND($B13:$L13,$B$2:$L$2,P$2)} -> 741215.3 | Q13: {=TREND($B13:$L13,$B$2:$L$2,Q$2)} -> 747165.3 | R13: {=TREND($B13:$L13,$B$2:$L$2,R$2)} -> 753115.3 | S13: {=TREND($B13:$L13,$B$2:$L$2,S$2)} -> 759065.3 | T13: {=TREND($B13:$L13,$B$2:$L$2,T$2)} -> 765015.3 | ... AF13: {=TREND($B13:$L13,$B$2:$L$2,AF$2)} -> 836415.3
A14: lignite | B14: =KRW!B14 -> 1438461 | C14: =B14+($L14-$B14)/($L$2-$B$2) -> 1490860 | D14: =C14+($L14-$B14)/($L$2-$B$2) -> 1543259 | E14: =D14+($L14-$B14)/($L$2-$B$2) -> 1595658 | F14: =E14+($L14-$B14)/($L$2-$B$2) -> 1648057 | G14: =F14+($L14-$B14)/($L$2-$B$2) -> 1700456 | H14: =G14+($L14-$B14)/($L$2-$B$2) -> 1752855 | I14: =H14+($L14-$B14)/($L$2-$B$2) -> 1805254 | J14: =I14+($L14-$B14)/($L$2-$B$2) -> 1857653 | K14: =J14+($L14-$B14)/($L$2-$B$2) -> 1910052 | L14: =KRW!D14 -> 1962451 | M14: {=TREND($B14:$L14,$B$2:$L$2,M$2)} -> 2014850 | N14: {=TREND($B14:$L14,$B$2:$L$2,N$2)} -> 2067249 | O14: {=TREND($B14:$L14,$B$2:$L$2,O$2)} -> 2119648 | P14: {=TREND($B14:$L14,$B$2:$L$2,P$2)} -> 2172047 | Q14: {=TREND($B14:$L14,$B$2:$L$2,Q$2)} -> 2224446 | R14: {=TREND($B14:$L14,$B$2:$L$2,R$2)} -> 2276845 | S14: {=TREND($B14:$L14,$B$2:$L$2,S$2)} -> 2329244 | T14: {=TREND($B14:$L14,$B$2:$L$2,T$2)} -> 2381643 | ... AF14: {=TREND($B14:$L14,$B$2:$L$2,AF$2)} -> 3010431
A15: offshore wind | B15: =KRW!B15 -> 6005300 | C15: =B15+($L15-$B15)/($L$2-$B$2) -> 5849162.2 | D15: =C15+($L15-$B15)/($L$2-$B$2) -> 5693024.4 | E15: =D15+($L15-$B15)/($L$2-$B$2) -> 5536886.6 | F15: =E15+($L15-$B15)/($L$2-$B$2) -> 5380748.8 | G15: =F15+($L15-$B15)/($L$2-$B$2) -> 5224611 | H15: =G15+($L15-$B15)/($L$2-$B$2) -> 5068473.2 | I15: =H15+($L15-$B15)/($L$2-$B$2) -> 4912335.4 | J15: =I15+($L15-$B15)/($L$2-$B$2) -> 4756197.6 | K15: =J15+($L15-$B15)/($L$2-$B$2) -> 4600059.8 | L15: =KRW!D15 -> 4443922 | M15: {=TREND($B15:$L15,$B$2:$L$2,M$2)} -> 4287784.2 | N15: {=TREND($B15:$L15,$B$2:$L$2,N$2)} -> 4131646.4 | O15: {=TREND($B15:$L15,$B$2:$L$2,O$2)} -> 3975508.6 | P15: {=TREND($B15:$L15,$B$2:$L$2,P$2)} -> 3819370.8 | Q15: {=TREND($B15:$L15,$B$2:$L$2,Q$2)} -> 3663233 | R15: {=TREND($B15:$L15,$B$2:$L$2,R$2)} -> 3507095.2 | S15: {=TREND($B15:$L15,$B$2:$L$2,S$2)} -> 3350957.4 | T15: {=TREND($B15:$L15,$B$2:$L$2,T$2)} -> 3194819.6 | ... AF15: {=TREND($B15:$L15,$B$2:$L$2,AF$2)} -> 1321166
A16: crude oil | B16: =KRW!B16 -> 1895634 | C16: =B16+($L16-$B16)/($L$2-$B$2) -> 1895634 | D16: =C16+($L16-$B16)/($L$2-$B$2) -> 1895634 | E16: =D16+($L16-$B16)/($L$2-$B$2) -> 1895634 | F16: =E16+($L16-$B16)/($L$2-$B$2) -> 1895634 | G16: =F16+($L16-$B16)/($L$2-$B$2) -> 1895634 | H16: =G16+($L16-$B16)/($L$2-$B$2) -> 1895634 | I16: =H16+($L16-$B16)/($L$2-$B$2) -> 1895634 | J16: =I16+($L16-$B16)/($L$2-$B$2) -> 1895634 | K16: =J16+($L16-$B16)/($L$2-$B$2) -> 1895634 | L16: =KRW!D16 -> 1895634 | M16: {=TREND($B16:$L16,$B$2:$L$2,M$2)} -> 1895634 | N16: {=TREND($B16:$L16,$B$2:$L$2,N$2)} -> 1895634 | O16: {=TREND($B16:$L16,$B$2:$L$2,O$2)} -> 1895634 | P16: {=TREND($B16:$L16,$B$2:$L$2,P$2)} -> 1895634 | Q16: {=TREND($B16:$L16,$B$2:$L$2,Q$2)} -> 1895634 | R16: {=TREND($B16:$L16,$B$2:$L$2,R$2)} -> 1895634 | S16: {=TREND($B16:$L16,$B$2:$L$2,S$2)} -> 1895634 | T16: {=TREND($B16:$L16,$B$2:$L$2,T$2)} -> 1895634 | ... AF16: {=TREND($B16:$L16,$B$2:$L$2,AF$2)} -> 1895634
A17: heavy or residual fuel oil | B17: =KRW!B17 -> 1895634 | C17: =B17+($L17-$B17)/($L$2-$B$2) -> 1895634 | D17: =C17+($L17-$B17)/($L$2-$B$2) -> 1895634 | E17: =D17+($L17-$B17)/($L$2-$B$2) -> 1895634 | F17: =E17+($L17-$B17)/($L$2-$B$2) -> 1895634 | G17: =F17+($L17-$B17)/($L$2-$B$2) -> 1895634 | H17: =G17+($L17-$B17)/($L$2-$B$2) -> 1895634 | I17: =H17+($L17-$B17)/($L$2-$B$2) -> 1895634 | J17: =I17+($L17-$B17)/($L$2-$B$2) -> 1895634 | K17: =J17+($L17-$B17)/($L$2-$B$2) -> 1895634 | L17: =KRW!D17 -> 1895634 | M17: {=TREND($B17:$L17,$B$2:$L$2,M$2)} -> 1895634 | N17: {=TREND($B17:$L17,$B$2:$L$2,N$2)} -> 1895634 | O17: {=TREND($B17:$L17,$B$2:$L$2,O$2)} -> 1895634 | P17: {=TREND($B17:$L17,$B$2:$L$2,P$2)} -> 1895634 | Q17: {=TREND($B17:$L17,$B$2:$L$2,Q$2)} -> 1895634 | R17: {=TREND($B17:$L17,$B$2:$L$2,R$2)} -> 1895634 | S17: {=TREND($B17:$L17,$B$2:$L$2,S$2)} -> 1895634 | T17: {=TREND($B17:$L17,$B$2:$L$2,T$2)} -> 1895634 | ... AF17: {=TREND($B17:$L17,$B$2:$L$2,AF$2)} -> 1895634
A18: municipal solid waste | B18: =KRW!B18 -> 4800000 | C18: =B18+($L18-$B18)/($L$2-$B$2) -> 4800000 | D18: =C18+($L18-$B18)/($L$2-$B$2) -> 4800000 | E18: =D18+($L18-$B18)/($L$2-$B$2) -> 4800000 | F18: =E18+($L18-$B18)/($L$2-$B$2) -> 4800000 | G18: =F18+($L18-$B18)/($L$2-$B$2) -> 4800000 | H18: =G18+($L18-$B18)/($L$2-$B$2) -> 4800000 | I18: =H18+($L18-$B18)/($L$2-$B$2) -> 4800000 | J18: =I18+($L18-$B18)/($L$2-$B$2) -> 4800000 | K18: =J18+($L18-$B18)/($L$2-$B$2) -> 4800000 | L18: =KRW!D18 -> 4800000 | M18: {=TREND($B18:$L18,$B$2:$L$2,M$2)} -> 4800000 | N18: {=TREND($B18:$L18,$B$2:$L$2,N$2)} -> 4800000 | O18: {=TREND($B18:$L18,$B$2:$L$2,O$2)} -> 4800000 | P18: {=TREND($B18:$L18,$B$2:$L$2,P$2)} -> 4800000 | Q18: {=TREND($B18:$L18,$B$2:$L$2,Q$2)} -> 4800000 | R18: {=TREND($B18:$L18,$B$2:$L$2,R$2)} -> 4800000 | S18: {=TREND($B18:$L18,$B$2:$L$2,S$2)} -> 4800000 | T18: {=TREND($B18:$L18,$B$2:$L$2,T$2)} -> 4800000 | ... AF18: {=TREND($B18:$L18,$B$2:$L$2,AF$2)} -> 4800000
A20: Fixed O&M (KRW/kW-yr) | B20: 2020 | C20: 2021 | D20: 2022 | E20: 2023 | F20: 2024 | G20: 2025 | H20: 2026 | I20: 2027 | J20: 2028 | K20: 2029 | L20: 2030 | M20: 2031 | N20: 2032 | O20: 2033 | P20: 2034 | Q20: 2035 | R20: 2036 | S20: 2037 | T20: 2038 | U20: 2039 | V20: 2040 | W20: 2041 | X20: 2042 | Y20: 2043 | Z20: 2044 | AA20: 2045 | AB20: 2046 | AC20: 2047 | AD20: 2048 | AE20: 2049 | AF20: 2050
A21: hard coal | B21: =KRW!B21 -> 66670.32 | C21: =B21+($L21-$B21)/($L$2-$B$2) -> 66670.32 | D21: =C21+($L21-$B21)/($L$2-$B$2) -> 66670.32 | E21: =D21+($L21-$B21)/($L$2-$B$2) -> 66670.32 | F21: =E21+($L21-$B21)/($L$2-$B$2) -> 66670.32 | G21: =F21+($L21-$B21)/($L$2-$B$2) -> 66670.32 | H21: =G21+($L21-$B21)/($L$2-$B$2) -> 66670.32 | I21: =H21+($L21-$B21)/($L$2-$B$2) -> 66670.32 | J21: =I21+($L21-$B21)/($L$2-$B$2) -> 66670.32 | K21: =J21+($L21-$B21)/($L$2-$B$2) -> 66670.32 | L21: =KRW!D21 -> 66670.32 | M21: {=TREND($B21:$L21,$B$2:$L$2,M$2)} -> 66670.32 | N21: {=TREND($B21:$L21,$B$2:$L$2,N$2)} -> 66670.32 | O21: {=TREND($B21:$L21,$B$2:$L$2,O$2)} -> 66670.32 | P21: {=TREND($B21:$L21,$B$2:$L$2,P$2)} -> 66670.32 | Q21: {=TREND($B21:$L21,$B$2:$L$2,Q$2)} -> 66670.32 | R21: {=TREND($B21:$L21,$B$2:$L$2,R$2)} -> 66670.32 | S21: {=TREND($B21:$L21,$B$2:$L$2,S$2)} -> 66670.32 | T21: {=TREND($B21:$L21,$B$2:$L$2,T$2)} -> 66670.32 | ... AF21: {=TREND($B21:$L21,$B$2:$L$2,AF$2)} -> 66670.32
A22: natural gas nonpeaker | B22: =KRW!B22 -> 43835.64 | C22: =B22+($L22-$B22)/($L$2-$B$2) -> 43835.64 | D22: =C22+($L22-$B22)/($L$2-$B$2) -> 43835.64 | E22: =D22+($L22-$B22)/($L$2-$B$2) -> 43835.64 | F22: =E22+($L22-$B22)/($L$2-$B$2) -> 43835.64 | G22: =F22+($L22-$B22)/($L$2-$B$2) -> 43835.64 | H22: =G22+($L22-$B22)/($L$2-$B$2) -> 43835.64 | I22: =H22+($L22-$B22)/($L$2-$B$2) -> 43835.64 | J22: =I22+($L22-$B22)/($L$2-$B$2) -> 43835.64 | K22: =J22+($L22-$B22)/($L$2-$B$2) -> 43835.64 | L22: =KRW!D22 -> 43835.64 | M22: {=TREND($B22:$L22,$B$2:$L$2,M$2)} -> 43835.64 | N22: {=TREND($B22:$L22,$B$2:$L$2,N$2)} -> 43835.64 | O22: {=TREND($B22:$L22,$B$2:$L$2,O$2)} -> 43835.64 | P22: {=TREND($B22:$L22,$B$2:$L$2,P$2)} -> 43835.64 | Q22: {=TREND($B22:$L22,$B$2:$L$2,Q$2)} -> 43835.64 | R22: {=TREND($B22:$L22,$B$2:$L$2,R$2)} -> 43835.64 | S22: {=TREND($B22:$L22,$B$2:$L$2,S$2)} -> 43835.64 | T22: {=TREND($B22:$L22,$B$2:$L$2,T$2)} -> 43835.64 | ... AF22: {=TREND($B22:$L22,$B$2:$L$2,AF$2)} -> 43835.64
A23: nuclear | B23: =KRW!B23 -> 166937.76 | C23: =B23+($L23-$B23)/($L$2-$B$2) -> 166937.76 | D23: =C23+($L23-$B23)/($L$2-$B$2) -> 166937.76 | E23: =D23+($L23-$B23)/($L$2-$B$2) -> 166937.76 | F23: =E23+($L23-$B23)/($L$2-$B$2) -> 166937.76 | G23: =F23+($L23-$B23)/($L$2-$B$2) -> 166937.76 | H23: =G23+($L23-$B23)/($L$2-$B$2) -> 166937.76 | I23: =H23+($L23-$B23)/($L$2-$B$2) -> 166937.76 | J23: =I23+($L23-$B23)/($L$2-$B$2) -> 166937.76 | K23: =J23+($L23-$B23)/($L$2-$B$2) -> 166937.76 | L23: =KRW!D23 -> 166937.76 | M23: {=TREND($B23:$L23,$B$2:$L$2,M$2)} -> 166937.76 | N23: {=TREND($B23:$L23,$B$2:$L$2,N$2)} -> 166937.76 | O23: {=TREND($B23:$L23,$B$2:$L$2,O$2)} -> 166937.76 | P23: {=TREND($B23:$L23,$B$2:$L$2,P$2)} -> 166937.76 | Q23: {=TREND($B23:$L23,$B$2:$L$2,Q$2)} -> 166937.76 | R23: {=TREND($B23:$L23,$B$2:$L$2,R$2)} -> 166937.76 | S23: {=TREND($B23:$L23,$B$2:$L$2,S$2)} -> 166937.76 | T23: {=TREND($B23:$L23,$B$2:$L$2,T$2)} -> 166937.76 | ... AF23: {=TREND($B23:$L23,$B$2:$L$2,AF$2)} -> 166937.76
A24: hydro | B24: =KRW!B24 -> 24217.5 | C24: =B24+($L24-$B24)/($L$2-$B$2) -> 24217.5 | D24: =C24+($L24-$B24)/($L$2-$B$2) -> 24217.5 | E24: =D24+($L24-$B24)/($L$2-$B$2) -> 24217.5 | F24: =E24+($L24-$B24)/($L$2-$B$2) -> 24217.5 | G24: =F24+($L24-$B24)/($L$2-$B$2) -> 24217.5 | H24: =G24+($L24-$B24)/($L$2-$B$2) -> 24217.5 | I24: =H24+($L24-$B24)/($L$2-$B$2) -> 24217.5 | J24: =I24+($L24-$B24)/($L$2-$B$2) -> 24217.5 | K24: =J24+($L24-$B24)/($L$2-$B$2) -> 24217.5 | L24: =KRW!D24 -> 24217.5 | M24: {=TREND($B24:$L24,$B$2:$L$2,M$2)} -> 24217.5 | N24: {=TREND($B24:$L24,$B$2:$L$2,N$2)} -> 24217.5 | O24: {=TREND($B24:$L24,$B$2:$L$2,O$2)} -> 24217.5 | P24: {=TREND($B24:$L24,$B$2:$L$2,P$2)} -> 24217.5 | Q24: {=TREND($B24:$L24,$B$2:$L$2,Q$2)} -> 24217.5 | R24: {=TREND($B24:$L24,$B$2:$L$2,R$2)} -> 24217.5 | S24: {=TREND($B24:$L24,$B$2:$L$2,S$2)} -> 24217.5 | T24: {=TREND($B24:$L24,$B$2:$L$2,T$2)} -> 24217.5 | ... AF24: {=TREND($B24:$L24,$B$2:$L$2,AF$2)} -> 24217.5
A25: onshore wind | B25: =KRW!B25 -> 51027 | C25: =B25+($G25-$B25)/($G$2-$B$2) -> 51027 | D25: =C25+($G25-$B25)/($G$2-$B$2) -> 51027 | E25: =D25+($G25-$B25)/($G$2-$B$2) -> 51027 | F25: =E25+($G25-$B25)/($G$2-$B$2) -> 51027 | G25: =KRW!C25 -> 51027 | H25: =G25+($L25-$G25)/($L$2-$G$2) -> 51027 | I25: =H25+($L25-$G25)/($L$2-$G$2) -> 51027 | J25: =I25+($L25-$G25)/($L$2-$G$2) -> 51027 | K25: =J25+($L25-$G25)/($L$2-$G$2) -> 51027 | L25: =KRW!D25 -> 51027 | M25: {=TREND($B25:$L25,$B$2:$L$2,M$2)} -> 51027 | N25: {=TREND($B25:$L25,$B$2:$L$2,N$2)} -> 51027 | O25: {=TREND($B25:$L25,$B$2:$L$2,O$2)} -> 51027 | P25: {=TREND($B25:$L25,$B$2:$L$2,P$2)} -> 51027 | Q25: {=TREND($B25:$L25,$B$2:$L$2,Q$2)} -> 51027 | R25: {=TREND($B25:$L25,$B$2:$L$2,R$2)} -> 51027 | S25: {=TREND($B25:$L25,$B$2:$L$2,S$2)} -> 51027 | T25: {=TREND($B25:$L25,$B$2:$L$2,T$2)} -> 51027 | ... AF25: {=TREND($B25:$L25,$B$2:$L$2,AF$2)} -> 51027
A26: solar PV | B26: =KRW!B26 -> 24871 | C26: =B26+($G26-$B26)/($G$2-$B$2) -> 24871 | D26: =C26+($G26-$B26)/($G$2-$B$2) -> 24871 | E26: =D26+($G26-$B26)/($G$2-$B$2) -> 24871 | F26: =E26+($G26-$B26)/($G$2-$B$2) -> 24871 | G26: =KRW!C26 -> 24871 | H26: =G26+($L26-$G26)/($L$2-$G$2) -> 24871 | I26: =H26+($L26-$G26)/($L$2-$G$2) -> 24871 | J26: =I26+($L26-$G26)/($L$2-$G$2) -> 24871 | K26: =J26+($L26-$G26)/($L$2-$G$2) -> 24871 | L26: =KRW!D26 -> 24871 | M26: {=TREND($B26:$L26,$B$2:$L$2,M$2)} -> 24871 | N26: {=TREND($B26:$L26,$B$2:$L$2,N$2)} -> 24871 | O26: {=TREND($B26:$L26,$B$2:$L$2,O$2)} -> 24871 | P26: {=TREND($B26:$L26,$B$2:$L$2,P$2)} -> 24871 | Q26: {=TREND($B26:$L26,$B$2:$L$2,Q$2)} -> 24871 | R26: {=TREND($B26:$L26,$B$2:$L$2,R$2)} -> 24871 | S26: {=TREND($B26:$L26,$B$2:$L$2,S$2)} -> 24871 | T26: {=TREND($B26:$L26,$B$2:$L$2,T$2)} -> 24871 | ... AF26: {=TREND($B26:$L26,$B$2:$L$2,AF$2)} -> 24871
A27: solar thermal | B27: =KRW!B27 -> 0 | C27: =B27+($L27-$B27)/($L$2-$B$2) -> 0 | D27: =C27+($L27-$B27)/($L$2-$B$2) -> 0 | E27: =D27+($L27-$B27)/($L$2-$B$2) -> 0 | F27: =E27+($L27-$B27)/($L$2-$B$2) -> 0 | G27: =F27+($L27-$B27)/($L$2-$B$2) -> 0 | H27: =G27+($L27-$B27)/($L$2-$B$2) -> 0 | I27: =H27+($L27-$B27)/($L$2-$B$2) -> 0 | J27: =I27+($L27-$B27)/($L$2-$B$2) -> 0 | K27: =J27+($L27-$B27)/($L$2-$B$2) -> 0 | L27: =KRW!D27 -> 0 | M27: {=TREND($B27:$L27,$B$2:$L$2,M$2)} -> 0 | N27: {=TREND($B27:$L27,$B$2:$L$2,N$2)} -> 0 | O27: {=TREND($B27:$L27,$B$2:$L$2,O$2)} -> 0 | P27: {=TREND($B27:$L27,$B$2:$L$2,P$2)} -> 0 | Q27: {=TREND($B27:$L27,$B$2:$L$2,Q$2)} -> 0 | R27: {=TREND($B27:$L27,$B$2:$L$2,R$2)} -> 0 | S27: {=TREND($B27:$L27,$B$2:$L$2,S$2)} -> 0 | T27: {=TREND($B27:$L27,$B$2:$L$2,T$2)} -> 0 | ... AF27: {=TREND($B27:$L27,$B$2:$L$2,AF$2)} -> 0
A28: biomass | B28: =KRW!B28 -> 95583.338 | C28: =B28+($L28-$B28)/($L$2-$B$2) -> 95583.338 | D28: =C28+($L28-$B28)/($L$2-$B$2) -> 95583.338 | E28: =D28+($L28-$B28)/($L$2-$B$2) -> 95583.338 | F28: =E28+($L28-$B28)/($L$2-$B$2) -> 95583.338 | G28: =F28+($L28-$B28)/($L$2-$B$2) -> 95583.338 | H28: =G28+($L28-$B28)/($L$2-$B$2) -> 95583.338 | I28: =H28+($L28-$B28)/($L$2-$B$2) -> 95583.338 | J28: =I28+($L28-$B28)/($L$2-$B$2) -> 95583.338 | K28: =J28+($L28-$B28)/($L$2-$B$2) -> 95583.338 | L28: =KRW!D28 -> 95583.338 | M28: {=TREND($B28:$L28,$B$2:$L$2,M$2)} -> 95583.338 | N28: {=TREND($B28:$L28,$B$2:$L$2,N$2)} -> 95583.338 | O28: {=TREND($B28:$L28,$B$2:$L$2,O$2)} -> 95583.338 | P28: {=TREND($B28:$L28,$B$2:$L$2,P$2)} -> 95583.338 | Q28: {=TREND($B28:$L28,$B$2:$L$2,Q$2)} -> 95583.338 | R28: {=TREND($B28:$L28,$B$2:$L$2,R$2)} -> 95583.338 | S28: {=TREND($B28:$L28,$B$2:$L$2,S$2)} -> 95583.338 | T28: {=TREND($B28:$L28,$B$2:$L$2,T$2)} -> 95583.338 | ... AF28: {=TREND($B28:$L28,$B$2:$L$2,AF$2)} -> 95583.338
A29: geothermal | B29: =KRW!B29 -> 220648.75 | C29: =B29+($L29-$B29)/($L$2-$B$2) -> 220648.75 | D29: =C29+($L29-$B29)/($L$2-$B$2) -> 220648.75 | E29: =D29+($L29-$B29)/($L$2-$B$2) -> 220648.75 | F29: =E29+($L29-$B29)/($L$2-$B$2) -> 220648.75 | G29: =F29+($L29-$B29)/($L$2-$B$2) -> 220648.75 | H29: =G29+($L29-$B29)/($L$2-$B$2) -> 220648.75 | I29: =H29+($L29-$B29)/($L$2-$B$2) -> 220648.75 | J29: =I29+($L29-$B29)/($L$2-$B$2) -> 220648.75 | K29: =J29+($L29-$B29)/($L$2-$B$2) -> 220648.75 | L29: =KRW!D29 -> 220648.75 | M29: {=TREND($B29:$L29,$B$2:$L$2,M$2)} -> 220648.75 | N29: {=TREND($B29:$L29,$B$2:$L$2,N$2)} -> 220648.75 | O29: {=TREND($B29:$L29,$B$2:$L$2,O$2)} -> 220648.75 | P29: {=TREND($B29:$L29,$B$2:$L$2,P$2)} -> 220648.75 | Q29: {=TREND($B29:$L29,$B$2:$L$2,Q$2)} -> 220648.75 | R29: {=TREND($B29:$L29,$B$2:$L$2,R$2)} -> 220648.75 | S29: {=TREND($B29:$L29,$B$2:$L$2,S$2)} -> 220648.75 | T29: {=TREND($B29:$L29,$B$2:$L$2,T$2)} -> 220648.75 | ... AF29: {=TREND($B29:$L29,$B$2:$L$2,AF$2)} -> 220648.75
A30: petroleum | B30: =KRW!B30 -> 47390.85 | C30: =B30+($L30-$B30)/($L$2-$B$2) -> 47390.85 | D30: =C30+($L30-$B30)/($L$2-$B$2) -> 47390.85 | E30: =D30+($L30-$B30)/($L$2-$B$2) -> 47390.85 | F30: =E30+($L30-$B30)/($L$2-$B$2) -> 47390.85 | G30: =F30+($L30-$B30)/($L$2-$B$2) -> 47390.85 | H30: =G30+($L30-$B30)/($L$2-$B$2) -> 47390.85 | I30: =H30+($L30-$B30)/($L$2-$B$2) -> 47390.85 | J30: =I30+($L30-$B30)/($L$2-$B$2) -> 47390.85 | K30: =J30+($L30-$B30)/($L$2-$B$2) -> 47390.85 | L30: =KRW!D30 -> 47390.85 | M30: {=TREND($B30:$L30,$B$2:$L$2,M$2)} -> 47390.85 | N30: {=TREND($B30:$L30,$B$2:$L$2,N$2)} -> 47390.85 | O30: {=TREND($B30:$L30,$B$2:$L$2,O$2)} -> 47390.85 | P30: {=TREND($B30:$L30,$B$2:$L$2,P$2)} -> 47390.85 | Q30: {=TREND($B30:$L30,$B$2:$L$2,Q$2)} -> 47390.85 | R30: {=TREND($B30:$L30,$B$2:$L$2,R$2)} -> 47390.85 | S30: {=TREND($B30:$L30,$B$2:$L$2,S$2)} -> 47390.85 | T30: {=TREND($B30:$L30,$B$2:$L$2,T$2)} -> 47390.85 | ... AF30: {=TREND($B30:$L30,$B$2:$L$2,AF$2)} -> 47390.85
A31: natural gas peaker | B31: =KRW!B31 -> 16447.882 | C31: =B31+($L31-$B31)/($L$2-$B$2) -> 16447.882 | D31: =C31+($L31-$B31)/($L$2-$B$2) -> 16447.882 | E31: =D31+($L31-$B31)/($L$2-$B$2) -> 16447.882 | F31: =E31+($L31-$B31)/($L$2-$B$2) -> 16447.882 | G31: =F31+($L31-$B31)/($L$2-$B$2) -> 16447.882 | H31: =G31+($L31-$B31)/($L$2-$B$2) -> 16447.882 | I31: =H31+($L31-$B31)/($L$2-$B$2) -> 16447.882 | J31: =I31+($L31-$B31)/($L$2-$B$2) -> 16447.882 | K31: =J31+($L31-$B31)/($L$2-$B$2) -> 16447.882 | L31: =KRW!D31 -> 16447.882 | M31: {=TREND($B31:$L31,$B$2:$L$2,M$2)} -> 16447.883 | N31: {=TREND($B31:$L31,$B$2:$L$2,N$2)} -> 16447.883 | O31: {=TREND($B31:$L31,$B$2:$L$2,O$2)} -> 16447.883 | P31: {=TREND($B31:$L31,$B$2:$L$2,P$2)} -> 16447.883 | Q31: {=TREND($B31:$L31,$B$2:$L$2,Q$2)} -> 16447.883 | R31: {=TREND($B31:$L31,$B$2:$L$2,R$2)} -> 16447.883 | S31: {=TREND($B31:$L31,$B$2:$L$2,S$2)} -> 16447.883 | T31: {=TREND($B31:$L31,$B$2:$L$2,T$2)} -> 16447.883 | ... AF31: {=TREND($B31:$L31,$B$2:$L$2,AF$2)} -> 16447.883
A32: lignite | B32: =KRW!B32 -> 66670.32 | C32: =B32+($L32-$B32)/($L$2-$B$2) -> 66670.32 | D32: =C32+($L32-$B32)/($L$2-$B$2) -> 66670.32 | E32: =D32+($L32-$B32)/($L$2-$B$2) -> 66670.32 | F32: =E32+($L32-$B32)/($L$2-$B$2) -> 66670.32 | G32: =F32+($L32-$B32)/($L$2-$B$2) -> 66670.32 | H32: =G32+($L32-$B32)/($L$2-$B$2) -> 66670.32 | I32: =H32+($L32-$B32)/($L$2-$B$2) -> 66670.32 | J32: =I32+($L32-$B32)/($L$2-$B$2) -> 66670.32 | K32: =J32+($L32-$B32)/($L$2-$B$2) -> 66670.32 | L32: =KRW!D32 -> 66670.32 | M32: {=TREND($B32:$L32,$B$2:$L$2,M$2)} -> 66670.32 | N32: {=TREND($B32:$L32,$B$2:$L$2,N$2)} -> 66670.32 | O32: {=TREND($B32:$L32,$B$2:$L$2,O$2)} -> 66670.32 | P32: {=TREND($B32:$L32,$B$2:$L$2,P$2)} -> 66670.32 | Q32: {=TREND($B32:$L32,$B$2:$L$2,Q$2)} -> 66670.32 | R32: {=TREND($B32:$L32,$B$2:$L$2,R$2)} -> 66670.32 | S32: {=TREND($B32:$L32,$B$2:$L$2,S$2)} -> 66670.32 | T32: {=TREND($B32:$L32,$B$2:$L$2,T$2)} -> 66670.32 | ... AF32: {=TREND($B32:$L32,$B$2:$L$2,AF$2)} -> 66670.32
A33: offshore wind | B33: =KRW!B33 -> 122000 | C33: =B33+($L33-$B33)/($L$2-$B$2) -> 122000 | D33: =C33+($L33-$B33)/($L$2-$B$2) -> 122000 | E33: =D33+($L33-$B33)/($L$2-$B$2) -> 122000 | F33: =E33+($L33-$B33)/($L$2-$B$2) -> 122000 | G33: =F33+($L33-$B33)/($L$2-$B$2) -> 122000 | H33: =G33+($L33-$B33)/($L$2-$B$2) -> 122000 | I33: =H33+($L33-$B33)/($L$2-$B$2) -> 122000 | J33: =I33+($L33-$B33)/($L$2-$B$2) -> 122000 | K33: =J33+($L33-$B33)/($L$2-$B$2) -> 122000 | L33: =KRW!D33 -> 122000 | M33: {=TREND($B33:$L33,$B$2:$L$2,M$2)} -> 122000 | N33: {=TREND($B33:$L33,$B$2:$L$2,N$2)} -> 122000 | O33: {=TREND($B33:$L33,$B$2:$L$2,O$2)} -> 122000 | P33: {=TREND($B33:$L33,$B$2:$L$2,P$2)} -> 122000 | Q33: {=TREND($B33:$L33,$B$2:$L$2,Q$2)} -> 122000 | R33: {=TREND($B33:$L33,$B$2:$L$2,R$2)} -> 122000 | S33: {=TREND($B33:$L33,$B$2:$L$2,S$2)} -> 122000 | T33: {=TREND($B33:$L33,$B$2:$L$2,T$2)} -> 122000 | ... AF33: {=TREND($B33:$L33,$B$2:$L$2,AF$2)} -> 122000
A34: crude oil | B34: =KRW!B34 -> 47390.85 | C34: =B34+($L34-$B34)/($L$2-$B$2) -> 47390.85 | D34: =C34+($L34-$B34)/($L$2-$B$2) -> 47390.85 | E34: =D34+($L34-$B34)/($L$2-$B$2) -> 47390.85 | F34: =E34+($L34-$B34)/($L$2-$B$2) -> 47390.85 | G34: =F34+($L34-$B34)/($L$2-$B$2) -> 47390.85 | H34: =G34+($L34-$B34)/($L$2-$B$2) -> 47390.85 | I34: =H34+($L34-$B34)/($L$2-$B$2) -> 47390.85 | J34: =I34+($L34-$B34)/($L$2-$B$2) -> 47390.85 | K34: =J34+($L34-$B34)/($L$2-$B$2) -> 47390.85 | L34: =KRW!D34 -> 47390.85 | M34: {=TREND($B34:$L34,$B$2:$L$2,M$2)} -> 47390.85 | N34: {=TREND($B34:$L34,$B$2:$L$2,N$2)} -> 47390.85 | O34: {=TREND($B34:$L34,$B$2:$L$2,O$2)} -> 47390.85 | P34: {=TREND($B34:$L34,$B$2:$L$2,P$2)} -> 47390.85 | Q34: {=TREND($B34:$L34,$B$2:$L$2,Q$2)} -> 47390.85 | R34: {=TREND($B34:$L34,$B$2:$L$2,R$2)} -> 47390.85 | S34: {=TREND($B34:$L34,$B$2:$L$2,S$2)} -> 47390.85 | T34: {=TREND($B34:$L34,$B$2:$L$2,T$2)} -> 47390.85 | ... AF34: {=TREND($B34:$L34,$B$2:$L$2,AF$2)} -> 47390.85
A35: heavy or residual fuel oil | B35: =KRW!B35 -> 47390.85 | C35: =B35+($L35-$B35)/($L$2-$B$2) -> 47390.85 | D35: =C35+($L35-$B35)/($L$2-$B$2) -> 47390.85 | E35: =D35+($L35-$B35)/($L$2-$B$2) -> 47390.85 | F35: =E35+($L35-$B35)/($L$2-$B$2) -> 47390.85 | G35: =F35+($L35-$B35)/($L$2-$B$2) -> 47390.85 | H35: =G35+($L35-$B35)/($L$2-$B$2) -> 47390.85 | I35: =H35+($L35-$B35)/($L$2-$B$2) -> 47390.85 | J35: =I35+($L35-$B35)/($L$2-$B$2) -> 47390.85 | K35: =J35+($L35-$B35)/($L$2-$B$2) -> 47390.85 | L35: =KRW!D35 -> 47390.85 | M35: {=TREND($B35:$L35,$B$2:$L$2,M$2)} -> 47390.85 | N35: {=TREND($B35:$L35,$B$2:$L$2,N$2)} -> 47390.85 | O35: {=TREND($B35:$L35,$B$2:$L$2,O$2)} -> 47390.85 | P35: {=TREND($B35:$L35,$B$2:$L$2,P$2)} -> 47390.85 | Q35: {=TREND($B35:$L35,$B$2:$L$2,Q$2)} -> 47390.85 | R35: {=TREND($B35:$L35,$B$2:$L$2,R$2)} -> 47390.85 | S35: {=TREND($B35:$L35,$B$2:$L$2,S$2)} -> 47390.85 | T35: {=TREND($B35:$L35,$B$2:$L$2,T$2)} -> 47390.85 | ... AF35: {=TREND($B35:$L35,$B$2:$L$2,AF$2)} -> 47390.85
A36: municipal solid waste | B36: =KRW!B36 -> 120000 | C36: =B36+($L36-$B36)/($L$2-$B$2) -> 120000 | D36: =C36+($L36-$B36)/($L$2-$B$2) -> 120000 | E36: =D36+($L36-$B36)/($L$2-$B$2) -> 120000 | F36: =E36+($L36-$B36)/($L$2-$B$2) -> 120000 | G36: =F36+($L36-$B36)/($L$2-$B$2) -> 120000 | H36: =G36+($L36-$B36)/($L$2-$B$2) -> 120000 | I36: =H36+($L36-$B36)/($L$2-$B$2) -> 120000 | J36: =I36+($L36-$B36)/($L$2-$B$2) -> 120000 | K36: =J36+($L36-$B36)/($L$2-$B$2) -> 120000 | L36: =KRW!D36 -> 120000 | M36: {=TREND($B36:$L36,$B$2:$L$2,M$2)} -> 120000 | N36: {=TREND($B36:$L36,$B$2:$L$2,N$2)} -> 120000 | O36: {=TREND($B36:$L36,$B$2:$L$2,O$2)} -> 120000 | P36: {=TREND($B36:$L36,$B$2:$L$2,P$2)} -> 120000 | Q36: {=TREND($B36:$L36,$B$2:$L$2,Q$2)} -> 120000 | R36: {=TREND($B36:$L36,$B$2:$L$2,R$2)} -> 120000 | S36: {=TREND($B36:$L36,$B$2:$L$2,S$2)} -> 120000 | T36: {=TREND($B36:$L36,$B$2:$L$2,T$2)} -> 120000 | ... AF36: {=TREND($B36:$L36,$B$2:$L$2,AF$2)} -> 120000
A38: Variable O&M (KRW/MWh) | B38: 2020 | C38: 2021 | D38: 2022 | E38: 2023 | F38: 2024 | G38: 2025 | H38: 2026 | I38: 2027 | J38: 2028 | K38: 2029 | L38: 2030 | M38: 2031 | N38: 2032 | O38: 2033 | P38: 2034 | Q38: 2035 | R38: 2036 | S38: 2037 | T38: 2038 | U38: 2039 | V38: 2040 | W38: 2041 | X38: 2042 | Y38: 2043 | Z38: 2044 | AA38: 2045 | AB38: 2046 | AC38: 2047 | AD38: 2048 | AE38: 2049 | AF38: 2050
A39: hard coal | B39: =KRW!B39 -> 1180 | C39: =B39+($L39-$B39)/($L$2-$B$2) -> 1180 | D39: =C39+($L39-$B39)/($L$2-$B$2) -> 1180 | E39: =D39+($L39-$B39)/($L$2-$B$2) -> 1180 | F39: =E39+($L39-$B39)/($L$2-$B$2) -> 1180 | G39: =F39+($L39-$B39)/($L$2-$B$2) -> 1180 | H39: =G39+($L39-$B39)/($L$2-$B$2) -> 1180 | I39: =H39+($L39-$B39)/($L$2-$B$2) -> 1180 | J39: =I39+($L39-$B39)/($L$2-$B$2) -> 1180 | K39: =J39+($L39-$B39)/($L$2-$B$2) -> 1180 | L39: =KRW!D39 -> 1180 | M39: {=TREND($B39:$L39,$B$2:$L$2,M$2)} -> 1180 | N39: {=TREND($B39:$L39,$B$2:$L$2,N$2)} -> 1180 | O39: {=TREND($B39:$L39,$B$2:$L$2,O$2)} -> 1180 | P39: {=TREND($B39:$L39,$B$2:$L$2,P$2)} -> 1180 | Q39: {=TREND($B39:$L39,$B$2:$L$2,Q$2)} -> 1180 | R39: {=TREND($B39:$L39,$B$2:$L$2,R$2)} -> 1180 | S39: {=TREND($B39:$L39,$B$2:$L$2,S$2)} -> 1180 | T39: {=TREND($B39:$L39,$B$2:$L$2,T$2)} -> 1180 | ... AF39: {=TREND($B39:$L39,$B$2:$L$2,AF$2)} -> 1180
A40: natural gas nonpeaker | B40: =KRW!B40 -> 640 | C40: =B40+($L40-$B40)/($L$2-$B$2) -> 640 | D40: =C40+($L40-$B40)/($L$2-$B$2) -> 640 | E40: =D40+($L40-$B40)/($L$2-$B$2) -> 640 | F40: =E40+($L40-$B40)/($L$2-$B$2) -> 640 | G40: =F40+($L40-$B40)/($L$2-$B$2) -> 640 | H40: =G40+($L40-$B40)/($L$2-$B$2) -> 640 | I40: =H40+($L40-$B40)/($L$2-$B$2) -> 640 | J40: =I40+($L40-$B40)/($L$2-$B$2) -> 640 | K40: =J40+($L40-$B40)/($L$2-$B$2) -> 640 | L40: =KRW!D40 -> 640 | M40: {=TREND($B40:$L40,$B$2:$L$2,M$2)} -> 640 | N40: {=TREND($B40:$L40,$B$2:$L$2,N$2)} -> 640 | O40: {=TREND($B40:$L40,$B$2:$L$2,O$2)} -> 640 | P40: {=TREND($B40:$L40,$B$2:$L$2,P$2)} -> 640 | Q40: {=TREND($B40:$L40,$B$2:$L$2,Q$2)} -> 640 | R40: {=TREND($B40:$L40,$B$2:$L$2,R$2)} -> 640 | S40: {=TREND($B40:$L40,$B$2:$L$2,S$2)} -> 640 | T40: {=TREND($B40:$L40,$B$2:$L$2,T$2)} -> 640 | ... AF40: {=TREND($B40:$L40,$B$2:$L$2,AF$2)} -> 640
A41: nuclear | B41: =KRW!B41 -> 1990 | C41: =B41+($L41-$B41)/($L$2-$B$2) -> 1990 | D41: =C41+($L41-$B41)/($L$2-$B$2) -> 1990 | E41: =D41+($L41-$B41)/($L$2-$B$2) -> 1990 | F41: =E41+($L41-$B41)/($L$2-$B$2) -> 1990 | G41: =F41+($L41-$B41)/($L$2-$B$2) -> 1990 | H41: =G41+($L41-$B41)/($L$2-$B$2) -> 1990 | I41: =H41+($L41-$B41)/($L$2-$B$2) -> 1990 | J41: =I41+($L41-$B41)/($L$2-$B$2) -> 1990 | K41: =J41+($L41-$B41)/($L$2-$B$2) -> 1990 | L41: =KRW!D41 -> 1990 | M41: {=TREND($B41:$L41,$B$2:$L$2,M$2)} -> 1990 | N41: {=TREND($B41:$L41,$B$2:$L$2,N$2)} -> 1990 | O41: {=TREND($B41:$L41,$B$2:$L$2,O$2)} -> 1990 | P41: {=TREND($B41:$L41,$B$2:$L$2,P$2)} -> 1990 | Q41: {=TREND($B41:$L41,$B$2:$L$2,Q$2)} -> 1990 | R41: {=TREND($B41:$L41,$B$2:$L$2,R$2)} -> 1990 | S41: {=TREND($B41:$L41,$B$2:$L$2,S$2)} -> 1990 | T41: {=TREND($B41:$L41,$B$2:$L$2,T$2)} -> 1990 | ... AF41: {=TREND($B41:$L41,$B$2:$L$2,AF$2)} -> 1990
A42: hydro | B42: =KRW!B42 -> 200 | C42: =B42+($L42-$B42)/($L$2-$B$2) -> 200 | D42: =C42+($L42-$B42)/($L$2-$B$2) -> 200 | E42: =D42+($L42-$B42)/($L$2-$B$2) -> 200 | F42: =E42+($L42-$B42)/($L$2-$B$2) -> 200 | G42: =F42+($L42-$B42)/($L$2-$B$2) -> 200 | H42: =G42+($L42-$B42)/($L$2-$B$2) -> 200 | I42: =H42+($L42-$B42)/($L$2-$B$2) -> 200 | J42: =I42+($L42-$B42)/($L$2-$B$2) -> 200 | K42: =J42+($L42-$B42)/($L$2-$B$2) -> 200 | L42: =KRW!D42 -> 200 | M42: {=TREND($B42:$L42,$B$2:$L$2,M$2)} -> 200 | N42: {=TREND($B42:$L42,$B$2:$L$2,N$2)} -> 200 | O42: {=TREND($B42:$L42,$B$2:$L$2,O$2)} -> 200 | P42: {=TREND($B42:$L42,$B$2:$L$2,P$2)} -> 200 | Q42: {=TREND($B42:$L42,$B$2:$L$2,Q$2)} -> 200 | R42: {=TREND($B42:$L42,$B$2:$L$2,R$2)} -> 200 | S42: {=TREND($B42:$L42,$B$2:$L$2,S$2)} -> 200 | T42: {=TREND($B42:$L42,$B$2:$L$2,T$2)} -> 200 | ... AF42: {=TREND($B42:$L42,$B$2:$L$2,AF$2)} -> 200
A43: onshore wind | B43: =KRW!B43 -> 100 | C43: =B43+($L43-$B43)/($L$2-$B$2) -> 100 | D43: =C43+($L43-$B43)/($L$2-$B$2) -> 100 | E43: =D43+($L43-$B43)/($L$2-$B$2) -> 100 | F43: =E43+($L43-$B43)/($L$2-$B$2) -> 100 | G43: =F43+($L43-$B43)/($L$2-$B$2) -> 100 | H43: =G43+($L43-$B43)/($L$2-$B$2) -> 100 | I43: =H43+($L43-$B43)/($L$2-$B$2) -> 100 | J43: =I43+($L43-$B43)/($L$2-$B$2) -> 100 | K43: =J43+($L43-$B43)/($L$2-$B$2) -> 100 | L43: =KRW!D43 -> 100 | M43: {=TREND($B43:$L43,$B$2:$L$2,M$2)} -> 100 | N43: {=TREND($B43:$L43,$B$2:$L$2,N$2)} -> 100 | O43: {=TREND($B43:$L43,$B$2:$L$2,O$2)} -> 100 | P43: {=TREND($B43:$L43,$B$2:$L$2,P$2)} -> 100 | Q43: {=TREND($B43:$L43,$B$2:$L$2,Q$2)} -> 100 | R43: {=TREND($B43:$L43,$B$2:$L$2,R$2)} -> 100 | S43: {=TREND($B43:$L43,$B$2:$L$2,S$2)} -> 100 | T43: {=TREND($B43:$L43,$B$2:$L$2,T$2)} -> 100 | ... AF43: {=TREND($B43:$L43,$B$2:$L$2,AF$2)} -> 100
A44: solar PV | B44: =KRW!B44 -> 100 | C44: =B44+($L44-$B44)/($L$2-$B$2) -> 100 | D44: =C44+($L44-$B44)/($L$2-$B$2) -> 100 | E44: =D44+($L44-$B44)/($L$2-$B$2) -> 100 | F44: =E44+($L44-$B44)/($L$2-$B$2) -> 100 | G44: =F44+($L44-$B44)/($L$2-$B$2) -> 100 | H44: =G44+($L44-$B44)/($L$2-$B$2) -> 100 | I44: =H44+($L44-$B44)/($L$2-$B$2) -> 100 | J44: =I44+($L44-$B44)/($L$2-$B$2) -> 100 | K44: =J44+($L44-$B44)/($L$2-$B$2) -> 100 | L44: =KRW!D44 -> 100 | M44: {=TREND($B44:$L44,$B$2:$L$2,M$2)} -> 100 | N44: {=TREND($B44:$L44,$B$2:$L$2,N$2)} -> 100 | O44: {=TREND($B44:$L44,$B$2:$L$2,O$2)} -> 100 | P44: {=TREND($B44:$L44,$B$2:$L$2,P$2)} -> 100 | Q44: {=TREND($B44:$L44,$B$2:$L$2,Q$2)} -> 100 | R44: {=TREND($B44:$L44,$B$2:$L$2,R$2)} -> 100 | S44: {=TREND($B44:$L44,$B$2:$L$2,S$2)} -> 100 | T44: {=TREND($B44:$L44,$B$2:$L$2,T$2)} -> 100 | ... AF44: {=TREND($B44:$L44,$B$2:$L$2,AF$2)} -> 100
A45: solar thermal | B45: =KRW!B45 -> 0 | C45: =B45+($L45-$B45)/($L$2-$B$2) -> 0 | D45: =C45+($L45-$B45)/($L$2-$B$2) -> 0 | E45: =D45+($L45-$B45)/($L$2-$B$2) -> 0 | F45: =E45+($L45-$B45)/($L$2-$B$2) -> 0 | G45: =F45+($L45-$B45)/($L$2-$B$2) -> 0 | H45: =G45+($L45-$B45)/($L$2-$B$2) -> 0 | I45: =H45+($L45-$B45)/($L$2-$B$2) -> 0 | J45: =I45+($L45-$B45)/($L$2-$B$2) -> 0 | K45: =J45+($L45-$B45)/($L$2-$B$2) -> 0 | L45: =KRW!D45 -> 0 | M45: {=TREND($B45:$L45,$B$2:$L$2,M$2)} -> 0 | N45: {=TREND($B45:$L45,$B$2:$L$2,N$2)} -> 0 | O45: {=TREND($B45:$L45,$B$2:$L$2,O$2)} -> 0 | P45: {=TREND($B45:$L45,$B$2:$L$2,P$2)} -> 0 | Q45: {=TREND($B45:$L45,$B$2:$L$2,Q$2)} -> 0 | R45: {=TREND($B45:$L45,$B$2:$L$2,R$2)} -> 0 | S45: {=TREND($B45:$L45,$B$2:$L$2,S$2)} -> 0 | T45: {=TREND($B45:$L45,$B$2:$L$2,T$2)} -> 0 | ... AF45: {=TREND($B45:$L45,$B$2:$L$2,AF$2)} -> 0
A46: biomass | B46: =KRW!B46 -> 100 | C46: =B46+($L46-$B46)/($L$2-$B$2) -> 100 | D46: =C46+($L46-$B46)/($L$2-$B$2) -> 100 | E46: =D46+($L46-$B46)/($L$2-$B$2) -> 100 | F46: =E46+($L46-$B46)/($L$2-$B$2) -> 100 | G46: =F46+($L46-$B46)/($L$2-$B$2) -> 100 | H46: =G46+($L46-$B46)/($L$2-$B$2) -> 100 | I46: =H46+($L46-$B46)/($L$2-$B$2) -> 100 | J46: =I46+($L46-$B46)/($L$2-$B$2) -> 100 | K46: =J46+($L46-$B46)/($L$2-$B$2) -> 100 | L46: =KRW!D46 -> 100 | M46: {=TREND($B46:$L46,$B$2:$L$2,M$2)} -> 100 | N46: {=TREND($B46:$L46,$B$2:$L$2,N$2)} -> 100 | O46: {=TREND($B46:$L46,$B$2:$L$2,O$2)} -> 100 | P46: {=TREND($B46:$L46,$B$2:$L$2,P$2)} -> 100 | Q46: {=TREND($B46:$L46,$B$2:$L$2,Q$2)} -> 100 | R46: {=TREND($B46:$L46,$B$2:$L$2,R$2)} -> 100 | S46: {=TREND($B46:$L46,$B$2:$L$2,S$2)} -> 100 | T46: {=TREND($B46:$L46,$B$2:$L$2,T$2)} -> 100 | ... AF46: {=TREND($B46:$L46,$B$2:$L$2,AF$2)} -> 100
A47: geothermal | B47: =KRW!B47 -> 100 | C47: =B47+($L47-$B47)/($L$2-$B$2) -> 100 | D47: =C47+($L47-$B47)/($L$2-$B$2) -> 100 | E47: =D47+($L47-$B47)/($L$2-$B$2) -> 100 | F47: =E47+($L47-$B47)/($L$2-$B$2) -> 100 | G47: =F47+($L47-$B47)/($L$2-$B$2) -> 100 | H47: =G47+($L47-$B47)/($L$2-$B$2) -> 100 | I47: =H47+($L47-$B47)/($L$2-$B$2) -> 100 | J47: =I47+($L47-$B47)/($L$2-$B$2) -> 100 | K47: =J47+($L47-$B47)/($L$2-$B$2) -> 100 | L47: =KRW!D47 -> 100 | M47: {=TREND($B47:$L47,$B$2:$L$2,M$2)} -> 100 | N47: {=TREND($B47:$L47,$B$2:$L$2,N$2)} -> 100 | O47: {=TREND($B47:$L47,$B$2:$L$2,O$2)} -> 100 | P47: {=TREND($B47:$L47,$B$2:$L$2,P$2)} -> 100 | Q47: {=TREND($B47:$L47,$B$2:$L$2,Q$2)} -> 100 | R47: {=TREND($B47:$L47,$B$2:$L$2,R$2)} -> 100 | S47: {=TREND($B47:$L47,$B$2:$L$2,S$2)} -> 100 | T47: {=TREND($B47:$L47,$B$2:$L$2,T$2)} -> 100 | ... AF47: {=TREND($B47:$L47,$B$2:$L$2,AF$2)} -> 100
A48: petroleum | B48: =KRW!B48 -> 150 | C48: =B48+($L48-$B48)/($L$2-$B$2) -> 150 | D48: =C48+($L48-$B48)/($L$2-$B$2) -> 150 | E48: =D48+($L48-$B48)/($L$2-$B$2) -> 150 | F48: =E48+($L48-$B48)/($L$2-$B$2) -> 150 | G48: =F48+($L48-$B48)/($L$2-$B$2) -> 150 | H48: =G48+($L48-$B48)/($L$2-$B$2) -> 150 | I48: =H48+($L48-$B48)/($L$2-$B$2) -> 150 | J48: =I48+($L48-$B48)/($L$2-$B$2) -> 150 | K48: =J48+($L48-$B48)/($L$2-$B$2) -> 150 | L48: =KRW!D48 -> 150 | M48: {=TREND($B48:$L48,$B$2:$L$2,M$2)} -> 150 | N48: {=TREND($B48:$L48,$B$2:$L$2,N$2)} -> 150 | O48: {=TREND($B48:$L48,$B$2:$L$2,O$2)} -> 150 | P48: {=TREND($B48:$L48,$B$2:$L$2,P$2)} -> 150 | Q48: {=TREND($B48:$L48,$B$2:$L$2,Q$2)} -> 150 | R48: {=TREND($B48:$L48,$B$2:$L$2,R$2)} -> 150 | S48: {=TREND($B48:$L48,$B$2:$L$2,S$2)} -> 150 | T48: {=TREND($B48:$L48,$B$2:$L$2,T$2)} -> 150 | ... AF48: {=TREND($B48:$L48,$B$2:$L$2,AF$2)} -> 150
A49: natural gas peaker | B49: =KRW!B49 -> 640 | C49: =B49+($L49-$B49)/($L$2-$B$2) -> 640 | D49: =C49+($L49-$B49)/($L$2-$B$2) -> 640 | E49: =D49+($L49-$B49)/($L$2-$B$2) -> 640 | F49: =E49+($L49-$B49)/($L$2-$B$2) -> 640 | G49: =F49+($L49-$B49)/($L$2-$B$2) -> 640 | H49: =G49+($L49-$B49)/($L$2-$B$2) -> 640 | I49: =H49+($L49-$B49)/($L$2-$B$2) -> 640 | J49: =I49+($L49-$B49)/($L$2-$B$2) -> 640 | K49: =J49+($L49-$B49)/($L$2-$B$2) -> 640 | L49: =KRW!D49 -> 640 | M49: {=TREND($B49:$L49,$B$2:$L$2,M$2)} -> 640 | N49: {=TREND($B49:$L49,$B$2:$L$2,N$2)} -> 640 | O49: {=TREND($B49:$L49,$B$2:$L$2,O$2)} -> 640 | P49: {=TREND($B49:$L49,$B$2:$L$2,P$2)} -> 640 | Q49: {=TREND($B49:$L49,$B$2:$L$2,Q$2)} -> 640 | R49: {=TREND($B49:$L49,$B$2:$L$2,R$2)} -> 640 | S49: {=TREND($B49:$L49,$B$2:$L$2,S$2)} -> 640 | T49: {=TREND($B49:$L49,$B$2:$L$2,T$2)} -> 640 | ... AF49: {=TREND($B49:$L49,$B$2:$L$2,AF$2)} -> 640
A50: lignite | B50: =KRW!B50 -> 1180 | C50: =B50+($L50-$B50)/($L$2-$B$2) -> 1180 | D50: =C50+($L50-$B50)/($L$2-$B$2) -> 1180 | E50: =D50+($L50-$B50)/($L$2-$B$2) -> 1180 | F50: =E50+($L50-$B50)/($L$2-$B$2) -> 1180 | G50: =F50+($L50-$B50)/($L$2-$B$2) -> 1180 | H50: =G50+($L50-$B50)/($L$2-$B$2) -> 1180 | I50: =H50+($L50-$B50)/($L$2-$B$2) -> 1180 | J50: =I50+($L50-$B50)/($L$2-$B$2) -> 1180 | K50: =J50+($L50-$B50)/($L$2-$B$2) -> 1180 | L50: =KRW!D50 -> 1180 | M50: {=TREND($B50:$L50,$B$2:$L$2,M$2)} -> 1180 | N50: {=TREND($B50:$L50,$B$2:$L$2,N$2)} -> 1180 | O50: {=TREND($B50:$L50,$B$2:$L$2,O$2)} -> 1180 | P50: {=TREND($B50:$L50,$B$2:$L$2,P$2)} -> 1180 | Q50: {=TREND($B50:$L50,$B$2:$L$2,Q$2)} -> 1180 | R50: {=TREND($B50:$L50,$B$2:$L$2,R$2)} -> 1180 | S50: {=TREND($B50:$L50,$B$2:$L$2,S$2)} -> 1180 | T50: {=TREND($B50:$L50,$B$2:$L$2,T$2)} -> 1180 | ... AF50: {=TREND($B50:$L50,$B$2:$L$2,AF$2)} -> 1180
... A54: municipal solid waste | B54: =KRW!B54 -> 100 | C54: =B54+($L54-$B54)/($L$2-$B$2) -> 100 | D54: =C54+($L54-$B54)/($L$2-$B$2) -> 100 | E54: =D54+($L54-$B54)/($L$2-$B$2) -> 100 | F54: =E54+($L54-$B54)/($L$2-$B$2) -> 100 | G54: =F54+($L54-$B54)/($L$2-$B$2) -> 100 | H54: =G54+($L54-$B54)/($L$2-$B$2) -> 100 | I54: =H54+($L54-$B54)/($L$2-$B$2) -> 100 | J54: =I54+($L54-$B54)/($L$2-$B$2) -> 100 | K54: =J54+($L54-$B54)/($L$2-$B$2) -> 100 | L54: =KRW!D54 -> 100 | M54: {=TREND($B54:$L54,$B$2:$L$2,M$2)} -> 100 | N54: {=TREND($B54:$L54,$B$2:$L$2,N$2)} -> 100 | O54: {=TREND($B54:$L54,$B$2:$L$2,O$2)} -> 100 | P54: {=TREND($B54:$L54,$B$2:$L$2,P$2)} -> 100 | Q54: {=TREND($B54:$L54,$B$2:$L$2,Q$2)} -> 100 | R54: {=TREND($B54:$L54,$B$2:$L$2,R$2)} -> 100 | S54: {=TREND($B54:$L54,$B$2:$L$2,S$2)} -> 100 | T54: {=TREND($B54:$L54,$B$2:$L$2,T$2)} -> 100 | ... AF54: {=TREND($B54:$L54,$B$2:$L$2,AF$2)} -> 100
A56: CAPEX (USD/MW) | B56: 2020 | C56: 2021 | D56: 2022 | E56: 2023 | F56: 2024 | G56: 2025 | H56: 2026 | I56: 2027 | J56: 2028 | K56: 2029 | L56: 2030 | M56: 2031 | N56: 2032 | O56: 2033 | P56: 2034 | Q56: 2035 | R56: 2036 | S56: 2037 | T56: 2038 | U56: 2039 | V56: 2040 | W56: 2041 | X56: 2042 | Y56: 2043 | Z56: 2044 | AA56: 2045 | AB56: 2046 | AC56: 2047 | AD56: 2048 | AE56: 2049 | AF56: 2050
A57: hard coal | B57: =B3/About!$A$39*1000 -> 1337746.9 | C57: =C3/About!$A$39*1000 -> 1386477.2 | D57: =D3/About!$A$39*1000 -> 1435207.5 | E57: =E3/About!$A$39*1000 -> 1483937.8 | F57: =F3/About!$A$39*1000 -> 1532668.1 | G57: =G3/About!$A$39*1000 -> 1581398.3 | H57: =H3/About!$A$39*1000 -> 1630128.6 | I57: =I3/About!$A$39*1000 -> 1678858.9 | ... AF57: =AF3/About!$A$39*1000 -> 2799655.2
A58: natural gas nonpeaker | B58: =B4/About!$A$39*1000 -> 874073.24 | C58: =C4/About!$A$39*1000 -> 881978.11 | D58: =D4/About!$A$39*1000 -> 889882.98 | E58: =E4/About!$A$39*1000 -> 897787.85 | F58: =F4/About!$A$39*1000 -> 905692.72 | G58: =G4/About!$A$39*1000 -> 913597.59 | H58: =H4/About!$A$39*1000 -> 921502.46 | I58: =I4/About!$A$39*1000 -> 929407.34 | ... AF58: =AF4/About!$A$39*1000 -> 1111219.4
A59: nuclear | B59: =B5/About!$A$39*1000 -> 4215729.5 | C59: =C5/About!$A$39*1000 -> 4319515.8 | D59: =D5/About!$A$39*1000 -> 4423302.1 | E59: =E5/About!$A$39*1000 -> 4527088.4 | F59: =F5/About!$A$39*1000 -> 4630874.7 | G59: =G5/About!$A$39*1000 -> 4734661 | H59: =H5/About!$A$39*1000 -> 4838447.4 | I59: =I5/About!$A$39*1000 -> 4942233.7 | ... AF59: =AF5/About!$A$39*1000 -> 7329318.8
A60: hydro | B60: =B6/About!$A$39*1000 -> 900876.33 | C60: =C6/About!$A$39*1000 -> 900876.33 | D60: =D6/About!$A$39*1000 -> 900876.33 | E60: =E6/About!$A$39*1000 -> 900876.33 | F60: =F6/About!$A$39*1000 -> 900876.33 | G60: =G6/About!$A$39*1000 -> 900876.33 | H60: =H6/About!$A$39*1000 -> 900876.33 | I60: =I6/About!$A$39*1000 -> 900876.33 | ... AF60: =AF6/About!$A$39*1000 -> 900876.33
A61: onshore wind | B61: =B7/About!$A$39*1000 -> 2544790.1 | C61: =C7/About!$A$39*1000 -> 2519342.2 | D61: =D7/About!$A$39*1000 -> 2493894.3 | E61: =E7/About!$A$39*1000 -> 2468446.4 | F61: =F7/About!$A$39*1000 -> 2442998.5 | G61: =G7/About!$A$39*1000 -> 2417550.6 | H61: =H7/About!$A$39*1000 -> 2371744.4 | I61: =I7/About!$A$39*1000 -> 2325938.2 | ... AF61: =AF7/About!$A$39*1000 -> 1499112.7
A62: solar PV | B62: =B8/About!$A$39*1000 -> 1274241.1 | C62: =C8/About!$A$39*1000 -> 1274241.1 | D62: =D8/About!$A$39*1000 -> 1274241.1 | E62: =E8/About!$A$39*1000 -> 1274241.1 | F62: =F8/About!$A$39*1000 -> 1274241.1 | G62: =G8/About!$A$39*1000 -> 1274241.1 | H62: =H8/About!$A$39*1000 -> 1228368.4 | I62: =I8/About!$A$39*1000 -> 1182495.7 | ... AF62: =AF8/About!$A$39*1000 -> 638278.94
A63: solar thermal | B63: =B9/About!$A$39*1000 -> 0 | C63: =C9/About!$A$39*1000 -> 0 | D63: =D9/About!$A$39*1000 -> 0 | E63: =E9/About!$A$39*1000 -> 0 | F63: =F9/About!$A$39*1000 -> 0 | G63: =G9/About!$A$39*1000 -> 0 | H63: =H9/About!$A$39*1000 -> 0 | I63: =I9/About!$A$39*1000 -> 0 | ... AF63: =AF9/About!$A$39*1000 -> 0
A64: biomass | B64: =B10/About!$A$39*1000 -> 3555642.3 | C64: =C10/About!$A$39*1000 -> 3555642.3 | D64: =D10/About!$A$39*1000 -> 3555642.3 | E64: =E10/About!$A$39*1000 -> 3555642.3 | F64: =F10/About!$A$39*1000 -> 3555642.3 | G64: =G10/About!$A$39*1000 -> 3555642.3 | H64: =H10/About!$A$39*1000 -> 3555642.3 | I64: =I10/About!$A$39*1000 -> 3555642.3 | ... AF64: =AF10/About!$A$39*1000 -> 3555642.3
A65: geothermal | B65: =B11/About!$A$39*1000 -> 8208000 | C65: =C11/About!$A$39*1000 -> 8208000 | D65: =D11/About!$A$39*1000 -> 8208000 | E65: =E11/About!$A$39*1000 -> 8208000 | F65: =F11/About!$A$39*1000 -> 8208000 | G65: =G11/About!$A$39*1000 -> 8208000 | H65: =H11/About!$A$39*1000 -> 8208000 | I65: =I11/About!$A$39*1000 -> 8208000 | ... AF65: =AF11/About!$A$39*1000 -> 8208000
A66: petroleum | B66: =B12/About!$A$39*1000 -> 1762910.9 | C66: =C12/About!$A$39*1000 -> 1762910.9 | D66: =D12/About!$A$39*1000 -> 1762910.9 | E66: =E12/About!$A$39*1000 -> 1762910.9 | F66: =F12/About!$A$39*1000 -> 1762910.9 | G66: =G12/About!$A$39*1000 -> 1762910.9 | H66: =H12/About!$A$39*1000 -> 1762910.9 | I66: =I12/About!$A$39*1000 -> 1762910.9 | ... AF66: =AF12/About!$A$39*1000 -> 1762910.9
A67: natural gas peaker | B67: =B13/About!$A$39*1000 -> 611851.27 | C67: =C13/About!$A$39*1000 -> 617384.68 | D67: =D13/About!$A$39*1000 -> 622918.09 | E67: =E13/About!$A$39*1000 -> 628451.5 | F67: =F13/About!$A$39*1000 -> 633984.91 | G67: =G13/About!$A$39*1000 -> 639518.32 | H67: =H13/About!$A$39*1000 -> 645051.73 | I67: =I13/About!$A$39*1000 -> 650585.14 | ... AF67: =AF13/About!$A$39*1000 -> 777853.56
A68: lignite | B68: =B14/About!$A$39*1000 -> 1337746.9 | C68: =C14/About!$A$39*1000 -> 1386477.2 | D68: =D14/About!$A$39*1000 -> 1435207.5 | E68: =E14/About!$A$39*1000 -> 1483937.8 | F68: =F14/About!$A$39*1000 -> 1532668.1 | G68: =G14/About!$A$39*1000 -> 1581398.3 | H68: =H14/About!$A$39*1000 -> 1630128.6 | I68: =I14/About!$A$39*1000 -> 1678858.9 | ... AF68: =AF14/About!$A$39*1000 -> 2799655.2
... A72: municipal solid waste | B72: =B18/About!$A$39*1000 -> 4463927.3 | C72: =C18/About!$A$39*1000 -> 4463927.3 | D72: =D18/About!$A$39*1000 -> 4463927.3 | E72: =E18/About!$A$39*1000 -> 4463927.3 | F72: =F18/About!$A$39*1000 -> 4463927.3 | G72: =G18/About!$A$39*1000 -> 4463927.3 | H72: =H18/About!$A$39*1000 -> 4463927.3 | I72: =I18/About!$A$39*1000 -> 4463927.3 | ... AF72: =AF18/About!$A$39*1000 -> 4463927.3
A74: Fixed O&M (USD/MW-yr) | B74: 2020 | C74: 2021 | D74: 2022 | E74: 2023 | F74: 2024 | G74: 2025 | H74: 2026 | I74: 2027 | J74: 2028 | K74: 2029 | L74: 2030 | M74: 2031 | N74: 2032 | O74: 2033 | P74: 2034 | Q74: 2035 | R74: 2036 | S74: 2037 | T74: 2038 | U74: 2039 | V74: 2040 | W74: 2041 | X74: 2042 | Y74: 2043 | Z74: 2044 | AA74: 2045 | AB74: 2046 | AC74: 2047 | AD74: 2048 | AE74: 2049 | AF74: 2050
A75: hard coal | B75: =B21/About!$A$39*1000 -> 62002.388 | C75: =C21/About!$A$39*1000 -> 62002.388 | D75: =D21/About!$A$39*1000 -> 62002.388 | E75: =E21/About!$A$39*1000 -> 62002.388 | F75: =F21/About!$A$39*1000 -> 62002.388 | G75: =G21/About!$A$39*1000 -> 62002.388 | H75: =H21/About!$A$39*1000 -> 62002.388 | I75: =I21/About!$A$39*1000 -> 62002.388 | ... AF75: =AF21/About!$A$39*1000 -> 62002.388
A76: natural gas nonpeaker | B76: =B22/About!$A$39*1000 -> 40766.481 | C76: =C22/About!$A$39*1000 -> 40766.481 | D76: =D22/About!$A$39*1000 -> 40766.481 | E76: =E22/About!$A$39*1000 -> 40766.481 | F76: =F22/About!$A$39*1000 -> 40766.481 | G76: =G22/About!$A$39*1000 -> 40766.481 | H76: =H22/About!$A$39*1000 -> 40766.481 | I76: =I22/About!$A$39*1000 -> 40766.481 | ... AF76: =AF22/About!$A$39*1000 -> 40766.481
A77: nuclear | B77: =B23/About!$A$39*1000 -> 155249.59 | C77: =C23/About!$A$39*1000 -> 155249.59 | D77: =D23/About!$A$39*1000 -> 155249.59 | E77: =E23/About!$A$39*1000 -> 155249.59 | F77: =F23/About!$A$39*1000 -> 155249.59 | G77: =G23/About!$A$39*1000 -> 155249.59 | H77: =H23/About!$A$39*1000 -> 155249.59 | I77: =I23/About!$A$39*1000 -> 155249.59 | ... AF77: =AF23/About!$A$39*1000 -> 155249.59
A78: hydro | B78: =B24/About!$A$39*1000 -> 22521.908 | C78: =C24/About!$A$39*1000 -> 22521.908 | D78: =D24/About!$A$39*1000 -> 22521.908 | E78: =E24/About!$A$39*1000 -> 22521.908 | F78: =F24/About!$A$39*1000 -> 22521.908 | G78: =G24/About!$A$39*1000 -> 22521.908 | H78: =H24/About!$A$39*1000 -> 22521.908 | I78: =I24/About!$A$39*1000 -> 22521.908 | ... AF78: =AF24/About!$A$39*1000 -> 22521.908
A79: onshore wind | B79: =B25/About!$A$39*1000 -> 47454.337 | C79: =C25/About!$A$39*1000 -> 47454.337 | D79: =D25/About!$A$39*1000 -> 47454.337 | E79: =E25/About!$A$39*1000 -> 47454.337 | F79: =F25/About!$A$39*1000 -> 47454.337 | G79: =G25/About!$A$39*1000 -> 47454.337 | H79: =H25/About!$A$39*1000 -> 47454.337 | I79: =I25/About!$A$39*1000 -> 47454.337 | ... AF79: =AF25/About!$A$39*1000 -> 47454.337
A80: solar PV | B80: =B26/About!$A$39*1000 -> 23129.653 | C80: =C26/About!$A$39*1000 -> 23129.653 | D80: =D26/About!$A$39*1000 -> 23129.653 | E80: =E26/About!$A$39*1000 -> 23129.653 | F80: =F26/About!$A$39*1000 -> 23129.653 | G80: =G26/About!$A$39*1000 -> 23129.653 | H80: =H26/About!$A$39*1000 -> 23129.653 | I80: =I26/About!$A$39*1000 -> 23129.653 | ... AF80: =AF26/About!$A$39*1000 -> 23129.653
A81: solar thermal | B81: =B27/About!$A$39*1000 -> 0 | C81: =C27/About!$A$39*1000 -> 0 | D81: =D27/About!$A$39*1000 -> 0 | E81: =E27/About!$A$39*1000 -> 0 | F81: =F27/About!$A$39*1000 -> 0 | G81: =G27/About!$A$39*1000 -> 0 | H81: =H27/About!$A$39*1000 -> 0 | I81: =I27/About!$A$39*1000 -> 0 | ... AF81: =AF27/About!$A$39*1000 -> 0
A82: biomass | B82: =B28/About!$A$39*1000 -> 88891.056 | C82: =C28/About!$A$39*1000 -> 88891.056 | D82: =D28/About!$A$39*1000 -> 88891.056 | E82: =E28/About!$A$39*1000 -> 88891.056 | F82: =F28/About!$A$39*1000 -> 88891.056 | G82: =G28/About!$A$39*1000 -> 88891.056 | H82: =H28/About!$A$39*1000 -> 88891.056 | I82: =I28/About!$A$39*1000 -> 88891.056 | ... AF82: =AF28/About!$A$39*1000 -> 88891.056
A83: geothermal | B83: =B29/About!$A$39*1000 -> 205200 | C83: =C29/About!$A$39*1000 -> 205200 | D83: =D29/About!$A$39*1000 -> 205200 | E83: =E29/About!$A$39*1000 -> 205200 | F83: =F29/About!$A$39*1000 -> 205200 | G83: =G29/About!$A$39*1000 -> 205200 | H83: =H29/About!$A$39*1000 -> 205200 | I83: =I29/About!$A$39*1000 -> 205200 | ... AF83: =AF29/About!$A$39*1000 -> 205200
A84: petroleum | B84: =B30/About!$A$39*1000 -> 44072.773 | C84: =C30/About!$A$39*1000 -> 44072.773 | D84: =D30/About!$A$39*1000 -> 44072.773 | E84: =E30/About!$A$39*1000 -> 44072.773 | F84: =F30/About!$A$39*1000 -> 44072.773 | G84: =G30/About!$A$39*1000 -> 44072.773 | H84: =H30/About!$A$39*1000 -> 44072.773 | I84: =I30/About!$A$39*1000 -> 44072.773 | ... AF84: =AF30/About!$A$39*1000 -> 44072.773
A85: natural gas peaker | B85: =B31/About!$A$39*1000 -> 15296.282 | C85: =C31/About!$A$39*1000 -> 15296.282 | D85: =D31/About!$A$39*1000 -> 15296.282 | E85: =E31/About!$A$39*1000 -> 15296.282 | F85: =F31/About!$A$39*1000 -> 15296.282 | G85: =G31/About!$A$39*1000 -> 15296.282 | H85: =H31/About!$A$39*1000 -> 15296.282 | I85: =I31/About!$A$39*1000 -> 15296.282 | ... AF85: =AF31/About!$A$39*1000 -> 15296.282
A86: lignite | B86: =B32/About!$A$39*1000 -> 62002.388 | C86: =C32/About!$A$39*1000 -> 62002.388 | D86: =D32/About!$A$39*1000 -> 62002.388 | E86: =E32/About!$A$39*1000 -> 62002.388 | F86: =F32/About!$A$39*1000 -> 62002.388 | G86: =G32/About!$A$39*1000 -> 62002.388 | H86: =H32/About!$A$39*1000 -> 62002.388 | I86: =I32/About!$A$39*1000 -> 62002.388 | ... AF86: =AF32/About!$A$39*1000 -> 62002.388
... A90: municipal solid waste | B90: =B36/About!$A$39*1000 -> 111598.18 | C90: =C36/About!$A$39*1000 -> 111598.18 | D90: =D36/About!$A$39*1000 -> 111598.18 | E90: =E36/About!$A$39*1000 -> 111598.18 | F90: =F36/About!$A$39*1000 -> 111598.18 | G90: =G36/About!$A$39*1000 -> 111598.18 | H90: =H36/About!$A$39*1000 -> 111598.18 | I90: =I36/About!$A$39*1000 -> 111598.18 | ... AF90: =AF36/About!$A$39*1000 -> 111598.18
A92: Variable O&M (USD/MWh) | B92: 2020 | C92: 2021 | D92: 2022 | E92: 2023 | F92: 2024 | G92: 2025 | H92: 2026 | I92: 2027 | J92: 2028 | K92: 2029 | L92: 2030 | M92: 2031 | N92: 2032 | O92: 2033 | P92: 2034 | Q92: 2035 | R92: 2036 | S92: 2037 | T92: 2038 | U92: 2039 | V92: 2040 | W92: 2041 | X92: 2042 | Y92: 2043 | Z92: 2044 | AA92: 2045 | AB92: 2046 | AC92: 2047 | AD92: 2048 | AE92: 2049 | AF92: 2050
A93: hard coal | B93: =B39/About!$A$39 -> 1.0973821 | C93: =C39/About!$A$39 -> 1.0973821 | D93: =D39/About!$A$39 -> 1.0973821 | E93: =E39/About!$A$39 -> 1.0973821 | F93: =F39/About!$A$39 -> 1.0973821 | G93: =G39/About!$A$39 -> 1.0973821 | H93: =H39/About!$A$39 -> 1.0973821 | I93: =I39/About!$A$39 -> 1.0973821 | ... AF93: =AF39/About!$A$39 -> 1.0973821
A94: natural gas nonpeaker | B94: =B40/About!$A$39 -> 0.59519031 | C94: =C40/About!$A$39 -> 0.59519031 | D94: =D40/About!$A$39 -> 0.59519031 | E94: =E40/About!$A$39 -> 0.59519031 | F94: =F40/About!$A$39 -> 0.59519031 | G94: =G40/About!$A$39 -> 0.59519031 | H94: =H40/About!$A$39 -> 0.59519031 | I94: =I40/About!$A$39 -> 0.59519031 | ... AF94: =AF40/About!$A$39 -> 0.59519031
A95: nuclear | B95: =B41/About!$A$39 -> 1.8506699 | C95: =C41/About!$A$39 -> 1.8506699 | D95: =D41/About!$A$39 -> 1.8506699 | E95: =E41/About!$A$39 -> 1.8506699 | F95: =F41/About!$A$39 -> 1.8506699 | G95: =G41/About!$A$39 -> 1.8506699 | H95: =H41/About!$A$39 -> 1.8506699 | I95: =I41/About!$A$39 -> 1.8506699 | ... AF95: =AF41/About!$A$39 -> 1.8506699
A96: hydro | B96: =B42/About!$A$39 -> 0.18599697 | C96: =C42/About!$A$39 -> 0.18599697 | D96: =D42/About!$A$39 -> 0.18599697 | E96: =E42/About!$A$39 -> 0.18599697 | F96: =F42/About!$A$39 -> 0.18599697 | G96: =G42/About!$A$39 -> 0.18599697 | H96: =H42/About!$A$39 -> 0.18599697 | I96: =I42/About!$A$39 -> 0.18599697 | ... AF96: =AF42/About!$A$39 -> 0.18599697
A97: onshore wind | B97: =B43/About!$A$39 -> 0.092998486 | C97: =C43/About!$A$39 -> 0.092998486 | D97: =D43/About!$A$39 -> 0.092998486 | E97: =E43/About!$A$39 -> 0.092998486 | F97: =F43/About!$A$39 -> 0.092998486 | G97: =G43/About!$A$39 -> 0.092998486 | H97: =H43/About!$A$39 -> 0.092998486 | I97: =I43/About!$A$39 -> 0.092998486 | ... AF97: =AF43/About!$A$39 -> 0.092998486
A98: solar PV | B98: =B44/About!$A$39 -> 0.092998486 | C98: =C44/About!$A$39 -> 0.092998486 | D98: =D44/About!$A$39 -> 0.092998486 | E98: =E44/About!$A$39 -> 0.092998486 | F98: =F44/About!$A$39 -> 0.092998486 | G98: =G44/About!$A$39 -> 0.092998486 | H98: =H44/About!$A$39 -> 0.092998486 | I98: =I44/About!$A$39 -> 0.092998486 | ... AF98: =AF44/About!$A$39 -> 0.092998486
A99: solar thermal | B99: =B45/About!$A$39 -> 0 | C99: =C45/About!$A$39 -> 0 | D99: =D45/About!$A$39 -> 0 | E99: =E45/About!$A$39 -> 0 | F99: =F45/About!$A$39 -> 0 | G99: =G45/About!$A$39 -> 0 | H99: =H45/About!$A$39 -> 0 | I99: =I45/About!$A$39 -> 0 | ... AF99: =AF45/About!$A$39 -> 0
A100: biomass | B100: =B46/About!$A$39 -> 0.092998486 | C100: =C46/About!$A$39 -> 0.092998486 | D100: =D46/About!$A$39 -> 0.092998486 | E100: =E46/About!$A$39 -> 0.092998486 | F100: =F46/About!$A$39 -> 0.092998486 | G100: =G46/About!$A$39 -> 0.092998486 | H100: =H46/About!$A$39 -> 0.092998486 | I100: =I46/About!$A$39 -> 0.092998486 | ... AF100: =AF46/About!$A$39 -> 0.092998486
A101: geothermal | B101: =B47/About!$A$39 -> 0.092998486 | C101: =C47/About!$A$39 -> 0.092998486 | D101: =D47/About!$A$39 -> 0.092998486 | E101: =E47/About!$A$39 -> 0.092998486 | F101: =F47/About!$A$39 -> 0.092998486 | G101: =G47/About!$A$39 -> 0.092998486 | H101: =H47/About!$A$39 -> 0.092998486 | I101: =I47/About!$A$39 -> 0.092998486 | ... AF101: =AF47/About!$A$39 -> 0.092998486
A102: petroleum | B102: =B48/About!$A$39 -> 0.13949773 | C102: =C48/About!$A$39 -> 0.13949773 | D102: =D48/About!$A$39 -> 0.13949773 | E102: =E48/About!$A$39 -> 0.13949773 | F102: =F48/About!$A$39 -> 0.13949773 | G102: =G48/About!$A$39 -> 0.13949773 | H102: =H48/About!$A$39 -> 0.13949773 | I102: =I48/About!$A$39 -> 0.13949773 | ... AF102: =AF48/About!$A$39 -> 0.13949773
A103: natural gas peaker | B103: =B49/About!$A$39 -> 0.59519031 | C103: =C49/About!$A$39 -> 0.59519031 | D103: =D49/About!$A$39 -> 0.59519031 | E103: =E49/About!$A$39 -> 0.59519031 | F103: =F49/About!$A$39 -> 0.59519031 | G103: =G49/About!$A$39 -> 0.59519031 | H103: =H49/About!$A$39 -> 0.59519031 | I103: =I49/About!$A$39 -> 0.59519031 | ... AF103: =AF49/About!$A$39 -> 0.59519031
A104: lignite | B104: =B50/About!$A$39 -> 1.0973821 | C104: =C50/About!$A$39 -> 1.0973821 | D104: =D50/About!$A$39 -> 1.0973821 | E104: =E50/About!$A$39 -> 1.0973821 | F104: =F50/About!$A$39 -> 1.0973821 | G104: =G50/About!$A$39 -> 1.0973821 | H104: =H50/About!$A$39 -> 1.0973821 | I104: =I50/About!$A$39 -> 1.0973821 | ... AF104: =AF50/About!$A$39 -> 1.0973821
... A108: municipal solid waste | B108: =B54/About!$A$39 -> 0.092998486 | C108: =C54/About!$A$39 -> 0.092998486 | D108: =D54/About!$A$39 -> 0.092998486 | E108: =E54/About!$A$39 -> 0.092998486 | F108: =F54/About!$A$39 -> 0.092998486 | G108: =G54/About!$A$39 -> 0.092998486 | H108: =H54/About!$A$39 -> 0.092998486 | I108: =I54/About!$A$39 -> 0.092998486 | ... AF108: =AF54/About!$A$39 -> 0.092998486
A110: Spur line (grid connection) cost, USD/MW, constant in real terms = KRW!B59:B61 / exchange rate x 1000 (same conversion as CAPEX)
A111: onshore wind | B111: =KRW!B59/About!$A$39*1000 -> 39059.364
A112: solar PV | B112: =KRW!B60/About!$A$39*1000 -> 21389.652
A113: offshore wind | B113: =KRW!B61/About!$A$39*1000 -> 301315.09
A115: CAPEX EXCLUDING SPUR LINE, USD/MW = CAPEX row - spur line (USED IN CCaMC-BCCpUC for these three rows)
A116: Year | C116: =C56 -> 2021 | D116: =D56 -> 2022 | E116: =E56 -> 2023 | F116: =F56 -> 2024 | G116: =G56 -> 2025 | H116: =H56 -> 2026 | I116: =I56 -> 2027 | J116: =J56 -> 2028 | ... AF116: =AF56 -> 2050
A117: onshore wind | C117: =C61-$B$111 -> 2480282.8 | D117: =D61-$B$111 -> 2454834.9 | E117: =E61-$B$111 -> 2429387 | F117: =F61-$B$111 -> 2403939.1 | G117: =G61-$B$111 -> 2378491.2 | H117: =H61-$B$111 -> 2332685 | I117: =I61-$B$111 -> 2286878.8 | J117: =J61-$B$111 -> 2241072.6 | ... AF117: =AF61-$B$111 -> 1460053.4
A118: solar PV | C118: =C62-$B$112 -> 1252851.4 | D118: =D62-$B$112 -> 1252851.4 | E118: =E62-$B$112 -> 1252851.4 | F118: =F62-$B$112 -> 1252851.4 | G118: =G62-$B$112 -> 1252851.4 | H118: =H62-$B$112 -> 1206978.7 | I118: =I62-$B$112 -> 1161106.1 | J118: =J62-$B$112 -> 1115233.4 | ... AF118: =AF62-$B$112 -> 616889.28
A119: offshore wind | C119: =C69-$B$113 -> 5138317.2 | D119: =D69-$B$113 -> 4993111.4 | E119: =E69-$B$113 -> 4847905.6 | F119: =F69-$B$113 -> 4702699.8 | G119: =G69-$B$113 -> 4557494 | H119: =H69-$B$113 -> 4412288.2 | I119: =I69-$B$113 -> 4267082.4 | J119: =J69-$B$113 -> 4121876.6 | ... AF119: =AF69-$B$113 -> 927349.28

Sheet US Values >

Sheet CCaMC-ACAPEXpUC US
A1: Annual CapEx ($/MW) | B1: 2019 | C1: 2020 | D1: 2021 | E1: 2022 | F1: 2023 | G1: 2024 | H1: 2025 | I1: 2026 | J1: 2027 | K1: 2028 | L1: 2029 | M1: 2030 | N1: 2031 | O1: 2032 | P1: 2033 | Q1: 2034 | R1: 2035 | S1: 2036 | T1: 2037 | U1: 2038 | V1: 2039 | W1: 2040 | X1: 2041 | Y1: 2042 | Z1: 2043 | AA1: 2044 | AB1: 2045 | AC1: 2046 | AD1: 2047 | AE1: 2048 | AF1: 2049 | AG1: 2050
A2: hard coal | B2: 24015.21 | C2: 24015.21 | D2: 24015.21 | E2: 24015.21 | F2: 24015.21 | G2: 24015.21 | H2: 24015.21 | I2: 24015.21 | J2: 24015.21 | K2: 24015.21 | L2: 24015.21 | M2: 24015.21 | N2: 24015.21 | O2: 24015.21 | P2: 24015.21 | Q2: 24015.21 | R2: 24015.21 | S2: 24015.21 | T2: 24015.21 | U2: 24015.21 | V2: 24015.21 | W2: 24015.21 | X2: 24015.21 | Y2: 24015.21 | Z2: 24015.21 | AA2: 24015.21 | AB2: 24015.21 | AC2: 24015.21 | AD2: 24015.21 | AE2: 24015.21 | AF2: 24015.21 | AG2: 24015.21
A3: natural gas steam turbine | B3: 8473.0413 | C3: 8473.0413 | D3: 8473.0413 | E3: 8473.0413 | F3: 8473.0413 | G3: 8473.0413 | H3: 8473.0413 | I3: 8473.0413 | J3: 8473.0413 | K3: 8473.0413 | L3: 8473.0413 | M3: 8473.0413 | N3: 8473.0413 | O3: 8473.0413 | P3: 8473.0413 | Q3: 8473.0413 | R3: 8473.0413 | S3: 8473.0413 | T3: 8473.0413 | U3: 8473.0413 | V3: 8473.0413 | W3: 8473.0413 | X3: 8473.0413 | Y3: 8473.0413 | Z3: 8473.0413 | AA3: 8473.0413 | AB3: 8473.0413 | AC3: 8473.0413 | AD3: 8473.0413 | AE3: 8473.0413 | AF3: 8473.0413 | AG3: 8473.0413
A4: natural gas combined cycle | B4: 0 | C4: 0 | D4: 0 | E4: 0 | F4: 0 | G4: 0 | H4: 0 | I4: 0 | J4: 0 | K4: 0 | L4: 0 | M4: 0 | N4: 0 | O4: 0 | P4: 0 | Q4: 0 | R4: 0 | S4: 0 | T4: 0 | U4: 0 | V4: 0 | W4: 0 | X4: 0 | Y4: 0 | Z4: 0 | AA4: 0 | AB4: 0 | AC4: 0 | AD4: 0 | AE4: 0 | AF4: 0 | AG4: 0
A5: nuclear | B5: 55528.115 | C5: 55528.115 | D5: 55528.115 | E5: 55528.115 | F5: 55528.115 | G5: 55528.115 | H5: 55528.115 | I5: 55528.115 | J5: 55528.115 | K5: 55528.115 | L5: 55528.115 | M5: 55528.115 | N5: 55528.115 | O5: 55528.115 | P5: 55528.115 | Q5: 55528.115 | R5: 55528.115 | S5: 55528.115 | T5: 55528.115 | U5: 55528.115 | V5: 55528.115 | W5: 55528.115 | X5: 55528.115 | Y5: 55528.115 | Z5: 55528.115 | AA5: 55528.115 | AB5: 55528.115 | AC5: 55528.115 | AD5: 55528.115 | AE5: 55528.115 | AF5: 55528.115 | AG5: 55528.115
A6: hydro | B6: 0 | C6: 0 | D6: 0 | E6: 0 | F6: 0 | G6: 0 | H6: 0 | I6: 0 | J6: 0 | K6: 0 | L6: 0 | M6: 0 | N6: 0 | O6: 0 | P6: 0 | Q6: 0 | R6: 0 | S6: 0 | T6: 0 | U6: 0 | V6: 0 | W6: 0 | X6: 0 | Y6: 0 | Z6: 0 | AA6: 0 | AB6: 0 | AC6: 0 | AD6: 0 | AE6: 0 | AF6: 0 | AG6: 0
A7: onshore wind | B7: 4236.5206 | C7: 4236.5206 | D7: 4236.5206 | E7: 4236.5206 | F7: 4236.5206 | G7: 4236.5206 | H7: 4236.5206 | I7: 4236.5206 | J7: 4236.5206 | K7: 4236.5206 | L7: 4236.5206 | M7: 4236.5206 | N7: 4236.5206 | O7: 4236.5206 | P7: 4236.5206 | Q7: 4236.5206 | R7: 4236.5206 | S7: 4236.5206 | T7: 4236.5206 | U7: 4236.5206 | V7: 4236.5206 | W7: 4236.5206 | X7: 4236.5206 | Y7: 4236.5206 | Z7: 4236.5206 | AA7: 4236.5206 | AB7: 4236.5206 | AC7: 4236.5206 | AD7: 4236.5206 | AE7: 4236.5206 | AF7: 4236.5206 | AG7: 4236.5206
A8: solar PV | B8: 0 | C8: 0 | D8: 0 | E8: 0 | F8: 0 | G8: 0 | H8: 0 | I8: 0 | J8: 0 | K8: 0 | L8: 0 | M8: 0 | N8: 0 | O8: 0 | P8: 0 | Q8: 0 | R8: 0 | S8: 0 | T8: 0 | U8: 0 | V8: 0 | W8: 0 | X8: 0 | Y8: 0 | Z8: 0 | AA8: 0 | AB8: 0 | AC8: 0 | AD8: 0 | AE8: 0 | AF8: 0 | AG8: 0
A9: solar thermal | B9: 0 | C9: 0 | D9: 0 | E9: 0 | F9: 0 | G9: 0 | H9: 0 | I9: 0 | J9: 0 | K9: 0 | L9: 0 | M9: 0 | N9: 0 | O9: 0 | P9: 0 | Q9: 0 | R9: 0 | S9: 0 | T9: 0 | U9: 0 | V9: 0 | W9: 0 | X9: 0 | Y9: 0 | Z9: 0 | AA9: 0 | AB9: 0 | AC9: 0 | AD9: 0 | AE9: 0 | AF9: 0 | AG9: 0
A10: biomass | B10: 8473.0413 | C10: 8473.0413 | D10: 8473.0413 | E10: 8473.0413 | F10: 8473.0413 | G10: 8473.0413 | H10: 8473.0413 | I10: 8473.0413 | J10: 8473.0413 | K10: 8473.0413 | L10: 8473.0413 | M10: 8473.0413 | N10: 8473.0413 | O10: 8473.0413 | P10: 8473.0413 | Q10: 8473.0413 | R10: 8473.0413 | S10: 8473.0413 | T10: 8473.0413 | U10: 8473.0413 | V10: 8473.0413 | W10: 8473.0413 | X10: 8473.0413 | Y10: 8473.0413 | Z10: 8473.0413 | AA10: 8473.0413 | AB10: 8473.0413 | AC10: 8473.0413 | AD10: 8473.0413 | AE10: 8473.0413 | AF10: 8473.0413 | AG10: 8473.0413
A11: geothermal | B11: 0 | C11: 0 | D11: 0 | E11: 0 | F11: 0 | G11: 0 | H11: 0 | I11: 0 | J11: 0 | K11: 0 | L11: 0 | M11: 0 | N11: 0 | O11: 0 | P11: 0 | Q11: 0 | R11: 0 | S11: 0 | T11: 0 | U11: 0 | V11: 0 | W11: 0 | X11: 0 | Y11: 0 | Z11: 0 | AA11: 0 | AB11: 0 | AC11: 0 | AD11: 0 | AE11: 0 | AF11: 0 | AG11: 0
A12: petroleum | B12: 8473.0413 | C12: 8473.0413 | D12: 8473.0413 | E12: 8473.0413 | F12: 8473.0413 | G12: 8473.0413 | H12: 8473.0413 | I12: 8473.0413 | J12: 8473.0413 | K12: 8473.0413 | L12: 8473.0413 | M12: 8473.0413 | N12: 8473.0413 | O12: 8473.0413 | P12: 8473.0413 | Q12: 8473.0413 | R12: 8473.0413 | S12: 8473.0413 | T12: 8473.0413 | U12: 8473.0413 | V12: 8473.0413 | W12: 8473.0413 | X12: 8473.0413 | Y12: 8473.0413 | Z12: 8473.0413 | AA12: 8473.0413 | AB12: 8473.0413 | AC12: 8473.0413 | AD12: 8473.0413 | AE12: 8473.0413 | AF12: 8473.0413 | AG12: 8473.0413
... A25: hydrogen combined cycle | B25: 0 | C25: 0 | D25: 0 | E25: 0 | F25: 0 | G25: 0 | H25: 0 | I25: 0 | J25: 0 | K25: 0 | L25: 0 | M25: 0 | N25: 0 | O25: 0 | P25: 0 | Q25: 0 | R25: 0 | S25: 0 | T25: 0 | U25: 0 | V25: 0 | W25: 0 | X25: 0 | Y25: 0 | Z25: 0 | AA25: 0 | AB25: 0 | AC25: 0 | AD25: 0 | AE25: 0 | AF25: 0 | AG25: 0

Sheet CCaMC-AFOaMCpUC US
A1: Fixed O&M ($/MW) | B1: 2019 | C1: 2020 | D1: 2021 | E1: 2022 | F1: 2023 | G1: 2024 | H1: 2025 | I1: 2026 | J1: 2027 | K1: 2028 | L1: 2029 | M1: 2030 | N1: 2031 | O1: 2032 | P1: 2033 | Q1: 2034 | R1: 2035 | S1: 2036 | T1: 2037 | U1: 2038 | V1: 2039 | W1: 2040 | X1: 2041 | Y1: 2042 | Z1: 2043 | AA1: 2044 | AB1: 2045 | AC1: 2046 | AD1: 2047 | AE1: 2048 | AF1: 2049 | AG1: 2050
A2: hard coal | B2: 17670.92 | C2: 17670.92 | D2: 65750.8 | E2: 67861.068 | F2: 67547.26 | G2: 67233.452 | H2: 66919.643 | I2: 66605.835 | J2: 66292.026 | K2: 65978.218 | L2: 65664.41 | M2: 65350.601 | N2: 65036.793 | O2: 64722.984 | P2: 64095.368 | Q2: 63703.107 | R2: 63703.107 | S2: 63232.394 | T2: 62683.23 | U2: 62212.517 | V2: 61663.352 | W2: 61114.188 | X2: 60643.475 | Y2: 60094.31 | Z2: 59545.146 | AA2: 59074.433 | AB2: 58525.268 | AC2: 58054.556 | AD2: 57505.391 | AE2: 56956.226 | AF2: 56485.514 | AG2: 55936.349
A3: natural gas steam turbine | B3: 7973.6811 | C3: 14029.026 | D3: 14089.504 | E3: 14089.504 | F3: 14089.504 | G3: 14089.504 | H3: 14089.504 | I3: 14089.504 | J3: 14089.504 | K3: 14089.504 | L3: 14089.504 | M3: 14089.504 | N3: 14089.504 | O3: 14089.504 | P3: 14089.504 | Q3: 14089.504 | R3: 14089.504 | S3: 14089.504 | T3: 14089.504 | U3: 14089.504 | V3: 14089.504 | W3: 14089.504 | X3: 14089.504 | Y3: 14089.504 | Z3: 14089.504 | AA3: 14089.504 | AB3: 14089.504 | AC3: 14089.504 | AD3: 14089.504 | AE3: 14089.504 | AF3: 14089.504 | AG3: 14089.504
A4: natural gas combined cycle | B4: 8958.6976 | C4: 8299.6588 | D4: 26096.967 | E4: 31380.841 | F4: 31380.841 | G4: 30596.32 | H4: 30596.32 | I4: 30596.32 | J4: 29811.799 | K4: 29811.799 | L4: 29811.799 | M4: 29811.799 | N4: 29027.278 | O4: 29027.278 | P4: 29027.278 | Q4: 28242.757 | R4: 28242.757 | S4: 28242.757 | T4: 28242.757 | U4: 27458.236 | V4: 27458.236 | W4: 27458.236 | X4: 27458.236 | Y4: 26673.715 | Z4: 26673.715 | AA4: 26673.715 | AB4: 25889.194 | AC4: 25889.194 | AD4: 25889.194 | AE4: 25889.194 | AF4: 25104.673 | AG4: 25104.673
A5: nuclear | B5: 158387.64 | C5: 158387.64 | D5: 128891.9 | E5: 128891.9 | F5: 128891.9 | G5: 128891.9 | H5: 128891.9 | I5: 128891.9 | J5: 128891.9 | K5: 128891.9 | L5: 128891.9 | M5: 137291.18 | N5: 137291.18 | O5: 137291.18 | P5: 137291.18 | Q5: 137291.18 | R5: 137291.18 | S5: 137291.18 | T5: 137291.18 | U5: 137291.18 | V5: 137291.18 | W5: 137291.18 | X5: 137291.18 | Y5: 137291.18 | Z5: 137291.18 | AA5: 137291.18 | AB5: 137291.18 | AC5: 137291.18 | AD5: 137291.18 | AE5: 137291.18 | AF5: 137291.18 | AG5: 137291.18
A6: hydro | B6: 16314.109 | C6: 16314.109 | D6: 147430.92 | E6: 147489.95 | F6: 147489.95 | G6: 147489.95 | H6: 147489.95 | I6: 147489.95 | J6: 147489.95 | K6: 147489.95 | L6: 147489.95 | M6: 147489.95 | N6: 147489.95 | O6: 147489.95 | P6: 147489.95 | Q6: 147489.95 | R6: 147489.95 | S6: 147489.95 | T6: 147489.95 | U6: 147489.95 | V6: 147489.95 | W6: 147489.95 | X6: 141998.31 | Y6: 141998.31 | Z6: 141998.31 | AA6: 141998.31 | AB6: 141998.31 | AC6: 141998.31 | AD6: 141998.31 | AE6: 141998.31 | AF6: 141998.31 | AG6: 141998.31
A7: onshore wind | B7: 45662.124 | C7: 45662.124 | D7: 25673.315 | E7: 25452.253 | F7: 25140.477 | G7: 24828.701 | H7: 24516.925 | I7: 24205.149 | J7: 23893.373 | K7: 23581.597 | L7: 23269.821 | M7: 22958.045 | N7: 22800.74 | O7: 22643.435 | P7: 22486.13 | Q7: 22328.825 | R7: 22171.52 | S7: 22014.214 | T7: 21856.909 | U7: 21699.604 | V7: 21542.299 | W7: 21384.994 | X7: 21227.689 | Y7: 21070.384 | Z7: 20913.079 | AA7: 20755.773 | AB7: 20598.468 | AC7: 20441.163 | AD7: 20283.858 | AE7: 20126.553 | AF7: 19969.248 | AG7: 19811.943
A8: solar PV | B8: 31437.566 | C8: 32038.064 | D8: 19088.838 | E8: 18644.616 | F8: 17431.118 | G8: 16952.628 | H8: 16475.786 | I8: 16000.526 | J8: 15526.783 | K8: 15054.496 | L8: 14583.609 | M8: 14114.068 | N8: 13645.82 | O8: 13178.817 | P8: 12713.011 | Q8: 12248.36 | R8: 11784.821 | S8: 11665.293 | T8: 11545.985 | U8: 11426.893 | V8: 11308.015 | W8: 11189.347 | X8: 11070.885 | Y8: 10952.625 | Z8: 10834.566 | AA8: 10716.703 | AB8: 10599.033 | AC8: 10481.554 | AD8: 10364.263 | AE8: 10247.156 | AF8: 10130.231 | AG8: 10013.484
A9: solar thermal | B9: 77455.969 | C9: 77455.969 | D9: 58550.41 | E9: 58548.929 | F9: 56623.895 | G9: 54698.861 | H9: 52773.827 | I9: 50848.793 | J9: 48923.759 | K9: 46998.725 | L9: 45073.69 | M9: 43148.656 | N9: 43030.978 | O9: 42913.3 | P9: 42795.622 | Q9: 42677.944 | R9: 42560.266 | S9: 42442.587 | T9: 42324.909 | U9: 42207.231 | V9: 42089.553 | W9: 41971.875 | X9: 41854.197 | Y9: 41736.518 | Z9: 41618.84 | AA9: 41501.162 | AB9: 41383.484 | AC9: 41265.806 | AD9: 41148.128 | AE9: 41030.45 | AF9: 40912.771 | AG9: 40795.093
A10: biomass | B10: 121955.64 | C10: 121955.64 | D10: 133213.16 | E10: 128399.43 | F10: 128399.43 | G10: 128399.43 | H10: 128399.43 | I10: 128399.43 | J10: 128399.43 | K10: 128399.43 | L10: 128399.43 | M10: 128399.43 | N10: 128399.43 | O10: 128399.43 | P10: 128399.43 | Q10: 128399.43 | R10: 128399.43 | S10: 128399.43 | T10: 128399.43 | U10: 128399.43 | V10: 128399.43 | W10: 128399.43 | X10: 128399.43 | Y10: 128399.43 | Z10: 128399.43 | AA10: 128399.43 | AB10: 128399.43 | AC10: 128399.43 | AD10: 128399.43 | AE10: 128399.43 | AF10: 128399.43 | AG10: 128399.43
A11: geothermal | B11: 152401.1 | C11: 152401.1 | D11: 383420.67 | E11: 156873.4 | F11: 154564.21 | G11: 152255.03 | H11: 149945.84 | I11: 147636.65 | J11: 145327.47 | K11: 143018.28 | L11: 140709.09 | M11: 138399.91 | N11: 136090.72 | O11: 133781.53 | P11: 131472.35 | Q11: 129163.16 | R11: 126853.97 | S11: 126853.97 | T11: 126853.97 | U11: 126853.97 | V11: 126853.97 | W11: 126853.97 | X11: 126853.97 | Y11: 126853.97 | Z11: 126853.97 | AA11: 126853.97 | AB11: 126853.97 | AC11: 126853.97 | AD11: 126853.97 | AE11: 126853.97 | AF11: 126853.97 | AG11: 126853.97
A12: petroleum | B12: 7973.6811 | C12: 14029.026 | D12: 14089.504 | E12: 14089.504 | F12: 14089.504 | G12: 14089.504 | H12: 14089.504 | I12: 14089.504 | J12: 14089.504 | K12: 14089.504 | L12: 14089.504 | M12: 14089.504 | N12: 14089.504 | O12: 14089.504 | P12: 14089.504 | Q12: 14089.504 | R12: 14089.504 | S12: 14089.504 | T12: 14089.504 | U12: 14089.504 | V12: 14089.504 | W12: 14089.504 | X12: 14089.504 | Y12: 14089.504 | Z12: 14089.504 | AA12: 14089.504 | AB12: 14089.504 | AC12: 14089.504 | AD12: 14089.504 | AE12: 14089.504 | AF12: 14089.504 | AG12: 14089.504
... A25: hydrogen combined cycle | B25: 8958.6976 | C25: 8299.6588 | D25: 26096.967 | E25: 31380.841 | F25: 31380.841 | G25: 30596.32 | H25: 30596.32 | I25: 30596.32 | J25: 29811.799 | K25: 29811.799 | L25: 29811.799 | M25: 29811.799 | N25: 29027.278 | O25: 29027.278 | P25: 29027.278 | Q25: 28242.757 | R25: 28242.757 | S25: 28242.757 | T25: 28242.757 | U25: 27458.236 | V25: 27458.236 | W25: 27458.236 | X25: 27458.236 | Y25: 26673.715 | Z25: 26673.715 | AA25: 26673.715 | AB25: 25889.194 | AC25: 25889.194 | AD25: 25889.194 | AE25: 25889.194 | AF25: 25104.673 | AG25: 25104.673

Sheet CCaMC-VOaMCpUC US
A1: Variable O&M ($/MWh) | B1: 2019 | C1: 2020 | D1: 2021 | E1: 2022 | F1: 2023 | G1: 2024 | H1: 2025 | I1: 2026 | J1: 2027 | K1: 2028 | L1: 2029 | M1: 2030 | N1: 2031 | O1: 2032 | P1: 2033 | Q1: 2034 | R1: 2035 | S1: 2036 | T1: 2037 | U1: 2038 | V1: 2039 | W1: 2040 | X1: 2041 | Y1: 2042 | Z1: 2043 | AA1: 2044 | AB1: 2045 | AC1: 2046 | AD1: 2047 | AE1: 2048 | AF1: 2049 | AG1: 2050
A2: hard coal | B2: 3.6256792 | C2: 3.6256792 | D2: 7.1681929 | E2: 3.6256792 | F2: 3.6256792 | G2: 3.6256792 | H2: 3.6256792 | I2: 3.6256792 | J2: 3.6256792 | K2: 3.6256792 | L2: 3.6256792 | M2: 3.6256792 | N2: 3.6256792 | O2: 3.6256792 | P2: 3.6256792 | Q2: 3.6256792 | R2: 3.6256792 | S2: 3.6256792 | T2: 3.6256792 | U2: 3.6256792 | V2: 3.6256792 | W2: 3.6256792 | X2: 3.6256792 | Y2: 3.6256792 | Z2: 3.6256792 | AA2: 3.6256792 | AB2: 3.6256792 | AC2: 3.6256792 | AD2: 3.6256792 | AE2: 3.6256792 | AF2: 3.6256792 | AG2: 3.6256792
A3: natural gas steam turbine | B3: 39.450873 | C3: 2.2058058 | D3: 2.2124868 | E3: 2.2058058 | F3: 2.2058058 | G3: 2.2058058 | H3: 2.2058058 | I3: 2.2058058 | J3: 2.2058058 | K3: 2.2058058 | L3: 2.2058058 | M3: 2.2058058 | N3: 2.2058058 | O3: 2.2058058 | P3: 2.2058058 | Q3: 2.2058058 | R3: 2.2058058 | S3: 2.2058058 | T3: 2.2058058 | U3: 2.2058058 | V3: 2.2058058 | W3: 2.2058058 | X3: 2.2058058 | Y3: 2.2058058 | Z3: 2.2058058 | AA3: 2.2058058 | AB3: 2.2058058 | AC3: 2.2058058 | AD3: 2.2058058 | AE3: 2.2058058 | AF3: 2.2058058 | AG3: 2.2058058
A4: natural gas combined cycle | B4: 2.1561187 | C4: 1.7590301 | D4: 1.6607161 | E4: 1.7590301 | F4: 1.7590301 | G4: 1.7590301 | H4: 1.7590301 | I4: 1.7590301 | J4: 1.7590301 | K4: 1.7590301 | L4: 1.7590301 | M4: 1.7590301 | N4: 1.7590301 | O4: 1.7590301 | P4: 1.7590301 | Q4: 1.7590301 | R4: 1.7590301 | S4: 1.7590301 | T4: 1.7590301 | U4: 1.7590301 | V4: 1.7590301 | W4: 1.7590301 | X4: 1.7590301 | Y4: 1.7590301 | Z4: 1.7590301 | AA4: 1.7590301 | AB4: 1.7590301 | AC4: 1.7590301 | AD4: 1.7590301 | AE4: 1.7590301 | AF4: 1.7590301 | AG4: 1.7590301
A5: nuclear | B5: 0.15598967 | C5: 0.15598967 | D5: 2.0928412 | E5: 0.15598967 | F5: 0.15598967 | G5: 0.15598967 | H5: 0.15598967 | I5: 0.15598967 | J5: 0.15598967 | K5: 0.15598967 | L5: 0.15598967 | M5: 0.15598967 | N5: 0.15598967 | O5: 0.15598967 | P5: 0.15598967 | Q5: 0.15598967 | R5: 0.15598967 | S5: 0.15598967 | T5: 0.15598967 | U5: 0.15598967 | V5: 0.15598967 | W5: 0.15598967 | X5: 0.15598967 | Y5: 0.15598967 | Z5: 0.15598967 | AA5: 0.15598967 | AB5: 0.15598967 | AC5: 0.15598967 | AD5: 0.15598967 | AE5: 0.15598967 | AF5: 0.15598967 | AG5: 0.15598967
A6: hydro | B6: 0 | C6: 0 | D6: 0 | E6: 0 | F6: 0 | G6: 0 | H6: 0 | I6: 0 | J6: 0 | K6: 0 | L6: 0 | M6: 0 | N6: 0 | O6: 0 | P6: 0 | Q6: 0 | R6: 0 | S6: 0 | T6: 0 | U6: 0 | V6: 0 | W6: 0 | X6: 0 | Y6: 0 | Z6: 0 | AA6: 0 | AB6: 0 | AC6: 0 | AD6: 0 | AE6: 0 | AF6: 0 | AG6: 0
A7: onshore wind | B7: 0 | C7: 0 | D7: 0 | E7: 0 | F7: 0 | G7: 0 | H7: 0 | I7: 0 | J7: 0 | K7: 0 | L7: 0 | M7: 0 | N7: 0 | O7: 0 | P7: 0 | Q7: 0 | R7: 0 | S7: 0 | T7: 0 | U7: 0 | V7: 0 | W7: 0 | X7: 0 | Y7: 0 | Z7: 0 | AA7: 0 | AB7: 0 | AC7: 0 | AD7: 0 | AE7: 0 | AF7: 0 | AG7: 0
A8: solar PV | B8: 0 | C8: 0 | D8: 0 | E8: 0 | F8: 0 | G8: 0 | H8: 0 | I8: 0 | J8: 0 | K8: 0 | L8: 0 | M8: 0 | N8: 0 | O8: 0 | P8: 0 | Q8: 0 | R8: 0 | S8: 0 | T8: 0 | U8: 0 | V8: 0 | W8: 0 | X8: 0 | Y8: 0 | Z8: 0 | AA8: 0 | AB8: 0 | AC8: 0 | AD8: 0 | AE8: 0 | AF8: 0 | AG8: 0
A9: solar thermal | B9: 0 | C9: 0 | D9: 3.104946 | E9: 0 | F9: 0 | G9: 0 | H9: 0 | I9: 0 | J9: 0 | K9: 0 | L9: 0 | M9: 0 | N9: 0 | O9: 0 | P9: 0 | Q9: 0 | R9: 0 | S9: 0 | T9: 0 | U9: 0 | V9: 0 | W9: 0 | X9: 0 | Y9: 0 | Z9: 0 | AA9: 0 | AB9: 0 | AC9: 0 | AD9: 0 | AE9: 0 | AF9: 0 | AG9: 0
A10: biomass | B10: 6.0733272 | C10: 6.0733272 | D10: 4.2704128 | E10: 6.0733272 | F10: 6.0733272 | G10: 6.0733272 | H10: 6.0733272 | I10: 6.0733272 | J10: 6.0733272 | K10: 6.0733272 | L10: 6.0733272 | M10: 6.0733272 | N10: 6.0733272 | O10: 6.0733272 | P10: 6.0733272 | Q10: 6.0733272 | R10: 6.0733272 | S10: 6.0733272 | T10: 6.0733272 | U10: 6.0733272 | V10: 6.0733272 | W10: 6.0733272 | X10: 6.0733272 | Y10: 6.0733272 | Z10: 6.0733272 | AA10: 6.0733272 | AB10: 6.0733272 | AC10: 6.0733272 | AD10: 6.0733272 | AE10: 6.0733272 | AF10: 6.0733272 | AG10: 6.0733272
A11: geothermal | B11: 0 | C11: 0 | D11: 0 | E11: 0 | F11: 0 | G11: 0 | H11: 0 | I11: 0 | J11: 0 | K11: 0 | L11: 0 | M11: 0 | N11: 0 | O11: 0 | P11: 0 | Q11: 0 | R11: 0 | S11: 0 | T11: 0 | U11: 0 | V11: 0 | W11: 0 | X11: 0 | Y11: 0 | Z11: 0 | AA11: 0 | AB11: 0 | AC11: 0 | AD11: 0 | AE11: 0 | AF11: 0 | AG11: 0
A12: petroleum | B12: 39.450873 | C12: 2.2058058 | D12: 2.2124868 | E12: 2.2058058 | F12: 2.2058058 | G12: 2.2058058 | H12: 2.2058058 | I12: 2.2058058 | J12: 2.2058058 | K12: 2.2058058 | L12: 2.2058058 | M12: 2.2058058 | N12: 2.2058058 | O12: 2.2058058 | P12: 2.2058058 | Q12: 2.2058058 | R12: 2.2058058 | S12: 2.2058058 | T12: 2.2058058 | U12: 2.2058058 | V12: 2.2058058 | W12: 2.2058058 | X12: 2.2058058 | Y12: 2.2058058 | Z12: 2.2058058 | AA12: 2.2058058 | AB12: 2.2058058 | AC12: 2.2058058 | AD12: 2.2058058 | AE12: 2.2058058 | AF12: 2.2058058 | AG12: 2.2058058
... A25: hydrogen combined cycle | B25: 2.1561187 | C25: 1.7590301 | D25: 1.6607161 | E25: 1.7590301 | F25: 1.7590301 | G25: 1.7590301 | H25: 1.7590301 | I25: 1.7590301 | J25: 1.7590301 | K25: 1.7590301 | L25: 1.7590301 | M25: 1.7590301 | N25: 1.7590301 | O25: 1.7590301 | P25: 1.7590301 | Q25: 1.7590301 | R25: 1.7590301 | S25: 1.7590301 | T25: 1.7590301 | U25: 1.7590301 | V25: 1.7590301 | W25: 1.7590301 | X25: 1.7590301 | Y25: 1.7590301 | Z25: 1.7590301 | AA25: 1.7590301 | AB25: 1.7590301 | AC25: 1.7590301 | AD25: 1.7590301 | AE25: 1.7590301 | AF25: 1.7590301 | AG25: 1.7590301

Sheet CCaMC-BSCpUC US
A1: Unit: $/MW | B1: 2021 | C1: 2022 | D1: 2023 | E1: 2024 | F1: 2025 | G1: 2026 | H1: 2027 | I1: 2028 | J1: 2029 | K1: 2030 | L1: 2031 | M1: 2032 | N1: 2033 | O1: 2034 | P1: 2035 | Q1: 2036 | R1: 2037 | S1: 2038 | T1: 2039 | U1: 2040 | V1: 2041 | W1: 2042 | X1: 2043 | Y1: 2044 | Z1: 2045 | AA1: 2046 | AB1: 2047 | AC1: 2048 | AD1: 2049 | AE1: 2050
A2: Hard Coal (NOT USED) | B2: 0 | C2: 0 | D2: 0 | E2: 0 | F2: 0 | G2: 0 | H2: 0 | I2: 0 | J2: 0 | K2: 0 | L2: 0 | M2: 0 | N2: 0 | O2: 0 | P2: 0 | Q2: 0 | R2: 0 | S2: 0 | T2: 0 | U2: 0 | V2: 0 | W2: 0 | X2: 0 | Y2: 0 | Z2: 0 | AA2: 0 | AB2: 0 | AC2: 0 | AD2: 0 | AE2: 0
A3: Natural Gas Steam Turbine (NOT USED) | B3: 0 | C3: 0 | D3: 0 | E3: 0 | F3: 0 | G3: 0 | H3: 0 | I3: 0 | J3: 0 | K3: 0 | L3: 0 | M3: 0 | N3: 0 | O3: 0 | P3: 0 | Q3: 0 | R3: 0 | S3: 0 | T3: 0 | U3: 0 | V3: 0 | W3: 0 | X3: 0 | Y3: 0 | Z3: 0 | AA3: 0 | AB3: 0 | AC3: 0 | AD3: 0 | AE3: 0
A4: Natural Gas Combined Cycle (NOT USED) | B4: 0 | C4: 0 | D4: 0 | E4: 0 | F4: 0 | G4: 0 | H4: 0 | I4: 0 | J4: 0 | K4: 0 | L4: 0 | M4: 0 | N4: 0 | O4: 0 | P4: 0 | Q4: 0 | R4: 0 | S4: 0 | T4: 0 | U4: 0 | V4: 0 | W4: 0 | X4: 0 | Y4: 0 | Z4: 0 | AA4: 0 | AB4: 0 | AC4: 0 | AD4: 0 | AE4: 0
A5: Nuclear (NOT USED) | B5: 0 | C5: 0 | D5: 0 | E5: 0 | F5: 0 | G5: 0 | H5: 0 | I5: 0 | J5: 0 | K5: 0 | L5: 0 | M5: 0 | N5: 0 | O5: 0 | P5: 0 | Q5: 0 | R5: 0 | S5: 0 | T5: 0 | U5: 0 | V5: 0 | W5: 0 | X5: 0 | Y5: 0 | Z5: 0 | AA5: 0 | AB5: 0 | AC5: 0 | AD5: 0 | AE5: 0
A6: Hydro (NOT USED) | B6: 0 | C6: 0 | D6: 0 | E6: 0 | F6: 0 | G6: 0 | H6: 0 | I6: 0 | J6: 0 | K6: 0 | L6: 0 | M6: 0 | N6: 0 | O6: 0 | P6: 0 | Q6: 0 | R6: 0 | S6: 0 | T6: 0 | U6: 0 | V6: 0 | W6: 0 | X6: 0 | Y6: 0 | Z6: 0 | AA6: 0 | AB6: 0 | AC6: 0 | AD6: 0 | AE6: 0
A7: Onshore Wind | B7: 153983.4 | C7: 115487.55 | D7: 76991.702 | E7: 38495.851 | F7: 0 | G7: 0 | H7: 0 | I7: 0 | J7: 0 | K7: 0 | L7: 0 | M7: 0 | N7: 0 | O7: 0 | P7: 0 | Q7: 0 | R7: 0 | S7: 0 | T7: 0 | U7: 0 | V7: 0 | W7: 0 | X7: 0 | Y7: 0 | Z7: 0 | AA7: 0 | AB7: 0 | AC7: 0 | AD7: 0 | AE7: 0
A8: Solar PV | B8: 557789.8 | C8: 557789.8 | D8: 557789.8 | E8: 557789.8 | F8: 557789.8 | G8: 533728.28 | H8: 509666.75 | I8: 485605.23 | J8: 461543.71 | K8: 437482.19 | L8: 404671.03 | M8: 371859.86 | N8: 339048.7 | O8: 306237.53 | P8: 273426.37 | Q8: 268322.41 | R8: 263218.45 | S8: 258114.49 | T8: 253010.53 | U8: 247906.58 | V8: 242802.62 | W8: 237698.66 | X8: 232594.7 | Y8: 227490.74 | Z8: 222386.78 | AA8: 217282.82 | AB8: 212178.86 | AC8: 207074.9 | AD8: 201970.95 | AE8: 196866.99
A9: Solar Thermal (NOT USED) | B9: 0 | C9: 0 | D9: 0 | E9: 0 | F9: 0 | G9: 0 | H9: 0 | I9: 0 | J9: 0 | K9: 0 | L9: 0 | M9: 0 | N9: 0 | O9: 0 | P9: 0 | Q9: 0 | R9: 0 | S9: 0 | T9: 0 | U9: 0 | V9: 0 | W9: 0 | X9: 0 | Y9: 0 | Z9: 0 | AA9: 0 | AB9: 0 | AC9: 0 | AD9: 0 | AE9: 0
A10: Biomass (NOT USED) | B10: 0 | C10: 0 | D10: 0 | E10: 0 | F10: 0 | G10: 0 | H10: 0 | I10: 0 | J10: 0 | K10: 0 | L10: 0 | M10: 0 | N10: 0 | O10: 0 | P10: 0 | Q10: 0 | R10: 0 | S10: 0 | T10: 0 | U10: 0 | V10: 0 | W10: 0 | X10: 0 | Y10: 0 | Z10: 0 | AA10: 0 | AB10: 0 | AC10: 0 | AD10: 0 | AE10: 0
A11: Geothermal (NOT USED) | B11: 0 | C11: 0 | D11: 0 | E11: 0 | F11: 0 | G11: 0 | H11: 0 | I11: 0 | J11: 0 | K11: 0 | L11: 0 | M11: 0 | N11: 0 | O11: 0 | P11: 0 | Q11: 0 | R11: 0 | S11: 0 | T11: 0 | U11: 0 | V11: 0 | W11: 0 | X11: 0 | Y11: 0 | Z11: 0 | AA11: 0 | AB11: 0 | AC11: 0 | AD11: 0 | AE11: 0
A12: Petroleum (NOT USED) | B12: 0 | C12: 0 | D12: 0 | E12: 0 | F12: 0 | G12: 0 | H12: 0 | I12: 0 | J12: 0 | K12: 0 | L12: 0 | M12: 0 | N12: 0 | O12: 0 | P12: 0 | Q12: 0 | R12: 0 | S12: 0 | T12: 0 | U12: 0 | V12: 0 | W12: 0 | X12: 0 | Y12: 0 | Z12: 0 | AA12: 0 | AB12: 0 | AC12: 0 | AD12: 0 | AE12: 0
... A25: hydrogen combined cycle (NOT USED) | B25: 0 | C25: 0 | D25: 0 | E25: 0 | F25: 0 | G25: 0 | H25: 0 | I25: 0 | J25: 0 | K25: 0 | L25: 0 | M25: 0 | N25: 0 | O25: 0 | P25: 0 | Q25: 0 | R25: 0 | S25: 0 | T25: 0 | U25: 0 | V25: 0 | W25: 0 | X25: 0 | Y25: 0 | Z25: 0 | AA25: 0 | AB25: 0 | AC25: 0 | AD25: 0 | AE25: 0

Sheet CCaMC-BCCpUC US
A1: Unit: $/MW | B1: 2021 | C1: 2022 | D1: 2023 | E1: 2024 | F1: 2025 | G1: 2026 | H1: 2027 | I1: 2028 | J1: 2029 | K1: 2030 | L1: 2031 | M1: 2032 | N1: 2033 | O1: 2034 | P1: 2035 | Q1: 2036 | R1: 2037 | S1: 2038 | T1: 2039 | U1: 2040 | V1: 2041 | W1: 2042 | X1: 2043 | Y1: 2044 | Z1: 2045 | AA1: 2046 | AB1: 2047 | AC1: 2048 | AD1: 2049 | AE1: 2050
A2: hard coal | B2: 3007428.5 | C2: 3199718.3 | D2: 3182756.3 | E2: 3165794.2 | F2: 3148832.2 | G2: 3131870.2 | H2: 3114908.1 | I2: 3097946.1 | J2: 3080984.1 | K2: 3064022 | L2: 3047060 | M2: 3030098 | N2: 2996173.9 | O2: 2979211.9 | P2: 2979211.9 | Q2: 2951588 | R2: 2923867.2 | S2: 2896243.3 | T2: 2868522.5 | U2: 2840801.7 | V2: 2813177.8 | W2: 2785457 | X2: 2757833.1 | Y2: 2730112.3 | Z2: 2702391.4 | AA2: 2674767.6 | AB2: 2647046.7 | AC2: 2619422.9 | AD2: 2591702 | AE2: 2564078.2
A3: natural gas steam turbine | B3: 3007428.5 | C3: 3199718.3 | D3: 3182756.3 | E3: 3165794.2 | F3: 3148832.2 | G3: 3131870.2 | H3: 3114908.1 | I3: 3097946.1 | J3: 3080984.1 | K3: 3064022 | L3: 3047060 | M3: 3030098 | N3: 2996173.9 | O3: 2979211.9 | P3: 2979211.9 | Q3: 2951588 | R3: 2923867.2 | S3: 2896243.3 | T3: 2868522.5 | U3: 2840801.7 | V3: 2813177.8 | W3: 2785457 | X3: 2757833.1 | Y3: 2730112.3 | Z3: 2702391.4 | AA3: 2674767.6 | AB3: 2647046.7 | AC3: 2619422.9 | AD3: 2591702 | AE3: 2564078.2
A4: natural gas combined cycle | B4: 1087150.6 | C4: 1205045.3 | D4: 1194379.6 | E4: 1183801.4 | F4: 1173135.7 | G4: 1162557.5 | H4: 1151891.8 | I4: 1141313.6 | J4: 1130647.9 | K4: 1120069.7 | L4: 1109404 | M4: 1098825.8 | N4: 1088160.1 | O4: 1077581.8 | P4: 1066916.2 | Q4: 1058873.2 | R4: 1050830.3 | S4: 1042787.3 | T4: 1034744.3 | U4: 1026701.4 | V4: 1018658.4 | W4: 1010528 | X4: 1002485.1 | Y4: 994442.11 | Z4: 986399.15 | AA4: 978356.19 | AB4: 970313.23 | AC4: 962270.27 | AD4: 954139.89 | AE4: 946096.93
A5: nuclear | B5: 7998667.7 | C5: 7732140.6 | D5: 7465613.5 | E5: 7199086.5 | F5: 6868265.1 | G5: 6741015.3 | H5: 6673383.1 | I5: 6629469 | J5: 6588789.5 | K5: 5975193.7 | L5: 5924123.7 | M5: 5873053.7 | N5: 5821983.6 | O5: 5770913.6 | P5: 5719843.6 | Q5: 5566633.5 | R5: 5413423.4 | S5: 5260213.3 | T5: 5107003.2 | U5: 4953793.1 | V5: 4851653 | W5: 4749513 | X5: 4647372.9 | Y5: 4545232.8 | Z5: 4443092.8 | AA5: 4340952.7 | AB5: 4238812.6 | AC5: 4136672.6 | AD5: 4034532.5 | AE5: 3932392.5
A6: hydro | B6: 11194179 | C6: 11171208 | D6: 11171208 | E6: 11171208 | F6: 11171208 | G6: 10756160 | H6: 10341948 | I6: 9927735.5 | J6: 9512688 | K6: 14484907 | L6: 13821833 | M6: 13158759 | N6: 12496520 | O6: 11833446 | P6: 11171208 | Q6: 11171208 | R6: 11171208 | S6: 11171208 | T6: 11171208 | U6: 11171208 | V6: 11171208 | W6: 11171208 | X6: 11171208 | Y6: 11171208 | Z6: 11171208 | AA6: 11171208 | AB6: 11171208 | AC6: 11171208 | AD6: 11171208 | AE6: 11171208
A7: onshore wind | B7: 1154875.5 | C7: 1223688.5 | D7: 1318244.4 | E7: 0 | F7: 0 | G7: 0 | H7: 0 | I7: 0 | J7: 0 | K7: 0 | L7: 0 | M7: 0 | N7: 0 | O7: 0 | P7: 0 | Q7: 0 | R7: 0 | S7: 0 | T7: 0 | U7: 0 | V7: 0 | W7: 0 | X7: 0 | Y7: 0 | Z7: 0 | AA7: 0 | AB7: 0 | AC7: 0 | AD7: 0 | AE7: 0
A8: solar PV | B8: 1093705.5 | C8: 1110537.8 | D8: 1165954.2 | E8: 0 | F8: 0 | G8: 0 | H8: 0 | I8: 0 | J8: 0 | K8: 0 | L8: 0 | M8: 0 | N8: 0 | O8: 0 | P8: 0 | Q8: 0 | R8: 0 | S8: 0 | T8: 0 | U8: 0 | V8: 0 | W8: 0 | X8: 0 | Y8: 0 | Z8: 0 | AA8: 0 | AB8: 0 | AC8: 0 | AD8: 0 | AE8: 0
A9: solar thermal | B9: 6146160.4 | C9: 6207145.7 | D9: 5939220.6 | E9: 5671295.4 | F9: 5403370.2 | G9: 5135445.1 | H9: 4867519.9 | I9: 4599594.8 | J9: 4331669.6 | K9: 4063744.4 | L9: 4035313.1 | M9: 4006881.7 | N9: 3978450.3 | O9: 3950018.9 | P9: 3921587.6 | Q9: 3893156.2 | R9: 3864724.8 | S9: 3836293.4 | T9: 3807862.1 | U9: 3779430.7 | V9: 3750999.3 | W9: 3722567.9 | X9: 3694136.6 | Y9: 3665705.2 | Z9: 3637273.8 | AA9: 3608842.4 | AB9: 3580411.1 | AC9: 3551979.7 | AD9: 3523548.3 | AE9: 3495116.9
A10: biomass | B10: 4567459.3 | C10: 4336979.6 | D10: 4190383.3 | E10: 4043787 | F10: 3927136.4 | G10: 3855726.2 | H10: 3817909.2 | I10: 3793348.8 | J10: 3770596.6 | K10: 3748514.2 | L10: 3720135.4 | M10: 3693885.6 | N10: 3671883.2 | O10: 3648867.5 | P10: 3626511.7 | Q10: 3600902.8 | R10: 3575516.4 | S10: 3552281.7 | T10: 3525101 | U10: 3501512 | V10: 3480393.6 | W10: 3455446.9 | X10: 3433404 | Y10: 3409558.7 | Z10: 3384164.2 | AA10: 3359285.3 | AB10: 3335704.6 | AC10: 3310640.5 | AD10: 3284159.3 | AE10: 3244353.7
A11: geothermal | B11: 23925367 | C11: 10524278 | D11: 10094897 | E11: 9725926.2 | F11: 9403155.4 | G11: 9116748.7 | H11: 8859636.2 | I11: 8626577.6 | J11: 8413589.5 | K11: 8217577.5 | L11: 8036094.2 | M11: 7867172.3 | N11: 7709208.9 | O11: 7560881.5 | P11: 7421087.8 | Q11: 7384522.2 | R11: 7348139.5 | S11: 7311938.7 | T11: 7275918.8 | U11: 7240079.1 | V11: 7204418.6 | W11: 7168936.4 | X11: 7133631.6 | Y11: 7098503.3 | Z11: 7063550.6 | AA11: 7028772.7 | AB11: 6994168.7 | AC11: 6959737.8 | AD11: 6925479 | AE11: 6891391.4
A12: petroleum | B12: 949292.13 | C12: 1058173.8 | D12: 1050480.6 | E12: 1042787.3 | F12: 1035094 | G12: 1027400.8 | H12: 1019707.5 | I12: 1012014.2 | J12: 1004408.4 | K12: 996715.12 | L12: 989021.86 | M12: 981328.59 | N12: 973635.32 | O12: 965942.06 | P12: 958248.79 | Q12: 950555.52 | R12: 942949.68 | S12: 935256.41 | T12: 927563.15 | U12: 919869.88 | V12: 912176.62 | W12: 904483.35 | X12: 896790.08 | Y12: 889096.82 | Z12: 881490.97 | AA12: 873797.71 | AB12: 866104.44 | AC12: 858411.17 | AD12: 850717.91 | AE12: 843024.64
... A25: hydrogen combined cycle | B25: 1087150.6 | C25: 1205045.3 | D25: 1194379.6 | E25: 1183801.4 | F25: 1173135.7 | G25: 1162557.5 | H25: 1151891.8 | I25: 1141313.6 | J25: 1130647.9 | K25: 1120069.7 | L25: 1109404 | M25: 1098825.8 | N25: 1088160.1 | O25: 1077581.8 | P25: 1066916.2 | Q25: 1058873.2 | R25: 1050830.3 | S25: 1042787.3 | T25: 1034744.3 | U25: 1026701.4 | V25: 1018658.4 | W25: 1010528 | X25: 1002485.1 | Y25: 994442.11 | Z25: 986399.15 | AA25: 978356.19 | AB25: 970313.23 | AC25: 962270.27 | AD25: 954139.89 | AE25: 946096.93

Sheet CCaMC-BCCUSRCpUC US
A1: Unit: $/MW | B1: 2021 | C1: 2022 | D1: 2023 | E1: 2024 | F1: 2025 | G1: 2026 | H1: 2027 | I1: 2028 | J1: 2029 | K1: 2030 | L1: 2031 | M1: 2032 | N1: 2033 | O1: 2034 | P1: 2035 | Q1: 2036 | R1: 2037 | S1: 2038 | T1: 2039 | U1: 2040 | V1: 2041 | W1: 2042 | X1: 2043 | Y1: 2044 | Z1: 2045 | AA1: 2046 | AB1: 2047 | AC1: 2048 | AD1: 2049 | AE1: 2050
A2: Hard Coal (NOT USED) | B2: 99999 | C2: 99999 | D2: 99999 | E2: 99999 | F2: 99999 | G2: 99999 | H2: 99999 | I2: 99999 | J2: 99999 | K2: 99999 | L2: 99999 | M2: 99999 | N2: 99999 | O2: 99999 | P2: 99999 | Q2: 99999 | R2: 99999 | S2: 99999 | T2: 99999 | U2: 99999 | V2: 99999 | W2: 99999 | X2: 99999 | Y2: 99999 | Z2: 99999 | AA2: 99999 | AB2: 99999 | AC2: 99999 | AD2: 99999 | AE2: 99999
A3: Natural Gas Steam Turbine (NOT USED) | B3: 99999 | C3: 99999 | D3: 99999 | E3: 99999 | F3: 99999 | G3: 99999 | H3: 99999 | I3: 99999 | J3: 99999 | K3: 99999 | L3: 99999 | M3: 99999 | N3: 99999 | O3: 99999 | P3: 99999 | Q3: 99999 | R3: 99999 | S3: 99999 | T3: 99999 | U3: 99999 | V3: 99999 | W3: 99999 | X3: 99999 | Y3: 99999 | Z3: 99999 | AA3: 99999 | AB3: 99999 | AC3: 99999 | AD3: 99999 | AE3: 99999
A4: Natural Gas Combined Cycle (NOT USED) | B4: 99999 | C4: 99999 | D4: 99999 | E4: 99999 | F4: 99999 | G4: 99999 | H4: 99999 | I4: 99999 | J4: 99999 | K4: 99999 | L4: 99999 | M4: 99999 | N4: 99999 | O4: 99999 | P4: 99999 | Q4: 99999 | R4: 99999 | S4: 99999 | T4: 99999 | U4: 99999 | V4: 99999 | W4: 99999 | X4: 99999 | Y4: 99999 | Z4: 99999 | AA4: 99999 | AB4: 99999 | AC4: 99999 | AD4: 99999 | AE4: 99999
A5: Nuclear (NOT USED) | B5: 99999 | C5: 99999 | D5: 99999 | E5: 99999 | F5: 99999 | G5: 99999 | H5: 99999 | I5: 99999 | J5: 99999 | K5: 99999 | L5: 99999 | M5: 99999 | N5: 99999 | O5: 99999 | P5: 99999 | Q5: 99999 | R5: 99999 | S5: 99999 | T5: 99999 | U5: 99999 | V5: 99999 | W5: 99999 | X5: 99999 | Y5: 99999 | Z5: 99999 | AA5: 99999 | AB5: 99999 | AC5: 99999 | AD5: 99999 | AE5: 99999
A6: Hydro (NOT USED) | B6: 99999 | C6: 99999 | D6: 99999 | E6: 99999 | F6: 99999 | G6: 99999 | H6: 99999 | I6: 99999 | J6: 99999 | K6: 99999 | L6: 99999 | M6: 99999 | N6: 99999 | O6: 99999 | P6: 99999 | Q6: 99999 | R6: 99999 | S6: 99999 | T6: 99999 | U6: 99999 | V6: 99999 | W6: 99999 | X6: 99999 | Y6: 99999 | Z6: 99999 | AA6: 99999 | AB6: 99999 | AC6: 99999 | AD6: 99999 | AE6: 99999
A7: Onshore Wind (NOT USED) | B7: 99999 | C7: 99999 | D7: 99999 | E7: 99999 | F7: 99999 | G7: 99999 | H7: 99999 | I7: 99999 | J7: 99999 | K7: 99999 | L7: 99999 | M7: 99999 | N7: 99999 | O7: 99999 | P7: 99999 | Q7: 99999 | R7: 99999 | S7: 99999 | T7: 99999 | U7: 99999 | V7: 99999 | W7: 99999 | X7: 99999 | Y7: 99999 | Z7: 99999 | AA7: 99999 | AB7: 99999 | AC7: 99999 | AD7: 99999 | AE7: 99999
A8: Solar PV (NOT USED) | B8: 99999 | C8: 99999 | D8: 99999 | E8: 99999 | F8: 99999 | G8: 99999 | H8: 99999 | I8: 99999 | J8: 99999 | K8: 99999 | L8: 99999 | M8: 99999 | N8: 99999 | O8: 99999 | P8: 99999 | Q8: 99999 | R8: 99999 | S8: 99999 | T8: 99999 | U8: 99999 | V8: 99999 | W8: 99999 | X8: 99999 | Y8: 99999 | Z8: 99999 | AA8: 99999 | AB8: 99999 | AC8: 99999 | AD8: 99999 | AE8: 99999
A9: Solar Thermal (NOT USED) | B9: 99999 | C9: 99999 | D9: 99999 | E9: 99999 | F9: 99999 | G9: 99999 | H9: 99999 | I9: 99999 | J9: 99999 | K9: 99999 | L9: 99999 | M9: 99999 | N9: 99999 | O9: 99999 | P9: 99999 | Q9: 99999 | R9: 99999 | S9: 99999 | T9: 99999 | U9: 99999 | V9: 99999 | W9: 99999 | X9: 99999 | Y9: 99999 | Z9: 99999 | AA9: 99999 | AB9: 99999 | AC9: 99999 | AD9: 99999 | AE9: 99999
A10: Biomass (NOT USED) | B10: 99999 | C10: 99999 | D10: 99999 | E10: 99999 | F10: 99999 | G10: 99999 | H10: 99999 | I10: 99999 | J10: 99999 | K10: 99999 | L10: 99999 | M10: 99999 | N10: 99999 | O10: 99999 | P10: 99999 | Q10: 99999 | R10: 99999 | S10: 99999 | T10: 99999 | U10: 99999 | V10: 99999 | W10: 99999 | X10: 99999 | Y10: 99999 | Z10: 99999 | AA10: 99999 | AB10: 99999 | AC10: 99999 | AD10: 99999 | AE10: 99999
A11: Geothermal (NOT USED) | B11: 99999 | C11: 99999 | D11: 99999 | E11: 99999 | F11: 99999 | G11: 99999 | H11: 99999 | I11: 99999 | J11: 99999 | K11: 99999 | L11: 99999 | M11: 99999 | N11: 99999 | O11: 99999 | P11: 99999 | Q11: 99999 | R11: 99999 | S11: 99999 | T11: 99999 | U11: 99999 | V11: 99999 | W11: 99999 | X11: 99999 | Y11: 99999 | Z11: 99999 | AA11: 99999 | AB11: 99999 | AC11: 99999 | AD11: 99999 | AE11: 99999
A12: Petroleum (NOT USED) | B12: 99999 | C12: 99999 | D12: 99999 | E12: 99999 | F12: 99999 | G12: 99999 | H12: 99999 | I12: 99999 | J12: 99999 | K12: 99999 | L12: 99999 | M12: 99999 | N12: 99999 | O12: 99999 | P12: 99999 | Q12: 99999 | R12: 99999 | S12: 99999 | T12: 99999 | U12: 99999 | V12: 99999 | W12: 99999 | X12: 99999 | Y12: 99999 | Z12: 99999 | AA12: 99999 | AB12: 99999 | AC12: 99999 | AD12: 99999 | AE12: 99999
... A25: hydrogen combined cycle (NOT USED) | B25: 99999 | C25: 99999 | D25: 99999 | E25: 99999 | F25: 99999 | G25: 99999 | H25: 99999 | I25: 99999 | J25: 99999 | K25: 99999 | L25: 99999 | M25: 99999 | N25: 99999 | O25: 99999 | P25: 99999 | Q25: 99999 | R25: 99999 | S25: 99999 | T25: 99999 | U25: 99999 | V25: 99999 | W25: 99999 | X25: 99999 | Y25: 99999 | Z25: 99999 | AA25: 99999 | AB25: 99999 | AC25: 99999 | AD25: 99999 | AE25: 99999

Sheet CCaMC-ACAPEXpUC
A1: Annual CapEx ($/MW) | B1: Vintage1891 | C1: Vintage1892 | D1: Vintage1893 | E1: Vintage1894 | F1: Vintage1895 | G1: Vintage1896 | H1: Vintage1897 | I1: Vintage1898 | J1: Vintage1899 | K1: Vintage1900 | L1: Vintage1901 | M1: Vintage1902 | N1: Vintage1903 | O1: Vintage1904 | P1: Vintage1905 | Q1: Vintage1906 | R1: Vintage1907 | S1: Vintage1908 | T1: Vintage1909 | U1: Vintage1910 | V1: Vintage1911 | W1: Vintage1912 | X1: Vintage1913 | Y1: Vintage1914 | Z1: Vintage1915 | AA1: Vintage1916 | AB1: Vintage1917 | AC1: Vintage1918 | AD1: Vintage1919 | AE1: Vintage1920 | AF1: Vintage1921 | AG1: Vintage1922 | AH1: Vintage1923 | AI1: Vintage1924 | AJ1: Vintage1925 | AK1: Vintage1926 | AL1: Vintage1927 | AM1: Vintage1928 | AN1: Vintage1929 | AO1: Vintage1930 | AP1: Vintage1931 | AQ1: Vintage1932 | AR1: Vintage1933 | AS1: Vintage1934 | AT1: Vintage1935 | AU1: Vintage1936 | AV1: Vintage1937 | AW1: Vintage1938 | AX1: Vintage1939 | AY1: Vintage1940 | AZ1: Vintage1941 | BA1: Vintage1942 | BB1: Vintage1943 | BC1: Vintage1944 | BD1: Vintage1945 | BE1: Vintage1946 | BF1: Vintage1947 | BG1: Vintage1948 | BH1: Vintage1949 | BI1: Vintage1950 | BJ1: Vintage1951 | BK1: Vintage1952 | BL1: Vintage1953 | BM1: Vintage1954 | BN1: Vintage1955 | BO1: Vintage1956 | BP1: Vintage1957 | BQ1: Vintage1958 | BR1: Vintage1959 | BS1: Vintage1960 | BT1: Vintage1961 | BU1: Vintage1962 | BV1: Vintage1963 | BW1: Vintage1964 | BX1: Vintage1965 | BY1: Vintage1966 | BZ1: Vintage1967 | CA1: Vintage1968 | CB1: Vintage1969 | CC1: Vintage1970 | CD1: Vintage1971 | CE1: Vintage1972 | CF1: Vintage1973 | CG1: Vintage1974 | CH1: Vintage1975 | CI1: Vintage1976 | CJ1: Vintage1977 | CK1: Vintage1978 | CL1: Vintage1979 | CM1: Vintage1980 | CN1: Vintage1981 | CO1: Vintage1982 | CP1: Vintage1983 | CQ1: Vintage1984 | CR1: Vintage1985 | CS1: Vintage1986 | CT1: Vintage1987 | CU1: Vintage1988 | CV1: Vintage1989 | CW1: Vintage1990 | CX1: Vintage1991 | CY1: Vintage1992 | CZ1: Vintage1993 | DA1: Vintage1994 | DB1: Vintage1995 | DC1: Vintage1996 | DD1: Vintage1997 | DE1: Vintage1998 | DF1: Vintage1999 | DG1: Vintage2000 | DH1: Vintage2001 | DI1: Vintage2002 | DJ1: Vintage2003 | DK1: Vintage2004 | DL1: Vintage2005 | DM1: Vintage2006 | DN1: Vintage2007 | DO1: Vintage2008 | DP1: Vintage2009 | DQ1: Vintage2010 | DR1: Vintage2011 | DS1: Vintage2012 | DT1: Vintage2013 | DU1: Vintage2014 | DV1: Vintage2015 | DW1: Vintage2016 | DX1: Vintage2017 | DY1: Vintage2018 | DZ1: Vintage2019 | EA1: Vintage2020 | EB1: Vintage2021 | EC1: Vintage2022 | ED1: Vintage2023 | EE1: Vintage2024 | EF1: Vintage2025 | EG1: Vintage2026 | EH1: Vintage2027 | EI1: Vintage2028 | EJ1: Vintage2029 | EK1: Vintage2030 | EL1: Vintage2031 | EM1: Vintage2032 | EN1: Vintage2033 | EO1: Vintage2034 | EP1: Vintage2035 | EQ1: Vintage2036 | ER1: Vintage2037 | ES1: Vintage2038 | ET1: Vintage2039 | EU1: Vintage2040 | EV1: Vintage2041 | EW1: Vintage2042 | EX1: Vintage2043 | EY1: Vintage2044 | EZ1: Vintage2045 | FA1: Vintage2046 | FB1: Vintage2047 | FC1: Vintage2048 | FD1: Vintage2049 | FE1: Vintage2050 | FF1: Vintage2051 | FG1: Vintage2052 | FH1: Vintage2053 | FI1: Vintage2054 | FJ1: Vintage2055 | FK1: Vintage2056 | FL1: Vintage2057 | FM1: Vintage2058 | FN1: Vintage2059 | FO1: Vintage2060 | FP1: Vintage2061 | FQ1: Vintage2062 | FR1: Vintage2063 | FS1: Vintage2064 | FT1: Vintage2065 | FU1: Vintage2066 | FV1: Vintage2067 | FW1: Vintage2068 | FX1: Vintage2069 | FY1: Vintage2070 | FZ1: Vintage2071 | GA1: Vintage2072 | GB1: Vintage2073 | GC1: Vintage2074 | GD1: Vintage2075 | GE1: Vintage2076 | GF1: Vintage2077 | GG1: Vintage2078 | GH1: Vintage2079 | GI1: Vintage2080 | GJ1: Vintage2081 | GK1: Vintage2082 | GL1: Vintage2083 | GM1: Vintage2084 | GN1: Vintage2085 | GO1: Vintage2086 | GP1: Vintage2087 | GQ1: Vintage2088 | GR1: Vintage2089 | GS1: Vintage2090 | GT1: Vintage2091 | GU1: Vintage2092 | GV1: Vintage2093 | GW1: Vintage2094 | GX1: Vintage2095 | GY1: Vintage2096 | GZ1: Vintage2097 | HA1: Vintage2098 | HB1: Vintage2099 | HC1: Vintage2100
A2: hard coal | B2: =C2 -> 11071.433 | C2: =D2 -> 11071.433 | D2: =E2 -> 11071.433 | E2: =F2 -> 11071.433 | F2: =G2 -> 11071.433 | G2: =H2 -> 11071.433 | H2: =I2 -> 11071.433 | I2: =J2 -> 11071.433 | ... EA2: =EB2 -> 11071.433 | EB2: ='CCaMC-ACAPEXpUC US'!D2/'CCaMC-BCCpUC US'!B2*'CCaMC-BCCpUC'!B2 -> 11071.433 | EC2: =EB2 -> 11071.433 | ED2: =EC2 -> 11071.433 | EE2: =ED2 -> 11071.433 | EF2: =EE2 -> 11071.433 | EG2: =EF2 -> 11071.433 | EH2: =EG2 -> 11071.433 | EI2: =EH2 -> 11071.433 | EJ2: =EI2 -> 11071.433 | ... HC2: =HB2 -> 11071.433
A3: natural gas steam turbine | B3: =C3 -> 6873.9664 | C3: =D3 -> 6873.9664 | D3: =E3 -> 6873.9664 | E3: =F3 -> 6873.9664 | F3: =G3 -> 6873.9664 | G3: =H3 -> 6873.9664 | H3: =I3 -> 6873.9664 | I3: =J3 -> 6873.9664 | ... EA3: =EB3 -> 6873.9664 | EB3: ='CCaMC-ACAPEXpUC US'!D3/'CCaMC-BCCpUC US'!B3*'CCaMC-BCCpUC'!B3 -> 6873.9664 | EC3: =EB3 -> 6873.9664 | ED3: =EC3 -> 6873.9664 | EE3: =ED3 -> 6873.9664 | EF3: =EE3 -> 6873.9664 | EG3: =EF3 -> 6873.9664 | EH3: =EG3 -> 6873.9664 | EI3: =EH3 -> 6873.9664 | EJ3: =EI3 -> 6873.9664 | ... HC3: =HB3 -> 6873.9664
A4: natural gas combined cycle | B4: =C4 -> 0 | C4: =D4 -> 0 | D4: =E4 -> 0 | E4: =F4 -> 0 | F4: =G4 -> 0 | G4: =H4 -> 0 | H4: =I4 -> 0 | I4: =J4 -> 0 | ... EA4: =EB4 -> 0 | EB4: ='CCaMC-ACAPEXpUC US'!D4/'CCaMC-BCCpUC US'!B4*'CCaMC-BCCpUC'!B4 -> 0 | EC4: =EB4 -> 0 | ED4: =EC4 -> 0 | EE4: =ED4 -> 0 | EF4: =EE4 -> 0 | EG4: =EF4 -> 0 | EH4: =EG4 -> 0 | EI4: =EH4 -> 0 | EJ4: =EI4 -> 0 | ... HC4: =HB4 -> 0
A5: nuclear | B5: =C5 -> 29986.816 | C5: =D5 -> 29986.816 | D5: =E5 -> 29986.816 | E5: =F5 -> 29986.816 | F5: =G5 -> 29986.816 | G5: =H5 -> 29986.816 | H5: =I5 -> 29986.816 | I5: =J5 -> 29986.816 | ... EA5: =EB5 -> 29986.816 | EB5: ='CCaMC-ACAPEXpUC US'!D5/'CCaMC-BCCpUC US'!B5*'CCaMC-BCCpUC'!B5 -> 29986.816 | EC5: =EB5 -> 29986.816 | ED5: =EC5 -> 29986.816 | EE5: =ED5 -> 29986.816 | EF5: =EE5 -> 29986.816 | EG5: =EF5 -> 29986.816 | EH5: =EG5 -> 29986.816 | EI5: =EH5 -> 29986.816 | EJ5: =EI5 -> 29986.816 | ... HC5: =HB5 -> 29986.816
A6: hydro | B6: =C6 -> 0 | C6: =D6 -> 0 | D6: =E6 -> 0 | E6: =F6 -> 0 | F6: =G6 -> 0 | G6: =H6 -> 0 | H6: =I6 -> 0 | I6: =J6 -> 0 | ... EA6: =EB6 -> 0 | EB6: ='CCaMC-ACAPEXpUC US'!D6/'CCaMC-BCCpUC US'!B6*'CCaMC-BCCpUC'!B6 -> 0 | EC6: =EB6 -> 0 | ED6: =EC6 -> 0 | EE6: =ED6 -> 0 | EF6: =EE6 -> 0 | EG6: =EF6 -> 0 | EH6: =EG6 -> 0 | EI6: =EH6 -> 0 | EJ6: =EI6 -> 0 | ... HC6: =HB6 -> 0
A7: onshore wind | B7: =C7 -> 9098.6164 | C7: =D7 -> 9098.6164 | D7: =E7 -> 9098.6164 | E7: =F7 -> 9098.6164 | F7: =G7 -> 9098.6164 | G7: =H7 -> 9098.6164 | H7: =I7 -> 9098.6164 | I7: =J7 -> 9098.6164 | ... EA7: =EB7 -> 9098.6164 | EB7: ='CCaMC-ACAPEXpUC US'!D7/'CCaMC-BCCpUC US'!B7*'CCaMC-BCCpUC'!B7 -> 9098.6164 | EC7: =EB7 -> 9098.6164 | ED7: =EC7 -> 9098.6164 | EE7: =ED7 -> 9098.6164 | EF7: =EE7 -> 9098.6164 | EG7: =EF7 -> 9098.6164 | EH7: =EG7 -> 9098.6164 | EI7: =EH7 -> 9098.6164 | EJ7: =EI7 -> 9098.6164 | ... HC7: =HB7 -> 9098.6164
A8: solar PV | B8: =C8 -> 0 | C8: =D8 -> 0 | D8: =E8 -> 0 | E8: =F8 -> 0 | F8: =G8 -> 0 | G8: =H8 -> 0 | H8: =I8 -> 0 | I8: =J8 -> 0 | ... EA8: =EB8 -> 0 | EB8: ='CCaMC-ACAPEXpUC US'!D8/'CCaMC-BCCpUC US'!B8*'CCaMC-BCCpUC'!B8 -> 0 | EC8: =EB8 -> 0 | ED8: =EC8 -> 0 | EE8: =ED8 -> 0 | EF8: =EE8 -> 0 | EG8: =EF8 -> 0 | EH8: =EG8 -> 0 | EI8: =EH8 -> 0 | EJ8: =EI8 -> 0 | ... HC8: =HB8 -> 0
A9: solar thermal | B9: =C9 -> 0 | C9: =D9 -> 0 | D9: =E9 -> 0 | E9: =F9 -> 0 | F9: =G9 -> 0 | G9: =H9 -> 0 | H9: =I9 -> 0 | I9: =J9 -> 0 | ... EA9: =EB9 -> 0 | EB9: ='CCaMC-ACAPEXpUC US'!D9/'CCaMC-BCCpUC US'!B9*'CCaMC-BCCpUC'!B9 -> 0 | EC9: =EB9 -> 0 | ED9: =EC9 -> 0 | EE9: =ED9 -> 0 | EF9: =EE9 -> 0 | EG9: =EF9 -> 0 | EH9: =EG9 -> 0 | EI9: =EH9 -> 0 | EJ9: =EI9 -> 0 | ... HC9: =HB9 -> 0
A10: biomass | B10: =C10 -> 6596.0311 | C10: =D10 -> 6596.0311 | D10: =E10 -> 6596.0311 | E10: =F10 -> 6596.0311 | F10: =G10 -> 6596.0311 | G10: =H10 -> 6596.0311 | H10: =I10 -> 6596.0311 | I10: =J10 -> 6596.0311 | ... EA10: =EB10 -> 6596.0311 | EB10: ='CCaMC-ACAPEXpUC US'!D10/'CCaMC-BCCpUC US'!B10*'CCaMC-BCCpUC'!B10 -> 6596.0311 | EC10: =EB10 -> 6596.0311 | ED10: =EC10 -> 6596.0311 | EE10: =ED10 -> 6596.0311 | EF10: =EE10 -> 6596.0311 | EG10: =EF10 -> 6596.0311 | EH10: =EG10 -> 6596.0311 | EI10: =EH10 -> 6596.0311 | EJ10: =EI10 -> 6596.0311 | ... HC10: =HB10 -> 6596.0311
A11: geothermal | B11: =C11 -> 0 | C11: =D11 -> 0 | D11: =E11 -> 0 | E11: =F11 -> 0 | F11: =G11 -> 0 | G11: =H11 -> 0 | H11: =I11 -> 0 | I11: =J11 -> 0 | ... EA11: =EB11 -> 0 | EB11: ='CCaMC-ACAPEXpUC US'!D11/'CCaMC-BCCpUC US'!B11*'CCaMC-BCCpUC'!B11 -> 0 | EC11: =EB11 -> 0 | ED11: =EC11 -> 0 | EE11: =ED11 -> 0 | EF11: =EE11 -> 0 | EG11: =EF11 -> 0 | EH11: =EG11 -> 0 | EI11: =EH11 -> 0 | EJ11: =EI11 -> 0 | ... HC11: =HB11 -> 0
A12: petroleum | B12: =C12 -> 15735.111 | C12: =D12 -> 15735.111 | D12: =E12 -> 15735.111 | E12: =F12 -> 15735.111 | F12: =G12 -> 15735.111 | G12: =H12 -> 15735.111 | H12: =I12 -> 15735.111 | I12: =J12 -> 15735.111 | ... EA12: =EB12 -> 15735.111 | EB12: ='CCaMC-ACAPEXpUC US'!D12/'CCaMC-BCCpUC US'!B12*'CCaMC-BCCpUC'!B12 -> 15735.111 | EC12: =EB12 -> 15735.111 | ED12: =EC12 -> 15735.111 | EE12: =ED12 -> 15735.111 | EF12: =EE12 -> 15735.111 | EG12: =EF12 -> 15735.111 | EH12: =EG12 -> 15735.111 | EI12: =EH12 -> 15735.111 | EJ12: =EI12 -> 15735.111 | ... HC12: =HB12 -> 15735.111
A13: natural gas peaker | B13: =C13 -> 0 | C13: =D13 -> 0 | D13: =E13 -> 0 | E13: =F13 -> 0 | F13: =G13 -> 0 | G13: =H13 -> 0 | H13: =I13 -> 0 | I13: =J13 -> 0 | ... EA13: =EB13 -> 0 | EB13: ='CCaMC-ACAPEXpUC US'!D13/'CCaMC-BCCpUC US'!B13*'CCaMC-BCCpUC'!B13 -> 0 | EC13: =EB13 -> 0 | ED13: =EC13 -> 0 | EE13: =ED13 -> 0 | EF13: =EE13 -> 0 | EG13: =EF13 -> 0 | EH13: =EG13 -> 0 | EI13: =EH13 -> 0 | EJ13: =EI13 -> 0 | ... HC13: =HB13 -> 0
... A25: hydrogen combined cycle | B25: =C25 -> 0 | C25: =D25 -> 0 | D25: =E25 -> 0 | E25: =F25 -> 0 | F25: =G25 -> 0 | G25: =H25 -> 0 | H25: =I25 -> 0 | I25: =J25 -> 0 | ... EA25: =EB25 -> 0 | EB25: ='CCaMC-ACAPEXpUC US'!D25/'CCaMC-BCCpUC US'!B25*'CCaMC-BCCpUC'!B25 -> 0 | EC25: =EB25 -> 0 | ED25: =EC25 -> 0 | EE25: =ED25 -> 0 | EF25: =EE25 -> 0 | EG25: =EF25 -> 0 | EH25: =EG25 -> 0 | EI25: =EH25 -> 0 | EJ25: =EI25 -> 0 | ... HC25: =HB25 -> 0

Sheet CCaMC-AFOaMCpUC
A1: Fixed O&M ($/MW) | B1: Vintage1891 | C1: Vintage1892 | D1: Vintage1893 | E1: Vintage1894 | F1: Vintage1895 | G1: Vintage1896 | H1: Vintage1897 | I1: Vintage1898 | J1: Vintage1899 | K1: Vintage1900 | L1: Vintage1901 | M1: Vintage1902 | N1: Vintage1903 | O1: Vintage1904 | P1: Vintage1905 | Q1: Vintage1906 | R1: Vintage1907 | S1: Vintage1908 | T1: Vintage1909 | U1: Vintage1910 | V1: Vintage1911 | W1: Vintage1912 | X1: Vintage1913 | Y1: Vintage1914 | Z1: Vintage1915 | AA1: Vintage1916 | AB1: Vintage1917 | AC1: Vintage1918 | AD1: Vintage1919 | AE1: Vintage1920 | AF1: Vintage1921 | AG1: Vintage1922 | AH1: Vintage1923 | AI1: Vintage1924 | AJ1: Vintage1925 | AK1: Vintage1926 | AL1: Vintage1927 | AM1: Vintage1928 | AN1: Vintage1929 | AO1: Vintage1930 | AP1: Vintage1931 | AQ1: Vintage1932 | AR1: Vintage1933 | AS1: Vintage1934 | AT1: Vintage1935 | AU1: Vintage1936 | AV1: Vintage1937 | AW1: Vintage1938 | AX1: Vintage1939 | AY1: Vintage1940 | AZ1: Vintage1941 | BA1: Vintage1942 | BB1: Vintage1943 | BC1: Vintage1944 | BD1: Vintage1945 | BE1: Vintage1946 | BF1: Vintage1947 | BG1: Vintage1948 | BH1: Vintage1949 | BI1: Vintage1950 | BJ1: Vintage1951 | BK1: Vintage1952 | BL1: Vintage1953 | BM1: Vintage1954 | BN1: Vintage1955 | BO1: Vintage1956 | BP1: Vintage1957 | BQ1: Vintage1958 | BR1: Vintage1959 | BS1: Vintage1960 | BT1: Vintage1961 | BU1: Vintage1962 | BV1: Vintage1963 | BW1: Vintage1964 | BX1: Vintage1965 | BY1: Vintage1966 | BZ1: Vintage1967 | CA1: Vintage1968 | CB1: Vintage1969 | CC1: Vintage1970 | CD1: Vintage1971 | CE1: Vintage1972 | CF1: Vintage1973 | CG1: Vintage1974 | CH1: Vintage1975 | CI1: Vintage1976 | CJ1: Vintage1977 | CK1: Vintage1978 | CL1: Vintage1979 | CM1: Vintage1980 | CN1: Vintage1981 | CO1: Vintage1982 | CP1: Vintage1983 | CQ1: Vintage1984 | CR1: Vintage1985 | CS1: Vintage1986 | CT1: Vintage1987 | CU1: Vintage1988 | CV1: Vintage1989 | CW1: Vintage1990 | CX1: Vintage1991 | CY1: Vintage1992 | CZ1: Vintage1993 | DA1: Vintage1994 | DB1: Vintage1995 | DC1: Vintage1996 | DD1: Vintage1997 | DE1: Vintage1998 | DF1: Vintage1999 | DG1: Vintage2000 | DH1: Vintage2001 | DI1: Vintage2002 | DJ1: Vintage2003 | DK1: Vintage2004 | DL1: Vintage2005 | DM1: Vintage2006 | DN1: Vintage2007 | DO1: Vintage2008 | DP1: Vintage2009 | DQ1: Vintage2010 | DR1: Vintage2011 | DS1: Vintage2012 | DT1: Vintage2013 | DU1: Vintage2014 | DV1: Vintage2015 | DW1: Vintage2016 | DX1: Vintage2017 | DY1: Vintage2018 | DZ1: Vintage2019 | EA1: Vintage2020 | EB1: Vintage2021 | EC1: Vintage2022 | ED1: Vintage2023 | EE1: Vintage2024 | EF1: Vintage2025 | EG1: Vintage2026 | EH1: Vintage2027 | EI1: Vintage2028 | EJ1: Vintage2029 | EK1: Vintage2030 | EL1: Vintage2031 | EM1: Vintage2032 | EN1: Vintage2033 | EO1: Vintage2034 | EP1: Vintage2035 | EQ1: Vintage2036 | ER1: Vintage2037 | ES1: Vintage2038 | ET1: Vintage2039 | EU1: Vintage2040 | EV1: Vintage2041 | EW1: Vintage2042 | EX1: Vintage2043 | EY1: Vintage2044 | EZ1: Vintage2045 | FA1: Vintage2046 | FB1: Vintage2047 | FC1: Vintage2048 | FD1: Vintage2049 | FE1: Vintage2050 | FF1: Vintage2051 | FG1: Vintage2052 | FH1: Vintage2053 | FI1: Vintage2054 | FJ1: Vintage2055 | FK1: Vintage2056 | FL1: Vintage2057 | FM1: Vintage2058 | FN1: Vintage2059 | FO1: Vintage2060 | FP1: Vintage2061 | FQ1: Vintage2062 | FR1: Vintage2063 | FS1: Vintage2064 | FT1: Vintage2065 | FU1: Vintage2066 | FV1: Vintage2067 | FW1: Vintage2068 | FX1: Vintage2069 | FY1: Vintage2070 | FZ1: Vintage2071 | GA1: Vintage2072 | GB1: Vintage2073 | GC1: Vintage2074 | GD1: Vintage2075 | GE1: Vintage2076 | GF1: Vintage2077 | GG1: Vintage2078 | GH1: Vintage2079 | GI1: Vintage2080 | GJ1: Vintage2081 | GK1: Vintage2082 | GL1: Vintage2083 | GM1: Vintage2084 | GN1: Vintage2085 | GO1: Vintage2086 | GP1: Vintage2087 | GQ1: Vintage2088 | GR1: Vintage2089 | GS1: Vintage2090 | GT1: Vintage2091 | GU1: Vintage2092 | GV1: Vintage2093 | GW1: Vintage2094 | GX1: Vintage2095 | GY1: Vintage2096 | GZ1: Vintage2097 | HA1: Vintage2098 | HB1: Vintage2099 | HC1: Vintage2100
A2: hard coal | B2: 56505.06 | C2: =D2 -> 62002.388 | D2: =E2 -> 62002.388 | E2: =F2 -> 62002.388 | F2: =G2 -> 62002.388 | G2: =H2 -> 62002.388 | H2: =I2 -> 62002.388 | I2: =J2 -> 62002.388 | J2: =K2 -> 62002.388 | ... DY2: =DZ2 -> 62002.388 | DZ2: =Calculation!B75 -> 62002.388 | EA2: =$DZ2 -> 62002.388 | EB2: =$DZ2 -> 62002.388 | EC2: =$DZ2 -> 62002.388 | ED2: =$DZ2 -> 62002.388 | EE2: =$DZ2 -> 62002.388 | EF2: =$DZ2 -> 62002.388 | EG2: =$DZ2 -> 62002.388 | EH2: =$DZ2 -> 62002.388 | ... HC2: =$DZ2 -> 62002.388
A3: natural gas steam turbine | B3: 37151.996 | C3: =D3 -> 40766.481 | D3: =E3 -> 40766.481 | E3: =F3 -> 40766.481 | F3: =G3 -> 40766.481 | G3: =H3 -> 40766.481 | H3: =I3 -> 40766.481 | I3: =J3 -> 40766.481 | J3: =K3 -> 40766.481 | ... DY3: =DZ3 -> 40766.481 | DZ3: =Calculation!B76 -> 40766.481 | EA3: =$DZ3 -> 40766.481 | EB3: =$DZ3 -> 40766.481 | EC3: =$DZ3 -> 40766.481 | ED3: =$DZ3 -> 40766.481 | EE3: =$DZ3 -> 40766.481 | EF3: =$DZ3 -> 40766.481 | EG3: =$DZ3 -> 40766.481 | EH3: =$DZ3 -> 40766.481 | ... HC3: =$DZ3 -> 40766.481
A4: natural gas combined cycle | B4: 37151.996 | C4: =D4 -> 40766.481 | D4: =E4 -> 40766.481 | E4: =F4 -> 40766.481 | F4: =G4 -> 40766.481 | G4: =H4 -> 40766.481 | H4: =I4 -> 40766.481 | I4: =J4 -> 40766.481 | J4: =K4 -> 40766.481 | ... DY4: =DZ4 -> 40766.481 | DZ4: =Calculation!B76 -> 40766.481 | EA4: =$DZ4 -> 40766.481 | EB4: =$DZ4 -> 40766.481 | EC4: =$DZ4 -> 40766.481 | ED4: =$DZ4 -> 40766.481 | EE4: =$DZ4 -> 40766.481 | EF4: =$DZ4 -> 40766.481 | EG4: =$DZ4 -> 40766.481 | EH4: =$DZ4 -> 40766.481 | ... HC4: =$DZ4 -> 40766.481
A5: nuclear | B5: 141484.67 | C5: =D5 -> 155249.59 | D5: =E5 -> 155249.59 | E5: =F5 -> 155249.59 | F5: =G5 -> 155249.59 | G5: =H5 -> 155249.59 | H5: =I5 -> 155249.59 | I5: =J5 -> 155249.59 | J5: =K5 -> 155249.59 | ... DY5: =DZ5 -> 155249.59 | DZ5: =Calculation!B77 -> 155249.59 | EA5: =$DZ5 -> 155249.59 | EB5: =$DZ5 -> 155249.59 | EC5: =$DZ5 -> 155249.59 | ED5: =$DZ5 -> 155249.59 | EE5: =$DZ5 -> 155249.59 | EF5: =$DZ5 -> 155249.59 | EG5: =$DZ5 -> 155249.59 | EH5: =$DZ5 -> 155249.59 | ... HC5: =$DZ5 -> 155249.59
A6: hydro | B6: 16314.109 | C6: =D6 -> 16314.109 | D6: =E6 -> 16314.109 | E6: =F6 -> 16314.109 | F6: =G6 -> 16314.109 | G6: =H6 -> 16314.109 | H6: =I6 -> 16314.109 | I6: =J6 -> 16314.109 | J6: =K6 -> 16314.109 | ... DY6: =DZ6 -> 16314.109 | DZ6: ='CCaMC-AFOaMCpUC US'!B6 -> 16314.109 | EA6: =$DZ6 -> 16314.109 | EB6: =$DZ6 -> 16314.109 | EC6: =$DZ6 -> 16314.109 | ED6: =$DZ6 -> 16314.109 | EE6: =$DZ6 -> 16314.109 | EF6: =$DZ6 -> 16314.109 | EG6: =$DZ6 -> 16314.109 | EH6: =$DZ6 -> 16314.109 | ... HC6: =$DZ6 -> 16314.109
A7: onshore wind | B7: 43246.885 | C7: =D7 -> 47454.337 | D7: =E7 -> 47454.337 | E7: =F7 -> 47454.337 | F7: =G7 -> 47454.337 | G7: =H7 -> 47454.337 | H7: =I7 -> 47454.337 | I7: =J7 -> 47454.337 | J7: =K7 -> 47454.337 | ... DY7: =DZ7 -> 47454.337 | DZ7: =Calculation!B79 -> 47454.337 | EA7: =$DZ7 -> 47454.337 | EB7: =$DZ7 -> 47454.337 | EC7: =$DZ7 -> 47454.337 | ED7: =$DZ7 -> 47454.337 | EE7: =$DZ7 -> 47454.337 | EF7: =$DZ7 -> 47454.337 | EG7: =$DZ7 -> 47454.337 | EH7: =$DZ7 -> 47454.337 | ... HC7: =$DZ7 -> 47454.337
A8: solar PV | B8: 21078.905 | C8: =D8 -> 23129.653 | D8: =E8 -> 23129.653 | E8: =F8 -> 23129.653 | F8: =G8 -> 23129.653 | G8: =H8 -> 23129.653 | H8: =I8 -> 23129.653 | I8: =J8 -> 23129.653 | J8: =K8 -> 23129.653 | ... DY8: =DZ8 -> 23129.653 | DZ8: =Calculation!B80 -> 23129.653 | EA8: =$DZ8 -> 23129.653 | EB8: =$DZ8 -> 23129.653 | EC8: =$DZ8 -> 23129.653 | ED8: =$DZ8 -> 23129.653 | EE8: =$DZ8 -> 23129.653 | EF8: =$DZ8 -> 23129.653 | EG8: =$DZ8 -> 23129.653 | EH8: =$DZ8 -> 23129.653 | ... HC8: =$DZ8 -> 23129.653
A9: solar thermal | B9: 77455.969 | C9: =D9 -> 77455.969 | D9: =E9 -> 77455.969 | E9: =F9 -> 77455.969 | F9: =G9 -> 77455.969 | G9: =H9 -> 77455.969 | H9: =I9 -> 77455.969 | I9: =J9 -> 77455.969 | J9: =K9 -> 77455.969 | ... DY9: =DZ9 -> 77455.969 | DZ9: ='CCaMC-AFOaMCpUC US'!B9 -> 77455.969 | EA9: =$DZ9 -> 77455.969 | EB9: =$DZ9 -> 77455.969 | EC9: =$DZ9 -> 77455.969 | ED9: =$DZ9 -> 77455.969 | EE9: =$DZ9 -> 77455.969 | EF9: =$DZ9 -> 77455.969 | EG9: =$DZ9 -> 77455.969 | EH9: =$DZ9 -> 77455.969 | ... HC9: =$DZ9 -> 77455.969
A10: biomass | B10: 81009.694 | C10: =D10 -> 88891.056 | D10: =E10 -> 88891.056 | E10: =F10 -> 88891.056 | F10: =G10 -> 88891.056 | G10: =H10 -> 88891.056 | H10: =I10 -> 88891.056 | I10: =J10 -> 88891.056 | J10: =K10 -> 88891.056 | ... DY10: =DZ10 -> 88891.056 | DZ10: =Calculation!B82 -> 88891.056 | EA10: =$DZ10 -> 88891.056 | EB10: =$DZ10 -> 88891.056 | EC10: =$DZ10 -> 88891.056 | ED10: =$DZ10 -> 88891.056 | EE10: =$DZ10 -> 88891.056 | EF10: =$DZ10 -> 88891.056 | EG10: =$DZ10 -> 88891.056 | EH10: =$DZ10 -> 88891.056 | ... HC10: =$DZ10 -> 88891.056
A11: geothermal | B11: 152401.1 | C11: =D11 -> 152401.1 | D11: =E11 -> 152401.1 | E11: =F11 -> 152401.1 | F11: =G11 -> 152401.1 | G11: =H11 -> 152401.1 | H11: =I11 -> 152401.1 | I11: =J11 -> 152401.1 | J11: =K11 -> 152401.1 | ... DY11: =DZ11 -> 152401.1 | DZ11: ='CCaMC-AFOaMCpUC US'!B11 -> 152401.1 | EA11: =$DZ11 -> 152401.1 | EB11: =$DZ11 -> 152401.1 | EC11: =$DZ11 -> 152401.1 | ED11: =$DZ11 -> 152401.1 | EE11: =$DZ11 -> 152401.1 | EF11: =$DZ11 -> 152401.1 | EG11: =$DZ11 -> 152401.1 | EH11: =$DZ11 -> 152401.1 | ... HC11: =$DZ11 -> 152401.1
A12: petroleum | B12: 7973.6811 | C12: =D12 -> 7973.6811 | D12: =E12 -> 7973.6811 | E12: =F12 -> 7973.6811 | F12: =G12 -> 7973.6811 | G12: =H12 -> 7973.6811 | H12: =I12 -> 7973.6811 | I12: =J12 -> 7973.6811 | J12: =K12 -> 7973.6811 | ... DY12: =DZ12 -> 7973.6811 | DZ12: ='CCaMC-AFOaMCpUC US'!B12 -> 7973.6811 | EA12: =$DZ12 -> 7973.6811 | EB12: =$DZ12 -> 7973.6811 | EC12: =$DZ12 -> 7973.6811 | ED12: =$DZ12 -> 7973.6811 | EE12: =$DZ12 -> 7973.6811 | EF12: =$DZ12 -> 7973.6811 | EG12: =$DZ12 -> 7973.6811 | EH12: =$DZ12 -> 7973.6811 | ... HC12: =$DZ12 -> 7973.6811
A13: natural gas peaker | B13: 7144.2571 | C13: =D13 -> 7144.2571 | D13: =E13 -> 7144.2571 | E13: =F13 -> 7144.2571 | F13: =G13 -> 7144.2571 | G13: =H13 -> 7144.2571 | H13: =I13 -> 7144.2571 | I13: =J13 -> 7144.2571 | J13: =K13 -> 7144.2571 | ... DY13: =DZ13 -> 7144.2571 | DZ13: ='CCaMC-AFOaMCpUC US'!B13 -> 7144.2571 | EA13: =$DZ13 -> 7144.2571 | EB13: =$DZ13 -> 7144.2571 | EC13: =$DZ13 -> 7144.2571 | ED13: =$DZ13 -> 7144.2571 | EE13: =$DZ13 -> 7144.2571 | EF13: =$DZ13 -> 7144.2571 | EG13: =$DZ13 -> 7144.2571 | EH13: =$DZ13 -> 7144.2571 | ... HC13: =$DZ13 -> 7144.2571
A14: lignite | B14: 56505.06 | C14: =D14 -> 62002.388 | D14: =E14 -> 62002.388 | E14: =F14 -> 62002.388 | F14: =G14 -> 62002.388 | G14: =H14 -> 62002.388 | H14: =I14 -> 62002.388 | I14: =J14 -> 62002.388 | J14: =K14 -> 62002.388 | ... DY14: =DZ14 -> 62002.388 | DZ14: =Calculation!B86 -> 62002.388 | EA14: =$DZ14 -> 62002.388 | EB14: =$DZ14 -> 62002.388 | EC14: =$DZ14 -> 62002.388 | ED14: =$DZ14 -> 62002.388 | EE14: =$DZ14 -> 62002.388 | EF14: =$DZ14 -> 62002.388 | EG14: =$DZ14 -> 62002.388 | EH14: =$DZ14 -> 62002.388 | ... HC14: =$DZ14 -> 62002.388
A15: offshore wind | B15: 107112.17 | C15: =D15 -> 107112.17 | D15: =E15 -> 107112.17 | E15: =F15 -> 107112.17 | F15: =G15 -> 107112.17 | G15: =H15 -> 107112.17 | H15: =I15 -> 107112.17 | I15: =J15 -> 107112.17 | J15: =K15 -> 107112.17 | ... DY15: =DZ15 -> 107112.17 | DZ15: ='CCaMC-AFOaMCpUC US'!B15 -> 107112.17 | EA15: =$DZ15 -> 107112.17 | EB15: =$DZ15 -> 107112.17 | EC15: =$DZ15 -> 107112.17 | ED15: =$DZ15 -> 107112.17 | EE15: =$DZ15 -> 107112.17 | EF15: =$DZ15 -> 107112.17 | EG15: =$DZ15 -> 107112.17 | EH15: =$DZ15 -> 107112.17 | ... HC15: =$DZ15 -> 107112.17
A16: crude oil | B16: 7973.6811 | C16: =D16 -> 7973.6811 | D16: =E16 -> 7973.6811 | E16: =F16 -> 7973.6811 | F16: =G16 -> 7973.6811 | G16: =H16 -> 7973.6811 | H16: =I16 -> 7973.6811 | I16: =J16 -> 7973.6811 | J16: =K16 -> 7973.6811 | ... DY16: =DZ16 -> 7973.6811 | DZ16: ='CCaMC-AFOaMCpUC US'!B16 -> 7973.6811 | EA16: =$DZ16 -> 7973.6811 | EB16: =$DZ16 -> 7973.6811 | EC16: =$DZ16 -> 7973.6811 | ED16: =$DZ16 -> 7973.6811 | EE16: =$DZ16 -> 7973.6811 | EF16: =$DZ16 -> 7973.6811 | EG16: =$DZ16 -> 7973.6811 | EH16: =$DZ16 -> 7973.6811 | ... HC16: =$DZ16 -> 7973.6811
A17: heavy or residual fuel oil | B17: 7973.6811 | C17: =D17 -> 7973.6811 | D17: =E17 -> 7973.6811 | E17: =F17 -> 7973.6811 | F17: =G17 -> 7973.6811 | G17: =H17 -> 7973.6811 | H17: =I17 -> 7973.6811 | I17: =J17 -> 7973.6811 | J17: =K17 -> 7973.6811 | ... DY17: =DZ17 -> 7973.6811 | DZ17: ='CCaMC-AFOaMCpUC US'!B17 -> 7973.6811 | EA17: =$DZ17 -> 7973.6811 | EB17: =$DZ17 -> 7973.6811 | EC17: =$DZ17 -> 7973.6811 | ED17: =$DZ17 -> 7973.6811 | EE17: =$DZ17 -> 7973.6811 | EF17: =$DZ17 -> 7973.6811 | EG17: =$DZ17 -> 7973.6811 | EH17: =$DZ17 -> 7973.6811 | ... HC17: =$DZ17 -> 7973.6811
A18: municipal solid waste | B18: 453528.99 | C18: =D18 -> 453528.99 | D18: =E18 -> 453528.99 | E18: =F18 -> 453528.99 | F18: =G18 -> 453528.99 | G18: =H18 -> 453528.99 | H18: =I18 -> 453528.99 | I18: =J18 -> 453528.99 | J18: =K18 -> 453528.99 | ... DY18: =DZ18 -> 453528.99 | DZ18: ='CCaMC-AFOaMCpUC US'!B18 -> 453528.99 | EA18: =$DZ18 -> 453528.99 | EB18: =$DZ18 -> 453528.99 | EC18: =$DZ18 -> 453528.99 | ED18: =$DZ18 -> 453528.99 | EE18: =$DZ18 -> 453528.99 | EF18: =$DZ18 -> 453528.99 | EG18: =$DZ18 -> 453528.99 | EH18: =$DZ18 -> 453528.99 | ... HC18: =$DZ18 -> 453528.99
A19: hard coal w CCS | B19: 105574.09 | C19: =D19 -> 105574.09 | D19: =E19 -> 105574.09 | E19: =F19 -> 105574.09 | F19: =G19 -> 105574.09 | G19: =H19 -> 105574.09 | H19: =I19 -> 105574.09 | I19: =J19 -> 105574.09 | J19: =K19 -> 105574.09 | ... DY19: =DZ19 -> 105574.09 | DZ19: ='CCaMC-AFOaMCpUC US'!B19 -> 105574.09 | EA19: =$DZ19 -> 105574.09 | EB19: =$DZ19 -> 105574.09 | EC19: =$DZ19 -> 105574.09 | ED19: =$DZ19 -> 105574.09 | EE19: =$DZ19 -> 105574.09 | EF19: =$DZ19 -> 105574.09 | EG19: =$DZ19 -> 105574.09 | EH19: =$DZ19 -> 105574.09 | ... HC19: =$DZ19 -> 105574.09
A20: natural gas combined cycle w CCS | B20: 50922.978 | C20: =D20 -> 50922.978 | D20: =E20 -> 50922.978 | E20: =F20 -> 50922.978 | F20: =G20 -> 50922.978 | G20: =H20 -> 50922.978 | H20: =I20 -> 50922.978 | I20: =J20 -> 50922.978 | J20: =K20 -> 50922.978 | ... DY20: =DZ20 -> 50922.978 | DZ20: ='CCaMC-AFOaMCpUC US'!B20 -> 50922.978 | EA20: =$DZ20 -> 50922.978 | EB20: =$DZ20 -> 50922.978 | EC20: =$DZ20 -> 50922.978 | ED20: =$DZ20 -> 50922.978 | EE20: =$DZ20 -> 50922.978 | EF20: =$DZ20 -> 50922.978 | EG20: =$DZ20 -> 50922.978 | EH20: =$DZ20 -> 50922.978 | ... HC20: =$DZ20 -> 50922.978
A21: biomass w CCS | B21: 170571.91 | C21: =D21 -> 170571.91 | D21: =E21 -> 170571.91 | E21: =F21 -> 170571.91 | F21: =G21 -> 170571.91 | G21: =H21 -> 170571.91 | H21: =I21 -> 170571.91 | I21: =J21 -> 170571.91 | J21: =K21 -> 170571.91 | ... DY21: =DZ21 -> 170571.91 | DZ21: ='CCaMC-AFOaMCpUC US'!B21 -> 170571.91 | EA21: =$DZ21 -> 170571.91 | EB21: =$DZ21 -> 170571.91 | EC21: =$DZ21 -> 170571.91 | ED21: =$DZ21 -> 170571.91 | EE21: =$DZ21 -> 170571.91 | EF21: =$DZ21 -> 170571.91 | EG21: =$DZ21 -> 170571.91 | EH21: =$DZ21 -> 170571.91 | ... HC21: =$DZ21 -> 170571.91
A22: lignite w CCS | B22: 105574.09 | C22: =D22 -> 105574.09 | D22: =E22 -> 105574.09 | E22: =F22 -> 105574.09 | F22: =G22 -> 105574.09 | G22: =H22 -> 105574.09 | H22: =I22 -> 105574.09 | I22: =J22 -> 105574.09 | J22: =K22 -> 105574.09 | ... DY22: =DZ22 -> 105574.09 | DZ22: ='CCaMC-AFOaMCpUC US'!B22 -> 105574.09 | EA22: =$DZ22 -> 105574.09 | EB22: =$DZ22 -> 105574.09 | EC22: =$DZ22 -> 105574.09 | ED22: =$DZ22 -> 105574.09 | EE22: =$DZ22 -> 105574.09 | EF22: =$DZ22 -> 105574.09 | EG22: =$DZ22 -> 105574.09 | EH22: =$DZ22 -> 105574.09 | ... HC22: =$DZ22 -> 105574.09
A23: small modular reactor | B23: 100659.73 | C23: =D23 -> 100659.73 | D23: =E23 -> 100659.73 | E23: =F23 -> 100659.73 | F23: =G23 -> 100659.73 | G23: =H23 -> 100659.73 | H23: =I23 -> 100659.73 | I23: =J23 -> 100659.73 | J23: =K23 -> 100659.73 | ... DY23: =DZ23 -> 100659.73 | DZ23: ='CCaMC-AFOaMCpUC US'!B23 -> 100659.73 | EA23: =$DZ23 -> 100659.73 | EB23: =$DZ23 -> 100659.73 | EC23: =$DZ23 -> 100659.73 | ED23: =$DZ23 -> 100659.73 | EE23: =$DZ23 -> 100659.73 | EF23: =$DZ23 -> 100659.73 | EG23: =$DZ23 -> 100659.73 | EH23: =$DZ23 -> 100659.73 | ... HC23: =$DZ23 -> 100659.73
A24: hydrogen combustion turbine | B24: 7144.2571 | C24: =D24 -> 7144.2571 | D24: =E24 -> 7144.2571 | E24: =F24 -> 7144.2571 | F24: =G24 -> 7144.2571 | G24: =H24 -> 7144.2571 | H24: =I24 -> 7144.2571 | I24: =J24 -> 7144.2571 | J24: =K24 -> 7144.2571 | ... DY24: =DZ24 -> 7144.2571 | DZ24: ='CCaMC-AFOaMCpUC US'!B24 -> 7144.2571 | EA24: =$DZ24 -> 7144.2571 | EB24: =$DZ24 -> 7144.2571 | EC24: =$DZ24 -> 7144.2571 | ED24: =$DZ24 -> 7144.2571 | EE24: =$DZ24 -> 7144.2571 | EF24: =$DZ24 -> 7144.2571 | EG24: =$DZ24 -> 7144.2571 | EH24: =$DZ24 -> 7144.2571 | ... HC24: =$DZ24 -> 7144.2571
A25: hydrogen combined cycle | B25: 8958.6976 | C25: =D25 -> 8958.6976 | D25: =E25 -> 8958.6976 | E25: =F25 -> 8958.6976 | F25: =G25 -> 8958.6976 | G25: =H25 -> 8958.6976 | H25: =I25 -> 8958.6976 | I25: =J25 -> 8958.6976 | J25: =K25 -> 8958.6976 | ... DY25: =DZ25 -> 8958.6976 | DZ25: ='CCaMC-AFOaMCpUC US'!B25 -> 8958.6976 | EA25: =$DZ25 -> 8958.6976 | EB25: =$DZ25 -> 8958.6976 | EC25: =$DZ25 -> 8958.6976 | ED25: =$DZ25 -> 8958.6976 | EE25: =$DZ25 -> 8958.6976 | EF25: =$DZ25 -> 8958.6976 | EG25: =$DZ25 -> 8958.6976 | EH25: =$DZ25 -> 8958.6976 | ... HC25: =$DZ25 -> 8958.6976

Sheet CCaMC-VOaMCpUC
A1: Variable O&M ($/MWh) | B1: Vintage1891 | C1: Vintage1892 | D1: Vintage1893 | E1: Vintage1894 | F1: Vintage1895 | G1: Vintage1896 | H1: Vintage1897 | I1: Vintage1898 | J1: Vintage1899 | K1: Vintage1900 | L1: Vintage1901 | M1: Vintage1902 | N1: Vintage1903 | O1: Vintage1904 | P1: Vintage1905 | Q1: Vintage1906 | R1: Vintage1907 | S1: Vintage1908 | T1: Vintage1909 | U1: Vintage1910 | V1: Vintage1911 | W1: Vintage1912 | X1: Vintage1913 | Y1: Vintage1914 | Z1: Vintage1915 | AA1: Vintage1916 | AB1: Vintage1917 | AC1: Vintage1918 | AD1: Vintage1919 | AE1: Vintage1920 | AF1: Vintage1921 | AG1: Vintage1922 | AH1: Vintage1923 | AI1: Vintage1924 | AJ1: Vintage1925 | AK1: Vintage1926 | AL1: Vintage1927 | AM1: Vintage1928 | AN1: Vintage1929 | AO1: Vintage1930 | AP1: Vintage1931 | AQ1: Vintage1932 | AR1: Vintage1933 | AS1: Vintage1934 | AT1: Vintage1935 | AU1: Vintage1936 | AV1: Vintage1937 | AW1: Vintage1938 | AX1: Vintage1939 | AY1: Vintage1940 | AZ1: Vintage1941 | BA1: Vintage1942 | BB1: Vintage1943 | BC1: Vintage1944 | BD1: Vintage1945 | BE1: Vintage1946 | BF1: Vintage1947 | BG1: Vintage1948 | BH1: Vintage1949 | BI1: Vintage1950 | BJ1: Vintage1951 | BK1: Vintage1952 | BL1: Vintage1953 | BM1: Vintage1954 | BN1: Vintage1955 | BO1: Vintage1956 | BP1: Vintage1957 | BQ1: Vintage1958 | BR1: Vintage1959 | BS1: Vintage1960 | BT1: Vintage1961 | BU1: Vintage1962 | BV1: Vintage1963 | BW1: Vintage1964 | BX1: Vintage1965 | BY1: Vintage1966 | BZ1: Vintage1967 | CA1: Vintage1968 | CB1: Vintage1969 | CC1: Vintage1970 | CD1: Vintage1971 | CE1: Vintage1972 | CF1: Vintage1973 | CG1: Vintage1974 | CH1: Vintage1975 | CI1: Vintage1976 | CJ1: Vintage1977 | CK1: Vintage1978 | CL1: Vintage1979 | CM1: Vintage1980 | CN1: Vintage1981 | CO1: Vintage1982 | CP1: Vintage1983 | CQ1: Vintage1984 | CR1: Vintage1985 | CS1: Vintage1986 | CT1: Vintage1987 | CU1: Vintage1988 | CV1: Vintage1989 | CW1: Vintage1990 | CX1: Vintage1991 | CY1: Vintage1992 | CZ1: Vintage1993 | DA1: Vintage1994 | DB1: Vintage1995 | DC1: Vintage1996 | DD1: Vintage1997 | DE1: Vintage1998 | DF1: Vintage1999 | DG1: Vintage2000 | DH1: Vintage2001 | DI1: Vintage2002 | DJ1: Vintage2003 | DK1: Vintage2004 | DL1: Vintage2005 | DM1: Vintage2006 | DN1: Vintage2007 | DO1: Vintage2008 | DP1: Vintage2009 | DQ1: Vintage2010 | DR1: Vintage2011 | DS1: Vintage2012 | DT1: Vintage2013 | DU1: Vintage2014 | DV1: Vintage2015 | DW1: Vintage2016 | DX1: Vintage2017 | DY1: Vintage2018 | DZ1: Vintage2019 | EA1: Vintage2020 | EB1: Vintage2021 | EC1: Vintage2022 | ED1: Vintage2023 | EE1: Vintage2024 | EF1: Vintage2025 | EG1: Vintage2026 | EH1: Vintage2027 | EI1: Vintage2028 | EJ1: Vintage2029 | EK1: Vintage2030 | EL1: Vintage2031 | EM1: Vintage2032 | EN1: Vintage2033 | EO1: Vintage2034 | EP1: Vintage2035 | EQ1: Vintage2036 | ER1: Vintage2037 | ES1: Vintage2038 | ET1: Vintage2039 | EU1: Vintage2040 | EV1: Vintage2041 | EW1: Vintage2042 | EX1: Vintage2043 | EY1: Vintage2044 | EZ1: Vintage2045 | FA1: Vintage2046 | FB1: Vintage2047 | FC1: Vintage2048 | FD1: Vintage2049 | FE1: Vintage2050 | FF1: Vintage2051 | FG1: Vintage2052 | FH1: Vintage2053 | FI1: Vintage2054 | FJ1: Vintage2055 | FK1: Vintage2056 | FL1: Vintage2057 | FM1: Vintage2058 | FN1: Vintage2059 | FO1: Vintage2060 | FP1: Vintage2061 | FQ1: Vintage2062 | FR1: Vintage2063 | FS1: Vintage2064 | FT1: Vintage2065 | FU1: Vintage2066 | FV1: Vintage2067 | FW1: Vintage2068 | FX1: Vintage2069 | FY1: Vintage2070 | FZ1: Vintage2071 | GA1: Vintage2072 | GB1: Vintage2073 | GC1: Vintage2074 | GD1: Vintage2075 | GE1: Vintage2076 | GF1: Vintage2077 | GG1: Vintage2078 | GH1: Vintage2079 | GI1: Vintage2080 | GJ1: Vintage2081 | GK1: Vintage2082 | GL1: Vintage2083 | GM1: Vintage2084 | GN1: Vintage2085 | GO1: Vintage2086 | GP1: Vintage2087 | GQ1: Vintage2088 | GR1: Vintage2089 | GS1: Vintage2090 | GT1: Vintage2091 | GU1: Vintage2092 | GV1: Vintage2093 | GW1: Vintage2094 | GX1: Vintage2095 | GY1: Vintage2096 | GZ1: Vintage2097 | HA1: Vintage2098 | HB1: Vintage2099 | HC1: Vintage2100
A2: hard coal | B2: =Calculation!B93 -> 1.0973821 | C2: =$B2 -> 1.0973821 | D2: =$B2 -> 1.0973821 | E2: =$B2 -> 1.0973821 | F2: =$B2 -> 1.0973821 | G2: =$B2 -> 1.0973821 | H2: =$B2 -> 1.0973821 | I2: =$B2 -> 1.0973821 | J2: =$B2 -> 1.0973821 | ... HC2: =$B2 -> 1.0973821
A3: natural gas steam turbine | B3: =Calculation!B94 -> 0.59519031 | C3: =$B3 -> 0.59519031 | D3: =$B3 -> 0.59519031 | E3: =$B3 -> 0.59519031 | F3: =$B3 -> 0.59519031 | G3: =$B3 -> 0.59519031 | H3: =$B3 -> 0.59519031 | I3: =$B3 -> 0.59519031 | J3: =$B3 -> 0.59519031 | ... HC3: =$B3 -> 0.59519031
A4: natural gas combined cycle | B4: =Calculation!B94 -> 0.59519031 | C4: =$B4 -> 0.59519031 | D4: =$B4 -> 0.59519031 | E4: =$B4 -> 0.59519031 | F4: =$B4 -> 0.59519031 | G4: =$B4 -> 0.59519031 | H4: =$B4 -> 0.59519031 | I4: =$B4 -> 0.59519031 | J4: =$B4 -> 0.59519031 | ... HC4: =$B4 -> 0.59519031
A5: nuclear | B5: =Calculation!B95 -> 1.8506699 | C5: =$B5 -> 1.8506699 | D5: =$B5 -> 1.8506699 | E5: =$B5 -> 1.8506699 | F5: =$B5 -> 1.8506699 | G5: =$B5 -> 1.8506699 | H5: =$B5 -> 1.8506699 | I5: =$B5 -> 1.8506699 | J5: =$B5 -> 1.8506699 | ... HC5: =$B5 -> 1.8506699
A6: hydro | B6: ='CCaMC-VOaMCpUC US'!B6 -> 0 | C6: =$B6 -> 0 | D6: =$B6 -> 0 | E6: =$B6 -> 0 | F6: =$B6 -> 0 | G6: =$B6 -> 0 | H6: =$B6 -> 0 | I6: =$B6 -> 0 | J6: =$B6 -> 0 | ... HC6: =$B6 -> 0
A7: onshore wind | B7: =Calculation!B97 -> 0.092998486 | C7: =$B7 -> 0.092998486 | D7: =$B7 -> 0.092998486 | E7: =$B7 -> 0.092998486 | F7: =$B7 -> 0.092998486 | G7: =$B7 -> 0.092998486 | H7: =$B7 -> 0.092998486 | I7: =$B7 -> 0.092998486 | J7: =$B7 -> 0.092998486 | ... HC7: =$B7 -> 0.092998486
A8: solar PV | B8: =Calculation!B98 -> 0.092998486 | C8: =$B8 -> 0.092998486 | D8: =$B8 -> 0.092998486 | E8: =$B8 -> 0.092998486 | F8: =$B8 -> 0.092998486 | G8: =$B8 -> 0.092998486 | H8: =$B8 -> 0.092998486 | I8: =$B8 -> 0.092998486 | J8: =$B8 -> 0.092998486 | ... HC8: =$B8 -> 0.092998486
A9: solar thermal | B9: ='CCaMC-VOaMCpUC US'!B9 -> 0 | C9: =$B9 -> 0 | D9: =$B9 -> 0 | E9: =$B9 -> 0 | F9: =$B9 -> 0 | G9: =$B9 -> 0 | H9: =$B9 -> 0 | I9: =$B9 -> 0 | J9: =$B9 -> 0 | ... HC9: =$B9 -> 0
A10: biomass | B10: ='CCaMC-VOaMCpUC US'!B10 -> 6.0733272 | C10: =$B10 -> 6.0733272 | D10: =$B10 -> 6.0733272 | E10: =$B10 -> 6.0733272 | F10: =$B10 -> 6.0733272 | G10: =$B10 -> 6.0733272 | H10: =$B10 -> 6.0733272 | I10: =$B10 -> 6.0733272 | J10: =$B10 -> 6.0733272 | ... HC10: =$B10 -> 6.0733272
A11: geothermal | B11: ='CCaMC-VOaMCpUC US'!B11 -> 0 | C11: =$B11 -> 0 | D11: =$B11 -> 0 | E11: =$B11 -> 0 | F11: =$B11 -> 0 | G11: =$B11 -> 0 | H11: =$B11 -> 0 | I11: =$B11 -> 0 | J11: =$B11 -> 0 | ... HC11: =$B11 -> 0
A12: petroleum | B12: ='CCaMC-VOaMCpUC US'!B12 -> 39.450873 | C12: =$B12 -> 39.450873 | D12: =$B12 -> 39.450873 | E12: =$B12 -> 39.450873 | F12: =$B12 -> 39.450873 | G12: =$B12 -> 39.450873 | H12: =$B12 -> 39.450873 | I12: =$B12 -> 39.450873 | J12: =$B12 -> 39.450873 | ... HC12: =$B12 -> 39.450873
A13: natural gas peaker | B13: ='CCaMC-VOaMCpUC US'!B13 -> 5.9582423 | C13: =$B13 -> 5.9582423 | D13: =$B13 -> 5.9582423 | E13: =$B13 -> 5.9582423 | F13: =$B13 -> 5.9582423 | G13: =$B13 -> 5.9582423 | H13: =$B13 -> 5.9582423 | I13: =$B13 -> 5.9582423 | J13: =$B13 -> 5.9582423 | ... HC13: =$B13 -> 5.9582423
A14: lignite | B14: ='CCaMC-VOaMCpUC US'!B14 -> 6.142327 | C14: =$B14 -> 6.142327 | D14: =$B14 -> 6.142327 | E14: =$B14 -> 6.142327 | F14: =$B14 -> 6.142327 | G14: =$B14 -> 6.142327 | H14: =$B14 -> 6.142327 | I14: =$B14 -> 6.142327 | J14: =$B14 -> 6.142327 | ... HC14: =$B14 -> 6.142327
A15: offshore wind | B15: ='CCaMC-VOaMCpUC US'!B15 -> 0 | C15: =$B15 -> 0 | D15: =$B15 -> 0 | E15: =$B15 -> 0 | F15: =$B15 -> 0 | G15: =$B15 -> 0 | H15: =$B15 -> 0 | I15: =$B15 -> 0 | J15: =$B15 -> 0 | ... HC15: =$B15 -> 0
A16: crude oil | B16: ='CCaMC-VOaMCpUC US'!B16 -> 39.450873 | C16: =$B16 -> 39.450873 | D16: =$B16 -> 39.450873 | E16: =$B16 -> 39.450873 | F16: =$B16 -> 39.450873 | G16: =$B16 -> 39.450873 | H16: =$B16 -> 39.450873 | I16: =$B16 -> 39.450873 | J16: =$B16 -> 39.450873 | ... HC16: =$B16 -> 39.450873
A17: heavy or residual fuel oil | B17: ='CCaMC-VOaMCpUC US'!B17 -> 39.450873 | C17: =$B17 -> 39.450873 | D17: =$B17 -> 39.450873 | E17: =$B17 -> 39.450873 | F17: =$B17 -> 39.450873 | G17: =$B17 -> 39.450873 | H17: =$B17 -> 39.450873 | I17: =$B17 -> 39.450873 | J17: =$B17 -> 39.450873 | ... HC17: =$B17 -> 39.450873
A18: municipal solid waste | B18: ='CCaMC-VOaMCpUC US'!B18 -> 10.101328 | C18: =$B18 -> 10.101328 | D18: =$B18 -> 10.101328 | E18: =$B18 -> 10.101328 | F18: =$B18 -> 10.101328 | G18: =$B18 -> 10.101328 | H18: =$B18 -> 10.101328 | I18: =$B18 -> 10.101328 | J18: =$B18 -> 10.101328 | ... HC18: =$B18 -> 10.101328
A19: hard coal w CCS | B19: ='CCaMC-VOaMCpUC US'!B19 -> 12.751927 | C19: =$B19 -> 12.751927 | D19: =$B19 -> 12.751927 | E19: =$B19 -> 12.751927 | F19: =$B19 -> 12.751927 | G19: =$B19 -> 12.751927 | H19: =$B19 -> 12.751927 | I19: =$B19 -> 12.751927 | J19: =$B19 -> 12.751927 | ... HC19: =$B19 -> 12.751927
A20: natural gas combined cycle w CCS | B20: ='CCaMC-VOaMCpUC US'!B20 -> 3.7959225 | C20: =$B20 -> 3.7959225 | D20: =$B20 -> 3.7959225 | E20: =$B20 -> 3.7959225 | F20: =$B20 -> 3.7959225 | G20: =$B20 -> 3.7959225 | H20: =$B20 -> 3.7959225 | I20: =$B20 -> 3.7959225 | J20: =$B20 -> 3.7959225 | ... HC20: =$B20 -> 3.7959225
... A25: hydrogen combined cycle | B25: ='CCaMC-VOaMCpUC US'!B25 -> 2.1561187 | C25: =$B25 -> 2.1561187 | D25: =$B25 -> 2.1561187 | E25: =$B25 -> 2.1561187 | F25: =$B25 -> 2.1561187 | G25: =$B25 -> 2.1561187 | H25: =$B25 -> 2.1561187 | I25: =$B25 -> 2.1561187 | J25: =$B25 -> 2.1561187 | ... HC25: =$B25 -> 2.1561187

Sheet CCaMC-BCCpUC
A1: Unit: $/MW | B1: 2021 | C1: 2022 | D1: 2023 | E1: 2024 | F1: 2025 | G1: 2026 | H1: 2027 | I1: 2028 | J1: 2029 | K1: 2030 | L1: 2031 | M1: 2032 | N1: 2033 | O1: 2034 | P1: 2035 | Q1: 2036 | R1: 2037 | S1: 2038 | T1: 2039 | U1: 2040 | V1: 2041 | W1: 2042 | X1: 2043 | Y1: 2044 | Z1: 2045 | AA1: 2046 | AB1: 2047 | AC1: 2048 | AD1: 2049 | AE1: 2050
A2: hard coal | B2: =Calculation!C57 -> 1386477.2 | C2: =Calculation!D57 -> 1435207.5 | D2: =Calculation!E57 -> 1483937.8 | E2: =Calculation!F57 -> 1532668.1 | F2: =Calculation!G57 -> 1581398.3 | G2: =Calculation!H57 -> 1630128.6 | H2: =Calculation!I57 -> 1678858.9 | I2: =Calculation!J57 -> 1727589.2 | ... AE2: =Calculation!AF57 -> 2799655.2
A3: natural gas steam turbine | B3: =B4*'CCaMC-BCCpUC US'!B3/'CCaMC-BCCpUC US'!B4 -> 2439851.5 | C3: =C4*'CCaMC-BCCpUC US'!C3/'CCaMC-BCCpUC US'!C4 -> 2362877.9 | D3: =D4*'CCaMC-BCCpUC US'!D3/'CCaMC-BCCpUC US'!D4 -> 2392405.1 | E3: =E4*'CCaMC-BCCpUC US'!E3/'CCaMC-BCCpUC US'!E4 -> 2422059 | F3: =F4*'CCaMC-BCCpUC US'!F3/'CCaMC-BCCpUC US'!F4 -> 2452201.8 | G3: =G4*'CCaMC-BCCpUC US'!G3/'CCaMC-BCCpUC US'!G4 -> 2482480.4 | H3: =H4*'CCaMC-BCCpUC US'!H3/'CCaMC-BCCpUC US'!H4 -> 2513272.9 | I3: =I4*'CCaMC-BCCpUC US'!I3/'CCaMC-BCCpUC US'!I4 -> 2544211.2 | ... AE3: =AE4*'CCaMC-BCCpUC US'!AE3/'CCaMC-BCCpUC US'!AE4 -> 3011587.1
A4: natural gas combined cycle | B4: =Calculation!C58 -> 881978.11 | C4: =Calculation!D58 -> 889882.98 | D4: =Calculation!E58 -> 897787.85 | E4: =Calculation!F58 -> 905692.72 | F4: =Calculation!G58 -> 913597.59 | G4: =Calculation!H58 -> 921502.46 | H4: =Calculation!I58 -> 929407.34 | I4: =Calculation!J58 -> 937312.21 | ... AE4: =Calculation!AF58 -> 1111219.4
A5: nuclear | B5: =Calculation!C59 -> 4319515.8 | C5: =Calculation!D59 -> 4423302.1 | D5: =Calculation!E59 -> 4527088.4 | E5: =Calculation!F59 -> 4630874.7 | F5: =Calculation!G59 -> 4734661 | G5: =Calculation!H59 -> 4838447.4 | H5: =Calculation!I59 -> 4942233.7 | I5: =Calculation!J59 -> 5046020 | ... AE5: =Calculation!AF59 -> 7329318.8
A6: hydro | B6: =Calculation!C60 -> 900876.33 | C6: =Calculation!D60 -> 900876.33 | D6: =Calculation!E60 -> 900876.33 | E6: =Calculation!F60 -> 900876.33 | F6: =Calculation!G60 -> 900876.33 | G6: =Calculation!H60 -> 900876.33 | H6: =Calculation!I60 -> 900876.33 | I6: =Calculation!J60 -> 900876.33 | ... AE6: =Calculation!AF60 -> 900876.33
A7: onshore wind | B7: =Calculation!C117 -> 2480282.8 | C7: =Calculation!D117 -> 2454834.9 | D7: =Calculation!E117 -> 2429387 | E7: =Calculation!F117 -> 2403939.1 | F7: =Calculation!G117 -> 2378491.2 | G7: =Calculation!H117 -> 2332685 | H7: =Calculation!I117 -> 2286878.8 | I7: =Calculation!J117 -> 2241072.6 | ... AE7: =Calculation!AF117 -> 1460053.4
A8: solar PV | B8: =Calculation!C118 -> 1252851.4 | C8: =Calculation!D118 -> 1252851.4 | D8: =Calculation!E118 -> 1252851.4 | E8: =Calculation!F118 -> 1252851.4 | F8: =Calculation!G118 -> 1252851.4 | G8: =Calculation!H118 -> 1206978.7 | H8: =Calculation!I118 -> 1161106.1 | I8: =Calculation!J118 -> 1115233.4 | ... AE8: =Calculation!AF118 -> 616889.28
A9: solar thermal | B9: ='CCaMC-BCCpUC US'!B9 -> 6146160.4 | C9: ='CCaMC-BCCpUC US'!C9 -> 6207145.7 | D9: ='CCaMC-BCCpUC US'!D9 -> 5939220.6 | E9: ='CCaMC-BCCpUC US'!E9 -> 5671295.4 | F9: ='CCaMC-BCCpUC US'!F9 -> 5403370.2 | G9: ='CCaMC-BCCpUC US'!G9 -> 5135445.1 | H9: ='CCaMC-BCCpUC US'!H9 -> 4867519.9 | I9: ='CCaMC-BCCpUC US'!I9 -> 4599594.8 | ... AE9: ='CCaMC-BCCpUC US'!AE9 -> 3495116.9
A10: biomass | B10: =Calculation!C64 -> 3555642.3 | C10: =Calculation!D64 -> 3555642.3 | D10: =Calculation!E64 -> 3555642.3 | E10: =Calculation!F64 -> 3555642.3 | F10: =Calculation!G64 -> 3555642.3 | G10: =Calculation!H64 -> 3555642.3 | H10: =Calculation!I64 -> 3555642.3 | I10: =Calculation!J64 -> 3555642.3 | ... AE10: =Calculation!AF64 -> 3555642.3
A11: geothermal | B11: =Calculation!C65 -> 8208000 | C11: =Calculation!D65 -> 8208000 | D11: =Calculation!E65 -> 8208000 | E11: =Calculation!F65 -> 8208000 | F11: =Calculation!G65 -> 8208000 | G11: =Calculation!H65 -> 8208000 | H11: =Calculation!I65 -> 8208000 | I11: =Calculation!J65 -> 8208000 | ... AE11: =Calculation!AF65 -> 8208000
A12: petroleum | B12: =Calculation!C66 -> 1762910.9 | C12: =Calculation!D66 -> 1762910.9 | D12: =Calculation!E66 -> 1762910.9 | E12: =Calculation!F66 -> 1762910.9 | F12: =Calculation!G66 -> 1762910.9 | G12: =Calculation!H66 -> 1762910.9 | H12: =Calculation!I66 -> 1762910.9 | I12: =Calculation!J66 -> 1762910.9 | ... AE12: =Calculation!AF66 -> 1762910.9
A13: natural gas peaker | B13: =B4*'CCaMC-BCCpUC US'!B13/'CCaMC-BCCpUC US'!B4 -> 770136.95 | C13: =C4*'CCaMC-BCCpUC US'!C13/'CCaMC-BCCpUC US'!C4 -> 781423.65 | D13: =D4*'CCaMC-BCCpUC US'!D13/'CCaMC-BCCpUC US'!D4 -> 789622.22 | E13: =E4*'CCaMC-BCCpUC US'!E13/'CCaMC-BCCpUC US'!E4 -> 797806.87 | F13: =F4*'CCaMC-BCCpUC US'!F13/'CCaMC-BCCpUC US'!F4 -> 806095.5 | G13: =G4*'CCaMC-BCCpUC US'!G13/'CCaMC-BCCpUC US'!G4 -> 814370.35 | H13: =H4*'CCaMC-BCCpUC US'!H13/'CCaMC-BCCpUC US'!H4 -> 822754.03 | I13: =I4*'CCaMC-BCCpUC US'!I13/'CCaMC-BCCpUC US'!I4 -> 831124.18 | ... AE13: =AE4*'CCaMC-BCCpUC US'!AE13/'CCaMC-BCCpUC US'!AE4 -> 990157.87
A14: lignite | B14: =Calculation!C68 -> 1386477.2 | C14: =Calculation!D68 -> 1435207.5 | D14: =Calculation!E68 -> 1483937.8 | E14: =Calculation!F68 -> 1532668.1 | F14: =Calculation!G68 -> 1581398.3 | G14: =Calculation!H68 -> 1630128.6 | H14: =Calculation!I68 -> 1678858.9 | I14: =Calculation!J68 -> 1727589.2 | ... AE14: =Calculation!AF68 -> 2799655.2
A15: offshore wind | B15: =Calculation!C119 -> 5138317.2 | C15: =Calculation!D119 -> 4993111.4 | D15: =Calculation!E119 -> 4847905.6 | E15: =Calculation!F119 -> 4702699.8 | F15: =Calculation!G119 -> 4557494 | G15: =Calculation!H119 -> 4412288.2 | H15: =Calculation!I119 -> 4267082.4 | I15: =Calculation!J119 -> 4121876.6 | ... AE15: =Calculation!AF119 -> 927349.28
A16: crude oil | B16: =Calculation!C70 -> 1762910.9 | C16: =Calculation!D70 -> 1762910.9 | D16: =Calculation!E70 -> 1762910.9 | E16: =Calculation!F70 -> 1762910.9 | F16: =Calculation!G70 -> 1762910.9 | G16: =Calculation!H70 -> 1762910.9 | H16: =Calculation!I70 -> 1762910.9 | I16: =Calculation!J70 -> 1762910.9 | ... AE16: =Calculation!AF70 -> 1762910.9
A17: heavy or residual fuel oil | B17: =Calculation!C71 -> 1762910.9 | C17: =Calculation!D71 -> 1762910.9 | D17: =Calculation!E71 -> 1762910.9 | E17: =Calculation!F71 -> 1762910.9 | F17: =Calculation!G71 -> 1762910.9 | G17: =Calculation!H71 -> 1762910.9 | H17: =Calculation!I71 -> 1762910.9 | I17: =Calculation!J71 -> 1762910.9 | ... AE17: =Calculation!AF71 -> 1762910.9
A18: municipal solid waste | B18: =Calculation!C72 -> 4463927.3 | C18: =Calculation!D72 -> 4463927.3 | D18: =Calculation!E72 -> 4463927.3 | E18: =Calculation!F72 -> 4463927.3 | F18: =Calculation!G72 -> 4463927.3 | G18: =Calculation!H72 -> 4463927.3 | H18: =Calculation!I72 -> 4463927.3 | I18: =Calculation!J72 -> 4463927.3 | ... AE18: =Calculation!AF72 -> 4463927.3
A19: hard coal w CCS | B19: ='CCaMC-BCCpUC US'!B19 -> 5111375.6 | C19: ='CCaMC-BCCpUC US'!C19 -> 5365237.1 | D19: ='CCaMC-BCCpUC US'!D19 -> 5301847.6 | E19: ='CCaMC-BCCpUC US'!E19 -> 5238458 | F19: ='CCaMC-BCCpUC US'!F19 -> 5175068.5 | G19: ='CCaMC-BCCpUC US'!G19 -> 5111678.9 | H19: ='CCaMC-BCCpUC US'!H19 -> 5048289.4 | I19: ='CCaMC-BCCpUC US'!I19 -> 4984899.8 | ... AE19: ='CCaMC-BCCpUC US'!AE19 -> 3813259.4
A20: natural gas combined cycle w CCS | B20: ='CCaMC-BCCpUC US'!B20 -> 2175532.1 | C20: ='CCaMC-BCCpUC US'!C20 -> 2325464.6 | D20: ='CCaMC-BCCpUC US'!D20 -> 2285249.8 | E20: ='CCaMC-BCCpUC US'!E20 -> 2245035 | F20: ='CCaMC-BCCpUC US'!F20 -> 2204820.2 | G20: ='CCaMC-BCCpUC US'!G20 -> 2164605.4 | H20: ='CCaMC-BCCpUC US'!H20 -> 2124390.6 | I20: ='CCaMC-BCCpUC US'!I20 -> 2085050.1 | ... AE20: ='CCaMC-BCCpUC US'!AE20 -> 1508929.3
A21: biomass w CCS | B21: ='CCaMC-BCCpUC US'!B21 -> 5857355.1 | C21: ='CCaMC-BCCpUC US'!C21 -> 5839455.6 | D21: ='CCaMC-BCCpUC US'!D21 -> 5821556 | E21: ='CCaMC-BCCpUC US'!E21 -> 5803656.5 | F21: ='CCaMC-BCCpUC US'!F21 -> 5785757 | G21: ='CCaMC-BCCpUC US'!G21 -> 5767857.5 | H21: ='CCaMC-BCCpUC US'!H21 -> 5749958 | I21: ='CCaMC-BCCpUC US'!I21 -> 5732058.4 | ... AE21: ='CCaMC-BCCpUC US'!AE21 -> 5369856.4
A22: lignite w CCS | B22: ='CCaMC-BCCpUC US'!B22 -> 5923789.3 | C22: ='CCaMC-BCCpUC US'!C22 -> 6218000.1 | D22: ='CCaMC-BCCpUC US'!D22 -> 6144535.3 | E22: ='CCaMC-BCCpUC US'!E22 -> 6071070.5 | F22: ='CCaMC-BCCpUC US'!F22 -> 5997605.7 | G22: ='CCaMC-BCCpUC US'!G22 -> 5924140.8 | H22: ='CCaMC-BCCpUC US'!H22 -> 5850676 | I22: ='CCaMC-BCCpUC US'!I22 -> 5777211.2 | ... AE22: ='CCaMC-BCCpUC US'!AE22 -> 4419347.5
A23: small modular reactor | B23: ='CCaMC-BCCpUC US'!B23 -> 8587076.7 | C23: ='CCaMC-BCCpUC US'!C23 -> 8300944.1 | D23: ='CCaMC-BCCpUC US'!D23 -> 8014811.5 | E23: ='CCaMC-BCCpUC US'!E23 -> 7728678.9 | F23: ='CCaMC-BCCpUC US'!F23 -> 7501037.2 | G23: ='CCaMC-BCCpUC US'!G23 -> 7362296.2 | H23: ='CCaMC-BCCpUC US'!H23 -> 7288664.8 | I23: ='CCaMC-BCCpUC US'!I23 -> 7240937 | ... AE23: ='CCaMC-BCCpUC US'!AE23 -> 3832046.5
A24: hydrogen combustion turbine | B24: ='CCaMC-BCCpUC US'!B24 -> 949292.13 | C24: ='CCaMC-BCCpUC US'!C24 -> 1058173.8 | D24: ='CCaMC-BCCpUC US'!D24 -> 1050480.6 | E24: ='CCaMC-BCCpUC US'!E24 -> 1042787.3 | F24: ='CCaMC-BCCpUC US'!F24 -> 1035094 | G24: ='CCaMC-BCCpUC US'!G24 -> 1027400.8 | H24: ='CCaMC-BCCpUC US'!H24 -> 1019707.5 | I24: ='CCaMC-BCCpUC US'!I24 -> 1012014.2 | ... AE24: ='CCaMC-BCCpUC US'!AE24 -> 843024.64
A25: hydrogen combined cycle | B25: ='CCaMC-BCCpUC US'!B25 -> 1087150.6 | C25: ='CCaMC-BCCpUC US'!C25 -> 1205045.3 | D25: ='CCaMC-BCCpUC US'!D25 -> 1194379.6 | E25: ='CCaMC-BCCpUC US'!E25 -> 1183801.4 | F25: ='CCaMC-BCCpUC US'!F25 -> 1173135.7 | G25: ='CCaMC-BCCpUC US'!G25 -> 1162557.5 | H25: ='CCaMC-BCCpUC US'!H25 -> 1151891.8 | I25: ='CCaMC-BCCpUC US'!I25 -> 1141313.6 | ... AE25: ='CCaMC-BCCpUC US'!AE25 -> 946096.93

Sheet CCaMC-SLCCpUC
A1: Unit: $/MW | B1: 2021 | C1: 2022 | D1: 2023 | E1: 2024 | F1: 2025 | G1: 2026 | H1: 2027 | I1: 2028 | J1: 2029 | K1: 2030 | L1: 2031 | M1: 2032 | N1: 2033 | O1: 2034 | P1: 2035 | Q1: 2036 | R1: 2037 | S1: 2038 | T1: 2039 | U1: 2040 | V1: 2041 | W1: 2042 | X1: 2043 | Y1: 2044 | Z1: 2045 | AA1: 2046 | AB1: 2047 | AC1: 2048 | AD1: 2049 | AE1: 2050
A2: hard coal | B2: 0 | C2: 0 | D2: 0 | E2: 0 | F2: 0 | G2: 0 | H2: 0 | I2: 0 | J2: 0 | K2: 0 | L2: 0 | M2: 0 | N2: 0 | O2: 0 | P2: 0 | Q2: 0 | R2: 0 | S2: 0 | T2: 0 | U2: 0 | V2: 0 | W2: 0 | X2: 0 | Y2: 0 | Z2: 0 | AA2: 0 | AB2: 0 | AC2: 0 | AD2: 0 | AE2: 0
A3: natural gas steam turbine | B3: 0 | C3: 0 | D3: 0 | E3: 0 | F3: 0 | G3: 0 | H3: 0 | I3: 0 | J3: 0 | K3: 0 | L3: 0 | M3: 0 | N3: 0 | O3: 0 | P3: 0 | Q3: 0 | R3: 0 | S3: 0 | T3: 0 | U3: 0 | V3: 0 | W3: 0 | X3: 0 | Y3: 0 | Z3: 0 | AA3: 0 | AB3: 0 | AC3: 0 | AD3: 0 | AE3: 0
A4: natural gas combined cycle | B4: 0 | C4: 0 | D4: 0 | E4: 0 | F4: 0 | G4: 0 | H4: 0 | I4: 0 | J4: 0 | K4: 0 | L4: 0 | M4: 0 | N4: 0 | O4: 0 | P4: 0 | Q4: 0 | R4: 0 | S4: 0 | T4: 0 | U4: 0 | V4: 0 | W4: 0 | X4: 0 | Y4: 0 | Z4: 0 | AA4: 0 | AB4: 0 | AC4: 0 | AD4: 0 | AE4: 0
A5: nuclear | B5: 0 | C5: 0 | D5: 0 | E5: 0 | F5: 0 | G5: 0 | H5: 0 | I5: 0 | J5: 0 | K5: 0 | L5: 0 | M5: 0 | N5: 0 | O5: 0 | P5: 0 | Q5: 0 | R5: 0 | S5: 0 | T5: 0 | U5: 0 | V5: 0 | W5: 0 | X5: 0 | Y5: 0 | Z5: 0 | AA5: 0 | AB5: 0 | AC5: 0 | AD5: 0 | AE5: 0
A6: hydro | B6: 0 | C6: 0 | D6: 0 | E6: 0 | F6: 0 | G6: 0 | H6: 0 | I6: 0 | J6: 0 | K6: 0 | L6: 0 | M6: 0 | N6: 0 | O6: 0 | P6: 0 | Q6: 0 | R6: 0 | S6: 0 | T6: 0 | U6: 0 | V6: 0 | W6: 0 | X6: 0 | Y6: 0 | Z6: 0 | AA6: 0 | AB6: 0 | AC6: 0 | AD6: 0 | AE6: 0
A7: onshore wind | B7: =Calculation!$B$111 -> 39059.364 | C7: =Calculation!$B$111 -> 39059.364 | D7: =Calculation!$B$111 -> 39059.364 | E7: =Calculation!$B$111 -> 39059.364 | F7: =Calculation!$B$111 -> 39059.364 | G7: =Calculation!$B$111 -> 39059.364 | H7: =Calculation!$B$111 -> 39059.364 | I7: =Calculation!$B$111 -> 39059.364 | ... AE7: =Calculation!$B$111 -> 39059.364
A8: solar PV | B8: =Calculation!$B$112 -> 21389.652 | C8: =Calculation!$B$112 -> 21389.652 | D8: =Calculation!$B$112 -> 21389.652 | E8: =Calculation!$B$112 -> 21389.652 | F8: =Calculation!$B$112 -> 21389.652 | G8: =Calculation!$B$112 -> 21389.652 | H8: =Calculation!$B$112 -> 21389.652 | I8: =Calculation!$B$112 -> 21389.652 | ... AE8: =Calculation!$B$112 -> 21389.652
A9: solar thermal | B9: 0 | C9: 0 | D9: 0 | E9: 0 | F9: 0 | G9: 0 | H9: 0 | I9: 0 | J9: 0 | K9: 0 | L9: 0 | M9: 0 | N9: 0 | O9: 0 | P9: 0 | Q9: 0 | R9: 0 | S9: 0 | T9: 0 | U9: 0 | V9: 0 | W9: 0 | X9: 0 | Y9: 0 | Z9: 0 | AA9: 0 | AB9: 0 | AC9: 0 | AD9: 0 | AE9: 0
A10: biomass | B10: 0 | C10: 0 | D10: 0 | E10: 0 | F10: 0 | G10: 0 | H10: 0 | I10: 0 | J10: 0 | K10: 0 | L10: 0 | M10: 0 | N10: 0 | O10: 0 | P10: 0 | Q10: 0 | R10: 0 | S10: 0 | T10: 0 | U10: 0 | V10: 0 | W10: 0 | X10: 0 | Y10: 0 | Z10: 0 | AA10: 0 | AB10: 0 | AC10: 0 | AD10: 0 | AE10: 0
A11: geothermal | B11: 0 | C11: 0 | D11: 0 | E11: 0 | F11: 0 | G11: 0 | H11: 0 | I11: 0 | J11: 0 | K11: 0 | L11: 0 | M11: 0 | N11: 0 | O11: 0 | P11: 0 | Q11: 0 | R11: 0 | S11: 0 | T11: 0 | U11: 0 | V11: 0 | W11: 0 | X11: 0 | Y11: 0 | Z11: 0 | AA11: 0 | AB11: 0 | AC11: 0 | AD11: 0 | AE11: 0
A12: petroleum | B12: 0 | C12: 0 | D12: 0 | E12: 0 | F12: 0 | G12: 0 | H12: 0 | I12: 0 | J12: 0 | K12: 0 | L12: 0 | M12: 0 | N12: 0 | O12: 0 | P12: 0 | Q12: 0 | R12: 0 | S12: 0 | T12: 0 | U12: 0 | V12: 0 | W12: 0 | X12: 0 | Y12: 0 | Z12: 0 | AA12: 0 | AB12: 0 | AC12: 0 | AD12: 0 | AE12: 0
A13: natural gas peaker | B13: 0 | C13: 0 | D13: 0 | E13: 0 | F13: 0 | G13: 0 | H13: 0 | I13: 0 | J13: 0 | K13: 0 | L13: 0 | M13: 0 | N13: 0 | O13: 0 | P13: 0 | Q13: 0 | R13: 0 | S13: 0 | T13: 0 | U13: 0 | V13: 0 | W13: 0 | X13: 0 | Y13: 0 | Z13: 0 | AA13: 0 | AB13: 0 | AC13: 0 | AD13: 0 | AE13: 0
A14: lignite | B14: 0 | C14: 0 | D14: 0 | E14: 0 | F14: 0 | G14: 0 | H14: 0 | I14: 0 | J14: 0 | K14: 0 | L14: 0 | M14: 0 | N14: 0 | O14: 0 | P14: 0 | Q14: 0 | R14: 0 | S14: 0 | T14: 0 | U14: 0 | V14: 0 | W14: 0 | X14: 0 | Y14: 0 | Z14: 0 | AA14: 0 | AB14: 0 | AC14: 0 | AD14: 0 | AE14: 0
A15: offshore wind | B15: =Calculation!$B$113 -> 301315.09 | C15: =Calculation!$B$113 -> 301315.09 | D15: =Calculation!$B$113 -> 301315.09 | E15: =Calculation!$B$113 -> 301315.09 | F15: =Calculation!$B$113 -> 301315.09 | G15: =Calculation!$B$113 -> 301315.09 | H15: =Calculation!$B$113 -> 301315.09 | I15: =Calculation!$B$113 -> 301315.09 | ... AE15: =Calculation!$B$113 -> 301315.09
A16: crude oil | B16: 0 | C16: 0 | D16: 0 | E16: 0 | F16: 0 | G16: 0 | H16: 0 | I16: 0 | J16: 0 | K16: 0 | L16: 0 | M16: 0 | N16: 0 | O16: 0 | P16: 0 | Q16: 0 | R16: 0 | S16: 0 | T16: 0 | U16: 0 | V16: 0 | W16: 0 | X16: 0 | Y16: 0 | Z16: 0 | AA16: 0 | AB16: 0 | AC16: 0 | AD16: 0 | AE16: 0
A17: heavy or residual fuel oil | B17: 0 | C17: 0 | D17: 0 | E17: 0 | F17: 0 | G17: 0 | H17: 0 | I17: 0 | J17: 0 | K17: 0 | L17: 0 | M17: 0 | N17: 0 | O17: 0 | P17: 0 | Q17: 0 | R17: 0 | S17: 0 | T17: 0 | U17: 0 | V17: 0 | W17: 0 | X17: 0 | Y17: 0 | Z17: 0 | AA17: 0 | AB17: 0 | AC17: 0 | AD17: 0 | AE17: 0
A18: municipal solid waste | B18: 0 | C18: 0 | D18: 0 | E18: 0 | F18: 0 | G18: 0 | H18: 0 | I18: 0 | J18: 0 | K18: 0 | L18: 0 | M18: 0 | N18: 0 | O18: 0 | P18: 0 | Q18: 0 | R18: 0 | S18: 0 | T18: 0 | U18: 0 | V18: 0 | W18: 0 | X18: 0 | Y18: 0 | Z18: 0 | AA18: 0 | AB18: 0 | AC18: 0 | AD18: 0 | AE18: 0
A19: hard coal w CCS | B19: 0 | C19: 0 | D19: 0 | E19: 0 | F19: 0 | G19: 0 | H19: 0 | I19: 0 | J19: 0 | K19: 0 | L19: 0 | M19: 0 | N19: 0 | O19: 0 | P19: 0 | Q19: 0 | R19: 0 | S19: 0 | T19: 0 | U19: 0 | V19: 0 | W19: 0 | X19: 0 | Y19: 0 | Z19: 0 | AA19: 0 | AB19: 0 | AC19: 0 | AD19: 0 | AE19: 0
A20: natural gas combined cycle w CCS | B20: 0 | C20: 0 | D20: 0 | E20: 0 | F20: 0 | G20: 0 | H20: 0 | I20: 0 | J20: 0 | K20: 0 | L20: 0 | M20: 0 | N20: 0 | O20: 0 | P20: 0 | Q20: 0 | R20: 0 | S20: 0 | T20: 0 | U20: 0 | V20: 0 | W20: 0 | X20: 0 | Y20: 0 | Z20: 0 | AA20: 0 | AB20: 0 | AC20: 0 | AD20: 0 | AE20: 0
A21: biomass w CCS | B21: 0 | C21: 0 | D21: 0 | E21: 0 | F21: 0 | G21: 0 | H21: 0 | I21: 0 | J21: 0 | K21: 0 | L21: 0 | M21: 0 | N21: 0 | O21: 0 | P21: 0 | Q21: 0 | R21: 0 | S21: 0 | T21: 0 | U21: 0 | V21: 0 | W21: 0 | X21: 0 | Y21: 0 | Z21: 0 | AA21: 0 | AB21: 0 | AC21: 0 | AD21: 0 | AE21: 0
A22: lignite w CCS | B22: 0 | C22: 0 | D22: 0 | E22: 0 | F22: 0 | G22: 0 | H22: 0 | I22: 0 | J22: 0 | K22: 0 | L22: 0 | M22: 0 | N22: 0 | O22: 0 | P22: 0 | Q22: 0 | R22: 0 | S22: 0 | T22: 0 | U22: 0 | V22: 0 | W22: 0 | X22: 0 | Y22: 0 | Z22: 0 | AA22: 0 | AB22: 0 | AC22: 0 | AD22: 0 | AE22: 0
A23: small modular reactor | B23: 0 | C23: 0 | D23: 0 | E23: 0 | F23: 0 | G23: 0 | H23: 0 | I23: 0 | J23: 0 | K23: 0 | L23: 0 | M23: 0 | N23: 0 | O23: 0 | P23: 0 | Q23: 0 | R23: 0 | S23: 0 | T23: 0 | U23: 0 | V23: 0 | W23: 0 | X23: 0 | Y23: 0 | Z23: 0 | AA23: 0 | AB23: 0 | AC23: 0 | AD23: 0 | AE23: 0
A24: hydrogen combustion turbine | B24: 0 | C24: 0 | D24: 0 | E24: 0 | F24: 0 | G24: 0 | H24: 0 | I24: 0 | J24: 0 | K24: 0 | L24: 0 | M24: 0 | N24: 0 | O24: 0 | P24: 0 | Q24: 0 | R24: 0 | S24: 0 | T24: 0 | U24: 0 | V24: 0 | W24: 0 | X24: 0 | Y24: 0 | Z24: 0 | AA24: 0 | AB24: 0 | AC24: 0 | AD24: 0 | AE24: 0
A25: hydrogen combined cycle | B25: 0 | C25: 0 | D25: 0 | E25: 0 | F25: 0 | G25: 0 | H25: 0 | I25: 0 | J25: 0 | K25: 0 | L25: 0 | M25: 0 | N25: 0 | O25: 0 | P25: 0 | Q25: 0 | R25: 0 | S25: 0 | T25: 0 | U25: 0 | V25: 0 | W25: 0 | X25: 0 | Y25: 0 | Z25: 0 | AA25: 0 | AB25: 0 | AC25: 0 | AD25: 0 | AE25: 0

Sheet CCaMC-BSCpUC
A1: Unit: $/MW | B1: 2021 | C1: 2022 | D1: 2023 | E1: 2024 | F1: 2025 | G1: 2026 | H1: 2027 | I1: 2028 | J1: 2029 | K1: 2030 | L1: 2031 | M1: 2032 | N1: 2033 | O1: 2034 | P1: 2035 | Q1: 2036 | R1: 2037 | S1: 2038 | T1: 2039 | U1: 2040 | V1: 2041 | W1: 2042 | X1: 2043 | Y1: 2044 | Z1: 2045 | AA1: 2046 | AB1: 2047 | AC1: 2048 | AD1: 2049 | AE1: 2050
A2: Hard Coal (NOT USED) | B2: 0 | C2: 0 | D2: 0 | E2: 0 | F2: 0 | G2: 0 | H2: 0 | I2: 0 | J2: 0 | K2: 0 | L2: 0 | M2: 0 | N2: 0 | O2: 0 | P2: 0 | Q2: 0 | R2: 0 | S2: 0 | T2: 0 | U2: 0 | V2: 0 | W2: 0 | X2: 0 | Y2: 0 | Z2: 0 | AA2: 0 | AB2: 0 | AC2: 0 | AD2: 0 | AE2: 0
A3: Natural Gas Steam Turbine (NOT USED) | B3: 0 | C3: 0 | D3: 0 | E3: 0 | F3: 0 | G3: 0 | H3: 0 | I3: 0 | J3: 0 | K3: 0 | L3: 0 | M3: 0 | N3: 0 | O3: 0 | P3: 0 | Q3: 0 | R3: 0 | S3: 0 | T3: 0 | U3: 0 | V3: 0 | W3: 0 | X3: 0 | Y3: 0 | Z3: 0 | AA3: 0 | AB3: 0 | AC3: 0 | AD3: 0 | AE3: 0
A4: Natural Gas Combined Cycle (NOT USED) | B4: 0 | C4: 0 | D4: 0 | E4: 0 | F4: 0 | G4: 0 | H4: 0 | I4: 0 | J4: 0 | K4: 0 | L4: 0 | M4: 0 | N4: 0 | O4: 0 | P4: 0 | Q4: 0 | R4: 0 | S4: 0 | T4: 0 | U4: 0 | V4: 0 | W4: 0 | X4: 0 | Y4: 0 | Z4: 0 | AA4: 0 | AB4: 0 | AC4: 0 | AD4: 0 | AE4: 0
A5: Nuclear (NOT USED) | B5: 0 | C5: 0 | D5: 0 | E5: 0 | F5: 0 | G5: 0 | H5: 0 | I5: 0 | J5: 0 | K5: 0 | L5: 0 | M5: 0 | N5: 0 | O5: 0 | P5: 0 | Q5: 0 | R5: 0 | S5: 0 | T5: 0 | U5: 0 | V5: 0 | W5: 0 | X5: 0 | Y5: 0 | Z5: 0 | AA5: 0 | AB5: 0 | AC5: 0 | AD5: 0 | AE5: 0
A6: Hydro (NOT USED) | B6: 0 | C6: 0 | D6: 0 | E6: 0 | F6: 0 | G6: 0 | H6: 0 | I6: 0 | J6: 0 | K6: 0 | L6: 0 | M6: 0 | N6: 0 | O6: 0 | P6: 0 | Q6: 0 | R6: 0 | S6: 0 | T6: 0 | U6: 0 | V6: 0 | W6: 0 | X6: 0 | Y6: 0 | Z6: 0 | AA6: 0 | AB6: 0 | AC6: 0 | AD6: 0 | AE6: 0
A7: Onshore Wind | B7: ='CCaMC-BSCpUC US'!B7/'CCaMC-BCCpUC US'!B7*'CCaMC-BCCpUC'!B7 -> 330704.38 | C7: =$B7*'CCaMC-BSCpUC US'!C7/'CCaMC-BSCpUC US'!$B7 -> 248028.28 | D7: =$B7*'CCaMC-BSCpUC US'!D7/'CCaMC-BSCpUC US'!$B7 -> 165352.19 | E7: =$B7*'CCaMC-BSCpUC US'!E7/'CCaMC-BSCpUC US'!$B7 -> 82676.095 | F7: =$B7*'CCaMC-BSCpUC US'!F7/'CCaMC-BSCpUC US'!$B7 -> 0 | G7: =$B7*'CCaMC-BSCpUC US'!G7/'CCaMC-BSCpUC US'!$B7 -> 0 | H7: =$B7*'CCaMC-BSCpUC US'!H7/'CCaMC-BSCpUC US'!$B7 -> 0 | I7: =$B7*'CCaMC-BSCpUC US'!I7/'CCaMC-BSCpUC US'!$B7 -> 0 | J7: =$B7*'CCaMC-BSCpUC US'!J7/'CCaMC-BSCpUC US'!$B7 -> 0 | ... AE7: =$B7*'CCaMC-BSCpUC US'!AE7/'CCaMC-BSCpUC US'!$B7 -> 0
A8: Solar PV | B8: ='CCaMC-BSCpUC US'!B8/'CCaMC-BCCpUC US'!B8*'CCaMC-BCCpUC'!B8 -> 638954.22 | C8: =$B8*'CCaMC-BSCpUC US'!C8/'CCaMC-BSCpUC US'!$B8 -> 638954.22 | D8: =$B8*'CCaMC-BSCpUC US'!D8/'CCaMC-BSCpUC US'!$B8 -> 638954.22 | E8: =$B8*'CCaMC-BSCpUC US'!E8/'CCaMC-BSCpUC US'!$B8 -> 638954.22 | F8: =$B8*'CCaMC-BSCpUC US'!F8/'CCaMC-BSCpUC US'!$B8 -> 638954.22 | G8: =$B8*'CCaMC-BSCpUC US'!G8/'CCaMC-BSCpUC US'!$B8 -> 611391.49 | H8: =$B8*'CCaMC-BSCpUC US'!H8/'CCaMC-BSCpUC US'!$B8 -> 583828.76 | I8: =$B8*'CCaMC-BSCpUC US'!I8/'CCaMC-BSCpUC US'!$B8 -> 556266.03 | J8: =$B8*'CCaMC-BSCpUC US'!J8/'CCaMC-BSCpUC US'!$B8 -> 528703.3 | ... AE8: =$B8*'CCaMC-BSCpUC US'!AE8/'CCaMC-BSCpUC US'!$B8 -> 225513.26
A9: Solar Thermal (NOT USED) | B9: 0 | C9: 0 | D9: 0 | E9: 0 | F9: 0 | G9: 0 | H9: 0 | I9: 0 | J9: 0 | K9: 0 | L9: 0 | M9: 0 | N9: 0 | O9: 0 | P9: 0 | Q9: 0 | R9: 0 | S9: 0 | T9: 0 | U9: 0 | V9: 0 | W9: 0 | X9: 0 | Y9: 0 | Z9: 0 | AA9: 0 | AB9: 0 | AC9: 0 | AD9: 0 | AE9: 0
A10: Biomass (NOT USED) | B10: 0 | C10: 0 | D10: 0 | E10: 0 | F10: 0 | G10: 0 | H10: 0 | I10: 0 | J10: 0 | K10: 0 | L10: 0 | M10: 0 | N10: 0 | O10: 0 | P10: 0 | Q10: 0 | R10: 0 | S10: 0 | T10: 0 | U10: 0 | V10: 0 | W10: 0 | X10: 0 | Y10: 0 | Z10: 0 | AA10: 0 | AB10: 0 | AC10: 0 | AD10: 0 | AE10: 0
A11: Geothermal (NOT USED) | B11: 0 | C11: 0 | D11: 0 | E11: 0 | F11: 0 | G11: 0 | H11: 0 | I11: 0 | J11: 0 | K11: 0 | L11: 0 | M11: 0 | N11: 0 | O11: 0 | P11: 0 | Q11: 0 | R11: 0 | S11: 0 | T11: 0 | U11: 0 | V11: 0 | W11: 0 | X11: 0 | Y11: 0 | Z11: 0 | AA11: 0 | AB11: 0 | AC11: 0 | AD11: 0 | AE11: 0
A12: Petroleum (NOT USED) | B12: 0 | C12: 0 | D12: 0 | E12: 0 | F12: 0 | G12: 0 | H12: 0 | I12: 0 | J12: 0 | K12: 0 | L12: 0 | M12: 0 | N12: 0 | O12: 0 | P12: 0 | Q12: 0 | R12: 0 | S12: 0 | T12: 0 | U12: 0 | V12: 0 | W12: 0 | X12: 0 | Y12: 0 | Z12: 0 | AA12: 0 | AB12: 0 | AC12: 0 | AD12: 0 | AE12: 0
A13: Natural Gas Peaker (NOT USED) | B13: 0 | C13: 0 | D13: 0 | E13: 0 | F13: 0 | G13: 0 | H13: 0 | I13: 0 | J13: 0 | K13: 0 | L13: 0 | M13: 0 | N13: 0 | O13: 0 | P13: 0 | Q13: 0 | R13: 0 | S13: 0 | T13: 0 | U13: 0 | V13: 0 | W13: 0 | X13: 0 | Y13: 0 | Z13: 0 | AA13: 0 | AB13: 0 | AC13: 0 | AD13: 0 | AE13: 0
A14: Lignite (NOT USED) | B14: 0 | C14: 0 | D14: 0 | E14: 0 | F14: 0 | G14: 0 | H14: 0 | I14: 0 | J14: 0 | K14: 0 | L14: 0 | M14: 0 | N14: 0 | O14: 0 | P14: 0 | Q14: 0 | R14: 0 | S14: 0 | T14: 0 | U14: 0 | V14: 0 | W14: 0 | X14: 0 | Y14: 0 | Z14: 0 | AA14: 0 | AB14: 0 | AC14: 0 | AD14: 0 | AE14: 0
A15: Offshore Wind | B15: ='CCaMC-BSCpUC US'!B15/'CCaMC-BCCpUC US'!B15*'CCaMC-BCCpUC'!B15 -> 1137770.2 | C15: =$B15*'CCaMC-BSCpUC US'!C15/'CCaMC-BSCpUC US'!$B15 -> 1247877 | D15: =$B15*'CCaMC-BSCpUC US'!D15/'CCaMC-BSCpUC US'!$B15 -> 1357983.8 | E15: =$B15*'CCaMC-BSCpUC US'!E15/'CCaMC-BSCpUC US'!$B15 -> 1468090.6 | F15: =$B15*'CCaMC-BSCpUC US'!F15/'CCaMC-BSCpUC US'!$B15 -> 1578197.4 | G15: =$B15*'CCaMC-BSCpUC US'!G15/'CCaMC-BSCpUC US'!$B15 -> 1688304.2 | H15: =$B15*'CCaMC-BSCpUC US'!H15/'CCaMC-BSCpUC US'!$B15 -> 1798411 | I15: =$B15*'CCaMC-BSCpUC US'!I15/'CCaMC-BSCpUC US'!$B15 -> 1541495.2 | J15: =$B15*'CCaMC-BSCpUC US'!J15/'CCaMC-BSCpUC US'!$B15 -> 1284579.3 | ... AE15: =$B15*'CCaMC-BSCpUC US'!AE15/'CCaMC-BSCpUC US'!$B15 -> 513831.72
A16: Crude Oil (NOT USED) | B16: 0 | C16: 0 | D16: 0 | E16: 0 | F16: 0 | G16: 0 | H16: 0 | I16: 0 | J16: 0 | K16: 0 | L16: 0 | M16: 0 | N16: 0 | O16: 0 | P16: 0 | Q16: 0 | R16: 0 | S16: 0 | T16: 0 | U16: 0 | V16: 0 | W16: 0 | X16: 0 | Y16: 0 | Z16: 0 | AA16: 0 | AB16: 0 | AC16: 0 | AD16: 0 | AE16: 0
A17: Heavy or Residual Fuel Oil (NOT USED) | B17: 0 | C17: 0 | D17: 0 | E17: 0 | F17: 0 | G17: 0 | H17: 0 | I17: 0 | J17: 0 | K17: 0 | L17: 0 | M17: 0 | N17: 0 | O17: 0 | P17: 0 | Q17: 0 | R17: 0 | S17: 0 | T17: 0 | U17: 0 | V17: 0 | W17: 0 | X17: 0 | Y17: 0 | Z17: 0 | AA17: 0 | AB17: 0 | AC17: 0 | AD17: 0 | AE17: 0
A18: Municipal Solid Waste (NOT USED) | B18: 0 | C18: 0 | D18: 0 | E18: 0 | F18: 0 | G18: 0 | H18: 0 | I18: 0 | J18: 0 | K18: 0 | L18: 0 | M18: 0 | N18: 0 | O18: 0 | P18: 0 | Q18: 0 | R18: 0 | S18: 0 | T18: 0 | U18: 0 | V18: 0 | W18: 0 | X18: 0 | Y18: 0 | Z18: 0 | AA18: 0 | AB18: 0 | AC18: 0 | AD18: 0 | AE18: 0
A19: hard coal w CCS | B19: ='CCaMC-BCCpUC'!B2 -> 1386477.2 | C19: =$B19*'CCaMC-BSCpUC US'!C19/'CCaMC-BSCpUC US'!$B19 -> 1475126.2 | D19: =$B19*'CCaMC-BSCpUC US'!D19/'CCaMC-BSCpUC US'!$B19 -> 1467306.4 | E19: =$B19*'CCaMC-BSCpUC US'!E19/'CCaMC-BSCpUC US'!$B19 -> 1459486.6 | F19: =$B19*'CCaMC-BSCpUC US'!F19/'CCaMC-BSCpUC US'!$B19 -> 1451666.8 | G19: =$B19*'CCaMC-BSCpUC US'!G19/'CCaMC-BSCpUC US'!$B19 -> 1443847 | H19: =$B19*'CCaMC-BSCpUC US'!H19/'CCaMC-BSCpUC US'!$B19 -> 1436027.2 | I19: =$B19*'CCaMC-BSCpUC US'!I19/'CCaMC-BSCpUC US'!$B19 -> 1428207.4 | J19: =$B19*'CCaMC-BSCpUC US'!J19/'CCaMC-BSCpUC US'!$B19 -> 1420387.6 | ... AE19: =$B19*'CCaMC-BSCpUC US'!AE19/'CCaMC-BSCpUC US'!$B19 -> 1182085
A20: natural gas combined cycle w CCS | B20: ='CCaMC-BCCpUC'!B4 -> 881978.11 | C20: =$B20*'CCaMC-BSCpUC US'!C20/'CCaMC-BSCpUC US'!$B20 -> 977623.09 | D20: =$B20*'CCaMC-BSCpUC US'!D20/'CCaMC-BSCpUC US'!$B20 -> 968970.3 | E20: =$B20*'CCaMC-BSCpUC US'!E20/'CCaMC-BSCpUC US'!$B20 -> 960388.44 | F20: =$B20*'CCaMC-BSCpUC US'!F20/'CCaMC-BSCpUC US'!$B20 -> 951735.65 | G20: =$B20*'CCaMC-BSCpUC US'!G20/'CCaMC-BSCpUC US'!$B20 -> 943153.79 | H20: =$B20*'CCaMC-BSCpUC US'!H20/'CCaMC-BSCpUC US'!$B20 -> 934501 | I20: =$B20*'CCaMC-BSCpUC US'!I20/'CCaMC-BSCpUC US'!$B20 -> 925919.14 | J20: =$B20*'CCaMC-BSCpUC US'!J20/'CCaMC-BSCpUC US'!$B20 -> 917266.35 | ... AE20: =$B20*'CCaMC-BSCpUC US'!AE20/'CCaMC-BSCpUC US'!$B20 -> 767544.77
A21: biomass w CCS | B21: ='CCaMC-BCCpUC'!B10 -> 3555642.3 | C21: =$B21*'CCaMC-BSCpUC US'!C21/'CCaMC-BSCpUC US'!$B21 -> 3376220.1 | D21: =$B21*'CCaMC-BSCpUC US'!D21/'CCaMC-BSCpUC US'!$B21 -> 3262098.9 | E21: =$B21*'CCaMC-BSCpUC US'!E21/'CCaMC-BSCpUC US'!$B21 -> 3147977.7 | F21: =$B21*'CCaMC-BSCpUC US'!F21/'CCaMC-BSCpUC US'!$B21 -> 3057168.4 | G21: =$B21*'CCaMC-BSCpUC US'!G21/'CCaMC-BSCpUC US'!$B21 -> 3001577.5 | H21: =$B21*'CCaMC-BSCpUC US'!H21/'CCaMC-BSCpUC US'!$B21 -> 2972138 | I21: =$B21*'CCaMC-BSCpUC US'!I21/'CCaMC-BSCpUC US'!$B21 -> 2953018.4 | J21: =$B21*'CCaMC-BSCpUC US'!J21/'CCaMC-BSCpUC US'!$B21 -> 2935306.4 | ... AE21: =$B21*'CCaMC-BSCpUC US'!AE21/'CCaMC-BSCpUC US'!$B21 -> 2525640.7
A22: lignite w CCS | B22: ='CCaMC-BCCpUC'!B14 -> 1386477.2 | C22: =$B22*'CCaMC-BSCpUC US'!C22/'CCaMC-BSCpUC US'!$B22 -> 1475126.2 | D22: =$B22*'CCaMC-BSCpUC US'!D22/'CCaMC-BSCpUC US'!$B22 -> 1467306.4 | E22: =$B22*'CCaMC-BSCpUC US'!E22/'CCaMC-BSCpUC US'!$B22 -> 1459486.6 | F22: =$B22*'CCaMC-BSCpUC US'!F22/'CCaMC-BSCpUC US'!$B22 -> 1451666.8 | G22: =$B22*'CCaMC-BSCpUC US'!G22/'CCaMC-BSCpUC US'!$B22 -> 1443847 | H22: =$B22*'CCaMC-BSCpUC US'!H22/'CCaMC-BSCpUC US'!$B22 -> 1436027.2 | I22: =$B22*'CCaMC-BSCpUC US'!I22/'CCaMC-BSCpUC US'!$B22 -> 1428207.4 | J22: =$B22*'CCaMC-BSCpUC US'!J22/'CCaMC-BSCpUC US'!$B22 -> 1420387.6 | ... AE22: =$B22*'CCaMC-BSCpUC US'!AE22/'CCaMC-BSCpUC US'!$B22 -> 1182085
A23: small modular reactor (NOT USED) | B23: 0 | C23: 0 | D23: 0 | E23: 0 | F23: 0 | G23: 0 | H23: 0 | I23: 0 | J23: 0 | K23: 0 | L23: 0 | M23: 0 | N23: 0 | O23: 0 | P23: 0 | Q23: 0 | R23: 0 | S23: 0 | T23: 0 | U23: 0 | V23: 0 | W23: 0 | X23: 0 | Y23: 0 | Z23: 0 | AA23: 0 | AB23: 0 | AC23: 0 | AD23: 0 | AE23: 0
A24: hydrogen combustion turbine (NOT USED) | B24: 0 | C24: 0 | D24: 0 | E24: 0 | F24: 0 | G24: 0 | H24: 0 | I24: 0 | J24: 0 | K24: 0 | L24: 0 | M24: 0 | N24: 0 | O24: 0 | P24: 0 | Q24: 0 | R24: 0 | S24: 0 | T24: 0 | U24: 0 | V24: 0 | W24: 0 | X24: 0 | Y24: 0 | Z24: 0 | AA24: 0 | AB24: 0 | AC24: 0 | AD24: 0 | AE24: 0
A25: hydrogen combined cycle (NOT USED) | B25: 0 | C25: 0 | D25: 0 | E25: 0 | F25: 0 | G25: 0 | H25: 0 | I25: 0 | J25: 0 | K25: 0 | L25: 0 | M25: 0 | N25: 0 | O25: 0 | P25: 0 | Q25: 0 | R25: 0 | S25: 0 | T25: 0 | U25: 0 | V25: 0 | W25: 0 | X25: 0 | Y25: 0 | Z25: 0 | AA25: 0 | AB25: 0 | AC25: 0 | AD25: 0 | AE25: 0

Sheet CCaMC-BCCUSRCpUC
A1: Unit: $/MW | B1: 2021 | C1: 2022 | D1: 2023 | E1: 2024 | F1: 2025 | G1: 2026 | H1: 2027 | I1: 2028 | J1: 2029 | K1: 2030 | L1: 2031 | M1: 2032 | N1: 2033 | O1: 2034 | P1: 2035 | Q1: 2036 | R1: 2037 | S1: 2038 | T1: 2039 | U1: 2040 | V1: 2041 | W1: 2042 | X1: 2043 | Y1: 2044 | Z1: 2045 | AA1: 2046 | AB1: 2047 | AC1: 2048 | AD1: 2049 | AE1: 2050
A2: Hard Coal (NOT USED) | B2: ='CCaMC-BCCUSRCpUC US'!B2 -> 99999 | C2: ='CCaMC-BCCUSRCpUC US'!C2 -> 99999 | D2: ='CCaMC-BCCUSRCpUC US'!D2 -> 99999 | E2: ='CCaMC-BCCUSRCpUC US'!E2 -> 99999 | F2: ='CCaMC-BCCUSRCpUC US'!F2 -> 99999 | G2: ='CCaMC-BCCUSRCpUC US'!G2 -> 99999 | H2: ='CCaMC-BCCUSRCpUC US'!H2 -> 99999 | I2: ='CCaMC-BCCUSRCpUC US'!I2 -> 99999 | ... AE2: ='CCaMC-BCCUSRCpUC US'!AE2 -> 99999
A3: Natural Gas Steam Turbine (NOT USED) | B3: ='CCaMC-BCCUSRCpUC US'!B3 -> 99999 | C3: ='CCaMC-BCCUSRCpUC US'!C3 -> 99999 | D3: ='CCaMC-BCCUSRCpUC US'!D3 -> 99999 | E3: ='CCaMC-BCCUSRCpUC US'!E3 -> 99999 | F3: ='CCaMC-BCCUSRCpUC US'!F3 -> 99999 | G3: ='CCaMC-BCCUSRCpUC US'!G3 -> 99999 | H3: ='CCaMC-BCCUSRCpUC US'!H3 -> 99999 | I3: ='CCaMC-BCCUSRCpUC US'!I3 -> 99999 | ... AE3: ='CCaMC-BCCUSRCpUC US'!AE3 -> 99999
A4: Natural Gas Combined Cycle (NOT USED) | B4: ='CCaMC-BCCUSRCpUC US'!B4 -> 99999 | C4: ='CCaMC-BCCUSRCpUC US'!C4 -> 99999 | D4: ='CCaMC-BCCUSRCpUC US'!D4 -> 99999 | E4: ='CCaMC-BCCUSRCpUC US'!E4 -> 99999 | F4: ='CCaMC-BCCUSRCpUC US'!F4 -> 99999 | G4: ='CCaMC-BCCUSRCpUC US'!G4 -> 99999 | H4: ='CCaMC-BCCUSRCpUC US'!H4 -> 99999 | I4: ='CCaMC-BCCUSRCpUC US'!I4 -> 99999 | ... AE4: ='CCaMC-BCCUSRCpUC US'!AE4 -> 99999
A5: Nuclear (NOT USED) | B5: ='CCaMC-BCCUSRCpUC US'!B5 -> 99999 | C5: ='CCaMC-BCCUSRCpUC US'!C5 -> 99999 | D5: ='CCaMC-BCCUSRCpUC US'!D5 -> 99999 | E5: ='CCaMC-BCCUSRCpUC US'!E5 -> 99999 | F5: ='CCaMC-BCCUSRCpUC US'!F5 -> 99999 | G5: ='CCaMC-BCCUSRCpUC US'!G5 -> 99999 | H5: ='CCaMC-BCCUSRCpUC US'!H5 -> 99999 | I5: ='CCaMC-BCCUSRCpUC US'!I5 -> 99999 | ... AE5: ='CCaMC-BCCUSRCpUC US'!AE5 -> 99999
A6: Hydro (NOT USED) | B6: ='CCaMC-BCCUSRCpUC US'!B6 -> 99999 | C6: ='CCaMC-BCCUSRCpUC US'!C6 -> 99999 | D6: ='CCaMC-BCCUSRCpUC US'!D6 -> 99999 | E6: ='CCaMC-BCCUSRCpUC US'!E6 -> 99999 | F6: ='CCaMC-BCCUSRCpUC US'!F6 -> 99999 | G6: ='CCaMC-BCCUSRCpUC US'!G6 -> 99999 | H6: ='CCaMC-BCCUSRCpUC US'!H6 -> 99999 | I6: ='CCaMC-BCCUSRCpUC US'!I6 -> 99999 | ... AE6: ='CCaMC-BCCUSRCpUC US'!AE6 -> 99999
A7: Onshore Wind (NOT USED) | B7: ='CCaMC-BCCUSRCpUC US'!B7 -> 99999 | C7: ='CCaMC-BCCUSRCpUC US'!C7 -> 99999 | D7: ='CCaMC-BCCUSRCpUC US'!D7 -> 99999 | E7: ='CCaMC-BCCUSRCpUC US'!E7 -> 99999 | F7: ='CCaMC-BCCUSRCpUC US'!F7 -> 99999 | G7: ='CCaMC-BCCUSRCpUC US'!G7 -> 99999 | H7: ='CCaMC-BCCUSRCpUC US'!H7 -> 99999 | I7: ='CCaMC-BCCUSRCpUC US'!I7 -> 99999 | ... AE7: ='CCaMC-BCCUSRCpUC US'!AE7 -> 99999
