Workbook

Sheet About
A1: TTS Transportation Technology Shareweights
A3: Source: | B3: All vehicles
B4: See SYVbT variable.
A6: Notes
A7: This variable provides the shareweights used in the modified logit equation for vehicle
A8: technology selection. We base them on estimated potential maximum sales shares in each year.
A9: For more on this, see the "Modified Logit" equation description at:
A10: https://jgcri.github.io/gcam-doc/choice.html
A12: When adapting the model to a new country or region, it may be helpful
A13: to calibrate this variable after replacing the input data for other variables.
A15: To make it easier to set the values for this variable, it is set up to interpolate
A16: between the current sales share and the potential 2050 sales share.
A17: The easiest way to calibrate this variable is to simply adjust these first and
A18: last year values (on the "Data" tab).
A20: Here are the assumptions we use for the U.S.:
B22: First and Last Simulated Year Values
B24: All nonroad modes have a 100% share of the "nonroad vehicle"
B25: technology type and a 0% share of the other technology types.
B26: Technology allocation is only used for on-road vehicles in the EPS.
B28: On-road modes all have a 0% share of the "nonroad vehicle"
B29: technology type.
B31: The technology that is the reference type for a given vehicle type is
B32: allowed a 100% share in all years. (This is "gasoline vehicle" for LDVs
B33: and motorbikes, "diesel vehicle" for HDVs.)
B35: First Simulated Year Values Only
B37: For passenger LDVs, we use the sales shares by technology from AEO 38
B38: in year 2030 as the maximum potential in the first simulated year.
... B89: as 100% of U.S. motorbike sales in 205.

Sheet SYVbT-passenger
A1: Number of Vehicles | B1: battery electric vehicle | C1: natural gas vehicle | D1: gasoline vehicle | E1: diesel vehicle | F1: plugin hybrid vehicle | G1: LPG vehicle | H1: hydrogen vehicle
A2: LDVs | B2: 84650.742 | C2: 25214.587 | D2: 8072982.1 | E2: 4633956.5 | F2: 477958.9 | G2: 1315953.3 | H2: 7728.571
A3: HDVs | B3: 34802.258 | C3: 10314.283 | D3: 3302335.3 | E3: 1895566.9 | F3: 195513.94 | G3: 538304.04 | H3: 3161.4504
A4: aircraft | B4: 0 | C4: 0 | D4: 0 | E4: 822 | F4: 0 | G4: 0 | H4: 0
A5: rail | B5: 1046.875 | C5: 0 | D5: 0 | E5: 669.83333 | F5: 0 | G5: 0 | H5: 0
A6: ships | B6: 0 | C6: 0 | D6: 0.48232457 | E6: 328 | F6: 0 | G6: 0.19292983 | H6: 0
A7: motorbikes | B7: 0 | C7: 0 | D7: 272564 | E7: 0 | F7: 0 | G7: 0 | H7: 0

Sheet SYVbT-freight
A1: Number of Vehicles | B1: battery electric vehicle | C1: natural gas vehicle | D1: gasoline vehicle | E1: diesel vehicle | F1: plugin hybrid vehicle | G1: LPG vehicle | H1: hydrogen vehicle
A2: LDVs | B2: 11965.957 | C2: 1366 | D2: 14255.143 | E2: 2664174.8 | F2: 0 | G2: 94459.997 | H2: 0
A3: HDVs | B3: 3543.0434 | C3: 0 | D3: 4220.857 | E3: 788845.18 | F3: 0 | G3: 27969.003 | H3: 0
A4: aircraft | B4: 0 | C4: 0 | D4: 0 | E4: 36 | F4: 0 | G4: 0 | H4: 0
A5: rail | B5: 87.5 | C5: 0 | D5: 0 | E5: 127 | F5: 0 | G5: 0 | H5: 0
A6: ships | B6: 0 | C6: 0 | D6: 2.11017 | E6: 630.10014 | F6: 0 | G6: 0.844068 | H6: 0
A7: motorbikes | B7: 0 | C7: 0 | D7: 2016445 | E7: 0 | F7: 0 | G7: 0 | H7: 0

Sheet Sheet1
B2: Time (Year) | C2: 2021 | D2: 2022 | E2: 2023 | F2: 2024 | G2: 2025 | H2: 2026 | I2: 2027 | J2: 2028 | K2: 2029 | L2: 2030 | M2: 2031 | N2: 2032 | O2: 2033 | P2: 2034 | Q2: 2035 | R2: 2036 | S2: 2037 | T2: 2038 | U2: 2039 | V2: 2040 | W2: 2041 | X2: 2042 | Y2: 2043 | Z2: 2044 | AA2: 2045 | AB2: 2046 | AC2: 2047 | AD2: 2048 | AE2: 2049 | AF2: 2050
B3: NPV of Lifetime Vehicle Cost[rail,passenger,battery electric vehicle] : NoSettings | C3: 49233500 | D3: 49235000 | E3: 49827200 | F3: 53422400 | G3: 54626000 | H3: 56242500 | I3: 55110700 | J3: 53945200 | K3: 53056900 | L3: 52838500 | M3: 52446900 | N3: 51692900 | O3: 53332800 | P3: 52977500 | Q3: 52958600 | R3: 52732200 | S3: 54927200 | T3: 56761300 | U3: 56864400 | V3: 56747500 | W3: 56851800 | X3: 56830700 | Y3: 56722200 | Z3: 56637500 | AA3: 56401400 | AB3: 56093800 | AC3: 55766000 | AD3: 55692800 | AE3: 55626600 | AF3: 55552800
B4: NPV of Lifetime Vehicle Cost[rail,passenger,natural gas vehicle] : NoSettings | C4: 1042500000 | D4: 1042500000 | E4: 1042500000 | F4: 1042500000 | G4: 1042500000 | H4: 1042500000 | I4: 1042500000 | J4: 1042500000 | K4: 1042500000 | L4: 1042500000 | M4: 1042500000 | N4: 1042500000 | O4: 1042500000 | P4: 1042500000 | Q4: 1042500000 | R4: 1042500000 | S4: 1042500000 | T4: 1042500000 | U4: 1042500000 | V4: 1042500000 | W4: 1042500000 | X4: 1042500000 | Y4: 1042500000 | Z4: 1042500000 | AA4: 1042500000 | AB4: 1042500000 | AC4: 1042500000 | AD4: 1042500000 | AE4: 1042500000 | AF4: 1042500000
B5: NPV of Lifetime Vehicle Cost[rail,passenger,gasoline vehicle] : NoSettings | C5: 1042500000 | D5: 1042500000 | E5: 1042500000 | F5: 1042500000 | G5: 1042500000 | H5: 1042500000 | I5: 1042500000 | J5: 1042500000 | K5: 1042500000 | L5: 1042500000 | M5: 1042500000 | N5: 1042500000 | O5: 1042500000 | P5: 1042500000 | Q5: 1042500000 | R5: 1042500000 | S5: 1042500000 | T5: 1042500000 | U5: 1042500000 | V5: 1042500000 | W5: 1042500000 | X5: 1042500000 | Y5: 1042500000 | Z5: 1042500000 | AA5: 1042500000 | AB5: 1042500000 | AC5: 1042500000 | AD5: 1042500000 | AE5: 1042500000 | AF5: 1042500000
B6: NPV of Lifetime Vehicle Cost[rail,passenger,diesel vehicle] : NoSettings | C6: 46244200 | D6: 46573700 | E6: 46593600 | F6: 46612900 | G6: 46633700 | H6: 46653800 | I6: 46675300 | J6: 46699700 | K6: 46721300 | L6: 46743700 | M6: 46766100 | N6: 46788500 | O6: 46816200 | P6: 46839500 | Q6: 46863400 | R6: 46888200 | S6: 46913000 | T6: 46938500 | U6: 46968100 | V6: 46994400 | W6: 47020800 | X6: 47047900 | Y6: 47075800 | Z6: 47103700 | AA6: 47136800 | AB6: 47166300 | AC6: 47195800 | AD6: 47226100 | AE6: 47256400 | AF6: 47287500
B7: NPV of Lifetime Vehicle Cost[rail,passenger,plugin hybrid vehicle] : NoSettings | C7: 1042500000 | D7: 1042500000 | E7: 1042500000 | F7: 1042500000 | G7: 1042500000 | H7: 1042500000 | I7: 1042500000 | J7: 1042500000 | K7: 1042500000 | L7: 1042500000 | M7: 1042500000 | N7: 1042500000 | O7: 1042500000 | P7: 1042500000 | Q7: 1042500000 | R7: 1042500000 | S7: 1042500000 | T7: 1042500000 | U7: 1042500000 | V7: 1042500000 | W7: 1042500000 | X7: 1042500000 | Y7: 1042500000 | Z7: 1042500000 | AA7: 1042500000 | AB7: 1042500000 | AC7: 1042500000 | AD7: 1042500000 | AE7: 1042500000 | AF7: 1042500000
B8: NPV of Lifetime Vehicle Cost[rail,passenger,LPG vehicle] : NoSettings | C8: 1042500000 | D8: 1042500000 | E8: 1042500000 | F8: 1042500000 | G8: 1042500000 | H8: 1042500000 | I8: 1042500000 | J8: 1042500000 | K8: 1042500000 | L8: 1042500000 | M8: 1042500000 | N8: 1042500000 | O8: 1042500000 | P8: 1042500000 | Q8: 1042500000 | R8: 1042500000 | S8: 1042500000 | T8: 1042500000 | U8: 1042500000 | V8: 1042500000 | W8: 1042500000 | X8: 1042500000 | Y8: 1042500000 | Z8: 1042500000 | AA8: 1042500000 | AB8: 1042500000 | AC8: 1042500000 | AD8: 1042500000 | AE8: 1042500000 | AF8: 1042500000
B9: NPV of Lifetime Vehicle Cost[rail,passenger,hydrogen vehicle] : NoSettings | C9: 35312800 | D9: 35076200 | E9: 35025300 | F9: 34820700 | G9: 34621000 | H9: 34427000 | I9: 34134300 | J9: 33850300 | K9: 33598700 | L9: 33364700 | M9: 33294400 | N9: 33238700 | O9: 33194300 | P9: 33155000 | Q9: 33114200 | R9: 33070700 | S9: 33030700 | T9: 32986500 | U9: 32950700 | V9: 32923500 | W9: 32896900 | X9: 32873600 | Y9: 32853400 | Z9: 32831400 | AA9: 32812300 | AB9: 32797800 | AC9: 32787600 | AD9: 32777800 | AE9: 32768500 | AF9: 32759300
B10: NPV of Lifetime Vehicle Cost[rail,freight,battery electric vehicle] : NoSettings | C10: 43448100 | D10: 43376300 | E10: 43602100 | F10: 45461100 | G10: 45986800 | H10: 46712100 | I10: 46125100 | J10: 45445100 | K10: 44915700 | L10: 44807100 | M10: 44522200 | N10: 44076900 | O10: 44876200 | P10: 44624300 | Q10: 44527000 | R10: 44418800 | S10: 45383800 | T10: 46162300 | U10: 46108500 | V10: 46054200 | W10: 46015200 | X10: 45919600 | Y10: 45857400 | Z10: 45735200 | AA10: 45547200 | AB10: 45330500 | AC10: 45173000 | AD10: 45064600 | AE10: 44961200 | AF10: 44856100
B11: NPV of Lifetime Vehicle Cost[rail,freight,natural gas vehicle] : NoSettings | C11: 1042500000 | D11: 1042500000 | E11: 1042500000 | F11: 1042500000 | G11: 1042500000 | H11: 1042500000 | I11: 1042500000 | J11: 1042500000 | K11: 1042500000 | L11: 1042500000 | M11: 1042500000 | N11: 1042500000 | O11: 1042500000 | P11: 1042500000 | Q11: 1042500000 | R11: 1042500000 | S11: 1042500000 | T11: 1042500000 | U11: 1042500000 | V11: 1042500000 | W11: 1042500000 | X11: 1042500000 | Y11: 1042500000 | Z11: 1042500000 | AA11: 1042500000 | AB11: 1042500000 | AC11: 1042500000 | AD11: 1042500000 | AE11: 1042500000 | AF11: 1042500000
B12: NPV of Lifetime Vehicle Cost[rail,freight,gasoline vehicle] : NoSettings | C12: 1042500000 | D12: 1042500000 | E12: 1042500000 | F12: 1042500000 | G12: 1042500000 | H12: 1042500000 | I12: 1042500000 | J12: 1042500000 | K12: 1042500000 | L12: 1042500000 | M12: 1042500000 | N12: 1042500000 | O12: 1042500000 | P12: 1042500000 | Q12: 1042500000 | R12: 1042500000 | S12: 1042500000 | T12: 1042500000 | U12: 1042500000 | V12: 1042500000 | W12: 1042500000 | X12: 1042500000 | Y12: 1042500000 | Z12: 1042500000 | AA12: 1042500000 | AB12: 1042500000 | AC12: 1042500000 | AD12: 1042500000 | AE12: 1042500000 | AF12: 1042500000
B13: NPV of Lifetime Vehicle Cost[rail,freight,diesel vehicle] : NoSettings | C13: 45539700 | D13: 45612800 | E13: 45614800 | F13: 45616600 | G13: 45618800 | H13: 45620700 | I13: 45623000 | J13: 45625100 | K13: 45627300 | L13: 45627100 | M13: 45629500 | N13: 45631800 | O13: 45634400 | P13: 45636900 | Q13: 45639400 | R13: 45642100 | S13: 45644800 | T13: 45647600 | U13: 45647800 | V13: 45650700 | W13: 45653600 | X13: 45656600 | Y13: 45659700 | Z13: 45662800 | AA13: 45663500 | AB13: 45666800 | AC13: 45670100 | AD13: 45673500 | AE13: 45676900 | AF13: 45677800
... B16: NPV of Lifetime Vehicle Cost[rail,freight,hydrogen vehicle] : NoSettings | C16: 39699000 | D16: 39030400 | E16: 38884700 | F16: 38306200 | G16: 37741600 | H16: 37193100 | I16: 36645600 | J16: 36104900 | K16: 35595500 | L16: 35102000 | M16: 35030200 | N16: 34952800 | O16: 34886900 | P16: 34822000 | Q16: 34759800 | R16: 34703400 | S16: 34650100 | T16: 34598600 | U16: 34550700 | V16: 34506900 | W16: 34464600 | X16: 34425100 | Y16: 34387600 | Z16: 34351600 | AA16: 34317400 | AB16: 34284900 | AC16: 34255200 | AD16: 34227000 | AE16: 34199900 | AF16: 34173100
B23: TTS Transportation Technology Shareweights[Vehicle Type,Cargo Type,Vehicle Technology
B24: ]
B25: * exp(MAX(1, NPV of Lifetime Vehicle Cost[Vehicle Type,Cargo Type,Vehicle Technology
B26: ]* Vehicle Allocation Unit Correction)/1e+06*TTLE Transportation Technology Logit Exponents
B27: [Vehicle Type,Cargo Type])
B28: )
B29: /
B30: (
B31: SUM(TTS Transportation Technology Shareweights[Vehicle Type,Cargo Type,Vehicle Technology
B32: !]
B33: * exp(MAX(1, NPV of Lifetime Vehicle Cost[Vehicle Type,Cargo Type,Vehicle Technology
B34: !]* Vehicle Allocation Unit Correction)/1e+06*TTLE Transportation Technology Logit Exponents
B35: [Vehicle Type,Cargo Type])

Sheet recalculated_shareweights
A1: year | B1: vehicle_type | C1: vehicle_tech | D1: cost | E1: share_obs | F1: w | G1: alpha
A2: 2021 | B2: passenger LDVs | C2: battery electric vehicle | D2: 58414 | E2: 0.035339647 | F2: 0.0734902 | G2: -2.6106032
A3: 2021 | B3: passenger LDVs | C3: natural gas vehicle | D3: 54549 | E3: 0.001699983 | F3: 0.0033619456 | G3: -5.6952354
A4: 2021 | B4: passenger LDVs | C4: gasoline vehicle | D4: 49019 | E4: 0.54334457 | F4: 1 | G4: 0
A5: 2021 | B5: passenger LDVs | C5: diesel vehicle | D5: 51468 | E5: 0.31188688 | F5: 0.59258194 | G5: -0.52326612
A6: 2021 | B6: passenger LDVs | C6: plugin hybrid vehicle | D6: 55470 | E6: 0.013419866 | F6: 0.026859262 | G6: -3.6171445
A7: 2021 | B7: passenger LDVs | C7: LPG vehicle | D7: 52804 | E7: 0.088569114 | F7: 0.17122865 | G7: -1.7647555
A8: 2021 | B8: passenger LDVs | C8: hydrogen vehicle | D8: 69435 | E8: 0.0057399426 | F8: 0.013775185 | G8: -4.2848865
A9: 2022 | B9: passenger LDVs | C9: battery electric vehicle | D9: 57856 | E9: 0.0748 | F9: 0.15782531 | G9: -1.8462665
A10: 2022 | B10: passenger LDVs | C10: natural gas vehicle | D10: 53186 | E10: 0.00163 | F10: 0.0032366568 | G10: -5.7332143
A11: 2022 | B11: passenger LDVs | C11: gasoline vehicle | D11: 50400 | E11: 0.52218 | F11: 1 | G11: 0
A12: 2022 | B12: passenger LDVs | C12: diesel vehicle | D12: 52846 | E12: 0.29974 | F12: 0.5925625 | G12: -0.52329892
A13: 2022 | B13: passenger LDVs | C13: plugin hybrid vehicle | D13: 55608 | E13: 0.00947 | F13: 0.019405875 | G13: -3.9421794
... A36: 2025 | B36: passenger LDVs | C36: hydrogen vehicle | D36: 56469 | E36: 0.00375 | F36: 0.0081683077 | G36: -4.8074935

Sheet Data
A1: We use sigmoidal interpolation for relatively new technologies (battery electric vehicles, natural gas vehicles, and | H1: Sigmoidal Curve Values for Vehicle Technologies (all except battery electric passenger LDVs) | N1: Sigmoidal Curve Values for battery electric passenger LDV Technologies
A2: plugin hybrid vehicles) and linear interpolation for other vehicle technologies. Technologies with constant values | H2: L | I2: 1 | N2: L | O2: 1
A3: do not require interpolation. | H3: k | I3: -0.3 | N3: k | O3: -1
A4: The values (to the right) that define the shape of the sigmoidal curve are assumptions, which neatly approach the | H4: Xo | I4: -16 | N4: Xo | O4: -5
A5: specified 2050 max sales share with a flattening curve. (Of course, linear interpolation is similarly an assumption.)
D6: Max Potential Sales Share | E6: Max Potential Sales Share | F6: Interpolation Method
C7: Psgr LDVs only | D7: 2020 | E7: 2035
D8: 2020 | E8: 2050 | F8: *for passenger LDVs only, see Assumptions page | R8: indicates value hardcoded during calibration
A9: Vehicle Type | B9: Cargo Type | C9: Vehicle Technology | D9: 2020 | E9: 2050 | H9: =D9 -> 2020 | I9: =H9+1 -> 2021 | J9: =I9+1 -> 2022 | K9: =J9+1 -> 2023 | L9: =K9+1 -> 2024 | M9: =L9+1 -> 2025 | N9: =M9+1 -> 2026 | O9: =N9+1 -> 2027 | P9: =O9+1 -> 2028 | ... AL9: =AK9+1 -> 2050
A10: LDVs | B10: passenger | C10: battery electric vehicle | D10: 0.1 | E10: 1 | F10: =IF(D10=E10,"n/a",IF(OR(C10="battery electric vehicle",C10="natural gas vehicle",C10="plugin hybrid vehicle"),"s-curve","linear")) -> s-curve | H10: =I10 -> 0.0734902 | I10: =SUMIFS(recalculated_shareweights!$F:$F,recalculated_shareweights!$A:$A,Data!I$9,recalculated_shareweights!$C:$C,Data!$C10) -> 0.0734902 | J10: =SUMIFS(recalculated_shareweights!$F:$F,recalculated_shareweights!$A:$A,Data!J$9,recalculated_shareweights!$C:$C,Data!$C10) -> 0.15782531 | K10: =SUMIFS(recalculated_shareweights!$F:$F,recalculated_shareweights!$A:$A,Data!K$9,recalculated_shareweights!$C:$C,Data!$C10) -> 0.1300531 | L10: =SUMIFS(recalculated_shareweights!$F:$F,recalculated_shareweights!$A:$A,Data!L$9,recalculated_shareweights!$C:$C,Data!$C10) -> 0.17042213 | M10: =SUMIFS(recalculated_shareweights!$F:$F,recalculated_shareweights!$A:$A,Data!M$9,recalculated_shareweights!$C:$C,Data!$C10) -> 0.26665969 | N10: =M10+($R$10-$M$10)/($R$9-$M$9) -> 0.30932775 | O10: =N10+($R$10-$M$10)/($R$9-$M$9) -> 0.35199581 | P10: =O10+($R$10-$M$10)/($R$9-$M$9) -> 0.39466388 | Q10: =P10+($R$10-$M$10)/($R$9-$M$9) -> 0.43733194 | R10: 0.48 | S10: =R10+($W$10-$R$10)/($W$9-$R$9) -> 0.504 | T10: =S10+($W$10-$R$10)/($W$9-$R$9) -> 0.528 | U10: =T10+($W$10-$R$10)/($W$9-$R$9) -> 0.552 | V10: =U10+($W$10-$R$10)/($W$9-$R$9) -> 0.576 | W10: 0.6 | X10: =W10+($AB$10-$W$10)/($AB$9-$W$9) -> 0.646 | Y10: =X10+($AB$10-$W$10)/($AB$9-$W$9) -> 0.692 | Z10: =Y10+($AB$10-$W$10)/($AB$9-$W$9) -> 0.738 | AA10: =Z10+($AB$10-$W$10)/($AB$9-$W$9) -> 0.784 | AB10: 0.83 | AC10: =AB10+($AG$10-$AB$10)/($AG$9-$AB$9) -> 0.944 | AD10: =AC10+($AG$10-$AB$10)/($AG$9-$AB$9) -> 1.058 | AE10: =AD10+($AG$10-$AB$10)/($AG$9-$AB$9) -> 1.172 | AF10: =AE10+($AG$10-$AB$10)/($AG$9-$AB$9) -> 1.286 | AG10: 1.4 | AH10: =AG10+($AL$10-$AG$10)/($AL$9-$AG$9) -> 1.64 | AI10: =AH10+($AL$10-$AG$10)/($AL$9-$AG$9) -> 1.88 | AJ10: =AI10+($AL$10-$AG$10)/($AL$9-$AG$9) -> 2.12 | AK10: =AJ10+($AL$10-$AG$10)/($AL$9-$AG$9) -> 2.36 | AL10: 2.6
C11: natural gas vehicle | D11: =1.25*INDEX('SYVbT-passenger'!$B$2:$H$2,MATCH(Data!$C11,'SYVbT-passenger'!$B$1:$H$1,0))/SUM('SYVbT-passenger'!$B$2:$H$2) -> 0.0021560593 | E11: =D11 -> 0.0021560593 | F11: =IF(D11=E11,"n/a",IF(OR(C11="battery electric vehicle",C11="natural gas vehicle",C11="plugin hybrid vehicle"),"s-curve","linear")) -> n/a | H11: =I11 -> 0.0033619456 | I11: =SUMIFS(recalculated_shareweights!$F:$F,recalculated_shareweights!$A:$A,Data!I$9,recalculated_shareweights!$C:$C,Data!$C11) -> 0.0033619456 | J11: =SUMIFS(recalculated_shareweights!$F:$F,recalculated_shareweights!$A:$A,Data!J$9,recalculated_shareweights!$C:$C,Data!$C11) -> 0.0032366568 | K11: =SUMIFS(recalculated_shareweights!$F:$F,recalculated_shareweights!$A:$A,Data!K$9,recalculated_shareweights!$C:$C,Data!$C11) -> 0.0033102715 | L11: =SUMIFS(recalculated_shareweights!$F:$F,recalculated_shareweights!$A:$A,Data!L$9,recalculated_shareweights!$C:$C,Data!$C11) -> 0.0033107854 | M11: =SUMIFS(recalculated_shareweights!$F:$F,recalculated_shareweights!$A:$A,Data!M$9,recalculated_shareweights!$C:$C,Data!$C11) -> 0.003309012 | N11: =M11 -> 0.003309012 | O11: =N11 -> 0.003309012 | P11: =O11 -> 0.003309012 | Q11: =P11 -> 0.003309012 | R11: =Q11 -> 0.003309012 | S11: =R11 -> 0.003309012 | T11: =S11 -> 0.003309012 | U11: =T11 -> 0.003309012 | ... AL11: =AK11 -> 0.003309012
C12: gasoline vehicle | D12: =1.25*INDEX('SYVbT-passenger'!$B$2:$H$2,MATCH(Data!$C12,'SYVbT-passenger'!$B$1:$H$1,0))/SUM('SYVbT-passenger'!$B$2:$H$2)*3 -> 2.0709237 | E12: =D12 -> 2.0709237 | F12: =IF(D12=E12,"n/a",IF(OR(C12="battery electric vehicle",C12="natural gas vehicle",C12="plugin hybrid vehicle"),"s-curve","linear")) -> n/a | H12: =I12 -> 1 | I12: =SUMIFS(recalculated_shareweights!$F:$F,recalculated_shareweights!$A:$A,Data!I$9,recalculated_shareweights!$C:$C,Data!$C12) -> 1 | J12: =SUMIFS(recalculated_shareweights!$F:$F,recalculated_shareweights!$A:$A,Data!J$9,recalculated_shareweights!$C:$C,Data!$C12) -> 1 | K12: =SUMIFS(recalculated_shareweights!$F:$F,recalculated_shareweights!$A:$A,Data!K$9,recalculated_shareweights!$C:$C,Data!$C12) -> 1 | L12: =SUMIFS(recalculated_shareweights!$F:$F,recalculated_shareweights!$A:$A,Data!L$9,recalculated_shareweights!$C:$C,Data!$C12) -> 1 | M12: =SUMIFS(recalculated_shareweights!$F:$F,recalculated_shareweights!$A:$A,Data!M$9,recalculated_shareweights!$C:$C,Data!$C12) -> 1 | N12: =M12 -> 1 | O12: =N12 -> 1 | P12: =O12 -> 1 | Q12: =P12 -> 1 | R12: =Q12 -> 1 | S12: =R12 -> 1 | T12: =S12 -> 1 | U12: =T12 -> 1 | ... AL12: =AK12 -> 1
C13: diesel vehicle | D13: =1.25*INDEX('SYVbT-passenger'!$B$2:$H$2,MATCH(Data!$C13,'SYVbT-passenger'!$B$1:$H$1,0))/SUM('SYVbT-passenger'!$B$2:$H$2)*3 -> 1.1887268 | E13: =D13 -> 1.1887268 | F13: =IF(D13=E13,"n/a",IF(OR(C13="battery electric vehicle",C13="natural gas vehicle",C13="plugin hybrid vehicle"),"s-curve","linear")) -> n/a | H13: =I13 -> 0.59258194 | I13: =SUMIFS(recalculated_shareweights!$F:$F,recalculated_shareweights!$A:$A,Data!I$9,recalculated_shareweights!$C:$C,Data!$C13) -> 0.59258194 | J13: =SUMIFS(recalculated_shareweights!$F:$F,recalculated_shareweights!$A:$A,Data!J$9,recalculated_shareweights!$C:$C,Data!$C13) -> 0.5925625 | K13: =SUMIFS(recalculated_shareweights!$F:$F,recalculated_shareweights!$A:$A,Data!K$9,recalculated_shareweights!$C:$C,Data!$C13) -> 0.59219617 | L13: =SUMIFS(recalculated_shareweights!$F:$F,recalculated_shareweights!$A:$A,Data!L$9,recalculated_shareweights!$C:$C,Data!$C13) -> 0.59201468 | M13: =SUMIFS(recalculated_shareweights!$F:$F,recalculated_shareweights!$A:$A,Data!M$9,recalculated_shareweights!$C:$C,Data!$C13) -> 0.59122138 | N13: =M13 -> 0.59122138 | O13: =N13 -> 0.59122138 | P13: =O13 -> 0.59122138 | Q13: =P13 -> 0.59122138 | R13: =Q13 -> 0.59122138 | S13: =R13 -> 0.59122138 | T13: =S13 -> 0.59122138 | U13: =T13 -> 0.59122138 | ... AL13: =AK13 -> 0.59122138
C14: plugin hybrid vehicle | D14: =1.25*INDEX('SYVbT-passenger'!$B$2:$H$2,MATCH(Data!$C14,'SYVbT-passenger'!$B$1:$H$1,0))/SUM('SYVbT-passenger'!$B$2:$H$2) -> 0.040869507 | E14: 0.25 | F14: =IF(D14=E14,"n/a",IF(OR(C14="battery electric vehicle",C14="natural gas vehicle",C14="plugin hybrid vehicle",C14="hydrogen vehicle"),"s-curve","linear")) -> s-curve | H14: =I14 -> 0.026859262 | I14: =SUMIFS(recalculated_shareweights!$F:$F,recalculated_shareweights!$A:$A,Data!I$9,recalculated_shareweights!$C:$C,Data!$C14) -> 0.026859262 | J14: =SUMIFS(recalculated_shareweights!$F:$F,recalculated_shareweights!$A:$A,Data!J$9,recalculated_shareweights!$C:$C,Data!$C14) -> 0.019405875 | K14: =SUMIFS(recalculated_shareweights!$F:$F,recalculated_shareweights!$A:$A,Data!K$9,recalculated_shareweights!$C:$C,Data!$C14) -> 0.01817122 | L14: =SUMIFS(recalculated_shareweights!$F:$F,recalculated_shareweights!$A:$A,Data!L$9,recalculated_shareweights!$C:$C,Data!$C14) -> 0.016437479 | M14: =SUMIFS(recalculated_shareweights!$F:$F,recalculated_shareweights!$A:$A,Data!M$9,recalculated_shareweights!$C:$C,Data!$C14) -> 0.022877518 | N14: =M14+($R$14-$M$14)/($R$9-$M$9) -> 0.027902014 | O14: =N14+($R$14-$M$14)/($R$9-$M$9) -> 0.032926511 | P14: =O14+($R$14-$M$14)/($R$9-$M$9) -> 0.037951007 | Q14: =P14+($R$14-$M$14)/($R$9-$M$9) -> 0.042975504 | R14: 0.048 | S14: =R14+($W$14-$R$14)/($W$9-$R$9) -> 0.0524 | T14: =S14+($W$14-$R$14)/($W$9-$R$9) -> 0.0568 | U14: =T14+($W$14-$R$14)/($W$9-$R$9) -> 0.0612 | V14: =U14+($W$14-$R$14)/($W$9-$R$9) -> 0.0656 | W14: 0.07 | X14: =W14+($AB$14-$W$14)/($AB$9-$W$9) -> 0.0746 | Y14: =X14+($AB$14-$W$14)/($AB$9-$W$9) -> 0.0792 | Z14: =Y14+($AB$14-$W$14)/($AB$9-$W$9) -> 0.0838 | AA14: =Z14+($AB$14-$W$14)/($AB$9-$W$9) -> 0.0884 | AB14: 0.093 | AC14: =AB14+($AG$14-$AB$14)/($AG$9-$AB$9) -> 0.1024 | AD14: =AC14+($AG$14-$AB$14)/($AG$9-$AB$9) -> 0.1118 | AE14: =AD14+($AG$14-$AB$14)/($AG$9-$AB$9) -> 0.1212 | AF14: =AE14+($AG$14-$AB$14)/($AG$9-$AB$9) -> 0.1306 | AG14: 0.14 | AH14: =AG14+($AL$14-$AG$14)/($AL$9-$AG$9) -> 0.164 | AI14: =AH14+($AL$14-$AG$14)/($AL$9-$AG$9) -> 0.188 | AJ14: =AI14+($AL$14-$AG$14)/($AL$9-$AG$9) -> 0.212 | AK14: =AJ14+($AL$14-$AG$14)/($AL$9-$AG$9) -> 0.236 | AL14: 0.26
C15: LPG vehicle | D15: =1.25*INDEX('SYVbT-passenger'!$B$2:$H$2,MATCH(Data!$C15,'SYVbT-passenger'!$B$1:$H$1,0))/SUM('SYVbT-passenger'!$B$2:$H$2) -> 0.11252508 | E15: =D15 -> 0.11252508 | F15: =IF(D15=E15,"n/a",IF(OR(C15="battery electric vehicle",C15="natural gas vehicle",C15="plugin hybrid vehicle",C15="hydrogen vehicle"),"s-curve","linear")) -> n/a | H15: =I15 -> 0.17122865 | I15: =SUMIFS(recalculated_shareweights!$F:$F,recalculated_shareweights!$A:$A,Data!I$9,recalculated_shareweights!$C:$C,Data!$C15) -> 0.17122865 | J15: =SUMIFS(recalculated_shareweights!$F:$F,recalculated_shareweights!$A:$A,Data!J$9,recalculated_shareweights!$C:$C,Data!$C15) -> 0.16057545 | K15: =SUMIFS(recalculated_shareweights!$F:$F,recalculated_shareweights!$A:$A,Data!K$9,recalculated_shareweights!$C:$C,Data!$C15) -> 0.16035867 | L15: =SUMIFS(recalculated_shareweights!$F:$F,recalculated_shareweights!$A:$A,Data!L$9,recalculated_shareweights!$C:$C,Data!$C15) -> 0.16022472 | M15: =SUMIFS(recalculated_shareweights!$F:$F,recalculated_shareweights!$A:$A,Data!M$9,recalculated_shareweights!$C:$C,Data!$C15) -> 0.15979464 | N15: =M15 -> 0.15979464 | O15: =N15 -> 0.15979464 | P15: =O15 -> 0.15979464 | Q15: =P15 -> 0.15979464 | R15: =Q15 -> 0.15979464 | S15: =R15 -> 0.15979464 | T15: =S15 -> 0.15979464 | U15: =T15 -> 0.15979464 | ... AL15: =AK15 -> 0.15979464
C16: hydrogen vehicle | D16: =1.25*INDEX('SYVbT-passenger'!$B$2:$H$2,MATCH(Data!$C16,'SYVbT-passenger'!$B$1:$H$1,0))/SUM('SYVbT-passenger'!$B$2:$H$2) -> 0.00066085784 | E16: =E11 -> 0.0021560593 | F16: =IF(D16=E16,"n/a",IF(OR(C16="battery electric vehicle",C16="natural gas vehicle",C16="plugin hybrid vehicle",C16="hydrogen vehicle"),"s-curve","linear")) -> s-curve | H16: =I16 -> 0.013775185 | I16: =SUMIFS(recalculated_shareweights!$F:$F,recalculated_shareweights!$A:$A,Data!I$9,recalculated_shareweights!$C:$C,Data!$C16) -> 0.013775185 | J16: =SUMIFS(recalculated_shareweights!$F:$F,recalculated_shareweights!$A:$A,Data!J$9,recalculated_shareweights!$C:$C,Data!$C16) -> 0.015049924 | K16: =SUMIFS(recalculated_shareweights!$F:$F,recalculated_shareweights!$A:$A,Data!K$9,recalculated_shareweights!$C:$C,Data!$C16) -> 0.0059981476 | L16: =SUMIFS(recalculated_shareweights!$F:$F,recalculated_shareweights!$A:$A,Data!L$9,recalculated_shareweights!$C:$C,Data!$C16) -> 0.0039475989 | M16: =SUMIFS(recalculated_shareweights!$F:$F,recalculated_shareweights!$A:$A,Data!M$9,recalculated_shareweights!$C:$C,Data!$C16) -> 0.0081683077 | N16: =M16 -> 0.0081683077 | O16: =N16 -> 0.0081683077 | P16: =O16 -> 0.0081683077 | Q16: =P16 -> 0.0081683077 | R16: =Q16 -> 0.0081683077 | S16: =R16 -> 0.0081683077 | T16: =S16 -> 0.0081683077 | U16: =T16 -> 0.0081683077 | ... AL16: =AK16 -> 0.0081683077
A17: LDVs | B17: freight | C17: battery electric vehicle | D17: 0.05 | E17: 0.5 | F17: =IF(D17=E17,"n/a",IF(OR(C17="battery electric vehicle",C17="natural gas vehicle",C17="plugin hybrid vehicle"),"s-curve","linear")) -> s-curve | H17: =D17 -> 0.05 | I17: =IF($F17="s-curve",$D17+($E17-$D17)*$I$2/(1+EXP($I$3*(COUNT($H$9:I$9)+$I$4))),TREND($D17:$E17,$D$9:$E$9,I$9)) -> 0.056648314 | J17: =IF($F17="s-curve",$D17+($E17-$D17)*$I$2/(1+EXP($I$3*(COUNT($H$9:J$9)+$I$4))),TREND($D17:$E17,$D$9:$E$9,J$9)) -> 0.058928138 | K17: =IF($F17="s-curve",$D17+($E17-$D17)*$I$2/(1+EXP($I$3*(COUNT($H$9:K$9)+$I$4))),TREND($D17:$E17,$D$9:$E$9,K$9)) -> 0.061968647 | L17: =IF($F17="s-curve",$D17+($E17-$D17)*$I$2/(1+EXP($I$3*(COUNT($H$9:L$9)+$I$4))),TREND($D17:$E17,$D$9:$E$9,L$9)) -> 0.066007035 | M17: =IF($F17="s-curve",$D17+($E17-$D17)*$I$2/(1+EXP($I$3*(COUNT($H$9:M$9)+$I$4))),TREND($D17:$E17,$D$9:$E$9,M$9)) -> 0.071341643 | N17: =IF($F17="s-curve",$D17+($E17-$D17)*$I$2/(1+EXP($I$3*(COUNT($H$9:N$9)+$I$4))),TREND($D17:$E17,$D$9:$E$9,N$9)) -> 0.07833801 | O17: =IF($F17="s-curve",$D17+($E17-$D17)*$I$2/(1+EXP($I$3*(COUNT($H$9:O$9)+$I$4))),TREND($D17:$E17,$D$9:$E$9,O$9)) -> 0.087427713 | P17: =IF($F17="s-curve",$D17+($E17-$D17)*$I$2/(1+EXP($I$3*(COUNT($H$9:P$9)+$I$4))),TREND($D17:$E17,$D$9:$E$9,P$9)) -> 0.09909357 | ... AL17: =IF($F17="s-curve",$D17+($E17-$D17)*$I$2/(1+EXP($I$3*(COUNT($H$9:AL$9)+$I$4))),TREND($D17:$E17,$D$9:$E$9,AL$9)) -> 0.49505588
C18: natural gas vehicle | D18: =MIN(1.25*INDEX('SYVbT-freight'!$B$2:$H$2,MATCH(Data!$C11,'SYVbT-passenger'!$B$1:$H$1,0))/SUM('SYVbT-freight'!$B$2:$H$2),1) -> 0.00061283704 | E18: =D18 -> 0.00061283704 | F18: linear | H18: =D18 -> 0.00061283704 | I18: =IF($F18="s-curve",$D18+($E18-$D18)*$I$2/(1+EXP($I$3*(COUNT($H$9:I$9)+$I$4))),TREND($D18:$E18,$D$9:$E$9,I$9)) -> 0.00061283704 | J18: =IF($F18="s-curve",$D18+($E18-$D18)*$I$2/(1+EXP($I$3*(COUNT($H$9:J$9)+$I$4))),TREND($D18:$E18,$D$9:$E$9,J$9)) -> 0.00061283704 | K18: =IF($F18="s-curve",$D18+($E18-$D18)*$I$2/(1+EXP($I$3*(COUNT($H$9:K$9)+$I$4))),TREND($D18:$E18,$D$9:$E$9,K$9)) -> 0.00061283704 | L18: =IF($F18="s-curve",$D18+($E18-$D18)*$I$2/(1+EXP($I$3*(COUNT($H$9:L$9)+$I$4))),TREND($D18:$E18,$D$9:$E$9,L$9)) -> 0.00061283704 | M18: =IF($F18="s-curve",$D18+($E18-$D18)*$I$2/(1+EXP($I$3*(COUNT($H$9:M$9)+$I$4))),TREND($D18:$E18,$D$9:$E$9,M$9)) -> 0.00061283704 | N18: =IF($F18="s-curve",$D18+($E18-$D18)*$I$2/(1+EXP($I$3*(COUNT($H$9:N$9)+$I$4))),TREND($D18:$E18,$D$9:$E$9,N$9)) -> 0.00061283704 | O18: =IF($F18="s-curve",$D18+($E18-$D18)*$I$2/(1+EXP($I$3*(COUNT($H$9:O$9)+$I$4))),TREND($D18:$E18,$D$9:$E$9,O$9)) -> 0.00061283704 | P18: =IF($F18="s-curve",$D18+($E18-$D18)*$I$2/(1+EXP($I$3*(COUNT($H$9:P$9)+$I$4))),TREND($D18:$E18,$D$9:$E$9,P$9)) -> 0.00061283704 | ... AL18: =IF($F18="s-curve",$D18+($E18-$D18)*$I$2/(1+EXP($I$3*(COUNT($H$9:AL$9)+$I$4))),TREND($D18:$E18,$D$9:$E$9,AL$9)) -> 0.00061283704
C19: gasoline vehicle | D19: =MIN(1.25*INDEX('SYVbT-freight'!$B$2:$H$2,MATCH(Data!$C12,'SYVbT-passenger'!$B$1:$H$1,0))/SUM('SYVbT-freight'!$B$2:$H$2),1)*3 -> 0.019186119 | E19: =D19 -> 0.019186119 | F19: =IF(D19=E19,"n/a",IF(OR(C19="battery electric vehicle",C19="natural gas vehicle",C19="plugin hybrid vehicle"),"s-curve","linear")) -> n/a | H19: =D19 -> 0.019186119 | I19: =IF($F19="s-curve",$D19+($E19-$D19)*$I$2/(1+EXP($I$3*(COUNT($H$9:I$9)+$I$4))),TREND($D19:$E19,$D$9:$E$9,I$9)) -> 0.019186119 | J19: =IF($F19="s-curve",$D19+($E19-$D19)*$I$2/(1+EXP($I$3*(COUNT($H$9:J$9)+$I$4))),TREND($D19:$E19,$D$9:$E$9,J$9)) -> 0.019186119 | K19: =IF($F19="s-curve",$D19+($E19-$D19)*$I$2/(1+EXP($I$3*(COUNT($H$9:K$9)+$I$4))),TREND($D19:$E19,$D$9:$E$9,K$9)) -> 0.019186119 | L19: =IF($F19="s-curve",$D19+($E19-$D19)*$I$2/(1+EXP($I$3*(COUNT($H$9:L$9)+$I$4))),TREND($D19:$E19,$D$9:$E$9,L$9)) -> 0.019186119 | M19: =IF($F19="s-curve",$D19+($E19-$D19)*$I$2/(1+EXP($I$3*(COUNT($H$9:M$9)+$I$4))),TREND($D19:$E19,$D$9:$E$9,M$9)) -> 0.019186119 | N19: =IF($F19="s-curve",$D19+($E19-$D19)*$I$2/(1+EXP($I$3*(COUNT($H$9:N$9)+$I$4))),TREND($D19:$E19,$D$9:$E$9,N$9)) -> 0.019186119 | O19: =IF($F19="s-curve",$D19+($E19-$D19)*$I$2/(1+EXP($I$3*(COUNT($H$9:O$9)+$I$4))),TREND($D19:$E19,$D$9:$E$9,O$9)) -> 0.019186119 | P19: =IF($F19="s-curve",$D19+($E19-$D19)*$I$2/(1+EXP($I$3*(COUNT($H$9:P$9)+$I$4))),TREND($D19:$E19,$D$9:$E$9,P$9)) -> 0.019186119 | ... AL19: =IF($F19="s-curve",$D19+($E19-$D19)*$I$2/(1+EXP($I$3*(COUNT($H$9:AL$9)+$I$4))),TREND($D19:$E19,$D$9:$E$9,AL$9)) -> 0.019186119
C20: diesel vehicle | D20: 3 | E20: =D20 -> 3 | F20: =IF(D20=E20,"n/a",IF(OR(C20="battery electric vehicle",C20="natural gas vehicle",C20="plugin hybrid vehicle"),"s-curve","linear")) -> n/a | H20: =D20 -> 3 | I20: =IF($F20="s-curve",$D20+($E20-$D20)*$I$2/(1+EXP($I$3*(COUNT($H$9:I$9)+$I$4))),TREND($D20:$E20,$D$9:$E$9,I$9)) -> 3 | J20: =IF($F20="s-curve",$D20+($E20-$D20)*$I$2/(1+EXP($I$3*(COUNT($H$9:J$9)+$I$4))),TREND($D20:$E20,$D$9:$E$9,J$9)) -> 3 | K20: =IF($F20="s-curve",$D20+($E20-$D20)*$I$2/(1+EXP($I$3*(COUNT($H$9:K$9)+$I$4))),TREND($D20:$E20,$D$9:$E$9,K$9)) -> 3 | L20: =IF($F20="s-curve",$D20+($E20-$D20)*$I$2/(1+EXP($I$3*(COUNT($H$9:L$9)+$I$4))),TREND($D20:$E20,$D$9:$E$9,L$9)) -> 3 | M20: =IF($F20="s-curve",$D20+($E20-$D20)*$I$2/(1+EXP($I$3*(COUNT($H$9:M$9)+$I$4))),TREND($D20:$E20,$D$9:$E$9,M$9)) -> 3 | N20: =IF($F20="s-curve",$D20+($E20-$D20)*$I$2/(1+EXP($I$3*(COUNT($H$9:N$9)+$I$4))),TREND($D20:$E20,$D$9:$E$9,N$9)) -> 3 | O20: =IF($F20="s-curve",$D20+($E20-$D20)*$I$2/(1+EXP($I$3*(COUNT($H$9:O$9)+$I$4))),TREND($D20:$E20,$D$9:$E$9,O$9)) -> 3 | P20: =IF($F20="s-curve",$D20+($E20-$D20)*$I$2/(1+EXP($I$3*(COUNT($H$9:P$9)+$I$4))),TREND($D20:$E20,$D$9:$E$9,P$9)) -> 3 | ... AL20: =IF($F20="s-curve",$D20+($E20-$D20)*$I$2/(1+EXP($I$3*(COUNT($H$9:AL$9)+$I$4))),TREND($D20:$E20,$D$9:$E$9,AL$9)) -> 3
C21: plugin hybrid vehicle | D21: =MIN(1.25*INDEX('SYVbT-freight'!$B$2:$H$2,MATCH(Data!$C14,'SYVbT-passenger'!$B$1:$H$1,0))/SUM('SYVbT-freight'!$B$2:$H$2),1) -> 0 | E21: =E14 -> 0.25 | F21: =IF(D21=E21,"n/a",IF(OR(C21="battery electric vehicle",C21="natural gas vehicle",C21="plugin hybrid vehicle"),"s-curve","linear")) -> s-curve | H21: =D21 -> 0 | I21: =IF($F21="s-curve",$D21+($E21-$D21)*$I$2/(1+EXP($I$3*(COUNT($H$9:I$9)+$I$4))),TREND($D21:$E21,$D$9:$E$9,I$9)) -> 0.0036935079 | J21: =IF($F21="s-curve",$D21+($E21-$D21)*$I$2/(1+EXP($I$3*(COUNT($H$9:J$9)+$I$4))),TREND($D21:$E21,$D$9:$E$9,J$9)) -> 0.0049600764 | K21: =IF($F21="s-curve",$D21+($E21-$D21)*$I$2/(1+EXP($I$3*(COUNT($H$9:K$9)+$I$4))),TREND($D21:$E21,$D$9:$E$9,K$9)) -> 0.0066492484 | L21: =IF($F21="s-curve",$D21+($E21-$D21)*$I$2/(1+EXP($I$3*(COUNT($H$9:L$9)+$I$4))),TREND($D21:$E21,$D$9:$E$9,L$9)) -> 0.0088927973 | M21: =IF($F21="s-curve",$D21+($E21-$D21)*$I$2/(1+EXP($I$3*(COUNT($H$9:M$9)+$I$4))),TREND($D21:$E21,$D$9:$E$9,M$9)) -> 0.011856468 | N21: =IF($F21="s-curve",$D21+($E21-$D21)*$I$2/(1+EXP($I$3*(COUNT($H$9:N$9)+$I$4))),TREND($D21:$E21,$D$9:$E$9,N$9)) -> 0.015743339 | O21: =IF($F21="s-curve",$D21+($E21-$D21)*$I$2/(1+EXP($I$3*(COUNT($H$9:O$9)+$I$4))),TREND($D21:$E21,$D$9:$E$9,O$9)) -> 0.020793174 | P21: =IF($F21="s-curve",$D21+($E21-$D21)*$I$2/(1+EXP($I$3*(COUNT($H$9:P$9)+$I$4))),TREND($D21:$E21,$D$9:$E$9,P$9)) -> 0.027274205 | ... AL21: =IF($F21="s-curve",$D21+($E21-$D21)*$I$2/(1+EXP($I$3*(COUNT($H$9:AL$9)+$I$4))),TREND($D21:$E21,$D$9:$E$9,AL$9)) -> 0.24725326
C22: LPG vehicle | D22: =MIN(1.25*INDEX('SYVbT-freight'!$B$2:$H$2,MATCH(Data!$C15,'SYVbT-passenger'!$B$1:$H$1,0))/SUM('SYVbT-freight'!$B$2:$H$2),1) -> 0.042378174 | E22: =D22 -> 0.042378174 | F22: =IF(D22=E22,"n/a",IF(OR(C22="battery electric vehicle",C22="natural gas vehicle",C22="plugin hybrid vehicle",C22="hydrogen vehicle"),"s-curve","linear")) -> n/a | H22: =D22 -> 0.042378174 | I22: =IF($F22="s-curve",$D22+($E22-$D22)*$I$2/(1+EXP($I$3*(COUNT($H$9:I$9)+$I$4))),TREND($D22:$E22,$D$9:$E$9,I$9)) -> 0.042378174 | J22: =IF($F22="s-curve",$D22+($E22-$D22)*$I$2/(1+EXP($I$3*(COUNT($H$9:J$9)+$I$4))),TREND($D22:$E22,$D$9:$E$9,J$9)) -> 0.042378174 | K22: =IF($F22="s-curve",$D22+($E22-$D22)*$I$2/(1+EXP($I$3*(COUNT($H$9:K$9)+$I$4))),TREND($D22:$E22,$D$9:$E$9,K$9)) -> 0.042378174 | L22: =IF($F22="s-curve",$D22+($E22-$D22)*$I$2/(1+EXP($I$3*(COUNT($H$9:L$9)+$I$4))),TREND($D22:$E22,$D$9:$E$9,L$9)) -> 0.042378174 | M22: =IF($F22="s-curve",$D22+($E22-$D22)*$I$2/(1+EXP($I$3*(COUNT($H$9:M$9)+$I$4))),TREND($D22:$E22,$D$9:$E$9,M$9)) -> 0.042378174 | N22: =IF($F22="s-curve",$D22+($E22-$D22)*$I$2/(1+EXP($I$3*(COUNT($H$9:N$9)+$I$4))),TREND($D22:$E22,$D$9:$E$9,N$9)) -> 0.042378174 | O22: =IF($F22="s-curve",$D22+($E22-$D22)*$I$2/(1+EXP($I$3*(COUNT($H$9:O$9)+$I$4))),TREND($D22:$E22,$D$9:$E$9,O$9)) -> 0.042378174 | P22: =IF($F22="s-curve",$D22+($E22-$D22)*$I$2/(1+EXP($I$3*(COUNT($H$9:P$9)+$I$4))),TREND($D22:$E22,$D$9:$E$9,P$9)) -> 0.042378174 | ... AL22: =IF($F22="s-curve",$D22+($E22-$D22)*$I$2/(1+EXP($I$3*(COUNT($H$9:AL$9)+$I$4))),TREND($D22:$E22,$D$9:$E$9,AL$9)) -> 0.042378174
C23: hydrogen vehicle | D23: =MIN(1.25*INDEX('SYVbT-freight'!$B$2:$H$2,MATCH(Data!$C16,'SYVbT-passenger'!$B$1:$H$1,0))/SUM('SYVbT-freight'!$B$2:$H$2),1) -> 0 | E23: =E18 -> 0.00061283704 | F23: =IF(D23=E23,"n/a",IF(OR(C23="battery electric vehicle",C23="natural gas vehicle",C23="plugin hybrid vehicle",C23="hydrogen vehicle"),"s-curve","linear")) -> s-curve | H23: =D23 -> 0 | I23: =IF($F23="s-curve",$D23+($E23-$D23)*$I$2/(1+EXP($I$3*(COUNT($H$9:I$9)+$I$4))),TREND($D23:$E23,$D$9:$E$9,I$9)) -> 9.0540739e-06 | J23: =IF($F23="s-curve",$D23+($E23-$D23)*$I$2/(1+EXP($I$3*(COUNT($H$9:J$9)+$I$4))),TREND($D23:$E23,$D$9:$E$9,J$9)) -> 1.2158874e-05 | K23: =IF($F23="s-curve",$D23+($E23-$D23)*$I$2/(1+EXP($I$3*(COUNT($H$9:K$9)+$I$4))),TREND($D23:$E23,$D$9:$E$9,K$9)) -> 1.6299623e-05 | L23: =IF($F23="s-curve",$D23+($E23-$D23)*$I$2/(1+EXP($I$3*(COUNT($H$9:L$9)+$I$4))),TREND($D23:$E23,$D$9:$E$9,L$9)) -> 2.1799342e-05 | M23: =IF($F23="s-curve",$D23+($E23-$D23)*$I$2/(1+EXP($I$3*(COUNT($H$9:M$9)+$I$4))),TREND($D23:$E23,$D$9:$E$9,M$9)) -> 2.9064332e-05 | N23: =IF($F23="s-curve",$D23+($E23-$D23)*$I$2/(1+EXP($I$3*(COUNT($H$9:N$9)+$I$4))),TREND($D23:$E23,$D$9:$E$9,N$9)) -> 3.8592405e-05 | O23: =IF($F23="s-curve",$D23+($E23-$D23)*$I$2/(1+EXP($I$3*(COUNT($H$9:O$9)+$I$4))),TREND($D23:$E23,$D$9:$E$9,O$9)) -> 5.0971309e-05 | P23: =IF($F23="s-curve",$D23+($E23-$D23)*$I$2/(1+EXP($I$3*(COUNT($H$9:P$9)+$I$4))),TREND($D23:$E23,$D$9:$E$9,P$9)) -> 6.6858573e-05 | ... AL23: =IF($F23="s-curve",$D23+($E23-$D23)*$I$2/(1+EXP($I$3*(COUNT($H$9:AL$9)+$I$4))),TREND($D23:$E23,$D$9:$E$9,AL$9)) -> 0.00060610384
A24: HDVs | B24: passenger | C24: battery electric vehicle | D24: 0.05 | E24: 1 | F24: =IF(D24=E24,"n/a",IF(OR(C24="battery electric vehicle",C24="natural gas vehicle",C24="plugin hybrid vehicle"),"s-curve","linear")) -> s-curve | H24: =D24 -> 0.05 | I24: =IF($F24="s-curve",$D24+($E24-$D24)*$I$2/(1+EXP($I$3*(COUNT($H$9:I$9)+$I$4))),TREND($D24:$E24,$D$9:$E$9,I$9)) -> 0.06403533 | J24: =IF($F24="s-curve",$D24+($E24-$D24)*$I$2/(1+EXP($I$3*(COUNT($H$9:J$9)+$I$4))),TREND($D24:$E24,$D$9:$E$9,J$9)) -> 0.06884829 | K24: =IF($F24="s-curve",$D24+($E24-$D24)*$I$2/(1+EXP($I$3*(COUNT($H$9:K$9)+$I$4))),TREND($D24:$E24,$D$9:$E$9,K$9)) -> 0.075267144 | L24: =IF($F24="s-curve",$D24+($E24-$D24)*$I$2/(1+EXP($I$3*(COUNT($H$9:L$9)+$I$4))),TREND($D24:$E24,$D$9:$E$9,L$9)) -> 0.08379263 | M24: =IF($F24="s-curve",$D24+($E24-$D24)*$I$2/(1+EXP($I$3*(COUNT($H$9:M$9)+$I$4))),TREND($D24:$E24,$D$9:$E$9,M$9)) -> 0.09505458 | N24: =IF($F24="s-curve",$D24+($E24-$D24)*$I$2/(1+EXP($I$3*(COUNT($H$9:N$9)+$I$4))),TREND($D24:$E24,$D$9:$E$9,N$9)) -> 0.10982469 | O24: =IF($F24="s-curve",$D24+($E24-$D24)*$I$2/(1+EXP($I$3*(COUNT($H$9:O$9)+$I$4))),TREND($D24:$E24,$D$9:$E$9,O$9)) -> 0.12901406 | P24: =IF($F24="s-curve",$D24+($E24-$D24)*$I$2/(1+EXP($I$3*(COUNT($H$9:P$9)+$I$4))),TREND($D24:$E24,$D$9:$E$9,P$9)) -> 0.15364198 | ... AL24: =IF($F24="s-curve",$D24+($E24-$D24)*$I$2/(1+EXP($I$3*(COUNT($H$9:AL$9)+$I$4))),TREND($D24:$E24,$D$9:$E$9,AL$9)) -> 0.9895624
C25: natural gas vehicle | D25: =MIN(1.25*INDEX('SYVbT-passenger'!$B$3:$H$3,MATCH(Data!$C11,'SYVbT-passenger'!$B$1:$H$1,0))/SUM('SYVbT-passenger'!$B$3:$H$3),1) -> 0.0021559962 | E25: =D25 -> 0.0021559962 | F25: =IF(D25=E25,"n/a",IF(OR(C25="battery electric vehicle",C25="natural gas vehicle",C25="plugin hybrid vehicle"),"s-curve","linear")) -> n/a | H25: =D25 -> 0.0021559962 | I25: =IF($F25="s-curve",$D25+($E25-$D25)*$I$2/(1+EXP($I$3*(COUNT($H$9:I$9)+$I$4))),TREND($D25:$E25,$D$9:$E$9,I$9)) -> 0.0021559962 | J25: =IF($F25="s-curve",$D25+($E25-$D25)*$I$2/(1+EXP($I$3*(COUNT($H$9:J$9)+$I$4))),TREND($D25:$E25,$D$9:$E$9,J$9)) -> 0.0021559962 | K25: =IF($F25="s-curve",$D25+($E25-$D25)*$I$2/(1+EXP($I$3*(COUNT($H$9:K$9)+$I$4))),TREND($D25:$E25,$D$9:$E$9,K$9)) -> 0.0021559962 | L25: =IF($F25="s-curve",$D25+($E25-$D25)*$I$2/(1+EXP($I$3*(COUNT($H$9:L$9)+$I$4))),TREND($D25:$E25,$D$9:$E$9,L$9)) -> 0.0021559962 | M25: =IF($F25="s-curve",$D25+($E25-$D25)*$I$2/(1+EXP($I$3*(COUNT($H$9:M$9)+$I$4))),TREND($D25:$E25,$D$9:$E$9,M$9)) -> 0.0021559962 | N25: =IF($F25="s-curve",$D25+($E25-$D25)*$I$2/(1+EXP($I$3*(COUNT($H$9:N$9)+$I$4))),TREND($D25:$E25,$D$9:$E$9,N$9)) -> 0.0021559962 | O25: =IF($F25="s-curve",$D25+($E25-$D25)*$I$2/(1+EXP($I$3*(COUNT($H$9:O$9)+$I$4))),TREND($D25:$E25,$D$9:$E$9,O$9)) -> 0.0021559962 | P25: =IF($F25="s-curve",$D25+($E25-$D25)*$I$2/(1+EXP($I$3*(COUNT($H$9:P$9)+$I$4))),TREND($D25:$E25,$D$9:$E$9,P$9)) -> 0.0021559962 | ... AL25: =IF($F25="s-curve",$D25+($E25-$D25)*$I$2/(1+EXP($I$3*(COUNT($H$9:AL$9)+$I$4))),TREND($D25:$E25,$D$9:$E$9,AL$9)) -> 0.0021559962
C26: gasoline vehicle | D26: =MIN(1.25*INDEX('SYVbT-passenger'!$B$3:$H$3,MATCH(Data!$C12,'SYVbT-passenger'!$B$1:$H$1,0))/SUM('SYVbT-passenger'!$B$3:$H$3),1)*3 -> 2.070863 | E26: =D26 -> 2.070863 | F26: =IF(D26=E26,"n/a",IF(OR(C26="battery electric vehicle",C26="natural gas vehicle",C26="plugin hybrid vehicle"),"s-curve","linear")) -> n/a | H26: =D26 -> 2.070863 | I26: =IF($F26="s-curve",$D26+($E26-$D26)*$I$2/(1+EXP($I$3*(COUNT($H$9:I$9)+$I$4))),TREND($D26:$E26,$D$9:$E$9,I$9)) -> 2.070863 | J26: =IF($F26="s-curve",$D26+($E26-$D26)*$I$2/(1+EXP($I$3*(COUNT($H$9:J$9)+$I$4))),TREND($D26:$E26,$D$9:$E$9,J$9)) -> 2.070863 | K26: =IF($F26="s-curve",$D26+($E26-$D26)*$I$2/(1+EXP($I$3*(COUNT($H$9:K$9)+$I$4))),TREND($D26:$E26,$D$9:$E$9,K$9)) -> 2.070863 | L26: =IF($F26="s-curve",$D26+($E26-$D26)*$I$2/(1+EXP($I$3*(COUNT($H$9:L$9)+$I$4))),TREND($D26:$E26,$D$9:$E$9,L$9)) -> 2.070863 | M26: =IF($F26="s-curve",$D26+($E26-$D26)*$I$2/(1+EXP($I$3*(COUNT($H$9:M$9)+$I$4))),TREND($D26:$E26,$D$9:$E$9,M$9)) -> 2.070863 | N26: =IF($F26="s-curve",$D26+($E26-$D26)*$I$2/(1+EXP($I$3*(COUNT($H$9:N$9)+$I$4))),TREND($D26:$E26,$D$9:$E$9,N$9)) -> 2.070863 | O26: =IF($F26="s-curve",$D26+($E26-$D26)*$I$2/(1+EXP($I$3*(COUNT($H$9:O$9)+$I$4))),TREND($D26:$E26,$D$9:$E$9,O$9)) -> 2.070863 | P26: =IF($F26="s-curve",$D26+($E26-$D26)*$I$2/(1+EXP($I$3*(COUNT($H$9:P$9)+$I$4))),TREND($D26:$E26,$D$9:$E$9,P$9)) -> 2.070863 | ... AL26: =IF($F26="s-curve",$D26+($E26-$D26)*$I$2/(1+EXP($I$3*(COUNT($H$9:AL$9)+$I$4))),TREND($D26:$E26,$D$9:$E$9,AL$9)) -> 2.070863
C27: diesel vehicle | D27: =MIN(1.25*INDEX('SYVbT-passenger'!$B$3:$H$3,MATCH(Data!$C13,'SYVbT-passenger'!$B$1:$H$1,0))/SUM('SYVbT-passenger'!$B$3:$H$3),1)*3 -> 1.188692 | E27: =D27 -> 1.188692 | F27: =IF(D27=E27,"n/a",IF(OR(C27="battery electric vehicle",C27="natural gas vehicle",C27="plugin hybrid vehicle"),"s-curve","linear")) -> n/a | H27: =D27 -> 1.188692 | I27: =IF($F27="s-curve",$D27+($E27-$D27)*$I$2/(1+EXP($I$3*(COUNT($H$9:I$9)+$I$4))),TREND($D27:$E27,$D$9:$E$9,I$9)) -> 1.188692 | J27: =IF($F27="s-curve",$D27+($E27-$D27)*$I$2/(1+EXP($I$3*(COUNT($H$9:J$9)+$I$4))),TREND($D27:$E27,$D$9:$E$9,J$9)) -> 1.188692 | K27: =IF($F27="s-curve",$D27+($E27-$D27)*$I$2/(1+EXP($I$3*(COUNT($H$9:K$9)+$I$4))),TREND($D27:$E27,$D$9:$E$9,K$9)) -> 1.188692 | L27: =IF($F27="s-curve",$D27+($E27-$D27)*$I$2/(1+EXP($I$3*(COUNT($H$9:L$9)+$I$4))),TREND($D27:$E27,$D$9:$E$9,L$9)) -> 1.188692 | M27: =IF($F27="s-curve",$D27+($E27-$D27)*$I$2/(1+EXP($I$3*(COUNT($H$9:M$9)+$I$4))),TREND($D27:$E27,$D$9:$E$9,M$9)) -> 1.188692 | N27: =IF($F27="s-curve",$D27+($E27-$D27)*$I$2/(1+EXP($I$3*(COUNT($H$9:N$9)+$I$4))),TREND($D27:$E27,$D$9:$E$9,N$9)) -> 1.188692 | O27: =IF($F27="s-curve",$D27+($E27-$D27)*$I$2/(1+EXP($I$3*(COUNT($H$9:O$9)+$I$4))),TREND($D27:$E27,$D$9:$E$9,O$9)) -> 1.188692 | P27: =IF($F27="s-curve",$D27+($E27-$D27)*$I$2/(1+EXP($I$3*(COUNT($H$9:P$9)+$I$4))),TREND($D27:$E27,$D$9:$E$9,P$9)) -> 1.188692 | ... AL27: =IF($F27="s-curve",$D27+($E27-$D27)*$I$2/(1+EXP($I$3*(COUNT($H$9:AL$9)+$I$4))),TREND($D27:$E27,$D$9:$E$9,AL$9)) -> 1.188692
C28: plugin hybrid vehicle | D28: =MIN(1.25*INDEX('SYVbT-passenger'!$B$3:$H$3,MATCH(Data!$C14,'SYVbT-passenger'!$B$1:$H$1,0))/SUM('SYVbT-passenger'!$B$3:$H$3),1) -> 0.040868311 | E28: =D28 -> 0.040868311 | F28: =IF(D28=E28,"n/a",IF(OR(C28="battery electric vehicle",C28="natural gas vehicle",C28="plugin hybrid vehicle"),"s-curve","linear")) -> n/a | H28: =D28 -> 0.040868311 | I28: =IF($F28="s-curve",$D28+($E28-$D28)*$I$2/(1+EXP($I$3*(COUNT($H$9:I$9)+$I$4))),TREND($D28:$E28,$D$9:$E$9,I$9)) -> 0.040868311 | J28: =IF($F28="s-curve",$D28+($E28-$D28)*$I$2/(1+EXP($I$3*(COUNT($H$9:J$9)+$I$4))),TREND($D28:$E28,$D$9:$E$9,J$9)) -> 0.040868311 | K28: =IF($F28="s-curve",$D28+($E28-$D28)*$I$2/(1+EXP($I$3*(COUNT($H$9:K$9)+$I$4))),TREND($D28:$E28,$D$9:$E$9,K$9)) -> 0.040868311 | L28: =IF($F28="s-curve",$D28+($E28-$D28)*$I$2/(1+EXP($I$3*(COUNT($H$9:L$9)+$I$4))),TREND($D28:$E28,$D$9:$E$9,L$9)) -> 0.040868311 | M28: =IF($F28="s-curve",$D28+($E28-$D28)*$I$2/(1+EXP($I$3*(COUNT($H$9:M$9)+$I$4))),TREND($D28:$E28,$D$9:$E$9,M$9)) -> 0.040868311 | N28: =IF($F28="s-curve",$D28+($E28-$D28)*$I$2/(1+EXP($I$3*(COUNT($H$9:N$9)+$I$4))),TREND($D28:$E28,$D$9:$E$9,N$9)) -> 0.040868311 | O28: =IF($F28="s-curve",$D28+($E28-$D28)*$I$2/(1+EXP($I$3*(COUNT($H$9:O$9)+$I$4))),TREND($D28:$E28,$D$9:$E$9,O$9)) -> 0.040868311 | P28: =IF($F28="s-curve",$D28+($E28-$D28)*$I$2/(1+EXP($I$3*(COUNT($H$9:P$9)+$I$4))),TREND($D28:$E28,$D$9:$E$9,P$9)) -> 0.040868311 | ... AL28: =IF($F28="s-curve",$D28+($E28-$D28)*$I$2/(1+EXP($I$3*(COUNT($H$9:AL$9)+$I$4))),TREND($D28:$E28,$D$9:$E$9,AL$9)) -> 0.040868311
C29: LPG vehicle | D29: =MIN(1.25*INDEX('SYVbT-passenger'!$B$3:$H$3,MATCH(Data!$C15,'SYVbT-passenger'!$B$1:$H$1,0))/SUM('SYVbT-passenger'!$B$3:$H$3),1) -> 0.11252178 | E29: =D29 -> 0.11252178 | F29: =IF(D29=E29,"n/a",IF(OR(C29="battery electric vehicle",C29="natural gas vehicle",C29="plugin hybrid vehicle",C29="hydrogen vehicle"),"s-curve","linear")) -> n/a | H29: =D29 -> 0.11252178 | I29: =IF($F29="s-curve",$D29+($E29-$D29)*$I$2/(1+EXP($I$3*(COUNT($H$9:I$9)+$I$4))),TREND($D29:$E29,$D$9:$E$9,I$9)) -> 0.11252178 | J29: =IF($F29="s-curve",$D29+($E29-$D29)*$I$2/(1+EXP($I$3*(COUNT($H$9:J$9)+$I$4))),TREND($D29:$E29,$D$9:$E$9,J$9)) -> 0.11252178 | K29: =IF($F29="s-curve",$D29+($E29-$D29)*$I$2/(1+EXP($I$3*(COUNT($H$9:K$9)+$I$4))),TREND($D29:$E29,$D$9:$E$9,K$9)) -> 0.11252178 | L29: =IF($F29="s-curve",$D29+($E29-$D29)*$I$2/(1+EXP($I$3*(COUNT($H$9:L$9)+$I$4))),TREND($D29:$E29,$D$9:$E$9,L$9)) -> 0.11252178 | M29: =IF($F29="s-curve",$D29+($E29-$D29)*$I$2/(1+EXP($I$3*(COUNT($H$9:M$9)+$I$4))),TREND($D29:$E29,$D$9:$E$9,M$9)) -> 0.11252178 | N29: =IF($F29="s-curve",$D29+($E29-$D29)*$I$2/(1+EXP($I$3*(COUNT($H$9:N$9)+$I$4))),TREND($D29:$E29,$D$9:$E$9,N$9)) -> 0.11252178 | O29: =IF($F29="s-curve",$D29+($E29-$D29)*$I$2/(1+EXP($I$3*(COUNT($H$9:O$9)+$I$4))),TREND($D29:$E29,$D$9:$E$9,O$9)) -> 0.11252178 | P29: =IF($F29="s-curve",$D29+($E29-$D29)*$I$2/(1+EXP($I$3*(COUNT($H$9:P$9)+$I$4))),TREND($D29:$E29,$D$9:$E$9,P$9)) -> 0.11252178 | ... AL29: =IF($F29="s-curve",$D29+($E29-$D29)*$I$2/(1+EXP($I$3*(COUNT($H$9:AL$9)+$I$4))),TREND($D29:$E29,$D$9:$E$9,AL$9)) -> 0.11252178
C30: hydrogen vehicle | D30: =MIN(1.25*INDEX('SYVbT-passenger'!$B$3:$H$3,MATCH(Data!$C16,'SYVbT-passenger'!$B$1:$H$1,0))/SUM('SYVbT-passenger'!$B$3:$H$3),1) -> 0.0006608385 | E30: =E25 -> 0.0021559962 | F30: =IF(D30=E30,"n/a",IF(OR(C30="battery electric vehicle",C30="natural gas vehicle",C30="plugin hybrid vehicle",C30="hydrogen vehicle"),"s-curve","linear")) -> s-curve | H30: =D30 -> 0.0006608385 | I30: =IF($F30="s-curve",$D30+($E30-$D30)*$I$2/(1+EXP($I$3*(COUNT($H$9:I$9)+$I$4))),TREND($D30:$E30,$D$9:$E$9,I$9)) -> 0.00068292801 | J30: =IF($F30="s-curve",$D30+($E30-$D30)*$I$2/(1+EXP($I$3*(COUNT($H$9:J$9)+$I$4))),TREND($D30:$E30,$D$9:$E$9,J$9)) -> 0.00069050288 | K30: =IF($F30="s-curve",$D30+($E30-$D30)*$I$2/(1+EXP($I$3*(COUNT($H$9:K$9)+$I$4))),TREND($D30:$E30,$D$9:$E$9,K$9)) -> 0.0007006052 | L30: =IF($F30="s-curve",$D30+($E30-$D30)*$I$2/(1+EXP($I$3*(COUNT($H$9:L$9)+$I$4))),TREND($D30:$E30,$D$9:$E$9,L$9)) -> 0.00071402304 | M30: =IF($F30="s-curve",$D30+($E30-$D30)*$I$2/(1+EXP($I$3*(COUNT($H$9:M$9)+$I$4))),TREND($D30:$E30,$D$9:$E$9,M$9)) -> 0.00073174766 | N30: =IF($F30="s-curve",$D30+($E30-$D30)*$I$2/(1+EXP($I$3*(COUNT($H$9:N$9)+$I$4))),TREND($D30:$E30,$D$9:$E$9,N$9)) -> 0.0007549936 | O30: =IF($F30="s-curve",$D30+($E30-$D30)*$I$2/(1+EXP($I$3*(COUNT($H$9:O$9)+$I$4))),TREND($D30:$E30,$D$9:$E$9,O$9)) -> 0.0007851948 | P30: =IF($F30="s-curve",$D30+($E30-$D30)*$I$2/(1+EXP($I$3*(COUNT($H$9:P$9)+$I$4))),TREND($D30:$E30,$D$9:$E$9,P$9)) -> 0.00082395545 | ... AL30: =IF($F30="s-curve",$D30+($E30-$D30)*$I$2/(1+EXP($I$3*(COUNT($H$9:AL$9)+$I$4))),TREND($D30:$E30,$D$9:$E$9,AL$9)) -> 0.002139569
A31: HDVs | B31: freight | C31: battery electric vehicle | D31: =MIN(1.25*INDEX('SYVbT-freight'!$B$3:$H$3,MATCH(Data!$C10,'SYVbT-passenger'!$B$1:$H$1,0))/SUM('SYVbT-freight'!$B$3:$H$3),1) -> 0.0053709945 | E31: 0.5 | F31: =IF(D31=E31,"n/a",IF(OR(C31="battery electric vehicle",C31="natural gas vehicle",C31="plugin hybrid vehicle"),"s-curve","linear")) -> s-curve | H31: =D31 -> 0.0053709945 | I31: =IF($F31="s-curve",$D31+($E31-$D31)*$I$2/(1+EXP($I$3*(COUNT($H$9:I$9)+$I$4))),TREND($D31:$E31,$D$9:$E$9,I$9)) -> 0.012678659 | J31: =IF($F31="s-curve",$D31+($E31-$D31)*$I$2/(1+EXP($I$3*(COUNT($H$9:J$9)+$I$4))),TREND($D31:$E31,$D$9:$E$9,J$9)) -> 0.015184585 | K31: =IF($F31="s-curve",$D31+($E31-$D31)*$I$2/(1+EXP($I$3*(COUNT($H$9:K$9)+$I$4))),TREND($D31:$E31,$D$9:$E$9,K$9)) -> 0.018526639 | L31: =IF($F31="s-curve",$D31+($E31-$D31)*$I$2/(1+EXP($I$3*(COUNT($H$9:L$9)+$I$4))),TREND($D31:$E31,$D$9:$E$9,L$9)) -> 0.022965536 | M31: =IF($F31="s-curve",$D31+($E31-$D31)*$I$2/(1+EXP($I$3*(COUNT($H$9:M$9)+$I$4))),TREND($D31:$E31,$D$9:$E$9,M$9)) -> 0.028829207 | N31: =IF($F31="s-curve",$D31+($E31-$D31)*$I$2/(1+EXP($I$3*(COUNT($H$9:N$9)+$I$4))),TREND($D31:$E31,$D$9:$E$9,N$9)) -> 0.036519443 | O31: =IF($F31="s-curve",$D31+($E31-$D31)*$I$2/(1+EXP($I$3*(COUNT($H$9:O$9)+$I$4))),TREND($D31:$E31,$D$9:$E$9,O$9)) -> 0.046510623 | P31: =IF($F31="s-curve",$D31+($E31-$D31)*$I$2/(1+EXP($I$3*(COUNT($H$9:P$9)+$I$4))),TREND($D31:$E31,$D$9:$E$9,P$9)) -> 0.059333447 | ... AL31: =IF($F31="s-curve",$D31+($E31-$D31)*$I$2/(1+EXP($I$3*(COUNT($H$9:AL$9)+$I$4))),TREND($D31:$E31,$D$9:$E$9,AL$9)) -> 0.49456554
C32: natural gas vehicle | D32: =MIN(1.25*INDEX('SYVbT-freight'!$B$3:$H$3,MATCH(Data!$C11,'SYVbT-passenger'!$B$1:$H$1,0))/SUM('SYVbT-freight'!$B$3:$H$3),1) -> 0 | E32: =D32 -> 0 | F32: =IF(D32=E32,"n/a",IF(OR(C32="battery electric vehicle",C32="natural gas vehicle",C32="plugin hybrid vehicle"),"s-curve","linear")) -> n/a | H32: =D32 -> 0 | I32: =IF($F32="s-curve",$D32+($E32-$D32)*$I$2/(1+EXP($I$3*(COUNT($H$9:I$9)+$I$4))),TREND($D32:$E32,$D$9:$E$9,I$9)) -> 0 | J32: =IF($F32="s-curve",$D32+($E32-$D32)*$I$2/(1+EXP($I$3*(COUNT($H$9:J$9)+$I$4))),TREND($D32:$E32,$D$9:$E$9,J$9)) -> 0 | K32: =IF($F32="s-curve",$D32+($E32-$D32)*$I$2/(1+EXP($I$3*(COUNT($H$9:K$9)+$I$4))),TREND($D32:$E32,$D$9:$E$9,K$9)) -> 0 | L32: =IF($F32="s-curve",$D32+($E32-$D32)*$I$2/(1+EXP($I$3*(COUNT($H$9:L$9)+$I$4))),TREND($D32:$E32,$D$9:$E$9,L$9)) -> 0 | M32: =IF($F32="s-curve",$D32+($E32-$D32)*$I$2/(1+EXP($I$3*(COUNT($H$9:M$9)+$I$4))),TREND($D32:$E32,$D$9:$E$9,M$9)) -> 0 | N32: =IF($F32="s-curve",$D32+($E32-$D32)*$I$2/(1+EXP($I$3*(COUNT($H$9:N$9)+$I$4))),TREND($D32:$E32,$D$9:$E$9,N$9)) -> 0 | O32: =IF($F32="s-curve",$D32+($E32-$D32)*$I$2/(1+EXP($I$3*(COUNT($H$9:O$9)+$I$4))),TREND($D32:$E32,$D$9:$E$9,O$9)) -> 0 | P32: =IF($F32="s-curve",$D32+($E32-$D32)*$I$2/(1+EXP($I$3*(COUNT($H$9:P$9)+$I$4))),TREND($D32:$E32,$D$9:$E$9,P$9)) -> 0 | ... AL32: =IF($F32="s-curve",$D32+($E32-$D32)*$I$2/(1+EXP($I$3*(COUNT($H$9:AL$9)+$I$4))),TREND($D32:$E32,$D$9:$E$9,AL$9)) -> 0
C33: gasoline vehicle | D33: =MIN(1.25*INDEX('SYVbT-freight'!$B$3:$H$3,MATCH(Data!$C12,'SYVbT-passenger'!$B$1:$H$1,0))/SUM('SYVbT-freight'!$B$3:$H$3),1)*3 -> 0.01919553 | E33: =D33 -> 0.01919553 | F33: =IF(D33=E33,"n/a",IF(OR(C33="battery electric vehicle",C33="natural gas vehicle",C33="plugin hybrid vehicle"),"s-curve","linear")) -> n/a | H33: =D33 -> 0.01919553 | I33: =IF($F33="s-curve",$D33+($E33-$D33)*$I$2/(1+EXP($I$3*(COUNT($H$9:I$9)+$I$4))),TREND($D33:$E33,$D$9:$E$9,I$9)) -> 0.01919553 | J33: =IF($F33="s-curve",$D33+($E33-$D33)*$I$2/(1+EXP($I$3*(COUNT($H$9:J$9)+$I$4))),TREND($D33:$E33,$D$9:$E$9,J$9)) -> 0.01919553 | K33: =IF($F33="s-curve",$D33+($E33-$D33)*$I$2/(1+EXP($I$3*(COUNT($H$9:K$9)+$I$4))),TREND($D33:$E33,$D$9:$E$9,K$9)) -> 0.01919553 | L33: =IF($F33="s-curve",$D33+($E33-$D33)*$I$2/(1+EXP($I$3*(COUNT($H$9:L$9)+$I$4))),TREND($D33:$E33,$D$9:$E$9,L$9)) -> 0.01919553 | M33: =IF($F33="s-curve",$D33+($E33-$D33)*$I$2/(1+EXP($I$3*(COUNT($H$9:M$9)+$I$4))),TREND($D33:$E33,$D$9:$E$9,M$9)) -> 0.01919553 | N33: =IF($F33="s-curve",$D33+($E33-$D33)*$I$2/(1+EXP($I$3*(COUNT($H$9:N$9)+$I$4))),TREND($D33:$E33,$D$9:$E$9,N$9)) -> 0.01919553 | O33: =IF($F33="s-curve",$D33+($E33-$D33)*$I$2/(1+EXP($I$3*(COUNT($H$9:O$9)+$I$4))),TREND($D33:$E33,$D$9:$E$9,O$9)) -> 0.01919553 | P33: =IF($F33="s-curve",$D33+($E33-$D33)*$I$2/(1+EXP($I$3*(COUNT($H$9:P$9)+$I$4))),TREND($D33:$E33,$D$9:$E$9,P$9)) -> 0.01919553 | ... AL33: =IF($F33="s-curve",$D33+($E33-$D33)*$I$2/(1+EXP($I$3*(COUNT($H$9:AL$9)+$I$4))),TREND($D33:$E33,$D$9:$E$9,AL$9)) -> 0.01919553
C34: diesel vehicle | D34: =MIN(1.25*INDEX('SYVbT-freight'!$B$3:$H$3,MATCH(Data!$C13,'SYVbT-passenger'!$B$1:$H$1,0))/SUM('SYVbT-freight'!$B$3:$H$3),1)*3 -> 3 | E34: =D34 -> 3 | F34: =IF(D34=E34,"n/a",IF(OR(C34="battery electric vehicle",C34="natural gas vehicle",C34="plugin hybrid vehicle"),"s-curve","linear")) -> n/a | H34: =D34 -> 3 | I34: =IF($F34="s-curve",$D34+($E34-$D34)*$I$2/(1+EXP($I$3*(COUNT($H$9:I$9)+$I$4))),TREND($D34:$E34,$D$9:$E$9,I$9)) -> 3 | J34: =IF($F34="s-curve",$D34+($E34-$D34)*$I$2/(1+EXP($I$3*(COUNT($H$9:J$9)+$I$4))),TREND($D34:$E34,$D$9:$E$9,J$9)) -> 3 | K34: =IF($F34="s-curve",$D34+($E34-$D34)*$I$2/(1+EXP($I$3*(COUNT($H$9:K$9)+$I$4))),TREND($D34:$E34,$D$9:$E$9,K$9)) -> 3 | L34: =IF($F34="s-curve",$D34+($E34-$D34)*$I$2/(1+EXP($I$3*(COUNT($H$9:L$9)+$I$4))),TREND($D34:$E34,$D$9:$E$9,L$9)) -> 3 | M34: =IF($F34="s-curve",$D34+($E34-$D34)*$I$2/(1+EXP($I$3*(COUNT($H$9:M$9)+$I$4))),TREND($D34:$E34,$D$9:$E$9,M$9)) -> 3 | N34: =IF($F34="s-curve",$D34+($E34-$D34)*$I$2/(1+EXP($I$3*(COUNT($H$9:N$9)+$I$4))),TREND($D34:$E34,$D$9:$E$9,N$9)) -> 3 | O34: =IF($F34="s-curve",$D34+($E34-$D34)*$I$2/(1+EXP($I$3*(COUNT($H$9:O$9)+$I$4))),TREND($D34:$E34,$D$9:$E$9,O$9)) -> 3 | P34: =IF($F34="s-curve",$D34+($E34-$D34)*$I$2/(1+EXP($I$3*(COUNT($H$9:P$9)+$I$4))),TREND($D34:$E34,$D$9:$E$9,P$9)) -> 3 | ... AL34: =IF($F34="s-curve",$D34+($E34-$D34)*$I$2/(1+EXP($I$3*(COUNT($H$9:AL$9)+$I$4))),TREND($D34:$E34,$D$9:$E$9,AL$9)) -> 3
C35: plugin hybrid vehicle | D35: =MIN(1.25*INDEX('SYVbT-freight'!$B$3:$H$3,MATCH(Data!$C14,'SYVbT-passenger'!$B$1:$H$1,0))/SUM('SYVbT-freight'!$B$3:$H$3),1) -> 0 | E35: =D35 -> 0 | F35: =IF(D35=E35,"n/a",IF(OR(C35="battery electric vehicle",C35="natural gas vehicle",C35="plugin hybrid vehicle"),"s-curve","linear")) -> n/a | H35: =D35 -> 0 | I35: =IF($F35="s-curve",$D35+($E35-$D35)*$I$2/(1+EXP($I$3*(COUNT($H$9:I$9)+$I$4))),TREND($D35:$E35,$D$9:$E$9,I$9)) -> 0 | J35: =IF($F35="s-curve",$D35+($E35-$D35)*$I$2/(1+EXP($I$3*(COUNT($H$9:J$9)+$I$4))),TREND($D35:$E35,$D$9:$E$9,J$9)) -> 0 | K35: =IF($F35="s-curve",$D35+($E35-$D35)*$I$2/(1+EXP($I$3*(COUNT($H$9:K$9)+$I$4))),TREND($D35:$E35,$D$9:$E$9,K$9)) -> 0 | L35: =IF($F35="s-curve",$D35+($E35-$D35)*$I$2/(1+EXP($I$3*(COUNT($H$9:L$9)+$I$4))),TREND($D35:$E35,$D$9:$E$9,L$9)) -> 0 | M35: =IF($F35="s-curve",$D35+($E35-$D35)*$I$2/(1+EXP($I$3*(COUNT($H$9:M$9)+$I$4))),TREND($D35:$E35,$D$9:$E$9,M$9)) -> 0 | N35: =IF($F35="s-curve",$D35+($E35-$D35)*$I$2/(1+EXP($I$3*(COUNT($H$9:N$9)+$I$4))),TREND($D35:$E35,$D$9:$E$9,N$9)) -> 0 | O35: =IF($F35="s-curve",$D35+($E35-$D35)*$I$2/(1+EXP($I$3*(COUNT($H$9:O$9)+$I$4))),TREND($D35:$E35,$D$9:$E$9,O$9)) -> 0 | P35: =IF($F35="s-curve",$D35+($E35-$D35)*$I$2/(1+EXP($I$3*(COUNT($H$9:P$9)+$I$4))),TREND($D35:$E35,$D$9:$E$9,P$9)) -> 0 | ... AL35: =IF($F35="s-curve",$D35+($E35-$D35)*$I$2/(1+EXP($I$3*(COUNT($H$9:AL$9)+$I$4))),TREND($D35:$E35,$D$9:$E$9,AL$9)) -> 0
C36: LPG vehicle | D36: =MIN(1.25*INDEX('SYVbT-freight'!$B$3:$H$3,MATCH(Data!$C15,'SYVbT-passenger'!$B$1:$H$1,0))/SUM('SYVbT-freight'!$B$3:$H$3),1) -> 0.042398961 | E36: =D36 -> 0.042398961 | F36: =IF(D36=E36,"n/a",IF(OR(C36="battery electric vehicle",C36="natural gas vehicle",C36="plugin hybrid vehicle",C36="hydrogen vehicle"),"s-curve","linear")) -> n/a | H36: =D36 -> 0.042398961 | I36: =IF($F36="s-curve",$D36+($E36-$D36)*$I$2/(1+EXP($I$3*(COUNT($H$9:I$9)+$I$4))),TREND($D36:$E36,$D$9:$E$9,I$9)) -> 0.042398961 | J36: =IF($F36="s-curve",$D36+($E36-$D36)*$I$2/(1+EXP($I$3*(COUNT($H$9:J$9)+$I$4))),TREND($D36:$E36,$D$9:$E$9,J$9)) -> 0.042398961 | K36: =IF($F36="s-curve",$D36+($E36-$D36)*$I$2/(1+EXP($I$3*(COUNT($H$9:K$9)+$I$4))),TREND($D36:$E36,$D$9:$E$9,K$9)) -> 0.042398961 | L36: =IF($F36="s-curve",$D36+($E36-$D36)*$I$2/(1+EXP($I$3*(COUNT($H$9:L$9)+$I$4))),TREND($D36:$E36,$D$9:$E$9,L$9)) -> 0.042398961 | M36: =IF($F36="s-curve",$D36+($E36-$D36)*$I$2/(1+EXP($I$3*(COUNT($H$9:M$9)+$I$4))),TREND($D36:$E36,$D$9:$E$9,M$9)) -> 0.042398961 | N36: =IF($F36="s-curve",$D36+($E36-$D36)*$I$2/(1+EXP($I$3*(COUNT($H$9:N$9)+$I$4))),TREND($D36:$E36,$D$9:$E$9,N$9)) -> 0.042398961 | O36: =IF($F36="s-curve",$D36+($E36-$D36)*$I$2/(1+EXP($I$3*(COUNT($H$9:O$9)+$I$4))),TREND($D36:$E36,$D$9:$E$9,O$9)) -> 0.042398961 | P36: =IF($F36="s-curve",$D36+($E36-$D36)*$I$2/(1+EXP($I$3*(COUNT($H$9:P$9)+$I$4))),TREND($D36:$E36,$D$9:$E$9,P$9)) -> 0.042398961 | ... AL36: =IF($F36="s-curve",$D36+($E36-$D36)*$I$2/(1+EXP($I$3*(COUNT($H$9:AL$9)+$I$4))),TREND($D36:$E36,$D$9:$E$9,AL$9)) -> 0.042398961
C37: hydrogen vehicle | D37: =MIN(1.25*INDEX('SYVbT-freight'!$B$3:$H$3,MATCH(Data!$C16,'SYVbT-passenger'!$B$1:$H$1,0))/SUM('SYVbT-freight'!$B$3:$H$3),1) -> 0 | E37: =E36 -> 0.042398961 | F37: =IF(D37=E37,"n/a",IF(OR(C37="battery electric vehicle",C37="natural gas vehicle",C37="plugin hybrid vehicle",C37="hydrogen vehicle"),"s-curve","linear")) -> s-curve | H37: =D37 -> 0 | I37: =IF($F37="s-curve",$D37+($E37-$D37)*$I$2/(1+EXP($I$3*(COUNT($H$9:I$9)+$I$4))),TREND($D37:$E37,$D$9:$E$9,I$9)) -> 0.00062640359 | J37: =IF($F37="s-curve",$D37+($E37-$D37)*$I$2/(1+EXP($I$3*(COUNT($H$9:J$9)+$I$4))),TREND($D37:$E37,$D$9:$E$9,J$9)) -> 0.00084120834 | K37: =IF($F37="s-curve",$D37+($E37-$D37)*$I$2/(1+EXP($I$3*(COUNT($H$9:K$9)+$I$4))),TREND($D37:$E37,$D$9:$E$9,K$9)) -> 0.0011276849 | L37: =IF($F37="s-curve",$D37+($E37-$D37)*$I$2/(1+EXP($I$3*(COUNT($H$9:L$9)+$I$4))),TREND($D37:$E37,$D$9:$E$9,L$9)) -> 0.0015081815 | M37: =IF($F37="s-curve",$D37+($E37-$D37)*$I$2/(1+EXP($I$3*(COUNT($H$9:M$9)+$I$4))),TREND($D37:$E37,$D$9:$E$9,M$9)) -> 0.0020108077 | N37: =IF($F37="s-curve",$D37+($E37-$D37)*$I$2/(1+EXP($I$3*(COUNT($H$9:N$9)+$I$4))),TREND($D37:$E37,$D$9:$E$9,N$9)) -> 0.0026700048 | O37: =IF($F37="s-curve",$D37+($E37-$D37)*$I$2/(1+EXP($I$3*(COUNT($H$9:O$9)+$I$4))),TREND($D37:$E37,$D$9:$E$9,O$9)) -> 0.0035264359 | P37: =IF($F37="s-curve",$D37+($E37-$D37)*$I$2/(1+EXP($I$3*(COUNT($H$9:P$9)+$I$4))),TREND($D37:$E37,$D$9:$E$9,P$9)) -> 0.0046255918 | ... AL37: =IF($F37="s-curve",$D37+($E37-$D37)*$I$2/(1+EXP($I$3*(COUNT($H$9:AL$9)+$I$4))),TREND($D37:$E37,$D$9:$E$9,AL$9)) -> 0.041933126
A38: aircraft | B38: passenger | C38: battery electric vehicle | D38: 0 | E38: 0 | F38: =IF(D38=E38,"n/a",IF(OR(C38="battery electric vehicle",C38="natural gas vehicle",C38="plugin hybrid vehicle"),"s-curve","linear")) -> n/a | H38: =D38 -> 0 | I38: =IF($F38="s-curve",$D38+($E38-$D38)*$I$2/(1+EXP($I$3*(COUNT($H$9:I$9)+$I$4))),TREND($D38:$E38,$D$9:$E$9,I$9)) -> 0 | J38: =IF($F38="s-curve",$D38+($E38-$D38)*$I$2/(1+EXP($I$3*(COUNT($H$9:J$9)+$I$4))),TREND($D38:$E38,$D$9:$E$9,J$9)) -> 0 | K38: =IF($F38="s-curve",$D38+($E38-$D38)*$I$2/(1+EXP($I$3*(COUNT($H$9:K$9)+$I$4))),TREND($D38:$E38,$D$9:$E$9,K$9)) -> 0 | L38: =IF($F38="s-curve",$D38+($E38-$D38)*$I$2/(1+EXP($I$3*(COUNT($H$9:L$9)+$I$4))),TREND($D38:$E38,$D$9:$E$9,L$9)) -> 0 | M38: =IF($F38="s-curve",$D38+($E38-$D38)*$I$2/(1+EXP($I$3*(COUNT($H$9:M$9)+$I$4))),TREND($D38:$E38,$D$9:$E$9,M$9)) -> 0 | N38: =IF($F38="s-curve",$D38+($E38-$D38)*$I$2/(1+EXP($I$3*(COUNT($H$9:N$9)+$I$4))),TREND($D38:$E38,$D$9:$E$9,N$9)) -> 0 | O38: =IF($F38="s-curve",$D38+($E38-$D38)*$I$2/(1+EXP($I$3*(COUNT($H$9:O$9)+$I$4))),TREND($D38:$E38,$D$9:$E$9,O$9)) -> 0 | P38: =IF($F38="s-curve",$D38+($E38-$D38)*$I$2/(1+EXP($I$3*(COUNT($H$9:P$9)+$I$4))),TREND($D38:$E38,$D$9:$E$9,P$9)) -> 0 | ... AL38: =IF($F38="s-curve",$D38+($E38-$D38)*$I$2/(1+EXP($I$3*(COUNT($H$9:AL$9)+$I$4))),TREND($D38:$E38,$D$9:$E$9,AL$9)) -> 0
C39: natural gas vehicle | D39: 0 | E39: 0 | F39: =IF(D39=E39,"n/a",IF(OR(C39="battery electric vehicle",C39="natural gas vehicle",C39="plugin hybrid vehicle"),"s-curve","linear")) -> n/a | H39: =D39 -> 0 | I39: =IF($F39="s-curve",$D39+($E39-$D39)*$I$2/(1+EXP($I$3*(COUNT($H$9:I$9)+$I$4))),TREND($D39:$E39,$D$9:$E$9,I$9)) -> 0 | J39: =IF($F39="s-curve",$D39+($E39-$D39)*$I$2/(1+EXP($I$3*(COUNT($H$9:J$9)+$I$4))),TREND($D39:$E39,$D$9:$E$9,J$9)) -> 0 | K39: =IF($F39="s-curve",$D39+($E39-$D39)*$I$2/(1+EXP($I$3*(COUNT($H$9:K$9)+$I$4))),TREND($D39:$E39,$D$9:$E$9,K$9)) -> 0 | L39: =IF($F39="s-curve",$D39+($E39-$D39)*$I$2/(1+EXP($I$3*(COUNT($H$9:L$9)+$I$4))),TREND($D39:$E39,$D$9:$E$9,L$9)) -> 0 | M39: =IF($F39="s-curve",$D39+($E39-$D39)*$I$2/(1+EXP($I$3*(COUNT($H$9:M$9)+$I$4))),TREND($D39:$E39,$D$9:$E$9,M$9)) -> 0 | N39: =IF($F39="s-curve",$D39+($E39-$D39)*$I$2/(1+EXP($I$3*(COUNT($H$9:N$9)+$I$4))),TREND($D39:$E39,$D$9:$E$9,N$9)) -> 0 | O39: =IF($F39="s-curve",$D39+($E39-$D39)*$I$2/(1+EXP($I$3*(COUNT($H$9:O$9)+$I$4))),TREND($D39:$E39,$D$9:$E$9,O$9)) -> 0 | P39: =IF($F39="s-curve",$D39+($E39-$D39)*$I$2/(1+EXP($I$3*(COUNT($H$9:P$9)+$I$4))),TREND($D39:$E39,$D$9:$E$9,P$9)) -> 0 | ... AL39: =IF($F39="s-curve",$D39+($E39-$D39)*$I$2/(1+EXP($I$3*(COUNT($H$9:AL$9)+$I$4))),TREND($D39:$E39,$D$9:$E$9,AL$9)) -> 0
C40: gasoline vehicle | D40: 0 | E40: 0 | F40: =IF(D40=E40,"n/a",IF(OR(C40="battery electric vehicle",C40="natural gas vehicle",C40="plugin hybrid vehicle"),"s-curve","linear")) -> n/a | H40: =D40 -> 0 | I40: =IF($F40="s-curve",$D40+($E40-$D40)*$I$2/(1+EXP($I$3*(COUNT($H$9:I$9)+$I$4))),TREND($D40:$E40,$D$9:$E$9,I$9)) -> 0 | J40: =IF($F40="s-curve",$D40+($E40-$D40)*$I$2/(1+EXP($I$3*(COUNT($H$9:J$9)+$I$4))),TREND($D40:$E40,$D$9:$E$9,J$9)) -> 0 | K40: =IF($F40="s-curve",$D40+($E40-$D40)*$I$2/(1+EXP($I$3*(COUNT($H$9:K$9)+$I$4))),TREND($D40:$E40,$D$9:$E$9,K$9)) -> 0 | L40: =IF($F40="s-curve",$D40+($E40-$D40)*$I$2/(1+EXP($I$3*(COUNT($H$9:L$9)+$I$4))),TREND($D40:$E40,$D$9:$E$9,L$9)) -> 0 | M40: =IF($F40="s-curve",$D40+($E40-$D40)*$I$2/(1+EXP($I$3*(COUNT($H$9:M$9)+$I$4))),TREND($D40:$E40,$D$9:$E$9,M$9)) -> 0 | N40: =IF($F40="s-curve",$D40+($E40-$D40)*$I$2/(1+EXP($I$3*(COUNT($H$9:N$9)+$I$4))),TREND($D40:$E40,$D$9:$E$9,N$9)) -> 0 | O40: =IF($F40="s-curve",$D40+($E40-$D40)*$I$2/(1+EXP($I$3*(COUNT($H$9:O$9)+$I$4))),TREND($D40:$E40,$D$9:$E$9,O$9)) -> 0 | P40: =IF($F40="s-curve",$D40+($E40-$D40)*$I$2/(1+EXP($I$3*(COUNT($H$9:P$9)+$I$4))),TREND($D40:$E40,$D$9:$E$9,P$9)) -> 0 | ... AL40: =IF($F40="s-curve",$D40+($E40-$D40)*$I$2/(1+EXP($I$3*(COUNT($H$9:AL$9)+$I$4))),TREND($D40:$E40,$D$9:$E$9,AL$9)) -> 0
C41: diesel vehicle | D41: 1 | E41: 1 | F41: =IF(D41=E41,"n/a",IF(OR(C41="battery electric vehicle",C41="natural gas vehicle",C41="plugin hybrid vehicle"),"s-curve","linear")) -> n/a | H41: =D41 -> 1 | I41: =IF($F41="s-curve",$D41+($E41-$D41)*$I$2/(1+EXP($I$3*(COUNT($H$9:I$9)+$I$4))),TREND($D41:$E41,$D$9:$E$9,I$9)) -> 1 | J41: =IF($F41="s-curve",$D41+($E41-$D41)*$I$2/(1+EXP($I$3*(COUNT($H$9:J$9)+$I$4))),TREND($D41:$E41,$D$9:$E$9,J$9)) -> 1 | K41: =IF($F41="s-curve",$D41+($E41-$D41)*$I$2/(1+EXP($I$3*(COUNT($H$9:K$9)+$I$4))),TREND($D41:$E41,$D$9:$E$9,K$9)) -> 1 | L41: =IF($F41="s-curve",$D41+($E41-$D41)*$I$2/(1+EXP($I$3*(COUNT($H$9:L$9)+$I$4))),TREND($D41:$E41,$D$9:$E$9,L$9)) -> 1 | M41: =IF($F41="s-curve",$D41+($E41-$D41)*$I$2/(1+EXP($I$3*(COUNT($H$9:M$9)+$I$4))),TREND($D41:$E41,$D$9:$E$9,M$9)) -> 1 | N41: =IF($F41="s-curve",$D41+($E41-$D41)*$I$2/(1+EXP($I$3*(COUNT($H$9:N$9)+$I$4))),TREND($D41:$E41,$D$9:$E$9,N$9)) -> 1 | O41: =IF($F41="s-curve",$D41+($E41-$D41)*$I$2/(1+EXP($I$3*(COUNT($H$9:O$9)+$I$4))),TREND($D41:$E41,$D$9:$E$9,O$9)) -> 1 | P41: =IF($F41="s-curve",$D41+($E41-$D41)*$I$2/(1+EXP($I$3*(COUNT($H$9:P$9)+$I$4))),TREND($D41:$E41,$D$9:$E$9,P$9)) -> 1 | ... AL41: =IF($F41="s-curve",$D41+($E41-$D41)*$I$2/(1+EXP($I$3*(COUNT($H$9:AL$9)+$I$4))),TREND($D41:$E41,$D$9:$E$9,AL$9)) -> 1
C42: plugin hybrid vehicle | D42: 0 | E42: 0 | F42: =IF(D42=E42,"n/a",IF(OR(C42="battery electric vehicle",C42="natural gas vehicle",C42="plugin hybrid vehicle"),"s-curve","linear")) -> n/a | H42: =D42 -> 0 | I42: =IF($F42="s-curve",$D42+($E42-$D42)*$I$2/(1+EXP($I$3*(COUNT($H$9:I$9)+$I$4))),TREND($D42:$E42,$D$9:$E$9,I$9)) -> 0 | J42: =IF($F42="s-curve",$D42+($E42-$D42)*$I$2/(1+EXP($I$3*(COUNT($H$9:J$9)+$I$4))),TREND($D42:$E42,$D$9:$E$9,J$9)) -> 0 | K42: =IF($F42="s-curve",$D42+($E42-$D42)*$I$2/(1+EXP($I$3*(COUNT($H$9:K$9)+$I$4))),TREND($D42:$E42,$D$9:$E$9,K$9)) -> 0 | L42: =IF($F42="s-curve",$D42+($E42-$D42)*$I$2/(1+EXP($I$3*(COUNT($H$9:L$9)+$I$4))),TREND($D42:$E42,$D$9:$E$9,L$9)) -> 0 | M42: =IF($F42="s-curve",$D42+($E42-$D42)*$I$2/(1+EXP($I$3*(COUNT($H$9:M$9)+$I$4))),TREND($D42:$E42,$D$9:$E$9,M$9)) -> 0 | N42: =IF($F42="s-curve",$D42+($E42-$D42)*$I$2/(1+EXP($I$3*(COUNT($H$9:N$9)+$I$4))),TREND($D42:$E42,$D$9:$E$9,N$9)) -> 0 | O42: =IF($F42="s-curve",$D42+($E42-$D42)*$I$2/(1+EXP($I$3*(COUNT($H$9:O$9)+$I$4))),TREND($D42:$E42,$D$9:$E$9,O$9)) -> 0 | P42: =IF($F42="s-curve",$D42+($E42-$D42)*$I$2/(1+EXP($I$3*(COUNT($H$9:P$9)+$I$4))),TREND($D42:$E42,$D$9:$E$9,P$9)) -> 0 | ... AL42: =IF($F42="s-curve",$D42+($E42-$D42)*$I$2/(1+EXP($I$3*(COUNT($H$9:AL$9)+$I$4))),TREND($D42:$E42,$D$9:$E$9,AL$9)) -> 0
C43: LPG vehicle | D43: 0 | E43: 0 | F43: =IF(D43=E43,"n/a",IF(OR(C43="battery electric vehicle",C43="natural gas vehicle",C43="plugin hybrid vehicle",C43="hydrogen vehicle"),"s-curve","linear")) -> n/a | H43: =D43 -> 0 | I43: =IF($F43="s-curve",$D43+($E43-$D43)*$I$2/(1+EXP($I$3*(COUNT($H$9:I$9)+$I$4))),TREND($D43:$E43,$D$9:$E$9,I$9)) -> 0 | J43: =IF($F43="s-curve",$D43+($E43-$D43)*$I$2/(1+EXP($I$3*(COUNT($H$9:J$9)+$I$4))),TREND($D43:$E43,$D$9:$E$9,J$9)) -> 0 | K43: =IF($F43="s-curve",$D43+($E43-$D43)*$I$2/(1+EXP($I$3*(COUNT($H$9:K$9)+$I$4))),TREND($D43:$E43,$D$9:$E$9,K$9)) -> 0 | L43: =IF($F43="s-curve",$D43+($E43-$D43)*$I$2/(1+EXP($I$3*(COUNT($H$9:L$9)+$I$4))),TREND($D43:$E43,$D$9:$E$9,L$9)) -> 0 | M43: =IF($F43="s-curve",$D43+($E43-$D43)*$I$2/(1+EXP($I$3*(COUNT($H$9:M$9)+$I$4))),TREND($D43:$E43,$D$9:$E$9,M$9)) -> 0 | N43: =IF($F43="s-curve",$D43+($E43-$D43)*$I$2/(1+EXP($I$3*(COUNT($H$9:N$9)+$I$4))),TREND($D43:$E43,$D$9:$E$9,N$9)) -> 0 | O43: =IF($F43="s-curve",$D43+($E43-$D43)*$I$2/(1+EXP($I$3*(COUNT($H$9:O$9)+$I$4))),TREND($D43:$E43,$D$9:$E$9,O$9)) -> 0 | P43: =IF($F43="s-curve",$D43+($E43-$D43)*$I$2/(1+EXP($I$3*(COUNT($H$9:P$9)+$I$4))),TREND($D43:$E43,$D$9:$E$9,P$9)) -> 0 | ... AL43: =IF($F43="s-curve",$D43+($E43-$D43)*$I$2/(1+EXP($I$3*(COUNT($H$9:AL$9)+$I$4))),TREND($D43:$E43,$D$9:$E$9,AL$9)) -> 0
C44: hydrogen vehicle | D44: 0 | E44: 0 | F44: =IF(D44=E44,"n/a",IF(OR(C44="battery electric vehicle",C44="natural gas vehicle",C44="plugin hybrid vehicle",C44="hydrogen vehicle"),"s-curve","linear")) -> n/a | H44: =D44 -> 0 | I44: =IF($F44="s-curve",$D44+($E44-$D44)*$I$2/(1+EXP($I$3*(COUNT($H$9:I$9)+$I$4))),TREND($D44:$E44,$D$9:$E$9,I$9)) -> 0 | J44: =IF($F44="s-curve",$D44+($E44-$D44)*$I$2/(1+EXP($I$3*(COUNT($H$9:J$9)+$I$4))),TREND($D44:$E44,$D$9:$E$9,J$9)) -> 0 | K44: =IF($F44="s-curve",$D44+($E44-$D44)*$I$2/(1+EXP($I$3*(COUNT($H$9:K$9)+$I$4))),TREND($D44:$E44,$D$9:$E$9,K$9)) -> 0 | L44: =IF($F44="s-curve",$D44+($E44-$D44)*$I$2/(1+EXP($I$3*(COUNT($H$9:L$9)+$I$4))),TREND($D44:$E44,$D$9:$E$9,L$9)) -> 0 | M44: =IF($F44="s-curve",$D44+($E44-$D44)*$I$2/(1+EXP($I$3*(COUNT($H$9:M$9)+$I$4))),TREND($D44:$E44,$D$9:$E$9,M$9)) -> 0 | N44: =IF($F44="s-curve",$D44+($E44-$D44)*$I$2/(1+EXP($I$3*(COUNT($H$9:N$9)+$I$4))),TREND($D44:$E44,$D$9:$E$9,N$9)) -> 0 | O44: =IF($F44="s-curve",$D44+($E44-$D44)*$I$2/(1+EXP($I$3*(COUNT($H$9:O$9)+$I$4))),TREND($D44:$E44,$D$9:$E$9,O$9)) -> 0 | P44: =IF($F44="s-curve",$D44+($E44-$D44)*$I$2/(1+EXP($I$3*(COUNT($H$9:P$9)+$I$4))),TREND($D44:$E44,$D$9:$E$9,P$9)) -> 0 | ... AL44: =IF($F44="s-curve",$D44+($E44-$D44)*$I$2/(1+EXP($I$3*(COUNT($H$9:AL$9)+$I$4))),TREND($D44:$E44,$D$9:$E$9,AL$9)) -> 0
A45: aircraft | B45: freight | C45: battery electric vehicle | D45: 0 | E45: 0 | F45: =IF(D45=E45,"n/a",IF(OR(C45="battery electric vehicle",C45="natural gas vehicle",C45="plugin hybrid vehicle"),"s-curve","linear")) -> n/a | H45: =D45 -> 0 | I45: =IF($F45="s-curve",$D45+($E45-$D45)*$I$2/(1+EXP($I$3*(COUNT($H$9:I$9)+$I$4))),TREND($D45:$E45,$D$9:$E$9,I$9)) -> 0 | J45: =IF($F45="s-curve",$D45+($E45-$D45)*$I$2/(1+EXP($I$3*(COUNT($H$9:J$9)+$I$4))),TREND($D45:$E45,$D$9:$E$9,J$9)) -> 0 | K45: =IF($F45="s-curve",$D45+($E45-$D45)*$I$2/(1+EXP($I$3*(COUNT($H$9:K$9)+$I$4))),TREND($D45:$E45,$D$9:$E$9,K$9)) -> 0 | L45: =IF($F45="s-curve",$D45+($E45-$D45)*$I$2/(1+EXP($I$3*(COUNT($H$9:L$9)+$I$4))),TREND($D45:$E45,$D$9:$E$9,L$9)) -> 0 | M45: =IF($F45="s-curve",$D45+($E45-$D45)*$I$2/(1+EXP($I$3*(COUNT($H$9:M$9)+$I$4))),TREND($D45:$E45,$D$9:$E$9,M$9)) -> 0 | N45: =IF($F45="s-curve",$D45+($E45-$D45)*$I$2/(1+EXP($I$3*(COUNT($H$9:N$9)+$I$4))),TREND($D45:$E45,$D$9:$E$9,N$9)) -> 0 | O45: =IF($F45="s-curve",$D45+($E45-$D45)*$I$2/(1+EXP($I$3*(COUNT($H$9:O$9)+$I$4))),TREND($D45:$E45,$D$9:$E$9,O$9)) -> 0 | P45: =IF($F45="s-curve",$D45+($E45-$D45)*$I$2/(1+EXP($I$3*(COUNT($H$9:P$9)+$I$4))),TREND($D45:$E45,$D$9:$E$9,P$9)) -> 0 | ... AL45: =IF($F45="s-curve",$D45+($E45-$D45)*$I$2/(1+EXP($I$3*(COUNT($H$9:AL$9)+$I$4))),TREND($D45:$E45,$D$9:$E$9,AL$9)) -> 0
C46: natural gas vehicle | D46: 0 | E46: 0 | F46: =IF(D46=E46,"n/a",IF(OR(C46="battery electric vehicle",C46="natural gas vehicle",C46="plugin hybrid vehicle"),"s-curve","linear")) -> n/a | H46: =D46 -> 0 | I46: =IF($F46="s-curve",$D46+($E46-$D46)*$I$2/(1+EXP($I$3*(COUNT($H$9:I$9)+$I$4))),TREND($D46:$E46,$D$9:$E$9,I$9)) -> 0 | J46: =IF($F46="s-curve",$D46+($E46-$D46)*$I$2/(1+EXP($I$3*(COUNT($H$9:J$9)+$I$4))),TREND($D46:$E46,$D$9:$E$9,J$9)) -> 0 | K46: =IF($F46="s-curve",$D46+($E46-$D46)*$I$2/(1+EXP($I$3*(COUNT($H$9:K$9)+$I$4))),TREND($D46:$E46,$D$9:$E$9,K$9)) -> 0 | L46: =IF($F46="s-curve",$D46+($E46-$D46)*$I$2/(1+EXP($I$3*(COUNT($H$9:L$9)+$I$4))),TREND($D46:$E46,$D$9:$E$9,L$9)) -> 0 | M46: =IF($F46="s-curve",$D46+($E46-$D46)*$I$2/(1+EXP($I$3*(COUNT($H$9:M$9)+$I$4))),TREND($D46:$E46,$D$9:$E$9,M$9)) -> 0 | N46: =IF($F46="s-curve",$D46+($E46-$D46)*$I$2/(1+EXP($I$3*(COUNT($H$9:N$9)+$I$4))),TREND($D46:$E46,$D$9:$E$9,N$9)) -> 0 | O46: =IF($F46="s-curve",$D46+($E46-$D46)*$I$2/(1+EXP($I$3*(COUNT($H$9:O$9)+$I$4))),TREND($D46:$E46,$D$9:$E$9,O$9)) -> 0 | P46: =IF($F46="s-curve",$D46+($E46-$D46)*$I$2/(1+EXP($I$3*(COUNT($H$9:P$9)+$I$4))),TREND($D46:$E46,$D$9:$E$9,P$9)) -> 0 | ... AL46: =IF($F46="s-curve",$D46+($E46-$D46)*$I$2/(1+EXP($I$3*(COUNT($H$9:AL$9)+$I$4))),TREND($D46:$E46,$D$9:$E$9,AL$9)) -> 0
C47: gasoline vehicle | D47: 0 | E47: 0 | F47: =IF(D47=E47,"n/a",IF(OR(C47="battery electric vehicle",C47="natural gas vehicle",C47="plugin hybrid vehicle"),"s-curve","linear")) -> n/a | H47: =D47 -> 0 | I47: =IF($F47="s-curve",$D47+($E47-$D47)*$I$2/(1+EXP($I$3*(COUNT($H$9:I$9)+$I$4))),TREND($D47:$E47,$D$9:$E$9,I$9)) -> 0 | J47: =IF($F47="s-curve",$D47+($E47-$D47)*$I$2/(1+EXP($I$3*(COUNT($H$9:J$9)+$I$4))),TREND($D47:$E47,$D$9:$E$9,J$9)) -> 0 | K47: =IF($F47="s-curve",$D47+($E47-$D47)*$I$2/(1+EXP($I$3*(COUNT($H$9:K$9)+$I$4))),TREND($D47:$E47,$D$9:$E$9,K$9)) -> 0 | L47: =IF($F47="s-curve",$D47+($E47-$D47)*$I$2/(1+EXP($I$3*(COUNT($H$9:L$9)+$I$4))),TREND($D47:$E47,$D$9:$E$9,L$9)) -> 0 | M47: =IF($F47="s-curve",$D47+($E47-$D47)*$I$2/(1+EXP($I$3*(COUNT($H$9:M$9)+$I$4))),TREND($D47:$E47,$D$9:$E$9,M$9)) -> 0 | N47: =IF($F47="s-curve",$D47+($E47-$D47)*$I$2/(1+EXP($I$3*(COUNT($H$9:N$9)+$I$4))),TREND($D47:$E47,$D$9:$E$9,N$9)) -> 0 | O47: =IF($F47="s-curve",$D47+($E47-$D47)*$I$2/(1+EXP($I$3*(COUNT($H$9:O$9)+$I$4))),TREND($D47:$E47,$D$9:$E$9,O$9)) -> 0 | P47: =IF($F47="s-curve",$D47+($E47-$D47)*$I$2/(1+EXP($I$3*(COUNT($H$9:P$9)+$I$4))),TREND($D47:$E47,$D$9:$E$9,P$9)) -> 0 | ... AL47: =IF($F47="s-curve",$D47+($E47-$D47)*$I$2/(1+EXP($I$3*(COUNT($H$9:AL$9)+$I$4))),TREND($D47:$E47,$D$9:$E$9,AL$9)) -> 0
C48: diesel vehicle | D48: 1 | E48: 1 | F48: =IF(D48=E48,"n/a",IF(OR(C48="battery electric vehicle",C48="natural gas vehicle",C48="plugin hybrid vehicle"),"s-curve","linear")) -> n/a | H48: =D48 -> 1 | I48: =IF($F48="s-curve",$D48+($E48-$D48)*$I$2/(1+EXP($I$3*(COUNT($H$9:I$9)+$I$4))),TREND($D48:$E48,$D$9:$E$9,I$9)) -> 1 | J48: =IF($F48="s-curve",$D48+($E48-$D48)*$I$2/(1+EXP($I$3*(COUNT($H$9:J$9)+$I$4))),TREND($D48:$E48,$D$9:$E$9,J$9)) -> 1 | K48: =IF($F48="s-curve",$D48+($E48-$D48)*$I$2/(1+EXP($I$3*(COUNT($H$9:K$9)+$I$4))),TREND($D48:$E48,$D$9:$E$9,K$9)) -> 1 | L48: =IF($F48="s-curve",$D48+($E48-$D48)*$I$2/(1+EXP($I$3*(COUNT($H$9:L$9)+$I$4))),TREND($D48:$E48,$D$9:$E$9,L$9)) -> 1 | M48: =IF($F48="s-curve",$D48+($E48-$D48)*$I$2/(1+EXP($I$3*(COUNT($H$9:M$9)+$I$4))),TREND($D48:$E48,$D$9:$E$9,M$9)) -> 1 | N48: =IF($F48="s-curve",$D48+($E48-$D48)*$I$2/(1+EXP($I$3*(COUNT($H$9:N$9)+$I$4))),TREND($D48:$E48,$D$9:$E$9,N$9)) -> 1 | O48: =IF($F48="s-curve",$D48+($E48-$D48)*$I$2/(1+EXP($I$3*(COUNT($H$9:O$9)+$I$4))),TREND($D48:$E48,$D$9:$E$9,O$9)) -> 1 | P48: =IF($F48="s-curve",$D48+($E48-$D48)*$I$2/(1+EXP($I$3*(COUNT($H$9:P$9)+$I$4))),TREND($D48:$E48,$D$9:$E$9,P$9)) -> 1 | ... AL48: =IF($F48="s-curve",$D48+($E48-$D48)*$I$2/(1+EXP($I$3*(COUNT($H$9:AL$9)+$I$4))),TREND($D48:$E48,$D$9:$E$9,AL$9)) -> 1
C49: plugin hybrid vehicle | D49: 0 | E49: 0 | F49: =IF(D49=E49,"n/a",IF(OR(C49="battery electric vehicle",C49="natural gas vehicle",C49="plugin hybrid vehicle"),"s-curve","linear")) -> n/a | H49: =D49 -> 0 | I49: =IF($F49="s-curve",$D49+($E49-$D49)*$I$2/(1+EXP($I$3*(COUNT($H$9:I$9)+$I$4))),TREND($D49:$E49,$D$9:$E$9,I$9)) -> 0 | J49: =IF($F49="s-curve",$D49+($E49-$D49)*$I$2/(1+EXP($I$3*(COUNT($H$9:J$9)+$I$4))),TREND($D49:$E49,$D$9:$E$9,J$9)) -> 0 | K49: =IF($F49="s-curve",$D49+($E49-$D49)*$I$2/(1+EXP($I$3*(COUNT($H$9:K$9)+$I$4))),TREND($D49:$E49,$D$9:$E$9,K$9)) -> 0 | L49: =IF($F49="s-curve",$D49+($E49-$D49)*$I$2/(1+EXP($I$3*(COUNT($H$9:L$9)+$I$4))),TREND($D49:$E49,$D$9:$E$9,L$9)) -> 0 | M49: =IF($F49="s-curve",$D49+($E49-$D49)*$I$2/(1+EXP($I$3*(COUNT($H$9:M$9)+$I$4))),TREND($D49:$E49,$D$9:$E$9,M$9)) -> 0 | N49: =IF($F49="s-curve",$D49+($E49-$D49)*$I$2/(1+EXP($I$3*(COUNT($H$9:N$9)+$I$4))),TREND($D49:$E49,$D$9:$E$9,N$9)) -> 0 | O49: =IF($F49="s-curve",$D49+($E49-$D49)*$I$2/(1+EXP($I$3*(COUNT($H$9:O$9)+$I$4))),TREND($D49:$E49,$D$9:$E$9,O$9)) -> 0 | P49: =IF($F49="s-curve",$D49+($E49-$D49)*$I$2/(1+EXP($I$3*(COUNT($H$9:P$9)+$I$4))),TREND($D49:$E49,$D$9:$E$9,P$9)) -> 0 | ... AL49: =IF($F49="s-curve",$D49+($E49-$D49)*$I$2/(1+EXP($I$3*(COUNT($H$9:AL$9)+$I$4))),TREND($D49:$E49,$D$9:$E$9,AL$9)) -> 0
C50: LPG vehicle | D50: 0 | E50: 0 | F50: =IF(D50=E50,"n/a",IF(OR(C50="battery electric vehicle",C50="natural gas vehicle",C50="plugin hybrid vehicle",C50="hydrogen vehicle"),"s-curve","linear")) -> n/a | H50: =D50 -> 0 | I50: =IF($F50="s-curve",$D50+($E50-$D50)*$I$2/(1+EXP($I$3*(COUNT($H$9:I$9)+$I$4))),TREND($D50:$E50,$D$9:$E$9,I$9)) -> 0 | J50: =IF($F50="s-curve",$D50+($E50-$D50)*$I$2/(1+EXP($I$3*(COUNT($H$9:J$9)+$I$4))),TREND($D50:$E50,$D$9:$E$9,J$9)) -> 0 | K50: =IF($F50="s-curve",$D50+($E50-$D50)*$I$2/(1+EXP($I$3*(COUNT($H$9:K$9)+$I$4))),TREND($D50:$E50,$D$9:$E$9,K$9)) -> 0 | L50: =IF($F50="s-curve",$D50+($E50-$D50)*$I$2/(1+EXP($I$3*(COUNT($H$9:L$9)+$I$4))),TREND($D50:$E50,$D$9:$E$9,L$9)) -> 0 | M50: =IF($F50="s-curve",$D50+($E50-$D50)*$I$2/(1+EXP($I$3*(COUNT($H$9:M$9)+$I$4))),TREND($D50:$E50,$D$9:$E$9,M$9)) -> 0 | N50: =IF($F50="s-curve",$D50+($E50-$D50)*$I$2/(1+EXP($I$3*(COUNT($H$9:N$9)+$I$4))),TREND($D50:$E50,$D$9:$E$9,N$9)) -> 0 | O50: =IF($F50="s-curve",$D50+($E50-$D50)*$I$2/(1+EXP($I$3*(COUNT($H$9:O$9)+$I$4))),TREND($D50:$E50,$D$9:$E$9,O$9)) -> 0 | P50: =IF($F50="s-curve",$D50+($E50-$D50)*$I$2/(1+EXP($I$3*(COUNT($H$9:P$9)+$I$4))),TREND($D50:$E50,$D$9:$E$9,P$9)) -> 0 | ... AL50: =IF($F50="s-curve",$D50+($E50-$D50)*$I$2/(1+EXP($I$3*(COUNT($H$9:AL$9)+$I$4))),TREND($D50:$E50,$D$9:$E$9,AL$9)) -> 0
C51: hydrogen vehicle | D51: 0 | E51: 0 | F51: =IF(D51=E51,"n/a",IF(OR(C51="battery electric vehicle",C51="natural gas vehicle",C51="plugin hybrid vehicle",C51="hydrogen vehicle"),"s-curve","linear")) -> n/a | H51: =D51 -> 0 | I51: =IF($F51="s-curve",$D51+($E51-$D51)*$I$2/(1+EXP($I$3*(COUNT($H$9:I$9)+$I$4))),TREND($D51:$E51,$D$9:$E$9,I$9)) -> 0 | J51: =IF($F51="s-curve",$D51+($E51-$D51)*$I$2/(1+EXP($I$3*(COUNT($H$9:J$9)+$I$4))),TREND($D51:$E51,$D$9:$E$9,J$9)) -> 0 | K51: =IF($F51="s-curve",$D51+($E51-$D51)*$I$2/(1+EXP($I$3*(COUNT($H$9:K$9)+$I$4))),TREND($D51:$E51,$D$9:$E$9,K$9)) -> 0 | L51: =IF($F51="s-curve",$D51+($E51-$D51)*$I$2/(1+EXP($I$3*(COUNT($H$9:L$9)+$I$4))),TREND($D51:$E51,$D$9:$E$9,L$9)) -> 0 | M51: =IF($F51="s-curve",$D51+($E51-$D51)*$I$2/(1+EXP($I$3*(COUNT($H$9:M$9)+$I$4))),TREND($D51:$E51,$D$9:$E$9,M$9)) -> 0 | N51: =IF($F51="s-curve",$D51+($E51-$D51)*$I$2/(1+EXP($I$3*(COUNT($H$9:N$9)+$I$4))),TREND($D51:$E51,$D$9:$E$9,N$9)) -> 0 | O51: =IF($F51="s-curve",$D51+($E51-$D51)*$I$2/(1+EXP($I$3*(COUNT($H$9:O$9)+$I$4))),TREND($D51:$E51,$D$9:$E$9,O$9)) -> 0 | P51: =IF($F51="s-curve",$D51+($E51-$D51)*$I$2/(1+EXP($I$3*(COUNT($H$9:P$9)+$I$4))),TREND($D51:$E51,$D$9:$E$9,P$9)) -> 0 | ... AL51: =IF($F51="s-curve",$D51+($E51-$D51)*$I$2/(1+EXP($I$3*(COUNT($H$9:AL$9)+$I$4))),TREND($D51:$E51,$D$9:$E$9,AL$9)) -> 0
A52: rail | B52: passenger | C52: battery electric vehicle | D52: 1 | E52: =D52 -> 1 | F52: =IF(D52=E52,"n/a",IF(OR(C52="battery electric vehicle",C52="natural gas vehicle",C52="plugin hybrid vehicle"),"s-curve","linear")) -> n/a | H52: =D52 -> 1 | I52: =IF($F52="s-curve",$D52+($E52-$D52)*$I$2/(1+EXP($I$3*(COUNT($H$9:I$9)+$I$4))),TREND($D52:$E52,$D$9:$E$9,I$9)) -> 1 | J52: =IF($F52="s-curve",$D52+($E52-$D52)*$I$2/(1+EXP($I$3*(COUNT($H$9:J$9)+$I$4))),TREND($D52:$E52,$D$9:$E$9,J$9)) -> 1 | K52: =IF($F52="s-curve",$D52+($E52-$D52)*$I$2/(1+EXP($I$3*(COUNT($H$9:K$9)+$I$4))),TREND($D52:$E52,$D$9:$E$9,K$9)) -> 1 | L52: =IF($F52="s-curve",$D52+($E52-$D52)*$I$2/(1+EXP($I$3*(COUNT($H$9:L$9)+$I$4))),TREND($D52:$E52,$D$9:$E$9,L$9)) -> 1 | M52: =IF($F52="s-curve",$D52+($E52-$D52)*$I$2/(1+EXP($I$3*(COUNT($H$9:M$9)+$I$4))),TREND($D52:$E52,$D$9:$E$9,M$9)) -> 1 | N52: =IF($F52="s-curve",$D52+($E52-$D52)*$I$2/(1+EXP($I$3*(COUNT($H$9:N$9)+$I$4))),TREND($D52:$E52,$D$9:$E$9,N$9)) -> 1 | O52: =IF($F52="s-curve",$D52+($E52-$D52)*$I$2/(1+EXP($I$3*(COUNT($H$9:O$9)+$I$4))),TREND($D52:$E52,$D$9:$E$9,O$9)) -> 1 | P52: =IF($F52="s-curve",$D52+($E52-$D52)*$I$2/(1+EXP($I$3*(COUNT($H$9:P$9)+$I$4))),TREND($D52:$E52,$D$9:$E$9,P$9)) -> 1 | ... AL52: =IF($F52="s-curve",$D52+($E52-$D52)*$I$2/(1+EXP($I$3*(COUNT($H$9:AL$9)+$I$4))),TREND($D52:$E52,$D$9:$E$9,AL$9)) -> 1
C53: natural gas vehicle | D53: =MIN(1.25*INDEX('SYVbT-passenger'!$B$5:$H$5,MATCH(Data!$C11,'SYVbT-passenger'!$B$1:$H$1,0))/SUM('SYVbT-passenger'!$B$5:$H$5),1) -> 0 | E53: =D53 -> 0 | F53: =IF(D53=E53,"n/a",IF(OR(C53="battery electric vehicle",C53="natural gas vehicle",C53="plugin hybrid vehicle"),"s-curve","linear")) -> n/a | H53: =D53 -> 0 | I53: =IF($F53="s-curve",$D53+($E53-$D53)*$I$2/(1+EXP($I$3*(COUNT($H$9:I$9)+$I$4))),TREND($D53:$E53,$D$9:$E$9,I$9)) -> 0 | J53: =IF($F53="s-curve",$D53+($E53-$D53)*$I$2/(1+EXP($I$3*(COUNT($H$9:J$9)+$I$4))),TREND($D53:$E53,$D$9:$E$9,J$9)) -> 0 | K53: =IF($F53="s-curve",$D53+($E53-$D53)*$I$2/(1+EXP($I$3*(COUNT($H$9:K$9)+$I$4))),TREND($D53:$E53,$D$9:$E$9,K$9)) -> 0 | L53: =IF($F53="s-curve",$D53+($E53-$D53)*$I$2/(1+EXP($I$3*(COUNT($H$9:L$9)+$I$4))),TREND($D53:$E53,$D$9:$E$9,L$9)) -> 0 | M53: =IF($F53="s-curve",$D53+($E53-$D53)*$I$2/(1+EXP($I$3*(COUNT($H$9:M$9)+$I$4))),TREND($D53:$E53,$D$9:$E$9,M$9)) -> 0 | N53: =IF($F53="s-curve",$D53+($E53-$D53)*$I$2/(1+EXP($I$3*(COUNT($H$9:N$9)+$I$4))),TREND($D53:$E53,$D$9:$E$9,N$9)) -> 0 | O53: =IF($F53="s-curve",$D53+($E53-$D53)*$I$2/(1+EXP($I$3*(COUNT($H$9:O$9)+$I$4))),TREND($D53:$E53,$D$9:$E$9,O$9)) -> 0 | P53: =IF($F53="s-curve",$D53+($E53-$D53)*$I$2/(1+EXP($I$3*(COUNT($H$9:P$9)+$I$4))),TREND($D53:$E53,$D$9:$E$9,P$9)) -> 0 | ... AL53: =IF($F53="s-curve",$D53+($E53-$D53)*$I$2/(1+EXP($I$3*(COUNT($H$9:AL$9)+$I$4))),TREND($D53:$E53,$D$9:$E$9,AL$9)) -> 0
C54: gasoline vehicle | D54: =MIN(1.25*INDEX('SYVbT-passenger'!$B$5:$H$5,MATCH(Data!$C12,'SYVbT-passenger'!$B$1:$H$1,0))/SUM('SYVbT-passenger'!$B$5:$H$5),1) -> 0 | E54: =D54 -> 0 | F54: =IF(D54=E54,"n/a",IF(OR(C54="battery electric vehicle",C54="natural gas vehicle",C54="plugin hybrid vehicle"),"s-curve","linear")) -> n/a | H54: =D54 -> 0 | I54: =IF($F54="s-curve",$D54+($E54-$D54)*$I$2/(1+EXP($I$3*(COUNT($H$9:I$9)+$I$4))),TREND($D54:$E54,$D$9:$E$9,I$9)) -> 0 | J54: =IF($F54="s-curve",$D54+($E54-$D54)*$I$2/(1+EXP($I$3*(COUNT($H$9:J$9)+$I$4))),TREND($D54:$E54,$D$9:$E$9,J$9)) -> 0 | K54: =IF($F54="s-curve",$D54+($E54-$D54)*$I$2/(1+EXP($I$3*(COUNT($H$9:K$9)+$I$4))),TREND($D54:$E54,$D$9:$E$9,K$9)) -> 0 | L54: =IF($F54="s-curve",$D54+($E54-$D54)*$I$2/(1+EXP($I$3*(COUNT($H$9:L$9)+$I$4))),TREND($D54:$E54,$D$9:$E$9,L$9)) -> 0 | M54: =IF($F54="s-curve",$D54+($E54-$D54)*$I$2/(1+EXP($I$3*(COUNT($H$9:M$9)+$I$4))),TREND($D54:$E54,$D$9:$E$9,M$9)) -> 0 | N54: =IF($F54="s-curve",$D54+($E54-$D54)*$I$2/(1+EXP($I$3*(COUNT($H$9:N$9)+$I$4))),TREND($D54:$E54,$D$9:$E$9,N$9)) -> 0 | O54: =IF($F54="s-curve",$D54+($E54-$D54)*$I$2/(1+EXP($I$3*(COUNT($H$9:O$9)+$I$4))),TREND($D54:$E54,$D$9:$E$9,O$9)) -> 0 | P54: =IF($F54="s-curve",$D54+($E54-$D54)*$I$2/(1+EXP($I$3*(COUNT($H$9:P$9)+$I$4))),TREND($D54:$E54,$D$9:$E$9,P$9)) -> 0 | ... AL54: =IF($F54="s-curve",$D54+($E54-$D54)*$I$2/(1+EXP($I$3*(COUNT($H$9:AL$9)+$I$4))),TREND($D54:$E54,$D$9:$E$9,AL$9)) -> 0
C55: diesel vehicle | D55: 0.52 | E55: =D55 -> 0.52 | F55: =IF(D55=E55,"n/a",IF(OR(C55="battery electric vehicle",C55="natural gas vehicle",C55="plugin hybrid vehicle"),"s-curve","linear")) -> n/a | H55: =D55 -> 0.52 | I55: =IF($F55="s-curve",$D55+($E55-$D55)*$I$2/(1+EXP($I$3*(COUNT($H$9:I$9)+$I$4))),TREND($D55:$E55,$D$9:$E$9,I$9)) -> 0.52 | J55: =IF($F55="s-curve",$D55+($E55-$D55)*$I$2/(1+EXP($I$3*(COUNT($H$9:J$9)+$I$4))),TREND($D55:$E55,$D$9:$E$9,J$9)) -> 0.52 | K55: =IF($F55="s-curve",$D55+($E55-$D55)*$I$2/(1+EXP($I$3*(COUNT($H$9:K$9)+$I$4))),TREND($D55:$E55,$D$9:$E$9,K$9)) -> 0.52 | L55: =IF($F55="s-curve",$D55+($E55-$D55)*$I$2/(1+EXP($I$3*(COUNT($H$9:L$9)+$I$4))),TREND($D55:$E55,$D$9:$E$9,L$9)) -> 0.52 | M55: =IF($F55="s-curve",$D55+($E55-$D55)*$I$2/(1+EXP($I$3*(COUNT($H$9:M$9)+$I$4))),TREND($D55:$E55,$D$9:$E$9,M$9)) -> 0.52 | N55: =IF($F55="s-curve",$D55+($E55-$D55)*$I$2/(1+EXP($I$3*(COUNT($H$9:N$9)+$I$4))),TREND($D55:$E55,$D$9:$E$9,N$9)) -> 0.52 | O55: =IF($F55="s-curve",$D55+($E55-$D55)*$I$2/(1+EXP($I$3*(COUNT($H$9:O$9)+$I$4))),TREND($D55:$E55,$D$9:$E$9,O$9)) -> 0.52 | P55: =IF($F55="s-curve",$D55+($E55-$D55)*$I$2/(1+EXP($I$3*(COUNT($H$9:P$9)+$I$4))),TREND($D55:$E55,$D$9:$E$9,P$9)) -> 0.52 | ... AL55: =IF($F55="s-curve",$D55+($E55-$D55)*$I$2/(1+EXP($I$3*(COUNT($H$9:AL$9)+$I$4))),TREND($D55:$E55,$D$9:$E$9,AL$9)) -> 0.52
C56: plugin hybrid vehicle | D56: =MIN(1.25*INDEX('SYVbT-passenger'!$B$5:$H$5,MATCH(Data!$C14,'SYVbT-passenger'!$B$1:$H$1,0))/SUM('SYVbT-passenger'!$B$5:$H$5),1) -> 0 | E56: =D56 -> 0 | F56: =IF(D56=E56,"n/a",IF(OR(C56="battery electric vehicle",C56="natural gas vehicle",C56="plugin hybrid vehicle"),"s-curve","linear")) -> n/a | H56: =D56 -> 0 | I56: =IF($F56="s-curve",$D56+($E56-$D56)*$I$2/(1+EXP($I$3*(COUNT($H$9:I$9)+$I$4))),TREND($D56:$E56,$D$9:$E$9,I$9)) -> 0 | J56: =IF($F56="s-curve",$D56+($E56-$D56)*$I$2/(1+EXP($I$3*(COUNT($H$9:J$9)+$I$4))),TREND($D56:$E56,$D$9:$E$9,J$9)) -> 0 | K56: =IF($F56="s-curve",$D56+($E56-$D56)*$I$2/(1+EXP($I$3*(COUNT($H$9:K$9)+$I$4))),TREND($D56:$E56,$D$9:$E$9,K$9)) -> 0 | L56: =IF($F56="s-curve",$D56+($E56-$D56)*$I$2/(1+EXP($I$3*(COUNT($H$9:L$9)+$I$4))),TREND($D56:$E56,$D$9:$E$9,L$9)) -> 0 | M56: =IF($F56="s-curve",$D56+($E56-$D56)*$I$2/(1+EXP($I$3*(COUNT($H$9:M$9)+$I$4))),TREND($D56:$E56,$D$9:$E$9,M$9)) -> 0 | N56: =IF($F56="s-curve",$D56+($E56-$D56)*$I$2/(1+EXP($I$3*(COUNT($H$9:N$9)+$I$4))),TREND($D56:$E56,$D$9:$E$9,N$9)) -> 0 | O56: =IF($F56="s-curve",$D56+($E56-$D56)*$I$2/(1+EXP($I$3*(COUNT($H$9:O$9)+$I$4))),TREND($D56:$E56,$D$9:$E$9,O$9)) -> 0 | P56: =IF($F56="s-curve",$D56+($E56-$D56)*$I$2/(1+EXP($I$3*(COUNT($H$9:P$9)+$I$4))),TREND($D56:$E56,$D$9:$E$9,P$9)) -> 0 | ... AL56: =IF($F56="s-curve",$D56+($E56-$D56)*$I$2/(1+EXP($I$3*(COUNT($H$9:AL$9)+$I$4))),TREND($D56:$E56,$D$9:$E$9,AL$9)) -> 0
C57: LPG vehicle | D57: =MIN(1.25*INDEX('SYVbT-passenger'!$B$5:$H$5,MATCH(Data!$C15,'SYVbT-passenger'!$B$1:$H$1,0))/SUM('SYVbT-passenger'!$B$5:$H$5),1) -> 0 | E57: =D57 -> 0 | F57: =IF(D57=E57,"n/a",IF(OR(C57="battery electric vehicle",C57="natural gas vehicle",C57="plugin hybrid vehicle",C57="hydrogen vehicle"),"s-curve","linear")) -> n/a | H57: =D57 -> 0 | I57: =IF($F57="s-curve",$D57+($E57-$D57)*$I$2/(1+EXP($I$3*(COUNT($H$9:I$9)+$I$4))),TREND($D57:$E57,$D$9:$E$9,I$9)) -> 0 | J57: =IF($F57="s-curve",$D57+($E57-$D57)*$I$2/(1+EXP($I$3*(COUNT($H$9:J$9)+$I$4))),TREND($D57:$E57,$D$9:$E$9,J$9)) -> 0 | K57: =IF($F57="s-curve",$D57+($E57-$D57)*$I$2/(1+EXP($I$3*(COUNT($H$9:K$9)+$I$4))),TREND($D57:$E57,$D$9:$E$9,K$9)) -> 0 | L57: =IF($F57="s-curve",$D57+($E57-$D57)*$I$2/(1+EXP($I$3*(COUNT($H$9:L$9)+$I$4))),TREND($D57:$E57,$D$9:$E$9,L$9)) -> 0 | M57: =IF($F57="s-curve",$D57+($E57-$D57)*$I$2/(1+EXP($I$3*(COUNT($H$9:M$9)+$I$4))),TREND($D57:$E57,$D$9:$E$9,M$9)) -> 0 | N57: =IF($F57="s-curve",$D57+($E57-$D57)*$I$2/(1+EXP($I$3*(COUNT($H$9:N$9)+$I$4))),TREND($D57:$E57,$D$9:$E$9,N$9)) -> 0 | O57: =IF($F57="s-curve",$D57+($E57-$D57)*$I$2/(1+EXP($I$3*(COUNT($H$9:O$9)+$I$4))),TREND($D57:$E57,$D$9:$E$9,O$9)) -> 0 | P57: =IF($F57="s-curve",$D57+($E57-$D57)*$I$2/(1+EXP($I$3*(COUNT($H$9:P$9)+$I$4))),TREND($D57:$E57,$D$9:$E$9,P$9)) -> 0 | ... AL57: =IF($F57="s-curve",$D57+($E57-$D57)*$I$2/(1+EXP($I$3*(COUNT($H$9:AL$9)+$I$4))),TREND($D57:$E57,$D$9:$E$9,AL$9)) -> 0
C58: hydrogen vehicle | D58: =MIN(1.25*INDEX('SYVbT-passenger'!$B$5:$H$5,MATCH(Data!$C16,'SYVbT-passenger'!$B$1:$H$1,0))/SUM('SYVbT-passenger'!$B$5:$H$5),1) -> 0 | E58: =D58 -> 0 | F58: =IF(D58=E58,"n/a",IF(OR(C58="battery electric vehicle",C58="natural gas vehicle",C58="plugin hybrid vehicle",C58="hydrogen vehicle"),"s-curve","linear")) -> n/a | H58: =D58 -> 0 | I58: =IF($F58="s-curve",$D58+($E58-$D58)*$I$2/(1+EXP($I$3*(COUNT($H$9:I$9)+$I$4))),TREND($D58:$E58,$D$9:$E$9,I$9)) -> 0 | J58: =IF($F58="s-curve",$D58+($E58-$D58)*$I$2/(1+EXP($I$3*(COUNT($H$9:J$9)+$I$4))),TREND($D58:$E58,$D$9:$E$9,J$9)) -> 0 | K58: =IF($F58="s-curve",$D58+($E58-$D58)*$I$2/(1+EXP($I$3*(COUNT($H$9:K$9)+$I$4))),TREND($D58:$E58,$D$9:$E$9,K$9)) -> 0 | L58: =IF($F58="s-curve",$D58+($E58-$D58)*$I$2/(1+EXP($I$3*(COUNT($H$9:L$9)+$I$4))),TREND($D58:$E58,$D$9:$E$9,L$9)) -> 0 | M58: =IF($F58="s-curve",$D58+($E58-$D58)*$I$2/(1+EXP($I$3*(COUNT($H$9:M$9)+$I$4))),TREND($D58:$E58,$D$9:$E$9,M$9)) -> 0 | N58: =IF($F58="s-curve",$D58+($E58-$D58)*$I$2/(1+EXP($I$3*(COUNT($H$9:N$9)+$I$4))),TREND($D58:$E58,$D$9:$E$9,N$9)) -> 0 | O58: =IF($F58="s-curve",$D58+($E58-$D58)*$I$2/(1+EXP($I$3*(COUNT($H$9:O$9)+$I$4))),TREND($D58:$E58,$D$9:$E$9,O$9)) -> 0 | P58: =IF($F58="s-curve",$D58+($E58-$D58)*$I$2/(1+EXP($I$3*(COUNT($H$9:P$9)+$I$4))),TREND($D58:$E58,$D$9:$E$9,P$9)) -> 0 | ... AL58: =IF($F58="s-curve",$D58+($E58-$D58)*$I$2/(1+EXP($I$3*(COUNT($H$9:AL$9)+$I$4))),TREND($D58:$E58,$D$9:$E$9,AL$9)) -> 0
A59: rail | B59: freight | C59: battery electric vehicle | D59: 0.2 | E59: =D59 -> 0.2 | F59: =IF(D59=E59,"n/a",IF(OR(C59="battery electric vehicle",C59="natural gas vehicle",C59="plugin hybrid vehicle"),"s-curve","linear")) -> n/a | H59: =D59 -> 0.2 | I59: =IF($F59="s-curve",$D59+($E59-$D59)*$I$2/(1+EXP($I$3*(COUNT($H$9:I$9)+$I$4))),TREND($D59:$E59,$D$9:$E$9,I$9)) -> 0.2 | J59: =IF($F59="s-curve",$D59+($E59-$D59)*$I$2/(1+EXP($I$3*(COUNT($H$9:J$9)+$I$4))),TREND($D59:$E59,$D$9:$E$9,J$9)) -> 0.2 | K59: =IF($F59="s-curve",$D59+($E59-$D59)*$I$2/(1+EXP($I$3*(COUNT($H$9:K$9)+$I$4))),TREND($D59:$E59,$D$9:$E$9,K$9)) -> 0.2 | L59: =IF($F59="s-curve",$D59+($E59-$D59)*$I$2/(1+EXP($I$3*(COUNT($H$9:L$9)+$I$4))),TREND($D59:$E59,$D$9:$E$9,L$9)) -> 0.2 | M59: =IF($F59="s-curve",$D59+($E59-$D59)*$I$2/(1+EXP($I$3*(COUNT($H$9:M$9)+$I$4))),TREND($D59:$E59,$D$9:$E$9,M$9)) -> 0.2 | N59: =IF($F59="s-curve",$D59+($E59-$D59)*$I$2/(1+EXP($I$3*(COUNT($H$9:N$9)+$I$4))),TREND($D59:$E59,$D$9:$E$9,N$9)) -> 0.2 | O59: =IF($F59="s-curve",$D59+($E59-$D59)*$I$2/(1+EXP($I$3*(COUNT($H$9:O$9)+$I$4))),TREND($D59:$E59,$D$9:$E$9,O$9)) -> 0.2 | P59: =IF($F59="s-curve",$D59+($E59-$D59)*$I$2/(1+EXP($I$3*(COUNT($H$9:P$9)+$I$4))),TREND($D59:$E59,$D$9:$E$9,P$9)) -> 0.2 | ... AL59: =IF($F59="s-curve",$D59+($E59-$D59)*$I$2/(1+EXP($I$3*(COUNT($H$9:AL$9)+$I$4))),TREND($D59:$E59,$D$9:$E$9,AL$9)) -> 0.2
C60: natural gas vehicle | D60: =MIN(1.25*INDEX('SYVbT-freight'!$B$5:$H$5,MATCH(Data!$C11,'SYVbT-passenger'!$B$1:$H$1,0))/SUM('SYVbT-freight'!$B$5:$H$5),1) -> 0 | E60: =D60 -> 0 | F60: =IF(D60=E60,"n/a",IF(OR(C60="battery electric vehicle",C60="natural gas vehicle",C60="plugin hybrid vehicle"),"s-curve","linear")) -> n/a | H60: =D60 -> 0 | I60: =IF($F60="s-curve",$D60+($E60-$D60)*$I$2/(1+EXP($I$3*(COUNT($H$9:I$9)+$I$4))),TREND($D60:$E60,$D$9:$E$9,I$9)) -> 0 | J60: =IF($F60="s-curve",$D60+($E60-$D60)*$I$2/(1+EXP($I$3*(COUNT($H$9:J$9)+$I$4))),TREND($D60:$E60,$D$9:$E$9,J$9)) -> 0 | K60: =IF($F60="s-curve",$D60+($E60-$D60)*$I$2/(1+EXP($I$3*(COUNT($H$9:K$9)+$I$4))),TREND($D60:$E60,$D$9:$E$9,K$9)) -> 0 | L60: =IF($F60="s-curve",$D60+($E60-$D60)*$I$2/(1+EXP($I$3*(COUNT($H$9:L$9)+$I$4))),TREND($D60:$E60,$D$9:$E$9,L$9)) -> 0 | M60: =IF($F60="s-curve",$D60+($E60-$D60)*$I$2/(1+EXP($I$3*(COUNT($H$9:M$9)+$I$4))),TREND($D60:$E60,$D$9:$E$9,M$9)) -> 0 | N60: =IF($F60="s-curve",$D60+($E60-$D60)*$I$2/(1+EXP($I$3*(COUNT($H$9:N$9)+$I$4))),TREND($D60:$E60,$D$9:$E$9,N$9)) -> 0 | O60: =IF($F60="s-curve",$D60+($E60-$D60)*$I$2/(1+EXP($I$3*(COUNT($H$9:O$9)+$I$4))),TREND($D60:$E60,$D$9:$E$9,O$9)) -> 0 | P60: =IF($F60="s-curve",$D60+($E60-$D60)*$I$2/(1+EXP($I$3*(COUNT($H$9:P$9)+$I$4))),TREND($D60:$E60,$D$9:$E$9,P$9)) -> 0 | ... AL60: =IF($F60="s-curve",$D60+($E60-$D60)*$I$2/(1+EXP($I$3*(COUNT($H$9:AL$9)+$I$4))),TREND($D60:$E60,$D$9:$E$9,AL$9)) -> 0
C61: gasoline vehicle | D61: =MIN(1.25*INDEX('SYVbT-freight'!$B$5:$H$5,MATCH(Data!$C12,'SYVbT-passenger'!$B$1:$H$1,0))/SUM('SYVbT-freight'!$B$5:$H$5),1) -> 0 | E61: =D61 -> 0 | F61: =IF(D61=E61,"n/a",IF(OR(C61="battery electric vehicle",C61="natural gas vehicle",C61="plugin hybrid vehicle"),"s-curve","linear")) -> n/a | H61: =D61 -> 0 | I61: =IF($F61="s-curve",$D61+($E61-$D61)*$I$2/(1+EXP($I$3*(COUNT($H$9:I$9)+$I$4))),TREND($D61:$E61,$D$9:$E$9,I$9)) -> 0 | J61: =IF($F61="s-curve",$D61+($E61-$D61)*$I$2/(1+EXP($I$3*(COUNT($H$9:J$9)+$I$4))),TREND($D61:$E61,$D$9:$E$9,J$9)) -> 0 | K61: =IF($F61="s-curve",$D61+($E61-$D61)*$I$2/(1+EXP($I$3*(COUNT($H$9:K$9)+$I$4))),TREND($D61:$E61,$D$9:$E$9,K$9)) -> 0 | L61: =IF($F61="s-curve",$D61+($E61-$D61)*$I$2/(1+EXP($I$3*(COUNT($H$9:L$9)+$I$4))),TREND($D61:$E61,$D$9:$E$9,L$9)) -> 0 | M61: =IF($F61="s-curve",$D61+($E61-$D61)*$I$2/(1+EXP($I$3*(COUNT($H$9:M$9)+$I$4))),TREND($D61:$E61,$D$9:$E$9,M$9)) -> 0 | N61: =IF($F61="s-curve",$D61+($E61-$D61)*$I$2/(1+EXP($I$3*(COUNT($H$9:N$9)+$I$4))),TREND($D61:$E61,$D$9:$E$9,N$9)) -> 0 | O61: =IF($F61="s-curve",$D61+($E61-$D61)*$I$2/(1+EXP($I$3*(COUNT($H$9:O$9)+$I$4))),TREND($D61:$E61,$D$9:$E$9,O$9)) -> 0 | P61: =IF($F61="s-curve",$D61+($E61-$D61)*$I$2/(1+EXP($I$3*(COUNT($H$9:P$9)+$I$4))),TREND($D61:$E61,$D$9:$E$9,P$9)) -> 0 | ... AL61: =IF($F61="s-curve",$D61+($E61-$D61)*$I$2/(1+EXP($I$3*(COUNT($H$9:AL$9)+$I$4))),TREND($D61:$E61,$D$9:$E$9,AL$9)) -> 0
C62: diesel vehicle | D62: 1 | E62: =D62 -> 1 | F62: =IF(D62=E62,"n/a",IF(OR(C62="battery electric vehicle",C62="natural gas vehicle",C62="plugin hybrid vehicle"),"s-curve","linear")) -> n/a | H62: =D62 -> 1 | I62: =IF($F62="s-curve",$D62+($E62-$D62)*$I$2/(1+EXP($I$3*(COUNT($H$9:I$9)+$I$4))),TREND($D62:$E62,$D$9:$E$9,I$9)) -> 1 | J62: =IF($F62="s-curve",$D62+($E62-$D62)*$I$2/(1+EXP($I$3*(COUNT($H$9:J$9)+$I$4))),TREND($D62:$E62,$D$9:$E$9,J$9)) -> 1 | K62: =IF($F62="s-curve",$D62+($E62-$D62)*$I$2/(1+EXP($I$3*(COUNT($H$9:K$9)+$I$4))),TREND($D62:$E62,$D$9:$E$9,K$9)) -> 1 | L62: =IF($F62="s-curve",$D62+($E62-$D62)*$I$2/(1+EXP($I$3*(COUNT($H$9:L$9)+$I$4))),TREND($D62:$E62,$D$9:$E$9,L$9)) -> 1 | M62: =IF($F62="s-curve",$D62+($E62-$D62)*$I$2/(1+EXP($I$3*(COUNT($H$9:M$9)+$I$4))),TREND($D62:$E62,$D$9:$E$9,M$9)) -> 1 | N62: =IF($F62="s-curve",$D62+($E62-$D62)*$I$2/(1+EXP($I$3*(COUNT($H$9:N$9)+$I$4))),TREND($D62:$E62,$D$9:$E$9,N$9)) -> 1 | O62: =IF($F62="s-curve",$D62+($E62-$D62)*$I$2/(1+EXP($I$3*(COUNT($H$9:O$9)+$I$4))),TREND($D62:$E62,$D$9:$E$9,O$9)) -> 1 | P62: =IF($F62="s-curve",$D62+($E62-$D62)*$I$2/(1+EXP($I$3*(COUNT($H$9:P$9)+$I$4))),TREND($D62:$E62,$D$9:$E$9,P$9)) -> 1 | ... AL62: =IF($F62="s-curve",$D62+($E62-$D62)*$I$2/(1+EXP($I$3*(COUNT($H$9:AL$9)+$I$4))),TREND($D62:$E62,$D$9:$E$9,AL$9)) -> 1
C63: plugin hybrid vehicle | D63: =MIN(1.25*INDEX('SYVbT-freight'!$B$5:$H$5,MATCH(Data!$C14,'SYVbT-passenger'!$B$1:$H$1,0))/SUM('SYVbT-freight'!$B$5:$H$5),1) -> 0 | E63: =D63 -> 0 | F63: =IF(D63=E63,"n/a",IF(OR(C63="battery electric vehicle",C63="natural gas vehicle",C63="plugin hybrid vehicle"),"s-curve","linear")) -> n/a | H63: =D63 -> 0 | I63: =IF($F63="s-curve",$D63+($E63-$D63)*$I$2/(1+EXP($I$3*(COUNT($H$9:I$9)+$I$4))),TREND($D63:$E63,$D$9:$E$9,I$9)) -> 0 | J63: =IF($F63="s-curve",$D63+($E63-$D63)*$I$2/(1+EXP($I$3*(COUNT($H$9:J$9)+$I$4))),TREND($D63:$E63,$D$9:$E$9,J$9)) -> 0 | K63: =IF($F63="s-curve",$D63+($E63-$D63)*$I$2/(1+EXP($I$3*(COUNT($H$9:K$9)+$I$4))),TREND($D63:$E63,$D$9:$E$9,K$9)) -> 0 | L63: =IF($F63="s-curve",$D63+($E63-$D63)*$I$2/(1+EXP($I$3*(COUNT($H$9:L$9)+$I$4))),TREND($D63:$E63,$D$9:$E$9,L$9)) -> 0 | M63: =IF($F63="s-curve",$D63+($E63-$D63)*$I$2/(1+EXP($I$3*(COUNT($H$9:M$9)+$I$4))),TREND($D63:$E63,$D$9:$E$9,M$9)) -> 0 | N63: =IF($F63="s-curve",$D63+($E63-$D63)*$I$2/(1+EXP($I$3*(COUNT($H$9:N$9)+$I$4))),TREND($D63:$E63,$D$9:$E$9,N$9)) -> 0 | O63: =IF($F63="s-curve",$D63+($E63-$D63)*$I$2/(1+EXP($I$3*(COUNT($H$9:O$9)+$I$4))),TREND($D63:$E63,$D$9:$E$9,O$9)) -> 0 | P63: =IF($F63="s-curve",$D63+($E63-$D63)*$I$2/(1+EXP($I$3*(COUNT($H$9:P$9)+$I$4))),TREND($D63:$E63,$D$9:$E$9,P$9)) -> 0 | ... AL63: =IF($F63="s-curve",$D63+($E63-$D63)*$I$2/(1+EXP($I$3*(COUNT($H$9:AL$9)+$I$4))),TREND($D63:$E63,$D$9:$E$9,AL$9)) -> 0
C64: LPG vehicle | D64: =MIN(1.25*INDEX('SYVbT-freight'!$B$5:$H$5,MATCH(Data!$C15,'SYVbT-passenger'!$B$1:$H$1,0))/SUM('SYVbT-freight'!$B$5:$H$5),1) -> 0 | E64: =D64 -> 0 | F64: =IF(D64=E64,"n/a",IF(OR(C64="battery electric vehicle",C64="natural gas vehicle",C64="plugin hybrid vehicle",C64="hydrogen vehicle"),"s-curve","linear")) -> n/a | H64: =D64 -> 0 | I64: =IF($F64="s-curve",$D64+($E64-$D64)*$I$2/(1+EXP($I$3*(COUNT($H$9:I$9)+$I$4))),TREND($D64:$E64,$D$9:$E$9,I$9)) -> 0 | J64: =IF($F64="s-curve",$D64+($E64-$D64)*$I$2/(1+EXP($I$3*(COUNT($H$9:J$9)+$I$4))),TREND($D64:$E64,$D$9:$E$9,J$9)) -> 0 | K64: =IF($F64="s-curve",$D64+($E64-$D64)*$I$2/(1+EXP($I$3*(COUNT($H$9:K$9)+$I$4))),TREND($D64:$E64,$D$9:$E$9,K$9)) -> 0 | L64: =IF($F64="s-curve",$D64+($E64-$D64)*$I$2/(1+EXP($I$3*(COUNT($H$9:L$9)+$I$4))),TREND($D64:$E64,$D$9:$E$9,L$9)) -> 0 | M64: =IF($F64="s-curve",$D64+($E64-$D64)*$I$2/(1+EXP($I$3*(COUNT($H$9:M$9)+$I$4))),TREND($D64:$E64,$D$9:$E$9,M$9)) -> 0 | N64: =IF($F64="s-curve",$D64+($E64-$D64)*$I$2/(1+EXP($I$3*(COUNT($H$9:N$9)+$I$4))),TREND($D64:$E64,$D$9:$E$9,N$9)) -> 0 | O64: =IF($F64="s-curve",$D64+($E64-$D64)*$I$2/(1+EXP($I$3*(COUNT($H$9:O$9)+$I$4))),TREND($D64:$E64,$D$9:$E$9,O$9)) -> 0 | P64: =IF($F64="s-curve",$D64+($E64-$D64)*$I$2/(1+EXP($I$3*(COUNT($H$9:P$9)+$I$4))),TREND($D64:$E64,$D$9:$E$9,P$9)) -> 0 | ... AL64: =IF($F64="s-curve",$D64+($E64-$D64)*$I$2/(1+EXP($I$3*(COUNT($H$9:AL$9)+$I$4))),TREND($D64:$E64,$D$9:$E$9,AL$9)) -> 0
C65: hydrogen vehicle | D65: =MIN(1.25*INDEX('SYVbT-freight'!$B$5:$H$5,MATCH(Data!$C16,'SYVbT-passenger'!$B$1:$H$1,0))/SUM('SYVbT-freight'!$B$5:$H$5),1) -> 0 | E65: =D65 -> 0 | F65: =IF(D65=E65,"n/a",IF(OR(C65="battery electric vehicle",C65="natural gas vehicle",C65="plugin hybrid vehicle",C65="hydrogen vehicle"),"s-curve","linear")) -> n/a | H65: =D65 -> 0 | I65: =IF($F65="s-curve",$D65+($E65-$D65)*$I$2/(1+EXP($I$3*(COUNT($H$9:I$9)+$I$4))),TREND($D65:$E65,$D$9:$E$9,I$9)) -> 0 | J65: =IF($F65="s-curve",$D65+($E65-$D65)*$I$2/(1+EXP($I$3*(COUNT($H$9:J$9)+$I$4))),TREND($D65:$E65,$D$9:$E$9,J$9)) -> 0 | K65: =IF($F65="s-curve",$D65+($E65-$D65)*$I$2/(1+EXP($I$3*(COUNT($H$9:K$9)+$I$4))),TREND($D65:$E65,$D$9:$E$9,K$9)) -> 0 | L65: =IF($F65="s-curve",$D65+($E65-$D65)*$I$2/(1+EXP($I$3*(COUNT($H$9:L$9)+$I$4))),TREND($D65:$E65,$D$9:$E$9,L$9)) -> 0 | M65: =IF($F65="s-curve",$D65+($E65-$D65)*$I$2/(1+EXP($I$3*(COUNT($H$9:M$9)+$I$4))),TREND($D65:$E65,$D$9:$E$9,M$9)) -> 0 | N65: =IF($F65="s-curve",$D65+($E65-$D65)*$I$2/(1+EXP($I$3*(COUNT($H$9:N$9)+$I$4))),TREND($D65:$E65,$D$9:$E$9,N$9)) -> 0 | O65: =IF($F65="s-curve",$D65+($E65-$D65)*$I$2/(1+EXP($I$3*(COUNT($H$9:O$9)+$I$4))),TREND($D65:$E65,$D$9:$E$9,O$9)) -> 0 | P65: =IF($F65="s-curve",$D65+($E65-$D65)*$I$2/(1+EXP($I$3*(COUNT($H$9:P$9)+$I$4))),TREND($D65:$E65,$D$9:$E$9,P$9)) -> 0 | ... AL65: =IF($F65="s-curve",$D65+($E65-$D65)*$I$2/(1+EXP($I$3*(COUNT($H$9:AL$9)+$I$4))),TREND($D65:$E65,$D$9:$E$9,AL$9)) -> 0
A66: ships | B66: passenger | C66: battery electric vehicle | D66: 0 | E66: 0 | F66: =IF(D66=E66,"n/a",IF(OR(C66="battery electric vehicle",C66="natural gas vehicle",C66="plugin hybrid vehicle"),"s-curve","linear")) -> n/a | H66: =D66 -> 0 | I66: =IF($F66="s-curve",$D66+($E66-$D66)*$I$2/(1+EXP($I$3*(COUNT($H$9:I$9)+$I$4))),TREND($D66:$E66,$D$9:$E$9,I$9)) -> 0 | J66: =IF($F66="s-curve",$D66+($E66-$D66)*$I$2/(1+EXP($I$3*(COUNT($H$9:J$9)+$I$4))),TREND($D66:$E66,$D$9:$E$9,J$9)) -> 0 | K66: =IF($F66="s-curve",$D66+($E66-$D66)*$I$2/(1+EXP($I$3*(COUNT($H$9:K$9)+$I$4))),TREND($D66:$E66,$D$9:$E$9,K$9)) -> 0 | L66: =IF($F66="s-curve",$D66+($E66-$D66)*$I$2/(1+EXP($I$3*(COUNT($H$9:L$9)+$I$4))),TREND($D66:$E66,$D$9:$E$9,L$9)) -> 0 | M66: =IF($F66="s-curve",$D66+($E66-$D66)*$I$2/(1+EXP($I$3*(COUNT($H$9:M$9)+$I$4))),TREND($D66:$E66,$D$9:$E$9,M$9)) -> 0 | N66: =IF($F66="s-curve",$D66+($E66-$D66)*$I$2/(1+EXP($I$3*(COUNT($H$9:N$9)+$I$4))),TREND($D66:$E66,$D$9:$E$9,N$9)) -> 0 | O66: =IF($F66="s-curve",$D66+($E66-$D66)*$I$2/(1+EXP($I$3*(COUNT($H$9:O$9)+$I$4))),TREND($D66:$E66,$D$9:$E$9,O$9)) -> 0 | P66: =IF($F66="s-curve",$D66+($E66-$D66)*$I$2/(1+EXP($I$3*(COUNT($H$9:P$9)+$I$4))),TREND($D66:$E66,$D$9:$E$9,P$9)) -> 0 | ... AL66: =IF($F66="s-curve",$D66+($E66-$D66)*$I$2/(1+EXP($I$3*(COUNT($H$9:AL$9)+$I$4))),TREND($D66:$E66,$D$9:$E$9,AL$9)) -> 0
C67: natural gas vehicle | D67: 0 | E67: 0 | F67: =IF(D67=E67,"n/a",IF(OR(C67="battery electric vehicle",C67="natural gas vehicle",C67="plugin hybrid vehicle"),"s-curve","linear")) -> n/a | H67: =D67 -> 0 | I67: =IF($F67="s-curve",$D67+($E67-$D67)*$I$2/(1+EXP($I$3*(COUNT($H$9:I$9)+$I$4))),TREND($D67:$E67,$D$9:$E$9,I$9)) -> 0 | J67: =IF($F67="s-curve",$D67+($E67-$D67)*$I$2/(1+EXP($I$3*(COUNT($H$9:J$9)+$I$4))),TREND($D67:$E67,$D$9:$E$9,J$9)) -> 0 | K67: =IF($F67="s-curve",$D67+($E67-$D67)*$I$2/(1+EXP($I$3*(COUNT($H$9:K$9)+$I$4))),TREND($D67:$E67,$D$9:$E$9,K$9)) -> 0 | L67: =IF($F67="s-curve",$D67+($E67-$D67)*$I$2/(1+EXP($I$3*(COUNT($H$9:L$9)+$I$4))),TREND($D67:$E67,$D$9:$E$9,L$9)) -> 0 | M67: =IF($F67="s-curve",$D67+($E67-$D67)*$I$2/(1+EXP($I$3*(COUNT($H$9:M$9)+$I$4))),TREND($D67:$E67,$D$9:$E$9,M$9)) -> 0 | N67: =IF($F67="s-curve",$D67+($E67-$D67)*$I$2/(1+EXP($I$3*(COUNT($H$9:N$9)+$I$4))),TREND($D67:$E67,$D$9:$E$9,N$9)) -> 0 | O67: =IF($F67="s-curve",$D67+($E67-$D67)*$I$2/(1+EXP($I$3*(COUNT($H$9:O$9)+$I$4))),TREND($D67:$E67,$D$9:$E$9,O$9)) -> 0 | P67: =IF($F67="s-curve",$D67+($E67-$D67)*$I$2/(1+EXP($I$3*(COUNT($H$9:P$9)+$I$4))),TREND($D67:$E67,$D$9:$E$9,P$9)) -> 0 | ... AL67: =IF($F67="s-curve",$D67+($E67-$D67)*$I$2/(1+EXP($I$3*(COUNT($H$9:AL$9)+$I$4))),TREND($D67:$E67,$D$9:$E$9,AL$9)) -> 0
C68: gasoline vehicle | D68: 0 | E68: 0 | F68: =IF(D68=E68,"n/a",IF(OR(C68="battery electric vehicle",C68="natural gas vehicle",C68="plugin hybrid vehicle"),"s-curve","linear")) -> n/a | H68: =D68 -> 0 | I68: =IF($F68="s-curve",$D68+($E68-$D68)*$I$2/(1+EXP($I$3*(COUNT($H$9:I$9)+$I$4))),TREND($D68:$E68,$D$9:$E$9,I$9)) -> 0 | J68: =IF($F68="s-curve",$D68+($E68-$D68)*$I$2/(1+EXP($I$3*(COUNT($H$9:J$9)+$I$4))),TREND($D68:$E68,$D$9:$E$9,J$9)) -> 0 | K68: =IF($F68="s-curve",$D68+($E68-$D68)*$I$2/(1+EXP($I$3*(COUNT($H$9:K$9)+$I$4))),TREND($D68:$E68,$D$9:$E$9,K$9)) -> 0 | L68: =IF($F68="s-curve",$D68+($E68-$D68)*$I$2/(1+EXP($I$3*(COUNT($H$9:L$9)+$I$4))),TREND($D68:$E68,$D$9:$E$9,L$9)) -> 0 | M68: =IF($F68="s-curve",$D68+($E68-$D68)*$I$2/(1+EXP($I$3*(COUNT($H$9:M$9)+$I$4))),TREND($D68:$E68,$D$9:$E$9,M$9)) -> 0 | N68: =IF($F68="s-curve",$D68+($E68-$D68)*$I$2/(1+EXP($I$3*(COUNT($H$9:N$9)+$I$4))),TREND($D68:$E68,$D$9:$E$9,N$9)) -> 0 | O68: =IF($F68="s-curve",$D68+($E68-$D68)*$I$2/(1+EXP($I$3*(COUNT($H$9:O$9)+$I$4))),TREND($D68:$E68,$D$9:$E$9,O$9)) -> 0 | P68: =IF($F68="s-curve",$D68+($E68-$D68)*$I$2/(1+EXP($I$3*(COUNT($H$9:P$9)+$I$4))),TREND($D68:$E68,$D$9:$E$9,P$9)) -> 0 | ... AL68: =IF($F68="s-curve",$D68+($E68-$D68)*$I$2/(1+EXP($I$3*(COUNT($H$9:AL$9)+$I$4))),TREND($D68:$E68,$D$9:$E$9,AL$9)) -> 0
C69: diesel vehicle | D69: 1 | E69: 1 | F69: =IF(D69=E69,"n/a",IF(OR(C69="battery electric vehicle",C69="natural gas vehicle",C69="plugin hybrid vehicle"),"s-curve","linear")) -> n/a | H69: =D69 -> 1 | I69: =IF($F69="s-curve",$D69+($E69-$D69)*$I$2/(1+EXP($I$3*(COUNT($H$9:I$9)+$I$4))),TREND($D69:$E69,$D$9:$E$9,I$9)) -> 1 | J69: =IF($F69="s-curve",$D69+($E69-$D69)*$I$2/(1+EXP($I$3*(COUNT($H$9:J$9)+$I$4))),TREND($D69:$E69,$D$9:$E$9,J$9)) -> 1 | K69: =IF($F69="s-curve",$D69+($E69-$D69)*$I$2/(1+EXP($I$3*(COUNT($H$9:K$9)+$I$4))),TREND($D69:$E69,$D$9:$E$9,K$9)) -> 1 | L69: =IF($F69="s-curve",$D69+($E69-$D69)*$I$2/(1+EXP($I$3*(COUNT($H$9:L$9)+$I$4))),TREND($D69:$E69,$D$9:$E$9,L$9)) -> 1 | M69: =IF($F69="s-curve",$D69+($E69-$D69)*$I$2/(1+EXP($I$3*(COUNT($H$9:M$9)+$I$4))),TREND($D69:$E69,$D$9:$E$9,M$9)) -> 1 | N69: =IF($F69="s-curve",$D69+($E69-$D69)*$I$2/(1+EXP($I$3*(COUNT($H$9:N$9)+$I$4))),TREND($D69:$E69,$D$9:$E$9,N$9)) -> 1 | O69: =IF($F69="s-curve",$D69+($E69-$D69)*$I$2/(1+EXP($I$3*(COUNT($H$9:O$9)+$I$4))),TREND($D69:$E69,$D$9:$E$9,O$9)) -> 1 | P69: =IF($F69="s-curve",$D69+($E69-$D69)*$I$2/(1+EXP($I$3*(COUNT($H$9:P$9)+$I$4))),TREND($D69:$E69,$D$9:$E$9,P$9)) -> 1 | ... AL69: =IF($F69="s-curve",$D69+($E69-$D69)*$I$2/(1+EXP($I$3*(COUNT($H$9:AL$9)+$I$4))),TREND($D69:$E69,$D$9:$E$9,AL$9)) -> 1
C70: plugin hybrid vehicle | D70: 0 | E70: 0 | F70: =IF(D70=E70,"n/a",IF(OR(C70="battery electric vehicle",C70="natural gas vehicle",C70="plugin hybrid vehicle"),"s-curve","linear")) -> n/a | H70: =D70 -> 0 | I70: =IF($F70="s-curve",$D70+($E70-$D70)*$I$2/(1+EXP($I$3*(COUNT($H$9:I$9)+$I$4))),TREND($D70:$E70,$D$9:$E$9,I$9)) -> 0 | J70: =IF($F70="s-curve",$D70+($E70-$D70)*$I$2/(1+EXP($I$3*(COUNT($H$9:J$9)+$I$4))),TREND($D70:$E70,$D$9:$E$9,J$9)) -> 0 | K70: =IF($F70="s-curve",$D70+($E70-$D70)*$I$2/(1+EXP($I$3*(COUNT($H$9:K$9)+$I$4))),TREND($D70:$E70,$D$9:$E$9,K$9)) -> 0 | L70: =IF($F70="s-curve",$D70+($E70-$D70)*$I$2/(1+EXP($I$3*(COUNT($H$9:L$9)+$I$4))),TREND($D70:$E70,$D$9:$E$9,L$9)) -> 0 | M70: =IF($F70="s-curve",$D70+($E70-$D70)*$I$2/(1+EXP($I$3*(COUNT($H$9:M$9)+$I$4))),TREND($D70:$E70,$D$9:$E$9,M$9)) -> 0 | N70: =IF($F70="s-curve",$D70+($E70-$D70)*$I$2/(1+EXP($I$3*(COUNT($H$9:N$9)+$I$4))),TREND($D70:$E70,$D$9:$E$9,N$9)) -> 0 | O70: =IF($F70="s-curve",$D70+($E70-$D70)*$I$2/(1+EXP($I$3*(COUNT($H$9:O$9)+$I$4))),TREND($D70:$E70,$D$9:$E$9,O$9)) -> 0 | P70: =IF($F70="s-curve",$D70+($E70-$D70)*$I$2/(1+EXP($I$3*(COUNT($H$9:P$9)+$I$4))),TREND($D70:$E70,$D$9:$E$9,P$9)) -> 0 | ... AL70: =IF($F70="s-curve",$D70+($E70-$D70)*$I$2/(1+EXP($I$3*(COUNT($H$9:AL$9)+$I$4))),TREND($D70:$E70,$D$9:$E$9,AL$9)) -> 0
C71: LPG vehicle | D71: 0 | E71: 0 | F71: =IF(D71=E71,"n/a",IF(OR(C71="battery electric vehicle",C71="natural gas vehicle",C71="plugin hybrid vehicle",C71="hydrogen vehicle"),"s-curve","linear")) -> n/a | H71: =D71 -> 0 | I71: =IF($F71="s-curve",$D71+($E71-$D71)*$I$2/(1+EXP($I$3*(COUNT($H$9:I$9)+$I$4))),TREND($D71:$E71,$D$9:$E$9,I$9)) -> 0 | J71: =IF($F71="s-curve",$D71+($E71-$D71)*$I$2/(1+EXP($I$3*(COUNT($H$9:J$9)+$I$4))),TREND($D71:$E71,$D$9:$E$9,J$9)) -> 0 | K71: =IF($F71="s-curve",$D71+($E71-$D71)*$I$2/(1+EXP($I$3*(COUNT($H$9:K$9)+$I$4))),TREND($D71:$E71,$D$9:$E$9,K$9)) -> 0 | L71: =IF($F71="s-curve",$D71+($E71-$D71)*$I$2/(1+EXP($I$3*(COUNT($H$9:L$9)+$I$4))),TREND($D71:$E71,$D$9:$E$9,L$9)) -> 0 | M71: =IF($F71="s-curve",$D71+($E71-$D71)*$I$2/(1+EXP($I$3*(COUNT($H$9:M$9)+$I$4))),TREND($D71:$E71,$D$9:$E$9,M$9)) -> 0 | N71: =IF($F71="s-curve",$D71+($E71-$D71)*$I$2/(1+EXP($I$3*(COUNT($H$9:N$9)+$I$4))),TREND($D71:$E71,$D$9:$E$9,N$9)) -> 0 | O71: =IF($F71="s-curve",$D71+($E71-$D71)*$I$2/(1+EXP($I$3*(COUNT($H$9:O$9)+$I$4))),TREND($D71:$E71,$D$9:$E$9,O$9)) -> 0 | P71: =IF($F71="s-curve",$D71+($E71-$D71)*$I$2/(1+EXP($I$3*(COUNT($H$9:P$9)+$I$4))),TREND($D71:$E71,$D$9:$E$9,P$9)) -> 0 | ... AL71: =IF($F71="s-curve",$D71+($E71-$D71)*$I$2/(1+EXP($I$3*(COUNT($H$9:AL$9)+$I$4))),TREND($D71:$E71,$D$9:$E$9,AL$9)) -> 0
C72: hydrogen vehicle | D72: 0 | E72: 0 | F72: =IF(D72=E72,"n/a",IF(OR(C72="battery electric vehicle",C72="natural gas vehicle",C72="plugin hybrid vehicle",C72="hydrogen vehicle"),"s-curve","linear")) -> n/a | H72: =D72 -> 0 | I72: =IF($F72="s-curve",$D72+($E72-$D72)*$I$2/(1+EXP($I$3*(COUNT($H$9:I$9)+$I$4))),TREND($D72:$E72,$D$9:$E$9,I$9)) -> 0 | J72: =IF($F72="s-curve",$D72+($E72-$D72)*$I$2/(1+EXP($I$3*(COUNT($H$9:J$9)+$I$4))),TREND($D72:$E72,$D$9:$E$9,J$9)) -> 0 | K72: =IF($F72="s-curve",$D72+($E72-$D72)*$I$2/(1+EXP($I$3*(COUNT($H$9:K$9)+$I$4))),TREND($D72:$E72,$D$9:$E$9,K$9)) -> 0 | L72: =IF($F72="s-curve",$D72+($E72-$D72)*$I$2/(1+EXP($I$3*(COUNT($H$9:L$9)+$I$4))),TREND($D72:$E72,$D$9:$E$9,L$9)) -> 0 | M72: =IF($F72="s-curve",$D72+($E72-$D72)*$I$2/(1+EXP($I$3*(COUNT($H$9:M$9)+$I$4))),TREND($D72:$E72,$D$9:$E$9,M$9)) -> 0 | N72: =IF($F72="s-curve",$D72+($E72-$D72)*$I$2/(1+EXP($I$3*(COUNT($H$9:N$9)+$I$4))),TREND($D72:$E72,$D$9:$E$9,N$9)) -> 0 | O72: =IF($F72="s-curve",$D72+($E72-$D72)*$I$2/(1+EXP($I$3*(COUNT($H$9:O$9)+$I$4))),TREND($D72:$E72,$D$9:$E$9,O$9)) -> 0 | P72: =IF($F72="s-curve",$D72+($E72-$D72)*$I$2/(1+EXP($I$3*(COUNT($H$9:P$9)+$I$4))),TREND($D72:$E72,$D$9:$E$9,P$9)) -> 0 | ... AL72: =IF($F72="s-curve",$D72+($E72-$D72)*$I$2/(1+EXP($I$3*(COUNT($H$9:AL$9)+$I$4))),TREND($D72:$E72,$D$9:$E$9,AL$9)) -> 0
A73: ships | B73: freight | C73: battery electric vehicle | D73: =MIN(1.25*INDEX('SYVbT-freight'!$B$6:$H$6,MATCH(Data!$C10,'SYVbT-passenger'!$B$1:$H$1,0))/SUM('SYVbT-freight'!$B$6:$H$6),1) -> 0 | E73: =D73 -> 0 | F73: =IF(D73=E73,"n/a",IF(OR(C73="battery electric vehicle",C73="natural gas vehicle",C73="plugin hybrid vehicle"),"s-curve","linear")) -> n/a | H73: =D73 -> 0 | I73: =IF($F73="s-curve",$D73+($E73-$D73)*$I$2/(1+EXP($I$3*(COUNT($H$9:I$9)+$I$4))),TREND($D73:$E73,$D$9:$E$9,I$9)) -> 0 | J73: =IF($F73="s-curve",$D73+($E73-$D73)*$I$2/(1+EXP($I$3*(COUNT($H$9:J$9)+$I$4))),TREND($D73:$E73,$D$9:$E$9,J$9)) -> 0 | K73: =IF($F73="s-curve",$D73+($E73-$D73)*$I$2/(1+EXP($I$3*(COUNT($H$9:K$9)+$I$4))),TREND($D73:$E73,$D$9:$E$9,K$9)) -> 0 | L73: =IF($F73="s-curve",$D73+($E73-$D73)*$I$2/(1+EXP($I$3*(COUNT($H$9:L$9)+$I$4))),TREND($D73:$E73,$D$9:$E$9,L$9)) -> 0 | M73: =IF($F73="s-curve",$D73+($E73-$D73)*$I$2/(1+EXP($I$3*(COUNT($H$9:M$9)+$I$4))),TREND($D73:$E73,$D$9:$E$9,M$9)) -> 0 | N73: =IF($F73="s-curve",$D73+($E73-$D73)*$I$2/(1+EXP($I$3*(COUNT($H$9:N$9)+$I$4))),TREND($D73:$E73,$D$9:$E$9,N$9)) -> 0 | O73: =IF($F73="s-curve",$D73+($E73-$D73)*$I$2/(1+EXP($I$3*(COUNT($H$9:O$9)+$I$4))),TREND($D73:$E73,$D$9:$E$9,O$9)) -> 0 | P73: =IF($F73="s-curve",$D73+($E73-$D73)*$I$2/(1+EXP($I$3*(COUNT($H$9:P$9)+$I$4))),TREND($D73:$E73,$D$9:$E$9,P$9)) -> 0 | ... AL73: =IF($F73="s-curve",$D73+($E73-$D73)*$I$2/(1+EXP($I$3*(COUNT($H$9:AL$9)+$I$4))),TREND($D73:$E73,$D$9:$E$9,AL$9)) -> 0
C74: natural gas vehicle | D74: =MIN(1.25*INDEX('SYVbT-freight'!$B$6:$H$6,MATCH(Data!$C11,'SYVbT-passenger'!$B$1:$H$1,0))/SUM('SYVbT-freight'!$B$6:$H$6),1) -> 0 | E74: =D74 -> 0 | F74: =IF(D74=E74,"n/a",IF(OR(C74="battery electric vehicle",C74="natural gas vehicle",C74="plugin hybrid vehicle"),"s-curve","linear")) -> n/a | H74: =D74 -> 0 | I74: =IF($F74="s-curve",$D74+($E74-$D74)*$I$2/(1+EXP($I$3*(COUNT($H$9:I$9)+$I$4))),TREND($D74:$E74,$D$9:$E$9,I$9)) -> 0 | J74: =IF($F74="s-curve",$D74+($E74-$D74)*$I$2/(1+EXP($I$3*(COUNT($H$9:J$9)+$I$4))),TREND($D74:$E74,$D$9:$E$9,J$9)) -> 0 | K74: =IF($F74="s-curve",$D74+($E74-$D74)*$I$2/(1+EXP($I$3*(COUNT($H$9:K$9)+$I$4))),TREND($D74:$E74,$D$9:$E$9,K$9)) -> 0 | L74: =IF($F74="s-curve",$D74+($E74-$D74)*$I$2/(1+EXP($I$3*(COUNT($H$9:L$9)+$I$4))),TREND($D74:$E74,$D$9:$E$9,L$9)) -> 0 | M74: =IF($F74="s-curve",$D74+($E74-$D74)*$I$2/(1+EXP($I$3*(COUNT($H$9:M$9)+$I$4))),TREND($D74:$E74,$D$9:$E$9,M$9)) -> 0 | N74: =IF($F74="s-curve",$D74+($E74-$D74)*$I$2/(1+EXP($I$3*(COUNT($H$9:N$9)+$I$4))),TREND($D74:$E74,$D$9:$E$9,N$9)) -> 0 | O74: =IF($F74="s-curve",$D74+($E74-$D74)*$I$2/(1+EXP($I$3*(COUNT($H$9:O$9)+$I$4))),TREND($D74:$E74,$D$9:$E$9,O$9)) -> 0 | P74: =IF($F74="s-curve",$D74+($E74-$D74)*$I$2/(1+EXP($I$3*(COUNT($H$9:P$9)+$I$4))),TREND($D74:$E74,$D$9:$E$9,P$9)) -> 0 | ... AL74: =IF($F74="s-curve",$D74+($E74-$D74)*$I$2/(1+EXP($I$3*(COUNT($H$9:AL$9)+$I$4))),TREND($D74:$E74,$D$9:$E$9,AL$9)) -> 0
C75: gasoline vehicle | D75: =MIN(1.25*INDEX('SYVbT-freight'!$B$6:$H$6,MATCH(Data!$C12,'SYVbT-passenger'!$B$1:$H$1,0))/SUM('SYVbT-freight'!$B$6:$H$6),1) -> 0.0041666444 | E75: =D75 -> 0.0041666444 | F75: =IF(D75=E75,"n/a",IF(OR(C75="battery electric vehicle",C75="natural gas vehicle",C75="plugin hybrid vehicle"),"s-curve","linear")) -> n/a | H75: =D75 -> 0.0041666444 | I75: =IF($F75="s-curve",$D75+($E75-$D75)*$I$2/(1+EXP($I$3*(COUNT($H$9:I$9)+$I$4))),TREND($D75:$E75,$D$9:$E$9,I$9)) -> 0.0041666444 | J75: =IF($F75="s-curve",$D75+($E75-$D75)*$I$2/(1+EXP($I$3*(COUNT($H$9:J$9)+$I$4))),TREND($D75:$E75,$D$9:$E$9,J$9)) -> 0.0041666444 | K75: =IF($F75="s-curve",$D75+($E75-$D75)*$I$2/(1+EXP($I$3*(COUNT($H$9:K$9)+$I$4))),TREND($D75:$E75,$D$9:$E$9,K$9)) -> 0.0041666444 | L75: =IF($F75="s-curve",$D75+($E75-$D75)*$I$2/(1+EXP($I$3*(COUNT($H$9:L$9)+$I$4))),TREND($D75:$E75,$D$9:$E$9,L$9)) -> 0.0041666444 | M75: =IF($F75="s-curve",$D75+($E75-$D75)*$I$2/(1+EXP($I$3*(COUNT($H$9:M$9)+$I$4))),TREND($D75:$E75,$D$9:$E$9,M$9)) -> 0.0041666444 | N75: =IF($F75="s-curve",$D75+($E75-$D75)*$I$2/(1+EXP($I$3*(COUNT($H$9:N$9)+$I$4))),TREND($D75:$E75,$D$9:$E$9,N$9)) -> 0.0041666444 | O75: =IF($F75="s-curve",$D75+($E75-$D75)*$I$2/(1+EXP($I$3*(COUNT($H$9:O$9)+$I$4))),TREND($D75:$E75,$D$9:$E$9,O$9)) -> 0.0041666444 | P75: =IF($F75="s-curve",$D75+($E75-$D75)*$I$2/(1+EXP($I$3*(COUNT($H$9:P$9)+$I$4))),TREND($D75:$E75,$D$9:$E$9,P$9)) -> 0.0041666444 | ... AL75: =IF($F75="s-curve",$D75+($E75-$D75)*$I$2/(1+EXP($I$3*(COUNT($H$9:AL$9)+$I$4))),TREND($D75:$E75,$D$9:$E$9,AL$9)) -> 0.0041666444
C76: diesel vehicle | D76: =MIN(1.25*INDEX('SYVbT-freight'!$B$6:$H$6,MATCH(Data!$C13,'SYVbT-passenger'!$B$1:$H$1,0))/SUM('SYVbT-freight'!$B$6:$H$6),1) -> 1 | E76: =D76 -> 1 | F76: =IF(D76=E76,"n/a",IF(OR(C76="battery electric vehicle",C76="natural gas vehicle",C76="plugin hybrid vehicle"),"s-curve","linear")) -> n/a | H76: =D76 -> 1 | I76: =IF($F76="s-curve",$D76+($E76-$D76)*$I$2/(1+EXP($I$3*(COUNT($H$9:I$9)+$I$4))),TREND($D76:$E76,$D$9:$E$9,I$9)) -> 1 | J76: =IF($F76="s-curve",$D76+($E76-$D76)*$I$2/(1+EXP($I$3*(COUNT($H$9:J$9)+$I$4))),TREND($D76:$E76,$D$9:$E$9,J$9)) -> 1 | K76: =IF($F76="s-curve",$D76+($E76-$D76)*$I$2/(1+EXP($I$3*(COUNT($H$9:K$9)+$I$4))),TREND($D76:$E76,$D$9:$E$9,K$9)) -> 1 | L76: =IF($F76="s-curve",$D76+($E76-$D76)*$I$2/(1+EXP($I$3*(COUNT($H$9:L$9)+$I$4))),TREND($D76:$E76,$D$9:$E$9,L$9)) -> 1 | M76: =IF($F76="s-curve",$D76+($E76-$D76)*$I$2/(1+EXP($I$3*(COUNT($H$9:M$9)+$I$4))),TREND($D76:$E76,$D$9:$E$9,M$9)) -> 1 | N76: =IF($F76="s-curve",$D76+($E76-$D76)*$I$2/(1+EXP($I$3*(COUNT($H$9:N$9)+$I$4))),TREND($D76:$E76,$D$9:$E$9,N$9)) -> 1 | O76: =IF($F76="s-curve",$D76+($E76-$D76)*$I$2/(1+EXP($I$3*(COUNT($H$9:O$9)+$I$4))),TREND($D76:$E76,$D$9:$E$9,O$9)) -> 1 | P76: =IF($F76="s-curve",$D76+($E76-$D76)*$I$2/(1+EXP($I$3*(COUNT($H$9:P$9)+$I$4))),TREND($D76:$E76,$D$9:$E$9,P$9)) -> 1 | ... AL76: =IF($F76="s-curve",$D76+($E76-$D76)*$I$2/(1+EXP($I$3*(COUNT($H$9:AL$9)+$I$4))),TREND($D76:$E76,$D$9:$E$9,AL$9)) -> 1
C77: plugin hybrid vehicle | D77: =MIN(1.25*INDEX('SYVbT-freight'!$B$6:$H$6,MATCH(Data!$C14,'SYVbT-passenger'!$B$1:$H$1,0))/SUM('SYVbT-freight'!$B$6:$H$6),1) -> 0 | E77: =D77 -> 0 | F77: =IF(D77=E77,"n/a",IF(OR(C77="battery electric vehicle",C77="natural gas vehicle",C77="plugin hybrid vehicle"),"s-curve","linear")) -> n/a | H77: =D77 -> 0 | I77: =IF($F77="s-curve",$D77+($E77-$D77)*$I$2/(1+EXP($I$3*(COUNT($H$9:I$9)+$I$4))),TREND($D77:$E77,$D$9:$E$9,I$9)) -> 0 | J77: =IF($F77="s-curve",$D77+($E77-$D77)*$I$2/(1+EXP($I$3*(COUNT($H$9:J$9)+$I$4))),TREND($D77:$E77,$D$9:$E$9,J$9)) -> 0 | K77: =IF($F77="s-curve",$D77+($E77-$D77)*$I$2/(1+EXP($I$3*(COUNT($H$9:K$9)+$I$4))),TREND($D77:$E77,$D$9:$E$9,K$9)) -> 0 | L77: =IF($F77="s-curve",$D77+($E77-$D77)*$I$2/(1+EXP($I$3*(COUNT($H$9:L$9)+$I$4))),TREND($D77:$E77,$D$9:$E$9,L$9)) -> 0 | M77: =IF($F77="s-curve",$D77+($E77-$D77)*$I$2/(1+EXP($I$3*(COUNT($H$9:M$9)+$I$4))),TREND($D77:$E77,$D$9:$E$9,M$9)) -> 0 | N77: =IF($F77="s-curve",$D77+($E77-$D77)*$I$2/(1+EXP($I$3*(COUNT($H$9:N$9)+$I$4))),TREND($D77:$E77,$D$9:$E$9,N$9)) -> 0 | O77: =IF($F77="s-curve",$D77+($E77-$D77)*$I$2/(1+EXP($I$3*(COUNT($H$9:O$9)+$I$4))),TREND($D77:$E77,$D$9:$E$9,O$9)) -> 0 | P77: =IF($F77="s-curve",$D77+($E77-$D77)*$I$2/(1+EXP($I$3*(COUNT($H$9:P$9)+$I$4))),TREND($D77:$E77,$D$9:$E$9,P$9)) -> 0 | ... AL77: =IF($F77="s-curve",$D77+($E77-$D77)*$I$2/(1+EXP($I$3*(COUNT($H$9:AL$9)+$I$4))),TREND($D77:$E77,$D$9:$E$9,AL$9)) -> 0
C78: LPG vehicle | D78: =MIN(1.25*INDEX('SYVbT-freight'!$B$6:$H$6,MATCH(Data!$C15,'SYVbT-passenger'!$B$1:$H$1,0))/SUM('SYVbT-freight'!$B$6:$H$6),1) -> 0.0016666578 | E78: =D78 -> 0.0016666578 | F78: =IF(D78=E78,"n/a",IF(OR(C78="battery electric vehicle",C78="natural gas vehicle",C78="plugin hybrid vehicle",C78="hydrogen vehicle"),"s-curve","linear")) -> n/a | H78: =D78 -> 0.0016666578 | I78: =IF($F78="s-curve",$D78+($E78-$D78)*$I$2/(1+EXP($I$3*(COUNT($H$9:I$9)+$I$4))),TREND($D78:$E78,$D$9:$E$9,I$9)) -> 0.0016666578 | J78: =IF($F78="s-curve",$D78+($E78-$D78)*$I$2/(1+EXP($I$3*(COUNT($H$9:J$9)+$I$4))),TREND($D78:$E78,$D$9:$E$9,J$9)) -> 0.0016666578 | K78: =IF($F78="s-curve",$D78+($E78-$D78)*$I$2/(1+EXP($I$3*(COUNT($H$9:K$9)+$I$4))),TREND($D78:$E78,$D$9:$E$9,K$9)) -> 0.0016666578 | L78: =IF($F78="s-curve",$D78+($E78-$D78)*$I$2/(1+EXP($I$3*(COUNT($H$9:L$9)+$I$4))),TREND($D78:$E78,$D$9:$E$9,L$9)) -> 0.0016666578 | M78: =IF($F78="s-curve",$D78+($E78-$D78)*$I$2/(1+EXP($I$3*(COUNT($H$9:M$9)+$I$4))),TREND($D78:$E78,$D$9:$E$9,M$9)) -> 0.0016666578 | N78: =IF($F78="s-curve",$D78+($E78-$D78)*$I$2/(1+EXP($I$3*(COUNT($H$9:N$9)+$I$4))),TREND($D78:$E78,$D$9:$E$9,N$9)) -> 0.0016666578 | O78: =IF($F78="s-curve",$D78+($E78-$D78)*$I$2/(1+EXP($I$3*(COUNT($H$9:O$9)+$I$4))),TREND($D78:$E78,$D$9:$E$9,O$9)) -> 0.0016666578 | P78: =IF($F78="s-curve",$D78+($E78-$D78)*$I$2/(1+EXP($I$3*(COUNT($H$9:P$9)+$I$4))),TREND($D78:$E78,$D$9:$E$9,P$9)) -> 0.0016666578 | ... AL78: =IF($F78="s-curve",$D78+($E78-$D78)*$I$2/(1+EXP($I$3*(COUNT($H$9:AL$9)+$I$4))),TREND($D78:$E78,$D$9:$E$9,AL$9)) -> 0.0016666578
C79: hydrogen vehicle | D79: =MIN(1.25*INDEX('SYVbT-freight'!$B$6:$H$6,MATCH(Data!$C16,'SYVbT-passenger'!$B$1:$H$1,0))/SUM('SYVbT-freight'!$B$6:$H$6),1) -> 0 | E79: =D79 -> 0 | F79: =IF(D79=E79,"n/a",IF(OR(C79="battery electric vehicle",C79="natural gas vehicle",C79="plugin hybrid vehicle",C79="hydrogen vehicle"),"s-curve","linear")) -> n/a | H79: =D79 -> 0 | I79: =IF($F79="s-curve",$D79+($E79-$D79)*$I$2/(1+EXP($I$3*(COUNT($H$9:I$9)+$I$4))),TREND($D79:$E79,$D$9:$E$9,I$9)) -> 0 | J79: =IF($F79="s-curve",$D79+($E79-$D79)*$I$2/(1+EXP($I$3*(COUNT($H$9:J$9)+$I$4))),TREND($D79:$E79,$D$9:$E$9,J$9)) -> 0 | K79: =IF($F79="s-curve",$D79+($E79-$D79)*$I$2/(1+EXP($I$3*(COUNT($H$9:K$9)+$I$4))),TREND($D79:$E79,$D$9:$E$9,K$9)) -> 0 | L79: =IF($F79="s-curve",$D79+($E79-$D79)*$I$2/(1+EXP($I$3*(COUNT($H$9:L$9)+$I$4))),TREND($D79:$E79,$D$9:$E$9,L$9)) -> 0 | M79: =IF($F79="s-curve",$D79+($E79-$D79)*$I$2/(1+EXP($I$3*(COUNT($H$9:M$9)+$I$4))),TREND($D79:$E79,$D$9:$E$9,M$9)) -> 0 | N79: =IF($F79="s-curve",$D79+($E79-$D79)*$I$2/(1+EXP($I$3*(COUNT($H$9:N$9)+$I$4))),TREND($D79:$E79,$D$9:$E$9,N$9)) -> 0 | O79: =IF($F79="s-curve",$D79+($E79-$D79)*$I$2/(1+EXP($I$3*(COUNT($H$9:O$9)+$I$4))),TREND($D79:$E79,$D$9:$E$9,O$9)) -> 0 | P79: =IF($F79="s-curve",$D79+($E79-$D79)*$I$2/(1+EXP($I$3*(COUNT($H$9:P$9)+$I$4))),TREND($D79:$E79,$D$9:$E$9,P$9)) -> 0 | ... AL79: =IF($F79="s-curve",$D79+($E79-$D79)*$I$2/(1+EXP($I$3*(COUNT($H$9:AL$9)+$I$4))),TREND($D79:$E79,$D$9:$E$9,AL$9)) -> 0
A80: motorbikes | B80: passenger | C80: battery electric vehicle | D80: 0 | E80: 1 | F80: =IF(D80=E80,"n/a",IF(OR(C80="battery electric vehicle",C80="natural gas vehicle",C80="plugin hybrid vehicle"),"s-curve","linear")) -> s-curve | H80: =D80 -> 0 | I80: =IF($F80="s-curve",$D80+($E80-$D80)*$I$2/(1+EXP($I$3*(COUNT($H$9:I$9)+$I$4))),TREND($D80:$E80,$D$9:$E$9,I$9)) -> 0.014774032 | J80: =IF($F80="s-curve",$D80+($E80-$D80)*$I$2/(1+EXP($I$3*(COUNT($H$9:J$9)+$I$4))),TREND($D80:$E80,$D$9:$E$9,J$9)) -> 0.019840306 | K80: =IF($F80="s-curve",$D80+($E80-$D80)*$I$2/(1+EXP($I$3*(COUNT($H$9:K$9)+$I$4))),TREND($D80:$E80,$D$9:$E$9,K$9)) -> 0.026596994 | L80: =IF($F80="s-curve",$D80+($E80-$D80)*$I$2/(1+EXP($I$3*(COUNT($H$9:L$9)+$I$4))),TREND($D80:$E80,$D$9:$E$9,L$9)) -> 0.035571189 | M80: =IF($F80="s-curve",$D80+($E80-$D80)*$I$2/(1+EXP($I$3*(COUNT($H$9:M$9)+$I$4))),TREND($D80:$E80,$D$9:$E$9,M$9)) -> 0.047425873 | N80: =IF($F80="s-curve",$D80+($E80-$D80)*$I$2/(1+EXP($I$3*(COUNT($H$9:N$9)+$I$4))),TREND($D80:$E80,$D$9:$E$9,N$9)) -> 0.062973356 | O80: =IF($F80="s-curve",$D80+($E80-$D80)*$I$2/(1+EXP($I$3*(COUNT($H$9:O$9)+$I$4))),TREND($D80:$E80,$D$9:$E$9,O$9)) -> 0.083172696 | P80: =IF($F80="s-curve",$D80+($E80-$D80)*$I$2/(1+EXP($I$3*(COUNT($H$9:P$9)+$I$4))),TREND($D80:$E80,$D$9:$E$9,P$9)) -> 0.10909682 | ... AL80: =IF($F80="s-curve",$D80+($E80-$D80)*$I$2/(1+EXP($I$3*(COUNT($H$9:AL$9)+$I$4))),TREND($D80:$E80,$D$9:$E$9,AL$9)) -> 0.98901306
C81: natural gas vehicle | D81: ='SYVbT-passenger'!C7/SUM('SYVbT-passenger'!7:7) -> 0 | E81: 0 | F81: =IF(D81=E81,"n/a",IF(OR(C81="battery electric vehicle",C81="natural gas vehicle",C81="plugin hybrid vehicle"),"s-curve","linear")) -> n/a | H81: =D81 -> 0 | I81: =IF($F81="s-curve",$D81+($E81-$D81)*$I$2/(1+EXP($I$3*(COUNT($H$9:I$9)+$I$4))),TREND($D81:$E81,$D$9:$E$9,I$9)) -> 0 | J81: =IF($F81="s-curve",$D81+($E81-$D81)*$I$2/(1+EXP($I$3*(COUNT($H$9:J$9)+$I$4))),TREND($D81:$E81,$D$9:$E$9,J$9)) -> 0 | K81: =IF($F81="s-curve",$D81+($E81-$D81)*$I$2/(1+EXP($I$3*(COUNT($H$9:K$9)+$I$4))),TREND($D81:$E81,$D$9:$E$9,K$9)) -> 0 | L81: =IF($F81="s-curve",$D81+($E81-$D81)*$I$2/(1+EXP($I$3*(COUNT($H$9:L$9)+$I$4))),TREND($D81:$E81,$D$9:$E$9,L$9)) -> 0 | M81: =IF($F81="s-curve",$D81+($E81-$D81)*$I$2/(1+EXP($I$3*(COUNT($H$9:M$9)+$I$4))),TREND($D81:$E81,$D$9:$E$9,M$9)) -> 0 | N81: =IF($F81="s-curve",$D81+($E81-$D81)*$I$2/(1+EXP($I$3*(COUNT($H$9:N$9)+$I$4))),TREND($D81:$E81,$D$9:$E$9,N$9)) -> 0 | O81: =IF($F81="s-curve",$D81+($E81-$D81)*$I$2/(1+EXP($I$3*(COUNT($H$9:O$9)+$I$4))),TREND($D81:$E81,$D$9:$E$9,O$9)) -> 0 | P81: =IF($F81="s-curve",$D81+($E81-$D81)*$I$2/(1+EXP($I$3*(COUNT($H$9:P$9)+$I$4))),TREND($D81:$E81,$D$9:$E$9,P$9)) -> 0 | ... AL81: =IF($F81="s-curve",$D81+($E81-$D81)*$I$2/(1+EXP($I$3*(COUNT($H$9:AL$9)+$I$4))),TREND($D81:$E81,$D$9:$E$9,AL$9)) -> 0
C82: gasoline vehicle | D82: 3 | E82: 3 | F82: =IF(D82=E82,"n/a",IF(OR(C82="battery electric vehicle",C82="natural gas vehicle",C82="plugin hybrid vehicle"),"s-curve","linear")) -> n/a | H82: =D82 -> 3 | I82: =IF($F82="s-curve",$D82+($E82-$D82)*$I$2/(1+EXP($I$3*(COUNT($H$9:I$9)+$I$4))),TREND($D82:$E82,$D$9:$E$9,I$9)) -> 3 | J82: =IF($F82="s-curve",$D82+($E82-$D82)*$I$2/(1+EXP($I$3*(COUNT($H$9:J$9)+$I$4))),TREND($D82:$E82,$D$9:$E$9,J$9)) -> 3 | K82: =IF($F82="s-curve",$D82+($E82-$D82)*$I$2/(1+EXP($I$3*(COUNT($H$9:K$9)+$I$4))),TREND($D82:$E82,$D$9:$E$9,K$9)) -> 3 | L82: =IF($F82="s-curve",$D82+($E82-$D82)*$I$2/(1+EXP($I$3*(COUNT($H$9:L$9)+$I$4))),TREND($D82:$E82,$D$9:$E$9,L$9)) -> 3 | M82: =IF($F82="s-curve",$D82+($E82-$D82)*$I$2/(1+EXP($I$3*(COUNT($H$9:M$9)+$I$4))),TREND($D82:$E82,$D$9:$E$9,M$9)) -> 3 | N82: =IF($F82="s-curve",$D82+($E82-$D82)*$I$2/(1+EXP($I$3*(COUNT($H$9:N$9)+$I$4))),TREND($D82:$E82,$D$9:$E$9,N$9)) -> 3 | O82: =IF($F82="s-curve",$D82+($E82-$D82)*$I$2/(1+EXP($I$3*(COUNT($H$9:O$9)+$I$4))),TREND($D82:$E82,$D$9:$E$9,O$9)) -> 3 | P82: =IF($F82="s-curve",$D82+($E82-$D82)*$I$2/(1+EXP($I$3*(COUNT($H$9:P$9)+$I$4))),TREND($D82:$E82,$D$9:$E$9,P$9)) -> 3 | ... AL82: =IF($F82="s-curve",$D82+($E82-$D82)*$I$2/(1+EXP($I$3*(COUNT($H$9:AL$9)+$I$4))),TREND($D82:$E82,$D$9:$E$9,AL$9)) -> 3
C83: diesel vehicle | D83: ='SYVbT-passenger'!E7/SUM('SYVbT-passenger'!7:7) -> 0 | E83: 0 | F83: =IF(D83=E83,"n/a",IF(OR(C83="battery electric vehicle",C83="natural gas vehicle",C83="plugin hybrid vehicle"),"s-curve","linear")) -> n/a | H83: =D83 -> 0 | I83: =IF($F83="s-curve",$D83+($E83-$D83)*$I$2/(1+EXP($I$3*(COUNT($H$9:I$9)+$I$4))),TREND($D83:$E83,$D$9:$E$9,I$9)) -> 0 | J83: =IF($F83="s-curve",$D83+($E83-$D83)*$I$2/(1+EXP($I$3*(COUNT($H$9:J$9)+$I$4))),TREND($D83:$E83,$D$9:$E$9,J$9)) -> 0 | K83: =IF($F83="s-curve",$D83+($E83-$D83)*$I$2/(1+EXP($I$3*(COUNT($H$9:K$9)+$I$4))),TREND($D83:$E83,$D$9:$E$9,K$9)) -> 0 | L83: =IF($F83="s-curve",$D83+($E83-$D83)*$I$2/(1+EXP($I$3*(COUNT($H$9:L$9)+$I$4))),TREND($D83:$E83,$D$9:$E$9,L$9)) -> 0 | M83: =IF($F83="s-curve",$D83+($E83-$D83)*$I$2/(1+EXP($I$3*(COUNT($H$9:M$9)+$I$4))),TREND($D83:$E83,$D$9:$E$9,M$9)) -> 0 | N83: =IF($F83="s-curve",$D83+($E83-$D83)*$I$2/(1+EXP($I$3*(COUNT($H$9:N$9)+$I$4))),TREND($D83:$E83,$D$9:$E$9,N$9)) -> 0 | O83: =IF($F83="s-curve",$D83+($E83-$D83)*$I$2/(1+EXP($I$3*(COUNT($H$9:O$9)+$I$4))),TREND($D83:$E83,$D$9:$E$9,O$9)) -> 0 | P83: =IF($F83="s-curve",$D83+($E83-$D83)*$I$2/(1+EXP($I$3*(COUNT($H$9:P$9)+$I$4))),TREND($D83:$E83,$D$9:$E$9,P$9)) -> 0 | ... AL83: =IF($F83="s-curve",$D83+($E83-$D83)*$I$2/(1+EXP($I$3*(COUNT($H$9:AL$9)+$I$4))),TREND($D83:$E83,$D$9:$E$9,AL$9)) -> 0
C84: plugin hybrid vehicle | D84: ='SYVbT-passenger'!F7/SUM('SYVbT-passenger'!7:7) -> 0 | E84: 0 | F84: =IF(D84=E84,"n/a",IF(OR(C84="battery electric vehicle",C84="natural gas vehicle",C84="plugin hybrid vehicle"),"s-curve","linear")) -> n/a | H84: =D84 -> 0 | I84: =IF($F84="s-curve",$D84+($E84-$D84)*$I$2/(1+EXP($I$3*(COUNT($H$9:I$9)+$I$4))),TREND($D84:$E84,$D$9:$E$9,I$9)) -> 0 | J84: =IF($F84="s-curve",$D84+($E84-$D84)*$I$2/(1+EXP($I$3*(COUNT($H$9:J$9)+$I$4))),TREND($D84:$E84,$D$9:$E$9,J$9)) -> 0 | K84: =IF($F84="s-curve",$D84+($E84-$D84)*$I$2/(1+EXP($I$3*(COUNT($H$9:K$9)+$I$4))),TREND($D84:$E84,$D$9:$E$9,K$9)) -> 0 | L84: =IF($F84="s-curve",$D84+($E84-$D84)*$I$2/(1+EXP($I$3*(COUNT($H$9:L$9)+$I$4))),TREND($D84:$E84,$D$9:$E$9,L$9)) -> 0 | M84: =IF($F84="s-curve",$D84+($E84-$D84)*$I$2/(1+EXP($I$3*(COUNT($H$9:M$9)+$I$4))),TREND($D84:$E84,$D$9:$E$9,M$9)) -> 0 | N84: =IF($F84="s-curve",$D84+($E84-$D84)*$I$2/(1+EXP($I$3*(COUNT($H$9:N$9)+$I$4))),TREND($D84:$E84,$D$9:$E$9,N$9)) -> 0 | O84: =IF($F84="s-curve",$D84+($E84-$D84)*$I$2/(1+EXP($I$3*(COUNT($H$9:O$9)+$I$4))),TREND($D84:$E84,$D$9:$E$9,O$9)) -> 0 | P84: =IF($F84="s-curve",$D84+($E84-$D84)*$I$2/(1+EXP($I$3*(COUNT($H$9:P$9)+$I$4))),TREND($D84:$E84,$D$9:$E$9,P$9)) -> 0 | ... AL84: =IF($F84="s-curve",$D84+($E84-$D84)*$I$2/(1+EXP($I$3*(COUNT($H$9:AL$9)+$I$4))),TREND($D84:$E84,$D$9:$E$9,AL$9)) -> 0
C85: LPG vehicle | D85: ='SYVbT-passenger'!G7/SUM('SYVbT-passenger'!7:7) -> 0 | E85: 0 | F85: =IF(D85=E85,"n/a",IF(OR(C85="battery electric vehicle",C85="natural gas vehicle",C85="plugin hybrid vehicle",C85="hydrogen vehicle"),"s-curve","linear")) -> n/a | H85: =D85 -> 0 | I85: =IF($F85="s-curve",$D85+($E85-$D85)*$I$2/(1+EXP($I$3*(COUNT($H$9:I$9)+$I$4))),TREND($D85:$E85,$D$9:$E$9,I$9)) -> 0 | J85: =IF($F85="s-curve",$D85+($E85-$D85)*$I$2/(1+EXP($I$3*(COUNT($H$9:J$9)+$I$4))),TREND($D85:$E85,$D$9:$E$9,J$9)) -> 0 | K85: =IF($F85="s-curve",$D85+($E85-$D85)*$I$2/(1+EXP($I$3*(COUNT($H$9:K$9)+$I$4))),TREND($D85:$E85,$D$9:$E$9,K$9)) -> 0 | L85: =IF($F85="s-curve",$D85+($E85-$D85)*$I$2/(1+EXP($I$3*(COUNT($H$9:L$9)+$I$4))),TREND($D85:$E85,$D$9:$E$9,L$9)) -> 0 | M85: =IF($F85="s-curve",$D85+($E85-$D85)*$I$2/(1+EXP($I$3*(COUNT($H$9:M$9)+$I$4))),TREND($D85:$E85,$D$9:$E$9,M$9)) -> 0 | N85: =IF($F85="s-curve",$D85+($E85-$D85)*$I$2/(1+EXP($I$3*(COUNT($H$9:N$9)+$I$4))),TREND($D85:$E85,$D$9:$E$9,N$9)) -> 0 | O85: =IF($F85="s-curve",$D85+($E85-$D85)*$I$2/(1+EXP($I$3*(COUNT($H$9:O$9)+$I$4))),TREND($D85:$E85,$D$9:$E$9,O$9)) -> 0 | P85: =IF($F85="s-curve",$D85+($E85-$D85)*$I$2/(1+EXP($I$3*(COUNT($H$9:P$9)+$I$4))),TREND($D85:$E85,$D$9:$E$9,P$9)) -> 0 | ... AL85: =IF($F85="s-curve",$D85+($E85-$D85)*$I$2/(1+EXP($I$3*(COUNT($H$9:AL$9)+$I$4))),TREND($D85:$E85,$D$9:$E$9,AL$9)) -> 0
C86: hydrogen vehicle | D86: ='SYVbT-passenger'!H7/SUM('SYVbT-passenger'!7:7) -> 0 | E86: 0 | F86: =IF(D86=E86,"n/a",IF(OR(C86="battery electric vehicle",C86="natural gas vehicle",C86="plugin hybrid vehicle",C86="hydrogen vehicle"),"s-curve","linear")) -> n/a | H86: =D86 -> 0 | I86: =IF($F86="s-curve",$D86+($E86-$D86)*$I$2/(1+EXP($I$3*(COUNT($H$9:I$9)+$I$4))),TREND($D86:$E86,$D$9:$E$9,I$9)) -> 0 | J86: =IF($F86="s-curve",$D86+($E86-$D86)*$I$2/(1+EXP($I$3*(COUNT($H$9:J$9)+$I$4))),TREND($D86:$E86,$D$9:$E$9,J$9)) -> 0 | K86: =IF($F86="s-curve",$D86+($E86-$D86)*$I$2/(1+EXP($I$3*(COUNT($H$9:K$9)+$I$4))),TREND($D86:$E86,$D$9:$E$9,K$9)) -> 0 | L86: =IF($F86="s-curve",$D86+($E86-$D86)*$I$2/(1+EXP($I$3*(COUNT($H$9:L$9)+$I$4))),TREND($D86:$E86,$D$9:$E$9,L$9)) -> 0 | M86: =IF($F86="s-curve",$D86+($E86-$D86)*$I$2/(1+EXP($I$3*(COUNT($H$9:M$9)+$I$4))),TREND($D86:$E86,$D$9:$E$9,M$9)) -> 0 | N86: =IF($F86="s-curve",$D86+($E86-$D86)*$I$2/(1+EXP($I$3*(COUNT($H$9:N$9)+$I$4))),TREND($D86:$E86,$D$9:$E$9,N$9)) -> 0 | O86: =IF($F86="s-curve",$D86+($E86-$D86)*$I$2/(1+EXP($I$3*(COUNT($H$9:O$9)+$I$4))),TREND($D86:$E86,$D$9:$E$9,O$9)) -> 0 | P86: =IF($F86="s-curve",$D86+($E86-$D86)*$I$2/(1+EXP($I$3*(COUNT($H$9:P$9)+$I$4))),TREND($D86:$E86,$D$9:$E$9,P$9)) -> 0 | ... AL86: =IF($F86="s-curve",$D86+($E86-$D86)*$I$2/(1+EXP($I$3*(COUNT($H$9:AL$9)+$I$4))),TREND($D86:$E86,$D$9:$E$9,AL$9)) -> 0
A87: motorbikes | B87: freight | C87: battery electric vehicle | D87: =D80 -> 0 | E87: =E80 -> 1 | F87: =IF(D87=E87,"n/a",IF(OR(C87="battery electric vehicle",C87="natural gas vehicle",C87="plugin hybrid vehicle"),"s-curve","linear")) -> s-curve | H87: =D87 -> 0 | I87: =IF($F87="s-curve",$D87+($E87-$D87)*$I$2/(1+EXP($I$3*(COUNT($H$9:I$9)+$I$4))),TREND($D87:$E87,$D$9:$E$9,I$9)) -> 0.014774032 | J87: =IF($F87="s-curve",$D87+($E87-$D87)*$I$2/(1+EXP($I$3*(COUNT($H$9:J$9)+$I$4))),TREND($D87:$E87,$D$9:$E$9,J$9)) -> 0.019840306 | K87: =IF($F87="s-curve",$D87+($E87-$D87)*$I$2/(1+EXP($I$3*(COUNT($H$9:K$9)+$I$4))),TREND($D87:$E87,$D$9:$E$9,K$9)) -> 0.026596994 | L87: =IF($F87="s-curve",$D87+($E87-$D87)*$I$2/(1+EXP($I$3*(COUNT($H$9:L$9)+$I$4))),TREND($D87:$E87,$D$9:$E$9,L$9)) -> 0.035571189 | M87: =IF($F87="s-curve",$D87+($E87-$D87)*$I$2/(1+EXP($I$3*(COUNT($H$9:M$9)+$I$4))),TREND($D87:$E87,$D$9:$E$9,M$9)) -> 0.047425873 | N87: =IF($F87="s-curve",$D87+($E87-$D87)*$I$2/(1+EXP($I$3*(COUNT($H$9:N$9)+$I$4))),TREND($D87:$E87,$D$9:$E$9,N$9)) -> 0.062973356 | O87: =IF($F87="s-curve",$D87+($E87-$D87)*$I$2/(1+EXP($I$3*(COUNT($H$9:O$9)+$I$4))),TREND($D87:$E87,$D$9:$E$9,O$9)) -> 0.083172696 | P87: =IF($F87="s-curve",$D87+($E87-$D87)*$I$2/(1+EXP($I$3*(COUNT($H$9:P$9)+$I$4))),TREND($D87:$E87,$D$9:$E$9,P$9)) -> 0.10909682 | ... AL87: =IF($F87="s-curve",$D87+($E87-$D87)*$I$2/(1+EXP($I$3*(COUNT($H$9:AL$9)+$I$4))),TREND($D87:$E87,$D$9:$E$9,AL$9)) -> 0.98901306
C88: natural gas vehicle | D88: =D81 -> 0 | E88: =E81 -> 0 | F88: =IF(D88=E88,"n/a",IF(OR(C88="battery electric vehicle",C88="natural gas vehicle",C88="plugin hybrid vehicle"),"s-curve","linear")) -> n/a | H88: =D88 -> 0 | I88: =IF($F88="s-curve",$D88+($E88-$D88)*$I$2/(1+EXP($I$3*(COUNT($H$9:I$9)+$I$4))),TREND($D88:$E88,$D$9:$E$9,I$9)) -> 0 | J88: =IF($F88="s-curve",$D88+($E88-$D88)*$I$2/(1+EXP($I$3*(COUNT($H$9:J$9)+$I$4))),TREND($D88:$E88,$D$9:$E$9,J$9)) -> 0 | K88: =IF($F88="s-curve",$D88+($E88-$D88)*$I$2/(1+EXP($I$3*(COUNT($H$9:K$9)+$I$4))),TREND($D88:$E88,$D$9:$E$9,K$9)) -> 0 | L88: =IF($F88="s-curve",$D88+($E88-$D88)*$I$2/(1+EXP($I$3*(COUNT($H$9:L$9)+$I$4))),TREND($D88:$E88,$D$9:$E$9,L$9)) -> 0 | M88: =IF($F88="s-curve",$D88+($E88-$D88)*$I$2/(1+EXP($I$3*(COUNT($H$9:M$9)+$I$4))),TREND($D88:$E88,$D$9:$E$9,M$9)) -> 0 | N88: =IF($F88="s-curve",$D88+($E88-$D88)*$I$2/(1+EXP($I$3*(COUNT($H$9:N$9)+$I$4))),TREND($D88:$E88,$D$9:$E$9,N$9)) -> 0 | O88: =IF($F88="s-curve",$D88+($E88-$D88)*$I$2/(1+EXP($I$3*(COUNT($H$9:O$9)+$I$4))),TREND($D88:$E88,$D$9:$E$9,O$9)) -> 0 | P88: =IF($F88="s-curve",$D88+($E88-$D88)*$I$2/(1+EXP($I$3*(COUNT($H$9:P$9)+$I$4))),TREND($D88:$E88,$D$9:$E$9,P$9)) -> 0 | ... AL88: =IF($F88="s-curve",$D88+($E88-$D88)*$I$2/(1+EXP($I$3*(COUNT($H$9:AL$9)+$I$4))),TREND($D88:$E88,$D$9:$E$9,AL$9)) -> 0
C89: gasoline vehicle | D89: =D82 -> 3 | E89: =E82 -> 3 | F89: =IF(D89=E89,"n/a",IF(OR(C89="battery electric vehicle",C89="natural gas vehicle",C89="plugin hybrid vehicle"),"s-curve","linear")) -> n/a | H89: =D89 -> 3 | I89: =IF($F89="s-curve",$D89+($E89-$D89)*$I$2/(1+EXP($I$3*(COUNT($H$9:I$9)+$I$4))),TREND($D89:$E89,$D$9:$E$9,I$9)) -> 3 | J89: =IF($F89="s-curve",$D89+($E89-$D89)*$I$2/(1+EXP($I$3*(COUNT($H$9:J$9)+$I$4))),TREND($D89:$E89,$D$9:$E$9,J$9)) -> 3 | K89: =IF($F89="s-curve",$D89+($E89-$D89)*$I$2/(1+EXP($I$3*(COUNT($H$9:K$9)+$I$4))),TREND($D89:$E89,$D$9:$E$9,K$9)) -> 3 | L89: =IF($F89="s-curve",$D89+($E89-$D89)*$I$2/(1+EXP($I$3*(COUNT($H$9:L$9)+$I$4))),TREND($D89:$E89,$D$9:$E$9,L$9)) -> 3 | M89: =IF($F89="s-curve",$D89+($E89-$D89)*$I$2/(1+EXP($I$3*(COUNT($H$9:M$9)+$I$4))),TREND($D89:$E89,$D$9:$E$9,M$9)) -> 3 | N89: =IF($F89="s-curve",$D89+($E89-$D89)*$I$2/(1+EXP($I$3*(COUNT($H$9:N$9)+$I$4))),TREND($D89:$E89,$D$9:$E$9,N$9)) -> 3 | O89: =IF($F89="s-curve",$D89+($E89-$D89)*$I$2/(1+EXP($I$3*(COUNT($H$9:O$9)+$I$4))),TREND($D89:$E89,$D$9:$E$9,O$9)) -> 3 | P89: =IF($F89="s-curve",$D89+($E89-$D89)*$I$2/(1+EXP($I$3*(COUNT($H$9:P$9)+$I$4))),TREND($D89:$E89,$D$9:$E$9,P$9)) -> 3 | ... AL89: =IF($F89="s-curve",$D89+($E89-$D89)*$I$2/(1+EXP($I$3*(COUNT($H$9:AL$9)+$I$4))),TREND($D89:$E89,$D$9:$E$9,AL$9)) -> 3
C90: diesel vehicle | D90: =D83 -> 0 | E90: =E83 -> 0 | F90: =IF(D90=E90,"n/a",IF(OR(C90="battery electric vehicle",C90="natural gas vehicle",C90="plugin hybrid vehicle"),"s-curve","linear")) -> n/a | H90: =D90 -> 0 | I90: =IF($F90="s-curve",$D90+($E90-$D90)*$I$2/(1+EXP($I$3*(COUNT($H$9:I$9)+$I$4))),TREND($D90:$E90,$D$9:$E$9,I$9)) -> 0 | J90: =IF($F90="s-curve",$D90+($E90-$D90)*$I$2/(1+EXP($I$3*(COUNT($H$9:J$9)+$I$4))),TREND($D90:$E90,$D$9:$E$9,J$9)) -> 0 | K90: =IF($F90="s-curve",$D90+($E90-$D90)*$I$2/(1+EXP($I$3*(COUNT($H$9:K$9)+$I$4))),TREND($D90:$E90,$D$9:$E$9,K$9)) -> 0 | L90: =IF($F90="s-curve",$D90+($E90-$D90)*$I$2/(1+EXP($I$3*(COUNT($H$9:L$9)+$I$4))),TREND($D90:$E90,$D$9:$E$9,L$9)) -> 0 | M90: =IF($F90="s-curve",$D90+($E90-$D90)*$I$2/(1+EXP($I$3*(COUNT($H$9:M$9)+$I$4))),TREND($D90:$E90,$D$9:$E$9,M$9)) -> 0 | N90: =IF($F90="s-curve",$D90+($E90-$D90)*$I$2/(1+EXP($I$3*(COUNT($H$9:N$9)+$I$4))),TREND($D90:$E90,$D$9:$E$9,N$9)) -> 0 | O90: =IF($F90="s-curve",$D90+($E90-$D90)*$I$2/(1+EXP($I$3*(COUNT($H$9:O$9)+$I$4))),TREND($D90:$E90,$D$9:$E$9,O$9)) -> 0 | P90: =IF($F90="s-curve",$D90+($E90-$D90)*$I$2/(1+EXP($I$3*(COUNT($H$9:P$9)+$I$4))),TREND($D90:$E90,$D$9:$E$9,P$9)) -> 0 | ... AL90: =IF($F90="s-curve",$D90+($E90-$D90)*$I$2/(1+EXP($I$3*(COUNT($H$9:AL$9)+$I$4))),TREND($D90:$E90,$D$9:$E$9,AL$9)) -> 0
C91: plugin hybrid vehicle | D91: =D84 -> 0 | E91: =E84 -> 0 | F91: =IF(D91=E91,"n/a",IF(OR(C91="battery electric vehicle",C91="natural gas vehicle",C91="plugin hybrid vehicle"),"s-curve","linear")) -> n/a | H91: =D91 -> 0 | I91: =IF($F91="s-curve",$D91+($E91-$D91)*$I$2/(1+EXP($I$3*(COUNT($H$9:I$9)+$I$4))),TREND($D91:$E91,$D$9:$E$9,I$9)) -> 0 | J91: =IF($F91="s-curve",$D91+($E91-$D91)*$I$2/(1+EXP($I$3*(COUNT($H$9:J$9)+$I$4))),TREND($D91:$E91,$D$9:$E$9,J$9)) -> 0 | K91: =IF($F91="s-curve",$D91+($E91-$D91)*$I$2/(1+EXP($I$3*(COUNT($H$9:K$9)+$I$4))),TREND($D91:$E91,$D$9:$E$9,K$9)) -> 0 | L91: =IF($F91="s-curve",$D91+($E91-$D91)*$I$2/(1+EXP($I$3*(COUNT($H$9:L$9)+$I$4))),TREND($D91:$E91,$D$9:$E$9,L$9)) -> 0 | M91: =IF($F91="s-curve",$D91+($E91-$D91)*$I$2/(1+EXP($I$3*(COUNT($H$9:M$9)+$I$4))),TREND($D91:$E91,$D$9:$E$9,M$9)) -> 0 | N91: =IF($F91="s-curve",$D91+($E91-$D91)*$I$2/(1+EXP($I$3*(COUNT($H$9:N$9)+$I$4))),TREND($D91:$E91,$D$9:$E$9,N$9)) -> 0 | O91: =IF($F91="s-curve",$D91+($E91-$D91)*$I$2/(1+EXP($I$3*(COUNT($H$9:O$9)+$I$4))),TREND($D91:$E91,$D$9:$E$9,O$9)) -> 0 | P91: =IF($F91="s-curve",$D91+($E91-$D91)*$I$2/(1+EXP($I$3*(COUNT($H$9:P$9)+$I$4))),TREND($D91:$E91,$D$9:$E$9,P$9)) -> 0 | ... AL91: =IF($F91="s-curve",$D91+($E91-$D91)*$I$2/(1+EXP($I$3*(COUNT($H$9:AL$9)+$I$4))),TREND($D91:$E91,$D$9:$E$9,AL$9)) -> 0
C92: LPG vehicle | D92: =D85 -> 0 | E92: =E85 -> 0 | F92: =IF(D92=E92,"n/a",IF(OR(C92="battery electric vehicle",C92="natural gas vehicle",C92="plugin hybrid vehicle",C92="hydrogen vehicle"),"s-curve","linear")) -> n/a | H92: =D92 -> 0 | I92: =IF($F92="s-curve",$D92+($E92-$D92)*$I$2/(1+EXP($I$3*(COUNT($H$9:I$9)+$I$4))),TREND($D92:$E92,$D$9:$E$9,I$9)) -> 0 | J92: =IF($F92="s-curve",$D92+($E92-$D92)*$I$2/(1+EXP($I$3*(COUNT($H$9:J$9)+$I$4))),TREND($D92:$E92,$D$9:$E$9,J$9)) -> 0 | K92: =IF($F92="s-curve",$D92+($E92-$D92)*$I$2/(1+EXP($I$3*(COUNT($H$9:K$9)+$I$4))),TREND($D92:$E92,$D$9:$E$9,K$9)) -> 0 | L92: =IF($F92="s-curve",$D92+($E92-$D92)*$I$2/(1+EXP($I$3*(COUNT($H$9:L$9)+$I$4))),TREND($D92:$E92,$D$9:$E$9,L$9)) -> 0 | M92: =IF($F92="s-curve",$D92+($E92-$D92)*$I$2/(1+EXP($I$3*(COUNT($H$9:M$9)+$I$4))),TREND($D92:$E92,$D$9:$E$9,M$9)) -> 0 | N92: =IF($F92="s-curve",$D92+($E92-$D92)*$I$2/(1+EXP($I$3*(COUNT($H$9:N$9)+$I$4))),TREND($D92:$E92,$D$9:$E$9,N$9)) -> 0 | O92: =IF($F92="s-curve",$D92+($E92-$D92)*$I$2/(1+EXP($I$3*(COUNT($H$9:O$9)+$I$4))),TREND($D92:$E92,$D$9:$E$9,O$9)) -> 0 | P92: =IF($F92="s-curve",$D92+($E92-$D92)*$I$2/(1+EXP($I$3*(COUNT($H$9:P$9)+$I$4))),TREND($D92:$E92,$D$9:$E$9,P$9)) -> 0 | ... AL92: =IF($F92="s-curve",$D92+($E92-$D92)*$I$2/(1+EXP($I$3*(COUNT($H$9:AL$9)+$I$4))),TREND($D92:$E92,$D$9:$E$9,AL$9)) -> 0
C93: hydrogen vehicle | D93: =D86 -> 0 | E93: 0 | F93: =IF(D93=E93,"n/a",IF(OR(C93="battery electric vehicle",C93="natural gas vehicle",C93="plugin hybrid vehicle",C93="hydrogen vehicle"),"s-curve","linear")) -> n/a | H93: =D93 -> 0 | I93: =IF($F93="s-curve",$D93+($E93-$D93)*$I$2/(1+EXP($I$3*(COUNT($H$9:I$9)+$I$4))),TREND($D93:$E93,$D$9:$E$9,I$9)) -> 0 | J93: =IF($F93="s-curve",$D93+($E93-$D93)*$I$2/(1+EXP($I$3*(COUNT($H$9:J$9)+$I$4))),TREND($D93:$E93,$D$9:$E$9,J$9)) -> 0 | K93: =IF($F93="s-curve",$D93+($E93-$D93)*$I$2/(1+EXP($I$3*(COUNT($H$9:K$9)+$I$4))),TREND($D93:$E93,$D$9:$E$9,K$9)) -> 0 | L93: =IF($F93="s-curve",$D93+($E93-$D93)*$I$2/(1+EXP($I$3*(COUNT($H$9:L$9)+$I$4))),TREND($D93:$E93,$D$9:$E$9,L$9)) -> 0 | M93: =IF($F93="s-curve",$D93+($E93-$D93)*$I$2/(1+EXP($I$3*(COUNT($H$9:M$9)+$I$4))),TREND($D93:$E93,$D$9:$E$9,M$9)) -> 0 | N93: =IF($F93="s-curve",$D93+($E93-$D93)*$I$2/(1+EXP($I$3*(COUNT($H$9:N$9)+$I$4))),TREND($D93:$E93,$D$9:$E$9,N$9)) -> 0 | O93: =IF($F93="s-curve",$D93+($E93-$D93)*$I$2/(1+EXP($I$3*(COUNT($H$9:O$9)+$I$4))),TREND($D93:$E93,$D$9:$E$9,O$9)) -> 0 | P93: =IF($F93="s-curve",$D93+($E93-$D93)*$I$2/(1+EXP($I$3*(COUNT($H$9:P$9)+$I$4))),TREND($D93:$E93,$D$9:$E$9,P$9)) -> 0 | ... AL93: =IF($F93="s-curve",$D93+($E93-$D93)*$I$2/(1+EXP($I$3*(COUNT($H$9:AL$9)+$I$4))),TREND($D93:$E93,$D$9:$E$9,AL$9)) -> 0

Sheet TTS-LDVs-psgr
A1: Max Fraction of Production (dimensionless) | B1: =Data!H9 -> 2020 | C1: =Data!I9 -> 2021 | D1: =Data!J9 -> 2022 | E1: =Data!K9 -> 2023 | F1: =Data!L9 -> 2024 | G1: =Data!M9 -> 2025 | H1: =Data!N9 -> 2026 | I1: =Data!O9 -> 2027 | ... AF1: =Data!AL9 -> 2050
A2: battery electric vehicle | B2: =Data!H10 -> 0.0734902 | C2: =Data!I10 -> 0.0734902 | D2: =Data!J10 -> 0.15782531 | E2: =Data!K10 -> 0.1300531 | F2: =Data!L10 -> 0.17042213 | G2: =Data!M10 -> 0.26665969 | H2: =Data!N10 -> 0.30932775 | I2: =Data!O10 -> 0.35199581 | ... AF2: =Data!AL10 -> 2.6
A3: natural gas vehicle | B3: =Data!H11 -> 0.0033619456 | C3: =Data!I11 -> 0.0033619456 | D3: =Data!J11 -> 0.0032366568 | E3: =Data!K11 -> 0.0033102715 | F3: =Data!L11 -> 0.0033107854 | G3: =Data!M11 -> 0.003309012 | H3: =Data!N11 -> 0.003309012 | I3: =Data!O11 -> 0.003309012 | ... AF3: =Data!AL11 -> 0.003309012
A4: gasoline vehicle | B4: =Data!H12 -> 1 | C4: =Data!I12 -> 1 | D4: =Data!J12 -> 1 | E4: =Data!K12 -> 1 | F4: =Data!L12 -> 1 | G4: =Data!M12 -> 1 | H4: =Data!N12 -> 1 | I4: =Data!O12 -> 1 | ... AF4: =Data!AL12 -> 1
A5: diesel vehicle | B5: =Data!H13 -> 0.59258194 | C5: =Data!I13 -> 0.59258194 | D5: =Data!J13 -> 0.5925625 | E5: =Data!K13 -> 0.59219617 | F5: =Data!L13 -> 0.59201468 | G5: =Data!M13 -> 0.59122138 | H5: =Data!N13 -> 0.59122138 | I5: =Data!O13 -> 0.59122138 | ... AF5: =Data!AL13 -> 0.59122138
A6: plugin hybrid vehicle | B6: =Data!H14 -> 0.026859262 | C6: =Data!I14 -> 0.026859262 | D6: =Data!J14 -> 0.019405875 | E6: =Data!K14 -> 0.01817122 | F6: =Data!L14 -> 0.016437479 | G6: =Data!M14 -> 0.022877518 | H6: =Data!N14 -> 0.027902014 | I6: =Data!O14 -> 0.032926511 | ... AF6: =Data!AL14 -> 0.26
A7: LPG vehicle | B7: =Data!H15 -> 0.17122865 | C7: =Data!I15 -> 0.17122865 | D7: =Data!J15 -> 0.16057545 | E7: =Data!K15 -> 0.16035867 | F7: =Data!L15 -> 0.16022472 | G7: =Data!M15 -> 0.15979464 | H7: =Data!N15 -> 0.15979464 | I7: =Data!O15 -> 0.15979464 | ... AF7: =Data!AL15 -> 0.15979464
A8: hydrogen vehicle | B8: =Data!H16 -> 0.013775185 | C8: =Data!I16 -> 0.013775185 | D8: =Data!J16 -> 0.015049924 | E8: =Data!K16 -> 0.0059981476 | F8: =Data!L16 -> 0.0039475989 | G8: =Data!M16 -> 0.0081683077 | H8: =Data!N16 -> 0.0081683077 | I8: =Data!O16 -> 0.0081683077 | ... AF8: =Data!AL16 -> 0.0081683077

Sheet TTS-LDVs-frgt
A1: Max Fraction of Production (dimensionless) | B1: =Data!H9 -> 2020 | C1: =Data!I9 -> 2021 | D1: =Data!J9 -> 2022 | E1: =Data!K9 -> 2023 | F1: =Data!L9 -> 2024 | G1: =Data!M9 -> 2025 | H1: =Data!N9 -> 2026 | I1: =Data!O9 -> 2027 | ... AF1: =Data!AL9 -> 2050
A2: battery electric vehicle | B2: =Data!H17 -> 0.05 | C2: =Data!I17 -> 0.056648314 | D2: =Data!J17 -> 0.058928138 | E2: =Data!K17 -> 0.061968647 | F2: =Data!L17 -> 0.066007035 | G2: =Data!M17 -> 0.071341643 | H2: =Data!N17 -> 0.07833801 | I2: =Data!O17 -> 0.087427713 | ... AF2: =Data!AL17 -> 0.49505588
A3: natural gas vehicle | B3: =Data!H18 -> 0.00061283704 | C3: =Data!I18 -> 0.00061283704 | D3: =Data!J18 -> 0.00061283704 | E3: =Data!K18 -> 0.00061283704 | F3: =Data!L18 -> 0.00061283704 | G3: =Data!M18 -> 0.00061283704 | H3: =Data!N18 -> 0.00061283704 | I3: =Data!O18 -> 0.00061283704 | ... AF3: =Data!AL18 -> 0.00061283704
A4: gasoline vehicle | B4: =Data!H19 -> 0.019186119 | C4: =Data!I19 -> 0.019186119 | D4: =Data!J19 -> 0.019186119 | E4: =Data!K19 -> 0.019186119 | F4: =Data!L19 -> 0.019186119 | G4: =Data!M19 -> 0.019186119 | H4: =Data!N19 -> 0.019186119 | I4: =Data!O19 -> 0.019186119 | ... AF4: =Data!AL19 -> 0.019186119
A5: diesel vehicle | B5: =Data!H20 -> 3 | C5: =Data!I20 -> 3 | D5: =Data!J20 -> 3 | E5: =Data!K20 -> 3 | F5: =Data!L20 -> 3 | G5: =Data!M20 -> 3 | H5: =Data!N20 -> 3 | I5: =Data!O20 -> 3 | ... AF5: =Data!AL20 -> 3
A6: plugin hybrid vehicle | B6: =Data!H21 -> 0 | C6: =Data!I21 -> 0.0036935079 | D6: =Data!J21 -> 0.0049600764 | E6: =Data!K21 -> 0.0066492484 | F6: =Data!L21 -> 0.0088927973 | G6: =Data!M21 -> 0.011856468 | H6: =Data!N21 -> 0.015743339 | I6: =Data!O21 -> 0.020793174 | ... AF6: =Data!AL21 -> 0.24725326
A7: LPG vehicle | B7: =Data!H22 -> 0.042378174 | C7: =Data!I22 -> 0.042378174 | D7: =Data!J22 -> 0.042378174 | E7: =Data!K22 -> 0.042378174 | F7: =Data!L22 -> 0.042378174 | G7: =Data!M22 -> 0.042378174 | H7: =Data!N22 -> 0.042378174 | I7: =Data!O22 -> 0.042378174 | ... AF7: =Data!AL22 -> 0.042378174
A8: hydrogen vehicle | B8: =Data!H23 -> 0 | C8: =Data!I23 -> 9.0540739e-06 | D8: =Data!J23 -> 1.2158874e-05 | E8: =Data!K23 -> 1.6299623e-05 | F8: =Data!L23 -> 2.1799342e-05 | G8: =Data!M23 -> 2.9064332e-05 | H8: =Data!N23 -> 3.8592405e-05 | I8: =Data!O23 -> 5.0971309e-05 | ... AF8: =Data!AL23 -> 0.00060610384

Sheet TTS-HDVs-psgr
A1: Max Fraction of Production (dimensionless) | B1: =Data!H9 -> 2020 | C1: =Data!I9 -> 2021 | D1: =Data!J9 -> 2022 | E1: =Data!K9 -> 2023 | F1: =Data!L9 -> 2024 | G1: =Data!M9 -> 2025 | H1: =Data!N9 -> 2026 | I1: =Data!O9 -> 2027 | ... AF1: =Data!AL9 -> 2050
A2: battery electric vehicle | B2: =Data!H24 -> 0.05 | C2: =Data!I24 -> 0.06403533 | D2: =Data!J24 -> 0.06884829 | E2: =Data!K24 -> 0.075267144 | F2: =Data!L24 -> 0.08379263 | G2: =Data!M24 -> 0.09505458 | H2: =Data!N24 -> 0.10982469 | I2: =Data!O24 -> 0.12901406 | ... AF2: =Data!AL24 -> 0.9895624
A3: natural gas vehicle | B3: =Data!H25 -> 0.0021559962 | C3: =Data!I25 -> 0.0021559962 | D3: =Data!J25 -> 0.0021559962 | E3: =Data!K25 -> 0.0021559962 | F3: =Data!L25 -> 0.0021559962 | G3: =Data!M25 -> 0.0021559962 | H3: =Data!N25 -> 0.0021559962 | I3: =Data!O25 -> 0.0021559962 | ... AF3: =Data!AL25 -> 0.0021559962
A4: gasoline vehicle | B4: =Data!H26 -> 2.070863 | C4: =Data!I26 -> 2.070863 | D4: =Data!J26 -> 2.070863 | E4: =Data!K26 -> 2.070863 | F4: =Data!L26 -> 2.070863 | G4: =Data!M26 -> 2.070863 | H4: =Data!N26 -> 2.070863 | I4: =Data!O26 -> 2.070863 | ... AF4: =Data!AL26 -> 2.070863
A5: diesel vehicle | B5: =Data!H27 -> 1.188692 | C5: =Data!I27 -> 1.188692 | D5: =Data!J27 -> 1.188692 | E5: =Data!K27 -> 1.188692 | F5: =Data!L27 -> 1.188692 | G5: =Data!M27 -> 1.188692 | H5: =Data!N27 -> 1.188692 | I5: =Data!O27 -> 1.188692 | ... AF5: =Data!AL27 -> 1.188692
A6: plugin hybrid vehicle | B6: =Data!H28 -> 0.040868311 | C6: =Data!I28 -> 0.040868311 | D6: =Data!J28 -> 0.040868311 | E6: =Data!K28 -> 0.040868311 | F6: =Data!L28 -> 0.040868311 | G6: =Data!M28 -> 0.040868311 | H6: =Data!N28 -> 0.040868311 | I6: =Data!O28 -> 0.040868311 | ... AF6: =Data!AL28 -> 0.040868311
A7: LPG vehicle | B7: =Data!H29 -> 0.11252178 | C7: =Data!I29 -> 0.11252178 | D7: =Data!J29 -> 0.11252178 | E7: =Data!K29 -> 0.11252178 | F7: =Data!L29 -> 0.11252178 | G7: =Data!M29 -> 0.11252178 | H7: =Data!N29 -> 0.11252178 | I7: =Data!O29 -> 0.11252178 | ... AF7: =Data!AL29 -> 0.11252178
A8: hydrogen vehicle | B8: =Data!H30 -> 0.0006608385 | C8: =Data!I30 -> 0.00068292801 | D8: =Data!J30 -> 0.00069050288 | E8: =Data!K30 -> 0.0007006052 | F8: =Data!L30 -> 0.00071402304 | G8: =Data!M30 -> 0.00073174766 | H8: =Data!N30 -> 0.0007549936 | I8: =Data!O30 -> 0.0007851948 | ... AF8: =Data!AL30 -> 0.002139569

Sheet TTS-HDVs-frgt
A1: Max Fraction of Production (dimensionless) | B1: =Data!H9 -> 2020 | C1: =Data!I9 -> 2021 | D1: =Data!J9 -> 2022 | E1: =Data!K9 -> 2023 | F1: =Data!L9 -> 2024 | G1: =Data!M9 -> 2025 | H1: =Data!N9 -> 2026 | I1: =Data!O9 -> 2027 | ... AF1: =Data!AL9 -> 2050
A2: battery electric vehicle | B2: =Data!H31 -> 0.0053709945 | C2: =Data!I31 -> 0.012678659 | D2: =Data!J31 -> 0.015184585 | E2: =Data!K31 -> 0.018526639 | F2: =Data!L31 -> 0.022965536 | G2: =Data!M31 -> 0.028829207 | H2: =Data!N31 -> 0.036519443 | I2: =Data!O31 -> 0.046510623 | ... AF2: =Data!AL31 -> 0.49456554
A3: natural gas vehicle | B3: =Data!H32 -> 0 | C3: =Data!I32 -> 0 | D3: =Data!J32 -> 0 | E3: =Data!K32 -> 0 | F3: =Data!L32 -> 0 | G3: =Data!M32 -> 0 | H3: =Data!N32 -> 0 | I3: =Data!O32 -> 0 | ... AF3: =Data!AL32 -> 0
A4: gasoline vehicle | B4: =Data!H33 -> 0.01919553 | C4: =Data!I33 -> 0.01919553 | D4: =Data!J33 -> 0.01919553 | E4: =Data!K33 -> 0.01919553 | F4: =Data!L33 -> 0.01919553 | G4: =Data!M33 -> 0.01919553 | H4: =Data!N33 -> 0.01919553 | I4: =Data!O33 -> 0.01919553 | ... AF4: =Data!AL33 -> 0.01919553
A5: diesel vehicle | B5: =Data!H34 -> 3 | C5: =Data!I34 -> 3 | D5: =Data!J34 -> 3 | E5: =Data!K34 -> 3 | F5: =Data!L34 -> 3 | G5: =Data!M34 -> 3 | H5: =Data!N34 -> 3 | I5: =Data!O34 -> 3 | ... AF5: =Data!AL34 -> 3
A6: plugin hybrid vehicle | B6: =Data!H35 -> 0 | C6: =Data!I35 -> 0 | D6: =Data!J35 -> 0 | E6: =Data!K35 -> 0 | F6: =Data!L35 -> 0 | G6: =Data!M35 -> 0 | H6: =Data!N35 -> 0 | I6: =Data!O35 -> 0 | ... AF6: =Data!AL35 -> 0
A7: LPG vehicle | B7: =Data!H36 -> 0.042398961 | C7: =Data!I36 -> 0.042398961 | D7: =Data!J36 -> 0.042398961 | E7: =Data!K36 -> 0.042398961 | F7: =Data!L36 -> 0.042398961 | G7: =Data!M36 -> 0.042398961 | H7: =Data!N36 -> 0.042398961 | I7: =Data!O36 -> 0.042398961 | ... AF7: =Data!AL36 -> 0.042398961
A8: hydrogen vehicle | B8: =Data!H37 -> 0 | C8: =Data!I37 -> 0.00062640359 | D8: =Data!J37 -> 0.00084120834 | E8: =Data!K37 -> 0.0011276849 | F8: =Data!L37 -> 0.0015081815 | G8: =Data!M37 -> 0.0020108077 | H8: =Data!N37 -> 0.0026700048 | I8: =Data!O37 -> 0.0035264359 | ... AF8: =Data!AL37 -> 0.041933126

Sheet TTS-aircraft-psgr
A1: Max Fraction of Production (dimensionless) | B1: =Data!H9 -> 2020 | C1: =Data!I9 -> 2021 | D1: =Data!J9 -> 2022 | E1: =Data!K9 -> 2023 | F1: =Data!L9 -> 2024 | G1: =Data!M9 -> 2025 | H1: =Data!N9 -> 2026 | I1: =Data!O9 -> 2027 | ... AF1: =Data!AL9 -> 2050
A2: battery electric vehicle | B2: =Data!H38 -> 0 | C2: =Data!I38 -> 0 | D2: =Data!J38 -> 0 | E2: =Data!K38 -> 0 | F2: =Data!L38 -> 0 | G2: =Data!M38 -> 0 | H2: =Data!N38 -> 0 | I2: =Data!O38 -> 0 | ... AF2: =Data!AL38 -> 0
A3: natural gas vehicle | B3: =Data!H39 -> 0 | C3: =Data!I39 -> 0 | D3: =Data!J39 -> 0 | E3: =Data!K39 -> 0 | F3: =Data!L39 -> 0 | G3: =Data!M39 -> 0 | H3: =Data!N39 -> 0 | I3: =Data!O39 -> 0 | ... AF3: =Data!AL39 -> 0
A4: gasoline vehicle | B4: =Data!H40 -> 0 | C4: =Data!I40 -> 0 | D4: =Data!J40 -> 0 | E4: =Data!K40 -> 0 | F4: =Data!L40 -> 0 | G4: =Data!M40 -> 0 | H4: =Data!N40 -> 0 | I4: =Data!O40 -> 0 | ... AF4: =Data!AL40 -> 0
A5: diesel vehicle | B5: =Data!H41 -> 1 | C5: =Data!I41 -> 1 | D5: =Data!J41 -> 1 | E5: =Data!K41 -> 1 | F5: =Data!L41 -> 1 | G5: =Data!M41 -> 1 | H5: =Data!N41 -> 1 | I5: =Data!O41 -> 1 | ... AF5: =Data!AL41 -> 1
A6: plugin hybrid vehicle | B6: =Data!H42 -> 0 | C6: =Data!I42 -> 0 | D6: =Data!J42 -> 0 | E6: =Data!K42 -> 0 | F6: =Data!L42 -> 0 | G6: =Data!M42 -> 0 | H6: =Data!N42 -> 0 | I6: =Data!O42 -> 0 | ... AF6: =Data!AL42 -> 0
A7: LPG vehicle | B7: =Data!H43 -> 0 | C7: =Data!I43 -> 0 | D7: =Data!J43 -> 0 | E7: =Data!K43 -> 0 | F7: =Data!L43 -> 0 | G7: =Data!M43 -> 0 | H7: =Data!N43 -> 0 | I7: =Data!O43 -> 0 | ... AF7: =Data!AL43 -> 0
A8: hydrogen vehicle | B8: =Data!H44 -> 0 | C8: =Data!I44 -> 0 | D8: =Data!J44 -> 0 | E8: =Data!K44 -> 0 | F8: =Data!L44 -> 0 | G8: =Data!M44 -> 0 | H8: =Data!N44 -> 0 | I8: =Data!O44 -> 0 | ... AF8: =Data!AL44 -> 0

Sheet TTS-aircraft-frgt
A1: Max Fraction of Production (dimensionless) | B1: =Data!H9 -> 2020 | C1: =Data!I9 -> 2021 | D1: =Data!J9 -> 2022 | E1: =Data!K9 -> 2023 | F1: =Data!L9 -> 2024 | G1: =Data!M9 -> 2025 | H1: =Data!N9 -> 2026 | I1: =Data!O9 -> 2027 | ... AF1: =Data!AL9 -> 2050
A2: battery electric vehicle | B2: =Data!H45 -> 0 | C2: =Data!I45 -> 0 | D2: =Data!J45 -> 0 | E2: =Data!K45 -> 0 | F2: =Data!L45 -> 0 | G2: =Data!M45 -> 0 | H2: =Data!N45 -> 0 | I2: =Data!O45 -> 0 | ... AF2: =Data!AL45 -> 0
A3: natural gas vehicle | B3: =Data!H46 -> 0 | C3: =Data!I46 -> 0 | D3: =Data!J46 -> 0 | E3: =Data!K46 -> 0 | F3: =Data!L46 -> 0 | G3: =Data!M46 -> 0 | H3: =Data!N46 -> 0 | I3: =Data!O46 -> 0 | ... AF3: =Data!AL46 -> 0
A4: gasoline vehicle | B4: =Data!H47 -> 0 | C4: =Data!I47 -> 0 | D4: =Data!J47 -> 0 | E4: =Data!K47 -> 0 | F4: =Data!L47 -> 0 | G4: =Data!M47 -> 0 | H4: =Data!N47 -> 0 | I4: =Data!O47 -> 0 | ... AF4: =Data!AL47 -> 0
A5: diesel vehicle | B5: =Data!H48 -> 1 | C5: =Data!I48 -> 1 | D5: =Data!J48 -> 1 | E5: =Data!K48 -> 1 | F5: =Data!L48 -> 1 | G5: =Data!M48 -> 1 | H5: =Data!N48 -> 1 | I5: =Data!O48 -> 1 | ... AF5: =Data!AL48 -> 1
A6: plugin hybrid vehicle | B6: =Data!H49 -> 0 | C6: =Data!I49 -> 0 | D6: =Data!J49 -> 0 | E6: =Data!K49 -> 0 | F6: =Data!L49 -> 0 | G6: =Data!M49 -> 0 | H6: =Data!N49 -> 0 | I6: =Data!O49 -> 0 | ... AF6: =Data!AL49 -> 0
A7: LPG vehicle | B7: =Data!H50 -> 0 | C7: =Data!I50 -> 0 | D7: =Data!J50 -> 0 | E7: =Data!K50 -> 0 | F7: =Data!L50 -> 0 | G7: =Data!M50 -> 0 | H7: =Data!N50 -> 0 | I7: =Data!O50 -> 0 | ... AF7: =Data!AL50 -> 0
A8: hydrogen vehicle | B8: =Data!H51 -> 0 | C8: =Data!I51 -> 0 | D8: =Data!J51 -> 0 | E8: =Data!K51 -> 0 | F8: =Data!L51 -> 0 | G8: =Data!M51 -> 0 | H8: =Data!N51 -> 0 | I8: =Data!O51 -> 0 | ... AF8: =Data!AL51 -> 0

Sheet TTS-rail-psgr
A1: Max Fraction of Production (dimensionless) | B1: =Data!H9 -> 2020 | C1: =Data!I9 -> 2021 | D1: =Data!J9 -> 2022 | E1: =Data!K9 -> 2023 | F1: =Data!L9 -> 2024 | G1: =Data!M9 -> 2025 | H1: =Data!N9 -> 2026 | I1: =Data!O9 -> 2027 | ... AF1: =Data!AL9 -> 2050
A2: battery electric vehicle | B2: =Data!H52 -> 1 | C2: =Data!I52 -> 1 | D2: =Data!J52 -> 1 | E2: =Data!K52 -> 1 | F2: =Data!L52 -> 1 | G2: =Data!M52 -> 1 | H2: =Data!N52 -> 1 | I2: =Data!O52 -> 1 | ... AF2: =Data!AL52 -> 1
A3: natural gas vehicle | B3: =Data!H53 -> 0 | C3: =Data!I53 -> 0 | D3: =Data!J53 -> 0 | E3: =Data!K53 -> 0 | F3: =Data!L53 -> 0 | G3: =Data!M53 -> 0 | H3: =Data!N53 -> 0 | I3: =Data!O53 -> 0 | ... AF3: =Data!AL53 -> 0
A4: gasoline vehicle | B4: =Data!H54 -> 0 | C4: =Data!I54 -> 0 | D4: =Data!J54 -> 0 | E4: =Data!K54 -> 0 | F4: =Data!L54 -> 0 | G4: =Data!M54 -> 0 | H4: =Data!N54 -> 0 | I4: =Data!O54 -> 0 | ... AF4: =Data!AL54 -> 0
A5: diesel vehicle | B5: =Data!H55 -> 0.52 | C5: =Data!I55 -> 0.52 | D5: =Data!J55 -> 0.52 | E5: =Data!K55 -> 0.52 | F5: =Data!L55 -> 0.52 | G5: =Data!M55 -> 0.52 | H5: =Data!N55 -> 0.52 | I5: =Data!O55 -> 0.52 | ... AF5: =Data!AL55 -> 0.52
A6: plugin hybrid vehicle | B6: =Data!H56 -> 0 | C6: =Data!I56 -> 0 | D6: =Data!J56 -> 0 | E6: =Data!K56 -> 0 | F6: =Data!L56 -> 0 | G6: =Data!M56 -> 0 | H6: =Data!N56 -> 0 | I6: =Data!O56 -> 0 | ... AF6: =Data!AL56 -> 0
A7: LPG vehicle | B7: =Data!H57 -> 0 | C7: =Data!I57 -> 0 | D7: =Data!J57 -> 0 | E7: =Data!K57 -> 0 | F7: =Data!L57 -> 0 | G7: =Data!M57 -> 0 | H7: =Data!N57 -> 0 | I7: =Data!O57 -> 0 | ... AF7: =Data!AL57 -> 0
A8: hydrogen vehicle | B8: =Data!H58 -> 0 | C8: =Data!I58 -> 0 | D8: =Data!J58 -> 0 | E8: =Data!K58 -> 0 | F8: =Data!L58 -> 0 | G8: =Data!M58 -> 0 | H8: =Data!N58 -> 0 | I8: =Data!O58 -> 0 | ... AF8: =Data!AL58 -> 0

Sheet TTS-rail-frgt
A1: Max Fraction of Production (dimensionless) | B1: =Data!H9 -> 2020 | C1: =Data!I9 -> 2021 | D1: =Data!J9 -> 2022 | E1: =Data!K9 -> 2023 | F1: =Data!L9 -> 2024 | G1: =Data!M9 -> 2025 | H1: =Data!N9 -> 2026 | I1: =Data!O9 -> 2027 | ... AF1: =Data!AL9 -> 2050
A2: battery electric vehicle | B2: =Data!H59 -> 0.2 | C2: =Data!I59 -> 0.2 | D2: =Data!J59 -> 0.2 | E2: =Data!K59 -> 0.2 | F2: =Data!L59 -> 0.2 | G2: =Data!M59 -> 0.2 | H2: =Data!N59 -> 0.2 | I2: =Data!O59 -> 0.2 | ... AF2: =Data!AL59 -> 0.2
A3: natural gas vehicle | B3: =Data!H60 -> 0 | C3: =Data!I60 -> 0 | D3: =Data!J60 -> 0 | E3: =Data!K60 -> 0 | F3: =Data!L60 -> 0 | G3: =Data!M60 -> 0 | H3: =Data!N60 -> 0 | I3: =Data!O60 -> 0 | ... AF3: =Data!AL60 -> 0
A4: gasoline vehicle | B4: =Data!H61 -> 0 | C4: =Data!I61 -> 0 | D4: =Data!J61 -> 0 | E4: =Data!K61 -> 0 | F4: =Data!L61 -> 0 | G4: =Data!M61 -> 0 | H4: =Data!N61 -> 0 | I4: =Data!O61 -> 0 | ... AF4: =Data!AL61 -> 0
A5: diesel vehicle | B5: =Data!H62 -> 1 | C5: =Data!I62 -> 1 | D5: =Data!J62 -> 1 | E5: =Data!K62 -> 1 | F5: =Data!L62 -> 1 | G5: =Data!M62 -> 1 | H5: =Data!N62 -> 1 | I5: =Data!O62 -> 1 | ... AF5: =Data!AL62 -> 1
A6: plugin hybrid vehicle | B6: =Data!H63 -> 0 | C6: =Data!I63 -> 0 | D6: =Data!J63 -> 0 | E6: =Data!K63 -> 0 | F6: =Data!L63 -> 0 | G6: =Data!M63 -> 0 | H6: =Data!N63 -> 0 | I6: =Data!O63 -> 0 | ... AF6: =Data!AL63 -> 0
A7: LPG vehicle | B7: =Data!H64 -> 0 | C7: =Data!I64 -> 0 | D7: =Data!J64 -> 0 | E7: =Data!K64 -> 0 | F7: =Data!L64 -> 0 | G7: =Data!M64 -> 0 | H7: =Data!N64 -> 0 | I7: =Data!O64 -> 0 | ... AF7: =Data!AL64 -> 0
A8: hydrogen vehicle | B8: =Data!H65 -> 0 | C8: =Data!I65 -> 0 | D8: =Data!J65 -> 0 | E8: =Data!K65 -> 0 | F8: =Data!L65 -> 0 | G8: =Data!M65 -> 0 | H8: =Data!N65 -> 0 | I8: =Data!O65 -> 0 | ... AF8: =Data!AL65 -> 0

Sheet TTS-ships-psgr
A1: Max Fraction of Production (dimensionless) | B1: =Data!H9 -> 2020 | C1: =Data!I9 -> 2021 | D1: =Data!J9 -> 2022 | E1: =Data!K9 -> 2023 | F1: =Data!L9 -> 2024 | G1: =Data!M9 -> 2025 | H1: =Data!N9 -> 2026 | I1: =Data!O9 -> 2027 | ... AF1: =Data!AL9 -> 2050
A2: battery electric vehicle | B2: =Data!H66 -> 0 | C2: =Data!I66 -> 0 | D2: =Data!J66 -> 0 | E2: =Data!K66 -> 0 | F2: =Data!L66 -> 0 | G2: =Data!M66 -> 0 | H2: =Data!N66 -> 0 | I2: =Data!O66 -> 0 | ... AF2: =Data!AL66 -> 0
A3: natural gas vehicle | B3: =Data!H67 -> 0 | C3: =Data!I67 -> 0 | D3: =Data!J67 -> 0 | E3: =Data!K67 -> 0 | F3: =Data!L67 -> 0 | G3: =Data!M67 -> 0 | H3: =Data!N67 -> 0 | I3: =Data!O67 -> 0 | ... AF3: =Data!AL67 -> 0
A4: gasoline vehicle | B4: =Data!H68 -> 0 | C4: =Data!I68 -> 0 | D4: =Data!J68 -> 0 | E4: =Data!K68 -> 0 | F4: =Data!L68 -> 0 | G4: =Data!M68 -> 0 | H4: =Data!N68 -> 0 | I4: =Data!O68 -> 0 | ... AF4: =Data!AL68 -> 0
A5: diesel vehicle | B5: =Data!H69 -> 1 | C5: =Data!I69 -> 1 | D5: =Data!J69 -> 1 | E5: =Data!K69 -> 1 | F5: =Data!L69 -> 1 | G5: =Data!M69 -> 1 | H5: =Data!N69 -> 1 | I5: =Data!O69 -> 1 | ... AF5: =Data!AL69 -> 1
A6: plugin hybrid vehicle | B6: =Data!H70 -> 0 | C6: =Data!I70 -> 0 | D6: =Data!J70 -> 0 | E6: =Data!K70 -> 0 | F6: =Data!L70 -> 0 | G6: =Data!M70 -> 0 | H6: =Data!N70 -> 0 | I6: =Data!O70 -> 0 | ... AF6: =Data!AL70 -> 0
A7: LPG vehicle | B7: =Data!H71 -> 0 | C7: =Data!I71 -> 0 | D7: =Data!J71 -> 0 | E7: =Data!K71 -> 0 | F7: =Data!L71 -> 0 | G7: =Data!M71 -> 0 | H7: =Data!N71 -> 0 | I7: =Data!O71 -> 0 | ... AF7: =Data!AL71 -> 0
A8: hydrogen vehicle | B8: =Data!H72 -> 0 | C8: =Data!I72 -> 0 | D8: =Data!J72 -> 0 | E8: =Data!K72 -> 0 | F8: =Data!L72 -> 0 | G8: =Data!M72 -> 0 | H8: =Data!N72 -> 0 | I8: =Data!O72 -> 0 | ... AF8: =Data!AL72 -> 0

Sheet TTS-ships-frgt
A1: Max Fraction of Production (dimensionless) | B1: =Data!H9 -> 2020 | C1: =Data!I9 -> 2021 | D1: =Data!J9 -> 2022 | E1: =Data!K9 -> 2023 | F1: =Data!L9 -> 2024 | G1: =Data!M9 -> 2025 | H1: =Data!N9 -> 2026 | I1: =Data!O9 -> 2027 | ... AF1: =Data!AL9 -> 2050
A2: battery electric vehicle | B2: =Data!H73 -> 0 | C2: =Data!I73 -> 0 | D2: =Data!J73 -> 0 | E2: =Data!K73 -> 0 | F2: =Data!L73 -> 0 | G2: =Data!M73 -> 0 | H2: =Data!N73 -> 0 | I2: =Data!O73 -> 0 | ... AF2: =Data!AL73 -> 0
A3: natural gas vehicle | B3: =Data!H74 -> 0 | C3: =Data!I74 -> 0 | D3: =Data!J74 -> 0 | E3: =Data!K74 -> 0 | F3: =Data!L74 -> 0 | G3: =Data!M74 -> 0 | H3: =Data!N74 -> 0 | I3: =Data!O74 -> 0 | ... AF3: =Data!AL74 -> 0
A4: gasoline vehicle | B4: =Data!H75 -> 0.0041666444 | C4: =Data!I75 -> 0.0041666444 | D4: =Data!J75 -> 0.0041666444 | E4: =Data!K75 -> 0.0041666444 | F4: =Data!L75 -> 0.0041666444 | G4: =Data!M75 -> 0.0041666444 | H4: =Data!N75 -> 0.0041666444 | I4: =Data!O75 -> 0.0041666444 | ... AF4: =Data!AL75 -> 0.0041666444
A5: diesel vehicle | B5: =Data!H76 -> 1 | C5: =Data!I76 -> 1 | D5: =Data!J76 -> 1 | E5: =Data!K76 -> 1 | F5: =Data!L76 -> 1 | G5: =Data!M76 -> 1 | H5: =Data!N76 -> 1 | I5: =Data!O76 -> 1 | ... AF5: =Data!AL76 -> 1
A6: plugin hybrid vehicle | B6: =Data!H77 -> 0 | C6: =Data!I77 -> 0 | D6: =Data!J77 -> 0 | E6: =Data!K77 -> 0 | F6: =Data!L77 -> 0 | G6: =Data!M77 -> 0 | H6: =Data!N77 -> 0 | I6: =Data!O77 -> 0 | ... AF6: =Data!AL77 -> 0
A7: LPG vehicle | B7: =Data!H78 -> 0.0016666578 | C7: =Data!I78 -> 0.0016666578 | D7: =Data!J78 -> 0.0016666578 | E7: =Data!K78 -> 0.0016666578 | F7: =Data!L78 -> 0.0016666578 | G7: =Data!M78 -> 0.0016666578 | H7: =Data!N78 -> 0.0016666578 | I7: =Data!O78 -> 0.0016666578 | ... AF7: =Data!AL78 -> 0.0016666578
A8: hydrogen vehicle | B8: =Data!H79 -> 0 | C8: =Data!I79 -> 0 | D8: =Data!J79 -> 0 | E8: =Data!K79 -> 0 | F8: =Data!L79 -> 0 | G8: =Data!M79 -> 0 | H8: =Data!N79 -> 0 | I8: =Data!O79 -> 0 | ... AF8: =Data!AL79 -> 0

Sheet TTS-motorbikes-psgr
A1: Max Fraction of Production (dimensionless) | B1: =Data!H9 -> 2020 | C1: =Data!I9 -> 2021 | D1: =Data!J9 -> 2022 | E1: =Data!K9 -> 2023 | F1: =Data!L9 -> 2024 | G1: =Data!M9 -> 2025 | H1: =Data!N9 -> 2026 | I1: =Data!O9 -> 2027 | ... AF1: =Data!AL9 -> 2050
A2: battery electric vehicle | B2: =Data!H80 -> 0 | C2: =Data!I80 -> 0.014774032 | D2: =Data!J80 -> 0.019840306 | E2: =Data!K80 -> 0.026596994 | F2: =Data!L80 -> 0.035571189 | G2: =Data!M80 -> 0.047425873 | H2: =Data!N80 -> 0.062973356 | I2: =Data!O80 -> 0.083172696 | ... AF2: =Data!AL80 -> 0.98901306
A3: natural gas vehicle | B3: =Data!H81 -> 0 | C3: =Data!I81 -> 0 | D3: =Data!J81 -> 0 | E3: =Data!K81 -> 0 | F3: =Data!L81 -> 0 | G3: =Data!M81 -> 0 | H3: =Data!N81 -> 0 | I3: =Data!O81 -> 0 | ... AF3: =Data!AL81 -> 0
A4: gasoline vehicle | B4: =Data!H82 -> 3 | C4: =Data!I82 -> 3 | D4: =Data!J82 -> 3 | E4: =Data!K82 -> 3 | F4: =Data!L82 -> 3 | G4: =Data!M82 -> 3 | H4: =Data!N82 -> 3 | I4: =Data!O82 -> 3 | ... AF4: =Data!AL82 -> 3
A5: diesel vehicle | B5: =Data!H83 -> 0 | C5: =Data!I83 -> 0 | D5: =Data!J83 -> 0 | E5: =Data!K83 -> 0 | F5: =Data!L83 -> 0 | G5: =Data!M83 -> 0 | H5: =Data!N83 -> 0 | I5: =Data!O83 -> 0 | ... AF5: =Data!AL83 -> 0
A6: plugin hybrid vehicle | B6: =Data!H84 -> 0 | C6: =Data!I84 -> 0 | D6: =Data!J84 -> 0 | E6: =Data!K84 -> 0 | F6: =Data!L84 -> 0 | G6: =Data!M84 -> 0 | H6: =Data!N84 -> 0 | I6: =Data!O84 -> 0 | ... AF6: =Data!AL84 -> 0
A7: LPG vehicle | B7: =Data!H85 -> 0 | C7: =Data!I85 -> 0 | D7: =Data!J85 -> 0 | E7: =Data!K85 -> 0 | F7: =Data!L85 -> 0 | G7: =Data!M85 -> 0 | H7: =Data!N85 -> 0 | I7: =Data!O85 -> 0 | ... AF7: =Data!AL85 -> 0
A8: hydrogen vehicle | B8: =Data!H86 -> 0 | C8: =Data!I86 -> 0 | D8: =Data!J86 -> 0 | E8: =Data!K86 -> 0 | F8: =Data!L86 -> 0 | G8: =Data!M86 -> 0 | H8: =Data!N86 -> 0 | I8: =Data!O86 -> 0 | ... AF8: =Data!AL86 -> 0

Sheet TTS-motorbikes-frgt
A1: Max Fraction of Production (dimensionless) | B1: =Data!H9 -> 2020 | C1: =Data!I9 -> 2021 | D1: =Data!J9 -> 2022 | E1: =Data!K9 -> 2023 | F1: =Data!L9 -> 2024 | G1: =Data!M9 -> 2025 | H1: =Data!N9 -> 2026 | I1: =Data!O9 -> 2027 | ... AF1: =Data!AL9 -> 2050
A2: battery electric vehicle | B2: =Data!H87 -> 0 | C2: =Data!I87 -> 0.014774032 | D2: =Data!J87 -> 0.019840306 | E2: =Data!K87 -> 0.026596994 | F2: =Data!L87 -> 0.035571189 | G2: =Data!M87 -> 0.047425873 | H2: =Data!N87 -> 0.062973356 | I2: =Data!O87 -> 0.083172696 | ... AF2: =Data!AL87 -> 0.98901306
A3: natural gas vehicle | B3: =Data!H88 -> 0 | C3: =Data!I88 -> 0 | D3: =Data!J88 -> 0 | E3: =Data!K88 -> 0 | F3: =Data!L88 -> 0 | G3: =Data!M88 -> 0 | H3: =Data!N88 -> 0 | I3: =Data!O88 -> 0 | ... AF3: =Data!AL88 -> 0
A4: gasoline vehicle | B4: =Data!H89 -> 3 | C4: =Data!I89 -> 3 | D4: =Data!J89 -> 3 | E4: =Data!K89 -> 3 | F4: =Data!L89 -> 3 | G4: =Data!M89 -> 3 | H4: =Data!N89 -> 3 | I4: =Data!O89 -> 3 | ... AF4: =Data!AL89 -> 3
A5: diesel vehicle | B5: =Data!H90 -> 0 | C5: =Data!I90 -> 0 | D5: =Data!J90 -> 0 | E5: =Data!K90 -> 0 | F5: =Data!L90 -> 0 | G5: =Data!M90 -> 0 | H5: =Data!N90 -> 0 | I5: =Data!O90 -> 0 | ... AF5: =Data!AL90 -> 0
A6: plugin hybrid vehicle | B6: =Data!H91 -> 0 | C6: =Data!I91 -> 0 | D6: =Data!J91 -> 0 | E6: =Data!K91 -> 0 | F6: =Data!L91 -> 0 | G6: =Data!M91 -> 0 | H6: =Data!N91 -> 0 | I6: =Data!O91 -> 0 | ... AF6: =Data!AL91 -> 0
A7: LPG vehicle | B7: =Data!H92 -> 0 | C7: =Data!I92 -> 0 | D7: =Data!J92 -> 0 | E7: =Data!K92 -> 0 | F7: =Data!L92 -> 0 | G7: =Data!M92 -> 0 | H7: =Data!N92 -> 0 | I7: =Data!O92 -> 0 | ... AF7: =Data!AL92 -> 0
A8: hydrogen vehicle | B8: =Data!H93 -> 0 | C8: =Data!I93 -> 0 | D8: =Data!J93 -> 0 | E8: =Data!K93 -> 0 | F8: =Data!L93 -> 0 | G8: =Data!M93 -> 0 | H8: =Data!N93 -> 0 | I8: =Data!O93 -> 0 | ... AF8: =Data!AL93 -> 0
