Workbook

Sheet About
A1: Web App Data
A3: This spreadsheet contains data that is used to populate the web application interface
A4: for the Energy Policy Simulator. The data in other tabs in this spreadsheet are used
A5: to establish the policy levers, lever bounds, descriptive text for pop-over
A6: panels, output graphs, and reference scenarios available in the web app.
A8: A live version of the web application interface powered by a copy of this model
A9: can be found at:
A10: https://www.energypolicy.solutions
A12: You are unlikely to need to use or change the contents of this spreadsheet, unless
A13: you are adapting the Energy Policy Simulator to a new country and desire
A14: a web application interface customized for your country-specific model version.
A16: Checks for Policy ID Number Validity
A17: Max policy ID number in use | B17: =MAX(PolicyLevers!H:H) -> 2769
A18: Lowest duplicate ID number | B18: {=IF(MIN(IF(COUNTIF(PolicyLevers!$H$2:$H$2025,PolicyLevers!$H$2:$H$2025)>1,PolicyLevers!$H$2:$H$2025, ""))=0,"No duplicate ID numbers",MIN(IF(COUNTIF(PolicyLevers!$H$2:$H$2025,PolicyLevers!$H$2:$H$2025)>1,PolicyLevers!$H$2:$H$2025, "")))} -> No duplicate ID numbers
A19: Row of first policy missing a valid ID number | B19: {=IF(MIN(IF((NOT(ISNUMBER(PolicyLevers!$H$2:$H$2025)))*(ISTEXT(PolicyLevers!$I$2:$I$2025)),ROW(PolicyLevers!$H$2:$H$2025)))=0,"No missing ID numbers",MIN(IF((NOT(ISNUMBER(PolicyLevers!$H$2:$H$2025)))*(ISTEXT(PolicyLevers!$I$2:$I$2025)),ROW(PolicyLevers!$H$2:$H$2025))))} -> No missing ID numbers
A21: Customizing Policy Levers
A22: Define most policy properties on the "Policy Characteristics" tab.
A23: Specify the subscripted elements of each policy and which are enabled/disabled on the "PolicyLevers" tab.
A24: On the PolicyLevers tab, only manually edit the cells under the green column headers. Simply extend the
A25: existing formulas up or down to fill cells under the red headers on that tab.
A27: Notes on Meaning of Blank Cells on the Policy Characteristics Tab
A28: Leave the "Policy Schedule Subscript" cell blank to deny the ability to edit the implementation
A29: schedule for a lever. This should generally only be done for levers that do not use an
A30: implementation schedule: the toggle to Non-BAU Mandated Capacity Construction
A31: (which has its own schedule built into its input data) and the Nuclear Lifetime Extension
A32: (which simply delays retirements that would occur in the BAU Retirements input data).
A34: Leave the "Policy Group" cell blank to exclude a lever from wedge diagrams and abatement cost curves.
... A53: step size (e.g. 1.5% is not a valid step size, but 1%, 2%, 0.5% and 0.05% are all valid).

Sheet Policy Characteristics
A1: This tab contains information about each policy that does not vary by subscripted element of that policy.
A2: It matches policies to the listing in the "PolicyLevers" tab using the "Vensim Variable Name" column.
A3: Sector | B3: Short Name | C3: Vensim Variable Name | D3: Policy Group | E3: Policy Schedule Subscript | F3: Min Slider Value | G3: Max Slider Value | H3: Slider Step Size | I3: Units | J3: Text for Pop-Over Panel Description | K3: URL for "How the model handles this policy" links | L3: URL for "How to design this policy well" links | M3: Source for Guidance Text (if any) | N3: Source for Max Slider Value (if any)
A4: Transportation | B4: Conventional Pollutant Standards | C4: Percentage Reduction of Separately Regulated Pollutants | D4: Conventional Pollutant Standard | E4: trans reduce regulated pollutants | F4: 0 | G4: 1 | H4: 0.02 | I4: % reduction in emissions | J4: **Description:** This policy represents strengthening standards for the selected pollutant(s) emitted by the selected vehicle type(s). Conventional pollutants' most important, harmful impacts are on human health rather than on climate change. // **Guidance for setting values:** In South Korea, the 24-hour national ambient air quality standard (NAAQS) for PM2.5, the most harmful type of particulate for human health, is 35 µg/m^3. | K4: transportation-sector-main.html#conv-pol-stds | L4: conventional-pollutant-standards.html
A5: Transportation | B5: Electric Vehicle Charger Deployment | C5: Percentage Increase in EV Chargers | D5: EV Charger Deployment | E5: trans EV charger deployment | F5: -1 | G5: 3 | H5: 0.1 | I5: % change | J5: **Description:** This policy represents increasing the deployment of EV charging stations, including DC Fast and Level 2 charging stations. It is set in chargers per 100,000 people (cumulative, not per year), additional to chargers in the BAU case. This policy lever does not have an effect on energy use/emissions/deployment. It is meant to account for the costs of additional charging infrastructure. // **Guidance for setting values:** As of Dec 2021, South Korea had 91,592 chargers, just under 177 chargers per 100k pop. In Dec 2020, South Korea had 12,635 gas stations with an average of 14 fuel pumps each, or 342 pumps per 100k pop. Therefore, a lever setting of 165 would cause the population density of EV chargers to equal the 2020 population density of fuel pumps. | L5: ev-charger-deployment.html | M5: Number of EV chargers: https://evadoption.com/ev-charging-stations-statistics/ Number of gas stations: U.S. Census, Statistics of U.S. Businesses, https://www.census.gov/data/tables/2016/econ/susb/2016-susb-annual.html Pumps per station: https://247wallst.com/economy/2014/05/22/why-are-there-115000-or-150000-gas-stations-in-america/
A6: Transportation | B6: Electric Vehicle Range | C6: Reduce EV Range Anxiety | D6: EV Range & Charging Time | E6: trans reduce EV range anxiety | F6: 0 | G6: 1 | H6: 0.02 | I6: % reduction in concern | J6: **Description:** This policy specifies a percentage reduction in vehicle buyers' aversion to electric vehicles due to concerns over the vehicles' range (how far the EV can travel on a charge). A 100% setting implies consumers are no more concerned about EV range and charging time than they are about range and fueling time of gasoline vehicles. It does not imply that range is infinite. This policy only affects passenger cars and SUVs (most light-duty road vehicles). // **Guidance for setting values:** U.S. model year 2017 all-electric (not hybrid) vehicles had ranges from 58 to 335 miles (median 114 miles). | L6: reduce-range-anxiety-charging-time.html | M6: Ranges: https://www.energy.gov/eere/vehicles/articles/fotw-1010-january-1-2018-all-electric-light-vehicle-ranges-can-exceed-those Charging Times: https://www.chargepoint.com/files/Quick_Guide_to_Fast_Charging.pdf
A7: Transportation | B7: Passenger Vehicle Subsidy | C7: Additional Passenger Vehicle Subsidy | D7: Vehicle Subsidy | E7: trans psgr subsidy | F7: -60000000 | G7: 60000000 | H7: 100000 | I7: KRW/vehicle | J7: **Description:** This policy specifies the dollar amount offered as a subsidy to the purchaser of a new passenger vehicle. This is in addition to subsidies that exist in the BAU case. A negative value implies a tax or removal of subsidies. // **Guidance for setting values:** In South Korea, as of 2019, electric vehicle national subsidies were up to $7,628 and local subsidies were up to $5,933. In 2021, electric vehicle national subsidies are up to $6,781 and local subsidies are up to $5,933. Subsidies for Passenger-LDVs are 28% of the average car price, 24% for passenger-HDV, and 44% for freight-LDV. | K7: transportation-sector-main.html#ev-subsidy | L7: ev-subsidy.html | M7: https://www.fueleconomy.gov/feg/taxevb.shtml plus Chevrolet and Tesla websites
A8: Transportation | B8: Freight Vehicle Subsidy | C8: Additional Freight Vehicle Subsidy | D8: Vehicle Subsidy | E8: trans frgt subsidy | F8: -60000000 | G8: 60000000 | H8: 100000 | I8: KRW/vehicle | J8: **Description:** This policy specifies the dollar amount offered as a subsidy to the purchaser of a new freight vehicle. This is in addition to subsidies that exist in the BAU case. A negative value implies a tax or removal of subsidies. // **Guidance for setting values:** South Korea aims, by 2025, to deploy 193,000 electric trucks, 11,000 electric buses, 4,600 hydrogen buses, and 900 hydrogen trucks. The government operates a subsidy scheme that provides approximately KRW 16 million (≈ US $14,200) per truck, KRW 150 million (≈ US $133,200) per bus, and up to KRW 10 million (≈ US $8,900) per taxi. This initiative is regarded as a core national policy to establish a foundation for carbon neutrality in the transport sector through the expansion of electric and hydrogen vehicle adoption.(Sources: Ministry of Environment, “4th Basic Plan for Eco-friendly Vehicles(2021–2025)”) | K8: transportation-sector-main.html#ev-subsidy | L8: ev-subsidy.html
A9: Transportation | B9: Feebate | C9: LDVs Feebate Rate | D9: Feebate | E9: trans LDVs feebate | F9: 0 | G9: 1 | H9: 0.02 | I9: % of global best practice rate | J9: **Description:** This policy implements a fee on sales of inefficient cars and SUVs (light-duty road vehicles; LDVs) that is rebated to buyers of efficient LDVs. The feebate policy is revenue-neutral, as the pivot point (the efficiency level that incurs neither a rebate nor a fee) is set such that the total of all fees equals the total of all rebates. // **Guidance for setting values:** The feebate is set as a fraction of the global best practice feebate rate. The global best practice feebate rate is $2000 per (hundredth gal/mile), which equates to a $2000 fee on an LDV that gets 20 mpg if the pivot point is 25 mpg. (To see this: 20 mpg is 0.04 gpm. 25 mpg is 0.05 gpm. The difference is -.01 gpm. So in order to levy a $2000 fee on the 20 mpg car when the pivot point is 25 mpg, we need a rate of $2000/.01 gpm.) As of now, the feebate system is not systematically implemented or in operation in South Korea. | K9: transportation-sector-main.html#feebate | L9: feebate.html | M9: Greene et al., 2005, "Feebates, rebates and gas-guzzler taxes: a study of incentives for increased fuel economy", Energy Policy, 33(6), 757-775, http://cta.ornl.gov/cta/Publications/Reports/FeebateEnergyPolicy_FINAL.pdf. | N9: John German and Dan Meszler, 2010, "Best Practices for Feebate Program Design and Implementation", ICCT, http://www.theicct.org/sites/default/files/publications/ICCT_feebates_may2010.pdf, Table 2
A10: Transportation | B10: Fuel Economy Standard | C10: Percentage Additional Improvement of Fuel Economy Std | D10: Vehicle Fuel Economy Standards | E10: trans fuel economy standards | F10: -0.25 | G10: =ROUND(MaxBoundCalculations!B88,1) -> 1 | H10: 0.01 | I10: % change in miles/gal | J10: Description: This policy specifies a percentage improvement in fuel economy (distance traveled on the same quantity of fuel with the same cargo or passenger loading) due to fuel economy standards for newly sold vehicles of the selected type(s) with fossil fuel-burning engines. Guidance for setting values: LDVs (Light Duty Vehicles): South Korea combined fuel economy standards for light duty cars is 67.5mpg (28.7 km/L) (at 1070kg inertia weight) and light trucks is 44.9mpg(19.1 km/L)(at 1070kg inertia weight) in 2021. These are scheduled to rise to 89.6mpg (38.1 km/L) (at 1110kg inertia weight) for cars and 51.0mpg(21.7 km/L) (at 1110kg inertia weight) for light trucks through 2030, then remain constant. In South Korea, there is no plan for other vehicles' fuel economy. This data is based on the "Notice on Automobile Average Energy Consumption Efficiency Standards, Greenhouse Gas Emission Standards, and Application and Management of Standards." | K10: transportation-sector-main.html#fuel-econ-std | L10: fuel-economy-standard.html | M10: U. S. EPA, 2012, "Fact Sheet: EPA and NHTSA Set Standards to Reduce Greenhouse Gases and Improve Fuel Economy for Model Years 2017-2025 Cars and Light Trucks", https://nepis.epa.gov/Exe/ZyNET.exe/P100EZ7C.txt?ZyActionD=ZyDocument&Client=EPA&Index=2011%20Thru%202015&Docs=&Query=&Time=&EndTime=&SearchMethod=1&TocRestrict=n&Toc=&TocEntry=&QField=&QFieldYear=&QFieldMonth=&QFieldDay=&UseQField=&IntQFieldOp=0&ExtQFieldOp=0&XmlQuery=&File=D%3A%5CZYFILES%5CINDEX%20DATA%5C11THRU15%5CTXT%5C00000005%5CP100EZ7C.txt&User=ANONYMOUS&Password=anonymous&SortMethod=h%7C-&MaximumDocuments=1&FuzzyDegree=0&ImageQuality=r75g8/r75g8/x150y150g16/i425&Display=hpfr&DefSeekPage=x&SearchBack=ZyActionL&Back=ZyActionS&BackDesc=Results%20page&MaximumPages=1&ZyEntry=4, Table 1, Row 4. U.S. EPA, 2015, "EPA and NHTSA Propose Standards to Reduce Greenhouse Gas Emissions and Improve Fuel Efficiency of Medium- and Heavy-Duty Vehicles for Model Year 2018 and Beyond", https://nepis.epa.gov/Exe/ZyNET.exe/P100P7NL.txt?ZyActionD=ZyDocument&Client=EPA&Index=2016%20Thru%202020&Docs=&Query=&Time=&EndTime=&SearchMethod=1&TocRestrict=n&Toc=&TocEntry=&QField=&QFieldYear=&QFieldMonth=&QFieldDay=&UseQField=&IntQFieldOp=0&ExtQFieldOp=0&XmlQuery=&File=D%3A%5CZYFILES%5CINDEX%20DATA%5C16THRU20%5CTXT%5C00000002%5CP100P7NL.txt&User=ANONYMOUS&Password=anonymous&SortMethod=h%7C-&MaximumDocuments=1&FuzzyDegree=0&ImageQuality=r75g8/r75g8/x150y150g16/i425&Display=hpfr&DefSeekPage=x&SearchBack=ZyActionL&Back=ZyActionS&BackDesc=Results%20page&MaximumPages=1&ZyEntry=3, Page 3. https://theicct.org/sites/default/files/publications/ICCT_ShipEfficiency_20130723.pdf Others calculated from model input data. | N10: National Research Council, 2013, "Transitions to Alternative Vehicles and Fuels", https://www.nap.edu/catalog/18264/transitions-to-alternative-vehicles-and-fuels, Table 2.9, Fuel economy test mpg. U.S. DoE, 2013, "Potential for Energy Efficiency Improvement Beyond the Light-Duty-Vehicle Sector," http://www.nrel.gov/docs/fy13osti/55637.pdf, Table 2.2 and Section 3.4.5, Paragraph 1 David McCollum, Gregory Gould, and Davide Greene, 2009, "Greenhouse Gas Emissions from Aviation and Marine Transportation: Mitigation Potential and Policies", Pew Center on Global Climate Change, http://www.c2es.org/docUploads/aviation-and-marine-report-2009.pdf, Table 4 https://theicct.org/sites/default/files/publications/ICCT_ShipEfficiency_20130723.pdf
A11: Transportation | B11: Low Carbon Fuel Standard | C11: Additional LCFS Percentage | D11: Low Carbon Fuel Standard | E11: trans LCFS | F11: 0 | G11: 1 | H11: 0.01 | I11: % reduction in carbon emissions | J11: **Description:** This policy specifies the percentage reduction in carbon emissions from the transportation sector that must be achieved via fuel switching. By default, this policy applies to all non-aviation vehicle types. If the lever Non-BAU LCFS-Qualifying Vehicles is enabled, this policy only applies to aviation and represents the use of sustainable aviation fuels. The value set in this lever is in addition to BAU requirements. // **Guidance for setting values:** South Korea has a plan to reduce greenhouse gas emissions by 37.8% (to 61 million tons) in 2030 compared to greenhouse gas emissions (98.1 million tons) in 2018. Although South Korea has not yet adopted a Low Carbon Fuel Standard (LCFS) system, which directly regulates the Carbon Intensity (CI) of fuels like the United States or Europe, it operates a similar policy known as the Renewable Fuel Standard (RFS). This policy mandates the blending of renewable fuels, such as biodiesel, into fossil fuels like diesel at a certain percentage, aiming to reduce greenhouse gas emissions in the transportation sector by lowering the carbon content of the fuel itself. Since its implementation on July 31, 2015, oil refiners and importers/distributors must blend biodiesel when selling automotive diesel, and the blending ratio is being gradually increased. The government has presented a plan to raise the blending ratio to 4.0% for 2024-2026, 4.5% for 2027-2029, and to 5.0% or more from 2030 onward, with long-term consideration for increasing it up to 8%. Although this system regulates the blending ratio of fuel components, it effectively serves to gradually reduce the carbon emission intensity of transportation fuels, leading to its evaluation as the foundational form of a Korean-style LCFS. (Source: Ministry of Trade, Industry and Energy's Enforcement Decree of the Renewable Energy Development, Use and Dissemination Promotion Act, Korea Energy Agency Renewable Energy Center RFS system explanatory materials, 2024 basis) | K11: transportation-sector-main.html#lcfs | L11: low-carbon-fuel-standard.html | M11: https://www.arb.ca.gov/fuels/lcfs/background/basics.htm
A12: Transportation | B12: Non-BAU LCFS-Qualifying Vehicles | C12: Boolean Use Non BAU LCFS Vehicle Types | D12: Low Carbon Fuel Standard | E12: trans LCFS vehicles | F12: 0 | G12: 1 | H12: 1 | I12: on/off | J12: **Description:** This lever changes which vehicles qualify under the low carbon fuel standard. With the lever off, LCFS-qualifying vehicles include all vehicle types except aircraft. With the lever on, only aircraft qualify. | K12: transportation-sector-main.html#lcfs | L12: low-carbon-fuel-standard.html | M12: https://www.arb.ca.gov/fuels/lcfs/background/basics.htm
A13: Transportation | B13: Mode Shifting | C13: Percent of Travel Demand Shifted to Other Modes or Eliminated | D13: Mode Shifting | E13: trans mode shifting | F13: 0 | G13: =-ROUND(MaxBoundCalculations!$B$206,2) -> 0.33 | H13: 0.01 | I13: % of trips shifted | J13: **Description:** This policy represents a set of measures aimed at reducing demand for passenger or freight transportation in the selected vehicle type(s). **Passenger car and SUV** trips may be shifted to other travel modes, such as buses, rail, walking, biking, or eliminated through technology such as videoconferencing. Example measures include improved public transit systems, more walking and bike paths, zoning for higher density along transit corridors, zoning for mixed-use developments, roadway and congestion pricing, and increased parking fees. **Commercial passenger and freight flight** trips may be shifted to inter-city rail or eliminated using technology such as videoconferencing. **Heavy Heavy Duty Truck** trips can be reduced through improved logistics that avoids backhauls and transporting empty shipping containers. The following descriptions detail the different vehicle types: // **Passenger cars and SUVs:** most light-duty road vehicles // **Heavy Duty Trucks:** all other heavy road vehicles (mostly freight trucks) // **Commercial passenger flights:** this is not general aviation // **Guidance for setting values:** The Korean government aims to reduce the total vehicle travel distance of internal combustion engine vehicles by 39%–47% from the 2018 level by 2035 through demand management measures. | K13: transportation-sector-main.html#tdm | L13: transportation-demand-management.html | M13: International Energy Agency, 2009, "Transport, Energy and CO2: Moving toward Sustainability", http://www.iea.org/publications/freepublications/publication/transport2009.pdf "Freight Facts and Figures", 2013, https://ops.fhwa.dot.gov/freight/freight_analysis/nat_freight_stats/docs/13factsfigures/pdfs/fff2013_highres.pdf
A14: Transportation | B14: Federal Zero-Emission Vehicle Sales Standard | C14: Additional Minimum Required ZEV Sales Percentage for Model Region | D14: ZEV Sales Standard | E14: trans ZEV minimum | F14: -1 | G14: 1 | H14: 0.01 | I14: % of new vehicles sold | J14: **Description:** This policy requires a specified percentage of newly sold vehicles of the selected type(s) to consist of zero-emission vehicles. If that percentage would already be achieved through BAU sales plus the effects of other policies, such as an EV subsidy, this policy has no effect. Manufactures may meet a sales standard through techniques such as more heavily marketing electric vehicles, lowering the price of electric vehicles, or raising the price of non-electric vehicles. A negative setting for this lever implies a decrease in ZEV sales requirements relative to the Current Policies scenario. The following descriptions detail the different vehicle types: // **Passenger Cars and SUVs:** most light-duty road vehicles //**Light and Medium Freight Trucks:** commercial trucks carrying freight, not passengers // **Buses:** including school, transit, and intercity buses // **Heavy Duty Trucks:** all other heavy road vehicles (mostly freight trucks) // **Passenger Motorbikes:** registered motorcycles //**Guidance for setting values:** // In South Korea, by 2025, EVs will account for about 20% of new car sales by 2025, and about 31% of new car sales by 2030, in "4th Eco-friendly Vehicle Master Plan" planed by Ministry of Trade, Industry and Energy(MOTIE). | K14: transportation-sector-main.html#ev-mandate | L14: ev-mandate.html | M14: https://autoalliance.org/energy-environment/state-electric-vehicle-mandate/ https://www.cnbc.com/2019/08/26/colorado-joins-california-in-requiring-automakers-to-sell-more-evs.html https://www.consumerreports.org/hybrids-evs/california-says-new-cars-sold-in-the-state-must-be-zero-emissions-by-2035/ https://www.greentechmedia.com/articles/read/electric-buses-are-going-to-dominate statistics from FoVObE variable https://www.prnewswire.com/news-releases/electric-boats-and-ships-2017-2027-300561222.html
A15: Transportation | B15: Non-BAU ZEV-Qualifying Vehicles | C15: Boolean Use Non BAU ZEV Qualifying Vehicle Definitions | D15: ZEV Sales Standard | E15: trans non BAU ZEV vehicle definitions | F15: 0 | G15: 1 | H15: 1 | I15: on/off | J15: **Description:** This lever changes which vehicles qualify under the ZEV standard. With the lever off, ZEV-qualifying vehicles include battery electric vehicles, plugin hybrid vehicles, and hydrogen-fueled vehicles. With the lever on, only battery electric vehicles and hydrogen-fueled vehicles qualify.
A16: Transportation | B16: Subsidy for Vehicle Battery Production | C16: Additional Subsidy for Vehicle Battery Production | D16: Vehicle Battery Production Subsidy | E16: trans battery subsidy | F16: -100000 | G16: 100000 | H16: =G16/50 -> 2000 | I16: KRW/kWh | J16: **Description:** This policy specifies a dollar per kilowatt-hour subsidy for production of vehicle batteries, additional to any BAU subsidies. The subsidy will only be applied to the fraction of vehicle batteries produced domestically. A negative value implies a tax or removal of subsidies. // **Guidance for setting values:** Currently, South Korea does not implement a direct subsidy program for electric vehicle battery manufacturers similar to the Inflation Reduction Act (IRA) in the United States. Instead, the government provides subsidies to electric vehicle buyers to promote the adoption of EVs.
A17: Transportation | B17: Non-BAU State-Level Zero-Emission Vehicle Sales Standard | C17: Boolean Use Non BAU Minimum Required ZEV Sales Percentage by Subregion | D17: ZEV Sales Standard | E17: trans non BAU ZEV minimum | F17: 0 | G17: 1 | H17: 1 | I17: on/off | J17: **Description:** This policy applies alternate assumptions for state level minimum ZEV requirements (specified through an input data file). In the United States model, this tests reversing state Advanced Clean Cars and Advanced Clean Trucks requirements starting in 2025.
A18: Buildings and Appliances | B18: Building Component Electrification | C18: Fraction of New Bldg Components Shifted to Other Fuels | D18: Building Component Electrification | E18: bldgs new component fuel shifting | F18: 0 | G18: 1 | H18: 0.01 | I18: % of newly sold non-electric building components | J18: **Description:** This policy replaces the specified fraction of newly sold non-electric building components of the selected type(s) in buildings of the selected type(s) with electricity-using components. // **Guidance for setting values:** // **Urban Residential Heating:** // In the BAU case, in the United States, the share of electricity among fuels used for heating in urban, residential buildings will stay roughly constant at 12% through 2050. // **Urban Residential Appliances:** In the BAU case, in the United States, the share of electricity among fuels used by appliances in urban, residential buildings will remain constant at roughly 51% through 2050. // **Urban Residential Other Components:** In the BAU case, in the United States, the share of electricity among fuels used by other components in urban, residential buildings will rise from 87% to 90% through 2050. // **Rural Residential Heating:** In the BAU case, in the United States, the share of electricity among fuels used for heating in rural, residential buildings will stay roughly constant at 12% through 2050. // **Rural Residential Appliances:** In the BAU case, in the United States, the share of electricity among fuels used by appliances in rural, residential buildings will remain constant at roughly 51% through 2050. // **Rural Residential Other Components:** In the BAU case, in the United States, the share of electricity among fuels used by other components in urban, residential buildings will rise from 87% to 90% through 2050. // **Commercial Heating:** In the BAU case, in the United States, the share of electricity among fuels used for heating in commercial buildings will stay roughly constant at 4% through 2050. // **Commercial Appliances:** In the BAU case, in the United States, the share of electricity among fuels used by appliances in commercial buildings will fall from 42% to 39% through 2050. // **Commercial Other Components:** In the BAU case, in the United States, the share of electricity among fuels used by other components in commercial buildings will increase from 67% to 72% through 2050. | K18: buildings-sector-main.html#component-elec | L18: building-component-electrification.html | M18: EIA AEO
A19: Buildings and Appliances | B19: Building Energy Efficiency Standards | C19: Reduction in E Use Allowed by Component Eff Std | D19: Building Energy Efficiency Standards | E19: bldgs efficiency standards | F19: 0 | G19: 0.75 | H19: 0.01 | I19: % reduction in energy use | J19: **Description:** This policy tightens energy efficiency standards for the selected component(s) in the selected building type(s). The policy only applies to newly sold components each year (whether for new buildings or replacement of old components of existing buildings). // **Guidance for setting values:** In "2050 Carbon Neutral Scenario" (2021), the South Korean government considered approximately 23% reduction in building energy use (scenario A and B) from 2018 to 2050. | K19: buildings-sector-main.html#eff-stds | L19: building-energy-efficiency-standards.html | M19: Edison Foundation, 2011, "Assessment of Electricity Savings in the U.S. Achievable through New Appliance/Equipment Efficiency Standards and Building Efficiency Codes (2010 - 2025)", http://www.edisonfoundation.net/iei/Documents/IEE_CodesandStandardsAssessment_2010-2025_UPDATE.pdf, Page B-2, Table B-1. | N19: Itron, 2007, "ASSESSMENT OF LONG-TERM ELECTRIC ENERGY EFFICIENCY POTENTIAL IN CALIFORNIA’S RESIDENTIAL SECTOR," http://www.energy.ca.gov/2007publications/CEC-500-2007-002/CEC-500-2007-002.PDF, p.33, Table 5-1
A20: Buildings and Appliances | B20: Contractor Training | C20: Boolean Improved Contractor Edu and Training | D20: Contractor Training | E20: bldgs contractor training | F20: 0 | G20: 1 | H20: 1 | I20: on/off | J20: **Description:** This policy represents a program to train contractors in energy-efficient products and installation practices. This covers activities such as air sealing, building framing, and choice and application of insulation. This policy affects newly sold building envelope components, which reduce the energy use of heating, cooling, and ventilation systems in buildings by 3.7% (based on a 2006 study from the Energy Center of Wisconsin). | K20: buildings-sector-main.html#contractor-ed | L20: contractor-training.html
A21: Buildings and Appliances | B21: Distributed Solar Carve-Out | C21: Min Fraction of Total Elec Demand to be Met by Distributed Solar PV | D21: Distributed Solar Promotion | E21: bldgs min fraction distributed solar | F21: 0 | G21: =ROUND(MaxBoundCalculations!B172,2) -> 0.24 | H21: 0.005 | I21: minimum % elec from solar | J21: **Description:** This policy requires at least the specified percentage of total retail electricity demand to be generated by residential and commercial buildings' distributed solar systems (typically rooftop PV). // **Guidance for setting values:**Public parking lots in Korea are legally required to install solar photovoltaic systems to promote renewable energy use. In addition, public institutions must equip new, expanded, or renovated buildings over 1,000 m² with renewable energy systems, ensuring that at least 32% of their energy use comes from renewables (as of 2022). | K21: buildings-sector-main.html#solar-carve-out | L21: solar-carve-out.html | M21: MASSACHUSETTS: http://www.mass.gov/eea/energy-utilities-clean-tech/renewable-energy/solar/rps-solar-carve-out/current-status-of-the-rps-solar-carve-out-program.html COLORADO: http://www.seia.org/research-resources/rps-solar-carve-out-colorado | N21: RMI, 2011, "Reinventing Fire Electricity Sector Methodology," http://www.rmi.org/cms/Download.aspx?id=10765&file=Reinventing+Fire+Electricity+Sector+Methodology.pdf&title=Reinventing+Fire+Electricity+Sector+Methodology, Page 11, 2050 Generation by Case
A22: Buildings and Appliances | B22: Distributed Solar Subsidy | C22: Additional Perc Subsidy for Distributed Solar PV Capacity | D22: Distributed Solar Promotion | E22: bldgs distributed solar subsidy | F22: 0 | G22: 0.5 | H22: 0.01 | I22: % of PV system cost | J22: **Description:** This policy causes the government to reimburse building owners for an additional percentage of the cost of new distributed solar PV capacity that is installed on or around buildings. // **Guidance for setting values:**In South Korea, support for distributed solar PV installation is primarily provided through installation subsidies and financing programs. For example, under the Renewable Energy Deployment Support Program managed by the Ministry of Trade, Industry and Energy (MOTIE): Residential buildings: subsidies currently cover approximately 47–50% of installation costs (as of 2023 and beyond) Innovative technologies, such as Building-Integrated Photovoltaics (BIPV) and fuel cells, receive preferential support of up to 70%, reflecting the government’s effort to accelerate adoption of advanced renewable technologies. | K22: buildings-sector-main.html#distributed-solar-subsidy | L22: distributed-solar-subsidy.html | M22: Department of Energy. Business Energy Investment Tax Credit (ITC). http://energy.gov/savings/business-energy-investment-tax-credit-itc
A23: Buildings and Appliances | B23: Distributed Solar Capacity Requirement | C23: Min Required Rooftop Solar Capacity | D23: Distributed Solar Promotion | E23: bldgs min req rooftop solar | F23: 0 | G23: 600000 | H23: 5000 | I23: MW | J23: **Description:** This policy requires at least the specified capacity of distributed solar be built by the model. // **Guidance for setting values:** The NEXTgroup estimated South Korea’s rooftop solar potential — including general buildings and industrial complexes — at approximately 42.2 GW.
A24: Buildings and Appliances | B24: Non BAU Distributed Solar Capacity | C24: Boolean Use Non BAU Distributed Solar Capacity | D24: Distributed Solar Promotion | E24: non BAU dist solar | F24: 0 | G24: 1 | H24: 1 | I24: on/off | J24: **Description:** This policy adds or subtracts an amount of distributed solar according to an alternate input data file. //
A25: Buildings and Appliances | B25: Improved Labeling | C25: Boolean Improved Device Labeling | D25: Improved Labeling | E25: bldgs device labeling | F25: 0 | G25: 1 | H25: 1 | I25: on/off | J25: **Description:** This policy represents a program requiring newly sold heating systems, cooling and ventilation systems, and appliances to feature prominent, well-designed labels highlighting their energy efficiencies. The policy reduces energy consumption of newly sold building components of these types by 10%. | K25: buildings-sector-main.html#device-labeling | L25: improved-labeling.html | M25: none
A26: Buildings and Appliances | B26: Retrofit Existing Buildings | C26: Share of Preexisting Buildings Subject to Retrofitting | D26: Increased Retrofitting | E26: bldgs retrofitting | F26: 0 | G26: 0.5 | H26: 0.01 | I26: % of existing buildings | J26: **Description:** Each year, the specified percentage of the selected building type(s) that existed at the start of the model run will be retrofit with more efficient heating, cooling, and envelope components. // **Guidance for setting values:** According to 2050 Carbon Neutral Scenarios, by 2050, 100% of the preexisting buildings in South Korea will meet 1st grade for Zero Energy Building (ZEB) grade. 100% of newly built ones also will meet 1++ for green remodeling efficiency grade, 1+ for commercial grade. | K26: buildings-sector-main.html#retrofitting | L26: increased-retrofitting.html | M26: Calculated from model data; see the relevant variable(s) in the InputData folder for source information.
A27: Buildings and Appliances | B27: Rebate for Efficient Products | C27: Boolean Rebate Program for Efficient Components | D27: Rebate for Efficient Products | E27: bldgs rebate | F27: 0 | G27: 1 | H27: 1 | I27: on/off | J27: **Description:** This policy represents a modest rebate paid to customers who purchase energy-efficient building equipment of the selected type(s). Typical rebate amounts represented by this policy are $50-100 for a clothes washer and $25-50 for a dishwasher or refrigerator. | K27: buildings-sector-main.html#rebate | L27: rebate-for-efficient-products.html
A28: Electricity Supply | B28: Ban New Power Plants | C28: Boolean Ban New Power Plants | D28: Ban New Power Plants | E28: elec ban new power plants | F28: 0 | G28: 1 | H28: 1 | I28: on/off | J28: **Description:** This policy prevents new capacity of the selected type(s) from being built or deployed. | K28: electricity-sector-main.html#ban | L28: ban-new-capacity.html
A29: Electricity Supply | B29: Ban New Power Plant Retrofits | C29: Boolean Ban New Power Plant Retrofits | D29: Ban New Power Plant Retrofits | E29: elec ban new power plant retrofits | F29: 0 | G29: 1 | H29: 1 | I29: on/off | J29: **Description:** This policy prevents new capacity of the selected CCS plant type(s) from being built to replace existing non-CCS plants.
A30: Electricity Supply | B30: Clean Electricity Standard | C30: Renewable Portfolio Std Percentage | D30: Clean Electricity Standard | E30: elec renewable portfolio standards | F30: 0 | G30: 1 | H30: 0.01 | I30: % of electricity generation | J30: **Description:** This policy specifies the fraction of electricity generation that must come from qualifying carbon-free sources (wind, solar, biomass, hydro, and geothermal) in 2050. This policy has no effect until the user-set value exceeds the existing fraction of carbon-free electricity and any carbon-free electricity standards which have been enacted at the state level, which in total reaches 47% in 2050 as a generation-weighted national average. By default, the implementation schedule is set to start at roughly 42% in 2024, matching the BAU share of clean electricity in that year. If you set this policy to a value less than 100%, you should be sure to adjust the 2023 implementation schedule value accordingly. For example, if your chosen lever setting is 80%, the fraction of policy achieved in 2024 should be 42% * 80% (or 33.6%), and the fraction of policy achieved in 2050 should be 100%. Also note that the model incorporates a cap on the CES credit price. If the CES credit price hits this $/MWh amount in a given year, the model will not deploy any additional CES qualifying resources. You can change the maximum CES credit price in the Clean Electricity Standard Alternative Compliance Payment lever. // **Guidance for setting values:** According to Korea’s 11th Basic Plan for Long-term Electricity Supply and Demand, the share of carbon-free electricity(renewable, nuclear, clean hydrogen & ammonia) is projected to reach around 70% by 2038. Korea’s renewable energy share is expected to reach 18.8% (120.9 TWh) in 2030 and 29.2% (205.7 TWh) in 2038. At very high CES values, the associated policy costs are highly uncertain and should be complemented with other modeling. | K30: electricity-sector-main.html#ces | L30: clean-energy-standard.html | M30: White House, 2015, "Fact Sheet: President Obama to Announce Historic Carbon Pollution Standards for Power Plants", https://www.whitehouse.gov/the-press-office/2015/08/03/fact-sheet-president-obama-announce-historic-carbon-pollution-standards.
A31: Electricity Supply | B31: Clean Electricity Standard Foresight | C31: BESHFoFRV Boolean Electricity Suppliers Have Foresight of Future RPS Values | F31: 0 | G31: 1 | H31: 1 | I31: on/off | J31: **Description:** This setting indicates whether electricity suppliers have foresight of future-year CES values (both BAU case values and any values set by the user in the CES policy lever). With foresight, electricity suppliers will build some CES-qualifying resources in earlier years than would be strictly necessary to meet the CES requirement in those years if it allows them to approach a higher, future-year CES target more gradually, lessening the need to build power plants abruptly if the CES rises more steeply in the future.
A32: Electricity Supply | B32: Lift the Clean Electricity Standard Alternative Compliance Payment | C32: Boolean Use Non BAU RPS Alternative Compliance Payment | D32: Clean Electricity Standard | E32: elec non BAU RACP | F32: 0 | G32: 1 | H32: 1 | I32: on/off | J32: **Description:** The BAU scenario includes a CES alternative compliance payment of roughly 180 $/MWh, meaning the model will not deploy any additional CES qualifying resources above this price in an attempt to meet the CES. Enabling this policy lifts this cap, meaning there is no price constraint on new resources.
A33: Electricity Supply | B33: Change Electricity Exports | C33: Percent Change in Electricity Exports | D33: Electricity Imports and Exports | E33: elec change exports | F33: -0.5 | G33: 1 | H33: 0.02 | I33: % change in exports | J33: **Description:** This policy increases or decreases the amount of electricity exported from the current country to Canada and Mexico. It does not cause the construction or removal of transmission lines linking these countries. // **Guidance for setting values:** South Korea does not export electricity to foreign countries. | K33: electricity-sector-main.html#elec-exports | L33: electricity-imports-exports.html | M33: Energy Information Administation. 2016. Electric Power Annual. Table 2.13.
A34: Electricity Supply | B34: Change Electricity Imports | C34: Percent Change in Electricity Imports | D34: Electricity Imports and Exports | E34: elec change imports | F34: -0.5 | G34: 1 | H34: 0.02 | I34: % change in imports | J34: **Description:** This policy increases or decreases the amount of electricity imported to the current country from Canada and Mexico. It does not cause the construction or removal of transmission lines linking these countries. // **Guidance for setting values:** South Korea does not import electricity from foreign countries. | K34: electricity-sector-main.html#elec-imports | L34: electricity-imports-exports.html | M34: Energy Information Administation. 2016. Electric Power Annual. Table 2.13.
A35: Electricity Supply | B35: Non BAU Guaranteed Dispatch | C35: Boolean Use Non BAU Guaranteed Dispatch Settings | D35: Non BAU Guaranteed Dispatch | E35: elec non BAU guaranteed dispatch | F35: 0 | G35: 1 | H35: 1 | I35: on/off
A36: Electricity Supply | B36: Decrease Cost of Capital | C36: Percentage Decrease in Cost of Capital for Power Plants | D36: Decrease Electricity Sector Cost of Capital | E36: elec power plant cost of capital | F36: 0 | G36: 1 | H36: 1 | I36: % decrease | J36: **Description:** This policy decreases the cost of capital for new power plant investments, making the specified plant type more attractive to deploy. // **Guidance for setting values:** The BAU cost of capital for all plant types is calculated as 7.4%, based on data from Lazard. | M36: https://www.lazard.com/media/451905/lazards-levelized-cost-of-energy-version-150-vf.pdf
A37: Electricity Supply | B37: Demand Response | C37: Fraction of Additional Demand Response Potential Achieved | D37: Demand Response | E37: elec demand response | F37: 0 | G37: 1 | H37: 0.01 | I37: % of potential achieved | J37: **Description:** This policy represents regulations that cause more demand response (DR) capacity to be added to the electric grid. Demand response provides flexibility that allows for the integration of more wind and solar PV, if the electricity system is flexibility-constrained. Demand response can be load-shedding (demand is reduced in the worst hours without adding demand in other hours) or load-shifting (demand is reduced in the worst hours and added in other hours). The type of demand response modeled here is load-shedding, which is by far the most common type of demand response that exists today. // **Guidance for setting values:** Additional 4406 MW of DR capacity will be provided in 2050, from 2568 MW in 2021 to 6974 MW in 2050. | K37: electricity-sector-main.html#dr | L37: demand-response.html | M37: Calculated from model data; see the relevant variable(s) in the InputData folder for source information.
A38: Electricity Supply | B38: Early Retirement of Power Plants | C38: Annual Additional Capacity Retired due to Early Retirement Policy | D38: Early Retirement of Power Plants | E38: elec early retirement | F38: 0 | G38: 25000 | H38: 500 | I38: MW/year | J38: **Description:** This policy causes the specified quantity of otherwise non-retiring capacity of the selected type(s) to be retired each year. | K38: electricity-sector-main.html#early-ret | L38: early-retirement-of-power-plants.html | M38: Energy Information Administration, 2014, "Annual Energy Outlook 2014", http://www.eia.gov/oiaf/aeo/tablebrowser/#release=AEO2014&subject=6-AEO2014&table=9-AEO2014&region=0-0&cases=hccstom-d012314a,ref2014-d102413a, Table Browser. Select Electric Power Sector, Electricity Generating Capacity (and check Reference and Accelerated coal retirements scenarios). | N38: The Brattle Group, 2012, "Potential Coal Plant Retirements: 2012 Update," http://greatlakeslegalfoundation.org/wwcms/wp-content/uploads/documents/regulatory/TrainWreck/12Oct15_BrattleStudy.pdf, Page 8, Table 4
A39: Electricity Supply | B39: Non BAU Capacity Retirement Schedule | C39: Boolean Use Non BAU Capacity Retirement Schedule | D39: Non BAU Capacity Retirement Schedule | F39: 0 | G39: 1 | H39: 1 | I39: on/off | J39: **Description:** The EPS calculates economc capacity additions and retirements in each time step. In addition, it incorporates any announced retirements through input data files. This policy uses an alternate input data file specifying planned retirement schedules for existing capacity of the selected type(s). // **Guidance for setting values:** In South Korea, the 2024–2050 power plant retirement data (2024–2050 Retirements) is based on the plans of the Ministry of Trade, Industry and Energy (MOTIE). In particular, the retirement schedule for 2024–2036 is derived from the 10th Basic Electricity Supply Plan. Activating this policy lever enables the model to reflect the government’s official retirement schedule for power plants after 2036.
A40: Electricity Supply | B40: Non BAU Mandated Capacity Construction | C40: Boolean Use Non BAU Mandated Capacity Construction Schedule | D40: Non BAU Mandated Capacity Construction | F40: 0 | G40: 1 | H40: 1 | I40: on/off | J40: **Description:** The business-as-usual (BAU) scenario includes all power plants currently under construction, based on data from the 9th Basic Electricity Supply Plan. This policy represents the use of an alternate set of planned capacity additions. // **Guidance for setting values**: Solar PV and Onshore Wind: This policy lever includes all capacity currently under construction as well as planned projects that have not yet started construction. Offshore Wind: When applied in the context of the Nationally Determined Contribution (NDC) scenario, this policy assumes that 1.25 GW of offshore wind capacity will be installed each year from 2025 to 2035.
A41: Electricity Supply | B41: Non BAU Mandated Capacity CCUS Retrofits | C41: Boolean Use Non BAU Mandated Capacity Retrofit Schedule | D41: Non BAU Mandated Capacity CCUS Retrofits | F41: 0 | G41: 1 | H41: 1 | I41: on/off | J41: **Description:** Turning on this policy lever assumes that these CCUS retrofits will not take place. However, the South Korea model does not include such retrofit plans.
A42: Electricity Supply | B42: Non BAU RPS Qualifying Resources | C42: Boolean Use Non BAU RPS Qualifying Resource Definitions | D42: Non BAU RPS Qualifying Resources | E42: elec non BAU RPS qualifying resources | F42: 0 | G42: 1 | H42: 1 | I42: on/off
A43: Electricity Supply | B43: Change in Expected Power Plant Capacity Factor | C43: Percentage Reduction in Plant Downtime | D43: Reduce Plant Downtime | E43: elec reduce plant downtime | F43: -0.3 | G43: 0.6 | H43: 0.01 | I43: % reduction in downtime | J43: **Description:** This policy specifies the change in capacity factor (time spent generating power) for new natural gas combined cycle plants. This policy changes these plants' expected capacity factors, but it does not force them to be dispatched if it would be uneconomical to do so. A negative value implies a decrease in capacity factor relative to the Current Policies scenario. //**Guidance for setting values:** // **Preexisting Natural Gas Nonpeaker:** Preexisting Korean natural gas nonpeakers have an average capacity factor of 38%. // **New Wind:** Availability of wind cannot be changed by policy, so the main method of increasing capacity factor is technological improvement of wind turbines. The National Renewable Energy Laboratory estimates that "near-future" wind technology could increase capacity factors by about 10 percentage points in most parts of the country. The capacity factor of new wind turbines in the BAU case rises from 20.5% in 2019 to 22.8% in 2050. // **New Solar PV:** Availability of sunlight cannot be changed by policy, so the main method of improvement is increasing the efficiency of solar cells. Typical crystalline silicon cells today have efficiencies of 20-25%, while today's best multi-junction cells (used primarily in concentrator PV and aerospace applications) have efficiencies of 40-45%. If the typical cells installed in 2050 will have efficiencies similar to today's best multi-junction cells, this might be represented as a 26% setting of this policy lever. | K43: electricity-sector-main.html#red-downtime | L43: reduce-downtime.html | M43: E&E Publishing. The Clean Power Plan - A Summary. http://www.eenews.net/interactive/clean_power_plan/fact_sheets/rule National Renewable Energy Laboratory. United States (48 Contiguous States) Potential Wind Capacity Cumulative Area vs. Gross Capacity Factor. http://apps2.eere.energy.gov/wind/windexchange/pdfs/wind_maps/us_contiguous_wind_potential_chart.pdf See the discussion of multi-junction solar cells on Wikipedia at https://en.wikipedia.org/wiki/Multi-junction_solar_cell. Also NREL has a useful chart at http://www.nrel.gov/ncpv/images/efficiency_chart.jpg.
A44: Electricity Supply | B44: Reduce Soft Costs | C44: Percent Reduction in Soft Costs of Capacity Construction | D44: Reduce Soft Costs | E44: elec reduce soft costs | F44: 0 | G44: 0.9 | H44: 0.01 | I44: % reduction in soft costs | J44: **Description:** This policy specifies a reduction in soft costs (costs for things other than capital equipment) for new plants of the selected type(s), such as the costs of permitting, financing, project management, assembly, etc. // **Guidance for setting values:** Costs of permitting and financing can be reduced by streamlining permitting processes, but some soft costs (such as labor) may be difficult to reduce via policy. A value of 50% would be an aggressive soft cost reduction. | K44: endogenous-learning.html#red-soft-costs | L44: reduce-soft-costs.html
A45: Electricity Supply | B45: Reduce Transmission & Distribution Losses | C45: Percentage TnD Losses Avoided | D45: Reduce T&D Losses | E45: elec avoid TND loss | F45: 0 | G45: 0.4 | H45: 0.01 | I45: % of losses avoided | J45: **Description:** This policy specifies the reduction in transmission and distribution losses that will be achieved by 2050. // **Guidance for setting values:** South Korea has transmission and distribution losses of about 3.5%. U.S. have T&D losses of about 6%, and Germany, Japan, Finland, and Netherlands have around 4%. | K45: electricity-sector-main.html#red-tnd-losses | L45: reduce-tnd-losses.html | M45: The World Bank. Electric power transmission and distribution losses (% of output). http://data.worldbank.org/indicator/EG.ELC.LOSS.ZS
A46: Electricity Supply | B46: Subsidy for Capacity Construction | C46: Perc Subsidy for Elec Capacity Construction | D46: Subsidy for Capacity Construction | E46: elec capacity construction subsidy | F46: 0 | G46: 0.95 | H46: 0.01 | I46: % of construction cost | J46: **Description:** This policy is a subsidy paid by the government to electricity suppliers per unit of new capacity constructed. This only applies to utilities, not distributed systems (such as rooftop solar). // **Guidance for setting values:** South Korea currently does not operate direct cash subsidies paid per unit of capacity or generation, nor does it have a PTC-type tax credit system. Instead, it indirectly alleviates the construction burden through investment tax credits and low-interest loans, and provides market incentives based on electricity generation (RPS and REC trading) | K46: electricity-sector-main.html#subsidies | M46: https://www.energy.gov/articles/secretary-perry-announces-financial-close-additional-loan-guarantees-during-trip-vogtle https://www.energysage.com/solar/cost-benefit/solar-investment-tax-credit/ http://biomassmagazine.com/articles/8185/usda-loan-guarantees-support-3-biomass-power-plants
A47: Electricity Supply | B47: Subsidy for Electricity Production | C47: Subsidy for Elec Production by Fuel | D47: Subsidy for Electricity Production | E47: elec generation subsidy | F47: 0 | G47: 100000 | H47: =G47/100 -> 1000 | I47: KRW/kWh | J47: **Description:** This policy is a subsidy paid by the government to suppliers of electricity per unit of electricity generated from the selected plant type(s). // **Guidance for setting values:** South Korea currently does not operate direct cash subsidies paid per unit of capacity or generation, nor does it have a PTC-type (Production Tax Credit) tax credit system. Instead, South Korea utilizes an investment tax credit scheme, which allows companies to claim deductions from corporate or income tax for investments made in renewable energy facilities. This provides an indirect initial investment burden relief effect, similar to the U.S. ITC (Investment Tax Credit). | K47: electricity-sector-main.html#subsidies | L47: subsidy-for-electricity-production.html | M47: PRODUCTION TAX CREDIT: Database of State Incentives for Renewables & Efficiency, 2013, "Renewable Energy Production Tax Credit (PTC)", http://dsireusa.org/incentives/incentive.cfm?Incentive_Code=US13F. STATE-LEVEL INCENTIVES: Energy Information Administration, 2013, "Feed-In Tariffs and similar programs", http://www.eia.gov/electricity/policies/provider_programs.cfm.
A48: Electricity Supply | B48: Use EVs for Grid Balancing | C48: Share of EVs Used for Grid Balancing | D48: EVs for Grid Balancing | E48: elec use EVs for grid balancing | F48: 0 | G48: 1 | H48: 0.01 | I48: % of EVs used | J48: **Description:** This policy increases the share of EVs that are used to assist in grid balancing on an average day. This means the EV is connected to the grid during the hours when demand-shifting would be helpful (hours of net peak load) and can pause its charging or, ideally, can partially discharge its battery during these hours to help provide electricity to the grid. // **Guidance for setting values:** Today, EVs generally are not used to help with grid balancing, and EVs and chargers may not have the capability to send electricity in the reverse direction to supply the grid (and have suitable safety cut-off systems to prevent energizing the grid when utilities intentionally shut it down to do repairs and maintenance). Automatically changing the hours when an EV charges (but not discharging to support the grid) is technologically easier but provides less support to the grid.
A49: Electricity Supply | B49: Subsidy for Grid Battery Production | C49: Additional Subsidy for Grid Battery Production | D49: Grid Battery Subsidy | E49: elec battery production subsidy | F49: -150000 | G49: 150000 | H49: 3000 | I49: KRW/kWh | J49: **Description:** This policy provides a subsidy in units of dollars per kilowatt-hour of battery capacity produced by manufacturers, additional to any BAU subsidies. A negative value implies a tax or removal of subsidies. // **Guidance for setting values:** In South Korea, financial assistance is primarily provided through tax incentives and capital cost subsidies, while direct production-based subsidy systems are limited to certain renewable energy programs such as FIT or RPS
A50: Electricity Supply | B50: Subsidy for Grid Battery Output | C50: Additional Subsidy per Unit Electricity Supplied to the Grid by Grid Batteries | D50: Grid Battery Subsidy | E50: elec battery subsidy per output | F50: -150000 | G50: 150000 | H50: 3000 | I50: KRW/kWh | J50: **Description:** This policy provides a subsidy in units of dollar per megawatt-hour electricity supplied to the grid, additional to any BAU subsidies. A negative value implies a tax or removal of subsidies. // **Guidance for setting values:** In South Korea, there is no subsidy program that provides payments based on the electricity output (MWh) of grid batteries.
A51: Electricity Supply | B51: Subsidy for Grid Battery Capacity | C51: Additional Percent Subsidy per Unit Grid Battery Capacity Deployed | D51: Grid Battery Subsidy | E51: elec battery construction subsidy | F51: -1 | G51: 1 | H51: 0.01 | I51: % of capital costs | J51: **Description:** This policy subsidizes a percentage of grid battery capacity costs, additional to any BAU capacity construction subsidies. A negative value implies a tax or removal of subsidies. // **Guidance for setting values:**The subsidy data were obtained from the Korea Energy Agency (KEA) through the Renewable Energy-Linked ESS Deployment Support Program, and the subsidy rate applied to grid-stabilization energy storage systems (ESS) was reflected. In addition, the calculation method used in the U.S. model based on the Inflation Reduction Act (IRA) was adopted, and the relevant data were adjusted to reflect South Korea’s context. In the business-as-usual (BAU) scenario, the subsidy rate was assumed to be approximately 41.6% of installation costs.
A52: Electricity Supply | B52: Electricity CCS Subsidy | C52: Additional Subsidy for Elec CCS | D52: Electricity CCS Subsidy | E52: elec CCS subsidy | F52: -150000 | G52: 150000 | H52: 3000 | I52: KRW/metric ton CO2e | J52: **Description:** This policy provides a dollar per metric ton CO2e subsidy, additional to any BAU subsidies. // **Guidance for setting values:** Currently, South Korea does not have a direct tax credit scheme per ton (PTC-type) like this.
A53: Industry | B53: Buy In-Region Products | C53: Fraction of Imported Industrial Outputs Shifted to In Region Suppliers | D53: Buy In-Region Products | E53: indst buy in region outputs | F53: 0 | G53: 0.5 | H53: 0.01 | I53: % of imports shifted | J53: **Description:** This policy increases the extent to which the selected industry's products are supplied by producers within the modeled region. // **Guidance for setting values:** The lever specifies the percentage of imported products (in the BAU case) that are shifted to domestic suppliers (in the policy case). For example, suppose buyers within the modeled region purchase 60% of their road vehicles from domestic automakers and 40% from automakers outside the modeled region. If this policy lever is applied to the "Road Vehicles" industry with a 50% setting, buyers will obtain 80% of their road vehicles from domestic automakers and 20% from automakers outside the modeled region. // **Implementation Note:** This policy reduces imports. In reality, other regions might retaliate by restricting their own purchases of goods produced by the modeled region. However, the EPS only considers policies within the modeled region, so the Buy In-Region Products policy does not affect export levels (i.e., other countries/regions are assumed not to retaliate).
A54: Industry | B54: Carbon Capture and Sequestration | C54: Industry Sector Fraction of Potential Additional CCS Achieved | D54: Industry CCS | E54: indst CCS | F54: 0 | G54: 1 | H54: 0.01 | I54: % of CO2 captured | J54: **Description:** This policy specifies the fraction of CO2 emissions from industry that is captured and stored, above the amount predicted in the business-as-usual scenario. // **Guidance for setting values:** Very few CCS-equipped industrial facilities exist today, so in a scenario where industry does not transition to clean energy, a value over 20% is likely very optimistic. However, in scenarios in which industry mostly or entirely transitions to clean energy (i.e. due to other policies, such as industrial fuel switching and industrial energy efficiency), CCS settings as high as 100% (to capture the small amount of residual CO2 emissions, such as process CO2 from the cement industry) may be very feasible. | K54: ccs.html#ccs | L54: carbon-capture-and-sequestration.html
A55: Industry | B55: Non BAU Industry CCS Subsidy | C55: Boolean Use Non BAU Industry CCS Subsidies | D55: Industry CCS | E55: indst non BAU CCS | F55: 0 | G55: 1 | H55: 1 | I55: on/off | J55: **Description:** This policy allows users to model the emissions and cash flow impact of a non-BAU industry CCS subsidy. For the United States, this lever is set up to test the impacts of removing all CCS subsidies flowing to industry in the BAU scenario. // **Guidance for setting values:**South Korea does not have a subsidy system for CCS | K55: ccs.html#ccs | L55: carbon-capture-and-sequestration.html
A56: Industry | B56: Cement Clinker Substitution | C56: Fraction of Cement Measures Achieved | D56: Cement Clinker Substitution | E56: indst cement measures | F56: 0 | G56: 1 | H56: 0.01 | I56: % of potential achieved | J56: **Description:** This policy reduces CO2 emissions from the cement industry by substituting other inputs, such as fly ash, for a portion of the clinker in cement. // **Guidance for setting values:** If this policy is fully implemented, the share of clinker in cement is reduced to 60%. | K56: industry-ag-main.html#clinker | L56: cement-clinker-substitution.html | M56: International Energy Agency and Cement Sustainability Initiative. 2018. Technology Roadmap: Low-Carbon Transition in the Cement Industry. p41. http://www.iea.org/publications/freepublications/publication/TechnologyRoadmapLowCarbonTransitionintheCementIndustry.pdf
A57: Industry | B57: Cogeneration and Waste Heat Recovery | C57: Fraction of Potential Cogeneration and Waste Heat Recovery Adopted | D57: Cogeneration and Waste Heat Recovery | E57: indst CHP | F57: 0 | G57: 1 | H57: 0.01 | I57: % of potential achieved | J57: **Description:** This policy reduces fuel consumption in the industry sector by increasing the use of cogeneration (also known as combined heat and power) and recovery of waste heat (to perform useful work). // **Guidance for setting values:** If this policy is fully implemented, fuel use is reduced by 5.4% for all industries in 2050. | K57: industry-ag-main.html#cogen | L57: cogeneration-and-waste-heat-recovery.html | M57: Calculated from model data; see the relevant variable(s) in the InputData folder for source information.
A58: Industry | B58: Early Retirement of Industrial Facilities | C58: Fraction of Energy Savings from Early Facility Retirement Achieved | D58: Early Retirement of Industrial Facilities | E58: indst early retirement | F58: 0 | G58: 1 | H58: 0.01 | I58: % of potential achieved | J58: **Description:** This policy reduces fuel consumption in the industry sector by retiring older, inefficient industrial facilities sooner than they otherwise would retire. This policy does not affect demand for industrial products, so it is assumed that any facilities retired under this policy are replaced by new facilities or increased output from existing facilities in the same year. // **Guidance for setting values:** If this policy is fully implemented, fuel use is reduced for most industries between 2% and 9% in 2050. | K58: industry-ag-main.html#early-ret | L58: early-retirement-of-industrial-facilities.html | M58: Calculated from model data; see the relevant variable(s) in the InputData folder for source information.
A59: Industry | B59: Industry Energy Efficiency Standards | C59: Percentage Improvement in Eqpt Efficiency Standards above BAU | D59: Industry Energy Efficiency Standards | E59: indst efficiency standards | F59: 0 | G59: 0.25 | H59: 0.01 | I59: % reduction in energy use | J59: **Description:** This policy reduces fuel consumption by the selected industry by increasing the efficiency of industrial equipment through stronger standards. The policy setting refers to overall energy use reduction, not the reduction in energy use of newly sold equipment. // **Guidance for setting values:** In 2016, the U.S. Department of Energy developed an industrial energy efficiency potential analysis that suggests the US could double its annual rate of improvement rate through 2030. Extended through 2050, this equates to a maximum potential improvement of 17% by 2050 relative to BAU. Values are assumed to be similar for South Korea. | K59: industry-ag-main.html#eff-stds | L59: industry-energy-efficiency-standards.html | M59: U.S. DOE, 2016, Industrial Energy Efficiency Potential Analysis, https://energy.gov/sites/prod/files/2017/04/f34/energy-savings-by-state-industrial-methodology.pdf | N59: U.S. DOE, 2016, Industrial Energy Efficiency Potential Analysis, https://energy.gov/sites/prod/files/2017/04/f34/energy-savings-by-state-industrial-methodology.pdf
A60: Industry | B60: Improved System Design | C60: Fraction of Installation and System Integration Issues Remedied | D60: Improved System Design | E60: indst system integration | F60: 0 | G60: 1 | H60: 0.01 | I60: % of potential achieved | J60: **Description:** This policy reduces fuel consumption in the industry sector by improving the way components are put together and the way material or energy flows between them. // **Guidance for setting values:** If this policy is fully implemented, fuel use is reduced by 3.6% for all industries in 2050. | K60: industry-ag-main.html#system-integ | L60: improved-system-design.html | M60: Calculated from model data; see the relevant variable(s) in the InputData folder for source information.
A61: Industry | B61: Electrification | C61: Fraction of Eligible Industrial Energy Use Shifted to Electricity | D61: Electrification | E61: indst shift to electricity | F61: 0 | G61: 1 | H61: 0.01 | I61: % of fuel shifted | J61: **Description:** This policy reduces greenhouse gas emissions from the selected industry by switching the fuels used by facilities to electricity. Only fuel consumed for energy, not fuel used as a chemical feedstock, is affected by this policy. Biomass and purchased heat (steam) are also unaffected. // **Guidance for setting values:** Over 90% of manufacturers' thermal fuels (excluding feedstocks) are used to generate process heat, including to fuel boilers. Generally, boilers/steam and low-temperature non-boiler heat are easier to electrify than higher-temperature heat. | K61: industry-ag-main.html#fuel-switching | L61: industry-elec-and-hydrogen.html
A62: Industry | B62: F-Gas Substitution | C62: Fraction of F Gas Substitution Achieved | D62: F-gas Measures | E62: indst f gas substitution | F62: 0 | G62: 1 | H62: 0.01 | I62: % of potential achieved | J62: **Description:** This policy reduces emissions of high-GWP, fluorinated gases (F-gases) from the industry sector by substituting less-harmful chemicals. // **Guidance for setting values:** The production and consumption of f-gases are limited in the U.S. by the American Innovation and Manufacturing (AIM) Act, which is incorporated in the BAU. Therefore, the U.S. model reflects limited additional abatement potential. If this policy is fully implemented, F-gas emissions in 2050 are reduced by 27%. | K62: industry-ag-main.html#avoid-f-gases | L62: avoid-f-gases.html | M62: Calculated from model data; see the relevant variable(s) in the InputData folder for source information.
A63: Industry | B63: F-Gas Destruction | C63: Fraction of F Gas Destruction Achieved | D63: F-gas Measures | E63: indst f gas destruction | F63: 0 | G63: 1 | H63: 0.01 | I63: % of potential achieved | J63: **Description:** This policy reduces emissions of high-GWP, fluorinated gases (F-gases) from the industry sector by destroying F-gases created as byproducts during the creation of desired products. // **Guidance for setting values:** The production and consumption of f-gases are limited in the U.S. by the American Innovation and Manufacturing (AIM) Act, which is incorporated in the BAU. Therefore, the U.S. model reflects limited additional abatement potential. If this policy is fully implemented, F-gas emissions in 2050 are reduced by 1%. | K63: industry-ag-main.html#avoid-f-gases | L63: avoid-f-gases.html
A64: Industry | B64: F-Gas Recovery | C64: Fraction of F Gas Recovery Achieved | D64: F-gas Measures | E64: indst f gas recovery | F64: 0 | G64: 1 | H64: 0.01 | I64: % of potential achieved | J64: **Description:** This policy reduces emissions of high-GWP, fluorinated gases (F-gases) by recovering F-gases from equipment at the end of its service life and destroying or recycling those F-gases. // **Guidance for setting values:** The production and consumption of f-gases are limited in the U.S. by the American Innovation and Manufacturing (AIM) Act, which is incorporated in the BAU. Therefore, the U.S. model reflects limited additional abatement potential. If this policy is fully implemented, F-gas emissions in 2050 are reduced by 2%. | K64: industry-ag-main.html#avoid-f-gases | L64: avoid-f-gases.html
A65: Industry | B65: F-Gas Eqpt. Maintenance & Retrofits | C65: Fraction of F Gas Inspct Maint Retrofit Achieved | D65: F-gas Measures | E65: indst f gas inspct maint retrofit | F65: 0 | G65: 1 | H65: 0.01 | I65: % of potential achieved | J65: **Description:** This policy reduces emissions of high-GWP, fluorinated gases (F-gases) from the industry sector by reducing leakage and losses through improved inspections, maintenance, and retrofitting of equipment. // **Guidance for setting values:** The production and consumption of f-gases are limited in the U.S. by the American Innovation and Manufacturing (AIM) Act, which is incorporated in the BAU. Therefore, the U.S. model reflects limited additional abatement potential. If this policy is fully implemented, F-gas emissions in 2050 are reduced by less than 1%. | K65: industry-ag-main.html#avoid-f-gases | L65: avoid-f-gases.html
A66: Industry | B66: Feedstock Shifting | C66: Fraction of Feedstock Shifted | D66: Feedstock Shifting | E66: indst feedstock shifting | F66: 0 | G66: 1 | H66: 0.01 | I66: % of potential achieved | J66: **Description:** This policy shifts the use of fossil-fuel feedstocks to hydrogen. The production method for this new hydrogen demand can be shifted wiht the Fraction of Hydrogen Production Pathways Shifted lever. // **Guidance for setting values (Chemicals):** Approximately 52 percent of natural gas consumed as a chemical feedstock globally goes to producing ammonia and methanol. These pathways can be replaced with green electrolytic hydrogen to eliminate process emissions associated with production. // **Guidance for setting values (Iron & Steel):** Coal is the most significant feedstock used in the steel industry, largely for reducing iron ore in blast furnaces. A transition from the traditional steelmaking route (blast furnace-basic oxygen furnace) to alternatives (like hydrogen-based direct reduced iron with electric arc furnaces) can be represented by pairing this lever with electrification of industrial heat.
A67: Industry | B67: Hydrogen Combustion | C67: Fraction of Eligible Industrial Energy Use Shifted to Hydrogen | D67: Hydrogen Combustion | E67: indst shift to hydrogen | F67: 0 | G67: 1 | H67: 0.01 | I67: % of fuel shifted | J67: **Description:** This policy reduces greenhouse gas emissions from the selected industry by switching the fuels used by facilities to hydrogen combustion. Only fuel consumed for energy, not fuel used as a chemical feedstock, is affected by this policy. Biomass and purchased heat (steam) are also unaffected. // **Guidance for setting values:** Over 90% of manufacturers' thermal fuels (excluding feedstocks) are used to generate process heat, including to fuel boilers. Generally, hydrogen combustion is reserved for high-temperature heat, since it is often simpler and more efficient to directly electrify heat at lower temperatures. | K67: industry-ag-main.html#fuel-switching | L67: industry-elec-and-hydrogen.html
A68: Industry | B68: Material Efficiency, Longevity, & Re-Use | C68: Percent Reduction in Nonenergy Nonagriculture Industry Product Demand | D68: Material Efficiency, Longevity, & Re-Use | E68: indst reduce nonenergy product demand | F68: 0 | G68: 1 | H68: 0.01 | I68: % demand reduction | J68: **Description:** // **Cement and Iron & Steel:** This policy reduces demand for the selected materials through techniques such as material-efficient building codes (using modern designs that require less material per unit floor area), requirements for greater building and infrastructure longevity, greater re-use and re-purposing of buildings (rather than tearing down and building new), etc. // **Guidance for setting values:** In "Sustainable Materials Without the Hot Air: Making Buildings, Vehicles and Products Efficiently and with Less New Material," Allwood and Cullen estimate that concrete use could be reduced by up to 40% using optimized molds, and concrete building longevity could be more than doubled to 200 years. Together, these measures might reduce concrete demand by up to 70%, if demand for building floorspace reaches steady state. They estimate that steel use could be reduced by 30% by optimizing designs and controlling the loads they experience during installation and use. If the lifetime of steel products could be doubled, the resulting material reduction could be up to 65%, if sales reach steady state. // **Water and Waste:** This policy reduces demand for water treatment and waste management services through techniques such as water conservation, reduction in disposable packaging, requirements for greater product longevity, greater repair and re-use of products, and increased recycling and composting. // **Guidance for setting values:** The majority of energy use and emissions from the water and waste sector are a result of water treatment, not solid waste management. Non-agriculture uses, including lawn irrigation and in-home use, may be able to achieve similar savings through improved practices and fixtures. | L68: material-efficiency-longevity-reuse.html | M68: Allwood and Cullen, "Sustainable Materials Without the Hot Air: Making Buildings, Vehicles and Products Efficiently and with Less New Material" Allwood and Cullen, "Sustainable Materials With Both Eyes Open" - page 185, http://www.withbotheyesopen.com/read.php?c=12 USDA Irrigation & Water Use: https://www.ers.usda.gov/topics/farm-practices-management/irrigation-water-use.aspx and EPA WaterSense Statistics and Facts: https://www.epa.gov/watersense/statistics-and-facts
A69: Industry | B69: Methane Capture | C69: Fraction of Methane Capture Opportunities Achieved | D69: Methane Capture and Destruction | E69: indst methane capture | F69: 0 | G69: 1 | H69: 0.01 | I69: % of potential achieved | J69: **Description:** This policy reduces methane emissions from the selected industry by increasing the capture of methane that is currently being released into the atmosphere (for example, stopping leaks from wellheads, pipes, coal mines, landfills, etc.). **Guidance for setting values:** The U.S. has standards for new and existing equipment covering the oil and gas production and energy pipelines and gas processing industries in the EPS, which are reflected in the BAU. The rules for existing equipment are together expected to reduce emissions by 119 MMT CO2e by the year 2039. Values are assumed to be similar for South Korea. | K69: industry-ag-main.html#methane-capture | L69: methane-capture.html
A70: Industry | B70: Methane Destruction | C70: Fraction of Methane Destruction Opportunities Achieved | D70: Methane Capture and Destruction | E70: indst methane destruction | F70: 0 | G70: 1 | H70: 0.01 | I70: % of potential achieved | J70: **Description:** This policy reduces methane emissions from the selected industry by increasing the burning of methane that is currently being released into the atmosphere (i.e. flaring instead of venting/leaking). **Guidance for setting values:** The U.S. has standards for new and existing equipment covering the oil and gas production and energy pipelines and gas processing industries in the EPS, which are reflected in the BAU. The rules for existing equipment are together expected to reduce emissions by 119 MMT CO2e by the year 2039. | K70: industry-ag-main.html#methane-destr | L70: methane-destruction.html
A71: Industry | B71: N2O Abatement | C71: Fraction of N2O Abatement Achieved | D71: N2O Abatement | E71: indst N2O abatement | F71: 0 | G71: 1 | H71: 0.01 | I71: % of potential achieved | J71: **Description:** This policy reduces nitrous oxide (N2O) process emissions from the chemicals industry (primarily from the production of nitric acid and adipic acid) by destroying the N2O rather than venting it to the atmosphere. //
A72: Industry | B72: Non BAU Increase in Process Emissions | C72: Boolean Use Non BAU Process Emissions Additions | D72: Process Emissions Increases | E72: non BAU indst process emissions | F72: 0 | G72: 1 | H72: 1 | I72: on/off | J72: **Description:** This policy lever tests increases in industrial process emissions relative to the Current Policies scenario according to schedules set via model input data. // **Guidance for setting values:** //**Methane capture and destruction:** This lever repeals the relevant standards. // **Cropland, rice, and livestock measures:** This lever removes the relevant financial support and the associated projected emissions reductions.
A73: Industry | B73: Reduce Fossil Fuel Exports | C73: Percent Reduction in Fossil Fuel Exports | D73: Percent Reduction in Fossil Fuel Exports | E73: indst reduce fossil fuel exports | F73: 0 | G73: 1 | H73: 0.01 | I73: % reduction in exports | J73: **Description:** This policy reduces production of the selected fuel type(s) for export. This lever may represent a reduction in fuel demand by actors outside the modeled region (i.e., not caused by domestic policy) or a conscious policy within the modeled region to transition its economy away from dependence on fossil fuel exports. // **Guidance for setting values:** In the South Korea model, this lever has virtually no impact, as South Korea is a net importer of coal, oil, and LNG. Fuel exports essentially do not exist, aside from small volumes of re-exported petroleum products, which are minimal. | L73: reduce-fuel-exports.html | M73: Calculated from model data; see the relevant variable(s) in the InputData folder for source information.
A74: Agriculture, Land Use, and Forestry | B74: Afforestation and Reforestation | C74: Fraction of Afforestation and Reforestation Achieved | D74: Afforestation and Reforestation | E74: land afforestation and reforestation | F74: -3 | G74: 1 | H74: 0.01 | I74: % of potential achieved | J74: **Description:** This policy increases the sequestration of CO2 by planting forests. Planted forests are assumed to be managed with best practices and are not used for timber harvesting. A negative values implies less sequestration compared to the Current Policies scenario. // **Guidance for setting values:** Forest management in Korea is broadly divided into afforestation and forest management. Afforestation refers to the artificial establishment of forests, such as sowing seeds or planting trees. Reforestation, on the other hand, refers to the continuous management of forests after planting or activities aimed at improving forest conditions. Therefore, the figure representing the area converted to forest reflects only the area of reforestation, not general forest management activities. If this policy is implemented at 100%, approximately 57,957 acres/year of land would be converted to forest each year. | K74: lulucf.html#aff-ref | L74: afforestation-and-reforestation.html | M74: Calculated from model data; see the relevant variable(s) in the InputData folder for source information. | N74: Ross W. Gorte, 2009, "U.S. Tree Planting for Carbon Sequestration," Congressional Research Service, https://www.fas.org/sgp/crs/misc/R40562.pdf, p.3, paragraph 1
A75: Agriculture, Land Use, and Forestry | B75: Avoid Deforestation | C75: Fraction of Avoided Deforestation Achieved | D75: Avoid Deforestation | E75: land avoid deforestation | F75: 0 | G75: 1 | H75: 0.01 | I75: % of potential achieved | J75: **Description:** This policy prevents clear cutting of forests that would otherwise be cleared. Preserved forests are assumed to be managed with best practices. // **Guidance for setting values:** If this policy is fully implemented at 100%, the model avoids 1976 acres/year of deforestation. | K75: lulucf.html#avoid-def | L75: avoid-deforestation.html
A76: Agriculture, Land Use, and Forestry | B76: Grassland Restoration and Avoided Conversion | C76: Fraction of Forest Restoration Achieved | D76: Grassland Restoration and Avoided Conversion | E76: land forest restoration | F76: 0 | G76: 1 | H76: 0.01 | I76: % of potential achieved | J76: **Description:** This policy increases CO2 sequestration by avoiding the conversion of grasslands and restoring grassland areas. // **Guidance for setting values:**A 100% setting of this lever avoids the conversion of approximately 113 acres/year of grassland. | L76: forest-restoration.html | M76: See file PLANAbPiaSY
A77: Agriculture, Land Use, and Forestry | B77: Forest Set-Asides | C77: Fraction of Forest Set Asides Achieved | D77: Forest Set-Asides | E77: land forest set asides | F77: 0 | G77: 1 | H77: 0.01 | I77: % of potential achieved | J77: **Description:** This policy avoids the release of CO2 from forests by reducing timber harvesting. // **Guidance for setting values:** Because most Korean forests were established during the 1970–1980 afforestation period and have now reached an age at which carbon uptake declines, the Korea Forest Service emphasizes structural improvement (e.g., thinning and stand renewal) rather than reducing timber harvesting. Given Korea’s low level of commercial timber harvest and limited deforestation pressure, we set the deforestation reduction rate to zero in our modeling. | K77: lulucf.html#set-asides | L77: forest-set-asides.html | M77: Calculated from model data; see the relevant variable(s) in the InputData folder for source information.
A78: Agriculture, Land Use, and Forestry | B78: Cropland and Rice Measures | C78: Fraction of Cropland and Rice Measures Achieved | D78: Cropland and Rice Measures | E78: indst cropland and rice measures | F78: 0 | G78: 1 | H78: 0.01 | I78: % of potential achieved | J78: **Description:** This policy reduces CH4 and N2O emissions from agriculture through cropland management practices, such as improved crop rotations, reduced soil tillage, and improvements in fertilizer composition and application. Measures particular to rice cultivation include improved flooding practices that avoid anaerobic, methane-forming conditions. // **Guidance for setting values:** The BAU reflects increased uptake of cropland and rice measures due to incentives provided in the Inflation Reduction Act. This lever represents additional potential on top of BAU emissions reductions. To be conservative, we do not assume permanent emissions reductions after IRA funds expire, so therefore phase out the IRA impact over the course of four years after funds expire in 2032. The total potential for this policy lever is sourced from EPA's 2024 Forestry and Agriculture Sector Mitigation Analysis, which evaluates various carbon price scenarios across both the forestry and agriculture sectors and considers land use competition. At the maximum level of $100 per ton, the cropland and rice measures potential is roughly 10 MMT CO2e in 2050. | K78: industry-ag-main.html#cropland | L78: cropland-management.html | M78: Calculated from model data; see the relevant variable(s) in the InputData folder for source information.
A79: Agriculture, Land Use, and Forestry | B79: Improved Soil Measures | C79: Fraction of CO2 Storage Through Tillage Practices | D79: Improved Soil Measures | E79: indst tillage | F79: 0 | G79: 1 | H79: 0.01 | I79: % of potential achieved | J79: **Description:** This policy stores CO2 in agricultural soils through improved tillage practices, retiring organic and marginal soils, and establishing windbreaks/shelterbelts. // **Guidance for setting values:** If this policy is fully implemented, approximately 70 MMT CO2 is stored in soils.
A80: Agriculture, Land Use, and Forestry | B80: Improved Forest Management | C80: Fraction of Improved Forest Management Achieved | D80: Improved Forest Management | E80: land forest management | F80: -1.5 | G80: 1 | H80: 0.01 | I80: % of potential achieved | J80: **Description:** This policy increases CO2 sequestration by forests through improved forest management practices. A negative values implies less sequestration compared to the Current Policies scenario. // **Guidance for setting values:**The potential for this policy lever is based on Korea’s 2024 Forest and Forestry Statistics Yearbook. This dataset and related analyses incorporate a range of carbon price scenarios across the forestry and agriculture sectors and account for land-use competition. Under a full implementation (100% setting), the model assumes that approximately 540,608 acres per year are managed through improved forest management practices. | K80: lulucf.html#forest-mgmt | L80: improved-forest-management.html | M80: Calculated from model data; see the relevant variable(s) in the InputData folder for source information.
A81: Agriculture, Land Use, and Forestry | B81: Livestock Measures | C81: Fraction of Livestock Measures Achieved | D81: Livestock Measures | E81: indst livestock measures | F81: 0 | G81: 1 | H81: 0.01 | I81: % of potential achieved | J81: **Description:** This policy reduces greenhouse gas emissions from agriculture through livestock-related measures, such as feed supplements or drugs to prevent enteric methane formation. // **Guidance for setting values:** The BAU reflects increased uptake of livestock measures due to incentives provided in the Inflation Reduction Act. This lever represents additional potential on top of BAU emissions reductions. To be conservative, we do not assume permanent emissions reductions after IRA funds expire, so therefore phase out the IRA impact over the course of four years after funds expire in 2032. The potential for this policy lever is sourced from EPA's 2024 Forestry and Agriculture Sector Mitigation Analysis, which evaluates various carbon price scenarios across both the forestry and agriculture sectors and considers land use competition. At a level of $100 per ton, the livestock measures potential is roughly 55 MMT CO2e in 2050. | K81: industry-ag-main.html#livestock | L81: livestock-measures.html | M81: Calculated from model data; see the relevant variable(s) in the InputData folder for source information.
A82: Agriculture, Land Use, and Forestry | B82: Wetland Restoration | C82: Fraction of Peatland Restoration Achieved | D82: Wetland Restoration | E82: land peatland restoration | F82: 0 | G82: 1 | H82: 0.01 | I82: % of potential achieved | J82: **Description:** This policy increases CO2 sequestration by restoring wetlands and riparian forest buffers. // **Guidance for setting values:**In the Korean EPS (Earth-Peat Lands) model, this policy was expanded to cover overall wetland restoration. If this policy is fully implemented, 30km2 of tidal flats will be restored by 2050. | L82: peatland-restoration.html | M82: https://www.usda.gov/sites/default/files/documents/White_Paper_WEB71816.pdf
A83: Agriculture, Land Use, and Forestry | B83: Shift to Non-Animal Products | C83: Percent Animal Products Shifted to Nonanimal Products | D83: Shift to Non-Animal Products | E83: indst shift to nonanimal products | F83: 0 | G83: 1 | H83: 0.01 | I83: % reduction in animal products | J83: **Description:** This policy causes animal products to be substituted for non-animal products, which might be achieved by changes in consumer preferences or by changes in costs of agricultural products (such as by redirecting subsidies currently paid to farmers who raise animals or feed crops to farmers growing fruits, vegetables, and other plant-based foods for human consumption). Moderate settings of this policy lever do not imply a vegan diet: for instance, a 50% setting could represent each individual consuming half as many animal products, rather than half of the population consuming no animal products. // **Guidance for setting values:** According to OECD statistics, South Korea consumes 57 kg/person/year, which is moderate compared to other countries. The US consumes 98 kg/person/yr, Europe is at 70 kg/person/yr, Japan at 36 kg/person/yr, or India 3 kg/person/yr. | L83: shift-to-non-animal-products.html | M83: https://en.wikipedia.org/wiki/List_of_countries_by_meat_consumption_per_capita (article revision 00:12, 22 Feb 2019)
A84: District Heat and Hydrogen | B84: Use CHP for District Heat | C84: Fraction of Non CHP Heat Production Converted to CHP | D84: District Heat CHP | E84: heat convert heat to CHP | F84: 0 | G84: 1 | H84: 0.01 | I84: % non-CHP heat converted | J84: **Description:** This policy causes a percentage of the district heat that would be generated by dedicated heat plants to instead be generated via CHP plants. In this model, this causes them to consume no additional fuel, since it is assumed CHP plants would be run anyway in order to produce electricity. // **Guidance for setting values:** In the BAU Scenario, the fraction of heat derived from CHP plants is constant at roughly 50%. Therefore, a policy setting of 50% would increase the CHP fraction to 75% in 2050. | K84: district-heating.html#chp | L84: convert-non-chp-heat-production.html | M84: Calculated from model data; see the relevant variable(s) in the InputData folder for source information.
A85: District Heat and Hydrogen | B85: Produce District Heat with Electricity | C85: Fraction of District Heat Fuel Use Shifted to Other Fuels | D85: District Heat Fuel Switching | E85: heat fuel type shifting | F85: 0 | G85: 1 | H85: 0.01 | I85: % of fuel use | J85: **Description:** This policy causes a percentage of the demand for district heat to be met with electricity instead of the fuels used in the BAU case. // **Guidance for setting values:** * In South Korea, 80% of district heat is made by burning natural gas, 17% from coal, 3% from petroleum. Hydrogen technologies are still emerging, and it is not yet clear if it will be more economical to electrify end uses of heat (ceasing to use district heat), or if decarbonizing district heat facilities will be an economical pathway. | K85: district-heating.html#convert-coal | L85: district-heat-fuel-switching.html | M85: Calculated from model data; see the relevant variable(s) in the InputData folder for source information.
A86: District Heat and Hydrogen | B86: Shift Hydrogen Production Pathways | C86: Fraction of Hydrogen Production Pathways Shifted | D86: Shift Hydrogen Production Pathways | E86: hydgn shift production pathways | F86: 0 | G86: 1 | H86: 0.01 | I86: % of hydrogen production | J86: **Description:** By default, this policy causes a percentage of merchant hydrogen (i.e. hydrogen produced for sale, not hydrogen produced and consumed on-site within a facility) to be produced via electrolysis rather than via other production pathways. If the Non BAU Hydrogen Production Pathways lever is enabled, this lever works in the opposite direction by shifting hydrogen production to steam methane reforming. // **Guidance for setting values:** Today, roughly 95% of hydrogen is produced via steam reforming of natural gas and 5% is produced via electrolysis. These shares are not projected to change in the BAU case. | L86: switch-hydrogen-production-pathway.html
A87: District Heat and Hydrogen | B87: Non BAU Hydrogen Production Pathways | C87: Boolean Use Non BAU Hydrogen Shifting | D87: Hydrogen Steam Methane Reforming | E87: hydgn non BAU shift | F87: 0 | G87: 1 | H87: 1 | I87: on/off | J87: **Description:** This lever changes the direction of the "Shift Hydrogen Production Pathways" lever. By default, the "Shift Hydrogen Production Pathways" lever causes a percentage of merchant hydrogen (i.e. hydrogen produced for sale, not hydrogen produced and consumed on-site within a facility) to be produced via electrolysis rather than via other production pathways. If the Non BAU Hydrogen Production Pathways lever is enabled, it causes hydrogen production pathway shifting to work in the opposite direction by shifting hydrogen production to steam methane reforming. // **Guidance for setting values:** Today, roughly 95% of hydrogen is produced via steam reforming of natural gas and 5% is produced via electrolysis. These shares are projected to shift towards electrolysis in the Current Policies scenario due to hydrogen tax credits provided by the Inflation Reduction Act. Enabling this lever can be used to model repealing the Inflation Reduction Act tax credits. | L87: switch-hydrogen-production-pathway.html
A88: Cross-Sector | B88: Carbon Price | C88: Additional Carbon Tax Rate | D88: Carbon Price | E88: cross carbon tax | F88: 0 | G88: 500000 | H88: 10000 | I88: KRW/metric ton CO2e | J88: **Description:** This policy applies a price on fuels used in the selected sector(s) based on their greenhouse gas emissions. It also increases the base cost of capital equipment (e.g., vehicles, power plants, building components) according to their embedded carbon content. When applied to the Industry Sector, the tax **is** levied on greenhouse gas emissions from non-energy industrial and agricultural processes by default, but these emissions sources can be exempted from the tax by enabling the policy lever "Exempt Process Emissions from C Tax." Note that by default, a carbon price will not include a border adjustment, but a border adjustment can be enabled using the policy lever "Toggle Carbon Tax Border Adjustment." // **Guidance for setting values:** The U.S. government's revised Social Cost of Carbon estimates for the year 2050 range from $200 to $520 per ton (in inflation-adjusted 2020 dollars), depending on one's choice of discount rate. The same assumption is assumed for Korea as well. | K88: fuels.html#carbon-tax | L88: carbon-tax.html | M88: U.S. EPA, 2015, "The Social Cost of Carbon", https://www.epa.gov/climatechange/social-cost-carbon, Row "2050". (For source for adjustment to 2018 dollars, see cpi.xlsx in InputData.) | N88: U.S. EPA, 2016, "Social Cost of CO2, 2015-2020," https://www.epa.gov/climatechange/social-cost-carbon
A89: Cross-Sector | B89: End Existing Subsidies | C89: Percent Reduction in BAU Subsidies | D89: End Existing Subsidies | E89: cross reduce BAU subsidies | F89: 0 | G89: 1 | H89: 0.01 | I89: % reduction in BAU subsidies | J89: **Description:** This policy reduces the subsidies paid for the production of the selected energy source(s) (relative to the BAU case). Note that some subsidies affect the cost of fuel (such as coal and natural gas), while some subsidies are for electricity production or capacity construction (Production Tax Credits and Investment Tax Credits). // **Guidance for setting values:** A value of 100% eliminates investment tax credits for wind, solar, geothermal, hydrogen, and nuclear. South Korea’s investment tax credit for renewable energy facilities is calculated by applying a fixed percentage (e.g., 1%, 3%, 7%) to the facility investment cost. As a result, subsidies for small-scale power generators may be overestimated compared to actual conditions. | K89: fuels.html#end-subsidies | L89: end-existing-subsidies.html | M89: Calculated from model data; see the relevant variable(s) in the InputData folder for source information.
A90: Cross-Sector | B90: Exempt Non-CO2 Emissions from C Tax | C90: Toggle Whether Carbon Tax Affects Non CO2 Emissions | E90: cross toggle whether carbon tax affects non CO2 emissions | F90: 0 | G90: 1 | H90: 1 | I90: on/off | J90: **Description:** By default, the carbon tax applies to CO2 and non-CO2 emissions. This policy exempts non-CO2 emissions, meaning the carbon tax will only apply to CO2 emissions. | K90: fuels.html#carbon-tax | L90: carbon-tax.html
A91: Cross-Sector | B91: Exempt Process Emissions from C Tax | C91: BEPEfCT Boolean Exempt Process Emissions from Carbon Tax | E91: cross toggle whether carbon tax affects process emissions | F91: 0 | G91: 1 | H91: 1 | I91: on/off | J91: **Description:** Turning this policy lever on prevents the carbon tax from being levied on process emissions from the selected industry categories. (Process emissions are non-energy greenhouse gas emissions from industrial and agricultural operations, for example emissions released due to chemical reactions during cement production). By default, we exempt agriculture and water and waste process emissions, as these categories are generally not covered by carbon tax proposals. | K91: fuels.html#carbon-tax | L91: carbon-tax.html
A92: Cross-Sector | B92: Toggle Carbon Tax Border Adjustment | C92: BDCTBA Boolean Disable Carbon Tax Border Adjustment | F92: 0 | G92: 1 | H92: 1 | I92: on/off | J92: **Description:** By default, carbon taxes apply to only domestically produced goods. Turning this policy lever on enables carbon tax border adjustments, meaning the carbon tax will apply to both domestically produced and imported goods. | K92: fuels.html#carbon-tax | L92: carbon-tax.html
A93: Cross-Sector | B93: Fixed Energy Prices | C93: Toggle Whether Policies Affect Energy Prices | D93: Fixed Energy Prices | E93: cross toggle whether policies affect energy prices | F93: 0 | G93: 1 | H93: 1 | I93: on/off
A94: Cross-Sector | B94: Fuel Price Deregulation | C94: Fuel Price Deregulation | D94: Fuel Price Deregulation | E94: cross fuel price deregulation | F94: 0 | G94: 1 | H94: 0.01 | I94: % of price deregulated | J94: **Description:** This policy causes the price of the selected fuel(s) for domestic buyers to approach international market prices. // **Guidance for setting values:** A value of 100% causes domestic fuel prices to equal international market prices, increasing the domestic price by roughly X% in 2050. | K94: fuels.html#fuel-price-deregulation
A95: Cross-Sector | B95: Fuel Taxes or Subsidies | C95: Additional Fuel Tax or Subsidy Rate by Fuel | D95: Fuel Taxes or Subsidies | E95: cross fuel tax | F95: -0.9 | G95: 0.9 | H95: 0.01 | I95: % of BAU price | J95: **Description:** This policy changes the tax rate for the selected fuel type(s). It is expressed as a percentage of the BAU Scenario price, which includes sales and excise taxes. To increase the tax rate, set a positive value. To reduce the BAU tax rate (or to apply a subsidy), set a negative value. // **Guidance for setting values:** South Korea’s current energy taxation system is based on a specific tax structure, in which taxes are imposed per unit of energy consumed. The system is heavily concentrated on transportation fuels, particularly gasoline, diesel, and LPG (butane). As of 2019, the applicable tax rates were as follows. For transportation fuels, tax rates in 2019 were 762.36 won/L for gasoline, 545.22 won/L for diesel, and 383.057 won/kg for LPG (butane). For heating and industrial use, the rates were 88.92 won/L for kerosene, 36.02 won/L for heavy fuel oil, and 24.527 won/kg for LPG (propane). For power generation and other uses, the rates were 20.63 won/kg for LNG and 46 won/kg for bituminous coal. | K95: fuels.html#fuel-taxes | L95: fuel-taxes.html | M95: AVG SALES TAX: The Sales Tax Clearinghouse, FAQ, https://thestc.com/FAQ.stm, Question "What is the average sales tax nationally?" AVG GASOLINE TAX: Energy Information Administration, 2014, Annual Energy Outlook 2014, http://www.eia.gov/forecasts/aeo/supplement/suptab_130.xlsx, Supplement Table 130.
A96: Cross-Sector | B96: Non BAU Carbon Tax Vehicle Qualification | C96: Boolean Use Non BAU Carbon Tax Vehicle Type Qualification | F96: 0 | G96: 1 | H96: 1 | I96: on/off | J96: **Description:** This lever determines which vehicle types are captured under the scope of a carbon tax. In some regions, only certain vehicle types are covered by a carbon tax or cap.
A97: Cross-Sector | B97: Non BAU Carbon Tax Industry Qualification | C97: Boolean Use Non BAU Carbon Tax Industry Category Qualification | F97: 0 | G97: 1 | H97: 1 | I97: on/off | J97: **Description:** This lever determines which industry categories are captured under the scope of a carbon tax. In some regions, only certain industries are covered by a carbon tax or cap.
A98: Cross-Sector | B98: Non BAU CBAM Industry Qualification | C98: Boolean Use Non BAU Carbon Tax Border Adjustment Industry Qualification | F98: 0 | G98: 1 | H98: 1 | I98: on/off | J98: **Description:** This lever determines which industry categories are captured under the scope of a carbon border adjustment mechanism. In some regions, only certain industries are covered by a border mechanism.
A99: Research and Development | B99: Capital Cost Reduction | C99: RnD Building Capital Cost Perc Reduction | D99: R&D Capital Cost Reductions | E99: RnD building capital cost reduction | F99: 0 | G99: 0.4 | H99: 0.01 | I99: % reduction in cost | J99: **Description:** This policy causes the capital cost of the selected type(s) of equipment to decline by the set percentage over the course of the model run. The R&D progress caused by this policy is additional to any R&D necessary to comply with other policies, such as tighter fuel economy standards. No costs associated with conducting this additional R&D (such as investments in laboratories or engineers' salaries) are included in the model. // **Guidance for setting values:** This policy should generally be set to zero unless you are exploring a scenario with unusual and unexpected technological advancement. If setting a non-zero value, more mature technologies, such as coal, should have lower values than younger technologies, such as solar. A setting of 30% implies an average of roughly 1% annual improvement, which is very substantial. | K99: architectural-design.html#rnd | L99: research-and-development.html
A100: =A$99 -> Research and Development | B100: =B$99 -> Capital Cost Reduction | C100: RnD CCS Capital Cost Perc Reduction | D100: =D$99 -> R&D Capital Cost Reductions | E100: RnD CCS capital cost reduction | F100: =F$99 -> 0 | G100: =G$99 -> 0.4 | H100: =H$99 -> 0.01 | I100: =I$99 -> % reduction in cost | J100: =J$99 -> **Description:** This policy causes the capital cost of the selected type(s) of equipment to decline by the set percentage over the course of the model run. The R&D progress caused by this policy is additional to any R&D necessary to comply with other policies, such as tighter fuel economy standards. No costs associated with conducting this additional R&D (such as investments in laboratories or engineers' salaries) are included in the model. // **Guidance for setting values:** This policy should generally be set to zero unless you are exploring a scenario with unusual and unexpected technological advancement. If setting a non-zero value, more mature technologies, such as coal, should have lower values than younger technologies, such as solar. A setting of 30% implies an average of roughly 1% annual improvement, which is very substantial. | K100: =K$99 -> architectural-design.html#rnd | L100: =L$99 -> research-and-development.html
...

Sheet PolicyLevers
A1: Sector | B1: Short Name | C1: Vensim Variable Name | D1: Subscript 1 Value | E1: Subscript 2 Value | F1: Subscript 1 Display Name | G1: Subscript 2 Display Name | H1: Policy ID Number | I1: Include in Web App | J1: Policy Group | K1: Policy Schedule Subscript | L1: Min Slider Value | M1: Max Slider Value | N1: Slider Step Size | O1: Units | P1: Text for Pop-Over Panel Description | Q1: URL for "How the model handles this policy" links | R1: URL for "How to design this policy well" links
A2: =IF(ISBLANK(INDEX('Policy Characteristics'!A:A,MATCH($C2,'Policy Characteristics'!$C:$C,0))),"",INDEX('Policy Characteristics'!A:A,MATCH($C2,'Policy Characteristics'!$C:$C,0))) -> Transportation | B2: =IF(ISBLANK(INDEX('Policy Characteristics'!B:B,MATCH($C2,'Policy Characteristics'!$C:$C,0))),"",INDEX('Policy Characteristics'!B:B,MATCH($C2,'Policy Characteristics'!$C:$C,0))) -> Conventional Pollutant Standards | C2: Percentage Reduction of Separately Regulated Pollutants | D2: LDVs | E2: VOC | F2: Passenger cars, SUVs, Light and Medium Commercial Trucks | G2: VOCs | H2: 300 | I2: Yes | J2: =IF(ISBLANK(INDEX('Policy Characteristics'!D:D,MATCH($C2,'Policy Characteristics'!$C:$C,0))),"",INDEX('Policy Characteristics'!D:D,MATCH($C2,'Policy Characteristics'!$C:$C,0))) -> Conventional Pollutant Standard | K2: =IF(ISBLANK(INDEX('Policy Characteristics'!E:E,MATCH($C2,'Policy Characteristics'!$C:$C,0))),"",INDEX('Policy Characteristics'!E:E,MATCH($C2,'Policy Characteristics'!$C:$C,0))) -> trans reduce regulated pollutants | L2: =IF(ISBLANK(INDEX('Policy Characteristics'!F:F,MATCH($C2,'Policy Characteristics'!$C:$C,0))),"",INDEX('Policy Characteristics'!F:F,MATCH($C2,'Policy Characteristics'!$C:$C,0))) -> 0 | M2: =IF(ISBLANK(INDEX('Policy Characteristics'!G:G,MATCH($C2,'Policy Characteristics'!$C:$C,0))),"",INDEX('Policy Characteristics'!G:G,MATCH($C2,'Policy Characteristics'!$C:$C,0))) -> 1 | N2: =IF(ISBLANK(INDEX('Policy Characteristics'!H:H,MATCH($C2,'Policy Characteristics'!$C:$C,0))),"",INDEX('Policy Characteristics'!H:H,MATCH($C2,'Policy Characteristics'!$C:$C,0))) -> 0.02 | O2: =IF(ISBLANK(INDEX('Policy Characteristics'!I:I,MATCH($C2,'Policy Characteristics'!$C:$C,0))),"",INDEX('Policy Characteristics'!I:I,MATCH($C2,'Policy Characteristics'!$C:$C,0))) -> % reduction in emissions | P2: =IF(ISBLANK(INDEX('Policy Characteristics'!J:J,MATCH($C2,'Policy Characteristics'!$C:$C,0))),"",INDEX('Policy Characteristics'!J:J,MATCH($C2,'Policy Characteristics'!$C:$C,0))) -> **Description:** This policy represents strengthening standards for the selected pollutant(s) emitted by the selected vehicle type(s). Conventional pollutants' most important, harmful impacts are on human health rather than on climate change. // **Guidance for setting values:** In South Korea, the 24-hour national ambient air quality standard (NAAQS) for PM2.5, the most harmful type of particulate for human health, is 35 µg/m^3. | Q2: =IF(ISBLANK(INDEX('Policy Characteristics'!K:K,MATCH($C2,'Policy Characteristics'!$C:$C,0))),"",INDEX('Policy Characteristics'!K:K,MATCH($C2,'Policy Characteristics'!$C:$C,0))) -> transportation-sector-main.html#conv-pol-stds | R2: =IF(ISBLANK(INDEX('Policy Characteristics'!L:L,MATCH($C2,'Policy Characteristics'!$C:$C,0))),"",INDEX('Policy Characteristics'!L:L,MATCH($C2,'Policy Characteristics'!$C:$C,0))) -> conventional-pollutant-standards.html
A3: =IF(ISBLANK(INDEX('Policy Characteristics'!A:A,MATCH($C3,'Policy Characteristics'!$C:$C,0))),"",INDEX('Policy Characteristics'!A:A,MATCH($C3,'Policy Characteristics'!$C:$C,0))) -> Transportation | B3: =IF(ISBLANK(INDEX('Policy Characteristics'!B:B,MATCH($C3,'Policy Characteristics'!$C:$C,0))),"",INDEX('Policy Characteristics'!B:B,MATCH($C3,'Policy Characteristics'!$C:$C,0))) -> Conventional Pollutant Standards | C3: =C$2 -> Percentage Reduction of Separately Regulated Pollutants | D3: LDVs | E3: CO | F3: Passenger cars, SUVs, Light and Medium Commercial Trucks | G3: CO | H3: 301 | I3: Yes | J3: =IF(ISBLANK(INDEX('Policy Characteristics'!D:D,MATCH($C3,'Policy Characteristics'!$C:$C,0))),"",INDEX('Policy Characteristics'!D:D,MATCH($C3,'Policy Characteristics'!$C:$C,0))) -> Conventional Pollutant Standard | K3: =IF(ISBLANK(INDEX('Policy Characteristics'!E:E,MATCH($C3,'Policy Characteristics'!$C:$C,0))),"",INDEX('Policy Characteristics'!E:E,MATCH($C3,'Policy Characteristics'!$C:$C,0))) -> trans reduce regulated pollutants | L3: =IF(ISBLANK(INDEX('Policy Characteristics'!F:F,MATCH($C3,'Policy Characteristics'!$C:$C,0))),"",INDEX('Policy Characteristics'!F:F,MATCH($C3,'Policy Characteristics'!$C:$C,0))) -> 0 | M3: =IF(ISBLANK(INDEX('Policy Characteristics'!G:G,MATCH($C3,'Policy Characteristics'!$C:$C,0))),"",INDEX('Policy Characteristics'!G:G,MATCH($C3,'Policy Characteristics'!$C:$C,0))) -> 1 | N3: =IF(ISBLANK(INDEX('Policy Characteristics'!H:H,MATCH($C3,'Policy Characteristics'!$C:$C,0))),"",INDEX('Policy Characteristics'!H:H,MATCH($C3,'Policy Characteristics'!$C:$C,0))) -> 0.02 | O3: =IF(ISBLANK(INDEX('Policy Characteristics'!I:I,MATCH($C3,'Policy Characteristics'!$C:$C,0))),"",INDEX('Policy Characteristics'!I:I,MATCH($C3,'Policy Characteristics'!$C:$C,0))) -> % reduction in emissions | P3: =IF(ISBLANK(INDEX('Policy Characteristics'!J:J,MATCH($C3,'Policy Characteristics'!$C:$C,0))),"",INDEX('Policy Characteristics'!J:J,MATCH($C3,'Policy Characteristics'!$C:$C,0))) -> **Description:** This policy represents strengthening standards for the selected pollutant(s) emitted by the selected vehicle type(s). Conventional pollutants' most important, harmful impacts are on human health rather than on climate change. // **Guidance for setting values:** In South Korea, the 24-hour national ambient air quality standard (NAAQS) for PM2.5, the most harmful type of particulate for human health, is 35 µg/m^3. | Q3: =IF(ISBLANK(INDEX('Policy Characteristics'!K:K,MATCH($C3,'Policy Characteristics'!$C:$C,0))),"",INDEX('Policy Characteristics'!K:K,MATCH($C3,'Policy Characteristics'!$C:$C,0))) -> transportation-sector-main.html#conv-pol-stds | R3: =IF(ISBLANK(INDEX('Policy Characteristics'!L:L,MATCH($C3,'Policy Characteristics'!$C:$C,0))),"",INDEX('Policy Characteristics'!L:L,MATCH($C3,'Policy Characteristics'!$C:$C,0))) -> conventional-pollutant-standards.html
A4: =IF(ISBLANK(INDEX('Policy Characteristics'!A:A,MATCH($C4,'Policy Characteristics'!$C:$C,0))),"",INDEX('Policy Characteristics'!A:A,MATCH($C4,'Policy Characteristics'!$C:$C,0))) -> Transportation | B4: =IF(ISBLANK(INDEX('Policy Characteristics'!B:B,MATCH($C4,'Policy Characteristics'!$C:$C,0))),"",INDEX('Policy Characteristics'!B:B,MATCH($C4,'Policy Characteristics'!$C:$C,0))) -> Conventional Pollutant Standards | C4: =C$2 -> Percentage Reduction of Separately Regulated Pollutants | D4: LDVs | E4: NOx | F4: Passenger cars, SUVs, Light and Medium Commercial Trucks | G4: NOx | H4: 302 | I4: Yes | J4: =IF(ISBLANK(INDEX('Policy Characteristics'!D:D,MATCH($C4,'Policy Characteristics'!$C:$C,0))),"",INDEX('Policy Characteristics'!D:D,MATCH($C4,'Policy Characteristics'!$C:$C,0))) -> Conventional Pollutant Standard | K4: =IF(ISBLANK(INDEX('Policy Characteristics'!E:E,MATCH($C4,'Policy Characteristics'!$C:$C,0))),"",INDEX('Policy Characteristics'!E:E,MATCH($C4,'Policy Characteristics'!$C:$C,0))) -> trans reduce regulated pollutants | L4: =IF(ISBLANK(INDEX('Policy Characteristics'!F:F,MATCH($C4,'Policy Characteristics'!$C:$C,0))),"",INDEX('Policy Characteristics'!F:F,MATCH($C4,'Policy Characteristics'!$C:$C,0))) -> 0 | M4: =IF(ISBLANK(INDEX('Policy Characteristics'!G:G,MATCH($C4,'Policy Characteristics'!$C:$C,0))),"",INDEX('Policy Characteristics'!G:G,MATCH($C4,'Policy Characteristics'!$C:$C,0))) -> 1 | N4: =IF(ISBLANK(INDEX('Policy Characteristics'!H:H,MATCH($C4,'Policy Characteristics'!$C:$C,0))),"",INDEX('Policy Characteristics'!H:H,MATCH($C4,'Policy Characteristics'!$C:$C,0))) -> 0.02 | O4: =IF(ISBLANK(INDEX('Policy Characteristics'!I:I,MATCH($C4,'Policy Characteristics'!$C:$C,0))),"",INDEX('Policy Characteristics'!I:I,MATCH($C4,'Policy Characteristics'!$C:$C,0))) -> % reduction in emissions | P4: =IF(ISBLANK(INDEX('Policy Characteristics'!J:J,MATCH($C4,'Policy Characteristics'!$C:$C,0))),"",INDEX('Policy Characteristics'!J:J,MATCH($C4,'Policy Characteristics'!$C:$C,0))) -> **Description:** This policy represents strengthening standards for the selected pollutant(s) emitted by the selected vehicle type(s). Conventional pollutants' most important, harmful impacts are on human health rather than on climate change. // **Guidance for setting values:** In South Korea, the 24-hour national ambient air quality standard (NAAQS) for PM2.5, the most harmful type of particulate for human health, is 35 µg/m^3. | Q4: =IF(ISBLANK(INDEX('Policy Characteristics'!K:K,MATCH($C4,'Policy Characteristics'!$C:$C,0))),"",INDEX('Policy Characteristics'!K:K,MATCH($C4,'Policy Characteristics'!$C:$C,0))) -> transportation-sector-main.html#conv-pol-stds | R4: =IF(ISBLANK(INDEX('Policy Characteristics'!L:L,MATCH($C4,'Policy Characteristics'!$C:$C,0))),"",INDEX('Policy Characteristics'!L:L,MATCH($C4,'Policy Characteristics'!$C:$C,0))) -> conventional-pollutant-standards.html
A5: =IF(ISBLANK(INDEX('Policy Characteristics'!A:A,MATCH($C5,'Policy Characteristics'!$C:$C,0))),"",INDEX('Policy Characteristics'!A:A,MATCH($C5,'Policy Characteristics'!$C:$C,0))) -> Transportation | B5: =IF(ISBLANK(INDEX('Policy Characteristics'!B:B,MATCH($C5,'Policy Characteristics'!$C:$C,0))),"",INDEX('Policy Characteristics'!B:B,MATCH($C5,'Policy Characteristics'!$C:$C,0))) -> Conventional Pollutant Standards | C5: =C$2 -> Percentage Reduction of Separately Regulated Pollutants | D5: LDVs | E5: PM10 | F5: Passenger cars, SUVs, Light and Medium Commercial Trucks | G5: PM10 | H5: 303 | I5: Yes | J5: =IF(ISBLANK(INDEX('Policy Characteristics'!D:D,MATCH($C5,'Policy Characteristics'!$C:$C,0))),"",INDEX('Policy Characteristics'!D:D,MATCH($C5,'Policy Characteristics'!$C:$C,0))) -> Conventional Pollutant Standard | K5: =IF(ISBLANK(INDEX('Policy Characteristics'!E:E,MATCH($C5,'Policy Characteristics'!$C:$C,0))),"",INDEX('Policy Characteristics'!E:E,MATCH($C5,'Policy Characteristics'!$C:$C,0))) -> trans reduce regulated pollutants | L5: =IF(ISBLANK(INDEX('Policy Characteristics'!F:F,MATCH($C5,'Policy Characteristics'!$C:$C,0))),"",INDEX('Policy Characteristics'!F:F,MATCH($C5,'Policy Characteristics'!$C:$C,0))) -> 0 | M5: =IF(ISBLANK(INDEX('Policy Characteristics'!G:G,MATCH($C5,'Policy Characteristics'!$C:$C,0))),"",INDEX('Policy Characteristics'!G:G,MATCH($C5,'Policy Characteristics'!$C:$C,0))) -> 1 | N5: =IF(ISBLANK(INDEX('Policy Characteristics'!H:H,MATCH($C5,'Policy Characteristics'!$C:$C,0))),"",INDEX('Policy Characteristics'!H:H,MATCH($C5,'Policy Characteristics'!$C:$C,0))) -> 0.02 | O5: =IF(ISBLANK(INDEX('Policy Characteristics'!I:I,MATCH($C5,'Policy Characteristics'!$C:$C,0))),"",INDEX('Policy Characteristics'!I:I,MATCH($C5,'Policy Characteristics'!$C:$C,0))) -> % reduction in emissions | P5: =IF(ISBLANK(INDEX('Policy Characteristics'!J:J,MATCH($C5,'Policy Characteristics'!$C:$C,0))),"",INDEX('Policy Characteristics'!J:J,MATCH($C5,'Policy Characteristics'!$C:$C,0))) -> **Description:** This policy represents strengthening standards for the selected pollutant(s) emitted by the selected vehicle type(s). Conventional pollutants' most important, harmful impacts are on human health rather than on climate change. // **Guidance for setting values:** In South Korea, the 24-hour national ambient air quality standard (NAAQS) for PM2.5, the most harmful type of particulate for human health, is 35 µg/m^3. | Q5: =IF(ISBLANK(INDEX('Policy Characteristics'!K:K,MATCH($C5,'Policy Characteristics'!$C:$C,0))),"",INDEX('Policy Characteristics'!K:K,MATCH($C5,'Policy Characteristics'!$C:$C,0))) -> transportation-sector-main.html#conv-pol-stds | R5: =IF(ISBLANK(INDEX('Policy Characteristics'!L:L,MATCH($C5,'Policy Characteristics'!$C:$C,0))),"",INDEX('Policy Characteristics'!L:L,MATCH($C5,'Policy Characteristics'!$C:$C,0))) -> conventional-pollutant-standards.html
A6: =IF(ISBLANK(INDEX('Policy Characteristics'!A:A,MATCH($C6,'Policy Characteristics'!$C:$C,0))),"",INDEX('Policy Characteristics'!A:A,MATCH($C6,'Policy Characteristics'!$C:$C,0))) -> Transportation | B6: =IF(ISBLANK(INDEX('Policy Characteristics'!B:B,MATCH($C6,'Policy Characteristics'!$C:$C,0))),"",INDEX('Policy Characteristics'!B:B,MATCH($C6,'Policy Characteristics'!$C:$C,0))) -> Conventional Pollutant Standards | C6: =C$2 -> Percentage Reduction of Separately Regulated Pollutants | D6: LDVs | E6: PM25 | F6: Passenger cars, SUVs, Light and Medium Commercial Trucks | G6: PM2.5 | H6: 304 | I6: Yes | J6: =IF(ISBLANK(INDEX('Policy Characteristics'!D:D,MATCH($C6,'Policy Characteristics'!$C:$C,0))),"",INDEX('Policy Characteristics'!D:D,MATCH($C6,'Policy Characteristics'!$C:$C,0))) -> Conventional Pollutant Standard | K6: =IF(ISBLANK(INDEX('Policy Characteristics'!E:E,MATCH($C6,'Policy Characteristics'!$C:$C,0))),"",INDEX('Policy Characteristics'!E:E,MATCH($C6,'Policy Characteristics'!$C:$C,0))) -> trans reduce regulated pollutants | L6: =IF(ISBLANK(INDEX('Policy Characteristics'!F:F,MATCH($C6,'Policy Characteristics'!$C:$C,0))),"",INDEX('Policy Characteristics'!F:F,MATCH($C6,'Policy Characteristics'!$C:$C,0))) -> 0 | M6: =IF(ISBLANK(INDEX('Policy Characteristics'!G:G,MATCH($C6,'Policy Characteristics'!$C:$C,0))),"",INDEX('Policy Characteristics'!G:G,MATCH($C6,'Policy Characteristics'!$C:$C,0))) -> 1 | N6: =IF(ISBLANK(INDEX('Policy Characteristics'!H:H,MATCH($C6,'Policy Characteristics'!$C:$C,0))),"",INDEX('Policy Characteristics'!H:H,MATCH($C6,'Policy Characteristics'!$C:$C,0))) -> 0.02 | O6: =IF(ISBLANK(INDEX('Policy Characteristics'!I:I,MATCH($C6,'Policy Characteristics'!$C:$C,0))),"",INDEX('Policy Characteristics'!I:I,MATCH($C6,'Policy Characteristics'!$C:$C,0))) -> % reduction in emissions | P6: =IF(ISBLANK(INDEX('Policy Characteristics'!J:J,MATCH($C6,'Policy Characteristics'!$C:$C,0))),"",INDEX('Policy Characteristics'!J:J,MATCH($C6,'Policy Characteristics'!$C:$C,0))) -> **Description:** This policy represents strengthening standards for the selected pollutant(s) emitted by the selected vehicle type(s). Conventional pollutants' most important, harmful impacts are on human health rather than on climate change. // **Guidance for setting values:** In South Korea, the 24-hour national ambient air quality standard (NAAQS) for PM2.5, the most harmful type of particulate for human health, is 35 µg/m^3. | Q6: =IF(ISBLANK(INDEX('Policy Characteristics'!K:K,MATCH($C6,'Policy Characteristics'!$C:$C,0))),"",INDEX('Policy Characteristics'!K:K,MATCH($C6,'Policy Characteristics'!$C:$C,0))) -> transportation-sector-main.html#conv-pol-stds | R6: =IF(ISBLANK(INDEX('Policy Characteristics'!L:L,MATCH($C6,'Policy Characteristics'!$C:$C,0))),"",INDEX('Policy Characteristics'!L:L,MATCH($C6,'Policy Characteristics'!$C:$C,0))) -> conventional-pollutant-standards.html
A7: =IF(ISBLANK(INDEX('Policy Characteristics'!A:A,MATCH($C7,'Policy Characteristics'!$C:$C,0))),"",INDEX('Policy Characteristics'!A:A,MATCH($C7,'Policy Characteristics'!$C:$C,0))) -> Transportation | B7: =IF(ISBLANK(INDEX('Policy Characteristics'!B:B,MATCH($C7,'Policy Characteristics'!$C:$C,0))),"",INDEX('Policy Characteristics'!B:B,MATCH($C7,'Policy Characteristics'!$C:$C,0))) -> Conventional Pollutant Standards | C7: =C$2 -> Percentage Reduction of Separately Regulated Pollutants | D7: LDVs | E7: SOx | F7: Passenger cars, SUVs, Light and Medium Commercial Trucks | G7: SOx | H7: 305 | I7: Yes | J7: =IF(ISBLANK(INDEX('Policy Characteristics'!D:D,MATCH($C7,'Policy Characteristics'!$C:$C,0))),"",INDEX('Policy Characteristics'!D:D,MATCH($C7,'Policy Characteristics'!$C:$C,0))) -> Conventional Pollutant Standard | K7: =IF(ISBLANK(INDEX('Policy Characteristics'!E:E,MATCH($C7,'Policy Characteristics'!$C:$C,0))),"",INDEX('Policy Characteristics'!E:E,MATCH($C7,'Policy Characteristics'!$C:$C,0))) -> trans reduce regulated pollutants | L7: =IF(ISBLANK(INDEX('Policy Characteristics'!F:F,MATCH($C7,'Policy Characteristics'!$C:$C,0))),"",INDEX('Policy Characteristics'!F:F,MATCH($C7,'Policy Characteristics'!$C:$C,0))) -> 0 | M7: =IF(ISBLANK(INDEX('Policy Characteristics'!G:G,MATCH($C7,'Policy Characteristics'!$C:$C,0))),"",INDEX('Policy Characteristics'!G:G,MATCH($C7,'Policy Characteristics'!$C:$C,0))) -> 1 | N7: =IF(ISBLANK(INDEX('Policy Characteristics'!H:H,MATCH($C7,'Policy Characteristics'!$C:$C,0))),"",INDEX('Policy Characteristics'!H:H,MATCH($C7,'Policy Characteristics'!$C:$C,0))) -> 0.02 | O7: =IF(ISBLANK(INDEX('Policy Characteristics'!I:I,MATCH($C7,'Policy Characteristics'!$C:$C,0))),"",INDEX('Policy Characteristics'!I:I,MATCH($C7,'Policy Characteristics'!$C:$C,0))) -> % reduction in emissions | P7: =IF(ISBLANK(INDEX('Policy Characteristics'!J:J,MATCH($C7,'Policy Characteristics'!$C:$C,0))),"",INDEX('Policy Characteristics'!J:J,MATCH($C7,'Policy Characteristics'!$C:$C,0))) -> **Description:** This policy represents strengthening standards for the selected pollutant(s) emitted by the selected vehicle type(s). Conventional pollutants' most important, harmful impacts are on human health rather than on climate change. // **Guidance for setting values:** In South Korea, the 24-hour national ambient air quality standard (NAAQS) for PM2.5, the most harmful type of particulate for human health, is 35 µg/m^3. | Q7: =IF(ISBLANK(INDEX('Policy Characteristics'!K:K,MATCH($C7,'Policy Characteristics'!$C:$C,0))),"",INDEX('Policy Characteristics'!K:K,MATCH($C7,'Policy Characteristics'!$C:$C,0))) -> transportation-sector-main.html#conv-pol-stds | R7: =IF(ISBLANK(INDEX('Policy Characteristics'!L:L,MATCH($C7,'Policy Characteristics'!$C:$C,0))),"",INDEX('Policy Characteristics'!L:L,MATCH($C7,'Policy Characteristics'!$C:$C,0))) -> conventional-pollutant-standards.html
A8: =IF(ISBLANK(INDEX('Policy Characteristics'!A:A,MATCH($C8,'Policy Characteristics'!$C:$C,0))),"",INDEX('Policy Characteristics'!A:A,MATCH($C8,'Policy Characteristics'!$C:$C,0))) -> Transportation | B8: =IF(ISBLANK(INDEX('Policy Characteristics'!B:B,MATCH($C8,'Policy Characteristics'!$C:$C,0))),"",INDEX('Policy Characteristics'!B:B,MATCH($C8,'Policy Characteristics'!$C:$C,0))) -> Conventional Pollutant Standards | C8: =C$2 -> Percentage Reduction of Separately Regulated Pollutants | D8: LDVs | E8: BC | F8: Passenger cars, SUVs, Light and Medium Commercial Trucks | G8: BC | H8: 306 | I8: Yes | J8: =IF(ISBLANK(INDEX('Policy Characteristics'!D:D,MATCH($C8,'Policy Characteristics'!$C:$C,0))),"",INDEX('Policy Characteristics'!D:D,MATCH($C8,'Policy Characteristics'!$C:$C,0))) -> Conventional Pollutant Standard | K8: =IF(ISBLANK(INDEX('Policy Characteristics'!E:E,MATCH($C8,'Policy Characteristics'!$C:$C,0))),"",INDEX('Policy Characteristics'!E:E,MATCH($C8,'Policy Characteristics'!$C:$C,0))) -> trans reduce regulated pollutants | L8: =IF(ISBLANK(INDEX('Policy Characteristics'!F:F,MATCH($C8,'Policy Characteristics'!$C:$C,0))),"",INDEX('Policy Characteristics'!F:F,MATCH($C8,'Policy Characteristics'!$C:$C,0))) -> 0 | M8: =IF(ISBLANK(INDEX('Policy Characteristics'!G:G,MATCH($C8,'Policy Characteristics'!$C:$C,0))),"",INDEX('Policy Characteristics'!G:G,MATCH($C8,'Policy Characteristics'!$C:$C,0))) -> 1 | N8: =IF(ISBLANK(INDEX('Policy Characteristics'!H:H,MATCH($C8,'Policy Characteristics'!$C:$C,0))),"",INDEX('Policy Characteristics'!H:H,MATCH($C8,'Policy Characteristics'!$C:$C,0))) -> 0.02 | O8: =IF(ISBLANK(INDEX('Policy Characteristics'!I:I,MATCH($C8,'Policy Characteristics'!$C:$C,0))),"",INDEX('Policy Characteristics'!I:I,MATCH($C8,'Policy Characteristics'!$C:$C,0))) -> % reduction in emissions | P8: =IF(ISBLANK(INDEX('Policy Characteristics'!J:J,MATCH($C8,'Policy Characteristics'!$C:$C,0))),"",INDEX('Policy Characteristics'!J:J,MATCH($C8,'Policy Characteristics'!$C:$C,0))) -> **Description:** This policy represents strengthening standards for the selected pollutant(s) emitted by the selected vehicle type(s). Conventional pollutants' most important, harmful impacts are on human health rather than on climate change. // **Guidance for setting values:** In South Korea, the 24-hour national ambient air quality standard (NAAQS) for PM2.5, the most harmful type of particulate for human health, is 35 µg/m^3. | Q8: =IF(ISBLANK(INDEX('Policy Characteristics'!K:K,MATCH($C8,'Policy Characteristics'!$C:$C,0))),"",INDEX('Policy Characteristics'!K:K,MATCH($C8,'Policy Characteristics'!$C:$C,0))) -> transportation-sector-main.html#conv-pol-stds | R8: =IF(ISBLANK(INDEX('Policy Characteristics'!L:L,MATCH($C8,'Policy Characteristics'!$C:$C,0))),"",INDEX('Policy Characteristics'!L:L,MATCH($C8,'Policy Characteristics'!$C:$C,0))) -> conventional-pollutant-standards.html
A9: =IF(ISBLANK(INDEX('Policy Characteristics'!A:A,MATCH($C9,'Policy Characteristics'!$C:$C,0))),"",INDEX('Policy Characteristics'!A:A,MATCH($C9,'Policy Characteristics'!$C:$C,0))) -> Transportation | B9: =IF(ISBLANK(INDEX('Policy Characteristics'!B:B,MATCH($C9,'Policy Characteristics'!$C:$C,0))),"",INDEX('Policy Characteristics'!B:B,MATCH($C9,'Policy Characteristics'!$C:$C,0))) -> Conventional Pollutant Standards | C9: =C$2 -> Percentage Reduction of Separately Regulated Pollutants | D9: LDVs | E9: OC | F9: Passenger cars, SUVs, Light and Medium Commercial Trucks | G9: OC | H9: 307 | I9: Yes | J9: =IF(ISBLANK(INDEX('Policy Characteristics'!D:D,MATCH($C9,'Policy Characteristics'!$C:$C,0))),"",INDEX('Policy Characteristics'!D:D,MATCH($C9,'Policy Characteristics'!$C:$C,0))) -> Conventional Pollutant Standard | K9: =IF(ISBLANK(INDEX('Policy Characteristics'!E:E,MATCH($C9,'Policy Characteristics'!$C:$C,0))),"",INDEX('Policy Characteristics'!E:E,MATCH($C9,'Policy Characteristics'!$C:$C,0))) -> trans reduce regulated pollutants | L9: =IF(ISBLANK(INDEX('Policy Characteristics'!F:F,MATCH($C9,'Policy Characteristics'!$C:$C,0))),"",INDEX('Policy Characteristics'!F:F,MATCH($C9,'Policy Characteristics'!$C:$C,0))) -> 0 | M9: =IF(ISBLANK(INDEX('Policy Characteristics'!G:G,MATCH($C9,'Policy Characteristics'!$C:$C,0))),"",INDEX('Policy Characteristics'!G:G,MATCH($C9,'Policy Characteristics'!$C:$C,0))) -> 1 | N9: =IF(ISBLANK(INDEX('Policy Characteristics'!H:H,MATCH($C9,'Policy Characteristics'!$C:$C,0))),"",INDEX('Policy Characteristics'!H:H,MATCH($C9,'Policy Characteristics'!$C:$C,0))) -> 0.02 | O9: =IF(ISBLANK(INDEX('Policy Characteristics'!I:I,MATCH($C9,'Policy Characteristics'!$C:$C,0))),"",INDEX('Policy Characteristics'!I:I,MATCH($C9,'Policy Characteristics'!$C:$C,0))) -> % reduction in emissions | P9: =IF(ISBLANK(INDEX('Policy Characteristics'!J:J,MATCH($C9,'Policy Characteristics'!$C:$C,0))),"",INDEX('Policy Characteristics'!J:J,MATCH($C9,'Policy Characteristics'!$C:$C,0))) -> **Description:** This policy represents strengthening standards for the selected pollutant(s) emitted by the selected vehicle type(s). Conventional pollutants' most important, harmful impacts are on human health rather than on climate change. // **Guidance for setting values:** In South Korea, the 24-hour national ambient air quality standard (NAAQS) for PM2.5, the most harmful type of particulate for human health, is 35 µg/m^3. | Q9: =IF(ISBLANK(INDEX('Policy Characteristics'!K:K,MATCH($C9,'Policy Characteristics'!$C:$C,0))),"",INDEX('Policy Characteristics'!K:K,MATCH($C9,'Policy Characteristics'!$C:$C,0))) -> transportation-sector-main.html#conv-pol-stds | R9: =IF(ISBLANK(INDEX('Policy Characteristics'!L:L,MATCH($C9,'Policy Characteristics'!$C:$C,0))),"",INDEX('Policy Characteristics'!L:L,MATCH($C9,'Policy Characteristics'!$C:$C,0))) -> conventional-pollutant-standards.html
A10: =IF(ISBLANK(INDEX('Policy Characteristics'!A:A,MATCH($C10,'Policy Characteristics'!$C:$C,0))),"",INDEX('Policy Characteristics'!A:A,MATCH($C10,'Policy Characteristics'!$C:$C,0))) -> Transportation | B10: =IF(ISBLANK(INDEX('Policy Characteristics'!B:B,MATCH($C10,'Policy Characteristics'!$C:$C,0))),"",INDEX('Policy Characteristics'!B:B,MATCH($C10,'Policy Characteristics'!$C:$C,0))) -> Conventional Pollutant Standards | C10: =C$2 -> Percentage Reduction of Separately Regulated Pollutants | D10: LDVs | E10: CH4 | F10: Passenger cars, SUVs, Light and Medium Commercial Trucks | G10: CH4 | H10: 308 | I10: No | J10: =IF(ISBLANK(INDEX('Policy Characteristics'!D:D,MATCH($C10,'Policy Characteristics'!$C:$C,0))),"",INDEX('Policy Characteristics'!D:D,MATCH($C10,'Policy Characteristics'!$C:$C,0))) -> Conventional Pollutant Standard | K10: =IF(ISBLANK(INDEX('Policy Characteristics'!E:E,MATCH($C10,'Policy Characteristics'!$C:$C,0))),"",INDEX('Policy Characteristics'!E:E,MATCH($C10,'Policy Characteristics'!$C:$C,0))) -> trans reduce regulated pollutants | L10: =IF(ISBLANK(INDEX('Policy Characteristics'!F:F,MATCH($C10,'Policy Characteristics'!$C:$C,0))),"",INDEX('Policy Characteristics'!F:F,MATCH($C10,'Policy Characteristics'!$C:$C,0))) -> 0 | M10: =IF(ISBLANK(INDEX('Policy Characteristics'!G:G,MATCH($C10,'Policy Characteristics'!$C:$C,0))),"",INDEX('Policy Characteristics'!G:G,MATCH($C10,'Policy Characteristics'!$C:$C,0))) -> 1 | N10: =IF(ISBLANK(INDEX('Policy Characteristics'!H:H,MATCH($C10,'Policy Characteristics'!$C:$C,0))),"",INDEX('Policy Characteristics'!H:H,MATCH($C10,'Policy Characteristics'!$C:$C,0))) -> 0.02 | O10: =IF(ISBLANK(INDEX('Policy Characteristics'!I:I,MATCH($C10,'Policy Characteristics'!$C:$C,0))),"",INDEX('Policy Characteristics'!I:I,MATCH($C10,'Policy Characteristics'!$C:$C,0))) -> % reduction in emissions | P10: =IF(ISBLANK(INDEX('Policy Characteristics'!J:J,MATCH($C10,'Policy Characteristics'!$C:$C,0))),"",INDEX('Policy Characteristics'!J:J,MATCH($C10,'Policy Characteristics'!$C:$C,0))) -> **Description:** This policy represents strengthening standards for the selected pollutant(s) emitted by the selected vehicle type(s). Conventional pollutants' most important, harmful impacts are on human health rather than on climate change. // **Guidance for setting values:** In South Korea, the 24-hour national ambient air quality standard (NAAQS) for PM2.5, the most harmful type of particulate for human health, is 35 µg/m^3. | Q10: =IF(ISBLANK(INDEX('Policy Characteristics'!K:K,MATCH($C10,'Policy Characteristics'!$C:$C,0))),"",INDEX('Policy Characteristics'!K:K,MATCH($C10,'Policy Characteristics'!$C:$C,0))) -> transportation-sector-main.html#conv-pol-stds | R10: =IF(ISBLANK(INDEX('Policy Characteristics'!L:L,MATCH($C10,'Policy Characteristics'!$C:$C,0))),"",INDEX('Policy Characteristics'!L:L,MATCH($C10,'Policy Characteristics'!$C:$C,0))) -> conventional-pollutant-standards.html
A11: =IF(ISBLANK(INDEX('Policy Characteristics'!A:A,MATCH($C11,'Policy Characteristics'!$C:$C,0))),"",INDEX('Policy Characteristics'!A:A,MATCH($C11,'Policy Characteristics'!$C:$C,0))) -> Transportation | B11: =IF(ISBLANK(INDEX('Policy Characteristics'!B:B,MATCH($C11,'Policy Characteristics'!$C:$C,0))),"",INDEX('Policy Characteristics'!B:B,MATCH($C11,'Policy Characteristics'!$C:$C,0))) -> Conventional Pollutant Standards | C11: =C$2 -> Percentage Reduction of Separately Regulated Pollutants | D11: LDVs | E11: N2O | F11: Passenger cars, SUVs, Light and Medium Commercial Trucks | G11: N2O | H11: 309 | I11: No | J11: =IF(ISBLANK(INDEX('Policy Characteristics'!D:D,MATCH($C11,'Policy Characteristics'!$C:$C,0))),"",INDEX('Policy Characteristics'!D:D,MATCH($C11,'Policy Characteristics'!$C:$C,0))) -> Conventional Pollutant Standard | K11: =IF(ISBLANK(INDEX('Policy Characteristics'!E:E,MATCH($C11,'Policy Characteristics'!$C:$C,0))),"",INDEX('Policy Characteristics'!E:E,MATCH($C11,'Policy Characteristics'!$C:$C,0))) -> trans reduce regulated pollutants | L11: =IF(ISBLANK(INDEX('Policy Characteristics'!F:F,MATCH($C11,'Policy Characteristics'!$C:$C,0))),"",INDEX('Policy Characteristics'!F:F,MATCH($C11,'Policy Characteristics'!$C:$C,0))) -> 0 | M11: =IF(ISBLANK(INDEX('Policy Characteristics'!G:G,MATCH($C11,'Policy Characteristics'!$C:$C,0))),"",INDEX('Policy Characteristics'!G:G,MATCH($C11,'Policy Characteristics'!$C:$C,0))) -> 1 | N11: =IF(ISBLANK(INDEX('Policy Characteristics'!H:H,MATCH($C11,'Policy Characteristics'!$C:$C,0))),"",INDEX('Policy Characteristics'!H:H,MATCH($C11,'Policy Characteristics'!$C:$C,0))) -> 0.02 | O11: =IF(ISBLANK(INDEX('Policy Characteristics'!I:I,MATCH($C11,'Policy Characteristics'!$C:$C,0))),"",INDEX('Policy Characteristics'!I:I,MATCH($C11,'Policy Characteristics'!$C:$C,0))) -> % reduction in emissions | P11: =IF(ISBLANK(INDEX('Policy Characteristics'!J:J,MATCH($C11,'Policy Characteristics'!$C:$C,0))),"",INDEX('Policy Characteristics'!J:J,MATCH($C11,'Policy Characteristics'!$C:$C,0))) -> **Description:** This policy represents strengthening standards for the selected pollutant(s) emitted by the selected vehicle type(s). Conventional pollutants' most important, harmful impacts are on human health rather than on climate change. // **Guidance for setting values:** In South Korea, the 24-hour national ambient air quality standard (NAAQS) for PM2.5, the most harmful type of particulate for human health, is 35 µg/m^3. | Q11: =IF(ISBLANK(INDEX('Policy Characteristics'!K:K,MATCH($C11,'Policy Characteristics'!$C:$C,0))),"",INDEX('Policy Characteristics'!K:K,MATCH($C11,'Policy Characteristics'!$C:$C,0))) -> transportation-sector-main.html#conv-pol-stds | R11: =IF(ISBLANK(INDEX('Policy Characteristics'!L:L,MATCH($C11,'Policy Characteristics'!$C:$C,0))),"",INDEX('Policy Characteristics'!L:L,MATCH($C11,'Policy Characteristics'!$C:$C,0))) -> conventional-pollutant-standards.html
A12: =IF(ISBLANK(INDEX('Policy Characteristics'!A:A,MATCH($C12,'Policy Characteristics'!$C:$C,0))),"",INDEX('Policy Characteristics'!A:A,MATCH($C12,'Policy Characteristics'!$C:$C,0))) -> Transportation | B12: =IF(ISBLANK(INDEX('Policy Characteristics'!B:B,MATCH($C12,'Policy Characteristics'!$C:$C,0))),"",INDEX('Policy Characteristics'!B:B,MATCH($C12,'Policy Characteristics'!$C:$C,0))) -> Conventional Pollutant Standards | C12: =C$2 -> Percentage Reduction of Separately Regulated Pollutants | D12: HDVs | E12: VOC | F12: Buses and Heavy Duty Trucks | G12: VOCs | H12: 310 | I12: Yes | J12: =IF(ISBLANK(INDEX('Policy Characteristics'!D:D,MATCH($C12,'Policy Characteristics'!$C:$C,0))),"",INDEX('Policy Characteristics'!D:D,MATCH($C12,'Policy Characteristics'!$C:$C,0))) -> Conventional Pollutant Standard | K12: =IF(ISBLANK(INDEX('Policy Characteristics'!E:E,MATCH($C12,'Policy Characteristics'!$C:$C,0))),"",INDEX('Policy Characteristics'!E:E,MATCH($C12,'Policy Characteristics'!$C:$C,0))) -> trans reduce regulated pollutants | L12: =IF(ISBLANK(INDEX('Policy Characteristics'!F:F,MATCH($C12,'Policy Characteristics'!$C:$C,0))),"",INDEX('Policy Characteristics'!F:F,MATCH($C12,'Policy Characteristics'!$C:$C,0))) -> 0 | M12: =IF(ISBLANK(INDEX('Policy Characteristics'!G:G,MATCH($C12,'Policy Characteristics'!$C:$C,0))),"",INDEX('Policy Characteristics'!G:G,MATCH($C12,'Policy Characteristics'!$C:$C,0))) -> 1 | N12: =IF(ISBLANK(INDEX('Policy Characteristics'!H:H,MATCH($C12,'Policy Characteristics'!$C:$C,0))),"",INDEX('Policy Characteristics'!H:H,MATCH($C12,'Policy Characteristics'!$C:$C,0))) -> 0.02 | O12: =IF(ISBLANK(INDEX('Policy Characteristics'!I:I,MATCH($C12,'Policy Characteristics'!$C:$C,0))),"",INDEX('Policy Characteristics'!I:I,MATCH($C12,'Policy Characteristics'!$C:$C,0))) -> % reduction in emissions | P12: =IF(ISBLANK(INDEX('Policy Characteristics'!J:J,MATCH($C12,'Policy Characteristics'!$C:$C,0))),"",INDEX('Policy Characteristics'!J:J,MATCH($C12,'Policy Characteristics'!$C:$C,0))) -> **Description:** This policy represents strengthening standards for the selected pollutant(s) emitted by the selected vehicle type(s). Conventional pollutants' most important, harmful impacts are on human health rather than on climate change. // **Guidance for setting values:** In South Korea, the 24-hour national ambient air quality standard (NAAQS) for PM2.5, the most harmful type of particulate for human health, is 35 µg/m^3. | Q12: =IF(ISBLANK(INDEX('Policy Characteristics'!K:K,MATCH($C12,'Policy Characteristics'!$C:$C,0))),"",INDEX('Policy Characteristics'!K:K,MATCH($C12,'Policy Characteristics'!$C:$C,0))) -> transportation-sector-main.html#conv-pol-stds | R12: =IF(ISBLANK(INDEX('Policy Characteristics'!L:L,MATCH($C12,'Policy Characteristics'!$C:$C,0))),"",INDEX('Policy Characteristics'!L:L,MATCH($C12,'Policy Characteristics'!$C:$C,0))) -> conventional-pollutant-standards.html
A13: =IF(ISBLANK(INDEX('Policy Characteristics'!A:A,MATCH($C13,'Policy Characteristics'!$C:$C,0))),"",INDEX('Policy Characteristics'!A:A,MATCH($C13,'Policy Characteristics'!$C:$C,0))) -> Transportation | B13: =IF(ISBLANK(INDEX('Policy Characteristics'!B:B,MATCH($C13,'Policy Characteristics'!$C:$C,0))),"",INDEX('Policy Characteristics'!B:B,MATCH($C13,'Policy Characteristics'!$C:$C,0))) -> Conventional Pollutant Standards | C13: =C$2 -> Percentage Reduction of Separately Regulated Pollutants | D13: HDVs | E13: CO | F13: Buses and Heavy Duty Trucks | G13: CO | H13: 311 | I13: Yes | J13: =IF(ISBLANK(INDEX('Policy Characteristics'!D:D,MATCH($C13,'Policy Characteristics'!$C:$C,0))),"",INDEX('Policy Characteristics'!D:D,MATCH($C13,'Policy Characteristics'!$C:$C,0))) -> Conventional Pollutant Standard | K13: =IF(ISBLANK(INDEX('Policy Characteristics'!E:E,MATCH($C13,'Policy Characteristics'!$C:$C,0))),"",INDEX('Policy Characteristics'!E:E,MATCH($C13,'Policy Characteristics'!$C:$C,0))) -> trans reduce regulated pollutants | L13: =IF(ISBLANK(INDEX('Policy Characteristics'!F:F,MATCH($C13,'Policy Characteristics'!$C:$C,0))),"",INDEX('Policy Characteristics'!F:F,MATCH($C13,'Policy Characteristics'!$C:$C,0))) -> 0 | M13: =IF(ISBLANK(INDEX('Policy Characteristics'!G:G,MATCH($C13,'Policy Characteristics'!$C:$C,0))),"",INDEX('Policy Characteristics'!G:G,MATCH($C13,'Policy Characteristics'!$C:$C,0))) -> 1 | N13: =IF(ISBLANK(INDEX('Policy Characteristics'!H:H,MATCH($C13,'Policy Characteristics'!$C:$C,0))),"",INDEX('Policy Characteristics'!H:H,MATCH($C13,'Policy Characteristics'!$C:$C,0))) -> 0.02 | O13: =IF(ISBLANK(INDEX('Policy Characteristics'!I:I,MATCH($C13,'Policy Characteristics'!$C:$C,0))),"",INDEX('Policy Characteristics'!I:I,MATCH($C13,'Policy Characteristics'!$C:$C,0))) -> % reduction in emissions | P13: =IF(ISBLANK(INDEX('Policy Characteristics'!J:J,MATCH($C13,'Policy Characteristics'!$C:$C,0))),"",INDEX('Policy Characteristics'!J:J,MATCH($C13,'Policy Characteristics'!$C:$C,0))) -> **Description:** This policy represents strengthening standards for the selected pollutant(s) emitted by the selected vehicle type(s). Conventional pollutants' most important, harmful impacts are on human health rather than on climate change. // **Guidance for setting values:** In South Korea, the 24-hour national ambient air quality standard (NAAQS) for PM2.5, the most harmful type of particulate for human health, is 35 µg/m^3. | Q13: =IF(ISBLANK(INDEX('Policy Characteristics'!K:K,MATCH($C13,'Policy Characteristics'!$C:$C,0))),"",INDEX('Policy Characteristics'!K:K,MATCH($C13,'Policy Characteristics'!$C:$C,0))) -> transportation-sector-main.html#conv-pol-stds | R13: =IF(ISBLANK(INDEX('Policy Characteristics'!L:L,MATCH($C13,'Policy Characteristics'!$C:$C,0))),"",INDEX('Policy Characteristics'!L:L,MATCH($C13,'Policy Characteristics'!$C:$C,0))) -> conventional-pollutant-standards.html
A14: =IF(ISBLANK(INDEX('Policy Characteristics'!A:A,MATCH($C14,'Policy Characteristics'!$C:$C,0))),"",INDEX('Policy Characteristics'!A:A,MATCH($C14,'Policy Characteristics'!$C:$C,0))) -> Transportation | B14: =IF(ISBLANK(INDEX('Policy Characteristics'!B:B,MATCH($C14,'Policy Characteristics'!$C:$C,0))),"",INDEX('Policy Characteristics'!B:B,MATCH($C14,'Policy Characteristics'!$C:$C,0))) -> Conventional Pollutant Standards | C14: =C$2 -> Percentage Reduction of Separately Regulated Pollutants | D14: HDVs | E14: NOx | F14: Buses and Heavy Duty Trucks | G14: NOx | H14: 312 | I14: Yes | J14: =IF(ISBLANK(INDEX('Policy Characteristics'!D:D,MATCH($C14,'Policy Characteristics'!$C:$C,0))),"",INDEX('Policy Characteristics'!D:D,MATCH($C14,'Policy Characteristics'!$C:$C,0))) -> Conventional Pollutant Standard | K14: =IF(ISBLANK(INDEX('Policy Characteristics'!E:E,MATCH($C14,'Policy Characteristics'!$C:$C,0))),"",INDEX('Policy Characteristics'!E:E,MATCH($C14,'Policy Characteristics'!$C:$C,0))) -> trans reduce regulated pollutants | L14: =IF(ISBLANK(INDEX('Policy Characteristics'!F:F,MATCH($C14,'Policy Characteristics'!$C:$C,0))),"",INDEX('Policy Characteristics'!F:F,MATCH($C14,'Policy Characteristics'!$C:$C,0))) -> 0 | M14: =IF(ISBLANK(INDEX('Policy Characteristics'!G:G,MATCH($C14,'Policy Characteristics'!$C:$C,0))),"",INDEX('Policy Characteristics'!G:G,MATCH($C14,'Policy Characteristics'!$C:$C,0))) -> 1 | N14: =IF(ISBLANK(INDEX('Policy Characteristics'!H:H,MATCH($C14,'Policy Characteristics'!$C:$C,0))),"",INDEX('Policy Characteristics'!H:H,MATCH($C14,'Policy Characteristics'!$C:$C,0))) -> 0.02 | O14: =IF(ISBLANK(INDEX('Policy Characteristics'!I:I,MATCH($C14,'Policy Characteristics'!$C:$C,0))),"",INDEX('Policy Characteristics'!I:I,MATCH($C14,'Policy Characteristics'!$C:$C,0))) -> % reduction in emissions | P14: =IF(ISBLANK(INDEX('Policy Characteristics'!J:J,MATCH($C14,'Policy Characteristics'!$C:$C,0))),"",INDEX('Policy Characteristics'!J:J,MATCH($C14,'Policy Characteristics'!$C:$C,0))) -> **Description:** This policy represents strengthening standards for the selected pollutant(s) emitted by the selected vehicle type(s). Conventional pollutants' most important, harmful impacts are on human health rather than on climate change. // **Guidance for setting values:** In South Korea, the 24-hour national ambient air quality standard (NAAQS) for PM2.5, the most harmful type of particulate for human health, is 35 µg/m^3. | Q14: =IF(ISBLANK(INDEX('Policy Characteristics'!K:K,MATCH($C14,'Policy Characteristics'!$C:$C,0))),"",INDEX('Policy Characteristics'!K:K,MATCH($C14,'Policy Characteristics'!$C:$C,0))) -> transportation-sector-main.html#conv-pol-stds | R14: =IF(ISBLANK(INDEX('Policy Characteristics'!L:L,MATCH($C14,'Policy Characteristics'!$C:$C,0))),"",INDEX('Policy Characteristics'!L:L,MATCH($C14,'Policy Characteristics'!$C:$C,0))) -> conventional-pollutant-standards.html
... A61: =IF(ISBLANK(INDEX('Policy Characteristics'!A:A,MATCH($C61,'Policy Characteristics'!$C:$C,0))),"",INDEX('Policy Characteristics'!A:A,MATCH($C61,'Policy Characteristics'!$C:$C,0))) -> Transportation | B61: =IF(ISBLANK(INDEX('Policy Characteristics'!B:B,MATCH($C61,'Policy Characteristics'!$C:$C,0))),"",INDEX('Policy Characteristics'!B:B,MATCH($C61,'Policy Characteristics'!$C:$C,0))) -> Conventional Pollutant Standards | C61: =C$2 -> Percentage Reduction of Separately Regulated Pollutants | D61: motorbikes | E61: N2O | F61: Passenger motorbikes | G61: N2O | H61: 359 | I61: No | J61: =IF(ISBLANK(INDEX('Policy Characteristics'!D:D,MATCH($C61,'Policy Characteristics'!$C:$C,0))),"",INDEX('Policy Characteristics'!D:D,MATCH($C61,'Policy Characteristics'!$C:$C,0))) -> Conventional Pollutant Standard | K61: =IF(ISBLANK(INDEX('Policy Characteristics'!E:E,MATCH($C61,'Policy Characteristics'!$C:$C,0))),"",INDEX('Policy Characteristics'!E:E,MATCH($C61,'Policy Characteristics'!$C:$C,0))) -> trans reduce regulated pollutants | L61: =IF(ISBLANK(INDEX('Policy Characteristics'!F:F,MATCH($C61,'Policy Characteristics'!$C:$C,0))),"",INDEX('Policy Characteristics'!F:F,MATCH($C61,'Policy Characteristics'!$C:$C,0))) -> 0 | M61: =IF(ISBLANK(INDEX('Policy Characteristics'!G:G,MATCH($C61,'Policy Characteristics'!$C:$C,0))),"",INDEX('Policy Characteristics'!G:G,MATCH($C61,'Policy Characteristics'!$C:$C,0))) -> 1 | N61: =IF(ISBLANK(INDEX('Policy Characteristics'!H:H,MATCH($C61,'Policy Characteristics'!$C:$C,0))),"",INDEX('Policy Characteristics'!H:H,MATCH($C61,'Policy Characteristics'!$C:$C,0))) -> 0.02 | O61: =IF(ISBLANK(INDEX('Policy Characteristics'!I:I,MATCH($C61,'Policy Characteristics'!$C:$C,0))),"",INDEX('Policy Characteristics'!I:I,MATCH($C61,'Policy Characteristics'!$C:$C,0))) -> % reduction in emissions | P61: =IF(ISBLANK(INDEX('Policy Characteristics'!J:J,MATCH($C61,'Policy Characteristics'!$C:$C,0))),"",INDEX('Policy Characteristics'!J:J,MATCH($C61,'Policy Characteristics'!$C:$C,0))) -> **Description:** This policy represents strengthening standards for the selected pollutant(s) emitted by the selected vehicle type(s). Conventional pollutants' most important, harmful impacts are on human health rather than on climate change. // **Guidance for setting values:** In South Korea, the 24-hour national ambient air quality standard (NAAQS) for PM2.5, the most harmful type of particulate for human health, is 35 µg/m^3. | Q61: =IF(ISBLANK(INDEX('Policy Characteristics'!K:K,MATCH($C61,'Policy Characteristics'!$C:$C,0))),"",INDEX('Policy Characteristics'!K:K,MATCH($C61,'Policy Characteristics'!$C:$C,0))) -> transportation-sector-main.html#conv-pol-stds | R61: =IF(ISBLANK(INDEX('Policy Characteristics'!L:L,MATCH($C61,'Policy Characteristics'!$C:$C,0))),"",INDEX('Policy Characteristics'!L:L,MATCH($C61,'Policy Characteristics'!$C:$C,0))) -> conventional-pollutant-standards.html
A62: =IF(ISBLANK(INDEX('Policy Characteristics'!A:A,MATCH($C62,'Policy Characteristics'!$C:$C,0))),"",INDEX('Policy Characteristics'!A:A,MATCH($C62,'Policy Characteristics'!$C:$C,0))) -> Transportation | B62: =IF(ISBLANK(INDEX('Policy Characteristics'!B:B,MATCH($C62,'Policy Characteristics'!$C:$C,0))),"",INDEX('Policy Characteristics'!B:B,MATCH($C62,'Policy Characteristics'!$C:$C,0))) -> Electric Vehicle Charger Deployment | C62: Percentage Increase in EV Chargers | H62: 360 | I62: Yes | J62: =IF(ISBLANK(INDEX('Policy Characteristics'!D:D,MATCH($C62,'Policy Characteristics'!$C:$C,0))),"",INDEX('Policy Characteristics'!D:D,MATCH($C62,'Policy Characteristics'!$C:$C,0))) -> EV Charger Deployment | K62: =IF(ISBLANK(INDEX('Policy Characteristics'!E:E,MATCH($C62,'Policy Characteristics'!$C:$C,0))),"",INDEX('Policy Characteristics'!E:E,MATCH($C62,'Policy Characteristics'!$C:$C,0))) -> trans EV charger deployment | L62: =IF(ISBLANK(INDEX('Policy Characteristics'!F:F,MATCH($C62,'Policy Characteristics'!$C:$C,0))),"",INDEX('Policy Characteristics'!F:F,MATCH($C62,'Policy Characteristics'!$C:$C,0))) -> -1 | M62: =IF(ISBLANK(INDEX('Policy Characteristics'!G:G,MATCH($C62,'Policy Characteristics'!$C:$C,0))),"",INDEX('Policy Characteristics'!G:G,MATCH($C62,'Policy Characteristics'!$C:$C,0))) -> 3 | N62: =IF(ISBLANK(INDEX('Policy Characteristics'!H:H,MATCH($C62,'Policy Characteristics'!$C:$C,0))),"",INDEX('Policy Characteristics'!H:H,MATCH($C62,'Policy Characteristics'!$C:$C,0))) -> 0.1 | O62: =IF(ISBLANK(INDEX('Policy Characteristics'!I:I,MATCH($C62,'Policy Characteristics'!$C:$C,0))),"",INDEX('Policy Characteristics'!I:I,MATCH($C62,'Policy Characteristics'!$C:$C,0))) -> % change | P62: =IF(ISBLANK(INDEX('Policy Characteristics'!J:J,MATCH($C62,'Policy Characteristics'!$C:$C,0))),"",INDEX('Policy Characteristics'!J:J,MATCH($C62,'Policy Characteristics'!$C:$C,0))) -> **Description:** This policy represents increasing the deployment of EV charging stations, including DC Fast and Level 2 charging stations. It is set in chargers per 100,000 people (cumulative, not per year), additional to chargers in the BAU case. This policy lever does not have an effect on energy use/emissions/deployment. It is meant to account for the costs of additional charging infrastructure. // **Guidance for setting values:** As of Dec 2021, South Korea had 91,592 chargers, just under 177 chargers per 100k pop. In Dec 2020, South Korea had 12,635 gas stations with an average of 14 fuel pumps each, or 342 pumps per 100k pop. Therefore, a lever setting of 165 would cause the population density of EV chargers to equal the 2020 population density of fuel pumps. | Q62: =IF(ISBLANK(INDEX('Policy Characteristics'!K:K,MATCH($C62,'Policy Characteristics'!$C:$C,0))),"",INDEX('Policy Characteristics'!K:K,MATCH($C62,'Policy Characteristics'!$C:$C,0))) | R62: =IF(ISBLANK(INDEX('Policy Characteristics'!L:L,MATCH($C62,'Policy Characteristics'!$C:$C,0))),"",INDEX('Policy Characteristics'!L:L,MATCH($C62,'Policy Characteristics'!$C:$C,0))) -> ev-charger-deployment.html
A63: =IF(ISBLANK(INDEX('Policy Characteristics'!A:A,MATCH($C63,'Policy Characteristics'!$C:$C,0))),"",INDEX('Policy Characteristics'!A:A,MATCH($C63,'Policy Characteristics'!$C:$C,0))) -> Transportation | B63: =IF(ISBLANK(INDEX('Policy Characteristics'!B:B,MATCH($C63,'Policy Characteristics'!$C:$C,0))),"",INDEX('Policy Characteristics'!B:B,MATCH($C63,'Policy Characteristics'!$C:$C,0))) -> Passenger Vehicle Subsidy | C63: Additional Passenger Vehicle Subsidy | D63: LDVs | E63: battery electric vehicle | F63: Cars and SUVs | G63: Battery electric vehicle | H63: 189 | I63: Yes | J63: =IF(ISBLANK(INDEX('Policy Characteristics'!D:D,MATCH($C63,'Policy Characteristics'!$C:$C,0))),"",INDEX('Policy Characteristics'!D:D,MATCH($C63,'Policy Characteristics'!$C:$C,0))) -> Vehicle Subsidy | K63: =IF(ISBLANK(INDEX('Policy Characteristics'!E:E,MATCH($C63,'Policy Characteristics'!$C:$C,0))),"",INDEX('Policy Characteristics'!E:E,MATCH($C63,'Policy Characteristics'!$C:$C,0))) -> trans psgr subsidy | L63: =IF(ISBLANK(INDEX('Policy Characteristics'!F:F,MATCH($C63,'Policy Characteristics'!$C:$C,0))),"",INDEX('Policy Characteristics'!F:F,MATCH($C63,'Policy Characteristics'!$C:$C,0))) -> -60000000 | M63: =IF(ISBLANK(INDEX('Policy Characteristics'!G:G,MATCH($C63,'Policy Characteristics'!$C:$C,0))),"",INDEX('Policy Characteristics'!G:G,MATCH($C63,'Policy Characteristics'!$C:$C,0))) -> 60000000 | N63: =IF(ISBLANK(INDEX('Policy Characteristics'!H:H,MATCH($C63,'Policy Characteristics'!$C:$C,0))),"",INDEX('Policy Characteristics'!H:H,MATCH($C63,'Policy Characteristics'!$C:$C,0))) -> 100000 | O63: =IF(ISBLANK(INDEX('Policy Characteristics'!I:I,MATCH($C63,'Policy Characteristics'!$C:$C,0))),"",INDEX('Policy Characteristics'!I:I,MATCH($C63,'Policy Characteristics'!$C:$C,0))) -> KRW/vehicle | P63: =IF(ISBLANK(INDEX('Policy Characteristics'!J:J,MATCH($C63,'Policy Characteristics'!$C:$C,0))),"",INDEX('Policy Characteristics'!J:J,MATCH($C63,'Policy Characteristics'!$C:$C,0))) -> **Description:** This policy specifies the dollar amount offered as a subsidy to the purchaser of a new passenger vehicle. This is in addition to subsidies that exist in the BAU case. A negative value implies a tax or removal of subsidies. // **Guidance for setting values:** In South Korea, as of 2019, electric vehicle national subsidies were up to $7,628 and local subsidies were up to $5,933. In 2021, electric vehicle national subsidies are up to $6,781 and local subsidies are up to $5,933. Subsidies for Passenger-LDVs are 28% of the average car price, 24% for passenger-HDV, and 44% for freight-LDV. | Q63: =IF(ISBLANK(INDEX('Policy Characteristics'!K:K,MATCH($C63,'Policy Characteristics'!$C:$C,0))),"",INDEX('Policy Characteristics'!K:K,MATCH($C63,'Policy Characteristics'!$C:$C,0))) -> transportation-sector-main.html#ev-subsidy | R63: =IF(ISBLANK(INDEX('Policy Characteristics'!L:L,MATCH($C63,'Policy Characteristics'!$C:$C,0))),"",INDEX('Policy Characteristics'!L:L,MATCH($C63,'Policy Characteristics'!$C:$C,0))) -> ev-subsidy.html
A64: =IF(ISBLANK(INDEX('Policy Characteristics'!A:A,MATCH($C64,'Policy Characteristics'!$C:$C,0))),"",INDEX('Policy Characteristics'!A:A,MATCH($C64,'Policy Characteristics'!$C:$C,0))) -> Transportation | B64: =IF(ISBLANK(INDEX('Policy Characteristics'!B:B,MATCH($C64,'Policy Characteristics'!$C:$C,0))),"",INDEX('Policy Characteristics'!B:B,MATCH($C64,'Policy Characteristics'!$C:$C,0))) -> Passenger Vehicle Subsidy | C64: =C$63 -> Additional Passenger Vehicle Subsidy | D64: LDVs | E64: natural gas vehicle | F64: Cars and SUVs | G64: Natural gas vehicle | H64: 592 | I64: No | J64: =IF(ISBLANK(INDEX('Policy Characteristics'!D:D,MATCH($C64,'Policy Characteristics'!$C:$C,0))),"",INDEX('Policy Characteristics'!D:D,MATCH($C64,'Policy Characteristics'!$C:$C,0))) -> Vehicle Subsidy | K64: =IF(ISBLANK(INDEX('Policy Characteristics'!E:E,MATCH($C64,'Policy Characteristics'!$C:$C,0))),"",INDEX('Policy Characteristics'!E:E,MATCH($C64,'Policy Characteristics'!$C:$C,0))) -> trans psgr subsidy | L64: =IF(ISBLANK(INDEX('Policy Characteristics'!F:F,MATCH($C64,'Policy Characteristics'!$C:$C,0))),"",INDEX('Policy Characteristics'!F:F,MATCH($C64,'Policy Characteristics'!$C:$C,0))) -> -60000000 | M64: =IF(ISBLANK(INDEX('Policy Characteristics'!G:G,MATCH($C64,'Policy Characteristics'!$C:$C,0))),"",INDEX('Policy Characteristics'!G:G,MATCH($C64,'Policy Characteristics'!$C:$C,0))) -> 60000000 | N64: =IF(ISBLANK(INDEX('Policy Characteristics'!H:H,MATCH($C64,'Policy Characteristics'!$C:$C,0))),"",INDEX('Policy Characteristics'!H:H,MATCH($C64,'Policy Characteristics'!$C:$C,0))) -> 100000 | O64: =IF(ISBLANK(INDEX('Policy Characteristics'!I:I,MATCH($C64,'Policy Characteristics'!$C:$C,0))),"",INDEX('Policy Characteristics'!I:I,MATCH($C64,'Policy Characteristics'!$C:$C,0))) -> KRW/vehicle | P64: =IF(ISBLANK(INDEX('Policy Characteristics'!J:J,MATCH($C64,'Policy Characteristics'!$C:$C,0))),"",INDEX('Policy Characteristics'!J:J,MATCH($C64,'Policy Characteristics'!$C:$C,0))) -> **Description:** This policy specifies the dollar amount offered as a subsidy to the purchaser of a new passenger vehicle. This is in addition to subsidies that exist in the BAU case. A negative value implies a tax or removal of subsidies. // **Guidance for setting values:** In South Korea, as of 2019, electric vehicle national subsidies were up to $7,628 and local subsidies were up to $5,933. In 2021, electric vehicle national subsidies are up to $6,781 and local subsidies are up to $5,933. Subsidies for Passenger-LDVs are 28% of the average car price, 24% for passenger-HDV, and 44% for freight-LDV. | Q64: =IF(ISBLANK(INDEX('Policy Characteristics'!K:K,MATCH($C64,'Policy Characteristics'!$C:$C,0))),"",INDEX('Policy Characteristics'!K:K,MATCH($C64,'Policy Characteristics'!$C:$C,0))) -> transportation-sector-main.html#ev-subsidy | R64: =IF(ISBLANK(INDEX('Policy Characteristics'!L:L,MATCH($C64,'Policy Characteristics'!$C:$C,0))),"",INDEX('Policy Characteristics'!L:L,MATCH($C64,'Policy Characteristics'!$C:$C,0))) -> ev-subsidy.html
A65: =IF(ISBLANK(INDEX('Policy Characteristics'!A:A,MATCH($C65,'Policy Characteristics'!$C:$C,0))),"",INDEX('Policy Characteristics'!A:A,MATCH($C65,'Policy Characteristics'!$C:$C,0))) -> Transportation | B65: =IF(ISBLANK(INDEX('Policy Characteristics'!B:B,MATCH($C65,'Policy Characteristics'!$C:$C,0))),"",INDEX('Policy Characteristics'!B:B,MATCH($C65,'Policy Characteristics'!$C:$C,0))) -> Passenger Vehicle Subsidy | C65: =C$63 -> Additional Passenger Vehicle Subsidy | D65: LDVs | E65: gasoline vehicle | F65: Cars and SUVs | G65: Gasoline vehicle | H65: 593 | I65: No | J65: =IF(ISBLANK(INDEX('Policy Characteristics'!D:D,MATCH($C65,'Policy Characteristics'!$C:$C,0))),"",INDEX('Policy Characteristics'!D:D,MATCH($C65,'Policy Characteristics'!$C:$C,0))) -> Vehicle Subsidy | K65: =IF(ISBLANK(INDEX('Policy Characteristics'!E:E,MATCH($C65,'Policy Characteristics'!$C:$C,0))),"",INDEX('Policy Characteristics'!E:E,MATCH($C65,'Policy Characteristics'!$C:$C,0))) -> trans psgr subsidy | L65: =IF(ISBLANK(INDEX('Policy Characteristics'!F:F,MATCH($C65,'Policy Characteristics'!$C:$C,0))),"",INDEX('Policy Characteristics'!F:F,MATCH($C65,'Policy Characteristics'!$C:$C,0))) -> -60000000 | M65: =IF(ISBLANK(INDEX('Policy Characteristics'!G:G,MATCH($C65,'Policy Characteristics'!$C:$C,0))),"",INDEX('Policy Characteristics'!G:G,MATCH($C65,'Policy Characteristics'!$C:$C,0))) -> 60000000 | N65: =IF(ISBLANK(INDEX('Policy Characteristics'!H:H,MATCH($C65,'Policy Characteristics'!$C:$C,0))),"",INDEX('Policy Characteristics'!H:H,MATCH($C65,'Policy Characteristics'!$C:$C,0))) -> 100000 | O65: =IF(ISBLANK(INDEX('Policy Characteristics'!I:I,MATCH($C65,'Policy Characteristics'!$C:$C,0))),"",INDEX('Policy Characteristics'!I:I,MATCH($C65,'Policy Characteristics'!$C:$C,0))) -> KRW/vehicle | P65: =IF(ISBLANK(INDEX('Policy Characteristics'!J:J,MATCH($C65,'Policy Characteristics'!$C:$C,0))),"",INDEX('Policy Characteristics'!J:J,MATCH($C65,'Policy Characteristics'!$C:$C,0))) -> **Description:** This policy specifies the dollar amount offered as a subsidy to the purchaser of a new passenger vehicle. This is in addition to subsidies that exist in the BAU case. A negative value implies a tax or removal of subsidies. // **Guidance for setting values:** In South Korea, as of 2019, electric vehicle national subsidies were up to $7,628 and local subsidies were up to $5,933. In 2021, electric vehicle national subsidies are up to $6,781 and local subsidies are up to $5,933. Subsidies for Passenger-LDVs are 28% of the average car price, 24% for passenger-HDV, and 44% for freight-LDV. | Q65: =IF(ISBLANK(INDEX('Policy Characteristics'!K:K,MATCH($C65,'Policy Characteristics'!$C:$C,0))),"",INDEX('Policy Characteristics'!K:K,MATCH($C65,'Policy Characteristics'!$C:$C,0))) -> transportation-sector-main.html#ev-subsidy | R65: =IF(ISBLANK(INDEX('Policy Characteristics'!L:L,MATCH($C65,'Policy Characteristics'!$C:$C,0))),"",INDEX('Policy Characteristics'!L:L,MATCH($C65,'Policy Characteristics'!$C:$C,0))) -> ev-subsidy.html
A66: =IF(ISBLANK(INDEX('Policy Characteristics'!A:A,MATCH($C66,'Policy Characteristics'!$C:$C,0))),"",INDEX('Policy Characteristics'!A:A,MATCH($C66,'Policy Characteristics'!$C:$C,0))) -> Transportation | B66: =IF(ISBLANK(INDEX('Policy Characteristics'!B:B,MATCH($C66,'Policy Characteristics'!$C:$C,0))),"",INDEX('Policy Characteristics'!B:B,MATCH($C66,'Policy Characteristics'!$C:$C,0))) -> Passenger Vehicle Subsidy | C66: =C$63 -> Additional Passenger Vehicle Subsidy | D66: LDVs | E66: diesel vehicle | F66: Cars and SUVs | G66: Diesel vehicle | H66: 594 | I66: No | J66: =IF(ISBLANK(INDEX('Policy Characteristics'!D:D,MATCH($C66,'Policy Characteristics'!$C:$C,0))),"",INDEX('Policy Characteristics'!D:D,MATCH($C66,'Policy Characteristics'!$C:$C,0))) -> Vehicle Subsidy | K66: =IF(ISBLANK(INDEX('Policy Characteristics'!E:E,MATCH($C66,'Policy Characteristics'!$C:$C,0))),"",INDEX('Policy Characteristics'!E:E,MATCH($C66,'Policy Characteristics'!$C:$C,0))) -> trans psgr subsidy | L66: =IF(ISBLANK(INDEX('Policy Characteristics'!F:F,MATCH($C66,'Policy Characteristics'!$C:$C,0))),"",INDEX('Policy Characteristics'!F:F,MATCH($C66,'Policy Characteristics'!$C:$C,0))) -> -60000000 | M66: =IF(ISBLANK(INDEX('Policy Characteristics'!G:G,MATCH($C66,'Policy Characteristics'!$C:$C,0))),"",INDEX('Policy Characteristics'!G:G,MATCH($C66,'Policy Characteristics'!$C:$C,0))) -> 60000000 | N66: =IF(ISBLANK(INDEX('Policy Characteristics'!H:H,MATCH($C66,'Policy Characteristics'!$C:$C,0))),"",INDEX('Policy Characteristics'!H:H,MATCH($C66,'Policy Characteristics'!$C:$C,0))) -> 100000 | O66: =IF(ISBLANK(INDEX('Policy Characteristics'!I:I,MATCH($C66,'Policy Characteristics'!$C:$C,0))),"",INDEX('Policy Characteristics'!I:I,MATCH($C66,'Policy Characteristics'!$C:$C,0))) -> KRW/vehicle | P66: =IF(ISBLANK(INDEX('Policy Characteristics'!J:J,MATCH($C66,'Policy Characteristics'!$C:$C,0))),"",INDEX('Policy Characteristics'!J:J,MATCH($C66,'Policy Characteristics'!$C:$C,0))) -> **Description:** This policy specifies the dollar amount offered as a subsidy to the purchaser of a new passenger vehicle. This is in addition to subsidies that exist in the BAU case. A negative value implies a tax or removal of subsidies. // **Guidance for setting values:** In South Korea, as of 2019, electric vehicle national subsidies were up to $7,628 and local subsidies were up to $5,933. In 2021, electric vehicle national subsidies are up to $6,781 and local subsidies are up to $5,933. Subsidies for Passenger-LDVs are 28% of the average car price, 24% for passenger-HDV, and 44% for freight-LDV. | Q66: =IF(ISBLANK(INDEX('Policy Characteristics'!K:K,MATCH($C66,'Policy Characteristics'!$C:$C,0))),"",INDEX('Policy Characteristics'!K:K,MATCH($C66,'Policy Characteristics'!$C:$C,0))) -> transportation-sector-main.html#ev-subsidy | R66: =IF(ISBLANK(INDEX('Policy Characteristics'!L:L,MATCH($C66,'Policy Characteristics'!$C:$C,0))),"",INDEX('Policy Characteristics'!L:L,MATCH($C66,'Policy Characteristics'!$C:$C,0))) -> ev-subsidy.html
A67: =IF(ISBLANK(INDEX('Policy Characteristics'!A:A,MATCH($C67,'Policy Characteristics'!$C:$C,0))),"",INDEX('Policy Characteristics'!A:A,MATCH($C67,'Policy Characteristics'!$C:$C,0))) -> Transportation | B67: =IF(ISBLANK(INDEX('Policy Characteristics'!B:B,MATCH($C67,'Policy Characteristics'!$C:$C,0))),"",INDEX('Policy Characteristics'!B:B,MATCH($C67,'Policy Characteristics'!$C:$C,0))) -> Passenger Vehicle Subsidy | C67: =C$63 -> Additional Passenger Vehicle Subsidy | D67: LDVs | E67: plugin hybrid vehicle | F67: Cars and SUVs | G67: Plugin hybrid vehicle | H67: 595 | I67: Yes | J67: =IF(ISBLANK(INDEX('Policy Characteristics'!D:D,MATCH($C67,'Policy Characteristics'!$C:$C,0))),"",INDEX('Policy Characteristics'!D:D,MATCH($C67,'Policy Characteristics'!$C:$C,0))) -> Vehicle Subsidy | K67: =IF(ISBLANK(INDEX('Policy Characteristics'!E:E,MATCH($C67,'Policy Characteristics'!$C:$C,0))),"",INDEX('Policy Characteristics'!E:E,MATCH($C67,'Policy Characteristics'!$C:$C,0))) -> trans psgr subsidy | L67: =IF(ISBLANK(INDEX('Policy Characteristics'!F:F,MATCH($C67,'Policy Characteristics'!$C:$C,0))),"",INDEX('Policy Characteristics'!F:F,MATCH($C67,'Policy Characteristics'!$C:$C,0))) -> -60000000 | M67: =IF(ISBLANK(INDEX('Policy Characteristics'!G:G,MATCH($C67,'Policy Characteristics'!$C:$C,0))),"",INDEX('Policy Characteristics'!G:G,MATCH($C67,'Policy Characteristics'!$C:$C,0))) -> 60000000 | N67: =IF(ISBLANK(INDEX('Policy Characteristics'!H:H,MATCH($C67,'Policy Characteristics'!$C:$C,0))),"",INDEX('Policy Characteristics'!H:H,MATCH($C67,'Policy Characteristics'!$C:$C,0))) -> 100000 | O67: =IF(ISBLANK(INDEX('Policy Characteristics'!I:I,MATCH($C67,'Policy Characteristics'!$C:$C,0))),"",INDEX('Policy Characteristics'!I:I,MATCH($C67,'Policy Characteristics'!$C:$C,0))) -> KRW/vehicle | P67: =IF(ISBLANK(INDEX('Policy Characteristics'!J:J,MATCH($C67,'Policy Characteristics'!$C:$C,0))),"",INDEX('Policy Characteristics'!J:J,MATCH($C67,'Policy Characteristics'!$C:$C,0))) -> **Description:** This policy specifies the dollar amount offered as a subsidy to the purchaser of a new passenger vehicle. This is in addition to subsidies that exist in the BAU case. A negative value implies a tax or removal of subsidies. // **Guidance for setting values:** In South Korea, as of 2019, electric vehicle national subsidies were up to $7,628 and local subsidies were up to $5,933. In 2021, electric vehicle national subsidies are up to $6,781 and local subsidies are up to $5,933. Subsidies for Passenger-LDVs are 28% of the average car price, 24% for passenger-HDV, and 44% for freight-LDV. | Q67: =IF(ISBLANK(INDEX('Policy Characteristics'!K:K,MATCH($C67,'Policy Characteristics'!$C:$C,0))),"",INDEX('Policy Characteristics'!K:K,MATCH($C67,'Policy Characteristics'!$C:$C,0))) -> transportation-sector-main.html#ev-subsidy | R67: =IF(ISBLANK(INDEX('Policy Characteristics'!L:L,MATCH($C67,'Policy Characteristics'!$C:$C,0))),"",INDEX('Policy Characteristics'!L:L,MATCH($C67,'Policy Characteristics'!$C:$C,0))) -> ev-subsidy.html
A68: =IF(ISBLANK(INDEX('Policy Characteristics'!A:A,MATCH($C68,'Policy Characteristics'!$C:$C,0))),"",INDEX('Policy Characteristics'!A:A,MATCH($C68,'Policy Characteristics'!$C:$C,0))) -> Transportation | B68: =IF(ISBLANK(INDEX('Policy Characteristics'!B:B,MATCH($C68,'Policy Characteristics'!$C:$C,0))),"",INDEX('Policy Characteristics'!B:B,MATCH($C68,'Policy Characteristics'!$C:$C,0))) -> Passenger Vehicle Subsidy | C68: =C$63 -> Additional Passenger Vehicle Subsidy | D68: LDVs | E68: LPG vehicle | F68: Cars and SUVs | G68: LPG vehicle | H68: 596 | I68: No | J68: =IF(ISBLANK(INDEX('Policy Characteristics'!D:D,MATCH($C68,'Policy Characteristics'!$C:$C,0))),"",INDEX('Policy Characteristics'!D:D,MATCH($C68,'Policy Characteristics'!$C:$C,0))) -> Vehicle Subsidy | K68: =IF(ISBLANK(INDEX('Policy Characteristics'!E:E,MATCH($C68,'Policy Characteristics'!$C:$C,0))),"",INDEX('Policy Characteristics'!E:E,MATCH($C68,'Policy Characteristics'!$C:$C,0))) -> trans psgr subsidy | L68: =IF(ISBLANK(INDEX('Policy Characteristics'!F:F,MATCH($C68,'Policy Characteristics'!$C:$C,0))),"",INDEX('Policy Characteristics'!F:F,MATCH($C68,'Policy Characteristics'!$C:$C,0))) -> -60000000 | M68: =IF(ISBLANK(INDEX('Policy Characteristics'!G:G,MATCH($C68,'Policy Characteristics'!$C:$C,0))),"",INDEX('Policy Characteristics'!G:G,MATCH($C68,'Policy Characteristics'!$C:$C,0))) -> 60000000 | N68: =IF(ISBLANK(INDEX('Policy Characteristics'!H:H,MATCH($C68,'Policy Characteristics'!$C:$C,0))),"",INDEX('Policy Characteristics'!H:H,MATCH($C68,'Policy Characteristics'!$C:$C,0))) -> 100000 | O68: =IF(ISBLANK(INDEX('Policy Characteristics'!I:I,MATCH($C68,'Policy Characteristics'!$C:$C,0))),"",INDEX('Policy Characteristics'!I:I,MATCH($C68,'Policy Characteristics'!$C:$C,0))) -> KRW/vehicle | P68: =IF(ISBLANK(INDEX('Policy Characteristics'!J:J,MATCH($C68,'Policy Characteristics'!$C:$C,0))),"",INDEX('Policy Characteristics'!J:J,MATCH($C68,'Policy Characteristics'!$C:$C,0))) -> **Description:** This policy specifies the dollar amount offered as a subsidy to the purchaser of a new passenger vehicle. This is in addition to subsidies that exist in the BAU case. A negative value implies a tax or removal of subsidies. // **Guidance for setting values:** In South Korea, as of 2019, electric vehicle national subsidies were up to $7,628 and local subsidies were up to $5,933. In 2021, electric vehicle national subsidies are up to $6,781 and local subsidies are up to $5,933. Subsidies for Passenger-LDVs are 28% of the average car price, 24% for passenger-HDV, and 44% for freight-LDV. | Q68: =IF(ISBLANK(INDEX('Policy Characteristics'!K:K,MATCH($C68,'Policy Characteristics'!$C:$C,0))),"",INDEX('Policy Characteristics'!K:K,MATCH($C68,'Policy Characteristics'!$C:$C,0))) -> transportation-sector-main.html#ev-subsidy | R68: =IF(ISBLANK(INDEX('Policy Characteristics'!L:L,MATCH($C68,'Policy Characteristics'!$C:$C,0))),"",INDEX('Policy Characteristics'!L:L,MATCH($C68,'Policy Characteristics'!$C:$C,0))) -> ev-subsidy.html
A69: =IF(ISBLANK(INDEX('Policy Characteristics'!A:A,MATCH($C69,'Policy Characteristics'!$C:$C,0))),"",INDEX('Policy Characteristics'!A:A,MATCH($C69,'Policy Characteristics'!$C:$C,0))) -> Transportation | B69: =IF(ISBLANK(INDEX('Policy Characteristics'!B:B,MATCH($C69,'Policy Characteristics'!$C:$C,0))),"",INDEX('Policy Characteristics'!B:B,MATCH($C69,'Policy Characteristics'!$C:$C,0))) -> Passenger Vehicle Subsidy | C69: =C$63 -> Additional Passenger Vehicle Subsidy | D69: LDVs | E69: hydrogen vehicle | F69: Cars and SUVs | G69: Hydrogen vehicle | H69: 597 | I69: Yes | J69: =IF(ISBLANK(INDEX('Policy Characteristics'!D:D,MATCH($C69,'Policy Characteristics'!$C:$C,0))),"",INDEX('Policy Characteristics'!D:D,MATCH($C69,'Policy Characteristics'!$C:$C,0))) -> Vehicle Subsidy | K69: =IF(ISBLANK(INDEX('Policy Characteristics'!E:E,MATCH($C69,'Policy Characteristics'!$C:$C,0))),"",INDEX('Policy Characteristics'!E:E,MATCH($C69,'Policy Characteristics'!$C:$C,0))) -> trans psgr subsidy | L69: =IF(ISBLANK(INDEX('Policy Characteristics'!F:F,MATCH($C69,'Policy Characteristics'!$C:$C,0))),"",INDEX('Policy Characteristics'!F:F,MATCH($C69,'Policy Characteristics'!$C:$C,0))) -> -60000000 | M69: =IF(ISBLANK(INDEX('Policy Characteristics'!G:G,MATCH($C69,'Policy Characteristics'!$C:$C,0))),"",INDEX('Policy Characteristics'!G:G,MATCH($C69,'Policy Characteristics'!$C:$C,0))) -> 60000000 | N69: =IF(ISBLANK(INDEX('Policy Characteristics'!H:H,MATCH($C69,'Policy Characteristics'!$C:$C,0))),"",INDEX('Policy Characteristics'!H:H,MATCH($C69,'Policy Characteristics'!$C:$C,0))) -> 100000 | O69: =IF(ISBLANK(INDEX('Policy Characteristics'!I:I,MATCH($C69,'Policy Characteristics'!$C:$C,0))),"",INDEX('Policy Characteristics'!I:I,MATCH($C69,'Policy Characteristics'!$C:$C,0))) -> KRW/vehicle | P69: =IF(ISBLANK(INDEX('Policy Characteristics'!J:J,MATCH($C69,'Policy Characteristics'!$C:$C,0))),"",INDEX('Policy Characteristics'!J:J,MATCH($C69,'Policy Characteristics'!$C:$C,0))) -> **Description:** This policy specifies the dollar amount offered as a subsidy to the purchaser of a new passenger vehicle. This is in addition to subsidies that exist in the BAU case. A negative value implies a tax or removal of subsidies. // **Guidance for setting values:** In South Korea, as of 2019, electric vehicle national subsidies were up to $7,628 and local subsidies were up to $5,933. In 2021, electric vehicle national subsidies are up to $6,781 and local subsidies are up to $5,933. Subsidies for Passenger-LDVs are 28% of the average car price, 24% for passenger-HDV, and 44% for freight-LDV. | Q69: =IF(ISBLANK(INDEX('Policy Characteristics'!K:K,MATCH($C69,'Policy Characteristics'!$C:$C,0))),"",INDEX('Policy Characteristics'!K:K,MATCH($C69,'Policy Characteristics'!$C:$C,0))) -> transportation-sector-main.html#ev-subsidy | R69: =IF(ISBLANK(INDEX('Policy Characteristics'!L:L,MATCH($C69,'Policy Characteristics'!$C:$C,0))),"",INDEX('Policy Characteristics'!L:L,MATCH($C69,'Policy Characteristics'!$C:$C,0))) -> ev-subsidy.html
A70: =IF(ISBLANK(INDEX('Policy Characteristics'!A:A,MATCH($C70,'Policy Characteristics'!$C:$C,0))),"",INDEX('Policy Characteristics'!A:A,MATCH($C70,'Policy Characteristics'!$C:$C,0))) -> Transportation | B70: =IF(ISBLANK(INDEX('Policy Characteristics'!B:B,MATCH($C70,'Policy Characteristics'!$C:$C,0))),"",INDEX('Policy Characteristics'!B:B,MATCH($C70,'Policy Characteristics'!$C:$C,0))) -> Passenger Vehicle Subsidy | C70: =C$63 -> Additional Passenger Vehicle Subsidy | D70: HDVs | E70: battery electric vehicle | F70: Buses | G70: Battery electric vehicle | H70: 598 | I70: Yes | J70: =IF(ISBLANK(INDEX('Policy Characteristics'!D:D,MATCH($C70,'Policy Characteristics'!$C:$C,0))),"",INDEX('Policy Characteristics'!D:D,MATCH($C70,'Policy Characteristics'!$C:$C,0))) -> Vehicle Subsidy | K70: =IF(ISBLANK(INDEX('Policy Characteristics'!E:E,MATCH($C70,'Policy Characteristics'!$C:$C,0))),"",INDEX('Policy Characteristics'!E:E,MATCH($C70,'Policy Characteristics'!$C:$C,0))) -> trans psgr subsidy | L70: =IF(ISBLANK(INDEX('Policy Characteristics'!F:F,MATCH($C70,'Policy Characteristics'!$C:$C,0))),"",INDEX('Policy Characteristics'!F:F,MATCH($C70,'Policy Characteristics'!$C:$C,0))) -> -60000000 | M70: =IF(ISBLANK(INDEX('Policy Characteristics'!G:G,MATCH($C70,'Policy Characteristics'!$C:$C,0))),"",INDEX('Policy Characteristics'!G:G,MATCH($C70,'Policy Characteristics'!$C:$C,0))) -> 60000000 | N70: =IF(ISBLANK(INDEX('Policy Characteristics'!H:H,MATCH($C70,'Policy Characteristics'!$C:$C,0))),"",INDEX('Policy Characteristics'!H:H,MATCH($C70,'Policy Characteristics'!$C:$C,0))) -> 100000 | O70: =IF(ISBLANK(INDEX('Policy Characteristics'!I:I,MATCH($C70,'Policy Characteristics'!$C:$C,0))),"",INDEX('Policy Characteristics'!I:I,MATCH($C70,'Policy Characteristics'!$C:$C,0))) -> KRW/vehicle | P70: =IF(ISBLANK(INDEX('Policy Characteristics'!J:J,MATCH($C70,'Policy Characteristics'!$C:$C,0))),"",INDEX('Policy Characteristics'!J:J,MATCH($C70,'Policy Characteristics'!$C:$C,0))) -> **Description:** This policy specifies the dollar amount offered as a subsidy to the purchaser of a new passenger vehicle. This is in addition to subsidies that exist in the BAU case. A negative value implies a tax or removal of subsidies. // **Guidance for setting values:** In South Korea, as of 2019, electric vehicle national subsidies were up to $7,628 and local subsidies were up to $5,933. In 2021, electric vehicle national subsidies are up to $6,781 and local subsidies are up to $5,933. Subsidies for Passenger-LDVs are 28% of the average car price, 24% for passenger-HDV, and 44% for freight-LDV. | Q70: =IF(ISBLANK(INDEX('Policy Characteristics'!K:K,MATCH($C70,'Policy Characteristics'!$C:$C,0))),"",INDEX('Policy Characteristics'!K:K,MATCH($C70,'Policy Characteristics'!$C:$C,0))) -> transportation-sector-main.html#ev-subsidy | R70: =IF(ISBLANK(INDEX('Policy Characteristics'!L:L,MATCH($C70,'Policy Characteristics'!$C:$C,0))),"",INDEX('Policy Characteristics'!L:L,MATCH($C70,'Policy Characteristics'!$C:$C,0))) -> ev-subsidy.html
A71: =IF(ISBLANK(INDEX('Policy Characteristics'!A:A,MATCH($C71,'Policy Characteristics'!$C:$C,0))),"",INDEX('Policy Characteristics'!A:A,MATCH($C71,'Policy Characteristics'!$C:$C,0))) -> Transportation | B71: =IF(ISBLANK(INDEX('Policy Characteristics'!B:B,MATCH($C71,'Policy Characteristics'!$C:$C,0))),"",INDEX('Policy Characteristics'!B:B,MATCH($C71,'Policy Characteristics'!$C:$C,0))) -> Passenger Vehicle Subsidy | C71: =C$63 -> Additional Passenger Vehicle Subsidy | D71: HDVs | E71: natural gas vehicle | F71: Buses | G71: Natural gas vehicle | H71: 599 | I71: No | J71: =IF(ISBLANK(INDEX('Policy Characteristics'!D:D,MATCH($C71,'Policy Characteristics'!$C:$C,0))),"",INDEX('Policy Characteristics'!D:D,MATCH($C71,'Policy Characteristics'!$C:$C,0))) -> Vehicle Subsidy | K71: =IF(ISBLANK(INDEX('Policy Characteristics'!E:E,MATCH($C71,'Policy Characteristics'!$C:$C,0))),"",INDEX('Policy Characteristics'!E:E,MATCH($C71,'Policy Characteristics'!$C:$C,0))) -> trans psgr subsidy | L71: =IF(ISBLANK(INDEX('Policy Characteristics'!F:F,MATCH($C71,'Policy Characteristics'!$C:$C,0))),"",INDEX('Policy Characteristics'!F:F,MATCH($C71,'Policy Characteristics'!$C:$C,0))) -> -60000000 | M71: =IF(ISBLANK(INDEX('Policy Characteristics'!G:G,MATCH($C71,'Policy Characteristics'!$C:$C,0))),"",INDEX('Policy Characteristics'!G:G,MATCH($C71,'Policy Characteristics'!$C:$C,0))) -> 60000000 | N71: =IF(ISBLANK(INDEX('Policy Characteristics'!H:H,MATCH($C71,'Policy Characteristics'!$C:$C,0))),"",INDEX('Policy Characteristics'!H:H,MATCH($C71,'Policy Characteristics'!$C:$C,0))) -> 100000 | O71: =IF(ISBLANK(INDEX('Policy Characteristics'!I:I,MATCH($C71,'Policy Characteristics'!$C:$C,0))),"",INDEX('Policy Characteristics'!I:I,MATCH($C71,'Policy Characteristics'!$C:$C,0))) -> KRW/vehicle | P71: =IF(ISBLANK(INDEX('Policy Characteristics'!J:J,MATCH($C71,'Policy Characteristics'!$C:$C,0))),"",INDEX('Policy Characteristics'!J:J,MATCH($C71,'Policy Characteristics'!$C:$C,0))) -> **Description:** This policy specifies the dollar amount offered as a subsidy to the purchaser of a new passenger vehicle. This is in addition to subsidies that exist in the BAU case. A negative value implies a tax or removal of subsidies. // **Guidance for setting values:** In South Korea, as of 2019, electric vehicle national subsidies were up to $7,628 and local subsidies were up to $5,933. In 2021, electric vehicle national subsidies are up to $6,781 and local subsidies are up to $5,933. Subsidies for Passenger-LDVs are 28% of the average car price, 24% for passenger-HDV, and 44% for freight-LDV. | Q71: =IF(ISBLANK(INDEX('Policy Characteristics'!K:K,MATCH($C71,'Policy Characteristics'!$C:$C,0))),"",INDEX('Policy Characteristics'!K:K,MATCH($C71,'Policy Characteristics'!$C:$C,0))) -> transportation-sector-main.html#ev-subsidy | R71: =IF(ISBLANK(INDEX('Policy Characteristics'!L:L,MATCH($C71,'Policy Characteristics'!$C:$C,0))),"",INDEX('Policy Characteristics'!L:L,MATCH($C71,'Policy Characteristics'!$C:$C,0))) -> ev-subsidy.html
A72: =IF(ISBLANK(INDEX('Policy Characteristics'!A:A,MATCH($C72,'Policy Characteristics'!$C:$C,0))),"",INDEX('Policy Characteristics'!A:A,MATCH($C72,'Policy Characteristics'!$C:$C,0))) -> Transportation | B72: =IF(ISBLANK(INDEX('Policy Characteristics'!B:B,MATCH($C72,'Policy Characteristics'!$C:$C,0))),"",INDEX('Policy Characteristics'!B:B,MATCH($C72,'Policy Characteristics'!$C:$C,0))) -> Passenger Vehicle Subsidy | C72: =C$63 -> Additional Passenger Vehicle Subsidy | D72: HDVs | E72: gasoline vehicle | F72: Buses | G72: Gasoline vehicle | H72: 600 | I72: No | J72: =IF(ISBLANK(INDEX('Policy Characteristics'!D:D,MATCH($C72,'Policy Characteristics'!$C:$C,0))),"",INDEX('Policy Characteristics'!D:D,MATCH($C72,'Policy Characteristics'!$C:$C,0))) -> Vehicle Subsidy | K72: =IF(ISBLANK(INDEX('Policy Characteristics'!E:E,MATCH($C72,'Policy Characteristics'!$C:$C,0))),"",INDEX('Policy Characteristics'!E:E,MATCH($C72,'Policy Characteristics'!$C:$C,0))) -> trans psgr subsidy | L72: =IF(ISBLANK(INDEX('Policy Characteristics'!F:F,MATCH($C72,'Policy Characteristics'!$C:$C,0))),"",INDEX('Policy Characteristics'!F:F,MATCH($C72,'Policy Characteristics'!$C:$C,0))) -> -60000000 | M72: =IF(ISBLANK(INDEX('Policy Characteristics'!G:G,MATCH($C72,'Policy Characteristics'!$C:$C,0))),"",INDEX('Policy Characteristics'!G:G,MATCH($C72,'Policy Characteristics'!$C:$C,0))) -> 60000000 | N72: =IF(ISBLANK(INDEX('Policy Characteristics'!H:H,MATCH($C72,'Policy Characteristics'!$C:$C,0))),"",INDEX('Policy Characteristics'!H:H,MATCH($C72,'Policy Characteristics'!$C:$C,0))) -> 100000 | O72: =IF(ISBLANK(INDEX('Policy Characteristics'!I:I,MATCH($C72,'Policy Characteristics'!$C:$C,0))),"",INDEX('Policy Characteristics'!I:I,MATCH($C72,'Policy Characteristics'!$C:$C,0))) -> KRW/vehicle | P72: =IF(ISBLANK(INDEX('Policy Characteristics'!J:J,MATCH($C72,'Policy Characteristics'!$C:$C,0))),"",INDEX('Policy Characteristics'!J:J,MATCH($C72,'Policy Characteristics'!$C:$C,0))) -> **Description:** This policy specifies the dollar amount offered as a subsidy to the purchaser of a new passenger vehicle. This is in addition to subsidies that exist in the BAU case. A negative value implies a tax or removal of subsidies. // **Guidance for setting values:** In South Korea, as of 2019, electric vehicle national subsidies were up to $7,628 and local subsidies were up to $5,933. In 2021, electric vehicle national subsidies are up to $6,781 and local subsidies are up to $5,933. Subsidies for Passenger-LDVs are 28% of the average car price, 24% for passenger-HDV, and 44% for freight-LDV. | Q72: =IF(ISBLANK(INDEX('Policy Characteristics'!K:K,MATCH($C72,'Policy Characteristics'!$C:$C,0))),"",INDEX('Policy Characteristics'!K:K,MATCH($C72,'Policy Characteristics'!$C:$C,0))) -> transportation-sector-main.html#ev-subsidy | R72: =IF(ISBLANK(INDEX('Policy Characteristics'!L:L,MATCH($C72,'Policy Characteristics'!$C:$C,0))),"",INDEX('Policy Characteristics'!L:L,MATCH($C72,'Policy Characteristics'!$C:$C,0))) -> ev-subsidy.html
A73: =IF(ISBLANK(INDEX('Policy Characteristics'!A:A,MATCH($C73,'Policy Characteristics'!$C:$C,0))),"",INDEX('Policy Characteristics'!A:A,MATCH($C73,'Policy Characteristics'!$C:$C,0))) -> Transportation | B73: =IF(ISBLANK(INDEX('Policy Characteristics'!B:B,MATCH($C73,'Policy Characteristics'!$C:$C,0))),"",INDEX('Policy Characteristics'!B:B,MATCH($C73,'Policy Characteristics'!$C:$C,0))) -> Passenger Vehicle Subsidy | C73: =C$63 -> Additional Passenger Vehicle Subsidy | D73: HDVs | E73: diesel vehicle | F73: Buses | G73: Diesel vehicle | H73: 601 | I73: No | J73: =IF(ISBLANK(INDEX('Policy Characteristics'!D:D,MATCH($C73,'Policy Characteristics'!$C:$C,0))),"",INDEX('Policy Characteristics'!D:D,MATCH($C73,'Policy Characteristics'!$C:$C,0))) -> Vehicle Subsidy | K73: =IF(ISBLANK(INDEX('Policy Characteristics'!E:E,MATCH($C73,'Policy Characteristics'!$C:$C,0))),"",INDEX('Policy Characteristics'!E:E,MATCH($C73,'Policy Characteristics'!$C:$C,0))) -> trans psgr subsidy | L73: =IF(ISBLANK(INDEX('Policy Characteristics'!F:F,MATCH($C73,'Policy Characteristics'!$C:$C,0))),"",INDEX('Policy Characteristics'!F:F,MATCH($C73,'Policy Characteristics'!$C:$C,0))) -> -60000000 | M73: =IF(ISBLANK(INDEX('Policy Characteristics'!G:G,MATCH($C73,'Policy Characteristics'!$C:$C,0))),"",INDEX('Policy Characteristics'!G:G,MATCH($C73,'Policy Characteristics'!$C:$C,0))) -> 60000000 | N73: =IF(ISBLANK(INDEX('Policy Characteristics'!H:H,MATCH($C73,'Policy Characteristics'!$C:$C,0))),"",INDEX('Policy Characteristics'!H:H,MATCH($C73,'Policy Characteristics'!$C:$C,0))) -> 100000 | O73: =IF(ISBLANK(INDEX('Policy Characteristics'!I:I,MATCH($C73,'Policy Characteristics'!$C:$C,0))),"",INDEX('Policy Characteristics'!I:I,MATCH($C73,'Policy Characteristics'!$C:$C,0))) -> KRW/vehicle | P73: =IF(ISBLANK(INDEX('Policy Characteristics'!J:J,MATCH($C73,'Policy Characteristics'!$C:$C,0))),"",INDEX('Policy Characteristics'!J:J,MATCH($C73,'Policy Characteristics'!$C:$C,0))) -> **Description:** This policy specifies the dollar amount offered as a subsidy to the purchaser of a new passenger vehicle. This is in addition to subsidies that exist in the BAU case. A negative value implies a tax or removal of subsidies. // **Guidance for setting values:** In South Korea, as of 2019, electric vehicle national subsidies were up to $7,628 and local subsidies were up to $5,933. In 2021, electric vehicle national subsidies are up to $6,781 and local subsidies are up to $5,933. Subsidies for Passenger-LDVs are 28% of the average car price, 24% for passenger-HDV, and 44% for freight-LDV. | Q73: =IF(ISBLANK(INDEX('Policy Characteristics'!K:K,MATCH($C73,'Policy Characteristics'!$C:$C,0))),"",INDEX('Policy Characteristics'!K:K,MATCH($C73,'Policy Characteristics'!$C:$C,0))) -> transportation-sector-main.html#ev-subsidy | R73: =IF(ISBLANK(INDEX('Policy Characteristics'!L:L,MATCH($C73,'Policy Characteristics'!$C:$C,0))),"",INDEX('Policy Characteristics'!L:L,MATCH($C73,'Policy Characteristics'!$C:$C,0))) -> ev-subsidy.html
A74: =IF(ISBLANK(INDEX('Policy Characteristics'!A:A,MATCH($C74,'Policy Characteristics'!$C:$C,0))),"",INDEX('Policy Characteristics'!A:A,MATCH($C74,'Policy Characteristics'!$C:$C,0))) -> Transportation | B74: =IF(ISBLANK(INDEX('Policy Characteristics'!B:B,MATCH($C74,'Policy Characteristics'!$C:$C,0))),"",INDEX('Policy Characteristics'!B:B,MATCH($C74,'Policy Characteristics'!$C:$C,0))) -> Passenger Vehicle Subsidy | C74: =C$63 -> Additional Passenger Vehicle Subsidy | D74: HDVs | E74: plugin hybrid vehicle | F74: Buses | G74: Plugin hybrid vehicle | H74: 602 | I74: Yes | J74: =IF(ISBLANK(INDEX('Policy Characteristics'!D:D,MATCH($C74,'Policy Characteristics'!$C:$C,0))),"",INDEX('Policy Characteristics'!D:D,MATCH($C74,'Policy Characteristics'!$C:$C,0))) -> Vehicle Subsidy | K74: =IF(ISBLANK(INDEX('Policy Characteristics'!E:E,MATCH($C74,'Policy Characteristics'!$C:$C,0))),"",INDEX('Policy Characteristics'!E:E,MATCH($C74,'Policy Characteristics'!$C:$C,0))) -> trans psgr subsidy | L74: =IF(ISBLANK(INDEX('Policy Characteristics'!F:F,MATCH($C74,'Policy Characteristics'!$C:$C,0))),"",INDEX('Policy Characteristics'!F:F,MATCH($C74,'Policy Characteristics'!$C:$C,0))) -> -60000000 | M74: =IF(ISBLANK(INDEX('Policy Characteristics'!G:G,MATCH($C74,'Policy Characteristics'!$C:$C,0))),"",INDEX('Policy Characteristics'!G:G,MATCH($C74,'Policy Characteristics'!$C:$C,0))) -> 60000000 | N74: =IF(ISBLANK(INDEX('Policy Characteristics'!H:H,MATCH($C74,'Policy Characteristics'!$C:$C,0))),"",INDEX('Policy Characteristics'!H:H,MATCH($C74,'Policy Characteristics'!$C:$C,0))) -> 100000 | O74: =IF(ISBLANK(INDEX('Policy Characteristics'!I:I,MATCH($C74,'Policy Characteristics'!$C:$C,0))),"",INDEX('Policy Characteristics'!I:I,MATCH($C74,'Policy Characteristics'!$C:$C,0))) -> KRW/vehicle | P74: =IF(ISBLANK(INDEX('Policy Characteristics'!J:J,MATCH($C74,'Policy Characteristics'!$C:$C,0))),"",INDEX('Policy Characteristics'!J:J,MATCH($C74,'Policy Characteristics'!$C:$C,0))) -> **Description:** This policy specifies the dollar amount offered as a subsidy to the purchaser of a new passenger vehicle. This is in addition to subsidies that exist in the BAU case. A negative value implies a tax or removal of subsidies. // **Guidance for setting values:** In South Korea, as of 2019, electric vehicle national subsidies were up to $7,628 and local subsidies were up to $5,933. In 2021, electric vehicle national subsidies are up to $6,781 and local subsidies are up to $5,933. Subsidies for Passenger-LDVs are 28% of the average car price, 24% for passenger-HDV, and 44% for freight-LDV. | Q74: =IF(ISBLANK(INDEX('Policy Characteristics'!K:K,MATCH($C74,'Policy Characteristics'!$C:$C,0))),"",INDEX('Policy Characteristics'!K:K,MATCH($C74,'Policy Characteristics'!$C:$C,0))) -> transportation-sector-main.html#ev-subsidy | R74: =IF(ISBLANK(INDEX('Policy Characteristics'!L:L,MATCH($C74,'Policy Characteristics'!$C:$C,0))),"",INDEX('Policy Characteristics'!L:L,MATCH($C74,'Policy Characteristics'!$C:$C,0))) -> ev-subsidy.html
A75: =IF(ISBLANK(INDEX('Policy Characteristics'!A:A,MATCH($C75,'Policy Characteristics'!$C:$C,0))),"",INDEX('Policy Characteristics'!A:A,MATCH($C75,'Policy Characteristics'!$C:$C,0))) -> Transportation | B75: =IF(ISBLANK(INDEX('Policy Characteristics'!B:B,MATCH($C75,'Policy Characteristics'!$C:$C,0))),"",INDEX('Policy Characteristics'!B:B,MATCH($C75,'Policy Characteristics'!$C:$C,0))) -> Passenger Vehicle Subsidy | C75: =C$63 -> Additional Passenger Vehicle Subsidy | D75: HDVs | E75: LPG vehicle | F75: Buses | G75: LPG vehicle | H75: 1656 | I75: No | J75: =IF(ISBLANK(INDEX('Policy Characteristics'!D:D,MATCH($C75,'Policy Characteristics'!$C:$C,0))),"",INDEX('Policy Characteristics'!D:D,MATCH($C75,'Policy Characteristics'!$C:$C,0))) -> Vehicle Subsidy | K75: =IF(ISBLANK(INDEX('Policy Characteristics'!E:E,MATCH($C75,'Policy Characteristics'!$C:$C,0))),"",INDEX('Policy Characteristics'!E:E,MATCH($C75,'Policy Characteristics'!$C:$C,0))) -> trans psgr subsidy | L75: =IF(ISBLANK(INDEX('Policy Characteristics'!F:F,MATCH($C75,'Policy Characteristics'!$C:$C,0))),"",INDEX('Policy Characteristics'!F:F,MATCH($C75,'Policy Characteristics'!$C:$C,0))) -> -60000000 | M75: =IF(ISBLANK(INDEX('Policy Characteristics'!G:G,MATCH($C75,'Policy Characteristics'!$C:$C,0))),"",INDEX('Policy Characteristics'!G:G,MATCH($C75,'Policy Characteristics'!$C:$C,0))) -> 60000000 | N75: =IF(ISBLANK(INDEX('Policy Characteristics'!H:H,MATCH($C75,'Policy Characteristics'!$C:$C,0))),"",INDEX('Policy Characteristics'!H:H,MATCH($C75,'Policy Characteristics'!$C:$C,0))) -> 100000 | O75: =IF(ISBLANK(INDEX('Policy Characteristics'!I:I,MATCH($C75,'Policy Characteristics'!$C:$C,0))),"",INDEX('Policy Characteristics'!I:I,MATCH($C75,'Policy Characteristics'!$C:$C,0))) -> KRW/vehicle | P75: =IF(ISBLANK(INDEX('Policy Characteristics'!J:J,MATCH($C75,'Policy Characteristics'!$C:$C,0))),"",INDEX('Policy Characteristics'!J:J,MATCH($C75,'Policy Characteristics'!$C:$C,0))) -> **Description:** This policy specifies the dollar amount offered as a subsidy to the purchaser of a new passenger vehicle. This is in addition to subsidies that exist in the BAU case. A negative value implies a tax or removal of subsidies. // **Guidance for setting values:** In South Korea, as of 2019, electric vehicle national subsidies were up to $7,628 and local subsidies were up to $5,933. In 2021, electric vehicle national subsidies are up to $6,781 and local subsidies are up to $5,933. Subsidies for Passenger-LDVs are 28% of the average car price, 24% for passenger-HDV, and 44% for freight-LDV. | Q75: =IF(ISBLANK(INDEX('Policy Characteristics'!K:K,MATCH($C75,'Policy Characteristics'!$C:$C,0))),"",INDEX('Policy Characteristics'!K:K,MATCH($C75,'Policy Characteristics'!$C:$C,0))) -> transportation-sector-main.html#ev-subsidy | R75: =IF(ISBLANK(INDEX('Policy Characteristics'!L:L,MATCH($C75,'Policy Characteristics'!$C:$C,0))),"",INDEX('Policy Characteristics'!L:L,MATCH($C75,'Policy Characteristics'!$C:$C,0))) -> ev-subsidy.html
... A104: =IF(ISBLANK(INDEX('Policy Characteristics'!A:A,MATCH($C104,'Policy Characteristics'!$C:$C,0))),"",INDEX('Policy Characteristics'!A:A,MATCH($C104,'Policy Characteristics'!$C:$C,0))) -> Transportation | B104: =IF(ISBLANK(INDEX('Policy Characteristics'!B:B,MATCH($C104,'Policy Characteristics'!$C:$C,0))),"",INDEX('Policy Characteristics'!B:B,MATCH($C104,'Policy Characteristics'!$C:$C,0))) -> Passenger Vehicle Subsidy | C104: =C$63 -> Additional Passenger Vehicle Subsidy | D104: motorbikes | E104: hydrogen vehicle | F104: Motorbikes | G104: Hydrogen vehicle | H104: 1685 | I104: Yes | J104: =IF(ISBLANK(INDEX('Policy Characteristics'!D:D,MATCH($C104,'Policy Characteristics'!$C:$C,0))),"",INDEX('Policy Characteristics'!D:D,MATCH($C104,'Policy Characteristics'!$C:$C,0))) -> Vehicle Subsidy | K104: =IF(ISBLANK(INDEX('Policy Characteristics'!E:E,MATCH($C104,'Policy Characteristics'!$C:$C,0))),"",INDEX('Policy Characteristics'!E:E,MATCH($C104,'Policy Characteristics'!$C:$C,0))) -> trans psgr subsidy | L104: =IF(ISBLANK(INDEX('Policy Characteristics'!F:F,MATCH($C104,'Policy Characteristics'!$C:$C,0))),"",INDEX('Policy Characteristics'!F:F,MATCH($C104,'Policy Characteristics'!$C:$C,0))) -> -60000000 | M104: =IF(ISBLANK(INDEX('Policy Characteristics'!G:G,MATCH($C104,'Policy Characteristics'!$C:$C,0))),"",INDEX('Policy Characteristics'!G:G,MATCH($C104,'Policy Characteristics'!$C:$C,0))) -> 60000000 | N104: =IF(ISBLANK(INDEX('Policy Characteristics'!H:H,MATCH($C104,'Policy Characteristics'!$C:$C,0))),"",INDEX('Policy Characteristics'!H:H,MATCH($C104,'Policy Characteristics'!$C:$C,0))) -> 100000 | O104: =IF(ISBLANK(INDEX('Policy Characteristics'!I:I,MATCH($C104,'Policy Characteristics'!$C:$C,0))),"",INDEX('Policy Characteristics'!I:I,MATCH($C104,'Policy Characteristics'!$C:$C,0))) -> KRW/vehicle | P104: =IF(ISBLANK(INDEX('Policy Characteristics'!J:J,MATCH($C104,'Policy Characteristics'!$C:$C,0))),"",INDEX('Policy Characteristics'!J:J,MATCH($C104,'Policy Characteristics'!$C:$C,0))) -> **Description:** This policy specifies the dollar amount offered as a subsidy to the purchaser of a new passenger vehicle. This is in addition to subsidies that exist in the BAU case. A negative value implies a tax or removal of subsidies. // **Guidance for setting values:** In South Korea, as of 2019, electric vehicle national subsidies were up to $7,628 and local subsidies were up to $5,933. In 2021, electric vehicle national subsidies are up to $6,781 and local subsidies are up to $5,933. Subsidies for Passenger-LDVs are 28% of the average car price, 24% for passenger-HDV, and 44% for freight-LDV. | Q104: =IF(ISBLANK(INDEX('Policy Characteristics'!K:K,MATCH($C104,'Policy Characteristics'!$C:$C,0))),"",INDEX('Policy Characteristics'!K:K,MATCH($C104,'Policy Characteristics'!$C:$C,0))) -> transportation-sector-main.html#ev-subsidy | R104: =IF(ISBLANK(INDEX('Policy Characteristics'!L:L,MATCH($C104,'Policy Characteristics'!$C:$C,0))),"",INDEX('Policy Characteristics'!L:L,MATCH($C104,'Policy Characteristics'!$C:$C,0))) -> ev-subsidy.html
A105: =IF(ISBLANK(INDEX('Policy Characteristics'!A:A,MATCH($C105,'Policy Characteristics'!$C:$C,0))),"",INDEX('Policy Characteristics'!A:A,MATCH($C105,'Policy Characteristics'!$C:$C,0))) -> Transportation | B105: =IF(ISBLANK(INDEX('Policy Characteristics'!B:B,MATCH($C105,'Policy Characteristics'!$C:$C,0))),"",INDEX('Policy Characteristics'!B:B,MATCH($C105,'Policy Characteristics'!$C:$C,0))) -> Freight Vehicle Subsidy | C105: Additional Freight Vehicle Subsidy | D105: LDVs | E105: battery electric vehicle | F105: Light and Medium Commercial Trucks | G105: Battery electric vehicle | H105: 1686 | I105: Yes | J105: =IF(ISBLANK(INDEX('Policy Characteristics'!D:D,MATCH($C105,'Policy Characteristics'!$C:$C,0))),"",INDEX('Policy Characteristics'!D:D,MATCH($C105,'Policy Characteristics'!$C:$C,0))) -> Vehicle Subsidy | K105: =IF(ISBLANK(INDEX('Policy Characteristics'!E:E,MATCH($C105,'Policy Characteristics'!$C:$C,0))),"",INDEX('Policy Characteristics'!E:E,MATCH($C105,'Policy Characteristics'!$C:$C,0))) -> trans frgt subsidy | L105: =IF(ISBLANK(INDEX('Policy Characteristics'!F:F,MATCH($C105,'Policy Characteristics'!$C:$C,0))),"",INDEX('Policy Characteristics'!F:F,MATCH($C105,'Policy Characteristics'!$C:$C,0))) -> -60000000 | M105: =IF(ISBLANK(INDEX('Policy Characteristics'!G:G,MATCH($C105,'Policy Characteristics'!$C:$C,0))),"",INDEX('Policy Characteristics'!G:G,MATCH($C105,'Policy Characteristics'!$C:$C,0))) -> 60000000 | N105: =IF(ISBLANK(INDEX('Policy Characteristics'!H:H,MATCH($C105,'Policy Characteristics'!$C:$C,0))),"",INDEX('Policy Characteristics'!H:H,MATCH($C105,'Policy Characteristics'!$C:$C,0))) -> 100000 | O105: =IF(ISBLANK(INDEX('Policy Characteristics'!I:I,MATCH($C105,'Policy Characteristics'!$C:$C,0))),"",INDEX('Policy Characteristics'!I:I,MATCH($C105,'Policy Characteristics'!$C:$C,0))) -> KRW/vehicle | P105: =IF(ISBLANK(INDEX('Policy Characteristics'!J:J,MATCH($C105,'Policy Characteristics'!$C:$C,0))),"",INDEX('Policy Characteristics'!J:J,MATCH($C105,'Policy Characteristics'!$C:$C,0))) -> **Description:** This policy specifies the dollar amount offered as a subsidy to the purchaser of a new freight vehicle. This is in addition to subsidies that exist in the BAU case. A negative value implies a tax or removal of subsidies. // **Guidance for setting values:** South Korea aims, by 2025, to deploy 193,000 electric trucks, 11,000 electric buses, 4,600 hydrogen buses, and 900 hydrogen trucks. The government operates a subsidy scheme that provides approximately KRW 16 million (≈ US $14,200) per truck, KRW 150 million (≈ US $133,200) per bus, and up to KRW 10 million (≈ US $8,900) per taxi. This initiative is regarded as a core national policy to establish a foundation for carbon neutrality in the transport sector through the expansion of electric and hydrogen vehicle adoption.(Sources: Ministry of Environment, “4th Basic Plan for Eco-friendly Vehicles(2021–2025)”) | Q105: =IF(ISBLANK(INDEX('Policy Characteristics'!K:K,MATCH($C105,'Policy Characteristics'!$C:$C,0))),"",INDEX('Policy Characteristics'!K:K,MATCH($C105,'Policy Characteristics'!$C:$C,0))) -> transportation-sector-main.html#ev-subsidy | R105: =IF(ISBLANK(INDEX('Policy Characteristics'!L:L,MATCH($C105,'Policy Characteristics'!$C:$C,0))),"",INDEX('Policy Characteristics'!L:L,MATCH($C105,'Policy Characteristics'!$C:$C,0))) -> ev-subsidy.html
A106: =IF(ISBLANK(INDEX('Policy Characteristics'!A:A,MATCH($C106,'Policy Characteristics'!$C:$C,0))),"",INDEX('Policy Characteristics'!A:A,MATCH($C106,'Policy Characteristics'!$C:$C,0))) -> Transportation | B106: =IF(ISBLANK(INDEX('Policy Characteristics'!B:B,MATCH($C106,'Policy Characteristics'!$C:$C,0))),"",INDEX('Policy Characteristics'!B:B,MATCH($C106,'Policy Characteristics'!$C:$C,0))) -> Freight Vehicle Subsidy | C106: =C$105 -> Additional Freight Vehicle Subsidy | D106: LDVs | E106: natural gas vehicle | F106: Light and Medium Commercial Trucks | G106: Natural gas vehicle | H106: 1687 | I106: Yes | J106: =IF(ISBLANK(INDEX('Policy Characteristics'!D:D,MATCH($C106,'Policy Characteristics'!$C:$C,0))),"",INDEX('Policy Characteristics'!D:D,MATCH($C106,'Policy Characteristics'!$C:$C,0))) -> Vehicle Subsidy | K106: =IF(ISBLANK(INDEX('Policy Characteristics'!E:E,MATCH($C106,'Policy Characteristics'!$C:$C,0))),"",INDEX('Policy Characteristics'!E:E,MATCH($C106,'Policy Characteristics'!$C:$C,0))) -> trans frgt subsidy | L106: =IF(ISBLANK(INDEX('Policy Characteristics'!F:F,MATCH($C106,'Policy Characteristics'!$C:$C,0))),"",INDEX('Policy Characteristics'!F:F,MATCH($C106,'Policy Characteristics'!$C:$C,0))) -> -60000000 | M106: =IF(ISBLANK(INDEX('Policy Characteristics'!G:G,MATCH($C106,'Policy Characteristics'!$C:$C,0))),"",INDEX('Policy Characteristics'!G:G,MATCH($C106,'Policy Characteristics'!$C:$C,0))) -> 60000000 | N106: =IF(ISBLANK(INDEX('Policy Characteristics'!H:H,MATCH($C106,'Policy Characteristics'!$C:$C,0))),"",INDEX('Policy Characteristics'!H:H,MATCH($C106,'Policy Characteristics'!$C:$C,0))) -> 100000 | O106: =IF(ISBLANK(INDEX('Policy Characteristics'!I:I,MATCH($C106,'Policy Characteristics'!$C:$C,0))),"",INDEX('Policy Characteristics'!I:I,MATCH($C106,'Policy Characteristics'!$C:$C,0))) -> KRW/vehicle | P106: =IF(ISBLANK(INDEX('Policy Characteristics'!J:J,MATCH($C106,'Policy Characteristics'!$C:$C,0))),"",INDEX('Policy Characteristics'!J:J,MATCH($C106,'Policy Characteristics'!$C:$C,0))) -> **Description:** This policy specifies the dollar amount offered as a subsidy to the purchaser of a new freight vehicle. This is in addition to subsidies that exist in the BAU case. A negative value implies a tax or removal of subsidies. // **Guidance for setting values:** South Korea aims, by 2025, to deploy 193,000 electric trucks, 11,000 electric buses, 4,600 hydrogen buses, and 900 hydrogen trucks. The government operates a subsidy scheme that provides approximately KRW 16 million (≈ US $14,200) per truck, KRW 150 million (≈ US $133,200) per bus, and up to KRW 10 million (≈ US $8,900) per taxi. This initiative is regarded as a core national policy to establish a foundation for carbon neutrality in the transport sector through the expansion of electric and hydrogen vehicle adoption.(Sources: Ministry of Environment, “4th Basic Plan for Eco-friendly Vehicles(2021–2025)”) | Q106: =IF(ISBLANK(INDEX('Policy Characteristics'!K:K,MATCH($C106,'Policy Characteristics'!$C:$C,0))),"",INDEX('Policy Characteristics'!K:K,MATCH($C106,'Policy Characteristics'!$C:$C,0))) -> transportation-sector-main.html#ev-subsidy | R106: =IF(ISBLANK(INDEX('Policy Characteristics'!L:L,MATCH($C106,'Policy Characteristics'!$C:$C,0))),"",INDEX('Policy Characteristics'!L:L,MATCH($C106,'Policy Characteristics'!$C:$C,0))) -> ev-subsidy.html
A107: =IF(ISBLANK(INDEX('Policy Characteristics'!A:A,MATCH($C107,'Policy Characteristics'!$C:$C,0))),"",INDEX('Policy Characteristics'!A:A,MATCH($C107,'Policy Characteristics'!$C:$C,0))) -> Transportation | B107: =IF(ISBLANK(INDEX('Policy Characteristics'!B:B,MATCH($C107,'Policy Characteristics'!$C:$C,0))),"",INDEX('Policy Characteristics'!B:B,MATCH($C107,'Policy Characteristics'!$C:$C,0))) -> Freight Vehicle Subsidy | C107: =C$105 -> Additional Freight Vehicle Subsidy | D107: LDVs | E107: gasoline vehicle | F107: Light and Medium Commercial Trucks | G107: Gasoline vehicle | H107: 1688 | I107: No | J107: =IF(ISBLANK(INDEX('Policy Characteristics'!D:D,MATCH($C107,'Policy Characteristics'!$C:$C,0))),"",INDEX('Policy Characteristics'!D:D,MATCH($C107,'Policy Characteristics'!$C:$C,0))) -> Vehicle Subsidy | K107: =IF(ISBLANK(INDEX('Policy Characteristics'!E:E,MATCH($C107,'Policy Characteristics'!$C:$C,0))),"",INDEX('Policy Characteristics'!E:E,MATCH($C107,'Policy Characteristics'!$C:$C,0))) -> trans frgt subsidy | L107: =IF(ISBLANK(INDEX('Policy Characteristics'!F:F,MATCH($C107,'Policy Characteristics'!$C:$C,0))),"",INDEX('Policy Characteristics'!F:F,MATCH($C107,'Policy Characteristics'!$C:$C,0))) -> -60000000 | M107: =IF(ISBLANK(INDEX('Policy Characteristics'!G:G,MATCH($C107,'Policy Characteristics'!$C:$C,0))),"",INDEX('Policy Characteristics'!G:G,MATCH($C107,'Policy Characteristics'!$C:$C,0))) -> 60000000 | N107: =IF(ISBLANK(INDEX('Policy Characteristics'!H:H,MATCH($C107,'Policy Characteristics'!$C:$C,0))),"",INDEX('Policy Characteristics'!H:H,MATCH($C107,'Policy Characteristics'!$C:$C,0))) -> 100000 | O107: =IF(ISBLANK(INDEX('Policy Characteristics'!I:I,MATCH($C107,'Policy Characteristics'!$C:$C,0))),"",INDEX('Policy Characteristics'!I:I,MATCH($C107,'Policy Characteristics'!$C:$C,0))) -> KRW/vehicle | P107: =IF(ISBLANK(INDEX('Policy Characteristics'!J:J,MATCH($C107,'Policy Characteristics'!$C:$C,0))),"",INDEX('Policy Characteristics'!J:J,MATCH($C107,'Policy Characteristics'!$C:$C,0))) -> **Description:** This policy specifies the dollar amount offered as a subsidy to the purchaser of a new freight vehicle. This is in addition to subsidies that exist in the BAU case. A negative value implies a tax or removal of subsidies. // **Guidance for setting values:** South Korea aims, by 2025, to deploy 193,000 electric trucks, 11,000 electric buses, 4,600 hydrogen buses, and 900 hydrogen trucks. The government operates a subsidy scheme that provides approximately KRW 16 million (≈ US $14,200) per truck, KRW 150 million (≈ US $133,200) per bus, and up to KRW 10 million (≈ US $8,900) per taxi. This initiative is regarded as a core national policy to establish a foundation for carbon neutrality in the transport sector through the expansion of electric and hydrogen vehicle adoption.(Sources: Ministry of Environment, “4th Basic Plan for Eco-friendly Vehicles(2021–2025)”) | Q107: =IF(ISBLANK(INDEX('Policy Characteristics'!K:K,MATCH($C107,'Policy Characteristics'!$C:$C,0))),"",INDEX('Policy Characteristics'!K:K,MATCH($C107,'Policy Characteristics'!$C:$C,0))) -> transportation-sector-main.html#ev-subsidy | R107: =IF(ISBLANK(INDEX('Policy Characteristics'!L:L,MATCH($C107,'Policy Characteristics'!$C:$C,0))),"",INDEX('Policy Characteristics'!L:L,MATCH($C107,'Policy Characteristics'!$C:$C,0))) -> ev-subsidy.html
