Workbook

Sheet About
A1: Web App Data
A3: This spreadsheet contains data that is used to populate the web application interface
A4: for the Energy Policy Simulator. The data in other tabs in this spreadsheet are used
A5: to establish the policy levers, lever bounds, descriptive text for pop-over
A6: panels, output graphs, and reference scenarios available in the web app.
A8: A live version of the web application interface powered by a copy of this model
A9: can be found at:
A10: https://www.energypolicy.solutions
A12: You are unlikely to need to use or change the contents of this spreadsheet, unless
A13: you are adapting the Energy Policy Simulator to a new country and desire
A14: a web application interface customized for your country-specific model version.
A16: Checks for Policy ID Number Validity
A17: Max policy ID number in use | B17: =MAX(PolicyLevers!H:H) -> 2798
A18: Lowest duplicate ID number | B18: {=IF(MIN(IF(COUNTIF(PolicyLevers!$H$2:$H$2053,PolicyLevers!$H$2:$H$2053)>1,PolicyLevers!$H$2:$H$2053, ""))=0,"No duplicate ID numbers",MIN(IF(COUNTIF(PolicyLevers!$H$2:$H$2053,PolicyLevers!$H$2:$H$2053)>1,PolicyLevers!$H$2:$H$2053, "")))} -> No duplicate ID numbers
A19: Row of first policy missing a valid ID number | B19: {=IF(MIN(IF((NOT(ISNUMBER(PolicyLevers!$H$2:$H$2053)))*(ISTEXT(PolicyLevers!$I$2:$I$2053)),ROW(PolicyLevers!$H$2:$H$2053)))=0,"No missing ID numbers",MIN(IF((NOT(ISNUMBER(PolicyLevers!$H$2:$H$2053)))*(ISTEXT(PolicyLevers!$I$2:$I$2053)),ROW(PolicyLevers!$H$2:$H$2053))))} -> No missing ID numbers
A21: Customizing Policy Levers
A22: Define most policy properties on the "Policy Characteristics" tab.
A23: Specify the subscripted elements of each policy and which are enabled/disabled on the "PolicyLevers" tab.
A24: On the PolicyLevers tab, only manually edit the cells under the green column headers. Simply extend the
A25: existing formulas up or down to fill cells under the red headers on that tab.
A27: Notes on Meaning of Blank Cells on the Policy Characteristics Tab
A28: Leave the "Policy Schedule Subscript" cell blank to deny the ability to edit the implementation
A29: schedule for a lever. This should generally only be done for levers that do not use an
A30: implementation schedule: the toggle to Non-BAU Mandated Capacity Construction
A31: (which has its own schedule built into its input data) and the Nuclear Lifetime Extension
A32: (which simply delays retirements that would occur in the BAU Retirements input data).
A34: Leave the "Policy Group" cell blank to exclude a lever from wedge diagrams and abatement cost curves.
... A59: are ignored. The web app will look for an equals sign in Units to choose the selector input control.

Sheet Policy Characteristics
A1: This tab contains information about each policy that does not vary by subscripted element of that policy.
A2: It matches policies to the listing in the "PolicyLevers" tab using the "Vensim Variable Name" column.
A3: Sector | B3: Short Name | C3: Vensim Variable Name | D3: Policy Group | E3: Policy Schedule Subscript | F3: Min Slider Value | G3: Max Slider Value | H3: Slider Step Size | I3: Units | J3: Text for Pop-Over Panel Description | K3: URL for "How the model handles this policy" links | L3: URL for "How to design this policy well" links | M3: Source for Guidance Text (if any) | N3: Source for Max Slider Value (if any)
A4: Transportation | B4: Conventional Pollutant Standards | C4: Percentage Reduction of Separately Regulated Pollutants | D4: Conventional Pollutant Standard | E4: trans reduce regulated pollutants | F4: 0 | G4: 1 | H4: 0.02 | I4: % reduction in emissions | J4: **Description:** This policy represents strengthening standards for the selected pollutant(s) emitted by the selected vehicle type(s). Conventional pollutants' most important, harmful impacts are on human health rather than on climate change. // **Guidance for setting values:** In South Korea, the 24-hour national ambient air quality standard (NAAQS) for PM2.5, the most harmful type of particulate for human health, is 35 µg/m^3. For example, setting this policy lever to 5% means that the emission intensity for the selected pollutant(s) will be reduced by 5% relative to the current level, reflecting tighter tailpipe standards or enhanced inspection and maintenance programs. This level can be interpreted as a modest but meaningful tightening of emission control requirements. | K4: transportation-sector-main.html#conv-pol-stds | L4: conventional-pollutant-standards.html
A5: Transportation | B5: Electric Vehicle Charger Deployment | C5: Percentage Increase in EV Chargers | D5: EV Charger Deployment | E5: trans EV charger deployment | F5: -1 | G5: 3 | H5: 0.1 | I5: % change | J5: **Description:** This policy represents EV chargers deployed in addition to the Business-As-Usual (BAU) scenario, including DC fast chargers and Level 2 chargers. The lever is expressed as a percentage change from the BAU deployment level, applied to the cumulative charger stock rather than annual installations. This policy instrument does not directly affect energy use, emissions, or vehicle deployment. Its primary purpose is to account for the additional infrastructure costs associated with expanded charging networks.//**Guidance for setting values:** Considering the growth rate of EV charger deployment between 2020 and 2024, the BAU scenario assumes approximately 930,000 chargers by 2030. A setting of 300% means that chargers equal to three times the BAU quantity are added, resulting in a total stock equal to four times the BAU level. As of December 2021, South Korea had a total of 94,041 EV chargers, which corresponds to approximately 181 chargers per 100,000 people. For comparison, as of December 2020, there were 12,635 domestic gas stations, each with an average of 14 fueling pumps, corresponding to approximately 342 fueling pumps per 100,000 people. The South Korean government has set a target of 1.23 million EV chargers by 2030. | L5: ev-charger-deployment.html | M5: Number of EV chargers: https://evadoption.com/ev-charging-stations-statistics/ Number of gas stations: U.S. Census, Statistics of U.S. Businesses, https://www.census.gov/data/tables/2016/econ/susb/2016-susb-annual.html Pumps per station: https://247wallst.com/economy/2014/05/22/why-are-there-115000-or-150000-gas-stations-in-america/
A6: Transportation | B6: Electric Vehicle Range | C6: Reduce EV Range Anxiety | D6: EV Range & Charging Time | E6: trans reduce EV range anxiety | F6: 0 | G6: 1 | H6: 0.02 | I6: % reduction in concern | J6: **Description:** This policy specifies a percentage reduction in vehicle buyers' aversion to electric vehicles due to concerns over the vehicles' range (how far the EV can travel on a charge). A 100% setting implies consumers are no more concerned about EV range and charging time than they are about range and fueling time of gasoline vehicles. It does not imply that range is infinite. This policy only affects passenger cars and SUVs (most light-duty road vehicles). // **Guidance for setting values:** U.S. model year 2017 all-electric (not hybrid) vehicles had ranges from 58 to 335 miles (median 114 miles). | L6: reduce-range-anxiety-charging-time.html | M6: Ranges: https://www.energy.gov/eere/vehicles/articles/fotw-1010-january-1-2018-all-electric-light-vehicle-ranges-can-exceed-those Charging Times: https://www.chargepoint.com/files/Quick_Guide_to_Fast_Charging.pdf
A7: Transportation | B7: Passenger Vehicle Subsidy | C7: Additional Passenger Vehicle Subsidy | D7: Vehicle Subsidy | E7: trans psgr subsidy | F7: =-60000000/1000 -> -60000 | G7: =60000000/1000 -> 60000 | H7: 1000 | I7: thousand KRW/vehicle | J7: **Description:** This policy specifies the subsidy amount offered to purchasers of new passenger vehicle. This is in addition to subsidies that exist in the BAU case. A negative value implies a tax or removal of subsidies. // **Guidance for setting values:** As of 2025, South Korea provides substantial purchase subsidies for zero-emission vehicles. For battery electric vehicles (BEVs), the maximum combined national and local subsidy is KRW 6.4 million. For hydrogen fuel cell vehicles (FCEVs), the maximum subsidy reaches KRW 29.5 million. For heavy-duty vehicles, the support is even more significant: large battery-electric HDVs receive up to KRW 198.12 million (combined national and Seoul municipal subsidies), while hydrogen-powered buses and large vans can receive up to KRW 350 million. These subsidy levels can be used as reference points when setting the policy lever values. | K7: transportation-sector-main.html#ev-subsidy | L7: ev-subsidy.html | M7: https://www.fueleconomy.gov/feg/taxevb.shtml plus Chevrolet and Tesla websites
A8: Transportation | B8: Freight Vehicle Subsidy | C8: Additional Freight Vehicle Subsidy | D8: Vehicle Subsidy | E8: trans frgt subsidy | F8: =-60000000/1000 -> -60000 | G8: =60000000/1000 -> 60000 | H8: 1000 | I8: thousand KRW/vehicle | J8: **Description:** This policy specifies the amount of subsidy provided to purchasers of new freight trucks. This value represents additional support on top of what already exists in the BAU scenario. A negative value indicates a reduction of existing subsidies or the imposition of a tax. //**Guidance for setting values:** As of 2025, subsidies for light electric freight trucks in Korea can reach up to 7.67 million KRW (combined national and local support), while subsidies for heavy-duty electric trucks can reach up to 19.9 million KRW. Korea aims to deploy 193,000 electric trucks and 900 hydrogen trucks by 2025. (Source: Ministry of Environment, 4th Basic Plan for Eco-Friendly Vehicles (2021–2025)) | K8: transportation-sector-main.html#ev-subsidy | L8: ev-subsidy.html
A9: Transportation | B9: Feebate | C9: LDVs Feebate Rate | D9: Feebate | E9: trans LDVs feebate | F9: 0 | G9: 1 | H9: 0.02 | I9: % of global best practice rate | J9: **Description:** This policy imposes a fee on the sale of inefficient light-duty road vehicles (LDVs), including passenger cars and SUVs, and uses the resulting revenue to provide rebates for more efficient LDVs. The policy is designed to be revenue-neutral, as the pivot point (the efficiency level that incurs neither a rebate nor a fee) is set such that the total of all fees equals the total of all rebates.//**Guidance for setting values:** The lever is expressed as a percentage of the global best-practice feebate rate. The benchmark rate is $2,000 per 0.01 gallon per mile (gpm). For example, a vehicle rated at 20 mpg consumes 0.05 gpm, while a vehicle rated at 25 mpg consumes 0.04 gpm. The difference is 0.01 gpm, resulting in a $2,000 fee when the pivot point is 25 mpg. South Korea considered the introduction of a feebate-type Low-Carbon Vehicle Cooperation Scheme, but the scheme was not ultimately implemented. | K9: transportation-sector-main.html#feebate | L9: feebate.html | M9: Greene et al., 2005, "Feebates, rebates and gas-guzzler taxes: a study of incentives for increased fuel economy", Energy Policy, 33(6), 757-775, http://cta.ornl.gov/cta/Publications/Reports/FeebateEnergyPolicy_FINAL.pdf. | N9: John German and Dan Meszler, 2010, "Best Practices for Feebate Program Design and Implementation", ICCT, http://www.theicct.org/sites/default/files/publications/ICCT_feebates_may2010.pdf, Table 2
A10: Transportation | B10: Fuel Economy Standard | C10: Percentage Additional Improvement of Fuel Economy Std | D10: Vehicle Fuel Economy Standards | E10: trans fuel economy standards | F10: -0.25 | G10: =ROUND(MaxBoundCalculations!B88,1) -> 1 | H10: 0.01 | I10: % change in miles/gal | J10: **Description**: This policy specifies a percentage improvement in fuel economy (distance traveled on the same quantity of fuel with the same cargo or passenger loading) due to fuel economy standards for newly sold vehicles of the selected type(s) with fossil fuel-burning engines. //**Guidance for setting values** : LDVs (Light Duty Vehicles): South Korea combined fuel economy standards for light duty cars is 67.5mpg (28.7 km/L) (at 1070kg inertia weight) and light trucks is 44.9mpg(19.1 km/L)(at 1070kg inertia weight) in 2021. These are scheduled to rise to 89.6mpg (38.1 km/L, Approximately 33% improvement) (at 1110kg inertia weight) for cars and 51.0mpg(21.7 km/L, Approximately 14% improvement) (at 1110kg inertia weight) for light trucks through 2030, then remain constant. In South Korea, there is no plan for other vehicles' fuel economy. This data is based on the "Notice on Automobile Average Energy Consumption Efficiency Standards, Greenhouse Gas Emission Standards, and Application and Management of Standards." | K10: transportation-sector-main.html#fuel-econ-std | L10: fuel-economy-standard.html | M10: U. S. EPA, 2012, "Fact Sheet: EPA and NHTSA Set Standards to Reduce Greenhouse Gases and Improve Fuel Economy for Model Years 2017-2025 Cars and Light Trucks", https://nepis.epa.gov/Exe/ZyNET.exe/P100EZ7C.txt?ZyActionD=ZyDocument&Client=EPA&Index=2011%20Thru%202015&Docs=&Query=&Time=&EndTime=&SearchMethod=1&TocRestrict=n&Toc=&TocEntry=&QField=&QFieldYear=&QFieldMonth=&QFieldDay=&UseQField=&IntQFieldOp=0&ExtQFieldOp=0&XmlQuery=&File=D%3A%5CZYFILES%5CINDEX%20DATA%5C11THRU15%5CTXT%5C00000005%5CP100EZ7C.txt&User=ANONYMOUS&Password=anonymous&SortMethod=h%7C-&MaximumDocuments=1&FuzzyDegree=0&ImageQuality=r75g8/r75g8/x150y150g16/i425&Display=hpfr&DefSeekPage=x&SearchBack=ZyActionL&Back=ZyActionS&BackDesc=Results%20page&MaximumPages=1&ZyEntry=4, Table 1, Row 4. U.S. EPA, 2015, "EPA and NHTSA Propose Standards to Reduce Greenhouse Gas Emissions and Improve Fuel Efficiency of Medium- and Heavy-Duty Vehicles for Model Year 2018 and Beyond", https://nepis.epa.gov/Exe/ZyNET.exe/P100P7NL.txt?ZyActionD=ZyDocument&Client=EPA&Index=2016%20Thru%202020&Docs=&Query=&Time=&EndTime=&SearchMethod=1&TocRestrict=n&Toc=&TocEntry=&QField=&QFieldYear=&QFieldMonth=&QFieldDay=&UseQField=&IntQFieldOp=0&ExtQFieldOp=0&XmlQuery=&File=D%3A%5CZYFILES%5CINDEX%20DATA%5C16THRU20%5CTXT%5C00000002%5CP100P7NL.txt&User=ANONYMOUS&Password=anonymous&SortMethod=h%7C-&MaximumDocuments=1&FuzzyDegree=0&ImageQuality=r75g8/r75g8/x150y150g16/i425&Display=hpfr&DefSeekPage=x&SearchBack=ZyActionL&Back=ZyActionS&BackDesc=Results%20page&MaximumPages=1&ZyEntry=3, Page 3. https://theicct.org/sites/default/files/publications/ICCT_ShipEfficiency_20130723.pdf Others calculated from model input data. | N10: National Research Council, 2013, "Transitions to Alternative Vehicles and Fuels", https://www.nap.edu/catalog/18264/transitions-to-alternative-vehicles-and-fuels, Table 2.9, Fuel economy test mpg. U.S. DoE, 2013, "Potential for Energy Efficiency Improvement Beyond the Light-Duty-Vehicle Sector," http://www.nrel.gov/docs/fy13osti/55637.pdf, Table 2.2 and Section 3.4.5, Paragraph 1 David McCollum, Gregory Gould, and Davide Greene, 2009, "Greenhouse Gas Emissions from Aviation and Marine Transportation: Mitigation Potential and Policies", Pew Center on Global Climate Change, http://www.c2es.org/docUploads/aviation-and-marine-report-2009.pdf, Table 4 https://theicct.org/sites/default/files/publications/ICCT_ShipEfficiency_20130723.pdf
A11: Transportation | B11: Low Carbon Fuel Standard | C11: Additional LCFS Percentage | D11: Low Carbon Fuel Standard | E11: trans LCFS | F11: 0 | G11: 1 | H11: 0.01 | I11: % reduction in carbon emissions | J11: **Description:** This policy specifies the percentage reduction in carbon emissions from the transportation sector that must be achieved via fuel switching. By default, this policy applies to all non-aviation vehicle types. If the lever Non-BAU LCFS-Qualifying Vehicles is enabled, this policy only applies to aviation and represents the use of sustainable aviation fuels. The value set in this lever is in addition to BAU requirements. // **Guidance for setting values:** Although South Korea has not yet adopted a Low Carbon Fuel Standard (LCFS) system, which directly regulates the Carbon Intensity (CI) of fuels like the United States or Europe, it operates a similar policy known as the Renewable Fuel Standard (RFS). This policy mandates the blending of renewable fuels, such as biodiesel, into fossil fuels like diesel at a certain percentage, aiming to reduce greenhouse gas emissions in the transportation sector by lowering the carbon content of the fuel itself. //Although this system regulates the blending ratio of fuel components, it effectively serves to gradually reduce the carbon emission intensity of transportation fuels, leading to its evaluation as the foundational form of a Korean-style LCFS. (Source: Ministry of Trade, Industry and Energy's Enforcement Decree of the Renewable Energy Development, Use and Dissemination Promotion Act, Korea Energy Agency Renewable Energy Center RFS system explanatory materials, 2024 basis) | K11: transportation-sector-main.html#lcfs | L11: low-carbon-fuel-standard.html | M11: https://www.arb.ca.gov/fuels/lcfs/background/basics.htm
A12: Transportation | B12: Non-BAU LCFS-Qualifying Vehicles | C12: Boolean Use Non BAU LCFS Vehicle Types | D12: Low Carbon Fuel Standard | E12: trans LCFS vehicles | F12: 0 | G12: 1 | H12: 1 | I12: on/off | J12: **Description:** This lever changes which vehicles qualify under the low carbon fuel standard. With the lever off, LCFS-qualifying vehicles include all vehicle types except aircraft. With the lever on, only aircraft qualify. | K12: transportation-sector-main.html#lcfs | L12: low-carbon-fuel-standard.html | M12: https://www.arb.ca.gov/fuels/lcfs/background/basics.htm
A13: Transportation | B13: Mode Shifting | C13: Percent of Travel Demand Shifted to Other Modes or Eliminated | D13: Mode Shifting | E13: trans mode shifting | F13: 0 | G13: 0.5 | H13: 0.01 | I13: % of trips shifted | J13: **Description:** This policy represents a set of measures aimed at reducing demand for passenger or freight transportation in the selected vehicle type(s). **Passenger car and SUV** trips may be shifted to other travel modes, such as buses, rail, walking, biking, or eliminated through technology such as videoconferencing. Example measures include improved public transit systems, more walking and bike paths, zoning for higher density along transit corridors, zoning for mixed-use developments, roadway and congestion pricing, and increased parking fees. **Commercial passenger and freight flight** trips may be shifted to inter-city rail or eliminated using technology such as videoconferencing. **Heavy Heavy Duty Truck** trips can be reduced through improved logistics that avoids backhauls and transporting empty shipping containers. The following descriptions detail the different vehicle types: // **Passenger cars and SUVs:** most light-duty road vehicles // **Heavy Duty Trucks:** all other heavy road vehicles (mostly freight trucks) // **Commercial passenger flights:** this is not general aviation // **Guidance for setting values:** The Korean government aims to reduce the total vehicle travel distance of internal combustion engine vehicles by 39%–47% from the 2018 level by 2035 through demand management measures. | K13: transportation-sector-main.html#tdm | L13: transportation-demand-management.html | M13: International Energy Agency, 2009, "Transport, Energy and CO2: Moving toward Sustainability", http://www.iea.org/publications/freepublications/publication/transport2009.pdf "Freight Facts and Figures", 2013, https://ops.fhwa.dot.gov/freight/freight_analysis/nat_freight_stats/docs/13factsfigures/pdfs/fff2013_highres.pdf
A14: Transportation | B14: Federal Zero-Emission Vehicle Sales Standard | C14: Additional Minimum Required ZEV Sales Percentage for Model Region | D14: ZEV Sales Standard | E14: trans ZEV minimum | F14: -1 | G14: 1 | H14: 0.01 | I14: % of new vehicles sold | J14: **Description:** This policy requires a specified percentage of newly sold vehicles of the selected type(s) to consist of zero-emission vehicles. If that percentage would already be achieved through BAU sales plus the effects of other policies, such as an EV subsidy, this policy has no effect. Manufactures may meet a sales standard through techniques such as more heavily marketing electric vehicles, lowering the price of electric vehicles, or raising the price of non-electric vehicles. A negative setting for this lever implies a decrease in ZEV sales requirements relative to the Current Policies scenario. The following descriptions detail the different vehicle types: // **Passenger Cars and SUVs:** most light-duty road vehicles //**Light and Medium Freight Trucks:** commercial trucks carrying freight, not passengers // **Buses:** including school, transit, and intercity buses // **Heavy Duty Trucks:** all other heavy road vehicles (mostly freight trucks) // **Passenger Motorbikes:** registered motorcycles //**Guidance for setting values:** // In South Korea, by 2025, EVs will account for about 20% of new car sales by 2025, and about 31% of new car sales by 2030, in "4th Eco-friendly Vehicle Master Plan" planed by Ministry of Trade, Industry and Energy(MOTIE). | K14: transportation-sector-main.html#ev-mandate | L14: ev-mandate.html | M14: https://autoalliance.org/energy-environment/state-electric-vehicle-mandate/ https://www.cnbc.com/2019/08/26/colorado-joins-california-in-requiring-automakers-to-sell-more-evs.html https://www.consumerreports.org/hybrids-evs/california-says-new-cars-sold-in-the-state-must-be-zero-emissions-by-2035/ https://www.greentechmedia.com/articles/read/electric-buses-are-going-to-dominate statistics from FoVObE variable https://www.prnewswire.com/news-releases/electric-boats-and-ships-2017-2027-300561222.html
A15: Transportation | B15: Non-BAU ZEV-Qualifying Vehicles | C15: Boolean Use Non BAU ZEV Qualifying Vehicle Definitions | D15: ZEV Sales Standard | E15: trans non BAU ZEV vehicle definitions | F15: 0 | G15: 1 | H15: 1 | I15: on/off | J15: **Description:** This lever changes which vehicles qualify under the ZEV standard. With the lever off, ZEV-qualifying vehicles include battery electric vehicles, plugin hybrid vehicles, and hydrogen-fueled vehicles. With the lever on, only battery electric vehicles and hydrogen-fueled vehicles qualify.
A16: Transportation | B16: Subsidy for Vehicle Battery Production | C16: Additional Subsidy for Vehicle Battery Production | D16: Vehicle Battery Production Subsidy | E16: trans battery subsidy | F16: =-100000/1000 -> -100 | G16: =100000/1000 -> 100 | H16: =G16/100 -> 1 | I16: thousand KRW/kWh | J16: **Description:** This policy establishes a direct subsidy (in thousand KRW per kWh) for vehicle battery production. Since South Korea currently lacks a direct subsidy for manufacturers, the value entered here represents the total newly introduced subsidy. The subsidy is applied to all units based on the assumption that 100% of vehicle batteries are produced domestically. A negative value indicates a tax or a reduction in existing support measures.//**Guidance for setting values:** Unlike the U.S. Inflation Reduction Act (IRA), South Korea currently promotes the market through consumer-side EV purchase subsidies rather than direct manufacturer incentives. This lever allows for modeling a scenario where direct financial support is provided to producers. For modeling purposes, it is assumed that all vehicle batteries used in the market are manufactured within South Korea.
A17: Transportation | B17: Non-BAU State-Level Zero-Emission Vehicle Sales Standard | C17: Boolean Use Non BAU Minimum Required ZEV Sales Percentage by Subregion | D17: ZEV Sales Standard | E17: trans non BAU ZEV minimum | F17: 0 | G17: 1 | H17: 1 | I17: on/off | J17: **Description:** This policy allows the model to apply alternate assumptions for minimum required ZEV (specified through an input data file) sales percentages by region. However, since South Korea does not implement region-specific (subnational) ZEV sales mandates, this policy effectively defaults to the nationally applied BAU requirement in the Korean EPS model. Consequently, the Boolean switch should remain off (0) to ensure the model consistently uses the national BAU ZEV sales percentages.
A18: Transportation | B18: Non-BAU Max Fuel Consumption by Vehicle Type | C18: Boolean Use Non BAU Max Fuel Consumption by Veh Type | D18: Low Carbon Fuel Standard | F18: 0 | G18: 1 | H18: 1 | I18: on/off | J18: **Description:** The EPS' LCFS policy can be used to drive deployment of alternative fuels such as sustainable aviation fuel or drop-in renewable diesel. The LCFS' maximum potential is determined by the carbon intensity of each fuel and the maximum potential for those fuels' use in vehicles (e.g., cars can use up to 15% ethanol). This Boolean substitutes an alternative maximum potential for alternative fuels in vehicles, allowing the user to test scenarios with differing assumptions about technology advancement.
A19: Buildings and Appliances | B19: Building Component Electrification | C19: Fraction of New Bldg Components Shifted to Other Fuels | D19: Building Component Electrification | E19: bldgs new component fuel shifting | F19: 0 | G19: 1 | H19: 0.01 | I19: % of newly sold non-electric building components | J19: **Description:** This policy replaces the specified fraction of newly sold non-electric building components of the selected type(s) in buildings of the selected type(s) with electricity-using components. // **Guidance for setting values:**//**Urban Residential Heating:** In the BAU case, the share of electricity used for space heating in urban residential buildings in South Korea is 3% in 2021 and remains nearly constant at around 5% through 2050.//**Urban Residential Appliances:**Under BAU, the share of electricity used for appliances in urban residential buildings increases from 72% in 2021 to approximately 80% by 2050.//**Rural Residential Heating:**In the BAU scenario, electricity accounts for about 5% of heating energy use in rural residential buildings, and this share remains nearly unchanged through 2050.//**Rural Residential Appliances:**For rural residential buildings, the electricity share for appliance energy use increases from 72% in 2021 to approximately 80% by 2050 in the BAU case.//**Commercial Heating:**For commercial buildings in South Korea, the electricity share of heating energy use remains nearly constant at about 49–50% through 2050 under BAU.//**Commercial Appliances:**In the BAU case, the electricity share for appliance energy use in commercial buildings maintains a level of roughly 37–40% through 2050.//**Commercial Other Components:**For other commercial building components, the electricity share remains at 100% through 2050 under the BAU scenario. | K19: buildings-sector-main.html#component-elec | L19: building-component-electrification.html | M19: EIA AEO
A20: Buildings and Appliances | B20: Building Energy Efficiency Standards | C20: Reduction in E Use Allowed by Component Eff Std | D20: Building Energy Efficiency Standards | E20: bldgs efficiency standards | F20: 0 | G20: 0.75 | H20: 0.01 | I20: % reduction in energy use | J20: **Description:** This policy tightens energy efficiency standards for the selected component(s) in the selected building type(s). The policy only applies to newly sold components each year (whether for new buildings or replacement of old components of existing buildings). // **Guidance for setting values:** In "2050 Carbon Neutral Scenario" (2021), the South Korean government considered approximately 23% reduction in building energy use from 2018 to 2050. | K20: buildings-sector-main.html#eff-stds | L20: building-energy-efficiency-standards.html | M20: Edison Foundation, 2011, "Assessment of Electricity Savings in the U.S. Achievable through New Appliance/Equipment Efficiency Standards and Building Efficiency Codes (2010 - 2025)", http://www.edisonfoundation.net/iei/Documents/IEE_CodesandStandardsAssessment_2010-2025_UPDATE.pdf, Page B-2, Table B-1. | N20: Itron, 2007, "ASSESSMENT OF LONG-TERM ELECTRIC ENERGY EFFICIENCY POTENTIAL IN CALIFORNIA’S RESIDENTIAL SECTOR," http://www.energy.ca.gov/2007publications/CEC-500-2007-002/CEC-500-2007-002.PDF, p.33, Table 5-1
A21: Buildings and Appliances | B21: Contractor Training | C21: Boolean Improved Contractor Edu and Training | D21: Contractor Training | E21: bldgs contractor training | F21: 0 | G21: 1 | H21: 1 | I21: on/off | J21: **Description:** This policy represents a program to train contractors in energy-efficient products and installation practices. This covers activities such as air sealing, building framing, and choice and application of insulation. This policy affects newly sold building envelope components, which reduce the energy use of heating, cooling, and ventilation systems in buildings by 3.7% (based on a 2006 study from the Energy Center of Wisconsin). | K21: buildings-sector-main.html#contractor-ed | L21: contractor-training.html
A22: Buildings and Appliances | B22: Distributed Solar Carve-Out | C22: Min Fraction of Total Elec Demand to be Met by Distributed Solar PV | D22: Distributed Solar Promotion | E22: bldgs min fraction distributed solar | F22: 0 | G22: 0.5 | H22: 0.005 | I22: minimum % elec from solar | J22: **Description:** This policy requires at least the specified percentage of total retail electricity demand to be generated by residential and commercial buildings' distributed solar systems (typically rooftop PV). // **Guidance for setting values:**Public parking lots in Korea are legally required to install solar photovoltaic systems to promote renewable energy use. In addition, public institutions must equip new, expanded, or renovated buildings over 1,000 m² with renewable energy systems, ensuring that at least 32% of their energy use comes from renewables (as of 2022). | K22: buildings-sector-main.html#solar-carve-out | L22: solar-carve-out.html | M22: MASSACHUSETTS: http://www.mass.gov/eea/energy-utilities-clean-tech/renewable-energy/solar/rps-solar-carve-out/current-status-of-the-rps-solar-carve-out-program.html COLORADO: http://www.seia.org/research-resources/rps-solar-carve-out-colorado | N22: RMI, 2011, "Reinventing Fire Electricity Sector Methodology," http://www.rmi.org/cms/Download.aspx?id=10765&file=Reinventing+Fire+Electricity+Sector+Methodology.pdf&title=Reinventing+Fire+Electricity+Sector+Methodology, Page 11, 2050 Generation by Case
A23: Buildings and Appliances | B23: Distributed Solar Subsidy | C23: Additional Perc Subsidy for Distributed Solar PV Capacity | D23: Distributed Solar Promotion | E23: bldgs distributed solar subsidy | F23: 0 | G23: 0.5 | H23: 0.01 | I23: % of PV system cost | J23: **Description:** This policy causes the government to reimburse building owners for an additional percentage of the cost of new distributed solar PV capacity that is installed on or around buildings. // **Guidance for setting values:** In South Korea, support for distributed solar PV is primarily implemented through direct installation grants and low-interest financing programs. The subsidy rate is estimated by dividing the unit subsidy amount by the total installation cost. For urban residential buildings, this rate is estimated at 13%, while for rural residential buildings, it is approximately 16%. | K23: buildings-sector-main.html#distributed-solar-subsidy | L23: distributed-solar-subsidy.html | M23: Department of Energy. Business Energy Investment Tax Credit (ITC). http://energy.gov/savings/business-energy-investment-tax-credit-itc
A24: Buildings and Appliances | B24: Distributed Solar Capacity Requirement | C24: Min Required Rooftop Solar Capacity | D24: Distributed Solar Promotion | E24: bldgs min req rooftop solar | F24: 0 | G24: 100000 | H24: 200 | I24: MW | J24: **Description:** This policy requires at least the specified capacity of distributed solar be built by the model. // **Guidance for setting values:** The NEXTgroup estimated South Korea’s rooftop solar potential — including general buildings and industrial complexes — at approximately 42.2 GW.
A25: Buildings and Appliances | B25: Non BAU Distributed Solar Capacity | C25: Boolean Use Non BAU Distributed Solar Capacity | D25: Distributed Solar Promotion | E25: non BAU dist solar | F25: 0 | G25: 1 | H25: 1 | I25: on/off | J25: **Description:** When this policy is activated, it is assumed that the distributed solar deployment policy will not be implemented.
A26: Buildings and Appliances | B26: Improved Labeling | C26: Boolean Improved Device Labeling | D26: Improved Labeling | E26: bldgs device labeling | F26: 0 | G26: 1 | H26: 1 | I26: on/off | J26: **Description:** This policy represents a program requiring newly sold heating systems, cooling and ventilation systems, and appliances to feature prominent, well-designed labels highlighting their energy efficiencies. The policy reduces energy consumption of newly sold building components of these types by 10%. | K26: buildings-sector-main.html#device-labeling | L26: improved-labeling.html | M26: none
A27: Buildings and Appliances | B27: Retrofit Existing Buildings | C27: Share of Preexisting Buildings Subject to Retrofitting | D27: Increased Retrofitting | E27: bldgs retrofitting | F27: 0 | G27: 0.5 | H27: 0.01 | I27: % of existing buildings | J27: **Description:** Each year, the specified percentage of the selected building type(s) that existed at the start of the model run will be retrofit with more efficient heating, cooling, and envelope components. // **Guidance for setting values:** According to 2050 Carbon Neutral Scenarios, by 2050, 100% of the preexisting buildings in South Korea will meet 1st grade for Zero Energy Building (ZEB) grade. 100% of newly built ones also will meet 1++ for green remodeling efficiency grade, 1+ for commercial grade. | K27: buildings-sector-main.html#retrofitting | L27: increased-retrofitting.html | M27: Calculated from model data; see the relevant variable(s) in the InputData folder for source information.
A28: Buildings and Appliances | B28: Rebate for Efficient Products | C28: Boolean Rebate Program for Efficient Components | D28: Rebate for Efficient Products | E28: bldgs rebate | F28: 0 | G28: 1 | H28: 1 | I28: on/off | J28: **Description:** This policy represents a modest rebate provided to customers who purchase energy-efficient building equipment of the selected type(s). Typical rebate values in Korea are approximately KRW 58,000–116,000 for a clothes washer and KRW 29,000–58,000 for a dishwasher or refrigerator. These rebates lower the upfront purchase cost and help accelerate the adoption of high-efficiency appliances. | K28: buildings-sector-main.html#rebate | L28: rebate-for-efficient-products.html
A29: Electricity Supply | B29: Restrict New Power Plants | C29: Boolean Ban New Power Plants | D29: Restrict New Power Plants | E29: elec ban new power plants | F29: 0 | G29: 1 | H29: 1 | I29: on/off | J29: **Description:** This policy prevents new capacity of the selected type(s) from being built or deployed. | K29: electricity-sector-main.html#ban | L29: ban-new-capacity.html
A30: Electricity Supply | B30: Restrict New Power Plant Retrofits | C30: Boolean Ban New Power Plant Retrofits | D30: Restrict New Power Plant Retrofits | E30: elec ban new power plant retrofits | F30: 0 | G30: 1 | H30: 1 | I30: on/off | J30: **Description:** This policy prevents new capacity of the selected CCS plant type(s) from being built to replace existing non-CCS plants.
A31: Electricity Supply | B31: Clean Electricity Standard | C31: Clean Electricity Std Percentage | D31: Clean Electricity Standard | E31: elec clean electricity standards | F31: 0 | G31: 1 | H31: 0.01 | I31: % of electricity generation | J31: **Description:** This policy specifies the fraction of electricity generation that must come from qualified carbon-free energy sources (including wind, solar, biomass, nuclear, hydro, and geothermal) in 2050. The policy lever becomes effective only when the user-defined target exceeds the existing national baseline, which is projected to reach approximately 47% by 2050.//**Guidance for Setting Values:** According to Korea’s 11th Basic Plan for Long-term Electricity Supply and Demand, the combined share of carbon-free energy sources (including renewables, nuclear, and clean hydrogen/ammonia) is projected to reach approximately 70% by 2038. Focusing strictly on renewables, the share is expected to reach 18.8% (120.9 TWh) in 2030 and 29.2% (205.7 TWh) in 2038. Setting exceptionally high CES targets significantly increases uncertainty regarding policy implementation costs. To ensure accuracy in such scenarios, we recommend using supplementary modeling to analyze detailed cost impacts. | K31: electricity-sector-main.html#ces | L31: clean-energy-standard.html | M31: White House, 2015, "Fact Sheet: President Obama to Announce Historic Carbon Pollution Standards for Power Plants", https://www.whitehouse.gov/the-press-office/2015/08/03/fact-sheet-president-obama-announce-historic-carbon-pollution-standards.
A32: Electricity Supply | B32: Renewable Portfolio Standard | C32: Renewable Portfolio Std Percentage | D32: Renewable Portfolio Standard | E32: elec renewable portfolio standards | F32: 0 | G32: 1 | H32: 0.01 | I32: % of electricity generation | J32: **Description:** This policy specifies the fraction of electricity generation that must come from qualifying renewable sources (wind, solar, hydro, biomass, geothermal, and hydrogen) in 2050. This policy has no effect until the user-set value exceeds the existing fraction of renewable electricity. Also note that the model incorporates a cap on the RPS credit price. If the RPS credit price hits this $/MWh amount in a given year, the model will not deploy any additional RPS qualifying resources. In the BAU scenario this cap is 89.37 $/MWh (approximately KRW 100,700/MWh). You can change the maximum RPS credit price in the Clean Electricity Standard Alternative Compliance Payment lever. // **Guidance for setting values:** According to Korea’s 11th Basic Plan for Long-term Electricity Supply and Demand, the combined share of renewable energy sources is expected to reach 18.8% (120.9 TWh) in 2030 and 29.2% (205.7 TWh) in 2038. Setting exceptionally high RPS targets significantly increases uncertainty regarding policy implementation costs. To ensure accuracy in such scenarios, we recommend using supplementary modeling to analyze detailed cost impacts.
A33: Electricity Supply | B33: Clean Electricity Standard Foresight | C33: BESHFoFRV Boolean Electricity Suppliers Have Foresight of Future RPS Values | F33: 0 | G33: 1 | H33: 1 | I33: on/off | J33: **Description:** This setting indicates whether electricity suppliers have foresight of future-year CES values (both BAU case values and any values set by the user in the CES policy lever). With foresight, electricity suppliers will build some CES-qualifying resources in earlier years than would be strictly necessary to meet the CES requirement in those years if it allows them to approach a higher, future-year CES target more gradually, lessening the need to build power plants abruptly if the CES rises more steeply in the future.
A34: Electricity Supply | B34: Lift the Clean Electricity Standard Alternative Compliance Payment | C34: Boolean Use Non BAU RPS Alternative Compliance Payment | D34: Clean Electricity Standard | E34: elec non BAU RACP | F34: 0 | G34: 1 | H34: 1 | I34: on/off | J34: **Description:** The BAU scenario includes a CES alternative compliance payment of roughly 180 $/MWh, meaning the model will not deploy any additional CES qualifying resources above this price in an attempt to meet the CES. Enabling this policy lifts this cap, meaning there is no price constraint on new resources.
A35: Electricity Supply | B35: Change Electricity Exports | C35: Percent Change in Electricity Exports | D35: Electricity Imports and Exports | E35: elec change exports | F35: -0.5 | G35: 1 | H35: 0.02 | I35: % change in exports | J35: **Description:** This policy increases or decreases the amount of electricity exported from South Korea. It does not cause the construction or removal of transmission lines linking these countries. // **Guidance for setting values:** South Korea does not export electricity to foreign countries. | K35: electricity-sector-main.html#elec-exports | L35: electricity-imports-exports.html | M35: Energy Information Administation. 2016. Electric Power Annual. Table 2.13.
A36: Electricity Supply | B36: Change Electricity Imports | C36: Percent Change in Electricity Imports | D36: Electricity Imports and Exports | E36: elec change imports | F36: -0.5 | G36: 1 | H36: 0.02 | I36: % change in imports | J36: **Description:** This policy increases or decreases the amount of electricity imported to South Korea. It does not cause the construction or removal of transmission lines linking these countries. // **Guidance for setting values:** South Korea does not import electricity from foreign countries. | K36: electricity-sector-main.html#elec-imports | L36: electricity-imports-exports.html | M36: Energy Information Administation. 2016. Electric Power Annual. Table 2.13.
A37: Electricity Supply | B37: Non BAU Guaranteed Dispatch | C37: Boolean Use Non BAU Guaranteed Dispatch Settings | D37: Non BAU Guaranteed Dispatch | E37: elec non BAU guaranteed dispatch | F37: 0 | G37: 1 | H37: 1 | I37: on/off
A38: Electricity Supply | B38: Decrease Cost of Capital | C38: Percentage Decrease in Cost of Capital for Power Plants | D38: Decrease Electricity Sector Cost of Capital | E38: elec power plant cost of capital | F38: 0 | G38: 1 | H38: 0.01 | I38: % decrease | J38: **Description:** This policy decreases the cost of capital for new power plant investments, making the specified plant type more attractive to deploy. // **Guidance for setting values:** The BAU cost of capital for all plant types is calculated as 7.4%, based on data from Lazard. | M38: https://www.lazard.com/media/451905/lazards-levelized-cost-of-energy-version-150-vf.pdf
A39: Electricity Supply | B39: Demand Response | C39: Fraction of Additional Demand Response Potential Achieved | D39: Demand Response | E39: elec demand response | F39: 0 | G39: 1 | H39: 0.01 | I39: % of potential achieved | J39: **Description:** This policy determines the share of additional demand response (DR) potential that is realized beyond the DR capacity already included in the Business-As-Usual (BAU) scenario. It does not directly set total DR capacity. Demand response provides flexibility that allows for the integration of more wind and solar PV, if the electricity system is flexibility-constrained. Demand response can be load-shedding (demand is reduced in the worst hours without adding demand in other hours) or load-shifting (demand is reduced in the worst hours and added in other hours). The type of demand response modeled here is load-shedding, which is by far the most common type of demand response that exists today. // **Guidance for setting values:** In the BAU scenario, DR capacity increases from 2,507 MW in 2021 to 7,172 MW in 2050. The lever setting applies only to additional DR potential beyond this BAU trajectory. | K39: electricity-sector-main.html#dr | L39: demand-response.html | M39: Calculated from model data; see the relevant variable(s) in the InputData folder for source information.
A40: Electricity Supply | B40: Early Retirement of Power Plants | C40: Annual Additional Capacity Retired due to Early Retirement Policy | D40: Early Retirement of Power Plants | E40: elec early retirement | F40: 0 | G40: 25000 | H40: 500 | I40: MW/year | J40: **Description:** This policy causes the specified quantity of otherwise non-retiring capacity of the selected type(s) to be retired each year. | K40: electricity-sector-main.html#early-ret | L40: early-retirement-of-power-plants.html | M40: Energy Information Administration, 2014, "Annual Energy Outlook 2014", http://www.eia.gov/oiaf/aeo/tablebrowser/#release=AEO2014&subject=6-AEO2014&table=9-AEO2014&region=0-0&cases=hccstom-d012314a,ref2014-d102413a, Table Browser. Select Electric Power Sector, Electricity Generating Capacity (and check Reference and Accelerated coal retirements scenarios). | N40: The Brattle Group, 2012, "Potential Coal Plant Retirements: 2012 Update," http://greatlakeslegalfoundation.org/wwcms/wp-content/uploads/documents/regulatory/TrainWreck/12Oct15_BrattleStudy.pdf, Page 8, Table 4
A41: Electricity Supply | B41: Non BAU Capacity Retirement Schedule | C41: Boolean Use Non BAU Capacity Retirement Schedule | D41: Non BAU Capacity Retirement Schedule | F41: 0 | G41: 1 | H41: 1 | I41: on/off | J41: **Description:** The EPS calculates economic capacity additions and retirements in each time step. In addition, it incorporates any announced retirements through input data files. When this lever is activated for a selected generation technology, the model replaces the corresponding BAU retirement schedule with an alternate schedule specified in a separate input data file. The two schedules are alternatives and are not added together. // **Guidance for setting values:** In South Korea, the BAU retirement schedule is based on the Ministry of Trade, Industry and Energy's 11th Basic Plan for Long-term Electricity Supply and Demand for 2024–2038, and on plant lifetimes for 2039–2050 (30 years for coal and 60 years for nuclear), totalling about 18.9 GW of retirements over 2039–2050. In the BAU, natural gas plants are subject only to economic retirement after 2038. Activating this lever substitutes an alternate schedule that also retires natural gas combined cycle plants on a lifetime basis, raising retirements over the same period to about 42.3 GW, of which 22.6 GW is natural gas combined cycle.
A42: Electricity Supply | B42: Non BAU Mandated Capacity Construction | C42: Boolean Use Non BAU Mandated Capacity Construction Schedule | D42: Non BAU Mandated Capacity Construction | F42: 0 | G42: 1 | H42: 1 | I42: on/off | J42: **Description:** The business-as-usual case includes the capacity additions mandated by Korea's 11th Basic Plan for Long-term Electricity Supply and Demand. This policy uses an alternate set of planned capacity additions, which replaces the BAU schedule rather than adding to it. // **Guidance for setting values:** // **Solar PV and Offshore Wind:** The alternate schedule mandates faster deployment. Cumulative mandated additions through 2050 rise from 65.8 GW to 98.1 GW for solar PV, and from 31.9 GW to 44.6 GW for offshore wind. // **Thermal, Nuclear and Onshore Wind:** The alternate schedule contains no mandated additions for these technologies, leaving their build-out to the model's economic capacity decisions.
A43: Electricity Supply | B43: Non BAU Mandated Capacity CCUS Retrofits | C43: Boolean Use Non BAU Mandated Capacity Retrofit Schedule | D43: Non BAU Mandated Capacity CCUS Retrofits | F43: 0 | G43: 1 | H43: 1 | I43: on/off | J43: **Description:** Turning on this policy lever assumes that these CCUS retrofits will not take place. However, the South Korea model does not include such retrofit plans.
A44: Electricity Supply | B44: Non BAU RPS Qualifying Resources | C44: Boolean Use Non BAU RPS Qualifying Resource Definitions | D44: Non BAU RPS Qualifying Resources | E44: elec non BAU RPS qualifying resources | F44: 0 | G44: 1 | H44: 1 | I44: on/off
A45: Electricity Supply | B45: Change in Expected Power Plant Capacity Factor | C45: Percentage Reduction in Plant Downtime | D45: Reduce Plant Downtime | E45: elec reduce plant downtime | F45: -0.3 | G45: 0.6 | H45: 0.01 | I45: % reduction in downtime | J45: **Description:** This policy specifies the change in capacity factor (time spent generating power) for new natural gas combined cycle plants. This policy changes these plants' expected capacity factors, but it does not force them to be dispatched if it would be uneconomical to do so. A negative value implies a decrease in capacity factor relative to the Current Policies scenario. //**Guidance for setting values:** // **Preexisting Natural Gas Nonpeaker:** Preexisting Korean natural gas nonpeakers have an average capacity factor of 38% | K45: electricity-sector-main.html#red-downtime | L45: reduce-downtime.html | M45: E&E Publishing. The Clean Power Plan - A Summary. http://www.eenews.net/interactive/clean_power_plan/fact_sheets/rule National Renewable Energy Laboratory. United States (48 Contiguous States) Potential Wind Capacity Cumulative Area vs. Gross Capacity Factor. http://apps2.eere.energy.gov/wind/windexchange/pdfs/wind_maps/us_contiguous_wind_potential_chart.pdf See the discussion of multi-junction solar cells on Wikipedia at https://en.wikipedia.org/wiki/Multi-junction_solar_cell. Also NREL has a useful chart at http://www.nrel.gov/ncpv/images/efficiency_chart.jpg.
A46: Electricity Supply | B46: Reduce Soft Costs | C46: Percent Reduction in Soft Costs of Capacity Construction | D46: Reduce Soft Costs | E46: elec reduce soft costs | F46: 0 | G46: 0.9 | H46: 0.01 | I46: % reduction in soft costs | J46: **Description:** This policy specifies a reduction in soft costs (costs for things other than capital equipment) for new plants of the selected type(s), such as the costs of permitting, financing, project management, assembly, etc. // **Guidance for setting values:** Costs of permitting and financing can be reduced by streamlining permitting processes, but some soft costs (such as labor) may be difficult to reduce via policy. A value of 50% would be an aggressive soft cost reduction. | K46: endogenous-learning.html#red-soft-costs | L46: reduce-soft-costs.html
A47: Electricity Supply | B47: Reduce Transmission & Distribution Losses | C47: Percentage TnD Losses Avoided | D47: Reduce T&D Losses | E47: elec avoid TND loss | F47: 0 | G47: 0.4 | H47: 0.01 | I47: % of losses avoided | J47: **Description:** This policy specifies the reduction in transmission and distribution losses that will be achieved by 2050. // **Guidance for setting values:** South Korea has transmission and distribution losses of about 3.5%. U.S. have T&D losses of about 6%, and Germany, Japan, Finland, and Netherlands have around 4%. | K47: electricity-sector-main.html#red-tnd-losses | L47: reduce-tnd-losses.html | M47: The World Bank. Electric power transmission and distribution losses (% of output). http://data.worldbank.org/indicator/EG.ELC.LOSS.ZS
A48: Electricity Supply | B48: Subsidy for Capacity Construction | C48: Perc Subsidy for Elec Capacity Construction | D48: Subsidy for Capacity Construction | E48: elec capacity construction subsidy | F48: 0 | G48: 0.95 | H48: 0.01 | I48: % of construction cost | J48: **Description:** This policy is a subsidy paid by the government to electricity suppliers per unit of new capacity constructed. This only applies to utilities, not distributed systems (such as rooftop solar). // **Guidance for setting values:** South Korea currently does not operate direct cash subsidies paid per unit of capacity or generation, nor does it have a PTC-type tax credit system. Instead, it indirectly alleviates the construction burden through investment tax credits and low-interest loans, and provides market incentives based on electricity generation (RPS and REC trading) | K48: electricity-sector-main.html#subsidies | M48: https://www.energy.gov/articles/secretary-perry-announces-financial-close-additional-loan-guarantees-during-trip-vogtle https://www.energysage.com/solar/cost-benefit/solar-investment-tax-credit/ http://biomassmagazine.com/articles/8185/usda-loan-guarantees-support-3-biomass-power-plants
A49: Electricity Supply | B49: Subsidy for Electricity Production | C49: Subsidy for Elec Production by Fuel | D49: Subsidy for Electricity Production | E49: elec generation subsidy | F49: 0 | G49: =100000/1000 -> 100 | H49: =G49/100 -> 1 | I49: thousand KRW/kWh | J49: **Description:** This policy is a subsidy paid by the government to suppliers of electricity per unit of electricity generated from the selected plant type(s). // **Guidance for setting values:** South Korea currently does not operate direct cash subsidies paid per unit of capacity or generation, nor does it have a PTC-type (Production Tax Credit) tax credit system. Instead, South Korea utilizes an investment tax credit scheme, which allows companies to claim deductions from corporate or income tax for investments made in renewable energy facilities. This provides an indirect initial investment burden relief effect, similar to the U.S. ITC (Investment Tax Credit). | K49: electricity-sector-main.html#subsidies | L49: subsidy-for-electricity-production.html | M49: PRODUCTION TAX CREDIT: Database of State Incentives for Renewables & Efficiency, 2013, "Renewable Energy Production Tax Credit (PTC)", http://dsireusa.org/incentives/incentive.cfm?Incentive_Code=US13F. STATE-LEVEL INCENTIVES: Energy Information Administration, 2013, "Feed-In Tariffs and similar programs", http://www.eia.gov/electricity/policies/provider_programs.cfm.
A50: Electricity Supply | B50: Existing Power Plant Production Subsidy | C50: Additional Subsidy for Elec Production for Existing Plants | D50: Existing Power Plant Production Subsidy | E50: elec existing plant generation subsidy | F50: 0 | G50: 60 | H50: 1 | I50: thousand KRW/MWh | J50: **Description:** This policy is a subsidy paid by the government to suppliers of electricity per unit of electricity generated from the selected plant type(s) for preexisting plants. // **Guidance for setting values: Also note that the Energy Policy Simulator chooses which new power plants to build based on lifetime plant costs, and unlike the PTC, which is only available for the first 10 years of a project, this variable subsidy is available for the duration of a plant's lifetime.
A51: Electricity Supply | B51: Use EVs for Grid Balancing | C51: Share of EVs Used for Grid Balancing | D51: EVs for Grid Balancing | E51: elec use EVs for grid balancing | F51: 0 | G51: 1 | H51: 0.01 | I51: % of EVs used | J51: **Description:** This policy increases the share of EVs that are used to assist in grid balancing on an average day. This means the EV is connected to the grid during the hours when demand-shifting would be helpful (hours of net peak load) and can pause its charging or, ideally, can partially discharge its battery during these hours to help provide electricity to the grid. // **Guidance for setting values:** Today, EVs generally are not used to help with grid balancing, and EVs and chargers may not have the capability to send electricity in the reverse direction to supply the grid (and have suitable safety cut-off systems to prevent energizing the grid when utilities intentionally shut it down to do repairs and maintenance). Automatically changing the hours when an EV charges (but not discharging to support the grid) is technologically easier but provides less support to the grid.
A52: Electricity Supply | B52: Subsidy for Grid Battery Production | C52: Additional Subsidy for Grid Battery Production | D52: Grid Battery Subsidy | E52: elec battery production subsidy | F52: =-150000/1000 -> -150 | G52: =150000/1000 -> 150 | H52: 1 | I52: thousand KRW/kWh | J52: **Description:** This policy provides grid battery manufacturers with an additional production subsidy, expressed in thousand KRW per kWh of battery capacity produced. Since South Korea currently has no direct production subsidy for grid battery manufacturers, the value entered here represents the total newly introduced subsidy. A negative value represents a production tax or the removal of existing support. // **Guidance for setting values:** South Korea generally supports battery manufacturing through tax incentives, investment support, grants, and research and development programs rather than through a uniform subsidy paid per kWh produced. Direct production-based subsidies exist mainly in renewable energy programs such as the FIT and the RPS. This lever can therefore be used to test a hypothetical additional production-based subsidy.
A53: Electricity Supply | B53: Subsidy for Grid Battery Output | C53: Additional Subsidy per Unit Electricity Supplied to the Grid by Grid Batteries | D53: Grid Battery Subsidy | E53: elec battery subsidy per output | F53: -100 | G53: 100 | H53: 1 | I53: $/kWh | J53: **Description:** This policy provides a subsidy in units of dollar per megawatt-hour electricity supplied to the grid, additional to any BAU subsidies. A negative value implies a tax or removal of subsidies. // **Guidance for setting values:** The BAU case has grid batteries claiming the Subsidy for Grid Battery Capacity, not a subsidy per unit output.
A54: Electricity Supply | B54: Subsidy for Grid Battery Capacity | C54: Additional Percent Subsidy per Unit Grid Battery Capacity Deployed | D54: Grid Battery Subsidy | E54: elec battery construction subsidy | F54: -1 | G54: 1 | H54: 0.01 | I54: % of capital costs | J54: **Description:** This policy subsidizes a percentage of grid battery capacity costs, additional to any BAU capacity construction subsidies. A negative value implies a tax or removal of subsidies. // **Guidance for setting values:**The subsidy data were obtained from the Korea Energy Agency (KEA) through the Renewable Energy-Linked ESS Deployment Support Program, and the subsidy rate applied to grid-stabilization energy storage systems (ESS) was reflected. In addition, the calculation method used in the U.S. model based on the Inflation Reduction Act (IRA) was adopted, and the relevant data were adjusted to reflect South Korea’s context. In the business-as-usual (BAU) scenario, the subsidy rate was assumed to be approximately 41.6% of installation costs.
A55: Electricity Supply | B55: Electricity CCS Subsidy | C55: Additional Subsidy for Elec CCS | D55: Electricity CCS Subsidy | E55: elec CCS subsidy | F55: =-150000/1000 -> -150 | G55: =150000/1000 -> 150 | H55: 1 | I55: thousand KRW/metric ton CO2e | J55: **Description:** This policy provides an additional subsidy for CO2 captured and stored by electricity generators, expressed in thousand KRW per metric ton CO2e. Since the BAU scenario contains no CCS subsidy for electricity generators, the value entered here represents the total newly introduced incentive. // **Guidance for setting values:** South Korea does not currently operate a standardized nationwide production tax credit that pays electricity generators a fixed amount for each metric ton of CO2 captured and stored. This lever can be used to test an additional per-ton CCS incentive.
A56: Industry | B56: Buy In-Region Products | C56: Fraction of Imported Industrial Outputs Shifted to In Region Suppliers | D56: Buy In-Region Products | E56: indst buy in region outputs | F56: 0 | G56: 0.5 | H56: 0.01 | I56: % of imports shifted | J56: **Description:** This policy increases the extent to which the selected industry's products are supplied by producers within the modeled region. // **Guidance for setting values:** The lever specifies the percentage of imported products (in the BAU case) that are shifted to domestic suppliers (in the policy case). For example, suppose buyers within the modeled region purchase 60% of their road vehicles from domestic automakers and 40% from automakers outside the modeled region. If this policy lever is applied to the "Road Vehicles" industry with a 50% setting, buyers will obtain 80% of their road vehicles from domestic automakers and 20% from automakers outside the modeled region. // **Implementation Note:** This policy reduces imports. In reality, other regions might retaliate by restricting their own purchases of goods produced by the modeled region. However, the EPS only considers policies within the modeled region, so the Buy In-Region Products policy does not affect export levels (i.e., other countries/regions are assumed not to retaliate).
A57: Industry | B57: Carbon Capture and Sequestration | C57: Industry Sector Fraction of Potential Additional CCS Achieved | D57: Industry CCS | E57: indst CCS | F57: 0 | G57: 1 | H57: 0.01 | I57: % of CO2 captured | J57: **Description:** This policy specifies the fraction of CO2 emissions from industry that is captured and stored, above the amount predicted in the business-as-usual scenario. // **Guidance for setting values:** Very few CCS-equipped industrial facilities exist today, so in a scenario where industry does not transition to clean energy, a value over 20% is likely very optimistic. However, in scenarios in which industry mostly or entirely transitions to clean energy (i.e. due to other policies, such as industrial fuel switching and industrial energy efficiency), CCS settings as high as 100% (to capture the small amount of residual CO2 emissions, such as process CO2 from the cement industry) may be very feasible.//**- 2050 BAU Scenario**//Cement Sector: Achieves capture of approximately 52.5% of process emissions.//Petroleum Refining Sector: Achieves capture of approximately 61.3% of process emissions and 44.2% of energy emissions.//Steel Sector: Achieves capture of approximately 27.7% of process emissions. | K57: ccs.html#ccs | L57: carbon-capture-and-sequestration.html
A58: Industry | B58: Non BAU Industry CCS Subsidy | C58: Boolean Use Non BAU Industry CCS Subsidies | D58: Industry CCS | E58: indst non BAU CCS | F58: 0 | G58: 1 | H58: 1 | I58: on/off | J58: **Description:** This policy allows users to model the emissions and cash flow impact of a non-BAU industry CCS subsidy. This lever is set up to test the impacts of removing all CCS subsidies flowing to industry in the BAU scenario. | K58: ccs.html#ccs | L58: carbon-capture-and-sequestration.html
A59: Industry | B59: Cement Clinker Substitution | C59: Fraction of Cement Measures Achieved | D59: Cement Clinker Substitution | E59: indst cement measures | F59: 0 | G59: 1 | H59: 0.01 | I59: % of potential achieved | J59: **Description:** This policy reduces CO2 emissions from the cement industry by substituting other inputs, such as fly ash, for a portion of the clinker in cement. // **Guidance for setting values:** If this policy is fully implemented (set to 100%), the share of clinker in cement will be reduced to 60%. This reduction achieves the full potential for carbon emission abatement assessed from the current level of clinker use. | K59: industry-ag-main.html#clinker | L59: cement-clinker-substitution.html | M59: International Energy Agency and Cement Sustainability Initiative. 2018. Technology Roadmap: Low-Carbon Transition in the Cement Industry. p41. http://www.iea.org/publications/freepublications/publication/TechnologyRoadmapLowCarbonTransitionintheCementIndustry.pdf
A60: Industry | B60: Cogeneration and Waste Heat Recovery | C60: Fraction of Potential Cogeneration and Waste Heat Recovery Adopted | D60: Cogeneration and Waste Heat Recovery | E60: indst CHP | F60: 0 | G60: 1 | H60: 0.01 | I60: % of potential achieved | J60: **Description:** This policy reduces fuel consumption in the industry sector by increasing the use of cogeneration (also known as combined heat and power) and recovery of waste heat (to perform useful work). // **Guidance for setting values:** If this policy is fully implemented, fuel use is reduced by 5.4% for all industries in 2050. | K60: industry-ag-main.html#cogen | L60: cogeneration-and-waste-heat-recovery.html | M60: Calculated from model data; see the relevant variable(s) in the InputData folder for source information.
A61: Industry | B61: Early Retirement of Industrial Facilities | C61: Fraction of Energy Savings from Early Facility Retirement Achieved | D61: Early Retirement of Industrial Facilities | E61: indst early retirement | F61: 0 | G61: 1 | H61: 0.01 | I61: % of potential achieved | J61: **Description:** This policy reduces fuel consumption in the industry sector by retiring older, inefficient industrial facilities sooner than they otherwise would retire. This policy does not affect demand for industrial products, so it is assumed that any facilities retired under this policy are replaced by new facilities or increased output from existing facilities in the same year. // **Guidance for setting values:** If this policy is fully implemented, fuel use is reduced for most industries between 2% and 9% in 2050. | K61: industry-ag-main.html#early-ret | L61: early-retirement-of-industrial-facilities.html | M61: Calculated from model data; see the relevant variable(s) in the InputData folder for source information.
A62: Industry | B62: Industry Energy Efficiency Standards | C62: Percentage Improvement in Eqpt Efficiency Standards above BAU | D62: Industry Energy Efficiency Standards | E62: indst efficiency standards | F62: 0 | G62: 0.25 | H62: 0.01 | I62: % reduction in energy use | J62: **Description:** This policy reduces fuel consumption by the selected industry by increasing the efficiency of industrial equipment through stronger standards. The value set for this lever (e.g., '10%') represents the target percentage reduction in overall industrial fuel use in that sector, and the model calculates this as a proportional increase in energy efficiency. The policy setting refers to overall energy use reduction, not the reduction in energy use of newly sold equipment. // **Guidance for setting values:** In 2016, the U.S. Department of Energy developed an industrial energy efficiency potential analysis that suggests the US could double its annual rate of improvement rate through 2030. Extended through 2050, this equates to a maximum potential improvement of 17% by 2050 relative to BAU. Values are assumed to be similar for South Korea. | K62: industry-ag-main.html#eff-stds | L62: industry-energy-efficiency-standards.html | M62: U.S. DOE, 2016, Industrial Energy Efficiency Potential Analysis, https://energy.gov/sites/prod/files/2017/04/f34/energy-savings-by-state-industrial-methodology.pdf | N62: U.S. DOE, 2016, Industrial Energy Efficiency Potential Analysis, https://energy.gov/sites/prod/files/2017/04/f34/energy-savings-by-state-industrial-methodology.pdf
A63: Industry | B63: Improved System Design | C63: Fraction of Installation and System Integration Issues Remedied | D63: Improved System Design | E63: indst system integration | F63: 0 | G63: 1 | H63: 0.01 | I63: % of potential achieved | J63: **Description:** This policy reduces fuel consumption in the industry sector by improving the way components are put together and the way material or energy flows between them. // **Guidance for setting values:** If this policy is fully implemented, fuel use is reduced by 3.6% for all industries in 2050. | K63: industry-ag-main.html#system-integ | L63: improved-system-design.html | M63: Calculated from model data; see the relevant variable(s) in the InputData folder for source information.
A64: Industry | B64: Electrification | C64: Fraction of Eligible Industrial Energy Use Shifted to Electricity | D64: Electrification | E64: indst shift to electricity | F64: 0 | G64: 1 | H64: 0.01 | I64: % of fuel shifted | J64: **Description:** This policy reduces greenhouse gas emissions from the selected industry by switching the fuels used by facilities to electricity. Only fuel consumed for energy, not fuel used as a chemical feedstock, is affected by this policy. Biomass and purchased heat (steam) are also unaffected. // **Guidance for setting values:** Over 90% of manufacturers' thermal fuels (excluding feedstocks) are used to generate process heat, including to fuel boilers. Generally, boilers/steam and low-temperature non-boiler heat are easier to electrify than higher-temperature heat. | K64: industry-ag-main.html#fuel-switching | L64: industry-elec-and-hydrogen.html
A65: Industry | B65: F-Gas Substitution | C65: Fraction of F Gas Substitution Achieved | D65: F-gas Measures | E65: indst f gas substitution | F65: 0 | G65: 1 | H65: 0.01 | I65: % of potential achieved | J65: **Description:** This policy reduces emissions of high-GWP, fluorinated gases (F-gases) from the industry sector by substituting less-harmful chemicals. // **Guidance for setting values:** This dataset is based on the global non-CO₂ mitigation potential (MAC) dataset developed by the U.S. EPA. South Korea is estimated to emit approximately 21.3 MMT CO₂e of F-gases in 2021. If this policy lever is set to 100% in 2050, approximately 12 MMT CO₂e of emissions are reduced. | K65: industry-ag-main.html#avoid-f-gases | L65: avoid-f-gases.html | M65: Calculated from model data; see the relevant variable(s) in the InputData folder for source information.
A66: Industry | B66: F-Gas Destruction | C66: Fraction of F Gas Destruction Achieved | D66: F-gas Measures | E66: indst f gas destruction | F66: 0 | G66: 1 | H66: 0.01 | I66: % of potential achieved | J66: **Description:** This policy reduces emissions of high-GWP, fluorinated gases (F-gases) from the industry sector by destroying F-gases created as byproducts during the creation of desired products. // **Guidance for setting values:** This dataset is based on the global non-CO₂ mitigation potential (MAC) dataset developed by the U.S. EPA. South Korea is estimated to emit approximately 21.3 MMT CO₂e of F-gases in 2021. If this policy lever is set to 100% in 2050, approximately 6 CO₂e of emissions are reduced. | K66: industry-ag-main.html#avoid-f-gases | L66: avoid-f-gases.html
A67: Industry | B67: F-Gas Recovery | C67: Fraction of F Gas Recovery Achieved | D67: F-gas Measures | E67: indst f gas recovery | F67: 0 | G67: 1 | H67: 0.01 | I67: % of potential achieved | J67: **Description:** This policy reduces emissions of high-GWP, fluorinated gases (F-gases) by recovering F-gases from equipment at the end of its service life and destroying or recycling those F-gases. // **Guidance for setting values:**This dataset is based on the global non-CO₂ mitigation potential (MAC) dataset developed by the U.S. EPA. South Korea is estimated to emit approximately 21.3 MMT CO₂e of F-gases in 2021. If this policy lever is set to 100% in 2050, approximately 1.6 CO₂e of emissions are reduced. | K67: industry-ag-main.html#avoid-f-gases | L67: avoid-f-gases.html
A68: Industry | B68: F-Gas Eqpt. Maintenance & Retrofits | C68: Fraction of F Gas Inspct Maint Retrofit Achieved | D68: F-gas Measures | E68: indst f gas inspct maint retrofit | F68: 0 | G68: 1 | H68: 0.01 | I68: % of potential achieved | J68: **Description:** This policy reduces emissions of high-GWP, fluorinated gases (F-gases) from the industry sector by reducing leakage and losses through improved inspections, maintenance, and retrofitting of equipment. // **Guidance for setting values:**This dataset is based on the global non-CO₂ mitigation potential (MAC) dataset developed by the U.S. EPA. South Korea is estimated to emit approximately 21.3 MMT CO₂e of F-gases in 2021. If this policy lever is set to 100% in 2050, approximately 5.6 CO₂e of emissions are reduced. | K68: industry-ag-main.html#avoid-f-gases | L68: avoid-f-gases.html
A69: Industry | B69: Feedstock Shifting | C69: Fraction of Feedstock Shifted | D69: Feedstock Shifting | E69: indst feedstock shifting | F69: 0 | G69: 1 | H69: 0.01 | I69: % of potential achieved | J69: **Description:** : This policy shifts the use of fossil-fuel feedstocks to hydrogen. If this policy lever is set to 100%, it signifies that 100% of the fossil fuel currently used as feedstock in this sector is replaced by the alternative feedstock (hydrogen) within the timeframe defined by the model. The production method for this new hydrogen demand can be shifted wiht the 'Shift Hydrogen Production Pathways' lever. // **Guidance for setting values (Chemicals):** Approximately 52 percent of natural gas consumed as a chemical feedstock globally goes to producing ammonia and methanol. These pathways can be replaced with green electrolytic hydrogen to eliminate process emissions associated with production. // **Guidance for setting values (Iron & Steel):** Coal is the most significant feedstock used in the steel industry, largely for reducing iron ore in blast furnaces. A transition from the traditional steelmaking route (blast furnace-basic oxygen furnace) to alternatives (like hydrogen-based direct reduced iron with electric arc furnaces) can be represented by pairing this lever with electrification of industrial heat.
A70: Industry | B70: Hydrogen Combustion | C70: Fraction of Eligible Industrial Energy Use Shifted to Hydrogen | D70: Hydrogen Combustion | E70: indst shift to hydrogen | F70: 0 | G70: 1 | H70: 0.01 | I70: % of fuel shifted | J70: **Description:** This policy reduces greenhouse gas emissions from the selected industry by switching the fuels used by facilities to hydrogen combustion. Only fuel consumed for energy, not fuel used as a chemical feedstock, is affected by this policy. Biomass and purchased heat (steam) are also unaffected. // **Guidance for setting values:** Over 90% of manufacturers' thermal fuels (excluding feedstocks) are used to generate process heat, including to fuel boilers. Generally, hydrogen combustion is reserved for high-temperature heat, since it is often simpler and more efficient to directly electrify heat at lower temperatures. | K70: industry-ag-main.html#fuel-switching | L70: industry-elec-and-hydrogen.html
A71: Industry | B71: Material Efficiency, Longevity, & Re-Use | C71: Percent Reduction in Nonenergy Nonagriculture Industry Product Demand | D71: Material Efficiency, Longevity, & Re-Use | E71: indst reduce nonenergy product demand | F71: 0 | G71: 1 | H71: 0.01 | I71: % demand reduction | J71: **Description:** This is a comprehensive Resource and Material Efficiency Policy designed to reduce the overall product and service demand across various industry categories. The value set for this lever represents the target percentage reduction in the Industry Category's product and service demand resulting from these efficiency measures. The policy achieves this demand reduction by promoting techniques that increase the efficiency of resource use and extend product/infrastructure longevity.//**Guidance for setting values**//**- Cement and Iron & Steel:** This policy reduces demand for the selected materials through techniques such as material-efficient building codes (using modern designs that require less material per unit floor area), requirements for greater building and infrastructure longevity, greater re-use and re-purposing of buildings (rather than tearing down and building new), etc. In "Sustainable Materials Without the Hot Air: Making Buildings, Vehicles and Products Efficiently and with Less New Material," Allwood and Cullen estimate that concrete use could be reduced by up to 40% using optimized molds, and concrete building longevity could be more than doubled to 200 years. Together, these measures might reduce concrete demand by up to 70%, if demand for building floorspace reaches steady state. They estimate that steel use could be reduced by 30% by optimizing designs and controlling the loads they experience during installation and use. If the lifetime of steel products could be doubled, the resulting material reduction could be up to 65%, if sales reach steady state.//**- Water and Waste:** The value set for this lever represents the target percentage reduction in the Industry Category's product demand. This policy reduces demand for water treatment and waste management services through techniques such as water conservation, reduction in disposable packaging, requirements for greater product longevity, greater repair and re-use of products, and increased recycling and composting. The majority of energy use and emissions from the water and waste sector are a result of water treatment, not solid waste management. Non-agriculture uses, including lawn irrigation and in-home use, may be able to achieve similar savings through improved practices and fixtures. | L71: material-efficiency-longevity-reuse.html | M71: Allwood and Cullen, "Sustainable Materials Without the Hot Air: Making Buildings, Vehicles and Products Efficiently and with Less New Material" Allwood and Cullen, "Sustainable Materials With Both Eyes Open" - page 185, http://www.withbotheyesopen.com/read.php?c=12 USDA Irrigation & Water Use: https://www.ers.usda.gov/topics/farm-practices-management/irrigation-water-use.aspx and EPA WaterSense Statistics and Facts: https://www.epa.gov/watersense/statistics-and-facts
A72: Industry | B72: Methane Capture | C72: Fraction of Methane Capture Opportunities Achieved | D72: Methane Capture and Destruction | E72: indst methane capture | F72: 0 | G72: 1 | H72: 0.01 | I72: % of potential achieved | J72: **Description:** This policy reduces methane emissions from the selected industry by increasing the capture of methane that is currently being released into the atmosphere (for example, stopping leaks from wellheads, pipes, coal mines, landfills, etc.). **Guidance for setting values:** This dataset is based on the U.S. EPA’s global non-CO₂ Marginal Abatement Cost (MAC) dataset. As of 2021, Korea is estimated to emit approximately 42.5 million metric tons of CO₂e from methane. If this policy lever is set to 100% by 2050, it would reduce emissions by approximately 1,623 CO₂e. | K72: industry-ag-main.html#methane-capture | L72: methane-capture.html
A73: Industry | B73: Methane Destruction | C73: Fraction of Methane Destruction Opportunities Achieved | D73: Methane Capture and Destruction | E73: indst methane destruction | F73: 0 | G73: 1 | H73: 0.01 | I73: % of potential achieved | J73: **Description:** This policy reduces methane emissions from the selected industry by increasing the burning of methane that is currently being released into the atmosphere (i.e. flaring instead of venting/leaking). **Guidance for setting values:** This dataset is based on the U.S. EPA’s global non-CO₂ Marginal Abatement Cost (MAC) dataset. As of 2021, Korea is estimated to emit approximately 42.5 million metric tons of CO₂e from methane. If this policy lever is set to 100% by 2050, it would reduce emissions by approximately 200 CO₂e. | K73: industry-ag-main.html#methane-destr | L73: methane-destruction.html
A74: Industry | B74: N2O Abatement | C74: Fraction of N2O Abatement Achieved | D74: N2O Abatement | E74: indst N2O abatement | F74: 0 | G74: 1 | H74: 0.01 | I74: % of potential achieved | J74: **Description:** This policy reduces nitrous oxide (N2O) process emissions from the chemicals industry (primarily from the production of nitric acid and adipic acid) by destroying the N2O rather than venting it to the atmosphere. //
A75: Industry | B75: Non BAU Increase in Process Emissions | C75: Boolean Use Non BAU Process Emissions Additions | D75: Process Emissions Increases | E75: non BAU indst process emissions | F75: 0 | G75: 1 | H75: 1 | I75: on/off | J75: **Description:** This policy lever tests increases in industrial process emissions relative to the Current Policies scenario according to schedules set via model input data. // **Guidance for setting values:** //**Methane capture and destruction:** This lever repeals the relevant standards. // **Cropland, rice, and livestock measures:** This lever removes the relevant financial support and the associated projected emissions reductions.
A76: Industry | B76: Reduce Fossil Fuel Exports | C76: Percent Reduction in Fossil Fuel Exports | D76: Percent Reduction in Fossil Fuel Exports | E76: indst reduce fossil fuel exports | F76: 0 | G76: 1 | H76: 0.01 | I76: % reduction in exports | J76: **Description:** This policy reduces production of the selected fuel type(s) for export. This lever may represent a reduction in fuel demand by actors outside the modeled region (i.e., not caused by domestic policy) or a conscious policy within the modeled region to transition its economy away from dependence on fossil fuel exports. // **Guidance for setting values:** In the South Korea model, this lever has virtually no impact, as South Korea is a net importer of coal, oil, and LNG. Fuel exports essentially do not exist, aside from small volumes of re-exported petroleum products, which are minimal. | L76: reduce-fuel-exports.html | M76: Calculated from model data; see the relevant variable(s) in the InputData folder for source information.
A77: Agriculture, Land Use, and Forestry | B77: Afforestation and Reforestation | C77: Fraction of Afforestation and Reforestation Achieved | D77: Afforestation and Reforestation | E77: land afforestation and reforestation | F77: -3 | G77: 1 | H77: 0.01 | I77: % of potential achieved | J77: **Description:** This policy increases the sequestration of CO2 by planting forests. Planted forests are assumed to be managed with best practices and are not used for timber harvesting. A negative values implies less sequestration compared to the Current Policies scenario. // **Guidance for setting values:** Forest management in Korea is broadly divided into afforestation and forest management. Afforestation refers to the artificial establishment of forests, such as sowing seeds or planting trees. Reforestation, on the other hand, refers to the continuous management of forests after planting or activities aimed at improving forest conditions. Therefore, the figure representing the area converted to forest reflects only the area of reforestation, not general forest management activities. If this policy is implemented at 100%, approximately 57,957 acres/year of land would be converted to forest each year. | K77: lulucf.html#aff-ref | L77: afforestation-and-reforestation.html | M77: Calculated from model data; see the relevant variable(s) in the InputData folder for source information. | N77: Ross W. Gorte, 2009, "U.S. Tree Planting for Carbon Sequestration," Congressional Research Service, https://www.fas.org/sgp/crs/misc/R40562.pdf, p.3, paragraph 1
A78: Agriculture, Land Use, and Forestry | B78: Avoid Deforestation | C78: Fraction of Avoided Deforestation Achieved | D78: Avoid Deforestation | E78: land avoid deforestation | F78: 0 | G78: 1 | H78: 0.01 | I78: % of potential achieved | J78: **Description:** This policy prevents clear cutting of forests that would otherwise be cleared. Preserved forests are assumed to be managed with best practices. // **Guidance for setting values:** If this policy is fully implemented at 100%, the model avoids 1976 acres/year of deforestation. | K78: lulucf.html#avoid-def | L78: avoid-deforestation.html
A79: Agriculture, Land Use, and Forestry | B79: Grassland Restoration and Avoided Conversion | C79: Fraction of Forest Restoration Achieved | D79: Grassland Restoration and Avoided Conversion | E79: land forest restoration | F79: 0 | G79: 1 | H79: 0.01 | I79: % of potential achieved | J79: **Description:** This policy increases CO2 sequestration by avoiding the conversion of grasslands and restoring grassland areas. // **Guidance for setting values:**A 100% setting of this lever avoids the conversion of approximately 113 acres/year of grassland. | L79: forest-restoration.html | M79: See file PLANAbPiaSY
A80: Agriculture, Land Use, and Forestry | B80: Forest Set-Asides | C80: Fraction of Forest Set Asides Achieved | D80: Forest Set-Asides | E80: land forest set asides | F80: 0 | G80: 1 | H80: 0.01 | I80: % of potential achieved | J80: **Description:** This policy avoids the release of CO2 from forests by reducing timber harvesting. // **Guidance for setting values:** Because most Korean forests were established during the 1970–1980 afforestation period and have now reached an age at which carbon uptake declines, the Korea Forest Service emphasizes structural improvement (e.g., thinning and stand renewal) rather than reducing timber harvesting. Given Korea’s low level of commercial timber harvest and limited deforestation pressure, we set the deforestation reduction rate to zero in our modeling. | K80: lulucf.html#set-asides | L80: forest-set-asides.html | M80: Calculated from model data; see the relevant variable(s) in the InputData folder for source information.
A81: Agriculture, Land Use, and Forestry | B81: Cropland and Rice Measures | C81: Fraction of Cropland and Rice Measures Achieved | D81: Cropland and Rice Measures | E81: indst cropland and rice measures | F81: 0 | G81: 1 | H81: 0.01 | I81: % of potential achieved | J81: **Description:** This policy reduces CH4 and N2O emissions from agriculture through cropland management practices, such as improved crop rotations, reduced soil tillage, and improvements in fertilizer composition and application. Measures particular to rice cultivation include improved flooding practices that avoid anaerobic, methane-forming conditions. // **Guidance for setting values:**This dataset is based on the U.S. EPA’s global non-CO₂ Marginal Abatement Cost (MAC) dataset. In Korea, the agriculture and livestock sector emitted approximately 21.7 million metric tons of CO₂e in 2021. If this policy lever is set to 100% by 2050, it would reduce emissions by approximately 50 CO₂e. | K81: industry-ag-main.html#cropland | L81: cropland-management.html | M81: Calculated from model data; see the relevant variable(s) in the InputData folder for source information.
A82: Agriculture, Land Use, and Forestry | B82: Improved Soil Measures | C82: Fraction of CO2 Storage Through Tillage Practices | D82: Improved Soil Measures | E82: indst tillage | F82: 0 | G82: 1 | H82: 0.01 | I82: % of potential achieved | J82: **Description:** This policy stores CO2 in agricultural soils through improved tillage practices, retiring organic and marginal soils, and establishing windbreaks/shelterbelts. // **Guidance for setting values:** If this policy is fully implemented, approximately 70 MMT CO2 is stored in soils.
A83: Agriculture, Land Use, and Forestry | B83: Improved Forest Management | C83: Fraction of Improved Forest Management Achieved | D83: Improved Forest Management | E83: land forest management | F83: -1.5 | G83: 1 | H83: 0.01 | I83: % of potential achieved | J83: **Description:** This policy increases CO2 sequestration by forests through improved forest management practices. A negative values implies less sequestration compared to the Current Policies scenario. // **Guidance for setting values:**The potential for this policy lever is based on Korea’s 2024 Forest and Forestry Statistics Yearbook. This dataset and related analyses incorporate a range of carbon price scenarios across the forestry and agriculture sectors and account for land-use competition. Under a full implementation (100% setting), the model assumes that approximately 540,608 acres per year are managed through improved forest management practices. | K83: lulucf.html#forest-mgmt | L83: improved-forest-management.html | M83: Calculated from model data; see the relevant variable(s) in the InputData folder for source information.
A84: Agriculture, Land Use, and Forestry | B84: Livestock Measures | C84: Fraction of Livestock Measures Achieved | D84: Livestock Measures | E84: indst livestock measures | F84: 0 | G84: 1 | H84: 0.01 | I84: % of potential achieved | J84: **Description:** This policy reduces greenhouse gas emissions from agriculture through livestock-related measures, such as feed supplements or drugs to prevent enteric methane formation. // **Guidance for setting values:**This dataset is based on the U.S. EPA’s global non-CO₂ Marginal Abatement Cost (MAC) dataset. In Korea, the agriculture and livestock sector emitted approximately 21.7 million metric tons of CO₂e in 2021. If this policy lever is set to 100% by 2050, it would reduce emissions by approximately 36 CO₂e. | K84: industry-ag-main.html#livestock | L84: livestock-measures.html | M84: Calculated from model data; see the relevant variable(s) in the InputData folder for source information.
A85: Agriculture, Land Use, and Forestry | B85: Wetland Restoration | C85: Fraction of Peatland Restoration Achieved | D85: Wetland Restoration | E85: land peatland restoration | F85: 0 | G85: 1 | H85: 0.01 | I85: % of potential achieved | J85: **Description:** This policy increases CO2 sequestration by restoring wetlands and riparian forest buffers. // **Guidance for setting values:**In the Korean model, this policy was expanded to cover overall wetland restoration. If this policy is fully implemented, 30km2 of tidal flats will be restored by 2050. | L85: peatland-restoration.html | M85: https://www.usda.gov/sites/default/files/documents/White_Paper_WEB71816.pdf
A86: Agriculture, Land Use, and Forestry | B86: Shift to Non-Animal Products | C86: Percent Animal Products Shifted to Nonanimal Products | D86: Shift to Non-Animal Products | E86: indst shift to nonanimal products | F86: 0 | G86: 1 | H86: 0.01 | I86: % reduction in animal products | J86: **Description:** This policy causes animal products to be substituted for non-animal products, which might be achieved by changes in consumer preferences or by changes in costs of agricultural products (such as by redirecting subsidies currently paid to farmers who raise animals or feed crops to farmers growing fruits, vegetables, and other plant-based foods for human consumption). Moderate settings of this policy lever do not imply a vegan diet: for instance, a 50% setting could represent each individual consuming half as many animal products, rather than half of the population consuming no animal products. // **Guidance for setting values:** According to OECD statistics, South Korea consumes 57 kg/person/year, which is moderate compared to other countries. The US consumes 98 kg/person/yr, Europe is at 70 kg/person/yr, Japan at 36 kg/person/yr, or India 3 kg/person/yr. | L86: shift-to-non-animal-products.html | M86: https://en.wikipedia.org/wiki/List_of_countries_by_meat_consumption_per_capita (article revision 00:12, 22 Feb 2019)
A87: District Heat and Hydrogen | B87: Use CHP for District Heat | C87: Fraction of Non CHP Heat Production Converted to CHP | D87: District Heat CHP | E87: heat convert heat to CHP | F87: 0 | G87: 1 | H87: 0.01 | I87: % non-CHP heat converted | J87: **Description:** This policy causes a percentage of the district heat that would be generated by dedicated heat plants to instead be generated via CHP plants. In this model, this causes them to consume no additional fuel, since it is assumed CHP plants would be run anyway in order to produce electricity. // **Guidance for setting values:** In the BAU Scenario, the fraction of heat derived from CHP plants is constant at roughly 50%. Therefore, a policy setting of 50% would increase the CHP fraction to 75% in 2050. | K87: district-heating.html#chp | L87: convert-non-chp-heat-production.html | M87: Calculated from model data; see the relevant variable(s) in the InputData folder for source information.
A88: District Heat and Hydrogen | B88: Produce District Heat with Electricity | C88: Fraction of District Heat Fuel Use Shifted to Other Fuels | D88: District Heat Fuel Switching | E88: heat fuel type shifting | F88: 0 | G88: 1 | H88: 0.01 | I88: % of fuel use | J88: **Description:** This policy causes a percentage of the demand for district heat to be met with electricity instead of the fuels used in the BAU case. // **Guidance for setting values:** In South Korea, 87% of district heat is made by burning natural gas, 12% from coal, 1% from petroleum. Hydrogen technologies are still emerging, and it is not yet clear if it will be more economical to electrify end uses of heat (ceasing to use district heat), or if decarbonizing district heat facilities will be an economical pathway. | K88: district-heating.html#convert-coal | L88: district-heat-fuel-switching.html | M88: Calculated from model data; see the relevant variable(s) in the InputData folder for source information.
A89: District Heat and Hydrogen | B89: Shift Hydrogen Production Pathways | C89: Fraction of Hydrogen Production Pathways Shifted | D89: Shift Hydrogen Production Pathways | E89: hydgn shift production pathways | F89: 0 | G89: 1 | H89: 0.01 | I89: % of hydrogen production | J89: **Description:** By default, this policy causes a percentage of merchant hydrogen (i.e. hydrogen produced for sale, not hydrogen produced and consumed on-site within a facility) to be produced via electrolysis rather than via other production pathways. If the Non BAU Hydrogen Production Pathways lever is enabled, this lever works in the opposite direction by shifting hydrogen production to steam methane reforming. // **Guidance for setting values:** Today, roughly 95% of hydrogen is produced via steam reforming of natural gas and 5% is produced via electrolysis. These shares are not projected to change in the BAU case. | L89: switch-hydrogen-production-pathway.html
A90: District Heat and Hydrogen | B90: Non BAU Hydrogen Production Pathways | C90: Boolean Use Non BAU Hydrogen Shifting | D90: Hydrogen Steam Methane Reforming | E90: hydgn non BAU shift | F90: 0 | G90: 1 | H90: 1 | I90: on/off | J90: **Description:** This lever changes the direction of the "Shift Hydrogen Production Pathways" lever. By default, the "Shift Hydrogen Production Pathways" lever causes a percentage of merchant hydrogen (i.e. hydrogen produced for sale, not hydrogen produced and consumed on-site within a facility) to be produced via electrolysis rather than via other production pathways. If the Non BAU Hydrogen Production Pathways lever is enabled, it causes hydrogen production pathway shifting to work in the opposite direction by shifting hydrogen production to steam methane reforming. // **Guidance for setting values:** Today, roughly 95% of hydrogen is produced via steam reforming of natural gas and 5% is produced via electrolysis. Enabling this lever can be used to model repealing tax credits. | L90: switch-hydrogen-production-pathway.html
A91: Carbon Removal | B91: Direct Air Capture | C91: Fraction of Direct Air Capture Potential Achieved | D91: Carbon Dioxide Removal | E91: geoeng direct air capture | F91: 0 | G91: 1 | H91: 0.01 | I91: % of potential achieved | J91: **Description:** This policy causes direct air capture (DAC) technology to be used to remove carbon dioxide from the atmosphere. The modeled technology is based on hydroxide sorbents, as this is the most mature DAC technology. Alternatives (such as amine-based technologies) are unlikely to have a perceptible impact by 2050, the last year of the EPS model run. Note that all DAC technologies, even hydroxide sorbents, have their greatest potential effects after 2050, which cannot be seen in a model run that ends in 2050. (DAC refers only to mechanical methods of carbon dioxide removal, not afforestation and other land use measures. For those measures, see the policy levers in the "Agriculture, Land Use, and Forestry" category.) // **Guidance for setting values:** A 100% setting implies large DAC research and development investments starting today. | K91: direct-air-capture.html#dac | L91: direct-air-capture.html | M91: Realmonte et al., 2019, An inter-model assessment of the role of direct air capture in deep mitigation pathways, https://www.nature.com/articles/s41467-019-10842-5, Table 2, https://static-content.springer.com/esm/art%3A10.1038%2Fs41467-019-10842-5/MediaObjects/41467_2019_10842_MOESM1_ESM.pdf, Supplementary materials, Fig 3
A92: Carbon Removal | B92: Enhanced Rock Weathering | C92: Fraction of Enhanced Rock Weathering Potential Achieved | D92: Carbon Dioxide Removal | E92: geoeng enhanced rock weathering | F92: 0 | G92: 1 | H92: 0.01 | I92: % of potential achieved | J92: **Description:** This policy causes deployment of enhanced rock weathering practices to absorb CO2 from the atmosphere. We use data from Fuhrman et al., which assumes application of crushed basalt to croplands. // **Guidance for setting values:** A 100% setting implies rock application to roughly 45 million acres. | M92: Strefler et al., 2018, (used as a source on total acrege for our Fuhrman et al. data, https://content.cld.iop.org/journals/1748-9326/13/3/034010/revision2/ERL_034010_SD.pdf?Expires=1720629928&Signature=jHMnzWhptSu-2LByE4KdFSDS-DnRp9gzhnqimxxA1RXqsDDTo015nrsWRJqNRyNqExM59e0IjQOWRK1k6zkpTdrMxwQTaE1yD5yczeGsUNqiCqXYn5Zfj08uJQ-HIiuHek1qKCp8Njc9HMrxocyo~nIcf7eRRWkaRfOclfayd-52YV1Dgwv9N~rc2fbap9xGqOB5p8gCkQDmkXX2z5QnMMIkGBr-tGCrxZUxe0CuCxiYpVtI3rRDXkIgQamshSf4yA1QfcIwukn3F564By~Ztx0vUTUvbT7CIcfvUNkYkQDSKpzzi50D2Nv7usXFRIyOckZu1AJWhhzHbzcwburKrQ__&Key-Pair-Id=KL1D8TIY3N7T8
A93: Cross-Sector | B93: Carbon Price | C93: Additional Carbon Tax Rate | D93: Carbon Price | E93: cross carbon tax | F93: 0 | G93: =500000/1000 -> 500 | H93: 10 | I93: thousand KRW/metric ton CO2e | J93: **Description:** This policy sets an economy-wide carbon price in thousand KRW per metric ton of CO2 equivalent (CO2e). The price applies to emissions from fuel combustion, to process emissions from industrial and agricultural operations, and to the embedded carbon in capital equipment such as vehicles, power plants, and building materials. Process emissions can be excluded using the "Exempt Process Emissions from C Tax" lever. The price applies to imported goods only when the "Toggle Carbon Tax Border Adjustment" lever is enabled. // **Guidance for setting values:** Enter the carbon price in thousand KRW per metric ton CO2e; for example, a setting of 100 represents KRW 100,000 per metric ton CO2e. The BAU scenario contains no carbon price, so the value set here represents the full economy-wide carbon price rather than an addition to an existing one. This lever represents a modeled policy price and should not be read as the current Korea Emissions Trading Scheme allowance price or as an official South Korean social cost of carbon. | K93: fuels.html#carbon-tax | L93: carbon-tax.html | M93: U.S. EPA, 2015, "The Social Cost of Carbon", https://www.epa.gov/climatechange/social-cost-carbon, Row "2050". (For source for adjustment to 2018 dollars, see cpi.xlsx in InputData.) | N93: U.S. EPA, 2016, "Social Cost of CO2, 2015-2020," https://www.epa.gov/climatechange/social-cost-carbon
A94: Cross-Sector | B94: End Existing Subsidies | C94: Percent Reduction in BAU Subsidies | D94: End Existing Subsidies | E94: cross reduce BAU subsidies | F94: 0 | G94: 1 | H94: 0.01 | I94: % reduction in BAU subsidies | J94: **Description:** This policy reduces the subsidies paid for the production of the selected energy source(s) (relative to the BAU case). Note that some subsidies affect the cost of fuel (such as coal and natural gas), while some subsidies are for electricity production or capacity construction (Production Tax Credits and Investment Tax Credits). // **Guidance for setting values:** A value of 100% eliminates investment tax credits for wind, solar, geothermal, hydrogen, and nuclear. South Korea’s investment tax credit for renewable energy facilities is calculated by applying a fixed percentage (e.g., 1%, 3%, 7%) to the facility investment cost. As a result, subsidies for small-scale power generators may be overestimated compared to actual conditions. | K94: fuels.html#end-subsidies | L94: end-existing-subsidies.html | M94: Calculated from model data; see the relevant variable(s) in the InputData folder for source information.
A95: Cross-Sector | B95: Exempt Non-CO2 Emissions from C Tax | C95: Toggle Whether Carbon Tax Affects Non CO2 Emissions | E95: cross toggle whether carbon tax affects non CO2 emissions | F95: 0 | G95: 1 | H95: 1 | I95: on/off | J95: **Description:** By default, the carbon tax applies to CO2 and non-CO2 emissions. This policy exempts non-CO2 emissions, meaning the carbon tax will only apply to CO2 emissions. | K95: fuels.html#carbon-tax | L95: carbon-tax.html
A96: Cross-Sector | B96: Exempt Process Emissions from C Tax | C96: BEPEfCT Boolean Exempt Process Emissions from Carbon Tax | E96: cross toggle whether carbon tax affects process emissions | F96: 0 | G96: 1 | H96: 1 | I96: on/off | J96: **Description:** Turning this policy lever on prevents the carbon tax from being levied on process emissions from the selected industry categories. (Process emissions are non-energy greenhouse gas emissions from industrial and agricultural operations, for example emissions released due to chemical reactions during cement production). By default, we exempt agriculture and water and waste process emissions, as these categories are generally not covered by carbon tax proposals. | K96: fuels.html#carbon-tax | L96: carbon-tax.html
A97: Cross-Sector | B97: Toggle Carbon Tax Border Adjustment | C97: BDCTBA Boolean Disable Carbon Tax Border Adjustment | F97: 0 | G97: 1 | H97: 1 | I97: on/off | J97: **Description:** By default, carbon taxes apply to only domestically produced goods. Turning this policy lever on enables carbon tax border adjustments, meaning the carbon tax will apply to both domestically produced and imported goods. | K97: fuels.html#carbon-tax | L97: carbon-tax.html
A98: Cross-Sector | B98: Fixed Energy Prices | C98: Toggle Whether Policies Affect Energy Prices | D98: Fixed Energy Prices | E98: cross toggle whether policies affect energy prices | F98: 0 | G98: 1 | H98: 1 | I98: on/off
A99: Cross-Sector | B99: Fuel Price Deregulation | C99: Fuel Price Deregulation | D99: Fuel Price Deregulation | E99: cross fuel price deregulation | F99: 0 | G99: 1 | H99: 0.01 | I99: % of price deregulated | J99: **Description:** This policy causes the price of the selected fuel(s) for domestic buyers to approach international market prices. // **Guidance for setting values:** A value of 100% causes domestic fuel prices to equal international market prices, increasing the domestic price by roughly X% in 2050. | K99: fuels.html#fuel-price-deregulation
A100: Cross-Sector | B100: Fuel Taxes or Subsidies | C100: Additional Fuel Tax or Subsidy Rate by Fuel | D100: Fuel Taxes or Subsidies | E100: cross fuel tax | F100: -0.9 | G100: 0.9 | H100: 0.01 | I100: % of BAU price | J100: **Description:** This policy changes the tax rate for the selected fuel type(s). It is expressed as a percentage of the BAU Scenario price, which includes sales and excise taxes. To increase the tax rate, set a positive value. To reduce the BAU tax rate (or to apply a subsidy), set a negative value. // **Guidance for setting values:** South Korea’s current energy taxation system employs a specific tax structure, where taxes are levied per unit of fuel consumed. The tax burden is heavily concentrated on transportation fuels, notably gasoline, diesel, and LPG (butane). As of 2019, the applicable specific tax rates were as follows://Transportation: 762.36 won/L for gasoline, 545.22 won/L for diesel, and 383.057 won/kg for LPG (butane).//Heating & Industrial: 88.92 won/L for kerosene, 36.02 won/L for heavy fuel oil, and 24.527 won/kg for LPG (propane).//Power Generation & Other: 20.63 won/kg for LNG and 46 won/kg for bituminous coal. | K100: fuels.html#fuel-taxes | L100: fuel-taxes.html | M100: AVG SALES TAX: The Sales Tax Clearinghouse, FAQ, https://thestc.com/FAQ.stm, Question "What is the average sales tax nationally?" AVG GASOLINE TAX: Energy Information Administration, 2014, Annual Energy Outlook 2014, http://www.eia.gov/forecasts/aeo/supplement/suptab_130.xlsx, Supplement Table 130.
...

Sheet PolicyLevers
A1: Sector | B1: Short Name | C1: Vensim Variable Name | D1: Subscript 1 Value | E1: Subscript 2 Value | F1: Subscript 1 Display Name | G1: Subscript 2 Display Name | H1: Policy ID Number | I1: Include in Web App | J1: Policy Group | K1: Policy Schedule Subscript | L1: Min Slider Value | M1: Max Slider Value | N1: Slider Step Size | O1: Units | P1: Text for Pop-Over Panel Description | Q1: URL for "How the model handles this policy" links | R1: URL for "How to design this policy well" links
A2: =IF(ISBLANK(INDEX('Policy Characteristics'!A:A,MATCH($C2,'Policy Characteristics'!$C:$C,0))),"",INDEX('Policy Characteristics'!A:A,MATCH($C2,'Policy Characteristics'!$C:$C,0))) -> Transportation | B2: =IF(ISBLANK(INDEX('Policy Characteristics'!B:B,MATCH($C2,'Policy Characteristics'!$C:$C,0))),"",INDEX('Policy Characteristics'!B:B,MATCH($C2,'Policy Characteristics'!$C:$C,0))) -> Conventional Pollutant Standards | C2: Percentage Reduction of Separately Regulated Pollutants | D2: LDVs | E2: VOC | F2: Passenger cars, SUVs, Light and Medium Commercial Trucks | G2: VOCs | H2: 300 | I2: Yes | J2: =IF(ISBLANK(INDEX('Policy Characteristics'!D:D,MATCH($C2,'Policy Characteristics'!$C:$C,0))),"",INDEX('Policy Characteristics'!D:D,MATCH($C2,'Policy Characteristics'!$C:$C,0))) -> Conventional Pollutant Standard | K2: =IF(ISBLANK(INDEX('Policy Characteristics'!E:E,MATCH($C2,'Policy Characteristics'!$C:$C,0))),"",INDEX('Policy Characteristics'!E:E,MATCH($C2,'Policy Characteristics'!$C:$C,0))) -> trans reduce regulated pollutants | L2: =IF(ISBLANK(INDEX('Policy Characteristics'!F:F,MATCH($C2,'Policy Characteristics'!$C:$C,0))),"",INDEX('Policy Characteristics'!F:F,MATCH($C2,'Policy Characteristics'!$C:$C,0))) -> 0 | M2: =IF(ISBLANK(INDEX('Policy Characteristics'!G:G,MATCH($C2,'Policy Characteristics'!$C:$C,0))),"",INDEX('Policy Characteristics'!G:G,MATCH($C2,'Policy Characteristics'!$C:$C,0))) -> 1 | N2: =IF(ISBLANK(INDEX('Policy Characteristics'!H:H,MATCH($C2,'Policy Characteristics'!$C:$C,0))),"",INDEX('Policy Characteristics'!H:H,MATCH($C2,'Policy Characteristics'!$C:$C,0))) -> 0.02 | O2: =IF(ISBLANK(INDEX('Policy Characteristics'!I:I,MATCH($C2,'Policy Characteristics'!$C:$C,0))),"",INDEX('Policy Characteristics'!I:I,MATCH($C2,'Policy Characteristics'!$C:$C,0))) -> % reduction in emissions | P2: =IF(ISBLANK(INDEX('Policy Characteristics'!J:J,MATCH($C2,'Policy Characteristics'!$C:$C,0))),"",INDEX('Policy Characteristics'!J:J,MATCH($C2,'Policy Characteristics'!$C:$C,0))) -> **Description:** This policy represents strengthening standards for the selected pollutant(s) emitted by the selected vehicle type(s). Conventional pollutants' most important, harmful impacts are on human health rather than on climate change. // **Guidance for setting values:** In South Korea, the 24-hour national ambient air quality standard (NAAQS) for PM2.5, the most harmful type of particulate for human health, is 35 µg/m^3. For example, setting this policy lever to 5% means that the emission intensity for the selected pollutant(s) will be reduced by 5% relative to the current level, reflecting tighter tailpipe standards or enhanced inspection and maintenance programs. This level can be interpreted as a modest but meaningful tightening of emission control requirements. | Q2: =IF(ISBLANK(INDEX('Policy Characteristics'!K:K,MATCH($C2,'Policy Characteristics'!$C:$C,0))),"",INDEX('Policy Characteristics'!K:K,MATCH($C2,'Policy Characteristics'!$C:$C,0))) -> transportation-sector-main.html#conv-pol-stds | R2: =IF(ISBLANK(INDEX('Policy Characteristics'!L:L,MATCH($C2,'Policy Characteristics'!$C:$C,0))),"",INDEX('Policy Characteristics'!L:L,MATCH($C2,'Policy Characteristics'!$C:$C,0))) -> conventional-pollutant-standards.html
A3: =IF(ISBLANK(INDEX('Policy Characteristics'!A:A,MATCH($C3,'Policy Characteristics'!$C:$C,0))),"",INDEX('Policy Characteristics'!A:A,MATCH($C3,'Policy Characteristics'!$C:$C,0))) -> Transportation | B3: =IF(ISBLANK(INDEX('Policy Characteristics'!B:B,MATCH($C3,'Policy Characteristics'!$C:$C,0))),"",INDEX('Policy Characteristics'!B:B,MATCH($C3,'Policy Characteristics'!$C:$C,0))) -> Conventional Pollutant Standards | C3: =C$2 -> Percentage Reduction of Separately Regulated Pollutants | D3: LDVs | E3: CO | F3: Passenger cars, SUVs, Light and Medium Commercial Trucks | G3: CO | H3: 301 | I3: Yes | J3: =IF(ISBLANK(INDEX('Policy Characteristics'!D:D,MATCH($C3,'Policy Characteristics'!$C:$C,0))),"",INDEX('Policy Characteristics'!D:D,MATCH($C3,'Policy Characteristics'!$C:$C,0))) -> Conventional Pollutant Standard | K3: =IF(ISBLANK(INDEX('Policy Characteristics'!E:E,MATCH($C3,'Policy Characteristics'!$C:$C,0))),"",INDEX('Policy Characteristics'!E:E,MATCH($C3,'Policy Characteristics'!$C:$C,0))) -> trans reduce regulated pollutants | L3: =IF(ISBLANK(INDEX('Policy Characteristics'!F:F,MATCH($C3,'Policy Characteristics'!$C:$C,0))),"",INDEX('Policy Characteristics'!F:F,MATCH($C3,'Policy Characteristics'!$C:$C,0))) -> 0 | M3: =IF(ISBLANK(INDEX('Policy Characteristics'!G:G,MATCH($C3,'Policy Characteristics'!$C:$C,0))),"",INDEX('Policy Characteristics'!G:G,MATCH($C3,'Policy Characteristics'!$C:$C,0))) -> 1 | N3: =IF(ISBLANK(INDEX('Policy Characteristics'!H:H,MATCH($C3,'Policy Characteristics'!$C:$C,0))),"",INDEX('Policy Characteristics'!H:H,MATCH($C3,'Policy Characteristics'!$C:$C,0))) -> 0.02 | O3: =IF(ISBLANK(INDEX('Policy Characteristics'!I:I,MATCH($C3,'Policy Characteristics'!$C:$C,0))),"",INDEX('Policy Characteristics'!I:I,MATCH($C3,'Policy Characteristics'!$C:$C,0))) -> % reduction in emissions | P3: =IF(ISBLANK(INDEX('Policy Characteristics'!J:J,MATCH($C3,'Policy Characteristics'!$C:$C,0))),"",INDEX('Policy Characteristics'!J:J,MATCH($C3,'Policy Characteristics'!$C:$C,0))) -> **Description:** This policy represents strengthening standards for the selected pollutant(s) emitted by the selected vehicle type(s). Conventional pollutants' most important, harmful impacts are on human health rather than on climate change. // **Guidance for setting values:** In South Korea, the 24-hour national ambient air quality standard (NAAQS) for PM2.5, the most harmful type of particulate for human health, is 35 µg/m^3. For example, setting this policy lever to 5% means that the emission intensity for the selected pollutant(s) will be reduced by 5% relative to the current level, reflecting tighter tailpipe standards or enhanced inspection and maintenance programs. This level can be interpreted as a modest but meaningful tightening of emission control requirements. | Q3: =IF(ISBLANK(INDEX('Policy Characteristics'!K:K,MATCH($C3,'Policy Characteristics'!$C:$C,0))),"",INDEX('Policy Characteristics'!K:K,MATCH($C3,'Policy Characteristics'!$C:$C,0))) -> transportation-sector-main.html#conv-pol-stds | R3: =IF(ISBLANK(INDEX('Policy Characteristics'!L:L,MATCH($C3,'Policy Characteristics'!$C:$C,0))),"",INDEX('Policy Characteristics'!L:L,MATCH($C3,'Policy Characteristics'!$C:$C,0))) -> conventional-pollutant-standards.html
A4: =IF(ISBLANK(INDEX('Policy Characteristics'!A:A,MATCH($C4,'Policy Characteristics'!$C:$C,0))),"",INDEX('Policy Characteristics'!A:A,MATCH($C4,'Policy Characteristics'!$C:$C,0))) -> Transportation | B4: =IF(ISBLANK(INDEX('Policy Characteristics'!B:B,MATCH($C4,'Policy Characteristics'!$C:$C,0))),"",INDEX('Policy Characteristics'!B:B,MATCH($C4,'Policy Characteristics'!$C:$C,0))) -> Conventional Pollutant Standards | C4: =C$2 -> Percentage Reduction of Separately Regulated Pollutants | D4: LDVs | E4: NOx | F4: Passenger cars, SUVs, Light and Medium Commercial Trucks | G4: NOx | H4: 302 | I4: Yes | J4: =IF(ISBLANK(INDEX('Policy Characteristics'!D:D,MATCH($C4,'Policy Characteristics'!$C:$C,0))),"",INDEX('Policy Characteristics'!D:D,MATCH($C4,'Policy Characteristics'!$C:$C,0))) -> Conventional Pollutant Standard | K4: =IF(ISBLANK(INDEX('Policy Characteristics'!E:E,MATCH($C4,'Policy Characteristics'!$C:$C,0))),"",INDEX('Policy Characteristics'!E:E,MATCH($C4,'Policy Characteristics'!$C:$C,0))) -> trans reduce regulated pollutants | L4: =IF(ISBLANK(INDEX('Policy Characteristics'!F:F,MATCH($C4,'Policy Characteristics'!$C:$C,0))),"",INDEX('Policy Characteristics'!F:F,MATCH($C4,'Policy Characteristics'!$C:$C,0))) -> 0 | M4: =IF(ISBLANK(INDEX('Policy Characteristics'!G:G,MATCH($C4,'Policy Characteristics'!$C:$C,0))),"",INDEX('Policy Characteristics'!G:G,MATCH($C4,'Policy Characteristics'!$C:$C,0))) -> 1 | N4: =IF(ISBLANK(INDEX('Policy Characteristics'!H:H,MATCH($C4,'Policy Characteristics'!$C:$C,0))),"",INDEX('Policy Characteristics'!H:H,MATCH($C4,'Policy Characteristics'!$C:$C,0))) -> 0.02 | O4: =IF(ISBLANK(INDEX('Policy Characteristics'!I:I,MATCH($C4,'Policy Characteristics'!$C:$C,0))),"",INDEX('Policy Characteristics'!I:I,MATCH($C4,'Policy Characteristics'!$C:$C,0))) -> % reduction in emissions | P4: =IF(ISBLANK(INDEX('Policy Characteristics'!J:J,MATCH($C4,'Policy Characteristics'!$C:$C,0))),"",INDEX('Policy Characteristics'!J:J,MATCH($C4,'Policy Characteristics'!$C:$C,0))) -> **Description:** This policy represents strengthening standards for the selected pollutant(s) emitted by the selected vehicle type(s). Conventional pollutants' most important, harmful impacts are on human health rather than on climate change. // **Guidance for setting values:** In South Korea, the 24-hour national ambient air quality standard (NAAQS) for PM2.5, the most harmful type of particulate for human health, is 35 µg/m^3. For example, setting this policy lever to 5% means that the emission intensity for the selected pollutant(s) will be reduced by 5% relative to the current level, reflecting tighter tailpipe standards or enhanced inspection and maintenance programs. This level can be interpreted as a modest but meaningful tightening of emission control requirements. | Q4: =IF(ISBLANK(INDEX('Policy Characteristics'!K:K,MATCH($C4,'Policy Characteristics'!$C:$C,0))),"",INDEX('Policy Characteristics'!K:K,MATCH($C4,'Policy Characteristics'!$C:$C,0))) -> transportation-sector-main.html#conv-pol-stds | R4: =IF(ISBLANK(INDEX('Policy Characteristics'!L:L,MATCH($C4,'Policy Characteristics'!$C:$C,0))),"",INDEX('Policy Characteristics'!L:L,MATCH($C4,'Policy Characteristics'!$C:$C,0))) -> conventional-pollutant-standards.html
A5: =IF(ISBLANK(INDEX('Policy Characteristics'!A:A,MATCH($C5,'Policy Characteristics'!$C:$C,0))),"",INDEX('Policy Characteristics'!A:A,MATCH($C5,'Policy Characteristics'!$C:$C,0))) -> Transportation | B5: =IF(ISBLANK(INDEX('Policy Characteristics'!B:B,MATCH($C5,'Policy Characteristics'!$C:$C,0))),"",INDEX('Policy Characteristics'!B:B,MATCH($C5,'Policy Characteristics'!$C:$C,0))) -> Conventional Pollutant Standards | C5: =C$2 -> Percentage Reduction of Separately Regulated Pollutants | D5: LDVs | E5: PM10 | F5: Passenger cars, SUVs, Light and Medium Commercial Trucks | G5: PM10 | H5: 303 | I5: Yes | J5: =IF(ISBLANK(INDEX('Policy Characteristics'!D:D,MATCH($C5,'Policy Characteristics'!$C:$C,0))),"",INDEX('Policy Characteristics'!D:D,MATCH($C5,'Policy Characteristics'!$C:$C,0))) -> Conventional Pollutant Standard | K5: =IF(ISBLANK(INDEX('Policy Characteristics'!E:E,MATCH($C5,'Policy Characteristics'!$C:$C,0))),"",INDEX('Policy Characteristics'!E:E,MATCH($C5,'Policy Characteristics'!$C:$C,0))) -> trans reduce regulated pollutants | L5: =IF(ISBLANK(INDEX('Policy Characteristics'!F:F,MATCH($C5,'Policy Characteristics'!$C:$C,0))),"",INDEX('Policy Characteristics'!F:F,MATCH($C5,'Policy Characteristics'!$C:$C,0))) -> 0 | M5: =IF(ISBLANK(INDEX('Policy Characteristics'!G:G,MATCH($C5,'Policy Characteristics'!$C:$C,0))),"",INDEX('Policy Characteristics'!G:G,MATCH($C5,'Policy Characteristics'!$C:$C,0))) -> 1 | N5: =IF(ISBLANK(INDEX('Policy Characteristics'!H:H,MATCH($C5,'Policy Characteristics'!$C:$C,0))),"",INDEX('Policy Characteristics'!H:H,MATCH($C5,'Policy Characteristics'!$C:$C,0))) -> 0.02 | O5: =IF(ISBLANK(INDEX('Policy Characteristics'!I:I,MATCH($C5,'Policy Characteristics'!$C:$C,0))),"",INDEX('Policy Characteristics'!I:I,MATCH($C5,'Policy Characteristics'!$C:$C,0))) -> % reduction in emissions | P5: =IF(ISBLANK(INDEX('Policy Characteristics'!J:J,MATCH($C5,'Policy Characteristics'!$C:$C,0))),"",INDEX('Policy Characteristics'!J:J,MATCH($C5,'Policy Characteristics'!$C:$C,0))) -> **Description:** This policy represents strengthening standards for the selected pollutant(s) emitted by the selected vehicle type(s). Conventional pollutants' most important, harmful impacts are on human health rather than on climate change. // **Guidance for setting values:** In South Korea, the 24-hour national ambient air quality standard (NAAQS) for PM2.5, the most harmful type of particulate for human health, is 35 µg/m^3. For example, setting this policy lever to 5% means that the emission intensity for the selected pollutant(s) will be reduced by 5% relative to the current level, reflecting tighter tailpipe standards or enhanced inspection and maintenance programs. This level can be interpreted as a modest but meaningful tightening of emission control requirements. | Q5: =IF(ISBLANK(INDEX('Policy Characteristics'!K:K,MATCH($C5,'Policy Characteristics'!$C:$C,0))),"",INDEX('Policy Characteristics'!K:K,MATCH($C5,'Policy Characteristics'!$C:$C,0))) -> transportation-sector-main.html#conv-pol-stds | R5: =IF(ISBLANK(INDEX('Policy Characteristics'!L:L,MATCH($C5,'Policy Characteristics'!$C:$C,0))),"",INDEX('Policy Characteristics'!L:L,MATCH($C5,'Policy Characteristics'!$C:$C,0))) -> conventional-pollutant-standards.html
A6: =IF(ISBLANK(INDEX('Policy Characteristics'!A:A,MATCH($C6,'Policy Characteristics'!$C:$C,0))),"",INDEX('Policy Characteristics'!A:A,MATCH($C6,'Policy Characteristics'!$C:$C,0))) -> Transportation | B6: =IF(ISBLANK(INDEX('Policy Characteristics'!B:B,MATCH($C6,'Policy Characteristics'!$C:$C,0))),"",INDEX('Policy Characteristics'!B:B,MATCH($C6,'Policy Characteristics'!$C:$C,0))) -> Conventional Pollutant Standards | C6: =C$2 -> Percentage Reduction of Separately Regulated Pollutants | D6: LDVs | E6: PM25 | F6: Passenger cars, SUVs, Light and Medium Commercial Trucks | G6: PM2.5 | H6: 304 | I6: Yes | J6: =IF(ISBLANK(INDEX('Policy Characteristics'!D:D,MATCH($C6,'Policy Characteristics'!$C:$C,0))),"",INDEX('Policy Characteristics'!D:D,MATCH($C6,'Policy Characteristics'!$C:$C,0))) -> Conventional Pollutant Standard | K6: =IF(ISBLANK(INDEX('Policy Characteristics'!E:E,MATCH($C6,'Policy Characteristics'!$C:$C,0))),"",INDEX('Policy Characteristics'!E:E,MATCH($C6,'Policy Characteristics'!$C:$C,0))) -> trans reduce regulated pollutants | L6: =IF(ISBLANK(INDEX('Policy Characteristics'!F:F,MATCH($C6,'Policy Characteristics'!$C:$C,0))),"",INDEX('Policy Characteristics'!F:F,MATCH($C6,'Policy Characteristics'!$C:$C,0))) -> 0 | M6: =IF(ISBLANK(INDEX('Policy Characteristics'!G:G,MATCH($C6,'Policy Characteristics'!$C:$C,0))),"",INDEX('Policy Characteristics'!G:G,MATCH($C6,'Policy Characteristics'!$C:$C,0))) -> 1 | N6: =IF(ISBLANK(INDEX('Policy Characteristics'!H:H,MATCH($C6,'Policy Characteristics'!$C:$C,0))),"",INDEX('Policy Characteristics'!H:H,MATCH($C6,'Policy Characteristics'!$C:$C,0))) -> 0.02 | O6: =IF(ISBLANK(INDEX('Policy Characteristics'!I:I,MATCH($C6,'Policy Characteristics'!$C:$C,0))),"",INDEX('Policy Characteristics'!I:I,MATCH($C6,'Policy Characteristics'!$C:$C,0))) -> % reduction in emissions | P6: =IF(ISBLANK(INDEX('Policy Characteristics'!J:J,MATCH($C6,'Policy Characteristics'!$C:$C,0))),"",INDEX('Policy Characteristics'!J:J,MATCH($C6,'Policy Characteristics'!$C:$C,0))) -> **Description:** This policy represents strengthening standards for the selected pollutant(s) emitted by the selected vehicle type(s). Conventional pollutants' most important, harmful impacts are on human health rather than on climate change. // **Guidance for setting values:** In South Korea, the 24-hour national ambient air quality standard (NAAQS) for PM2.5, the most harmful type of particulate for human health, is 35 µg/m^3. For example, setting this policy lever to 5% means that the emission intensity for the selected pollutant(s) will be reduced by 5% relative to the current level, reflecting tighter tailpipe standards or enhanced inspection and maintenance programs. This level can be interpreted as a modest but meaningful tightening of emission control requirements. | Q6: =IF(ISBLANK(INDEX('Policy Characteristics'!K:K,MATCH($C6,'Policy Characteristics'!$C:$C,0))),"",INDEX('Policy Characteristics'!K:K,MATCH($C6,'Policy Characteristics'!$C:$C,0))) -> transportation-sector-main.html#conv-pol-stds | R6: =IF(ISBLANK(INDEX('Policy Characteristics'!L:L,MATCH($C6,'Policy Characteristics'!$C:$C,0))),"",INDEX('Policy Characteristics'!L:L,MATCH($C6,'Policy Characteristics'!$C:$C,0))) -> conventional-pollutant-standards.html
A7: =IF(ISBLANK(INDEX('Policy Characteristics'!A:A,MATCH($C7,'Policy Characteristics'!$C:$C,0))),"",INDEX('Policy Characteristics'!A:A,MATCH($C7,'Policy Characteristics'!$C:$C,0))) -> Transportation | B7: =IF(ISBLANK(INDEX('Policy Characteristics'!B:B,MATCH($C7,'Policy Characteristics'!$C:$C,0))),"",INDEX('Policy Characteristics'!B:B,MATCH($C7,'Policy Characteristics'!$C:$C,0))) -> Conventional Pollutant Standards | C7: =C$2 -> Percentage Reduction of Separately Regulated Pollutants | D7: LDVs | E7: SOx | F7: Passenger cars, SUVs, Light and Medium Commercial Trucks | G7: SOx | H7: 305 | I7: Yes | J7: =IF(ISBLANK(INDEX('Policy Characteristics'!D:D,MATCH($C7,'Policy Characteristics'!$C:$C,0))),"",INDEX('Policy Characteristics'!D:D,MATCH($C7,'Policy Characteristics'!$C:$C,0))) -> Conventional Pollutant Standard | K7: =IF(ISBLANK(INDEX('Policy Characteristics'!E:E,MATCH($C7,'Policy Characteristics'!$C:$C,0))),"",INDEX('Policy Characteristics'!E:E,MATCH($C7,'Policy Characteristics'!$C:$C,0))) -> trans reduce regulated pollutants | L7: =IF(ISBLANK(INDEX('Policy Characteristics'!F:F,MATCH($C7,'Policy Characteristics'!$C:$C,0))),"",INDEX('Policy Characteristics'!F:F,MATCH($C7,'Policy Characteristics'!$C:$C,0))) -> 0 | M7: =IF(ISBLANK(INDEX('Policy Characteristics'!G:G,MATCH($C7,'Policy Characteristics'!$C:$C,0))),"",INDEX('Policy Characteristics'!G:G,MATCH($C7,'Policy Characteristics'!$C:$C,0))) -> 1 | N7: =IF(ISBLANK(INDEX('Policy Characteristics'!H:H,MATCH($C7,'Policy Characteristics'!$C:$C,0))),"",INDEX('Policy Characteristics'!H:H,MATCH($C7,'Policy Characteristics'!$C:$C,0))) -> 0.02 | O7: =IF(ISBLANK(INDEX('Policy Characteristics'!I:I,MATCH($C7,'Policy Characteristics'!$C:$C,0))),"",INDEX('Policy Characteristics'!I:I,MATCH($C7,'Policy Characteristics'!$C:$C,0))) -> % reduction in emissions | P7: =IF(ISBLANK(INDEX('Policy Characteristics'!J:J,MATCH($C7,'Policy Characteristics'!$C:$C,0))),"",INDEX('Policy Characteristics'!J:J,MATCH($C7,'Policy Characteristics'!$C:$C,0))) -> **Description:** This policy represents strengthening standards for the selected pollutant(s) emitted by the selected vehicle type(s). Conventional pollutants' most important, harmful impacts are on human health rather than on climate change. // **Guidance for setting values:** In South Korea, the 24-hour national ambient air quality standard (NAAQS) for PM2.5, the most harmful type of particulate for human health, is 35 µg/m^3. For example, setting this policy lever to 5% means that the emission intensity for the selected pollutant(s) will be reduced by 5% relative to the current level, reflecting tighter tailpipe standards or enhanced inspection and maintenance programs. This level can be interpreted as a modest but meaningful tightening of emission control requirements. | Q7: =IF(ISBLANK(INDEX('Policy Characteristics'!K:K,MATCH($C7,'Policy Characteristics'!$C:$C,0))),"",INDEX('Policy Characteristics'!K:K,MATCH($C7,'Policy Characteristics'!$C:$C,0))) -> transportation-sector-main.html#conv-pol-stds | R7: =IF(ISBLANK(INDEX('Policy Characteristics'!L:L,MATCH($C7,'Policy Characteristics'!$C:$C,0))),"",INDEX('Policy Characteristics'!L:L,MATCH($C7,'Policy Characteristics'!$C:$C,0))) -> conventional-pollutant-standards.html
A8: =IF(ISBLANK(INDEX('Policy Characteristics'!A:A,MATCH($C8,'Policy Characteristics'!$C:$C,0))),"",INDEX('Policy Characteristics'!A:A,MATCH($C8,'Policy Characteristics'!$C:$C,0))) -> Transportation | B8: =IF(ISBLANK(INDEX('Policy Characteristics'!B:B,MATCH($C8,'Policy Characteristics'!$C:$C,0))),"",INDEX('Policy Characteristics'!B:B,MATCH($C8,'Policy Characteristics'!$C:$C,0))) -> Conventional Pollutant Standards | C8: =C$2 -> Percentage Reduction of Separately Regulated Pollutants | D8: LDVs | E8: BC | F8: Passenger cars, SUVs, Light and Medium Commercial Trucks | G8: BC | H8: 306 | I8: Yes | J8: =IF(ISBLANK(INDEX('Policy Characteristics'!D:D,MATCH($C8,'Policy Characteristics'!$C:$C,0))),"",INDEX('Policy Characteristics'!D:D,MATCH($C8,'Policy Characteristics'!$C:$C,0))) -> Conventional Pollutant Standard | K8: =IF(ISBLANK(INDEX('Policy Characteristics'!E:E,MATCH($C8,'Policy Characteristics'!$C:$C,0))),"",INDEX('Policy Characteristics'!E:E,MATCH($C8,'Policy Characteristics'!$C:$C,0))) -> trans reduce regulated pollutants | L8: =IF(ISBLANK(INDEX('Policy Characteristics'!F:F,MATCH($C8,'Policy Characteristics'!$C:$C,0))),"",INDEX('Policy Characteristics'!F:F,MATCH($C8,'Policy Characteristics'!$C:$C,0))) -> 0 | M8: =IF(ISBLANK(INDEX('Policy Characteristics'!G:G,MATCH($C8,'Policy Characteristics'!$C:$C,0))),"",INDEX('Policy Characteristics'!G:G,MATCH($C8,'Policy Characteristics'!$C:$C,0))) -> 1 | N8: =IF(ISBLANK(INDEX('Policy Characteristics'!H:H,MATCH($C8,'Policy Characteristics'!$C:$C,0))),"",INDEX('Policy Characteristics'!H:H,MATCH($C8,'Policy Characteristics'!$C:$C,0))) -> 0.02 | O8: =IF(ISBLANK(INDEX('Policy Characteristics'!I:I,MATCH($C8,'Policy Characteristics'!$C:$C,0))),"",INDEX('Policy Characteristics'!I:I,MATCH($C8,'Policy Characteristics'!$C:$C,0))) -> % reduction in emissions | P8: =IF(ISBLANK(INDEX('Policy Characteristics'!J:J,MATCH($C8,'Policy Characteristics'!$C:$C,0))),"",INDEX('Policy Characteristics'!J:J,MATCH($C8,'Policy Characteristics'!$C:$C,0))) -> **Description:** This policy represents strengthening standards for the selected pollutant(s) emitted by the selected vehicle type(s). Conventional pollutants' most important, harmful impacts are on human health rather than on climate change. // **Guidance for setting values:** In South Korea, the 24-hour national ambient air quality standard (NAAQS) for PM2.5, the most harmful type of particulate for human health, is 35 µg/m^3. For example, setting this policy lever to 5% means that the emission intensity for the selected pollutant(s) will be reduced by 5% relative to the current level, reflecting tighter tailpipe standards or enhanced inspection and maintenance programs. This level can be interpreted as a modest but meaningful tightening of emission control requirements. | Q8: =IF(ISBLANK(INDEX('Policy Characteristics'!K:K,MATCH($C8,'Policy Characteristics'!$C:$C,0))),"",INDEX('Policy Characteristics'!K:K,MATCH($C8,'Policy Characteristics'!$C:$C,0))) -> transportation-sector-main.html#conv-pol-stds | R8: =IF(ISBLANK(INDEX('Policy Characteristics'!L:L,MATCH($C8,'Policy Characteristics'!$C:$C,0))),"",INDEX('Policy Characteristics'!L:L,MATCH($C8,'Policy Characteristics'!$C:$C,0))) -> conventional-pollutant-standards.html
A9: =IF(ISBLANK(INDEX('Policy Characteristics'!A:A,MATCH($C9,'Policy Characteristics'!$C:$C,0))),"",INDEX('Policy Characteristics'!A:A,MATCH($C9,'Policy Characteristics'!$C:$C,0))) -> Transportation | B9: =IF(ISBLANK(INDEX('Policy Characteristics'!B:B,MATCH($C9,'Policy Characteristics'!$C:$C,0))),"",INDEX('Policy Characteristics'!B:B,MATCH($C9,'Policy Characteristics'!$C:$C,0))) -> Conventional Pollutant Standards | C9: =C$2 -> Percentage Reduction of Separately Regulated Pollutants | D9: LDVs | E9: OC | F9: Passenger cars, SUVs, Light and Medium Commercial Trucks | G9: OC | H9: 307 | I9: Yes | J9: =IF(ISBLANK(INDEX('Policy Characteristics'!D:D,MATCH($C9,'Policy Characteristics'!$C:$C,0))),"",INDEX('Policy Characteristics'!D:D,MATCH($C9,'Policy Characteristics'!$C:$C,0))) -> Conventional Pollutant Standard | K9: =IF(ISBLANK(INDEX('Policy Characteristics'!E:E,MATCH($C9,'Policy Characteristics'!$C:$C,0))),"",INDEX('Policy Characteristics'!E:E,MATCH($C9,'Policy Characteristics'!$C:$C,0))) -> trans reduce regulated pollutants | L9: =IF(ISBLANK(INDEX('Policy Characteristics'!F:F,MATCH($C9,'Policy Characteristics'!$C:$C,0))),"",INDEX('Policy Characteristics'!F:F,MATCH($C9,'Policy Characteristics'!$C:$C,0))) -> 0 | M9: =IF(ISBLANK(INDEX('Policy Characteristics'!G:G,MATCH($C9,'Policy Characteristics'!$C:$C,0))),"",INDEX('Policy Characteristics'!G:G,MATCH($C9,'Policy Characteristics'!$C:$C,0))) -> 1 | N9: =IF(ISBLANK(INDEX('Policy Characteristics'!H:H,MATCH($C9,'Policy Characteristics'!$C:$C,0))),"",INDEX('Policy Characteristics'!H:H,MATCH($C9,'Policy Characteristics'!$C:$C,0))) -> 0.02 | O9: =IF(ISBLANK(INDEX('Policy Characteristics'!I:I,MATCH($C9,'Policy Characteristics'!$C:$C,0))),"",INDEX('Policy Characteristics'!I:I,MATCH($C9,'Policy Characteristics'!$C:$C,0))) -> % reduction in emissions | P9: =IF(ISBLANK(INDEX('Policy Characteristics'!J:J,MATCH($C9,'Policy Characteristics'!$C:$C,0))),"",INDEX('Policy Characteristics'!J:J,MATCH($C9,'Policy Characteristics'!$C:$C,0))) -> **Description:** This policy represents strengthening standards for the selected pollutant(s) emitted by the selected vehicle type(s). Conventional pollutants' most important, harmful impacts are on human health rather than on climate change. // **Guidance for setting values:** In South Korea, the 24-hour national ambient air quality standard (NAAQS) for PM2.5, the most harmful type of particulate for human health, is 35 µg/m^3. For example, setting this policy lever to 5% means that the emission intensity for the selected pollutant(s) will be reduced by 5% relative to the current level, reflecting tighter tailpipe standards or enhanced inspection and maintenance programs. This level can be interpreted as a modest but meaningful tightening of emission control requirements. | Q9: =IF(ISBLANK(INDEX('Policy Characteristics'!K:K,MATCH($C9,'Policy Characteristics'!$C:$C,0))),"",INDEX('Policy Characteristics'!K:K,MATCH($C9,'Policy Characteristics'!$C:$C,0))) -> transportation-sector-main.html#conv-pol-stds | R9: =IF(ISBLANK(INDEX('Policy Characteristics'!L:L,MATCH($C9,'Policy Characteristics'!$C:$C,0))),"",INDEX('Policy Characteristics'!L:L,MATCH($C9,'Policy Characteristics'!$C:$C,0))) -> conventional-pollutant-standards.html
A10: =IF(ISBLANK(INDEX('Policy Characteristics'!A:A,MATCH($C10,'Policy Characteristics'!$C:$C,0))),"",INDEX('Policy Characteristics'!A:A,MATCH($C10,'Policy Characteristics'!$C:$C,0))) -> Transportation | B10: =IF(ISBLANK(INDEX('Policy Characteristics'!B:B,MATCH($C10,'Policy Characteristics'!$C:$C,0))),"",INDEX('Policy Characteristics'!B:B,MATCH($C10,'Policy Characteristics'!$C:$C,0))) -> Conventional Pollutant Standards | C10: =C$2 -> Percentage Reduction of Separately Regulated Pollutants | D10: LDVs | E10: CH4 | F10: Passenger cars, SUVs, Light and Medium Commercial Trucks | G10: CH4 | H10: 308 | I10: No | J10: =IF(ISBLANK(INDEX('Policy Characteristics'!D:D,MATCH($C10,'Policy Characteristics'!$C:$C,0))),"",INDEX('Policy Characteristics'!D:D,MATCH($C10,'Policy Characteristics'!$C:$C,0))) -> Conventional Pollutant Standard | K10: =IF(ISBLANK(INDEX('Policy Characteristics'!E:E,MATCH($C10,'Policy Characteristics'!$C:$C,0))),"",INDEX('Policy Characteristics'!E:E,MATCH($C10,'Policy Characteristics'!$C:$C,0))) -> trans reduce regulated pollutants | L10: =IF(ISBLANK(INDEX('Policy Characteristics'!F:F,MATCH($C10,'Policy Characteristics'!$C:$C,0))),"",INDEX('Policy Characteristics'!F:F,MATCH($C10,'Policy Characteristics'!$C:$C,0))) -> 0 | M10: =IF(ISBLANK(INDEX('Policy Characteristics'!G:G,MATCH($C10,'Policy Characteristics'!$C:$C,0))),"",INDEX('Policy Characteristics'!G:G,MATCH($C10,'Policy Characteristics'!$C:$C,0))) -> 1 | N10: =IF(ISBLANK(INDEX('Policy Characteristics'!H:H,MATCH($C10,'Policy Characteristics'!$C:$C,0))),"",INDEX('Policy Characteristics'!H:H,MATCH($C10,'Policy Characteristics'!$C:$C,0))) -> 0.02 | O10: =IF(ISBLANK(INDEX('Policy Characteristics'!I:I,MATCH($C10,'Policy Characteristics'!$C:$C,0))),"",INDEX('Policy Characteristics'!I:I,MATCH($C10,'Policy Characteristics'!$C:$C,0))) -> % reduction in emissions | P10: =IF(ISBLANK(INDEX('Policy Characteristics'!J:J,MATCH($C10,'Policy Characteristics'!$C:$C,0))),"",INDEX('Policy Characteristics'!J:J,MATCH($C10,'Policy Characteristics'!$C:$C,0))) -> **Description:** This policy represents strengthening standards for the selected pollutant(s) emitted by the selected vehicle type(s). Conventional pollutants' most important, harmful impacts are on human health rather than on climate change. // **Guidance for setting values:** In South Korea, the 24-hour national ambient air quality standard (NAAQS) for PM2.5, the most harmful type of particulate for human health, is 35 µg/m^3. For example, setting this policy lever to 5% means that the emission intensity for the selected pollutant(s) will be reduced by 5% relative to the current level, reflecting tighter tailpipe standards or enhanced inspection and maintenance programs. This level can be interpreted as a modest but meaningful tightening of emission control requirements. | Q10: =IF(ISBLANK(INDEX('Policy Characteristics'!K:K,MATCH($C10,'Policy Characteristics'!$C:$C,0))),"",INDEX('Policy Characteristics'!K:K,MATCH($C10,'Policy Characteristics'!$C:$C,0))) -> transportation-sector-main.html#conv-pol-stds | R10: =IF(ISBLANK(INDEX('Policy Characteristics'!L:L,MATCH($C10,'Policy Characteristics'!$C:$C,0))),"",INDEX('Policy Characteristics'!L:L,MATCH($C10,'Policy Characteristics'!$C:$C,0))) -> conventional-pollutant-standards.html
A11: =IF(ISBLANK(INDEX('Policy Characteristics'!A:A,MATCH($C11,'Policy Characteristics'!$C:$C,0))),"",INDEX('Policy Characteristics'!A:A,MATCH($C11,'Policy Characteristics'!$C:$C,0))) -> Transportation | B11: =IF(ISBLANK(INDEX('Policy Characteristics'!B:B,MATCH($C11,'Policy Characteristics'!$C:$C,0))),"",INDEX('Policy Characteristics'!B:B,MATCH($C11,'Policy Characteristics'!$C:$C,0))) -> Conventional Pollutant Standards | C11: =C$2 -> Percentage Reduction of Separately Regulated Pollutants | D11: LDVs | E11: N2O | F11: Passenger cars, SUVs, Light and Medium Commercial Trucks | G11: N2O | H11: 309 | I11: No | J11: =IF(ISBLANK(INDEX('Policy Characteristics'!D:D,MATCH($C11,'Policy Characteristics'!$C:$C,0))),"",INDEX('Policy Characteristics'!D:D,MATCH($C11,'Policy Characteristics'!$C:$C,0))) -> Conventional Pollutant Standard | K11: =IF(ISBLANK(INDEX('Policy Characteristics'!E:E,MATCH($C11,'Policy Characteristics'!$C:$C,0))),"",INDEX('Policy Characteristics'!E:E,MATCH($C11,'Policy Characteristics'!$C:$C,0))) -> trans reduce regulated pollutants | L11: =IF(ISBLANK(INDEX('Policy Characteristics'!F:F,MATCH($C11,'Policy Characteristics'!$C:$C,0))),"",INDEX('Policy Characteristics'!F:F,MATCH($C11,'Policy Characteristics'!$C:$C,0))) -> 0 | M11: =IF(ISBLANK(INDEX('Policy Characteristics'!G:G,MATCH($C11,'Policy Characteristics'!$C:$C,0))),"",INDEX('Policy Characteristics'!G:G,MATCH($C11,'Policy Characteristics'!$C:$C,0))) -> 1 | N11: =IF(ISBLANK(INDEX('Policy Characteristics'!H:H,MATCH($C11,'Policy Characteristics'!$C:$C,0))),"",INDEX('Policy Characteristics'!H:H,MATCH($C11,'Policy Characteristics'!$C:$C,0))) -> 0.02 | O11: =IF(ISBLANK(INDEX('Policy Characteristics'!I:I,MATCH($C11,'Policy Characteristics'!$C:$C,0))),"",INDEX('Policy Characteristics'!I:I,MATCH($C11,'Policy Characteristics'!$C:$C,0))) -> % reduction in emissions | P11: =IF(ISBLANK(INDEX('Policy Characteristics'!J:J,MATCH($C11,'Policy Characteristics'!$C:$C,0))),"",INDEX('Policy Characteristics'!J:J,MATCH($C11,'Policy Characteristics'!$C:$C,0))) -> **Description:** This policy represents strengthening standards for the selected pollutant(s) emitted by the selected vehicle type(s). Conventional pollutants' most important, harmful impacts are on human health rather than on climate change. // **Guidance for setting values:** In South Korea, the 24-hour national ambient air quality standard (NAAQS) for PM2.5, the most harmful type of particulate for human health, is 35 µg/m^3. For example, setting this policy lever to 5% means that the emission intensity for the selected pollutant(s) will be reduced by 5% relative to the current level, reflecting tighter tailpipe standards or enhanced inspection and maintenance programs. This level can be interpreted as a modest but meaningful tightening of emission control requirements. | Q11: =IF(ISBLANK(INDEX('Policy Characteristics'!K:K,MATCH($C11,'Policy Characteristics'!$C:$C,0))),"",INDEX('Policy Characteristics'!K:K,MATCH($C11,'Policy Characteristics'!$C:$C,0))) -> transportation-sector-main.html#conv-pol-stds | R11: =IF(ISBLANK(INDEX('Policy Characteristics'!L:L,MATCH($C11,'Policy Characteristics'!$C:$C,0))),"",INDEX('Policy Characteristics'!L:L,MATCH($C11,'Policy Characteristics'!$C:$C,0))) -> conventional-pollutant-standards.html
A12: =IF(ISBLANK(INDEX('Policy Characteristics'!A:A,MATCH($C12,'Policy Characteristics'!$C:$C,0))),"",INDEX('Policy Characteristics'!A:A,MATCH($C12,'Policy Characteristics'!$C:$C,0))) -> Transportation | B12: =IF(ISBLANK(INDEX('Policy Characteristics'!B:B,MATCH($C12,'Policy Characteristics'!$C:$C,0))),"",INDEX('Policy Characteristics'!B:B,MATCH($C12,'Policy Characteristics'!$C:$C,0))) -> Conventional Pollutant Standards | C12: =C$2 -> Percentage Reduction of Separately Regulated Pollutants | D12: HDVs | E12: VOC | F12: Buses and Heavy Duty Trucks | G12: VOCs | H12: 310 | I12: Yes | J12: =IF(ISBLANK(INDEX('Policy Characteristics'!D:D,MATCH($C12,'Policy Characteristics'!$C:$C,0))),"",INDEX('Policy Characteristics'!D:D,MATCH($C12,'Policy Characteristics'!$C:$C,0))) -> Conventional Pollutant Standard | K12: =IF(ISBLANK(INDEX('Policy Characteristics'!E:E,MATCH($C12,'Policy Characteristics'!$C:$C,0))),"",INDEX('Policy Characteristics'!E:E,MATCH($C12,'Policy Characteristics'!$C:$C,0))) -> trans reduce regulated pollutants | L12: =IF(ISBLANK(INDEX('Policy Characteristics'!F:F,MATCH($C12,'Policy Characteristics'!$C:$C,0))),"",INDEX('Policy Characteristics'!F:F,MATCH($C12,'Policy Characteristics'!$C:$C,0))) -> 0 | M12: =IF(ISBLANK(INDEX('Policy Characteristics'!G:G,MATCH($C12,'Policy Characteristics'!$C:$C,0))),"",INDEX('Policy Characteristics'!G:G,MATCH($C12,'Policy Characteristics'!$C:$C,0))) -> 1 | N12: =IF(ISBLANK(INDEX('Policy Characteristics'!H:H,MATCH($C12,'Policy Characteristics'!$C:$C,0))),"",INDEX('Policy Characteristics'!H:H,MATCH($C12,'Policy Characteristics'!$C:$C,0))) -> 0.02 | O12: =IF(ISBLANK(INDEX('Policy Characteristics'!I:I,MATCH($C12,'Policy Characteristics'!$C:$C,0))),"",INDEX('Policy Characteristics'!I:I,MATCH($C12,'Policy Characteristics'!$C:$C,0))) -> % reduction in emissions | P12: =IF(ISBLANK(INDEX('Policy Characteristics'!J:J,MATCH($C12,'Policy Characteristics'!$C:$C,0))),"",INDEX('Policy Characteristics'!J:J,MATCH($C12,'Policy Characteristics'!$C:$C,0))) -> **Description:** This policy represents strengthening standards for the selected pollutant(s) emitted by the selected vehicle type(s). Conventional pollutants' most important, harmful impacts are on human health rather than on climate change. // **Guidance for setting values:** In South Korea, the 24-hour national ambient air quality standard (NAAQS) for PM2.5, the most harmful type of particulate for human health, is 35 µg/m^3. For example, setting this policy lever to 5% means that the emission intensity for the selected pollutant(s) will be reduced by 5% relative to the current level, reflecting tighter tailpipe standards or enhanced inspection and maintenance programs. This level can be interpreted as a modest but meaningful tightening of emission control requirements. | Q12: =IF(ISBLANK(INDEX('Policy Characteristics'!K:K,MATCH($C12,'Policy Characteristics'!$C:$C,0))),"",INDEX('Policy Characteristics'!K:K,MATCH($C12,'Policy Characteristics'!$C:$C,0))) -> transportation-sector-main.html#conv-pol-stds | R12: =IF(ISBLANK(INDEX('Policy Characteristics'!L:L,MATCH($C12,'Policy Characteristics'!$C:$C,0))),"",INDEX('Policy Characteristics'!L:L,MATCH($C12,'Policy Characteristics'!$C:$C,0))) -> conventional-pollutant-standards.html
A13: =IF(ISBLANK(INDEX('Policy Characteristics'!A:A,MATCH($C13,'Policy Characteristics'!$C:$C,0))),"",INDEX('Policy Characteristics'!A:A,MATCH($C13,'Policy Characteristics'!$C:$C,0))) -> Transportation | B13: =IF(ISBLANK(INDEX('Policy Characteristics'!B:B,MATCH($C13,'Policy Characteristics'!$C:$C,0))),"",INDEX('Policy Characteristics'!B:B,MATCH($C13,'Policy Characteristics'!$C:$C,0))) -> Conventional Pollutant Standards | C13: =C$2 -> Percentage Reduction of Separately Regulated Pollutants | D13: HDVs | E13: CO | F13: Buses and Heavy Duty Trucks | G13: CO | H13: 311 | I13: Yes | J13: =IF(ISBLANK(INDEX('Policy Characteristics'!D:D,MATCH($C13,'Policy Characteristics'!$C:$C,0))),"",INDEX('Policy Characteristics'!D:D,MATCH($C13,'Policy Characteristics'!$C:$C,0))) -> Conventional Pollutant Standard | K13: =IF(ISBLANK(INDEX('Policy Characteristics'!E:E,MATCH($C13,'Policy Characteristics'!$C:$C,0))),"",INDEX('Policy Characteristics'!E:E,MATCH($C13,'Policy Characteristics'!$C:$C,0))) -> trans reduce regulated pollutants | L13: =IF(ISBLANK(INDEX('Policy Characteristics'!F:F,MATCH($C13,'Policy Characteristics'!$C:$C,0))),"",INDEX('Policy Characteristics'!F:F,MATCH($C13,'Policy Characteristics'!$C:$C,0))) -> 0 | M13: =IF(ISBLANK(INDEX('Policy Characteristics'!G:G,MATCH($C13,'Policy Characteristics'!$C:$C,0))),"",INDEX('Policy Characteristics'!G:G,MATCH($C13,'Policy Characteristics'!$C:$C,0))) -> 1 | N13: =IF(ISBLANK(INDEX('Policy Characteristics'!H:H,MATCH($C13,'Policy Characteristics'!$C:$C,0))),"",INDEX('Policy Characteristics'!H:H,MATCH($C13,'Policy Characteristics'!$C:$C,0))) -> 0.02 | O13: =IF(ISBLANK(INDEX('Policy Characteristics'!I:I,MATCH($C13,'Policy Characteristics'!$C:$C,0))),"",INDEX('Policy Characteristics'!I:I,MATCH($C13,'Policy Characteristics'!$C:$C,0))) -> % reduction in emissions | P13: =IF(ISBLANK(INDEX('Policy Characteristics'!J:J,MATCH($C13,'Policy Characteristics'!$C:$C,0))),"",INDEX('Policy Characteristics'!J:J,MATCH($C13,'Policy Characteristics'!$C:$C,0))) -> **Description:** This policy represents strengthening standards for the selected pollutant(s) emitted by the selected vehicle type(s). Conventional pollutants' most important, harmful impacts are on human health rather than on climate change. // **Guidance for setting values:** In South Korea, the 24-hour national ambient air quality standard (NAAQS) for PM2.5, the most harmful type of particulate for human health, is 35 µg/m^3. For example, setting this policy lever to 5% means that the emission intensity for the selected pollutant(s) will be reduced by 5% relative to the current level, reflecting tighter tailpipe standards or enhanced inspection and maintenance programs. This level can be interpreted as a modest but meaningful tightening of emission control requirements. | Q13: =IF(ISBLANK(INDEX('Policy Characteristics'!K:K,MATCH($C13,'Policy Characteristics'!$C:$C,0))),"",INDEX('Policy Characteristics'!K:K,MATCH($C13,'Policy Characteristics'!$C:$C,0))) -> transportation-sector-main.html#conv-pol-stds | R13: =IF(ISBLANK(INDEX('Policy Characteristics'!L:L,MATCH($C13,'Policy Characteristics'!$C:$C,0))),"",INDEX('Policy Characteristics'!L:L,MATCH($C13,'Policy Characteristics'!$C:$C,0))) -> conventional-pollutant-standards.html
A14: =IF(ISBLANK(INDEX('Policy Characteristics'!A:A,MATCH($C14,'Policy Characteristics'!$C:$C,0))),"",INDEX('Policy Characteristics'!A:A,MATCH($C14,'Policy Characteristics'!$C:$C,0))) -> Transportation | B14: =IF(ISBLANK(INDEX('Policy Characteristics'!B:B,MATCH($C14,'Policy Characteristics'!$C:$C,0))),"",INDEX('Policy Characteristics'!B:B,MATCH($C14,'Policy Characteristics'!$C:$C,0))) -> Conventional Pollutant Standards | C14: =C$2 -> Percentage Reduction of Separately Regulated Pollutants | D14: HDVs | E14: NOx | F14: Buses and Heavy Duty Trucks | G14: NOx | H14: 312 | I14: Yes | J14: =IF(ISBLANK(INDEX('Policy Characteristics'!D:D,MATCH($C14,'Policy Characteristics'!$C:$C,0))),"",INDEX('Policy Characteristics'!D:D,MATCH($C14,'Policy Characteristics'!$C:$C,0))) -> Conventional Pollutant Standard | K14: =IF(ISBLANK(INDEX('Policy Characteristics'!E:E,MATCH($C14,'Policy Characteristics'!$C:$C,0))),"",INDEX('Policy Characteristics'!E:E,MATCH($C14,'Policy Characteristics'!$C:$C,0))) -> trans reduce regulated pollutants | L14: =IF(ISBLANK(INDEX('Policy Characteristics'!F:F,MATCH($C14,'Policy Characteristics'!$C:$C,0))),"",INDEX('Policy Characteristics'!F:F,MATCH($C14,'Policy Characteristics'!$C:$C,0))) -> 0 | M14: =IF(ISBLANK(INDEX('Policy Characteristics'!G:G,MATCH($C14,'Policy Characteristics'!$C:$C,0))),"",INDEX('Policy Characteristics'!G:G,MATCH($C14,'Policy Characteristics'!$C:$C,0))) -> 1 | N14: =IF(ISBLANK(INDEX('Policy Characteristics'!H:H,MATCH($C14,'Policy Characteristics'!$C:$C,0))),"",INDEX('Policy Characteristics'!H:H,MATCH($C14,'Policy Characteristics'!$C:$C,0))) -> 0.02 | O14: =IF(ISBLANK(INDEX('Policy Characteristics'!I:I,MATCH($C14,'Policy Characteristics'!$C:$C,0))),"",INDEX('Policy Characteristics'!I:I,MATCH($C14,'Policy Characteristics'!$C:$C,0))) -> % reduction in emissions | P14: =IF(ISBLANK(INDEX('Policy Characteristics'!J:J,MATCH($C14,'Policy Characteristics'!$C:$C,0))),"",INDEX('Policy Characteristics'!J:J,MATCH($C14,'Policy Characteristics'!$C:$C,0))) -> **Description:** This policy represents strengthening standards for the selected pollutant(s) emitted by the selected vehicle type(s). Conventional pollutants' most important, harmful impacts are on human health rather than on climate change. // **Guidance for setting values:** In South Korea, the 24-hour national ambient air quality standard (NAAQS) for PM2.5, the most harmful type of particulate for human health, is 35 µg/m^3. For example, setting this policy lever to 5% means that the emission intensity for the selected pollutant(s) will be reduced by 5% relative to the current level, reflecting tighter tailpipe standards or enhanced inspection and maintenance programs. This level can be interpreted as a modest but meaningful tightening of emission control requirements. | Q14: =IF(ISBLANK(INDEX('Policy Characteristics'!K:K,MATCH($C14,'Policy Characteristics'!$C:$C,0))),"",INDEX('Policy Characteristics'!K:K,MATCH($C14,'Policy Characteristics'!$C:$C,0))) -> transportation-sector-main.html#conv-pol-stds | R14: =IF(ISBLANK(INDEX('Policy Characteristics'!L:L,MATCH($C14,'Policy Characteristics'!$C:$C,0))),"",INDEX('Policy Characteristics'!L:L,MATCH($C14,'Policy Characteristics'!$C:$C,0))) -> conventional-pollutant-standards.html
... A61: =IF(ISBLANK(INDEX('Policy Characteristics'!A:A,MATCH($C61,'Policy Characteristics'!$C:$C,0))),"",INDEX('Policy Characteristics'!A:A,MATCH($C61,'Policy Characteristics'!$C:$C,0))) -> Transportation | B61: =IF(ISBLANK(INDEX('Policy Characteristics'!B:B,MATCH($C61,'Policy Characteristics'!$C:$C,0))),"",INDEX('Policy Characteristics'!B:B,MATCH($C61,'Policy Characteristics'!$C:$C,0))) -> Conventional Pollutant Standards | C61: =C$2 -> Percentage Reduction of Separately Regulated Pollutants | D61: motorbikes | E61: N2O | F61: Passenger motorbikes | G61: N2O | H61: 359 | I61: No | J61: =IF(ISBLANK(INDEX('Policy Characteristics'!D:D,MATCH($C61,'Policy Characteristics'!$C:$C,0))),"",INDEX('Policy Characteristics'!D:D,MATCH($C61,'Policy Characteristics'!$C:$C,0))) -> Conventional Pollutant Standard | K61: =IF(ISBLANK(INDEX('Policy Characteristics'!E:E,MATCH($C61,'Policy Characteristics'!$C:$C,0))),"",INDEX('Policy Characteristics'!E:E,MATCH($C61,'Policy Characteristics'!$C:$C,0))) -> trans reduce regulated pollutants | L61: =IF(ISBLANK(INDEX('Policy Characteristics'!F:F,MATCH($C61,'Policy Characteristics'!$C:$C,0))),"",INDEX('Policy Characteristics'!F:F,MATCH($C61,'Policy Characteristics'!$C:$C,0))) -> 0 | M61: =IF(ISBLANK(INDEX('Policy Characteristics'!G:G,MATCH($C61,'Policy Characteristics'!$C:$C,0))),"",INDEX('Policy Characteristics'!G:G,MATCH($C61,'Policy Characteristics'!$C:$C,0))) -> 1 | N61: =IF(ISBLANK(INDEX('Policy Characteristics'!H:H,MATCH($C61,'Policy Characteristics'!$C:$C,0))),"",INDEX('Policy Characteristics'!H:H,MATCH($C61,'Policy Characteristics'!$C:$C,0))) -> 0.02 | O61: =IF(ISBLANK(INDEX('Policy Characteristics'!I:I,MATCH($C61,'Policy Characteristics'!$C:$C,0))),"",INDEX('Policy Characteristics'!I:I,MATCH($C61,'Policy Characteristics'!$C:$C,0))) -> % reduction in emissions | P61: =IF(ISBLANK(INDEX('Policy Characteristics'!J:J,MATCH($C61,'Policy Characteristics'!$C:$C,0))),"",INDEX('Policy Characteristics'!J:J,MATCH($C61,'Policy Characteristics'!$C:$C,0))) -> **Description:** This policy represents strengthening standards for the selected pollutant(s) emitted by the selected vehicle type(s). Conventional pollutants' most important, harmful impacts are on human health rather than on climate change. // **Guidance for setting values:** In South Korea, the 24-hour national ambient air quality standard (NAAQS) for PM2.5, the most harmful type of particulate for human health, is 35 µg/m^3. For example, setting this policy lever to 5% means that the emission intensity for the selected pollutant(s) will be reduced by 5% relative to the current level, reflecting tighter tailpipe standards or enhanced inspection and maintenance programs. This level can be interpreted as a modest but meaningful tightening of emission control requirements. | Q61: =IF(ISBLANK(INDEX('Policy Characteristics'!K:K,MATCH($C61,'Policy Characteristics'!$C:$C,0))),"",INDEX('Policy Characteristics'!K:K,MATCH($C61,'Policy Characteristics'!$C:$C,0))) -> transportation-sector-main.html#conv-pol-stds | R61: =IF(ISBLANK(INDEX('Policy Characteristics'!L:L,MATCH($C61,'Policy Characteristics'!$C:$C,0))),"",INDEX('Policy Characteristics'!L:L,MATCH($C61,'Policy Characteristics'!$C:$C,0))) -> conventional-pollutant-standards.html
A62: =IF(ISBLANK(INDEX('Policy Characteristics'!A:A,MATCH($C62,'Policy Characteristics'!$C:$C,0))),"",INDEX('Policy Characteristics'!A:A,MATCH($C62,'Policy Characteristics'!$C:$C,0))) -> Transportation | B62: =IF(ISBLANK(INDEX('Policy Characteristics'!B:B,MATCH($C62,'Policy Characteristics'!$C:$C,0))),"",INDEX('Policy Characteristics'!B:B,MATCH($C62,'Policy Characteristics'!$C:$C,0))) -> Electric Vehicle Charger Deployment | C62: Percentage Increase in EV Chargers | H62: 360 | I62: Yes | J62: =IF(ISBLANK(INDEX('Policy Characteristics'!D:D,MATCH($C62,'Policy Characteristics'!$C:$C,0))),"",INDEX('Policy Characteristics'!D:D,MATCH($C62,'Policy Characteristics'!$C:$C,0))) -> EV Charger Deployment | K62: =IF(ISBLANK(INDEX('Policy Characteristics'!E:E,MATCH($C62,'Policy Characteristics'!$C:$C,0))),"",INDEX('Policy Characteristics'!E:E,MATCH($C62,'Policy Characteristics'!$C:$C,0))) -> trans EV charger deployment | L62: =IF(ISBLANK(INDEX('Policy Characteristics'!F:F,MATCH($C62,'Policy Characteristics'!$C:$C,0))),"",INDEX('Policy Characteristics'!F:F,MATCH($C62,'Policy Characteristics'!$C:$C,0))) -> -1 | M62: =IF(ISBLANK(INDEX('Policy Characteristics'!G:G,MATCH($C62,'Policy Characteristics'!$C:$C,0))),"",INDEX('Policy Characteristics'!G:G,MATCH($C62,'Policy Characteristics'!$C:$C,0))) -> 3 | N62: =IF(ISBLANK(INDEX('Policy Characteristics'!H:H,MATCH($C62,'Policy Characteristics'!$C:$C,0))),"",INDEX('Policy Characteristics'!H:H,MATCH($C62,'Policy Characteristics'!$C:$C,0))) -> 0.1 | O62: =IF(ISBLANK(INDEX('Policy Characteristics'!I:I,MATCH($C62,'Policy Characteristics'!$C:$C,0))),"",INDEX('Policy Characteristics'!I:I,MATCH($C62,'Policy Characteristics'!$C:$C,0))) -> % change | P62: =IF(ISBLANK(INDEX('Policy Characteristics'!J:J,MATCH($C62,'Policy Characteristics'!$C:$C,0))),"",INDEX('Policy Characteristics'!J:J,MATCH($C62,'Policy Characteristics'!$C:$C,0))) -> **Description:** This policy represents EV chargers deployed in addition to the Business-As-Usual (BAU) scenario, including DC fast chargers and Level 2 chargers. The lever is expressed as a percentage change from the BAU deployment level, applied to the cumulative charger stock rather than annual installations. This policy instrument does not directly affect energy use, emissions, or vehicle deployment. Its primary purpose is to account for the additional infrastructure costs associated with expanded charging networks.//**Guidance for setting values:** Considering the growth rate of EV charger deployment between 2020 and 2024, the BAU scenario assumes approximately 930,000 chargers by 2030. A setting of 300% means that chargers equal to three times the BAU quantity are added, resulting in a total stock equal to four times the BAU level. As of December 2021, South Korea had a total of 94,041 EV chargers, which corresponds to approximately 181 chargers per 100,000 people. For comparison, as of December 2020, there were 12,635 domestic gas stations, each with an average of 14 fueling pumps, corresponding to approximately 342 fueling pumps per 100,000 people. The South Korean government has set a target of 1.23 million EV chargers by 2030. | Q62: =IF(ISBLANK(INDEX('Policy Characteristics'!K:K,MATCH($C62,'Policy Characteristics'!$C:$C,0))),"",INDEX('Policy Characteristics'!K:K,MATCH($C62,'Policy Characteristics'!$C:$C,0))) | R62: =IF(ISBLANK(INDEX('Policy Characteristics'!L:L,MATCH($C62,'Policy Characteristics'!$C:$C,0))),"",INDEX('Policy Characteristics'!L:L,MATCH($C62,'Policy Characteristics'!$C:$C,0))) -> ev-charger-deployment.html
A63: =IF(ISBLANK(INDEX('Policy Characteristics'!A:A,MATCH($C63,'Policy Characteristics'!$C:$C,0))),"",INDEX('Policy Characteristics'!A:A,MATCH($C63,'Policy Characteristics'!$C:$C,0))) -> Transportation | B63: =IF(ISBLANK(INDEX('Policy Characteristics'!B:B,MATCH($C63,'Policy Characteristics'!$C:$C,0))),"",INDEX('Policy Characteristics'!B:B,MATCH($C63,'Policy Characteristics'!$C:$C,0))) -> Passenger Vehicle Subsidy | C63: Additional Passenger Vehicle Subsidy | D63: LDVs | E63: battery electric vehicle | F63: Cars and SUVs | G63: Battery electric vehicle | H63: 189 | I63: Yes | J63: =IF(ISBLANK(INDEX('Policy Characteristics'!D:D,MATCH($C63,'Policy Characteristics'!$C:$C,0))),"",INDEX('Policy Characteristics'!D:D,MATCH($C63,'Policy Characteristics'!$C:$C,0))) -> Vehicle Subsidy | K63: =IF(ISBLANK(INDEX('Policy Characteristics'!E:E,MATCH($C63,'Policy Characteristics'!$C:$C,0))),"",INDEX('Policy Characteristics'!E:E,MATCH($C63,'Policy Characteristics'!$C:$C,0))) -> trans psgr subsidy | L63: =IF(ISBLANK(INDEX('Policy Characteristics'!F:F,MATCH($C63,'Policy Characteristics'!$C:$C,0))),"",INDEX('Policy Characteristics'!F:F,MATCH($C63,'Policy Characteristics'!$C:$C,0))) -> -60000 | M63: =IF(ISBLANK(INDEX('Policy Characteristics'!G:G,MATCH($C63,'Policy Characteristics'!$C:$C,0))),"",INDEX('Policy Characteristics'!G:G,MATCH($C63,'Policy Characteristics'!$C:$C,0))) -> 60000 | N63: =IF(ISBLANK(INDEX('Policy Characteristics'!H:H,MATCH($C63,'Policy Characteristics'!$C:$C,0))),"",INDEX('Policy Characteristics'!H:H,MATCH($C63,'Policy Characteristics'!$C:$C,0))) -> 1000 | O63: =IF(ISBLANK(INDEX('Policy Characteristics'!I:I,MATCH($C63,'Policy Characteristics'!$C:$C,0))),"",INDEX('Policy Characteristics'!I:I,MATCH($C63,'Policy Characteristics'!$C:$C,0))) -> thousand KRW/vehicle | P63: =IF(ISBLANK(INDEX('Policy Characteristics'!J:J,MATCH($C63,'Policy Characteristics'!$C:$C,0))),"",INDEX('Policy Characteristics'!J:J,MATCH($C63,'Policy Characteristics'!$C:$C,0))) -> **Description:** This policy specifies the subsidy amount offered to purchasers of new passenger vehicle. This is in addition to subsidies that exist in the BAU case. A negative value implies a tax or removal of subsidies. // **Guidance for setting values:** As of 2025, South Korea provides substantial purchase subsidies for zero-emission vehicles. For battery electric vehicles (BEVs), the maximum combined national and local subsidy is KRW 6.4 million. For hydrogen fuel cell vehicles (FCEVs), the maximum subsidy reaches KRW 29.5 million. For heavy-duty vehicles, the support is even more significant: large battery-electric HDVs receive up to KRW 198.12 million (combined national and Seoul municipal subsidies), while hydrogen-powered buses and large vans can receive up to KRW 350 million. These subsidy levels can be used as reference points when setting the policy lever values. | Q63: =IF(ISBLANK(INDEX('Policy Characteristics'!K:K,MATCH($C63,'Policy Characteristics'!$C:$C,0))),"",INDEX('Policy Characteristics'!K:K,MATCH($C63,'Policy Characteristics'!$C:$C,0))) -> transportation-sector-main.html#ev-subsidy | R63: =IF(ISBLANK(INDEX('Policy Characteristics'!L:L,MATCH($C63,'Policy Characteristics'!$C:$C,0))),"",INDEX('Policy Characteristics'!L:L,MATCH($C63,'Policy Characteristics'!$C:$C,0))) -> ev-subsidy.html
A64: =IF(ISBLANK(INDEX('Policy Characteristics'!A:A,MATCH($C64,'Policy Characteristics'!$C:$C,0))),"",INDEX('Policy Characteristics'!A:A,MATCH($C64,'Policy Characteristics'!$C:$C,0))) -> Transportation | B64: =IF(ISBLANK(INDEX('Policy Characteristics'!B:B,MATCH($C64,'Policy Characteristics'!$C:$C,0))),"",INDEX('Policy Characteristics'!B:B,MATCH($C64,'Policy Characteristics'!$C:$C,0))) -> Passenger Vehicle Subsidy | C64: =C$63 -> Additional Passenger Vehicle Subsidy | D64: LDVs | E64: natural gas vehicle | F64: Cars and SUVs | G64: Natural gas vehicle | H64: 592 | I64: No | J64: =IF(ISBLANK(INDEX('Policy Characteristics'!D:D,MATCH($C64,'Policy Characteristics'!$C:$C,0))),"",INDEX('Policy Characteristics'!D:D,MATCH($C64,'Policy Characteristics'!$C:$C,0))) -> Vehicle Subsidy | K64: =IF(ISBLANK(INDEX('Policy Characteristics'!E:E,MATCH($C64,'Policy Characteristics'!$C:$C,0))),"",INDEX('Policy Characteristics'!E:E,MATCH($C64,'Policy Characteristics'!$C:$C,0))) -> trans psgr subsidy | L64: =IF(ISBLANK(INDEX('Policy Characteristics'!F:F,MATCH($C64,'Policy Characteristics'!$C:$C,0))),"",INDEX('Policy Characteristics'!F:F,MATCH($C64,'Policy Characteristics'!$C:$C,0))) -> -60000 | M64: =IF(ISBLANK(INDEX('Policy Characteristics'!G:G,MATCH($C64,'Policy Characteristics'!$C:$C,0))),"",INDEX('Policy Characteristics'!G:G,MATCH($C64,'Policy Characteristics'!$C:$C,0))) -> 60000 | N64: =IF(ISBLANK(INDEX('Policy Characteristics'!H:H,MATCH($C64,'Policy Characteristics'!$C:$C,0))),"",INDEX('Policy Characteristics'!H:H,MATCH($C64,'Policy Characteristics'!$C:$C,0))) -> 1000 | O64: =IF(ISBLANK(INDEX('Policy Characteristics'!I:I,MATCH($C64,'Policy Characteristics'!$C:$C,0))),"",INDEX('Policy Characteristics'!I:I,MATCH($C64,'Policy Characteristics'!$C:$C,0))) -> thousand KRW/vehicle | P64: =IF(ISBLANK(INDEX('Policy Characteristics'!J:J,MATCH($C64,'Policy Characteristics'!$C:$C,0))),"",INDEX('Policy Characteristics'!J:J,MATCH($C64,'Policy Characteristics'!$C:$C,0))) -> **Description:** This policy specifies the subsidy amount offered to purchasers of new passenger vehicle. This is in addition to subsidies that exist in the BAU case. A negative value implies a tax or removal of subsidies. // **Guidance for setting values:** As of 2025, South Korea provides substantial purchase subsidies for zero-emission vehicles. For battery electric vehicles (BEVs), the maximum combined national and local subsidy is KRW 6.4 million. For hydrogen fuel cell vehicles (FCEVs), the maximum subsidy reaches KRW 29.5 million. For heavy-duty vehicles, the support is even more significant: large battery-electric HDVs receive up to KRW 198.12 million (combined national and Seoul municipal subsidies), while hydrogen-powered buses and large vans can receive up to KRW 350 million. These subsidy levels can be used as reference points when setting the policy lever values. | Q64: =IF(ISBLANK(INDEX('Policy Characteristics'!K:K,MATCH($C64,'Policy Characteristics'!$C:$C,0))),"",INDEX('Policy Characteristics'!K:K,MATCH($C64,'Policy Characteristics'!$C:$C,0))) -> transportation-sector-main.html#ev-subsidy | R64: =IF(ISBLANK(INDEX('Policy Characteristics'!L:L,MATCH($C64,'Policy Characteristics'!$C:$C,0))),"",INDEX('Policy Characteristics'!L:L,MATCH($C64,'Policy Characteristics'!$C:$C,0))) -> ev-subsidy.html
A65: =IF(ISBLANK(INDEX('Policy Characteristics'!A:A,MATCH($C65,'Policy Characteristics'!$C:$C,0))),"",INDEX('Policy Characteristics'!A:A,MATCH($C65,'Policy Characteristics'!$C:$C,0))) -> Transportation | B65: =IF(ISBLANK(INDEX('Policy Characteristics'!B:B,MATCH($C65,'Policy Characteristics'!$C:$C,0))),"",INDEX('Policy Characteristics'!B:B,MATCH($C65,'Policy Characteristics'!$C:$C,0))) -> Passenger Vehicle Subsidy | C65: =C$63 -> Additional Passenger Vehicle Subsidy | D65: LDVs | E65: gasoline vehicle | F65: Cars and SUVs | G65: Gasoline vehicle | H65: 593 | I65: No | J65: =IF(ISBLANK(INDEX('Policy Characteristics'!D:D,MATCH($C65,'Policy Characteristics'!$C:$C,0))),"",INDEX('Policy Characteristics'!D:D,MATCH($C65,'Policy Characteristics'!$C:$C,0))) -> Vehicle Subsidy | K65: =IF(ISBLANK(INDEX('Policy Characteristics'!E:E,MATCH($C65,'Policy Characteristics'!$C:$C,0))),"",INDEX('Policy Characteristics'!E:E,MATCH($C65,'Policy Characteristics'!$C:$C,0))) -> trans psgr subsidy | L65: =IF(ISBLANK(INDEX('Policy Characteristics'!F:F,MATCH($C65,'Policy Characteristics'!$C:$C,0))),"",INDEX('Policy Characteristics'!F:F,MATCH($C65,'Policy Characteristics'!$C:$C,0))) -> -60000 | M65: =IF(ISBLANK(INDEX('Policy Characteristics'!G:G,MATCH($C65,'Policy Characteristics'!$C:$C,0))),"",INDEX('Policy Characteristics'!G:G,MATCH($C65,'Policy Characteristics'!$C:$C,0))) -> 60000 | N65: =IF(ISBLANK(INDEX('Policy Characteristics'!H:H,MATCH($C65,'Policy Characteristics'!$C:$C,0))),"",INDEX('Policy Characteristics'!H:H,MATCH($C65,'Policy Characteristics'!$C:$C,0))) -> 1000 | O65: =IF(ISBLANK(INDEX('Policy Characteristics'!I:I,MATCH($C65,'Policy Characteristics'!$C:$C,0))),"",INDEX('Policy Characteristics'!I:I,MATCH($C65,'Policy Characteristics'!$C:$C,0))) -> thousand KRW/vehicle | P65: =IF(ISBLANK(INDEX('Policy Characteristics'!J:J,MATCH($C65,'Policy Characteristics'!$C:$C,0))),"",INDEX('Policy Characteristics'!J:J,MATCH($C65,'Policy Characteristics'!$C:$C,0))) -> **Description:** This policy specifies the subsidy amount offered to purchasers of new passenger vehicle. This is in addition to subsidies that exist in the BAU case. A negative value implies a tax or removal of subsidies. // **Guidance for setting values:** As of 2025, South Korea provides substantial purchase subsidies for zero-emission vehicles. For battery electric vehicles (BEVs), the maximum combined national and local subsidy is KRW 6.4 million. For hydrogen fuel cell vehicles (FCEVs), the maximum subsidy reaches KRW 29.5 million. For heavy-duty vehicles, the support is even more significant: large battery-electric HDVs receive up to KRW 198.12 million (combined national and Seoul municipal subsidies), while hydrogen-powered buses and large vans can receive up to KRW 350 million. These subsidy levels can be used as reference points when setting the policy lever values. | Q65: =IF(ISBLANK(INDEX('Policy Characteristics'!K:K,MATCH($C65,'Policy Characteristics'!$C:$C,0))),"",INDEX('Policy Characteristics'!K:K,MATCH($C65,'Policy Characteristics'!$C:$C,0))) -> transportation-sector-main.html#ev-subsidy | R65: =IF(ISBLANK(INDEX('Policy Characteristics'!L:L,MATCH($C65,'Policy Characteristics'!$C:$C,0))),"",INDEX('Policy Characteristics'!L:L,MATCH($C65,'Policy Characteristics'!$C:$C,0))) -> ev-subsidy.html
A66: =IF(ISBLANK(INDEX('Policy Characteristics'!A:A,MATCH($C66,'Policy Characteristics'!$C:$C,0))),"",INDEX('Policy Characteristics'!A:A,MATCH($C66,'Policy Characteristics'!$C:$C,0))) -> Transportation | B66: =IF(ISBLANK(INDEX('Policy Characteristics'!B:B,MATCH($C66,'Policy Characteristics'!$C:$C,0))),"",INDEX('Policy Characteristics'!B:B,MATCH($C66,'Policy Characteristics'!$C:$C,0))) -> Passenger Vehicle Subsidy | C66: =C$63 -> Additional Passenger Vehicle Subsidy | D66: LDVs | E66: diesel vehicle | F66: Cars and SUVs | G66: Diesel vehicle | H66: 594 | I66: No | J66: =IF(ISBLANK(INDEX('Policy Characteristics'!D:D,MATCH($C66,'Policy Characteristics'!$C:$C,0))),"",INDEX('Policy Characteristics'!D:D,MATCH($C66,'Policy Characteristics'!$C:$C,0))) -> Vehicle Subsidy | K66: =IF(ISBLANK(INDEX('Policy Characteristics'!E:E,MATCH($C66,'Policy Characteristics'!$C:$C,0))),"",INDEX('Policy Characteristics'!E:E,MATCH($C66,'Policy Characteristics'!$C:$C,0))) -> trans psgr subsidy | L66: =IF(ISBLANK(INDEX('Policy Characteristics'!F:F,MATCH($C66,'Policy Characteristics'!$C:$C,0))),"",INDEX('Policy Characteristics'!F:F,MATCH($C66,'Policy Characteristics'!$C:$C,0))) -> -60000 | M66: =IF(ISBLANK(INDEX('Policy Characteristics'!G:G,MATCH($C66,'Policy Characteristics'!$C:$C,0))),"",INDEX('Policy Characteristics'!G:G,MATCH($C66,'Policy Characteristics'!$C:$C,0))) -> 60000 | N66: =IF(ISBLANK(INDEX('Policy Characteristics'!H:H,MATCH($C66,'Policy Characteristics'!$C:$C,0))),"",INDEX('Policy Characteristics'!H:H,MATCH($C66,'Policy Characteristics'!$C:$C,0))) -> 1000 | O66: =IF(ISBLANK(INDEX('Policy Characteristics'!I:I,MATCH($C66,'Policy Characteristics'!$C:$C,0))),"",INDEX('Policy Characteristics'!I:I,MATCH($C66,'Policy Characteristics'!$C:$C,0))) -> thousand KRW/vehicle | P66: =IF(ISBLANK(INDEX('Policy Characteristics'!J:J,MATCH($C66,'Policy Characteristics'!$C:$C,0))),"",INDEX('Policy Characteristics'!J:J,MATCH($C66,'Policy Characteristics'!$C:$C,0))) -> **Description:** This policy specifies the subsidy amount offered to purchasers of new passenger vehicle. This is in addition to subsidies that exist in the BAU case. A negative value implies a tax or removal of subsidies. // **Guidance for setting values:** As of 2025, South Korea provides substantial purchase subsidies for zero-emission vehicles. For battery electric vehicles (BEVs), the maximum combined national and local subsidy is KRW 6.4 million. For hydrogen fuel cell vehicles (FCEVs), the maximum subsidy reaches KRW 29.5 million. For heavy-duty vehicles, the support is even more significant: large battery-electric HDVs receive up to KRW 198.12 million (combined national and Seoul municipal subsidies), while hydrogen-powered buses and large vans can receive up to KRW 350 million. These subsidy levels can be used as reference points when setting the policy lever values. | Q66: =IF(ISBLANK(INDEX('Policy Characteristics'!K:K,MATCH($C66,'Policy Characteristics'!$C:$C,0))),"",INDEX('Policy Characteristics'!K:K,MATCH($C66,'Policy Characteristics'!$C:$C,0))) -> transportation-sector-main.html#ev-subsidy | R66: =IF(ISBLANK(INDEX('Policy Characteristics'!L:L,MATCH($C66,'Policy Characteristics'!$C:$C,0))),"",INDEX('Policy Characteristics'!L:L,MATCH($C66,'Policy Characteristics'!$C:$C,0))) -> ev-subsidy.html
A67: =IF(ISBLANK(INDEX('Policy Characteristics'!A:A,MATCH($C67,'Policy Characteristics'!$C:$C,0))),"",INDEX('Policy Characteristics'!A:A,MATCH($C67,'Policy Characteristics'!$C:$C,0))) -> Transportation | B67: =IF(ISBLANK(INDEX('Policy Characteristics'!B:B,MATCH($C67,'Policy Characteristics'!$C:$C,0))),"",INDEX('Policy Characteristics'!B:B,MATCH($C67,'Policy Characteristics'!$C:$C,0))) -> Passenger Vehicle Subsidy | C67: =C$63 -> Additional Passenger Vehicle Subsidy | D67: LDVs | E67: plugin hybrid vehicle | F67: Cars and SUVs | G67: Plugin hybrid vehicle | H67: 595 | I67: Yes | J67: =IF(ISBLANK(INDEX('Policy Characteristics'!D:D,MATCH($C67,'Policy Characteristics'!$C:$C,0))),"",INDEX('Policy Characteristics'!D:D,MATCH($C67,'Policy Characteristics'!$C:$C,0))) -> Vehicle Subsidy | K67: =IF(ISBLANK(INDEX('Policy Characteristics'!E:E,MATCH($C67,'Policy Characteristics'!$C:$C,0))),"",INDEX('Policy Characteristics'!E:E,MATCH($C67,'Policy Characteristics'!$C:$C,0))) -> trans psgr subsidy | L67: =IF(ISBLANK(INDEX('Policy Characteristics'!F:F,MATCH($C67,'Policy Characteristics'!$C:$C,0))),"",INDEX('Policy Characteristics'!F:F,MATCH($C67,'Policy Characteristics'!$C:$C,0))) -> -60000 | M67: =IF(ISBLANK(INDEX('Policy Characteristics'!G:G,MATCH($C67,'Policy Characteristics'!$C:$C,0))),"",INDEX('Policy Characteristics'!G:G,MATCH($C67,'Policy Characteristics'!$C:$C,0))) -> 60000 | N67: =IF(ISBLANK(INDEX('Policy Characteristics'!H:H,MATCH($C67,'Policy Characteristics'!$C:$C,0))),"",INDEX('Policy Characteristics'!H:H,MATCH($C67,'Policy Characteristics'!$C:$C,0))) -> 1000 | O67: =IF(ISBLANK(INDEX('Policy Characteristics'!I:I,MATCH($C67,'Policy Characteristics'!$C:$C,0))),"",INDEX('Policy Characteristics'!I:I,MATCH($C67,'Policy Characteristics'!$C:$C,0))) -> thousand KRW/vehicle | P67: =IF(ISBLANK(INDEX('Policy Characteristics'!J:J,MATCH($C67,'Policy Characteristics'!$C:$C,0))),"",INDEX('Policy Characteristics'!J:J,MATCH($C67,'Policy Characteristics'!$C:$C,0))) -> **Description:** This policy specifies the subsidy amount offered to purchasers of new passenger vehicle. This is in addition to subsidies that exist in the BAU case. A negative value implies a tax or removal of subsidies. // **Guidance for setting values:** As of 2025, South Korea provides substantial purchase subsidies for zero-emission vehicles. For battery electric vehicles (BEVs), the maximum combined national and local subsidy is KRW 6.4 million. For hydrogen fuel cell vehicles (FCEVs), the maximum subsidy reaches KRW 29.5 million. For heavy-duty vehicles, the support is even more significant: large battery-electric HDVs receive up to KRW 198.12 million (combined national and Seoul municipal subsidies), while hydrogen-powered buses and large vans can receive up to KRW 350 million. These subsidy levels can be used as reference points when setting the policy lever values. | Q67: =IF(ISBLANK(INDEX('Policy Characteristics'!K:K,MATCH($C67,'Policy Characteristics'!$C:$C,0))),"",INDEX('Policy Characteristics'!K:K,MATCH($C67,'Policy Characteristics'!$C:$C,0))) -> transportation-sector-main.html#ev-subsidy | R67: =IF(ISBLANK(INDEX('Policy Characteristics'!L:L,MATCH($C67,'Policy Characteristics'!$C:$C,0))),"",INDEX('Policy Characteristics'!L:L,MATCH($C67,'Policy Characteristics'!$C:$C,0))) -> ev-subsidy.html
A68: =IF(ISBLANK(INDEX('Policy Characteristics'!A:A,MATCH($C68,'Policy Characteristics'!$C:$C,0))),"",INDEX('Policy Characteristics'!A:A,MATCH($C68,'Policy Characteristics'!$C:$C,0))) -> Transportation | B68: =IF(ISBLANK(INDEX('Policy Characteristics'!B:B,MATCH($C68,'Policy Characteristics'!$C:$C,0))),"",INDEX('Policy Characteristics'!B:B,MATCH($C68,'Policy Characteristics'!$C:$C,0))) -> Passenger Vehicle Subsidy | C68: =C$63 -> Additional Passenger Vehicle Subsidy | D68: LDVs | E68: LPG vehicle | F68: Cars and SUVs | G68: LPG vehicle | H68: 596 | I68: No | J68: =IF(ISBLANK(INDEX('Policy Characteristics'!D:D,MATCH($C68,'Policy Characteristics'!$C:$C,0))),"",INDEX('Policy Characteristics'!D:D,MATCH($C68,'Policy Characteristics'!$C:$C,0))) -> Vehicle Subsidy | K68: =IF(ISBLANK(INDEX('Policy Characteristics'!E:E,MATCH($C68,'Policy Characteristics'!$C:$C,0))),"",INDEX('Policy Characteristics'!E:E,MATCH($C68,'Policy Characteristics'!$C:$C,0))) -> trans psgr subsidy | L68: =IF(ISBLANK(INDEX('Policy Characteristics'!F:F,MATCH($C68,'Policy Characteristics'!$C:$C,0))),"",INDEX('Policy Characteristics'!F:F,MATCH($C68,'Policy Characteristics'!$C:$C,0))) -> -60000 | M68: =IF(ISBLANK(INDEX('Policy Characteristics'!G:G,MATCH($C68,'Policy Characteristics'!$C:$C,0))),"",INDEX('Policy Characteristics'!G:G,MATCH($C68,'Policy Characteristics'!$C:$C,0))) -> 60000 | N68: =IF(ISBLANK(INDEX('Policy Characteristics'!H:H,MATCH($C68,'Policy Characteristics'!$C:$C,0))),"",INDEX('Policy Characteristics'!H:H,MATCH($C68,'Policy Characteristics'!$C:$C,0))) -> 1000 | O68: =IF(ISBLANK(INDEX('Policy Characteristics'!I:I,MATCH($C68,'Policy Characteristics'!$C:$C,0))),"",INDEX('Policy Characteristics'!I:I,MATCH($C68,'Policy Characteristics'!$C:$C,0))) -> thousand KRW/vehicle | P68: =IF(ISBLANK(INDEX('Policy Characteristics'!J:J,MATCH($C68,'Policy Characteristics'!$C:$C,0))),"",INDEX('Policy Characteristics'!J:J,MATCH($C68,'Policy Characteristics'!$C:$C,0))) -> **Description:** This policy specifies the subsidy amount offered to purchasers of new passenger vehicle. This is in addition to subsidies that exist in the BAU case. A negative value implies a tax or removal of subsidies. // **Guidance for setting values:** As of 2025, South Korea provides substantial purchase subsidies for zero-emission vehicles. For battery electric vehicles (BEVs), the maximum combined national and local subsidy is KRW 6.4 million. For hydrogen fuel cell vehicles (FCEVs), the maximum subsidy reaches KRW 29.5 million. For heavy-duty vehicles, the support is even more significant: large battery-electric HDVs receive up to KRW 198.12 million (combined national and Seoul municipal subsidies), while hydrogen-powered buses and large vans can receive up to KRW 350 million. These subsidy levels can be used as reference points when setting the policy lever values. | Q68: =IF(ISBLANK(INDEX('Policy Characteristics'!K:K,MATCH($C68,'Policy Characteristics'!$C:$C,0))),"",INDEX('Policy Characteristics'!K:K,MATCH($C68,'Policy Characteristics'!$C:$C,0))) -> transportation-sector-main.html#ev-subsidy | R68: =IF(ISBLANK(INDEX('Policy Characteristics'!L:L,MATCH($C68,'Policy Characteristics'!$C:$C,0))),"",INDEX('Policy Characteristics'!L:L,MATCH($C68,'Policy Characteristics'!$C:$C,0))) -> ev-subsidy.html
A69: =IF(ISBLANK(INDEX('Policy Characteristics'!A:A,MATCH($C69,'Policy Characteristics'!$C:$C,0))),"",INDEX('Policy Characteristics'!A:A,MATCH($C69,'Policy Characteristics'!$C:$C,0))) -> Transportation | B69: =IF(ISBLANK(INDEX('Policy Characteristics'!B:B,MATCH($C69,'Policy Characteristics'!$C:$C,0))),"",INDEX('Policy Characteristics'!B:B,MATCH($C69,'Policy Characteristics'!$C:$C,0))) -> Passenger Vehicle Subsidy | C69: =C$63 -> Additional Passenger Vehicle Subsidy | D69: LDVs | E69: hydrogen vehicle | F69: Cars and SUVs | G69: Hydrogen vehicle | H69: 597 | I69: Yes | J69: =IF(ISBLANK(INDEX('Policy Characteristics'!D:D,MATCH($C69,'Policy Characteristics'!$C:$C,0))),"",INDEX('Policy Characteristics'!D:D,MATCH($C69,'Policy Characteristics'!$C:$C,0))) -> Vehicle Subsidy | K69: =IF(ISBLANK(INDEX('Policy Characteristics'!E:E,MATCH($C69,'Policy Characteristics'!$C:$C,0))),"",INDEX('Policy Characteristics'!E:E,MATCH($C69,'Policy Characteristics'!$C:$C,0))) -> trans psgr subsidy | L69: =IF(ISBLANK(INDEX('Policy Characteristics'!F:F,MATCH($C69,'Policy Characteristics'!$C:$C,0))),"",INDEX('Policy Characteristics'!F:F,MATCH($C69,'Policy Characteristics'!$C:$C,0))) -> -60000 | M69: =IF(ISBLANK(INDEX('Policy Characteristics'!G:G,MATCH($C69,'Policy Characteristics'!$C:$C,0))),"",INDEX('Policy Characteristics'!G:G,MATCH($C69,'Policy Characteristics'!$C:$C,0))) -> 60000 | N69: =IF(ISBLANK(INDEX('Policy Characteristics'!H:H,MATCH($C69,'Policy Characteristics'!$C:$C,0))),"",INDEX('Policy Characteristics'!H:H,MATCH($C69,'Policy Characteristics'!$C:$C,0))) -> 1000 | O69: =IF(ISBLANK(INDEX('Policy Characteristics'!I:I,MATCH($C69,'Policy Characteristics'!$C:$C,0))),"",INDEX('Policy Characteristics'!I:I,MATCH($C69,'Policy Characteristics'!$C:$C,0))) -> thousand KRW/vehicle | P69: =IF(ISBLANK(INDEX('Policy Characteristics'!J:J,MATCH($C69,'Policy Characteristics'!$C:$C,0))),"",INDEX('Policy Characteristics'!J:J,MATCH($C69,'Policy Characteristics'!$C:$C,0))) -> **Description:** This policy specifies the subsidy amount offered to purchasers of new passenger vehicle. This is in addition to subsidies that exist in the BAU case. A negative value implies a tax or removal of subsidies. // **Guidance for setting values:** As of 2025, South Korea provides substantial purchase subsidies for zero-emission vehicles. For battery electric vehicles (BEVs), the maximum combined national and local subsidy is KRW 6.4 million. For hydrogen fuel cell vehicles (FCEVs), the maximum subsidy reaches KRW 29.5 million. For heavy-duty vehicles, the support is even more significant: large battery-electric HDVs receive up to KRW 198.12 million (combined national and Seoul municipal subsidies), while hydrogen-powered buses and large vans can receive up to KRW 350 million. These subsidy levels can be used as reference points when setting the policy lever values. | Q69: =IF(ISBLANK(INDEX('Policy Characteristics'!K:K,MATCH($C69,'Policy Characteristics'!$C:$C,0))),"",INDEX('Policy Characteristics'!K:K,MATCH($C69,'Policy Characteristics'!$C:$C,0))) -> transportation-sector-main.html#ev-subsidy | R69: =IF(ISBLANK(INDEX('Policy Characteristics'!L:L,MATCH($C69,'Policy Characteristics'!$C:$C,0))),"",INDEX('Policy Characteristics'!L:L,MATCH($C69,'Policy Characteristics'!$C:$C,0))) -> ev-subsidy.html
A70: =IF(ISBLANK(INDEX('Policy Characteristics'!A:A,MATCH($C70,'Policy Characteristics'!$C:$C,0))),"",INDEX('Policy Characteristics'!A:A,MATCH($C70,'Policy Characteristics'!$C:$C,0))) -> Transportation | B70: =IF(ISBLANK(INDEX('Policy Characteristics'!B:B,MATCH($C70,'Policy Characteristics'!$C:$C,0))),"",INDEX('Policy Characteristics'!B:B,MATCH($C70,'Policy Characteristics'!$C:$C,0))) -> Passenger Vehicle Subsidy | C70: =C$63 -> Additional Passenger Vehicle Subsidy | D70: HDVs | E70: battery electric vehicle | F70: Buses | G70: Battery electric vehicle | H70: 598 | I70: Yes | J70: =IF(ISBLANK(INDEX('Policy Characteristics'!D:D,MATCH($C70,'Policy Characteristics'!$C:$C,0))),"",INDEX('Policy Characteristics'!D:D,MATCH($C70,'Policy Characteristics'!$C:$C,0))) -> Vehicle Subsidy | K70: =IF(ISBLANK(INDEX('Policy Characteristics'!E:E,MATCH($C70,'Policy Characteristics'!$C:$C,0))),"",INDEX('Policy Characteristics'!E:E,MATCH($C70,'Policy Characteristics'!$C:$C,0))) -> trans psgr subsidy | L70: =IF(ISBLANK(INDEX('Policy Characteristics'!F:F,MATCH($C70,'Policy Characteristics'!$C:$C,0))),"",INDEX('Policy Characteristics'!F:F,MATCH($C70,'Policy Characteristics'!$C:$C,0))) -> -60000 | M70: =IF(ISBLANK(INDEX('Policy Characteristics'!G:G,MATCH($C70,'Policy Characteristics'!$C:$C,0))),"",INDEX('Policy Characteristics'!G:G,MATCH($C70,'Policy Characteristics'!$C:$C,0))) -> 60000 | N70: =IF(ISBLANK(INDEX('Policy Characteristics'!H:H,MATCH($C70,'Policy Characteristics'!$C:$C,0))),"",INDEX('Policy Characteristics'!H:H,MATCH($C70,'Policy Characteristics'!$C:$C,0))) -> 1000 | O70: =IF(ISBLANK(INDEX('Policy Characteristics'!I:I,MATCH($C70,'Policy Characteristics'!$C:$C,0))),"",INDEX('Policy Characteristics'!I:I,MATCH($C70,'Policy Characteristics'!$C:$C,0))) -> thousand KRW/vehicle | P70: =IF(ISBLANK(INDEX('Policy Characteristics'!J:J,MATCH($C70,'Policy Characteristics'!$C:$C,0))),"",INDEX('Policy Characteristics'!J:J,MATCH($C70,'Policy Characteristics'!$C:$C,0))) -> **Description:** This policy specifies the subsidy amount offered to purchasers of new passenger vehicle. This is in addition to subsidies that exist in the BAU case. A negative value implies a tax or removal of subsidies. // **Guidance for setting values:** As of 2025, South Korea provides substantial purchase subsidies for zero-emission vehicles. For battery electric vehicles (BEVs), the maximum combined national and local subsidy is KRW 6.4 million. For hydrogen fuel cell vehicles (FCEVs), the maximum subsidy reaches KRW 29.5 million. For heavy-duty vehicles, the support is even more significant: large battery-electric HDVs receive up to KRW 198.12 million (combined national and Seoul municipal subsidies), while hydrogen-powered buses and large vans can receive up to KRW 350 million. These subsidy levels can be used as reference points when setting the policy lever values. | Q70: =IF(ISBLANK(INDEX('Policy Characteristics'!K:K,MATCH($C70,'Policy Characteristics'!$C:$C,0))),"",INDEX('Policy Characteristics'!K:K,MATCH($C70,'Policy Characteristics'!$C:$C,0))) -> transportation-sector-main.html#ev-subsidy | R70: =IF(ISBLANK(INDEX('Policy Characteristics'!L:L,MATCH($C70,'Policy Characteristics'!$C:$C,0))),"",INDEX('Policy Characteristics'!L:L,MATCH($C70,'Policy Characteristics'!$C:$C,0))) -> ev-subsidy.html
A71: =IF(ISBLANK(INDEX('Policy Characteristics'!A:A,MATCH($C71,'Policy Characteristics'!$C:$C,0))),"",INDEX('Policy Characteristics'!A:A,MATCH($C71,'Policy Characteristics'!$C:$C,0))) -> Transportation | B71: =IF(ISBLANK(INDEX('Policy Characteristics'!B:B,MATCH($C71,'Policy Characteristics'!$C:$C,0))),"",INDEX('Policy Characteristics'!B:B,MATCH($C71,'Policy Characteristics'!$C:$C,0))) -> Passenger Vehicle Subsidy | C71: =C$63 -> Additional Passenger Vehicle Subsidy | D71: HDVs | E71: natural gas vehicle | F71: Buses | G71: Natural gas vehicle | H71: 599 | I71: No | J71: =IF(ISBLANK(INDEX('Policy Characteristics'!D:D,MATCH($C71,'Policy Characteristics'!$C:$C,0))),"",INDEX('Policy Characteristics'!D:D,MATCH($C71,'Policy Characteristics'!$C:$C,0))) -> Vehicle Subsidy | K71: =IF(ISBLANK(INDEX('Policy Characteristics'!E:E,MATCH($C71,'Policy Characteristics'!$C:$C,0))),"",INDEX('Policy Characteristics'!E:E,MATCH($C71,'Policy Characteristics'!$C:$C,0))) -> trans psgr subsidy | L71: =IF(ISBLANK(INDEX('Policy Characteristics'!F:F,MATCH($C71,'Policy Characteristics'!$C:$C,0))),"",INDEX('Policy Characteristics'!F:F,MATCH($C71,'Policy Characteristics'!$C:$C,0))) -> -60000 | M71: =IF(ISBLANK(INDEX('Policy Characteristics'!G:G,MATCH($C71,'Policy Characteristics'!$C:$C,0))),"",INDEX('Policy Characteristics'!G:G,MATCH($C71,'Policy Characteristics'!$C:$C,0))) -> 60000 | N71: =IF(ISBLANK(INDEX('Policy Characteristics'!H:H,MATCH($C71,'Policy Characteristics'!$C:$C,0))),"",INDEX('Policy Characteristics'!H:H,MATCH($C71,'Policy Characteristics'!$C:$C,0))) -> 1000 | O71: =IF(ISBLANK(INDEX('Policy Characteristics'!I:I,MATCH($C71,'Policy Characteristics'!$C:$C,0))),"",INDEX('Policy Characteristics'!I:I,MATCH($C71,'Policy Characteristics'!$C:$C,0))) -> thousand KRW/vehicle | P71: =IF(ISBLANK(INDEX('Policy Characteristics'!J:J,MATCH($C71,'Policy Characteristics'!$C:$C,0))),"",INDEX('Policy Characteristics'!J:J,MATCH($C71,'Policy Characteristics'!$C:$C,0))) -> **Description:** This policy specifies the subsidy amount offered to purchasers of new passenger vehicle. This is in addition to subsidies that exist in the BAU case. A negative value implies a tax or removal of subsidies. // **Guidance for setting values:** As of 2025, South Korea provides substantial purchase subsidies for zero-emission vehicles. For battery electric vehicles (BEVs), the maximum combined national and local subsidy is KRW 6.4 million. For hydrogen fuel cell vehicles (FCEVs), the maximum subsidy reaches KRW 29.5 million. For heavy-duty vehicles, the support is even more significant: large battery-electric HDVs receive up to KRW 198.12 million (combined national and Seoul municipal subsidies), while hydrogen-powered buses and large vans can receive up to KRW 350 million. These subsidy levels can be used as reference points when setting the policy lever values. | Q71: =IF(ISBLANK(INDEX('Policy Characteristics'!K:K,MATCH($C71,'Policy Characteristics'!$C:$C,0))),"",INDEX('Policy Characteristics'!K:K,MATCH($C71,'Policy Characteristics'!$C:$C,0))) -> transportation-sector-main.html#ev-subsidy | R71: =IF(ISBLANK(INDEX('Policy Characteristics'!L:L,MATCH($C71,'Policy Characteristics'!$C:$C,0))),"",INDEX('Policy Characteristics'!L:L,MATCH($C71,'Policy Characteristics'!$C:$C,0))) -> ev-subsidy.html
A72: =IF(ISBLANK(INDEX('Policy Characteristics'!A:A,MATCH($C72,'Policy Characteristics'!$C:$C,0))),"",INDEX('Policy Characteristics'!A:A,MATCH($C72,'Policy Characteristics'!$C:$C,0))) -> Transportation | B72: =IF(ISBLANK(INDEX('Policy Characteristics'!B:B,MATCH($C72,'Policy Characteristics'!$C:$C,0))),"",INDEX('Policy Characteristics'!B:B,MATCH($C72,'Policy Characteristics'!$C:$C,0))) -> Passenger Vehicle Subsidy | C72: =C$63 -> Additional Passenger Vehicle Subsidy | D72: HDVs | E72: gasoline vehicle | F72: Buses | G72: Gasoline vehicle | H72: 600 | I72: No | J72: =IF(ISBLANK(INDEX('Policy Characteristics'!D:D,MATCH($C72,'Policy Characteristics'!$C:$C,0))),"",INDEX('Policy Characteristics'!D:D,MATCH($C72,'Policy Characteristics'!$C:$C,0))) -> Vehicle Subsidy | K72: =IF(ISBLANK(INDEX('Policy Characteristics'!E:E,MATCH($C72,'Policy Characteristics'!$C:$C,0))),"",INDEX('Policy Characteristics'!E:E,MATCH($C72,'Policy Characteristics'!$C:$C,0))) -> trans psgr subsidy | L72: =IF(ISBLANK(INDEX('Policy Characteristics'!F:F,MATCH($C72,'Policy Characteristics'!$C:$C,0))),"",INDEX('Policy Characteristics'!F:F,MATCH($C72,'Policy Characteristics'!$C:$C,0))) -> -60000 | M72: =IF(ISBLANK(INDEX('Policy Characteristics'!G:G,MATCH($C72,'Policy Characteristics'!$C:$C,0))),"",INDEX('Policy Characteristics'!G:G,MATCH($C72,'Policy Characteristics'!$C:$C,0))) -> 60000 | N72: =IF(ISBLANK(INDEX('Policy Characteristics'!H:H,MATCH($C72,'Policy Characteristics'!$C:$C,0))),"",INDEX('Policy Characteristics'!H:H,MATCH($C72,'Policy Characteristics'!$C:$C,0))) -> 1000 | O72: =IF(ISBLANK(INDEX('Policy Characteristics'!I:I,MATCH($C72,'Policy Characteristics'!$C:$C,0))),"",INDEX('Policy Characteristics'!I:I,MATCH($C72,'Policy Characteristics'!$C:$C,0))) -> thousand KRW/vehicle | P72: =IF(ISBLANK(INDEX('Policy Characteristics'!J:J,MATCH($C72,'Policy Characteristics'!$C:$C,0))),"",INDEX('Policy Characteristics'!J:J,MATCH($C72,'Policy Characteristics'!$C:$C,0))) -> **Description:** This policy specifies the subsidy amount offered to purchasers of new passenger vehicle. This is in addition to subsidies that exist in the BAU case. A negative value implies a tax or removal of subsidies. // **Guidance for setting values:** As of 2025, South Korea provides substantial purchase subsidies for zero-emission vehicles. For battery electric vehicles (BEVs), the maximum combined national and local subsidy is KRW 6.4 million. For hydrogen fuel cell vehicles (FCEVs), the maximum subsidy reaches KRW 29.5 million. For heavy-duty vehicles, the support is even more significant: large battery-electric HDVs receive up to KRW 198.12 million (combined national and Seoul municipal subsidies), while hydrogen-powered buses and large vans can receive up to KRW 350 million. These subsidy levels can be used as reference points when setting the policy lever values. | Q72: =IF(ISBLANK(INDEX('Policy Characteristics'!K:K,MATCH($C72,'Policy Characteristics'!$C:$C,0))),"",INDEX('Policy Characteristics'!K:K,MATCH($C72,'Policy Characteristics'!$C:$C,0))) -> transportation-sector-main.html#ev-subsidy | R72: =IF(ISBLANK(INDEX('Policy Characteristics'!L:L,MATCH($C72,'Policy Characteristics'!$C:$C,0))),"",INDEX('Policy Characteristics'!L:L,MATCH($C72,'Policy Characteristics'!$C:$C,0))) -> ev-subsidy.html
A73: =IF(ISBLANK(INDEX('Policy Characteristics'!A:A,MATCH($C73,'Policy Characteristics'!$C:$C,0))),"",INDEX('Policy Characteristics'!A:A,MATCH($C73,'Policy Characteristics'!$C:$C,0))) -> Transportation | B73: =IF(ISBLANK(INDEX('Policy Characteristics'!B:B,MATCH($C73,'Policy Characteristics'!$C:$C,0))),"",INDEX('Policy Characteristics'!B:B,MATCH($C73,'Policy Characteristics'!$C:$C,0))) -> Passenger Vehicle Subsidy | C73: =C$63 -> Additional Passenger Vehicle Subsidy | D73: HDVs | E73: diesel vehicle | F73: Buses | G73: Diesel vehicle | H73: 601 | I73: No | J73: =IF(ISBLANK(INDEX('Policy Characteristics'!D:D,MATCH($C73,'Policy Characteristics'!$C:$C,0))),"",INDEX('Policy Characteristics'!D:D,MATCH($C73,'Policy Characteristics'!$C:$C,0))) -> Vehicle Subsidy | K73: =IF(ISBLANK(INDEX('Policy Characteristics'!E:E,MATCH($C73,'Policy Characteristics'!$C:$C,0))),"",INDEX('Policy Characteristics'!E:E,MATCH($C73,'Policy Characteristics'!$C:$C,0))) -> trans psgr subsidy | L73: =IF(ISBLANK(INDEX('Policy Characteristics'!F:F,MATCH($C73,'Policy Characteristics'!$C:$C,0))),"",INDEX('Policy Characteristics'!F:F,MATCH($C73,'Policy Characteristics'!$C:$C,0))) -> -60000 | M73: =IF(ISBLANK(INDEX('Policy Characteristics'!G:G,MATCH($C73,'Policy Characteristics'!$C:$C,0))),"",INDEX('Policy Characteristics'!G:G,MATCH($C73,'Policy Characteristics'!$C:$C,0))) -> 60000 | N73: =IF(ISBLANK(INDEX('Policy Characteristics'!H:H,MATCH($C73,'Policy Characteristics'!$C:$C,0))),"",INDEX('Policy Characteristics'!H:H,MATCH($C73,'Policy Characteristics'!$C:$C,0))) -> 1000 | O73: =IF(ISBLANK(INDEX('Policy Characteristics'!I:I,MATCH($C73,'Policy Characteristics'!$C:$C,0))),"",INDEX('Policy Characteristics'!I:I,MATCH($C73,'Policy Characteristics'!$C:$C,0))) -> thousand KRW/vehicle | P73: =IF(ISBLANK(INDEX('Policy Characteristics'!J:J,MATCH($C73,'Policy Characteristics'!$C:$C,0))),"",INDEX('Policy Characteristics'!J:J,MATCH($C73,'Policy Characteristics'!$C:$C,0))) -> **Description:** This policy specifies the subsidy amount offered to purchasers of new passenger vehicle. This is in addition to subsidies that exist in the BAU case. A negative value implies a tax or removal of subsidies. // **Guidance for setting values:** As of 2025, South Korea provides substantial purchase subsidies for zero-emission vehicles. For battery electric vehicles (BEVs), the maximum combined national and local subsidy is KRW 6.4 million. For hydrogen fuel cell vehicles (FCEVs), the maximum subsidy reaches KRW 29.5 million. For heavy-duty vehicles, the support is even more significant: large battery-electric HDVs receive up to KRW 198.12 million (combined national and Seoul municipal subsidies), while hydrogen-powered buses and large vans can receive up to KRW 350 million. These subsidy levels can be used as reference points when setting the policy lever values. | Q73: =IF(ISBLANK(INDEX('Policy Characteristics'!K:K,MATCH($C73,'Policy Characteristics'!$C:$C,0))),"",INDEX('Policy Characteristics'!K:K,MATCH($C73,'Policy Characteristics'!$C:$C,0))) -> transportation-sector-main.html#ev-subsidy | R73: =IF(ISBLANK(INDEX('Policy Characteristics'!L:L,MATCH($C73,'Policy Characteristics'!$C:$C,0))),"",INDEX('Policy Characteristics'!L:L,MATCH($C73,'Policy Characteristics'!$C:$C,0))) -> ev-subsidy.html
A74: =IF(ISBLANK(INDEX('Policy Characteristics'!A:A,MATCH($C74,'Policy Characteristics'!$C:$C,0))),"",INDEX('Policy Characteristics'!A:A,MATCH($C74,'Policy Characteristics'!$C:$C,0))) -> Transportation | B74: =IF(ISBLANK(INDEX('Policy Characteristics'!B:B,MATCH($C74,'Policy Characteristics'!$C:$C,0))),"",INDEX('Policy Characteristics'!B:B,MATCH($C74,'Policy Characteristics'!$C:$C,0))) -> Passenger Vehicle Subsidy | C74: =C$63 -> Additional Passenger Vehicle Subsidy | D74: HDVs | E74: plugin hybrid vehicle | F74: Buses | G74: Plugin hybrid vehicle | H74: 602 | I74: Yes | J74: =IF(ISBLANK(INDEX('Policy Characteristics'!D:D,MATCH($C74,'Policy Characteristics'!$C:$C,0))),"",INDEX('Policy Characteristics'!D:D,MATCH($C74,'Policy Characteristics'!$C:$C,0))) -> Vehicle Subsidy | K74: =IF(ISBLANK(INDEX('Policy Characteristics'!E:E,MATCH($C74,'Policy Characteristics'!$C:$C,0))),"",INDEX('Policy Characteristics'!E:E,MATCH($C74,'Policy Characteristics'!$C:$C,0))) -> trans psgr subsidy | L74: =IF(ISBLANK(INDEX('Policy Characteristics'!F:F,MATCH($C74,'Policy Characteristics'!$C:$C,0))),"",INDEX('Policy Characteristics'!F:F,MATCH($C74,'Policy Characteristics'!$C:$C,0))) -> -60000 | M74: =IF(ISBLANK(INDEX('Policy Characteristics'!G:G,MATCH($C74,'Policy Characteristics'!$C:$C,0))),"",INDEX('Policy Characteristics'!G:G,MATCH($C74,'Policy Characteristics'!$C:$C,0))) -> 60000 | N74: =IF(ISBLANK(INDEX('Policy Characteristics'!H:H,MATCH($C74,'Policy Characteristics'!$C:$C,0))),"",INDEX('Policy Characteristics'!H:H,MATCH($C74,'Policy Characteristics'!$C:$C,0))) -> 1000 | O74: =IF(ISBLANK(INDEX('Policy Characteristics'!I:I,MATCH($C74,'Policy Characteristics'!$C:$C,0))),"",INDEX('Policy Characteristics'!I:I,MATCH($C74,'Policy Characteristics'!$C:$C,0))) -> thousand KRW/vehicle | P74: =IF(ISBLANK(INDEX('Policy Characteristics'!J:J,MATCH($C74,'Policy Characteristics'!$C:$C,0))),"",INDEX('Policy Characteristics'!J:J,MATCH($C74,'Policy Characteristics'!$C:$C,0))) -> **Description:** This policy specifies the subsidy amount offered to purchasers of new passenger vehicle. This is in addition to subsidies that exist in the BAU case. A negative value implies a tax or removal of subsidies. // **Guidance for setting values:** As of 2025, South Korea provides substantial purchase subsidies for zero-emission vehicles. For battery electric vehicles (BEVs), the maximum combined national and local subsidy is KRW 6.4 million. For hydrogen fuel cell vehicles (FCEVs), the maximum subsidy reaches KRW 29.5 million. For heavy-duty vehicles, the support is even more significant: large battery-electric HDVs receive up to KRW 198.12 million (combined national and Seoul municipal subsidies), while hydrogen-powered buses and large vans can receive up to KRW 350 million. These subsidy levels can be used as reference points when setting the policy lever values. | Q74: =IF(ISBLANK(INDEX('Policy Characteristics'!K:K,MATCH($C74,'Policy Characteristics'!$C:$C,0))),"",INDEX('Policy Characteristics'!K:K,MATCH($C74,'Policy Characteristics'!$C:$C,0))) -> transportation-sector-main.html#ev-subsidy | R74: =IF(ISBLANK(INDEX('Policy Characteristics'!L:L,MATCH($C74,'Policy Characteristics'!$C:$C,0))),"",INDEX('Policy Characteristics'!L:L,MATCH($C74,'Policy Characteristics'!$C:$C,0))) -> ev-subsidy.html
A75: =IF(ISBLANK(INDEX('Policy Characteristics'!A:A,MATCH($C75,'Policy Characteristics'!$C:$C,0))),"",INDEX('Policy Characteristics'!A:A,MATCH($C75,'Policy Characteristics'!$C:$C,0))) -> Transportation | B75: =IF(ISBLANK(INDEX('Policy Characteristics'!B:B,MATCH($C75,'Policy Characteristics'!$C:$C,0))),"",INDEX('Policy Characteristics'!B:B,MATCH($C75,'Policy Characteristics'!$C:$C,0))) -> Passenger Vehicle Subsidy | C75: =C$63 -> Additional Passenger Vehicle Subsidy | D75: HDVs | E75: LPG vehicle | F75: Buses | G75: LPG vehicle | H75: 1656 | I75: No | J75: =IF(ISBLANK(INDEX('Policy Characteristics'!D:D,MATCH($C75,'Policy Characteristics'!$C:$C,0))),"",INDEX('Policy Characteristics'!D:D,MATCH($C75,'Policy Characteristics'!$C:$C,0))) -> Vehicle Subsidy | K75: =IF(ISBLANK(INDEX('Policy Characteristics'!E:E,MATCH($C75,'Policy Characteristics'!$C:$C,0))),"",INDEX('Policy Characteristics'!E:E,MATCH($C75,'Policy Characteristics'!$C:$C,0))) -> trans psgr subsidy | L75: =IF(ISBLANK(INDEX('Policy Characteristics'!F:F,MATCH($C75,'Policy Characteristics'!$C:$C,0))),"",INDEX('Policy Characteristics'!F:F,MATCH($C75,'Policy Characteristics'!$C:$C,0))) -> -60000 | M75: =IF(ISBLANK(INDEX('Policy Characteristics'!G:G,MATCH($C75,'Policy Characteristics'!$C:$C,0))),"",INDEX('Policy Characteristics'!G:G,MATCH($C75,'Policy Characteristics'!$C:$C,0))) -> 60000 | N75: =IF(ISBLANK(INDEX('Policy Characteristics'!H:H,MATCH($C75,'Policy Characteristics'!$C:$C,0))),"",INDEX('Policy Characteristics'!H:H,MATCH($C75,'Policy Characteristics'!$C:$C,0))) -> 1000 | O75: =IF(ISBLANK(INDEX('Policy Characteristics'!I:I,MATCH($C75,'Policy Characteristics'!$C:$C,0))),"",INDEX('Policy Characteristics'!I:I,MATCH($C75,'Policy Characteristics'!$C:$C,0))) -> thousand KRW/vehicle | P75: =IF(ISBLANK(INDEX('Policy Characteristics'!J:J,MATCH($C75,'Policy Characteristics'!$C:$C,0))),"",INDEX('Policy Characteristics'!J:J,MATCH($C75,'Policy Characteristics'!$C:$C,0))) -> **Description:** This policy specifies the subsidy amount offered to purchasers of new passenger vehicle. This is in addition to subsidies that exist in the BAU case. A negative value implies a tax or removal of subsidies. // **Guidance for setting values:** As of 2025, South Korea provides substantial purchase subsidies for zero-emission vehicles. For battery electric vehicles (BEVs), the maximum combined national and local subsidy is KRW 6.4 million. For hydrogen fuel cell vehicles (FCEVs), the maximum subsidy reaches KRW 29.5 million. For heavy-duty vehicles, the support is even more significant: large battery-electric HDVs receive up to KRW 198.12 million (combined national and Seoul municipal subsidies), while hydrogen-powered buses and large vans can receive up to KRW 350 million. These subsidy levels can be used as reference points when setting the policy lever values. | Q75: =IF(ISBLANK(INDEX('Policy Characteristics'!K:K,MATCH($C75,'Policy Characteristics'!$C:$C,0))),"",INDEX('Policy Characteristics'!K:K,MATCH($C75,'Policy Characteristics'!$C:$C,0))) -> transportation-sector-main.html#ev-subsidy | R75: =IF(ISBLANK(INDEX('Policy Characteristics'!L:L,MATCH($C75,'Policy Characteristics'!$C:$C,0))),"",INDEX('Policy Characteristics'!L:L,MATCH($C75,'Policy Characteristics'!$C:$C,0))) -> ev-subsidy.html
... A104: =IF(ISBLANK(INDEX('Policy Characteristics'!A:A,MATCH($C104,'Policy Characteristics'!$C:$C,0))),"",INDEX('Policy Characteristics'!A:A,MATCH($C104,'Policy Characteristics'!$C:$C,0))) -> Transportation | B104: =IF(ISBLANK(INDEX('Policy Characteristics'!B:B,MATCH($C104,'Policy Characteristics'!$C:$C,0))),"",INDEX('Policy Characteristics'!B:B,MATCH($C104,'Policy Characteristics'!$C:$C,0))) -> Passenger Vehicle Subsidy | C104: =C$63 -> Additional Passenger Vehicle Subsidy | D104: motorbikes | E104: hydrogen vehicle | F104: Motorbikes | G104: Hydrogen vehicle | H104: 1685 | I104: Yes | J104: =IF(ISBLANK(INDEX('Policy Characteristics'!D:D,MATCH($C104,'Policy Characteristics'!$C:$C,0))),"",INDEX('Policy Characteristics'!D:D,MATCH($C104,'Policy Characteristics'!$C:$C,0))) -> Vehicle Subsidy | K104: =IF(ISBLANK(INDEX('Policy Characteristics'!E:E,MATCH($C104,'Policy Characteristics'!$C:$C,0))),"",INDEX('Policy Characteristics'!E:E,MATCH($C104,'Policy Characteristics'!$C:$C,0))) -> trans psgr subsidy | L104: =IF(ISBLANK(INDEX('Policy Characteristics'!F:F,MATCH($C104,'Policy Characteristics'!$C:$C,0))),"",INDEX('Policy Characteristics'!F:F,MATCH($C104,'Policy Characteristics'!$C:$C,0))) -> -60000 | M104: =IF(ISBLANK(INDEX('Policy Characteristics'!G:G,MATCH($C104,'Policy Characteristics'!$C:$C,0))),"",INDEX('Policy Characteristics'!G:G,MATCH($C104,'Policy Characteristics'!$C:$C,0))) -> 60000 | N104: =IF(ISBLANK(INDEX('Policy Characteristics'!H:H,MATCH($C104,'Policy Characteristics'!$C:$C,0))),"",INDEX('Policy Characteristics'!H:H,MATCH($C104,'Policy Characteristics'!$C:$C,0))) -> 1000 | O104: =IF(ISBLANK(INDEX('Policy Characteristics'!I:I,MATCH($C104,'Policy Characteristics'!$C:$C,0))),"",INDEX('Policy Characteristics'!I:I,MATCH($C104,'Policy Characteristics'!$C:$C,0))) -> thousand KRW/vehicle | P104: =IF(ISBLANK(INDEX('Policy Characteristics'!J:J,MATCH($C104,'Policy Characteristics'!$C:$C,0))),"",INDEX('Policy Characteristics'!J:J,MATCH($C104,'Policy Characteristics'!$C:$C,0))) -> **Description:** This policy specifies the subsidy amount offered to purchasers of new passenger vehicle. This is in addition to subsidies that exist in the BAU case. A negative value implies a tax or removal of subsidies. // **Guidance for setting values:** As of 2025, South Korea provides substantial purchase subsidies for zero-emission vehicles. For battery electric vehicles (BEVs), the maximum combined national and local subsidy is KRW 6.4 million. For hydrogen fuel cell vehicles (FCEVs), the maximum subsidy reaches KRW 29.5 million. For heavy-duty vehicles, the support is even more significant: large battery-electric HDVs receive up to KRW 198.12 million (combined national and Seoul municipal subsidies), while hydrogen-powered buses and large vans can receive up to KRW 350 million. These subsidy levels can be used as reference points when setting the policy lever values. | Q104: =IF(ISBLANK(INDEX('Policy Characteristics'!K:K,MATCH($C104,'Policy Characteristics'!$C:$C,0))),"",INDEX('Policy Characteristics'!K:K,MATCH($C104,'Policy Characteristics'!$C:$C,0))) -> transportation-sector-main.html#ev-subsidy | R104: =IF(ISBLANK(INDEX('Policy Characteristics'!L:L,MATCH($C104,'Policy Characteristics'!$C:$C,0))),"",INDEX('Policy Characteristics'!L:L,MATCH($C104,'Policy Characteristics'!$C:$C,0))) -> ev-subsidy.html
