Workbook
Name CAP_CT: #REF!
Name CAP_GFCF: #REF!
Name CAP_IT: #REF!
Name CAP_OCon: #REF!
Name CAP_OMach: #REF!
Name CAP_Other: #REF!
Name CAP_QI: #REF!
Name CAP_RStruc: #REF!
Name CAP_Soft: #REF!
Name CAP_TraEq: #REF!
Name CAPIT: #REF!
Name CAPIT_QI: #REF!
Name capit_qph: #REF!
Name CAPNIT: #REF!
Name CAPNIT_QI: #REF!
Name capnit_qph: #REF!
Name FLAPPIE: #REF!
Name VAConL: #REF!

Sheet About
A1: DLIM Domestic Leontief Inverse Matrix
A3: Source: | B3: Most Data
B4: OECD
B5: 2023
B6: Input-Output Tables 2025 Edition
B7: https://www.oecd.org/en/data/datasets/input-output-tables.html
B8: Variable: LEONTFD
B10: Split for Chemicals/Pharmaceuticals and Coal/Petroleum Extraction Industries
B11: World Input-Output Database
B12: 2016
B13: National IO Tables
B14: http://www.wiod.org/database/niots16
B15: Korea NIOT, 2014 domestic data
B17: Split for All Other ISIC Codes
B18: Exiobase
B19: 2019
B20: Exiobase 3rx, 2016
B21: https://zenodo.org/record/2654460#.YEFjHmhKg2w
B22: A matrix, KOR
A24: Notes
A25: OECD Stat directly provides Leontief inverse matrices, both total and domestic-only, for
A26: 64 countries and regions.
A28: A domestic-only Leontief matrix filters out payments to foreign suppliers from the respending
A29: calculations. This type of Leontief matrix must be multiplied by a change in domestic (not total)
A30: output by ISIC code, as it does not filter the direct output changes by which it is multiplied.
A31: Conversely, a "Total" Leontief matrix must be multiplied by a change in total (not domestic)
A32: output by ISIC code, as it cannot restore imports that were removed from the direct output changes
A33: by which it is multiplied.
A35: For Korea, we use OECD data where possible, and use the World Input-Output Database (WIOD, see cells with
A36: light orange highlightings) and Exiobase (see cells with yellow highlighting). We follow the procedure below
A37: for those ISIC code splits. For certain cells in the ISIC 20/21 split highlighted in dark orange, the WIOD data source
... A91: before creating a Leontief Inverse Matrix.

Sheet ISIC Crosswalk
A1: Row / Ligne | B1: Row / Ligne source | C1: Row Name en | D1: Row ISIC | E1: Column / Colonne | F1: Column Name en | G1: Column ISIC | P1: ISIC 01T03, | Q1: {Agriculture, forestry and fishing}
A2: DOM_A01 | B2: Domestic | C2: Agriculture and hunting | D2: ISIC 01T03 | E2: A01 | F2: Agriculture and hunting | P2: ISIC 05, | Q2: {Coal mining}
A3: DOM_A02 | B3: Domestic | C3: Forestry and logging | D3: ISIC 01T03 | E3: A02 | F3: Forestry and logging | P3: ISIC 06, | Q3: {Oil and gas extraction}
A4: DOM_A03 | B4: Domestic | C4: Fishing and aquaculture | D4: ISIC 01T03 | E4: A03 | F4: Fishing and aquaculture | P4: ISIC 07T08, | Q4: {Mining and quarrying of non-energy producing products}
A5: DOM_B05 | B5: Domestic | C5: Mining of coal and lignite | D5: ISIC 05 | E5: B05 | F5: Mining of coal and lignite | P5: ISIC 09, | Q5: {Mining support service activities}
A6: DOM_B06 | B6: Domestic | C6: Extraction of crude petroleum and natural gas | D6: ISIC 06 | E6: B06 | F6: Extraction of crude petroleum and natural gas | P6: ISIC 10T12, | Q6: {Food products, beverages and tobacco}
A7: DOM_B07 | B7: Domestic | C7: Mining of metal ores | D7: ISIC 07T08 | E7: B07 | F7: Mining of metal ores | P7: ISIC 13T15, | Q7: {Textiles, wearing apparel, leather and related products}
A8: DOM_B08 | B8: Domestic | C8: Other mining and quarrying | D8: ISIC 07T08 | E8: B08 | F8: Other mining and quarrying | P8: ISIC 16, | Q8: {Wood and of products of wood and cork (except furniture)}
A9: DOM_B09 | B9: Domestic | C9: Mining support service activities | D9: ISIC 09 | E9: B09 | F9: Mining support service activities | P9: ISIC 17T18, | Q9: {Paper products and printing}
A10: DOM_C10T12 | B10: Domestic | C10: Food products, beverages and tobacco | D10: ISIC 10T12 | E10: C10T12 | F10: Food products, beverages and tobacco | P10: ISIC 19, | Q10: {Coke and refined petroleum products}
A11: DOM_C13T15 | B11: Domestic | C11: Textiles, textile products, leather and footwear | D11: ISIC 13T15 | E11: C13T15 | F11: Textiles, textile products, leather and footwear | P11: ISIC 20, | Q11: {Chemicals}
A12: DOM_C16 | B12: Domestic | C12: Wood and products of wood and cork | D12: ISIC 16 | E12: C16 | F12: Wood and products of wood and cork | P12: ISIC 21, | Q12: {Pharmaceuticals}
A13: DOM_C17_18 | B13: Domestic | C13: Paper products; printing and reproduction of recorded media | D13: ISIC 17T18 | E13: C17_18 | F13: Paper products; printing and reproduction of recorded media | P13: ISIC 22, | Q13: {Rubber and plastics products}
... A42: DOM_K | B42: Domestic | C42: Financial and insurance activities | D42: ISIC 64T66 | E42: K | F42: Financial and insurance activities | P42: ISIC 97T98 | Q42: {Private households with employed persons}
A43: DOM_L | B43: Domestic | C43: Real estate activities | D43: ISIC 68 | E43: L | F43: Real estate activities
A44: DOM_M | B44: Domestic | C44: Professional, scientific and technical activities | D44: ISIC 69T82 | E44: M | F44: Professional, scientific and technical activities
A45: DOM_N | B45: Domestic | C45: Administrative and support services | D45: ISIC 69T82 | E45: N | F45: Administrative and support services
A46: DOM_O | B46: Domestic | C46: Public administration and defence; compulsory social security | D46: ISIC 84 | E46: O | F46: Public administration and defence; compulsory social security
A47: DOM_P | B47: Domestic | C47: Education | D47: ISIC 85 | E47: P | F47: Education
A48: DOM_Q | B48: Domestic | C48: Human health and social work activities | D48: ISIC 86T88 | E48: Q | F48: Human health and social work activities
A49: DOM_R | B49: Domestic | C49: Arts, entertainment and recreation | D49: ISIC 90T96 | E49: R | F49: Arts, entertainment and recreation
A50: DOM_S | B50: Domestic | C50: Other service activities | D50: ISIC 90T96 | E50: S | F50: Other service activities
A51: DOM_T | B51: Domestic | C51: Activities of households as employers; undifferentiated goods- and services-producing activities of households for own use | D51: ISIC 97T98 | E51: T | F51: Activities of households as employers; undifferentiated goods- and services-producing activities of households for own use
A52: IMP_A01 | B52: Import | C52: Agriculture and hunting | D52: ISIC 01T03 | E52: HFCE | F52: Household final consumption expenditure (excluding direct purchases)
A53: IMP_A02 | B53: Import | C53: Forestry and logging | D53: ISIC 01T03 | E53: NPISH | F53: Final consumption expenditure of non-profit institutions serving households
A54: IMP_A03 | B54: Import | C54: Fishing and aquaculture | D54: ISIC 01T03 | E54: GGFC | F54: Final consumption expenditure of general government
... A61: IMP_C13T15 | B61: Import | C61: Textiles, textile products, leather and footwear | D61: ISIC 13T15 | E61: TOTAL | F61: Total
A62: IMP_C16 | B62: Import | C62: Wood and products of wood and cork | D62: ISIC 16
A63: IMP_C17_18 | B63: Import | C63: Paper products; printing and reproduction of recorded media | D63: ISIC 17T18
A64: IMP_C19 | B64: Import | C64: Coke and refined petroleum products | D64: ISIC 19
A65: IMP_C20 | B65: Import | C65: Chemical and chemical products | D65: ISIC 20
A66: IMP_C21 | B66: Import | C66: Pharmaceuticals, medicinal chemical and botanical products | D66: ISIC 21
A67: IMP_C22 | B67: Import | C67: Rubber and plastics products | D67: ISIC 22
A68: IMP_C23 | B68: Import | C68: Other non-metallic mineral products | D68: ISIC 231
A69: IMP_C24A | B69: Import | C69: Manufacture of basic iron and steel | D69: ISIC 241
A70: IMP_C24B | B70: Import | C70: Manufacture of basic precious and other non-ferrous metals | D70: ISIC 242
A71: IMP_C25 | B71: Import | C71: Fabricated metal products | D71: ISIC 25
A72: IMP_C26 | B72: Import | C72: Computer, electronic and optical equipment | D72: ISIC 26
A73: IMP_C27 | B73: Import | C73: Electrical equipment | D73: ISIC 27
... A102: IMP_OTHER | B102: Import | C102: Other imports | D102: OTHER IMPORTS
A103: TXS_INT_FNL | C103: Taxes less subsidies on intermediate and final products (paid in domestic agencies, includes duty on imported products)
A104: TTL_INT_FNL | C104: Total intermediate consumption at purchasers’ prices
A105: VALU | C105: Value added at basic prices
A106: OUTPUT | C106: Output at basic prices

Sheet OECD_KOR2022dom
B1: A01 | C1: A02 | D1: A03 | E1: B05 | F1: B06 | G1: B07 | H1: B08 | I1: B09 | J1: C10T12 | K1: C13T15 | L1: C16 | M1: C17_18 | N1: C19 | O1: C20 | P1: C21 | Q1: C22 | R1: C23 | S1: C24A | T1: C24B | U1: C25 | V1: C26 | W1: C27 | X1: C28 | Y1: C29 | Z1: C301 | AA1: C302T309 | AB1: C31T33 | AC1: D | AD1: E | AE1: F | AF1: G | AG1: H49 | AH1: H50 | AI1: H51 | AJ1: H52 | AK1: H53 | AL1: I | AM1: J58T60 | AN1: J61 | AO1: J62_63 | AP1: K | AQ1: L | AR1: M | AS1: N | AT1: O | AU1: P | AV1: Q | AW1: R | AX1: S | AY1: T | AZ1: HFCE | BA1: NPISH | BB1: GGFC | BC1: GFCF | BD1: INVNT | BE1: DPABR | BF1: CONS_NONRES | BG1: EXPO | BH1: .. | BI1: TOTAL
A2: DOM_A01 | B2: 2972.944 | C2: 35.361 | D2: 53.443 | E2: 0.014 | F2: 0.004 | G2: 0.003 | H2: 0.545 | I2: 0.001 | J2: 20981.346 | K2: 486.111 | L2: 11.969 | M2: 4.086 | N2: 0.355 | O2: 251.497 | P2: 47.453 | Q2: 81.025 | R2: 0.994 | S2: 0.44 | T2: 0.431 | U2: 0.947 | V2: 4.885 | W2: 1.437 | X2: 6.793 | Y2: 3.345 | Z2: 0.898 | AA2: 0.23 | AB2: 13.723 | AC2: 22.533 | AD2: 5.306 | AE2: 54.845 | AF2: 407.723 | AG2: 2.029 | AH2: 4.886 | AI2: 0.153 | AJ2: 6.918 | AK2: 0.603 | AL2: 4458.133 | AM2: 2.633 | AN2: 0.828 | AO2: 0.472 | AP2: 2.057 | AQ2: 8.563 | AR2: 49.211 | AS2: 36.942 | AT2: 47.886 | AU2: 58.946 | AV2: 147.215 | AW2: 31.316 | AX2: 46.865 | AY2: 0 | AZ2: 13717.814 | BA2: 15.803 | BB2: 0.764 | BC2: 290.073 | BD2: 6.014 | BE2: 0 | BF2: 70.645 | BG2: 614.131 | BH2: 0 | BI2: 45071.583
A3: DOM_A02 | B3: 72.761 | C3: 351.459 | D3: 2.964 | E3: 0.16 | F3: 0.006 | G3: 0.008 | H3: 0.435 | I3: 0 | J3: 219.116 | K3: 14.913 | L3: 935.907 | M3: 133.583 | N3: 0.292 | O3: 31.253 | P3: 1.54 | Q3: 90.787 | R3: 4.381 | S3: 2.099 | T3: 1.287 | U3: 0.912 | V3: 0.852 | W3: 0.614 | X3: 1.65 | Y3: 0.804 | Z3: 1.018 | AA3: 0.074 | AB3: 67.519 | AC3: 80.406 | AD3: 0.329 | AE3: 39.76 | AF3: 29.508 | AG3: 0.176 | AH3: 0.472 | AI3: 0.116 | AJ3: 0.647 | AK3: 0.138 | AL3: 80.7 | AM3: 0.79 | AN3: 0.559 | AO3: 0.54 | AP3: 0.827 | AQ3: 3.732 | AR3: 1.942 | AS3: 1.71 | AT3: 11.379 | AU3: 5.899 | AV3: 5.161 | AW3: 5.906 | AX3: 4.617 | AY3: 0 | AZ3: 523.368 | BA3: 15.967 | BB3: 0.03 | BC3: 282.703 | BD3: 2.873 | BE3: 0 | BF3: 0.374 | BG3: 45.905 | BH3: 0 | BI3: 3082.931
A4: DOM_A03 | B4: 4.855 | C4: 0.448 | D4: 431.333 | E4: 0.003 | F4: 0 | G4: 0.001 | H4: 0.045 | I4: 0 | J4: 2711.583 | K4: 0.912 | L4: 0.03 | M4: 0.088 | N4: 0.121 | O4: 2.273 | P4: 0.41 | Q4: 0.252 | R4: 0.161 | S4: 0.136 | T4: 0.125 | U4: 0.307 | V4: 0.607 | W4: 0.314 | X4: 0.469 | Y4: 0.183 | Z4: 0.192 | AA4: 0.012 | AB4: 0.149 | AC4: 0.215 | AD4: 0.097 | AE4: 0.784 | AF4: 40.507 | AG4: 0.087 | AH4: 1.421 | AI4: 0.035 | AJ4: 0.358 | AK4: 0.004 | AL4: 1256.01 | AM4: 0.518 | AN4: 0.175 | AO4: 0.352 | AP4: 0.686 | AQ4: 1.094 | AR4: 1.13 | AS4: 0.297 | AT4: 11.728 | AU4: 4.604 | AV4: 12.708 | AW4: 1.67 | AX4: 2.656 | AY4: 0 | AZ4: 2680.682 | BA4: 3.634 | BB4: 0.011 | BC4: 0.994 | BD4: 1.566 | BE4: 0 | BF4: 5.209 | BG4: 429.385 | BH4: 0 | BI4: 7613.625
A5: DOM_B05 | B5: 0.143 | C5: 0.007 | D5: 0.039 | E5: 0.244 | F5: 0 | G5: 0 | H5: 0.02 | I5: 0 | J5: 0.427 | K5: 0.214 | L5: 0.025 | M5: 0.112 | N5: 24.173 | O5: 0.627 | P5: 0.07 | Q5: 0.213 | R5: 0.159 | S5: 0.391 | T5: 0.134 | U5: 0.258 | V5: 0.773 | W5: 0.289 | X5: 0.432 | Y5: 0.394 | Z5: 0.095 | AA5: 0.037 | AB5: 0.095 | AC5: 208.802 | AD5: 0.072 | AE5: 0.458 | AF5: 0.348 | AG5: 0.06 | AH5: 0.122 | AI5: 0.09 | AJ5: 0.103 | AK5: 0.014 | AL5: 0.316 | AM5: 0.03 | AN5: 0.075 | AO5: 0.043 | AP5: 0.038 | AQ5: 0.084 | AR5: 0.169 | AS5: 0.085 | AT5: 0.126 | AU5: 0.103 | AV5: 0.192 | AW5: 0.047 | AX5: 0.09 | AY5: 0 | AZ5: 2.837 | BA5: 0.002 | BB5: 0.001 | BC5: 0.733 | BD5: 0.016 | BE5: 0 | BF5: 0.005 | BG5: 13.228 | BH5: 0 | BI5: 257.663
A6: DOM_B06 | B6: 0.037 | C6: 0.001 | D6: 0.008 | E6: 0 | F6: 0.008 | G6: 0 | H6: 0.003 | I6: 0 | J6: 0.164 | K6: 0.109 | L6: 0.009 | M6: 0.04 | N6: 102.895 | O6: 0.292 | P6: 0.034 | Q6: 0.106 | R6: 0.048 | S6: 0.11 | T6: 0.032 | U6: 0.098 | V6: 0.433 | W6: 0.14 | X6: 0.181 | Y6: 0.157 | Z6: 0.044 | AA6: 0.011 | AB6: 0.03 | AC6: 29.374 | AD6: 0.01 | AE6: 0.201 | AF6: 0.111 | AG6: 0.016 | AH6: 0.029 | AI6: 0.014 | AJ6: 0.022 | AK6: 0.004 | AL6: 0.125 | AM6: 0.013 | AN6: 0.019 | AO6: 0.01 | AP6: 0.009 | AQ6: 0.022 | AR6: 0.038 | AS6: 0.017 | AT6: 0.025 | AU6: 0.02 | AV6: 0.08 | AW6: 0.01 | AX6: 0.031 | AY6: 0 | AZ6: 1.502 | BA6: 0.001 | BB6: 0 | BC6: 0.488 | BD6: 0 | BE6: 0 | BF6: 0.004 | BG6: 2.2 | BH6: 0 | BI6: 139.391
A7: DOM_B07 | B7: 0.015 | C7: 0.001 | D7: 0.001 | E7: 0.001 | F7: 0 | G7: 0.007 | H7: 0.049 | I7: 0 | J7: 0.134 | K7: 0.023 | L7: 0.012 | M7: 0.013 | N7: 0.208 | O7: 0.691 | P7: 0.018 | Q7: 0.129 | R7: 0.93 | S7: 13.709 | T7: 12.837 | U7: 3.121 | V7: 0.876 | W7: 1.269 | X7: 1.825 | Y7: 1.616 | Z7: 0.365 | AA7: 0.12 | AB7: 0.179 | AC7: 0.246 | AD7: 0.083 | AE7: 2.979 | AF7: 0.08 | AG7: 0.004 | AH7: 0.008 | AI7: 0 | AJ7: 0.016 | AK7: 0.001 | AL7: 0.048 | AM7: 0.002 | AN7: 0.002 | AO7: 0.001 | AP7: 0.005 | AQ7: 0.175 | AR7: 0.062 | AS7: 0.01 | AT7: 0.014 | AU7: 0.02 | AV7: 0.013 | AW7: 0.007 | AX7: 0.036 | AY7: 0 | AZ7: 0.013 | BA7: 0 | BB7: 0 | BC7: 0.01 | BD7: 0 | BE7: 0 | BF7: 0 | BG7: 77.799 | BH7: 0 | BI7: 119.787
A8: DOM_B08 | B8: 10.737 | C8: 0.34 | D8: 2.014 | E8: 0.222 | F8: 0.05 | G8: 0.166 | H8: 55.72 | I8: 0.024 | J8: 30.286 | K8: 4.576 | L8: 0.461 | M8: 11.305 | N8: 56.448 | O8: 296.881 | P8: 1.547 | Q8: 8.366 | R8: 850.052 | S8: 299.728 | T8: 92.038 | U8: 15.779 | V8: 9.831 | W8: 11.333 | X8: 10.294 | Y8: 7.479 | Z8: 1.78 | AA8: 0.496 | AB8: 7.362 | AC8: 64.288 | AD8: 20.94 | AE8: 878.411 | AF8: 9.21 | AG8: 0.746 | AH8: 0.456 | AI8: 0.159 | AJ8: 1.768 | AK8: 0.346 | AL8: 9.259 | AM8: 0.427 | AN8: 0.46 | AO8: 0.297 | AP8: 0.688 | AQ8: 17.445 | AR8: 3.92 | AS8: 6.448 | AT8: 12.118 | AU8: 2.945 | AV8: 4.104 | AW8: 1.027 | AX8: 2.431 | AY8: 0 | AZ8: 38.618 | BA8: 0.206 | BB8: 0.017 | BC8: 3.378 | BD8: 0 | BE8: 0 | BF8: 0.558 | BG8: 408.298 | BH8: 0 | BI8: 3274.282
A9: DOM_B09 | B9: 0.019 | C9: 0.001 | D9: 0.004 | E9: 0 | F9: 0 | G9: 0 | H9: 0.002 | I9: 0 | J9: 0.085 | K9: 0.056 | L9: 0.005 | M9: 0.021 | N9: 0.078 | O9: 0.149 | P9: 0.018 | Q9: 0.055 | R9: 0.025 | S9: 0.057 | T9: 0.017 | U9: 0.053 | V9: 0.225 | W9: 0.073 | X9: 0.094 | Y9: 0.082 | Z9: 0.023 | AA9: 0.006 | AB9: 0.016 | AC9: 0.04 | AD9: 0.005 | AE9: 0.109 | AF9: 0.057 | AG9: 0.008 | AH9: 0.014 | AI9: 0.006 | AJ9: 0.011 | AK9: 0.002 | AL9: 0.064 | AM9: 0.007 | AN9: 0.01 | AO9: 0.005 | AP9: 0.005 | AQ9: 0.012 | AR9: 0.022 | AS9: 0.009 | AT9: 0.013 | AU9: 0.01 | AV9: 0.041 | AW9: 0.005 | AX9: 0.016 | AY9: 0 | AZ9: 0.775 | BA9: 0 | BB9: 0.015 | BC9: 0.938 | BD9: 0 | BE9: 0 | BF9: 0.002 | BG9: 15.464 | BH9: 0 | BI9: 18.831
A10: DOM_C10T12 | B10: 3218.393 | C10: 5.526 | D10: 444.398 | E10: 0.179 | F10: 0.09 | G10: 0.096 | H10: 4.425 | I10: 0.012 | J10: 21114.006 | K10: 182.59 | L10: 7.488 | M10: 72.351 | N10: 38.615 | O10: 1315.58 | P10: 190.093 | Q10: 73.633 | R10: 26.308 | S10: 30.264 | T10: 24.391 | U10: 42.693 | V10: 72.797 | W10: 47.362 | X10: 62.471 | Y10: 51.529 | Z10: 13.345 | AA10: 4.668 | AB10: 39.183 | AC10: 50.102 | AD10: 28.554 | AE10: 114.09 | AF10: 1570.638 | AG10: 22.63 | AH10: 101.817 | AI10: 18.461 | AJ10: 99.763 | AK10: 17.837 | AL10: 31471.801 | AM10: 99.323 | AN10: 46.775 | AO10: 61.488 | AP10: 123.502 | AQ10: 119.777 | AR10: 258.819 | AS10: 99.613 | AT10: 333.229 | AU10: 582.135 | AV10: 849.437 | AW10: 314.74 | AX10: 242.084 | AY10: 0 | AZ10: 58875.009 | BA10: 94.201 | BB10: 1.316 | BC10: 168.128 | BD10: 26.379 | BE10: 0 | BF10: 262.479 | BG10: 8119.898 | BH10: 0 | BI10: 131256.51
A11: DOM_C13T15 | B11: 64.374 | C11: 5.77 | D11: 102.875 | E11: 0.779 | F11: 0.235 | G11: 0.252 | H11: 8.637 | I11: 0.034 | J11: 243.527 | K11: 19216.841 | L11: 30.851 | M11: 304.11 | N11: 43.169 | O11: 764.631 | P11: 60.785 | Q11: 665.717 | R11: 161.282 | S11: 105.87 | T11: 47.908 | U11: 187.597 | V11: 319.488 | W11: 195.749 | X11: 285.355 | Y11: 1208.831 | Z11: 154.431 | AA11: 35.716 | AB11: 720.444 | AC11: 95.031 | AD11: 67.254 | AE11: 519.261 | AF11: 1401.572 | AG11: 23.638 | AH11: 25.239 | AI11: 13.709 | AJ11: 99.756 | AK11: 57.046 | AL11: 814.297 | AM11: 67.952 | AN11: 61.147 | AO11: 52.495 | AP11: 111.832 | AQ11: 190.967 | AR11: 463.648 | AS11: 296.569 | AT11: 578.686 | AU11: 293.469 | AV11: 732.823 | AW11: 324.525 | AX11: 759.089 | AY11: 0 | AZ11: 21633.878 | BA11: 22.059 | BB11: 0.006 | BC11: 1073.42 | BD11: 90.158 | BE11: 0 | BF11: 167.528 | BG11: 11322.246 | BH11: 0 | BI11: 66294.555
A12: DOM_C16 | B12: 36.229 | C12: 10.192 | D12: 5.386 | E12: 0.315 | F12: 0.037 | G12: 0.081 | H12: 2.983 | I12: 0.006 | J12: 154.832 | K12: 50.262 | L12: 1196.827 | M12: 238.841 | N12: 3.313 | O12: 192.434 | P12: 8.134 | Q12: 83.709 | R12: 120.84 | S12: 24.417 | T12: 27.056 | U12: 119.512 | V12: 85.124 | W12: 93.396 | X12: 96.55 | Y12: 255.236 | Z12: 169.62 | AA12: 9.86 | AB12: 995.48 | AC12: 56.182 | AD12: 8.662 | AE12: 3116.772 | AF12: 237.433 | AG12: 5.87 | AH12: 2.759 | AI12: 0.749 | AJ12: 52.395 | AK12: 1.839 | AL12: 123.976 | AM12: 16.909 | AN12: 5.881 | AO12: 4.888 | AP12: 8.778 | AQ12: 400.117 | AR12: 94.387 | AS12: 34.966 | AT12: 16.905 | AU12: 34.61 | AV12: 38.352 | AW12: 17.745 | AX12: 134.887 | AY12: 0 | AZ12: 178.36 | BA12: 0.252 | BB12: 0.005 | BC12: 34.397 | BD12: 1.421 | BE12: 0 | BF12: 9.433 | BG12: 124.5 | BH12: 0 | BI12: 8744.1
A13: DOM_C17_18 | B13: 66.752 | C13: 2.455 | D13: 24.406 | E13: 0.201 | F13: 0.161 | G13: 0.176 | H13: 4.715 | I13: 0.015 | J13: 2758.416 | K13: 390.263 | L13: 87.062 | M13: 9145.665 | N13: 35.847 | O13: 953.45 | P13: 289.259 | Q13: 483.944 | R13: 394.029 | S13: 91.489 | T13: 89.605 | U13: 328.865 | V13: 784.733 | W13: 448.036 | X13: 439.358 | Y13: 436.558 | Z13: 61.945 | AA13: 32.108 | AB13: 345.262 | AC13: 130.358 | AD13: 62.601 | AE13: 375.129 | AF13: 2467.089 | AG13: 32.001 | AH13: 51.766 | AI13: 9.81 | AJ13: 165.621 | AK13: 149.527 | AL13: 795.265 | AM13: 3013.991 | AN13: 282.529 | AO13: 448.85 | AP13: 1087.961 | AQ13: 218.179 | AR13: 1843.31 | AS13: 624.389 | AT13: 1002.419 | AU13: 1535.534 | AV13: 721.227 | AW13: 289.363 | AX13: 572.94 | AY13: 0 | AZ13: 1610.338 | BA13: 1.65 | BB13: 0.473 | BC13: 177.82 | BD13: 14.829 | BE13: 0 | BF13: 35.745 | BG13: 4208.812 | BH13: 0 | BI13: 39624.301
... A106: OUTPUT | B106: 45071.594 | C106: 3082.932 | D106: 7613.626 | E106: 257.663 | F106: 139.391 | G106: 119.787 | H106: 3274.283 | I106: 18.831 | J106: 131256.54 | K106: 66294.57 | L106: 8744.102 | M106: 39624.309 | N106: 156298.24 | O106: 219022.61 | P106: 32883.371 | Q106: 85333.618 | R106: 36219.597 | S106: 113509.79 | T106: 49961.975 | U106: 103590.67 | V106: 341950.93 | W106: 118568.59 | X106: 149990.61 | Y106: 216241.53 | Z106: 34342.836 | AA106: 10468.098 | AB106: 28733.736 | AC106: 106796.65 | AD106: 25019.693 | AE106: 240135.2 | AF106: 289787.2 | AG106: 41931.631 | AH106: 34657.052 | AI106: 26461.757 | AJ106: 51699.144 | AK106: 18192.044 | AL106: 146964.53 | AM106: 53469.527 | AN106: 47660.154 | AO106: 54186.568 | AP106: 170656.36 | AQ106: 201279.03 | AR106: 202235.36 | AS106: 82380.945 | AT106: 158136.92 | AU106: 115880.3 | AV106: 144675.9 | AW106: 37679.349 | AX106: 54973.27 | AY106: 2100.731 | AZ106: 0 | BA106: 0 | BB106: 0 | BC106: 0 | BD106: 0 | BE106: 0 | BF106: 0 | BG106: 0 | BH106: 0 | BI106: 4309573.2

Sheet Exiobase A Matrix
D1: Paddy rice | E1: Wheat | F1: Cereal grains nec | G1: Vegetables, fruit, nuts | H1: Oil seeds | I1: Sugar cane, sugar beet | J1: Plant-based fibers | K1: Crops nec | L1: Cattle | M1: Pigs | N1: Poultry | O1: Meat animals nec | P1: Animal products nec | Q1: Raw milk | R1: Wool, silk-worm cocoons | S1: Manure (conventional treatment) | T1: Manure (biogas treatment) | U1: Products of forestry, logging and related services (02) | V1: Fish and other fishing products; services incidental of fishing (05) | W1: Anthracite | X1: Coking Coal | Y1: Other Bituminous Coal | Z1: Sub-Bituminous Coal | AA1: Patent Fuel | AB1: Lignite/Brown Coal | AC1: BKB/Peat Briquettes | AD1: Peat | AE1: Crude petroleum and services related to crude oil extraction, excluding surveying | AF1: Natural gas and services related to natural gas extraction, excluding surveying | AG1: Natural Gas Liquids | AH1: Other Hydrocarbons | AI1: Uranium and thorium ores (12) | AJ1: Iron ores | AK1: Copper ores and concentrates | AL1: Nickel ores and concentrates | AM1: Aluminium ores and concentrates | AN1: Precious metal ores and concentrates | AO1: Lead, zinc and tin ores and concentrates | AP1: Other non-ferrous metal ores and concentrates | AQ1: Stone | AR1: Sand and clay | AS1: Chemical and fertilizer minerals, salt and other mining and quarrying products n.e.c. | AT1: Products of meat cattle | AU1: Products of meat pigs | AV1: Products of meat poultry | AW1: Meat products nec | AX1: products of Vegetable oils and fats | AY1: Dairy products | AZ1: Processed rice | BA1: Sugar | BB1: Food products nec | BC1: Beverages | BD1: Fish products | BE1: Tobacco products (16) | BF1: Textiles (17) | BG1: Wearing apparel; furs (18) | BH1: Leather and leather products (19) | BI1: Wood and products of wood and cork (except furniture); articles of straw and plaiting materials (20) | BJ1: Wood material for treatment, Re-processing of secondary wood material into new wood material | BK1: Pulp | BL1: Secondary paper for treatment, Re-processing of secondary paper into new pulp | BM1: Paper and paper products | BN1: Printed matter and recorded media (22) | BO1: Coke Oven Coke | BP1: Gas Coke | BQ1: Coal Tar | BR1: Motor Gasoline | BS1: Aviation Gasoline | BT1: Gasoline Type Jet Fuel | BU1: Kerosene Type Jet Fuel | BV1: Kerosene | BW1: Gas/Diesel Oil | BX1: Heavy Fuel Oil | BY1: Refinery Gas | BZ1: Liquefied Petroleum Gases (LPG) | CA1: Refinery Feedstocks | CB1: Ethane | CC1: Naphtha | CD1: White Spirit & SBP | CE1: Lubricants | CF1: Bitumen | CG1: Paraffin Waxes | CH1: Petroleum Coke | CI1: Non-specified Petroleum Products | CJ1: Nuclear fuel | CK1: Plastics, basic | CL1: Secondary plastic for treatment, Re-processing of secondary plastic into new plastic | CM1: N-fertiliser | CN1: P- and other fertiliser | CO1: Chemicals nec | CP1: Charcoal | CQ1: Additives/Blending Components | CR1: Biogasoline | CS1: Biodiesels | CT1: Other Liquid Biofuels | CU1: Rubber and plastic products (25) | CV1: Glass and glass products | CW1: Secondary glass for treatment, Re-processing of secondary glass into new glass | CX1: Ceramic goods | CY1: Bricks, tiles and construction products, in baked clay | CZ1: Cement, lime and plaster | DA1: Ash for treatment, Re-processing of ash into clinker | DB1: Other non-metallic mineral products | DC1: Basic iron and steel and of ferro-alloys and first products thereof | DD1: Secondary steel for treatment, Re-processing of secondary steel into new steel | DE1: Precious metals | DF1: Secondary preciuos metals for treatment, Re-processing of secondary preciuos metals into new preciuos metals | DG1: Aluminium and aluminium products | DH1: Secondary aluminium for treatment, Re-processing of secondary aluminium into new aluminium | DI1: Lead, zinc and tin and products thereof | DJ1: Secondary lead for treatment, Re-processing of secondary lead into new lead | DK1: Copper products | DL1: Secondary copper for treatment, Re-processing of secondary copper into new copper | DM1: Other non-ferrous metal products | DN1: Secondary other non-ferrous metals for treatment, Re-processing of secondary other non-ferrous metals into new other non-ferrous metals | DO1: Foundry work services | DP1: Fabricated metal products, except machinery and equipment (28) | DQ1: Machinery and equipment n.e.c. (29) | DR1: Office machinery and computers (30) | DS1: Electrical machinery and apparatus n.e.c. (31) | DT1: Radio, television and communication equipment and apparatus (32) | DU1: Medical, precision and optical instruments, watches and clocks (33) | DV1: Motor vehicles, trailers and semi-trailers (34) | DW1: Other transport equipment (35) | DX1: Furniture; other manufactured goods n.e.c. (36) | DY1: Secondary raw materials | DZ1: Bottles for treatment, Recycling of bottles by direct reuse | EA1: Electricity by coal | EB1: Electricity by gas | EC1: Electricity by nuclear | ED1: Electricity by hydro | EE1: Electricity by wind | EF1: Electricity by petroleum and other oil derivatives | EG1: Electricity by biomass and waste | EH1: Electricity by solar photovoltaic | EI1: Electricity by solar thermal | EJ1: Electricity by tide, wave, ocean | EK1: Electricity by Geothermal | EL1: Electricity nec | EM1: Transmission services of electricity | EN1: Distribution and trade services of electricity | EO1: Coke oven gas | EP1: Blast Furnace Gas | EQ1: Oxygen Steel Furnace Gas | ER1: Gas Works Gas | ES1: Biogas | ET1: Distribution services of gaseous fuels through mains | EU1: Steam and hot water supply services | EV1: Collected and purified water, distribution services of water (41) | EW1: Construction work (45) | EX1: Secondary construction material for treatment, Re-processing of secondary construction material into aggregates | EY1: Sale, maintenance, repair of motor vehicles, motor vehicles parts, motorcycles, motor cycles parts and accessoiries | EZ1: Retail trade services of motor fuel | FA1: Wholesale trade and commission trade services, except of motor vehicles and motorcycles (51) | FB1: Retail trade services, except of motor vehicles and motorcycles; repair services of personal and household goods (52) | FC1: Hotel and restaurant services (55) | FD1: Railway transportation services | FE1: Other land transportation services | FF1: Transportation services via pipelines | FG1: Sea and coastal water transportation services | FH1: Inland water transportation services | FI1: Air transport services (62) | FJ1: Supporting and auxiliary transport services; travel agency services (63) | FK1: Post and telecommunication services (64) | FL1: Financial intermediation services, except insurance and pension funding services (65) | FM1: Insurance and pension funding services, except compulsory social security services (66) | FN1: Services auxiliary to financial intermediation (67) | FO1: Real estate services (70) | FP1: Renting services of machinery and equipment without operator and of personal and household goods (71) | FQ1: Computer and related services (72) | FR1: Research and development services (73) | FS1: Other business services (74) | FT1: Public administration and defence services; compulsory social security services (75) | FU1: Education services (80) | FV1: Health and social work services (85) | FW1: Food waste for treatment: incineration | FX1: Paper waste for treatment: incineration | FY1: Plastic waste for treatment: incineration | FZ1: Intert/metal waste for treatment: incineration | GA1: Textiles waste for treatment: incineration | GB1: Wood waste for treatment: incineration | GC1: Oil/hazardous waste for treatment: incineration | GD1: Food waste for treatment: biogasification and land application | GE1: Paper waste for treatment: biogasification and land application | GF1: Sewage sludge for treatment: biogasification and land application | GG1: Food waste for treatment: composting and land application | GH1: Paper and wood waste for treatment: composting and land application | GI1: Food waste for treatment: waste water treatment | GJ1: Other waste for treatment: waste water treatment | GK1: Food waste for treatment: landfill | GL1: Paper for treatment: landfill | GM1: Plastic waste for treatment: landfill | GN1: Inert/metal/hazardous waste for treatment: landfill | GO1: Textiles waste for treatment: landfill | GP1: Wood waste for treatment: landfill | GQ1: Membership organisation services n.e.c. (91) | GR1: Recreational, cultural and sporting services (92) | GS1: Other services (93) | GT1: Private households with employed persons (95) | GU1: Extra-territorial organizations and bodies
D2: 1 | E2: 2 | F2: 3 | G2: 4 | H2: 5 | I2: 6 | J2: 7 | K2: 8 | L2: 9 | M2: 10 | N2: 11 | O2: 12 | P2: 13 | Q2: 14 | R2: 15 | S2: 16 | T2: 17 | U2: 18 | V2: 19 | W2: 20 | X2: 21 | Y2: 22 | Z2: 23 | AA2: 24 | AB2: 25 | AC2: 26 | AD2: 27 | AE2: 28 | AF2: 29 | AG2: 30 | AH2: 31 | AI2: 32 | AJ2: 33 | AK2: 34 | AL2: 35 | AM2: 36 | AN2: 37 | AO2: 38 | AP2: 39 | AQ2: 40 | AR2: 41 | AS2: 42 | AT2: 43 | AU2: 44 | AV2: 45 | AW2: 46 | AX2: 47 | AY2: 48 | AZ2: 49 | BA2: 50 | BB2: 51 | BC2: 52 | BD2: 53 | BE2: 54 | BF2: 55 | BG2: 56 | BH2: 57 | BI2: 58 | BJ2: 59 | BK2: 60 | BL2: 61 | BM2: 62 | BN2: 63 | BO2: 64 | BP2: 65 | BQ2: 66 | BR2: 67 | BS2: 68 | BT2: 69 | BU2: 70 | BV2: 71 | BW2: 72 | BX2: 73 | BY2: 74 | BZ2: 75 | CA2: 76 | CB2: 77 | CC2: 78 | CD2: 79 | CE2: 80 | CF2: 81 | CG2: 82 | CH2: 83 | CI2: 84 | CJ2: 85 | CK2: 86 | CL2: 87 | CM2: 88 | CN2: 89 | CO2: 90 | CP2: 91 | CQ2: 92 | CR2: 93 | CS2: 94 | CT2: 95 | CU2: 96 | CV2: 97 | CW2: 98 | CX2: 99 | CY2: 100 | CZ2: 101 | DA2: 102 | DB2: 103 | DC2: 104 | DD2: 105 | DE2: 106 | DF2: 107 | DG2: 108 | DH2: 109 | DI2: 110 | DJ2: 111 | DK2: 112 | DL2: 113 | DM2: 114 | DN2: 115 | DO2: 116 | DP2: 117 | DQ2: 118 | DR2: 119 | DS2: 120 | DT2: 121 | DU2: 122 | DV2: 123 | DW2: 124 | DX2: 125 | DY2: 126 | DZ2: 127 | EA2: 128 | EB2: 129 | EC2: 130 | ED2: 131 | EE2: 132 | EF2: 133 | EG2: 134 | EH2: 135 | EI2: 136 | EJ2: 137 | EK2: 138 | EL2: 139 | EM2: 140 | EN2: 141 | EO2: 142 | EP2: 143 | EQ2: 144 | ER2: 145 | ES2: 146 | ET2: 147 | EU2: 148 | EV2: 149 | EW2: 150 | EX2: 151 | EY2: 152 | EZ2: 153 | FA2: 154 | FB2: 155 | FC2: 156 | FD2: 157 | FE2: 158 | FF2: 159 | FG2: 160 | FH2: 161 | FI2: 162 | FJ2: 163 | FK2: 164 | FL2: 165 | FM2: 166 | FN2: 167 | FO2: 168 | FP2: 169 | FQ2: 170 | FR2: 171 | FS2: 172 | FT2: 173 | FU2: 174 | FV2: 175 | FW2: 176 | FX2: 177 | FY2: 178 | FZ2: 179 | GA2: 180 | GB2: 181 | GC2: 182 | GD2: 183 | GE2: 184 | GF2: 185 | GG2: 186 | GH2: 187 | GI2: 188 | GJ2: 189 | GK2: 190 | GL2: 191 | GM2: 192 | GN2: 193 | GO2: 194 | GP2: 195 | GQ2: 196 | GR2: 197 | GS2: 198 | GT2: 199 | GU2: 200
D3: ISIC 01T03 | E3: ISIC 01T03 | F3: ISIC 01T03 | G3: ISIC 01T03 | H3: ISIC 01T03 | I3: ISIC 01T03 | J3: ISIC 01T03 | K3: ISIC 01T03 | L3: ISIC 01T03 | M3: ISIC 01T03 | N3: ISIC 01T03 | O3: ISIC 01T03 | P3: ISIC 01T03 | Q3: ISIC 01T03 | R3: ISIC 01T03 | S3: ISIC 01T03 | T3: ISIC 01T03 | U3: ISIC 01T03 | V3: ISIC 01T03 | W3: ISIC 05 | X3: ISIC 05 | Y3: ISIC 05 | Z3: ISIC 05 | AA3: ISIC 05 | AB3: ISIC 05 | AC3: ISIC 05 | AD3: ISIC 05 | AE3: ISIC 06 | AF3: ISIC 06 | AG3: ISIC 06 | AH3: ISIC 06 | AI3: ISIC 07T08 | AJ3: ISIC 07T08 | AK3: ISIC 07T08 | AL3: ISIC 07T08 | AM3: ISIC 07T08 | AN3: ISIC 07T08 | AO3: ISIC 07T08 | AP3: ISIC 07T08 | AQ3: ISIC 07T08 | AR3: ISIC 07T08 | AS3: ISIC 07T08 | AT3: ISIC 10T12 | AU3: ISIC 10T12 | AV3: ISIC 10T12 | AW3: ISIC 10T12 | AX3: ISIC 10T12 | AY3: ISIC 10T12 | AZ3: ISIC 10T12 | BA3: ISIC 10T12 | BB3: ISIC 10T12 | BC3: ISIC 10T12 | BD3: ISIC 10T12 | BE3: ISIC 10T12 | BF3: ISIC 13T15 | BG3: ISIC 13T15 | BH3: ISIC 13T15 | BI3: ISIC 16 | BJ3: ISIC 16 | BK3: ISIC 17T18 | BL3: ISIC 17T18 | BM3: ISIC 17T18 | BN3: ISIC 17T18 | BO3: ISIC 19 | BP3: ISIC 19 | BQ3: ISIC 19 | BR3: ISIC 19 | BS3: ISIC 19 | BT3: ISIC 19 | BU3: ISIC 19 | BV3: ISIC 19 | BW3: ISIC 19 | BX3: ISIC 19 | BY3: ISIC 19 | BZ3: ISIC 19 | CA3: ISIC 19 | CB3: ISIC 19 | CC3: ISIC 19 | CD3: ISIC 19 | CE3: ISIC 19 | CF3: ISIC 19 | CG3: ISIC 19 | CH3: ISIC 19 | CI3: ISIC 19 | CJ3: ISIC 20 | CK3: ISIC 20 | CL3: ISIC 20 | CM3: ISIC 20 | CN3: ISIC 20 | CO3: ISIC 20 | CP3: ISIC 20 | CQ3: ISIC 20 | CR3: ISIC 19 | CS3: ISIC 19 | CT3: ISIC 19 | CU3: ISIC 22 | CV3: ISIC 231 | CW3: ISIC 231 | CX3: ISIC 239 | CY3: ISIC 239 | CZ3: ISIC 239 | DA3: ISIC 239 | DB3: ISIC 239 | DC3: ISIC 241 | DD3: ISIC 241 | DE3: ISIC 242 | DF3: ISIC 242 | DG3: ISIC 242 | DH3: ISIC 242 | DI3: ISIC 242 | DJ3: ISIC 242 | DK3: ISIC 242 | DL3: ISIC 242 | DM3: ISIC 242 | DN3: ISIC 242 | DO3: ISIC 242 | DP3: ISIC 25 | DQ3: ISIC 28 | DR3: ISIC 26 | DS3: ISIC 27 | DT3: ISIC 26 | DU3: ISIC 26 | DV3: ISIC 29 | DW3: ISIC 30 | DX3: ISIC 31T33 | DY3: ISIC 36T39 | DZ3: ISIC 36T39 | EA3: ISIC 351 | EB3: ISIC 351 | EC3: ISIC 351 | ED3: ISIC 351 | EE3: ISIC 351 | EF3: ISIC 351 | EG3: ISIC 351 | EH3: ISIC 351 | EI3: ISIC 351 | EJ3: ISIC 351 | EK3: ISIC 351 | EL3: ISIC 351 | EM3: ISIC 351 | EN3: ISIC 351 | EO3: ISIC 352T353 | EP3: ISIC 352T353 | EQ3: ISIC 352T353 | ER3: ISIC 352T353 | ES3: ISIC 352T353 | ET3: ISIC 352T353 | EU3: ISIC 36T39 | EV3: ISIC 36T39 | EW3: ISIC 41T43 | EX3: ISIC 41T43 | EY3: ISIC 45T47 | EZ3: ISIC 45T47 | FA3: ISIC 45T47 | FB3: ISIC 45T47 | FC3: ISIC 55T56 | FD3: ISIC 49T53 | FE3: ISIC 49T53 | FF3: ISIC 49T53 | FG3: ISIC 49T53 | FH3: ISIC 49T53 | FI3: ISIC 49T53 | FJ3: ISIC 49T53 | FK3: ISIC 61 | FL3: ISIC 64T66 | FM3: ISIC 64T66 | FN3: ISIC 64T66 | FO3: ISIC 68 | FP3: ISIC 69T82 | FQ3: ISIC 62T63 | FR3: ISIC 69T82 | FS3: ISIC 69T82 | FT3: ISIC 84 | FU3: ISIC 85 | FV3: ISIC 86T88 | FW3: ISIC 36T39 | FX3: ISIC 36T39 | FY3: ISIC 36T39 | FZ3: ISIC 36T39 | GA3: ISIC 36T39 | GB3: ISIC 36T39 | GC3: ISIC 36T39 | GD3: ISIC 36T39 | GE3: ISIC 36T39 | GF3: ISIC 36T39 | GG3: ISIC 36T39 | GH3: ISIC 36T39 | GI3: ISIC 36T39 | GJ3: ISIC 36T39 | GK3: ISIC 36T39 | GL3: ISIC 36T39 | GM3: ISIC 36T39 | GN3: ISIC 36T39 | GO3: ISIC 36T39 | GP3: ISIC 36T39 | GQ3: ISIC 90T96 | GR3: ISIC 90T96 | GS3: ISIC 90T96 | GT3: ISIC 97T98
A4: Paddy rice | B4: 1 | C4: ISIC 01T03 | D4: 0.23182364 | E4: 0 | F4: 0 | G4: 0 | H4: 0 | I4: 0 | J4: 0 | K4: 0 | L4: 0.003953085 | M4: 0.027659502 | N4: 0.056230309 | O4: 0.0018384108 | P4: 0.011277273 | Q4: 0.0068097128 | R4: 0 | S4: 0 | T4: 0 | U4: 0.00027364625 | V4: 7.7441152e-05 | W4: 0 | X4: 0 | Y4: 0 | Z4: 0 | AA4: 0 | AB4: 0 | AC4: 0 | AD4: 0 | AE4: 0 | AF4: 0 | AG4: 0 | AH4: 0 | AI4: 0 | AJ4: 0 | AK4: 0 | AL4: 0 | AM4: 0 | AN4: 0 | AO4: 0 | AP4: 0 | AQ4: 0 | AR4: 0 | AS4: 0 | AT4: 0 | AU4: 0 | AV4: 0 | AW4: 0 | AX4: 0 | AY4: 0 | AZ4: 0.58299411 | BA4: 0 | BB4: 0.15571364 | BC4: 0 | BD4: 0 | BE4: 0.0035626798 | BF4: 0.00015038442 | BG4: 5.6430352e-06 | BH4: 0.00048221545 | BI4: 0 | BJ4: 0 | BK4: 0 | BL4: 0 | BM4: 0 | BN4: 0 | BO4: 0 | BP4: 0 | BQ4: 0 | BR4: 0 | BS4: 0 | BT4: 0 | BU4: 0 | BV4: 0 | BW4: 0 | BX4: 0 | BY4: 0 | BZ4: 0 | CA4: 0 | CB4: 0 | CC4: 0 | CD4: 0 | CE4: 0 | CF4: 0 | CG4: 0 | CH4: 0 | CI4: 0 | CJ4: 0 | CK4: 0 | CL4: 0 | CM4: 0 | CN4: 0 | CO4: 0.0044366098 | CP4: 0 | CQ4: 0.0044366098 | CR4: 0 | CS4: 0.0044366098 | CT4: 0 | CU4: 0 | CV4: 0 | CW4: 0 | CX4: 0 | CY4: 0 | CZ4: 0 | DA4: 0 | DB4: 0 | DC4: 0 | DD4: 0 | DE4: 0 | DF4: 0 | DG4: 0 | DH4: 0 | DI4: 0 | DJ4: 0 | DK4: 0 | DL4: 0 | DM4: 0 | DN4: 0 | DO4: 0 | DP4: 0 | DQ4: 0 | DR4: 0 | DS4: 0 | DT4: 0 | DU4: 0 | DV4: 0 | DW4: 0 | DX4: 0 | DY4: 0 | DZ4: 0 | EA4: 0 | EB4: 0 | EC4: 0 | ED4: 0 | EE4: 0 | EF4: 0 | EG4: 0 | EH4: 0 | EI4: 0 | EJ4: 0 | EK4: 0 | EL4: 0 | EM4: 0 | EN4: 0 | EO4: 0 | EP4: 0 | EQ4: 0 | ER4: 0 | ES4: 0 | ET4: 0 | EU4: 0 | EV4: 0 | EW4: 0 | EX4: 0 | EY4: 0 | EZ4: 0 | FA4: 0 | FB4: 0 | FC4: 0.00016741682 | FD4: 0 | FE4: 0 | FF4: 0 | FG4: 0 | FH4: 0 | FI4: 0 | FJ4: 0 | FK4: 0 | FL4: 0 | FM4: 0 | FN4: 0 | FO4: 0 | FP4: 0 | FQ4: 0 | FR4: 0 | FS4: 0 | FT4: 3.9339592e-05 | FU4: 0 | FV4: 0.00040730654 | FW4: 0 | FX4: 0 | FY4: 0 | FZ4: 0 | GA4: 0 | GB4: 0 | GC4: 0 | GD4: 0 | GE4: 0 | GF4: 0 | GG4: 0 | GH4: 0 | GI4: 0 | GJ4: 0 | GK4: 0 | GL4: 0 | GM4: 0 | GN4: 0 | GO4: 0 | GP4: 0 | GQ4: 0 | GR4: 1.2806122e-05 | GS4: 0.00021975732 | GT4: 1.5489169e-05 | GU4: 0
A5: Wheat | B5: 2 | C5: ISIC 01T03 | D5: 0 | E5: 0.0052183943 | F5: 0.00050671251 | G5: 0 | H5: 0 | I5: 0 | J5: 0 | K5: 0 | L5: 0.00013911969 | M5: 1.7403321e-05 | N5: 1.5168723e-06 | O5: 8.2462747e-05 | P5: 0.00018915068 | Q5: 2.652729e-05 | R5: 0 | S5: 0 | T5: 0 | U5: 0 | V5: 0 | W5: 0 | X5: 0 | Y5: 0 | Z5: 0 | AA5: 0 | AB5: 0 | AC5: 0 | AD5: 0 | AE5: 0 | AF5: 0 | AG5: 0 | AH5: 0 | AI5: 0 | AJ5: 0 | AK5: 0 | AL5: 0 | AM5: 0 | AN5: 0 | AO5: 0 | AP5: 0 | AQ5: 0 | AR5: 0 | AS5: 0 | AT5: 0 | AU5: 0 | AV5: 0 | AW5: 0 | AX5: 0 | AY5: 0 | AZ5: 0 | BA5: 0 | BB5: 0.00065555338 | BC5: 0 | BD5: 0 | BE5: 0 | BF5: 0 | BG5: 0 | BH5: 0 | BI5: 0 | BJ5: 0 | BK5: 0 | BL5: 0 | BM5: 0 | BN5: 0 | BO5: 0 | BP5: 0 | BQ5: 0 | BR5: 0 | BS5: 0 | BT5: 0 | BU5: 0 | BV5: 0 | BW5: 0 | BX5: 0 | BY5: 0 | BZ5: 0 | CA5: 0 | CB5: 0 | CC5: 0 | CD5: 0 | CE5: 0 | CF5: 0 | CG5: 0 | CH5: 0 | CI5: 0 | CJ5: 0 | CK5: 0 | CL5: 0 | CM5: 0 | CN5: 0 | CO5: 0 | CP5: 0 | CQ5: 0 | CR5: 0 | CS5: 0 | CT5: 0 | CU5: 0 | CV5: 0 | CW5: 0 | CX5: 0 | CY5: 0 | CZ5: 0 | DA5: 0 | DB5: 0 | DC5: 0 | DD5: 0 | DE5: 0 | DF5: 0 | DG5: 0 | DH5: 0 | DI5: 0 | DJ5: 0 | DK5: 0 | DL5: 0 | DM5: 0 | DN5: 0 | DO5: 0 | DP5: 0 | DQ5: 0 | DR5: 0 | DS5: 0 | DT5: 0 | DU5: 0 | DV5: 0 | DW5: 0 | DX5: 0 | DY5: 0 | DZ5: 0 | EA5: 0 | EB5: 0 | EC5: 0 | ED5: 0 | EE5: 0 | EF5: 0 | EG5: 0 | EH5: 0 | EI5: 0 | EJ5: 0 | EK5: 0 | EL5: 0 | EM5: 0 | EN5: 0 | EO5: 0 | EP5: 0 | EQ5: 0 | ER5: 0 | ES5: 0 | ET5: 0 | EU5: 0 | EV5: 0 | EW5: 0 | EX5: 0 | EY5: 0 | EZ5: 0 | FA5: 0 | FB5: 0 | FC5: 0 | FD5: 0 | FE5: 0 | FF5: 0 | FG5: 0 | FH5: 0 | FI5: 0 | FJ5: 0 | FK5: 0 | FL5: 0 | FM5: 0 | FN5: 0 | FO5: 0 | FP5: 0 | FQ5: 0 | FR5: 0 | FS5: 0 | FT5: 0 | FU5: 0 | FV5: 0 | FW5: 0 | FX5: 0 | FY5: 0 | FZ5: 0 | GA5: 0 | GB5: 0 | GC5: 0 | GD5: 0 | GE5: 0 | GF5: 0 | GG5: 0 | GH5: 0 | GI5: 0 | GJ5: 0 | GK5: 0 | GL5: 0 | GM5: 0 | GN5: 0 | GO5: 0 | GP5: 0 | GQ5: 0 | GR5: 0 | GS5: 0 | GT5: 2.6828377e-06 | GU5: 0
A6: Cereal grains nec | B6: 3 | C6: ISIC 01T03 | D6: 0 | E6: 0 | F6: 0.0018664804 | G6: 0 | H6: 0 | I6: 0 | J6: 0 | K6: 0 | L6: 0.0001414954 | M6: 6.4789565e-05 | N6: 4.1146023e-05 | O6: 0.00061527757 | P6: 0.00053194016 | Q6: 0.0014515228 | R6: 0 | S6: 0 | T6: 0 | U6: 0 | V6: 0 | W6: 0 | X6: 0 | Y6: 0 | Z6: 0 | AA6: 0 | AB6: 0 | AC6: 0 | AD6: 0 | AE6: 0 | AF6: 0 | AG6: 0 | AH6: 0 | AI6: 0 | AJ6: 0 | AK6: 0 | AL6: 0 | AM6: 0 | AN6: 0 | AO6: 0 | AP6: 0 | AQ6: 0 | AR6: 0 | AS6: 0 | AT6: 0 | AU6: 0 | AV6: 0 | AW6: 0 | AX6: 0 | AY6: 0 | AZ6: 0 | BA6: 0 | BB6: 0.0026589592 | BC6: 0 | BD6: 0 | BE6: 0 | BF6: 0 | BG6: 0 | BH6: 0 | BI6: 0 | BJ6: 0 | BK6: 0 | BL6: 0 | BM6: 0 | BN6: 0 | BO6: 0 | BP6: 0 | BQ6: 0 | BR6: 0 | BS6: 0 | BT6: 0 | BU6: 0 | BV6: 0 | BW6: 0 | BX6: 0 | BY6: 0 | BZ6: 0 | CA6: 0 | CB6: 0 | CC6: 0 | CD6: 0 | CE6: 0 | CF6: 0 | CG6: 0 | CH6: 0 | CI6: 0 | CJ6: 0 | CK6: 0 | CL6: 0 | CM6: 0 | CN6: 0 | CO6: 4.5296209e-07 | CP6: 0 | CQ6: 4.5296209e-07 | CR6: 0 | CS6: 4.5296209e-07 | CT6: 0 | CU6: 0 | CV6: 0 | CW6: 0 | CX6: 0 | CY6: 0 | CZ6: 0 | DA6: 0 | DB6: 0 | DC6: 0 | DD6: 0 | DE6: 0 | DF6: 0 | DG6: 0 | DH6: 0 | DI6: 0 | DJ6: 0 | DK6: 0 | DL6: 0 | DM6: 0 | DN6: 0 | DO6: 0 | DP6: 0 | DQ6: 0 | DR6: 0 | DS6: 0 | DT6: 0 | DU6: 0 | DV6: 0 | DW6: 0 | DX6: 0 | DY6: 0 | DZ6: 0 | EA6: 0 | EB6: 0 | EC6: 0 | ED6: 0 | EE6: 0 | EF6: 0 | EG6: 0 | EH6: 0 | EI6: 0 | EJ6: 0 | EK6: 0 | EL6: 0 | EM6: 0 | EN6: 0 | EO6: 0 | EP6: 0 | EQ6: 0 | ER6: 0 | ES6: 0 | ET6: 0 | EU6: 0 | EV6: 0 | EW6: 0 | EX6: 0 | EY6: 0 | EZ6: 0 | FA6: 0 | FB6: 0 | FC6: 0 | FD6: 0 | FE6: 0 | FF6: 0 | FG6: 0 | FH6: 0 | FI6: 0 | FJ6: 0 | FK6: 0 | FL6: 0 | FM6: 0 | FN6: 0 | FO6: 0 | FP6: 0 | FQ6: 0 | FR6: 0 | FS6: 0 | FT6: 0 | FU6: 0 | FV6: 0 | FW6: 0 | FX6: 0 | FY6: 0 | FZ6: 0 | GA6: 0 | GB6: 0 | GC6: 0 | GD6: 0 | GE6: 0 | GF6: 0 | GG6: 0 | GH6: 0 | GI6: 0 | GJ6: 0 | GK6: 0 | GL6: 0 | GM6: 0 | GN6: 0 | GO6: 0 | GP6: 0 | GQ6: 0 | GR6: 4.9401846e-06 | GS6: 0 | GT6: 1.023745e-06 | GU6: 0
A7: Vegetables, fruit, nuts | B7: 4 | C7: ISIC 01T03 | D7: 0 | E7: 0 | F7: 0 | G7: 0.0017739543 | H7: 0 | I7: 0 | J7: 0 | K7: 0 | L7: 2.547094e-06 | M7: 4.9805315e-06 | N7: 2.2296592e-06 | O7: 5.3621191e-06 | P7: 2.0269611e-05 | Q7: 2.1698111e-06 | R7: 0 | S7: 0 | T7: 0 | U7: 0.0012003473 | V7: 0.00017569563 | W7: 0 | X7: 0 | Y7: 0 | Z7: 0 | AA7: 0 | AB7: 0 | AC7: 0 | AD7: 0 | AE7: 0 | AF7: 0 | AG7: 0 | AH7: 0 | AI7: 0 | AJ7: 0 | AK7: 0 | AL7: 0 | AM7: 0 | AN7: 0 | AO7: 0 | AP7: 0 | AQ7: 0 | AR7: 0 | AS7: 0 | AT7: 0 | AU7: 6.0351638e-08 | AV7: 3.7058064e-08 | AW7: 4.1839233e-06 | AX7: 0 | AY7: 0.012190316 | AZ7: 0 | BA7: 5.3307018e-07 | BB7: 0.028746545 | BC7: 0.0065662487 | BD7: 0.0002920653 | BE7: 2.0112508e-08 | BF7: 0.00035293316 | BG7: 7.3527628e-06 | BH7: 0.00079231063 | BI7: 0 | BJ7: 0 | BK7: 0 | BL7: 0 | BM7: 0 | BN7: 0 | BO7: 0 | BP7: 0 | BQ7: 0 | BR7: 0 | BS7: 0 | BT7: 0 | BU7: 0 | BV7: 0 | BW7: 0 | BX7: 0 | BY7: 0 | BZ7: 0 | CA7: 0 | CB7: 0 | CC7: 0 | CD7: 0 | CE7: 0 | CF7: 0 | CG7: 0 | CH7: 0 | CI7: 0 | CJ7: 0 | CK7: 0 | CL7: 0 | CM7: 0 | CN7: 0 | CO7: 4.3544805e-07 | CP7: 0 | CQ7: 4.3544805e-07 | CR7: 0 | CS7: 4.3544805e-07 | CT7: 0 | CU7: 0 | CV7: 0 | CW7: 0 | CX7: 0 | CY7: 0 | CZ7: 0 | DA7: 0 | DB7: 0 | DC7: 0 | DD7: 0 | DE7: 0 | DF7: 0 | DG7: 0 | DH7: 0 | DI7: 0 | DJ7: 0 | DK7: 0 | DL7: 0 | DM7: 0 | DN7: 0 | DO7: 0 | DP7: 0 | DQ7: 0 | DR7: 0 | DS7: 0 | DT7: 0 | DU7: 0 | DV7: 2.9887743e-05 | DW7: 0 | DX7: 0 | DY7: 6.1342215e-09 | DZ7: 0 | EA7: 0 | EB7: 0 | EC7: 0 | ED7: 0 | EE7: 0 | EF7: 0 | EG7: 0 | EH7: 0 | EI7: 0 | EJ7: 0 | EK7: 0 | EL7: 0 | EM7: 0 | EN7: 0 | EO7: 0 | EP7: 0 | EQ7: 0 | ER7: 0 | ES7: 0 | ET7: 0 | EU7: 0 | EV7: 0 | EW7: 0.0011229201 | EX7: 0 | EY7: 0 | EZ7: 0 | FA7: 0 | FB7: 0 | FC7: 0.015674925 | FD7: 0 | FE7: 0 | FF7: 0 | FG7: 0 | FH7: 0 | FI7: 0 | FJ7: 0 | FK7: 0 | FL7: 0 | FM7: 0 | FN7: 0 | FO7: 0 | FP7: 0 | FQ7: 0 | FR7: 4.0778299e-05 | FS7: 0 | FT7: 0.0013038992 | FU7: 1.4502995e-05 | FV7: 0.0045676496 | FW7: 0 | FX7: 0 | FY7: 0 | FZ7: 0 | GA7: 0 | GB7: 0 | GC7: 0 | GD7: 0 | GE7: 0 | GF7: 0 | GG7: 0 | GH7: 0 | GI7: 0 | GJ7: 0 | GK7: 0 | GL7: 0 | GM7: 0 | GN7: 0 | GO7: 0 | GP7: 0 | GQ7: 0 | GR7: 0.00021544884 | GS7: 0.0062699425 | GT7: 0.001198599 | GU7: 0
A8: Oil seeds | B8: 5 | C8: ISIC 01T03 | D8: 0 | E8: 0 | F8: 0 | G8: 0 | H8: 0.0055348157 | I8: 0 | J8: 0 | K8: 0 | L8: 8.9929215e-06 | M8: 3.5725974e-06 | N8: 1.7244841e-06 | O8: 6.8897357e-06 | P8: 7.6761008e-05 | Q8: 5.9976581e-05 | R8: 0 | S8: 0 | T8: 0 | U8: 0.00012584768 | V8: 2.5045149e-05 | W8: 0 | X8: 0 | Y8: 0 | Z8: 0 | AA8: 0 | AB8: 0 | AC8: 0 | AD8: 0 | AE8: 0 | AF8: 0 | AG8: 0 | AH8: 0 | AI8: 0 | AJ8: 0 | AK8: 0 | AL8: 0 | AM8: 0 | AN8: 0 | AO8: 0 | AP8: 0 | AQ8: 0 | AR8: 0 | AS8: 0 | AT8: 0 | AU8: 0 | AV8: 0 | AW8: 0 | AX8: 0.03995944 | AY8: 0 | AZ8: 0 | BA8: 0 | BB8: 0.0063394051 | BC8: 4.0773568e-08 | BD8: 3.8815669e-05 | BE8: 2.2174154e-08 | BF8: 2.3352958e-05 | BG8: 4.8668032e-07 | BH8: 5.2839224e-05 | BI8: 0 | BJ8: 0 | BK8: 0 | BL8: 0 | BM8: 0 | BN8: 0 | BO8: 0 | BP8: 0 | BQ8: 0 | BR8: 0 | BS8: 0 | BT8: 0 | BU8: 0 | BV8: 0 | BW8: 0 | BX8: 0 | BY8: 0 | BZ8: 0 | CA8: 0 | CB8: 0 | CC8: 0 | CD8: 0 | CE8: 0 | CF8: 0 | CG8: 0 | CH8: 0 | CI8: 0 | CJ8: 0 | CK8: 0 | CL8: 0 | CM8: 0 | CN8: 0 | CO8: 5.7892723e-08 | CP8: 0 | CQ8: 5.7892723e-08 | CR8: 0 | CS8: 5.7892723e-08 | CT8: 0 | CU8: 0 | CV8: 0 | CW8: 0 | CX8: 0 | CY8: 0 | CZ8: 0 | DA8: 0 | DB8: 0 | DC8: 0 | DD8: 0 | DE8: 0 | DF8: 0 | DG8: 0 | DH8: 0 | DI8: 0 | DJ8: 0 | DK8: 0 | DL8: 0 | DM8: 0 | DN8: 0 | DO8: 0 | DP8: 0 | DQ8: 0 | DR8: 0 | DS8: 0 | DT8: 0 | DU8: 0 | DV8: 2.7003735e-06 | DW8: 0 | DX8: 0 | DY8: 0 | DZ8: 0 | EA8: 0 | EB8: 0 | EC8: 0 | ED8: 0 | EE8: 0 | EF8: 0 | EG8: 0 | EH8: 0 | EI8: 0 | EJ8: 0 | EK8: 0 | EL8: 0 | EM8: 0 | EN8: 0 | EO8: 0 | EP8: 0 | EQ8: 0 | ER8: 0 | ES8: 0 | ET8: 0 | EU8: 0 | EV8: 0 | EW8: 0.00014971366 | EX8: 0 | EY8: 0 | EZ8: 0 | FA8: 0 | FB8: 0 | FC8: 0.0017647672 | FD8: 0 | FE8: 0 | FF8: 0 | FG8: 0 | FH8: 0 | FI8: 0 | FJ8: 0 | FK8: 0 | FL8: 0 | FM8: 0 | FN8: 0 | FO8: 0 | FP8: 0 | FQ8: 0 | FR8: 4.1425095e-06 | FS8: 0 | FT8: 0.00012718721 | FU8: 1.0098827e-06 | FV8: 0.00044354877 | FW8: 0 | FX8: 0 | FY8: 0 | FZ8: 0 | GA8: 0 | GB8: 0 | GC8: 0 | GD8: 0 | GE8: 0 | GF8: 0 | GG8: 0 | GH8: 0 | GI8: 0 | GJ8: 0 | GK8: 0 | GL8: 0 | GM8: 0 | GN8: 0 | GO8: 0 | GP8: 0 | GQ8: 0 | GR8: 2.1169093e-05 | GS8: 0.00060983684 | GT8: 3.3893709e-07 | GU8: 0
A9: Sugar cane, sugar beet | B9: 6 | C9: ISIC 01T03 | D9: 0 | E9: 0 | F9: 0 | G9: 0 | H9: 0 | I9: 0 | J9: 0 | K9: 0 | L9: 0 | M9: 0 | N9: 0 | O9: 0 | P9: 0 | Q9: 0 | R9: 0 | S9: 0 | T9: 0 | U9: 0 | V9: 0 | W9: 0 | X9: 0 | Y9: 0 | Z9: 0 | AA9: 0 | AB9: 0 | AC9: 0 | AD9: 0 | AE9: 0 | AF9: 0 | AG9: 0 | AH9: 0 | AI9: 0 | AJ9: 0 | AK9: 0 | AL9: 0 | AM9: 0 | AN9: 0 | AO9: 0 | AP9: 0 | AQ9: 0 | AR9: 0 | AS9: 0 | AT9: 0 | AU9: 0 | AV9: 0 | AW9: 0 | AX9: 0 | AY9: 0 | AZ9: 0 | BA9: 0 | BB9: 0 | BC9: 0 | BD9: 0 | BE9: 0 | BF9: 0 | BG9: 0 | BH9: 0 | BI9: 0 | BJ9: 0 | BK9: 0 | BL9: 0 | BM9: 0 | BN9: 0 | BO9: 0 | BP9: 0 | BQ9: 0 | BR9: 0 | BS9: 0 | BT9: 0 | BU9: 0 | BV9: 0 | BW9: 0 | BX9: 0 | BY9: 0 | BZ9: 0 | CA9: 0 | CB9: 0 | CC9: 0 | CD9: 0 | CE9: 0 | CF9: 0 | CG9: 0 | CH9: 0 | CI9: 0 | CJ9: 0 | CK9: 0 | CL9: 0 | CM9: 0 | CN9: 0 | CO9: 0 | CP9: 0 | CQ9: 0 | CR9: 0 | CS9: 0 | CT9: 0 | CU9: 0 | CV9: 0 | CW9: 0 | CX9: 0 | CY9: 0 | CZ9: 0 | DA9: 0 | DB9: 0 | DC9: 0 | DD9: 0 | DE9: 0 | DF9: 0 | DG9: 0 | DH9: 0 | DI9: 0 | DJ9: 0 | DK9: 0 | DL9: 0 | DM9: 0 | DN9: 0 | DO9: 0 | DP9: 0 | DQ9: 0 | DR9: 0 | DS9: 0 | DT9: 0 | DU9: 0 | DV9: 0 | DW9: 0 | DX9: 0 | DY9: 0 | DZ9: 0 | EA9: 0 | EB9: 0 | EC9: 0 | ED9: 0 | EE9: 0 | EF9: 0 | EG9: 0 | EH9: 0 | EI9: 0 | EJ9: 0 | EK9: 0 | EL9: 0 | EM9: 0 | EN9: 0 | EO9: 0 | EP9: 0 | EQ9: 0 | ER9: 0 | ES9: 0 | ET9: 0 | EU9: 0 | EV9: 0 | EW9: 0 | EX9: 0 | EY9: 0 | EZ9: 0 | FA9: 0 | FB9: 0 | FC9: 0 | FD9: 0 | FE9: 0 | FF9: 0 | FG9: 0 | FH9: 0 | FI9: 0 | FJ9: 0 | FK9: 0 | FL9: 0 | FM9: 0 | FN9: 0 | FO9: 0 | FP9: 0 | FQ9: 0 | FR9: 0 | FS9: 0 | FT9: 0 | FU9: 0 | FV9: 0 | FW9: 0 | FX9: 0 | FY9: 0 | FZ9: 0 | GA9: 0 | GB9: 0 | GC9: 0 | GD9: 0 | GE9: 0 | GF9: 0 | GG9: 0 | GH9: 0 | GI9: 0 | GJ9: 0 | GK9: 0 | GL9: 0 | GM9: 0 | GN9: 0 | GO9: 0 | GP9: 0 | GQ9: 0 | GR9: 0 | GS9: 0 | GT9: 0 | GU9: 0
A10: Plant-based fibers | B10: 7 | C10: ISIC 01T03 | D10: 0 | E10: 0 | F10: 0 | G10: 0 | H10: 0 | I10: 0 | J10: 0.00041501825 | K10: 0 | L10: 1.7326237e-09 | M10: 0 | N10: 3.2231651e-09 | O10: 0 | P10: 0 | Q10: 0 | R10: 0 | S10: 0 | T10: 0 | U10: 0 | V10: 4.3902864e-09 | W10: 0 | X10: 0 | Y10: 0 | Z10: 0 | AA10: 0 | AB10: 0 | AC10: 0 | AD10: 0 | AE10: 0 | AF10: 0 | AG10: 0 | AH10: 0 | AI10: 0 | AJ10: 0 | AK10: 0 | AL10: 0 | AM10: 0 | AN10: 0 | AO10: 0 | AP10: 0 | AQ10: 0 | AR10: 0 | AS10: 0 | AT10: 0 | AU10: 0 | AV10: 0 | AW10: 0 | AX10: 0 | AY10: 0 | AZ10: 0 | BA10: 0 | BB10: 2.0617203e-10 | BC10: 1.1125463e-09 | BD10: 1.7672933e-09 | BE10: 0 | BF10: 0 | BG10: 0 | BH10: 0 | BI10: 0 | BJ10: 0 | BK10: 0 | BL10: 0 | BM10: 0 | BN10: 0 | BO10: 0 | BP10: 0 | BQ10: 0 | BR10: 0 | BS10: 0 | BT10: 0 | BU10: 0 | BV10: 0 | BW10: 0 | BX10: 0 | BY10: 0 | BZ10: 0 | CA10: 0 | CB10: 0 | CC10: 0 | CD10: 0 | CE10: 0 | CF10: 0 | CG10: 0 | CH10: 0 | CI10: 0 | CJ10: 0 | CK10: 0 | CL10: 0 | CM10: 0 | CN10: 0 | CO10: 1.0325864e-10 | CP10: 0 | CQ10: 1.0325864e-10 | CR10: 0 | CS10: 1.0325864e-10 | CT10: 0 | CU10: 0 | CV10: 0 | CW10: 0 | CX10: 0 | CY10: 0 | CZ10: 0 | DA10: 0 | DB10: 0 | DC10: 0 | DD10: 0 | DE10: 0 | DF10: 0 | DG10: 0 | DH10: 0 | DI10: 0 | DJ10: 0 | DK10: 0 | DL10: 0 | DM10: 0 | DN10: 0 | DO10: 0 | DP10: 0 | DQ10: 0 | DR10: 0 | DS10: 0 | DT10: 0 | DU10: 0 | DV10: 0 | DW10: 0 | DX10: 0 | DY10: 0 | DZ10: 0 | EA10: 0 | EB10: 0 | EC10: 0 | ED10: 0 | EE10: 0 | EF10: 0 | EG10: 0 | EH10: 0 | EI10: 0 | EJ10: 0 | EK10: 0 | EL10: 0 | EM10: 0 | EN10: 0 | EO10: 0 | EP10: 0 | EQ10: 0 | ER10: 0 | ES10: 0 | ET10: 0 | EU10: 0 | EV10: 0 | EW10: 8.076256e-11 | EX10: 0 | EY10: 0 | EZ10: 0 | FA10: 0 | FB10: 0 | FC10: 9.8993272e-11 | FD10: 0 | FE10: 0 | FF10: 0 | FG10: 0 | FH10: 0 | FI10: 0 | FJ10: 0 | FK10: 0 | FL10: 0 | FM10: 0 | FN10: 0 | FO10: 0 | FP10: 0 | FQ10: 0 | FR10: 0 | FS10: 0 | FT10: 1.1825133e-10 | FU10: 0 | FV10: 1.7142832e-10 | FW10: 0 | FX10: 0 | FY10: 0 | FZ10: 0 | GA10: 0 | GB10: 0 | GC10: 0 | GD10: 0 | GE10: 0 | GF10: 0 | GG10: 0 | GH10: 0 | GI10: 0 | GJ10: 0 | GK10: 0 | GL10: 0 | GM10: 0 | GN10: 0 | GO10: 0 | GP10: 0 | GQ10: 0 | GR10: 2.5151947e-10 | GS10: 1.9886551e-10 | GT10: 5.8867154e-09 | GU10: 0
A11: Crops nec | B11: 8 | C11: ISIC 01T03 | D11: 0 | E11: 0 | F11: 0 | G11: 0 | H11: 0 | I11: 0 | J11: 0 | K11: 0.00020893629 | L11: 3.379523e-09 | M11: 4.9048161e-09 | N11: 6.3296258e-09 | O11: 3.1297911e-07 | P11: 8.5769631e-07 | Q11: 2.7241877e-08 | R11: 0.00012856897 | S11: 0 | T11: 0 | U11: 5.5381899e-08 | V11: 1.8274002e-08 | W11: 0 | X11: 0 | Y11: 0 | Z11: 0 | AA11: 0 | AB11: 0 | AC11: 0 | AD11: 0 | AE11: 0 | AF11: 0 | AG11: 0 | AH11: 0 | AI11: 0 | AJ11: 0 | AK11: 0 | AL11: 0 | AM11: 0 | AN11: 0 | AO11: 0 | AP11: 0 | AQ11: 0 | AR11: 0 | AS11: 0 | AT11: 0 | AU11: 4.4798101e-09 | AV11: 0 | AW11: 3.1279557e-07 | AX11: 0 | AY11: 5.3513743e-09 | AZ11: 0 | BA11: 0 | BB11: 0 | BC11: 0 | BD11: 4.5937232e-09 | BE11: 0 | BF11: 0 | BG11: 0 | BH11: 0 | BI11: 0 | BJ11: 0 | BK11: 0 | BL11: 0 | BM11: 0 | BN11: 0 | BO11: 0 | BP11: 0 | BQ11: 0 | BR11: 0 | BS11: 0 | BT11: 0 | BU11: 0 | BV11: 0 | BW11: 0 | BX11: 0 | BY11: 0 | BZ11: 0 | CA11: 0 | CB11: 0 | CC11: 0 | CD11: 0 | CE11: 0 | CF11: 0 | CG11: 0 | CH11: 0 | CI11: 0 | CJ11: 0 | CK11: 0 | CL11: 0 | CM11: 0 | CN11: 0 | CO11: 3.4677319e-10 | CP11: 0 | CQ11: 3.4677319e-10 | CR11: 0 | CS11: 3.4677319e-10 | CT11: 0 | CU11: 0 | CV11: 0 | CW11: 0 | CX11: 0 | CY11: 0 | CZ11: 0 | DA11: 0 | DB11: 0 | DC11: 0 | DD11: 0 | DE11: 0 | DF11: 0 | DG11: 0 | DH11: 0 | DI11: 0 | DJ11: 0 | DK11: 0 | DL11: 0 | DM11: 0 | DN11: 0 | DO11: 0 | DP11: 0 | DQ11: 0 | DR11: 0 | DS11: 0 | DT11: 0 | DU11: 0 | DV11: 0 | DW11: 0 | DX11: 0 | DY11: 2.1175375e-09 | DZ11: 0 | EA11: 0 | EB11: 0 | EC11: 0 | ED11: 0 | EE11: 0 | EF11: 0 | EG11: 0 | EH11: 0 | EI11: 0 | EJ11: 0 | EK11: 0 | EL11: 0 | EM11: 0 | EN11: 0 | EO11: 0 | EP11: 0 | EQ11: 0 | ER11: 0 | ES11: 0 | ET11: 0 | EU11: 0 | EV11: 0 | EW11: 2.1685493e-10 | EX11: 0 | EY11: 0 | EZ11: 0 | FA11: 0 | FB11: 0 | FC11: 2.1028209e-10 | FD11: 0 | FE11: 0 | FF11: 0 | FG11: 0 | FH11: 0 | FI11: 0 | FJ11: 0 | FK11: 0 | FL11: 0 | FM11: 0 | FN11: 0 | FO11: 0 | FP11: 0 | FQ11: 0 | FR11: 9.1788255e-10 | FS11: 0 | FT11: 7.8581497e-09 | FU11: 0 | FV11: 2.6210854e-05 | FW11: 0 | FX11: 0 | FY11: 0 | FZ11: 0 | GA11: 0 | GB11: 0 | GC11: 0 | GD11: 0 | GE11: 0 | GF11: 0 | GG11: 0 | GH11: 0 | GI11: 0 | GJ11: 0 | GK11: 0 | GL11: 0 | GM11: 0 | GN11: 0 | GO11: 0 | GP11: 0 | GQ11: 0 | GR11: 5.3929336e-10 | GS11: 5.4340821e-10 | GT11: 9.4365677e-09 | GU11: 0
A12: Cattle | B12: 9 | C12: ISIC 01T03 | D12: 0 | E12: 0 | F12: 0 | G12: 0 | H12: 0 | I12: 0 | J12: 0 | K12: 0 | L12: 0.26786337 | M12: 0.00032739664 | N12: 4.6846595e-05 | O12: 0.0025169752 | P12: 0.036851858 | Q12: 0.030309555 | R12: 0 | S12: 0 | T12: 0 | U12: 0.00055465172 | V12: 0 | W12: 0 | X12: 0 | Y12: 0 | Z12: 0 | AA12: 0 | AB12: 0 | AC12: 0 | AD12: 0 | AE12: 0 | AF12: 0 | AG12: 0 | AH12: 0 | AI12: 0 | AJ12: 0 | AK12: 0 | AL12: 0 | AM12: 0 | AN12: 0 | AO12: 0 | AP12: 0 | AQ12: 0 | AR12: 0 | AS12: 0 | AT12: 0.94922114 | AU12: 0 | AV12: 0 | AW12: 0 | AX12: 0 | AY12: 0 | AZ12: 0 | BA12: 0 | BB12: 0 | BC12: 0 | BD12: 0 | BE12: 0 | BF12: 0 | BG12: 0 | BH12: 0.0037614974 | BI12: 0 | BJ12: 0 | BK12: 0 | BL12: 0 | BM12: 0 | BN12: 0 | BO12: 0 | BP12: 0 | BQ12: 0 | BR12: 0 | BS12: 0 | BT12: 0 | BU12: 0 | BV12: 0 | BW12: 0 | BX12: 0 | BY12: 0 | BZ12: 0 | CA12: 0 | CB12: 0 | CC12: 0 | CD12: 0 | CE12: 0 | CF12: 0 | CG12: 0 | CH12: 0 | CI12: 0 | CJ12: 0 | CK12: 0 | CL12: 0 | CM12: 0 | CN12: 0 | CO12: 0 | CP12: 0 | CQ12: 0 | CR12: 0 | CS12: 0 | CT12: 0 | CU12: 0 | CV12: 0 | CW12: 0 | CX12: 0 | CY12: 0 | CZ12: 0 | DA12: 0 | DB12: 0 | DC12: 0 | DD12: 0 | DE12: 0 | DF12: 0 | DG12: 0 | DH12: 0 | DI12: 0 | DJ12: 0 | DK12: 0 | DL12: 0 | DM12: 0 | DN12: 0 | DO12: 0 | DP12: 0 | DQ12: 0 | DR12: 0 | DS12: 0 | DT12: 0 | DU12: 0 | DV12: 0 | DW12: 0 | DX12: 0 | DY12: 0 | DZ12: 0 | EA12: 0 | EB12: 0 | EC12: 0 | ED12: 0 | EE12: 0 | EF12: 0 | EG12: 0 | EH12: 0 | EI12: 0 | EJ12: 0 | EK12: 0 | EL12: 0 | EM12: 0 | EN12: 0 | EO12: 0 | EP12: 0 | EQ12: 0 | ER12: 0 | ES12: 0 | ET12: 0 | EU12: 0 | EV12: 0 | EW12: 0 | EX12: 0 | EY12: 0 | EZ12: 0 | FA12: 0 | FB12: 0 | FC12: 0 | FD12: 0 | FE12: 0 | FF12: 0 | FG12: 0 | FH12: 0 | FI12: 0 | FJ12: 0 | FK12: 0 | FL12: 0 | FM12: 0 | FN12: 0 | FO12: 0 | FP12: 0 | FQ12: 0 | FR12: 0.00018724593 | FS12: 0 | FT12: 0 | FU12: 0 | FV12: 0 | FW12: 0 | FX12: 0 | FY12: 0 | FZ12: 0 | GA12: 0 | GB12: 0 | GC12: 0 | GD12: 0 | GE12: 0 | GF12: 0 | GG12: 0 | GH12: 0 | GI12: 0 | GJ12: 0 | GK12: 0 | GL12: 0 | GM12: 0 | GN12: 0 | GO12: 0 | GP12: 0 | GQ12: 0 | GR12: 0 | GS12: 0 | GT12: 0 | GU12: 0
A13: Pigs | B13: 10 | C13: ISIC 01T03 | D13: 0 | E13: 0 | F13: 0 | G13: 0 | H13: 0 | I13: 0 | J13: 0 | K13: 0 | L13: 5.6781759e-06 | M13: 0.00081881718 | N13: 1.8205249e-06 | O13: 5.3702266e-06 | P13: 9.8690794e-05 | Q13: 1.0984732e-05 | R13: 0 | S13: 0 | T13: 0 | U13: 1.7858567e-05 | V13: 0.00023465816 | W13: 0 | X13: 0 | Y13: 0 | Z13: 0 | AA13: 0 | AB13: 0 | AC13: 0 | AD13: 0 | AE13: 0 | AF13: 0 | AG13: 0 | AH13: 0 | AI13: 0 | AJ13: 0 | AK13: 0 | AL13: 0 | AM13: 0 | AN13: 0 | AO13: 0 | AP13: 0 | AQ13: 0 | AR13: 0 | AS13: 0 | AT13: 0 | AU13: 0.81699332 | AV13: 1.7318042e-07 | AW13: 4.4576957e-06 | AX13: 0.011600805 | AY13: 2.2941697e-06 | AZ13: 0.0010799182 | BA13: 0.016943145 | BB13: 0.0030557445 | BC13: 0.00034180917 | BD13: 0 | BE13: 0 | BF13: 0 | BG13: 0 | BH13: 0.0051524354 | BI13: 0 | BJ13: 0 | BK13: 0 | BL13: 0 | BM13: 0 | BN13: 0 | BO13: 0 | BP13: 0 | BQ13: 0 | BR13: 0 | BS13: 0 | BT13: 0 | BU13: 0 | BV13: 0 | BW13: 0 | BX13: 0 | BY13: 0 | BZ13: 0 | CA13: 0 | CB13: 0 | CC13: 0 | CD13: 0 | CE13: 0 | CF13: 0 | CG13: 0 | CH13: 0 | CI13: 0 | CJ13: 0 | CK13: 0 | CL13: 0 | CM13: 0 | CN13: 2.404165e-06 | CO13: 0.00013533175 | CP13: 0 | CQ13: 0.00013533175 | CR13: 0 | CS13: 0.00013533175 | CT13: 0 | CU13: 0 | CV13: 0 | CW13: 0 | CX13: 0 | CY13: 0 | CZ13: 0 | DA13: 0 | DB13: 0 | DC13: 0 | DD13: 0 | DE13: 0 | DF13: 0 | DG13: 0 | DH13: 0 | DI13: 0 | DJ13: 0 | DK13: 0 | DL13: 0 | DM13: 0 | DN13: 0 | DO13: 0 | DP13: 0 | DQ13: 0 | DR13: 0 | DS13: 0 | DT13: 0 | DU13: 0 | DV13: 0 | DW13: 0 | DX13: 0 | DY13: 5.5667155e-09 | DZ13: 0 | EA13: 0 | EB13: 0 | EC13: 0 | ED13: 0 | EE13: 0 | EF13: 0 | EG13: 0 | EH13: 0 | EI13: 0 | EJ13: 0 | EK13: 0 | EL13: 0 | EM13: 0 | EN13: 0 | EO13: 0 | EP13: 0 | EQ13: 0 | ER13: 0 | ES13: 0 | ET13: 0 | EU13: 0 | EV13: 0 | EW13: 0 | EX13: 0 | EY13: 0 | EZ13: 0 | FA13: 0 | FB13: 0 | FC13: 0.00035341658 | FD13: 0 | FE13: 0 | FF13: 0 | FG13: 0 | FH13: 0 | FI13: 0 | FJ13: 0 | FK13: 0 | FL13: 0 | FM13: 0 | FN13: 0 | FO13: 0 | FP13: 0 | FQ13: 0 | FR13: 2.3242059e-07 | FS13: 0 | FT13: 4.5159077e-05 | FU13: 0 | FV13: 3.4596262e-05 | FW13: 0 | FX13: 0 | FY13: 0 | FZ13: 0 | GA13: 0 | GB13: 0 | GC13: 0 | GD13: 0 | GE13: 0 | GF13: 0 | GG13: 0 | GH13: 0 | GI13: 0 | GJ13: 0 | GK13: 0 | GL13: 0 | GM13: 0 | GN13: 0 | GO13: 0 | GP13: 0 | GQ13: 0 | GR13: 6.8707433e-08 | GS13: 0.00040942455 | GT13: 0 | GU13: 0
A14: Poultry | B14: 11 | C14: ISIC 01T03 | D14: 0 | E14: 0 | F14: 0 | G14: 0 | H14: 0 | I14: 0 | J14: 0 | K14: 0 | L14: 6.9169045e-06 | M14: 2.5124882e-06 | N14: 0.017323322 | O14: 1.076611e-05 | P14: 0.00047632613 | Q14: 1.6159151e-05 | R14: 0 | S14: 0 | T14: 0 | U14: 5.5252641e-06 | V14: 0 | W14: 0 | X14: 0 | Y14: 0 | Z14: 0 | AA14: 0 | AB14: 0 | AC14: 0 | AD14: 0 | AE14: 0 | AF14: 0 | AG14: 0 | AH14: 0 | AI14: 0 | AJ14: 0 | AK14: 0 | AL14: 0 | AM14: 0 | AN14: 0 | AO14: 0 | AP14: 0 | AQ14: 0 | AR14: 0 | AS14: 0 | AT14: 0 | AU14: 0 | AV14: 0.87477185 | AW14: 0 | AX14: 0 | AY14: 0 | AZ14: 0 | BA14: 0 | BB14: 0 | BC14: 0 | BD14: 0 | BE14: 0 | BF14: 0 | BG14: 0 | BH14: 0 | BI14: 0 | BJ14: 0 | BK14: 0 | BL14: 0 | BM14: 0 | BN14: 0 | BO14: 0 | BP14: 0 | BQ14: 0 | BR14: 0 | BS14: 0 | BT14: 0 | BU14: 0 | BV14: 0 | BW14: 0 | BX14: 0 | BY14: 0 | BZ14: 0 | CA14: 0 | CB14: 0 | CC14: 0 | CD14: 0 | CE14: 0 | CF14: 0 | CG14: 0 | CH14: 0 | CI14: 0 | CJ14: 0 | CK14: 0 | CL14: 0 | CM14: 0 | CN14: 0 | CO14: 0 | CP14: 0 | CQ14: 0 | CR14: 0 | CS14: 0 | CT14: 0 | CU14: 0 | CV14: 0 | CW14: 0 | CX14: 0 | CY14: 0 | CZ14: 0 | DA14: 0 | DB14: 0 | DC14: 0 | DD14: 0 | DE14: 0 | DF14: 0 | DG14: 0 | DH14: 0 | DI14: 0 | DJ14: 0 | DK14: 0 | DL14: 0 | DM14: 0 | DN14: 0 | DO14: 0 | DP14: 0 | DQ14: 0 | DR14: 0 | DS14: 0 | DT14: 0 | DU14: 0 | DV14: 0 | DW14: 0 | DX14: 0 | DY14: 0 | DZ14: 0 | EA14: 0 | EB14: 0 | EC14: 0 | ED14: 0 | EE14: 0 | EF14: 0 | EG14: 0 | EH14: 0 | EI14: 0 | EJ14: 0 | EK14: 0 | EL14: 0 | EM14: 0 | EN14: 0 | EO14: 0 | EP14: 0 | EQ14: 0 | ER14: 0 | ES14: 0 | ET14: 0 | EU14: 0 | EV14: 0 | EW14: 0 | EX14: 0 | EY14: 0 | EZ14: 0 | FA14: 0 | FB14: 0 | FC14: 0 | FD14: 0 | FE14: 0 | FF14: 0 | FG14: 0 | FH14: 0 | FI14: 0 | FJ14: 0 | FK14: 0 | FL14: 0 | FM14: 0 | FN14: 0 | FO14: 0 | FP14: 0 | FQ14: 0 | FR14: 0 | FS14: 0 | FT14: 0 | FU14: 0 | FV14: 0 | FW14: 0 | FX14: 0 | FY14: 0 | FZ14: 0 | GA14: 0 | GB14: 0 | GC14: 0 | GD14: 0 | GE14: 0 | GF14: 0 | GG14: 0 | GH14: 0 | GI14: 0 | GJ14: 0 | GK14: 0 | GL14: 0 | GM14: 0 | GN14: 0 | GO14: 0 | GP14: 0 | GQ14: 0 | GR14: 0 | GS14: 0 | GT14: 0 | GU14: 0
A15: Meat animals nec | B15: 12 | C15: ISIC 01T03 | D15: 0 | E15: 0 | F15: 0 | G15: 0 | H15: 0 | I15: 0 | J15: 0 | K15: 0 | L15: 0 | M15: 0 | N15: 7.6648804e-08 | O15: 0 | P15: 0 | Q15: 1.3981729e-05 | R15: 0 | S15: 0 | T15: 0 | U15: 0 | V15: 0 | W15: 0 | X15: 0 | Y15: 0 | Z15: 0 | AA15: 0 | AB15: 0 | AC15: 0 | AD15: 0 | AE15: 0 | AF15: 0 | AG15: 0 | AH15: 0 | AI15: 0 | AJ15: 0 | AK15: 0 | AL15: 0 | AM15: 0 | AN15: 0 | AO15: 0 | AP15: 0 | AQ15: 0 | AR15: 0 | AS15: 0 | AT15: 0 | AU15: 0 | AV15: 0 | AW15: 0 | AX15: 0 | AY15: 0 | AZ15: 0 | BA15: 0 | BB15: 0 | BC15: 0 | BD15: 0 | BE15: 0 | BF15: 0 | BG15: 0 | BH15: 0 | BI15: 0 | BJ15: 0 | BK15: 0 | BL15: 0 | BM15: 0 | BN15: 0 | BO15: 0 | BP15: 0 | BQ15: 0 | BR15: 0 | BS15: 0 | BT15: 0 | BU15: 0 | BV15: 0 | BW15: 0 | BX15: 0 | BY15: 0 | BZ15: 0 | CA15: 0 | CB15: 0 | CC15: 0 | CD15: 0 | CE15: 0 | CF15: 0 | CG15: 0 | CH15: 0 | CI15: 0 | CJ15: 0 | CK15: 0 | CL15: 0 | CM15: 0 | CN15: 0 | CO15: 0 | CP15: 0 | CQ15: 0 | CR15: 0 | CS15: 0 | CT15: 0 | CU15: 0 | CV15: 0 | CW15: 0 | CX15: 0 | CY15: 0 | CZ15: 0 | DA15: 0 | DB15: 0 | DC15: 0 | DD15: 0 | DE15: 0 | DF15: 0 | DG15: 0 | DH15: 0 | DI15: 0 | DJ15: 0 | DK15: 0 | DL15: 0 | DM15: 0 | DN15: 0 | DO15: 0 | DP15: 0 | DQ15: 0 | DR15: 0 | DS15: 0 | DT15: 0 | DU15: 0 | DV15: 0 | DW15: 0 | DX15: 0 | DY15: 0 | DZ15: 0 | EA15: 0 | EB15: 0 | EC15: 0 | ED15: 0 | EE15: 0 | EF15: 0 | EG15: 0 | EH15: 0 | EI15: 0 | EJ15: 0 | EK15: 0 | EL15: 0 | EM15: 0 | EN15: 0 | EO15: 0 | EP15: 0 | EQ15: 0 | ER15: 0 | ES15: 0 | ET15: 0 | EU15: 0 | EV15: 0 | EW15: 0 | EX15: 0 | EY15: 0 | EZ15: 0 | FA15: 0 | FB15: 0 | FC15: 0 | FD15: 0 | FE15: 0 | FF15: 0 | FG15: 0 | FH15: 0 | FI15: 0 | FJ15: 0 | FK15: 0 | FL15: 0 | FM15: 0 | FN15: 0 | FO15: 0 | FP15: 0 | FQ15: 0 | FR15: 0 | FS15: 0 | FT15: 0 | FU15: 0 | FV15: 0 | FW15: 0 | FX15: 0 | FY15: 0 | FZ15: 0 | GA15: 0 | GB15: 0 | GC15: 0 | GD15: 0 | GE15: 0 | GF15: 0 | GG15: 0 | GH15: 0 | GI15: 0 | GJ15: 0 | GK15: 0 | GL15: 0 | GM15: 0 | GN15: 0 | GO15: 0 | GP15: 0 | GQ15: 0 | GR15: 0 | GS15: 0 | GT15: 0 | GU15: 0
... A202: Private households with employed persons (95) | B202: 199 | C202: ISIC 97T98 | D202: 0 | E202: 0 | F202: 0 | G202: 0 | H202: 0 | I202: 0 | J202: 0 | K202: 0 | L202: 0 | M202: 0 | N202: 0 | O202: 0 | P202: 0 | Q202: 0 | R202: 0 | S202: 0 | T202: 0 | U202: 0 | V202: 0 | W202: 7.3509291e-05 | X202: 0 | Y202: 0 | Z202: 0 | AA202: 7.3509291e-05 | AB202: 0 | AC202: 0 | AD202: 0 | AE202: 1.6257889e-05 | AF202: 4.2901997e-08 | AG202: 0 | AH202: 0 | AI202: 1.2157294e-08 | AJ202: 0.00058311817 | AK202: 0 | AL202: 9.9491828e-09 | AM202: 0 | AN202: 4.5750296e-08 | AO202: 0 | AP202: 0 | AQ202: 0 | AR202: 0 | AS202: 0 | AT202: 0 | AU202: 0 | AV202: 0 | AW202: 0 | AX202: 0 | AY202: 0 | AZ202: 0 | BA202: 0 | BB202: 0 | BC202: 0 | BD202: 0 | BE202: 0 | BF202: 0 | BG202: 0 | BH202: 0 | BI202: 0 | BJ202: 0 | BK202: 0 | BL202: 0 | BM202: 0 | BN202: 0 | BO202: 0 | BP202: 0 | BQ202: 0 | BR202: 0 | BS202: 0 | BT202: 0 | BU202: 0 | BV202: 0 | BW202: 0 | BX202: 0 | BY202: 0 | BZ202: 0 | CA202: 0 | CB202: 0 | CC202: 0 | CD202: 0 | CE202: 0 | CF202: 0 | CG202: 0 | CH202: 0 | CI202: 0 | CJ202: 0 | CK202: 0 | CL202: 0 | CM202: 0 | CN202: 0 | CO202: 0 | CP202: 0 | CQ202: 0 | CR202: 0 | CS202: 0 | CT202: 0 | CU202: 0 | CV202: 0 | CW202: 0 | CX202: 0 | CY202: 0 | CZ202: 0 | DA202: 0 | DB202: 0 | DC202: 0 | DD202: 0 | DE202: 0 | DF202: 0 | DG202: 0 | DH202: 0 | DI202: 0 | DJ202: 0 | DK202: 0 | DL202: 0 | DM202: 0 | DN202: 0 | DO202: 0 | DP202: 0 | DQ202: 0 | DR202: 0 | DS202: 0 | DT202: 0 | DU202: 0 | DV202: 0 | DW202: 0 | DX202: 0 | DY202: 0 | DZ202: 0 | EA202: 0 | EB202: 0 | EC202: 0 | ED202: 0 | EE202: 0 | EF202: 0 | EG202: 0 | EH202: 0 | EI202: 0 | EJ202: 0 | EK202: 0 | EL202: 0 | EM202: 0 | EN202: 0 | EO202: 0 | EP202: 0 | EQ202: 0 | ER202: 0 | ES202: 0 | ET202: 0 | EU202: 0 | EV202: 0 | EW202: 0 | EX202: 0 | EY202: 0 | EZ202: 0 | FA202: 0 | FB202: 0 | FC202: 0 | FD202: 0 | FE202: 0 | FF202: 0 | FG202: 0 | FH202: 0 | FI202: 0 | FJ202: 0 | FK202: 0 | FL202: 0 | FM202: 0 | FN202: 0 | FO202: 0 | FP202: 0 | FQ202: 0 | FR202: 0 | FS202: 0 | FT202: 0 | FU202: 0 | FV202: 0 | FW202: 0 | FX202: 0 | FY202: 0 | FZ202: 0 | GA202: 0 | GB202: 0 | GC202: 0 | GD202: 0 | GE202: 0 | GF202: 0 | GG202: 0 | GH202: 0 | GI202: 0 | GJ202: 0 | GK202: 0 | GL202: 0 | GM202: 0 | GN202: 0 | GO202: 0 | GP202: 0 | GQ202: 0 | GR202: 0 | GS202: 0 | GT202: 2.369287e-06 | GU202: 0
A203: Extra-territorial organizations and bodies | B203: 200 | D203: 0 | E203: 0 | F203: 0 | G203: 0 | H203: 0 | I203: 0 | J203: 0 | K203: 0 | L203: 0 | M203: 0 | N203: 0 | O203: 0 | P203: 0 | Q203: 0 | R203: 0 | S203: 0 | T203: 0 | U203: 0 | V203: 0 | W203: 0 | X203: 0 | Y203: 0 | Z203: 0 | AA203: 0 | AB203: 0 | AC203: 0 | AD203: 0 | AE203: 0 | AF203: 0 | AG203: 0 | AH203: 0 | AI203: 0 | AJ203: 0 | AK203: 0 | AL203: 0 | AM203: 0 | AN203: 0 | AO203: 0 | AP203: 0 | AQ203: 0 | AR203: 0 | AS203: 0 | AT203: 0 | AU203: 0 | AV203: 0 | AW203: 0 | AX203: 0 | AY203: 0 | AZ203: 0 | BA203: 0 | BB203: 0 | BC203: 0 | BD203: 0 | BE203: 0 | BF203: 0 | BG203: 0 | BH203: 0 | BI203: 0 | BJ203: 0 | BK203: 0 | BL203: 0 | BM203: 0 | BN203: 0 | BO203: 0 | BP203: 0 | BQ203: 0 | BR203: 0 | BS203: 0 | BT203: 0 | BU203: 0 | BV203: 0 | BW203: 0 | BX203: 0 | BY203: 0 | BZ203: 0 | CA203: 0 | CB203: 0 | CC203: 0 | CD203: 0 | CE203: 0 | CF203: 0 | CG203: 0 | CH203: 0 | CI203: 0 | CJ203: 0 | CK203: 0 | CL203: 0 | CM203: 0 | CN203: 0 | CO203: 0 | CP203: 0 | CQ203: 0 | CR203: 0 | CS203: 0 | CT203: 0 | CU203: 0 | CV203: 0 | CW203: 0 | CX203: 0 | CY203: 0 | CZ203: 0 | DA203: 0 | DB203: 0 | DC203: 0 | DD203: 0 | DE203: 0 | DF203: 0 | DG203: 0 | DH203: 0 | DI203: 0 | DJ203: 0 | DK203: 0 | DL203: 0 | DM203: 0 | DN203: 0 | DO203: 0 | DP203: 0 | DQ203: 0 | DR203: 0 | DS203: 0 | DT203: 0 | DU203: 0 | DV203: 0 | DW203: 0 | DX203: 0 | DY203: 0 | DZ203: 0 | EA203: 0 | EB203: 0 | EC203: 0 | ED203: 0 | EE203: 0 | EF203: 0 | EG203: 0 | EH203: 0 | EI203: 0 | EJ203: 0 | EK203: 0 | EL203: 0 | EM203: 0 | EN203: 0 | EO203: 0 | EP203: 0 | EQ203: 0 | ER203: 0 | ES203: 0 | ET203: 0 | EU203: 0 | EV203: 0 | EW203: 0 | EX203: 0 | EY203: 0 | EZ203: 0 | FA203: 0 | FB203: 0 | FC203: 0 | FD203: 0 | FE203: 0 | FF203: 0 | FG203: 0 | FH203: 0 | FI203: 0 | FJ203: 0 | FK203: 0 | FL203: 0 | FM203: 0 | FN203: 0 | FO203: 0 | FP203: 0 | FQ203: 0 | FR203: 0 | FS203: 0 | FT203: 0 | FU203: 0 | FV203: 0 | FW203: 0 | FX203: 0 | FY203: 0 | FZ203: 0 | GA203: 0 | GB203: 0 | GC203: 0 | GD203: 0 | GE203: 0 | GF203: 0 | GG203: 0 | GH203: 0 | GI203: 0 | GJ203: 0 | GK203: 0 | GL203: 0 | GM203: 0 | GN203: 0 | GO203: 0 | GP203: 0 | GQ203: 0 | GR203: 0 | GS203: 0 | GT203: 0 | GU203: 0

Sheet Cement and Glass Split
A1: Total Values
B2: ISIC 01T03 | C2: ISIC 05 | D2: ISIC 06 | E2: ISIC 07T08 | F2: ISIC 09 | G2: ISIC 10T12 | H2: ISIC 13T15 | I2: ISIC 16 | J2: ISIC 17T18 | K2: ISIC 19 | L2: ISIC 20 | M2: ISIC 21 | N2: ISIC 22 | O2: ISIC 231 | P2: ISIC 239 | Q2: ISIC 241 | R2: ISIC 242 | S2: ISIC 25 | T2: ISIC 26 | U2: ISIC 27 | V2: ISIC 28 | W2: ISIC 29 | X2: ISIC 30 | Y2: ISIC 31T33 | Z2: ISIC 351 | AA2: ISIC 352T353 | AB2: ISIC 36T39 | AC2: ISIC 41T43 | AD2: ISIC 45T47 | AE2: ISIC 49T53 | AF2: ISIC 55T56 | AG2: ISIC 58T60 | AH2: ISIC 61 | AI2: ISIC 62T63 | AJ2: ISIC 64T66 | AK2: ISIC 68 | AL2: ISIC 69T82 | AM2: ISIC 84 | AN2: ISIC 85 | AO2: ISIC 86T88 | AP2: ISIC 90T96 | AQ2: ISIC 97T98
A3: ISIC 01T03 | B3: {=SUMPRODUCT(IF('Exiobase A Matrix'!$C$4:$C$203='Cement and Glass Split'!$A3,IF('Exiobase A Matrix'!$D$3:$GU$3='Cement and Glass Split'!B$2,'Exiobase A Matrix'!$D$4:$GU$203)))} -> 0.78530571 | C3: {=SUMPRODUCT(IF('Exiobase A Matrix'!$C$4:$C$203='Cement and Glass Split'!$A3,IF('Exiobase A Matrix'!$D$3:$GU$3='Cement and Glass Split'!C$2,'Exiobase A Matrix'!$D$4:$GU$203)))} -> 0.0005226715 | D3: {=SUMPRODUCT(IF('Exiobase A Matrix'!$C$4:$C$203='Cement and Glass Split'!$A3,IF('Exiobase A Matrix'!$D$3:$GU$3='Cement and Glass Split'!D$2,'Exiobase A Matrix'!$D$4:$GU$203)))} -> 1.7164467e-06 | E3: {=SUMPRODUCT(IF('Exiobase A Matrix'!$C$4:$C$203='Cement and Glass Split'!$A3,IF('Exiobase A Matrix'!$D$3:$GU$3='Cement and Glass Split'!E$2,'Exiobase A Matrix'!$D$4:$GU$203)))} -> 6.2158421e-05 | F3: {=SUMPRODUCT(IF('Exiobase A Matrix'!$C$4:$C$203='Cement and Glass Split'!$A3,IF('Exiobase A Matrix'!$D$3:$GU$3='Cement and Glass Split'!F$2,'Exiobase A Matrix'!$D$4:$GU$203)))} -> 0 | G3: {=SUMPRODUCT(IF('Exiobase A Matrix'!$C$4:$C$203='Cement and Glass Split'!$A3,IF('Exiobase A Matrix'!$D$3:$GU$3='Cement and Glass Split'!G$2,'Exiobase A Matrix'!$D$4:$GU$203)))} -> 4.0740886 | H3: {=SUMPRODUCT(IF('Exiobase A Matrix'!$C$4:$C$203='Cement and Glass Split'!$A3,IF('Exiobase A Matrix'!$D$3:$GU$3='Cement and Glass Split'!H$2,'Exiobase A Matrix'!$D$4:$GU$203)))} -> 0.014309994 | I3: {=SUMPRODUCT(IF('Exiobase A Matrix'!$C$4:$C$203='Cement and Glass Split'!$A3,IF('Exiobase A Matrix'!$D$3:$GU$3='Cement and Glass Split'!I$2,'Exiobase A Matrix'!$D$4:$GU$203)))} -> 0.030604382 | ... AQ3: {=SUMPRODUCT(IF('Exiobase A Matrix'!$C$4:$C$203='Cement and Glass Split'!$A3,IF('Exiobase A Matrix'!$D$3:$GU$3='Cement and Glass Split'!AQ$2,'Exiobase A Matrix'!$D$4:$GU$203)))} -> 0.001218149
A4: ISIC 05 | B4: {=SUMPRODUCT(IF('Exiobase A Matrix'!$C$4:$C$203='Cement and Glass Split'!$A4,IF('Exiobase A Matrix'!$D$3:$GU$3='Cement and Glass Split'!B$2,'Exiobase A Matrix'!$D$4:$GU$203)))} -> 0 | C4: {=SUMPRODUCT(IF('Exiobase A Matrix'!$C$4:$C$203='Cement and Glass Split'!$A4,IF('Exiobase A Matrix'!$D$3:$GU$3='Cement and Glass Split'!C$2,'Exiobase A Matrix'!$D$4:$GU$203)))} -> 0 | D4: {=SUMPRODUCT(IF('Exiobase A Matrix'!$C$4:$C$203='Cement and Glass Split'!$A4,IF('Exiobase A Matrix'!$D$3:$GU$3='Cement and Glass Split'!D$2,'Exiobase A Matrix'!$D$4:$GU$203)))} -> 0 | E4: {=SUMPRODUCT(IF('Exiobase A Matrix'!$C$4:$C$203='Cement and Glass Split'!$A4,IF('Exiobase A Matrix'!$D$3:$GU$3='Cement and Glass Split'!E$2,'Exiobase A Matrix'!$D$4:$GU$203)))} -> 0 | F4: {=SUMPRODUCT(IF('Exiobase A Matrix'!$C$4:$C$203='Cement and Glass Split'!$A4,IF('Exiobase A Matrix'!$D$3:$GU$3='Cement and Glass Split'!F$2,'Exiobase A Matrix'!$D$4:$GU$203)))} -> 0 | G4: {=SUMPRODUCT(IF('Exiobase A Matrix'!$C$4:$C$203='Cement and Glass Split'!$A4,IF('Exiobase A Matrix'!$D$3:$GU$3='Cement and Glass Split'!G$2,'Exiobase A Matrix'!$D$4:$GU$203)))} -> 0 | H4: {=SUMPRODUCT(IF('Exiobase A Matrix'!$C$4:$C$203='Cement and Glass Split'!$A4,IF('Exiobase A Matrix'!$D$3:$GU$3='Cement and Glass Split'!H$2,'Exiobase A Matrix'!$D$4:$GU$203)))} -> 0 | I4: {=SUMPRODUCT(IF('Exiobase A Matrix'!$C$4:$C$203='Cement and Glass Split'!$A4,IF('Exiobase A Matrix'!$D$3:$GU$3='Cement and Glass Split'!I$2,'Exiobase A Matrix'!$D$4:$GU$203)))} -> 0 | ... AQ4: {=SUMPRODUCT(IF('Exiobase A Matrix'!$C$4:$C$203='Cement and Glass Split'!$A4,IF('Exiobase A Matrix'!$D$3:$GU$3='Cement and Glass Split'!AQ$2,'Exiobase A Matrix'!$D$4:$GU$203)))} -> 0
A5: ISIC 06 | B5: {=SUMPRODUCT(IF('Exiobase A Matrix'!$C$4:$C$203='Cement and Glass Split'!$A5,IF('Exiobase A Matrix'!$D$3:$GU$3='Cement and Glass Split'!B$2,'Exiobase A Matrix'!$D$4:$GU$203)))} -> 0.00043922461 | C5: {=SUMPRODUCT(IF('Exiobase A Matrix'!$C$4:$C$203='Cement and Glass Split'!$A5,IF('Exiobase A Matrix'!$D$3:$GU$3='Cement and Glass Split'!C$2,'Exiobase A Matrix'!$D$4:$GU$203)))} -> 2.6613567e-08 | D5: {=SUMPRODUCT(IF('Exiobase A Matrix'!$C$4:$C$203='Cement and Glass Split'!$A5,IF('Exiobase A Matrix'!$D$3:$GU$3='Cement and Glass Split'!D$2,'Exiobase A Matrix'!$D$4:$GU$203)))} -> 1.1161836e-07 | E5: {=SUMPRODUCT(IF('Exiobase A Matrix'!$C$4:$C$203='Cement and Glass Split'!$A5,IF('Exiobase A Matrix'!$D$3:$GU$3='Cement and Glass Split'!E$2,'Exiobase A Matrix'!$D$4:$GU$203)))} -> 8.4979221e-07 | F5: {=SUMPRODUCT(IF('Exiobase A Matrix'!$C$4:$C$203='Cement and Glass Split'!$A5,IF('Exiobase A Matrix'!$D$3:$GU$3='Cement and Glass Split'!F$2,'Exiobase A Matrix'!$D$4:$GU$203)))} -> 0 | G5: {=SUMPRODUCT(IF('Exiobase A Matrix'!$C$4:$C$203='Cement and Glass Split'!$A5,IF('Exiobase A Matrix'!$D$3:$GU$3='Cement and Glass Split'!G$2,'Exiobase A Matrix'!$D$4:$GU$203)))} -> 1.7123178e-07 | H5: {=SUMPRODUCT(IF('Exiobase A Matrix'!$C$4:$C$203='Cement and Glass Split'!$A5,IF('Exiobase A Matrix'!$D$3:$GU$3='Cement and Glass Split'!H$2,'Exiobase A Matrix'!$D$4:$GU$203)))} -> 0.0080052173 | I5: {=SUMPRODUCT(IF('Exiobase A Matrix'!$C$4:$C$203='Cement and Glass Split'!$A5,IF('Exiobase A Matrix'!$D$3:$GU$3='Cement and Glass Split'!I$2,'Exiobase A Matrix'!$D$4:$GU$203)))} -> 0.0045377513 | ... AQ5: {=SUMPRODUCT(IF('Exiobase A Matrix'!$C$4:$C$203='Cement and Glass Split'!$A5,IF('Exiobase A Matrix'!$D$3:$GU$3='Cement and Glass Split'!AQ$2,'Exiobase A Matrix'!$D$4:$GU$203)))} -> 4.4036202e-09
A6: ISIC 07T08 | B6: {=SUMPRODUCT(IF('Exiobase A Matrix'!$C$4:$C$203='Cement and Glass Split'!$A6,IF('Exiobase A Matrix'!$D$3:$GU$3='Cement and Glass Split'!B$2,'Exiobase A Matrix'!$D$4:$GU$203)))} -> 0.0011069344 | C6: {=SUMPRODUCT(IF('Exiobase A Matrix'!$C$4:$C$203='Cement and Glass Split'!$A6,IF('Exiobase A Matrix'!$D$3:$GU$3='Cement and Glass Split'!C$2,'Exiobase A Matrix'!$D$4:$GU$203)))} -> 0 | D6: {=SUMPRODUCT(IF('Exiobase A Matrix'!$C$4:$C$203='Cement and Glass Split'!$A6,IF('Exiobase A Matrix'!$D$3:$GU$3='Cement and Glass Split'!D$2,'Exiobase A Matrix'!$D$4:$GU$203)))} -> 0 | E6: {=SUMPRODUCT(IF('Exiobase A Matrix'!$C$4:$C$203='Cement and Glass Split'!$A6,IF('Exiobase A Matrix'!$D$3:$GU$3='Cement and Glass Split'!E$2,'Exiobase A Matrix'!$D$4:$GU$203)))} -> 0 | F6: {=SUMPRODUCT(IF('Exiobase A Matrix'!$C$4:$C$203='Cement and Glass Split'!$A6,IF('Exiobase A Matrix'!$D$3:$GU$3='Cement and Glass Split'!F$2,'Exiobase A Matrix'!$D$4:$GU$203)))} -> 0 | G6: {=SUMPRODUCT(IF('Exiobase A Matrix'!$C$4:$C$203='Cement and Glass Split'!$A6,IF('Exiobase A Matrix'!$D$3:$GU$3='Cement and Glass Split'!G$2,'Exiobase A Matrix'!$D$4:$GU$203)))} -> 0.0011579334 | H6: {=SUMPRODUCT(IF('Exiobase A Matrix'!$C$4:$C$203='Cement and Glass Split'!$A6,IF('Exiobase A Matrix'!$D$3:$GU$3='Cement and Glass Split'!H$2,'Exiobase A Matrix'!$D$4:$GU$203)))} -> 0.00030002591 | I6: {=SUMPRODUCT(IF('Exiobase A Matrix'!$C$4:$C$203='Cement and Glass Split'!$A6,IF('Exiobase A Matrix'!$D$3:$GU$3='Cement and Glass Split'!I$2,'Exiobase A Matrix'!$D$4:$GU$203)))} -> 0 | ... AQ6: {=SUMPRODUCT(IF('Exiobase A Matrix'!$C$4:$C$203='Cement and Glass Split'!$A6,IF('Exiobase A Matrix'!$D$3:$GU$3='Cement and Glass Split'!AQ$2,'Exiobase A Matrix'!$D$4:$GU$203)))} -> 0
A7: ISIC 09 | B7: {=SUMPRODUCT(IF('Exiobase A Matrix'!$C$4:$C$203='Cement and Glass Split'!$A7,IF('Exiobase A Matrix'!$D$3:$GU$3='Cement and Glass Split'!B$2,'Exiobase A Matrix'!$D$4:$GU$203)))} -> 0 | C7: {=SUMPRODUCT(IF('Exiobase A Matrix'!$C$4:$C$203='Cement and Glass Split'!$A7,IF('Exiobase A Matrix'!$D$3:$GU$3='Cement and Glass Split'!C$2,'Exiobase A Matrix'!$D$4:$GU$203)))} -> 0 | D7: {=SUMPRODUCT(IF('Exiobase A Matrix'!$C$4:$C$203='Cement and Glass Split'!$A7,IF('Exiobase A Matrix'!$D$3:$GU$3='Cement and Glass Split'!D$2,'Exiobase A Matrix'!$D$4:$GU$203)))} -> 0 | E7: {=SUMPRODUCT(IF('Exiobase A Matrix'!$C$4:$C$203='Cement and Glass Split'!$A7,IF('Exiobase A Matrix'!$D$3:$GU$3='Cement and Glass Split'!E$2,'Exiobase A Matrix'!$D$4:$GU$203)))} -> 0 | F7: {=SUMPRODUCT(IF('Exiobase A Matrix'!$C$4:$C$203='Cement and Glass Split'!$A7,IF('Exiobase A Matrix'!$D$3:$GU$3='Cement and Glass Split'!F$2,'Exiobase A Matrix'!$D$4:$GU$203)))} -> 0 | G7: {=SUMPRODUCT(IF('Exiobase A Matrix'!$C$4:$C$203='Cement and Glass Split'!$A7,IF('Exiobase A Matrix'!$D$3:$GU$3='Cement and Glass Split'!G$2,'Exiobase A Matrix'!$D$4:$GU$203)))} -> 0 | H7: {=SUMPRODUCT(IF('Exiobase A Matrix'!$C$4:$C$203='Cement and Glass Split'!$A7,IF('Exiobase A Matrix'!$D$3:$GU$3='Cement and Glass Split'!H$2,'Exiobase A Matrix'!$D$4:$GU$203)))} -> 0 | I7: {=SUMPRODUCT(IF('Exiobase A Matrix'!$C$4:$C$203='Cement and Glass Split'!$A7,IF('Exiobase A Matrix'!$D$3:$GU$3='Cement and Glass Split'!I$2,'Exiobase A Matrix'!$D$4:$GU$203)))} -> 0 | ... AQ7: {=SUMPRODUCT(IF('Exiobase A Matrix'!$C$4:$C$203='Cement and Glass Split'!$A7,IF('Exiobase A Matrix'!$D$3:$GU$3='Cement and Glass Split'!AQ$2,'Exiobase A Matrix'!$D$4:$GU$203)))} -> 0
A8: ISIC 10T12 | B8: {=SUMPRODUCT(IF('Exiobase A Matrix'!$C$4:$C$203='Cement and Glass Split'!$A8,IF('Exiobase A Matrix'!$D$3:$GU$3='Cement and Glass Split'!B$2,'Exiobase A Matrix'!$D$4:$GU$203)))} -> 2.951659 | C8: {=SUMPRODUCT(IF('Exiobase A Matrix'!$C$4:$C$203='Cement and Glass Split'!$A8,IF('Exiobase A Matrix'!$D$3:$GU$3='Cement and Glass Split'!C$2,'Exiobase A Matrix'!$D$4:$GU$203)))} -> 0 | D8: {=SUMPRODUCT(IF('Exiobase A Matrix'!$C$4:$C$203='Cement and Glass Split'!$A8,IF('Exiobase A Matrix'!$D$3:$GU$3='Cement and Glass Split'!D$2,'Exiobase A Matrix'!$D$4:$GU$203)))} -> 0 | E8: {=SUMPRODUCT(IF('Exiobase A Matrix'!$C$4:$C$203='Cement and Glass Split'!$A8,IF('Exiobase A Matrix'!$D$3:$GU$3='Cement and Glass Split'!E$2,'Exiobase A Matrix'!$D$4:$GU$203)))} -> 0 | F8: {=SUMPRODUCT(IF('Exiobase A Matrix'!$C$4:$C$203='Cement and Glass Split'!$A8,IF('Exiobase A Matrix'!$D$3:$GU$3='Cement and Glass Split'!F$2,'Exiobase A Matrix'!$D$4:$GU$203)))} -> 0 | G8: {=SUMPRODUCT(IF('Exiobase A Matrix'!$C$4:$C$203='Cement and Glass Split'!$A8,IF('Exiobase A Matrix'!$D$3:$GU$3='Cement and Glass Split'!G$2,'Exiobase A Matrix'!$D$4:$GU$203)))} -> 1.3405578 | H8: {=SUMPRODUCT(IF('Exiobase A Matrix'!$C$4:$C$203='Cement and Glass Split'!$A8,IF('Exiobase A Matrix'!$D$3:$GU$3='Cement and Glass Split'!H$2,'Exiobase A Matrix'!$D$4:$GU$203)))} -> 0.089269535 | I8: {=SUMPRODUCT(IF('Exiobase A Matrix'!$C$4:$C$203='Cement and Glass Split'!$A8,IF('Exiobase A Matrix'!$D$3:$GU$3='Cement and Glass Split'!I$2,'Exiobase A Matrix'!$D$4:$GU$203)))} -> 0 | ... AQ8: {=SUMPRODUCT(IF('Exiobase A Matrix'!$C$4:$C$203='Cement and Glass Split'!$A8,IF('Exiobase A Matrix'!$D$3:$GU$3='Cement and Glass Split'!AQ$2,'Exiobase A Matrix'!$D$4:$GU$203)))} -> 0
A9: ISIC 13T15 | B9: {=SUMPRODUCT(IF('Exiobase A Matrix'!$C$4:$C$203='Cement and Glass Split'!$A9,IF('Exiobase A Matrix'!$D$3:$GU$3='Cement and Glass Split'!B$2,'Exiobase A Matrix'!$D$4:$GU$203)))} -> 0.079758623 | C9: {=SUMPRODUCT(IF('Exiobase A Matrix'!$C$4:$C$203='Cement and Glass Split'!$A9,IF('Exiobase A Matrix'!$D$3:$GU$3='Cement and Glass Split'!C$2,'Exiobase A Matrix'!$D$4:$GU$203)))} -> 0.0028549701 | D9: {=SUMPRODUCT(IF('Exiobase A Matrix'!$C$4:$C$203='Cement and Glass Split'!$A9,IF('Exiobase A Matrix'!$D$3:$GU$3='Cement and Glass Split'!D$2,'Exiobase A Matrix'!$D$4:$GU$203)))} -> 7.7342473e-06 | E9: {=SUMPRODUCT(IF('Exiobase A Matrix'!$C$4:$C$203='Cement and Glass Split'!$A9,IF('Exiobase A Matrix'!$D$3:$GU$3='Cement and Glass Split'!E$2,'Exiobase A Matrix'!$D$4:$GU$203)))} -> 0.0028623941 | F9: {=SUMPRODUCT(IF('Exiobase A Matrix'!$C$4:$C$203='Cement and Glass Split'!$A9,IF('Exiobase A Matrix'!$D$3:$GU$3='Cement and Glass Split'!F$2,'Exiobase A Matrix'!$D$4:$GU$203)))} -> 0 | G9: {=SUMPRODUCT(IF('Exiobase A Matrix'!$C$4:$C$203='Cement and Glass Split'!$A9,IF('Exiobase A Matrix'!$D$3:$GU$3='Cement and Glass Split'!G$2,'Exiobase A Matrix'!$D$4:$GU$203)))} -> 0.0089117404 | H9: {=SUMPRODUCT(IF('Exiobase A Matrix'!$C$4:$C$203='Cement and Glass Split'!$A9,IF('Exiobase A Matrix'!$D$3:$GU$3='Cement and Glass Split'!H$2,'Exiobase A Matrix'!$D$4:$GU$203)))} -> 0.77643453 | I9: {=SUMPRODUCT(IF('Exiobase A Matrix'!$C$4:$C$203='Cement and Glass Split'!$A9,IF('Exiobase A Matrix'!$D$3:$GU$3='Cement and Glass Split'!I$2,'Exiobase A Matrix'!$D$4:$GU$203)))} -> 0.0021274967 | ... AQ9: {=SUMPRODUCT(IF('Exiobase A Matrix'!$C$4:$C$203='Cement and Glass Split'!$A9,IF('Exiobase A Matrix'!$D$3:$GU$3='Cement and Glass Split'!AQ$2,'Exiobase A Matrix'!$D$4:$GU$203)))} -> 3.1983261e-06
A10: ISIC 16 | B10: {=SUMPRODUCT(IF('Exiobase A Matrix'!$C$4:$C$203='Cement and Glass Split'!$A10,IF('Exiobase A Matrix'!$D$3:$GU$3='Cement and Glass Split'!B$2,'Exiobase A Matrix'!$D$4:$GU$203)))} -> 0.077040739 | C10: {=SUMPRODUCT(IF('Exiobase A Matrix'!$C$4:$C$203='Cement and Glass Split'!$A10,IF('Exiobase A Matrix'!$D$3:$GU$3='Cement and Glass Split'!C$2,'Exiobase A Matrix'!$D$4:$GU$203)))} -> 0.0064736031 | D10: {=SUMPRODUCT(IF('Exiobase A Matrix'!$C$4:$C$203='Cement and Glass Split'!$A10,IF('Exiobase A Matrix'!$D$3:$GU$3='Cement and Glass Split'!D$2,'Exiobase A Matrix'!$D$4:$GU$203)))} -> 3.5231125e-06 | E10: {=SUMPRODUCT(IF('Exiobase A Matrix'!$C$4:$C$203='Cement and Glass Split'!$A10,IF('Exiobase A Matrix'!$D$3:$GU$3='Cement and Glass Split'!E$2,'Exiobase A Matrix'!$D$4:$GU$203)))} -> 0.0064464491 | F10: {=SUMPRODUCT(IF('Exiobase A Matrix'!$C$4:$C$203='Cement and Glass Split'!$A10,IF('Exiobase A Matrix'!$D$3:$GU$3='Cement and Glass Split'!F$2,'Exiobase A Matrix'!$D$4:$GU$203)))} -> 0 | G10: {=SUMPRODUCT(IF('Exiobase A Matrix'!$C$4:$C$203='Cement and Glass Split'!$A10,IF('Exiobase A Matrix'!$D$3:$GU$3='Cement and Glass Split'!G$2,'Exiobase A Matrix'!$D$4:$GU$203)))} -> 0.020888401 | H10: {=SUMPRODUCT(IF('Exiobase A Matrix'!$C$4:$C$203='Cement and Glass Split'!$A10,IF('Exiobase A Matrix'!$D$3:$GU$3='Cement and Glass Split'!H$2,'Exiobase A Matrix'!$D$4:$GU$203)))} -> 0.0007277073 | I10: {=SUMPRODUCT(IF('Exiobase A Matrix'!$C$4:$C$203='Cement and Glass Split'!$A10,IF('Exiobase A Matrix'!$D$3:$GU$3='Cement and Glass Split'!I$2,'Exiobase A Matrix'!$D$4:$GU$203)))} -> 0.24197373 | ... AQ10: {=SUMPRODUCT(IF('Exiobase A Matrix'!$C$4:$C$203='Cement and Glass Split'!$A10,IF('Exiobase A Matrix'!$D$3:$GU$3='Cement and Glass Split'!AQ$2,'Exiobase A Matrix'!$D$4:$GU$203)))} -> 0
A11: ISIC 17T18 | B11: {=SUMPRODUCT(IF('Exiobase A Matrix'!$C$4:$C$203='Cement and Glass Split'!$A11,IF('Exiobase A Matrix'!$D$3:$GU$3='Cement and Glass Split'!B$2,'Exiobase A Matrix'!$D$4:$GU$203)))} -> 0.037372673 | C11: {=SUMPRODUCT(IF('Exiobase A Matrix'!$C$4:$C$203='Cement and Glass Split'!$A11,IF('Exiobase A Matrix'!$D$3:$GU$3='Cement and Glass Split'!C$2,'Exiobase A Matrix'!$D$4:$GU$203)))} -> 0.00076277765 | D11: {=SUMPRODUCT(IF('Exiobase A Matrix'!$C$4:$C$203='Cement and Glass Split'!$A11,IF('Exiobase A Matrix'!$D$3:$GU$3='Cement and Glass Split'!D$2,'Exiobase A Matrix'!$D$4:$GU$203)))} -> 3.6911328e-06 | E11: {=SUMPRODUCT(IF('Exiobase A Matrix'!$C$4:$C$203='Cement and Glass Split'!$A11,IF('Exiobase A Matrix'!$D$3:$GU$3='Cement and Glass Split'!E$2,'Exiobase A Matrix'!$D$4:$GU$203)))} -> 0.00050383511 | F11: {=SUMPRODUCT(IF('Exiobase A Matrix'!$C$4:$C$203='Cement and Glass Split'!$A11,IF('Exiobase A Matrix'!$D$3:$GU$3='Cement and Glass Split'!F$2,'Exiobase A Matrix'!$D$4:$GU$203)))} -> 0 | G11: {=SUMPRODUCT(IF('Exiobase A Matrix'!$C$4:$C$203='Cement and Glass Split'!$A11,IF('Exiobase A Matrix'!$D$3:$GU$3='Cement and Glass Split'!G$2,'Exiobase A Matrix'!$D$4:$GU$203)))} -> 0.20700851 | H11: {=SUMPRODUCT(IF('Exiobase A Matrix'!$C$4:$C$203='Cement and Glass Split'!$A11,IF('Exiobase A Matrix'!$D$3:$GU$3='Cement and Glass Split'!H$2,'Exiobase A Matrix'!$D$4:$GU$203)))} -> 0.047180455 | I11: {=SUMPRODUCT(IF('Exiobase A Matrix'!$C$4:$C$203='Cement and Glass Split'!$A11,IF('Exiobase A Matrix'!$D$3:$GU$3='Cement and Glass Split'!I$2,'Exiobase A Matrix'!$D$4:$GU$203)))} -> 0.0090697457 | ... AQ11: {=SUMPRODUCT(IF('Exiobase A Matrix'!$C$4:$C$203='Cement and Glass Split'!$A11,IF('Exiobase A Matrix'!$D$3:$GU$3='Cement and Glass Split'!AQ$2,'Exiobase A Matrix'!$D$4:$GU$203)))} -> 2.524581e-06
A12: ISIC 19 | B12: {=SUMPRODUCT(IF('Exiobase A Matrix'!$C$4:$C$203='Cement and Glass Split'!$A12,IF('Exiobase A Matrix'!$D$3:$GU$3='Cement and Glass Split'!B$2,'Exiobase A Matrix'!$D$4:$GU$203)))} -> 0.05381433 | C12: {=SUMPRODUCT(IF('Exiobase A Matrix'!$C$4:$C$203='Cement and Glass Split'!$A12,IF('Exiobase A Matrix'!$D$3:$GU$3='Cement and Glass Split'!C$2,'Exiobase A Matrix'!$D$4:$GU$203)))} -> 0.0003272535 | D12: {=SUMPRODUCT(IF('Exiobase A Matrix'!$C$4:$C$203='Cement and Glass Split'!$A12,IF('Exiobase A Matrix'!$D$3:$GU$3='Cement and Glass Split'!D$2,'Exiobase A Matrix'!$D$4:$GU$203)))} -> 5.1871057e-05 | E12: {=SUMPRODUCT(IF('Exiobase A Matrix'!$C$4:$C$203='Cement and Glass Split'!$A12,IF('Exiobase A Matrix'!$D$3:$GU$3='Cement and Glass Split'!E$2,'Exiobase A Matrix'!$D$4:$GU$203)))} -> 0.024987465 | F12: {=SUMPRODUCT(IF('Exiobase A Matrix'!$C$4:$C$203='Cement and Glass Split'!$A12,IF('Exiobase A Matrix'!$D$3:$GU$3='Cement and Glass Split'!F$2,'Exiobase A Matrix'!$D$4:$GU$203)))} -> 0 | G12: {=SUMPRODUCT(IF('Exiobase A Matrix'!$C$4:$C$203='Cement and Glass Split'!$A12,IF('Exiobase A Matrix'!$D$3:$GU$3='Cement and Glass Split'!G$2,'Exiobase A Matrix'!$D$4:$GU$203)))} -> 0.0049728888 | H12: {=SUMPRODUCT(IF('Exiobase A Matrix'!$C$4:$C$203='Cement and Glass Split'!$A12,IF('Exiobase A Matrix'!$D$3:$GU$3='Cement and Glass Split'!H$2,'Exiobase A Matrix'!$D$4:$GU$203)))} -> 0.0015032452 | I12: {=SUMPRODUCT(IF('Exiobase A Matrix'!$C$4:$C$203='Cement and Glass Split'!$A12,IF('Exiobase A Matrix'!$D$3:$GU$3='Cement and Glass Split'!I$2,'Exiobase A Matrix'!$D$4:$GU$203)))} -> 0.0013251267 | ... AQ12: {=SUMPRODUCT(IF('Exiobase A Matrix'!$C$4:$C$203='Cement and Glass Split'!$A12,IF('Exiobase A Matrix'!$D$3:$GU$3='Cement and Glass Split'!AQ$2,'Exiobase A Matrix'!$D$4:$GU$203)))} -> 2.2228261e-05
A13: ISIC 20 | B13: {=SUMPRODUCT(IF('Exiobase A Matrix'!$C$4:$C$203='Cement and Glass Split'!$A13,IF('Exiobase A Matrix'!$D$3:$GU$3='Cement and Glass Split'!B$2,'Exiobase A Matrix'!$D$4:$GU$203)))} -> 0.76873938 | C13: {=SUMPRODUCT(IF('Exiobase A Matrix'!$C$4:$C$203='Cement and Glass Split'!$A13,IF('Exiobase A Matrix'!$D$3:$GU$3='Cement and Glass Split'!C$2,'Exiobase A Matrix'!$D$4:$GU$203)))} -> 0.0016845497 | D13: {=SUMPRODUCT(IF('Exiobase A Matrix'!$C$4:$C$203='Cement and Glass Split'!$A13,IF('Exiobase A Matrix'!$D$3:$GU$3='Cement and Glass Split'!D$2,'Exiobase A Matrix'!$D$4:$GU$203)))} -> 5.6474054e-05 | E13: {=SUMPRODUCT(IF('Exiobase A Matrix'!$C$4:$C$203='Cement and Glass Split'!$A13,IF('Exiobase A Matrix'!$D$3:$GU$3='Cement and Glass Split'!E$2,'Exiobase A Matrix'!$D$4:$GU$203)))} -> 0.011768454 | F13: {=SUMPRODUCT(IF('Exiobase A Matrix'!$C$4:$C$203='Cement and Glass Split'!$A13,IF('Exiobase A Matrix'!$D$3:$GU$3='Cement and Glass Split'!F$2,'Exiobase A Matrix'!$D$4:$GU$203)))} -> 0 | G13: {=SUMPRODUCT(IF('Exiobase A Matrix'!$C$4:$C$203='Cement and Glass Split'!$A13,IF('Exiobase A Matrix'!$D$3:$GU$3='Cement and Glass Split'!G$2,'Exiobase A Matrix'!$D$4:$GU$203)))} -> 0.017343474 | H13: {=SUMPRODUCT(IF('Exiobase A Matrix'!$C$4:$C$203='Cement and Glass Split'!$A13,IF('Exiobase A Matrix'!$D$3:$GU$3='Cement and Glass Split'!H$2,'Exiobase A Matrix'!$D$4:$GU$203)))} -> 0.050300566 | I13: {=SUMPRODUCT(IF('Exiobase A Matrix'!$C$4:$C$203='Cement and Glass Split'!$A13,IF('Exiobase A Matrix'!$D$3:$GU$3='Cement and Glass Split'!I$2,'Exiobase A Matrix'!$D$4:$GU$203)))} -> 0.01951789 | ... AQ13: {=SUMPRODUCT(IF('Exiobase A Matrix'!$C$4:$C$203='Cement and Glass Split'!$A13,IF('Exiobase A Matrix'!$D$3:$GU$3='Cement and Glass Split'!AQ$2,'Exiobase A Matrix'!$D$4:$GU$203)))} -> 0.00010529028
A14: ISIC 21 | B14: {=SUMPRODUCT(IF('Exiobase A Matrix'!$C$4:$C$203='Cement and Glass Split'!$A14,IF('Exiobase A Matrix'!$D$3:$GU$3='Cement and Glass Split'!B$2,'Exiobase A Matrix'!$D$4:$GU$203)))} -> 0 | C14: {=SUMPRODUCT(IF('Exiobase A Matrix'!$C$4:$C$203='Cement and Glass Split'!$A14,IF('Exiobase A Matrix'!$D$3:$GU$3='Cement and Glass Split'!C$2,'Exiobase A Matrix'!$D$4:$GU$203)))} -> 0 | D14: {=SUMPRODUCT(IF('Exiobase A Matrix'!$C$4:$C$203='Cement and Glass Split'!$A14,IF('Exiobase A Matrix'!$D$3:$GU$3='Cement and Glass Split'!D$2,'Exiobase A Matrix'!$D$4:$GU$203)))} -> 0 | E14: {=SUMPRODUCT(IF('Exiobase A Matrix'!$C$4:$C$203='Cement and Glass Split'!$A14,IF('Exiobase A Matrix'!$D$3:$GU$3='Cement and Glass Split'!E$2,'Exiobase A Matrix'!$D$4:$GU$203)))} -> 0 | F14: {=SUMPRODUCT(IF('Exiobase A Matrix'!$C$4:$C$203='Cement and Glass Split'!$A14,IF('Exiobase A Matrix'!$D$3:$GU$3='Cement and Glass Split'!F$2,'Exiobase A Matrix'!$D$4:$GU$203)))} -> 0 | G14: {=SUMPRODUCT(IF('Exiobase A Matrix'!$C$4:$C$203='Cement and Glass Split'!$A14,IF('Exiobase A Matrix'!$D$3:$GU$3='Cement and Glass Split'!G$2,'Exiobase A Matrix'!$D$4:$GU$203)))} -> 0 | H14: {=SUMPRODUCT(IF('Exiobase A Matrix'!$C$4:$C$203='Cement and Glass Split'!$A14,IF('Exiobase A Matrix'!$D$3:$GU$3='Cement and Glass Split'!H$2,'Exiobase A Matrix'!$D$4:$GU$203)))} -> 0 | I14: {=SUMPRODUCT(IF('Exiobase A Matrix'!$C$4:$C$203='Cement and Glass Split'!$A14,IF('Exiobase A Matrix'!$D$3:$GU$3='Cement and Glass Split'!I$2,'Exiobase A Matrix'!$D$4:$GU$203)))} -> 0 | ... AQ14: {=SUMPRODUCT(IF('Exiobase A Matrix'!$C$4:$C$203='Cement and Glass Split'!$A14,IF('Exiobase A Matrix'!$D$3:$GU$3='Cement and Glass Split'!AQ$2,'Exiobase A Matrix'!$D$4:$GU$203)))} -> 0
... A44: ISIC 97T98 | B44: {=SUMPRODUCT(IF('Exiobase A Matrix'!$C$4:$C$203='Cement and Glass Split'!$A44,IF('Exiobase A Matrix'!$D$3:$GU$3='Cement and Glass Split'!B$2,'Exiobase A Matrix'!$D$4:$GU$203)))} -> 0 | C44: {=SUMPRODUCT(IF('Exiobase A Matrix'!$C$4:$C$203='Cement and Glass Split'!$A44,IF('Exiobase A Matrix'!$D$3:$GU$3='Cement and Glass Split'!C$2,'Exiobase A Matrix'!$D$4:$GU$203)))} -> 0.00014701858 | D44: {=SUMPRODUCT(IF('Exiobase A Matrix'!$C$4:$C$203='Cement and Glass Split'!$A44,IF('Exiobase A Matrix'!$D$3:$GU$3='Cement and Glass Split'!D$2,'Exiobase A Matrix'!$D$4:$GU$203)))} -> 1.6300791e-05 | E44: {=SUMPRODUCT(IF('Exiobase A Matrix'!$C$4:$C$203='Cement and Glass Split'!$A44,IF('Exiobase A Matrix'!$D$3:$GU$3='Cement and Glass Split'!E$2,'Exiobase A Matrix'!$D$4:$GU$203)))} -> 0.00058318603 | F44: {=SUMPRODUCT(IF('Exiobase A Matrix'!$C$4:$C$203='Cement and Glass Split'!$A44,IF('Exiobase A Matrix'!$D$3:$GU$3='Cement and Glass Split'!F$2,'Exiobase A Matrix'!$D$4:$GU$203)))} -> 0 | G44: {=SUMPRODUCT(IF('Exiobase A Matrix'!$C$4:$C$203='Cement and Glass Split'!$A44,IF('Exiobase A Matrix'!$D$3:$GU$3='Cement and Glass Split'!G$2,'Exiobase A Matrix'!$D$4:$GU$203)))} -> 0 | H44: {=SUMPRODUCT(IF('Exiobase A Matrix'!$C$4:$C$203='Cement and Glass Split'!$A44,IF('Exiobase A Matrix'!$D$3:$GU$3='Cement and Glass Split'!H$2,'Exiobase A Matrix'!$D$4:$GU$203)))} -> 0 | I44: {=SUMPRODUCT(IF('Exiobase A Matrix'!$C$4:$C$203='Cement and Glass Split'!$A44,IF('Exiobase A Matrix'!$D$3:$GU$3='Cement and Glass Split'!I$2,'Exiobase A Matrix'!$D$4:$GU$203)))} -> 0 | ... AQ44: {=SUMPRODUCT(IF('Exiobase A Matrix'!$C$4:$C$203='Cement and Glass Split'!$A44,IF('Exiobase A Matrix'!$D$3:$GU$3='Cement and Glass Split'!AQ$2,'Exiobase A Matrix'!$D$4:$GU$203)))} -> 2.369287e-06
A46: Proportional shares for non-metallic minerals
B47: ISIC 01T03 | C47: ISIC 05 | D47: ISIC 06 | E47: ISIC 07T08 | F47: ISIC 09 | G47: ISIC 10T12 | H47: ISIC 13T15 | I47: ISIC 16 | J47: ISIC 17T18 | K47: ISIC 19 | L47: ISIC 20 | M47: ISIC 21 | N47: ISIC 22 | O47: ISIC 231 | P47: ISIC 239 | Q47: ISIC 241 | R47: ISIC 242 | S47: ISIC 25 | T47: ISIC 26 | U47: ISIC 27 | V47: ISIC 28 | W47: ISIC 29 | X47: ISIC 30 | Y47: ISIC 31T33 | Z47: ISIC 351 | AA47: ISIC 352T353 | AB47: ISIC 36T39 | AC47: ISIC 41T43 | AD47: ISIC 45T47 | AE47: ISIC 49T53 | AF47: ISIC 55T56 | AG47: ISIC 58T60 | AH47: ISIC 61 | AI47: ISIC 62T63 | AJ47: ISIC 64T66 | AK47: ISIC 68 | AL47: ISIC 69T82 | AM47: ISIC 84 | AN47: ISIC 85 | AO47: ISIC 86T88 | AP47: ISIC 90T96 | AQ47: ISIC 97T98
A48: ISIC 01T03 | O48: =IFERROR(O3/SUM(O3:P3),0) -> 0 | P48: =IFERROR(P3/SUM(O3:P3),0) -> 0
A49: ISIC 05 | O49: =IFERROR(O4/SUM(O4:P4),0) -> 0 | P49: =IFERROR(P4/SUM(O4:P4),0) -> 0
A50: ISIC 06 | O50: =IFERROR(O5/SUM(O5:P5),0) -> 0.011723421 | P50: =IFERROR(P5/SUM(O5:P5),0) -> 0.98827658
A51: ISIC 07T08 | O51: =IFERROR(O6/SUM(O6:P6),0) -> 0.011954715 | P51: =IFERROR(P6/SUM(O6:P6),0) -> 0.98804528
A52: ISIC 09 | O52: =IFERROR(O7/SUM(O7:P7),0) -> 0 | P52: =IFERROR(P7/SUM(O7:P7),0) -> 0
A53: ISIC 10T12 | O53: =IFERROR(O8/SUM(O8:P8),0) -> 0 | P53: =IFERROR(P8/SUM(O8:P8),0) -> 1
A54: ISIC 13T15 | O54: =IFERROR(O9/SUM(O9:P9),0) -> 0.18874206 | P54: =IFERROR(P9/SUM(O9:P9),0) -> 0.81125794
A55: ISIC 16 | O55: =IFERROR(O10/SUM(O10:P10),0) -> 0.23675036 | P55: =IFERROR(P10/SUM(O10:P10),0) -> 0.76324964
A56: ISIC 17T18 | O56: =IFERROR(O11/SUM(O11:P11),0) -> 0.15495407 | P56: =IFERROR(P11/SUM(O11:P11),0) -> 0.84504593
A57: ISIC 19 | O57: =IFERROR(O12/SUM(O12:P12),0) -> 0.18051426 | P57: =IFERROR(P12/SUM(O12:P12),0) -> 0.81948574
A58: ISIC 20 | O58: =IFERROR(O13/SUM(O13:P13),0) -> 0.91807233 | P58: =IFERROR(P13/SUM(O13:P13),0) -> 0.081927666
A59: ISIC 21 | O59: =IFERROR(O14/SUM(O14:P14),0) -> 0 | P59: =IFERROR(P14/SUM(O14:P14),0) -> 0
A60: ISIC 22 | O60: =IFERROR(O15/SUM(O15:P15),0) -> 0.5692734 | P60: =IFERROR(P15/SUM(O15:P15),0) -> 0.4307266
A61: ISIC 231 | B61: =IFERROR(B16/SUM(B16:B17),0) -> 0.7952041 | C61: =IFERROR(C16/SUM(C16:C17),0) -> 0.15078448 | D61: =IFERROR(D16/SUM(D16:D17),0) -> 0.00053171086 | E61: =IFERROR(E16/SUM(E16:E17),0) -> 0.51240388 | F61: =IFERROR(F16/SUM(F16:F17),0) -> 0 | G61: =IFERROR(G16/SUM(G16:G17),0) -> 0.99679585 | H61: =IFERROR(H16/SUM(H16:H17),0) -> 0.60083467 | I61: =IFERROR(I16/SUM(I16:I17),0) -> 0.19726537 | ... N61: =IFERROR(N16/SUM(N16:N17),0) -> 0.84573168 | O61: =O16/SUM($O$16:$P$17) -> 0.17512941 | P61: =P16/SUM($O$16:$P$17) -> 0.0012980402 | Q61: =IFERROR(Q16/SUM(Q16:Q17),0) -> 0.001678174 | R61: =IFERROR(R16/SUM(R16:R17),0) -> 0.018775534 | S61: =IFERROR(S16/SUM(S16:S17),0) -> 0.20801468 | T61: =IFERROR(T16/SUM(T16:T17),0) -> 0.92700902 | U61: =IFERROR(U16/SUM(U16:U17),0) -> 0.54377225 | V61: =IFERROR(V16/SUM(V16:V17),0) -> 0.37427783 | W61: =IFERROR(W16/SUM(W16:W17),0) -> 0.77979514 | X61: =IFERROR(X16/SUM(X16:X17),0) -> 0.42445753 | ... AQ61: =IFERROR(AQ16/SUM(AQ16:AQ17),0) -> 0.99976119
A62: ISIC 239 | B62: =IFERROR(B17/SUM(B17:B18),0) -> 0.1006087 | C62: =IFERROR(C17/SUM(C17:C18),0) -> 0.022319 | D62: =IFERROR(D17/SUM(D17:D18),0) -> 0.24518967 | E62: =IFERROR(E17/SUM(E17:E18),0) -> 0.0063399695 | F62: =IFERROR(F17/SUM(F17:F18),0) -> 0 | G62: =IFERROR(G17/SUM(G17:G18),0) -> 0.18013922 | H62: =IFERROR(H17/SUM(H17:H18),0) -> 0.95154979 | I62: =IFERROR(I17/SUM(I17:I18),0) -> 0.87830014 | ... N62: =IFERROR(N17/SUM(N17:N18),0) -> 0.2621003 | O62: =O17/SUM($O$16:$P$17) -> 0.012383838 | P62: =P17/SUM($O$16:$P$17) -> 0.81118871 | Q62: =IFERROR(Q17/SUM(Q17:Q18),0) -> 0.020203268 | R62: =IFERROR(R17/SUM(R17:R18),0) -> 0.30533546 | S62: =IFERROR(S17/SUM(S17:S18),0) -> 0.0073536935 | T62: =IFERROR(T17/SUM(T17:T18),0) -> 0.15153198 | U62: =IFERROR(U17/SUM(U17:U18),0) -> 0.11757343 | V62: =IFERROR(V17/SUM(V17:V18),0) -> 0.013665886 | W62: =IFERROR(W17/SUM(W17:W18),0) -> 0.025139701 | X62: =IFERROR(X17/SUM(X17:X18),0) -> 0.13849638 | ... AQ62: =IFERROR(AQ17/SUM(AQ17:AQ18),0) -> 0.66734536
A63: ISIC 241 | O63: =IFERROR(O18/SUM(O18:P18),0) -> 0.068469002 | P63: =IFERROR(P18/SUM(O18:P18),0) -> 0.931531
A64: ISIC 242 | O64: =IFERROR(O19/SUM(O19:P19),0) -> 0.17598674 | P64: =IFERROR(P19/SUM(O19:P19),0) -> 0.82401326
A65: ISIC 25 | O65: =IFERROR(O20/SUM(O20:P20),0) -> 0.36832634 | P65: =IFERROR(P20/SUM(O20:P20),0) -> 0.63167366
A66: ISIC 26 | O66: =IFERROR(O21/SUM(O21:P21),0) -> 0.37503467 | P66: =IFERROR(P21/SUM(O21:P21),0) -> 0.62496533
A67: ISIC 27 | O67: =IFERROR(O22/SUM(O22:P22),0) -> 0.42542879 | P67: =IFERROR(P22/SUM(O22:P22),0) -> 0.57457121
A68: ISIC 28 | O68: =IFERROR(O23/SUM(O23:P23),0) -> 0.34585479 | P68: =IFERROR(P23/SUM(O23:P23),0) -> 0.65414521
A69: ISIC 29 | O69: =IFERROR(O24/SUM(O24:P24),0) -> 0.079793825 | P69: =IFERROR(P24/SUM(O24:P24),0) -> 0.92020618
A70: ISIC 30 | O70: =IFERROR(O25/SUM(O25:P25),0) -> 0.36933609 | P70: =IFERROR(P25/SUM(O25:P25),0) -> 0.63066391
A71: ISIC 31T33 | O71: =IFERROR(O26/SUM(O26:P26),0) -> 0.5505639 | P71: =IFERROR(P26/SUM(O26:P26),0) -> 0.4494361
A72: ISIC 351 | O72: =IFERROR(O27/SUM(O27:P27),0) -> 0.16868532 | P72: =IFERROR(P27/SUM(O27:P27),0) -> 0.83131468
A73: ISIC 352T353 | O73: =IFERROR(O28/SUM(O28:P28),0) -> 0.99930587 | P73: =IFERROR(P28/SUM(O28:P28),0) -> 0.00069413015
A74: ISIC 36T39 | O74: =IFERROR(O29/SUM(O29:P29),0) -> 0.99260528 | P74: =IFERROR(P29/SUM(O29:P29),0) -> 0.0073947174
... A89: ISIC 97T98 | O89: =IFERROR(O44/SUM(O44:P44),0) -> 0 | P89: =IFERROR(P44/SUM(O44:P44),0) -> 0
A90: Output | O90: =SUM(O3:O44)/SUM($O$3:$P$44) -> 0.1498267 | P90: =SUM(P3:P44)/SUM($O$3:$P$44) -> 0.8501733

Sheet Reaggregated
A1: Original Output and Imports Matrices
C2: A01 | D2: A02 | E2: A03 | F2: B05 | G2: B06 | H2: B07 | I2: B08 | J2: B09 | K2: C10T12 | L2: C13T15 | M2: C16 | N2: C17_18 | O2: C19 | P2: C20 | Q2: C21 | R2: C22 | S2: C23 | T2: C24A | U2: C24B | V2: C25 | W2: C26 | X2: C27 | Y2: C28 | Z2: C29 | AA2: C301 | AB2: C302T309 | AC2: C31T33 | AD2: D | AE2: E | AF2: F | AG2: G | AH2: H49 | AI2: H50 | AJ2: H51 | AK2: H52 | AL2: H53 | AM2: I | AN2: J58T60 | AO2: J61 | AP2: J62_63 | AQ2: K | AR2: L | AS2: M | AT2: N | AU2: O | AV2: P | AW2: Q | AX2: R | AY2: S | AZ2: T | BA2: TOTAL
C3: =INDEX('ISIC Crosswalk'!$D$2:$D$61,MATCH(C2,'ISIC Crosswalk'!$E$2:$E$61,0),1) -> ISIC 01T03 | D3: =INDEX('ISIC Crosswalk'!$D$2:$D$61,MATCH(D2,'ISIC Crosswalk'!$E$2:$E$61,0),1) -> ISIC 01T03 | E3: =INDEX('ISIC Crosswalk'!$D$2:$D$61,MATCH(E2,'ISIC Crosswalk'!$E$2:$E$61,0),1) -> ISIC 01T03 | F3: =INDEX('ISIC Crosswalk'!$D$2:$D$61,MATCH(F2,'ISIC Crosswalk'!$E$2:$E$61,0),1) -> ISIC 05 | G3: =INDEX('ISIC Crosswalk'!$D$2:$D$61,MATCH(G2,'ISIC Crosswalk'!$E$2:$E$61,0),1) -> ISIC 06 | H3: =INDEX('ISIC Crosswalk'!$D$2:$D$61,MATCH(H2,'ISIC Crosswalk'!$E$2:$E$61,0),1) -> ISIC 07T08 | I3: =INDEX('ISIC Crosswalk'!$D$2:$D$61,MATCH(I2,'ISIC Crosswalk'!$E$2:$E$61,0),1) -> ISIC 07T08 | J3: =INDEX('ISIC Crosswalk'!$D$2:$D$61,MATCH(J2,'ISIC Crosswalk'!$E$2:$E$61,0),1) -> ISIC 09 | ... AZ3: =INDEX('ISIC Crosswalk'!$D$2:$D$61,MATCH(AZ2,'ISIC Crosswalk'!$E$2:$E$61,0),1) -> ISIC 97T98
A4: DOM_A01 | B4: =INDEX('ISIC Crosswalk'!$D$2:$D$107,MATCH(A4,'ISIC Crosswalk'!$A$2:$A$107,0),1) -> ISIC 01T03 | C4: 2972.944 | D4: 35.361 | E4: 53.443 | F4: 0.014 | G4: 0.004 | H4: 0.003 | I4: 0.545 | J4: 0.001 | K4: 20981.346 | L4: 486.111 | M4: 11.969 | N4: 4.086 | O4: 0.355 | P4: 251.497 | Q4: 47.453 | R4: 81.025 | S4: 0.994 | T4: 0.44 | U4: 0.431 | V4: 0.947 | W4: 4.885 | X4: 1.437 | Y4: 6.793 | Z4: 3.345 | AA4: 0.898 | AB4: 0.23 | AC4: 13.723 | AD4: 22.533 | AE4: 5.306 | AF4: 54.845 | AG4: 407.723 | AH4: 2.029 | AI4: 4.886 | AJ4: 0.153 | AK4: 6.918 | AL4: 0.603 | AM4: 4458.133 | AN4: 2.633 | AO4: 0.828 | AP4: 0.472 | AQ4: 2.057 | AR4: 8.563 | AS4: 49.211 | AT4: 36.942 | AU4: 47.886 | AV4: 58.946 | AW4: 147.215 | AX4: 31.316 | AY4: 46.865 | AZ4: 0 | BA4: =OECD_KOR2022dom!BI2 -> 45071.583
A5: DOM_A02 | B5: =INDEX('ISIC Crosswalk'!$D$2:$D$107,MATCH(A5,'ISIC Crosswalk'!$A$2:$A$107,0),1) -> ISIC 01T03 | C5: 72.761 | D5: 351.459 | E5: 2.964 | F5: 0.16 | G5: 0.006 | H5: 0.008 | I5: 0.435 | J5: 0 | K5: 219.116 | L5: 14.913 | M5: 935.907 | N5: 133.583 | O5: 0.292 | P5: 31.253 | Q5: 1.54 | R5: 90.787 | S5: 4.381 | T5: 2.099 | U5: 1.287 | V5: 0.912 | W5: 0.852 | X5: 0.614 | Y5: 1.65 | Z5: 0.804 | AA5: 1.018 | AB5: 0.074 | AC5: 67.519 | AD5: 80.406 | AE5: 0.329 | AF5: 39.76 | AG5: 29.508 | AH5: 0.176 | AI5: 0.472 | AJ5: 0.116 | AK5: 0.647 | AL5: 0.138 | AM5: 80.7 | AN5: 0.79 | AO5: 0.559 | AP5: 0.54 | AQ5: 0.827 | AR5: 3.732 | AS5: 1.942 | AT5: 1.71 | AU5: 11.379 | AV5: 5.899 | AW5: 5.161 | AX5: 5.906 | AY5: 4.617 | AZ5: 0 | BA5: =OECD_KOR2022dom!BI3 -> 3082.931
A6: DOM_A03 | B6: =INDEX('ISIC Crosswalk'!$D$2:$D$107,MATCH(A6,'ISIC Crosswalk'!$A$2:$A$107,0),1) -> ISIC 01T03 | C6: 4.855 | D6: 0.448 | E6: 431.333 | F6: 0.003 | G6: 0 | H6: 0.001 | I6: 0.045 | J6: 0 | K6: 2711.583 | L6: 0.912 | M6: 0.03 | N6: 0.088 | O6: 0.121 | P6: 2.273 | Q6: 0.41 | R6: 0.252 | S6: 0.161 | T6: 0.136 | U6: 0.125 | V6: 0.307 | W6: 0.607 | X6: 0.314 | Y6: 0.469 | Z6: 0.183 | AA6: 0.192 | AB6: 0.012 | AC6: 0.149 | AD6: 0.215 | AE6: 0.097 | AF6: 0.784 | AG6: 40.507 | AH6: 0.087 | AI6: 1.421 | AJ6: 0.035 | AK6: 0.358 | AL6: 0.004 | AM6: 1256.01 | AN6: 0.518 | AO6: 0.175 | AP6: 0.352 | AQ6: 0.686 | AR6: 1.094 | AS6: 1.13 | AT6: 0.297 | AU6: 11.728 | AV6: 4.604 | AW6: 12.708 | AX6: 1.67 | AY6: 2.656 | AZ6: 0 | BA6: =OECD_KOR2022dom!BI4 -> 7613.625
A7: DOM_B05 | B7: =INDEX('ISIC Crosswalk'!$D$2:$D$107,MATCH(A7,'ISIC Crosswalk'!$A$2:$A$107,0),1) -> ISIC 05 | C7: 0.143 | D7: 0.007 | E7: 0.039 | F7: 0.244 | G7: 0 | H7: 0 | I7: 0.02 | J7: 0 | K7: 0.427 | L7: 0.214 | M7: 0.025 | N7: 0.112 | O7: 24.173 | P7: 0.627 | Q7: 0.07 | R7: 0.213 | S7: 0.159 | T7: 0.391 | U7: 0.134 | V7: 0.258 | W7: 0.773 | X7: 0.289 | Y7: 0.432 | Z7: 0.394 | AA7: 0.095 | AB7: 0.037 | AC7: 0.095 | AD7: 208.802 | AE7: 0.072 | AF7: 0.458 | AG7: 0.348 | AH7: 0.06 | AI7: 0.122 | AJ7: 0.09 | AK7: 0.103 | AL7: 0.014 | AM7: 0.316 | AN7: 0.03 | AO7: 0.075 | AP7: 0.043 | AQ7: 0.038 | AR7: 0.084 | AS7: 0.169 | AT7: 0.085 | AU7: 0.126 | AV7: 0.103 | AW7: 0.192 | AX7: 0.047 | AY7: 0.09 | AZ7: 0 | BA7: =OECD_KOR2022dom!BI5 -> 257.663
A8: DOM_B06 | B8: =INDEX('ISIC Crosswalk'!$D$2:$D$107,MATCH(A8,'ISIC Crosswalk'!$A$2:$A$107,0),1) -> ISIC 06 | C8: 0.037 | D8: 0.001 | E8: 0.008 | F8: 0 | G8: 0.008 | H8: 0 | I8: 0.003 | J8: 0 | K8: 0.164 | L8: 0.109 | M8: 0.009 | N8: 0.04 | O8: 102.895 | P8: 0.292 | Q8: 0.034 | R8: 0.106 | S8: 0.048 | T8: 0.11 | U8: 0.032 | V8: 0.098 | W8: 0.433 | X8: 0.14 | Y8: 0.181 | Z8: 0.157 | AA8: 0.044 | AB8: 0.011 | AC8: 0.03 | AD8: 29.374 | AE8: 0.01 | AF8: 0.201 | AG8: 0.111 | AH8: 0.016 | AI8: 0.029 | AJ8: 0.014 | AK8: 0.022 | AL8: 0.004 | AM8: 0.125 | AN8: 0.013 | AO8: 0.019 | AP8: 0.01 | AQ8: 0.009 | AR8: 0.022 | AS8: 0.038 | AT8: 0.017 | AU8: 0.025 | AV8: 0.02 | AW8: 0.08 | AX8: 0.01 | AY8: 0.031 | AZ8: 0 | BA8: =OECD_KOR2022dom!BI6 -> 139.391
A9: DOM_B07 | B9: =INDEX('ISIC Crosswalk'!$D$2:$D$107,MATCH(A9,'ISIC Crosswalk'!$A$2:$A$107,0),1) -> ISIC 07T08 | C9: 0.015 | D9: 0.001 | E9: 0.001 | F9: 0.001 | G9: 0 | H9: 0.007 | I9: 0.049 | J9: 0 | K9: 0.134 | L9: 0.023 | M9: 0.012 | N9: 0.013 | O9: 0.208 | P9: 0.691 | Q9: 0.018 | R9: 0.129 | S9: 0.93 | T9: 13.709 | U9: 12.837 | V9: 3.121 | W9: 0.876 | X9: 1.269 | Y9: 1.825 | Z9: 1.616 | AA9: 0.365 | AB9: 0.12 | AC9: 0.179 | AD9: 0.246 | AE9: 0.083 | AF9: 2.979 | AG9: 0.08 | AH9: 0.004 | AI9: 0.008 | AJ9: 0 | AK9: 0.016 | AL9: 0.001 | AM9: 0.048 | AN9: 0.002 | AO9: 0.002 | AP9: 0.001 | AQ9: 0.005 | AR9: 0.175 | AS9: 0.062 | AT9: 0.01 | AU9: 0.014 | AV9: 0.02 | AW9: 0.013 | AX9: 0.007 | AY9: 0.036 | AZ9: 0 | BA9: =OECD_KOR2022dom!BI7 -> 119.787
A10: DOM_B08 | B10: =INDEX('ISIC Crosswalk'!$D$2:$D$107,MATCH(A10,'ISIC Crosswalk'!$A$2:$A$107,0),1) -> ISIC 07T08 | C10: 10.737 | D10: 0.34 | E10: 2.014 | F10: 0.222 | G10: 0.05 | H10: 0.166 | I10: 55.72 | J10: 0.024 | K10: 30.286 | L10: 4.576 | M10: 0.461 | N10: 11.305 | O10: 56.448 | P10: 296.881 | Q10: 1.547 | R10: 8.366 | S10: 850.052 | T10: 299.728 | U10: 92.038 | V10: 15.779 | W10: 9.831 | X10: 11.333 | Y10: 10.294 | Z10: 7.479 | AA10: 1.78 | AB10: 0.496 | AC10: 7.362 | AD10: 64.288 | AE10: 20.94 | AF10: 878.411 | AG10: 9.21 | AH10: 0.746 | AI10: 0.456 | AJ10: 0.159 | AK10: 1.768 | AL10: 0.346 | AM10: 9.259 | AN10: 0.427 | AO10: 0.46 | AP10: 0.297 | AQ10: 0.688 | AR10: 17.445 | AS10: 3.92 | AT10: 6.448 | AU10: 12.118 | AV10: 2.945 | AW10: 4.104 | AX10: 1.027 | AY10: 2.431 | AZ10: 0 | BA10: =OECD_KOR2022dom!BI8 -> 3274.282
A11: DOM_B09 | B11: =INDEX('ISIC Crosswalk'!$D$2:$D$107,MATCH(A11,'ISIC Crosswalk'!$A$2:$A$107,0),1) -> ISIC 09 | C11: 0.019 | D11: 0.001 | E11: 0.004 | F11: 0 | G11: 0 | H11: 0 | I11: 0.002 | J11: 0 | K11: 0.085 | L11: 0.056 | M11: 0.005 | N11: 0.021 | O11: 0.078 | P11: 0.149 | Q11: 0.018 | R11: 0.055 | S11: 0.025 | T11: 0.057 | U11: 0.017 | V11: 0.053 | W11: 0.225 | X11: 0.073 | Y11: 0.094 | Z11: 0.082 | AA11: 0.023 | AB11: 0.006 | AC11: 0.016 | AD11: 0.04 | AE11: 0.005 | AF11: 0.109 | AG11: 0.057 | AH11: 0.008 | AI11: 0.014 | AJ11: 0.006 | AK11: 0.011 | AL11: 0.002 | AM11: 0.064 | AN11: 0.007 | AO11: 0.01 | AP11: 0.005 | AQ11: 0.005 | AR11: 0.012 | AS11: 0.022 | AT11: 0.009 | AU11: 0.013 | AV11: 0.01 | AW11: 0.041 | AX11: 0.005 | AY11: 0.016 | AZ11: 0 | BA11: =OECD_KOR2022dom!BI9 -> 18.831
A12: DOM_C10T12 | B12: =INDEX('ISIC Crosswalk'!$D$2:$D$107,MATCH(A12,'ISIC Crosswalk'!$A$2:$A$107,0),1) -> ISIC 10T12 | C12: 3218.393 | D12: 5.526 | E12: 444.398 | F12: 0.179 | G12: 0.09 | H12: 0.096 | I12: 4.425 | J12: 0.012 | K12: 21114.006 | L12: 182.59 | M12: 7.488 | N12: 72.351 | O12: 38.615 | P12: 1315.58 | Q12: 190.093 | R12: 73.633 | S12: 26.308 | T12: 30.264 | U12: 24.391 | V12: 42.693 | W12: 72.797 | X12: 47.362 | Y12: 62.471 | Z12: 51.529 | AA12: 13.345 | AB12: 4.668 | AC12: 39.183 | AD12: 50.102 | AE12: 28.554 | AF12: 114.09 | AG12: 1570.638 | AH12: 22.63 | AI12: 101.817 | AJ12: 18.461 | AK12: 99.763 | AL12: 17.837 | AM12: 31471.801 | AN12: 99.323 | AO12: 46.775 | AP12: 61.488 | AQ12: 123.502 | AR12: 119.777 | AS12: 258.819 | AT12: 99.613 | AU12: 333.229 | AV12: 582.135 | AW12: 849.437 | AX12: 314.74 | AY12: 242.084 | AZ12: 0 | BA12: =OECD_KOR2022dom!BI10 -> 131256.51
A13: DOM_C13T15 | B13: =INDEX('ISIC Crosswalk'!$D$2:$D$107,MATCH(A13,'ISIC Crosswalk'!$A$2:$A$107,0),1) -> ISIC 13T15 | C13: 64.374 | D13: 5.77 | E13: 102.875 | F13: 0.779 | G13: 0.235 | H13: 0.252 | I13: 8.637 | J13: 0.034 | K13: 243.527 | L13: 19216.841 | M13: 30.851 | N13: 304.11 | O13: 43.169 | P13: 764.631 | Q13: 60.785 | R13: 665.717 | S13: 161.282 | T13: 105.87 | U13: 47.908 | V13: 187.597 | W13: 319.488 | X13: 195.749 | Y13: 285.355 | Z13: 1208.831 | AA13: 154.431 | AB13: 35.716 | AC13: 720.444 | AD13: 95.031 | AE13: 67.254 | AF13: 519.261 | AG13: 1401.572 | AH13: 23.638 | AI13: 25.239 | AJ13: 13.709 | AK13: 99.756 | AL13: 57.046 | AM13: 814.297 | AN13: 67.952 | AO13: 61.147 | AP13: 52.495 | AQ13: 111.832 | AR13: 190.967 | AS13: 463.648 | AT13: 296.569 | AU13: 578.686 | AV13: 293.469 | AW13: 732.823 | AX13: 324.525 | AY13: 759.089 | AZ13: 0 | BA13: =OECD_KOR2022dom!BI11 -> 66294.555
A14: DOM_C16 | B14: =INDEX('ISIC Crosswalk'!$D$2:$D$107,MATCH(A14,'ISIC Crosswalk'!$A$2:$A$107,0),1) -> ISIC 16 | C14: 36.229 | D14: 10.192 | E14: 5.386 | F14: 0.315 | G14: 0.037 | H14: 0.081 | I14: 2.983 | J14: 0.006 | K14: 154.832 | L14: 50.262 | M14: 1196.827 | N14: 238.841 | O14: 3.313 | P14: 192.434 | Q14: 8.134 | R14: 83.709 | S14: 120.84 | T14: 24.417 | U14: 27.056 | V14: 119.512 | W14: 85.124 | X14: 93.396 | Y14: 96.55 | Z14: 255.236 | AA14: 169.62 | AB14: 9.86 | AC14: 995.48 | AD14: 56.182 | AE14: 8.662 | AF14: 3116.772 | AG14: 237.433 | AH14: 5.87 | AI14: 2.759 | AJ14: 0.749 | AK14: 52.395 | AL14: 1.839 | AM14: 123.976 | AN14: 16.909 | AO14: 5.881 | AP14: 4.888 | AQ14: 8.778 | AR14: 400.117 | AS14: 94.387 | AT14: 34.966 | AU14: 16.905 | AV14: 34.61 | AW14: 38.352 | AX14: 17.745 | AY14: 134.887 | AZ14: 0 | BA14: =OECD_KOR2022dom!BI12 -> 8744.1
A15: DOM_C17_18 | B15: =INDEX('ISIC Crosswalk'!$D$2:$D$107,MATCH(A15,'ISIC Crosswalk'!$A$2:$A$107,0),1) -> ISIC 17T18 | C15: 66.752 | D15: 2.455 | E15: 24.406 | F15: 0.201 | G15: 0.161 | H15: 0.176 | I15: 4.715 | J15: 0.015 | K15: 2758.416 | L15: 390.263 | M15: 87.062 | N15: 9145.665 | O15: 35.847 | P15: 953.45 | Q15: 289.259 | R15: 483.944 | S15: 394.029 | T15: 91.489 | U15: 89.605 | V15: 328.865 | W15: 784.733 | X15: 448.036 | Y15: 439.358 | Z15: 436.558 | AA15: 61.945 | AB15: 32.108 | AC15: 345.262 | AD15: 130.358 | AE15: 62.601 | AF15: 375.129 | AG15: 2467.089 | AH15: 32.001 | AI15: 51.766 | AJ15: 9.81 | AK15: 165.621 | AL15: 149.527 | AM15: 795.265 | AN15: 3013.991 | AO15: 282.529 | AP15: 448.85 | AQ15: 1087.961 | AR15: 218.179 | AS15: 1843.31 | AT15: 624.389 | AU15: 1002.419 | AV15: 1535.534 | AW15: 721.227 | AX15: 289.363 | AY15: 572.94 | AZ15: 0 | BA15: =OECD_KOR2022dom!BI13 -> 39624.301
... A108: OUTPUT | B108: =INDEX('ISIC Crosswalk'!$D$2:$D$107,MATCH(A108,'ISIC Crosswalk'!$A$2:$A$107,0),1) -> 0 | C108: 45071.594 | D108: 3082.932 | E108: 7613.626 | F108: 257.663 | G108: 139.391 | H108: 119.787 | I108: 3274.283 | J108: 18.831 | K108: 131256.54 | L108: 66294.57 | M108: 8744.102 | N108: 39624.309 | O108: 156298.24 | P108: 219022.61 | Q108: 32883.371 | R108: 85333.618 | S108: 36219.597 | T108: 113509.79 | U108: 49961.975 | V108: 103590.67 | W108: 341950.93 | X108: 118568.59 | Y108: 149990.61 | Z108: 216241.53 | AA108: 34342.836 | AB108: 10468.098 | AC108: 28733.736 | AD108: 106796.65 | AE108: 25019.693 | AF108: 240135.2 | AG108: 289787.2 | AH108: 41931.631 | AI108: 34657.052 | AJ108: 26461.757 | AK108: 51699.144 | AL108: 18192.044 | AM108: 146964.53 | AN108: 53469.527 | AO108: 47660.154 | AP108: 54186.568 | AQ108: 170656.36 | AR108: 201279.03 | AS108: 202235.36 | AT108: 82380.945 | AU108: 158136.92 | AV108: 115880.3 | AW108: 144675.9 | AX108: 37679.349 | AY108: 54973.27 | AZ108: 2100.731 | BA108: =OECD_KOR2022dom!BI106 -> 4309573.2
A111: Consolidated Matrix to ISIC Codes
C112: ISIC 01T03 | D112: ISIC 05 | E112: ISIC 06 | F112: ISIC 07T08 | G112: ISIC 09 | H112: ISIC 10T12 | I112: ISIC 13T15 | J112: ISIC 16 | K112: ISIC 17T18 | L112: ISIC 19 | M112: ISIC 20 | N112: ISIC 21 | O112: ISIC 22 | P112: ISIC 231 | Q112: ISIC 239 | R112: ISIC 241 | S112: ISIC 242 | T112: ISIC 25 | U112: ISIC 26 | V112: ISIC 27 | W112: ISIC 28 | X112: ISIC 29 | Y112: ISIC 30 | Z112: ISIC 31T33 | AA112: ISIC 351 | AB112: ISIC 352T353 | AC112: ISIC 36T39 | AD112: ISIC 41T43 | AE112: ISIC 45T47 | AF112: ISIC 49T53 | AG112: ISIC 55T56 | AH112: ISIC 58T60 | AI112: ISIC 61 | AJ112: ISIC 62T63 | AK112: ISIC 64T66 | AL112: ISIC 68 | AM112: ISIC 69T82 | AN112: ISIC 84 | AO112: ISIC 85 | AP112: ISIC 86T88 | AQ112: ISIC 90T96 | AR112: ISIC 97T98 | AS112: TOTAL
A113: Domestic | B113: ISIC 01T03 | C113: {=SUMPRODUCT(IF(LEFT($A$4:$A$108,3)=LEFT($A113,3),IF($B$4:$B$108=$B113,IF($C$3:$AZ$3=C$112,$C$4:$AZ$108))))} -> 3925.568 | D113: {=SUMPRODUCT(IF(LEFT($A$4:$A$108,3)=LEFT($A113,3),IF($B$4:$B$108=$B113,IF($C$3:$AZ$3=D$112,$C$4:$AZ$108))))} -> 0.177 | E113: {=SUMPRODUCT(IF(LEFT($A$4:$A$108,3)=LEFT($A113,3),IF($B$4:$B$108=$B113,IF($C$3:$AZ$3=E$112,$C$4:$AZ$108))))} -> 0.01 | F113: {=SUMPRODUCT(IF(LEFT($A$4:$A$108,3)=LEFT($A113,3),IF($B$4:$B$108=$B113,IF($C$3:$AZ$3=F$112,$C$4:$AZ$108))))} -> 1.037 | G113: {=SUMPRODUCT(IF(LEFT($A$4:$A$108,3)=LEFT($A113,3),IF($B$4:$B$108=$B113,IF($C$3:$AZ$3=G$112,$C$4:$AZ$108))))} -> 0.001 | H113: {=SUMPRODUCT(IF(LEFT($A$4:$A$108,3)=LEFT($A113,3),IF($B$4:$B$108=$B113,IF($C$3:$AZ$3=H$112,$C$4:$AZ$108))))} -> 23912.045 | I113: {=SUMPRODUCT(IF(LEFT($A$4:$A$108,3)=LEFT($A113,3),IF($B$4:$B$108=$B113,IF($C$3:$AZ$3=I$112,$C$4:$AZ$108))))} -> 501.936 | J113: {=SUMPRODUCT(IF(LEFT($A$4:$A$108,3)=LEFT($A113,3),IF($B$4:$B$108=$B113,IF($C$3:$AZ$3=J$112,$C$4:$AZ$108))))} -> 947.906 | ... O113: {=SUMPRODUCT(IF(LEFT($A$4:$A$108,3)=LEFT($A113,3),IF($B$4:$B$108=$B113,IF($C$3:$AZ$3=O$112,$C$4:$AZ$108))))} -> 172.064 | P113: {=SUMPRODUCT(IF(LEFT($A$4:$A$108,3)=LEFT($A113,3),IF($B$4:$B$108=$B113,IF($C$3:$AZ$3=P$112,$C$4:$AZ$108))))*'Cement and Glass Split'!O48} -> 0 | Q113: {=SUMPRODUCT(IF(LEFT($A$4:$A$108,3)=LEFT($A113,3),IF($B$4:$B$108=$B113,IF($C$3:$AZ$3=P$112,$C$4:$AZ$108))))*'Cement and Glass Split'!P48} -> 0 | R113: {=SUMPRODUCT(IF(LEFT($A$4:$A$108,3)=LEFT($A113,3),IF($B$4:$B$108=$B113,IF($C$3:$AZ$3=R$112,$C$4:$AZ$108))))} -> 2.675 | S113: {=SUMPRODUCT(IF(LEFT($A$4:$A$108,3)=LEFT($A113,3),IF($B$4:$B$108=$B113,IF($C$3:$AZ$3=S$112,$C$4:$AZ$108))))} -> 1.843 | T113: {=SUMPRODUCT(IF(LEFT($A$4:$A$108,3)=LEFT($A113,3),IF($B$4:$B$108=$B113,IF($C$3:$AZ$3=T$112,$C$4:$AZ$108))))} -> 2.166 | U113: {=SUMPRODUCT(IF(LEFT($A$4:$A$108,3)=LEFT($A113,3),IF($B$4:$B$108=$B113,IF($C$3:$AZ$3=U$112,$C$4:$AZ$108))))} -> 6.344 | V113: {=SUMPRODUCT(IF(LEFT($A$4:$A$108,3)=LEFT($A113,3),IF($B$4:$B$108=$B113,IF($C$3:$AZ$3=V$112,$C$4:$AZ$108))))} -> 2.365 | W113: {=SUMPRODUCT(IF(LEFT($A$4:$A$108,3)=LEFT($A113,3),IF($B$4:$B$108=$B113,IF($C$3:$AZ$3=W$112,$C$4:$AZ$108))))} -> 8.912 | X113: {=SUMPRODUCT(IF(LEFT($A$4:$A$108,3)=LEFT($A113,3),IF($B$4:$B$108=$B113,IF($C$3:$AZ$3=X$112,$C$4:$AZ$108))))} -> 4.332 | Y113: {=SUMPRODUCT(IF(LEFT($A$4:$A$108,3)=LEFT($A113,3),IF($B$4:$B$108=$B113,IF($C$3:$AZ$3=Y$112,$C$4:$AZ$108))))} -> 2.424 | ... AR113: {=SUMPRODUCT(IF(LEFT($A$4:$A$108,3)=LEFT($A113,3),IF($B$4:$B$108=$B113,IF($C$3:$AZ$3=AR$112,$C$4:$AZ$108))))} -> 0 | AS113: =SUMIFS($BA$4:$BA$108,$B$4:$B$108,B113,$A$4:$A$108,"DOM*") -> 55768.139
A114: Domestic | B114: ISIC 05 | C114: {=SUMPRODUCT(IF(LEFT($A$4:$A$108,3)=LEFT($A114,3),IF($B$4:$B$108=$B114,IF($C$3:$AZ$3=C$112,$C$4:$AZ$108))))} -> 0.189 | D114: {=SUMPRODUCT(IF(LEFT($A$4:$A$108,3)=LEFT($A114,3),IF($B$4:$B$108=$B114,IF($C$3:$AZ$3=D$112,$C$4:$AZ$108))))} -> 0.244 | E114: {=SUMPRODUCT(IF(LEFT($A$4:$A$108,3)=LEFT($A114,3),IF($B$4:$B$108=$B114,IF($C$3:$AZ$3=E$112,$C$4:$AZ$108))))} -> 0 | F114: {=SUMPRODUCT(IF(LEFT($A$4:$A$108,3)=LEFT($A114,3),IF($B$4:$B$108=$B114,IF($C$3:$AZ$3=F$112,$C$4:$AZ$108))))} -> 0.02 | G114: {=SUMPRODUCT(IF(LEFT($A$4:$A$108,3)=LEFT($A114,3),IF($B$4:$B$108=$B114,IF($C$3:$AZ$3=G$112,$C$4:$AZ$108))))} -> 0 | H114: {=SUMPRODUCT(IF(LEFT($A$4:$A$108,3)=LEFT($A114,3),IF($B$4:$B$108=$B114,IF($C$3:$AZ$3=H$112,$C$4:$AZ$108))))} -> 0.427 | I114: {=SUMPRODUCT(IF(LEFT($A$4:$A$108,3)=LEFT($A114,3),IF($B$4:$B$108=$B114,IF($C$3:$AZ$3=I$112,$C$4:$AZ$108))))} -> 0.214 | J114: {=SUMPRODUCT(IF(LEFT($A$4:$A$108,3)=LEFT($A114,3),IF($B$4:$B$108=$B114,IF($C$3:$AZ$3=J$112,$C$4:$AZ$108))))} -> 0.025 | ... O114: {=SUMPRODUCT(IF(LEFT($A$4:$A$108,3)=LEFT($A114,3),IF($B$4:$B$108=$B114,IF($C$3:$AZ$3=O$112,$C$4:$AZ$108))))} -> 0.213 | P114: {=SUMPRODUCT(IF(LEFT($A$4:$A$108,3)=LEFT($A114,3),IF($B$4:$B$108=$B114,IF($C$3:$AZ$3=P$112,$C$4:$AZ$108))))*'Cement and Glass Split'!O49} -> 0 | Q114: {=SUMPRODUCT(IF(LEFT($A$4:$A$108,3)=LEFT($A114,3),IF($B$4:$B$108=$B114,IF($C$3:$AZ$3=P$112,$C$4:$AZ$108))))*'Cement and Glass Split'!P49} -> 0 | R114: {=SUMPRODUCT(IF(LEFT($A$4:$A$108,3)=LEFT($A114,3),IF($B$4:$B$108=$B114,IF($C$3:$AZ$3=R$112,$C$4:$AZ$108))))} -> 0.391 | S114: {=SUMPRODUCT(IF(LEFT($A$4:$A$108,3)=LEFT($A114,3),IF($B$4:$B$108=$B114,IF($C$3:$AZ$3=S$112,$C$4:$AZ$108))))} -> 0.134 | T114: {=SUMPRODUCT(IF(LEFT($A$4:$A$108,3)=LEFT($A114,3),IF($B$4:$B$108=$B114,IF($C$3:$AZ$3=T$112,$C$4:$AZ$108))))} -> 0.258 | U114: {=SUMPRODUCT(IF(LEFT($A$4:$A$108,3)=LEFT($A114,3),IF($B$4:$B$108=$B114,IF($C$3:$AZ$3=U$112,$C$4:$AZ$108))))} -> 0.773 | V114: {=SUMPRODUCT(IF(LEFT($A$4:$A$108,3)=LEFT($A114,3),IF($B$4:$B$108=$B114,IF($C$3:$AZ$3=V$112,$C$4:$AZ$108))))} -> 0.289 | W114: {=SUMPRODUCT(IF(LEFT($A$4:$A$108,3)=LEFT($A114,3),IF($B$4:$B$108=$B114,IF($C$3:$AZ$3=W$112,$C$4:$AZ$108))))} -> 0.432 | X114: {=SUMPRODUCT(IF(LEFT($A$4:$A$108,3)=LEFT($A114,3),IF($B$4:$B$108=$B114,IF($C$3:$AZ$3=X$112,$C$4:$AZ$108))))} -> 0.394 | Y114: {=SUMPRODUCT(IF(LEFT($A$4:$A$108,3)=LEFT($A114,3),IF($B$4:$B$108=$B114,IF($C$3:$AZ$3=Y$112,$C$4:$AZ$108))))} -> 0.132 | ... AR114: {=SUMPRODUCT(IF(LEFT($A$4:$A$108,3)=LEFT($A114,3),IF($B$4:$B$108=$B114,IF($C$3:$AZ$3=AR$112,$C$4:$AZ$108))))} -> 0 | AS114: =SUMIFS($BA$4:$BA$108,$B$4:$B$108,B114,$A$4:$A$108,"DOM*") -> 257.663
A115: Domestic | B115: ISIC 06 | C115: {=SUMPRODUCT(IF(LEFT($A$4:$A$108,3)=LEFT($A115,3),IF($B$4:$B$108=$B115,IF($C$3:$AZ$3=C$112,$C$4:$AZ$108))))} -> 0.046 | D115: {=SUMPRODUCT(IF(LEFT($A$4:$A$108,3)=LEFT($A115,3),IF($B$4:$B$108=$B115,IF($C$3:$AZ$3=D$112,$C$4:$AZ$108))))} -> 0 | E115: {=SUMPRODUCT(IF(LEFT($A$4:$A$108,3)=LEFT($A115,3),IF($B$4:$B$108=$B115,IF($C$3:$AZ$3=E$112,$C$4:$AZ$108))))} -> 0.008 | F115: {=SUMPRODUCT(IF(LEFT($A$4:$A$108,3)=LEFT($A115,3),IF($B$4:$B$108=$B115,IF($C$3:$AZ$3=F$112,$C$4:$AZ$108))))} -> 0.003 | G115: {=SUMPRODUCT(IF(LEFT($A$4:$A$108,3)=LEFT($A115,3),IF($B$4:$B$108=$B115,IF($C$3:$AZ$3=G$112,$C$4:$AZ$108))))} -> 0 | H115: {=SUMPRODUCT(IF(LEFT($A$4:$A$108,3)=LEFT($A115,3),IF($B$4:$B$108=$B115,IF($C$3:$AZ$3=H$112,$C$4:$AZ$108))))} -> 0.164 | I115: {=SUMPRODUCT(IF(LEFT($A$4:$A$108,3)=LEFT($A115,3),IF($B$4:$B$108=$B115,IF($C$3:$AZ$3=I$112,$C$4:$AZ$108))))} -> 0.109 | J115: {=SUMPRODUCT(IF(LEFT($A$4:$A$108,3)=LEFT($A115,3),IF($B$4:$B$108=$B115,IF($C$3:$AZ$3=J$112,$C$4:$AZ$108))))} -> 0.009 | ... O115: {=SUMPRODUCT(IF(LEFT($A$4:$A$108,3)=LEFT($A115,3),IF($B$4:$B$108=$B115,IF($C$3:$AZ$3=O$112,$C$4:$AZ$108))))} -> 0.106 | P115: {=SUMPRODUCT(IF(LEFT($A$4:$A$108,3)=LEFT($A115,3),IF($B$4:$B$108=$B115,IF($C$3:$AZ$3=P$112,$C$4:$AZ$108))))*'Cement and Glass Split'!O50} -> 0.00056272418 | Q115: {=SUMPRODUCT(IF(LEFT($A$4:$A$108,3)=LEFT($A115,3),IF($B$4:$B$108=$B115,IF($C$3:$AZ$3=P$112,$C$4:$AZ$108))))*'Cement and Glass Split'!P50} -> 0.047437276 | R115: {=SUMPRODUCT(IF(LEFT($A$4:$A$108,3)=LEFT($A115,3),IF($B$4:$B$108=$B115,IF($C$3:$AZ$3=R$112,$C$4:$AZ$108))))} -> 0.11 | S115: {=SUMPRODUCT(IF(LEFT($A$4:$A$108,3)=LEFT($A115,3),IF($B$4:$B$108=$B115,IF($C$3:$AZ$3=S$112,$C$4:$AZ$108))))} -> 0.032 | T115: {=SUMPRODUCT(IF(LEFT($A$4:$A$108,3)=LEFT($A115,3),IF($B$4:$B$108=$B115,IF($C$3:$AZ$3=T$112,$C$4:$AZ$108))))} -> 0.098 | U115: {=SUMPRODUCT(IF(LEFT($A$4:$A$108,3)=LEFT($A115,3),IF($B$4:$B$108=$B115,IF($C$3:$AZ$3=U$112,$C$4:$AZ$108))))} -> 0.433 | V115: {=SUMPRODUCT(IF(LEFT($A$4:$A$108,3)=LEFT($A115,3),IF($B$4:$B$108=$B115,IF($C$3:$AZ$3=V$112,$C$4:$AZ$108))))} -> 0.14 | W115: {=SUMPRODUCT(IF(LEFT($A$4:$A$108,3)=LEFT($A115,3),IF($B$4:$B$108=$B115,IF($C$3:$AZ$3=W$112,$C$4:$AZ$108))))} -> 0.181 | X115: {=SUMPRODUCT(IF(LEFT($A$4:$A$108,3)=LEFT($A115,3),IF($B$4:$B$108=$B115,IF($C$3:$AZ$3=X$112,$C$4:$AZ$108))))} -> 0.157 | Y115: {=SUMPRODUCT(IF(LEFT($A$4:$A$108,3)=LEFT($A115,3),IF($B$4:$B$108=$B115,IF($C$3:$AZ$3=Y$112,$C$4:$AZ$108))))} -> 0.055 | ... AR115: {=SUMPRODUCT(IF(LEFT($A$4:$A$108,3)=LEFT($A115,3),IF($B$4:$B$108=$B115,IF($C$3:$AZ$3=AR$112,$C$4:$AZ$108))))} -> 0 | AS115: =SUMIFS($BA$4:$BA$108,$B$4:$B$108,B115,$A$4:$A$108,"DOM*") -> 139.391
A116: Domestic | B116: ISIC 07T08 | C116: {=SUMPRODUCT(IF(LEFT($A$4:$A$108,3)=LEFT($A116,3),IF($B$4:$B$108=$B116,IF($C$3:$AZ$3=C$112,$C$4:$AZ$108))))} -> 13.108 | D116: {=SUMPRODUCT(IF(LEFT($A$4:$A$108,3)=LEFT($A116,3),IF($B$4:$B$108=$B116,IF($C$3:$AZ$3=D$112,$C$4:$AZ$108))))} -> 0.223 | E116: {=SUMPRODUCT(IF(LEFT($A$4:$A$108,3)=LEFT($A116,3),IF($B$4:$B$108=$B116,IF($C$3:$AZ$3=E$112,$C$4:$AZ$108))))} -> 0.05 | F116: {=SUMPRODUCT(IF(LEFT($A$4:$A$108,3)=LEFT($A116,3),IF($B$4:$B$108=$B116,IF($C$3:$AZ$3=F$112,$C$4:$AZ$108))))} -> 55.942 | G116: {=SUMPRODUCT(IF(LEFT($A$4:$A$108,3)=LEFT($A116,3),IF($B$4:$B$108=$B116,IF($C$3:$AZ$3=G$112,$C$4:$AZ$108))))} -> 0.024 | H116: {=SUMPRODUCT(IF(LEFT($A$4:$A$108,3)=LEFT($A116,3),IF($B$4:$B$108=$B116,IF($C$3:$AZ$3=H$112,$C$4:$AZ$108))))} -> 30.42 | I116: {=SUMPRODUCT(IF(LEFT($A$4:$A$108,3)=LEFT($A116,3),IF($B$4:$B$108=$B116,IF($C$3:$AZ$3=I$112,$C$4:$AZ$108))))} -> 4.599 | J116: {=SUMPRODUCT(IF(LEFT($A$4:$A$108,3)=LEFT($A116,3),IF($B$4:$B$108=$B116,IF($C$3:$AZ$3=J$112,$C$4:$AZ$108))))} -> 0.473 | ... O116: {=SUMPRODUCT(IF(LEFT($A$4:$A$108,3)=LEFT($A116,3),IF($B$4:$B$108=$B116,IF($C$3:$AZ$3=O$112,$C$4:$AZ$108))))} -> 8.495 | P116: {=SUMPRODUCT(IF(LEFT($A$4:$A$108,3)=LEFT($A116,3),IF($B$4:$B$108=$B116,IF($C$3:$AZ$3=P$112,$C$4:$AZ$108))))*'Cement and Glass Split'!O51} -> 10.173247 | Q116: {=SUMPRODUCT(IF(LEFT($A$4:$A$108,3)=LEFT($A116,3),IF($B$4:$B$108=$B116,IF($C$3:$AZ$3=P$112,$C$4:$AZ$108))))*'Cement and Glass Split'!P51} -> 840.80875 | R116: {=SUMPRODUCT(IF(LEFT($A$4:$A$108,3)=LEFT($A116,3),IF($B$4:$B$108=$B116,IF($C$3:$AZ$3=R$112,$C$4:$AZ$108))))} -> 313.437 | S116: {=SUMPRODUCT(IF(LEFT($A$4:$A$108,3)=LEFT($A116,3),IF($B$4:$B$108=$B116,IF($C$3:$AZ$3=S$112,$C$4:$AZ$108))))} -> 104.875 | T116: {=SUMPRODUCT(IF(LEFT($A$4:$A$108,3)=LEFT($A116,3),IF($B$4:$B$108=$B116,IF($C$3:$AZ$3=T$112,$C$4:$AZ$108))))} -> 18.9 | U116: {=SUMPRODUCT(IF(LEFT($A$4:$A$108,3)=LEFT($A116,3),IF($B$4:$B$108=$B116,IF($C$3:$AZ$3=U$112,$C$4:$AZ$108))))} -> 10.707 | V116: {=SUMPRODUCT(IF(LEFT($A$4:$A$108,3)=LEFT($A116,3),IF($B$4:$B$108=$B116,IF($C$3:$AZ$3=V$112,$C$4:$AZ$108))))} -> 12.602 | W116: {=SUMPRODUCT(IF(LEFT($A$4:$A$108,3)=LEFT($A116,3),IF($B$4:$B$108=$B116,IF($C$3:$AZ$3=W$112,$C$4:$AZ$108))))} -> 12.119 | X116: {=SUMPRODUCT(IF(LEFT($A$4:$A$108,3)=LEFT($A116,3),IF($B$4:$B$108=$B116,IF($C$3:$AZ$3=X$112,$C$4:$AZ$108))))} -> 9.095 | Y116: {=SUMPRODUCT(IF(LEFT($A$4:$A$108,3)=LEFT($A116,3),IF($B$4:$B$108=$B116,IF($C$3:$AZ$3=Y$112,$C$4:$AZ$108))))} -> 2.761 | ... AR116: {=SUMPRODUCT(IF(LEFT($A$4:$A$108,3)=LEFT($A116,3),IF($B$4:$B$108=$B116,IF($C$3:$AZ$3=AR$112,$C$4:$AZ$108))))} -> 0 | AS116: =SUMIFS($BA$4:$BA$108,$B$4:$B$108,B116,$A$4:$A$108,"DOM*") -> 3394.069
A117: Domestic | B117: ISIC 09 | C117: {=SUMPRODUCT(IF(LEFT($A$4:$A$108,3)=LEFT($A117,3),IF($B$4:$B$108=$B117,IF($C$3:$AZ$3=C$112,$C$4:$AZ$108))))} -> 0.024 | D117: {=SUMPRODUCT(IF(LEFT($A$4:$A$108,3)=LEFT($A117,3),IF($B$4:$B$108=$B117,IF($C$3:$AZ$3=D$112,$C$4:$AZ$108))))} -> 0 | E117: {=SUMPRODUCT(IF(LEFT($A$4:$A$108,3)=LEFT($A117,3),IF($B$4:$B$108=$B117,IF($C$3:$AZ$3=E$112,$C$4:$AZ$108))))} -> 0 | F117: {=SUMPRODUCT(IF(LEFT($A$4:$A$108,3)=LEFT($A117,3),IF($B$4:$B$108=$B117,IF($C$3:$AZ$3=F$112,$C$4:$AZ$108))))} -> 0.002 | G117: {=SUMPRODUCT(IF(LEFT($A$4:$A$108,3)=LEFT($A117,3),IF($B$4:$B$108=$B117,IF($C$3:$AZ$3=G$112,$C$4:$AZ$108))))} -> 0 | H117: {=SUMPRODUCT(IF(LEFT($A$4:$A$108,3)=LEFT($A117,3),IF($B$4:$B$108=$B117,IF($C$3:$AZ$3=H$112,$C$4:$AZ$108))))} -> 0.085 | I117: {=SUMPRODUCT(IF(LEFT($A$4:$A$108,3)=LEFT($A117,3),IF($B$4:$B$108=$B117,IF($C$3:$AZ$3=I$112,$C$4:$AZ$108))))} -> 0.056 | J117: {=SUMPRODUCT(IF(LEFT($A$4:$A$108,3)=LEFT($A117,3),IF($B$4:$B$108=$B117,IF($C$3:$AZ$3=J$112,$C$4:$AZ$108))))} -> 0.005 | ... O117: {=SUMPRODUCT(IF(LEFT($A$4:$A$108,3)=LEFT($A117,3),IF($B$4:$B$108=$B117,IF($C$3:$AZ$3=O$112,$C$4:$AZ$108))))} -> 0.055 | P117: {=SUMPRODUCT(IF(LEFT($A$4:$A$108,3)=LEFT($A117,3),IF($B$4:$B$108=$B117,IF($C$3:$AZ$3=P$112,$C$4:$AZ$108))))*'Cement and Glass Split'!O52} -> 0 | Q117: {=SUMPRODUCT(IF(LEFT($A$4:$A$108,3)=LEFT($A117,3),IF($B$4:$B$108=$B117,IF($C$3:$AZ$3=P$112,$C$4:$AZ$108))))*'Cement and Glass Split'!P52} -> 0 | R117: {=SUMPRODUCT(IF(LEFT($A$4:$A$108,3)=LEFT($A117,3),IF($B$4:$B$108=$B117,IF($C$3:$AZ$3=R$112,$C$4:$AZ$108))))} -> 0.057 | S117: {=SUMPRODUCT(IF(LEFT($A$4:$A$108,3)=LEFT($A117,3),IF($B$4:$B$108=$B117,IF($C$3:$AZ$3=S$112,$C$4:$AZ$108))))} -> 0.017 | T117: {=SUMPRODUCT(IF(LEFT($A$4:$A$108,3)=LEFT($A117,3),IF($B$4:$B$108=$B117,IF($C$3:$AZ$3=T$112,$C$4:$AZ$108))))} -> 0.053 | U117: {=SUMPRODUCT(IF(LEFT($A$4:$A$108,3)=LEFT($A117,3),IF($B$4:$B$108=$B117,IF($C$3:$AZ$3=U$112,$C$4:$AZ$108))))} -> 0.225 | V117: {=SUMPRODUCT(IF(LEFT($A$4:$A$108,3)=LEFT($A117,3),IF($B$4:$B$108=$B117,IF($C$3:$AZ$3=V$112,$C$4:$AZ$108))))} -> 0.073 | W117: {=SUMPRODUCT(IF(LEFT($A$4:$A$108,3)=LEFT($A117,3),IF($B$4:$B$108=$B117,IF($C$3:$AZ$3=W$112,$C$4:$AZ$108))))} -> 0.094 | X117: {=SUMPRODUCT(IF(LEFT($A$4:$A$108,3)=LEFT($A117,3),IF($B$4:$B$108=$B117,IF($C$3:$AZ$3=X$112,$C$4:$AZ$108))))} -> 0.082 | Y117: {=SUMPRODUCT(IF(LEFT($A$4:$A$108,3)=LEFT($A117,3),IF($B$4:$B$108=$B117,IF($C$3:$AZ$3=Y$112,$C$4:$AZ$108))))} -> 0.029 | ... AR117: {=SUMPRODUCT(IF(LEFT($A$4:$A$108,3)=LEFT($A117,3),IF($B$4:$B$108=$B117,IF($C$3:$AZ$3=AR$112,$C$4:$AZ$108))))} -> 0 | AS117: =SUMIFS($BA$4:$BA$108,$B$4:$B$108,B117,$A$4:$A$108,"DOM*") -> 18.831
A118: Domestic | B118: ISIC 10T12 | C118: {=SUMPRODUCT(IF(LEFT($A$4:$A$108,3)=LEFT($A118,3),IF($B$4:$B$108=$B118,IF($C$3:$AZ$3=C$112,$C$4:$AZ$108))))} -> 3668.317 | D118: {=SUMPRODUCT(IF(LEFT($A$4:$A$108,3)=LEFT($A118,3),IF($B$4:$B$108=$B118,IF($C$3:$AZ$3=D$112,$C$4:$AZ$108))))} -> 0.179 | E118: {=SUMPRODUCT(IF(LEFT($A$4:$A$108,3)=LEFT($A118,3),IF($B$4:$B$108=$B118,IF($C$3:$AZ$3=E$112,$C$4:$AZ$108))))} -> 0.09 | F118: {=SUMPRODUCT(IF(LEFT($A$4:$A$108,3)=LEFT($A118,3),IF($B$4:$B$108=$B118,IF($C$3:$AZ$3=F$112,$C$4:$AZ$108))))} -> 4.521 | G118: {=SUMPRODUCT(IF(LEFT($A$4:$A$108,3)=LEFT($A118,3),IF($B$4:$B$108=$B118,IF($C$3:$AZ$3=G$112,$C$4:$AZ$108))))} -> 0.012 | H118: {=SUMPRODUCT(IF(LEFT($A$4:$A$108,3)=LEFT($A118,3),IF($B$4:$B$108=$B118,IF($C$3:$AZ$3=H$112,$C$4:$AZ$108))))} -> 21114.006 | I118: {=SUMPRODUCT(IF(LEFT($A$4:$A$108,3)=LEFT($A118,3),IF($B$4:$B$108=$B118,IF($C$3:$AZ$3=I$112,$C$4:$AZ$108))))} -> 182.59 | J118: {=SUMPRODUCT(IF(LEFT($A$4:$A$108,3)=LEFT($A118,3),IF($B$4:$B$108=$B118,IF($C$3:$AZ$3=J$112,$C$4:$AZ$108))))} -> 7.488 | ... O118: {=SUMPRODUCT(IF(LEFT($A$4:$A$108,3)=LEFT($A118,3),IF($B$4:$B$108=$B118,IF($C$3:$AZ$3=O$112,$C$4:$AZ$108))))} -> 73.633 | P118: {=SUMPRODUCT(IF(LEFT($A$4:$A$108,3)=LEFT($A118,3),IF($B$4:$B$108=$B118,IF($C$3:$AZ$3=P$112,$C$4:$AZ$108))))*'Cement and Glass Split'!O53} -> 0 | Q118: {=SUMPRODUCT(IF(LEFT($A$4:$A$108,3)=LEFT($A118,3),IF($B$4:$B$108=$B118,IF($C$3:$AZ$3=P$112,$C$4:$AZ$108))))*'Cement and Glass Split'!P53} -> 26.308 | R118: {=SUMPRODUCT(IF(LEFT($A$4:$A$108,3)=LEFT($A118,3),IF($B$4:$B$108=$B118,IF($C$3:$AZ$3=R$112,$C$4:$AZ$108))))} -> 30.264 | S118: {=SUMPRODUCT(IF(LEFT($A$4:$A$108,3)=LEFT($A118,3),IF($B$4:$B$108=$B118,IF($C$3:$AZ$3=S$112,$C$4:$AZ$108))))} -> 24.391 | T118: {=SUMPRODUCT(IF(LEFT($A$4:$A$108,3)=LEFT($A118,3),IF($B$4:$B$108=$B118,IF($C$3:$AZ$3=T$112,$C$4:$AZ$108))))} -> 42.693 | U118: {=SUMPRODUCT(IF(LEFT($A$4:$A$108,3)=LEFT($A118,3),IF($B$4:$B$108=$B118,IF($C$3:$AZ$3=U$112,$C$4:$AZ$108))))} -> 72.797 | V118: {=SUMPRODUCT(IF(LEFT($A$4:$A$108,3)=LEFT($A118,3),IF($B$4:$B$108=$B118,IF($C$3:$AZ$3=V$112,$C$4:$AZ$108))))} -> 47.362 | W118: {=SUMPRODUCT(IF(LEFT($A$4:$A$108,3)=LEFT($A118,3),IF($B$4:$B$108=$B118,IF($C$3:$AZ$3=W$112,$C$4:$AZ$108))))} -> 62.471 | X118: {=SUMPRODUCT(IF(LEFT($A$4:$A$108,3)=LEFT($A118,3),IF($B$4:$B$108=$B118,IF($C$3:$AZ$3=X$112,$C$4:$AZ$108))))} -> 51.529 | Y118: {=SUMPRODUCT(IF(LEFT($A$4:$A$108,3)=LEFT($A118,3),IF($B$4:$B$108=$B118,IF($C$3:$AZ$3=Y$112,$C$4:$AZ$108))))} -> 18.013 | ... AR118: {=SUMPRODUCT(IF(LEFT($A$4:$A$108,3)=LEFT($A118,3),IF($B$4:$B$108=$B118,IF($C$3:$AZ$3=AR$112,$C$4:$AZ$108))))} -> 0 | AS118: =SUMIFS($BA$4:$BA$108,$B$4:$B$108,B118,$A$4:$A$108,"DOM*") -> 131256.51
A119: Domestic | B119: ISIC 13T15 | C119: {=SUMPRODUCT(IF(LEFT($A$4:$A$108,3)=LEFT($A119,3),IF($B$4:$B$108=$B119,IF($C$3:$AZ$3=C$112,$C$4:$AZ$108))))} -> 173.019 | D119: {=SUMPRODUCT(IF(LEFT($A$4:$A$108,3)=LEFT($A119,3),IF($B$4:$B$108=$B119,IF($C$3:$AZ$3=D$112,$C$4:$AZ$108))))} -> 0.779 | E119: {=SUMPRODUCT(IF(LEFT($A$4:$A$108,3)=LEFT($A119,3),IF($B$4:$B$108=$B119,IF($C$3:$AZ$3=E$112,$C$4:$AZ$108))))} -> 0.235 | F119: {=SUMPRODUCT(IF(LEFT($A$4:$A$108,3)=LEFT($A119,3),IF($B$4:$B$108=$B119,IF($C$3:$AZ$3=F$112,$C$4:$AZ$108))))} -> 8.889 | G119: {=SUMPRODUCT(IF(LEFT($A$4:$A$108,3)=LEFT($A119,3),IF($B$4:$B$108=$B119,IF($C$3:$AZ$3=G$112,$C$4:$AZ$108))))} -> 0.034 | H119: {=SUMPRODUCT(IF(LEFT($A$4:$A$108,3)=LEFT($A119,3),IF($B$4:$B$108=$B119,IF($C$3:$AZ$3=H$112,$C$4:$AZ$108))))} -> 243.527 | I119: {=SUMPRODUCT(IF(LEFT($A$4:$A$108,3)=LEFT($A119,3),IF($B$4:$B$108=$B119,IF($C$3:$AZ$3=I$112,$C$4:$AZ$108))))} -> 19216.841 | J119: {=SUMPRODUCT(IF(LEFT($A$4:$A$108,3)=LEFT($A119,3),IF($B$4:$B$108=$B119,IF($C$3:$AZ$3=J$112,$C$4:$AZ$108))))} -> 30.851 | ... O119: {=SUMPRODUCT(IF(LEFT($A$4:$A$108,3)=LEFT($A119,3),IF($B$4:$B$108=$B119,IF($C$3:$AZ$3=O$112,$C$4:$AZ$108))))} -> 665.717 | P119: {=SUMPRODUCT(IF(LEFT($A$4:$A$108,3)=LEFT($A119,3),IF($B$4:$B$108=$B119,IF($C$3:$AZ$3=P$112,$C$4:$AZ$108))))*'Cement and Glass Split'!O54} -> 30.440698 | Q119: {=SUMPRODUCT(IF(LEFT($A$4:$A$108,3)=LEFT($A119,3),IF($B$4:$B$108=$B119,IF($C$3:$AZ$3=P$112,$C$4:$AZ$108))))*'Cement and Glass Split'!P54} -> 130.8413 | R119: {=SUMPRODUCT(IF(LEFT($A$4:$A$108,3)=LEFT($A119,3),IF($B$4:$B$108=$B119,IF($C$3:$AZ$3=R$112,$C$4:$AZ$108))))} -> 105.87 | S119: {=SUMPRODUCT(IF(LEFT($A$4:$A$108,3)=LEFT($A119,3),IF($B$4:$B$108=$B119,IF($C$3:$AZ$3=S$112,$C$4:$AZ$108))))} -> 47.908 | T119: {=SUMPRODUCT(IF(LEFT($A$4:$A$108,3)=LEFT($A119,3),IF($B$4:$B$108=$B119,IF($C$3:$AZ$3=T$112,$C$4:$AZ$108))))} -> 187.597 | U119: {=SUMPRODUCT(IF(LEFT($A$4:$A$108,3)=LEFT($A119,3),IF($B$4:$B$108=$B119,IF($C$3:$AZ$3=U$112,$C$4:$AZ$108))))} -> 319.488 | V119: {=SUMPRODUCT(IF(LEFT($A$4:$A$108,3)=LEFT($A119,3),IF($B$4:$B$108=$B119,IF($C$3:$AZ$3=V$112,$C$4:$AZ$108))))} -> 195.749 | W119: {=SUMPRODUCT(IF(LEFT($A$4:$A$108,3)=LEFT($A119,3),IF($B$4:$B$108=$B119,IF($C$3:$AZ$3=W$112,$C$4:$AZ$108))))} -> 285.355 | X119: {=SUMPRODUCT(IF(LEFT($A$4:$A$108,3)=LEFT($A119,3),IF($B$4:$B$108=$B119,IF($C$3:$AZ$3=X$112,$C$4:$AZ$108))))} -> 1208.831 | Y119: {=SUMPRODUCT(IF(LEFT($A$4:$A$108,3)=LEFT($A119,3),IF($B$4:$B$108=$B119,IF($C$3:$AZ$3=Y$112,$C$4:$AZ$108))))} -> 190.147 | ... AR119: {=SUMPRODUCT(IF(LEFT($A$4:$A$108,3)=LEFT($A119,3),IF($B$4:$B$108=$B119,IF($C$3:$AZ$3=AR$112,$C$4:$AZ$108))))} -> 0 | AS119: =SUMIFS($BA$4:$BA$108,$B$4:$B$108,B119,$A$4:$A$108,"DOM*") -> 66294.555
A120: Domestic | B120: ISIC 16 | C120: {=SUMPRODUCT(IF(LEFT($A$4:$A$108,3)=LEFT($A120,3),IF($B$4:$B$108=$B120,IF($C$3:$AZ$3=C$112,$C$4:$AZ$108))))} -> 51.807 | D120: {=SUMPRODUCT(IF(LEFT($A$4:$A$108,3)=LEFT($A120,3),IF($B$4:$B$108=$B120,IF($C$3:$AZ$3=D$112,$C$4:$AZ$108))))} -> 0.315 | E120: {=SUMPRODUCT(IF(LEFT($A$4:$A$108,3)=LEFT($A120,3),IF($B$4:$B$108=$B120,IF($C$3:$AZ$3=E$112,$C$4:$AZ$108))))} -> 0.037 | F120: {=SUMPRODUCT(IF(LEFT($A$4:$A$108,3)=LEFT($A120,3),IF($B$4:$B$108=$B120,IF($C$3:$AZ$3=F$112,$C$4:$AZ$108))))} -> 3.064 | G120: {=SUMPRODUCT(IF(LEFT($A$4:$A$108,3)=LEFT($A120,3),IF($B$4:$B$108=$B120,IF($C$3:$AZ$3=G$112,$C$4:$AZ$108))))} -> 0.006 | H120: {=SUMPRODUCT(IF(LEFT($A$4:$A$108,3)=LEFT($A120,3),IF($B$4:$B$108=$B120,IF($C$3:$AZ$3=H$112,$C$4:$AZ$108))))} -> 154.832 | I120: {=SUMPRODUCT(IF(LEFT($A$4:$A$108,3)=LEFT($A120,3),IF($B$4:$B$108=$B120,IF($C$3:$AZ$3=I$112,$C$4:$AZ$108))))} -> 50.262 | J120: {=SUMPRODUCT(IF(LEFT($A$4:$A$108,3)=LEFT($A120,3),IF($B$4:$B$108=$B120,IF($C$3:$AZ$3=J$112,$C$4:$AZ$108))))} -> 1196.827 | ... O120: {=SUMPRODUCT(IF(LEFT($A$4:$A$108,3)=LEFT($A120,3),IF($B$4:$B$108=$B120,IF($C$3:$AZ$3=O$112,$C$4:$AZ$108))))} -> 83.709 | P120: {=SUMPRODUCT(IF(LEFT($A$4:$A$108,3)=LEFT($A120,3),IF($B$4:$B$108=$B120,IF($C$3:$AZ$3=P$112,$C$4:$AZ$108))))*'Cement and Glass Split'!O55} -> 28.608913 | Q120: {=SUMPRODUCT(IF(LEFT($A$4:$A$108,3)=LEFT($A120,3),IF($B$4:$B$108=$B120,IF($C$3:$AZ$3=P$112,$C$4:$AZ$108))))*'Cement and Glass Split'!P55} -> 92.231087 | R120: {=SUMPRODUCT(IF(LEFT($A$4:$A$108,3)=LEFT($A120,3),IF($B$4:$B$108=$B120,IF($C$3:$AZ$3=R$112,$C$4:$AZ$108))))} -> 24.417 | S120: {=SUMPRODUCT(IF(LEFT($A$4:$A$108,3)=LEFT($A120,3),IF($B$4:$B$108=$B120,IF($C$3:$AZ$3=S$112,$C$4:$AZ$108))))} -> 27.056 | T120: {=SUMPRODUCT(IF(LEFT($A$4:$A$108,3)=LEFT($A120,3),IF($B$4:$B$108=$B120,IF($C$3:$AZ$3=T$112,$C$4:$AZ$108))))} -> 119.512 | U120: {=SUMPRODUCT(IF(LEFT($A$4:$A$108,3)=LEFT($A120,3),IF($B$4:$B$108=$B120,IF($C$3:$AZ$3=U$112,$C$4:$AZ$108))))} -> 85.124 | V120: {=SUMPRODUCT(IF(LEFT($A$4:$A$108,3)=LEFT($A120,3),IF($B$4:$B$108=$B120,IF($C$3:$AZ$3=V$112,$C$4:$AZ$108))))} -> 93.396 | W120: {=SUMPRODUCT(IF(LEFT($A$4:$A$108,3)=LEFT($A120,3),IF($B$4:$B$108=$B120,IF($C$3:$AZ$3=W$112,$C$4:$AZ$108))))} -> 96.55 | X120: {=SUMPRODUCT(IF(LEFT($A$4:$A$108,3)=LEFT($A120,3),IF($B$4:$B$108=$B120,IF($C$3:$AZ$3=X$112,$C$4:$AZ$108))))} -> 255.236 | Y120: {=SUMPRODUCT(IF(LEFT($A$4:$A$108,3)=LEFT($A120,3),IF($B$4:$B$108=$B120,IF($C$3:$AZ$3=Y$112,$C$4:$AZ$108))))} -> 179.48 | ... AR120: {=SUMPRODUCT(IF(LEFT($A$4:$A$108,3)=LEFT($A120,3),IF($B$4:$B$108=$B120,IF($C$3:$AZ$3=AR$112,$C$4:$AZ$108))))} -> 0 | AS120: =SUMIFS($BA$4:$BA$108,$B$4:$B$108,B120,$A$4:$A$108,"DOM*") -> 8744.1
A121: Domestic | B121: ISIC 17T18 | C121: {=SUMPRODUCT(IF(LEFT($A$4:$A$108,3)=LEFT($A121,3),IF($B$4:$B$108=$B121,IF($C$3:$AZ$3=C$112,$C$4:$AZ$108))))} -> 93.613 | D121: {=SUMPRODUCT(IF(LEFT($A$4:$A$108,3)=LEFT($A121,3),IF($B$4:$B$108=$B121,IF($C$3:$AZ$3=D$112,$C$4:$AZ$108))))} -> 0.201 | E121: {=SUMPRODUCT(IF(LEFT($A$4:$A$108,3)=LEFT($A121,3),IF($B$4:$B$108=$B121,IF($C$3:$AZ$3=E$112,$C$4:$AZ$108))))} -> 0.161 | F121: {=SUMPRODUCT(IF(LEFT($A$4:$A$108,3)=LEFT($A121,3),IF($B$4:$B$108=$B121,IF($C$3:$AZ$3=F$112,$C$4:$AZ$108))))} -> 4.891 | G121: {=SUMPRODUCT(IF(LEFT($A$4:$A$108,3)=LEFT($A121,3),IF($B$4:$B$108=$B121,IF($C$3:$AZ$3=G$112,$C$4:$AZ$108))))} -> 0.015 | H121: {=SUMPRODUCT(IF(LEFT($A$4:$A$108,3)=LEFT($A121,3),IF($B$4:$B$108=$B121,IF($C$3:$AZ$3=H$112,$C$4:$AZ$108))))} -> 2758.416 | I121: {=SUMPRODUCT(IF(LEFT($A$4:$A$108,3)=LEFT($A121,3),IF($B$4:$B$108=$B121,IF($C$3:$AZ$3=I$112,$C$4:$AZ$108))))} -> 390.263 | J121: {=SUMPRODUCT(IF(LEFT($A$4:$A$108,3)=LEFT($A121,3),IF($B$4:$B$108=$B121,IF($C$3:$AZ$3=J$112,$C$4:$AZ$108))))} -> 87.062 | ... O121: {=SUMPRODUCT(IF(LEFT($A$4:$A$108,3)=LEFT($A121,3),IF($B$4:$B$108=$B121,IF($C$3:$AZ$3=O$112,$C$4:$AZ$108))))} -> 483.944 | P121: {=SUMPRODUCT(IF(LEFT($A$4:$A$108,3)=LEFT($A121,3),IF($B$4:$B$108=$B121,IF($C$3:$AZ$3=P$112,$C$4:$AZ$108))))*'Cement and Glass Split'!O56} -> 61.056395 | Q121: {=SUMPRODUCT(IF(LEFT($A$4:$A$108,3)=LEFT($A121,3),IF($B$4:$B$108=$B121,IF($C$3:$AZ$3=P$112,$C$4:$AZ$108))))*'Cement and Glass Split'!P56} -> 332.9726 | R121: {=SUMPRODUCT(IF(LEFT($A$4:$A$108,3)=LEFT($A121,3),IF($B$4:$B$108=$B121,IF($C$3:$AZ$3=R$112,$C$4:$AZ$108))))} -> 91.489 | S121: {=SUMPRODUCT(IF(LEFT($A$4:$A$108,3)=LEFT($A121,3),IF($B$4:$B$108=$B121,IF($C$3:$AZ$3=S$112,$C$4:$AZ$108))))} -> 89.605 | T121: {=SUMPRODUCT(IF(LEFT($A$4:$A$108,3)=LEFT($A121,3),IF($B$4:$B$108=$B121,IF($C$3:$AZ$3=T$112,$C$4:$AZ$108))))} -> 328.865 | U121: {=SUMPRODUCT(IF(LEFT($A$4:$A$108,3)=LEFT($A121,3),IF($B$4:$B$108=$B121,IF($C$3:$AZ$3=U$112,$C$4:$AZ$108))))} -> 784.733 | V121: {=SUMPRODUCT(IF(LEFT($A$4:$A$108,3)=LEFT($A121,3),IF($B$4:$B$108=$B121,IF($C$3:$AZ$3=V$112,$C$4:$AZ$108))))} -> 448.036 | W121: {=SUMPRODUCT(IF(LEFT($A$4:$A$108,3)=LEFT($A121,3),IF($B$4:$B$108=$B121,IF($C$3:$AZ$3=W$112,$C$4:$AZ$108))))} -> 439.358 | X121: {=SUMPRODUCT(IF(LEFT($A$4:$A$108,3)=LEFT($A121,3),IF($B$4:$B$108=$B121,IF($C$3:$AZ$3=X$112,$C$4:$AZ$108))))} -> 436.558 | Y121: {=SUMPRODUCT(IF(LEFT($A$4:$A$108,3)=LEFT($A121,3),IF($B$4:$B$108=$B121,IF($C$3:$AZ$3=Y$112,$C$4:$AZ$108))))} -> 94.053 | ... AR121: {=SUMPRODUCT(IF(LEFT($A$4:$A$108,3)=LEFT($A121,3),IF($B$4:$B$108=$B121,IF($C$3:$AZ$3=AR$112,$C$4:$AZ$108))))} -> 0 | AS121: =SUMIFS($BA$4:$BA$108,$B$4:$B$108,B121,$A$4:$A$108,"DOM*") -> 39624.301
A122: Domestic | B122: ISIC 19 | C122: {=SUMPRODUCT(IF(LEFT($A$4:$A$108,3)=LEFT($A122,3),IF($B$4:$B$108=$B122,IF($C$3:$AZ$3=C$112,$C$4:$AZ$108))))} -> 2689.303 | D122: {=SUMPRODUCT(IF(LEFT($A$4:$A$108,3)=LEFT($A122,3),IF($B$4:$B$108=$B122,IF($C$3:$AZ$3=D$112,$C$4:$AZ$108))))} -> 11.01 | E122: {=SUMPRODUCT(IF(LEFT($A$4:$A$108,3)=LEFT($A122,3),IF($B$4:$B$108=$B122,IF($C$3:$AZ$3=E$112,$C$4:$AZ$108))))} -> 3.448 | F122: {=SUMPRODUCT(IF(LEFT($A$4:$A$108,3)=LEFT($A122,3),IF($B$4:$B$108=$B122,IF($C$3:$AZ$3=F$112,$C$4:$AZ$108))))} -> 217.443 | G122: {=SUMPRODUCT(IF(LEFT($A$4:$A$108,3)=LEFT($A122,3),IF($B$4:$B$108=$B122,IF($C$3:$AZ$3=G$112,$C$4:$AZ$108))))} -> 0.721 | H122: {=SUMPRODUCT(IF(LEFT($A$4:$A$108,3)=LEFT($A122,3),IF($B$4:$B$108=$B122,IF($C$3:$AZ$3=H$112,$C$4:$AZ$108))))} -> 1999.519 | I122: {=SUMPRODUCT(IF(LEFT($A$4:$A$108,3)=LEFT($A122,3),IF($B$4:$B$108=$B122,IF($C$3:$AZ$3=I$112,$C$4:$AZ$108))))} -> 808.915 | J122: {=SUMPRODUCT(IF(LEFT($A$4:$A$108,3)=LEFT($A122,3),IF($B$4:$B$108=$B122,IF($C$3:$AZ$3=J$112,$C$4:$AZ$108))))} -> 215.299 | ... O122: {=SUMPRODUCT(IF(LEFT($A$4:$A$108,3)=LEFT($A122,3),IF($B$4:$B$108=$B122,IF($C$3:$AZ$3=O$112,$C$4:$AZ$108))))} -> 2167.443 | P122: {=SUMPRODUCT(IF(LEFT($A$4:$A$108,3)=LEFT($A122,3),IF($B$4:$B$108=$B122,IF($C$3:$AZ$3=P$112,$C$4:$AZ$108))))*'Cement and Glass Split'!O57} -> 239.32652 | Q122: {=SUMPRODUCT(IF(LEFT($A$4:$A$108,3)=LEFT($A122,3),IF($B$4:$B$108=$B122,IF($C$3:$AZ$3=P$112,$C$4:$AZ$108))))*'Cement and Glass Split'!P57} -> 1086.4775 | R122: {=SUMPRODUCT(IF(LEFT($A$4:$A$108,3)=LEFT($A122,3),IF($B$4:$B$108=$B122,IF($C$3:$AZ$3=R$112,$C$4:$AZ$108))))} -> 3387.855 | S122: {=SUMPRODUCT(IF(LEFT($A$4:$A$108,3)=LEFT($A122,3),IF($B$4:$B$108=$B122,IF($C$3:$AZ$3=S$112,$C$4:$AZ$108))))} -> 734.799 | T122: {=SUMPRODUCT(IF(LEFT($A$4:$A$108,3)=LEFT($A122,3),IF($B$4:$B$108=$B122,IF($C$3:$AZ$3=T$112,$C$4:$AZ$108))))} -> 805.598 | U122: {=SUMPRODUCT(IF(LEFT($A$4:$A$108,3)=LEFT($A122,3),IF($B$4:$B$108=$B122,IF($C$3:$AZ$3=U$112,$C$4:$AZ$108))))} -> 746.048 | V122: {=SUMPRODUCT(IF(LEFT($A$4:$A$108,3)=LEFT($A122,3),IF($B$4:$B$108=$B122,IF($C$3:$AZ$3=V$112,$C$4:$AZ$108))))} -> 1026.219 | W122: {=SUMPRODUCT(IF(LEFT($A$4:$A$108,3)=LEFT($A122,3),IF($B$4:$B$108=$B122,IF($C$3:$AZ$3=W$112,$C$4:$AZ$108))))} -> 766.987 | X122: {=SUMPRODUCT(IF(LEFT($A$4:$A$108,3)=LEFT($A122,3),IF($B$4:$B$108=$B122,IF($C$3:$AZ$3=X$112,$C$4:$AZ$108))))} -> 1576.207 | Y122: {=SUMPRODUCT(IF(LEFT($A$4:$A$108,3)=LEFT($A122,3),IF($B$4:$B$108=$B122,IF($C$3:$AZ$3=Y$112,$C$4:$AZ$108))))} -> 318.557 | ... AR122: {=SUMPRODUCT(IF(LEFT($A$4:$A$108,3)=LEFT($A122,3),IF($B$4:$B$108=$B122,IF($C$3:$AZ$3=AR$112,$C$4:$AZ$108))))} -> 0 | AS122: =SUMIFS($BA$4:$BA$108,$B$4:$B$108,B122,$A$4:$A$108,"DOM*") -> 156298.21
A123: Domestic | B123: ISIC 20 | C123: {=SUMPRODUCT(IF(LEFT($A$4:$A$108,3)=LEFT($A123,3),IF($B$4:$B$108=$B123,IF($C$3:$AZ$3=C$112,$C$4:$AZ$108))))} -> 3825.134 | D123: {=SUMPRODUCT(IF(LEFT($A$4:$A$108,3)=LEFT($A123,3),IF($B$4:$B$108=$B123,IF($C$3:$AZ$3=D$112,$C$4:$AZ$108))))} -> 5.997 | E123: {=SUMPRODUCT(IF(LEFT($A$4:$A$108,3)=LEFT($A123,3),IF($B$4:$B$108=$B123,IF($C$3:$AZ$3=E$112,$C$4:$AZ$108))))} -> 1.693 | F123: {=SUMPRODUCT(IF(LEFT($A$4:$A$108,3)=LEFT($A123,3),IF($B$4:$B$108=$B123,IF($C$3:$AZ$3=F$112,$C$4:$AZ$108))))} -> 130.486 | G123: {=SUMPRODUCT(IF(LEFT($A$4:$A$108,3)=LEFT($A123,3),IF($B$4:$B$108=$B123,IF($C$3:$AZ$3=G$112,$C$4:$AZ$108))))} -> 0.298 | H123: {=SUMPRODUCT(IF(LEFT($A$4:$A$108,3)=LEFT($A123,3),IF($B$4:$B$108=$B123,IF($C$3:$AZ$3=H$112,$C$4:$AZ$108))))} -> 2705.189 | I123: {=SUMPRODUCT(IF(LEFT($A$4:$A$108,3)=LEFT($A123,3),IF($B$4:$B$108=$B123,IF($C$3:$AZ$3=I$112,$C$4:$AZ$108))))} -> 5258.711 | J123: {=SUMPRODUCT(IF(LEFT($A$4:$A$108,3)=LEFT($A123,3),IF($B$4:$B$108=$B123,IF($C$3:$AZ$3=J$112,$C$4:$AZ$108))))} -> 505.022 | ... O123: {=SUMPRODUCT(IF(LEFT($A$4:$A$108,3)=LEFT($A123,3),IF($B$4:$B$108=$B123,IF($C$3:$AZ$3=O$112,$C$4:$AZ$108))))} -> 20063.012 | P123: {=SUMPRODUCT(IF(LEFT($A$4:$A$108,3)=LEFT($A123,3),IF($B$4:$B$108=$B123,IF($C$3:$AZ$3=P$112,$C$4:$AZ$108))))*'Cement and Glass Split'!O58} -> 1913.4243 | Q123: {=SUMPRODUCT(IF(LEFT($A$4:$A$108,3)=LEFT($A123,3),IF($B$4:$B$108=$B123,IF($C$3:$AZ$3=P$112,$C$4:$AZ$108))))*'Cement and Glass Split'!P58} -> 170.75168 | R123: {=SUMPRODUCT(IF(LEFT($A$4:$A$108,3)=LEFT($A123,3),IF($B$4:$B$108=$B123,IF($C$3:$AZ$3=R$112,$C$4:$AZ$108))))} -> 1415.608 | S123: {=SUMPRODUCT(IF(LEFT($A$4:$A$108,3)=LEFT($A123,3),IF($B$4:$B$108=$B123,IF($C$3:$AZ$3=S$112,$C$4:$AZ$108))))} -> 945.128 | T123: {=SUMPRODUCT(IF(LEFT($A$4:$A$108,3)=LEFT($A123,3),IF($B$4:$B$108=$B123,IF($C$3:$AZ$3=T$112,$C$4:$AZ$108))))} -> 1819.09 | U123: {=SUMPRODUCT(IF(LEFT($A$4:$A$108,3)=LEFT($A123,3),IF($B$4:$B$108=$B123,IF($C$3:$AZ$3=U$112,$C$4:$AZ$108))))} -> 3962.353 | V123: {=SUMPRODUCT(IF(LEFT($A$4:$A$108,3)=LEFT($A123,3),IF($B$4:$B$108=$B123,IF($C$3:$AZ$3=V$112,$C$4:$AZ$108))))} -> 2569.51 | W123: {=SUMPRODUCT(IF(LEFT($A$4:$A$108,3)=LEFT($A123,3),IF($B$4:$B$108=$B123,IF($C$3:$AZ$3=W$112,$C$4:$AZ$108))))} -> 1677.674 | X123: {=SUMPRODUCT(IF(LEFT($A$4:$A$108,3)=LEFT($A123,3),IF($B$4:$B$108=$B123,IF($C$3:$AZ$3=X$112,$C$4:$AZ$108))))} -> 3660.419 | Y123: {=SUMPRODUCT(IF(LEFT($A$4:$A$108,3)=LEFT($A123,3),IF($B$4:$B$108=$B123,IF($C$3:$AZ$3=Y$112,$C$4:$AZ$108))))} -> 1142.825 | ... AR123: {=SUMPRODUCT(IF(LEFT($A$4:$A$108,3)=LEFT($A123,3),IF($B$4:$B$108=$B123,IF($C$3:$AZ$3=AR$112,$C$4:$AZ$108))))} -> 0 | AS123: =SUMIFS($BA$4:$BA$108,$B$4:$B$108,B123,$A$4:$A$108,"DOM*") -> 219022.57
A124: Domestic | B124: ISIC 21 | C124: {=SUMPRODUCT(IF(LEFT($A$4:$A$108,3)=LEFT($A124,3),IF($B$4:$B$108=$B124,IF($C$3:$AZ$3=C$112,$C$4:$AZ$108))))} -> 271.292 | D124: {=SUMPRODUCT(IF(LEFT($A$4:$A$108,3)=LEFT($A124,3),IF($B$4:$B$108=$B124,IF($C$3:$AZ$3=D$112,$C$4:$AZ$108))))} -> 0.271 | E124: {=SUMPRODUCT(IF(LEFT($A$4:$A$108,3)=LEFT($A124,3),IF($B$4:$B$108=$B124,IF($C$3:$AZ$3=E$112,$C$4:$AZ$108))))} -> 0.117 | F124: {=SUMPRODUCT(IF(LEFT($A$4:$A$108,3)=LEFT($A124,3),IF($B$4:$B$108=$B124,IF($C$3:$AZ$3=F$112,$C$4:$AZ$108))))} -> 2.756 | G124: {=SUMPRODUCT(IF(LEFT($A$4:$A$108,3)=LEFT($A124,3),IF($B$4:$B$108=$B124,IF($C$3:$AZ$3=G$112,$C$4:$AZ$108))))} -> 0.006 | H124: {=SUMPRODUCT(IF(LEFT($A$4:$A$108,3)=LEFT($A124,3),IF($B$4:$B$108=$B124,IF($C$3:$AZ$3=H$112,$C$4:$AZ$108))))} -> 364.717 | I124: {=SUMPRODUCT(IF(LEFT($A$4:$A$108,3)=LEFT($A124,3),IF($B$4:$B$108=$B124,IF($C$3:$AZ$3=I$112,$C$4:$AZ$108))))} -> 44.577 | J124: {=SUMPRODUCT(IF(LEFT($A$4:$A$108,3)=LEFT($A124,3),IF($B$4:$B$108=$B124,IF($C$3:$AZ$3=J$112,$C$4:$AZ$108))))} -> 2.851 | ... O124: {=SUMPRODUCT(IF(LEFT($A$4:$A$108,3)=LEFT($A124,3),IF($B$4:$B$108=$B124,IF($C$3:$AZ$3=O$112,$C$4:$AZ$108))))} -> 31.487 | P124: {=SUMPRODUCT(IF(LEFT($A$4:$A$108,3)=LEFT($A124,3),IF($B$4:$B$108=$B124,IF($C$3:$AZ$3=P$112,$C$4:$AZ$108))))*'Cement and Glass Split'!O59} -> 0 | Q124: {=SUMPRODUCT(IF(LEFT($A$4:$A$108,3)=LEFT($A124,3),IF($B$4:$B$108=$B124,IF($C$3:$AZ$3=P$112,$C$4:$AZ$108))))*'Cement and Glass Split'!P59} -> 0 | R124: {=SUMPRODUCT(IF(LEFT($A$4:$A$108,3)=LEFT($A124,3),IF($B$4:$B$108=$B124,IF($C$3:$AZ$3=R$112,$C$4:$AZ$108))))} -> 20.058 | S124: {=SUMPRODUCT(IF(LEFT($A$4:$A$108,3)=LEFT($A124,3),IF($B$4:$B$108=$B124,IF($C$3:$AZ$3=S$112,$C$4:$AZ$108))))} -> 10.243 | T124: {=SUMPRODUCT(IF(LEFT($A$4:$A$108,3)=LEFT($A124,3),IF($B$4:$B$108=$B124,IF($C$3:$AZ$3=T$112,$C$4:$AZ$108))))} -> 15.532 | U124: {=SUMPRODUCT(IF(LEFT($A$4:$A$108,3)=LEFT($A124,3),IF($B$4:$B$108=$B124,IF($C$3:$AZ$3=U$112,$C$4:$AZ$108))))} -> 47.572 | V124: {=SUMPRODUCT(IF(LEFT($A$4:$A$108,3)=LEFT($A124,3),IF($B$4:$B$108=$B124,IF($C$3:$AZ$3=V$112,$C$4:$AZ$108))))} -> 14.379 | W124: {=SUMPRODUCT(IF(LEFT($A$4:$A$108,3)=LEFT($A124,3),IF($B$4:$B$108=$B124,IF($C$3:$AZ$3=W$112,$C$4:$AZ$108))))} -> 69.202 | X124: {=SUMPRODUCT(IF(LEFT($A$4:$A$108,3)=LEFT($A124,3),IF($B$4:$B$108=$B124,IF($C$3:$AZ$3=X$112,$C$4:$AZ$108))))} -> 28.554 | Y124: {=SUMPRODUCT(IF(LEFT($A$4:$A$108,3)=LEFT($A124,3),IF($B$4:$B$108=$B124,IF($C$3:$AZ$3=Y$112,$C$4:$AZ$108))))} -> 7.928 | ... AR124: {=SUMPRODUCT(IF(LEFT($A$4:$A$108,3)=LEFT($A124,3),IF($B$4:$B$108=$B124,IF($C$3:$AZ$3=AR$112,$C$4:$AZ$108))))} -> 0 | AS124: =SUMIFS($BA$4:$BA$108,$B$4:$B$108,B124,$A$4:$A$108,"DOM*") -> 32883.365
A125: Domestic | B125: ISIC 22 | C125: {=SUMPRODUCT(IF(LEFT($A$4:$A$108,3)=LEFT($A125,3),IF($B$4:$B$108=$B125,IF($C$3:$AZ$3=C$112,$C$4:$AZ$108))))} -> 461.914 | D125: {=SUMPRODUCT(IF(LEFT($A$4:$A$108,3)=LEFT($A125,3),IF($B$4:$B$108=$B125,IF($C$3:$AZ$3=D$112,$C$4:$AZ$108))))} -> 3.02 | E125: {=SUMPRODUCT(IF(LEFT($A$4:$A$108,3)=LEFT($A125,3),IF($B$4:$B$108=$B125,IF($C$3:$AZ$3=E$112,$C$4:$AZ$108))))} -> 0.968 | F125: {=SUMPRODUCT(IF(LEFT($A$4:$A$108,3)=LEFT($A125,3),IF($B$4:$B$108=$B125,IF($C$3:$AZ$3=F$112,$C$4:$AZ$108))))} -> 34.255 | G125: {=SUMPRODUCT(IF(LEFT($A$4:$A$108,3)=LEFT($A125,3),IF($B$4:$B$108=$B125,IF($C$3:$AZ$3=G$112,$C$4:$AZ$108))))} -> 0.089 | H125: {=SUMPRODUCT(IF(LEFT($A$4:$A$108,3)=LEFT($A125,3),IF($B$4:$B$108=$B125,IF($C$3:$AZ$3=H$112,$C$4:$AZ$108))))} -> 5087.108 | I125: {=SUMPRODUCT(IF(LEFT($A$4:$A$108,3)=LEFT($A125,3),IF($B$4:$B$108=$B125,IF($C$3:$AZ$3=I$112,$C$4:$AZ$108))))} -> 1243.255 | J125: {=SUMPRODUCT(IF(LEFT($A$4:$A$108,3)=LEFT($A125,3),IF($B$4:$B$108=$B125,IF($C$3:$AZ$3=J$112,$C$4:$AZ$108))))} -> 173.222 | ... O125: {=SUMPRODUCT(IF(LEFT($A$4:$A$108,3)=LEFT($A125,3),IF($B$4:$B$108=$B125,IF($C$3:$AZ$3=O$112,$C$4:$AZ$108))))} -> 10914.329 | P125: {=SUMPRODUCT(IF(LEFT($A$4:$A$108,3)=LEFT($A125,3),IF($B$4:$B$108=$B125,IF($C$3:$AZ$3=P$112,$C$4:$AZ$108))))*'Cement and Glass Split'!O60} -> 391.53372 | Q125: {=SUMPRODUCT(IF(LEFT($A$4:$A$108,3)=LEFT($A125,3),IF($B$4:$B$108=$B125,IF($C$3:$AZ$3=P$112,$C$4:$AZ$108))))*'Cement and Glass Split'!P60} -> 296.24428 | R125: {=SUMPRODUCT(IF(LEFT($A$4:$A$108,3)=LEFT($A125,3),IF($B$4:$B$108=$B125,IF($C$3:$AZ$3=R$112,$C$4:$AZ$108))))} -> 311.578 | S125: {=SUMPRODUCT(IF(LEFT($A$4:$A$108,3)=LEFT($A125,3),IF($B$4:$B$108=$B125,IF($C$3:$AZ$3=S$112,$C$4:$AZ$108))))} -> 319.233 | T125: {=SUMPRODUCT(IF(LEFT($A$4:$A$108,3)=LEFT($A125,3),IF($B$4:$B$108=$B125,IF($C$3:$AZ$3=T$112,$C$4:$AZ$108))))} -> 1603.375 | U125: {=SUMPRODUCT(IF(LEFT($A$4:$A$108,3)=LEFT($A125,3),IF($B$4:$B$108=$B125,IF($C$3:$AZ$3=U$112,$C$4:$AZ$108))))} -> 4647.614 | V125: {=SUMPRODUCT(IF(LEFT($A$4:$A$108,3)=LEFT($A125,3),IF($B$4:$B$108=$B125,IF($C$3:$AZ$3=V$112,$C$4:$AZ$108))))} -> 3831.163 | W125: {=SUMPRODUCT(IF(LEFT($A$4:$A$108,3)=LEFT($A125,3),IF($B$4:$B$108=$B125,IF($C$3:$AZ$3=W$112,$C$4:$AZ$108))))} -> 3525.305 | X125: {=SUMPRODUCT(IF(LEFT($A$4:$A$108,3)=LEFT($A125,3),IF($B$4:$B$108=$B125,IF($C$3:$AZ$3=X$112,$C$4:$AZ$108))))} -> 10341.9 | Y125: {=SUMPRODUCT(IF(LEFT($A$4:$A$108,3)=LEFT($A125,3),IF($B$4:$B$108=$B125,IF($C$3:$AZ$3=Y$112,$C$4:$AZ$108))))} -> 872.82 | ... AR125: {=SUMPRODUCT(IF(LEFT($A$4:$A$108,3)=LEFT($A125,3),IF($B$4:$B$108=$B125,IF($C$3:$AZ$3=AR$112,$C$4:$AZ$108))))} -> 0 | AS125: =SUMIFS($BA$4:$BA$108,$B$4:$B$108,B125,$A$4:$A$108,"DOM*") -> 85333.601
A126: Domestic | B126: ISIC 231 | C126: {=SUMPRODUCT(IF(LEFT($A$4:$A$108,3)=LEFT($A126,3),IF($B$4:$B$108=$B126,IF($C$3:$AZ$3=C$112,$C$4:$AZ$108))))*'Cement and Glass Split'!B61} -> 76.835006 | D126: {=SUMPRODUCT(IF(LEFT($A$4:$A$108,3)=LEFT($A126,3),IF($B$4:$B$108=$B126,IF($C$3:$AZ$3=D$112,$C$4:$AZ$108))))*'Cement and Glass Split'!C61} -> 0.08247911 | E126: {=SUMPRODUCT(IF(LEFT($A$4:$A$108,3)=LEFT($A126,3),IF($B$4:$B$108=$B126,IF($C$3:$AZ$3=E$112,$C$4:$AZ$108))))*'Cement and Glass Split'!D61} -> 0.00019194762 | F126: {=SUMPRODUCT(IF(LEFT($A$4:$A$108,3)=LEFT($A126,3),IF($B$4:$B$108=$B126,IF($C$3:$AZ$3=F$112,$C$4:$AZ$108))))*'Cement and Glass Split'!E61} -> 16.388726 | G126: {=SUMPRODUCT(IF(LEFT($A$4:$A$108,3)=LEFT($A126,3),IF($B$4:$B$108=$B126,IF($C$3:$AZ$3=G$112,$C$4:$AZ$108))))*'Cement and Glass Split'!F61} -> 0 | H126: {=SUMPRODUCT(IF(LEFT($A$4:$A$108,3)=LEFT($A126,3),IF($B$4:$B$108=$B126,IF($C$3:$AZ$3=H$112,$C$4:$AZ$108))))*'Cement and Glass Split'!G61} -> 723.56713 | I126: {=SUMPRODUCT(IF(LEFT($A$4:$A$108,3)=LEFT($A126,3),IF($B$4:$B$108=$B126,IF($C$3:$AZ$3=I$112,$C$4:$AZ$108))))*'Cement and Glass Split'!H61} -> 43.01075 | J126: {=SUMPRODUCT(IF(LEFT($A$4:$A$108,3)=LEFT($A126,3),IF($B$4:$B$108=$B126,IF($C$3:$AZ$3=J$112,$C$4:$AZ$108))))*'Cement and Glass Split'!I61} -> 11.558962 | ... P126: {=SUMPRODUCT(IF(LEFT($A$4:$A$108,3)=LEFT($A126,3),IF($B$4:$B$108=$B126,IF($C$3:$AZ$3=P$112,$C$4:$AZ$108))))*'Cement and Glass Split'!O61} -> 780.22306 | Q126: {=SUMPRODUCT(IF(LEFT($A$4:$A$108,3)=LEFT($A126,3),IF($B$4:$B$108=$B126,IF($C$3:$AZ$3=P$112,$C$4:$AZ$108))))*'Cement and Glass Split'!P61} -> 5.7829287 | R126: {=SUMPRODUCT(IF(LEFT($A$4:$A$108,3)=LEFT($A126,3),IF($B$4:$B$108=$B126,IF($C$3:$AZ$3=R$112,$C$4:$AZ$108))))*'Cement and Glass Split'!Q61} -> 1.5841274 | S126: {=SUMPRODUCT(IF(LEFT($A$4:$A$108,3)=LEFT($A126,3),IF($B$4:$B$108=$B126,IF($C$3:$AZ$3=S$112,$C$4:$AZ$108))))*'Cement and Glass Split'!R61} -> 4.8089776 | T126: {=SUMPRODUCT(IF(LEFT($A$4:$A$108,3)=LEFT($A126,3),IF($B$4:$B$108=$B126,IF($C$3:$AZ$3=T$112,$C$4:$AZ$108))))*'Cement and Glass Split'!S61} -> 84.34829 | U126: {=SUMPRODUCT(IF(LEFT($A$4:$A$108,3)=LEFT($A126,3),IF($B$4:$B$108=$B126,IF($C$3:$AZ$3=U$112,$C$4:$AZ$108))))*'Cement and Glass Split'!T61} -> 908.8072 | V126: {=SUMPRODUCT(IF(LEFT($A$4:$A$108,3)=LEFT($A126,3),IF($B$4:$B$108=$B126,IF($C$3:$AZ$3=V$112,$C$4:$AZ$108))))*'Cement and Glass Split'!U61} -> 310.02305 | W126: {=SUMPRODUCT(IF(LEFT($A$4:$A$108,3)=LEFT($A126,3),IF($B$4:$B$108=$B126,IF($C$3:$AZ$3=W$112,$C$4:$AZ$108))))*'Cement and Glass Split'!V61} -> 134.11984 | X126: {=SUMPRODUCT(IF(LEFT($A$4:$A$108,3)=LEFT($A126,3),IF($B$4:$B$108=$B126,IF($C$3:$AZ$3=X$112,$C$4:$AZ$108))))*'Cement and Glass Split'!W61} -> 834.68647 | Y126: {=SUMPRODUCT(IF(LEFT($A$4:$A$108,3)=LEFT($A126,3),IF($B$4:$B$108=$B126,IF($C$3:$AZ$3=Y$112,$C$4:$AZ$108))))*'Cement and Glass Split'!X61} -> 96.331062 | ... AR126: {=SUMPRODUCT(IF(LEFT($A$4:$A$108,3)=LEFT($A126,3),IF($B$4:$B$108=$B126,IF($C$3:$AZ$3=AR$112,$C$4:$AZ$108))))*'Cement and Glass Split'!AQ61} -> 0 | AS126: {=SUM(C126:AQ126/SUM($C$126:$AQ$127)*$BA$20)} -> 11309.82
A127: Domestic | B127: ISIC 239 | C127: {=SUMPRODUCT(IF(LEFT($A$4:$A$108,3)=LEFT($A126,3),IF($B$4:$B$108=$B126,IF($C$3:$AZ$3=C$112,$C$4:$AZ$108))))*'Cement and Glass Split'!B62} -> 9.7211147 | D127: {=SUMPRODUCT(IF(LEFT($A$4:$A$108,3)=LEFT($A126,3),IF($B$4:$B$108=$B126,IF($C$3:$AZ$3=D$112,$C$4:$AZ$108))))*'Cement and Glass Split'!C62} -> 0.012208493 | E127: {=SUMPRODUCT(IF(LEFT($A$4:$A$108,3)=LEFT($A126,3),IF($B$4:$B$108=$B126,IF($C$3:$AZ$3=E$112,$C$4:$AZ$108))))*'Cement and Glass Split'!D62} -> 0.088513472 | F127: {=SUMPRODUCT(IF(LEFT($A$4:$A$108,3)=LEFT($A126,3),IF($B$4:$B$108=$B126,IF($C$3:$AZ$3=F$112,$C$4:$AZ$108))))*'Cement and Glass Split'!E62} -> 0.20277759 | G127: {=SUMPRODUCT(IF(LEFT($A$4:$A$108,3)=LEFT($A126,3),IF($B$4:$B$108=$B126,IF($C$3:$AZ$3=G$112,$C$4:$AZ$108))))*'Cement and Glass Split'!F62} -> 0 | H127: {=SUMPRODUCT(IF(LEFT($A$4:$A$108,3)=LEFT($A126,3),IF($B$4:$B$108=$B126,IF($C$3:$AZ$3=H$112,$C$4:$AZ$108))))*'Cement and Glass Split'!G62} -> 130.7618 | I127: {=SUMPRODUCT(IF(LEFT($A$4:$A$108,3)=LEFT($A126,3),IF($B$4:$B$108=$B126,IF($C$3:$AZ$3=I$112,$C$4:$AZ$108))))*'Cement and Glass Split'!H62} -> 68.116692 | J127: {=SUMPRODUCT(IF(LEFT($A$4:$A$108,3)=LEFT($A126,3),IF($B$4:$B$108=$B126,IF($C$3:$AZ$3=J$112,$C$4:$AZ$108))))*'Cement and Glass Split'!I62} -> 51.464875 | ... O127: {=SUMPRODUCT(IF(LEFT($A$4:$A$108,3)=LEFT($A126,3),IF($B$4:$B$108=$B126,IF($C$3:$AZ$3=O$112,$C$4:$AZ$108))))*'Cement and Glass Split'!N62} -> 104.53897 | P127: {=SUMPRODUCT(IF(LEFT($A$4:$A$108,3)=LEFT($A127,3),IF($B$4:$B$108=$B126,IF($C$3:$AZ$3=P$112,$C$4:$AZ$108))))*'Cement and Glass Split'!O62} -> 55.17152 | Q127: {=SUMPRODUCT(IF(LEFT($A$4:$A$108,3)=LEFT($A127,3),IF($B$4:$B$108=$B126,IF($C$3:$AZ$3=P$112,$C$4:$AZ$108))))*'Cement and Glass Split'!P62} -> 3613.9455 | R127: {=SUMPRODUCT(IF(LEFT($A$4:$A$108,3)=LEFT($A126,3),IF($B$4:$B$108=$B126,IF($C$3:$AZ$3=R$112,$C$4:$AZ$108))))*'Cement and Glass Split'!Q62} -> 19.071057 | S127: {=SUMPRODUCT(IF(LEFT($A$4:$A$108,3)=LEFT($A126,3),IF($B$4:$B$108=$B126,IF($C$3:$AZ$3=S$112,$C$4:$AZ$108))))*'Cement and Glass Split'!R62} -> 78.205571 | T127: {=SUMPRODUCT(IF(LEFT($A$4:$A$108,3)=LEFT($A126,3),IF($B$4:$B$108=$B126,IF($C$3:$AZ$3=T$112,$C$4:$AZ$108))))*'Cement and Glass Split'!S62} -> 2.9818639 | U127: {=SUMPRODUCT(IF(LEFT($A$4:$A$108,3)=LEFT($A126,3),IF($B$4:$B$108=$B126,IF($C$3:$AZ$3=U$112,$C$4:$AZ$108))))*'Cement and Glass Split'!T62} -> 148.55665 | V127: {=SUMPRODUCT(IF(LEFT($A$4:$A$108,3)=LEFT($A126,3),IF($B$4:$B$108=$B126,IF($C$3:$AZ$3=V$112,$C$4:$AZ$108))))*'Cement and Glass Split'!U62} -> 67.032609 | W127: {=SUMPRODUCT(IF(LEFT($A$4:$A$108,3)=LEFT($A126,3),IF($B$4:$B$108=$B126,IF($C$3:$AZ$3=W$112,$C$4:$AZ$108))))*'Cement and Glass Split'!V62} -> 4.8970746 | X127: {=SUMPRODUCT(IF(LEFT($A$4:$A$108,3)=LEFT($A126,3),IF($B$4:$B$108=$B126,IF($C$3:$AZ$3=X$112,$C$4:$AZ$108))))*'Cement and Glass Split'!W62} -> 26.909335 | Y127: {=SUMPRODUCT(IF(LEFT($A$4:$A$108,3)=LEFT($A126,3),IF($B$4:$B$108=$B126,IF($C$3:$AZ$3=Y$112,$C$4:$AZ$108))))*'Cement and Glass Split'!X62} -> 31.431892 | ... AR127: {=SUMPRODUCT(IF(LEFT($A$4:$A$108,3)=LEFT($A126,3),IF($B$4:$B$108=$B126,IF($C$3:$AZ$3=AR$112,$C$4:$AZ$108))))*'Cement and Glass Split'!AQ62} -> 0 | AS127: {=SUM(C127:AQ127/SUM($C$126:$AQ$127)*$BA$20)} -> 24909.768
A128: Domestic | B128: ISIC 241 | C128: {=SUMPRODUCT(IF(LEFT($A$4:$A$108,3)=LEFT($A128,3),IF($B$4:$B$108=$B128,IF($C$3:$AZ$3=C$112,$C$4:$AZ$108))))} -> 26.061 | D128: {=SUMPRODUCT(IF(LEFT($A$4:$A$108,3)=LEFT($A128,3),IF($B$4:$B$108=$B128,IF($C$3:$AZ$3=D$112,$C$4:$AZ$108))))} -> 1.892 | E128: {=SUMPRODUCT(IF(LEFT($A$4:$A$108,3)=LEFT($A128,3),IF($B$4:$B$108=$B128,IF($C$3:$AZ$3=E$112,$C$4:$AZ$108))))} -> 1.697 | F128: {=SUMPRODUCT(IF(LEFT($A$4:$A$108,3)=LEFT($A128,3),IF($B$4:$B$108=$B128,IF($C$3:$AZ$3=F$112,$C$4:$AZ$108))))} -> 7.497 | G128: {=SUMPRODUCT(IF(LEFT($A$4:$A$108,3)=LEFT($A128,3),IF($B$4:$B$108=$B128,IF($C$3:$AZ$3=G$112,$C$4:$AZ$108))))} -> 0.064 | H128: {=SUMPRODUCT(IF(LEFT($A$4:$A$108,3)=LEFT($A128,3),IF($B$4:$B$108=$B128,IF($C$3:$AZ$3=H$112,$C$4:$AZ$108))))} -> 73.818 | I128: {=SUMPRODUCT(IF(LEFT($A$4:$A$108,3)=LEFT($A128,3),IF($B$4:$B$108=$B128,IF($C$3:$AZ$3=I$112,$C$4:$AZ$108))))} -> 43.348 | J128: {=SUMPRODUCT(IF(LEFT($A$4:$A$108,3)=LEFT($A128,3),IF($B$4:$B$108=$B128,IF($C$3:$AZ$3=J$112,$C$4:$AZ$108))))} -> 31.889 | ... O128: {=SUMPRODUCT(IF(LEFT($A$4:$A$108,3)=LEFT($A128,3),IF($B$4:$B$108=$B128,IF($C$3:$AZ$3=O$112,$C$4:$AZ$108))))} -> 424.222 | P128: {=SUMPRODUCT(IF(LEFT($A$4:$A$108,3)=LEFT($A128,3),IF($B$4:$B$108=$B128,IF($C$3:$AZ$3=P$112,$C$4:$AZ$108))))*'Cement and Glass Split'!O63} -> 26.958095 | Q128: {=SUMPRODUCT(IF(LEFT($A$4:$A$108,3)=LEFT($A128,3),IF($B$4:$B$108=$B128,IF($C$3:$AZ$3=P$112,$C$4:$AZ$108))))*'Cement and Glass Split'!P63} -> 366.76891 | R128: {=SUMPRODUCT(IF(LEFT($A$4:$A$108,3)=LEFT($A128,3),IF($B$4:$B$108=$B128,IF($C$3:$AZ$3=R$112,$C$4:$AZ$108))))} -> 27556.033 | S128: {=SUMPRODUCT(IF(LEFT($A$4:$A$108,3)=LEFT($A128,3),IF($B$4:$B$108=$B128,IF($C$3:$AZ$3=S$112,$C$4:$AZ$108))))} -> 979.041 | T128: {=SUMPRODUCT(IF(LEFT($A$4:$A$108,3)=LEFT($A128,3),IF($B$4:$B$108=$B128,IF($C$3:$AZ$3=T$112,$C$4:$AZ$108))))} -> 17287.533 | U128: {=SUMPRODUCT(IF(LEFT($A$4:$A$108,3)=LEFT($A128,3),IF($B$4:$B$108=$B128,IF($C$3:$AZ$3=U$112,$C$4:$AZ$108))))} -> 1900.338 | V128: {=SUMPRODUCT(IF(LEFT($A$4:$A$108,3)=LEFT($A128,3),IF($B$4:$B$108=$B128,IF($C$3:$AZ$3=V$112,$C$4:$AZ$108))))} -> 3004.49 | W128: {=SUMPRODUCT(IF(LEFT($A$4:$A$108,3)=LEFT($A128,3),IF($B$4:$B$108=$B128,IF($C$3:$AZ$3=W$112,$C$4:$AZ$108))))} -> 11028.23 | X128: {=SUMPRODUCT(IF(LEFT($A$4:$A$108,3)=LEFT($A128,3),IF($B$4:$B$108=$B128,IF($C$3:$AZ$3=X$112,$C$4:$AZ$108))))} -> 8596.851 | Y128: {=SUMPRODUCT(IF(LEFT($A$4:$A$108,3)=LEFT($A128,3),IF($B$4:$B$108=$B128,IF($C$3:$AZ$3=Y$112,$C$4:$AZ$108))))} -> 3083.223 | ... AR128: {=SUMPRODUCT(IF(LEFT($A$4:$A$108,3)=LEFT($A128,3),IF($B$4:$B$108=$B128,IF($C$3:$AZ$3=AR$112,$C$4:$AZ$108))))} -> 0 | AS128: =SUMIFS($BA$4:$BA$108,$B$4:$B$108,B128,$A$4:$A$108,"DOM*") -> 113509.76
A129: Domestic | B129: ISIC 242 | C129: {=SUMPRODUCT(IF(LEFT($A$4:$A$108,3)=LEFT($A129,3),IF($B$4:$B$108=$B129,IF($C$3:$AZ$3=C$112,$C$4:$AZ$108))))} -> 5.736 | D129: {=SUMPRODUCT(IF(LEFT($A$4:$A$108,3)=LEFT($A129,3),IF($B$4:$B$108=$B129,IF($C$3:$AZ$3=D$112,$C$4:$AZ$108))))} -> 0.079 | E129: {=SUMPRODUCT(IF(LEFT($A$4:$A$108,3)=LEFT($A129,3),IF($B$4:$B$108=$B129,IF($C$3:$AZ$3=E$112,$C$4:$AZ$108))))} -> 0.142 | F129: {=SUMPRODUCT(IF(LEFT($A$4:$A$108,3)=LEFT($A129,3),IF($B$4:$B$108=$B129,IF($C$3:$AZ$3=F$112,$C$4:$AZ$108))))} -> 1.572 | G129: {=SUMPRODUCT(IF(LEFT($A$4:$A$108,3)=LEFT($A129,3),IF($B$4:$B$108=$B129,IF($C$3:$AZ$3=G$112,$C$4:$AZ$108))))} -> 0.004 | H129: {=SUMPRODUCT(IF(LEFT($A$4:$A$108,3)=LEFT($A129,3),IF($B$4:$B$108=$B129,IF($C$3:$AZ$3=H$112,$C$4:$AZ$108))))} -> 126.723 | I129: {=SUMPRODUCT(IF(LEFT($A$4:$A$108,3)=LEFT($A129,3),IF($B$4:$B$108=$B129,IF($C$3:$AZ$3=I$112,$C$4:$AZ$108))))} -> 29.998 | J129: {=SUMPRODUCT(IF(LEFT($A$4:$A$108,3)=LEFT($A129,3),IF($B$4:$B$108=$B129,IF($C$3:$AZ$3=J$112,$C$4:$AZ$108))))} -> 12.082 | ... O129: {=SUMPRODUCT(IF(LEFT($A$4:$A$108,3)=LEFT($A129,3),IF($B$4:$B$108=$B129,IF($C$3:$AZ$3=O$112,$C$4:$AZ$108))))} -> 158.435 | P129: {=SUMPRODUCT(IF(LEFT($A$4:$A$108,3)=LEFT($A129,3),IF($B$4:$B$108=$B129,IF($C$3:$AZ$3=P$112,$C$4:$AZ$108))))*'Cement and Glass Split'!O64} -> 14.767048 | Q129: {=SUMPRODUCT(IF(LEFT($A$4:$A$108,3)=LEFT($A129,3),IF($B$4:$B$108=$B129,IF($C$3:$AZ$3=P$112,$C$4:$AZ$108))))*'Cement and Glass Split'!P64} -> 69.142952 | R129: {=SUMPRODUCT(IF(LEFT($A$4:$A$108,3)=LEFT($A129,3),IF($B$4:$B$108=$B129,IF($C$3:$AZ$3=R$112,$C$4:$AZ$108))))} -> 2171.248 | S129: {=SUMPRODUCT(IF(LEFT($A$4:$A$108,3)=LEFT($A129,3),IF($B$4:$B$108=$B129,IF($C$3:$AZ$3=S$112,$C$4:$AZ$108))))} -> 10595.299 | T129: {=SUMPRODUCT(IF(LEFT($A$4:$A$108,3)=LEFT($A129,3),IF($B$4:$B$108=$B129,IF($C$3:$AZ$3=T$112,$C$4:$AZ$108))))} -> 4090.978 | U129: {=SUMPRODUCT(IF(LEFT($A$4:$A$108,3)=LEFT($A129,3),IF($B$4:$B$108=$B129,IF($C$3:$AZ$3=U$112,$C$4:$AZ$108))))} -> 2603.84 | V129: {=SUMPRODUCT(IF(LEFT($A$4:$A$108,3)=LEFT($A129,3),IF($B$4:$B$108=$B129,IF($C$3:$AZ$3=V$112,$C$4:$AZ$108))))} -> 4030.676 | W129: {=SUMPRODUCT(IF(LEFT($A$4:$A$108,3)=LEFT($A129,3),IF($B$4:$B$108=$B129,IF($C$3:$AZ$3=W$112,$C$4:$AZ$108))))} -> 2278.462 | X129: {=SUMPRODUCT(IF(LEFT($A$4:$A$108,3)=LEFT($A129,3),IF($B$4:$B$108=$B129,IF($C$3:$AZ$3=X$112,$C$4:$AZ$108))))} -> 2363.754 | Y129: {=SUMPRODUCT(IF(LEFT($A$4:$A$108,3)=LEFT($A129,3),IF($B$4:$B$108=$B129,IF($C$3:$AZ$3=Y$112,$C$4:$AZ$108))))} -> 496.163 | ... AR129: {=SUMPRODUCT(IF(LEFT($A$4:$A$108,3)=LEFT($A129,3),IF($B$4:$B$108=$B129,IF($C$3:$AZ$3=AR$112,$C$4:$AZ$108))))} -> 0 | AS129: =SUMIFS($BA$4:$BA$108,$B$4:$B$108,B129,$A$4:$A$108,"DOM*") -> 49961.964
A130: Domestic | B130: ISIC 25 | C130: {=SUMPRODUCT(IF(LEFT($A$4:$A$108,3)=LEFT($A130,3),IF($B$4:$B$108=$B130,IF($C$3:$AZ$3=C$112,$C$4:$AZ$108))))} -> 237.258 | D130: {=SUMPRODUCT(IF(LEFT($A$4:$A$108,3)=LEFT($A130,3),IF($B$4:$B$108=$B130,IF($C$3:$AZ$3=D$112,$C$4:$AZ$108))))} -> 5.93 | E130: {=SUMPRODUCT(IF(LEFT($A$4:$A$108,3)=LEFT($A130,3),IF($B$4:$B$108=$B130,IF($C$3:$AZ$3=E$112,$C$4:$AZ$108))))} -> 2.283 | F130: {=SUMPRODUCT(IF(LEFT($A$4:$A$108,3)=LEFT($A130,3),IF($B$4:$B$108=$B130,IF($C$3:$AZ$3=F$112,$C$4:$AZ$108))))} -> 39.234 | G130: {=SUMPRODUCT(IF(LEFT($A$4:$A$108,3)=LEFT($A130,3),IF($B$4:$B$108=$B130,IF($C$3:$AZ$3=G$112,$C$4:$AZ$108))))} -> 0.303 | H130: {=SUMPRODUCT(IF(LEFT($A$4:$A$108,3)=LEFT($A130,3),IF($B$4:$B$108=$B130,IF($C$3:$AZ$3=H$112,$C$4:$AZ$108))))} -> 1808.278 | I130: {=SUMPRODUCT(IF(LEFT($A$4:$A$108,3)=LEFT($A130,3),IF($B$4:$B$108=$B130,IF($C$3:$AZ$3=I$112,$C$4:$AZ$108))))} -> 294.053 | J130: {=SUMPRODUCT(IF(LEFT($A$4:$A$108,3)=LEFT($A130,3),IF($B$4:$B$108=$B130,IF($C$3:$AZ$3=J$112,$C$4:$AZ$108))))} -> 228.106 | ... O130: {=SUMPRODUCT(IF(LEFT($A$4:$A$108,3)=LEFT($A130,3),IF($B$4:$B$108=$B130,IF($C$3:$AZ$3=O$112,$C$4:$AZ$108))))} -> 872.972 | P130: {=SUMPRODUCT(IF(LEFT($A$4:$A$108,3)=LEFT($A130,3),IF($B$4:$B$108=$B130,IF($C$3:$AZ$3=P$112,$C$4:$AZ$108))))*'Cement and Glass Split'!O65} -> 192.4553 | Q130: {=SUMPRODUCT(IF(LEFT($A$4:$A$108,3)=LEFT($A130,3),IF($B$4:$B$108=$B130,IF($C$3:$AZ$3=P$112,$C$4:$AZ$108))))*'Cement and Glass Split'!P65} -> 330.0577 | R130: {=SUMPRODUCT(IF(LEFT($A$4:$A$108,3)=LEFT($A130,3),IF($B$4:$B$108=$B130,IF($C$3:$AZ$3=R$112,$C$4:$AZ$108))))} -> 2777.544 | S130: {=SUMPRODUCT(IF(LEFT($A$4:$A$108,3)=LEFT($A130,3),IF($B$4:$B$108=$B130,IF($C$3:$AZ$3=S$112,$C$4:$AZ$108))))} -> 821.156 | T130: {=SUMPRODUCT(IF(LEFT($A$4:$A$108,3)=LEFT($A130,3),IF($B$4:$B$108=$B130,IF($C$3:$AZ$3=T$112,$C$4:$AZ$108))))} -> 13649.174 | U130: {=SUMPRODUCT(IF(LEFT($A$4:$A$108,3)=LEFT($A130,3),IF($B$4:$B$108=$B130,IF($C$3:$AZ$3=U$112,$C$4:$AZ$108))))} -> 3633.745 | V130: {=SUMPRODUCT(IF(LEFT($A$4:$A$108,3)=LEFT($A130,3),IF($B$4:$B$108=$B130,IF($C$3:$AZ$3=V$112,$C$4:$AZ$108))))} -> 3786.892 | W130: {=SUMPRODUCT(IF(LEFT($A$4:$A$108,3)=LEFT($A130,3),IF($B$4:$B$108=$B130,IF($C$3:$AZ$3=W$112,$C$4:$AZ$108))))} -> 12596.023 | X130: {=SUMPRODUCT(IF(LEFT($A$4:$A$108,3)=LEFT($A130,3),IF($B$4:$B$108=$B130,IF($C$3:$AZ$3=X$112,$C$4:$AZ$108))))} -> 10177.259 | Y130: {=SUMPRODUCT(IF(LEFT($A$4:$A$108,3)=LEFT($A130,3),IF($B$4:$B$108=$B130,IF($C$3:$AZ$3=Y$112,$C$4:$AZ$108))))} -> 3970.226 | ... AR130: {=SUMPRODUCT(IF(LEFT($A$4:$A$108,3)=LEFT($A130,3),IF($B$4:$B$108=$B130,IF($C$3:$AZ$3=AR$112,$C$4:$AZ$108))))} -> 0 | AS130: =SUMIFS($BA$4:$BA$108,$B$4:$B$108,B130,$A$4:$A$108,"DOM*") -> 103590.65
A131: Domestic | B131: ISIC 26 | C131: {=SUMPRODUCT(IF(LEFT($A$4:$A$108,3)=LEFT($A131,3),IF($B$4:$B$108=$B131,IF($C$3:$AZ$3=C$112,$C$4:$AZ$108))))} -> 105.988 | D131: {=SUMPRODUCT(IF(LEFT($A$4:$A$108,3)=LEFT($A131,3),IF($B$4:$B$108=$B131,IF($C$3:$AZ$3=D$112,$C$4:$AZ$108))))} -> 0.922 | E131: {=SUMPRODUCT(IF(LEFT($A$4:$A$108,3)=LEFT($A131,3),IF($B$4:$B$108=$B131,IF($C$3:$AZ$3=E$112,$C$4:$AZ$108))))} -> 0.615 | F131: {=SUMPRODUCT(IF(LEFT($A$4:$A$108,3)=LEFT($A131,3),IF($B$4:$B$108=$B131,IF($C$3:$AZ$3=F$112,$C$4:$AZ$108))))} -> 13.341 | G131: {=SUMPRODUCT(IF(LEFT($A$4:$A$108,3)=LEFT($A131,3),IF($B$4:$B$108=$B131,IF($C$3:$AZ$3=G$112,$C$4:$AZ$108))))} -> 0.078 | H131: {=SUMPRODUCT(IF(LEFT($A$4:$A$108,3)=LEFT($A131,3),IF($B$4:$B$108=$B131,IF($C$3:$AZ$3=H$112,$C$4:$AZ$108))))} -> 265.987 | I131: {=SUMPRODUCT(IF(LEFT($A$4:$A$108,3)=LEFT($A131,3),IF($B$4:$B$108=$B131,IF($C$3:$AZ$3=I$112,$C$4:$AZ$108))))} -> 140.058 | J131: {=SUMPRODUCT(IF(LEFT($A$4:$A$108,3)=LEFT($A131,3),IF($B$4:$B$108=$B131,IF($C$3:$AZ$3=J$112,$C$4:$AZ$108))))} -> 19.836 | ... O131: {=SUMPRODUCT(IF(LEFT($A$4:$A$108,3)=LEFT($A131,3),IF($B$4:$B$108=$B131,IF($C$3:$AZ$3=O$112,$C$4:$AZ$108))))} -> 388.662 | P131: {=SUMPRODUCT(IF(LEFT($A$4:$A$108,3)=LEFT($A131,3),IF($B$4:$B$108=$B131,IF($C$3:$AZ$3=P$112,$C$4:$AZ$108))))*'Cement and Glass Split'!O66} -> 57.646204 | Q131: {=SUMPRODUCT(IF(LEFT($A$4:$A$108,3)=LEFT($A131,3),IF($B$4:$B$108=$B131,IF($C$3:$AZ$3=P$112,$C$4:$AZ$108))))*'Cement and Glass Split'!P66} -> 96.062796 | R131: {=SUMPRODUCT(IF(LEFT($A$4:$A$108,3)=LEFT($A131,3),IF($B$4:$B$108=$B131,IF($C$3:$AZ$3=R$112,$C$4:$AZ$108))))} -> 188.645 | S131: {=SUMPRODUCT(IF(LEFT($A$4:$A$108,3)=LEFT($A131,3),IF($B$4:$B$108=$B131,IF($C$3:$AZ$3=S$112,$C$4:$AZ$108))))} -> 121.011 | T131: {=SUMPRODUCT(IF(LEFT($A$4:$A$108,3)=LEFT($A131,3),IF($B$4:$B$108=$B131,IF($C$3:$AZ$3=T$112,$C$4:$AZ$108))))} -> 588.559 | U131: {=SUMPRODUCT(IF(LEFT($A$4:$A$108,3)=LEFT($A131,3),IF($B$4:$B$108=$B131,IF($C$3:$AZ$3=U$112,$C$4:$AZ$108))))} -> 70046.538 | V131: {=SUMPRODUCT(IF(LEFT($A$4:$A$108,3)=LEFT($A131,3),IF($B$4:$B$108=$B131,IF($C$3:$AZ$3=V$112,$C$4:$AZ$108))))} -> 6425.627 | W131: {=SUMPRODUCT(IF(LEFT($A$4:$A$108,3)=LEFT($A131,3),IF($B$4:$B$108=$B131,IF($C$3:$AZ$3=W$112,$C$4:$AZ$108))))} -> 3958.054 | X131: {=SUMPRODUCT(IF(LEFT($A$4:$A$108,3)=LEFT($A131,3),IF($B$4:$B$108=$B131,IF($C$3:$AZ$3=X$112,$C$4:$AZ$108))))} -> 3815.146 | Y131: {=SUMPRODUCT(IF(LEFT($A$4:$A$108,3)=LEFT($A131,3),IF($B$4:$B$108=$B131,IF($C$3:$AZ$3=Y$112,$C$4:$AZ$108))))} -> 1309.771 | ... AR131: {=SUMPRODUCT(IF(LEFT($A$4:$A$108,3)=LEFT($A131,3),IF($B$4:$B$108=$B131,IF($C$3:$AZ$3=AR$112,$C$4:$AZ$108))))} -> 0 | AS131: =SUMIFS($BA$4:$BA$108,$B$4:$B$108,B131,$A$4:$A$108,"DOM*") -> 341950.86
A132: Domestic | B132: ISIC 27 | C132: {=SUMPRODUCT(IF(LEFT($A$4:$A$108,3)=LEFT($A132,3),IF($B$4:$B$108=$B132,IF($C$3:$AZ$3=C$112,$C$4:$AZ$108))))} -> 92.519 | D132: {=SUMPRODUCT(IF(LEFT($A$4:$A$108,3)=LEFT($A132,3),IF($B$4:$B$108=$B132,IF($C$3:$AZ$3=D$112,$C$4:$AZ$108))))} -> 1.533 | E132: {=SUMPRODUCT(IF(LEFT($A$4:$A$108,3)=LEFT($A132,3),IF($B$4:$B$108=$B132,IF($C$3:$AZ$3=E$112,$C$4:$AZ$108))))} -> 0.466 | F132: {=SUMPRODUCT(IF(LEFT($A$4:$A$108,3)=LEFT($A132,3),IF($B$4:$B$108=$B132,IF($C$3:$AZ$3=F$112,$C$4:$AZ$108))))} -> 25.204 | G132: {=SUMPRODUCT(IF(LEFT($A$4:$A$108,3)=LEFT($A132,3),IF($B$4:$B$108=$B132,IF($C$3:$AZ$3=G$112,$C$4:$AZ$108))))} -> 0.117 | H132: {=SUMPRODUCT(IF(LEFT($A$4:$A$108,3)=LEFT($A132,3),IF($B$4:$B$108=$B132,IF($C$3:$AZ$3=H$112,$C$4:$AZ$108))))} -> 221.102 | I132: {=SUMPRODUCT(IF(LEFT($A$4:$A$108,3)=LEFT($A132,3),IF($B$4:$B$108=$B132,IF($C$3:$AZ$3=I$112,$C$4:$AZ$108))))} -> 88.119 | J132: {=SUMPRODUCT(IF(LEFT($A$4:$A$108,3)=LEFT($A132,3),IF($B$4:$B$108=$B132,IF($C$3:$AZ$3=J$112,$C$4:$AZ$108))))} -> 17.835 | ... O132: {=SUMPRODUCT(IF(LEFT($A$4:$A$108,3)=LEFT($A132,3),IF($B$4:$B$108=$B132,IF($C$3:$AZ$3=O$112,$C$4:$AZ$108))))} -> 251.542 | P132: {=SUMPRODUCT(IF(LEFT($A$4:$A$108,3)=LEFT($A132,3),IF($B$4:$B$108=$B132,IF($C$3:$AZ$3=P$112,$C$4:$AZ$108))))*'Cement and Glass Split'!O67} -> 56.934709 | Q132: {=SUMPRODUCT(IF(LEFT($A$4:$A$108,3)=LEFT($A132,3),IF($B$4:$B$108=$B132,IF($C$3:$AZ$3=P$112,$C$4:$AZ$108))))*'Cement and Glass Split'!P67} -> 76.894291 | R132: {=SUMPRODUCT(IF(LEFT($A$4:$A$108,3)=LEFT($A132,3),IF($B$4:$B$108=$B132,IF($C$3:$AZ$3=R$112,$C$4:$AZ$108))))} -> 292.34 | S132: {=SUMPRODUCT(IF(LEFT($A$4:$A$108,3)=LEFT($A132,3),IF($B$4:$B$108=$B132,IF($C$3:$AZ$3=S$112,$C$4:$AZ$108))))} -> 198.384 | T132: {=SUMPRODUCT(IF(LEFT($A$4:$A$108,3)=LEFT($A132,3),IF($B$4:$B$108=$B132,IF($C$3:$AZ$3=T$112,$C$4:$AZ$108))))} -> 904.916 | U132: {=SUMPRODUCT(IF(LEFT($A$4:$A$108,3)=LEFT($A132,3),IF($B$4:$B$108=$B132,IF($C$3:$AZ$3=U$112,$C$4:$AZ$108))))} -> 9918.152 | V132: {=SUMPRODUCT(IF(LEFT($A$4:$A$108,3)=LEFT($A132,3),IF($B$4:$B$108=$B132,IF($C$3:$AZ$3=V$112,$C$4:$AZ$108))))} -> 20657.8 | W132: {=SUMPRODUCT(IF(LEFT($A$4:$A$108,3)=LEFT($A132,3),IF($B$4:$B$108=$B132,IF($C$3:$AZ$3=W$112,$C$4:$AZ$108))))} -> 5960.729 | X132: {=SUMPRODUCT(IF(LEFT($A$4:$A$108,3)=LEFT($A132,3),IF($B$4:$B$108=$B132,IF($C$3:$AZ$3=X$112,$C$4:$AZ$108))))} -> 8391.132 | Y132: {=SUMPRODUCT(IF(LEFT($A$4:$A$108,3)=LEFT($A132,3),IF($B$4:$B$108=$B132,IF($C$3:$AZ$3=Y$112,$C$4:$AZ$108))))} -> 1180.095 | ... AR132: {=SUMPRODUCT(IF(LEFT($A$4:$A$108,3)=LEFT($A132,3),IF($B$4:$B$108=$B132,IF($C$3:$AZ$3=AR$112,$C$4:$AZ$108))))} -> 0 | AS132: =SUMIFS($BA$4:$BA$108,$B$4:$B$108,B132,$A$4:$A$108,"DOM*") -> 118568.56
A133: Domestic | B133: ISIC 28 | C133: {=SUMPRODUCT(IF(LEFT($A$4:$A$108,3)=LEFT($A133,3),IF($B$4:$B$108=$B133,IF($C$3:$AZ$3=C$112,$C$4:$AZ$108))))} -> 219.979 | D133: {=SUMPRODUCT(IF(LEFT($A$4:$A$108,3)=LEFT($A133,3),IF($B$4:$B$108=$B133,IF($C$3:$AZ$3=D$112,$C$4:$AZ$108))))} -> 9.333 | E133: {=SUMPRODUCT(IF(LEFT($A$4:$A$108,3)=LEFT($A133,3),IF($B$4:$B$108=$B133,IF($C$3:$AZ$3=E$112,$C$4:$AZ$108))))} -> 3.479 | F133: {=SUMPRODUCT(IF(LEFT($A$4:$A$108,3)=LEFT($A133,3),IF($B$4:$B$108=$B133,IF($C$3:$AZ$3=F$112,$C$4:$AZ$108))))} -> 74.432 | G133: {=SUMPRODUCT(IF(LEFT($A$4:$A$108,3)=LEFT($A133,3),IF($B$4:$B$108=$B133,IF($C$3:$AZ$3=G$112,$C$4:$AZ$108))))} -> 0.439 | H133: {=SUMPRODUCT(IF(LEFT($A$4:$A$108,3)=LEFT($A133,3),IF($B$4:$B$108=$B133,IF($C$3:$AZ$3=H$112,$C$4:$AZ$108))))} -> 621.11 | I133: {=SUMPRODUCT(IF(LEFT($A$4:$A$108,3)=LEFT($A133,3),IF($B$4:$B$108=$B133,IF($C$3:$AZ$3=I$112,$C$4:$AZ$108))))} -> 195.117 | J133: {=SUMPRODUCT(IF(LEFT($A$4:$A$108,3)=LEFT($A133,3),IF($B$4:$B$108=$B133,IF($C$3:$AZ$3=J$112,$C$4:$AZ$108))))} -> 62.785 | ... O133: {=SUMPRODUCT(IF(LEFT($A$4:$A$108,3)=LEFT($A133,3),IF($B$4:$B$108=$B133,IF($C$3:$AZ$3=O$112,$C$4:$AZ$108))))} -> 364.03 | P133: {=SUMPRODUCT(IF(LEFT($A$4:$A$108,3)=LEFT($A133,3),IF($B$4:$B$108=$B133,IF($C$3:$AZ$3=P$112,$C$4:$AZ$108))))*'Cement and Glass Split'!O68} -> 196.19858 | Q133: {=SUMPRODUCT(IF(LEFT($A$4:$A$108,3)=LEFT($A133,3),IF($B$4:$B$108=$B133,IF($C$3:$AZ$3=P$112,$C$4:$AZ$108))))*'Cement and Glass Split'!P68} -> 371.08742 | R133: {=SUMPRODUCT(IF(LEFT($A$4:$A$108,3)=LEFT($A133,3),IF($B$4:$B$108=$B133,IF($C$3:$AZ$3=R$112,$C$4:$AZ$108))))} -> 1173.667 | S133: {=SUMPRODUCT(IF(LEFT($A$4:$A$108,3)=LEFT($A133,3),IF($B$4:$B$108=$B133,IF($C$3:$AZ$3=S$112,$C$4:$AZ$108))))} -> 445.635 | T133: {=SUMPRODUCT(IF(LEFT($A$4:$A$108,3)=LEFT($A133,3),IF($B$4:$B$108=$B133,IF($C$3:$AZ$3=T$112,$C$4:$AZ$108))))} -> 1429.215 | U133: {=SUMPRODUCT(IF(LEFT($A$4:$A$108,3)=LEFT($A133,3),IF($B$4:$B$108=$B133,IF($C$3:$AZ$3=U$112,$C$4:$AZ$108))))} -> 1967.918 | V133: {=SUMPRODUCT(IF(LEFT($A$4:$A$108,3)=LEFT($A133,3),IF($B$4:$B$108=$B133,IF($C$3:$AZ$3=V$112,$C$4:$AZ$108))))} -> 2643.774 | W133: {=SUMPRODUCT(IF(LEFT($A$4:$A$108,3)=LEFT($A133,3),IF($B$4:$B$108=$B133,IF($C$3:$AZ$3=W$112,$C$4:$AZ$108))))} -> 18680.703 | X133: {=SUMPRODUCT(IF(LEFT($A$4:$A$108,3)=LEFT($A133,3),IF($B$4:$B$108=$B133,IF($C$3:$AZ$3=X$112,$C$4:$AZ$108))))} -> 5937.143 | Y133: {=SUMPRODUCT(IF(LEFT($A$4:$A$108,3)=LEFT($A133,3),IF($B$4:$B$108=$B133,IF($C$3:$AZ$3=Y$112,$C$4:$AZ$108))))} -> 2276.005 | ... AR133: {=SUMPRODUCT(IF(LEFT($A$4:$A$108,3)=LEFT($A133,3),IF($B$4:$B$108=$B133,IF($C$3:$AZ$3=AR$112,$C$4:$AZ$108))))} -> 0 | AS133: =SUMIFS($BA$4:$BA$108,$B$4:$B$108,B133,$A$4:$A$108,"DOM*") -> 149990.58
A134: Domestic | B134: ISIC 29 | C134: {=SUMPRODUCT(IF(LEFT($A$4:$A$108,3)=LEFT($A134,3),IF($B$4:$B$108=$B134,IF($C$3:$AZ$3=C$112,$C$4:$AZ$108))))} -> 79.71 | D134: {=SUMPRODUCT(IF(LEFT($A$4:$A$108,3)=LEFT($A134,3),IF($B$4:$B$108=$B134,IF($C$3:$AZ$3=D$112,$C$4:$AZ$108))))} -> 0.523 | E134: {=SUMPRODUCT(IF(LEFT($A$4:$A$108,3)=LEFT($A134,3),IF($B$4:$B$108=$B134,IF($C$3:$AZ$3=E$112,$C$4:$AZ$108))))} -> 0.306 | F134: {=SUMPRODUCT(IF(LEFT($A$4:$A$108,3)=LEFT($A134,3),IF($B$4:$B$108=$B134,IF($C$3:$AZ$3=F$112,$C$4:$AZ$108))))} -> 14.445 | G134: {=SUMPRODUCT(IF(LEFT($A$4:$A$108,3)=LEFT($A134,3),IF($B$4:$B$108=$B134,IF($C$3:$AZ$3=G$112,$C$4:$AZ$108))))} -> 0.05 | H134: {=SUMPRODUCT(IF(LEFT($A$4:$A$108,3)=LEFT($A134,3),IF($B$4:$B$108=$B134,IF($C$3:$AZ$3=H$112,$C$4:$AZ$108))))} -> 140.086 | I134: {=SUMPRODUCT(IF(LEFT($A$4:$A$108,3)=LEFT($A134,3),IF($B$4:$B$108=$B134,IF($C$3:$AZ$3=I$112,$C$4:$AZ$108))))} -> 60.011 | J134: {=SUMPRODUCT(IF(LEFT($A$4:$A$108,3)=LEFT($A134,3),IF($B$4:$B$108=$B134,IF($C$3:$AZ$3=J$112,$C$4:$AZ$108))))} -> 13.312 | ... O134: {=SUMPRODUCT(IF(LEFT($A$4:$A$108,3)=LEFT($A134,3),IF($B$4:$B$108=$B134,IF($C$3:$AZ$3=O$112,$C$4:$AZ$108))))} -> 120.02 | P134: {=SUMPRODUCT(IF(LEFT($A$4:$A$108,3)=LEFT($A134,3),IF($B$4:$B$108=$B134,IF($C$3:$AZ$3=P$112,$C$4:$AZ$108))))*'Cement and Glass Split'!O69} -> 8.9243009 | Q134: {=SUMPRODUCT(IF(LEFT($A$4:$A$108,3)=LEFT($A134,3),IF($B$4:$B$108=$B134,IF($C$3:$AZ$3=P$112,$C$4:$AZ$108))))*'Cement and Glass Split'!P69} -> 102.9177 | R134: {=SUMPRODUCT(IF(LEFT($A$4:$A$108,3)=LEFT($A134,3),IF($B$4:$B$108=$B134,IF($C$3:$AZ$3=R$112,$C$4:$AZ$108))))} -> 137.133 | S134: {=SUMPRODUCT(IF(LEFT($A$4:$A$108,3)=LEFT($A134,3),IF($B$4:$B$108=$B134,IF($C$3:$AZ$3=S$112,$C$4:$AZ$108))))} -> 99.084 | T134: {=SUMPRODUCT(IF(LEFT($A$4:$A$108,3)=LEFT($A134,3),IF($B$4:$B$108=$B134,IF($C$3:$AZ$3=T$112,$C$4:$AZ$108))))} -> 273.078 | U134: {=SUMPRODUCT(IF(LEFT($A$4:$A$108,3)=LEFT($A134,3),IF($B$4:$B$108=$B134,IF($C$3:$AZ$3=U$112,$C$4:$AZ$108))))} -> 1262.731 | V134: {=SUMPRODUCT(IF(LEFT($A$4:$A$108,3)=LEFT($A134,3),IF($B$4:$B$108=$B134,IF($C$3:$AZ$3=V$112,$C$4:$AZ$108))))} -> 2315.707 | W134: {=SUMPRODUCT(IF(LEFT($A$4:$A$108,3)=LEFT($A134,3),IF($B$4:$B$108=$B134,IF($C$3:$AZ$3=W$112,$C$4:$AZ$108))))} -> 1405.481 | X134: {=SUMPRODUCT(IF(LEFT($A$4:$A$108,3)=LEFT($A134,3),IF($B$4:$B$108=$B134,IF($C$3:$AZ$3=X$112,$C$4:$AZ$108))))} -> 55827.983 | Y134: {=SUMPRODUCT(IF(LEFT($A$4:$A$108,3)=LEFT($A134,3),IF($B$4:$B$108=$B134,IF($C$3:$AZ$3=Y$112,$C$4:$AZ$108))))} -> 361.298 | ... AR134: {=SUMPRODUCT(IF(LEFT($A$4:$A$108,3)=LEFT($A134,3),IF($B$4:$B$108=$B134,IF($C$3:$AZ$3=AR$112,$C$4:$AZ$108))))} -> 0 | AS134: =SUMIFS($BA$4:$BA$108,$B$4:$B$108,B134,$A$4:$A$108,"DOM*") -> 216241.5
A135: Domestic | B135: ISIC 30 | C135: {=SUMPRODUCT(IF(LEFT($A$4:$A$108,3)=LEFT($A135,3),IF($B$4:$B$108=$B135,IF($C$3:$AZ$3=C$112,$C$4:$AZ$108))))} -> 33.927 | D135: {=SUMPRODUCT(IF(LEFT($A$4:$A$108,3)=LEFT($A135,3),IF($B$4:$B$108=$B135,IF($C$3:$AZ$3=D$112,$C$4:$AZ$108))))} -> 0.371 | E135: {=SUMPRODUCT(IF(LEFT($A$4:$A$108,3)=LEFT($A135,3),IF($B$4:$B$108=$B135,IF($C$3:$AZ$3=E$112,$C$4:$AZ$108))))} -> 0.153 | F135: {=SUMPRODUCT(IF(LEFT($A$4:$A$108,3)=LEFT($A135,3),IF($B$4:$B$108=$B135,IF($C$3:$AZ$3=F$112,$C$4:$AZ$108))))} -> 2.937 | G135: {=SUMPRODUCT(IF(LEFT($A$4:$A$108,3)=LEFT($A135,3),IF($B$4:$B$108=$B135,IF($C$3:$AZ$3=G$112,$C$4:$AZ$108))))} -> 0.018 | H135: {=SUMPRODUCT(IF(LEFT($A$4:$A$108,3)=LEFT($A135,3),IF($B$4:$B$108=$B135,IF($C$3:$AZ$3=H$112,$C$4:$AZ$108))))} -> 86.554 | I135: {=SUMPRODUCT(IF(LEFT($A$4:$A$108,3)=LEFT($A135,3),IF($B$4:$B$108=$B135,IF($C$3:$AZ$3=I$112,$C$4:$AZ$108))))} -> 14.313 | J135: {=SUMPRODUCT(IF(LEFT($A$4:$A$108,3)=LEFT($A135,3),IF($B$4:$B$108=$B135,IF($C$3:$AZ$3=J$112,$C$4:$AZ$108))))} -> 10.408 | ... O135: {=SUMPRODUCT(IF(LEFT($A$4:$A$108,3)=LEFT($A135,3),IF($B$4:$B$108=$B135,IF($C$3:$AZ$3=O$112,$C$4:$AZ$108))))} -> 40.396 | P135: {=SUMPRODUCT(IF(LEFT($A$4:$A$108,3)=LEFT($A135,3),IF($B$4:$B$108=$B135,IF($C$3:$AZ$3=P$112,$C$4:$AZ$108))))*'Cement and Glass Split'!O70} -> 11.04278 | Q135: {=SUMPRODUCT(IF(LEFT($A$4:$A$108,3)=LEFT($A135,3),IF($B$4:$B$108=$B135,IF($C$3:$AZ$3=P$112,$C$4:$AZ$108))))*'Cement and Glass Split'!P70} -> 18.85622 | R135: {=SUMPRODUCT(IF(LEFT($A$4:$A$108,3)=LEFT($A135,3),IF($B$4:$B$108=$B135,IF($C$3:$AZ$3=R$112,$C$4:$AZ$108))))} -> 208.225 | S135: {=SUMPRODUCT(IF(LEFT($A$4:$A$108,3)=LEFT($A135,3),IF($B$4:$B$108=$B135,IF($C$3:$AZ$3=S$112,$C$4:$AZ$108))))} -> 39.994 | T135: {=SUMPRODUCT(IF(LEFT($A$4:$A$108,3)=LEFT($A135,3),IF($B$4:$B$108=$B135,IF($C$3:$AZ$3=T$112,$C$4:$AZ$108))))} -> 638.157 | U135: {=SUMPRODUCT(IF(LEFT($A$4:$A$108,3)=LEFT($A135,3),IF($B$4:$B$108=$B135,IF($C$3:$AZ$3=U$112,$C$4:$AZ$108))))} -> 193.496 | V135: {=SUMPRODUCT(IF(LEFT($A$4:$A$108,3)=LEFT($A135,3),IF($B$4:$B$108=$B135,IF($C$3:$AZ$3=V$112,$C$4:$AZ$108))))} -> 208.621 | W135: {=SUMPRODUCT(IF(LEFT($A$4:$A$108,3)=LEFT($A135,3),IF($B$4:$B$108=$B135,IF($C$3:$AZ$3=W$112,$C$4:$AZ$108))))} -> 732.648 | X135: {=SUMPRODUCT(IF(LEFT($A$4:$A$108,3)=LEFT($A135,3),IF($B$4:$B$108=$B135,IF($C$3:$AZ$3=X$112,$C$4:$AZ$108))))} -> 808.292 | Y135: {=SUMPRODUCT(IF(LEFT($A$4:$A$108,3)=LEFT($A135,3),IF($B$4:$B$108=$B135,IF($C$3:$AZ$3=Y$112,$C$4:$AZ$108))))} -> 5209.471 | ... AR135: {=SUMPRODUCT(IF(LEFT($A$4:$A$108,3)=LEFT($A135,3),IF($B$4:$B$108=$B135,IF($C$3:$AZ$3=AR$112,$C$4:$AZ$108))))} -> 0 | AS135: =SUMIFS($BA$4:$BA$108,$B$4:$B$108,B135,$A$4:$A$108,"DOM*") -> 44810.926
A136: Domestic | B136: ISIC 31T33 | C136: {=SUMPRODUCT(IF(LEFT($A$4:$A$108,3)=LEFT($A136,3),IF($B$4:$B$108=$B136,IF($C$3:$AZ$3=C$112,$C$4:$AZ$108))))} -> 82.048 | D136: {=SUMPRODUCT(IF(LEFT($A$4:$A$108,3)=LEFT($A136,3),IF($B$4:$B$108=$B136,IF($C$3:$AZ$3=D$112,$C$4:$AZ$108))))} -> 0.443 | E136: {=SUMPRODUCT(IF(LEFT($A$4:$A$108,3)=LEFT($A136,3),IF($B$4:$B$108=$B136,IF($C$3:$AZ$3=E$112,$C$4:$AZ$108))))} -> 0.462 | F136: {=SUMPRODUCT(IF(LEFT($A$4:$A$108,3)=LEFT($A136,3),IF($B$4:$B$108=$B136,IF($C$3:$AZ$3=F$112,$C$4:$AZ$108))))} -> 10.107 | G136: {=SUMPRODUCT(IF(LEFT($A$4:$A$108,3)=LEFT($A136,3),IF($B$4:$B$108=$B136,IF($C$3:$AZ$3=G$112,$C$4:$AZ$108))))} -> 0.053 | H136: {=SUMPRODUCT(IF(LEFT($A$4:$A$108,3)=LEFT($A136,3),IF($B$4:$B$108=$B136,IF($C$3:$AZ$3=H$112,$C$4:$AZ$108))))} -> 181.847 | I136: {=SUMPRODUCT(IF(LEFT($A$4:$A$108,3)=LEFT($A136,3),IF($B$4:$B$108=$B136,IF($C$3:$AZ$3=I$112,$C$4:$AZ$108))))} -> 280.955 | J136: {=SUMPRODUCT(IF(LEFT($A$4:$A$108,3)=LEFT($A136,3),IF($B$4:$B$108=$B136,IF($C$3:$AZ$3=J$112,$C$4:$AZ$108))))} -> 20.928 | ... O136: {=SUMPRODUCT(IF(LEFT($A$4:$A$108,3)=LEFT($A136,3),IF($B$4:$B$108=$B136,IF($C$3:$AZ$3=O$112,$C$4:$AZ$108))))} -> 78.704 | P136: {=SUMPRODUCT(IF(LEFT($A$4:$A$108,3)=LEFT($A136,3),IF($B$4:$B$108=$B136,IF($C$3:$AZ$3=P$112,$C$4:$AZ$108))))*'Cement and Glass Split'!O71} -> 38.892935 | Q136: {=SUMPRODUCT(IF(LEFT($A$4:$A$108,3)=LEFT($A136,3),IF($B$4:$B$108=$B136,IF($C$3:$AZ$3=P$112,$C$4:$AZ$108))))*'Cement and Glass Split'!P71} -> 31.749065 | R136: {=SUMPRODUCT(IF(LEFT($A$4:$A$108,3)=LEFT($A136,3),IF($B$4:$B$108=$B136,IF($C$3:$AZ$3=R$112,$C$4:$AZ$108))))} -> 143.971 | S136: {=SUMPRODUCT(IF(LEFT($A$4:$A$108,3)=LEFT($A136,3),IF($B$4:$B$108=$B136,IF($C$3:$AZ$3=S$112,$C$4:$AZ$108))))} -> 66.817 | T136: {=SUMPRODUCT(IF(LEFT($A$4:$A$108,3)=LEFT($A136,3),IF($B$4:$B$108=$B136,IF($C$3:$AZ$3=T$112,$C$4:$AZ$108))))} -> 138.258 | U136: {=SUMPRODUCT(IF(LEFT($A$4:$A$108,3)=LEFT($A136,3),IF($B$4:$B$108=$B136,IF($C$3:$AZ$3=U$112,$C$4:$AZ$108))))} -> 538.39 | V136: {=SUMPRODUCT(IF(LEFT($A$4:$A$108,3)=LEFT($A136,3),IF($B$4:$B$108=$B136,IF($C$3:$AZ$3=V$112,$C$4:$AZ$108))))} -> 222.092 | W136: {=SUMPRODUCT(IF(LEFT($A$4:$A$108,3)=LEFT($A136,3),IF($B$4:$B$108=$B136,IF($C$3:$AZ$3=W$112,$C$4:$AZ$108))))} -> 275.637 | X136: {=SUMPRODUCT(IF(LEFT($A$4:$A$108,3)=LEFT($A136,3),IF($B$4:$B$108=$B136,IF($C$3:$AZ$3=X$112,$C$4:$AZ$108))))} -> 398.314 | Y136: {=SUMPRODUCT(IF(LEFT($A$4:$A$108,3)=LEFT($A136,3),IF($B$4:$B$108=$B136,IF($C$3:$AZ$3=Y$112,$C$4:$AZ$108))))} -> 183.115 | ... AR136: {=SUMPRODUCT(IF(LEFT($A$4:$A$108,3)=LEFT($A136,3),IF($B$4:$B$108=$B136,IF($C$3:$AZ$3=AR$112,$C$4:$AZ$108))))} -> 0 | AS136: =SUMIFS($BA$4:$BA$108,$B$4:$B$108,B136,$A$4:$A$108,"DOM*") -> 28733.729
A137: Domestic | B137: ISIC 351 | C137: {=SUMPRODUCT(IF(LEFT($A$4:$A$108,3)=LEFT($A137,3),IF($B$4:$B$108=$B137,IF($C$3:$AZ$3=C$112,$C$4:$AZ$108))))} -> 974.521 | D137: {=SUMPRODUCT(IF(LEFT($A$4:$A$108,3)=LEFT($A137,3),IF($B$4:$B$108=$B137,IF($C$3:$AZ$3=D$112,$C$4:$AZ$108))))} -> 12.124 | E137: {=SUMPRODUCT(IF(LEFT($A$4:$A$108,3)=LEFT($A137,3),IF($B$4:$B$108=$B137,IF($C$3:$AZ$3=E$112,$C$4:$AZ$108))))} -> 6.336 | F137: {=SUMPRODUCT(IF(LEFT($A$4:$A$108,3)=LEFT($A137,3),IF($B$4:$B$108=$B137,IF($C$3:$AZ$3=F$112,$C$4:$AZ$108))))} -> 199.208 | G137: {=SUMPRODUCT(IF(LEFT($A$4:$A$108,3)=LEFT($A137,3),IF($B$4:$B$108=$B137,IF($C$3:$AZ$3=G$112,$C$4:$AZ$108))))} -> 0.198 | H137: {=SUMPRODUCT(IF(LEFT($A$4:$A$108,3)=LEFT($A137,3),IF($B$4:$B$108=$B137,IF($C$3:$AZ$3=H$112,$C$4:$AZ$108))))} -> 3564.317 | I137: {=SUMPRODUCT(IF(LEFT($A$4:$A$108,3)=LEFT($A137,3),IF($B$4:$B$108=$B137,IF($C$3:$AZ$3=I$112,$C$4:$AZ$108))))} -> 1579.221 | J137: {=SUMPRODUCT(IF(LEFT($A$4:$A$108,3)=LEFT($A137,3),IF($B$4:$B$108=$B137,IF($C$3:$AZ$3=J$112,$C$4:$AZ$108))))} -> 199.562 | ... O137: {=SUMPRODUCT(IF(LEFT($A$4:$A$108,3)=LEFT($A137,3),IF($B$4:$B$108=$B137,IF($C$3:$AZ$3=O$112,$C$4:$AZ$108))))} -> 1762.577 | P137: {=SUMPRODUCT(IF(LEFT($A$4:$A$108,3)=LEFT($A137,3),IF($B$4:$B$108=$B137,IF($C$3:$AZ$3=P$112,$C$4:$AZ$108))))*'Cement and Glass Split'!O72} -> 331.94775 | Q137: {=SUMPRODUCT(IF(LEFT($A$4:$A$108,3)=LEFT($A137,3),IF($B$4:$B$108=$B137,IF($C$3:$AZ$3=P$112,$C$4:$AZ$108))))*'Cement and Glass Split'!P72} -> 1635.9042 | R137: {=SUMPRODUCT(IF(LEFT($A$4:$A$108,3)=LEFT($A137,3),IF($B$4:$B$108=$B137,IF($C$3:$AZ$3=R$112,$C$4:$AZ$108))))} -> 4634.572 | S137: {=SUMPRODUCT(IF(LEFT($A$4:$A$108,3)=LEFT($A137,3),IF($B$4:$B$108=$B137,IF($C$3:$AZ$3=S$112,$C$4:$AZ$108))))} -> 1867.817 | T137: {=SUMPRODUCT(IF(LEFT($A$4:$A$108,3)=LEFT($A137,3),IF($B$4:$B$108=$B137,IF($C$3:$AZ$3=T$112,$C$4:$AZ$108))))} -> 1785.344 | U137: {=SUMPRODUCT(IF(LEFT($A$4:$A$108,3)=LEFT($A137,3),IF($B$4:$B$108=$B137,IF($C$3:$AZ$3=U$112,$C$4:$AZ$108))))} -> 2264.68 | V137: {=SUMPRODUCT(IF(LEFT($A$4:$A$108,3)=LEFT($A137,3),IF($B$4:$B$108=$B137,IF($C$3:$AZ$3=V$112,$C$4:$AZ$108))))} -> 1151.637 | W137: {=SUMPRODUCT(IF(LEFT($A$4:$A$108,3)=LEFT($A137,3),IF($B$4:$B$108=$B137,IF($C$3:$AZ$3=W$112,$C$4:$AZ$108))))} -> 1459.048 | X137: {=SUMPRODUCT(IF(LEFT($A$4:$A$108,3)=LEFT($A137,3),IF($B$4:$B$108=$B137,IF($C$3:$AZ$3=X$112,$C$4:$AZ$108))))} -> 2168.138 | Y137: {=SUMPRODUCT(IF(LEFT($A$4:$A$108,3)=LEFT($A137,3),IF($B$4:$B$108=$B137,IF($C$3:$AZ$3=Y$112,$C$4:$AZ$108))))} -> 582.205 | ... AR137: {=SUMPRODUCT(IF(LEFT($A$4:$A$108,3)=LEFT($A137,3),IF($B$4:$B$108=$B137,IF($C$3:$AZ$3=AR$112,$C$4:$AZ$108))))} -> 0 | AS137: =SUMIFS($BA$4:$BA$108,$B$4:$B$108,B137,$A$4:$A$108,"DOM*") -> 106796.62
A138: Domestic | B138: ISIC 352T353 | C138: {=SUMPRODUCT(IF(LEFT($A$4:$A$108,3)=LEFT($A138,3),IF($B$4:$B$108=$B138,IF($C$3:$AZ$3=C$112,$C$4:$AZ$108))))} -> 340.866 | D138: {=SUMPRODUCT(IF(LEFT($A$4:$A$108,3)=LEFT($A138,3),IF($B$4:$B$108=$B138,IF($C$3:$AZ$3=D$112,$C$4:$AZ$108))))} -> 5.996 | E138: {=SUMPRODUCT(IF(LEFT($A$4:$A$108,3)=LEFT($A138,3),IF($B$4:$B$108=$B138,IF($C$3:$AZ$3=E$112,$C$4:$AZ$108))))} -> 2.031 | F138: {=SUMPRODUCT(IF(LEFT($A$4:$A$108,3)=LEFT($A138,3),IF($B$4:$B$108=$B138,IF($C$3:$AZ$3=F$112,$C$4:$AZ$108))))} -> 99.129 | G138: {=SUMPRODUCT(IF(LEFT($A$4:$A$108,3)=LEFT($A138,3),IF($B$4:$B$108=$B138,IF($C$3:$AZ$3=G$112,$C$4:$AZ$108))))} -> 0.223 | H138: {=SUMPRODUCT(IF(LEFT($A$4:$A$108,3)=LEFT($A138,3),IF($B$4:$B$108=$B138,IF($C$3:$AZ$3=H$112,$C$4:$AZ$108))))} -> 1568.664 | I138: {=SUMPRODUCT(IF(LEFT($A$4:$A$108,3)=LEFT($A138,3),IF($B$4:$B$108=$B138,IF($C$3:$AZ$3=I$112,$C$4:$AZ$108))))} -> 400.871 | J138: {=SUMPRODUCT(IF(LEFT($A$4:$A$108,3)=LEFT($A138,3),IF($B$4:$B$108=$B138,IF($C$3:$AZ$3=J$112,$C$4:$AZ$108))))} -> 127.34 | ... O138: {=SUMPRODUCT(IF(LEFT($A$4:$A$108,3)=LEFT($A138,3),IF($B$4:$B$108=$B138,IF($C$3:$AZ$3=O$112,$C$4:$AZ$108))))} -> 461.657 | P138: {=SUMPRODUCT(IF(LEFT($A$4:$A$108,3)=LEFT($A138,3),IF($B$4:$B$108=$B138,IF($C$3:$AZ$3=P$112,$C$4:$AZ$108))))*'Cement and Glass Split'!O73} -> 639.74163 | Q138: {=SUMPRODUCT(IF(LEFT($A$4:$A$108,3)=LEFT($A138,3),IF($B$4:$B$108=$B138,IF($C$3:$AZ$3=P$112,$C$4:$AZ$108))))*'Cement and Glass Split'!P73} -> 0.44437241 | R138: {=SUMPRODUCT(IF(LEFT($A$4:$A$108,3)=LEFT($A138,3),IF($B$4:$B$108=$B138,IF($C$3:$AZ$3=R$112,$C$4:$AZ$108))))} -> 976.195 | S138: {=SUMPRODUCT(IF(LEFT($A$4:$A$108,3)=LEFT($A138,3),IF($B$4:$B$108=$B138,IF($C$3:$AZ$3=S$112,$C$4:$AZ$108))))} -> 417.652 | T138: {=SUMPRODUCT(IF(LEFT($A$4:$A$108,3)=LEFT($A138,3),IF($B$4:$B$108=$B138,IF($C$3:$AZ$3=T$112,$C$4:$AZ$108))))} -> 598.202 | U138: {=SUMPRODUCT(IF(LEFT($A$4:$A$108,3)=LEFT($A138,3),IF($B$4:$B$108=$B138,IF($C$3:$AZ$3=U$112,$C$4:$AZ$108))))} -> 1272.107 | V138: {=SUMPRODUCT(IF(LEFT($A$4:$A$108,3)=LEFT($A138,3),IF($B$4:$B$108=$B138,IF($C$3:$AZ$3=V$112,$C$4:$AZ$108))))} -> 619.35 | W138: {=SUMPRODUCT(IF(LEFT($A$4:$A$108,3)=LEFT($A138,3),IF($B$4:$B$108=$B138,IF($C$3:$AZ$3=W$112,$C$4:$AZ$108))))} -> 795.853 | X138: {=SUMPRODUCT(IF(LEFT($A$4:$A$108,3)=LEFT($A138,3),IF($B$4:$B$108=$B138,IF($C$3:$AZ$3=X$112,$C$4:$AZ$108))))} -> 1105.99 | Y138: {=SUMPRODUCT(IF(LEFT($A$4:$A$108,3)=LEFT($A138,3),IF($B$4:$B$108=$B138,IF($C$3:$AZ$3=Y$112,$C$4:$AZ$108))))} -> 203.519 | ... AR138: {=SUMPRODUCT(IF(LEFT($A$4:$A$108,3)=LEFT($A138,3),IF($B$4:$B$108=$B138,IF($C$3:$AZ$3=AR$112,$C$4:$AZ$108))))} -> 0 | AS138: =SUMIFS($BA$4:$BA$108,$B$4:$B$108,B138,$A$4:$A$108,"DOM*") -> 41931.622
A139: Domestic | B139: ISIC 36T39 | C139: {=SUMPRODUCT(IF(LEFT($A$4:$A$108,3)=LEFT($A139,3),IF($B$4:$B$108=$B139,IF($C$3:$AZ$3=C$112,$C$4:$AZ$108))))} -> 145.48 | D139: {=SUMPRODUCT(IF(LEFT($A$4:$A$108,3)=LEFT($A139,3),IF($B$4:$B$108=$B139,IF($C$3:$AZ$3=D$112,$C$4:$AZ$108))))} -> 0.988 | E139: {=SUMPRODUCT(IF(LEFT($A$4:$A$108,3)=LEFT($A139,3),IF($B$4:$B$108=$B139,IF($C$3:$AZ$3=E$112,$C$4:$AZ$108))))} -> 0.45 | F139: {=SUMPRODUCT(IF(LEFT($A$4:$A$108,3)=LEFT($A139,3),IF($B$4:$B$108=$B139,IF($C$3:$AZ$3=F$112,$C$4:$AZ$108))))} -> 16.908 | G139: {=SUMPRODUCT(IF(LEFT($A$4:$A$108,3)=LEFT($A139,3),IF($B$4:$B$108=$B139,IF($C$3:$AZ$3=G$112,$C$4:$AZ$108))))} -> 0.075 | H139: {=SUMPRODUCT(IF(LEFT($A$4:$A$108,3)=LEFT($A139,3),IF($B$4:$B$108=$B139,IF($C$3:$AZ$3=H$112,$C$4:$AZ$108))))} -> 550.768 | I139: {=SUMPRODUCT(IF(LEFT($A$4:$A$108,3)=LEFT($A139,3),IF($B$4:$B$108=$B139,IF($C$3:$AZ$3=I$112,$C$4:$AZ$108))))} -> 131.024 | J139: {=SUMPRODUCT(IF(LEFT($A$4:$A$108,3)=LEFT($A139,3),IF($B$4:$B$108=$B139,IF($C$3:$AZ$3=J$112,$C$4:$AZ$108))))} -> 35.066 | ... O139: {=SUMPRODUCT(IF(LEFT($A$4:$A$108,3)=LEFT($A139,3),IF($B$4:$B$108=$B139,IF($C$3:$AZ$3=O$112,$C$4:$AZ$108))))} -> 164.851 | P139: {=SUMPRODUCT(IF(LEFT($A$4:$A$108,3)=LEFT($A139,3),IF($B$4:$B$108=$B139,IF($C$3:$AZ$3=P$112,$C$4:$AZ$108))))*'Cement and Glass Split'!O74} -> 195.78147 | Q139: {=SUMPRODUCT(IF(LEFT($A$4:$A$108,3)=LEFT($A139,3),IF($B$4:$B$108=$B139,IF($C$3:$AZ$3=P$112,$C$4:$AZ$108))))*'Cement and Glass Split'!P74} -> 1.4585341 | R139: {=SUMPRODUCT(IF(LEFT($A$4:$A$108,3)=LEFT($A139,3),IF($B$4:$B$108=$B139,IF($C$3:$AZ$3=R$112,$C$4:$AZ$108))))} -> 4369.558 | S139: {=SUMPRODUCT(IF(LEFT($A$4:$A$108,3)=LEFT($A139,3),IF($B$4:$B$108=$B139,IF($C$3:$AZ$3=S$112,$C$4:$AZ$108))))} -> 1950.65 | T139: {=SUMPRODUCT(IF(LEFT($A$4:$A$108,3)=LEFT($A139,3),IF($B$4:$B$108=$B139,IF($C$3:$AZ$3=T$112,$C$4:$AZ$108))))} -> 313.916 | U139: {=SUMPRODUCT(IF(LEFT($A$4:$A$108,3)=LEFT($A139,3),IF($B$4:$B$108=$B139,IF($C$3:$AZ$3=U$112,$C$4:$AZ$108))))} -> 207.545 | V139: {=SUMPRODUCT(IF(LEFT($A$4:$A$108,3)=LEFT($A139,3),IF($B$4:$B$108=$B139,IF($C$3:$AZ$3=V$112,$C$4:$AZ$108))))} -> 138.89 | W139: {=SUMPRODUCT(IF(LEFT($A$4:$A$108,3)=LEFT($A139,3),IF($B$4:$B$108=$B139,IF($C$3:$AZ$3=W$112,$C$4:$AZ$108))))} -> 269.347 | X139: {=SUMPRODUCT(IF(LEFT($A$4:$A$108,3)=LEFT($A139,3),IF($B$4:$B$108=$B139,IF($C$3:$AZ$3=X$112,$C$4:$AZ$108))))} -> 208.875 | Y139: {=SUMPRODUCT(IF(LEFT($A$4:$A$108,3)=LEFT($A139,3),IF($B$4:$B$108=$B139,IF($C$3:$AZ$3=Y$112,$C$4:$AZ$108))))} -> 106.241 | ... AR139: {=SUMPRODUCT(IF(LEFT($A$4:$A$108,3)=LEFT($A139,3),IF($B$4:$B$108=$B139,IF($C$3:$AZ$3=AR$112,$C$4:$AZ$108))))} -> 0 | AS139: =SUMIFS($BA$4:$BA$108,$B$4:$B$108,B139,$A$4:$A$108,"DOM*") -> 25019.687
... A154: Domestic | B154: ISIC 97T98 | C154: {=SUMPRODUCT(IF(LEFT($A$4:$A$108,3)=LEFT($A154,3),IF($B$4:$B$108=$B154,IF($C$3:$AZ$3=C$112,$C$4:$AZ$108))))} -> 0 | D154: {=SUMPRODUCT(IF(LEFT($A$4:$A$108,3)=LEFT($A154,3),IF($B$4:$B$108=$B154,IF($C$3:$AZ$3=D$112,$C$4:$AZ$108))))} -> 0 | E154: {=SUMPRODUCT(IF(LEFT($A$4:$A$108,3)=LEFT($A154,3),IF($B$4:$B$108=$B154,IF($C$3:$AZ$3=E$112,$C$4:$AZ$108))))} -> 0 | F154: {=SUMPRODUCT(IF(LEFT($A$4:$A$108,3)=LEFT($A154,3),IF($B$4:$B$108=$B154,IF($C$3:$AZ$3=F$112,$C$4:$AZ$108))))} -> 0 | G154: {=SUMPRODUCT(IF(LEFT($A$4:$A$108,3)=LEFT($A154,3),IF($B$4:$B$108=$B154,IF($C$3:$AZ$3=G$112,$C$4:$AZ$108))))} -> 0 | H154: {=SUMPRODUCT(IF(LEFT($A$4:$A$108,3)=LEFT($A154,3),IF($B$4:$B$108=$B154,IF($C$3:$AZ$3=H$112,$C$4:$AZ$108))))} -> 0 | I154: {=SUMPRODUCT(IF(LEFT($A$4:$A$108,3)=LEFT($A154,3),IF($B$4:$B$108=$B154,IF($C$3:$AZ$3=I$112,$C$4:$AZ$108))))} -> 0 | J154: {=SUMPRODUCT(IF(LEFT($A$4:$A$108,3)=LEFT($A154,3),IF($B$4:$B$108=$B154,IF($C$3:$AZ$3=J$112,$C$4:$AZ$108))))} -> 0 | ... O154: {=SUMPRODUCT(IF(LEFT($A$4:$A$108,3)=LEFT($A154,3),IF($B$4:$B$108=$B154,IF($C$3:$AZ$3=O$112,$C$4:$AZ$108))))} -> 0 | P154: {=SUMPRODUCT(IF(LEFT($A$4:$A$108,3)=LEFT($A154,3),IF($B$4:$B$108=$B154,IF($C$3:$AZ$3=P$112,$C$4:$AZ$108))))*'Cement and Glass Split'!O89} -> 0 | Q154: {=SUMPRODUCT(IF(LEFT($A$4:$A$108,3)=LEFT($A154,3),IF($B$4:$B$108=$B154,IF($C$3:$AZ$3=P$112,$C$4:$AZ$108))))*'Cement and Glass Split'!P89} -> 0 | R154: {=SUMPRODUCT(IF(LEFT($A$4:$A$108,3)=LEFT($A154,3),IF($B$4:$B$108=$B154,IF($C$3:$AZ$3=R$112,$C$4:$AZ$108))))} -> 0 | S154: {=SUMPRODUCT(IF(LEFT($A$4:$A$108,3)=LEFT($A154,3),IF($B$4:$B$108=$B154,IF($C$3:$AZ$3=S$112,$C$4:$AZ$108))))} -> 0 | T154: {=SUMPRODUCT(IF(LEFT($A$4:$A$108,3)=LEFT($A154,3),IF($B$4:$B$108=$B154,IF($C$3:$AZ$3=T$112,$C$4:$AZ$108))))} -> 0 | U154: {=SUMPRODUCT(IF(LEFT($A$4:$A$108,3)=LEFT($A154,3),IF($B$4:$B$108=$B154,IF($C$3:$AZ$3=U$112,$C$4:$AZ$108))))} -> 0 | V154: {=SUMPRODUCT(IF(LEFT($A$4:$A$108,3)=LEFT($A154,3),IF($B$4:$B$108=$B154,IF($C$3:$AZ$3=V$112,$C$4:$AZ$108))))} -> 0 | W154: {=SUMPRODUCT(IF(LEFT($A$4:$A$108,3)=LEFT($A154,3),IF($B$4:$B$108=$B154,IF($C$3:$AZ$3=W$112,$C$4:$AZ$108))))} -> 0 | X154: {=SUMPRODUCT(IF(LEFT($A$4:$A$108,3)=LEFT($A154,3),IF($B$4:$B$108=$B154,IF($C$3:$AZ$3=X$112,$C$4:$AZ$108))))} -> 0 | Y154: {=SUMPRODUCT(IF(LEFT($A$4:$A$108,3)=LEFT($A154,3),IF($B$4:$B$108=$B154,IF($C$3:$AZ$3=Y$112,$C$4:$AZ$108))))} -> 0 | ... AR154: {=SUMPRODUCT(IF(LEFT($A$4:$A$108,3)=LEFT($A154,3),IF($B$4:$B$108=$B154,IF($C$3:$AZ$3=AR$112,$C$4:$AZ$108))))} -> 0 | AS154: =SUMIFS($BA$4:$BA$108,$B$4:$B$108,B154,$A$4:$A$108,"DOM*") -> 2100.731
A155: Imports | B155: ISIC 01T03 | C155: {=SUMPRODUCT(IF(LEFT($A$4:$A$108,3)=LEFT($A155,3),IF($B$4:$B$108=$B155,IF($C$3:$AZ$3=C$112,$C$4:$AZ$108))))} -> 751.084 | D155: {=SUMPRODUCT(IF(LEFT($A$4:$A$108,3)=LEFT($A155,3),IF($B$4:$B$108=$B155,IF($C$3:$AZ$3=D$112,$C$4:$AZ$108))))} -> 0.029 | E155: {=SUMPRODUCT(IF(LEFT($A$4:$A$108,3)=LEFT($A155,3),IF($B$4:$B$108=$B155,IF($C$3:$AZ$3=E$112,$C$4:$AZ$108))))} -> 0.004 | F155: {=SUMPRODUCT(IF(LEFT($A$4:$A$108,3)=LEFT($A155,3),IF($B$4:$B$108=$B155,IF($C$3:$AZ$3=F$112,$C$4:$AZ$108))))} -> 0.274 | G155: {=SUMPRODUCT(IF(LEFT($A$4:$A$108,3)=LEFT($A155,3),IF($B$4:$B$108=$B155,IF($C$3:$AZ$3=G$112,$C$4:$AZ$108))))} -> 0 | H155: {=SUMPRODUCT(IF(LEFT($A$4:$A$108,3)=LEFT($A155,3),IF($B$4:$B$108=$B155,IF($C$3:$AZ$3=H$112,$C$4:$AZ$108))))} -> 4764.587 | I155: {=SUMPRODUCT(IF(LEFT($A$4:$A$108,3)=LEFT($A155,3),IF($B$4:$B$108=$B155,IF($C$3:$AZ$3=I$112,$C$4:$AZ$108))))} -> 108.184 | J155: {=SUMPRODUCT(IF(LEFT($A$4:$A$108,3)=LEFT($A155,3),IF($B$4:$B$108=$B155,IF($C$3:$AZ$3=J$112,$C$4:$AZ$108))))} -> 122.135 | ... O155: {=SUMPRODUCT(IF(LEFT($A$4:$A$108,3)=LEFT($A155,3),IF($B$4:$B$108=$B155,IF($C$3:$AZ$3=O$112,$C$4:$AZ$108))))} -> 30.694 | P155: {=SUMPRODUCT(IF(LEFT($A$4:$A$108,3)=LEFT($A155,3),IF($B$4:$B$108=$B155,IF($C$3:$AZ$3=P$112,$C$4:$AZ$108))))*'Cement and Glass Split'!O48} -> 0 | Q155: {=SUMPRODUCT(IF(LEFT($A$4:$A$108,3)=LEFT($A155,3),IF($B$4:$B$108=$B155,IF($C$3:$AZ$3=P$112,$C$4:$AZ$108))))*'Cement and Glass Split'!P48} -> 0 | R155: {=SUMPRODUCT(IF(LEFT($A$4:$A$108,3)=LEFT($A155,3),IF($B$4:$B$108=$B155,IF($C$3:$AZ$3=R$112,$C$4:$AZ$108))))} -> 1.725 | S155: {=SUMPRODUCT(IF(LEFT($A$4:$A$108,3)=LEFT($A155,3),IF($B$4:$B$108=$B155,IF($C$3:$AZ$3=S$112,$C$4:$AZ$108))))} -> 0.993 | T155: {=SUMPRODUCT(IF(LEFT($A$4:$A$108,3)=LEFT($A155,3),IF($B$4:$B$108=$B155,IF($C$3:$AZ$3=T$112,$C$4:$AZ$108))))} -> 1.311 | U155: {=SUMPRODUCT(IF(LEFT($A$4:$A$108,3)=LEFT($A155,3),IF($B$4:$B$108=$B155,IF($C$3:$AZ$3=U$112,$C$4:$AZ$108))))} -> 3.158 | V155: {=SUMPRODUCT(IF(LEFT($A$4:$A$108,3)=LEFT($A155,3),IF($B$4:$B$108=$B155,IF($C$3:$AZ$3=V$112,$C$4:$AZ$108))))} -> 1.574 | W155: {=SUMPRODUCT(IF(LEFT($A$4:$A$108,3)=LEFT($A155,3),IF($B$4:$B$108=$B155,IF($C$3:$AZ$3=W$112,$C$4:$AZ$108))))} -> 3.212 | X155: {=SUMPRODUCT(IF(LEFT($A$4:$A$108,3)=LEFT($A155,3),IF($B$4:$B$108=$B155,IF($C$3:$AZ$3=X$112,$C$4:$AZ$108))))} -> 4.302 | Y155: {=SUMPRODUCT(IF(LEFT($A$4:$A$108,3)=LEFT($A155,3),IF($B$4:$B$108=$B155,IF($C$3:$AZ$3=Y$112,$C$4:$AZ$108))))} -> 1.291 | ... AR155: {=SUMPRODUCT(IF(LEFT($A$4:$A$108,3)=LEFT($A155,3),IF($B$4:$B$108=$B155,IF($C$3:$AZ$3=AR$112,$C$4:$AZ$108))))} -> 0 | AS155: 0
A156: Imports | B156: ISIC 05 | C156: {=SUMPRODUCT(IF(LEFT($A$4:$A$108,3)=LEFT($A156,3),IF($B$4:$B$108=$B156,IF($C$3:$AZ$3=C$112,$C$4:$AZ$108))))} -> 10.829 | D156: {=SUMPRODUCT(IF(LEFT($A$4:$A$108,3)=LEFT($A156,3),IF($B$4:$B$108=$B156,IF($C$3:$AZ$3=D$112,$C$4:$AZ$108))))} -> 10.596 | E156: {=SUMPRODUCT(IF(LEFT($A$4:$A$108,3)=LEFT($A156,3),IF($B$4:$B$108=$B156,IF($C$3:$AZ$3=E$112,$C$4:$AZ$108))))} -> 0.156 | F156: {=SUMPRODUCT(IF(LEFT($A$4:$A$108,3)=LEFT($A156,3),IF($B$4:$B$108=$B156,IF($C$3:$AZ$3=F$112,$C$4:$AZ$108))))} -> 14.03 | G156: {=SUMPRODUCT(IF(LEFT($A$4:$A$108,3)=LEFT($A156,3),IF($B$4:$B$108=$B156,IF($C$3:$AZ$3=G$112,$C$4:$AZ$108))))} -> 0.053 | H156: {=SUMPRODUCT(IF(LEFT($A$4:$A$108,3)=LEFT($A156,3),IF($B$4:$B$108=$B156,IF($C$3:$AZ$3=H$112,$C$4:$AZ$108))))} -> 70.018 | I156: {=SUMPRODUCT(IF(LEFT($A$4:$A$108,3)=LEFT($A156,3),IF($B$4:$B$108=$B156,IF($C$3:$AZ$3=I$112,$C$4:$AZ$108))))} -> 29.077 | J156: {=SUMPRODUCT(IF(LEFT($A$4:$A$108,3)=LEFT($A156,3),IF($B$4:$B$108=$B156,IF($C$3:$AZ$3=J$112,$C$4:$AZ$108))))} -> 2.334 | ... O156: {=SUMPRODUCT(IF(LEFT($A$4:$A$108,3)=LEFT($A156,3),IF($B$4:$B$108=$B156,IF($C$3:$AZ$3=O$112,$C$4:$AZ$108))))} -> 26.967 | P156: {=SUMPRODUCT(IF(LEFT($A$4:$A$108,3)=LEFT($A156,3),IF($B$4:$B$108=$B156,IF($C$3:$AZ$3=P$112,$C$4:$AZ$108))))*'Cement and Glass Split'!O49} -> 0 | Q156: {=SUMPRODUCT(IF(LEFT($A$4:$A$108,3)=LEFT($A156,3),IF($B$4:$B$108=$B156,IF($C$3:$AZ$3=P$112,$C$4:$AZ$108))))*'Cement and Glass Split'!P49} -> 0 | R156: {=SUMPRODUCT(IF(LEFT($A$4:$A$108,3)=LEFT($A156,3),IF($B$4:$B$108=$B156,IF($C$3:$AZ$3=R$112,$C$4:$AZ$108))))} -> 3702.548 | S156: {=SUMPRODUCT(IF(LEFT($A$4:$A$108,3)=LEFT($A156,3),IF($B$4:$B$108=$B156,IF($C$3:$AZ$3=S$112,$C$4:$AZ$108))))} -> 461.861 | T156: {=SUMPRODUCT(IF(LEFT($A$4:$A$108,3)=LEFT($A156,3),IF($B$4:$B$108=$B156,IF($C$3:$AZ$3=T$112,$C$4:$AZ$108))))} -> 6.722 | U156: {=SUMPRODUCT(IF(LEFT($A$4:$A$108,3)=LEFT($A156,3),IF($B$4:$B$108=$B156,IF($C$3:$AZ$3=U$112,$C$4:$AZ$108))))} -> 5.705 | V156: {=SUMPRODUCT(IF(LEFT($A$4:$A$108,3)=LEFT($A156,3),IF($B$4:$B$108=$B156,IF($C$3:$AZ$3=V$112,$C$4:$AZ$108))))} -> 13.46 | W156: {=SUMPRODUCT(IF(LEFT($A$4:$A$108,3)=LEFT($A156,3),IF($B$4:$B$108=$B156,IF($C$3:$AZ$3=W$112,$C$4:$AZ$108))))} -> 14.983 | X156: {=SUMPRODUCT(IF(LEFT($A$4:$A$108,3)=LEFT($A156,3),IF($B$4:$B$108=$B156,IF($C$3:$AZ$3=X$112,$C$4:$AZ$108))))} -> 11.935 | Y156: {=SUMPRODUCT(IF(LEFT($A$4:$A$108,3)=LEFT($A156,3),IF($B$4:$B$108=$B156,IF($C$3:$AZ$3=Y$112,$C$4:$AZ$108))))} -> 11.429 | ... AR156: {=SUMPRODUCT(IF(LEFT($A$4:$A$108,3)=LEFT($A156,3),IF($B$4:$B$108=$B156,IF($C$3:$AZ$3=AR$112,$C$4:$AZ$108))))} -> 0 | AS156: 0
A157: Imports | B157: ISIC 06 | C157: {=SUMPRODUCT(IF(LEFT($A$4:$A$108,3)=LEFT($A157,3),IF($B$4:$B$108=$B157,IF($C$3:$AZ$3=C$112,$C$4:$AZ$108))))} -> 35.592 | D157: {=SUMPRODUCT(IF(LEFT($A$4:$A$108,3)=LEFT($A157,3),IF($B$4:$B$108=$B157,IF($C$3:$AZ$3=D$112,$C$4:$AZ$108))))} -> 6.58 | E157: {=SUMPRODUCT(IF(LEFT($A$4:$A$108,3)=LEFT($A157,3),IF($B$4:$B$108=$B157,IF($C$3:$AZ$3=E$112,$C$4:$AZ$108))))} -> 8.85 | F157: {=SUMPRODUCT(IF(LEFT($A$4:$A$108,3)=LEFT($A157,3),IF($B$4:$B$108=$B157,IF($C$3:$AZ$3=F$112,$C$4:$AZ$108))))} -> 80.74 | G157: {=SUMPRODUCT(IF(LEFT($A$4:$A$108,3)=LEFT($A157,3),IF($B$4:$B$108=$B157,IF($C$3:$AZ$3=G$112,$C$4:$AZ$108))))} -> 0.266 | H157: {=SUMPRODUCT(IF(LEFT($A$4:$A$108,3)=LEFT($A157,3),IF($B$4:$B$108=$B157,IF($C$3:$AZ$3=H$112,$C$4:$AZ$108))))} -> 423.22 | I157: {=SUMPRODUCT(IF(LEFT($A$4:$A$108,3)=LEFT($A157,3),IF($B$4:$B$108=$B157,IF($C$3:$AZ$3=I$112,$C$4:$AZ$108))))} -> 83.378 | J157: {=SUMPRODUCT(IF(LEFT($A$4:$A$108,3)=LEFT($A157,3),IF($B$4:$B$108=$B157,IF($C$3:$AZ$3=J$112,$C$4:$AZ$108))))} -> 20.049 | ... O157: {=SUMPRODUCT(IF(LEFT($A$4:$A$108,3)=LEFT($A157,3),IF($B$4:$B$108=$B157,IF($C$3:$AZ$3=O$112,$C$4:$AZ$108))))} -> 243.381 | P157: {=SUMPRODUCT(IF(LEFT($A$4:$A$108,3)=LEFT($A157,3),IF($B$4:$B$108=$B157,IF($C$3:$AZ$3=P$112,$C$4:$AZ$108))))*'Cement and Glass Split'!O50} -> 12.575537 | Q157: {=SUMPRODUCT(IF(LEFT($A$4:$A$108,3)=LEFT($A157,3),IF($B$4:$B$108=$B157,IF($C$3:$AZ$3=P$112,$C$4:$AZ$108))))*'Cement and Glass Split'!P50} -> 1060.1095 | R157: {=SUMPRODUCT(IF(LEFT($A$4:$A$108,3)=LEFT($A157,3),IF($B$4:$B$108=$B157,IF($C$3:$AZ$3=R$112,$C$4:$AZ$108))))} -> 2462.652 | S157: {=SUMPRODUCT(IF(LEFT($A$4:$A$108,3)=LEFT($A157,3),IF($B$4:$B$108=$B157,IF($C$3:$AZ$3=S$112,$C$4:$AZ$108))))} -> 1278.36 | T157: {=SUMPRODUCT(IF(LEFT($A$4:$A$108,3)=LEFT($A157,3),IF($B$4:$B$108=$B157,IF($C$3:$AZ$3=T$112,$C$4:$AZ$108))))} -> 336.76 | U157: {=SUMPRODUCT(IF(LEFT($A$4:$A$108,3)=LEFT($A157,3),IF($B$4:$B$108=$B157,IF($C$3:$AZ$3=U$112,$C$4:$AZ$108))))} -> 72.838 | V157: {=SUMPRODUCT(IF(LEFT($A$4:$A$108,3)=LEFT($A157,3),IF($B$4:$B$108=$B157,IF($C$3:$AZ$3=V$112,$C$4:$AZ$108))))} -> 76.74 | W157: {=SUMPRODUCT(IF(LEFT($A$4:$A$108,3)=LEFT($A157,3),IF($B$4:$B$108=$B157,IF($C$3:$AZ$3=W$112,$C$4:$AZ$108))))} -> 146.474 | X157: {=SUMPRODUCT(IF(LEFT($A$4:$A$108,3)=LEFT($A157,3),IF($B$4:$B$108=$B157,IF($C$3:$AZ$3=X$112,$C$4:$AZ$108))))} -> 188.705 | Y157: {=SUMPRODUCT(IF(LEFT($A$4:$A$108,3)=LEFT($A157,3),IF($B$4:$B$108=$B157,IF($C$3:$AZ$3=Y$112,$C$4:$AZ$108))))} -> 68.953 | ... AR157: {=SUMPRODUCT(IF(LEFT($A$4:$A$108,3)=LEFT($A157,3),IF($B$4:$B$108=$B157,IF($C$3:$AZ$3=AR$112,$C$4:$AZ$108))))} -> 0 | AS157: 0
A158: Imports | B158: ISIC 07T08 | C158: {=SUMPRODUCT(IF(LEFT($A$4:$A$108,3)=LEFT($A158,3),IF($B$4:$B$108=$B158,IF($C$3:$AZ$3=C$112,$C$4:$AZ$108))))} -> 10.542 | D158: {=SUMPRODUCT(IF(LEFT($A$4:$A$108,3)=LEFT($A158,3),IF($B$4:$B$108=$B158,IF($C$3:$AZ$3=D$112,$C$4:$AZ$108))))} -> 0.654 | E158: {=SUMPRODUCT(IF(LEFT($A$4:$A$108,3)=LEFT($A158,3),IF($B$4:$B$108=$B158,IF($C$3:$AZ$3=E$112,$C$4:$AZ$108))))} -> 0.109 | F158: {=SUMPRODUCT(IF(LEFT($A$4:$A$108,3)=LEFT($A158,3),IF($B$4:$B$108=$B158,IF($C$3:$AZ$3=F$112,$C$4:$AZ$108))))} -> 47.952 | G158: {=SUMPRODUCT(IF(LEFT($A$4:$A$108,3)=LEFT($A158,3),IF($B$4:$B$108=$B158,IF($C$3:$AZ$3=G$112,$C$4:$AZ$108))))} -> 0.054 | H158: {=SUMPRODUCT(IF(LEFT($A$4:$A$108,3)=LEFT($A158,3),IF($B$4:$B$108=$B158,IF($C$3:$AZ$3=H$112,$C$4:$AZ$108))))} -> 28.708 | I158: {=SUMPRODUCT(IF(LEFT($A$4:$A$108,3)=LEFT($A158,3),IF($B$4:$B$108=$B158,IF($C$3:$AZ$3=I$112,$C$4:$AZ$108))))} -> 10.36 | J158: {=SUMPRODUCT(IF(LEFT($A$4:$A$108,3)=LEFT($A158,3),IF($B$4:$B$108=$B158,IF($C$3:$AZ$3=J$112,$C$4:$AZ$108))))} -> 0.999 | ... O158: {=SUMPRODUCT(IF(LEFT($A$4:$A$108,3)=LEFT($A158,3),IF($B$4:$B$108=$B158,IF($C$3:$AZ$3=O$112,$C$4:$AZ$108))))} -> 31.542 | P158: {=SUMPRODUCT(IF(LEFT($A$4:$A$108,3)=LEFT($A158,3),IF($B$4:$B$108=$B158,IF($C$3:$AZ$3=P$112,$C$4:$AZ$108))))*'Cement and Glass Split'!O51} -> 6.2028952 | Q158: {=SUMPRODUCT(IF(LEFT($A$4:$A$108,3)=LEFT($A158,3),IF($B$4:$B$108=$B158,IF($C$3:$AZ$3=P$112,$C$4:$AZ$108))))*'Cement and Glass Split'!P51} -> 512.6631 | R158: {=SUMPRODUCT(IF(LEFT($A$4:$A$108,3)=LEFT($A158,3),IF($B$4:$B$108=$B158,IF($C$3:$AZ$3=R$112,$C$4:$AZ$108))))} -> 5641.106 | S158: {=SUMPRODUCT(IF(LEFT($A$4:$A$108,3)=LEFT($A158,3),IF($B$4:$B$108=$B158,IF($C$3:$AZ$3=S$112,$C$4:$AZ$108))))} -> 5971.675 | T158: {=SUMPRODUCT(IF(LEFT($A$4:$A$108,3)=LEFT($A158,3),IF($B$4:$B$108=$B158,IF($C$3:$AZ$3=T$112,$C$4:$AZ$108))))} -> 185.527 | U158: {=SUMPRODUCT(IF(LEFT($A$4:$A$108,3)=LEFT($A158,3),IF($B$4:$B$108=$B158,IF($C$3:$AZ$3=U$112,$C$4:$AZ$108))))} -> 46.321 | V158: {=SUMPRODUCT(IF(LEFT($A$4:$A$108,3)=LEFT($A158,3),IF($B$4:$B$108=$B158,IF($C$3:$AZ$3=V$112,$C$4:$AZ$108))))} -> 70.395 | W158: {=SUMPRODUCT(IF(LEFT($A$4:$A$108,3)=LEFT($A158,3),IF($B$4:$B$108=$B158,IF($C$3:$AZ$3=W$112,$C$4:$AZ$108))))} -> 56.395 | X158: {=SUMPRODUCT(IF(LEFT($A$4:$A$108,3)=LEFT($A158,3),IF($B$4:$B$108=$B158,IF($C$3:$AZ$3=X$112,$C$4:$AZ$108))))} -> 46.515 | Y158: {=SUMPRODUCT(IF(LEFT($A$4:$A$108,3)=LEFT($A158,3),IF($B$4:$B$108=$B158,IF($C$3:$AZ$3=Y$112,$C$4:$AZ$108))))} -> 9.461 | ... AR158: {=SUMPRODUCT(IF(LEFT($A$4:$A$108,3)=LEFT($A158,3),IF($B$4:$B$108=$B158,IF($C$3:$AZ$3=AR$112,$C$4:$AZ$108))))} -> 0 | AS158: 0
A159: Imports | B159: ISIC 09 | C159: {=SUMPRODUCT(IF(LEFT($A$4:$A$108,3)=LEFT($A159,3),IF($B$4:$B$108=$B159,IF($C$3:$AZ$3=C$112,$C$4:$AZ$108))))} -> 0.44 | D159: {=SUMPRODUCT(IF(LEFT($A$4:$A$108,3)=LEFT($A159,3),IF($B$4:$B$108=$B159,IF($C$3:$AZ$3=D$112,$C$4:$AZ$108))))} -> 0.014 | E159: {=SUMPRODUCT(IF(LEFT($A$4:$A$108,3)=LEFT($A159,3),IF($B$4:$B$108=$B159,IF($C$3:$AZ$3=E$112,$C$4:$AZ$108))))} -> 0.015 | F159: {=SUMPRODUCT(IF(LEFT($A$4:$A$108,3)=LEFT($A159,3),IF($B$4:$B$108=$B159,IF($C$3:$AZ$3=F$112,$C$4:$AZ$108))))} -> 0.216 | G159: {=SUMPRODUCT(IF(LEFT($A$4:$A$108,3)=LEFT($A159,3),IF($B$4:$B$108=$B159,IF($C$3:$AZ$3=G$112,$C$4:$AZ$108))))} -> 0.001 | H159: {=SUMPRODUCT(IF(LEFT($A$4:$A$108,3)=LEFT($A159,3),IF($B$4:$B$108=$B159,IF($C$3:$AZ$3=H$112,$C$4:$AZ$108))))} -> 1.502 | I159: {=SUMPRODUCT(IF(LEFT($A$4:$A$108,3)=LEFT($A159,3),IF($B$4:$B$108=$B159,IF($C$3:$AZ$3=I$112,$C$4:$AZ$108))))} -> 0.454 | J159: {=SUMPRODUCT(IF(LEFT($A$4:$A$108,3)=LEFT($A159,3),IF($B$4:$B$108=$B159,IF($C$3:$AZ$3=J$112,$C$4:$AZ$108))))} -> 0.093 | ... O159: {=SUMPRODUCT(IF(LEFT($A$4:$A$108,3)=LEFT($A159,3),IF($B$4:$B$108=$B159,IF($C$3:$AZ$3=O$112,$C$4:$AZ$108))))} -> 0.845 | P159: {=SUMPRODUCT(IF(LEFT($A$4:$A$108,3)=LEFT($A159,3),IF($B$4:$B$108=$B159,IF($C$3:$AZ$3=P$112,$C$4:$AZ$108))))*'Cement and Glass Split'!O52} -> 0 | Q159: {=SUMPRODUCT(IF(LEFT($A$4:$A$108,3)=LEFT($A159,3),IF($B$4:$B$108=$B159,IF($C$3:$AZ$3=P$112,$C$4:$AZ$108))))*'Cement and Glass Split'!P52} -> 0 | R159: {=SUMPRODUCT(IF(LEFT($A$4:$A$108,3)=LEFT($A159,3),IF($B$4:$B$108=$B159,IF($C$3:$AZ$3=R$112,$C$4:$AZ$108))))} -> 5.58 | S159: {=SUMPRODUCT(IF(LEFT($A$4:$A$108,3)=LEFT($A159,3),IF($B$4:$B$108=$B159,IF($C$3:$AZ$3=S$112,$C$4:$AZ$108))))} -> 3.378 | T159: {=SUMPRODUCT(IF(LEFT($A$4:$A$108,3)=LEFT($A159,3),IF($B$4:$B$108=$B159,IF($C$3:$AZ$3=T$112,$C$4:$AZ$108))))} -> 1.018 | U159: {=SUMPRODUCT(IF(LEFT($A$4:$A$108,3)=LEFT($A159,3),IF($B$4:$B$108=$B159,IF($C$3:$AZ$3=U$112,$C$4:$AZ$108))))} -> 1.04 | V159: {=SUMPRODUCT(IF(LEFT($A$4:$A$108,3)=LEFT($A159,3),IF($B$4:$B$108=$B159,IF($C$3:$AZ$3=V$112,$C$4:$AZ$108))))} -> 0.58 | W159: {=SUMPRODUCT(IF(LEFT($A$4:$A$108,3)=LEFT($A159,3),IF($B$4:$B$108=$B159,IF($C$3:$AZ$3=W$112,$C$4:$AZ$108))))} -> 0.951 | X159: {=SUMPRODUCT(IF(LEFT($A$4:$A$108,3)=LEFT($A159,3),IF($B$4:$B$108=$B159,IF($C$3:$AZ$3=X$112,$C$4:$AZ$108))))} -> 1.082 | Y159: {=SUMPRODUCT(IF(LEFT($A$4:$A$108,3)=LEFT($A159,3),IF($B$4:$B$108=$B159,IF($C$3:$AZ$3=Y$112,$C$4:$AZ$108))))} -> 0.342 | ... AR159: {=SUMPRODUCT(IF(LEFT($A$4:$A$108,3)=LEFT($A159,3),IF($B$4:$B$108=$B159,IF($C$3:$AZ$3=AR$112,$C$4:$AZ$108))))} -> 0 | AS159: 0
A160: Imports | B160: ISIC 10T12 | C160: {=SUMPRODUCT(IF(LEFT($A$4:$A$108,3)=LEFT($A160,3),IF($B$4:$B$108=$B160,IF($C$3:$AZ$3=C$112,$C$4:$AZ$108))))} -> 818.949 | D160: {=SUMPRODUCT(IF(LEFT($A$4:$A$108,3)=LEFT($A160,3),IF($B$4:$B$108=$B160,IF($C$3:$AZ$3=D$112,$C$4:$AZ$108))))} -> 0.051 | E160: {=SUMPRODUCT(IF(LEFT($A$4:$A$108,3)=LEFT($A160,3),IF($B$4:$B$108=$B160,IF($C$3:$AZ$3=E$112,$C$4:$AZ$108))))} -> 0.018 | F160: {=SUMPRODUCT(IF(LEFT($A$4:$A$108,3)=LEFT($A160,3),IF($B$4:$B$108=$B160,IF($C$3:$AZ$3=F$112,$C$4:$AZ$108))))} -> 1.613 | G160: {=SUMPRODUCT(IF(LEFT($A$4:$A$108,3)=LEFT($A160,3),IF($B$4:$B$108=$B160,IF($C$3:$AZ$3=G$112,$C$4:$AZ$108))))} -> 0.003 | H160: {=SUMPRODUCT(IF(LEFT($A$4:$A$108,3)=LEFT($A160,3),IF($B$4:$B$108=$B160,IF($C$3:$AZ$3=H$112,$C$4:$AZ$108))))} -> 4477.792 | I160: {=SUMPRODUCT(IF(LEFT($A$4:$A$108,3)=LEFT($A160,3),IF($B$4:$B$108=$B160,IF($C$3:$AZ$3=I$112,$C$4:$AZ$108))))} -> 45.654 | J160: {=SUMPRODUCT(IF(LEFT($A$4:$A$108,3)=LEFT($A160,3),IF($B$4:$B$108=$B160,IF($C$3:$AZ$3=J$112,$C$4:$AZ$108))))} -> 2.197 | ... O160: {=SUMPRODUCT(IF(LEFT($A$4:$A$108,3)=LEFT($A160,3),IF($B$4:$B$108=$B160,IF($C$3:$AZ$3=O$112,$C$4:$AZ$108))))} -> 35.451 | P160: {=SUMPRODUCT(IF(LEFT($A$4:$A$108,3)=LEFT($A160,3),IF($B$4:$B$108=$B160,IF($C$3:$AZ$3=P$112,$C$4:$AZ$108))))*'Cement and Glass Split'!O53} -> 0 | Q160: {=SUMPRODUCT(IF(LEFT($A$4:$A$108,3)=LEFT($A160,3),IF($B$4:$B$108=$B160,IF($C$3:$AZ$3=P$112,$C$4:$AZ$108))))*'Cement and Glass Split'!P53} -> 15.39 | R160: {=SUMPRODUCT(IF(LEFT($A$4:$A$108,3)=LEFT($A160,3),IF($B$4:$B$108=$B160,IF($C$3:$AZ$3=R$112,$C$4:$AZ$108))))} -> 15.133 | S160: {=SUMPRODUCT(IF(LEFT($A$4:$A$108,3)=LEFT($A160,3),IF($B$4:$B$108=$B160,IF($C$3:$AZ$3=S$112,$C$4:$AZ$108))))} -> 9.332 | T160: {=SUMPRODUCT(IF(LEFT($A$4:$A$108,3)=LEFT($A160,3),IF($B$4:$B$108=$B160,IF($C$3:$AZ$3=T$112,$C$4:$AZ$108))))} -> 9.351 | U160: {=SUMPRODUCT(IF(LEFT($A$4:$A$108,3)=LEFT($A160,3),IF($B$4:$B$108=$B160,IF($C$3:$AZ$3=U$112,$C$4:$AZ$108))))} -> 22.841 | V160: {=SUMPRODUCT(IF(LEFT($A$4:$A$108,3)=LEFT($A160,3),IF($B$4:$B$108=$B160,IF($C$3:$AZ$3=V$112,$C$4:$AZ$108))))} -> 11.258 | W160: {=SUMPRODUCT(IF(LEFT($A$4:$A$108,3)=LEFT($A160,3),IF($B$4:$B$108=$B160,IF($C$3:$AZ$3=W$112,$C$4:$AZ$108))))} -> 15.562 | X160: {=SUMPRODUCT(IF(LEFT($A$4:$A$108,3)=LEFT($A160,3),IF($B$4:$B$108=$B160,IF($C$3:$AZ$3=X$112,$C$4:$AZ$108))))} -> 14.077 | Y160: {=SUMPRODUCT(IF(LEFT($A$4:$A$108,3)=LEFT($A160,3),IF($B$4:$B$108=$B160,IF($C$3:$AZ$3=Y$112,$C$4:$AZ$108))))} -> 4.958 | ... AR160: {=SUMPRODUCT(IF(LEFT($A$4:$A$108,3)=LEFT($A160,3),IF($B$4:$B$108=$B160,IF($C$3:$AZ$3=AR$112,$C$4:$AZ$108))))} -> 0 | AS160: 0
