Workbook
Name a: [1]ISICrev3.1!$E:$F
Name Calculated_Relationship_HS12___HS07: '[2]Correlation HS2012-HS2007'!#REF!
Name CAP_CT: #REF!
Name CAP_CT: #REF!
Name CAP_CT: #REF!
Name CAP_CT: #REF!
Name CAP_GFCF: #REF!
Name CAP_GFCF: #REF!
Name CAP_GFCF: #REF!
Name CAP_GFCF: #REF!
Name CAP_IT: #REF!
Name CAP_IT: #REF!
Name CAP_IT: #REF!
Name CAP_IT: #REF!
Name CAP_OCon: #REF!
Name CAP_OCon: #REF!
Name CAP_OCon: #REF!
Name CAP_OCon: #REF!
Name CAP_OMach: #REF!
Name CAP_OMach: #REF!
Name CAP_OMach: #REF!
Name CAP_OMach: #REF!
Name CAP_Other: #REF!
Name CAP_Other: #REF!
Name CAP_Other: #REF!
Name CAP_Other: #REF!
Name CAP_QI: #REF!
Name CAP_QI: #REF!
Name CAP_QI: #REF!
Name CAP_QI: #REF!
Name CAP_RStruc: #REF!
Name CAP_RStruc: #REF!
Name CAP_RStruc: #REF!
Name CAP_RStruc: #REF!
Name CAP_Soft: #REF!
Name CAP_Soft: #REF!
Name CAP_Soft: #REF!
Name CAP_Soft: #REF!
Name CAP_TraEq: #REF!
Name CAP_TraEq: #REF!
Name CAP_TraEq: #REF!
Name CAP_TraEq: #REF!
Name CAPIT: #REF!
Name CAPIT: #REF!
Name CAPIT: #REF!
Name CAPIT: #REF!
Name CAPIT_QI: #REF!
Name CAPIT_QI: #REF!
Name CAPIT_QI: #REF!
Name CAPIT_QI: #REF!
Name capit_qph: #REF!
Name capit_qph: #REF!
Name capit_qph: #REF!
Name capit_qph: #REF!
Name CAPNIT: #REF!
Name CAPNIT: #REF!
Name CAPNIT: #REF!
Name CAPNIT: #REF!
Name CAPNIT_QI: #REF!
Name CAPNIT_QI: #REF!

Sheet About
A1: FoGPbEaIC Fraction of Goods Purchased by Entity and ISIC Code
A3: Source: | B3: All Industries
B4: see variable io-model/DLIM
B5: see variable io-model/BOibC
B6: see variable io-model/GAaHEbIC-government
B7: see variable io-model/GaHEbIC-household
B9: Split for Chemicals/Pharmaceuticals
B10: World Input-Output Database
B11: 2016
B12: National IO Tables
B13: http://www.wiod.org/database/niots16
B14: Korea NIOT, 2014
B16: Split for All Other ISIC Codes
B17: Exiobase
B18: 2019
B19: Exiobase 3rx, 2016
B20: https://zenodo.org/record/2654460#.YEFjHmhKg2w
B21: KOR, exports
A23: Notes
A25: Data Source
A26: The OECD input-output tables use ISIC codes that do not map well onto EPS industry categories.
A27: The following industry categories are particularly problematic for mapping onto OECD:
B28: chemicals (OECD doesn't split out pharmaceuticals)
B29: natural gas and petroleum systems
B30: coal mining
B31: waste management (water + waste)
A33: Also, even the industries that are mappable to OECD (such as iron and steel) can be improved by
A34: using a more disaggregated data source that (for example) breaks out iron and steel from other metals.
A36: Accordingly, we use the variables DLIM and BOIbC to break out the OECD data in several places. See the file io-model/DLIM
A37: for more information on the steps to transform a DLIM table into a standard input-output matrix. Ideally, we would use
A38: a Total Leontief Inverse matrix rather than a Domestic Leontief Inverse matrix for this step, but our source data does not provide
A39: that information.
A41: Procedure
A42: We calculate the share of each industry's output purchased by each ISIC code, disregarding
A43: the cash flow entities that are not assigned ISIC codes, such that the shares assigned to all
A44: ISIC codes sum to 100%. Note that this requires dividing by the total output from each industry
A45: to all ISIC codes in the denominator ourselves, since using the "Total Intermediate" column (col OS)
A46: from the BEA table introduces too much rounding error, and this is visible in EPS outputs.
... A66: the five energy supplier entities, does not introduce error.

Sheet DLIM
B1: ISIC 01T03 | C1: ISIC 05 | D1: ISIC 06 | E1: ISIC 07T08 | F1: ISIC 09 | G1: ISIC 10T12 | H1: ISIC 13T15 | I1: ISIC 16 | J1: ISIC 17T18 | K1: ISIC 19 | L1: ISIC 20 | M1: ISIC 21 | N1: ISIC 22 | O1: ISIC 231 | P1: ISIC 239 | Q1: ISIC 241 | R1: ISIC 242 | S1: ISIC 25 | T1: ISIC 26 | U1: ISIC 27 | V1: ISIC 28 | W1: ISIC 29 | X1: ISIC 30 | Y1: ISIC 31T33 | Z1: ISIC 351 | AA1: ISIC 352T353 | AB1: ISIC 36T39 | AC1: ISIC 41T43 | AD1: ISIC 45T47 | AE1: ISIC 49T53 | AF1: ISIC 55T56 | AG1: ISIC 58T60 | AH1: ISIC 61 | AI1: ISIC 62T63 | AJ1: ISIC 64T66 | AK1: ISIC 68 | AL1: ISIC 69T82 | AM1: ISIC 84 | AN1: ISIC 85 | AO1: ISIC 86T88 | AP1: ISIC 90T96 | AQ1: ISIC 97T98
A2: ISIC 01T03 | B2: 1.127 | C2: 0.00241574 | D2: 0.00142797 | E2: 0.005 | F2: 0.001 | G2: 0.345 | H2: 0.038 | I2: 0.146 | J2: 0.033 | K2: 0.004 | L2: 0.003499923 | M2: 0.003871442 | N2: 0.02 | O2: 0.000502634 | P2: 0.000302284 | Q2: 0.000458309 | R2: 0.00054797 | S2: 0.005 | T2: 0.003 | U2: 0.005 | V2: 0.005 | W2: 0.005 | X2: 0.007 | Y2: 0.02 | Z2: 0.00042866 | AA2: 0.000306575 | AB2: 0.000522561 | AC2: 0.009 | AD2: 0.017 | AE2: 0.006 | AF2: 0.127 | AG2: 0.01 | AH2: 0.004 | AI2: 0.005 | AJ2: 0.004 | AK2: 0.002 | AL2: 0.008 | AM2: 0.01 | AN2: 0.011 | AO2: 0.018 | AP2: 0.018 | AQ2: 0
A3: ISIC 05 | B3: 4.3415e-05 | C3: 1.0002745 | D3: 3.97617e-06 | E3: 1.43397e-05 | F3: 0 | G3: 6.01769e-05 | H3: 0.000133288 | I3: 0.000129813 | J3: 9.22289e-05 | K3: 0.000106888 | L3: 0.16191327 | M3: 0.017155755 | N3: 0.000166663 | O3: 9.25425e-05 | P3: 9.32291e-05 | Q3: 0.00959684 | R3: 0.000206103 | S3: 0.002472759 | T3: 0.000198713 | U3: 0.000524858 | V3: 0.001531313 | W3: 0.000560163 | X3: 0.000297087 | Y3: 0.000520489 | Z3: 0.001879803 | AA3: 3.79126e-06 | AB3: 0.000323272 | AC3: 0.000999946 | AD3: 8.65732e-12 | AE3: 1.75512e-05 | AF3: 3.3551e-05 | AG3: 0 | AH3: 1.10026e-11 | AI3: 5.74779e-06 | AJ3: 1.28005e-05 | AK3: 3.07835e-05 | AL3: 4.16975e-05 | AM3: 0.000105763 | AN3: 6.50104e-05 | AO3: 6.59603e-05 | AP3: 8.93854e-05 | AQ3: 0.000440919
A4: ISIC 06 | B4: 6.13748e-05 | C4: 3.73795e-05 | D4: 1 | E4: 5.36738e-06 | F4: 0 | G4: 3.35631e-05 | H4: 0.004412682 | I4: 0.004640572 | J4: 9.35094e-05 | K4: 1.10027e-05 | L4: 0.16191327 | M4: 0.017155755 | N4: 0.000178889 | O4: 5.39668e-05 | P4: 4.41729e-05 | Q4: 1.99555e-05 | R4: 2.94454e-05 | S4: 4.77392e-05 | T4: 3.64017e-05 | U4: 5.24229e-05 | V4: 5.22836e-05 | W4: 0.0002253 | X4: 4.55624e-05 | Y4: 0.004617212 | Z4: 2.68008e-05 | AA4: 1.88241e-06 | AB4: 3.40844e-05 | AC4: 0.000118676 | AD4: 4.23794e-11 | AE4: 8.00837e-06 | AF4: 4.03997e-05 | AG4: 0 | AH4: 4.75408e-11 | AI4: 9.29453e-06 | AJ4: 1.34371e-05 | AK4: 1.02182e-05 | AL4: 3.02865e-05 | AM4: 4.481e-05 | AN4: 8.17409e-05 | AO4: 4.78492e-05 | AP4: 0.000154157 | AQ4: 0.000143567
A5: ISIC 07T08 | B5: 0 | C5: 0.000173382 | D5: 1.37706e-05 | E5: 1.0018 | F5: 0.0065 | G5: 0.0009 | H5: 0.0009 | I5: 0.0009 | J5: 0.0014 | K5: 0.0006 | L5: 0.0047 | M5: 0.0014 | N5: 0.001 | O5: 0.004885463 | P5: 0.12496971 | Q5: 0.002935071 | R5: 0.001166741 | S5: 0.0021 | T5: 0.0011 | U5: 0.0019 | V5: 0.0014 | W5: 0.0016 | X5: 0.0018 | Y5: 0.0013 | Z5: 0.000107626 | AA5: 7.12252e-06 | AB5: 0.0009 | AC5: 0.006 | AD5: 0.0003 | AE5: 0 | AF5: 0.0006 | AG5: 0.0003 | AH5: 0.0003 | AI5: 0.0002 | AJ5: 0.0001 | AK5: 0.0004 | AL5: 0 | AM5: 0.0003 | AN5: 0.0002 | AO5: 0.0004 | AP5: 0 | AQ5: 0
A6: ISIC 09 | B6: 0 | C6: 0 | D6: 0 | E6: 0.0001 | F6: 1.0002 | G6: 0 | H6: 0 | I6: 0 | J6: 0 | K6: 0.0001 | L6: 0 | M6: 0 | N6: 0 | O6: 0 | P6: 0 | Q6: 0 | R6: 0 | S6: 0 | T6: 0 | U6: 0 | V6: 0 | W6: 0 | X6: 0 | Y6: 0 | Z6: 0 | AA6: 0 | AB6: 0 | AC6: 0 | AD6: 0 | AE6: 0 | AF6: 0 | AG6: 0 | AH6: 0 | AI6: 0 | AJ6: 0 | AK6: 0 | AL6: 0 | AM6: 0 | AN6: 0 | AO6: 0 | AP6: 0 | AQ6: 0
A7: ISIC 10T12 | B7: 0.147 | C7: 0.012929594 | D7: 0.007709781 | E7: 0.0163 | F7: 0.0081 | G7: 1.2033 | H7: 0.0325 | I7: 0.0293 | J7: 0.015 | K7: 0.007 | L7: 0.0173 | M7: 0.0241 | N7: 0.017 | O7: 0.002436091 | P7: 0.001569437 | Q7: 0.002274304 | R7: 0.002797122 | S7: 0.0128 | T7: 0.0073 | U7: 0.0113 | V7: 0.012 | W7: 0.0113 | X7: 0.0145 | Y7: 0.0145 | Z7: 0.002151024 | AA7: 0.001639455 | AB7: 0.0104 | AC7: 0.0095 | AD7: 0.0203 | AE7: 0.01 | AF7: 0.2791 | AG7: 0.0137 | AH7: 0.0123 | AI7: 0.0074 | AJ7: 0.012 | AK7: 0.0043 | AL7: 0.014 | AM7: 0.0126 | AN7: 0.0342 | AO7: 0.0327 | AP7: 0.039 | AQ7: 0
A8: ISIC 13T15 | B8: 0.013 | C8: 0.002877961 | D8: 0.000284925 | E8: 0.0132 | F8: 0.0086 | G8: 0.0153 | H8: 1.2742 | I8: 0.0201 | J8: 0.025 | K8: 0.0052 | L8: 0.0096 | M8: 0.0132 | N8: 0.044 | O8: 0.003775753 | P8: 0.004824909 | Q8: 0.002355152 | R8: 0.001604445 | S8: 0.017 | T8: 0.0095 | U8: 0.015 | V8: 0.0149 | W8: 0.0194 | X8: 0.0261 | Y8: 0.0571 | Z8: 0.001007791 | AA8: 0.000157205 | AB8: 0.0113 | AC8: 0.0098 | AD8: 0.012 | AE8: 0.014 | AF8: 0.0165 | AG8: 0.0078 | AH8: 0.0074 | AI8: 0.0032 | AJ8: 0.0061 | AK8: 0.0028 | AL8: 0.015 | AM8: 0.0098 | AN8: 0.0066 | AO8: 0.0139 | AP8: 0.038 | AQ8: 0
A9: ISIC 16 | B9: 0.002 | C9: 0.005178574 | D9: 0.000139887 | E9: 0.0023 | F9: 0.0018 | G9: 0.0029 | H9: 0.0036 | I9: 1.1648 | J9: 0.0031 | K9: 0.0009 | L9: 0.0015 | M9: 0.0015 | N9: 0.003 | O9: 0.009060494 | P9: 0.004884077 | Q9: 0.001417349 | R9: 0.00497255 | S9: 0.0037 | T9: 0.001 | U9: 0.0022 | V9: 0.0026 | W9: 0.0021 | X9: 0.0028 | Y9: 0.035 | Z9: 0.000659373 | AA9: 5.31305e-05 | AB9: 0.0013 | AC9: 0.0159 | AD9: 0.0018 | AE9: 0.001 | AF9: 0.0033 | AG9: 0.0008 | AH9: 0.0009 | AI9: 0.0005 | AJ9: 0.0005 | AK9: 0.0011 | AL9: 0.001 | AM9: 0.0006 | AN9: 0.0014 | AO9: 0.0013 | AP9: 0.003 | AQ9: 0
A10: ISIC 17T18 | B10: 0.008 | C10: 0.002740184 | D10: 0.000588579 | E10: 0.0092 | F10: 0.0079 | G10: 0.0367 | H10: 0.0255 | I10: 0.0287 | J10: 1.3466 | K10: 0.0069 | L10: 0.0153 | M10: 0.0276 | N10: 0.022 | O10: 0.014354751 | P10: 0.010288875 | Q10: 0.002597555 | R10: 0.004102689 | S10: 0.0143 | T10: 0.0074 | U10: 0.0164 | V10: 0.0105 | W10: 0.0108 | X10: 0.0111 | Y10: 0.0213 | Z10: 0.001694188 | AA10: 0.000408739 | AB10: 0.0076 | AC10: 0.0108 | AD10: 0.0195 | AE10: 0.008 | AF10: 0.0199 | AG10: 0.0409 | AH10: 0.0126 | AI10: 0.0111 | AJ10: 0.0165 | AK10: 0.0042 | AL10: 0.018 | AM10: 0.0095 | AN10: 0.0118 | AO10: 0.0123 | AP10: 0.023 | AQ10: 0
A11: ISIC 19 | B11: 0.033 | C11: 0.000239229 | D11: 5.92721e-05 | E11: 0.0527 | F11: 0.0438 | G11: 0.0254 | H11: 0.0317 | I11: 0.0323 | J11: 0.0306 | K11: 1.123 | L11: 0.1507 | M11: 0.0317 | N11: 0.07 | O11: 0.000431945 | P11: 0.001451235 | Q11: 0.00078648 | R11: 0.0004475 | S11: 0.0253 | T11: 0.0168 | U11: 0.0256 | V11: 0.0191 | W11: 0.0238 | X11: 0.0254 | Y11: 0.0238 | Z11: 0.001089533 | AA11: 3.93453e-05 | AB11: 0.0269 | AC11: 0.0237 | AD11: 0.0265 | AE11: 0.096 | AF11: 0.0257 | AG11: 0.0139 | AH11: 0.0138 | AI11: 0.0081 | AJ11: 0.0072 | AK11: 0.0061 | AL11: 0.015 | AM11: 0.0155 | AN11: 0.0177 | AO11: 0.0223 | AP11: 0.023 | AQ11: 0
A12: ISIC 20 | B12: 0.040642517 | C12: 0.023920855 | D12: 0.023920855 | E12: 0.0409 | F12: 0.0325 | G12: 0.0389 | H12: 0.0849 | I12: 0.0848 | J12: 0.0661 | K12: 0.0452 | L12: 1.2554 | M12: 0.075 | N12: 0.23627781 | O12: 0.048514813 | P12: 0.048514813 | Q12: 0.023237546 | R12: 0.023237546 | S12: 0.0478 | T12: 0.0448 | U12: 0.0606 | V12: 0.0337 | W12: 0.0493 | X12: 0.0386 | Y12: 0.0544 | Z12: 0.091912826 | AA12: 0.069063405 | AB12: 0.0283 | AC12: 0.0331 | AD12: 0.0145 | AE12: 0.016836741 | AF12: 0.0262 | AG12: 0.0177 | AH12: 0.0127 | AI12: 0.0081 | AJ12: 0.0071 | AK12: 0.0051 | AL12: 0 | AM12: 0.0091 | AN12: 0.0116 | AO12: 0.029 | AP12: 0 | AQ12: 0
A13: ISIC 21 | B13: 0.000768673 | C13: 1.29608e-05 | D13: 1.29608e-05 | E13: 0.0015 | F13: 0.0013 | G13: 0.0029 | H13: 0.0049 | I13: 0.0027 | J13: 0.0019 | K13: 0.0008 | L13: 0.0015 | M13: 1.0516 | N13: 0.000169813 | O13: 6.53827e-05 | P13: 6.53827e-05 | Q13: 3.10045e-05 | R13: 3.10045e-05 | S13: 0.0019 | T13: 0.0012 | U13: 0.0017 | V13: 0.0019 | W13: 0.0017 | X13: 0.0028 | Y13: 0.0021 | Z13: 4.58869e-05 | AA13: 3.63702e-05 | AB13: 0.0018 | AC13: 0.0012 | AD13: 0.0019 | AE13: 4.46328e-05 | AF13: 0.002 | AG13: 0.0009 | AH13: 0.0012 | AI13: 0.0006 | AJ13: 0.0007 | AK13: 0.0003 | AL13: 0 | AM13: 0.0014 | AN13: 0.0012 | AO13: 0.0929 | AP13: 0 | AQ13: 0
... A43: ISIC 97T98 | B43: 0 | C43: 7.35628e-05 | D43: 3.77375e-06 | E43: 0 | F43: 0 | G43: 0 | H43: 0 | I43: 0 | J43: 0 | K43: 0 | L43: 0 | M43: 0 | N43: 0 | O43: 1.55046e-08 | P43: 1.564e-08 | Q43: 1.88764e-06 | R43: 2.58299e-08 | S43: 0 | T43: 0 | U43: 0 | V43: 0 | W43: 0 | X43: 0 | Y43: 0 | Z43: 1.43935e-07 | AA43: 6.91656e-10 | AB43: 0 | AC43: 0 | AD43: 0 | AE43: 0 | AF43: 0 | AG43: 0 | AH43: 0 | AI43: 0 | AJ43: 0 | AK43: 0 | AL43: 0 | AM43: 0 | AN43: 0 | AO43: 0 | AP43: 0 | AQ43: 1

Sheet DLIM ISIC alignment
A1: =DLIM!A1 -> 0 | B1: =DLIM!B1 -> ISIC 01T03 | C1: =DLIM!C1 -> ISIC 05 | D1: =DLIM!D1 -> ISIC 06 | E1: =DLIM!E1 -> ISIC 07T08 | F1: =DLIM!F1 -> ISIC 09 | G1: =DLIM!G1 -> ISIC 10T12 | H1: =DLIM!H1 -> ISIC 13T15 | ... AQ1: =DLIM!AQ1 -> ISIC 97T98
A2: =DLIM!A2 -> ISIC 01T03 | B2: =DLIM!B2 -> 1.127 | C2: =DLIM!C2 -> 0.00241574 | D2: =DLIM!D2 -> 0.00142797 | E2: =DLIM!E2 -> 0.005 | F2: =DLIM!F2 -> 0.001 | G2: =DLIM!G2 -> 0.345 | H2: =DLIM!H2 -> 0.038 | ... AQ2: =DLIM!AQ2 -> 0
A3: =DLIM!A3 -> ISIC 05 | B3: =DLIM!B3 -> 4.3415e-05 | C3: =DLIM!C3 -> 1.0002745 | D3: =DLIM!D3 -> 3.97617e-06 | E3: =DLIM!E3 -> 1.43397e-05 | F3: =DLIM!F3 -> 0 | G3: =DLIM!G3 -> 6.01769e-05 | H3: =DLIM!H3 -> 0.000133288 | ... AQ3: =DLIM!AQ3 -> 0.000440919
A4: =DLIM!A4 -> ISIC 06 | B4: =DLIM!B4 -> 6.13748e-05 | C4: =DLIM!C4 -> 3.73795e-05 | D4: =DLIM!D4 -> 1 | E4: =DLIM!E4 -> 5.36738e-06 | F4: =DLIM!F4 -> 0 | G4: =DLIM!G4 -> 3.35631e-05 | H4: =DLIM!H4 -> 0.004412682 | ... AQ4: =DLIM!AQ4 -> 0.000143567
A5: =DLIM!A5 -> ISIC 07T08 | B5: =DLIM!B5 -> 0 | C5: =DLIM!C5 -> 0.000173382 | D5: =DLIM!D5 -> 1.37706e-05 | E5: =DLIM!E5 -> 1.0018 | F5: =DLIM!F5 -> 0.0065 | G5: =DLIM!G5 -> 0.0009 | H5: =DLIM!H5 -> 0.0009 | ... AQ5: =DLIM!AQ5 -> 0
A6: =DLIM!A6 -> ISIC 09 | B6: =DLIM!B6 -> 0 | C6: =DLIM!C6 -> 0 | D6: =DLIM!D6 -> 0 | E6: =DLIM!E6 -> 0.0001 | F6: =DLIM!F6 -> 1.0002 | G6: =DLIM!G6 -> 0 | H6: =DLIM!H6 -> 0 | ... AQ6: =DLIM!AQ6 -> 0
A7: =DLIM!A7 -> ISIC 10T12 | B7: =DLIM!B7 -> 0.147 | C7: =DLIM!C7 -> 0.012929594 | D7: =DLIM!D7 -> 0.007709781 | E7: =DLIM!E7 -> 0.0163 | F7: =DLIM!F7 -> 0.0081 | G7: =DLIM!G7 -> 1.2033 | H7: =DLIM!H7 -> 0.0325 | ... AQ7: =DLIM!AQ7 -> 0
A8: =DLIM!A8 -> ISIC 13T15 | B8: =DLIM!B8 -> 0.013 | C8: =DLIM!C8 -> 0.002877961 | D8: =DLIM!D8 -> 0.000284925 | E8: =DLIM!E8 -> 0.0132 | F8: =DLIM!F8 -> 0.0086 | G8: =DLIM!G8 -> 0.0153 | H8: =DLIM!H8 -> 1.2742 | ... AQ8: =DLIM!AQ8 -> 0
A9: =DLIM!A9 -> ISIC 16 | B9: =DLIM!B9 -> 0.002 | C9: =DLIM!C9 -> 0.005178574 | D9: =DLIM!D9 -> 0.000139887 | E9: =DLIM!E9 -> 0.0023 | F9: =DLIM!F9 -> 0.0018 | G9: =DLIM!G9 -> 0.0029 | H9: =DLIM!H9 -> 0.0036 | ... AQ9: =DLIM!AQ9 -> 0
A10: =DLIM!A10 -> ISIC 17T18 | B10: =DLIM!B10 -> 0.008 | C10: =DLIM!C10 -> 0.002740184 | D10: =DLIM!D10 -> 0.000588579 | E10: =DLIM!E10 -> 0.0092 | F10: =DLIM!F10 -> 0.0079 | G10: =DLIM!G10 -> 0.0367 | H10: =DLIM!H10 -> 0.0255 | ... AQ10: =DLIM!AQ10 -> 0
A11: =DLIM!A11 -> ISIC 19 | B11: =DLIM!B11 -> 0.033 | C11: =DLIM!C11 -> 0.000239229 | D11: =DLIM!D11 -> 5.92721e-05 | E11: =DLIM!E11 -> 0.0527 | F11: =DLIM!F11 -> 0.0438 | G11: =DLIM!G11 -> 0.0254 | H11: =DLIM!H11 -> 0.0317 | ... AQ11: =DLIM!AQ11 -> 0
A12: =DLIM!A12 -> ISIC 20 | B12: =DLIM!B12 -> 0.040642517 | C12: =DLIM!C12 -> 0.023920855 | D12: =DLIM!D12 -> 0.023920855 | E12: =DLIM!E12 -> 0.0409 | F12: =DLIM!F12 -> 0.0325 | G12: =DLIM!G12 -> 0.0389 | H12: =DLIM!H12 -> 0.0849 | ... AQ12: =DLIM!AQ12 -> 0
... A43: =DLIM!A43 -> ISIC 97T98 | B43: =DLIM!B43 -> 0 | C43: =DLIM!C43 -> 7.35628e-05 | D43: =DLIM!D43 -> 3.77375e-06 | E43: =DLIM!E43 -> 0 | F43: =DLIM!F43 -> 0 | G43: =DLIM!G43 -> 0 | H43: =DLIM!H43 -> 0 | ... AQ43: =DLIM!AQ43 -> 1

Sheet BObIC
A1: Unit: USD | B1: ISIC 01T03 | C1: ISIC 05 | D1: ISIC 06 | E1: ISIC 07T08 | F1: ISIC 09 | G1: ISIC 10T12 | H1: ISIC 13T15 | I1: ISIC 16 | J1: ISIC 17T18 | K1: ISIC 19 | L1: ISIC 20 | M1: ISIC 21 | N1: ISIC 22 | O1: ISIC 231 | P1: ISIC 239 | Q1: ISIC 241 | R1: ISIC 242 | S1: ISIC 25 | T1: ISIC 26 | U1: ISIC 27 | V1: ISIC 28 | W1: ISIC 29 | X1: ISIC 30 | Y1: ISIC 31T33 | Z1: ISIC 351 | AA1: ISIC 352T353 | AB1: ISIC 36T39 | AC1: ISIC 41T43 | AD1: ISIC 45T47 | AE1: ISIC 49T53 | AF1: ISIC 55T56 | AG1: ISIC 58T60 | AH1: ISIC 61 | AI1: ISIC 62T63 | AJ1: ISIC 64T66 | AK1: ISIC 68 | AL1: ISIC 69T82 | AM1: ISIC 84 | AN1: ISIC 85 | AO1: ISIC 86T88 | AP1: ISIC 90T96 | AQ1: ISIC 97T98
A2: Output | B2: 44846032000 | C2: 2.6230038e+08 | D2: 1.4865562e+08 | E2: 3305939000 | F2: 20020000 | G2: 102938654000 | H2: 64002939000 | I2: 7215390000 | J2: 32329297000 | K2: 111021001000 | L2: 142563876000 | M2: 18592210000 | N2: 59839560000 | O2: 1.1808344e+10 | P2: 2.446553e+10 | Q2: 9.8234755e+10 | R2: 2.6809983e+10 | S2: 84072352000 | T2: 286853112000 | U2: 81964883000 | V2: 1.220371e+11 | W2: 163254000000 | X2: 38348583000 | Y2: 29198533000 | Z2: 3.6868341e+10 | AA2: 1.2129536e+10 | AB2: 17124926000 | AC2: 213075681000 | AD2: 219045008000 | AE2: 106890256000 | AF2: 121327024000 | AG2: 46107880000 | AH2: 35588826000 | AI2: 41416102000 | AJ2: 149317077000 | AK2: 161103943000 | AL2: 145715504000 | AM2: 127571444000 | AN2: 108532151000 | AO2: 127008063000 | AP2: 57543376000 | AQ2: 1831193000

Sheet SIOM from DLIM
A1: Inverse of DLIM
B3: ISIC 01T03 | C3: ISIC 05 | D3: ISIC 06 | E3: ISIC 07T08 | F3: ISIC 09 | G3: ISIC 10T12 | H3: ISIC 13T15 | I3: ISIC 16 | J3: ISIC 17T18 | K3: ISIC 19 | L3: ISIC 20 | M3: ISIC 21 | N3: ISIC 22 | O3: ISIC 231 | P3: ISIC 239 | Q3: ISIC 241 | R3: ISIC 242 | S3: ISIC 25 | T3: ISIC 26 | U3: ISIC 27 | V3: ISIC 28 | W3: ISIC 29 | X3: ISIC 30 | Y3: ISIC 31T33 | Z3: ISIC 351 | AA3: ISIC 352T353 | AB3: ISIC 36T39 | AC3: ISIC 41T43 | AD3: ISIC 45T47 | AE3: ISIC 49T53 | AF3: ISIC 55T56 | AG3: ISIC 58T60 | AH3: ISIC 61 | AI3: ISIC 62T63 | AJ3: ISIC 64T66 | AK3: ISIC 68 | AL3: ISIC 69T82 | AM3: ISIC 84 | AN3: ISIC 85 | AO3: ISIC 86T88 | AP3: ISIC 90T96 | AQ3: ISIC 97T98
A4: ISIC 01T03 | B4: {=MINVERSE(DLIM!B2:AQ43)} -> 0.92267453 | C4: 0.0072844889 | D4: 0.0041218841 | E4: 0.0023296272 | F4: 0.0027641108 | G4: -0.26096578 | H4: -0.017943525 | I4: -0.10623339 | J4: -0.01737186 | K4: -0.00038606289 | L4: 0.0015965877 | M4: 0.0057204144 | N4: -0.010163399 | O4: 0.0020780753 | P4: 0.0010508184 | Q4: 0.00055061296 | R4: 0.0013501347 | S4: 0.0010561955 | T4: 0.00075727735 | U4: 0.0009802836 | V4: 0.00075638719 | W4: 0.0011702356 | X4: -3.5642196e-05 | Y4: -0.0066839445 | Z4: 0.00085018739 | AA4: 0.0007276673 | AB4: 0.0040226003 | AC4: -0.0022362361 | AD4: -0.0066614788 | AE4: -0.0011536566 | AF4: -0.040575968 | AG4: -0.0025167973 | AH4: 0.0026333433 | AI4: -0.0010606551 | AJ4: 0.0014213118 | AK4: 0.0001122521 | AL4: -0.0016309823 | AM4: -0.0043014997 | AN4: 0.0022949016 | AO4: -0.0054300741 | AP4: -0.003113081 | AQ4: -8.205069e-05
A5: ISIC 05 | B5: 0.0036790665 | C5: 1.0022065 | D5: 0.0030034581 | E5: 0.0038952272 | F5: 0.0030659258 | G5: 0.0014973771 | H5: 0.0066075131 | I5: 0.007358178 | J5: 0.0051449275 | K5: 0.0045803405 | L5: -0.13134479 | M5: -0.0086795292 | N5: 0.025140458 | O5: 0.0046829037 | P5: 0.0046913416 | Q5: -0.00356382 | R5: 0.0018137602 | S5: 0.0032770508 | T5: 0.0035492748 | U5: 0.004262885 | V5: 0.0011906359 | W5: 0.0015440915 | X5: 0.0021467089 | Y5: 0.0031245712 | Z5: 0.0089805428 | AA5: 0.0090155147 | AB5: 0.0022941239 | AC5: 0.0013171363 | AD5: 0.00081298317 | AE5: 0.00064405304 | AF5: 0.00098588157 | AG5: 0.0013335182 | AH5: 0.00056458449 | AI5: 0.00042193028 | AJ5: 0.00036271258 | AK5: 0.00015114335 | AL5: -0.0010049214 | AM5: 0.00045954079 | AN5: 0.000560258 | AO5: 0.0033765982 | AP5: -0.0016895709 | AQ5: -0.00040748482
A6: ISIC 06 | B6: 0.0036731909 | C6: 0.0021892612 | D6: 1.0030033 | E6: 0.0039634195 | F6: 0.0031150812 | G6: 0.0015546892 | H6: 0.0033245785 | I6: 0.0035222817 | J6: 0.0052059375 | K6: 0.0046225613 | L6: -0.13134205 | M6: -0.0086307341 | N6: 0.025139463 | O6: 0.0046854535 | P6: 0.0046921489 | Q6: 0.0012204137 | R6: 0.0018916699 | S6: 0.0033548937 | T6: 0.0035850638 | U6: 0.0043108301 | V6: 0.0012394482 | W6: 0.0014556953 | X6: 0.0022572437 | Y6: -0.0010274881 | Z6: 0.010785031 | AA6: 0.0090147856 | AB6: 0.0025622007 | AC6: 0.0013290168 | AD6: 0.00085844184 | AE6: 0.00068574485 | AF6: 0.0010295176 | AG6: 0.0013689342 | AH6: 0.0005867743 | AI6: 0.00042847972 | AJ6: 0.00037836234 | AK6: 0.00017528518 | AL6: -0.00097970939 | AM6: 0.00047434309 | AN6: 0.00058317974 | AO6: 0.0034191216 | AP6: -0.0017015986 | AQ6: -0.00047839405
A7: ISIC 07T08 | B7: 0.00028589145 | C7: 0.00019850415 | D7: 9.9358628e-05 | E7: 0.99848791 | F7: -0.0062688704 | G7: -0.00055462984 | H7: -0.00026609533 | I7: -0.00032493381 | J7: -0.00055583626 | K7: -0.00028642318 | L7: -0.0034913862 | M7: -0.00066934949 | N7: 7.7580855e-05 | O7: -0.003764716 | P7: -0.11065674 | Q7: -0.00094652276 | R7: -0.00062380712 | S7: -0.00080966467 | T7: -0.00035840303 | U7: -0.00087646592 | V7: -0.00036474476 | W7: -0.00064778785 | X7: -0.0010781589 | Y7: -0.00045752647 | Z7: 0.00028397303 | AA7: 0.00024161676 | AB7: -0.00064042368 | AC7: 0.00091336926 | AD7: -0.00016103535 | AE7: 0.00015607547 | AF7: -0.00022425441 | AG7: -0.00014643763 | AH7: -0.00012565126 | AI7: -0.00010223106 | AJ7: -9.7918436e-06 | AK7: -0.00032652993 | AL7: 0.00010565009 | AM7: -2.034267e-05 | AN7: -2.7821467e-05 | AO7: -7.4163095e-05 | AP7: 0.00022047678 | AQ7: 0.00019032664
A8: ISIC 09 | B8: 1.8354169e-06 | C8: -6.2440605e-07 | D8: -3.5697263e-07 | E8: -9.6273435e-05 | F8: 0.99980386 | G8: 3.2097156e-07 | H8: 8.1321292e-07 | I8: 7.0920655e-07 | J8: 9.2675567e-07 | K8: -8.9793384e-05 | L8: 1.0925075e-05 | M8: 1.4853726e-06 | N8: 2.6740474e-06 | O8: -3.6215895e-07 | P8: 9.8341508e-06 | Q8: -1.0943569e-07 | R8: -2.1491085e-07 | S8: 1.1478771e-06 | T8: 5.2237955e-07 | U8: 8.6894421e-07 | V8: 5.5719764e-07 | W8: 5.2037781e-07 | X8: 1.0135986e-06 | Y8: 5.3425762e-07 | Z8: -1.0040767e-06 | AA8: -7.7989304e-07 | AB8: 1.7939723e-06 | AC8: 9.7283679e-07 | AD8: 1.4039288e-06 | AE8: 7.1260575e-06 | AF8: 9.8521235e-07 | AG8: 3.9737591e-07 | AH8: 3.4348723e-07 | AI8: 1.9751166e-07 | AJ8: 1.2996843e-07 | AK8: 2.7854788e-07 | AL8: 7.6384892e-07 | AM8: 9.1723905e-07 | AN8: 1.0232816e-06 | AO8: 1.0054267e-06 | AP8: 1.2899469e-06 | AQ8: 2.1584095e-08
A9: ISIC 10T12 | B9: -0.11142643 | C9: 0.020301615 | D9: 0.01236963 | E9: -0.0035804568 | F9: -0.0020833054 | G9: 0.86954301 | H9: -0.012357317 | I9: 0.00010508111 | J9: -0.00051332073 | K9: -0.0010551991 | L9: -0.011231138 | M9: -0.012690937 | N9: -0.0058556328 | O9: 0.0034484574 | P9: 0.002878373 | Q9: 0.0014931317 | R9: 0.002753676 | S9: -0.0036239804 | T9: -0.0014450294 | U9: -0.0021439882 | V9: -0.0028571963 | W9: -0.0012023295 | X9: -0.0041143077 | Y9: -0.0013800454 | Z9: 0.00381004 | AA9: 0.0030959343 | AB9: -0.0016910859 | AC9: -0.0011716797 | AD9: -0.0023666088 | AE9: -0.0032130797 | AF9: -0.22037404 | AG9: -0.0016031706 | AH9: -0.0015184451 | AI9: -0.00027481542 | AJ9: -0.0013990503 | AK9: -0.00015684717 | AL9: -0.0055137405 | AM9: -0.0039519003 | AN9: -0.013827866 | AO9: -0.014112306 | AP9: -0.024059652 | AQ9: -0.00022721241
A10: ISIC 13T15 | B10: -0.0066345408 | C10: 0.0011027185 | D10: 0.00056409951 | E10: -0.006486538 | F10: -0.0041000701 | G10: -0.0037748984 | H10: 0.79056673 | I10: -0.0080888838 | J10: -0.011333032 | K10: -0.0017086035 | L10: -0.0038709307 | M10: -0.006166692 | N10: -0.026222238 | O10: -0.00038021276 | P10: -0.001009124 | Q10: -0.00017934798 | R10: 9.956499e-05 | S10: -0.0079275435 | T10: -0.0035542862 | U10: -0.0054131198 | V10: -0.0053405125 | W10: -0.0058944369 | X10: -0.013213056 | Y10: -0.03727952 | Z10: 0.00078750912 | AA10: 0.00040930228 | AB10: -0.0061176466 | AC10: -0.0021887981 | AD10: -0.0056338396 | AE10: -0.0070088735 | AF10: -0.0066432284 | AG10: -0.0019574458 | AH10: -0.0016709345 | AI10: 0.00014803836 | AJ10: -0.0020503103 | AK10: -0.0006246982 | AL10: -0.0084115961 | AM10: -0.0053625876 | AN10: -0.0021421729 | AO10: -0.0067715798 | AP10: -0.024937251 | AQ10: 3.8020071e-06
A11: ISIC 16 | B11: -0.0011259306 | C11: -0.0038890076 | D11: 4.1706852e-05 | E11: -0.0012437538 | F11: -0.0008045898 | G11: -0.0009421142 | H11: -0.00088195987 | I11: 0.85961158 | J11: -0.0013460118 | K11: -0.00035150593 | L11: -1.7077006e-05 | M11: -0.00040323074 | N11: -0.0017397701 | O11: -0.0066671161 | P11: -0.003400542 | Q11: -0.00047238219 | R11: -0.0030171586 | S11: -0.0017732613 | T11: 3.5159352e-05 | U11: -0.00065599033 | V11: -0.00087168706 | W11: -0.00047272804 | X11: -0.00088842117 | Y11: -0.02819785 | Z11: -0.00037201473 | AA11: 3.1743205e-06 | AB11: -0.00059942312 | AC11: -0.012361693 | AD11: -0.00093591439 | AE11: -0.00037505871 | AF11: -0.001524399 | AG11: -7.1073267e-05 | AH11: -0.00010619753 | AI11: -7.1299289e-05 | AJ11: -2.0318294e-05 | AK11: -3.4817753e-05 | AL11: -0.00046315162 | AM11: -1.7143433e-05 | AN11: -0.00039212382 | AO11: -0.00038120693 | AP11: -0.0019517262 | AQ11: 0.00011090778
A12: ISIC 17T18 | B12: -0.00064694377 | C12: 0.00037473797 | D12: 0.00033742442 | E12: -0.0030029578 | F12: -0.0029897584 | G12: -0.018110361 | H12: -0.010128047 | I12: -0.013490179 | J12: 0.74622566 | K12: -0.0023459116 | L12: -0.0064603724 | M12: -0.014983361 | N12: -0.0094619678 | O12: -0.007805849 | P12: -0.0052171601 | Q12: -0.00030251146 | R12: -0.0013771957 | S12: -0.0056656387 | T12: -0.0016054336 | U12: -0.0064360748 | V12: -0.0024853172 | W12: -0.0014856469 | X12: -0.0025343372 | Y12: -0.0089649757 | Z12: 0.00035210009 | AA12: 0.00035417265 | AB12: -0.0028755308 | AC12: -0.0028064867 | AD12: -0.010172999 | AE12: -0.0024462457 | AF12: -0.0048191822 | AG12: -0.024532898 | AH12: -0.0037162466 | AI12: -0.0044798478 | AJ12: -0.0081468793 | AK12: -0.00063382426 | AL12: -0.0095061788 | AM12: -0.0045047006 | AN12: -0.0054128802 | AO12: -0.0036834856 | AP12: -0.011762013 | AQ12: 9.2671482e-05
A13: ISIC 19 | B13: -0.018643731 | C13: 0.0060468052 | D13: 0.0034710816 | E13: -0.035561019 | F13: -0.031890966 | G13: -0.0026557277 | H13: -0.0078676603 | I13: -0.0067685501 | J13: -0.008713574 | K13: 0.89839985 | L13: -0.10578121 | M13: -0.014187347 | N13: -0.026823403 | O13: 0.0073870298 | P13: 0.012295565 | Q13: 0.0020410985 | R13: 0.0027733455 | S13: -0.010671403 | T13: -0.0048664372 | U13: -0.0078147141 | V13: -0.005208346 | W13: -0.004557031 | X13: -0.0090598548 | Y13: -0.0048861183 | Z13: 0.0097588024 | AA13: 0.0075588734 | AB13: -0.017302887 | AC13: -0.010643683 | AD13: -0.01388106 | AE13: -0.071430902 | AF13: -0.0096298395 | AG13: -0.0038281162 | AH13: -0.003309908 | AI13: -0.0018732805 | AJ13: -0.0012901524 | AK13: -0.0024595059 | AL13: -0.007745667 | AM13: -0.0091538823 | AN13: -0.010207041 | AO13: -0.0099821152 | AP13: -0.013122526 | AQ13: -0.00040621075
A14: ISIC 20 | B14: -0.022851053 | C14: -0.013675819 | D14: -0.018568658 | E14: -0.023966321 | F14: -0.018822956 | G14: -0.009087343 | H14: -0.040714043 | I14: -0.045554823 | J14: -0.031897809 | K14: -0.028442105 | L14: 0.8115369 | M14: -0.047127497 | N14: -0.15560599 | O14: -0.028977806 | P14: -0.029081529 | Q14: -0.0075592737 | R14: -0.011699169 | S14: -0.020253219 | T14: -0.021965496 | U14: -0.026319456 | V14: -0.0073034308 | W14: -0.0095033619 | X14: -0.013058826 | Y14: -0.019257492 | Z14: -0.066769059 | AA14: -0.055701695 | AB14: -0.015568121 | AC14: -0.0081009693 | AD14: -0.0048578502 | AE14: -0.0041557897 | AF14: -0.0060153842 | AG14: -0.0081417659 | AH14: -0.0033999185 | AI14: -0.0025492983 | AJ14: -0.0022147126 | AK14: -0.00098984626 | AL14: 0.0059047284 | AM14: -0.0027858934 | AN14: -0.0035472992 | AO14: -0.011712957 | AP14: 0.0098556266 | AQ14: 0.0020722259
A15: ISIC 21 | B15: 0.00052829251 | C15: 0.00028951463 | D15: 7.5703313e-05 | E15: -0.00080954795 | F15: -0.00076954258 | G15: -0.001888669 | H15: -0.0030881688 | I15: -0.0016225264 | J15: -0.00095631141 | K15: -0.00039675678 | L15: -0.00068517874 | M15: 0.95176159 | N15: 0.0013725274 | O15: -2.7486734e-05 | P15: 2.886793e-05 | Q15: -1.5121085e-05 | R15: -6.9645662e-06 | S15: -0.001097024 | T15: -0.00074808541 | U15: -0.00094551397 | V15: -0.0010210549 | W15: -0.00068880951 | X15: -0.0017904027 | Y15: -0.0012142333 | Z15: 2.951844e-05 | AA15: 1.2433892e-05 | AB15: -0.0011037746 | AC15: -0.0006080192 | AD15: -0.0012912419 | AE15: 0.0018949878 | AF15: -0.00066246739 | AG15: -0.00063842673 | AH15: -0.00061204192 | AI15: -0.00047701127 | AJ15: -0.00034090084 | AK15: -6.7026344e-05 | AL15: 0.0025646713 | AM15: -0.001123252 | AN15: -0.00070008355 | AO15: -0.087701314 | AP15: 0.0049260095 | AQ15: 7.4233695e-07
A16: ISIC 22 | B16: -0.0046953894 | C16: -0.00084069973 | D16: 0.00082356437 | E16: -0.009261182 | F16: -0.0068002334 | G16: -0.020211742 | H16: -0.022588331 | I16: -0.012700924 | J16: -0.010732489 | K16: -0.002706122 | L16: -0.012707937 | M16: -0.013863667 | N16: 0.85935353 | O16: -0.014892385 | P16: -0.0018857756 | Q16: -0.00105044 | R16: -0.001851385 | S16: -0.016990556 | T16: -0.018474157 | U16: -0.039346343 | V16: -0.023175256 | W16: -0.053766613 | X16: -0.016511426 | Y16: -0.050827316 | Z16: -0.0018688099 | AA16: 0.00089241537 | AB16: -0.0060492793 | AC16: -0.029241948 | AD16: -0.0065732225 | AE16: -0.010276909 | AF16: -0.010232569 | AG16: -0.0022635788 | AH16: -0.0014667436 | AI16: -0.00064202361 | AJ16: -0.00073246592 | AK16: -0.00057399263 | AL16: -0.0055804063 | AM16: -0.0010635743 | AN16: -0.0021650126 | AO16: -0.0024768701 | AP16: -0.0084516584 | AQ16: 0.00023321271
... A45: ISIC 97T98 | B45: -2.8673235e-07 | C45: -7.3707499e-05 | D45: -4.005262e-06 | E45: -3.1892153e-07 | F45: -2.6319154e-07 | G45: -1.2002279e-07 | H45: -5.0509416e-07 | I45: -5.6389325e-07 | J45: -4.0061064e-07 | K45: -3.5486501e-07 | L45: 1.0149068e-05 | M45: 6.6296748e-07 | N45: -1.9373052e-06 | O45: -3.740288e-07 | P45: -3.6885528e-07 | Q45: -6.9001124e-07 | R45: -1.5224562e-07 | S45: 1.5294621e-07 | T45: -2.5632542e-07 | U45: -2.7254878e-07 | V45: 1.181133e-07 | W45: -7.8467444e-08 | X45: -1.9366468e-07 | Y45: -1.6897866e-07 | Z45: -8.4286167e-07 | AA45: -6.9677997e-07 | AB45: -1.8043281e-07 | AC45: 3.9943556e-08 | AD45: -6.7912205e-08 | AE45: -5.6052034e-08 | AF45: -8.1029732e-08 | AG45: -1.0784261e-07 | AH45: -5.0313751e-08 | AI45: -3.6036949e-08 | AJ45: -2.9704533e-08 | AK45: -2.0646802e-08 | AL45: 7.630879e-08 | AM45: -2.4673802e-08 | AN45: -4.3475093e-08 | AO45: -2.6019732e-07 | AP45: 1.3467907e-07 | AQ45: 1.0000001
A47: I Matrix
B49: ISIC 01T03 | C49: ISIC 05 | D49: ISIC 06 | E49: ISIC 07T08 | F49: ISIC 09 | G49: ISIC 10T12 | H49: ISIC 13T15 | I49: ISIC 16 | J49: ISIC 17T18 | K49: ISIC 19 | L49: ISIC 20 | M49: ISIC 21 | N49: ISIC 22 | O49: ISIC 231 | P49: ISIC 239 | Q49: ISIC 241 | R49: ISIC 242 | S49: ISIC 25 | T49: ISIC 26 | U49: ISIC 27 | V49: ISIC 28 | W49: ISIC 29 | X49: ISIC 30 | Y49: ISIC 31T33 | Z49: ISIC 351 | AA49: ISIC 352T353 | AB49: ISIC 36T39 | AC49: ISIC 41T43 | AD49: ISIC 45T47 | AE49: ISIC 49T53 | AF49: ISIC 55T56 | AG49: ISIC 58T60 | AH49: ISIC 61 | AI49: ISIC 62T63 | AJ49: ISIC 64T66 | AK49: ISIC 68 | AL49: ISIC 69T82 | AM49: ISIC 84 | AN49: ISIC 85 | AO49: ISIC 86T88 | AP49: ISIC 90T96 | AQ49: ISIC 97T98
A50: ISIC 01T03 | B50: 1 | C50: 0 | D50: 0 | E50: 0 | F50: 0 | G50: 0 | H50: 0 | I50: 0 | J50: 0 | K50: 0 | L50: 0 | M50: 0 | N50: 0 | O50: 0 | P50: 0 | Q50: 0 | R50: 0 | S50: 0 | T50: 0 | U50: 0 | V50: 0 | W50: 0 | X50: 0 | Y50: 0 | Z50: 0 | AA50: 0 | AB50: 0 | AC50: 0 | AD50: 0 | AE50: 0 | AF50: 0 | AG50: 0 | AH50: 0 | AI50: 0 | AJ50: 0 | AK50: 0 | AL50: 0 | AM50: 0 | AN50: 0 | AO50: 0 | AP50: 0 | AQ50: 0
A51: ISIC 05 | B51: 0 | C51: 1 | D51: 0 | E51: 0 | F51: 0 | G51: 0 | H51: 0 | I51: 0 | J51: 0 | K51: 0 | L51: 0 | M51: 0 | N51: 0 | O51: 0 | P51: 0 | Q51: 0 | R51: 0 | S51: 0 | T51: 0 | U51: 0 | V51: 0 | W51: 0 | X51: 0 | Y51: 0 | Z51: 0 | AA51: 0 | AB51: 0 | AC51: 0 | AD51: 0 | AE51: 0 | AF51: 0 | AG51: 0 | AH51: 0 | AI51: 0 | AJ51: 0 | AK51: 0 | AL51: 0 | AM51: 0 | AN51: 0 | AO51: 0 | AP51: 0 | AQ51: 0
A52: ISIC 06 | B52: 0 | C52: 0 | D52: 1 | E52: 0 | F52: 0 | G52: 0 | H52: 0 | I52: 0 | J52: 0 | K52: 0 | L52: 0 | M52: 0 | N52: 0 | O52: 0 | P52: 0 | Q52: 0 | R52: 0 | S52: 0 | T52: 0 | U52: 0 | V52: 0 | W52: 0 | X52: 0 | Y52: 0 | Z52: 0 | AA52: 0 | AB52: 0 | AC52: 0 | AD52: 0 | AE52: 0 | AF52: 0 | AG52: 0 | AH52: 0 | AI52: 0 | AJ52: 0 | AK52: 0 | AL52: 0 | AM52: 0 | AN52: 0 | AO52: 0 | AP52: 0 | AQ52: 0
A53: ISIC 07T08 | B53: 0 | C53: 0 | D53: 0 | E53: 1 | F53: 0 | G53: 0 | H53: 0 | I53: 0 | J53: 0 | K53: 0 | L53: 0 | M53: 0 | N53: 0 | O53: 0 | P53: 0 | Q53: 0 | R53: 0 | S53: 0 | T53: 0 | U53: 0 | V53: 0 | W53: 0 | X53: 0 | Y53: 0 | Z53: 0 | AA53: 0 | AB53: 0 | AC53: 0 | AD53: 0 | AE53: 0 | AF53: 0 | AG53: 0 | AH53: 0 | AI53: 0 | AJ53: 0 | AK53: 0 | AL53: 0 | AM53: 0 | AN53: 0 | AO53: 0 | AP53: 0 | AQ53: 0
A54: ISIC 09 | B54: 0 | C54: 0 | D54: 0 | E54: 0 | F54: 1 | G54: 0 | H54: 0 | I54: 0 | J54: 0 | K54: 0 | L54: 0 | M54: 0 | N54: 0 | O54: 0 | P54: 0 | Q54: 0 | R54: 0 | S54: 0 | T54: 0 | U54: 0 | V54: 0 | W54: 0 | X54: 0 | Y54: 0 | Z54: 0 | AA54: 0 | AB54: 0 | AC54: 0 | AD54: 0 | AE54: 0 | AF54: 0 | AG54: 0 | AH54: 0 | AI54: 0 | AJ54: 0 | AK54: 0 | AL54: 0 | AM54: 0 | AN54: 0 | AO54: 0 | AP54: 0 | AQ54: 0
A55: ISIC 10T12 | B55: 0 | C55: 0 | D55: 0 | E55: 0 | F55: 0 | G55: 1 | H55: 0 | I55: 0 | J55: 0 | K55: 0 | L55: 0 | M55: 0 | N55: 0 | O55: 0 | P55: 0 | Q55: 0 | R55: 0 | S55: 0 | T55: 0 | U55: 0 | V55: 0 | W55: 0 | X55: 0 | Y55: 0 | Z55: 0 | AA55: 0 | AB55: 0 | AC55: 0 | AD55: 0 | AE55: 0 | AF55: 0 | AG55: 0 | AH55: 0 | AI55: 0 | AJ55: 0 | AK55: 0 | AL55: 0 | AM55: 0 | AN55: 0 | AO55: 0 | AP55: 0 | AQ55: 0
A56: ISIC 13T15 | B56: 0 | C56: 0 | D56: 0 | E56: 0 | F56: 0 | G56: 0 | H56: 1 | I56: 0 | J56: 0 | K56: 0 | L56: 0 | M56: 0 | N56: 0 | O56: 0 | P56: 0 | Q56: 0 | R56: 0 | S56: 0 | T56: 0 | U56: 0 | V56: 0 | W56: 0 | X56: 0 | Y56: 0 | Z56: 0 | AA56: 0 | AB56: 0 | AC56: 0 | AD56: 0 | AE56: 0 | AF56: 0 | AG56: 0 | AH56: 0 | AI56: 0 | AJ56: 0 | AK56: 0 | AL56: 0 | AM56: 0 | AN56: 0 | AO56: 0 | AP56: 0 | AQ56: 0
A57: ISIC 16 | B57: 0 | C57: 0 | D57: 0 | E57: 0 | F57: 0 | G57: 0 | H57: 0 | I57: 1 | J57: 0 | K57: 0 | L57: 0 | M57: 0 | N57: 0 | O57: 0 | P57: 0 | Q57: 0 | R57: 0 | S57: 0 | T57: 0 | U57: 0 | V57: 0 | W57: 0 | X57: 0 | Y57: 0 | Z57: 0 | AA57: 0 | AB57: 0 | AC57: 0 | AD57: 0 | AE57: 0 | AF57: 0 | AG57: 0 | AH57: 0 | AI57: 0 | AJ57: 0 | AK57: 0 | AL57: 0 | AM57: 0 | AN57: 0 | AO57: 0 | AP57: 0 | AQ57: 0
A58: ISIC 17T18 | B58: 0 | C58: 0 | D58: 0 | E58: 0 | F58: 0 | G58: 0 | H58: 0 | I58: 0 | J58: 1 | K58: 0 | L58: 0 | M58: 0 | N58: 0 | O58: 0 | P58: 0 | Q58: 0 | R58: 0 | S58: 0 | T58: 0 | U58: 0 | V58: 0 | W58: 0 | X58: 0 | Y58: 0 | Z58: 0 | AA58: 0 | AB58: 0 | AC58: 0 | AD58: 0 | AE58: 0 | AF58: 0 | AG58: 0 | AH58: 0 | AI58: 0 | AJ58: 0 | AK58: 0 | AL58: 0 | AM58: 0 | AN58: 0 | AO58: 0 | AP58: 0 | AQ58: 0
A59: ISIC 19 | B59: 0 | C59: 0 | D59: 0 | E59: 0 | F59: 0 | G59: 0 | H59: 0 | I59: 0 | J59: 0 | K59: 1 | L59: 0 | M59: 0 | N59: 0 | O59: 0 | P59: 0 | Q59: 0 | R59: 0 | S59: 0 | T59: 0 | U59: 0 | V59: 0 | W59: 0 | X59: 0 | Y59: 0 | Z59: 0 | AA59: 0 | AB59: 0 | AC59: 0 | AD59: 0 | AE59: 0 | AF59: 0 | AG59: 0 | AH59: 0 | AI59: 0 | AJ59: 0 | AK59: 0 | AL59: 0 | AM59: 0 | AN59: 0 | AO59: 0 | AP59: 0 | AQ59: 0
A60: ISIC 20 | B60: 0 | C60: 0 | D60: 0 | E60: 0 | F60: 0 | G60: 0 | H60: 0 | I60: 0 | J60: 0 | K60: 0 | L60: 1 | M60: 0 | N60: 0 | O60: 0 | P60: 0 | Q60: 0 | R60: 0 | S60: 0 | T60: 0 | U60: 0 | V60: 0 | W60: 0 | X60: 0 | Y60: 0 | Z60: 0 | AA60: 0 | AB60: 0 | AC60: 0 | AD60: 0 | AE60: 0 | AF60: 0 | AG60: 0 | AH60: 0 | AI60: 0 | AJ60: 0 | AK60: 0 | AL60: 0 | AM60: 0 | AN60: 0 | AO60: 0 | AP60: 0 | AQ60: 0
A61: ISIC 21 | B61: 0 | C61: 0 | D61: 0 | E61: 0 | F61: 0 | G61: 0 | H61: 0 | I61: 0 | J61: 0 | K61: 0 | L61: 0 | M61: 1 | N61: 0 | O61: 0 | P61: 0 | Q61: 0 | R61: 0 | S61: 0 | T61: 0 | U61: 0 | V61: 0 | W61: 0 | X61: 0 | Y61: 0 | Z61: 0 | AA61: 0 | AB61: 0 | AC61: 0 | AD61: 0 | AE61: 0 | AF61: 0 | AG61: 0 | AH61: 0 | AI61: 0 | AJ61: 0 | AK61: 0 | AL61: 0 | AM61: 0 | AN61: 0 | AO61: 0 | AP61: 0 | AQ61: 0
... A91: ISIC 97T98 | B91: 0 | C91: 0 | D91: 0 | E91: 0 | F91: 0 | G91: 0 | H91: 0 | I91: 0 | J91: 0 | K91: 0 | L91: 0 | M91: 0 | N91: 0 | O91: 0 | P91: 0 | Q91: 0 | R91: 0 | S91: 0 | T91: 0 | U91: 0 | V91: 0 | W91: 0 | X91: 0 | Y91: 0 | Z91: 0 | AA91: 0 | AB91: 0 | AC91: 0 | AD91: 0 | AE91: 0 | AF91: 0 | AG91: 0 | AH91: 0 | AI91: 0 | AJ91: 0 | AK91: 0 | AL91: 0 | AM91: 0 | AN91: 0 | AO91: 0 | AP91: 0 | AQ91: 1
A93: A Matrix
B95: ISIC 01T03 | C95: ISIC 05 | D95: ISIC 06 | E95: ISIC 07T08 | F95: ISIC 09 | G95: ISIC 10T12 | H95: ISIC 13T15 | I95: ISIC 16 | J95: ISIC 17T18 | K95: ISIC 19 | L95: ISIC 20 | M95: ISIC 21 | N95: ISIC 22 | O95: ISIC 231 | P95: ISIC 239 | Q95: ISIC 241 | R95: ISIC 242 | S95: ISIC 25 | T95: ISIC 26 | U95: ISIC 27 | V95: ISIC 28 | W95: ISIC 29 | X95: ISIC 30 | Y95: ISIC 31T33 | Z95: ISIC 351 | AA95: ISIC 352T353 | AB95: ISIC 36T39 | AC95: ISIC 41T43 | AD95: ISIC 45T47 | AE95: ISIC 49T53 | AF95: ISIC 55T56 | AG95: ISIC 58T60 | AH95: ISIC 61 | AI95: ISIC 62T63 | AJ95: ISIC 64T66 | AK95: ISIC 68 | AL95: ISIC 69T82 | AM95: ISIC 84 | AN95: ISIC 85 | AO95: ISIC 86T88 | AP95: ISIC 90T96 | AQ95: ISIC 97T98
A96: ISIC 01T03 | B96: =B50-B4 -> 0.077325465 | C96: =C50-C4 -> -0.0072844889 | D96: =D50-D4 -> -0.0041218841 | E96: =E50-E4 -> -0.0023296272 | F96: =F50-F4 -> -0.0027641108 | G96: =G50-G4 -> 0.26096578 | H96: =H50-H4 -> 0.017943525 | I96: =I50-I4 -> 0.10623339 | ... AQ96: =AQ50-AQ4 -> 8.205069e-05
A97: ISIC 05 | B97: =B51-B5 -> -0.0036790665 | C97: =C51-C5 -> -0.0022065007 | D97: =D51-D5 -> -0.0030034581 | E97: =E51-E5 -> -0.0038952272 | F97: =F51-F5 -> -0.0030659258 | G97: =G51-G5 -> -0.0014973771 | H97: =H51-H5 -> -0.0066075131 | I97: =I51-I5 -> -0.007358178 | ... AQ97: =AQ51-AQ5 -> 0.00040748482
A98: ISIC 06 | B98: =B52-B6 -> -0.0036731909 | C98: =C52-C6 -> -0.0021892612 | D98: =D52-D6 -> -0.0030032654 | E98: =E52-E6 -> -0.0039634195 | F98: =F52-F6 -> -0.0031150812 | G98: =G52-G6 -> -0.0015546892 | H98: =H52-H6 -> -0.0033245785 | I98: =I52-I6 -> -0.0035222817 | ... AQ98: =AQ52-AQ6 -> 0.00047839405
A99: ISIC 07T08 | B99: =B53-B7 -> -0.00028589145 | C99: =C53-C7 -> -0.00019850415 | D99: =D53-D7 -> -9.9358628e-05 | E99: =E53-E7 -> 0.0015120865 | F99: =F53-F7 -> 0.0062688704 | G99: =G53-G7 -> 0.00055462984 | H99: =H53-H7 -> 0.00026609533 | I99: =I53-I7 -> 0.00032493381 | ... AQ99: =AQ53-AQ7 -> -0.00019032664
A100: ISIC 09 | B100: =B54-B8 -> -1.8354169e-06 | C100: =C54-C8 -> 6.2440605e-07 | D100: =D54-D8 -> 3.5697263e-07 | E100: =E54-E8 -> 9.6273435e-05 | F100: =F54-F8 -> 0.00019614479 | G100: =G54-G8 -> -3.2097156e-07 | H100: =H54-H8 -> -8.1321292e-07 | I100: =I54-I8 -> -7.0920655e-07 | ... AQ100: =AQ54-AQ8 -> -2.1584095e-08
A101: ISIC 10T12 | B101: =B55-B9 -> 0.11142643 | C101: =C55-C9 -> -0.020301615 | D101: =D55-D9 -> -0.01236963 | E101: =E55-E9 -> 0.0035804568 | F101: =F55-F9 -> 0.0020833054 | G101: =G55-G9 -> 0.13045699 | H101: =H55-H9 -> 0.012357317 | I101: =I55-I9 -> -0.00010508111 | ... AQ101: =AQ55-AQ9 -> 0.00022721241
A102: ISIC 13T15 | B102: =B56-B10 -> 0.0066345408 | C102: =C56-C10 -> -0.0011027185 | D102: =D56-D10 -> -0.00056409951 | E102: =E56-E10 -> 0.006486538 | F102: =F56-F10 -> 0.0041000701 | G102: =G56-G10 -> 0.0037748984 | H102: =H56-H10 -> 0.20943327 | I102: =I56-I10 -> 0.0080888838 | ... AQ102: =AQ56-AQ10 -> -3.8020071e-06
A103: ISIC 16 | B103: =B57-B11 -> 0.0011259306 | C103: =C57-C11 -> 0.0038890076 | D103: =D57-D11 -> -4.1706852e-05 | E103: =E57-E11 -> 0.0012437538 | F103: =F57-F11 -> 0.0008045898 | G103: =G57-G11 -> 0.0009421142 | H103: =H57-H11 -> 0.00088195987 | I103: =I57-I11 -> 0.14038842 | ... AQ103: =AQ57-AQ11 -> -0.00011090778
A104: ISIC 17T18 | B104: =B58-B12 -> 0.00064694377 | C104: =C58-C12 -> -0.00037473797 | D104: =D58-D12 -> -0.00033742442 | E104: =E58-E12 -> 0.0030029578 | F104: =F58-F12 -> 0.0029897584 | G104: =G58-G12 -> 0.018110361 | H104: =H58-H12 -> 0.010128047 | I104: =I58-I12 -> 0.013490179 | ... AQ104: =AQ58-AQ12 -> -9.2671482e-05
A105: ISIC 19 | B105: =B59-B13 -> 0.018643731 | C105: =C59-C13 -> -0.0060468052 | D105: =D59-D13 -> -0.0034710816 | E105: =E59-E13 -> 0.035561019 | F105: =F59-F13 -> 0.031890966 | G105: =G59-G13 -> 0.0026557277 | H105: =H59-H13 -> 0.0078676603 | I105: =I59-I13 -> 0.0067685501 | ... AQ105: =AQ59-AQ13 -> 0.00040621075
A106: ISIC 20 | B106: =B60-B14 -> 0.022851053 | C106: =C60-C14 -> 0.013675819 | D106: =D60-D14 -> 0.018568658 | E106: =E60-E14 -> 0.023966321 | F106: =F60-F14 -> 0.018822956 | G106: =G60-G14 -> 0.009087343 | H106: =H60-H14 -> 0.040714043 | I106: =I60-I14 -> 0.045554823 | ... AQ106: =AQ60-AQ14 -> -0.0020722259
A107: ISIC 21 | B107: =B61-B15 -> -0.00052829251 | C107: =C61-C15 -> -0.00028951463 | D107: =D61-D15 -> -7.5703313e-05 | E107: =E61-E15 -> 0.00080954795 | F107: =F61-F15 -> 0.00076954258 | G107: =G61-G15 -> 0.001888669 | H107: =H61-H15 -> 0.0030881688 | I107: =I61-I15 -> 0.0016225264 | ... AQ107: =AQ61-AQ15 -> -7.4233695e-07
... A137: ISIC 97T98 | B137: =B91-B45 -> 2.8673235e-07 | C137: =C91-C45 -> 7.3707499e-05 | D137: =D91-D45 -> 4.005262e-06 | E137: =E91-E45 -> 3.1892153e-07 | F137: =F91-F45 -> 2.6319154e-07 | G137: =G91-G45 -> 1.2002279e-07 | H137: =H91-H45 -> 5.0509416e-07 | I137: =I91-I45 -> 5.6389325e-07 | ... AQ137: =AQ91-AQ45 -> -1.0210422e-07
A139: Standard Input Output Matrix
B141: ISIC 01T03 | C141: ISIC 05 | D141: ISIC 06 | E141: ISIC 07T08 | F141: ISIC 09 | G141: ISIC 10T12 | H141: ISIC 13T15 | I141: ISIC 16 | J141: ISIC 17T18 | K141: ISIC 19 | L141: ISIC 20 | M141: ISIC 21 | N141: ISIC 22 | O141: ISIC 231 | P141: ISIC 239 | Q141: ISIC 241 | R141: ISIC 242 | S141: ISIC 25 | T141: ISIC 26 | U141: ISIC 27 | V141: ISIC 28 | W141: ISIC 29 | X141: ISIC 30 | Y141: ISIC 31T33 | Z141: ISIC 351 | AA141: ISIC 352T353 | AB141: ISIC 36T39 | AC141: ISIC 41T43 | AD141: ISIC 45T47 | AE141: ISIC 49T53 | AF141: ISIC 55T56 | AG141: ISIC 58T60 | AH141: ISIC 61 | AI141: ISIC 62T63 | AJ141: ISIC 64T66 | AK141: ISIC 68 | AL141: ISIC 69T82 | AM141: ISIC 84 | AN141: ISIC 85 | AO141: ISIC 86T88 | AP141: ISIC 90T96 | AQ141: ISIC 97T98
A142: ISIC 01T03 | B142: =IF(B96*BObIC!B$2>0,B96*BObIC!B$2,0) -> 3.4677403e+09 | C142: =IF(C96*BObIC!C$2>0,C96*BObIC!C$2,0) -> 0 | D142: =IF(D96*BObIC!D$2>0,D96*BObIC!D$2,0) -> 0 | E142: =IF(E96*BObIC!E$2>0,E96*BObIC!E$2,0) -> 0 | F142: =IF(F96*BObIC!F$2>0,F96*BObIC!F$2,0) -> 0 | G142: =IF(G96*BObIC!G$2>0,G96*BObIC!G$2,0) -> 2.6863467e+10 | H142: =IF(H96*BObIC!H$2>0,H96*BObIC!H$2,0) -> 1.1484383e+09 | I142: =IF(I96*BObIC!I$2>0,I96*BObIC!I$2,0) -> 7.6651536e+08 | ... AQ142: =IF(AQ96*BObIC!AQ$2>0,AQ96*BObIC!AQ$2,0) -> 150250.65
A143: ISIC 05 | B143: =IF(B97*BObIC!B$2>0,B97*BObIC!B$2,0) -> 0 | C143: =IF(C97*BObIC!C$2>0,C97*BObIC!C$2,0) -> 0 | D143: =IF(D97*BObIC!D$2>0,D97*BObIC!D$2,0) -> 0 | E143: =IF(E97*BObIC!E$2>0,E97*BObIC!E$2,0) -> 0 | F143: =IF(F97*BObIC!F$2>0,F97*BObIC!F$2,0) -> 0 | G143: =IF(G97*BObIC!G$2>0,G97*BObIC!G$2,0) -> 0 | H143: =IF(H97*BObIC!H$2>0,H97*BObIC!H$2,0) -> 0 | I143: =IF(I97*BObIC!I$2>0,I97*BObIC!I$2,0) -> 0 | ... AQ143: =IF(AQ97*BObIC!AQ$2>0,AQ97*BObIC!AQ$2,0) -> 746183.36
A144: ISIC 06 | B144: =IF(B98*BObIC!B$2>0,B98*BObIC!B$2,0) -> 0 | C144: =IF(C98*BObIC!C$2>0,C98*BObIC!C$2,0) -> 0 | D144: =IF(D98*BObIC!D$2>0,D98*BObIC!D$2,0) -> 0 | E144: =IF(E98*BObIC!E$2>0,E98*BObIC!E$2,0) -> 0 | F144: =IF(F98*BObIC!F$2>0,F98*BObIC!F$2,0) -> 0 | G144: =IF(G98*BObIC!G$2>0,G98*BObIC!G$2,0) -> 0 | H144: =IF(H98*BObIC!H$2>0,H98*BObIC!H$2,0) -> 0 | I144: =IF(I98*BObIC!I$2>0,I98*BObIC!I$2,0) -> 0 | ... AQ144: =IF(AQ98*BObIC!AQ$2>0,AQ98*BObIC!AQ$2,0) -> 876031.84
A145: ISIC 07T08 | B145: =IF(B99*BObIC!B$2>0,B99*BObIC!B$2,0) -> 0 | C145: =IF(C99*BObIC!C$2>0,C99*BObIC!C$2,0) -> 0 | D145: =IF(D99*BObIC!D$2>0,D99*BObIC!D$2,0) -> 0 | E145: =IF(E99*BObIC!E$2>0,E99*BObIC!E$2,0) -> 4998865.7 | F145: =IF(F99*BObIC!F$2>0,F99*BObIC!F$2,0) -> 125502.79 | G145: =IF(G99*BObIC!G$2>0,G99*BObIC!G$2,0) -> 57092849 | H145: =IF(H99*BObIC!H$2>0,H99*BObIC!H$2,0) -> 17030883 | I145: =IF(I99*BObIC!I$2>0,I99*BObIC!I$2,0) -> 2344524.2 | ... AQ145: =IF(AQ99*BObIC!AQ$2>0,AQ99*BObIC!AQ$2,0) -> 0
A146: ISIC 09 | B146: =IF(B100*BObIC!B$2>0,B100*BObIC!B$2,0) -> 0 | C146: =IF(C100*BObIC!C$2>0,C100*BObIC!C$2,0) -> 163.78194 | D146: =IF(D100*BObIC!D$2>0,D100*BObIC!D$2,0) -> 53.065989 | E146: =IF(E100*BObIC!E$2>0,E100*BObIC!E$2,0) -> 318274.1 | F146: =IF(F100*BObIC!F$2>0,F100*BObIC!F$2,0) -> 3926.8186 | G146: =IF(G100*BObIC!G$2>0,G100*BObIC!G$2,0) -> 0 | H146: =IF(H100*BObIC!H$2>0,H100*BObIC!H$2,0) -> 0 | I146: =IF(I100*BObIC!I$2>0,I100*BObIC!I$2,0) -> 0 | ... AQ146: =IF(AQ100*BObIC!AQ$2>0,AQ100*BObIC!AQ$2,0) -> 0
A147: ISIC 10T12 | B147: =IF(B101*BObIC!B$2>0,B101*BObIC!B$2,0) -> 4.9970334e+09 | C147: =IF(C101*BObIC!C$2>0,C101*BObIC!C$2,0) -> 0 | D147: =IF(D101*BObIC!D$2>0,D101*BObIC!D$2,0) -> 0 | E147: =IF(E101*BObIC!E$2>0,E101*BObIC!E$2,0) -> 11836772 | F147: =IF(F101*BObIC!F$2>0,F101*BObIC!F$2,0) -> 41707.774 | G147: =IF(G101*BObIC!G$2>0,G101*BObIC!G$2,0) -> 1.3429067e+10 | H147: =IF(H101*BObIC!H$2>0,H101*BObIC!H$2,0) -> 7.9090463e+08 | I147: =IF(I101*BObIC!I$2>0,I101*BObIC!I$2,0) -> 0 | ... AQ147: =IF(AQ101*BObIC!AQ$2>0,AQ101*BObIC!AQ$2,0) -> 416069.77
A148: ISIC 13T15 | B148: =IF(B102*BObIC!B$2>0,B102*BObIC!B$2,0) -> 2.9753283e+08 | C148: =IF(C102*BObIC!C$2>0,C102*BObIC!C$2,0) -> 0 | D148: =IF(D102*BObIC!D$2>0,D102*BObIC!D$2,0) -> 0 | E148: =IF(E102*BObIC!E$2>0,E102*BObIC!E$2,0) -> 21444099 | F148: =IF(F102*BObIC!F$2>0,F102*BObIC!F$2,0) -> 82083.403 | G148: =IF(G102*BObIC!G$2>0,G102*BObIC!G$2,0) -> 3.8858296e+08 | H148: =IF(H102*BObIC!H$2>0,H102*BObIC!H$2,0) -> 1.3404345e+10 | I148: =IF(I102*BObIC!I$2>0,I102*BObIC!I$2,0) -> 58364451 | ... AQ148: =IF(AQ102*BObIC!AQ$2>0,AQ102*BObIC!AQ$2,0) -> 0
A149: ISIC 16 | B149: =IF(B103*BObIC!B$2>0,B103*BObIC!B$2,0) -> 50493521 | C149: =IF(C103*BObIC!C$2>0,C103*BObIC!C$2,0) -> 1020088.2 | D149: =IF(D103*BObIC!D$2>0,D103*BObIC!D$2,0) -> 0 | E149: =IF(E103*BObIC!E$2>0,E103*BObIC!E$2,0) -> 4111774.3 | F149: =IF(F103*BObIC!F$2>0,F103*BObIC!F$2,0) -> 16107.888 | G149: =IF(G103*BObIC!G$2>0,G103*BObIC!G$2,0) -> 96979968 | H149: =IF(H103*BObIC!H$2>0,H103*BObIC!H$2,0) -> 56448024 | I149: =IF(I103*BObIC!I$2>0,I103*BObIC!I$2,0) -> 1.0129572e+09 | ... AQ149: =IF(AQ103*BObIC!AQ$2>0,AQ103*BObIC!AQ$2,0) -> 0
A150: ISIC 17T18 | B150: =IF(B104*BObIC!B$2>0,B104*BObIC!B$2,0) -> 29012861 | C150: =IF(C104*BObIC!C$2>0,C104*BObIC!C$2,0) -> 0 | D150: =IF(D104*BObIC!D$2>0,D104*BObIC!D$2,0) -> 0 | E150: =IF(E104*BObIC!E$2>0,E104*BObIC!E$2,0) -> 9927595.3 | F150: =IF(F104*BObIC!F$2>0,F104*BObIC!F$2,0) -> 59854.963 | G150: =IF(G104*BObIC!G$2>0,G104*BObIC!G$2,0) -> 1.8642562e+09 | H150: =IF(H104*BObIC!H$2>0,H104*BObIC!H$2,0) -> 6.4822475e+08 | I150: =IF(I104*BObIC!I$2>0,I104*BObIC!I$2,0) -> 97336904 | ... AQ150: =IF(AQ104*BObIC!AQ$2>0,AQ104*BObIC!AQ$2,0) -> 0
A151: ISIC 19 | B151: =IF(B105*BObIC!B$2>0,B105*BObIC!B$2,0) -> 8.3609736e+08 | C151: =IF(C105*BObIC!C$2>0,C105*BObIC!C$2,0) -> 0 | D151: =IF(D105*BObIC!D$2>0,D105*BObIC!D$2,0) -> 0 | E151: =IF(E105*BObIC!E$2>0,E105*BObIC!E$2,0) -> 1.1756256e+08 | F151: =IF(F105*BObIC!F$2>0,F105*BObIC!F$2,0) -> 638457.14 | G151: =IF(G105*BObIC!G$2>0,G105*BObIC!G$2,0) -> 2.7337703e+08 | H151: =IF(H105*BObIC!H$2>0,H105*BObIC!H$2,0) -> 5.0355338e+08 | I151: =IF(I105*BObIC!I$2>0,I105*BObIC!I$2,0) -> 48837728 | ... AQ151: =IF(AQ105*BObIC!AQ$2>0,AQ105*BObIC!AQ$2,0) -> 743850.28
A152: ISIC 20 | B152: =IF(B106*BObIC!B$2>0,B106*BObIC!B$2,0) -> 1.0247791e+09 | C152: =IF(C106*BObIC!C$2>0,C106*BObIC!C$2,0) -> 3587172.4 | D152: =IF(D106*BObIC!D$2>0,D106*BObIC!D$2,0) -> 2760335.4 | E152: =IF(E106*BObIC!E$2>0,E106*BObIC!E$2,0) -> 79231195 | F152: =IF(F106*BObIC!F$2>0,F106*BObIC!F$2,0) -> 376835.57 | G152: =IF(G106*BObIC!G$2>0,G106*BObIC!G$2,0) -> 9.3543886e+08 | H152: =IF(H106*BObIC!H$2>0,H106*BObIC!H$2,0) -> 2.6058184e+09 | I152: =IF(I106*BObIC!I$2>0,I106*BObIC!I$2,0) -> 3.2869582e+08 | ... AQ152: =IF(AQ106*BObIC!AQ$2>0,AQ106*BObIC!AQ$2,0) -> 0
A153: ISIC 21 | B153: =IF(B107*BObIC!B$2>0,B107*BObIC!B$2,0) -> 0 | C153: =IF(C107*BObIC!C$2>0,C107*BObIC!C$2,0) -> 0 | D153: =IF(D107*BObIC!D$2>0,D107*BObIC!D$2,0) -> 0 | E153: =IF(E107*BObIC!E$2>0,E107*BObIC!E$2,0) -> 2676316.1 | F153: =IF(F107*BObIC!F$2>0,F107*BObIC!F$2,0) -> 15406.242 | G153: =IF(G107*BObIC!G$2>0,G107*BObIC!G$2,0) -> 1.9441704e+08 | H153: =IF(H107*BObIC!H$2>0,H107*BObIC!H$2,0) -> 1.9765188e+08 | I153: =IF(I107*BObIC!I$2>0,I107*BObIC!I$2,0) -> 11707161 | ... AQ153: =IF(AQ107*BObIC!AQ$2>0,AQ107*BObIC!AQ$2,0) -> 0
... A183: ISIC 97T98 | B183: =IF(B137*BObIC!B$2>0,B137*BObIC!B$2,0) -> 12858.808 | C183: =IF(C137*BObIC!C$2>0,C137*BObIC!C$2,0) -> 19333.505 | D183: =IF(D137*BObIC!D$2>0,D137*BObIC!D$2,0) -> 595.40472 | E183: =IF(E137*BObIC!E$2>0,E137*BObIC!E$2,0) -> 1054.3351 | F183: =IF(F137*BObIC!F$2>0,F137*BObIC!F$2,0) -> 5.2690947 | G183: =IF(G137*BObIC!G$2>0,G137*BObIC!G$2,0) -> 12354.984 | H183: =IF(H137*BObIC!H$2>0,H137*BObIC!H$2,0) -> 32327.511 | I183: =IF(I137*BObIC!I$2>0,I137*BObIC!I$2,0) -> 4068.7097 | ... AQ183: =IF(AQ137*BObIC!AQ$2>0,AQ137*BObIC!AQ$2,0) -> 0

Sheet SIOM
A1: *Note for CEA: This table is mostly complete, but is just missing values for some of the orange highlighted boxes. You can copy the method used in the first orange box (cells D4:E5) to fill out the others. Once you've done that, the FoGPbEaIC-isic tab will correctly reflect the share by entity.
B2: Matching EPS Industry | C2: D01T03: Agriculture, forestry and fishing | D2: coal mining 05 | E2: oil and gas extraction 06 | F2: D07T08: Mining and quarrying of non-energy producing products | G2: D09: Mining support service activities | H2: D10T12: Food products, beverages and tobacco | I2: D13T15: Textiles, wearing apparel, leather and related products | J2: D16: Wood and products of wood and cork | K2: D17T18: Paper products and printing | L2: D19: Coke and refined petroleum products | M2: chemicals 20 | N2: pharmaceuticals | O2: D22: Rubber and plastic products | P2: glass and glass products 231 | Q2: cement and other nonmetallic minerals 239 | R2: iron and steel 241 | S2: other metals 242 | T2: D25: Fabricated metal products | U2: D26: Computer, electronic and optical products | V2: D27: Electrical equipment | W2: D28: Machinery and equipment, nec | X2: D29: Motor vehicles, trailers and semi-trailers | Y2: D30: Other transport equipment | Z2: D31T33: Other manufacturing; repair and installation of machinery and equipment | AA2: electricity | AB2: energy pipelines and gas processing 352T353 | AC2: water and waste 36T39 | AD2: D41T43: Construction | AE2: D45T47: Wholesale and retail trade; repair of motor vehicles | AF2: D49T53: Transportation and storage | AG2: D55T56: Accomodation and food services | AH2: D58T60: Publishing, audiovisual and broadcasting activities | AI2: D61: Telecommunications | AJ2: D62T63: IT and other information services | AK2: D64T66: Financial and insurance activities | AL2: D68: Real estate activities | AM2: D69T82: Other business sector services | AN2: D84: Public admin. and defence; compulsory social security | AO2: D85: Education | AP2: D86T88: Human health and social work | AQ2: D90T96: Arts, entertainment, recreation and other service activities | AR2: D97T98: Private households with employed persons
A3: D01T03: Agriculture, forestry and fishing | B3: agriculture and forestry 01T03 | C3: ='OECD TTL - 2018'!C9 -> 4722.3 | D3: ='OECD TTL - 2018'!$D9*'SIOM from DLIM'!C142/SUM('SIOM from DLIM'!$C142:$D142) -> #DIV/0! | E3: ='OECD TTL - 2018'!$D9*'SIOM from DLIM'!D142/SUM('SIOM from DLIM'!$C142:$D142) -> #DIV/0! | F3: ='OECD TTL - 2018'!E9 -> 3.5 | G3: ='OECD TTL - 2018'!F9 -> 0 | H3: ='OECD TTL - 2018'!G9 -> 27898.7 | I3: ='OECD TTL - 2018'!H9 -> 1366.4 | J3: ='OECD TTL - 2018'!I9 -> 939.5 | K3: ='OECD TTL - 2018'!J9 -> 502.4 | L3: ='OECD TTL - 2018'!K9 -> 65.5 | M3: ='OECD TTL - 2018'!$L9*'SIOM from DLIM'!L142/SUM('SIOM from DLIM'!$L142:$M142) -> #DIV/0! | N3: ='OECD TTL - 2018'!$L9*'SIOM from DLIM'!M142/SUM('SIOM from DLIM'!$L142:$M142) -> #DIV/0! | O3: ='OECD TTL - 2018'!M9 -> 591.8 | P3: ='OECD TTL - 2018'!$N9*'SIOM from DLIM'!O142/SUM('SIOM from DLIM'!$O142:$P142) -> #DIV/0! | Q3: ='OECD TTL - 2018'!$N9*'SIOM from DLIM'!P142/SUM('SIOM from DLIM'!$O142:$P142) -> #DIV/0! | R3: ='OECD TTL - 2018'!$O9*'SIOM from DLIM'!Q142/SUM('SIOM from DLIM'!$Q142:$R142) -> #DIV/0! | S3: ='OECD TTL - 2018'!$O9*'SIOM from DLIM'!R142/SUM('SIOM from DLIM'!$Q142:$R142) -> #DIV/0! | T3: ='OECD TTL - 2018'!P9 -> 31.8 | U3: ='OECD TTL - 2018'!Q9 -> 21.2 | V3: ='OECD TTL - 2018'!R9 -> 21.4 | W3: ='OECD TTL - 2018'!S9 -> 30.1 | X3: ='OECD TTL - 2018'!T9 -> 19 | Y3: ='OECD TTL - 2018'!U9 -> 34.1 | Z3: ='OECD TTL - 2018'!V9 -> 124.8 | AA3: ='OECD TTL - 2018'!$W9*'SIOM from DLIM'!Z142/SUM('SIOM from DLIM'!$Z142:$AB142) -> #DIV/0! | AB3: ='OECD TTL - 2018'!$W9*'SIOM from DLIM'!AA142/SUM('SIOM from DLIM'!$Z142:$AB142) -> #DIV/0! | AC3: ='OECD TTL - 2018'!$W9*'SIOM from DLIM'!AB142/SUM('SIOM from DLIM'!$Z142:$AB142) -> #DIV/0! | AD3: ='OECD TTL - 2018'!X9 -> 313.8 | AE3: ='OECD TTL - 2018'!Y9 -> 1580.4 | AF3: ='OECD TTL - 2018'!Z9 -> 146.3 | AG3: ='OECD TTL - 2018'!AA9 -> 3624.3 | AH3: ='OECD TTL - 2018'!AB9 -> 30.5 | AI3: ='OECD TTL - 2018'!AC9 -> 3.1 | AJ3: ='OECD TTL - 2018'!AD9 -> 14 | AK3: ='OECD TTL - 2018'!AE9 -> 24 | ... AR3: ='OECD TTL - 2018'!AL9 -> 0
A4: coal mining 05 | B4: coal mining 05 | C4: ='OECD TTL - 2018'!C$10*'SIOM from DLIM'!B143/SUM('SIOM from DLIM'!B$143:B$144) -> #DIV/0! | D4: ='OECD TTL - 2018'!$D$10*'SIOM from DLIM'!C143/SUM('SIOM from DLIM'!$C$143:$D$144) -> #DIV/0! | E4: ='OECD TTL - 2018'!$D$10*'SIOM from DLIM'!D143/SUM('SIOM from DLIM'!$C$143:$D$144) -> #DIV/0! | F4: ='OECD TTL - 2018'!E$10*'SIOM from DLIM'!D143/SUM('SIOM from DLIM'!D$143:D$144) -> #DIV/0! | G4: ='OECD TTL - 2018'!F$10*'SIOM from DLIM'!E143/SUM('SIOM from DLIM'!E$143:E$144) -> #DIV/0! | H4: ='OECD TTL - 2018'!G$10*'SIOM from DLIM'!F143/SUM('SIOM from DLIM'!F$143:F$144) -> #DIV/0! | I4: ='OECD TTL - 2018'!H$10*'SIOM from DLIM'!G143/SUM('SIOM from DLIM'!G$143:G$144) -> #DIV/0! | J4: ='OECD TTL - 2018'!I$10*'SIOM from DLIM'!H143/SUM('SIOM from DLIM'!H$143:H$144) -> #DIV/0! | K4: ='OECD TTL - 2018'!J$10*'SIOM from DLIM'!I143/SUM('SIOM from DLIM'!I$143:I$144) -> #DIV/0! | L4: ='OECD TTL - 2018'!K$10*'SIOM from DLIM'!J143/SUM('SIOM from DLIM'!J$143:J$144) -> #DIV/0! | M4: ='OECD TTL - 2018'!$L$10*'SIOM from DLIM'!L143/SUM('SIOM from DLIM'!$L$143:$M$144) -> 2146.7735 | N4: ='OECD TTL - 2018'!$L$10*'SIOM from DLIM'!M143/SUM('SIOM from DLIM'!$L$143:$M$144) -> 18.500824 | O4: ='OECD TTL - 2018'!M$10*'SIOM from DLIM'!L143/SUM('SIOM from DLIM'!L$143:L$144) -> 117.75122 | P4: ='OECD TTL - 2018'!$N$10*'SIOM from DLIM'!O143/SUM('SIOM from DLIM'!$O$143:$P$144) -> #DIV/0! | Q4: ='OECD TTL - 2018'!$N$10*'SIOM from DLIM'!P143/SUM('SIOM from DLIM'!$O$143:$P$144) -> #DIV/0! | R4: ='OECD TTL - 2018'!$O$10*'SIOM from DLIM'!Q143/SUM('SIOM from DLIM'!$Q$143:$R$144) -> 3659.1 | S4: ='OECD TTL - 2018'!$O$10*'SIOM from DLIM'!R143/SUM('SIOM from DLIM'!$Q$143:$R$144) -> 0 | T4: ='OECD TTL - 2018'!P$10*'SIOM from DLIM'!O143/SUM('SIOM from DLIM'!O$143:O$144) -> #DIV/0! | U4: ='OECD TTL - 2018'!Q$10*'SIOM from DLIM'!P143/SUM('SIOM from DLIM'!P$143:P$144) -> #DIV/0! | V4: ='OECD TTL - 2018'!R$10*'SIOM from DLIM'!Q143/SUM('SIOM from DLIM'!Q$143:Q$144) -> 49.2 | W4: ='OECD TTL - 2018'!S$10*'SIOM from DLIM'!R143/SUM('SIOM from DLIM'!R$143:R$144) -> #DIV/0! | X4: ='OECD TTL - 2018'!T$10*'SIOM from DLIM'!S143/SUM('SIOM from DLIM'!S$143:S$144) -> #DIV/0! | Y4: ='OECD TTL - 2018'!U$10*'SIOM from DLIM'!T143/SUM('SIOM from DLIM'!T$143:T$144) -> #DIV/0! | Z4: ='OECD TTL - 2018'!V$10*'SIOM from DLIM'!U143/SUM('SIOM from DLIM'!U$143:U$144) -> #DIV/0! | AA4: ='OECD TTL - 2018'!$W$10*'SIOM from DLIM'!Z143/SUM('SIOM from DLIM'!$Z$143:$AB$144) -> #DIV/0! | AB4: ='OECD TTL - 2018'!$W$10*'SIOM from DLIM'!AA143/SUM('SIOM from DLIM'!$Z$143:$AB$144) -> #DIV/0! | AC4: ='OECD TTL - 2018'!$W$10*'SIOM from DLIM'!AB143/SUM('SIOM from DLIM'!$Z$143:$AB$144) -> #DIV/0! | AD4: ='OECD TTL - 2018'!X$10*'SIOM from DLIM'!W143/SUM('SIOM from DLIM'!W$143:W$144) -> #DIV/0! | AE4: ='OECD TTL - 2018'!Y$10*'SIOM from DLIM'!X143/SUM('SIOM from DLIM'!X$143:X$144) -> #DIV/0! | AF4: ='OECD TTL - 2018'!Z$10*'SIOM from DLIM'!Y143/SUM('SIOM from DLIM'!Y$143:Y$144) -> 0 | AG4: ='OECD TTL - 2018'!AA$10*'SIOM from DLIM'!Z143/SUM('SIOM from DLIM'!Z$143:Z$144) -> #DIV/0! | AH4: ='OECD TTL - 2018'!AB$10*'SIOM from DLIM'!AA143/SUM('SIOM from DLIM'!AA$143:AA$144) -> #DIV/0! | AI4: ='OECD TTL - 2018'!AC$10*'SIOM from DLIM'!AB143/SUM('SIOM from DLIM'!AB$143:AB$144) -> #DIV/0! | AJ4: ='OECD TTL - 2018'!AD$10*'SIOM from DLIM'!AC143/SUM('SIOM from DLIM'!AC$143:AC$144) -> #DIV/0! | AK4: ='OECD TTL - 2018'!AE$10*'SIOM from DLIM'!AD143/SUM('SIOM from DLIM'!AD$143:AD$144) -> #DIV/0! | ... AR4: ='OECD TTL - 2018'!AL$10*'SIOM from DLIM'!AK143/SUM('SIOM from DLIM'!AK$143:AK$144) -> #DIV/0!
A5: oil and gas extraction 06 | B5: oil and gas extraction 06 | C5: ='OECD TTL - 2018'!C$10*'SIOM from DLIM'!B144/SUM('SIOM from DLIM'!B$143:B$144) -> #DIV/0! | D5: ='OECD TTL - 2018'!$D$10*'SIOM from DLIM'!C144/SUM('SIOM from DLIM'!$C$143:$D$144) -> #DIV/0! | E5: ='OECD TTL - 2018'!$D$10*'SIOM from DLIM'!D144/SUM('SIOM from DLIM'!$C$143:$D$144) -> #DIV/0! | F5: ='OECD TTL - 2018'!E$10*'SIOM from DLIM'!D144/SUM('SIOM from DLIM'!D$143:D$144) -> #DIV/0! | G5: ='OECD TTL - 2018'!F$10*'SIOM from DLIM'!E144/SUM('SIOM from DLIM'!E$143:E$144) -> #DIV/0! | H5: ='OECD TTL - 2018'!G$10*'SIOM from DLIM'!F144/SUM('SIOM from DLIM'!F$143:F$144) -> #DIV/0! | I5: ='OECD TTL - 2018'!H$10*'SIOM from DLIM'!G144/SUM('SIOM from DLIM'!G$143:G$144) -> #DIV/0! | J5: ='OECD TTL - 2018'!I$10*'SIOM from DLIM'!H144/SUM('SIOM from DLIM'!H$143:H$144) -> #DIV/0! | K5: ='OECD TTL - 2018'!J$10*'SIOM from DLIM'!I144/SUM('SIOM from DLIM'!I$143:I$144) -> #DIV/0! | L5: ='OECD TTL - 2018'!K$10*'SIOM from DLIM'!J144/SUM('SIOM from DLIM'!J$143:J$144) -> #DIV/0! | M5: ='OECD TTL - 2018'!$L$10*'SIOM from DLIM'!L144/SUM('SIOM from DLIM'!$L$143:$M$144) -> 2146.7289 | N5: ='OECD TTL - 2018'!$L$10*'SIOM from DLIM'!M144/SUM('SIOM from DLIM'!$L$143:$M$144) -> 18.396815 | O5: ='OECD TTL - 2018'!M$10*'SIOM from DLIM'!L144/SUM('SIOM from DLIM'!L$143:L$144) -> 117.74878 | P5: ='OECD TTL - 2018'!$N$10*'SIOM from DLIM'!O144/SUM('SIOM from DLIM'!$O$143:$P$144) -> #DIV/0! | Q5: ='OECD TTL - 2018'!$N$10*'SIOM from DLIM'!P144/SUM('SIOM from DLIM'!$O$143:$P$144) -> #DIV/0! | R5: ='OECD TTL - 2018'!$O$10*'SIOM from DLIM'!Q144/SUM('SIOM from DLIM'!$Q$143:$R$144) -> 0 | S5: ='OECD TTL - 2018'!$O$10*'SIOM from DLIM'!R144/SUM('SIOM from DLIM'!$Q$143:$R$144) -> 0 | T5: ='OECD TTL - 2018'!P$10*'SIOM from DLIM'!O144/SUM('SIOM from DLIM'!O$143:O$144) -> #DIV/0! | U5: ='OECD TTL - 2018'!Q$10*'SIOM from DLIM'!P144/SUM('SIOM from DLIM'!P$143:P$144) -> #DIV/0! | V5: ='OECD TTL - 2018'!R$10*'SIOM from DLIM'!Q144/SUM('SIOM from DLIM'!Q$143:Q$144) -> 0 | W5: ='OECD TTL - 2018'!S$10*'SIOM from DLIM'!R144/SUM('SIOM from DLIM'!R$143:R$144) -> #DIV/0! | X5: ='OECD TTL - 2018'!T$10*'SIOM from DLIM'!S144/SUM('SIOM from DLIM'!S$143:S$144) -> #DIV/0! | Y5: ='OECD TTL - 2018'!U$10*'SIOM from DLIM'!T144/SUM('SIOM from DLIM'!T$143:T$144) -> #DIV/0! | Z5: ='OECD TTL - 2018'!V$10*'SIOM from DLIM'!U144/SUM('SIOM from DLIM'!U$143:U$144) -> #DIV/0! | AA5: ='OECD TTL - 2018'!$W$10*'SIOM from DLIM'!Z144/SUM('SIOM from DLIM'!$Z$143:$AB$144) -> #DIV/0! | AB5: ='OECD TTL - 2018'!$W$10*'SIOM from DLIM'!AA144/SUM('SIOM from DLIM'!$Z$143:$AB$144) -> #DIV/0! | AC5: ='OECD TTL - 2018'!$W$10*'SIOM from DLIM'!AB144/SUM('SIOM from DLIM'!$Z$143:$AB$144) -> #DIV/0! | AD5: ='OECD TTL - 2018'!X$10*'SIOM from DLIM'!W144/SUM('SIOM from DLIM'!W$143:W$144) -> #DIV/0! | AE5: ='OECD TTL - 2018'!Y$10*'SIOM from DLIM'!X144/SUM('SIOM from DLIM'!X$143:X$144) -> #DIV/0! | AF5: ='OECD TTL - 2018'!Z$10*'SIOM from DLIM'!Y144/SUM('SIOM from DLIM'!Y$143:Y$144) -> 293 | AG5: ='OECD TTL - 2018'!AA$10*'SIOM from DLIM'!Z144/SUM('SIOM from DLIM'!Z$143:Z$144) -> #DIV/0! | AH5: ='OECD TTL - 2018'!AB$10*'SIOM from DLIM'!AA144/SUM('SIOM from DLIM'!AA$143:AA$144) -> #DIV/0! | AI5: ='OECD TTL - 2018'!AC$10*'SIOM from DLIM'!AB144/SUM('SIOM from DLIM'!AB$143:AB$144) -> #DIV/0! | AJ5: ='OECD TTL - 2018'!AD$10*'SIOM from DLIM'!AC144/SUM('SIOM from DLIM'!AC$143:AC$144) -> #DIV/0! | AK5: ='OECD TTL - 2018'!AE$10*'SIOM from DLIM'!AD144/SUM('SIOM from DLIM'!AD$143:AD$144) -> #DIV/0! | ... AR5: ='OECD TTL - 2018'!AL$10*'SIOM from DLIM'!AK144/SUM('SIOM from DLIM'!AK$143:AK$144) -> #DIV/0!
A6: D07T08: Mining and quarrying of non-energy producing products | B6: other mining and quarrying 07T08 | C6: ='OECD TTL - 2018'!C11 -> 13.4 | D6: ='OECD TTL - 2018'!$D11*'SIOM from DLIM'!C145/SUM('SIOM from DLIM'!$C145:$D145) -> #DIV/0! | E6: ='OECD TTL - 2018'!$D11*'SIOM from DLIM'!D145/SUM('SIOM from DLIM'!$C145:$D145) -> #DIV/0! | F6: ='OECD TTL - 2018'!E11 -> 34 | G6: ='OECD TTL - 2018'!F11 -> 0 | H6: ='OECD TTL - 2018'!G11 -> 14.9 | I6: ='OECD TTL - 2018'!H11 -> 6.7 | J6: ='OECD TTL - 2018'!I11 -> 2.1 | K6: ='OECD TTL - 2018'!J11 -> 25.5 | L6: ='OECD TTL - 2018'!K11 -> 515.3 | M6: ='OECD TTL - 2018'!$L11*'SIOM from DLIM'!L145/SUM('SIOM from DLIM'!$L145:$M145) -> 638.92552 | N6: ='OECD TTL - 2018'!$L11*'SIOM from DLIM'!M145/SUM('SIOM from DLIM'!$L145:$M145) -> 15.974483 | O6: ='OECD TTL - 2018'!M11 -> 18.5 | P6: ='OECD TTL - 2018'!$N11*'SIOM from DLIM'!O145/SUM('SIOM from DLIM'!$O145:$P145) -> 12.142329 | Q6: ='OECD TTL - 2018'!$N11*'SIOM from DLIM'!P145/SUM('SIOM from DLIM'!$O145:$P145) -> 739.45767 | R6: ='OECD TTL - 2018'!$O11*'SIOM from DLIM'!Q145/SUM('SIOM from DLIM'!$Q145:$R145) -> 7734.5181 | S6: ='OECD TTL - 2018'!$O11*'SIOM from DLIM'!R145/SUM('SIOM from DLIM'!$Q145:$R145) -> 1391.1819 | T6: ='OECD TTL - 2018'!P11 -> 449.9 | U6: ='OECD TTL - 2018'!Q11 -> 142.6 | V6: ='OECD TTL - 2018'!R11 -> 287 | W6: ='OECD TTL - 2018'!S11 -> 211.1 | X6: ='OECD TTL - 2018'!T11 -> 79.2 | Y6: ='OECD TTL - 2018'!U11 -> 77.1 | Z6: ='OECD TTL - 2018'!V11 -> 72.1 | AA6: ='OECD TTL - 2018'!$W11*'SIOM from DLIM'!Z145/SUM('SIOM from DLIM'!$Z145:$AB145) -> 0 | AB6: ='OECD TTL - 2018'!$W11*'SIOM from DLIM'!AA145/SUM('SIOM from DLIM'!$Z145:$AB145) -> 0 | AC6: ='OECD TTL - 2018'!$W11*'SIOM from DLIM'!AB145/SUM('SIOM from DLIM'!$Z145:$AB145) -> 115.3 | AD6: ='OECD TTL - 2018'!X11 -> 814.1 | AE6: ='OECD TTL - 2018'!Y11 -> 38.6 | AF6: ='OECD TTL - 2018'!Z11 -> 13.9 | AG6: ='OECD TTL - 2018'!AA11 -> 7.7 | AH6: ='OECD TTL - 2018'!AB11 -> 0.8 | AI6: ='OECD TTL - 2018'!AC11 -> 1.9 | AJ6: ='OECD TTL - 2018'!AD11 -> 1.4 | AK6: ='OECD TTL - 2018'!AE11 -> 2.2 | ... AR6: ='OECD TTL - 2018'!AL11 -> 0
A7: D09: Mining support service activities | C7: ='OECD TTL - 2018'!C12 -> 9.4 | D7: ='OECD TTL - 2018'!$D12*'SIOM from DLIM'!C146/SUM('SIOM from DLIM'!$C146:$D146) -> 0.6797563 | E7: ='OECD TTL - 2018'!$D12*'SIOM from DLIM'!D146/SUM('SIOM from DLIM'!$C146:$D146) -> 0.2202437 | F7: ='OECD TTL - 2018'!E12 -> 1.9 | G7: ='OECD TTL - 2018'!F12 -> 0 | H7: ='OECD TTL - 2018'!G12 -> 1.3 | I7: ='OECD TTL - 2018'!H12 -> 0.1 | J7: ='OECD TTL - 2018'!I12 -> 0.1 | K7: ='OECD TTL - 2018'!J12 -> 0.7 | L7: ='OECD TTL - 2018'!K12 -> 6.6 | M7: ='OECD TTL - 2018'!$L12*'SIOM from DLIM'!L146/SUM('SIOM from DLIM'!$L146:$M146) -> #DIV/0! | N7: ='OECD TTL - 2018'!$L12*'SIOM from DLIM'!M146/SUM('SIOM from DLIM'!$L146:$M146) -> #DIV/0! | O7: ='OECD TTL - 2018'!M12 -> 2.1 | P7: ='OECD TTL - 2018'!$N12*'SIOM from DLIM'!O146/SUM('SIOM from DLIM'!$O146:$P146) -> 0.9 | Q7: ='OECD TTL - 2018'!$N12*'SIOM from DLIM'!P146/SUM('SIOM from DLIM'!$O146:$P146) -> 0 | R7: ='OECD TTL - 2018'!$O12*'SIOM from DLIM'!Q146/SUM('SIOM from DLIM'!$Q146:$R146) -> 1.8880725 | S7: ='OECD TTL - 2018'!$O12*'SIOM from DLIM'!R146/SUM('SIOM from DLIM'!$Q146:$R146) -> 1.0119275 | T7: ='OECD TTL - 2018'!P12 -> 0.5 | U7: ='OECD TTL - 2018'!Q12 -> 0.4 | V7: ='OECD TTL - 2018'!R12 -> 0.2 | W7: ='OECD TTL - 2018'!S12 -> 1.5 | X7: ='OECD TTL - 2018'!T12 -> 0.3 | Y7: ='OECD TTL - 2018'!U12 -> 0.3 | Z7: ='OECD TTL - 2018'!V12 -> 0.3 | AA7: ='OECD TTL - 2018'!$W12*'SIOM from DLIM'!Z146/SUM('SIOM from DLIM'!$Z146:$AB146) -> 6.8496428 | AB7: ='OECD TTL - 2018'!$W12*'SIOM from DLIM'!AA146/SUM('SIOM from DLIM'!$Z146:$AB146) -> 1.7503572 | AC7: ='OECD TTL - 2018'!$W12*'SIOM from DLIM'!AB146/SUM('SIOM from DLIM'!$Z146:$AB146) -> 0 | AD7: ='OECD TTL - 2018'!X12 -> 16.8 | AE7: ='OECD TTL - 2018'!Y12 -> 0.3 | AF7: ='OECD TTL - 2018'!Z12 -> 1.2 | AG7: ='OECD TTL - 2018'!AA12 -> 0.2 | AH7: ='OECD TTL - 2018'!AB12 -> 0 | AI7: ='OECD TTL - 2018'!AC12 -> 0 | AJ7: ='OECD TTL - 2018'!AD12 -> 0.1 | AK7: ='OECD TTL - 2018'!AE12 -> 0.1 | ... AR7: ='OECD TTL - 2018'!AL12 -> 0
A8: D10T12: Food products, beverages and tobacco | B8: food beverage and tobacco 10T12 | C8: ='OECD TTL - 2018'!C13 -> 5960.6 | D8: ='OECD TTL - 2018'!$D13*'SIOM from DLIM'!C147/SUM('SIOM from DLIM'!$C147:$D147) -> #DIV/0! | E8: ='OECD TTL - 2018'!$D13*'SIOM from DLIM'!D147/SUM('SIOM from DLIM'!$C147:$D147) -> #DIV/0! | F8: ='OECD TTL - 2018'!E13 -> 2 | G8: ='OECD TTL - 2018'!F13 -> 0 | H8: ='OECD TTL - 2018'!G13 -> 24001.4 | I8: ='OECD TTL - 2018'!H13 -> 917.8 | J8: ='OECD TTL - 2018'!I13 -> 36.3 | K8: ='OECD TTL - 2018'!J13 -> 265.5 | L8: ='OECD TTL - 2018'!K13 -> 179.4 | M8: ='OECD TTL - 2018'!$L13*'SIOM from DLIM'!L147/SUM('SIOM from DLIM'!$L147:$M147) -> 2639.4413 | N8: ='OECD TTL - 2018'!$L13*'SIOM from DLIM'!M147/SUM('SIOM from DLIM'!$L147:$M147) -> 388.95867 | O8: ='OECD TTL - 2018'!M13 -> 200.2 | P8: ='OECD TTL - 2018'!$N13*'SIOM from DLIM'!O147/SUM('SIOM from DLIM'!$O147:$P147) -> #DIV/0! | Q8: ='OECD TTL - 2018'!$N13*'SIOM from DLIM'!P147/SUM('SIOM from DLIM'!$O147:$P147) -> #DIV/0! | R8: ='OECD TTL - 2018'!$O13*'SIOM from DLIM'!Q147/SUM('SIOM from DLIM'!$Q147:$R147) -> #DIV/0! | S8: ='OECD TTL - 2018'!$O13*'SIOM from DLIM'!R147/SUM('SIOM from DLIM'!$Q147:$R147) -> #DIV/0! | T8: ='OECD TTL - 2018'!P13 -> 69.1 | U8: ='OECD TTL - 2018'!Q13 -> 127.1 | V8: ='OECD TTL - 2018'!R13 -> 52.3 | W8: ='OECD TTL - 2018'!S13 -> 87.2 | X8: ='OECD TTL - 2018'!T13 -> 68.9 | Y8: ='OECD TTL - 2018'!U13 -> 104.1 | Z8: ='OECD TTL - 2018'!V13 -> 74.1 | AA8: ='OECD TTL - 2018'!$W13*'SIOM from DLIM'!Z147/SUM('SIOM from DLIM'!$Z147:$AB147) -> 0 | AB8: ='OECD TTL - 2018'!$W13*'SIOM from DLIM'!AA147/SUM('SIOM from DLIM'!$Z147:$AB147) -> 0 | AC8: ='OECD TTL - 2018'!$W13*'SIOM from DLIM'!AB147/SUM('SIOM from DLIM'!$Z147:$AB147) -> 247.6 | AD8: ='OECD TTL - 2018'!X13 -> 352.2 | AE8: ='OECD TTL - 2018'!Y13 -> 3094.6 | AF8: ='OECD TTL - 2018'!Z13 -> 228.5 | AG8: ='OECD TTL - 2018'!AA13 -> 23070.1 | AH8: ='OECD TTL - 2018'!AB13 -> 69.9 | AI8: ='OECD TTL - 2018'!AC13 -> 18.8 | AJ8: ='OECD TTL - 2018'!AD13 -> 49.5 | AK8: ='OECD TTL - 2018'!AE13 -> 120.9 | ... AR8: ='OECD TTL - 2018'!AL13 -> 0
A9: D13T15: Textiles, wearing apparel, leather and related products | B9: textiles apparel and leather 13T15 | C9: ='OECD TTL - 2018'!C14 -> 322.9 | D9: ='OECD TTL - 2018'!$D14*'SIOM from DLIM'!C148/SUM('SIOM from DLIM'!$C148:$D148) -> #DIV/0! | E9: ='OECD TTL - 2018'!$D14*'SIOM from DLIM'!D148/SUM('SIOM from DLIM'!$C148:$D148) -> #DIV/0! | F9: ='OECD TTL - 2018'!E14 -> 17.5 | G9: ='OECD TTL - 2018'!F14 -> 0.1 | H9: ='OECD TTL - 2018'!G14 -> 278.5 | I9: ='OECD TTL - 2018'!H14 -> 27189 | J9: ='OECD TTL - 2018'!I14 -> 123 | K9: ='OECD TTL - 2018'!J14 -> 437.2 | L9: ='OECD TTL - 2018'!K14 -> 170.3 | M9: ='OECD TTL - 2018'!$L14*'SIOM from DLIM'!L148/SUM('SIOM from DLIM'!$L148:$M148) -> 1335.0353 | N9: ='OECD TTL - 2018'!$L14*'SIOM from DLIM'!M148/SUM('SIOM from DLIM'!$L148:$M148) -> 277.36467 | O9: ='OECD TTL - 2018'!M14 -> 1806.9 | P9: ='OECD TTL - 2018'!$N14*'SIOM from DLIM'!O148/SUM('SIOM from DLIM'!$O148:$P148) -> 46.299451 | Q9: ='OECD TTL - 2018'!$N14*'SIOM from DLIM'!P148/SUM('SIOM from DLIM'!$O148:$P148) -> 254.60055 | R9: ='OECD TTL - 2018'!$O14*'SIOM from DLIM'!Q148/SUM('SIOM from DLIM'!$Q148:$R148) -> 255.3 | S9: ='OECD TTL - 2018'!$O14*'SIOM from DLIM'!R148/SUM('SIOM from DLIM'!$Q148:$R148) -> 0 | T9: ='OECD TTL - 2018'!P14 -> 435.8 | U9: ='OECD TTL - 2018'!Q14 -> 820.1 | V9: ='OECD TTL - 2018'!R14 -> 374.7 | W9: ='OECD TTL - 2018'!S14 -> 535.9 | X9: ='OECD TTL - 2018'!T14 -> 1843.1 | Y9: ='OECD TTL - 2018'!U14 -> 2469.4 | Z9: ='OECD TTL - 2018'!V14 -> 1606.6 | AA9: ='OECD TTL - 2018'!$W14*'SIOM from DLIM'!Z148/SUM('SIOM from DLIM'!$Z148:$AB148) -> 0 | AB9: ='OECD TTL - 2018'!$W14*'SIOM from DLIM'!AA148/SUM('SIOM from DLIM'!$Z148:$AB148) -> 0 | AC9: ='OECD TTL - 2018'!$W14*'SIOM from DLIM'!AB148/SUM('SIOM from DLIM'!$Z148:$AB148) -> 495 | AD9: ='OECD TTL - 2018'!X14 -> 1275.7 | AE9: ='OECD TTL - 2018'!Y14 -> 3146.4 | AF9: ='OECD TTL - 2018'!Z14 -> 791.9 | AG9: ='OECD TTL - 2018'!AA14 -> 808.3 | AH9: ='OECD TTL - 2018'!AB14 -> 420.7 | AI9: ='OECD TTL - 2018'!AC14 -> 97.4 | AJ9: ='OECD TTL - 2018'!AD14 -> 130.7 | AK9: ='OECD TTL - 2018'!AE14 -> 591.9 | ... AR9: ='OECD TTL - 2018'!AL14 -> 0
A10: D16: Wood and products of wood and cork | B10: wood products 16 | C10: ='OECD TTL - 2018'!C15 -> 42.8 | D10: ='OECD TTL - 2018'!$D15*'SIOM from DLIM'!C149/SUM('SIOM from DLIM'!$C149:$D149) -> 6.6 | E10: ='OECD TTL - 2018'!$D15*'SIOM from DLIM'!D149/SUM('SIOM from DLIM'!$C149:$D149) -> 0 | F10: ='OECD TTL - 2018'!E15 -> 4.7 | G10: ='OECD TTL - 2018'!F15 -> 0 | H10: ='OECD TTL - 2018'!G15 -> 52.2 | I10: ='OECD TTL - 2018'!H15 -> 57.3 | J10: ='OECD TTL - 2018'!I15 -> 1278.1 | K10: ='OECD TTL - 2018'!J15 -> 222.2 | L10: ='OECD TTL - 2018'!K15 -> 26 | M10: ='OECD TTL - 2018'!$L15*'SIOM from DLIM'!L149/SUM('SIOM from DLIM'!$L149:$M149) -> 50.081128 | N10: ='OECD TTL - 2018'!$L15*'SIOM from DLIM'!M149/SUM('SIOM from DLIM'!$L149:$M149) -> 154.21887 | O10: ='OECD TTL - 2018'!M15 -> 131.1 | P10: ='OECD TTL - 2018'!$N15*'SIOM from DLIM'!O149/SUM('SIOM from DLIM'!$O149:$P149) -> 61.310065 | Q10: ='OECD TTL - 2018'!$N15*'SIOM from DLIM'!P149/SUM('SIOM from DLIM'!$O149:$P149) -> 64.789935 | R10: ='OECD TTL - 2018'!$O15*'SIOM from DLIM'!Q149/SUM('SIOM from DLIM'!$Q149:$R149) -> 16.805467 | S10: ='OECD TTL - 2018'!$O15*'SIOM from DLIM'!R149/SUM('SIOM from DLIM'!$Q149:$R149) -> 29.294533 | T10: ='OECD TTL - 2018'!P15 -> 178.3 | U10: ='OECD TTL - 2018'!Q15 -> 136.9 | V10: ='OECD TTL - 2018'!R15 -> 82.6 | W10: ='OECD TTL - 2018'!S15 -> 127.5 | X10: ='OECD TTL - 2018'!T15 -> 219.5 | Y10: ='OECD TTL - 2018'!U15 -> 434.7 | Z10: ='OECD TTL - 2018'!V15 -> 1193.9 | AA10: ='OECD TTL - 2018'!$W15*'SIOM from DLIM'!Z149/SUM('SIOM from DLIM'!$Z149:$AB149) -> 77.841472 | AB10: ='OECD TTL - 2018'!$W15*'SIOM from DLIM'!AA149/SUM('SIOM from DLIM'!$Z149:$AB149) -> 0 | AC10: ='OECD TTL - 2018'!$W15*'SIOM from DLIM'!AB149/SUM('SIOM from DLIM'!$Z149:$AB149) -> 58.258528 | AD10: ='OECD TTL - 2018'!X15 -> 3074.2 | AE10: ='OECD TTL - 2018'!Y15 -> 252.4 | AF10: ='OECD TTL - 2018'!Z15 -> 47.8 | AG10: ='OECD TTL - 2018'!AA15 -> 60.3 | AH10: ='OECD TTL - 2018'!AB15 -> 26 | AI10: ='OECD TTL - 2018'!AC15 -> 8.4 | AJ10: ='OECD TTL - 2018'!AD15 -> 19.2 | AK10: ='OECD TTL - 2018'!AE15 -> 16.7 | ... AR10: ='OECD TTL - 2018'!AL15 -> 0
A11: D17T18: Paper products and printing | B11: pulp paper and printing 17T18 | C11: ='OECD TTL - 2018'!C16 -> 89.5 | D11: ='OECD TTL - 2018'!$D16*'SIOM from DLIM'!C150/SUM('SIOM from DLIM'!$C150:$D150) -> #DIV/0! | E11: ='OECD TTL - 2018'!$D16*'SIOM from DLIM'!D150/SUM('SIOM from DLIM'!$C150:$D150) -> #DIV/0! | F11: ='OECD TTL - 2018'!E16 -> 11.7 | G11: ='OECD TTL - 2018'!F16 -> 0 | H11: ='OECD TTL - 2018'!G16 -> 1141.9 | I11: ='OECD TTL - 2018'!H16 -> 458.8 | J11: ='OECD TTL - 2018'!I16 -> 131.3 | K11: ='OECD TTL - 2018'!J16 -> 7691.1 | L11: ='OECD TTL - 2018'!K16 -> 122.3 | M11: ='OECD TTL - 2018'!$L16*'SIOM from DLIM'!L150/SUM('SIOM from DLIM'!$L150:$M150) -> 1067.8993 | N11: ='OECD TTL - 2018'!$L16*'SIOM from DLIM'!M150/SUM('SIOM from DLIM'!$L150:$M150) -> 323.00073 | O11: ='OECD TTL - 2018'!M16 -> 753.4 | P11: ='OECD TTL - 2018'!$N16*'SIOM from DLIM'!O150/SUM('SIOM from DLIM'!$O150:$P150) -> 206.97957 | Q11: ='OECD TTL - 2018'!$N16*'SIOM from DLIM'!P150/SUM('SIOM from DLIM'!$O150:$P150) -> 286.62043 | R11: ='OECD TTL - 2018'!$O16*'SIOM from DLIM'!Q150/SUM('SIOM from DLIM'!$Q150:$R150) -> 82.765953 | S11: ='OECD TTL - 2018'!$O16*'SIOM from DLIM'!R150/SUM('SIOM from DLIM'!$Q150:$R150) -> 102.83405 | T11: ='OECD TTL - 2018'!P16 -> 338.6 | U11: ='OECD TTL - 2018'!Q16 -> 791.7 | V11: ='OECD TTL - 2018'!R16 -> 389 | W11: ='OECD TTL - 2018'!S16 -> 435.9 | X11: ='OECD TTL - 2018'!T16 -> 402.3 | Y11: ='OECD TTL - 2018'!U16 -> 114.1 | Z11: ='OECD TTL - 2018'!V16 -> 318.6 | AA11: ='OECD TTL - 2018'!$W16*'SIOM from DLIM'!Z150/SUM('SIOM from DLIM'!$Z150:$AB150) -> 0 | AB11: ='OECD TTL - 2018'!$W16*'SIOM from DLIM'!AA150/SUM('SIOM from DLIM'!$Z150:$AB150) -> 0 | AC11: ='OECD TTL - 2018'!$W16*'SIOM from DLIM'!AB150/SUM('SIOM from DLIM'!$Z150:$AB150) -> 438.4 | AD11: ='OECD TTL - 2018'!X16 -> 408.2 | AE11: ='OECD TTL - 2018'!Y16 -> 2304.7 | AF11: ='OECD TTL - 2018'!Z16 -> 291.7 | AG11: ='OECD TTL - 2018'!AA16 -> 517.9 | AH11: ='OECD TTL - 2018'!AB16 -> 1578.3 | AI11: ='OECD TTL - 2018'!AC16 -> 200.1 | AJ11: ='OECD TTL - 2018'!AD16 -> 491.4 | AK11: ='OECD TTL - 2018'!AE16 -> 1217.7 | ... AR11: ='OECD TTL - 2018'!AL16 -> 0
A12: D19: Coke and refined petroleum products | B12: refined petroleum and coke 19 | C12: ='OECD TTL - 2018'!C17 -> 1199.3 | D12: ='OECD TTL - 2018'!$D17*'SIOM from DLIM'!C151/SUM('SIOM from DLIM'!$C151:$D151) -> #DIV/0! | E12: ='OECD TTL - 2018'!$D17*'SIOM from DLIM'!D151/SUM('SIOM from DLIM'!$C151:$D151) -> #DIV/0! | F12: ='OECD TTL - 2018'!E17 -> 119.3 | G12: ='OECD TTL - 2018'!F17 -> 0.4 | H12: ='OECD TTL - 2018'!G17 -> 510.8 | I12: ='OECD TTL - 2018'!H17 -> 736.2 | J12: ='OECD TTL - 2018'!I17 -> 151.4 | K12: ='OECD TTL - 2018'!J17 -> 489.6 | L12: ='OECD TTL - 2018'!K17 -> 7323.9 | M12: ='OECD TTL - 2018'!$L17*'SIOM from DLIM'!L151/SUM('SIOM from DLIM'!$L151:$M151) -> 11715.681 | N12: ='OECD TTL - 2018'!$L17*'SIOM from DLIM'!M151/SUM('SIOM from DLIM'!$L151:$M151) -> 204.91877 | O12: ='OECD TTL - 2018'!M17 -> 2363.2 | P12: ='OECD TTL - 2018'!$N17*'SIOM from DLIM'!O151/SUM('SIOM from DLIM'!$O151:$P151) -> #DIV/0! | Q12: ='OECD TTL - 2018'!$N17*'SIOM from DLIM'!P151/SUM('SIOM from DLIM'!$O151:$P151) -> #DIV/0! | R12: ='OECD TTL - 2018'!$O17*'SIOM from DLIM'!Q151/SUM('SIOM from DLIM'!$Q151:$R151) -> #DIV/0! | S12: ='OECD TTL - 2018'!$O17*'SIOM from DLIM'!R151/SUM('SIOM from DLIM'!$Q151:$R151) -> #DIV/0! | T12: ='OECD TTL - 2018'!P17 -> 706.1 | U12: ='OECD TTL - 2018'!Q17 -> 779.8 | V12: ='OECD TTL - 2018'!R17 -> 556.5 | W12: ='OECD TTL - 2018'!S17 -> 620 | X12: ='OECD TTL - 2018'!T17 -> 572.5 | Y12: ='OECD TTL - 2018'!U17 -> 555.4 | Z12: ='OECD TTL - 2018'!V17 -> 315.2 | AA12: ='OECD TTL - 2018'!$W17*'SIOM from DLIM'!Z151/SUM('SIOM from DLIM'!$Z151:$AB151) -> 0 | AB12: ='OECD TTL - 2018'!$W17*'SIOM from DLIM'!AA151/SUM('SIOM from DLIM'!$Z151:$AB151) -> 0 | AC12: ='OECD TTL - 2018'!$W17*'SIOM from DLIM'!AB151/SUM('SIOM from DLIM'!$Z151:$AB151) -> 3445.8 | AD12: ='OECD TTL - 2018'!X17 -> 3137 | AE12: ='OECD TTL - 2018'!Y17 -> 2691.4 | AF12: ='OECD TTL - 2018'!Z17 -> 11014.4 | AG12: ='OECD TTL - 2018'!AA17 -> 466.4 | AH12: ='OECD TTL - 2018'!AB17 -> 120.9 | AI12: ='OECD TTL - 2018'!AC17 -> 147.5 | AJ12: ='OECD TTL - 2018'!AD17 -> 233 | AK12: ='OECD TTL - 2018'!AE17 -> 641.7 | ... AR12: ='OECD TTL - 2018'!AL17 -> 0
A13: chemicals 20 | B13: chemicals 20 | C13: ='OECD TTL - 2018'!C$18*'SIOM from DLIM'!B152/SUM('SIOM from DLIM'!B$152:B$153) -> 1643.4 | D13: ='OECD TTL - 2018'!$D$18*'SIOM from DLIM'!C152/SUM('SIOM from DLIM'!$C$152:$D$153) -> 21.305433 | E13: ='OECD TTL - 2018'!$D$18*'SIOM from DLIM'!D152/SUM('SIOM from DLIM'!$C$152:$D$153) -> 16.394567 | F13: ='OECD TTL - 2018'!E$18*'SIOM from DLIM'!D152/SUM('SIOM from DLIM'!D$152:D$153) -> 77 | G13: ='OECD TTL - 2018'!F$18*'SIOM from DLIM'!E152/SUM('SIOM from DLIM'!E$152:E$153) -> 0.19346503 | H13: ='OECD TTL - 2018'!G$18*'SIOM from DLIM'!F152/SUM('SIOM from DLIM'!F$152:F$153) -> 858.50171 | I13: ='OECD TTL - 2018'!H$18*'SIOM from DLIM'!G152/SUM('SIOM from DLIM'!G$152:G$153) -> 2908.5924 | J13: ='OECD TTL - 2018'!I$18*'SIOM from DLIM'!H152/SUM('SIOM from DLIM'!H$152:H$153) -> 364.27004 | K13: ='OECD TTL - 2018'!J$18*'SIOM from DLIM'!I152/SUM('SIOM from DLIM'!I$152:I$153) -> 1516.0045 | L13: ='OECD TTL - 2018'!K$18*'SIOM from DLIM'!J152/SUM('SIOM from DLIM'!J$152:J$153) -> 4370.9567 | M13: ='OECD TTL - 2018'!$L$18*'SIOM from DLIM'!L152/SUM('SIOM from DLIM'!$L$152:$M$153) -> 35435.618 | N13: ='OECD TTL - 2018'!$L$18*'SIOM from DLIM'!M152/SUM('SIOM from DLIM'!$L$152:$M$153) -> 1155.6055 | O13: ='OECD TTL - 2018'!M$18*'SIOM from DLIM'!L152/SUM('SIOM from DLIM'!L$152:L$153) -> 14087.782 | P13: ='OECD TTL - 2018'!$N$18*'SIOM from DLIM'!O152/SUM('SIOM from DLIM'!$O$152:$P$153) -> 566.18786 | Q13: ='OECD TTL - 2018'!$N$18*'SIOM from DLIM'!P152/SUM('SIOM from DLIM'!$O$152:$P$153) -> 1177.2751 | R13: ='OECD TTL - 2018'!$O$18*'SIOM from DLIM'!Q152/SUM('SIOM from DLIM'!$Q$152:$R$153) -> 2894.9878 | S13: ='OECD TTL - 2018'!$O$18*'SIOM from DLIM'!R152/SUM('SIOM from DLIM'!$Q$152:$R$153) -> 1222.7933 | T13: ='OECD TTL - 2018'!P$18*'SIOM from DLIM'!O152/SUM('SIOM from DLIM'!O$152:O$153) -> 1751.7384 | U13: ='OECD TTL - 2018'!Q$18*'SIOM from DLIM'!P152/SUM('SIOM from DLIM'!P$152:P$153) -> 3086.6 | V13: ='OECD TTL - 2018'!R$18*'SIOM from DLIM'!Q152/SUM('SIOM from DLIM'!Q$152:Q$153) -> 1813.5722 | W13: ='OECD TTL - 2018'!S$18*'SIOM from DLIM'!R152/SUM('SIOM from DLIM'!R$152:R$153) -> 1343.9999 | X13: ='OECD TTL - 2018'!T$18*'SIOM from DLIM'!S152/SUM('SIOM from DLIM'!S$152:S$153) -> 1717.2827 | Y13: ='OECD TTL - 2018'!U$18*'SIOM from DLIM'!T152/SUM('SIOM from DLIM'!T$152:T$153) -> 1860.8253 | Z13: ='OECD TTL - 2018'!V$18*'SIOM from DLIM'!U152/SUM('SIOM from DLIM'!U$152:U$153) -> 834.80985 | AA13: ='OECD TTL - 2018'!$W$18*'SIOM from DLIM'!Z152/SUM('SIOM from DLIM'!$Z$152:$AB$153) -> 985.7287 | AB13: ='OECD TTL - 2018'!$W$18*'SIOM from DLIM'!AA152/SUM('SIOM from DLIM'!$Z$152:$AB$153) -> 270.54603 | AC13: ='OECD TTL - 2018'!$W$18*'SIOM from DLIM'!AB152/SUM('SIOM from DLIM'!$Z$152:$AB$153) -> 106.75629 | AD13: ='OECD TTL - 2018'!X$18*'SIOM from DLIM'!W152/SUM('SIOM from DLIM'!W$152:W$153) -> 2703.6386 | AE13: ='OECD TTL - 2018'!Y$18*'SIOM from DLIM'!X152/SUM('SIOM from DLIM'!X$152:X$153) -> 1372.6111 | AF13: ='OECD TTL - 2018'!Z$18*'SIOM from DLIM'!Y152/SUM('SIOM from DLIM'!Y$152:Y$153) -> 2060.5755 | AG13: ='OECD TTL - 2018'!AA$18*'SIOM from DLIM'!Z152/SUM('SIOM from DLIM'!Z$152:Z$153) -> 445.8 | AH13: ='OECD TTL - 2018'!AB$18*'SIOM from DLIM'!AA152/SUM('SIOM from DLIM'!AA$152:AA$153) -> 199.9 | AI13: ='OECD TTL - 2018'!AC$18*'SIOM from DLIM'!AB152/SUM('SIOM from DLIM'!AB$152:AB$153) -> 60.696629 | AJ13: ='OECD TTL - 2018'!AD$18*'SIOM from DLIM'!AC152/SUM('SIOM from DLIM'!AC$152:AC$153) -> 105.669 | AK13: ='OECD TTL - 2018'!AE$18*'SIOM from DLIM'!AD152/SUM('SIOM from DLIM'!AD$152:AD$153) -> 192.36767 | ... AR13: ='OECD TTL - 2018'!AL$18*'SIOM from DLIM'!AK152/SUM('SIOM from DLIM'!AK$152:AK$153) -> 0
A14: pharmaceuticals | B14: chemicals 20 | C14: ='OECD TTL - 2018'!C$18*'SIOM from DLIM'!B153/SUM('SIOM from DLIM'!B$152:B$153) -> 0 | D14: ='OECD TTL - 2018'!$D$18*'SIOM from DLIM'!C153/SUM('SIOM from DLIM'!$C$152:$D$153) -> 0 | E14: ='OECD TTL - 2018'!$D$18*'SIOM from DLIM'!D153/SUM('SIOM from DLIM'!$C$152:$D$153) -> 0 | F14: ='OECD TTL - 2018'!E$18*'SIOM from DLIM'!D153/SUM('SIOM from DLIM'!D$152:D$153) -> 0 | G14: ='OECD TTL - 2018'!F$18*'SIOM from DLIM'!E153/SUM('SIOM from DLIM'!E$152:E$153) -> 0.0065349712 | H14: ='OECD TTL - 2018'!G$18*'SIOM from DLIM'!F153/SUM('SIOM from DLIM'!F$152:F$153) -> 35.098293 | I14: ='OECD TTL - 2018'!H$18*'SIOM from DLIM'!G153/SUM('SIOM from DLIM'!G$152:G$153) -> 604.50763 | J14: ='OECD TTL - 2018'!I$18*'SIOM from DLIM'!H153/SUM('SIOM from DLIM'!H$152:H$153) -> 27.62996 | K14: ='OECD TTL - 2018'!J$18*'SIOM from DLIM'!I153/SUM('SIOM from DLIM'!I$152:I$153) -> 53.995539 | L14: ='OECD TTL - 2018'!K$18*'SIOM from DLIM'!J153/SUM('SIOM from DLIM'!J$152:J$153) -> 131.04335 | M14: ='OECD TTL - 2018'!$L$18*'SIOM from DLIM'!L153/SUM('SIOM from DLIM'!$L$152:$M$153) -> 128.83017 | N14: ='OECD TTL - 2018'!$L$18*'SIOM from DLIM'!M153/SUM('SIOM from DLIM'!$L$152:$M$153) -> 1182.8461 | O14: ='OECD TTL - 2018'!M$18*'SIOM from DLIM'!L153/SUM('SIOM from DLIM'!L$152:L$153) -> 51.217713 | P14: ='OECD TTL - 2018'!$N$18*'SIOM from DLIM'!O153/SUM('SIOM from DLIM'!$O$152:$P$153) -> 0.5370543 | Q14: ='OECD TTL - 2018'!$N$18*'SIOM from DLIM'!P153/SUM('SIOM from DLIM'!$O$152:$P$153) -> 0 | R14: ='OECD TTL - 2018'!$O$18*'SIOM from DLIM'!Q153/SUM('SIOM from DLIM'!$Q$152:$R$153) -> 5.7909474 | S14: ='OECD TTL - 2018'!$O$18*'SIOM from DLIM'!R153/SUM('SIOM from DLIM'!$Q$152:$R$153) -> 0.72793417 | T14: ='OECD TTL - 2018'!P$18*'SIOM from DLIM'!O153/SUM('SIOM from DLIM'!O$152:O$153) -> 1.6616016 | U14: ='OECD TTL - 2018'!Q$18*'SIOM from DLIM'!P153/SUM('SIOM from DLIM'!P$152:P$153) -> 0 | V14: ='OECD TTL - 2018'!R$18*'SIOM from DLIM'!Q153/SUM('SIOM from DLIM'!Q$152:Q$153) -> 3.6277533 | W14: ='OECD TTL - 2018'!S$18*'SIOM from DLIM'!R153/SUM('SIOM from DLIM'!R$152:R$153) -> 0.80008897 | X14: ='OECD TTL - 2018'!T$18*'SIOM from DLIM'!S153/SUM('SIOM from DLIM'!S$152:S$153) -> 93.017326 | Y14: ='OECD TTL - 2018'!U$18*'SIOM from DLIM'!T153/SUM('SIOM from DLIM'!T$152:T$153) -> 63.374681 | Z14: ='OECD TTL - 2018'!V$18*'SIOM from DLIM'!U153/SUM('SIOM from DLIM'!U$152:U$153) -> 29.990148 | AA14: ='OECD TTL - 2018'!$W$18*'SIOM from DLIM'!Z153/SUM('SIOM from DLIM'!$Z$152:$AB$153) -> 0 | AB14: ='OECD TTL - 2018'!$W$18*'SIOM from DLIM'!AA153/SUM('SIOM from DLIM'!$Z$152:$AB$153) -> 0 | AC14: ='OECD TTL - 2018'!$W$18*'SIOM from DLIM'!AB153/SUM('SIOM from DLIM'!$Z$152:$AB$153) -> 7.5689852 | AD14: ='OECD TTL - 2018'!X$18*'SIOM from DLIM'!W153/SUM('SIOM from DLIM'!W$152:W$153) -> 195.96139 | AE14: ='OECD TTL - 2018'!Y$18*'SIOM from DLIM'!X153/SUM('SIOM from DLIM'!X$152:X$153) -> 188.18893 | AF14: ='OECD TTL - 2018'!Z$18*'SIOM from DLIM'!Y153/SUM('SIOM from DLIM'!Y$152:Y$153) -> 129.92448 | AG14: ='OECD TTL - 2018'!AA$18*'SIOM from DLIM'!Z153/SUM('SIOM from DLIM'!Z$152:Z$153) -> 0 | AH14: ='OECD TTL - 2018'!AB$18*'SIOM from DLIM'!AA153/SUM('SIOM from DLIM'!AA$152:AA$153) -> 0 | AI14: ='OECD TTL - 2018'!AC$18*'SIOM from DLIM'!AB153/SUM('SIOM from DLIM'!AB$152:AB$153) -> 4.3033708 | AJ14: ='OECD TTL - 2018'!AD$18*'SIOM from DLIM'!AC153/SUM('SIOM from DLIM'!AC$152:AC$153) -> 7.9309992 | AK14: ='OECD TTL - 2018'!AE$18*'SIOM from DLIM'!AD153/SUM('SIOM from DLIM'!AD$152:AD$153) -> 51.13233 | ... AR14: ='OECD TTL - 2018'!AL$18*'SIOM from DLIM'!AK153/SUM('SIOM from DLIM'!AK$152:AK$153) -> 0
A15: D22: Rubber and plastic products | B15: rubber and plastic products 22 | C15: ='OECD TTL - 2018'!C19 -> 242.8 | D15: ='OECD TTL - 2018'!$D19*'SIOM from DLIM'!C154/SUM('SIOM from DLIM'!$C154:$D154) -> 30.4 | E15: ='OECD TTL - 2018'!$D19*'SIOM from DLIM'!D154/SUM('SIOM from DLIM'!$C154:$D154) -> 0 | F15: ='OECD TTL - 2018'!E19 -> 43.1 | G15: ='OECD TTL - 2018'!F19 -> 0.1 | H15: ='OECD TTL - 2018'!G19 -> 1866.4 | I15: ='OECD TTL - 2018'!H19 -> 1204.3 | J15: ='OECD TTL - 2018'!I19 -> 194.9 | K15: ='OECD TTL - 2018'!J19 -> 780.9 | L15: ='OECD TTL - 2018'!K19 -> 352.2 | M15: ='OECD TTL - 2018'!$L19*'SIOM from DLIM'!L154/SUM('SIOM from DLIM'!$L154:$M154) -> 2953.4954 | N15: ='OECD TTL - 2018'!$L19*'SIOM from DLIM'!M154/SUM('SIOM from DLIM'!$L154:$M154) -> 420.20465 | O15: ='OECD TTL - 2018'!M19 -> 10678.7 | P15: ='OECD TTL - 2018'!$N19*'SIOM from DLIM'!O154/SUM('SIOM from DLIM'!$O154:$P154) -> 843.42277 | Q15: ='OECD TTL - 2018'!$N19*'SIOM from DLIM'!P154/SUM('SIOM from DLIM'!$O154:$P154) -> 221.27723 | R15: ='OECD TTL - 2018'!$O19*'SIOM from DLIM'!Q154/SUM('SIOM from DLIM'!$Q154:$R154) -> 824.30065 | S15: ='OECD TTL - 2018'!$O19*'SIOM from DLIM'!R154/SUM('SIOM from DLIM'!$Q154:$R154) -> 396.49935 | T15: ='OECD TTL - 2018'!P19 -> 1643 | U15: ='OECD TTL - 2018'!Q19 -> 5169.6 | V15: ='OECD TTL - 2018'!R19 -> 3001.6 | W15: ='OECD TTL - 2018'!S19 -> 3307.7 | X15: ='OECD TTL - 2018'!T19 -> 6608.9 | Y15: ='OECD TTL - 2018'!U19 -> 2076.2 | Z15: ='OECD TTL - 2018'!V19 -> 1252.3 | AA15: ='OECD TTL - 2018'!$W19*'SIOM from DLIM'!Z154/SUM('SIOM from DLIM'!$Z154:$AB154) -> 205.18984 | AB15: ='OECD TTL - 2018'!$W19*'SIOM from DLIM'!AA154/SUM('SIOM from DLIM'!$Z154:$AB154) -> 0 | AC15: ='OECD TTL - 2018'!$W19*'SIOM from DLIM'!AB154/SUM('SIOM from DLIM'!$Z154:$AB154) -> 308.51016 | AD15: ='OECD TTL - 2018'!X19 -> 7556.3 | AE15: ='OECD TTL - 2018'!Y19 -> 3051.6 | AF15: ='OECD TTL - 2018'!Z19 -> 1292.1 | AG15: ='OECD TTL - 2018'!AA19 -> 629.7 | AH15: ='OECD TTL - 2018'!AB19 -> 116.4 | AI15: ='OECD TTL - 2018'!AC19 -> 225.6 | AJ15: ='OECD TTL - 2018'!AD19 -> 162.9 | AK15: ='OECD TTL - 2018'!AE19 -> 243.6 | ... AR15: ='OECD TTL - 2018'!AL19 -> 0
A16: glass and glass products 231 | B16: glass and glass products 231 | C16: ='OECD TTL - 2018'!C$20*'SIOM from DLIM'!B155/SUM('SIOM from DLIM'!B$155:B$156) -> 36.20301 | D16: ='OECD TTL - 2018'!$D$20*'SIOM from DLIM'!C155/SUM('SIOM from DLIM'!$C$155:$D$156) -> 3.1220163 | E16: ='OECD TTL - 2018'!$D$20*'SIOM from DLIM'!D155/SUM('SIOM from DLIM'!$C$155:$D$156) -> 0.3143881 | F16: ='OECD TTL - 2018'!E$20*'SIOM from DLIM'!D155/SUM('SIOM from DLIM'!D$155:D$156) -> 48.177392 | G16: ='OECD TTL - 2018'!F$20*'SIOM from DLIM'!E155/SUM('SIOM from DLIM'!E$155:E$156) -> #DIV/0! | H16: ='OECD TTL - 2018'!G$20*'SIOM from DLIM'!F155/SUM('SIOM from DLIM'!F$155:F$156) -> #DIV/0! | I16: ='OECD TTL - 2018'!H$20*'SIOM from DLIM'!G155/SUM('SIOM from DLIM'!G$155:G$156) -> 158.1 | J16: ='OECD TTL - 2018'!I$20*'SIOM from DLIM'!H155/SUM('SIOM from DLIM'!H$155:H$156) -> #DIV/0! | K16: ='OECD TTL - 2018'!J$20*'SIOM from DLIM'!I155/SUM('SIOM from DLIM'!I$155:I$156) -> 0 | L16: ='OECD TTL - 2018'!K$20*'SIOM from DLIM'!J155/SUM('SIOM from DLIM'!J$155:J$156) -> 0 | M16: ='OECD TTL - 2018'!$L$20*'SIOM from DLIM'!L155/SUM('SIOM from DLIM'!$L$155:$M$156) -> 242.27336 | N16: ='OECD TTL - 2018'!$L$20*'SIOM from DLIM'!M155/SUM('SIOM from DLIM'!$L$155:$M$156) -> 63.799933 | O16: ='OECD TTL - 2018'!M$20*'SIOM from DLIM'!L155/SUM('SIOM from DLIM'!L$155:L$156) -> 184.85571 | P16: ='OECD TTL - 2018'!$N$20*'SIOM from DLIM'!O155/SUM('SIOM from DLIM'!$O$155:$P$156) -> 2055.5112 | Q16: ='OECD TTL - 2018'!$N$20*'SIOM from DLIM'!P155/SUM('SIOM from DLIM'!$O$155:$P$156) -> 21.195466 | R16: ='OECD TTL - 2018'!$O$20*'SIOM from DLIM'!Q155/SUM('SIOM from DLIM'!$Q$155:$R$156) -> 45.386381 | S16: ='OECD TTL - 2018'!$O$20*'SIOM from DLIM'!R155/SUM('SIOM from DLIM'!$Q$155:$R$156) -> 17.104515 | T16: ='OECD TTL - 2018'!P$20*'SIOM from DLIM'!O155/SUM('SIOM from DLIM'!O$155:O$156) -> 776.63156 | U16: ='OECD TTL - 2018'!Q$20*'SIOM from DLIM'!P155/SUM('SIOM from DLIM'!P$155:P$156) -> 10.250103 | V16: ='OECD TTL - 2018'!R$20*'SIOM from DLIM'!Q155/SUM('SIOM from DLIM'!Q$155:Q$156) -> 30.945603 | W16: ='OECD TTL - 2018'!S$20*'SIOM from DLIM'!R155/SUM('SIOM from DLIM'!R$155:R$156) -> 127.18715 | X16: ='OECD TTL - 2018'!T$20*'SIOM from DLIM'!S155/SUM('SIOM from DLIM'!S$155:S$156) -> 0 | Y16: ='OECD TTL - 2018'!U$20*'SIOM from DLIM'!T155/SUM('SIOM from DLIM'!T$155:T$156) -> 741.23829 | Z16: ='OECD TTL - 2018'!V$20*'SIOM from DLIM'!U155/SUM('SIOM from DLIM'!U$155:U$156) -> 157.2107 | AA16: ='OECD TTL - 2018'!$W$20*'SIOM from DLIM'!Z155/SUM('SIOM from DLIM'!$Z$155:$AB$156) -> 286.44985 | AB16: ='OECD TTL - 2018'!$W$20*'SIOM from DLIM'!AA155/SUM('SIOM from DLIM'!$Z$155:$AB$156) -> 2.4501507 | AC16: ='OECD TTL - 2018'!$W$20*'SIOM from DLIM'!AB155/SUM('SIOM from DLIM'!$Z$155:$AB$156) -> 0 | AD16: ='OECD TTL - 2018'!X$20*'SIOM from DLIM'!W155/SUM('SIOM from DLIM'!W$155:W$156) -> 20867.691 | AE16: ='OECD TTL - 2018'!Y$20*'SIOM from DLIM'!X155/SUM('SIOM from DLIM'!X$155:X$156) -> 0 | AF16: ='OECD TTL - 2018'!Z$20*'SIOM from DLIM'!Y155/SUM('SIOM from DLIM'!Y$155:Y$156) -> 156.97987 | AG16: ='OECD TTL - 2018'!AA$20*'SIOM from DLIM'!Z155/SUM('SIOM from DLIM'!Z$155:Z$156) -> 260.5 | AH16: ='OECD TTL - 2018'!AB$20*'SIOM from DLIM'!AA155/SUM('SIOM from DLIM'!AA$155:AA$156) -> 24.3 | AI16: ='OECD TTL - 2018'!AC$20*'SIOM from DLIM'!AB155/SUM('SIOM from DLIM'!AB$155:AB$156) -> #DIV/0! | AJ16: ='OECD TTL - 2018'!AD$20*'SIOM from DLIM'!AC155/SUM('SIOM from DLIM'!AC$155:AC$156) -> 2.4723562 | AK16: ='OECD TTL - 2018'!AE$20*'SIOM from DLIM'!AD155/SUM('SIOM from DLIM'!AD$155:AD$156) -> #DIV/0! | ... AR16: ='OECD TTL - 2018'!AL$20*'SIOM from DLIM'!AK155/SUM('SIOM from DLIM'!AK$155:AK$156) -> #DIV/0!
A17: cement and other nonmetallic minerals 239 | B17: cement and other nonmetallic minerals 239 | C17: ='OECD TTL - 2018'!C$20*'SIOM from DLIM'!B156/SUM('SIOM from DLIM'!B$155:B$156) -> 63.89699 | D17: ='OECD TTL - 2018'!$D$20*'SIOM from DLIM'!C156/SUM('SIOM from DLIM'!$C$155:$D$156) -> 1.0432186 | E17: ='OECD TTL - 2018'!$D$20*'SIOM from DLIM'!D156/SUM('SIOM from DLIM'!$C$155:$D$156) -> 0.020377 | F17: ='OECD TTL - 2018'!E$20*'SIOM from DLIM'!D156/SUM('SIOM from DLIM'!D$155:D$156) -> 3.1226077 | G17: ='OECD TTL - 2018'!F$20*'SIOM from DLIM'!E156/SUM('SIOM from DLIM'!E$155:E$156) -> #DIV/0! | H17: ='OECD TTL - 2018'!G$20*'SIOM from DLIM'!F156/SUM('SIOM from DLIM'!F$155:F$156) -> #DIV/0! | I17: ='OECD TTL - 2018'!H$20*'SIOM from DLIM'!G156/SUM('SIOM from DLIM'!G$155:G$156) -> 0 | J17: ='OECD TTL - 2018'!I$20*'SIOM from DLIM'!H156/SUM('SIOM from DLIM'!H$155:H$156) -> #DIV/0! | K17: ='OECD TTL - 2018'!J$20*'SIOM from DLIM'!I156/SUM('SIOM from DLIM'!I$155:I$156) -> 63.2 | L17: ='OECD TTL - 2018'!K$20*'SIOM from DLIM'!J156/SUM('SIOM from DLIM'!J$155:J$156) -> 123.3 | M17: ='OECD TTL - 2018'!$L$20*'SIOM from DLIM'!L156/SUM('SIOM from DLIM'!$L$155:$M$156) -> 492.58451 | N17: ='OECD TTL - 2018'!$L$20*'SIOM from DLIM'!M156/SUM('SIOM from DLIM'!$L$155:$M$156) -> 110.0422 | O17: ='OECD TTL - 2018'!M$20*'SIOM from DLIM'!L156/SUM('SIOM from DLIM'!L$155:L$156) -> 375.84429 | P17: ='OECD TTL - 2018'!$N$20*'SIOM from DLIM'!O156/SUM('SIOM from DLIM'!$O$155:$P$156) -> 51.527138 | Q17: ='OECD TTL - 2018'!$N$20*'SIOM from DLIM'!P156/SUM('SIOM from DLIM'!$O$155:$P$156) -> 4367.5662 | R17: ='OECD TTL - 2018'!$O$20*'SIOM from DLIM'!Q156/SUM('SIOM from DLIM'!$Q$155:$R$156) -> 956.77583 | S17: ='OECD TTL - 2018'!$O$20*'SIOM from DLIM'!R156/SUM('SIOM from DLIM'!$Q$155:$R$156) -> 75.43327 | T17: ='OECD TTL - 2018'!P$20*'SIOM from DLIM'!O156/SUM('SIOM from DLIM'!O$155:O$156) -> 19.468443 | U17: ='OECD TTL - 2018'!Q$20*'SIOM from DLIM'!P156/SUM('SIOM from DLIM'!P$155:P$156) -> 2112.1499 | V17: ='OECD TTL - 2018'!R$20*'SIOM from DLIM'!Q156/SUM('SIOM from DLIM'!Q$155:Q$156) -> 652.3544 | W17: ='OECD TTL - 2018'!S$20*'SIOM from DLIM'!R156/SUM('SIOM from DLIM'!R$155:R$156) -> 560.91285 | X17: ='OECD TTL - 2018'!T$20*'SIOM from DLIM'!S156/SUM('SIOM from DLIM'!S$155:S$156) -> 1092.1 | Y17: ='OECD TTL - 2018'!U$20*'SIOM from DLIM'!T156/SUM('SIOM from DLIM'!T$155:T$156) -> 25.061707 | Z17: ='OECD TTL - 2018'!V$20*'SIOM from DLIM'!U156/SUM('SIOM from DLIM'!U$155:U$156) -> 70.089304 | AA17: ='OECD TTL - 2018'!$W$20*'SIOM from DLIM'!Z156/SUM('SIOM from DLIM'!$Z$155:$AB$156) -> 0 | AB17: ='OECD TTL - 2018'!$W$20*'SIOM from DLIM'!AA156/SUM('SIOM from DLIM'!$Z$155:$AB$156) -> 0 | AC17: ='OECD TTL - 2018'!$W$20*'SIOM from DLIM'!AB156/SUM('SIOM from DLIM'!$Z$155:$AB$156) -> 0 | AD17: ='OECD TTL - 2018'!X$20*'SIOM from DLIM'!W156/SUM('SIOM from DLIM'!W$155:W$156) -> 1145.7091 | AE17: ='OECD TTL - 2018'!Y$20*'SIOM from DLIM'!X156/SUM('SIOM from DLIM'!X$155:X$156) -> 707.3 | AF17: ='OECD TTL - 2018'!Z$20*'SIOM from DLIM'!Y156/SUM('SIOM from DLIM'!Y$155:Y$156) -> 34.420128 | AG17: ='OECD TTL - 2018'!AA$20*'SIOM from DLIM'!Z156/SUM('SIOM from DLIM'!Z$155:Z$156) -> 0 | AH17: ='OECD TTL - 2018'!AB$20*'SIOM from DLIM'!AA156/SUM('SIOM from DLIM'!AA$155:AA$156) -> 0 | AI17: ='OECD TTL - 2018'!AC$20*'SIOM from DLIM'!AB156/SUM('SIOM from DLIM'!AB$155:AB$156) -> #DIV/0! | AJ17: ='OECD TTL - 2018'!AD$20*'SIOM from DLIM'!AC156/SUM('SIOM from DLIM'!AC$155:AC$156) -> 36.727644 | AK17: ='OECD TTL - 2018'!AE$20*'SIOM from DLIM'!AD156/SUM('SIOM from DLIM'!AD$155:AD$156) -> #DIV/0! | ... AR17: ='OECD TTL - 2018'!AL$20*'SIOM from DLIM'!AK156/SUM('SIOM from DLIM'!AK$155:AK$156) -> #DIV/0!
A18: iron and steel 241 | B18: iron and steel 241 | C18: ='OECD TTL - 2018'!C$21*'SIOM from DLIM'!B157/SUM('SIOM from DLIM'!B$157:B$158) -> #DIV/0! | D18: ='OECD TTL - 2018'!$D$21*'SIOM from DLIM'!C157/SUM('SIOM from DLIM'!$C$157:$D$158) -> 8.0584225 | E18: ='OECD TTL - 2018'!$D$21*'SIOM from DLIM'!D157/SUM('SIOM from DLIM'!$C$157:$D$158) -> 0.14042807 | F18: ='OECD TTL - 2018'!E$21*'SIOM from DLIM'!D157/SUM('SIOM from DLIM'!D$157:D$158) -> 20.029919 | G18: ='OECD TTL - 2018'!F$21*'SIOM from DLIM'!E157/SUM('SIOM from DLIM'!E$157:E$158) -> #DIV/0! | H18: ='OECD TTL - 2018'!G$21*'SIOM from DLIM'!F157/SUM('SIOM from DLIM'!F$157:F$158) -> #DIV/0! | I18: ='OECD TTL - 2018'!H$21*'SIOM from DLIM'!G157/SUM('SIOM from DLIM'!G$157:G$158) -> #DIV/0! | J18: ='OECD TTL - 2018'!I$21*'SIOM from DLIM'!H157/SUM('SIOM from DLIM'!H$157:H$158) -> #DIV/0! | K18: ='OECD TTL - 2018'!J$21*'SIOM from DLIM'!I157/SUM('SIOM from DLIM'!I$157:I$158) -> #DIV/0! | L18: ='OECD TTL - 2018'!K$21*'SIOM from DLIM'!J157/SUM('SIOM from DLIM'!J$157:J$158) -> #DIV/0! | M18: ='OECD TTL - 2018'!$L$21*'SIOM from DLIM'!L157/SUM('SIOM from DLIM'!$L$157:$M$158) -> 0 | N18: ='OECD TTL - 2018'!$L$21*'SIOM from DLIM'!M157/SUM('SIOM from DLIM'!$L$157:$M$158) -> 0 | O18: ='OECD TTL - 2018'!M$21*'SIOM from DLIM'!L157/SUM('SIOM from DLIM'!L$157:L$158) -> 0 | P18: ='OECD TTL - 2018'!$N$21*'SIOM from DLIM'!O157/SUM('SIOM from DLIM'!$O$157:$P$158) -> 60.503588 | Q18: ='OECD TTL - 2018'!$N$21*'SIOM from DLIM'!P157/SUM('SIOM from DLIM'!$O$157:$P$158) -> 536.93318 | R18: ='OECD TTL - 2018'!$O$21*'SIOM from DLIM'!Q157/SUM('SIOM from DLIM'!$Q$157:$R$158) -> 26017.806 | S18: ='OECD TTL - 2018'!$O$21*'SIOM from DLIM'!R157/SUM('SIOM from DLIM'!$Q$157:$R$158) -> 51.341857 | T18: ='OECD TTL - 2018'!P$21*'SIOM from DLIM'!O157/SUM('SIOM from DLIM'!O$157:O$158) -> 16521.911 | U18: ='OECD TTL - 2018'!Q$21*'SIOM from DLIM'!P157/SUM('SIOM from DLIM'!P$157:P$158) -> 4665.2479 | V18: ='OECD TTL - 2018'!R$21*'SIOM from DLIM'!Q157/SUM('SIOM from DLIM'!Q$157:Q$158) -> 9172.6249 | W18: ='OECD TTL - 2018'!S$21*'SIOM from DLIM'!R157/SUM('SIOM from DLIM'!R$157:R$158) -> 168.90562 | X18: ='OECD TTL - 2018'!T$21*'SIOM from DLIM'!S157/SUM('SIOM from DLIM'!S$157:S$158) -> 6830.5228 | Y18: ='OECD TTL - 2018'!U$21*'SIOM from DLIM'!T157/SUM('SIOM from DLIM'!T$157:T$158) -> 4256.936 | Z18: ='OECD TTL - 2018'!V$21*'SIOM from DLIM'!U157/SUM('SIOM from DLIM'!U$157:U$158) -> 1106.2129 | AA18: ='OECD TTL - 2018'!$W$21*'SIOM from DLIM'!Z157/SUM('SIOM from DLIM'!$Z$157:$AB$158) -> 923.1676 | AB18: ='OECD TTL - 2018'!$W$21*'SIOM from DLIM'!AA157/SUM('SIOM from DLIM'!$Z$157:$AB$158) -> 167.684 | AC18: ='OECD TTL - 2018'!$W$21*'SIOM from DLIM'!AB157/SUM('SIOM from DLIM'!$Z$157:$AB$158) -> 0 | AD18: ='OECD TTL - 2018'!X$21*'SIOM from DLIM'!W157/SUM('SIOM from DLIM'!W$157:W$158) -> 10990.8 | AE18: ='OECD TTL - 2018'!Y$21*'SIOM from DLIM'!X157/SUM('SIOM from DLIM'!X$157:X$158) -> #DIV/0! | AF18: ='OECD TTL - 2018'!Z$21*'SIOM from DLIM'!Y157/SUM('SIOM from DLIM'!Y$157:Y$158) -> 189.58042 | AG18: ='OECD TTL - 2018'!AA$21*'SIOM from DLIM'!Z157/SUM('SIOM from DLIM'!Z$157:Z$158) -> 78.008607 | AH18: ='OECD TTL - 2018'!AB$21*'SIOM from DLIM'!AA157/SUM('SIOM from DLIM'!AA$157:AA$158) -> 21.3 | AI18: ='OECD TTL - 2018'!AC$21*'SIOM from DLIM'!AB157/SUM('SIOM from DLIM'!AB$157:AB$158) -> #DIV/0! | AJ18: ='OECD TTL - 2018'!AD$21*'SIOM from DLIM'!AC157/SUM('SIOM from DLIM'!AC$157:AC$158) -> 35.335136 | AK18: ='OECD TTL - 2018'!AE$21*'SIOM from DLIM'!AD157/SUM('SIOM from DLIM'!AD$157:AD$158) -> #DIV/0! | ... AR18: ='OECD TTL - 2018'!AL$21*'SIOM from DLIM'!AK157/SUM('SIOM from DLIM'!AK$157:AK$158) -> #DIV/0!
A19: other metals 242 | B19: other metals 242 | C19: ='OECD TTL - 2018'!C$21*'SIOM from DLIM'!B158/SUM('SIOM from DLIM'!B$157:B$158) -> #DIV/0! | D19: ='OECD TTL - 2018'!$D$21*'SIOM from DLIM'!C158/SUM('SIOM from DLIM'!$C$157:$D$158) -> 0.097152604 | E19: ='OECD TTL - 2018'!$D$21*'SIOM from DLIM'!D158/SUM('SIOM from DLIM'!$C$157:$D$158) -> 0.0039967893 | F19: ='OECD TTL - 2018'!E$21*'SIOM from DLIM'!D158/SUM('SIOM from DLIM'!D$157:D$158) -> 0.57008092 | G19: ='OECD TTL - 2018'!F$21*'SIOM from DLIM'!E158/SUM('SIOM from DLIM'!E$157:E$158) -> #DIV/0! | H19: ='OECD TTL - 2018'!G$21*'SIOM from DLIM'!F158/SUM('SIOM from DLIM'!F$157:F$158) -> #DIV/0! | I19: ='OECD TTL - 2018'!H$21*'SIOM from DLIM'!G158/SUM('SIOM from DLIM'!G$157:G$158) -> #DIV/0! | J19: ='OECD TTL - 2018'!I$21*'SIOM from DLIM'!H158/SUM('SIOM from DLIM'!H$157:H$158) -> #DIV/0! | K19: ='OECD TTL - 2018'!J$21*'SIOM from DLIM'!I158/SUM('SIOM from DLIM'!I$157:I$158) -> #DIV/0! | L19: ='OECD TTL - 2018'!K$21*'SIOM from DLIM'!J158/SUM('SIOM from DLIM'!J$157:J$158) -> #DIV/0! | M19: ='OECD TTL - 2018'!$L$21*'SIOM from DLIM'!L158/SUM('SIOM from DLIM'!$L$157:$M$158) -> 866.5 | N19: ='OECD TTL - 2018'!$L$21*'SIOM from DLIM'!M158/SUM('SIOM from DLIM'!$L$157:$M$158) -> 0 | O19: ='OECD TTL - 2018'!M$21*'SIOM from DLIM'!L158/SUM('SIOM from DLIM'!L$157:L$158) -> 659.6 | P19: ='OECD TTL - 2018'!$N$21*'SIOM from DLIM'!O158/SUM('SIOM from DLIM'!$O$157:$P$158) -> 13.27552 | Q19: ='OECD TTL - 2018'!$N$21*'SIOM from DLIM'!P158/SUM('SIOM from DLIM'!$O$157:$P$158) -> 28.38771 | R19: ='OECD TTL - 2018'!$O$21*'SIOM from DLIM'!Q158/SUM('SIOM from DLIM'!$Q$157:$R$158) -> 63.18244 | S19: ='OECD TTL - 2018'!$O$21*'SIOM from DLIM'!R158/SUM('SIOM from DLIM'!$Q$157:$R$158) -> 3680.4699 | T19: ='OECD TTL - 2018'!P$21*'SIOM from DLIM'!O158/SUM('SIOM from DLIM'!O$157:O$158) -> 3625.1893 | U19: ='OECD TTL - 2018'!Q$21*'SIOM from DLIM'!P158/SUM('SIOM from DLIM'!P$157:P$158) -> 246.65211 | V19: ='OECD TTL - 2018'!R$21*'SIOM from DLIM'!Q158/SUM('SIOM from DLIM'!Q$157:Q$158) -> 22.275085 | W19: ='OECD TTL - 2018'!S$21*'SIOM from DLIM'!R158/SUM('SIOM from DLIM'!R$157:R$158) -> 12108.094 | X19: ='OECD TTL - 2018'!T$21*'SIOM from DLIM'!S158/SUM('SIOM from DLIM'!S$157:S$158) -> 364.57724 | Y19: ='OECD TTL - 2018'!U$21*'SIOM from DLIM'!T158/SUM('SIOM from DLIM'!T$157:T$158) -> 1999.364 | Z19: ='OECD TTL - 2018'!V$21*'SIOM from DLIM'!U158/SUM('SIOM from DLIM'!U$157:U$158) -> 995.48706 | AA19: ='OECD TTL - 2018'!$W$21*'SIOM from DLIM'!Z158/SUM('SIOM from DLIM'!$Z$157:$AB$158) -> 3.4483951 | AB19: ='OECD TTL - 2018'!$W$21*'SIOM from DLIM'!AA158/SUM('SIOM from DLIM'!$Z$157:$AB$158) -> 0 | AC19: ='OECD TTL - 2018'!$W$21*'SIOM from DLIM'!AB158/SUM('SIOM from DLIM'!$Z$157:$AB$158) -> 0 | AD19: ='OECD TTL - 2018'!X$21*'SIOM from DLIM'!W158/SUM('SIOM from DLIM'!W$157:W$158) -> 0 | AE19: ='OECD TTL - 2018'!Y$21*'SIOM from DLIM'!X158/SUM('SIOM from DLIM'!X$157:X$158) -> #DIV/0! | AF19: ='OECD TTL - 2018'!Z$21*'SIOM from DLIM'!Y158/SUM('SIOM from DLIM'!Y$157:Y$158) -> 2.1195807 | AG19: ='OECD TTL - 2018'!AA$21*'SIOM from DLIM'!Z158/SUM('SIOM from DLIM'!Z$157:Z$158) -> 0.29139292 | AH19: ='OECD TTL - 2018'!AB$21*'SIOM from DLIM'!AA158/SUM('SIOM from DLIM'!AA$157:AA$158) -> 0 | AI19: ='OECD TTL - 2018'!AC$21*'SIOM from DLIM'!AB158/SUM('SIOM from DLIM'!AB$157:AB$158) -> #DIV/0! | AJ19: ='OECD TTL - 2018'!AD$21*'SIOM from DLIM'!AC158/SUM('SIOM from DLIM'!AC$157:AC$158) -> 1.1648642 | AK19: ='OECD TTL - 2018'!AE$21*'SIOM from DLIM'!AD158/SUM('SIOM from DLIM'!AD$157:AD$158) -> #DIV/0! | ... AR19: ='OECD TTL - 2018'!AL$21*'SIOM from DLIM'!AK158/SUM('SIOM from DLIM'!AK$157:AK$158) -> #DIV/0!
A20: D25: Fabricated metal products | B20: metal products except machinery and vehicles 25 | C20: ='OECD TTL - 2018'!C22 -> 253.2 | D20: ='OECD TTL - 2018'!$D22*'SIOM from DLIM'!C159/SUM('SIOM from DLIM'!$C159:$D159) -> 33.4 | E20: ='OECD TTL - 2018'!$D22*'SIOM from DLIM'!D159/SUM('SIOM from DLIM'!$C159:$D159) -> 0 | F20: ='OECD TTL - 2018'!E22 -> 46.6 | G20: ='OECD TTL - 2018'!F22 -> 0.3 | H20: ='OECD TTL - 2018'!G22 -> 1028.8 | I20: ='OECD TTL - 2018'!H22 -> 366.2 | J20: ='OECD TTL - 2018'!I22 -> 305.4 | K20: ='OECD TTL - 2018'!J22 -> 231.6 | L20: ='OECD TTL - 2018'!K22 -> 520.1 | M20: ='OECD TTL - 2018'!$L22*'SIOM from DLIM'!L159/SUM('SIOM from DLIM'!$L159:$M159) -> 1091.6792 | N20: ='OECD TTL - 2018'!$L22*'SIOM from DLIM'!M159/SUM('SIOM from DLIM'!$L159:$M159) -> 331.92084 | O20: ='OECD TTL - 2018'!M22 -> 1279.7 | P20: ='OECD TTL - 2018'!$N22*'SIOM from DLIM'!O159/SUM('SIOM from DLIM'!$O159:$P159) -> 377.1999 | Q20: ='OECD TTL - 2018'!$N22*'SIOM from DLIM'!P159/SUM('SIOM from DLIM'!$O159:$P159) -> 395.0001 | R20: ='OECD TTL - 2018'!$O22*'SIOM from DLIM'!Q159/SUM('SIOM from DLIM'!$Q159:$R159) -> 3939.6866 | S20: ='OECD TTL - 2018'!$O22*'SIOM from DLIM'!R159/SUM('SIOM from DLIM'!$Q159:$R159) -> 1496.4134 | T20: ='OECD TTL - 2018'!P22 -> 13339.8 | U20: ='OECD TTL - 2018'!Q22 -> 4148.1 | V20: ='OECD TTL - 2018'!R22 -> 3181.5 | W20: ='OECD TTL - 2018'!S22 -> 9968 | X20: ='OECD TTL - 2018'!T22 -> 6669.1 | Y20: ='OECD TTL - 2018'!U22 -> 5604.3 | Z20: ='OECD TTL - 2018'!V22 -> 1245.4 | AA20: ='OECD TTL - 2018'!$W22*'SIOM from DLIM'!Z159/SUM('SIOM from DLIM'!$Z159:$AB159) -> 562.52595 | AB20: ='OECD TTL - 2018'!$W22*'SIOM from DLIM'!AA159/SUM('SIOM from DLIM'!$Z159:$AB159) -> 0 | AC20: ='OECD TTL - 2018'!$W22*'SIOM from DLIM'!AB159/SUM('SIOM from DLIM'!$Z159:$AB159) -> 417.27405 | AD20: ='OECD TTL - 2018'!X22 -> 12873.2 | AE20: ='OECD TTL - 2018'!Y22 -> 1534.8 | AF20: ='OECD TTL - 2018'!Z22 -> 633.4 | AG20: ='OECD TTL - 2018'!AA22 -> 373.9 | AH20: ='OECD TTL - 2018'!AB22 -> 62.5 | AI20: ='OECD TTL - 2018'!AC22 -> 99.4 | AJ20: ='OECD TTL - 2018'!AD22 -> 174.2 | AK20: ='OECD TTL - 2018'!AE22 -> 185.4 | ... AR20: ='OECD TTL - 2018'!AL22 -> 0
A21: D26: Computer, electronic and optical products | B21: computers and electronics 26 | C21: ='OECD TTL - 2018'!C23 -> 200.3 | D21: ='OECD TTL - 2018'!$D23*'SIOM from DLIM'!C160/SUM('SIOM from DLIM'!$C160:$D160) -> #DIV/0! | E21: ='OECD TTL - 2018'!$D23*'SIOM from DLIM'!D160/SUM('SIOM from DLIM'!$C160:$D160) -> #DIV/0! | F21: ='OECD TTL - 2018'!E23 -> 17.4 | G21: ='OECD TTL - 2018'!F23 -> 0 | H21: ='OECD TTL - 2018'!G23 -> 841.9 | I21: ='OECD TTL - 2018'!H23 -> 461.4 | J21: ='OECD TTL - 2018'!I23 -> 81.6 | K21: ='OECD TTL - 2018'!J23 -> 353.6 | L21: ='OECD TTL - 2018'!K23 -> 303 | M21: ='OECD TTL - 2018'!$L23*'SIOM from DLIM'!L160/SUM('SIOM from DLIM'!$L160:$M160) -> 1075.1298 | N21: ='OECD TTL - 2018'!$L23*'SIOM from DLIM'!M160/SUM('SIOM from DLIM'!$L160:$M160) -> 211.27019 | O21: ='OECD TTL - 2018'!M23 -> 854 | P21: ='OECD TTL - 2018'!$N23*'SIOM from DLIM'!O160/SUM('SIOM from DLIM'!$O160:$P160) -> #DIV/0! | Q21: ='OECD TTL - 2018'!$N23*'SIOM from DLIM'!P160/SUM('SIOM from DLIM'!$O160:$P160) -> #DIV/0! | R21: ='OECD TTL - 2018'!$O23*'SIOM from DLIM'!Q160/SUM('SIOM from DLIM'!$Q160:$R160) -> 577.3 | S21: ='OECD TTL - 2018'!$O23*'SIOM from DLIM'!R160/SUM('SIOM from DLIM'!$Q160:$R160) -> 0 | T21: ='OECD TTL - 2018'!P23 -> 1195.6 | U21: ='OECD TTL - 2018'!Q23 -> 112588.6 | V21: ='OECD TTL - 2018'!R23 -> 6592.5 | W21: ='OECD TTL - 2018'!S23 -> 4884.6 | X21: ='OECD TTL - 2018'!T23 -> 4188.4 | Y21: ='OECD TTL - 2018'!U23 -> 2437.4 | Z21: ='OECD TTL - 2018'!V23 -> 896 | AA21: ='OECD TTL - 2018'!$W23*'SIOM from DLIM'!Z160/SUM('SIOM from DLIM'!$Z160:$AB160) -> 0 | AB21: ='OECD TTL - 2018'!$W23*'SIOM from DLIM'!AA160/SUM('SIOM from DLIM'!$Z160:$AB160) -> 0 | AC21: ='OECD TTL - 2018'!$W23*'SIOM from DLIM'!AB160/SUM('SIOM from DLIM'!$Z160:$AB160) -> 1036.9 | AD21: ='OECD TTL - 2018'!X23 -> 3275.3 | AE21: ='OECD TTL - 2018'!Y23 -> 4141.2 | AF21: ='OECD TTL - 2018'!Z23 -> 819.1 | AG21: ='OECD TTL - 2018'!AA23 -> 708.6 | AH21: ='OECD TTL - 2018'!AB23 -> 745.4 | AI21: ='OECD TTL - 2018'!AC23 -> 4517 | AJ21: ='OECD TTL - 2018'!AD23 -> 3612 | AK21: ='OECD TTL - 2018'!AE23 -> 1451.6 | ... AR21: ='OECD TTL - 2018'!AL23 -> 0
A22: D27: Electrical equipment | B22: appliances and electrical equipment 27 | C22: ='OECD TTL - 2018'!C24 -> 60.2 | D22: ='OECD TTL - 2018'!$D24*'SIOM from DLIM'!C161/SUM('SIOM from DLIM'!$C161:$D161) -> 10.2 | E22: ='OECD TTL - 2018'!$D24*'SIOM from DLIM'!D161/SUM('SIOM from DLIM'!$C161:$D161) -> 0 | F22: ='OECD TTL - 2018'!E24 -> 13 | G22: ='OECD TTL - 2018'!F24 -> 0 | H22: ='OECD TTL - 2018'!G24 -> 116.6 | I22: ='OECD TTL - 2018'!H24 -> 91.8 | J22: ='OECD TTL - 2018'!I24 -> 29.2 | K22: ='OECD TTL - 2018'!J24 -> 75.1 | L22: ='OECD TTL - 2018'!K24 -> 117.1 | M22: ='OECD TTL - 2018'!$L24*'SIOM from DLIM'!L161/SUM('SIOM from DLIM'!$L161:$M161) -> 353.84632 | N22: ='OECD TTL - 2018'!$L24*'SIOM from DLIM'!M161/SUM('SIOM from DLIM'!$L161:$M161) -> 59.953678 | O22: ='OECD TTL - 2018'!M24 -> 287 | P22: ='OECD TTL - 2018'!$N24*'SIOM from DLIM'!O161/SUM('SIOM from DLIM'!$O161:$P161) -> 175 | Q22: ='OECD TTL - 2018'!$N24*'SIOM from DLIM'!P161/SUM('SIOM from DLIM'!$O161:$P161) -> 0 | R22: ='OECD TTL - 2018'!$O24*'SIOM from DLIM'!Q161/SUM('SIOM from DLIM'!$Q161:$R161) -> 1111.7794 | S22: ='OECD TTL - 2018'!$O24*'SIOM from DLIM'!R161/SUM('SIOM from DLIM'!$Q161:$R161) -> 70.120555 | T22: ='OECD TTL - 2018'!P24 -> 960.3 | U22: ='OECD TTL - 2018'!Q24 -> 10712 | V22: ='OECD TTL - 2018'!R24 -> 13043.5 | W22: ='OECD TTL - 2018'!S24 -> 4425.5 | X22: ='OECD TTL - 2018'!T24 -> 4157.4 | Y22: ='OECD TTL - 2018'!U24 -> 2140.2 | Z22: ='OECD TTL - 2018'!V24 -> 409.2 | AA22: ='OECD TTL - 2018'!$W24*'SIOM from DLIM'!Z161/SUM('SIOM from DLIM'!$Z161:$AB161) -> 1316.1687 | AB22: ='OECD TTL - 2018'!$W24*'SIOM from DLIM'!AA161/SUM('SIOM from DLIM'!$Z161:$AB161) -> 0 | AC22: ='OECD TTL - 2018'!$W24*'SIOM from DLIM'!AB161/SUM('SIOM from DLIM'!$Z161:$AB161) -> 341.23127 | AD22: ='OECD TTL - 2018'!X24 -> 6006.3 | AE22: ='OECD TTL - 2018'!Y24 -> 1100.1 | AF22: ='OECD TTL - 2018'!Z24 -> 460.7 | AG22: ='OECD TTL - 2018'!AA24 -> 154.6 | AH22: ='OECD TTL - 2018'!AB24 -> 100.7 | AI22: ='OECD TTL - 2018'!AC24 -> 620.9 | AJ22: ='OECD TTL - 2018'!AD24 -> 368.8 | AK22: ='OECD TTL - 2018'!AE24 -> 170.6 | ... AR22: ='OECD TTL - 2018'!AL24 -> 0
A23: D28: Machinery and equipment, nec | B23: other machinery 28 | C23: ='OECD TTL - 2018'!C25 -> 424.4 | D23: ='OECD TTL - 2018'!$D25*'SIOM from DLIM'!C162/SUM('SIOM from DLIM'!$C162:$D162) -> 66.7 | E23: ='OECD TTL - 2018'!$D25*'SIOM from DLIM'!D162/SUM('SIOM from DLIM'!$C162:$D162) -> 0 | F23: ='OECD TTL - 2018'!E25 -> 113.3 | G23: ='OECD TTL - 2018'!F25 -> 0.9 | H23: ='OECD TTL - 2018'!G25 -> 362.1 | I23: ='OECD TTL - 2018'!H25 -> 441.3 | J23: ='OECD TTL - 2018'!I25 -> 125.7 | K23: ='OECD TTL - 2018'!J25 -> 400.1 | L23: ='OECD TTL - 2018'!K25 -> 542.4 | M23: ='OECD TTL - 2018'!$L25*'SIOM from DLIM'!L162/SUM('SIOM from DLIM'!$L162:$M162) -> 518.30193 | N23: ='OECD TTL - 2018'!$L25*'SIOM from DLIM'!M162/SUM('SIOM from DLIM'!$L162:$M162) -> 407.09807 | O23: ='OECD TTL - 2018'!M25 -> 824.4 | P23: ='OECD TTL - 2018'!$N25*'SIOM from DLIM'!O162/SUM('SIOM from DLIM'!$O162:$P162) -> 531.35902 | Q23: ='OECD TTL - 2018'!$N25*'SIOM from DLIM'!P162/SUM('SIOM from DLIM'!$O162:$P162) -> 195.84098 | R23: ='OECD TTL - 2018'!$O25*'SIOM from DLIM'!Q162/SUM('SIOM from DLIM'!$Q162:$R162) -> 1897.2519 | S23: ='OECD TTL - 2018'!$O25*'SIOM from DLIM'!R162/SUM('SIOM from DLIM'!$Q162:$R162) -> 450.04807 | T23: ='OECD TTL - 2018'!P25 -> 2072.8 | U23: ='OECD TTL - 2018'!Q25 -> 3986.3 | V23: ='OECD TTL - 2018'!R25 -> 2139.4 | W23: ='OECD TTL - 2018'!S25 -> 15423.9 | X23: ='OECD TTL - 2018'!T25 -> 6001.7 | Y23: ='OECD TTL - 2018'!U25 -> 5368.8 | Z23: ='OECD TTL - 2018'!V25 -> 601.9 | AA23: ='OECD TTL - 2018'!$W25*'SIOM from DLIM'!Z162/SUM('SIOM from DLIM'!$Z162:$AB162) -> 508.85291 | AB23: ='OECD TTL - 2018'!$W25*'SIOM from DLIM'!AA162/SUM('SIOM from DLIM'!$Z162:$AB162) -> 0 | AC23: ='OECD TTL - 2018'!$W25*'SIOM from DLIM'!AB162/SUM('SIOM from DLIM'!$Z162:$AB162) -> 513.44709 | AD23: ='OECD TTL - 2018'!X25 -> 4751.7 | AE23: ='OECD TTL - 2018'!Y25 -> 1482.9 | AF23: ='OECD TTL - 2018'!Z25 -> 789.4 | AG23: ='OECD TTL - 2018'!AA25 -> 146.6 | AH23: ='OECD TTL - 2018'!AB25 -> 86 | AI23: ='OECD TTL - 2018'!AC25 -> 191.7 | AJ23: ='OECD TTL - 2018'!AD25 -> 256.6 | AK23: ='OECD TTL - 2018'!AE25 -> 209.7 | ... AR23: ='OECD TTL - 2018'!AL25 -> 0
A24: D29: Motor vehicles, trailers and semi-trailers | B24: road vehicles 29 | C24: ='OECD TTL - 2018'!C26 -> 120.6 | D24: ='OECD TTL - 2018'!$D26*'SIOM from DLIM'!C163/SUM('SIOM from DLIM'!$C163:$D163) -> #DIV/0! | E24: ='OECD TTL - 2018'!$D26*'SIOM from DLIM'!D163/SUM('SIOM from DLIM'!$C163:$D163) -> #DIV/0! | F24: ='OECD TTL - 2018'!E26 -> 20.9 | G24: ='OECD TTL - 2018'!F26 -> 0 | H24: ='OECD TTL - 2018'!G26 -> 158.5 | I24: ='OECD TTL - 2018'!H26 -> 132.1 | J24: ='OECD TTL - 2018'!I26 -> 54 | K24: ='OECD TTL - 2018'!J26 -> 74.7 | L24: ='OECD TTL - 2018'!K26 -> 114 | M24: ='OECD TTL - 2018'!$L26*'SIOM from DLIM'!L163/SUM('SIOM from DLIM'!$L163:$M163) -> 304.74552 | N24: ='OECD TTL - 2018'!$L26*'SIOM from DLIM'!M163/SUM('SIOM from DLIM'!$L163:$M163) -> 54.25448 | O24: ='OECD TTL - 2018'!M26 -> 425.7 | P24: ='OECD TTL - 2018'!$N26*'SIOM from DLIM'!O163/SUM('SIOM from DLIM'!$O163:$P163) -> 22.09568 | Q24: ='OECD TTL - 2018'!$N26*'SIOM from DLIM'!P163/SUM('SIOM from DLIM'!$O163:$P163) -> 203.50432 | R24: ='OECD TTL - 2018'!$O26*'SIOM from DLIM'!Q163/SUM('SIOM from DLIM'!$Q163:$R163) -> 152.23773 | S24: ='OECD TTL - 2018'!$O26*'SIOM from DLIM'!R163/SUM('SIOM from DLIM'!$Q163:$R163) -> 127.86227 | T24: ='OECD TTL - 2018'!P26 -> 622.8 | U24: ='OECD TTL - 2018'!Q26 -> 952.2 | V24: ='OECD TTL - 2018'!R26 -> 1015.6 | W24: ='OECD TTL - 2018'!S26 -> 2558 | X24: ='OECD TTL - 2018'!T26 -> 58680.3 | Y24: ='OECD TTL - 2018'!U26 -> 749.9 | Z24: ='OECD TTL - 2018'!V26 -> 247.2 | AA24: ='OECD TTL - 2018'!$W26*'SIOM from DLIM'!Z163/SUM('SIOM from DLIM'!$Z163:$AB163) -> 21.663199 | AB24: ='OECD TTL - 2018'!$W26*'SIOM from DLIM'!AA163/SUM('SIOM from DLIM'!$Z163:$AB163) -> 3.2818047 | AC24: ='OECD TTL - 2018'!$W26*'SIOM from DLIM'!AB163/SUM('SIOM from DLIM'!$Z163:$AB163) -> 397.055 | AD24: ='OECD TTL - 2018'!X26 -> 1007.6 | AE24: ='OECD TTL - 2018'!Y26 -> 2872.9 | AF24: ='OECD TTL - 2018'!Z26 -> 2198.6 | AG24: ='OECD TTL - 2018'!AA26 -> 136 | AH24: ='OECD TTL - 2018'!AB26 -> 60.1 | AI24: ='OECD TTL - 2018'!AC26 -> 95.9 | AJ24: ='OECD TTL - 2018'!AD26 -> 113 | AK24: ='OECD TTL - 2018'!AE26 -> 164.3 | ... AR24: ='OECD TTL - 2018'!AL26 -> 0
A25: D30: Other transport equipment | B25: nonroad vehicles 30 | C25: ='OECD TTL - 2018'!C27 -> 64.9 | D25: ='OECD TTL - 2018'!$D27*'SIOM from DLIM'!C164/SUM('SIOM from DLIM'!$C164:$D164) -> 7.1879115 | E25: ='OECD TTL - 2018'!$D27*'SIOM from DLIM'!D164/SUM('SIOM from DLIM'!$C164:$D164) -> 0.012088489 | F25: ='OECD TTL - 2018'!E27 -> 8.4 | G25: ='OECD TTL - 2018'!F27 -> 0.1 | H25: ='OECD TTL - 2018'!G27 -> 66.8 | I25: ='OECD TTL - 2018'!H27 -> 34.8 | J25: ='OECD TTL - 2018'!I27 -> 20.7 | K25: ='OECD TTL - 2018'!J27 -> 30.3 | L25: ='OECD TTL - 2018'!K27 -> 60.7 | M25: ='OECD TTL - 2018'!$L27*'SIOM from DLIM'!L164/SUM('SIOM from DLIM'!$L164:$M164) -> 0 | N25: ='OECD TTL - 2018'!$L27*'SIOM from DLIM'!M164/SUM('SIOM from DLIM'!$L164:$M164) -> 123.3 | O25: ='OECD TTL - 2018'!M27 -> 110.4 | P25: ='OECD TTL - 2018'!$N27*'SIOM from DLIM'!O164/SUM('SIOM from DLIM'!$O164:$P164) -> 79.5 | Q25: ='OECD TTL - 2018'!$N27*'SIOM from DLIM'!P164/SUM('SIOM from DLIM'!$O164:$P164) -> 0 | R25: ='OECD TTL - 2018'!$O27*'SIOM from DLIM'!Q164/SUM('SIOM from DLIM'!$Q164:$R164) -> 381.2 | S25: ='OECD TTL - 2018'!$O27*'SIOM from DLIM'!R164/SUM('SIOM from DLIM'!$Q164:$R164) -> 0 | T25: ='OECD TTL - 2018'!P27 -> 716.7 | U25: ='OECD TTL - 2018'!Q27 -> 778.9 | V25: ='OECD TTL - 2018'!R27 -> 747.3 | W25: ='OECD TTL - 2018'!S27 -> 1463.8 | X25: ='OECD TTL - 2018'!T27 -> 709.1 | Y25: ='OECD TTL - 2018'!U27 -> 7144 | Z25: ='OECD TTL - 2018'!V27 -> 97.8 | AA25: ='OECD TTL - 2018'!$W27*'SIOM from DLIM'!Z164/SUM('SIOM from DLIM'!$Z164:$AB164) -> 61.445611 | AB25: ='OECD TTL - 2018'!$W27*'SIOM from DLIM'!AA164/SUM('SIOM from DLIM'!$Z164:$AB164) -> 14.555606 | AC25: ='OECD TTL - 2018'!$W27*'SIOM from DLIM'!AB164/SUM('SIOM from DLIM'!$Z164:$AB164) -> 77.098783 | AD25: ='OECD TTL - 2018'!X27 -> 1085.6 | AE25: ='OECD TTL - 2018'!Y27 -> 255.2 | AF25: ='OECD TTL - 2018'!Z27 -> 1330 | AG25: ='OECD TTL - 2018'!AA27 -> 30.9 | AH25: ='OECD TTL - 2018'!AB27 -> 12.9 | AI25: ='OECD TTL - 2018'!AC27 -> 46.8 | AJ25: ='OECD TTL - 2018'!AD27 -> 40.2 | AK25: ='OECD TTL - 2018'!AE27 -> 30.4 | ... AR25: ='OECD TTL - 2018'!AL27 -> 0
A26: D31T33: Other manufacturing; repair and installation of machinery and equipment | B26: other manufacturing 31T33 | C26: ='OECD TTL - 2018'!C28 -> 69.4 | D26: ='OECD TTL - 2018'!$D28*'SIOM from DLIM'!C165/SUM('SIOM from DLIM'!$C165:$D165) -> #DIV/0! | E26: ='OECD TTL - 2018'!$D28*'SIOM from DLIM'!D165/SUM('SIOM from DLIM'!$C165:$D165) -> #DIV/0! | F26: ='OECD TTL - 2018'!E28 -> 5 | G26: ='OECD TTL - 2018'!F28 -> 0 | H26: ='OECD TTL - 2018'!G28 -> 97.5 | I26: ='OECD TTL - 2018'!H28 -> 100 | J26: ='OECD TTL - 2018'!I28 -> 23.6 | K26: ='OECD TTL - 2018'!J28 -> 60.7 | L26: ='OECD TTL - 2018'!K28 -> 76.6 | M26: ='OECD TTL - 2018'!$L28*'SIOM from DLIM'!L165/SUM('SIOM from DLIM'!$L165:$M165) -> 148.4088 | N26: ='OECD TTL - 2018'!$L28*'SIOM from DLIM'!M165/SUM('SIOM from DLIM'!$L165:$M165) -> 33.591205 | O26: ='OECD TTL - 2018'!M28 -> 94 | P26: ='OECD TTL - 2018'!$N28*'SIOM from DLIM'!O165/SUM('SIOM from DLIM'!$O165:$P165) -> 92.4 | Q26: ='OECD TTL - 2018'!$N28*'SIOM from DLIM'!P165/SUM('SIOM from DLIM'!$O165:$P165) -> 0 | R26: ='OECD TTL - 2018'!$O28*'SIOM from DLIM'!Q165/SUM('SIOM from DLIM'!$Q165:$R165) -> 227.73887 | S26: ='OECD TTL - 2018'!$O28*'SIOM from DLIM'!R165/SUM('SIOM from DLIM'!$Q165:$R165) -> 288.76113 | T26: ='OECD TTL - 2018'!P28 -> 184.2 | U26: ='OECD TTL - 2018'!Q28 -> 455.7 | V26: ='OECD TTL - 2018'!R28 -> 172.1 | W26: ='OECD TTL - 2018'!S28 -> 344.5 | X26: ='OECD TTL - 2018'!T28 -> 246.9 | Y26: ='OECD TTL - 2018'!U28 -> 292.4 | Z26: ='OECD TTL - 2018'!V28 -> 192.3 | AA26: ='OECD TTL - 2018'!$W28*'SIOM from DLIM'!Z165/SUM('SIOM from DLIM'!$Z165:$AB165) -> 0 | AB26: ='OECD TTL - 2018'!$W28*'SIOM from DLIM'!AA165/SUM('SIOM from DLIM'!$Z165:$AB165) -> 0 | AC26: ='OECD TTL - 2018'!$W28*'SIOM from DLIM'!AB165/SUM('SIOM from DLIM'!$Z165:$AB165) -> 223 | AD26: ='OECD TTL - 2018'!X28 -> 372.6 | AE26: ='OECD TTL - 2018'!Y28 -> 226.9 | AF26: ='OECD TTL - 2018'!Z28 -> 340.8 | AG26: ='OECD TTL - 2018'!AA28 -> 60.2 | AH26: ='OECD TTL - 2018'!AB28 -> 28.3 | AI26: ='OECD TTL - 2018'!AC28 -> 71 | AJ26: ='OECD TTL - 2018'!AD28 -> 49.6 | AK26: ='OECD TTL - 2018'!AE28 -> 72.9 | ... AR26: ='OECD TTL - 2018'!AL28 -> 0
A27: electricity | C27: ='OECD TTL - 2018'!C$29*'SIOM from DLIM'!B166/SUM('SIOM from DLIM'!B$166:B$168) -> 449.59069 | D27: ='OECD TTL - 2018'!$D$29*'SIOM from DLIM'!C166/SUM('SIOM from DLIM'!$C$166:$D$168) -> 0 | E27: ='OECD TTL - 2018'!$D$29*'SIOM from DLIM'!D166/SUM('SIOM from DLIM'!$C$166:$D$168) -> 0 | F27: ='OECD TTL - 2018'!E$29*'SIOM from DLIM'!D166/SUM('SIOM from DLIM'!D$166:D$168) -> 0 | G27: ='OECD TTL - 2018'!F$29*'SIOM from DLIM'!E166/SUM('SIOM from DLIM'!E$166:E$168) -> 0 | H27: ='OECD TTL - 2018'!G$29*'SIOM from DLIM'!F166/SUM('SIOM from DLIM'!F$166:F$168) -> 0 | I27: ='OECD TTL - 2018'!H$29*'SIOM from DLIM'!G166/SUM('SIOM from DLIM'!G$166:G$168) -> 140.75557 | J27: ='OECD TTL - 2018'!I$29*'SIOM from DLIM'!H166/SUM('SIOM from DLIM'!H$166:H$168) -> 103.48796 | K27: ='OECD TTL - 2018'!J$29*'SIOM from DLIM'!I166/SUM('SIOM from DLIM'!I$166:I$168) -> 672.11768 | L27: ='OECD TTL - 2018'!K$29*'SIOM from DLIM'!J166/SUM('SIOM from DLIM'!J$166:J$168) -> 370.66463 | M27: ='OECD TTL - 2018'!$L$29*'SIOM from DLIM'!L166/SUM('SIOM from DLIM'!$L$166:$M$168) -> 3535.1966 | N27: ='OECD TTL - 2018'!$L$29*'SIOM from DLIM'!M166/SUM('SIOM from DLIM'!$L$166:$M$168) -> 210.49255 | O27: ='OECD TTL - 2018'!M$29*'SIOM from DLIM'!L166/SUM('SIOM from DLIM'!L$166:L$168) -> 1214.5759 | P27: ='OECD TTL - 2018'!$N$29*'SIOM from DLIM'!O166/SUM('SIOM from DLIM'!$O$166:$P$168) -> 54.903147 | Q27: ='OECD TTL - 2018'!$N$29*'SIOM from DLIM'!P166/SUM('SIOM from DLIM'!$O$166:$P$168) -> 168.38278 | R27: ='OECD TTL - 2018'!$O$29*'SIOM from DLIM'!Q166/SUM('SIOM from DLIM'!$Q$166:$R$168) -> 2333.1005 | S27: ='OECD TTL - 2018'!$O$29*'SIOM from DLIM'!R166/SUM('SIOM from DLIM'!$Q$166:$R$168) -> 1182.5736 | T27: ='OECD TTL - 2018'!P$29*'SIOM from DLIM'!O166/SUM('SIOM from DLIM'!O$166:O$168) -> 50.834825 | U27: ='OECD TTL - 2018'!Q$29*'SIOM from DLIM'!P166/SUM('SIOM from DLIM'!P$166:P$168) -> 1191.2628 | V27: ='OECD TTL - 2018'!R$29*'SIOM from DLIM'!Q166/SUM('SIOM from DLIM'!Q$166:Q$168) -> 262.70702 | W27: ='OECD TTL - 2018'!S$29*'SIOM from DLIM'!R166/SUM('SIOM from DLIM'!R$166:R$168) -> 616.863 | X27: ='OECD TTL - 2018'!T$29*'SIOM from DLIM'!S166/SUM('SIOM from DLIM'!S$166:S$168) -> 182.85872 | Y27: ='OECD TTL - 2018'!U$29*'SIOM from DLIM'!T166/SUM('SIOM from DLIM'!T$166:T$168) -> 465.24842 | Z27: ='OECD TTL - 2018'!V$29*'SIOM from DLIM'!U166/SUM('SIOM from DLIM'!U$166:U$168) -> 24.194458 | AA27: ='OECD TTL - 2018'!$W$29*'SIOM from DLIM'!Z166/SUM('SIOM from DLIM'!$Z$166:$AB$168) -> 49.812259 | AB27: ='OECD TTL - 2018'!$W$29*'SIOM from DLIM'!AA166/SUM('SIOM from DLIM'!$Z$166:$AB$168) -> 0 | AC27: ='OECD TTL - 2018'!$W$29*'SIOM from DLIM'!AB166/SUM('SIOM from DLIM'!$Z$166:$AB$168) -> 297.8637 | AD27: ='OECD TTL - 2018'!X$29*'SIOM from DLIM'!W166/SUM('SIOM from DLIM'!W$166:W$168) -> 191.19395 | AE27: ='OECD TTL - 2018'!Y$29*'SIOM from DLIM'!X166/SUM('SIOM from DLIM'!X$166:X$168) -> 0 | AF27: ='OECD TTL - 2018'!Z$29*'SIOM from DLIM'!Y166/SUM('SIOM from DLIM'!Y$166:Y$168) -> 374.45322 | AG27: ='OECD TTL - 2018'!AA$29*'SIOM from DLIM'!Z166/SUM('SIOM from DLIM'!Z$166:Z$168) -> 5.4596905 | AH27: ='OECD TTL - 2018'!AB$29*'SIOM from DLIM'!AA166/SUM('SIOM from DLIM'!AA$166:AA$168) -> 0 | AI27: ='OECD TTL - 2018'!AC$29*'SIOM from DLIM'!AB166/SUM('SIOM from DLIM'!AB$166:AB$168) -> 64.123486 | AJ27: ='OECD TTL - 2018'!AD$29*'SIOM from DLIM'!AC166/SUM('SIOM from DLIM'!AC$166:AC$168) -> 44.590543 | AK27: ='OECD TTL - 2018'!AE$29*'SIOM from DLIM'!AD166/SUM('SIOM from DLIM'!AD$166:AD$168) -> 0 | ... AR27: ='OECD TTL - 2018'!AL$29*'SIOM from DLIM'!AK166/SUM('SIOM from DLIM'!AK$166:AK$168) -> 0
A28: energy pipelines and gas processing 352T353 | B28: energy pipelines and gas processing 352T353 | C28: ='OECD TTL - 2018'!C$29*'SIOM from DLIM'!B167/SUM('SIOM from DLIM'!B$166:B$168) -> 67.909309 | D28: ='OECD TTL - 2018'!$D$29*'SIOM from DLIM'!C167/SUM('SIOM from DLIM'!$C$166:$D$168) -> 74.317402 | E28: ='OECD TTL - 2018'!$D$29*'SIOM from DLIM'!D167/SUM('SIOM from DLIM'!$C$166:$D$168) -> 4.8825983 | F28: ='OECD TTL - 2018'!E$29*'SIOM from DLIM'!D167/SUM('SIOM from DLIM'!D$166:D$168) -> 131.9 | G28: ='OECD TTL - 2018'!F$29*'SIOM from DLIM'!E167/SUM('SIOM from DLIM'!E$166:E$168) -> 0 | H28: ='OECD TTL - 2018'!G$29*'SIOM from DLIM'!F167/SUM('SIOM from DLIM'!F$166:F$168) -> 0 | I28: ='OECD TTL - 2018'!H$29*'SIOM from DLIM'!G167/SUM('SIOM from DLIM'!G$166:G$168) -> 42.259803 | J28: ='OECD TTL - 2018'!I$29*'SIOM from DLIM'!H167/SUM('SIOM from DLIM'!H$166:H$168) -> 50.69442 | K28: ='OECD TTL - 2018'!J$29*'SIOM from DLIM'!I167/SUM('SIOM from DLIM'!I$166:I$168) -> 218.8586 | L28: ='OECD TTL - 2018'!K$29*'SIOM from DLIM'!J167/SUM('SIOM from DLIM'!J$166:J$168) -> 95.44429 | M28: ='OECD TTL - 2018'!$L$29*'SIOM from DLIM'!L167/SUM('SIOM from DLIM'!$L$166:$M$168) -> 58.108617 | N28: ='OECD TTL - 2018'!$L$29*'SIOM from DLIM'!M167/SUM('SIOM from DLIM'!$L$166:$M$168) -> 2.4345385 | O28: ='OECD TTL - 2018'!M$29*'SIOM from DLIM'!L167/SUM('SIOM from DLIM'!L$166:L$168) -> 19.964187 | P28: ='OECD TTL - 2018'!$N$29*'SIOM from DLIM'!O167/SUM('SIOM from DLIM'!$O$166:$P$168) -> 246.15175 | Q28: ='OECD TTL - 2018'!$N$29*'SIOM from DLIM'!P167/SUM('SIOM from DLIM'!$O$166:$P$168) -> 71.032701 | R28: ='OECD TTL - 2018'!$O$29*'SIOM from DLIM'!Q167/SUM('SIOM from DLIM'!$Q$166:$R$168) -> 3579.5288 | S28: ='OECD TTL - 2018'!$O$29*'SIOM from DLIM'!R167/SUM('SIOM from DLIM'!$Q$166:$R$168) -> 966.07145 | T28: ='OECD TTL - 2018'!P$29*'SIOM from DLIM'!O167/SUM('SIOM from DLIM'!O$166:O$168) -> 227.91191 | U28: ='OECD TTL - 2018'!Q$29*'SIOM from DLIM'!P167/SUM('SIOM from DLIM'!P$166:P$168) -> 502.53722 | V28: ='OECD TTL - 2018'!R$29*'SIOM from DLIM'!Q167/SUM('SIOM from DLIM'!Q$166:Q$168) -> 403.05481 | W28: ='OECD TTL - 2018'!S$29*'SIOM from DLIM'!R167/SUM('SIOM from DLIM'!R$166:R$168) -> 503.92953 | X28: ='OECD TTL - 2018'!T$29*'SIOM from DLIM'!S167/SUM('SIOM from DLIM'!S$166:S$168) -> 234.2327 | Y28: ='OECD TTL - 2018'!U$29*'SIOM from DLIM'!T167/SUM('SIOM from DLIM'!T$166:T$168) -> 410.41359 | Z28: ='OECD TTL - 2018'!V$29*'SIOM from DLIM'!U167/SUM('SIOM from DLIM'!U$166:U$168) -> 131.10649 | AA28: ='OECD TTL - 2018'!$W$29*'SIOM from DLIM'!Z167/SUM('SIOM from DLIM'!$Z$166:$AB$168) -> 11910.681 | AB28: ='OECD TTL - 2018'!$W$29*'SIOM from DLIM'!AA167/SUM('SIOM from DLIM'!$Z$166:$AB$168) -> 92.982108 | AC28: ='OECD TTL - 2018'!$W$29*'SIOM from DLIM'!AB167/SUM('SIOM from DLIM'!$Z$166:$AB$168) -> 197.16818 | AD28: ='OECD TTL - 2018'!X$29*'SIOM from DLIM'!W167/SUM('SIOM from DLIM'!W$166:W$168) -> 42.991268 | AE28: ='OECD TTL - 2018'!Y$29*'SIOM from DLIM'!X167/SUM('SIOM from DLIM'!X$166:X$168) -> 0 | AF28: ='OECD TTL - 2018'!Z$29*'SIOM from DLIM'!Y167/SUM('SIOM from DLIM'!Y$166:Y$168) -> 175.21425 | AG28: ='OECD TTL - 2018'!AA$29*'SIOM from DLIM'!Z167/SUM('SIOM from DLIM'!Z$166:Z$168) -> 1305.4745 | AH28: ='OECD TTL - 2018'!AB$29*'SIOM from DLIM'!AA167/SUM('SIOM from DLIM'!AA$166:AA$168) -> 328.4 | AI28: ='OECD TTL - 2018'!AC$29*'SIOM from DLIM'!AB167/SUM('SIOM from DLIM'!AB$166:AB$168) -> 42.445961 | AJ28: ='OECD TTL - 2018'!AD$29*'SIOM from DLIM'!AC167/SUM('SIOM from DLIM'!AC$166:AC$168) -> 41.376578 | AK28: ='OECD TTL - 2018'!AE$29*'SIOM from DLIM'!AD167/SUM('SIOM from DLIM'!AD$166:AD$168) -> 0 | ... AR28: ='OECD TTL - 2018'!AL$29*'SIOM from DLIM'!AK167/SUM('SIOM from DLIM'!AK$166:AK$168) -> 0
A29: water and waste 36T39 | B29: water and waste 36T39 | C29: ='OECD TTL - 2018'!C$29*'SIOM from DLIM'!B168/SUM('SIOM from DLIM'!B$166:B$168) -> 0 | D29: ='OECD TTL - 2018'!$D$29*'SIOM from DLIM'!C168/SUM('SIOM from DLIM'!$C$166:$D$168) -> 0 | E29: ='OECD TTL - 2018'!$D$29*'SIOM from DLIM'!D168/SUM('SIOM from DLIM'!$C$166:$D$168) -> 0 | F29: ='OECD TTL - 2018'!E$29*'SIOM from DLIM'!D168/SUM('SIOM from DLIM'!D$166:D$168) -> 0 | G29: ='OECD TTL - 2018'!F$29*'SIOM from DLIM'!E168/SUM('SIOM from DLIM'!E$166:E$168) -> 0.3 | H29: ='OECD TTL - 2018'!G$29*'SIOM from DLIM'!F168/SUM('SIOM from DLIM'!F$166:F$168) -> 1097.3 | I29: ='OECD TTL - 2018'!H$29*'SIOM from DLIM'!G168/SUM('SIOM from DLIM'!G$166:G$168) -> 940.98462 | J29: ='OECD TTL - 2018'!I$29*'SIOM from DLIM'!H168/SUM('SIOM from DLIM'!H$166:H$168) -> 109.71762 | K29: ='OECD TTL - 2018'!J$29*'SIOM from DLIM'!I168/SUM('SIOM from DLIM'!I$166:I$168) -> 597.52372 | L29: ='OECD TTL - 2018'!K$29*'SIOM from DLIM'!J168/SUM('SIOM from DLIM'!J$166:J$168) -> 1131.2911 | M29: ='OECD TTL - 2018'!$L$29*'SIOM from DLIM'!L168/SUM('SIOM from DLIM'!$L$166:$M$168) -> 1470.0489 | N29: ='OECD TTL - 2018'!$L$29*'SIOM from DLIM'!M168/SUM('SIOM from DLIM'!$L$166:$M$168) -> 67.618817 | O29: ='OECD TTL - 2018'!M$29*'SIOM from DLIM'!L168/SUM('SIOM from DLIM'!L$166:L$168) -> 505.05987 | P29: ='OECD TTL - 2018'!$N$29*'SIOM from DLIM'!O168/SUM('SIOM from DLIM'!$O$166:$P$168) -> 1575.9296 | Q29: ='OECD TTL - 2018'!$N$29*'SIOM from DLIM'!P168/SUM('SIOM from DLIM'!$O$166:$P$168) -> 0 | R29: ='OECD TTL - 2018'!$O$29*'SIOM from DLIM'!Q168/SUM('SIOM from DLIM'!$Q$166:$R$168) -> 1253.4477 | S29: ='OECD TTL - 2018'!$O$29*'SIOM from DLIM'!R168/SUM('SIOM from DLIM'!$Q$166:$R$168) -> 687.47796 | T29: ='OECD TTL - 2018'!P$29*'SIOM from DLIM'!O168/SUM('SIOM from DLIM'!O$166:O$168) -> 1459.1533 | U29: ='OECD TTL - 2018'!Q$29*'SIOM from DLIM'!P168/SUM('SIOM from DLIM'!P$166:P$168) -> 0 | V29: ='OECD TTL - 2018'!R$29*'SIOM from DLIM'!Q168/SUM('SIOM from DLIM'!Q$166:Q$168) -> 141.13817 | W29: ='OECD TTL - 2018'!S$29*'SIOM from DLIM'!R168/SUM('SIOM from DLIM'!R$166:R$168) -> 358.60747 | X29: ='OECD TTL - 2018'!T$29*'SIOM from DLIM'!S168/SUM('SIOM from DLIM'!S$166:S$168) -> 830.20858 | Y29: ='OECD TTL - 2018'!U$29*'SIOM from DLIM'!T168/SUM('SIOM from DLIM'!T$166:T$168) -> 11.837988 | Z29: ='OECD TTL - 2018'!V$29*'SIOM from DLIM'!U168/SUM('SIOM from DLIM'!U$166:U$168) -> 221.19905 | AA29: ='OECD TTL - 2018'!$W$29*'SIOM from DLIM'!Z168/SUM('SIOM from DLIM'!$Z$166:$AB$168) -> 2501.3907 | AB29: ='OECD TTL - 2018'!$W$29*'SIOM from DLIM'!AA168/SUM('SIOM from DLIM'!$Z$166:$AB$168) -> 0 | AC29: ='OECD TTL - 2018'!$W$29*'SIOM from DLIM'!AB168/SUM('SIOM from DLIM'!$Z$166:$AB$168) -> 1952.5016 | AD29: ='OECD TTL - 2018'!X$29*'SIOM from DLIM'!W168/SUM('SIOM from DLIM'!W$166:W$168) -> 1109.2148 | AE29: ='OECD TTL - 2018'!Y$29*'SIOM from DLIM'!X168/SUM('SIOM from DLIM'!X$166:X$168) -> 3756.5 | AF29: ='OECD TTL - 2018'!Z$29*'SIOM from DLIM'!Y168/SUM('SIOM from DLIM'!Y$166:Y$168) -> 1057.2325 | AG29: ='OECD TTL - 2018'!AA$29*'SIOM from DLIM'!Z168/SUM('SIOM from DLIM'!Z$166:Z$168) -> 274.16582 | AH29: ='OECD TTL - 2018'!AB$29*'SIOM from DLIM'!AA168/SUM('SIOM from DLIM'!AA$166:AA$168) -> 0 | AI29: ='OECD TTL - 2018'!AC$29*'SIOM from DLIM'!AB168/SUM('SIOM from DLIM'!AB$166:AB$168) -> 420.33055 | AJ29: ='OECD TTL - 2018'!AD$29*'SIOM from DLIM'!AC168/SUM('SIOM from DLIM'!AC$166:AC$168) -> 371.93288 | AK29: ='OECD TTL - 2018'!AE$29*'SIOM from DLIM'!AD168/SUM('SIOM from DLIM'!AD$166:AD$168) -> 1168.8 | ... AR29: ='OECD TTL - 2018'!AL$29*'SIOM from DLIM'!AK168/SUM('SIOM from DLIM'!AK$166:AK$168) -> 0
A30: D41T43: Construction | B30: construction 41T43 | C30: ='OECD TTL - 2018'!C30 -> 26.5 | D30: ='OECD TTL - 2018'!$D30*'SIOM from DLIM'!C169/SUM('SIOM from DLIM'!$C169:$D169) -> #DIV/0! | E30: ='OECD TTL - 2018'!$D30*'SIOM from DLIM'!D169/SUM('SIOM from DLIM'!$C169:$D169) -> #DIV/0! | F30: ='OECD TTL - 2018'!E30 -> 6 | G30: ='OECD TTL - 2018'!F30 -> 0 | H30: ='OECD TTL - 2018'!G30 -> 28.2 | I30: ='OECD TTL - 2018'!H30 -> 21.3 | J30: ='OECD TTL - 2018'!I30 -> 6.6 | K30: ='OECD TTL - 2018'!J30 -> 16.6 | L30: ='OECD TTL - 2018'!K30 -> 46.4 | M30: ='OECD TTL - 2018'!$L30*'SIOM from DLIM'!L169/SUM('SIOM from DLIM'!$L169:$M169) -> 72.429273 | N30: ='OECD TTL - 2018'!$L30*'SIOM from DLIM'!M169/SUM('SIOM from DLIM'!$L169:$M169) -> 7.2707268 | O30: ='OECD TTL - 2018'!M30 -> 31.2 | P30: ='OECD TTL - 2018'!$N30*'SIOM from DLIM'!O169/SUM('SIOM from DLIM'!$O169:$P169) -> #DIV/0! | Q30: ='OECD TTL - 2018'!$N30*'SIOM from DLIM'!P169/SUM('SIOM from DLIM'!$O169:$P169) -> #DIV/0! | R30: ='OECD TTL - 2018'!$O30*'SIOM from DLIM'!Q169/SUM('SIOM from DLIM'!$Q169:$R169) -> 0 | S30: ='OECD TTL - 2018'!$O30*'SIOM from DLIM'!R169/SUM('SIOM from DLIM'!$Q169:$R169) -> 94.5 | T30: ='OECD TTL - 2018'!P30 -> 59.7 | U30: ='OECD TTL - 2018'!Q30 -> 84.3 | V30: ='OECD TTL - 2018'!R30 -> 35.7 | W30: ='OECD TTL - 2018'!S30 -> 57.9 | X30: ='OECD TTL - 2018'!T30 -> 43.1 | Y30: ='OECD TTL - 2018'!U30 -> 34.4 | Z30: ='OECD TTL - 2018'!V30 -> 21.3 | AA30: ='OECD TTL - 2018'!$W30*'SIOM from DLIM'!Z169/SUM('SIOM from DLIM'!$Z169:$AB169) -> 21.354304 | AB30: ='OECD TTL - 2018'!$W30*'SIOM from DLIM'!AA169/SUM('SIOM from DLIM'!$Z169:$AB169) -> 0 | AC30: ='OECD TTL - 2018'!$W30*'SIOM from DLIM'!AB169/SUM('SIOM from DLIM'!$Z169:$AB169) -> 186.5457 | AD30: ='OECD TTL - 2018'!X30 -> 2182.7 | AE30: ='OECD TTL - 2018'!Y30 -> 305 | AF30: ='OECD TTL - 2018'!Z30 -> 140.8 | AG30: ='OECD TTL - 2018'!AA30 -> 59.6 | AH30: ='OECD TTL - 2018'!AB30 -> 20.6 | AI30: ='OECD TTL - 2018'!AC30 -> 61.2 | AJ30: ='OECD TTL - 2018'!AD30 -> 37.1 | AK30: ='OECD TTL - 2018'!AE30 -> 127.9 | ... AR30: ='OECD TTL - 2018'!AL30 -> 0
A31: D45T47: Wholesale and retail trade; repair of motor vehicles | C31: ='OECD TTL - 2018'!C31 -> 3229.9 | D31: ='OECD TTL - 2018'!$D31*'SIOM from DLIM'!C170/SUM('SIOM from DLIM'!$C170:$D170) -> #DIV/0! | E31: ='OECD TTL - 2018'!$D31*'SIOM from DLIM'!D170/SUM('SIOM from DLIM'!$C170:$D170) -> #DIV/0! | F31: ='OECD TTL - 2018'!E31 -> 72.7 | G31: ='OECD TTL - 2018'!F31 -> 0.3 | H31: ='OECD TTL - 2018'!G31 -> 14779.7 | I31: ='OECD TTL - 2018'!H31 -> 7528.5 | J31: ='OECD TTL - 2018'!I31 -> 584.6 | K31: ='OECD TTL - 2018'!J31 -> 1940.2 | L31: ='OECD TTL - 2018'!K31 -> 3523.5 | M31: ='OECD TTL - 2018'!$L31*'SIOM from DLIM'!L170/SUM('SIOM from DLIM'!$L170:$M170) -> 8447.1232 | N31: ='OECD TTL - 2018'!$L31*'SIOM from DLIM'!M170/SUM('SIOM from DLIM'!$L170:$M170) -> 2228.3768 | O31: ='OECD TTL - 2018'!M31 -> 4844 | P31: ='OECD TTL - 2018'!$N31*'SIOM from DLIM'!O170/SUM('SIOM from DLIM'!$O170:$P170) -> #DIV/0! | Q31: ='OECD TTL - 2018'!$N31*'SIOM from DLIM'!P170/SUM('SIOM from DLIM'!$O170:$P170) -> #DIV/0! | R31: ='OECD TTL - 2018'!$O31*'SIOM from DLIM'!Q170/SUM('SIOM from DLIM'!$Q170:$R170) -> #DIV/0! | S31: ='OECD TTL - 2018'!$O31*'SIOM from DLIM'!R170/SUM('SIOM from DLIM'!$Q170:$R170) -> #DIV/0! | T31: ='OECD TTL - 2018'!P31 -> 3677.1 | U31: ='OECD TTL - 2018'!Q31 -> 16028 | V31: ='OECD TTL - 2018'!R31 -> 4448.1 | W31: ='OECD TTL - 2018'!S31 -> 5423.1 | X31: ='OECD TTL - 2018'!T31 -> 6904.3 | Y31: ='OECD TTL - 2018'!U31 -> 4892.5 | Z31: ='OECD TTL - 2018'!V31 -> 1473 | AA31: ='OECD TTL - 2018'!$W31*'SIOM from DLIM'!Z170/SUM('SIOM from DLIM'!$Z170:$AB170) -> 0 | AB31: ='OECD TTL - 2018'!$W31*'SIOM from DLIM'!AA170/SUM('SIOM from DLIM'!$Z170:$AB170) -> 0 | AC31: ='OECD TTL - 2018'!$W31*'SIOM from DLIM'!AB170/SUM('SIOM from DLIM'!$Z170:$AB170) -> 2955.7 | AD31: ='OECD TTL - 2018'!X31 -> 8179.6 | AE31: ='OECD TTL - 2018'!Y31 -> 17212 | AF31: ='OECD TTL - 2018'!Z31 -> 3558.9 | AG31: ='OECD TTL - 2018'!AA31 -> 8987 | AH31: ='OECD TTL - 2018'!AB31 -> 1343.4 | AI31: ='OECD TTL - 2018'!AC31 -> 1287 | AJ31: ='OECD TTL - 2018'!AD31 -> 1920.6 | AK31: ='OECD TTL - 2018'!AE31 -> 1704.4 | ... AR31: ='OECD TTL - 2018'!AL31 -> 0
A32: D49T53: Transportation and storage | C32: ='OECD TTL - 2018'!C32 -> 458.7 | D32: ='OECD TTL - 2018'!$D32*'SIOM from DLIM'!C171/SUM('SIOM from DLIM'!$C171:$D171) -> 0 | E32: ='OECD TTL - 2018'!$D32*'SIOM from DLIM'!D171/SUM('SIOM from DLIM'!$C171:$D171) -> 49.9 | F32: ='OECD TTL - 2018'!E32 -> 125.8 | G32: ='OECD TTL - 2018'!F32 -> 0.3 | H32: ='OECD TTL - 2018'!G32 -> 1483.2 | I32: ='OECD TTL - 2018'!H32 -> 1090.5 | J32: ='OECD TTL - 2018'!I32 -> 277.6 | K32: ='OECD TTL - 2018'!J32 -> 795.3 | L32: ='OECD TTL - 2018'!K32 -> 2056 | M32: ='OECD TTL - 2018'!$L32*'SIOM from DLIM'!L171/SUM('SIOM from DLIM'!$L171:$M171) -> #DIV/0! | N32: ='OECD TTL - 2018'!$L32*'SIOM from DLIM'!M171/SUM('SIOM from DLIM'!$L171:$M171) -> #DIV/0! | O32: ='OECD TTL - 2018'!M32 -> 1163.6 | P32: ='OECD TTL - 2018'!$N32*'SIOM from DLIM'!O171/SUM('SIOM from DLIM'!$O171:$P171) -> 107.53901 | Q32: ='OECD TTL - 2018'!$N32*'SIOM from DLIM'!P171/SUM('SIOM from DLIM'!$O171:$P171) -> 1408.461 | R32: ='OECD TTL - 2018'!$O32*'SIOM from DLIM'!Q171/SUM('SIOM from DLIM'!$Q171:$R171) -> 2861.0544 | S32: ='OECD TTL - 2018'!$O32*'SIOM from DLIM'!R171/SUM('SIOM from DLIM'!$Q171:$R171) -> 457.14559 | T32: ='OECD TTL - 2018'!P32 -> 1254.9 | U32: ='OECD TTL - 2018'!Q32 -> 3457.2 | V32: ='OECD TTL - 2018'!R32 -> 972.7 | W32: ='OECD TTL - 2018'!S32 -> 1545.2 | X32: ='OECD TTL - 2018'!T32 -> 1679.8 | Y32: ='OECD TTL - 2018'!U32 -> 1207.2 | Z32: ='OECD TTL - 2018'!V32 -> 479.4 | AA32: ='OECD TTL - 2018'!$W32*'SIOM from DLIM'!Z171/SUM('SIOM from DLIM'!$Z171:$AB171) -> 381.44226 | AB32: ='OECD TTL - 2018'!$W32*'SIOM from DLIM'!AA171/SUM('SIOM from DLIM'!$Z171:$AB171) -> 160.044 | AC32: ='OECD TTL - 2018'!$W32*'SIOM from DLIM'!AB171/SUM('SIOM from DLIM'!$Z171:$AB171) -> 858.81374 | AD32: ='OECD TTL - 2018'!X32 -> 2583.3 | AE32: ='OECD TTL - 2018'!Y32 -> 10323.8 | AF32: ='OECD TTL - 2018'!Z32 -> 22495 | AG32: ='OECD TTL - 2018'!AA32 -> 555.9 | AH32: ='OECD TTL - 2018'!AB32 -> 464.5 | AI32: ='OECD TTL - 2018'!AC32 -> 506.4 | AJ32: ='OECD TTL - 2018'!AD32 -> 770 | AK32: ='OECD TTL - 2018'!AE32 -> 1806 | ... AR32: ='OECD TTL - 2018'!AL32 -> 0
A33: D55T56: Accomodation and food services | C33: ='OECD TTL - 2018'!C33 -> 43.1 | D33: ='OECD TTL - 2018'!$D33*'SIOM from DLIM'!C172/SUM('SIOM from DLIM'!$C172:$D172) -> 1.7644414 | E33: ='OECD TTL - 2018'!$D33*'SIOM from DLIM'!D172/SUM('SIOM from DLIM'!$C172:$D172) -> 0.63555858 | F33: ='OECD TTL - 2018'!E33 -> 3.9 | G33: ='OECD TTL - 2018'!F33 -> 0.1 | H33: ='OECD TTL - 2018'!G33 -> 101.7 | I33: ='OECD TTL - 2018'!H33 -> 83.9 | J33: ='OECD TTL - 2018'!I33 -> 23.1 | K33: ='OECD TTL - 2018'!J33 -> 56.8 | L33: ='OECD TTL - 2018'!K33 -> 35.2 | M33: ='OECD TTL - 2018'!$L33*'SIOM from DLIM'!L172/SUM('SIOM from DLIM'!$L172:$M172) -> 0 | N33: ='OECD TTL - 2018'!$L33*'SIOM from DLIM'!M172/SUM('SIOM from DLIM'!$L172:$M172) -> 201.4 | O33: ='OECD TTL - 2018'!M33 -> 110 | P33: ='OECD TTL - 2018'!$N33*'SIOM from DLIM'!O172/SUM('SIOM from DLIM'!$O172:$P172) -> 43.111013 | Q33: ='OECD TTL - 2018'!$N33*'SIOM from DLIM'!P172/SUM('SIOM from DLIM'!$O172:$P172) -> 39.188987 | R33: ='OECD TTL - 2018'!$O33*'SIOM from DLIM'!Q172/SUM('SIOM from DLIM'!$Q172:$R172) -> 104.56882 | S33: ='OECD TTL - 2018'!$O33*'SIOM from DLIM'!R172/SUM('SIOM from DLIM'!$Q172:$R172) -> 59.231176 | T33: ='OECD TTL - 2018'!P33 -> 175.5 | U33: ='OECD TTL - 2018'!Q33 -> 166 | V33: ='OECD TTL - 2018'!R33 -> 83.8 | W33: ='OECD TTL - 2018'!S33 -> 188 | X33: ='OECD TTL - 2018'!T33 -> 144.3 | Y33: ='OECD TTL - 2018'!U33 -> 252.7 | Z33: ='OECD TTL - 2018'!V33 -> 62.5 | AA33: ='OECD TTL - 2018'!$W33*'SIOM from DLIM'!Z172/SUM('SIOM from DLIM'!$Z172:$AB172) -> 168.07774 | AB33: ='OECD TTL - 2018'!$W33*'SIOM from DLIM'!AA172/SUM('SIOM from DLIM'!$Z172:$AB172) -> 54.915157 | AC33: ='OECD TTL - 2018'!$W33*'SIOM from DLIM'!AB172/SUM('SIOM from DLIM'!$Z172:$AB172) -> 88.307098 | AD33: ='OECD TTL - 2018'!X33 -> 468.5 | AE33: ='OECD TTL - 2018'!Y33 -> 1306.1 | AF33: ='OECD TTL - 2018'!Z33 -> 914.9 | AG33: ='OECD TTL - 2018'!AA33 -> 420.8 | AH33: ='OECD TTL - 2018'!AB33 -> 159.4 | AI33: ='OECD TTL - 2018'!AC33 -> 75.7 | AJ33: ='OECD TTL - 2018'!AD33 -> 398.5 | AK33: ='OECD TTL - 2018'!AE33 -> 771 | ... AR33: ='OECD TTL - 2018'!AL33 -> 0
A34: D58T60: Publishing, audiovisual and broadcasting activities | C34: ='OECD TTL - 2018'!C34 -> 10.9 | D34: ='OECD TTL - 2018'!$D34*'SIOM from DLIM'!C173/SUM('SIOM from DLIM'!$C173:$D173) -> #DIV/0! | E34: ='OECD TTL - 2018'!$D34*'SIOM from DLIM'!D173/SUM('SIOM from DLIM'!$C173:$D173) -> #DIV/0! | F34: ='OECD TTL - 2018'!E34 -> 0.9 | G34: ='OECD TTL - 2018'!F34 -> 0 | H34: ='OECD TTL - 2018'!G34 -> 97 | I34: ='OECD TTL - 2018'!H34 -> 26.1 | J34: ='OECD TTL - 2018'!I34 -> 7.5 | K34: ='OECD TTL - 2018'!J34 -> 105.3 | L34: ='OECD TTL - 2018'!K34 -> 44.9 | M34: ='OECD TTL - 2018'!$L34*'SIOM from DLIM'!L173/SUM('SIOM from DLIM'!$L173:$M173) -> 136.23084 | N34: ='OECD TTL - 2018'!$L34*'SIOM from DLIM'!M173/SUM('SIOM from DLIM'!$L173:$M173) -> 19.869161 | O34: ='OECD TTL - 2018'!M34 -> 44.8 | P34: ='OECD TTL - 2018'!$N34*'SIOM from DLIM'!O173/SUM('SIOM from DLIM'!$O173:$P173) -> #DIV/0! | Q34: ='OECD TTL - 2018'!$N34*'SIOM from DLIM'!P173/SUM('SIOM from DLIM'!$O173:$P173) -> #DIV/0! | R34: ='OECD TTL - 2018'!$O34*'SIOM from DLIM'!Q173/SUM('SIOM from DLIM'!$Q173:$R173) -> #DIV/0! | S34: ='OECD TTL - 2018'!$O34*'SIOM from DLIM'!R173/SUM('SIOM from DLIM'!$Q173:$R173) -> #DIV/0! | T34: ='OECD TTL - 2018'!P34 -> 52.6 | U34: ='OECD TTL - 2018'!Q34 -> 195.3 | V34: ='OECD TTL - 2018'!R34 -> 45.6 | W34: ='OECD TTL - 2018'!S34 -> 75 | X34: ='OECD TTL - 2018'!T34 -> 62.6 | Y34: ='OECD TTL - 2018'!U34 -> 57 | Z34: ='OECD TTL - 2018'!V34 -> 30.5 | AA34: ='OECD TTL - 2018'!$W34*'SIOM from DLIM'!Z173/SUM('SIOM from DLIM'!$Z173:$AB173) -> 0 | AB34: ='OECD TTL - 2018'!$W34*'SIOM from DLIM'!AA173/SUM('SIOM from DLIM'!$Z173:$AB173) -> 0 | AC34: ='OECD TTL - 2018'!$W34*'SIOM from DLIM'!AB173/SUM('SIOM from DLIM'!$Z173:$AB173) -> 98.9 | AD34: ='OECD TTL - 2018'!X34 -> 132.4 | AE34: ='OECD TTL - 2018'!Y34 -> 836.7 | AF34: ='OECD TTL - 2018'!Z34 -> 151.5 | AG34: ='OECD TTL - 2018'!AA34 -> 103.6 | AH34: ='OECD TTL - 2018'!AB34 -> 3547.3 | AI34: ='OECD TTL - 2018'!AC34 -> 520.2 | AJ34: ='OECD TTL - 2018'!AD34 -> 450.6 | AK34: ='OECD TTL - 2018'!AE34 -> 398.7 | ... AR34: ='OECD TTL - 2018'!AL34 -> 0
A35: D61: Telecommunications | C35: ='OECD TTL - 2018'!C35 -> 84.8 | D35: ='OECD TTL - 2018'!$D35*'SIOM from DLIM'!C174/SUM('SIOM from DLIM'!$C174:$D174) -> 1.714193 | E35: ='OECD TTL - 2018'!$D35*'SIOM from DLIM'!D174/SUM('SIOM from DLIM'!$C174:$D174) -> 0.085807012 | F35: ='OECD TTL - 2018'!E35 -> 10.6 | G35: ='OECD TTL - 2018'!F35 -> 0.1 | H35: ='OECD TTL - 2018'!G35 -> 137.8 | I35: ='OECD TTL - 2018'!H35 -> 169.7 | J35: ='OECD TTL - 2018'!I35 -> 29.6 | K35: ='OECD TTL - 2018'!J35 -> 87.1 | L35: ='OECD TTL - 2018'!K35 -> 136.5 | M35: ='OECD TTL - 2018'!$L35*'SIOM from DLIM'!L174/SUM('SIOM from DLIM'!$L174:$M174) -> 0 | N35: ='OECD TTL - 2018'!$L35*'SIOM from DLIM'!M174/SUM('SIOM from DLIM'!$L174:$M174) -> 325.9 | O35: ='OECD TTL - 2018'!M35 -> 176.9 | P35: ='OECD TTL - 2018'!$N35*'SIOM from DLIM'!O174/SUM('SIOM from DLIM'!$O174:$P174) -> 40.749049 | Q35: ='OECD TTL - 2018'!$N35*'SIOM from DLIM'!P174/SUM('SIOM from DLIM'!$O174:$P174) -> 94.250951 | R35: ='OECD TTL - 2018'!$O35*'SIOM from DLIM'!Q174/SUM('SIOM from DLIM'!$Q174:$R174) -> 138.26114 | S35: ='OECD TTL - 2018'!$O35*'SIOM from DLIM'!R174/SUM('SIOM from DLIM'!$Q174:$R174) -> 45.938863 | T35: ='OECD TTL - 2018'!P35 -> 280.9 | U35: ='OECD TTL - 2018'!Q35 -> 645.5 | V35: ='OECD TTL - 2018'!R35 -> 173.1 | W35: ='OECD TTL - 2018'!S35 -> 373.5 | X35: ='OECD TTL - 2018'!T35 -> 256.5 | Y35: ='OECD TTL - 2018'!U35 -> 220.8 | Z35: ='OECD TTL - 2018'!V35 -> 103.1 | AA35: ='OECD TTL - 2018'!$W35*'SIOM from DLIM'!Z174/SUM('SIOM from DLIM'!$Z174:$AB174) -> 374.50876 | AB35: ='OECD TTL - 2018'!$W35*'SIOM from DLIM'!AA174/SUM('SIOM from DLIM'!$Z174:$AB174) -> 10.950343 | AC35: ='OECD TTL - 2018'!$W35*'SIOM from DLIM'!AB174/SUM('SIOM from DLIM'!$Z174:$AB174) -> 53.040893 | AD35: ='OECD TTL - 2018'!X35 -> 542.7 | AE35: ='OECD TTL - 2018'!Y35 -> 2128.7 | AF35: ='OECD TTL - 2018'!Z35 -> 810.8 | AG35: ='OECD TTL - 2018'!AA35 -> 310.8 | AH35: ='OECD TTL - 2018'!AB35 -> 823 | AI35: ='OECD TTL - 2018'!AC35 -> 8625 | AJ35: ='OECD TTL - 2018'!AD35 -> 1388.4 | AK35: ='OECD TTL - 2018'!AE35 -> 2409.8 | ... AR35: ='OECD TTL - 2018'!AL35 -> 0
A36: D62T63: IT and other information services | C36: ='OECD TTL - 2018'!C36 -> 18 | D36: ='OECD TTL - 2018'!$D36*'SIOM from DLIM'!C175/SUM('SIOM from DLIM'!$C175:$D175) -> 6.8 | E36: ='OECD TTL - 2018'!$D36*'SIOM from DLIM'!D175/SUM('SIOM from DLIM'!$C175:$D175) -> 0 | F36: ='OECD TTL - 2018'!E36 -> 4 | G36: ='OECD TTL - 2018'!F36 -> 0 | H36: ='OECD TTL - 2018'!G36 -> 139.7 | I36: ='OECD TTL - 2018'!H36 -> 96.6 | J36: ='OECD TTL - 2018'!I36 -> 18.3 | K36: ='OECD TTL - 2018'!J36 -> 92.5 | L36: ='OECD TTL - 2018'!K36 -> 132.4 | M36: ='OECD TTL - 2018'!$L36*'SIOM from DLIM'!L175/SUM('SIOM from DLIM'!$L175:$M175) -> 347.49547 | N36: ='OECD TTL - 2018'!$L36*'SIOM from DLIM'!M175/SUM('SIOM from DLIM'!$L175:$M175) -> 50.104532 | O36: ='OECD TTL - 2018'!M36 -> 126.2 | P36: ='OECD TTL - 2018'!$N36*'SIOM from DLIM'!O175/SUM('SIOM from DLIM'!$O175:$P175) -> 93.5 | Q36: ='OECD TTL - 2018'!$N36*'SIOM from DLIM'!P175/SUM('SIOM from DLIM'!$O175:$P175) -> 0 | R36: ='OECD TTL - 2018'!$O36*'SIOM from DLIM'!Q175/SUM('SIOM from DLIM'!$Q175:$R175) -> 143.81425 | S36: ='OECD TTL - 2018'!$O36*'SIOM from DLIM'!R175/SUM('SIOM from DLIM'!$Q175:$R175) -> 61.485753 | T36: ='OECD TTL - 2018'!P36 -> 187.6 | U36: ='OECD TTL - 2018'!Q36 -> 890.3 | V36: ='OECD TTL - 2018'!R36 -> 198.8 | W36: ='OECD TTL - 2018'!S36 -> 280.6 | X36: ='OECD TTL - 2018'!T36 -> 260.6 | Y36: ='OECD TTL - 2018'!U36 -> 82.8 | Z36: ='OECD TTL - 2018'!V36 -> 81.7 | AA36: ='OECD TTL - 2018'!$W36*'SIOM from DLIM'!Z175/SUM('SIOM from DLIM'!$Z175:$AB175) -> 262.66695 | AB36: ='OECD TTL - 2018'!$W36*'SIOM from DLIM'!AA175/SUM('SIOM from DLIM'!$Z175:$AB175) -> 0 | AC36: ='OECD TTL - 2018'!$W36*'SIOM from DLIM'!AB175/SUM('SIOM from DLIM'!$Z175:$AB175) -> 135.13305 | AD36: ='OECD TTL - 2018'!X36 -> 415.3 | AE36: ='OECD TTL - 2018'!Y36 -> 1440.1 | AF36: ='OECD TTL - 2018'!Z36 -> 633.6 | AG36: ='OECD TTL - 2018'!AA36 -> 186.4 | AH36: ='OECD TTL - 2018'!AB36 -> 418.6 | AI36: ='OECD TTL - 2018'!AC36 -> 776.3 | AJ36: ='OECD TTL - 2018'!AD36 -> 4196 | AK36: ='OECD TTL - 2018'!AE36 -> 2628 | ... AR36: ='OECD TTL - 2018'!AL36 -> 0
A37: D64T66: Financial and insurance activities | C37: ='OECD TTL - 2018'!C37 -> 691.4 | D37: ='OECD TTL - 2018'!$D37*'SIOM from DLIM'!C176/SUM('SIOM from DLIM'!$C176:$D176) -> #DIV/0! | E37: ='OECD TTL - 2018'!$D37*'SIOM from DLIM'!D176/SUM('SIOM from DLIM'!$C176:$D176) -> #DIV/0! | F37: ='OECD TTL - 2018'!E37 -> 55.8 | G37: ='OECD TTL - 2018'!F37 -> 0.2 | H37: ='OECD TTL - 2018'!G37 -> 739.7 | I37: ='OECD TTL - 2018'!H37 -> 761.6 | J37: ='OECD TTL - 2018'!I37 -> 176.4 | K37: ='OECD TTL - 2018'!J37 -> 489.8 | L37: ='OECD TTL - 2018'!K37 -> 890.3 | M37: ='OECD TTL - 2018'!$L37*'SIOM from DLIM'!L176/SUM('SIOM from DLIM'!$L176:$M176) -> 1696.4601 | N37: ='OECD TTL - 2018'!$L37*'SIOM from DLIM'!M176/SUM('SIOM from DLIM'!$L176:$M176) -> 309.53994 | O37: ='OECD TTL - 2018'!M37 -> 903.4 | P37: ='OECD TTL - 2018'!$N37*'SIOM from DLIM'!O176/SUM('SIOM from DLIM'!$O176:$P176) -> 689.1 | Q37: ='OECD TTL - 2018'!$N37*'SIOM from DLIM'!P176/SUM('SIOM from DLIM'!$O176:$P176) -> 0 | R37: ='OECD TTL - 2018'!$O37*'SIOM from DLIM'!Q176/SUM('SIOM from DLIM'!$Q176:$R176) -> 1945.3437 | S37: ='OECD TTL - 2018'!$O37*'SIOM from DLIM'!R176/SUM('SIOM from DLIM'!$Q176:$R176) -> 825.55628 | T37: ='OECD TTL - 2018'!P37 -> 1265.2 | U37: ='OECD TTL - 2018'!Q37 -> 2128.4 | V37: ='OECD TTL - 2018'!R37 -> 808.9 | W37: ='OECD TTL - 2018'!S37 -> 1431.4 | X37: ='OECD TTL - 2018'!T37 -> 1295 | Y37: ='OECD TTL - 2018'!U37 -> 1226 | Z37: ='OECD TTL - 2018'!V37 -> 439.4 | AA37: ='OECD TTL - 2018'!$W37*'SIOM from DLIM'!Z176/SUM('SIOM from DLIM'!$Z176:$AB176) -> 0 | AB37: ='OECD TTL - 2018'!$W37*'SIOM from DLIM'!AA176/SUM('SIOM from DLIM'!$Z176:$AB176) -> 16.039072 | AC37: ='OECD TTL - 2018'!$W37*'SIOM from DLIM'!AB176/SUM('SIOM from DLIM'!$Z176:$AB176) -> 2008.8609 | AD37: ='OECD TTL - 2018'!X37 -> 3450 | AE37: ='OECD TTL - 2018'!Y37 -> 6656 | AF37: ='OECD TTL - 2018'!Z37 -> 3418.5 | AG37: ='OECD TTL - 2018'!AA37 -> 962.4 | AH37: ='OECD TTL - 2018'!AB37 -> 506.8 | AI37: ='OECD TTL - 2018'!AC37 -> 716.1 | AJ37: ='OECD TTL - 2018'!AD37 -> 1178.3 | AK37: ='OECD TTL - 2018'!AE37 -> 28913.2 | ... AR37: ='OECD TTL - 2018'!AL37 -> 0
A38: D68: Real estate activities | C38: ='OECD TTL - 2018'!C38 -> 40.8 | D38: ='OECD TTL - 2018'!$D38*'SIOM from DLIM'!C177/SUM('SIOM from DLIM'!$C177:$D177) -> #DIV/0! | E38: ='OECD TTL - 2018'!$D38*'SIOM from DLIM'!D177/SUM('SIOM from DLIM'!$C177:$D177) -> #DIV/0! | F38: ='OECD TTL - 2018'!E38 -> 3.2 | G38: ='OECD TTL - 2018'!F38 -> 0 | H38: ='OECD TTL - 2018'!G38 -> 126.1 | I38: ='OECD TTL - 2018'!H38 -> 150.1 | J38: ='OECD TTL - 2018'!I38 -> 23.4 | K38: ='OECD TTL - 2018'!J38 -> 79.9 | L38: ='OECD TTL - 2018'!K38 -> 85 | M38: ='OECD TTL - 2018'!$L38*'SIOM from DLIM'!L177/SUM('SIOM from DLIM'!$L177:$M177) -> 173.06811 | N38: ='OECD TTL - 2018'!$L38*'SIOM from DLIM'!M177/SUM('SIOM from DLIM'!$L177:$M177) -> 23.931891 | O38: ='OECD TTL - 2018'!M38 -> 168.1 | P38: ='OECD TTL - 2018'!$N38*'SIOM from DLIM'!O177/SUM('SIOM from DLIM'!$O177:$P177) -> 32.034627 | Q38: ='OECD TTL - 2018'!$N38*'SIOM from DLIM'!P177/SUM('SIOM from DLIM'!$O177:$P177) -> 54.665373 | R38: ='OECD TTL - 2018'!$O38*'SIOM from DLIM'!Q177/SUM('SIOM from DLIM'!$Q177:$R177) -> 81.562838 | S38: ='OECD TTL - 2018'!$O38*'SIOM from DLIM'!R177/SUM('SIOM from DLIM'!$Q177:$R177) -> 27.037162 | T38: ='OECD TTL - 2018'!P38 -> 258.8 | U38: ='OECD TTL - 2018'!Q38 -> 323.7 | V38: ='OECD TTL - 2018'!R38 -> 129.3 | W38: ='OECD TTL - 2018'!S38 -> 212.1 | X38: ='OECD TTL - 2018'!T38 -> 289 | Y38: ='OECD TTL - 2018'!U38 -> 152.3 | Z38: ='OECD TTL - 2018'!V38 -> 100.6 | AA38: ='OECD TTL - 2018'!$W38*'SIOM from DLIM'!Z177/SUM('SIOM from DLIM'!$Z177:$AB177) -> 137.90658 | AB38: ='OECD TTL - 2018'!$W38*'SIOM from DLIM'!AA177/SUM('SIOM from DLIM'!$Z177:$AB177) -> 0 | AC38: ='OECD TTL - 2018'!$W38*'SIOM from DLIM'!AB177/SUM('SIOM from DLIM'!$Z177:$AB177) -> 125.09342 | AD38: ='OECD TTL - 2018'!X38 -> 741.7 | AE38: ='OECD TTL - 2018'!Y38 -> 4316 | AF38: ='OECD TTL - 2018'!Z38 -> 696.8 | AG38: ='OECD TTL - 2018'!AA38 -> 1136 | AH38: ='OECD TTL - 2018'!AB38 -> 196.8 | AI38: ='OECD TTL - 2018'!AC38 -> 363.5 | AJ38: ='OECD TTL - 2018'!AD38 -> 456.1 | AK38: ='OECD TTL - 2018'!AE38 -> 1105.3 | ... AR38: ='OECD TTL - 2018'!AL38 -> 0
A39: D69T82: Other business sector services | C39: ='OECD TTL - 2018'!C39 -> 423.2 | D39: ='OECD TTL - 2018'!$D39*'SIOM from DLIM'!C178/SUM('SIOM from DLIM'!$C178:$D178) -> #DIV/0! | E39: ='OECD TTL - 2018'!$D39*'SIOM from DLIM'!D178/SUM('SIOM from DLIM'!$C178:$D178) -> #DIV/0! | F39: ='OECD TTL - 2018'!E39 -> 70 | G39: ='OECD TTL - 2018'!F39 -> 0.5 | H39: ='OECD TTL - 2018'!G39 -> 1874.9 | I39: ='OECD TTL - 2018'!H39 -> 984.7 | J39: ='OECD TTL - 2018'!I39 -> 240.4 | K39: ='OECD TTL - 2018'!J39 -> 791.2 | L39: ='OECD TTL - 2018'!K39 -> 1473.5 | M39: ='OECD TTL - 2018'!$L39*'SIOM from DLIM'!L178/SUM('SIOM from DLIM'!$L178:$M178) -> #DIV/0! | N39: ='OECD TTL - 2018'!$L39*'SIOM from DLIM'!M178/SUM('SIOM from DLIM'!$L178:$M178) -> #DIV/0! | O39: ='OECD TTL - 2018'!M39 -> 1592.6 | P39: ='OECD TTL - 2018'!$N39*'SIOM from DLIM'!O178/SUM('SIOM from DLIM'!$O178:$P178) -> 1183.8 | Q39: ='OECD TTL - 2018'!$N39*'SIOM from DLIM'!P178/SUM('SIOM from DLIM'!$O178:$P178) -> 0 | R39: ='OECD TTL - 2018'!$O39*'SIOM from DLIM'!Q178/SUM('SIOM from DLIM'!$Q178:$R178) -> 1479.7123 | S39: ='OECD TTL - 2018'!$O39*'SIOM from DLIM'!R178/SUM('SIOM from DLIM'!$Q178:$R178) -> 395.38773 | T39: ='OECD TTL - 2018'!P39 -> 2019.6 | U39: ='OECD TTL - 2018'!Q39 -> 7432.6 | V39: ='OECD TTL - 2018'!R39 -> 1985.8 | W39: ='OECD TTL - 2018'!S39 -> 2762.6 | X39: ='OECD TTL - 2018'!T39 -> 2877 | Y39: ='OECD TTL - 2018'!U39 -> 2126.1 | Z39: ='OECD TTL - 2018'!V39 -> 872.8 | AA39: ='OECD TTL - 2018'!$W39*'SIOM from DLIM'!Z178/SUM('SIOM from DLIM'!$Z178:$AB178) -> 3001.1378 | AB39: ='OECD TTL - 2018'!$W39*'SIOM from DLIM'!AA178/SUM('SIOM from DLIM'!$Z178:$AB178) -> 94.662207 | AC39: ='OECD TTL - 2018'!$W39*'SIOM from DLIM'!AB178/SUM('SIOM from DLIM'!$Z178:$AB178) -> 0 | AD39: ='OECD TTL - 2018'!X39 -> 8394 | AE39: ='OECD TTL - 2018'!Y39 -> 14142.9 | AF39: ='OECD TTL - 2018'!Z39 -> 6480 | AG39: ='OECD TTL - 2018'!AA39 -> 2450.8 | AH39: ='OECD TTL - 2018'!AB39 -> 1775.8 | AI39: ='OECD TTL - 2018'!AC39 -> 2193.6 | AJ39: ='OECD TTL - 2018'!AD39 -> 3950.8 | AK39: ='OECD TTL - 2018'!AE39 -> 7987.6 | ... AR39: ='OECD TTL - 2018'!AL39 -> 0
A40: D84: Public admin. and defence; compulsory social security | C40: ='OECD TTL - 2018'!C40 -> 35.4 | D40: ='OECD TTL - 2018'!$D40*'SIOM from DLIM'!C179/SUM('SIOM from DLIM'!$C179:$D179) -> #DIV/0! | E40: ='OECD TTL - 2018'!$D40*'SIOM from DLIM'!D179/SUM('SIOM from DLIM'!$C179:$D179) -> #DIV/0! | F40: ='OECD TTL - 2018'!E40 -> 3.6 | G40: ='OECD TTL - 2018'!F40 -> 0 | H40: ='OECD TTL - 2018'!G40 -> 97 | I40: ='OECD TTL - 2018'!H40 -> 73.7 | J40: ='OECD TTL - 2018'!I40 -> 13.7 | K40: ='OECD TTL - 2018'!J40 -> 51.1 | L40: ='OECD TTL - 2018'!K40 -> 79.3 | M40: ='OECD TTL - 2018'!$L40*'SIOM from DLIM'!L179/SUM('SIOM from DLIM'!$L179:$M179) -> 105.82141 | N40: ='OECD TTL - 2018'!$L40*'SIOM from DLIM'!M179/SUM('SIOM from DLIM'!$L179:$M179) -> 70.878589 | O40: ='OECD TTL - 2018'!M40 -> 85.2 | P40: ='OECD TTL - 2018'!$N40*'SIOM from DLIM'!O179/SUM('SIOM from DLIM'!$O179:$P179) -> #DIV/0! | Q40: ='OECD TTL - 2018'!$N40*'SIOM from DLIM'!P179/SUM('SIOM from DLIM'!$O179:$P179) -> #DIV/0! | R40: ='OECD TTL - 2018'!$O40*'SIOM from DLIM'!Q179/SUM('SIOM from DLIM'!$Q179:$R179) -> #DIV/0! | S40: ='OECD TTL - 2018'!$O40*'SIOM from DLIM'!R179/SUM('SIOM from DLIM'!$Q179:$R179) -> #DIV/0! | T40: ='OECD TTL - 2018'!P40 -> 110.3 | U40: ='OECD TTL - 2018'!Q40 -> 180.5 | V40: ='OECD TTL - 2018'!R40 -> 65 | W40: ='OECD TTL - 2018'!S40 -> 106 | X40: ='OECD TTL - 2018'!T40 -> 101.7 | Y40: ='OECD TTL - 2018'!U40 -> 83 | Z40: ='OECD TTL - 2018'!V40 -> 36.3 | AA40: ='OECD TTL - 2018'!$W40*'SIOM from DLIM'!Z179/SUM('SIOM from DLIM'!$Z179:$AB179) -> 0 | AB40: ='OECD TTL - 2018'!$W40*'SIOM from DLIM'!AA179/SUM('SIOM from DLIM'!$Z179:$AB179) -> 0 | AC40: ='OECD TTL - 2018'!$W40*'SIOM from DLIM'!AB179/SUM('SIOM from DLIM'!$Z179:$AB179) -> 272.3 | AD40: ='OECD TTL - 2018'!X40 -> 256.4 | AE40: ='OECD TTL - 2018'!Y40 -> 767.5 | AF40: ='OECD TTL - 2018'!Z40 -> 483.2 | AG40: ='OECD TTL - 2018'!AA40 -> 166.5 | AH40: ='OECD TTL - 2018'!AB40 -> 110.5 | AI40: ='OECD TTL - 2018'!AC40 -> 91.7 | AJ40: ='OECD TTL - 2018'!AD40 -> 115.3 | AK40: ='OECD TTL - 2018'!AE40 -> 297.3 | ... AR40: ='OECD TTL - 2018'!AL40 -> 0
A41: D85: Education | C41: ='OECD TTL - 2018'!C41 -> 13.1 | D41: ='OECD TTL - 2018'!$D41*'SIOM from DLIM'!C180/SUM('SIOM from DLIM'!$C180:$D180) -> #DIV/0! | E41: ='OECD TTL - 2018'!$D41*'SIOM from DLIM'!D180/SUM('SIOM from DLIM'!$C180:$D180) -> #DIV/0! | F41: ='OECD TTL - 2018'!E41 -> 2.3 | G41: ='OECD TTL - 2018'!F41 -> 0 | H41: ='OECD TTL - 2018'!G41 -> 38.6 | I41: ='OECD TTL - 2018'!H41 -> 34.5 | J41: ='OECD TTL - 2018'!I41 -> 6.9 | K41: ='OECD TTL - 2018'!J41 -> 26.4 | L41: ='OECD TTL - 2018'!K41 -> 36.7 | M41: ='OECD TTL - 2018'!$L41*'SIOM from DLIM'!L180/SUM('SIOM from DLIM'!$L180:$M180) -> 83.801601 | N41: ='OECD TTL - 2018'!$L41*'SIOM from DLIM'!M180/SUM('SIOM from DLIM'!$L180:$M180) -> 10.398399 | O41: ='OECD TTL - 2018'!M41 -> 46.8 | P41: ='OECD TTL - 2018'!$N41*'SIOM from DLIM'!O180/SUM('SIOM from DLIM'!$O180:$P180) -> #DIV/0! | Q41: ='OECD TTL - 2018'!$N41*'SIOM from DLIM'!P180/SUM('SIOM from DLIM'!$O180:$P180) -> #DIV/0! | R41: ='OECD TTL - 2018'!$O41*'SIOM from DLIM'!Q180/SUM('SIOM from DLIM'!$Q180:$R180) -> #DIV/0! | S41: ='OECD TTL - 2018'!$O41*'SIOM from DLIM'!R180/SUM('SIOM from DLIM'!$Q180:$R180) -> #DIV/0! | T41: ='OECD TTL - 2018'!P41 -> 64.6 | U41: ='OECD TTL - 2018'!Q41 -> 184.4 | V41: ='OECD TTL - 2018'!R41 -> 52.4 | W41: ='OECD TTL - 2018'!S41 -> 79.5 | X41: ='OECD TTL - 2018'!T41 -> 81.2 | Y41: ='OECD TTL - 2018'!U41 -> 37.6 | Z41: ='OECD TTL - 2018'!V41 -> 24.7 | AA41: ='OECD TTL - 2018'!$W41*'SIOM from DLIM'!Z180/SUM('SIOM from DLIM'!$Z180:$AB180) -> 0 | AB41: ='OECD TTL - 2018'!$W41*'SIOM from DLIM'!AA180/SUM('SIOM from DLIM'!$Z180:$AB180) -> 0 | AC41: ='OECD TTL - 2018'!$W41*'SIOM from DLIM'!AB180/SUM('SIOM from DLIM'!$Z180:$AB180) -> 99 | AD41: ='OECD TTL - 2018'!X41 -> 122.8 | AE41: ='OECD TTL - 2018'!Y41 -> 385.5 | AF41: ='OECD TTL - 2018'!Z41 -> 196.5 | AG41: ='OECD TTL - 2018'!AA41 -> 66.2 | AH41: ='OECD TTL - 2018'!AB41 -> 68.4 | AI41: ='OECD TTL - 2018'!AC41 -> 73.6 | AJ41: ='OECD TTL - 2018'!AD41 -> 217.1 | AK41: ='OECD TTL - 2018'!AE41 -> 414.4 | ... AR41: ='OECD TTL - 2018'!AL41 -> 0
A42: D86T88: Human health and social work | C42: ='OECD TTL - 2018'!C42 -> 185.5 | D42: ='OECD TTL - 2018'!$D42*'SIOM from DLIM'!C181/SUM('SIOM from DLIM'!$C181:$D181) -> #DIV/0! | E42: ='OECD TTL - 2018'!$D42*'SIOM from DLIM'!D181/SUM('SIOM from DLIM'!$C181:$D181) -> #DIV/0! | F42: ='OECD TTL - 2018'!E42 -> 1.4 | G42: ='OECD TTL - 2018'!F42 -> 0 | H42: ='OECD TTL - 2018'!G42 -> 494.8 | I42: ='OECD TTL - 2018'!H42 -> 42.2 | J42: ='OECD TTL - 2018'!I42 -> 55.3 | K42: ='OECD TTL - 2018'!J42 -> 162 | L42: ='OECD TTL - 2018'!K42 -> 159.8 | M42: ='OECD TTL - 2018'!$L42*'SIOM from DLIM'!L181/SUM('SIOM from DLIM'!$L181:$M181) -> 1011.4651 | N42: ='OECD TTL - 2018'!$L42*'SIOM from DLIM'!M181/SUM('SIOM from DLIM'!$L181:$M181) -> 192.73495 | O42: ='OECD TTL - 2018'!M42 -> 343.5 | P42: ='OECD TTL - 2018'!$N42*'SIOM from DLIM'!O181/SUM('SIOM from DLIM'!$O181:$P181) -> #DIV/0! | Q42: ='OECD TTL - 2018'!$N42*'SIOM from DLIM'!P181/SUM('SIOM from DLIM'!$O181:$P181) -> #DIV/0! | R42: ='OECD TTL - 2018'!$O42*'SIOM from DLIM'!Q181/SUM('SIOM from DLIM'!$Q181:$R181) -> #DIV/0! | S42: ='OECD TTL - 2018'!$O42*'SIOM from DLIM'!R181/SUM('SIOM from DLIM'!$Q181:$R181) -> #DIV/0! | T42: ='OECD TTL - 2018'!P42 -> 424.5 | U42: ='OECD TTL - 2018'!Q42 -> 602.1 | V42: ='OECD TTL - 2018'!R42 -> 307.8 | W42: ='OECD TTL - 2018'!S42 -> 458.3 | X42: ='OECD TTL - 2018'!T42 -> 451.6 | Y42: ='OECD TTL - 2018'!U42 -> 115.7 | Z42: ='OECD TTL - 2018'!V42 -> 229.7 | AA42: ='OECD TTL - 2018'!$W42*'SIOM from DLIM'!Z181/SUM('SIOM from DLIM'!$Z181:$AB181) -> 0 | AB42: ='OECD TTL - 2018'!$W42*'SIOM from DLIM'!AA181/SUM('SIOM from DLIM'!$Z181:$AB181) -> 0 | AC42: ='OECD TTL - 2018'!$W42*'SIOM from DLIM'!AB181/SUM('SIOM from DLIM'!$Z181:$AB181) -> 690.8 | AD42: ='OECD TTL - 2018'!X42 -> 751 | AE42: ='OECD TTL - 2018'!Y42 -> 2586.6 | AF42: ='OECD TTL - 2018'!Z42 -> 1764.3 | AG42: ='OECD TTL - 2018'!AA42 -> 352.6 | AH42: ='OECD TTL - 2018'!AB42 -> 328.8 | AI42: ='OECD TTL - 2018'!AC42 -> 422.9 | AJ42: ='OECD TTL - 2018'!AD42 -> 878.5 | AK42: ='OECD TTL - 2018'!AE42 -> 4877.4 | ... AR42: ='OECD TTL - 2018'!AL42 -> 0
... A44: D97T98: Private households with employed persons | C44: ='OECD TTL - 2018'!C44 -> 0 | D44: ='OECD TTL - 2018'!$D44*'SIOM from DLIM'!C183/SUM('SIOM from DLIM'!$C183:$D183) -> 0 | E44: ='OECD TTL - 2018'!$D44*'SIOM from DLIM'!D183/SUM('SIOM from DLIM'!$C183:$D183) -> 0 | F44: ='OECD TTL - 2018'!E44 -> 0 | G44: ='OECD TTL - 2018'!F44 -> 0 | H44: ='OECD TTL - 2018'!G44 -> 0 | I44: ='OECD TTL - 2018'!H44 -> 0 | J44: ='OECD TTL - 2018'!I44 -> 0 | K44: ='OECD TTL - 2018'!J44 -> 0 | L44: ='OECD TTL - 2018'!K44 -> 0 | M44: ='OECD TTL - 2018'!$L44*'SIOM from DLIM'!L183/SUM('SIOM from DLIM'!$L183:$M183) -> #DIV/0! | N44: ='OECD TTL - 2018'!$L44*'SIOM from DLIM'!M183/SUM('SIOM from DLIM'!$L183:$M183) -> #DIV/0! | O44: ='OECD TTL - 2018'!M44 -> 0 | P44: ='OECD TTL - 2018'!$N44*'SIOM from DLIM'!O183/SUM('SIOM from DLIM'!$O183:$P183) -> 0 | Q44: ='OECD TTL - 2018'!$N44*'SIOM from DLIM'!P183/SUM('SIOM from DLIM'!$O183:$P183) -> 0 | R44: ='OECD TTL - 2018'!$O44*'SIOM from DLIM'!Q183/SUM('SIOM from DLIM'!$Q183:$R183) -> 0 | S44: ='OECD TTL - 2018'!$O44*'SIOM from DLIM'!R183/SUM('SIOM from DLIM'!$Q183:$R183) -> 0 | T44: ='OECD TTL - 2018'!P44 -> 0 | U44: ='OECD TTL - 2018'!Q44 -> 0 | V44: ='OECD TTL - 2018'!R44 -> 0 | W44: ='OECD TTL - 2018'!S44 -> 0 | X44: ='OECD TTL - 2018'!T44 -> 0 | Y44: ='OECD TTL - 2018'!U44 -> 0 | Z44: ='OECD TTL - 2018'!V44 -> 0 | AA44: ='OECD TTL - 2018'!$W44*'SIOM from DLIM'!Z183/SUM('SIOM from DLIM'!$Z183:$AB183) -> 0 | AB44: ='OECD TTL - 2018'!$W44*'SIOM from DLIM'!AA183/SUM('SIOM from DLIM'!$Z183:$AB183) -> 0 | AC44: ='OECD TTL - 2018'!$W44*'SIOM from DLIM'!AB183/SUM('SIOM from DLIM'!$Z183:$AB183) -> 0 | AD44: ='OECD TTL - 2018'!X44 -> 0 | AE44: ='OECD TTL - 2018'!Y44 -> 0 | AF44: ='OECD TTL - 2018'!Z44 -> 0 | AG44: ='OECD TTL - 2018'!AA44 -> 0 | AH44: ='OECD TTL - 2018'!AB44 -> 0 | AI44: ='OECD TTL - 2018'!AC44 -> 0 | AJ44: ='OECD TTL - 2018'!AD44 -> 0 | AK44: ='OECD TTL - 2018'!AE44 -> 0 | ... AR44: ='OECD TTL - 2018'!AL44 -> 0
A46: SIOM, without errors
B47: Matching EPS Industry | C47: ISIC 01T03 | D47: ISIC 05 | E47: ISIC 06 | F47: ISIC 07T08 | G47: ISIC 09 | H47: ISIC 10T12 | I47: ISIC 13T15 | J47: ISIC 16 | K47: ISIC 17T18 | L47: ISIC 19 | M47: ISIC 20 | N47: ISIC 21 | O47: ISIC 22 | P47: ISIC 231 | Q47: ISIC 239 | R47: ISIC 241 | S47: ISIC 242 | T47: ISIC 25 | U47: ISIC 26 | V47: ISIC 27 | W47: ISIC 28 | X47: ISIC 29 | Y47: ISIC 30 | Z47: ISIC 31T33 | AA47: ISIC 351 | AB47: ISIC 352T353 | AC47: ISIC 36T39 | AD47: ISIC 41T43 | AE47: ISIC 45T47 | AF47: ISIC 49T53 | AG47: ISIC 55T56 | AH47: ISIC 58T60 | AI47: ISIC 61 | AJ47: ISIC 62T63 | AK47: ISIC 64T66 | AL47: ISIC 68 | AM47: ISIC 69T82 | AN47: ISIC 84 | AO47: ISIC 85 | AP47: ISIC 86T88 | AQ47: ISIC 90T96 | AR47: ISIC 97T98 | AS47: 0
A48: D01T03: Agriculture, forestry and fishing | B48: agriculture and forestry 01T03 | C48: =IFERROR(C3,0) -> 4722.3 | D48: =IFERROR(D3,0) -> 0 | E48: =IFERROR(E3,0) -> 0 | F48: =IFERROR(F3,0) -> 3.5 | G48: =IFERROR(G3,0) -> 0 | H48: =IFERROR(H3,0) -> 27898.7 | I48: =IFERROR(I3,0) -> 1366.4 | J48: =IFERROR(J3,0) -> 939.5 | ... AR48: =IFERROR(AR3,0) -> 0
A49: coal mining 05 | B49: coal mining 05 | C49: =IFERROR(C4,0) -> 0 | D49: =IFERROR(D4,0) -> 0 | E49: =IFERROR(E4,0) -> 0 | F49: =IFERROR(F4,0) -> 0 | G49: =IFERROR(G4,0) -> 0 | H49: =IFERROR(H4,0) -> 0 | I49: =IFERROR(I4,0) -> 0 | J49: =IFERROR(J4,0) -> 0 | ... L49: =IFERROR(L4,0) -> 0 | M49: =IFERROR(M13,0) -> 35435.618 | N49: =IFERROR(N13,0) -> 1155.6055 | O49: =IFERROR(O4,0) -> 117.75122 | P49: =IFERROR(P4,0) -> 0 | Q49: =IFERROR(Q4,0) -> 0 | R49: =IFERROR(R4,0) -> 3659.1 | S49: =IFERROR(S4,0) -> 0 | T49: =IFERROR(T4,0) -> 0 | U49: =IFERROR(U4,0) -> 0 | V49: =IFERROR(V4,0) -> 49.2 | ... AR49: =IFERROR(AR4,0) -> 0
A50: oil and gas extraction 06 | B50: oil and gas extraction 06 | C50: =IFERROR(C5,0) -> 0 | D50: =IFERROR(D5,0) -> 0 | E50: =IFERROR(E5,0) -> 0 | F50: =IFERROR(F5,0) -> 0 | G50: =IFERROR(G5,0) -> 0 | H50: =IFERROR(H5,0) -> 0 | I50: =IFERROR(I5,0) -> 0 | J50: =IFERROR(J5,0) -> 0 | ... L50: =IFERROR(L5,0) -> 0 | M50: =IFERROR(M14,0) -> 128.83017 | N50: =IFERROR(N14,0) -> 1182.8461 | O50: =IFERROR(O5,0) -> 117.74878 | P50: =IFERROR(P5,0) -> 0 | Q50: =IFERROR(Q5,0) -> 0 | R50: =IFERROR(R5,0) -> 0 | S50: =IFERROR(S5,0) -> 0 | T50: =IFERROR(T5,0) -> 0 | U50: =IFERROR(U5,0) -> 0 | V50: =IFERROR(V5,0) -> 0 | ... AR50: =IFERROR(AR5,0) -> 0
A51: D07T08: Mining and quarrying of non-energy producing products | B51: other mining and quarrying 07T08 | C51: =IFERROR(C6,0) -> 13.4 | D51: =IFERROR(D6,0) -> 0 | E51: =IFERROR(E6,0) -> 0 | F51: =IFERROR(F6,0) -> 34 | G51: =IFERROR(G6,0) -> 0 | H51: =IFERROR(H6,0) -> 14.9 | I51: =IFERROR(I6,0) -> 6.7 | J51: =IFERROR(J6,0) -> 2.1 | ... AR51: =IFERROR(AR6,0) -> 0
A52: D09: Mining support service activities | C52: =IFERROR(C7,0) -> 9.4 | D52: =IFERROR(D7,0) -> 0.6797563 | E52: =IFERROR(E7,0) -> 0.2202437 | F52: =IFERROR(F7,0) -> 1.9 | G52: =IFERROR(G7,0) -> 0 | H52: =IFERROR(H7,0) -> 1.3 | I52: =IFERROR(I7,0) -> 0.1 | J52: =IFERROR(J7,0) -> 0.1 | ... AR52: =IFERROR(AR7,0) -> 0
A53: D10T12: Food products, beverages and tobacco | B53: food beverage and tobacco 10T12 | C53: =IFERROR(C8,0) -> 5960.6 | D53: =IFERROR(D8,0) -> 0 | E53: =IFERROR(E8,0) -> 0 | F53: =IFERROR(F8,0) -> 2 | G53: =IFERROR(G8,0) -> 0 | H53: =IFERROR(H8,0) -> 24001.4 | I53: =IFERROR(I8,0) -> 917.8 | J53: =IFERROR(J8,0) -> 36.3 | ... AR53: =IFERROR(AR8,0) -> 0
A54: D13T15: Textiles, wearing apparel, leather and related products | B54: textiles apparel and leather 13T15 | C54: =IFERROR(C9,0) -> 322.9 | D54: =IFERROR(D9,0) -> 0 | E54: =IFERROR(E9,0) -> 0 | F54: =IFERROR(F9,0) -> 17.5 | G54: =IFERROR(G9,0) -> 0.1 | H54: =IFERROR(H9,0) -> 278.5 | I54: =IFERROR(I9,0) -> 27189 | J54: =IFERROR(J9,0) -> 123 | ... AR54: =IFERROR(AR9,0) -> 0
A55: D16: Wood and products of wood and cork | B55: wood products 16 | C55: =IFERROR(C10,0) -> 42.8 | D55: =IFERROR(D10,0) -> 6.6 | E55: =IFERROR(E10,0) -> 0 | F55: =IFERROR(F10,0) -> 4.7 | G55: =IFERROR(G10,0) -> 0 | H55: =IFERROR(H10,0) -> 52.2 | I55: =IFERROR(I10,0) -> 57.3 | J55: =IFERROR(J10,0) -> 1278.1 | ... AR55: =IFERROR(AR10,0) -> 0
A56: D17T18: Paper products and printing | B56: pulp paper and printing 17T18 | C56: =IFERROR(C11,0) -> 89.5 | D56: =IFERROR(D11,0) -> 0 | E56: =IFERROR(E11,0) -> 0 | F56: =IFERROR(F11,0) -> 11.7 | G56: =IFERROR(G11,0) -> 0 | H56: =IFERROR(H11,0) -> 1141.9 | I56: =IFERROR(I11,0) -> 458.8 | J56: =IFERROR(J11,0) -> 131.3 | ... AR56: =IFERROR(AR11,0) -> 0
A57: D19: Coke and refined petroleum products | B57: refined petroleum and coke 19 | C57: =IFERROR(C12,0) -> 1199.3 | D57: =IFERROR(D12,0) -> 0 | E57: =IFERROR(E12,0) -> 0 | F57: =IFERROR(F12,0) -> 119.3 | G57: =IFERROR(G12,0) -> 0.4 | H57: =IFERROR(H12,0) -> 510.8 | I57: =IFERROR(I12,0) -> 736.2 | J57: =IFERROR(J12,0) -> 151.4 | ... AR57: =IFERROR(AR12,0) -> 0
A58: chemicals 20 | B58: chemicals 20 | C58: =IFERROR(C13,0) -> 1643.4 | D58: =IFERROR(D13,0) -> 21.305433 | E58: =IFERROR(E13,0) -> 16.394567 | F58: =IFERROR(F13,0) -> 77 | G58: =IFERROR(G13,0) -> 0.19346503 | H58: =IFERROR(H13,0) -> 858.50171 | I58: =IFERROR(I13,0) -> 2908.5924 | J58: =IFERROR(J13,0) -> 364.27004 | ... L58: =IFERROR(L13,0) -> 4370.9567 | M58: =IFERROR(#REF!,0) -> 0 | N58: =IFERROR(#REF!,0) -> 0 | O58: =IFERROR(O13,0) -> 14087.782 | P58: =IFERROR(P13,0) -> 566.18786 | Q58: =IFERROR(Q13,0) -> 1177.2751 | R58: =IFERROR(R13,0) -> 2894.9878 | S58: =IFERROR(S13,0) -> 1222.7933 | T58: =IFERROR(T13,0) -> 1751.7384 | U58: =IFERROR(U13,0) -> 3086.6 | V58: =IFERROR(V13,0) -> 1813.5722 | ... AR58: =IFERROR(AR13,0) -> 0
A59: pharmaceuticals | B59: chemicals 20 | C59: =IFERROR(C14,0) -> 0 | D59: =IFERROR(D14,0) -> 0 | E59: =IFERROR(E14,0) -> 0 | F59: =IFERROR(F14,0) -> 0 | G59: =IFERROR(G14,0) -> 0.0065349712 | H59: =IFERROR(H14,0) -> 35.098293 | I59: =IFERROR(I14,0) -> 604.50763 | J59: =IFERROR(J14,0) -> 27.62996 | ... L59: =IFERROR(L14,0) -> 131.04335 | M59: =IFERROR(#REF!,0) -> 0 | N59: =IFERROR(#REF!,0) -> 0 | O59: =IFERROR(O14,0) -> 51.217713 | P59: =IFERROR(P14,0) -> 0.5370543 | Q59: =IFERROR(Q14,0) -> 0 | R59: =IFERROR(R14,0) -> 5.7909474 | S59: =IFERROR(S14,0) -> 0.72793417 | T59: =IFERROR(T14,0) -> 1.6616016 | U59: =IFERROR(U14,0) -> 0 | V59: =IFERROR(V14,0) -> 3.6277533 | ... AR59: =IFERROR(AR14,0) -> 0
A60: D22: Rubber and plastic products | B60: rubber and plastic products 22 | C60: =IFERROR(C15,0) -> 242.8 | D60: =IFERROR(D15,0) -> 30.4 | E60: =IFERROR(E15,0) -> 0 | F60: =IFERROR(F15,0) -> 43.1 | G60: =IFERROR(G15,0) -> 0.1 | H60: =IFERROR(H15,0) -> 1866.4 | I60: =IFERROR(I15,0) -> 1204.3 | J60: =IFERROR(J15,0) -> 194.9 | ... AR60: =IFERROR(AR15,0) -> 0
A61: glass and glass products 231 | B61: glass and glass products 231 | C61: =IFERROR(C16,0) -> 36.20301 | D61: =IFERROR(D16,0) -> 3.1220163 | E61: =IFERROR(E16,0) -> 0.3143881 | F61: =IFERROR(F16,0) -> 48.177392 | G61: =IFERROR(G16,0) -> 0 | H61: =IFERROR(H16,0) -> 0 | I61: =IFERROR(I16,0) -> 158.1 | J61: =IFERROR(J16,0) -> 0 | ... AR61: =IFERROR(AR16,0) -> 0
A62: cement and other nonmetallic minerals 239 | B62: cement and other nonmetallic minerals 239 | C62: =IFERROR(C17,0) -> 63.89699 | D62: =IFERROR(D17,0) -> 1.0432186 | E62: =IFERROR(E17,0) -> 0.020377 | F62: =IFERROR(F17,0) -> 3.1226077 | G62: =IFERROR(G17,0) -> 0 | H62: =IFERROR(H17,0) -> 0 | I62: =IFERROR(I17,0) -> 0 | J62: =IFERROR(J17,0) -> 0 | ... AR62: =IFERROR(AR17,0) -> 0
A63: iron and steel 241 | B63: iron and steel 241 | C63: =IFERROR(C18,0) -> 0 | D63: =IFERROR(D18,0) -> 8.0584225 | E63: =IFERROR(E18,0) -> 0.14042807 | F63: =IFERROR(F18,0) -> 20.029919 | G63: =IFERROR(G18,0) -> 0 | H63: =IFERROR(H18,0) -> 0 | I63: =IFERROR(I18,0) -> 0 | J63: =IFERROR(J18,0) -> 0 | ... AR63: =IFERROR(AR18,0) -> 0
A64: other metals 242 | B64: other metals 242 | C64: =IFERROR(C19,0) -> 0 | D64: =IFERROR(D19,0) -> 0.097152604 | E64: =IFERROR(E19,0) -> 0.0039967893 | F64: =IFERROR(F19,0) -> 0.57008092 | G64: =IFERROR(G19,0) -> 0 | H64: =IFERROR(H19,0) -> 0 | I64: =IFERROR(I19,0) -> 0 | J64: =IFERROR(J19,0) -> 0 | ... AR64: =IFERROR(AR19,0) -> 0
A65: D25: Fabricated metal products | B65: metal products except machinery and vehicles 25 | C65: =IFERROR(C20,0) -> 253.2 | D65: =IFERROR(D20,0) -> 33.4 | E65: =IFERROR(E20,0) -> 0 | F65: =IFERROR(F20,0) -> 46.6 | G65: =IFERROR(G20,0) -> 0.3 | H65: =IFERROR(H20,0) -> 1028.8 | I65: =IFERROR(I20,0) -> 366.2 | J65: =IFERROR(J20,0) -> 305.4 | ... AR65: =IFERROR(AR20,0) -> 0
A66: D26: Computer, electronic and optical products | B66: computers and electronics 26 | C66: =IFERROR(C21,0) -> 200.3 | D66: =IFERROR(D21,0) -> 0 | E66: =IFERROR(E21,0) -> 0 | F66: =IFERROR(F21,0) -> 17.4 | G66: =IFERROR(G21,0) -> 0 | H66: =IFERROR(H21,0) -> 841.9 | I66: =IFERROR(I21,0) -> 461.4 | J66: =IFERROR(J21,0) -> 81.6 | ... AR66: =IFERROR(AR21,0) -> 0
A67: D27: Electrical equipment | B67: appliances and electrical equipment 27 | C67: =IFERROR(C22,0) -> 60.2 | D67: =IFERROR(D22,0) -> 10.2 | E67: =IFERROR(E22,0) -> 0 | F67: =IFERROR(F22,0) -> 13 | G67: =IFERROR(G22,0) -> 0 | H67: =IFERROR(H22,0) -> 116.6 | I67: =IFERROR(I22,0) -> 91.8 | J67: =IFERROR(J22,0) -> 29.2 | ... AR67: =IFERROR(AR22,0) -> 0
A68: D28: Machinery and equipment, nec | B68: other machinery 28 | C68: =IFERROR(C23,0) -> 424.4 | D68: =IFERROR(D23,0) -> 66.7 | E68: =IFERROR(E23,0) -> 0 | F68: =IFERROR(F23,0) -> 113.3 | G68: =IFERROR(G23,0) -> 0.9 | H68: =IFERROR(H23,0) -> 362.1 | I68: =IFERROR(I23,0) -> 441.3 | J68: =IFERROR(J23,0) -> 125.7 | ... AR68: =IFERROR(AR23,0) -> 0
A69: D29: Motor vehicles, trailers and semi-trailers | B69: road vehicles 29 | C69: =IFERROR(C24,0) -> 120.6 | D69: =IFERROR(D24,0) -> 0 | E69: =IFERROR(E24,0) -> 0 | F69: =IFERROR(F24,0) -> 20.9 | G69: =IFERROR(G24,0) -> 0 | H69: =IFERROR(H24,0) -> 158.5 | I69: =IFERROR(I24,0) -> 132.1 | J69: =IFERROR(J24,0) -> 54 | ... AR69: =IFERROR(AR24,0) -> 0
A70: D30: Other transport equipment | B70: nonroad vehicles 30 | C70: =IFERROR(C25,0) -> 64.9 | D70: =IFERROR(D25,0) -> 7.1879115 | E70: =IFERROR(E25,0) -> 0.012088489 | F70: =IFERROR(F25,0) -> 8.4 | G70: =IFERROR(G25,0) -> 0.1 | H70: =IFERROR(H25,0) -> 66.8 | I70: =IFERROR(I25,0) -> 34.8 | J70: =IFERROR(J25,0) -> 20.7 | ... AR70: =IFERROR(AR25,0) -> 0
A71: D31T33: Other manufacturing; repair and installation of machinery and equipment | B71: other manufacturing 31T33 | C71: =IFERROR(C26,0) -> 69.4 | D71: =IFERROR(D26,0) -> 0 | E71: =IFERROR(E26,0) -> 0 | F71: =IFERROR(F26,0) -> 5 | G71: =IFERROR(G26,0) -> 0 | H71: =IFERROR(H26,0) -> 97.5 | I71: =IFERROR(I26,0) -> 100 | J71: =IFERROR(J26,0) -> 23.6 | ... AR71: =IFERROR(AR26,0) -> 0
A72: electricity | C72: =IFERROR(C27,0) -> 449.59069 | D72: =IFERROR(D27,0) -> 0 | E72: =IFERROR(E27,0) -> 0 | F72: =IFERROR(F27,0) -> 0 | G72: =IFERROR(G27,0) -> 0 | H72: =IFERROR(H27,0) -> 0 | I72: =IFERROR(I27,0) -> 140.75557 | J72: =IFERROR(J27,0) -> 103.48796 | ... AR72: =IFERROR(AR27,0) -> 0
A73: energy pipelines and gas processing 352T353 | B73: energy pipelines and gas processing 352T353 | C73: =IFERROR(C28,0) -> 67.909309 | D73: =IFERROR(D28,0) -> 74.317402 | E73: =IFERROR(E28,0) -> 4.8825983 | F73: =IFERROR(F28,0) -> 131.9 | G73: =IFERROR(G28,0) -> 0 | H73: =IFERROR(H28,0) -> 0 | I73: =IFERROR(I28,0) -> 42.259803 | J73: =IFERROR(J28,0) -> 50.69442 | ... AR73: =IFERROR(AR28,0) -> 0
A74: water and waste 36T39 | B74: water and waste 36T39 | C74: =IFERROR(C29,0) -> 0 | D74: =IFERROR(D29,0) -> 0 | E74: =IFERROR(E29,0) -> 0 | F74: =IFERROR(F29,0) -> 0 | G74: =IFERROR(G29,0) -> 0.3 | H74: =IFERROR(H29,0) -> 1097.3 | I74: =IFERROR(I29,0) -> 940.98462 | J74: =IFERROR(J29,0) -> 109.71762 | ... AR74: =IFERROR(AR29,0) -> 0
A75: D41T43: Construction | B75: construction 41T43 | C75: =IFERROR(C30,0) -> 26.5 | D75: =IFERROR(D30,0) -> 0 | E75: =IFERROR(E30,0) -> 0 | F75: =IFERROR(F30,0) -> 6 | G75: =IFERROR(G30,0) -> 0 | H75: =IFERROR(H30,0) -> 28.2 | I75: =IFERROR(I30,0) -> 21.3 | J75: =IFERROR(J30,0) -> 6.6 | ... AR75: =IFERROR(AR30,0) -> 0
A76: D45T47: Wholesale and retail trade; repair of motor vehicles | C76: =IFERROR(C31,0) -> 3229.9 | D76: =IFERROR(D31,0) -> 0 | E76: =IFERROR(E31,0) -> 0 | F76: =IFERROR(F31,0) -> 72.7 | G76: =IFERROR(G31,0) -> 0.3 | H76: =IFERROR(H31,0) -> 14779.7 | I76: =IFERROR(I31,0) -> 7528.5 | J76: =IFERROR(J31,0) -> 584.6 | ... AR76: =IFERROR(AR31,0) -> 0
A77: D49T53: Transportation and storage | C77: =IFERROR(C32,0) -> 458.7 | D77: =IFERROR(D32,0) -> 0 | E77: =IFERROR(E32,0) -> 49.9 | F77: =IFERROR(F32,0) -> 125.8 | G77: =IFERROR(G32,0) -> 0.3 | H77: =IFERROR(H32,0) -> 1483.2 | I77: =IFERROR(I32,0) -> 1090.5 | J77: =IFERROR(J32,0) -> 277.6 | ... AR77: =IFERROR(AR32,0) -> 0
A78: D55T56: Accomodation and food services | C78: =IFERROR(C33,0) -> 43.1 | D78: =IFERROR(D33,0) -> 1.7644414 | E78: =IFERROR(E33,0) -> 0.63555858 | F78: =IFERROR(F33,0) -> 3.9 | G78: =IFERROR(G33,0) -> 0.1 | H78: =IFERROR(H33,0) -> 101.7 | I78: =IFERROR(I33,0) -> 83.9 | J78: =IFERROR(J33,0) -> 23.1 | ... AR78: =IFERROR(AR33,0) -> 0
A79: D58T60: Publishing, audiovisual and broadcasting activities | C79: =IFERROR(C34,0) -> 10.9 | D79: =IFERROR(D34,0) -> 0 | E79: =IFERROR(E34,0) -> 0 | F79: =IFERROR(F34,0) -> 0.9 | G79: =IFERROR(G34,0) -> 0 | H79: =IFERROR(H34,0) -> 97 | I79: =IFERROR(I34,0) -> 26.1 | J79: =IFERROR(J34,0) -> 7.5 | ... AR79: =IFERROR(AR34,0) -> 0
A80: D61: Telecommunications | C80: =IFERROR(C35,0) -> 84.8 | D80: =IFERROR(D35,0) -> 1.714193 | E80: =IFERROR(E35,0) -> 0.085807012 | F80: =IFERROR(F35,0) -> 10.6 | G80: =IFERROR(G35,0) -> 0.1 | H80: =IFERROR(H35,0) -> 137.8 | I80: =IFERROR(I35,0) -> 169.7 | J80: =IFERROR(J35,0) -> 29.6 | ... AR80: =IFERROR(AR35,0) -> 0
A81: D62T63: IT and other information services | C81: =IFERROR(C36,0) -> 18 | D81: =IFERROR(D36,0) -> 6.8 | E81: =IFERROR(E36,0) -> 0 | F81: =IFERROR(F36,0) -> 4 | G81: =IFERROR(G36,0) -> 0 | H81: =IFERROR(H36,0) -> 139.7 | I81: =IFERROR(I36,0) -> 96.6 | J81: =IFERROR(J36,0) -> 18.3 | ... AR81: =IFERROR(AR36,0) -> 0
A82: D64T66: Financial and insurance activities | C82: =IFERROR(C37,0) -> 691.4 | D82: =IFERROR(D37,0) -> 0 | E82: =IFERROR(E37,0) -> 0 | F82: =IFERROR(F37,0) -> 55.8 | G82: =IFERROR(G37,0) -> 0.2 | H82: =IFERROR(H37,0) -> 739.7 | I82: =IFERROR(I37,0) -> 761.6 | J82: =IFERROR(J37,0) -> 176.4 | ... AR82: =IFERROR(AR37,0) -> 0
A83: D68: Real estate activities | C83: =IFERROR(C38,0) -> 40.8 | D83: =IFERROR(D38,0) -> 0 | E83: =IFERROR(E38,0) -> 0 | F83: =IFERROR(F38,0) -> 3.2 | G83: =IFERROR(G38,0) -> 0 | H83: =IFERROR(H38,0) -> 126.1 | I83: =IFERROR(I38,0) -> 150.1 | J83: =IFERROR(J38,0) -> 23.4 | ... AR83: =IFERROR(AR38,0) -> 0
A84: D69T82: Other business sector services | C84: =IFERROR(C39,0) -> 423.2 | D84: =IFERROR(D39,0) -> 0 | E84: =IFERROR(E39,0) -> 0 | F84: =IFERROR(F39,0) -> 70 | G84: =IFERROR(G39,0) -> 0.5 | H84: =IFERROR(H39,0) -> 1874.9 | I84: =IFERROR(I39,0) -> 984.7 | J84: =IFERROR(J39,0) -> 240.4 | ... AR84: =IFERROR(AR39,0) -> 0
A85: D84: Public admin. and defence; compulsory social security | C85: =IFERROR(C40,0) -> 35.4 | D85: =IFERROR(D40,0) -> 0 | E85: =IFERROR(E40,0) -> 0 | F85: =IFERROR(F40,0) -> 3.6 | G85: =IFERROR(G40,0) -> 0 | H85: =IFERROR(H40,0) -> 97 | I85: =IFERROR(I40,0) -> 73.7 | J85: =IFERROR(J40,0) -> 13.7 | ... AR85: =IFERROR(AR40,0) -> 0
A86: D85: Education | C86: =IFERROR(C41,0) -> 13.1 | D86: =IFERROR(D41,0) -> 0 | E86: =IFERROR(E41,0) -> 0 | F86: =IFERROR(F41,0) -> 2.3 | G86: =IFERROR(G41,0) -> 0 | H86: =IFERROR(H41,0) -> 38.6 | I86: =IFERROR(I41,0) -> 34.5 | J86: =IFERROR(J41,0) -> 6.9 | ... AR86: =IFERROR(AR41,0) -> 0
A87: D86T88: Human health and social work | C87: =IFERROR(C42,0) -> 185.5 | D87: =IFERROR(D42,0) -> 0 | E87: =IFERROR(E42,0) -> 0 | F87: =IFERROR(F42,0) -> 1.4 | G87: =IFERROR(G42,0) -> 0 | H87: =IFERROR(H42,0) -> 494.8 | I87: =IFERROR(I42,0) -> 42.2 | J87: =IFERROR(J42,0) -> 55.3 | ... AR87: =IFERROR(AR42,0) -> 0
... A89: D97T98: Private households with employed persons | C89: =IFERROR(C44,0) -> 0 | D89: =IFERROR(D44,0) -> 0 | E89: =IFERROR(E44,0) -> 0 | F89: =IFERROR(F44,0) -> 0 | G89: =IFERROR(G44,0) -> 0 | H89: =IFERROR(H44,0) -> 0 | I89: =IFERROR(I44,0) -> 0 | J89: =IFERROR(J44,0) -> 0 | ... AR89: =IFERROR(AR44,0) -> 0

Sheet FoGPbEaIC-isic
A1: Unit: dimensionless (% of output purchased) | B1: ISIC 01T03 | C1: ISIC 05 | D1: ISIC 06 | E1: ISIC 07T08 | F1: ISIC 09 | G1: ISIC 10T12 | H1: ISIC 13T15 | I1: ISIC 16 | J1: ISIC 17T18 | K1: ISIC 19 | L1: ISIC 20 | M1: ISIC 21 | N1: ISIC 22 | O1: ISIC 231 | P1: ISIC 239 | Q1: ISIC 241 | R1: ISIC 242 | S1: ISIC 25 | T1: ISIC 26 | U1: ISIC 27 | V1: ISIC 28 | W1: ISIC 29 | X1: ISIC 30 | Y1: ISIC 31T33 | Z1: ISIC 351 | AA1: ISIC 352T353 | AB1: ISIC 36T39 | AC1: ISIC 41T43 | AD1: ISIC 45T47 | AE1: ISIC 49T53 | AF1: ISIC 55T56 | AG1: ISIC 58T60 | AH1: ISIC 61 | AI1: ISIC 62T63 | AJ1: ISIC 64T66 | AK1: ISIC 68 | AL1: ISIC 69T82 | AM1: ISIC 84 | AN1: ISIC 85 | AO1: ISIC 86T88 | AP1: ISIC 90T96 | AQ1: ISIC 97T98
A2: agriculture and forestry 01T03 | B2: {=SUMPRODUCT(SIOM!$C$48:$AR$89*(SIOM!$B$48:$B$89='FoGPbEaIC-isic'!$A2)*(SIOM!$C$47:$AR$47='FoGPbEaIC-isic'!B$1))/SUMPRODUCT(SIOM!$C$48:$AR$89*(SIOM!$B$48:$B$89='FoGPbEaIC-isic'!$A2))} -> 0.10793681 | C2: {=SUMPRODUCT(SIOM!$C$48:$AR$89*(SIOM!$B$48:$B$89='FoGPbEaIC-isic'!$A2)*(SIOM!$C$47:$AR$47='FoGPbEaIC-isic'!C$1))/SUMPRODUCT(SIOM!$C$48:$AR$89*(SIOM!$B$48:$B$89='FoGPbEaIC-isic'!$A2))} -> 0 | D2: {=SUMPRODUCT(SIOM!$C$48:$AR$89*(SIOM!$B$48:$B$89='FoGPbEaIC-isic'!$A2)*(SIOM!$C$47:$AR$47='FoGPbEaIC-isic'!D$1))/SUMPRODUCT(SIOM!$C$48:$AR$89*(SIOM!$B$48:$B$89='FoGPbEaIC-isic'!$A2))} -> 0 | E2: {=SUMPRODUCT(SIOM!$C$48:$AR$89*(SIOM!$B$48:$B$89='FoGPbEaIC-isic'!$A2)*(SIOM!$C$47:$AR$47='FoGPbEaIC-isic'!E$1))/SUMPRODUCT(SIOM!$C$48:$AR$89*(SIOM!$B$48:$B$89='FoGPbEaIC-isic'!$A2))} -> 7.9998903e-05 | F2: {=SUMPRODUCT(SIOM!$C$48:$AR$89*(SIOM!$B$48:$B$89='FoGPbEaIC-isic'!$A2)*(SIOM!$C$47:$AR$47='FoGPbEaIC-isic'!F$1))/SUMPRODUCT(SIOM!$C$48:$AR$89*(SIOM!$B$48:$B$89='FoGPbEaIC-isic'!$A2))} -> 0 | G2: {=SUMPRODUCT(SIOM!$C$48:$AR$89*(SIOM!$B$48:$B$89='FoGPbEaIC-isic'!$A2)*(SIOM!$C$47:$AR$47='FoGPbEaIC-isic'!G$1))/SUMPRODUCT(SIOM!$C$48:$AR$89*(SIOM!$B$48:$B$89='FoGPbEaIC-isic'!$A2))} -> 0.63767583 | H2: {=SUMPRODUCT(SIOM!$C$48:$AR$89*(SIOM!$B$48:$B$89='FoGPbEaIC-isic'!$A2)*(SIOM!$C$47:$AR$47='FoGPbEaIC-isic'!H$1))/SUMPRODUCT(SIOM!$C$48:$AR$89*(SIOM!$B$48:$B$89='FoGPbEaIC-isic'!$A2))} -> 0.031231572 | I2: {=SUMPRODUCT(SIOM!$C$48:$AR$89*(SIOM!$B$48:$B$89='FoGPbEaIC-isic'!$A2)*(SIOM!$C$47:$AR$47='FoGPbEaIC-isic'!I$1))/SUMPRODUCT(SIOM!$C$48:$AR$89*(SIOM!$B$48:$B$89='FoGPbEaIC-isic'!$A2))} -> 0.021473991 | ... AQ2: {=SUMPRODUCT(SIOM!$C$48:$AR$89*(SIOM!$B$48:$B$89='FoGPbEaIC-isic'!$A2)*(SIOM!$C$47:$AR$47='FoGPbEaIC-isic'!AQ$1))/SUMPRODUCT(SIOM!$C$48:$AR$89*(SIOM!$B$48:$B$89='FoGPbEaIC-isic'!$A2))} -> 0
A3: coal mining 05 | B3: {=SUMPRODUCT(SIOM!$C$48:$AR$89*(SIOM!$B$48:$B$89='FoGPbEaIC-isic'!$A3)*(SIOM!$C$47:$AR$47='FoGPbEaIC-isic'!B$1))/SUMPRODUCT(SIOM!$C$48:$AR$89*(SIOM!$B$48:$B$89='FoGPbEaIC-isic'!$A3))} -> 0 | C3: {=SUMPRODUCT(SIOM!$C$48:$AR$89*(SIOM!$B$48:$B$89='FoGPbEaIC-isic'!$A3)*(SIOM!$C$47:$AR$47='FoGPbEaIC-isic'!C$1))/SUMPRODUCT(SIOM!$C$48:$AR$89*(SIOM!$B$48:$B$89='FoGPbEaIC-isic'!$A3))} -> 0 | D3: {=SUMPRODUCT(SIOM!$C$48:$AR$89*(SIOM!$B$48:$B$89='FoGPbEaIC-isic'!$A3)*(SIOM!$C$47:$AR$47='FoGPbEaIC-isic'!D$1))/SUMPRODUCT(SIOM!$C$48:$AR$89*(SIOM!$B$48:$B$89='FoGPbEaIC-isic'!$A3))} -> 0 | E3: {=SUMPRODUCT(SIOM!$C$48:$AR$89*(SIOM!$B$48:$B$89='FoGPbEaIC-isic'!$A3)*(SIOM!$C$47:$AR$47='FoGPbEaIC-isic'!E$1))/SUMPRODUCT(SIOM!$C$48:$AR$89*(SIOM!$B$48:$B$89='FoGPbEaIC-isic'!$A3))} -> 0 | F3: {=SUMPRODUCT(SIOM!$C$48:$AR$89*(SIOM!$B$48:$B$89='FoGPbEaIC-isic'!$A3)*(SIOM!$C$47:$AR$47='FoGPbEaIC-isic'!F$1))/SUMPRODUCT(SIOM!$C$48:$AR$89*(SIOM!$B$48:$B$89='FoGPbEaIC-isic'!$A3))} -> 0 | G3: {=SUMPRODUCT(SIOM!$C$48:$AR$89*(SIOM!$B$48:$B$89='FoGPbEaIC-isic'!$A3)*(SIOM!$C$47:$AR$47='FoGPbEaIC-isic'!G$1))/SUMPRODUCT(SIOM!$C$48:$AR$89*(SIOM!$B$48:$B$89='FoGPbEaIC-isic'!$A3))} -> 0 | H3: {=SUMPRODUCT(SIOM!$C$48:$AR$89*(SIOM!$B$48:$B$89='FoGPbEaIC-isic'!$A3)*(SIOM!$C$47:$AR$47='FoGPbEaIC-isic'!H$1))/SUMPRODUCT(SIOM!$C$48:$AR$89*(SIOM!$B$48:$B$89='FoGPbEaIC-isic'!$A3))} -> 0 | I3: {=SUMPRODUCT(SIOM!$C$48:$AR$89*(SIOM!$B$48:$B$89='FoGPbEaIC-isic'!$A3)*(SIOM!$C$47:$AR$47='FoGPbEaIC-isic'!I$1))/SUMPRODUCT(SIOM!$C$48:$AR$89*(SIOM!$B$48:$B$89='FoGPbEaIC-isic'!$A3))} -> 0 | ... AQ3: {=SUMPRODUCT(SIOM!$C$48:$AR$89*(SIOM!$B$48:$B$89='FoGPbEaIC-isic'!$A3)*(SIOM!$C$47:$AR$47='FoGPbEaIC-isic'!AQ$1))/SUMPRODUCT(SIOM!$C$48:$AR$89*(SIOM!$B$48:$B$89='FoGPbEaIC-isic'!$A3))} -> 0
A4: oil and gas extraction 06 | B4: {=SUMPRODUCT(SIOM!$C$48:$AR$89*(SIOM!$B$48:$B$89='FoGPbEaIC-isic'!$A4)*(SIOM!$C$47:$AR$47='FoGPbEaIC-isic'!B$1))/SUMPRODUCT(SIOM!$C$48:$AR$89*(SIOM!$B$48:$B$89='FoGPbEaIC-isic'!$A4))} -> 0 | C4: {=SUMPRODUCT(SIOM!$C$48:$AR$89*(SIOM!$B$48:$B$89='FoGPbEaIC-isic'!$A4)*(SIOM!$C$47:$AR$47='FoGPbEaIC-isic'!C$1))/SUMPRODUCT(SIOM!$C$48:$AR$89*(SIOM!$B$48:$B$89='FoGPbEaIC-isic'!$A4))} -> 0 | D4: {=SUMPRODUCT(SIOM!$C$48:$AR$89*(SIOM!$B$48:$B$89='FoGPbEaIC-isic'!$A4)*(SIOM!$C$47:$AR$47='FoGPbEaIC-isic'!D$1))/SUMPRODUCT(SIOM!$C$48:$AR$89*(SIOM!$B$48:$B$89='FoGPbEaIC-isic'!$A4))} -> 0 | E4: {=SUMPRODUCT(SIOM!$C$48:$AR$89*(SIOM!$B$48:$B$89='FoGPbEaIC-isic'!$A4)*(SIOM!$C$47:$AR$47='FoGPbEaIC-isic'!E$1))/SUMPRODUCT(SIOM!$C$48:$AR$89*(SIOM!$B$48:$B$89='FoGPbEaIC-isic'!$A4))} -> 0 | F4: {=SUMPRODUCT(SIOM!$C$48:$AR$89*(SIOM!$B$48:$B$89='FoGPbEaIC-isic'!$A4)*(SIOM!$C$47:$AR$47='FoGPbEaIC-isic'!F$1))/SUMPRODUCT(SIOM!$C$48:$AR$89*(SIOM!$B$48:$B$89='FoGPbEaIC-isic'!$A4))} -> 0 | G4: {=SUMPRODUCT(SIOM!$C$48:$AR$89*(SIOM!$B$48:$B$89='FoGPbEaIC-isic'!$A4)*(SIOM!$C$47:$AR$47='FoGPbEaIC-isic'!G$1))/SUMPRODUCT(SIOM!$C$48:$AR$89*(SIOM!$B$48:$B$89='FoGPbEaIC-isic'!$A4))} -> 0 | H4: {=SUMPRODUCT(SIOM!$C$48:$AR$89*(SIOM!$B$48:$B$89='FoGPbEaIC-isic'!$A4)*(SIOM!$C$47:$AR$47='FoGPbEaIC-isic'!H$1))/SUMPRODUCT(SIOM!$C$48:$AR$89*(SIOM!$B$48:$B$89='FoGPbEaIC-isic'!$A4))} -> 0 | I4: {=SUMPRODUCT(SIOM!$C$48:$AR$89*(SIOM!$B$48:$B$89='FoGPbEaIC-isic'!$A4)*(SIOM!$C$47:$AR$47='FoGPbEaIC-isic'!I$1))/SUMPRODUCT(SIOM!$C$48:$AR$89*(SIOM!$B$48:$B$89='FoGPbEaIC-isic'!$A4))} -> 0 | ... AQ4: {=SUMPRODUCT(SIOM!$C$48:$AR$89*(SIOM!$B$48:$B$89='FoGPbEaIC-isic'!$A4)*(SIOM!$C$47:$AR$47='FoGPbEaIC-isic'!AQ$1))/SUMPRODUCT(SIOM!$C$48:$AR$89*(SIOM!$B$48:$B$89='FoGPbEaIC-isic'!$A4))} -> 0
A5: other mining and quarrying 07T08 | B5: {=SUMPRODUCT(SIOM!$C$48:$AR$89*(SIOM!$B$48:$B$89='FoGPbEaIC-isic'!$A5)*(SIOM!$C$47:$AR$47='FoGPbEaIC-isic'!B$1))/SUMPRODUCT(SIOM!$C$48:$AR$89*(SIOM!$B$48:$B$89='FoGPbEaIC-isic'!$A5))} -> 0.00098926573 | C5: {=SUMPRODUCT(SIOM!$C$48:$AR$89*(SIOM!$B$48:$B$89='FoGPbEaIC-isic'!$A5)*(SIOM!$C$47:$AR$47='FoGPbEaIC-isic'!C$1))/SUMPRODUCT(SIOM!$C$48:$AR$89*(SIOM!$B$48:$B$89='FoGPbEaIC-isic'!$A5))} -> 0 | D5: {=SUMPRODUCT(SIOM!$C$48:$AR$89*(SIOM!$B$48:$B$89='FoGPbEaIC-isic'!$A5)*(SIOM!$C$47:$AR$47='FoGPbEaIC-isic'!D$1))/SUMPRODUCT(SIOM!$C$48:$AR$89*(SIOM!$B$48:$B$89='FoGPbEaIC-isic'!$A5))} -> 0 | E5: {=SUMPRODUCT(SIOM!$C$48:$AR$89*(SIOM!$B$48:$B$89='FoGPbEaIC-isic'!$A5)*(SIOM!$C$47:$AR$47='FoGPbEaIC-isic'!E$1))/SUMPRODUCT(SIOM!$C$48:$AR$89*(SIOM!$B$48:$B$89='FoGPbEaIC-isic'!$A5))} -> 0.0025100772 | F5: {=SUMPRODUCT(SIOM!$C$48:$AR$89*(SIOM!$B$48:$B$89='FoGPbEaIC-isic'!$A5)*(SIOM!$C$47:$AR$47='FoGPbEaIC-isic'!F$1))/SUMPRODUCT(SIOM!$C$48:$AR$89*(SIOM!$B$48:$B$89='FoGPbEaIC-isic'!$A5))} -> 0 | G5: {=SUMPRODUCT(SIOM!$C$48:$AR$89*(SIOM!$B$48:$B$89='FoGPbEaIC-isic'!$A5)*(SIOM!$C$47:$AR$47='FoGPbEaIC-isic'!G$1))/SUMPRODUCT(SIOM!$C$48:$AR$89*(SIOM!$B$48:$B$89='FoGPbEaIC-isic'!$A5))} -> 0.0011000044 | H5: {=SUMPRODUCT(SIOM!$C$48:$AR$89*(SIOM!$B$48:$B$89='FoGPbEaIC-isic'!$A5)*(SIOM!$C$47:$AR$47='FoGPbEaIC-isic'!H$1))/SUMPRODUCT(SIOM!$C$48:$AR$89*(SIOM!$B$48:$B$89='FoGPbEaIC-isic'!$A5))} -> 0.00049463286 | I5: {=SUMPRODUCT(SIOM!$C$48:$AR$89*(SIOM!$B$48:$B$89='FoGPbEaIC-isic'!$A5)*(SIOM!$C$47:$AR$47='FoGPbEaIC-isic'!I$1))/SUMPRODUCT(SIOM!$C$48:$AR$89*(SIOM!$B$48:$B$89='FoGPbEaIC-isic'!$A5))} -> 0.00015503418 | ... AQ5: {=SUMPRODUCT(SIOM!$C$48:$AR$89*(SIOM!$B$48:$B$89='FoGPbEaIC-isic'!$A5)*(SIOM!$C$47:$AR$47='FoGPbEaIC-isic'!AQ$1))/SUMPRODUCT(SIOM!$C$48:$AR$89*(SIOM!$B$48:$B$89='FoGPbEaIC-isic'!$A5))} -> 0
A6: food beverage and tobacco 10T12 | B6: {=SUMPRODUCT(SIOM!$C$48:$AR$89*(SIOM!$B$48:$B$89='FoGPbEaIC-isic'!$A6)*(SIOM!$C$47:$AR$47='FoGPbEaIC-isic'!B$1))/SUMPRODUCT(SIOM!$C$48:$AR$89*(SIOM!$B$48:$B$89='FoGPbEaIC-isic'!$A6))} -> 0.085020618 | C6: {=SUMPRODUCT(SIOM!$C$48:$AR$89*(SIOM!$B$48:$B$89='FoGPbEaIC-isic'!$A6)*(SIOM!$C$47:$AR$47='FoGPbEaIC-isic'!C$1))/SUMPRODUCT(SIOM!$C$48:$AR$89*(SIOM!$B$48:$B$89='FoGPbEaIC-isic'!$A6))} -> 0 | D6: {=SUMPRODUCT(SIOM!$C$48:$AR$89*(SIOM!$B$48:$B$89='FoGPbEaIC-isic'!$A6)*(SIOM!$C$47:$AR$47='FoGPbEaIC-isic'!D$1))/SUMPRODUCT(SIOM!$C$48:$AR$89*(SIOM!$B$48:$B$89='FoGPbEaIC-isic'!$A6))} -> 0 | E6: {=SUMPRODUCT(SIOM!$C$48:$AR$89*(SIOM!$B$48:$B$89='FoGPbEaIC-isic'!$A6)*(SIOM!$C$47:$AR$47='FoGPbEaIC-isic'!E$1))/SUMPRODUCT(SIOM!$C$48:$AR$89*(SIOM!$B$48:$B$89='FoGPbEaIC-isic'!$A6))} -> 2.8527537e-05 | F6: {=SUMPRODUCT(SIOM!$C$48:$AR$89*(SIOM!$B$48:$B$89='FoGPbEaIC-isic'!$A6)*(SIOM!$C$47:$AR$47='FoGPbEaIC-isic'!F$1))/SUMPRODUCT(SIOM!$C$48:$AR$89*(SIOM!$B$48:$B$89='FoGPbEaIC-isic'!$A6))} -> 0 | G6: {=SUMPRODUCT(SIOM!$C$48:$AR$89*(SIOM!$B$48:$B$89='FoGPbEaIC-isic'!$A6)*(SIOM!$C$47:$AR$47='FoGPbEaIC-isic'!G$1))/SUMPRODUCT(SIOM!$C$48:$AR$89*(SIOM!$B$48:$B$89='FoGPbEaIC-isic'!$A6))} -> 0.34235041 | H6: {=SUMPRODUCT(SIOM!$C$48:$AR$89*(SIOM!$B$48:$B$89='FoGPbEaIC-isic'!$A6)*(SIOM!$C$47:$AR$47='FoGPbEaIC-isic'!H$1))/SUMPRODUCT(SIOM!$C$48:$AR$89*(SIOM!$B$48:$B$89='FoGPbEaIC-isic'!$A6))} -> 0.013091287 | I6: {=SUMPRODUCT(SIOM!$C$48:$AR$89*(SIOM!$B$48:$B$89='FoGPbEaIC-isic'!$A6)*(SIOM!$C$47:$AR$47='FoGPbEaIC-isic'!I$1))/SUMPRODUCT(SIOM!$C$48:$AR$89*(SIOM!$B$48:$B$89='FoGPbEaIC-isic'!$A6))} -> 0.0005177748 | ... AQ6: {=SUMPRODUCT(SIOM!$C$48:$AR$89*(SIOM!$B$48:$B$89='FoGPbEaIC-isic'!$A6)*(SIOM!$C$47:$AR$47='FoGPbEaIC-isic'!AQ$1))/SUMPRODUCT(SIOM!$C$48:$AR$89*(SIOM!$B$48:$B$89='FoGPbEaIC-isic'!$A6))} -> 0
A7: textiles apparel and leather 13T15 | B7: {=SUMPRODUCT(SIOM!$C$48:$AR$89*(SIOM!$B$48:$B$89='FoGPbEaIC-isic'!$A7)*(SIOM!$C$47:$AR$47='FoGPbEaIC-isic'!B$1))/SUMPRODUCT(SIOM!$C$48:$AR$89*(SIOM!$B$48:$B$89='FoGPbEaIC-isic'!$A7))} -> 0.0056324024 | C7: {=SUMPRODUCT(SIOM!$C$48:$AR$89*(SIOM!$B$48:$B$89='FoGPbEaIC-isic'!$A7)*(SIOM!$C$47:$AR$47='FoGPbEaIC-isic'!C$1))/SUMPRODUCT(SIOM!$C$48:$AR$89*(SIOM!$B$48:$B$89='FoGPbEaIC-isic'!$A7))} -> 0 | D7: {=SUMPRODUCT(SIOM!$C$48:$AR$89*(SIOM!$B$48:$B$89='FoGPbEaIC-isic'!$A7)*(SIOM!$C$47:$AR$47='FoGPbEaIC-isic'!D$1))/SUMPRODUCT(SIOM!$C$48:$AR$89*(SIOM!$B$48:$B$89='FoGPbEaIC-isic'!$A7))} -> 0 | E7: {=SUMPRODUCT(SIOM!$C$48:$AR$89*(SIOM!$B$48:$B$89='FoGPbEaIC-isic'!$A7)*(SIOM!$C$47:$AR$47='FoGPbEaIC-isic'!E$1))/SUMPRODUCT(SIOM!$C$48:$AR$89*(SIOM!$B$48:$B$89='FoGPbEaIC-isic'!$A7))} -> 0.00030525563 | F7: {=SUMPRODUCT(SIOM!$C$48:$AR$89*(SIOM!$B$48:$B$89='FoGPbEaIC-isic'!$A7)*(SIOM!$C$47:$AR$47='FoGPbEaIC-isic'!F$1))/SUMPRODUCT(SIOM!$C$48:$AR$89*(SIOM!$B$48:$B$89='FoGPbEaIC-isic'!$A7))} -> 1.7443179e-06 | G7: {=SUMPRODUCT(SIOM!$C$48:$AR$89*(SIOM!$B$48:$B$89='FoGPbEaIC-isic'!$A7)*(SIOM!$C$47:$AR$47='FoGPbEaIC-isic'!G$1))/SUMPRODUCT(SIOM!$C$48:$AR$89*(SIOM!$B$48:$B$89='FoGPbEaIC-isic'!$A7))} -> 0.0048579253 | H7: {=SUMPRODUCT(SIOM!$C$48:$AR$89*(SIOM!$B$48:$B$89='FoGPbEaIC-isic'!$A7)*(SIOM!$C$47:$AR$47='FoGPbEaIC-isic'!H$1))/SUMPRODUCT(SIOM!$C$48:$AR$89*(SIOM!$B$48:$B$89='FoGPbEaIC-isic'!$A7))} -> 0.47426259 | I7: {=SUMPRODUCT(SIOM!$C$48:$AR$89*(SIOM!$B$48:$B$89='FoGPbEaIC-isic'!$A7)*(SIOM!$C$47:$AR$47='FoGPbEaIC-isic'!I$1))/SUMPRODUCT(SIOM!$C$48:$AR$89*(SIOM!$B$48:$B$89='FoGPbEaIC-isic'!$A7))} -> 0.002145511 | ... AQ7: {=SUMPRODUCT(SIOM!$C$48:$AR$89*(SIOM!$B$48:$B$89='FoGPbEaIC-isic'!$A7)*(SIOM!$C$47:$AR$47='FoGPbEaIC-isic'!AQ$1))/SUMPRODUCT(SIOM!$C$48:$AR$89*(SIOM!$B$48:$B$89='FoGPbEaIC-isic'!$A7))} -> 0
A8: wood products 16 | B8: {=SUMPRODUCT(SIOM!$C$48:$AR$89*(SIOM!$B$48:$B$89='FoGPbEaIC-isic'!$A8)*(SIOM!$C$47:$AR$47='FoGPbEaIC-isic'!B$1))/SUMPRODUCT(SIOM!$C$48:$AR$89*(SIOM!$B$48:$B$89='FoGPbEaIC-isic'!$A8))} -> 0.0047598394 | C8: {=SUMPRODUCT(SIOM!$C$48:$AR$89*(SIOM!$B$48:$B$89='FoGPbEaIC-isic'!$A8)*(SIOM!$C$47:$AR$47='FoGPbEaIC-isic'!C$1))/SUMPRODUCT(SIOM!$C$48:$AR$89*(SIOM!$B$48:$B$89='FoGPbEaIC-isic'!$A8))} -> 0.00073399393 | D8: {=SUMPRODUCT(SIOM!$C$48:$AR$89*(SIOM!$B$48:$B$89='FoGPbEaIC-isic'!$A8)*(SIOM!$C$47:$AR$47='FoGPbEaIC-isic'!D$1))/SUMPRODUCT(SIOM!$C$48:$AR$89*(SIOM!$B$48:$B$89='FoGPbEaIC-isic'!$A8))} -> 0 | E8: {=SUMPRODUCT(SIOM!$C$48:$AR$89*(SIOM!$B$48:$B$89='FoGPbEaIC-isic'!$A8)*(SIOM!$C$47:$AR$47='FoGPbEaIC-isic'!E$1))/SUMPRODUCT(SIOM!$C$48:$AR$89*(SIOM!$B$48:$B$89='FoGPbEaIC-isic'!$A8))} -> 0.00052269265 | F8: {=SUMPRODUCT(SIOM!$C$48:$AR$89*(SIOM!$B$48:$B$89='FoGPbEaIC-isic'!$A8)*(SIOM!$C$47:$AR$47='FoGPbEaIC-isic'!F$1))/SUMPRODUCT(SIOM!$C$48:$AR$89*(SIOM!$B$48:$B$89='FoGPbEaIC-isic'!$A8))} -> 0 | G8: {=SUMPRODUCT(SIOM!$C$48:$AR$89*(SIOM!$B$48:$B$89='FoGPbEaIC-isic'!$A8)*(SIOM!$C$47:$AR$47='FoGPbEaIC-isic'!G$1))/SUMPRODUCT(SIOM!$C$48:$AR$89*(SIOM!$B$48:$B$89='FoGPbEaIC-isic'!$A8))} -> 0.0058052247 | H8: {=SUMPRODUCT(SIOM!$C$48:$AR$89*(SIOM!$B$48:$B$89='FoGPbEaIC-isic'!$A8)*(SIOM!$C$47:$AR$47='FoGPbEaIC-isic'!H$1))/SUMPRODUCT(SIOM!$C$48:$AR$89*(SIOM!$B$48:$B$89='FoGPbEaIC-isic'!$A8))} -> 0.0063724018 | I8: {=SUMPRODUCT(SIOM!$C$48:$AR$89*(SIOM!$B$48:$B$89='FoGPbEaIC-isic'!$A8)*(SIOM!$C$47:$AR$47='FoGPbEaIC-isic'!I$1))/SUMPRODUCT(SIOM!$C$48:$AR$89*(SIOM!$B$48:$B$89='FoGPbEaIC-isic'!$A8))} -> 0.14213904 | ... AQ8: {=SUMPRODUCT(SIOM!$C$48:$AR$89*(SIOM!$B$48:$B$89='FoGPbEaIC-isic'!$A8)*(SIOM!$C$47:$AR$47='FoGPbEaIC-isic'!AQ$1))/SUMPRODUCT(SIOM!$C$48:$AR$89*(SIOM!$B$48:$B$89='FoGPbEaIC-isic'!$A8))} -> 0
A9: pulp paper and printing 17T18 | B9: {=SUMPRODUCT(SIOM!$C$48:$AR$89*(SIOM!$B$48:$B$89='FoGPbEaIC-isic'!$A9)*(SIOM!$C$47:$AR$47='FoGPbEaIC-isic'!B$1))/SUMPRODUCT(SIOM!$C$48:$AR$89*(SIOM!$B$48:$B$89='FoGPbEaIC-isic'!$A9))} -> 0.0031869361 | C9: {=SUMPRODUCT(SIOM!$C$48:$AR$89*(SIOM!$B$48:$B$89='FoGPbEaIC-isic'!$A9)*(SIOM!$C$47:$AR$47='FoGPbEaIC-isic'!C$1))/SUMPRODUCT(SIOM!$C$48:$AR$89*(SIOM!$B$48:$B$89='FoGPbEaIC-isic'!$A9))} -> 0 | D9: {=SUMPRODUCT(SIOM!$C$48:$AR$89*(SIOM!$B$48:$B$89='FoGPbEaIC-isic'!$A9)*(SIOM!$C$47:$AR$47='FoGPbEaIC-isic'!D$1))/SUMPRODUCT(SIOM!$C$48:$AR$89*(SIOM!$B$48:$B$89='FoGPbEaIC-isic'!$A9))} -> 0 | E9: {=SUMPRODUCT(SIOM!$C$48:$AR$89*(SIOM!$B$48:$B$89='FoGPbEaIC-isic'!$A9)*(SIOM!$C$47:$AR$47='FoGPbEaIC-isic'!E$1))/SUMPRODUCT(SIOM!$C$48:$AR$89*(SIOM!$B$48:$B$89='FoGPbEaIC-isic'!$A9))} -> 0.00041661622 | F9: {=SUMPRODUCT(SIOM!$C$48:$AR$89*(SIOM!$B$48:$B$89='FoGPbEaIC-isic'!$A9)*(SIOM!$C$47:$AR$47='FoGPbEaIC-isic'!F$1))/SUMPRODUCT(SIOM!$C$48:$AR$89*(SIOM!$B$48:$B$89='FoGPbEaIC-isic'!$A9))} -> 0 | G9: {=SUMPRODUCT(SIOM!$C$48:$AR$89*(SIOM!$B$48:$B$89='FoGPbEaIC-isic'!$A9)*(SIOM!$C$47:$AR$47='FoGPbEaIC-isic'!G$1))/SUMPRODUCT(SIOM!$C$48:$AR$89*(SIOM!$B$48:$B$89='FoGPbEaIC-isic'!$A9))} -> 0.040661031 | H9: {=SUMPRODUCT(SIOM!$C$48:$AR$89*(SIOM!$B$48:$B$89='FoGPbEaIC-isic'!$A9)*(SIOM!$C$47:$AR$47='FoGPbEaIC-isic'!H$1))/SUMPRODUCT(SIOM!$C$48:$AR$89*(SIOM!$B$48:$B$89='FoGPbEaIC-isic'!$A9))} -> 0.016337053 | I9: {=SUMPRODUCT(SIOM!$C$48:$AR$89*(SIOM!$B$48:$B$89='FoGPbEaIC-isic'!$A9)*(SIOM!$C$47:$AR$47='FoGPbEaIC-isic'!I$1))/SUMPRODUCT(SIOM!$C$48:$AR$89*(SIOM!$B$48:$B$89='FoGPbEaIC-isic'!$A9))} -> 0.0046753598 | ... AQ9: {=SUMPRODUCT(SIOM!$C$48:$AR$89*(SIOM!$B$48:$B$89='FoGPbEaIC-isic'!$A9)*(SIOM!$C$47:$AR$47='FoGPbEaIC-isic'!AQ$1))/SUMPRODUCT(SIOM!$C$48:$AR$89*(SIOM!$B$48:$B$89='FoGPbEaIC-isic'!$A9))} -> 0
A10: refined petroleum and coke 19 | B10: {=SUMPRODUCT(SIOM!$C$48:$AR$89*(SIOM!$B$48:$B$89='FoGPbEaIC-isic'!$A10)*(SIOM!$C$47:$AR$47='FoGPbEaIC-isic'!B$1))/SUMPRODUCT(SIOM!$C$48:$AR$89*(SIOM!$B$48:$B$89='FoGPbEaIC-isic'!$A10))} -> 0.021513844 | C10: {=SUMPRODUCT(SIOM!$C$48:$AR$89*(SIOM!$B$48:$B$89='FoGPbEaIC-isic'!$A10)*(SIOM!$C$47:$AR$47='FoGPbEaIC-isic'!C$1))/SUMPRODUCT(SIOM!$C$48:$AR$89*(SIOM!$B$48:$B$89='FoGPbEaIC-isic'!$A10))} -> 0 | D10: {=SUMPRODUCT(SIOM!$C$48:$AR$89*(SIOM!$B$48:$B$89='FoGPbEaIC-isic'!$A10)*(SIOM!$C$47:$AR$47='FoGPbEaIC-isic'!D$1))/SUMPRODUCT(SIOM!$C$48:$AR$89*(SIOM!$B$48:$B$89='FoGPbEaIC-isic'!$A10))} -> 0 | E10: {=SUMPRODUCT(SIOM!$C$48:$AR$89*(SIOM!$B$48:$B$89='FoGPbEaIC-isic'!$A10)*(SIOM!$C$47:$AR$47='FoGPbEaIC-isic'!E$1))/SUMPRODUCT(SIOM!$C$48:$AR$89*(SIOM!$B$48:$B$89='FoGPbEaIC-isic'!$A10))} -> 0.0021400831 | F10: {=SUMPRODUCT(SIOM!$C$48:$AR$89*(SIOM!$B$48:$B$89='FoGPbEaIC-isic'!$A10)*(SIOM!$C$47:$AR$47='FoGPbEaIC-isic'!F$1))/SUMPRODUCT(SIOM!$C$48:$AR$89*(SIOM!$B$48:$B$89='FoGPbEaIC-isic'!$A10))} -> 7.1754671e-06 | G10: {=SUMPRODUCT(SIOM!$C$48:$AR$89*(SIOM!$B$48:$B$89='FoGPbEaIC-isic'!$A10)*(SIOM!$C$47:$AR$47='FoGPbEaIC-isic'!G$1))/SUMPRODUCT(SIOM!$C$48:$AR$89*(SIOM!$B$48:$B$89='FoGPbEaIC-isic'!$A10))} -> 0.0091630715 | H10: {=SUMPRODUCT(SIOM!$C$48:$AR$89*(SIOM!$B$48:$B$89='FoGPbEaIC-isic'!$A10)*(SIOM!$C$47:$AR$47='FoGPbEaIC-isic'!H$1))/SUMPRODUCT(SIOM!$C$48:$AR$89*(SIOM!$B$48:$B$89='FoGPbEaIC-isic'!$A10))} -> 0.013206447 | I10: {=SUMPRODUCT(SIOM!$C$48:$AR$89*(SIOM!$B$48:$B$89='FoGPbEaIC-isic'!$A10)*(SIOM!$C$47:$AR$47='FoGPbEaIC-isic'!I$1))/SUMPRODUCT(SIOM!$C$48:$AR$89*(SIOM!$B$48:$B$89='FoGPbEaIC-isic'!$A10))} -> 0.0027159143 | ... AQ10: {=SUMPRODUCT(SIOM!$C$48:$AR$89*(SIOM!$B$48:$B$89='FoGPbEaIC-isic'!$A10)*(SIOM!$C$47:$AR$47='FoGPbEaIC-isic'!AQ$1))/SUMPRODUCT(SIOM!$C$48:$AR$89*(SIOM!$B$48:$B$89='FoGPbEaIC-isic'!$A10))} -> 0
A11: chemicals 20 | B11: {=SUMPRODUCT(SIOM!$C$48:$AR$89*(SIOM!$B$48:$B$89='FoGPbEaIC-isic'!$A11)*(SIOM!$C$47:$AR$47='FoGPbEaIC-isic'!B$1))/SUMPRODUCT(SIOM!$C$48:$AR$89*(SIOM!$B$48:$B$89='FoGPbEaIC-isic'!$A11))} -> 0.025108937 | C11: {=SUMPRODUCT(SIOM!$C$48:$AR$89*(SIOM!$B$48:$B$89='FoGPbEaIC-isic'!$A11)*(SIOM!$C$47:$AR$47='FoGPbEaIC-isic'!C$1))/SUMPRODUCT(SIOM!$C$48:$AR$89*(SIOM!$B$48:$B$89='FoGPbEaIC-isic'!$A11))} -> 0.00032551829 | D11: {=SUMPRODUCT(SIOM!$C$48:$AR$89*(SIOM!$B$48:$B$89='FoGPbEaIC-isic'!$A11)*(SIOM!$C$47:$AR$47='FoGPbEaIC-isic'!D$1))/SUMPRODUCT(SIOM!$C$48:$AR$89*(SIOM!$B$48:$B$89='FoGPbEaIC-isic'!$A11))} -> 0.00025048689 | E11: {=SUMPRODUCT(SIOM!$C$48:$AR$89*(SIOM!$B$48:$B$89='FoGPbEaIC-isic'!$A11)*(SIOM!$C$47:$AR$47='FoGPbEaIC-isic'!E$1))/SUMPRODUCT(SIOM!$C$48:$AR$89*(SIOM!$B$48:$B$89='FoGPbEaIC-isic'!$A11))} -> 0.0011764562 | F11: {=SUMPRODUCT(SIOM!$C$48:$AR$89*(SIOM!$B$48:$B$89='FoGPbEaIC-isic'!$A11)*(SIOM!$C$47:$AR$47='FoGPbEaIC-isic'!F$1))/SUMPRODUCT(SIOM!$C$48:$AR$89*(SIOM!$B$48:$B$89='FoGPbEaIC-isic'!$A11))} -> 3.0557304e-06 | G11: {=SUMPRODUCT(SIOM!$C$48:$AR$89*(SIOM!$B$48:$B$89='FoGPbEaIC-isic'!$A11)*(SIOM!$C$47:$AR$47='FoGPbEaIC-isic'!G$1))/SUMPRODUCT(SIOM!$C$48:$AR$89*(SIOM!$B$48:$B$89='FoGPbEaIC-isic'!$A11))} -> 0.013653003 | H11: {=SUMPRODUCT(SIOM!$C$48:$AR$89*(SIOM!$B$48:$B$89='FoGPbEaIC-isic'!$A11)*(SIOM!$C$47:$AR$47='FoGPbEaIC-isic'!H$1))/SUMPRODUCT(SIOM!$C$48:$AR$89*(SIOM!$B$48:$B$89='FoGPbEaIC-isic'!$A11))} -> 0.053675433 | I11: {=SUMPRODUCT(SIOM!$C$48:$AR$89*(SIOM!$B$48:$B$89='FoGPbEaIC-isic'!$A11)*(SIOM!$C$47:$AR$47='FoGPbEaIC-isic'!I$1))/SUMPRODUCT(SIOM!$C$48:$AR$89*(SIOM!$B$48:$B$89='FoGPbEaIC-isic'!$A11))} -> 0.0059877037 | ... AQ11: {=SUMPRODUCT(SIOM!$C$48:$AR$89*(SIOM!$B$48:$B$89='FoGPbEaIC-isic'!$A11)*(SIOM!$C$47:$AR$47='FoGPbEaIC-isic'!AQ$1))/SUMPRODUCT(SIOM!$C$48:$AR$89*(SIOM!$B$48:$B$89='FoGPbEaIC-isic'!$A11))} -> 0
A12: rubber and plastic products 22 | B12: {=SUMPRODUCT(SIOM!$C$48:$AR$89*(SIOM!$B$48:$B$89='FoGPbEaIC-isic'!$A12)*(SIOM!$C$47:$AR$47='FoGPbEaIC-isic'!B$1))/SUMPRODUCT(SIOM!$C$48:$AR$89*(SIOM!$B$48:$B$89='FoGPbEaIC-isic'!$A12))} -> 0.0039785277 | C12: {=SUMPRODUCT(SIOM!$C$48:$AR$89*(SIOM!$B$48:$B$89='FoGPbEaIC-isic'!$A12)*(SIOM!$C$47:$AR$47='FoGPbEaIC-isic'!C$1))/SUMPRODUCT(SIOM!$C$48:$AR$89*(SIOM!$B$48:$B$89='FoGPbEaIC-isic'!$A12))} -> 0.00049813527 | D12: {=SUMPRODUCT(SIOM!$C$48:$AR$89*(SIOM!$B$48:$B$89='FoGPbEaIC-isic'!$A12)*(SIOM!$C$47:$AR$47='FoGPbEaIC-isic'!D$1))/SUMPRODUCT(SIOM!$C$48:$AR$89*(SIOM!$B$48:$B$89='FoGPbEaIC-isic'!$A12))} -> 0 | E12: {=SUMPRODUCT(SIOM!$C$48:$AR$89*(SIOM!$B$48:$B$89='FoGPbEaIC-isic'!$A12)*(SIOM!$C$47:$AR$47='FoGPbEaIC-isic'!E$1))/SUMPRODUCT(SIOM!$C$48:$AR$89*(SIOM!$B$48:$B$89='FoGPbEaIC-isic'!$A12))} -> 0.00070623783 | F12: {=SUMPRODUCT(SIOM!$C$48:$AR$89*(SIOM!$B$48:$B$89='FoGPbEaIC-isic'!$A12)*(SIOM!$C$47:$AR$47='FoGPbEaIC-isic'!F$1))/SUMPRODUCT(SIOM!$C$48:$AR$89*(SIOM!$B$48:$B$89='FoGPbEaIC-isic'!$A12))} -> 1.6386029e-06 | G12: {=SUMPRODUCT(SIOM!$C$48:$AR$89*(SIOM!$B$48:$B$89='FoGPbEaIC-isic'!$A12)*(SIOM!$C$47:$AR$47='FoGPbEaIC-isic'!G$1))/SUMPRODUCT(SIOM!$C$48:$AR$89*(SIOM!$B$48:$B$89='FoGPbEaIC-isic'!$A12))} -> 0.030582884 | H12: {=SUMPRODUCT(SIOM!$C$48:$AR$89*(SIOM!$B$48:$B$89='FoGPbEaIC-isic'!$A12)*(SIOM!$C$47:$AR$47='FoGPbEaIC-isic'!H$1))/SUMPRODUCT(SIOM!$C$48:$AR$89*(SIOM!$B$48:$B$89='FoGPbEaIC-isic'!$A12))} -> 0.019733694 | I12: {=SUMPRODUCT(SIOM!$C$48:$AR$89*(SIOM!$B$48:$B$89='FoGPbEaIC-isic'!$A12)*(SIOM!$C$47:$AR$47='FoGPbEaIC-isic'!I$1))/SUMPRODUCT(SIOM!$C$48:$AR$89*(SIOM!$B$48:$B$89='FoGPbEaIC-isic'!$A12))} -> 0.003193637 | ... AQ12: {=SUMPRODUCT(SIOM!$C$48:$AR$89*(SIOM!$B$48:$B$89='FoGPbEaIC-isic'!$A12)*(SIOM!$C$47:$AR$47='FoGPbEaIC-isic'!AQ$1))/SUMPRODUCT(SIOM!$C$48:$AR$89*(SIOM!$B$48:$B$89='FoGPbEaIC-isic'!$A12))} -> 0
A13: glass and glass products 231 | B13: {=SUMPRODUCT(SIOM!$C$48:$AR$89*(SIOM!$B$48:$B$89='FoGPbEaIC-isic'!$A13)*(SIOM!$C$47:$AR$47='FoGPbEaIC-isic'!B$1))/SUMPRODUCT(SIOM!$C$48:$AR$89*(SIOM!$B$48:$B$89='FoGPbEaIC-isic'!$A13))} -> 0.0013595766 | C13: {=SUMPRODUCT(SIOM!$C$48:$AR$89*(SIOM!$B$48:$B$89='FoGPbEaIC-isic'!$A13)*(SIOM!$C$47:$AR$47='FoGPbEaIC-isic'!C$1))/SUMPRODUCT(SIOM!$C$48:$AR$89*(SIOM!$B$48:$B$89='FoGPbEaIC-isic'!$A13))} -> 0.00011724496 | D13: {=SUMPRODUCT(SIOM!$C$48:$AR$89*(SIOM!$B$48:$B$89='FoGPbEaIC-isic'!$A13)*(SIOM!$C$47:$AR$47='FoGPbEaIC-isic'!D$1))/SUMPRODUCT(SIOM!$C$48:$AR$89*(SIOM!$B$48:$B$89='FoGPbEaIC-isic'!$A13))} -> 1.1806607e-05 | E13: {=SUMPRODUCT(SIOM!$C$48:$AR$89*(SIOM!$B$48:$B$89='FoGPbEaIC-isic'!$A13)*(SIOM!$C$47:$AR$47='FoGPbEaIC-isic'!E$1))/SUMPRODUCT(SIOM!$C$48:$AR$89*(SIOM!$B$48:$B$89='FoGPbEaIC-isic'!$A13))} -> 0.0018092655 | F13: {=SUMPRODUCT(SIOM!$C$48:$AR$89*(SIOM!$B$48:$B$89='FoGPbEaIC-isic'!$A13)*(SIOM!$C$47:$AR$47='FoGPbEaIC-isic'!F$1))/SUMPRODUCT(SIOM!$C$48:$AR$89*(SIOM!$B$48:$B$89='FoGPbEaIC-isic'!$A13))} -> 0 | G13: {=SUMPRODUCT(SIOM!$C$48:$AR$89*(SIOM!$B$48:$B$89='FoGPbEaIC-isic'!$A13)*(SIOM!$C$47:$AR$47='FoGPbEaIC-isic'!G$1))/SUMPRODUCT(SIOM!$C$48:$AR$89*(SIOM!$B$48:$B$89='FoGPbEaIC-isic'!$A13))} -> 0 | H13: {=SUMPRODUCT(SIOM!$C$48:$AR$89*(SIOM!$B$48:$B$89='FoGPbEaIC-isic'!$A13)*(SIOM!$C$47:$AR$47='FoGPbEaIC-isic'!H$1))/SUMPRODUCT(SIOM!$C$48:$AR$89*(SIOM!$B$48:$B$89='FoGPbEaIC-isic'!$A13))} -> 0.0059373258 | I13: {=SUMPRODUCT(SIOM!$C$48:$AR$89*(SIOM!$B$48:$B$89='FoGPbEaIC-isic'!$A13)*(SIOM!$C$47:$AR$47='FoGPbEaIC-isic'!I$1))/SUMPRODUCT(SIOM!$C$48:$AR$89*(SIOM!$B$48:$B$89='FoGPbEaIC-isic'!$A13))} -> 0 | ... AQ13: {=SUMPRODUCT(SIOM!$C$48:$AR$89*(SIOM!$B$48:$B$89='FoGPbEaIC-isic'!$A13)*(SIOM!$C$47:$AR$47='FoGPbEaIC-isic'!AQ$1))/SUMPRODUCT(SIOM!$C$48:$AR$89*(SIOM!$B$48:$B$89='FoGPbEaIC-isic'!$A13))} -> 0
... A26: construction 41T43 | B26: {=SUMPRODUCT(SIOM!$C$48:$AR$89*(SIOM!$B$48:$B$89='FoGPbEaIC-isic'!$A26)*(SIOM!$C$47:$AR$47='FoGPbEaIC-isic'!B$1))/SUMPRODUCT(SIOM!$C$48:$AR$89*(SIOM!$B$48:$B$89='FoGPbEaIC-isic'!$A26))} -> 0.0047060077 | C26: {=SUMPRODUCT(SIOM!$C$48:$AR$89*(SIOM!$B$48:$B$89='FoGPbEaIC-isic'!$A26)*(SIOM!$C$47:$AR$47='FoGPbEaIC-isic'!C$1))/SUMPRODUCT(SIOM!$C$48:$AR$89*(SIOM!$B$48:$B$89='FoGPbEaIC-isic'!$A26))} -> 0 | D26: {=SUMPRODUCT(SIOM!$C$48:$AR$89*(SIOM!$B$48:$B$89='FoGPbEaIC-isic'!$A26)*(SIOM!$C$47:$AR$47='FoGPbEaIC-isic'!D$1))/SUMPRODUCT(SIOM!$C$48:$AR$89*(SIOM!$B$48:$B$89='FoGPbEaIC-isic'!$A26))} -> 0 | E26: {=SUMPRODUCT(SIOM!$C$48:$AR$89*(SIOM!$B$48:$B$89='FoGPbEaIC-isic'!$A26)*(SIOM!$C$47:$AR$47='FoGPbEaIC-isic'!E$1))/SUMPRODUCT(SIOM!$C$48:$AR$89*(SIOM!$B$48:$B$89='FoGPbEaIC-isic'!$A26))} -> 0.0010655112 | F26: {=SUMPRODUCT(SIOM!$C$48:$AR$89*(SIOM!$B$48:$B$89='FoGPbEaIC-isic'!$A26)*(SIOM!$C$47:$AR$47='FoGPbEaIC-isic'!F$1))/SUMPRODUCT(SIOM!$C$48:$AR$89*(SIOM!$B$48:$B$89='FoGPbEaIC-isic'!$A26))} -> 0 | G26: {=SUMPRODUCT(SIOM!$C$48:$AR$89*(SIOM!$B$48:$B$89='FoGPbEaIC-isic'!$A26)*(SIOM!$C$47:$AR$47='FoGPbEaIC-isic'!G$1))/SUMPRODUCT(SIOM!$C$48:$AR$89*(SIOM!$B$48:$B$89='FoGPbEaIC-isic'!$A26))} -> 0.0050079025 | H26: {=SUMPRODUCT(SIOM!$C$48:$AR$89*(SIOM!$B$48:$B$89='FoGPbEaIC-isic'!$A26)*(SIOM!$C$47:$AR$47='FoGPbEaIC-isic'!H$1))/SUMPRODUCT(SIOM!$C$48:$AR$89*(SIOM!$B$48:$B$89='FoGPbEaIC-isic'!$A26))} -> 0.0037825647 | I26: {=SUMPRODUCT(SIOM!$C$48:$AR$89*(SIOM!$B$48:$B$89='FoGPbEaIC-isic'!$A26)*(SIOM!$C$47:$AR$47='FoGPbEaIC-isic'!I$1))/SUMPRODUCT(SIOM!$C$48:$AR$89*(SIOM!$B$48:$B$89='FoGPbEaIC-isic'!$A26))} -> 0.0011720623 | ... AQ26: {=SUMPRODUCT(SIOM!$C$48:$AR$89*(SIOM!$B$48:$B$89='FoGPbEaIC-isic'!$A26)*(SIOM!$C$47:$AR$47='FoGPbEaIC-isic'!AQ$1))/SUMPRODUCT(SIOM!$C$48:$AR$89*(SIOM!$B$48:$B$89='FoGPbEaIC-isic'!$A26))} -> 0

Sheet GaHEbIC-government
A1: Unit: USD | B1: ISIC 01T03 | C1: ISIC 05 | D1: ISIC 06 | E1: ISIC 07T08 | F1: ISIC 09 | G1: ISIC 10T12 | H1: ISIC 13T15 | I1: ISIC 16 | J1: ISIC 17T18 | K1: ISIC 19 | L1: ISIC 20 | M1: ISIC 21 | N1: ISIC 22 | O1: ISIC 231 | P1: ISIC 239 | Q1: ISIC 241 | R1: ISIC 242 | S1: ISIC 25 | T1: ISIC 26 | U1: ISIC 27 | V1: ISIC 28 | W1: ISIC 29 | X1: ISIC 30 | Y1: ISIC 31T33 | Z1: ISIC 351 | AA1: ISIC 352T353 | AB1: ISIC 36T39 | AC1: ISIC 41T43 | AD1: ISIC 45T47 | AE1: ISIC 49T53 | AF1: ISIC 55T56 | AG1: ISIC 58T60 | AH1: ISIC 61 | AI1: ISIC 62T63 | AJ1: ISIC 64T66 | AK1: ISIC 68 | AL1: ISIC 69T82 | AM1: ISIC 84 | AN1: ISIC 85 | AO1: ISIC 86T88 | AP1: ISIC 90T96 | AQ1: ISIC 97T98
A2: Government Expenditures | B2: 7.3784475e+08 | C2: 290412.29 | D2: 164587.71 | E2: 273000 | F2: 91000 | G2: 710983000 | H2: 2275000 | I2: 455000 | J2: 910000 | K2: 3640000 | L2: 19292000 | M2: 1071252000 | N2: 2093000 | O2: 355482.05 | P2: 736517.95 | Q2: 1572764.9 | R2: 429235.06 | S2: 3185000 | T2: 43134000 | U2: 4914000 | V2: 9009000 | W2: 17381000 | X2: 9100000 | Y2: 8645000 | Z2: 4793091.9 | AA2: 1576908.1 | AB2: 522886000 | AC2: 1729000 | AD2: 889343000 | AE2: 4.8900014e+09 | AF2: 5978609000 | AG2: 20930000 | AH2: 1638000 | AI2: 19656000 | AJ2: 3458000 | AK2: 546000 | AL2: 6.9654017e+09 | AM2: 120569176000 | AN2: 48108879000 | AO2: 68270020000 | AP2: 6.6290755e+09 | AQ2: 0

Sheet GaHEbIC-household
A1: Unit: USD | B1: ISIC 01T03 | C1: ISIC 05 | D1: ISIC 06 | E1: ISIC 07T08 | F1: ISIC 09 | G1: ISIC 10T12 | H1: ISIC 13T15 | I1: ISIC 16 | J1: ISIC 17T18 | K1: ISIC 19 | L1: ISIC 20 | M1: ISIC 21 | N1: ISIC 22 | O1: ISIC 231 | P1: ISIC 239 | Q1: ISIC 241 | R1: ISIC 242 | S1: ISIC 25 | T1: ISIC 26 | U1: ISIC 27 | V1: ISIC 28 | W1: ISIC 29 | X1: ISIC 30 | Y1: ISIC 31T33 | Z1: ISIC 351 | AA1: ISIC 352T353 | AB1: ISIC 36T39 | AC1: ISIC 41T43 | AD1: ISIC 45T47 | AE1: ISIC 49T53 | AF1: ISIC 55T56 | AG1: ISIC 58T60 | AH1: ISIC 61 | AI1: ISIC 62T63 | AJ1: ISIC 64T66 | AK1: ISIC 68 | AL1: ISIC 69T82 | AM1: ISIC 84 | AN1: ISIC 85 | AO1: ISIC 86T88 | AP1: ISIC 90T96 | AQ1: ISIC 97T98
A2: Household Expenditures | B2: 1.0940096e+10 | C2: 60115343 | D2: 34069657 | E2: 22659000 | F2: 1001000 | G2: 42904953000 | H2: 28177695000 | I2: 1.18482e+08 | J2: 1011192000 | K2: 11359712000 | L2: 8791874000 | M2: 1195012000 | N2: 780143000 | O2: 58091692 | P2: 1.2035931e+08 | Q2: 2.8095301e+08 | R2: 76676991 | S2: 1396213000 | T2: 18556902000 | U2: 6543992000 | V2: 2663388000 | W2: 22957662000 | X2: 574119000 | Y2: 6096909000 | Z2: 4793091.9 | AA2: 1576908.1 | AB2: 3201107000 | AC2: 425061000 | AD2: 55705832000 | AE2: 3.060036e+10 | AF2: 53314534000 | AG2: 9336145000 | AH2: 10364627000 | AI2: 6534983000 | AJ2: 55662243000 | AK2: 1.2205129e+11 | AL2: 1.3638746e+10 | AM2: 2310854000 | AN2: 49965552000 | AO2: 43943809000 | AP2: 3.5284517e+10 | AQ2: 1831193000

Sheet KOR WIOD IO-tables
A1: Source: World Input-Output Database
E2: A01 | F2: A02 | G2: A03 | H2: B | I2: C10-C12 | J2: C13-C15 | K2: C16 | L2: C17 | M2: C18 | N2: C19 | O2: C20 | P2: C21 | Q2: C22 | R2: C23 | S2: C24 | T2: C25 | U2: C26 | V2: C27 | W2: C28 | X2: C29 | Y2: C30 | Z2: C31_C32 | AA2: C33 | AB2: D35 | AC2: E36 | AD2: E37-E39 | AE2: F | AF2: G45 | AG2: G46 | AH2: G47 | AI2: H49 | AJ2: H50 | AK2: H51 | AL2: H52 | AM2: H53 | AN2: I | AO2: J58 | AP2: J59_J60 | AQ2: J61 | AR2: J62_J63 | AS2: K64 | AT2: K65 | AU2: K66 | AV2: L68 | AW2: M69_M70 | AX2: M71 | AY2: M72 | AZ2: M73 | BA2: M74_M75 | BB2: N | BC2: O84 | BD2: P85 | BE2: Q | BF2: R_S | BG2: T | BH2: U | BI2: CONS_h | BJ2: CONS_np | BK2: CONS_g | BL2: GFCF | BM2: INVEN | BN2: EXP | BO2: GO
