Workbook
Name CAP_CT: #REF!
Name CAP_CT: #REF!
Name CAP_GFCF: #REF!
Name CAP_GFCF: #REF!
Name CAP_IT: #REF!
Name CAP_IT: #REF!
Name CAP_OCon: #REF!
Name CAP_OCon: #REF!
Name CAP_OMach: #REF!
Name CAP_OMach: #REF!
Name CAP_Other: #REF!
Name CAP_Other: #REF!
Name CAP_QI: #REF!
Name CAP_QI: #REF!
Name CAP_RStruc: #REF!
Name CAP_RStruc: #REF!
Name CAP_Soft: #REF!
Name CAP_Soft: #REF!
Name CAP_TraEq: #REF!
Name CAP_TraEq: #REF!
Name CAPIT: #REF!
Name CAPIT: #REF!
Name CAPIT_QI: #REF!
Name CAPIT_QI: #REF!
Name capit_qph: #REF!
Name capit_qph: #REF!
Name CAPNIT: #REF!
Name CAPNIT: #REF!
Name CAPNIT_QI: #REF!
Name CAPNIT_QI: #REF!
Name capnit_qph: #REF!
Name capnit_qph: #REF!
Name FLAPPIE: #REF!
Name FLAPPIE: #REF!
Name VAConL: #REF!
Name VAConL: #REF!

Sheet About
A1: BECbIC BAU Employee Compensation by ISIC Code
A3: Source: | B3: Most Industries
B4: OECD
B5: 2018
B6: Input-Output Tables 2018 Edition (ISIC Rev. 4)
B7: https://stats.oecd.org/Index.aspx?DataSetCode=IOTSI4_2018
B8: Variable: VAL
B10: OECD
B11: 2025
B12: STAN Database for Structural Analysis, 2025 edition
B13: STAN Database for Structural Analysis_2025 edition
B14: Last updated: January 22, 2025 at 11:47:47 PM
B17: ISIC Splits
B18: Exiobase
B19: 2019
B20: Exiobase 3rx, 2016
B21: https://zenodo.org/record/2654460#.YEFjHmhKg2w
B22: Total compensation
A26: Notes
A27: In the OECD dataset, employee compensation includes not just salary and bonuses
A28: but also employer-paid benefits and employer-paid retirement plan contributions.
A30: We divide up a number of ISIC splits by applying EXIOBASE data on employee compensation to OECD data for the combined category
A31: We do the same for chemicals and pharmaceuticals (ISIC 20T21), splitting them into separate chemicals (ISIC 20) and pharmaceuticals
A32: (ISIC 21) industries using OECD data.
A34: We convert 2015 USD to 2012 USD with the following conversion factor:
A35: 0.96868157 | B35: 2012 USD per 2015 USD
A36: 0.88711067 | B36: 2012 USD per 2020 USD | C36: for OECD Chem Pharma Split

Sheet OECD VAL
A1: =DotStatQuery(B1) -> #NAME? | B1: Sorry, the query is too large to fit into the Excel cell. You will not be able to update your table with the .Stat Populator.
A2: Dataset: Input-Output Tables 2018 edition
A3: Variable | C3: VAL: Value added
A4: Country | C4: KOR: Korea
A5: Time | C5: 2015
A6: Unit | C6: US Dollar, Millions
A7: To: (sector in column) | C7: D01T03: Agriculture, forestry and fishing | D7: D05T06: Mining and extraction of energy producing products | E7: D07T08: Mining and quarrying of non-energy producing products | F7: D09: Mining support service activities | G7: D10T12: Food products, beverages and tobacco | H7: D13T15: Textiles, wearing apparel, leather and related products | I7: D16: Wood and products of wood and cork | J7: D17T18: Paper products and printing | K7: D19: Coke and refined petroleum products | L7: D20T21: Chemicals and pharmaceutical products | M7: D22: Rubber and plastic products | N7: D23: Other non-metallic mineral products | O7: D24: Basic metals | P7: D25: Fabricated metal products | Q7: D26: Computer, electronic and optical products | R7: D27: Electrical equipment | S7: D28: Machinery and equipment, nec | T7: D29: Motor vehicles, trailers and semi-trailers | U7: D30: Other transport equipment | V7: D31T33: Other manufacturing; repair and installation of machinery and equipment | W7: D35T39: Electricity, gas, water supply, sewerage, waste and remediation services | X7: D41T43: Construction | Y7: D45T47: Wholesale and retail trade; repair of motor vehicles | Z7: D49T53: Transportation and storage | AA7: D55T56: Accomodation and food services | AB7: D58T60: Publishing, audiovisual and broadcasting activities | AC7: D61: Telecommunications | AD7: D62T63: IT and other information services | AE7: D64T66: Financial and insurance activities | AF7: D68: Real estate activities | AG7: D69T82: Other business sector services | AH7: D84: Public admin. and defence; compulsory social security | AI7: D85: Education | AJ7: D86T88: Human health and social work | AK7: D90T96: Arts, entertainment, recreation and other service activities | AL7: D97T98: Private households with employed persons
A8: From: (sector in row)
A9: LABR: Compensation of employees | C9: 3941.796 | D9: 358.164 | E9: 487.612 | F9: 20.216 | G9: 8738.052 | H9: 9088.736 | I9: 1111.481 | J9: 4109.351 | K9: 1197.279 | L9: 10943.87 | M9: 11094.304 | N9: 3714.243 | O9: 9765.192 | P9: 15768.858 | Q9: 25452.728 | R9: 10930.598 | S9: 18842.476 | T9: 21089.247 | U9: 10541.995 | V9: 3535.126 | W9: 10755.867 | X9: 52109.947 | Y9: 40831.531 | Z9: 27553.891 | AA9: 18542.384 | AB9: 4676.938 | AC9: 3866.506 | AD9: 14280.075 | AE9: 30508.38 | AF9: 8656.746 | AG9: 64938.642 | AH9: 56918.25 | AI9: 56466.363 | AJ9: 41175.734 | AK9: 15089.665 | AL9: 1812.9
A10: OTXS: Other taxes less subsidies on production | C10: 1193.557 | D10: 7.318 | E10: 16.634 | F10: 2.51 | G10: 181.032 | H10: 123.002 | I10: 13.655 | J10: 50.732 | K10: 179.076 | L10: 310.903 | M10: 130.809 | N10: 67.193 | O10: 224.875 | P10: 164.069 | Q10: 508.055 | R10: 145.333 | S10: 205.552 | T10: 279.822 | U10: 142.725 | V10: 27.703 | W10: 317.513 | X10: 1123.141 | Y10: 1348.437 | Z10: 653.057 | AA10: 742.615 | AB10: 105.134 | AC10: 172.562 | AD10: 218.411 | AE10: 320.111 | AF10: 4310.082 | AG10: 535.008 | AH10: 2.949 | AI10: 125.807 | AJ10: 189.025 | AK10: 1294.219 | AL10: 0
A11: GOPS: Gross operating surplus and mixed income | C11: 23693.247 | D11: 373.818 | E11: 1090.153 | F11: 19.974 | G11: 8593.117 | H11: 8578.961 | I11: 715.764 | J11: 4223.018 | K11: 6675.345 | L11: 23007.227 | M11: 7876.888 | N11: 7009.064 | O11: 16491.233 | P11: 12836.473 | Q11: 55454.117 | R11: 11630.269 | S11: 14470.071 | T11: 19966.831 | U11: 5894.18 | V11: 2399.571 | W11: 28695.92 | X11: 12643.012 | Y11: 62280.332 | Z11: 21432.652 | AA11: 14476.702 | AB11: 4080.128 | AC11: 11080.132 | AD11: 9482.314 | AE11: 38740.509 | AF11: 84668.271 | AG11: 32748.65 | AH11: 33994.801 | AI11: 10800.129 | AJ11: 13424.741 | AK11: 14679.816 | AL11: 0
A12: Data extracted on 20 May 2021 15:47 UTC (GMT) from OECD.Stat
A19: [참고] 2018자료 원본 데이터
A20: Input-Output Tables (IOTs) 2018 ed.
A21: Variable: Value added
A22: Country: Korea
A23: Time: 2015
A25: To: (sector in column) | B25: To: (sector in column) | C25: Agriculture, forestry and fishing | D25: Mining and extraction of energy producing products | E25: Mining and quarrying of non-energy producing products | F25: Mining support service activities | G25: Food products, beverages and tobacco | H25: Textiles, wearing apparel, leather and related products | I25: Wood and products of wood and cork | J25: Paper products and printing | K25: Coke and refined petroleum products | L25: Chemicals and pharmaceutical products | M25: Rubber and plastic products | N25: Other non-metallic mineral products | O25: Basic metals | P25: Fabricated metal products | Q25: Computer, electronic and optical products | R25: Electrical equipment | S25: Machinery and equipment, nec | T25: Motor vehicles, trailers and semi-trailers | U25: Other transport equipment | V25: Other manufacturing; repair and installation of machinery and equipment | W25: Electricity, gas, water supply, sewerage, waste and remediation services | X25: Construction | Y25: Wholesale and retail trade; repair of motor vehicles | Z25: Transportation and storage | AA25: Accomodation and food services | AB25: Publishing, audiovisual and broadcasting activities | AC25: Telecommunications | AD25: IT and other information services | AE25: Financial and insurance activities | AF25: Real estate activities | AG25: Other business sector services | AH25: Public admin. and defence; compulsory social security | AI25: Education | AJ25: Human health and social work | AK25: Arts, entertainment, recreation and other service activities | AL25: Private households with employed persons
A26: From: (sector in row)
A27: Compensation of employees | C27: 3941.796 | D27: 358.164 | E27: 487.612 | F27: 20.216 | G27: 8738.052 | H27: 9088.736 | I27: 1111.481 | J27: 4109.351 | K27: 1197.279 | L27: 10943.87 | M27: 11094.304 | N27: 3714.243 | O27: 9765.192 | P27: 15768.858 | Q27: 25452.728 | R27: 10930.598 | S27: 18842.476 | T27: 21089.247 | U27: 10541.995 | V27: 3535.126 | W27: 10755.867 | X27: 52109.947 | Y27: 40831.531 | Z27: 27553.891 | AA27: 18542.384 | AB27: 4676.938 | AC27: 3866.506 | AD27: 14280.075 | AE27: 30508.38 | AF27: 8656.746 | AG27: 64938.642 | AH27: 56918.25 | AI27: 56466.363 | AJ27: 41175.734 | AK27: 15089.665 | AL27: 1812.9
A28: Other taxes less subsidies on production | C28: 1193.557 | D28: 7.318 | E28: 16.634 | F28: 2.51 | G28: 181.032 | H28: 123.002 | I28: 13.655 | J28: 50.732 | K28: 179.076 | L28: 310.903 | M28: 130.809 | N28: 67.193 | O28: 224.875 | P28: 164.069 | Q28: 508.055 | R28: 145.333 | S28: 205.552 | T28: 279.822 | U28: 142.725 | V28: 27.703 | W28: 317.513 | X28: 1123.141 | Y28: 1348.437 | Z28: 653.057 | AA28: 742.615 | AB28: 105.134 | AC28: 172.562 | AD28: 218.411 | AE28: 320.111 | AF28: 4310.082 | AG28: 535.008 | AH28: 2.949 | AI28: 125.807 | AJ28: 189.025 | AK28: 1294.219 | AL28: 0
A29: Gross operating surplus and mixed income | C29: 23693.247 | D29: 373.818 | E29: 1090.153 | F29: 19.974 | G29: 8593.117 | H29: 8578.961 | I29: 715.764 | J29: 4223.018 | K29: 6675.345 | L29: 23007.227 | M29: 7876.888 | N29: 7009.064 | O29: 16491.233 | P29: 12836.473 | Q29: 55454.117 | R29: 11630.269 | S29: 14470.071 | T29: 19966.831 | U29: 5894.18 | V29: 2399.571 | W29: 28695.92 | X29: 12643.012 | Y29: 62280.332 | Z29: 21432.652 | AA29: 14476.702 | AB29: 4080.128 | AC29: 11080.132 | AD29: 9482.314 | AE29: 38740.509 | AF29: 84668.271 | AG29: 32748.65 | AH29: 33994.801 | AI29: 10800.129 | AJ29: 13424.741 | AK29: 14679.816 | AL29: 0
A31: © Terms & conditions
A33: Applied filter(조회 조건) : Variable: value added/ Country: Korea/ To:(sector in column): 36 items / Time: start 2015, end: 2015

Sheet EXIOBASE EMP Splits
B2: Source: EXIOBASE
B3: Unit: M Euro
B5: ISIC | C5: ISIC 05 | D5: ISIC 06 | E5: ISIC 231 | F5: ISIC 239 | G5: ISIC 241 | H5: ISIC 242 | I5: ISIC 351 | J5: ISIC 352T353 | K5: ISIC 36T39
B6: EMP Compensation | C6: 270.65143 | D6: 126.89114 | E6: 1399.0964 | F6: 2804.215 | G6: 8404.0068 | H6: 1897.0136 | I6: 5285.7095 | J6: 703.06305 | K6: 5163.3145
B7: Ratio | C7: =C6/SUM(C6:D6) -> 0.68081119 | D7: =D6/SUM(C6:D6) -> 0.31918881 | E7: =E6/SUM(E6:F6) -> 0.33285575 | F7: =F6/SUM(E6:F6) -> 0.66714425 | G7: =G6/SUM(G6:H6) -> 0.81584217 | H7: =H6/SUM(G6:H6) -> 0.18415783 | I7: =I6/SUM($I$6:$K$6) -> 0.47396595 | J7: =J6/SUM($I$6:$K$6) -> 0.063043182 | K7: =K6/SUM($I$6:$K$6) -> 0.46299087

Sheet OECD Chem Pharma Split
A1: =DotStatQuery(B1) -> #NAME? | B1: <?xml version="1.0" encoding="utf-16"?><WebTableParameter xmlns:xsd="http://www.w3.org/2001/XMLSchema" xmlns:xsi="http://www.w3.org/2001/XMLSchema-instance" xmlns="http://stats.oecd.org/OECDStatWS/2004/03/01/"><DataTable Code="STANI4_2020" HasMetadata="true"><Name LocaleIsoCode="en">STAN Industrial Analysis (2020 ed.)</Name><Name LocaleIsoCode="fr">STAN pour l'Analyse Structurelle (éd. 2020)</Name><Dimension Code="LOCATION" HasMetadata="false" CommonCode="LOCATION" Display="labels"><Name LocaleIsoCode="en">Country</Name><Name LocaleIsoCode="fr">Pays</Name><Member Code="AUS" HasMetadata="true" HasOnlyUnitMetadata="false" HasChild="0"><Name LocaleIsoCode="en">Australia</Name><Name LocaleIsoCode="fr">Australie</Name></Member><Member Code="AUT" HasMetadata="true" HasOnlyUnitMetadata="false" HasChild="0"><Name LocaleIsoCode="en">Austria</Name><Name LocaleIsoCode="fr">Autriche</Name></Member><Member Code="BEL" HasMetadata="true" HasOnlyUnitMetadata="false" HasChild="0"><Name LocaleIsoCode="en">Belgium</Name><Name LocaleIsoCode="fr">Belgique</Name></Member><Member Code="CHL" HasMetadata="true" HasOnlyUnitMetadata="false" HasChild="0"><Name LocaleIsoCode="en">Chile</Name><Name LocaleIsoCode="fr">Chili</Name></Member><Member Code="CZE" HasMetadata="true" HasOnlyUnitMetadata="false" HasChild="0"><Name LocaleIsoCode="en">Czech Republic</Name><Name LocaleIsoCode="fr">République tchèque</Name></Member><Member Code="DNK" HasMetadata="true" HasOnlyUnitMetadata="false" HasChild="0"><Name LocaleIsoCode="en">Denmark</Name><Name LocaleIsoCode="fr">Danemark</Name></Member><Member Code="EST" HasMetadata="true" HasOnlyUnitMetadata="false" HasChild="0"><Name LocaleIsoCode="en">Estonia</Name><Name LocaleIsoCode="fr">Estonie</Name></Member><Member Code="FIN" HasMetadata="true" HasOnlyUnitMetadata="false" HasChild="0"><Name LocaleIsoCode="en">Finland</Name><Name LocaleIsoCode="fr">Finlande</Name></Member><Member Code="FRA" HasMetadata="true" HasOnlyUnitMetadata="false" HasChild="0"><Name LocaleIsoCode="en">France</Name><Name LocaleIsoCode="fr">France</Name></Member><Member Code="DEU" HasMetadata="true" HasOnlyUnitMetadata="false" HasChild="0"><Name LocaleIsoCode="en">Germany</Name><Name LocaleIsoCode="fr">Allemagne</Name></Member><Member Code="HUN" HasMetadata="true" HasOnlyUnitMetadata="false" HasChild="0"><Name LocaleIsoCode="en">Hungary</Name><Name LocaleIsoCode="fr">Hongrie</Name></Member><Member Code="ITA" HasMetadata="true" HasOnlyUnitMetadata="false" HasChild="0"><Name LocaleIsoCode="en">Italy</Name><Name LocaleIsoCode="fr">Italie</Name></Member><Member Code="JPN" HasMetadata="true" HasOnlyUnitMetadata="false" HasChild="0"><Name LocaleIsoCode="en">Japan</Name><Name LocaleIsoCode="fr">Japon</Name></Member><Member Code="KOR" HasMetadata="true" HasOnlyUnitMetadata="false" HasChild="0"><Name LocaleIsoCode="en">Korea</Name><Name LocaleIsoCode="fr">Corée</Name></Member><Member Code="LVA" HasMetadata="true" HasOnlyUnitMetadata="false" HasChild="0"><Name LocaleIsoCode="en">Latvia</Name><Name LocaleIsoCode="fr">Lettonie</Name></Member><Member Code="LTU" HasMetadata="false" HasOnlyUnitMetadata="false" HasChild="0"><Name LocaleIsoCode="en">Lithuania</Name><Name LocaleIsoCode="fr">Lituanie</Name></Member><Member Code="MEX" HasMetadata="true" HasOnlyUnitMetadata="false" HasChild="0"><Name LocaleIsoCode="en">Mexico</Name><Name LocaleIsoCode="fr">Mexique</Name></Member><Member Code="NLD" HasMetadata="true" HasOnlyUnitMetadata="false" HasChild="0"><Name LocaleIsoCode="en">Netherlands</Name><Name LocaleIsoCode="fr">Pays-Bas</Name></Member><Member Code="NOR" HasMetadata="true" HasOnlyUnitMetadata="false" HasChild="0"><Name LocaleIsoCode="en">Norway</Name><Name LocaleIsoCode="fr">Norvège</Name></Member><Member Code="PRT" HasMetadata="true" HasOnlyUnitMetadata="false" HasChild="0"><Name LocaleIsoCode="en">Portugal</Name><Name LocaleIsoCode="fr">Portugal</Name></Member><Member Code="SVK" HasMetadata="true" HasOnlyUnitMetadata="false" HasChild="0"><Name LocaleIsoCode="en">Slovak Republic</Name><Name LocaleIsoCode="fr">République slovaque</Name></Member><Member Code="ESP" HasMetadata="true" HasOnlyUnitMetadata="false" HasChild="0"><Name LocaleIsoCode="en">Spain</Name><Name LocaleIsoCode="fr">Espagne</Name></Member><Member Code="CHE" HasMetadata="true" HasOnlyUnitMetadata="false" HasChild="0"><Name LocaleIsoCode="en">Switzerland</Name><Name LocaleIsoCode="fr">Suisse</Name></Member><Member Code="GBR" HasMetadata="true" HasOnlyUnitMetadata="false" HasChild="0"><Name LocaleIsoCode="en">United Kingdom</Name><Name LocaleIsoCode="fr">Royaume-Uni</Name></Member><Member Code="USA" HasMetadata="true" HasOnlyUnitMetadata="false" HasChild="0"><Name LocaleIsoCode="en">United States</Name><Name LocaleIsoCode="fr">États-Unis</Name></Member></Dimension><Dimension Code="VAR" HasMetadata="false" Display="codesandlabels"><Name LocaleIsoCode="en">Variable</Name><Name LocaleIsoCode="fr">Variable</Name><Member Code="PROD" HasMetadata="true" HasOnlyUnitMetadata="true" HasChild="0"><Name LocaleIsoCode="en">Production (gross output), current prices</Name><Name LocaleIsoCode="fr">Production (brute), prix courants</Name></Member><Member Code="VALU" HasMetadata="true" HasOnlyUnitMetadata="false" HasChild="0"><Name LocaleIsoCode="en">Value added, current prices</Name><Name LocaleIsoCode="fr">Valeur ajoutée, prix courants</Name></Member><Member Code="LABR" HasMetadata="true" HasOnlyUnitMetadata="false" HasChild="0"><Name LocaleIsoCode="en">Labour costs (compensation of employees)</Name><Name LocaleIsoCode="fr">Coût de la main-d'oeuvre (rémunération)</Name></Member><Member Code="GOPS" HasMetadata="true" HasOnlyUnitMetadata="true" HasChild="0"><Name LocaleIsoCode="en">Gross operating surplus and mixed income</Name><Name LocaleIsoCode="fr">Excédent brut d'exploitation et revenu mixte</Name></Member><Member Code="OTXS" HasMetadata="true" HasOnlyUnitMetadata="true" HasChild="0"><Name LocaleIsoCode="en">Other taxes less subsidies on production</Name><Name LocaleIsoCode="fr">Autres impôts moins subventions sur la production</Name></Member><Member Code="EMPN" HasMetadata="true" HasOnlyUnitMetadata="true" HasChild="0"><Name LocaleIsoCode="en">Number of persons engaged (total employment)</Name><Name LocaleIsoCode="fr">Actifs occupés - emploi total</Name></Member></Dimension><Dimension Code="IND" HasMetadata="false" Display="codesandlabels"><Name LocaleIsoCode="en">Industry</Name><Name LocaleIsoCode="fr">Activité</Name><Member Code="D20" HasMetadata="false" HasOnlyUnitMetadata="false" HasChild="0"><Name LocaleIsoCode="en"> Chemicals and chemical products [CE]</Name><Name LocaleIsoCode="fr">Produits chimiques [CE]</Name></Member><Member Code="D21" HasMetadata="false" HasOnlyUnitMetadata="false" HasChild="0"><Name LocaleIsoCode="en"> Basic pharmaceutical products and pharmaceutical preparations [CF]</Name><Name LocaleIsoCode="fr">Produits et préparations pharmaceutiques [CF]</Name></Member></Dimension><Dimension Code="TIME" HasMetadata="false" CommonCode="TIME" Display="labels"><Name LocaleIsoCode="en">Time</Name><Name LocaleIsoCode="fr">Temps</Name><Member Code="2015" HasMetadata="false"><Name LocaleIsoCode="en">2015</Name><Name LocaleIsoCode="fr">2015</Name></Member></Dimension><WBOSInformations><TimeDimension WebTreeWasUsed="false"><StartCodes Annual="2015" /><EndCodes Annual="2015" /></TimeDimension></WBOSInformations><Tabulation Axis="horizontal"><Dimension Code="VAR" /><Dimension Code="IND" /></Tabulation><Tabulation Axis="vertical"><Dimension Code="LOCATION" /></Tabulation><Tabulation Axis="page"><Dimension Code="TIME" /></Tabulation><Formatting><Labels LocaleIsoCode="en" /><Power>0</Power><Decimals>1</Decimals><SkipEmptyLines>true</SkipEmptyLines><SkipEmptyCols>false</SkipEmptyCols><SkipLineHierarchy>true</SkipLineHierarchy><SkipColHierarchy>false</SkipColHierarchy><Page>1</Page></Formatting></DataTable><Format><ShowEmptyAxes>true</ShowEmptyAxes><Page>1</Page><EnableSort>true</EnableSort><IncludeFlagColumn>false</IncludeFlagColumn><IncludeTimeSeriesId>false</IncludeTimeSeriesId><DoBarChart>false</DoBarChart><FreezePanes>true</FreezePanes><MaxBarChartLen>65</MaxBarChartLen></Format><Query><AbsoluteUri>http://stats.oecd.org//View.aspx?QueryId=&amp;QueryType=Public&amp;Lang=en</AbsoluteUri></Query></WebTableParameter>
A2: STAN Database for Structural Analysis,2025 edition
A3: Time | C3: 2020
A4: Variable | C4: LABR: Labour costs (compensation of employees)
A5: Industry | C5: D20: Chemicals and chemical products [CE] | D5: D21: Basic pharmaceutical products and pharmaceutical preparations [CF]
A6: Country
A7: Korea | C7: 14186746 | D7: 4380310.7

Sheet BECbIC
A1: Unit: $ | B1: ISIC 01T03 | C1: ISIC 05 | D1: ISIC 06 | E1: ISIC 07T08 | F1: ISIC 09 | G1: ISIC 10T12 | H1: ISIC 13T15 | I1: ISIC 16 | J1: ISIC 17T18 | K1: ISIC 19 | L1: ISIC 20 | M1: ISIC 21 | N1: ISIC 22 | O1: ISIC 231 | P1: ISIC 239 | Q1: ISIC 241 | R1: ISIC 242 | S1: ISIC 25 | T1: ISIC 26 | U1: ISIC 27 | V1: ISIC 28 | W1: ISIC 29 | X1: ISIC 30 | Y1: ISIC 31T33 | Z1: ISIC 351 | AA1: ISIC 352T353 | AB1: ISIC 36T39 | AC1: ISIC 41T43 | AD1: ISIC 45T47 | AE1: ISIC 49T53 | AF1: ISIC 55T56 | AG1: ISIC 58T60 | AH1: ISIC 61 | AI1: ISIC 62T63 | AJ1: ISIC 64T66 | AK1: ISIC 68 | AL1: ISIC 69T82 | AM1: ISIC 84 | AN1: ISIC 85 | AO1: ISIC 86T88 | AP1: ISIC 90T96 | AQ1: ISIC 97T98
A2: Employee Compensation | B2: ='OECD VAL'!C9*10^6*About!$A$35 -> 3.8183451e+09 | C2: ='OECD VAL'!D9*10^6*About!$A$35*'EXIOBASE EMP Splits'!C7 -> 2.3620531e+08 | D2: ='OECD VAL'!D9*10^6*About!$A$35*'EXIOBASE EMP Splits'!D7 -> 1.1074156e+08 | E2: ='OECD VAL'!E9*10^6*About!$A$35 -> 4.7234076e+08 | F2: ='OECD VAL'!F9*10^6*About!$A$35 -> 19582867 | G2: ='OECD VAL'!G9*10^6*About!$A$35 -> 8.4643899e+09 | H2: ='OECD VAL'!H9*10^6*About!$A$35 -> 8.8040911e+09 | I2: ='OECD VAL'!I9*10^6*About!$A$35 -> 1.0766712e+09 | J2: ='OECD VAL'!J9*10^6*About!$A$35 -> 3.9806526e+09 | K2: ='OECD VAL'!K9*10^6*About!$A$35 -> 1.1597821e+09 | L2: ='OECD VAL'!L9*10^6*About!$A$36*('OECD Chem Pharma Split'!C7/SUM('OECD Chem Pharma Split'!C7:D7)) -> 7.4180279e+09 | M2: ='OECD VAL'!L9*10^6*About!$A$36*('OECD Chem Pharma Split'!D7/SUM('OECD Chem Pharma Split'!C7:D7)) -> 2.290396e+09 | N2: ='OECD VAL'!M9*10^6*About!$A$35 -> 1.0746848e+10 | O2: ='OECD VAL'!N9*10^6*About!$A$35*'EXIOBASE EMP Splits'!E7 -> 1.197588e+09 | P2: ='OECD VAL'!N9*10^6*About!$A$35*'EXIOBASE EMP Splits'!F7 -> 2.4003308e+09 | Q2: ='OECD VAL'!O9*10^6*About!$A$35*'EXIOBASE EMP Splits'!G7 -> 7.717346e+09 | R2: ='OECD VAL'!O9*10^6*About!$A$35*'EXIOBASE EMP Splits'!H7 -> 1.7420155e+09 | S2: ='OECD VAL'!P9*10^6*About!$A$35 -> 1.5275002e+10 | T2: ='OECD VAL'!Q9*10^6*About!$A$35 -> 2.4655589e+10 | U2: ='OECD VAL'!R9*10^6*About!$A$35 -> 1.0588269e+10 | V2: ='OECD VAL'!S9*10^6*About!$A$35 -> 1.8252359e+10 | W2: ='OECD VAL'!T9*10^6*About!$A$35 -> 2.0428765e+10 | X2: ='OECD VAL'!U9*10^6*About!$A$35 -> 1.0211836e+10 | Y2: ='OECD VAL'!V9*10^6*About!$A$35 -> 3.4244114e+09 | Z2: ='OECD VAL'!W9*10^6*About!$A$35*'EXIOBASE EMP Splits'!I7 -> 4.938256e+09 | AA2: ='OECD VAL'!W9*10^6*About!$A$35*'EXIOBASE EMP Splits'!J7 -> 6.5684755e+08 | AB2: ='OECD VAL'!W9*10^6*About!$A$35*'EXIOBASE EMP Splits'!K7 -> 4.8239066e+09 | AC2: ='OECD VAL'!X9*10^6*About!$A$35 -> 5.0477945e+10 | AD2: ='OECD VAL'!Y9*10^6*About!$A$35 -> 3.9552752e+10 | AE2: ='OECD VAL'!Z9*10^6*About!$A$35 -> 2.6690946e+10 | AF2: ='OECD VAL'!AA9*10^6*About!$A$35 -> 1.7961666e+10 | AG2: ='OECD VAL'!AB9*10^6*About!$A$35 -> 4.5304637e+09 | AH2: ='OECD VAL'!AC9*10^6*About!$A$35 -> 3.7454131e+09 | AI2: ='OECD VAL'!AD9*10^6*About!$A$35 -> 1.3832845e+10 | AJ2: ='OECD VAL'!AE9*10^6*About!$A$35 -> 2.9552905e+10 | ... AQ2: ='OECD VAL'!AL9*10^6*About!$A$35 -> 1.7561228e+09
