Workbook
Name dollars_2018_to_2012: About!$A$122
Name dollars_2020_2012: About!#REF!
Name dollars_2020_2012: About!#REF!
Name dollars_2021_2012: About!$A$118
Name dollars_2022_2012: #REF!
Name lignite_multiplier: '[1]Hard Coal and Lig Multipliers'!$N$15
Name nonlignite_multiplier: '[1]Hard Coal and Lig Multipliers'!$N$16

Sheet About
A1: BS BAU Subsidy for Thermal Fuels per Energy Unit Produced
A2: BS BAU Subsidy per Unit Electricity Output
A3: BS BAU Subsidy per Unit Electricity Capacity Built
A4: BS Duration of Subsidies per Unit Electricity Output
A6: Source: | B6: Fine dust project evaluation
B7: NABO
B8: 2019
B9: Domestic emission reduction: industry
B10: https://www.nabo.go.kr/system/common/JSPservlet/download.jsp?fCode=33315609&fSHC=&fName=%EB%AF%B8%EC%84%B8%EB%A8%BC%EC%A7%80+%EB%8C%80%EC%9D%91+%EC%82%AC%EC%97%85+%EB%B6%84%EC%84%9D.pdf&fMime=application/pdf&fBid=19&flag=bluenet
B11: page 49, 61
B13: Generation share of coal
B14: Index Korea
B15: 2021
B16: Generation share by source
B17: https://www.index.go.kr/potal/main/EachDtlPageDetail.do?idx_cd=1339
B19: KOSIS
B20: 2020
B21: Generation capacity by company
B22: https://kosis.kr/statHtml/statHtml.do?orgId=388&tblId=TX_38803_A000A
B24: Cost of PV, hydro, wind and bioenergy in 2010-2019
B25: IRENA
B26: 2019
B27: Global weighted average total installed costs
B28: https://www.irena.org/Statistics/View-Data-by-Topic/Costs/Global-Trends
B30: Installation cost of PV and wind in 2025 for estimating CAGR
B31: IRENA
B32: 2019
B33: The Power to change: solar and wind cost reduction potential to 2025
B34: https://www.irena.org/-/media/Files/IRENA/Agency/Publication/2016/IRENA_Power_to_Change_2016.pdf
B35: Page 10
B37: Installation cost of renewables in 2030 and 2050 for estimating CAGR
B38: Price prediction of solar photovoltaic in 2030 and 2050
B39: IRENA
B40: 2019
B41: Future of solar photovoltaic
B42: https://irena.org/-/media/Files/IRENA/Agency/Publication/2019/Nov/IRENA_Future_of_Solar_PV_2019.pdf
B43: Page 27
B45: Price prediction of onshore and offshore wind in 2030 and 2050
B46: Future of wind
B47: https://www.irena.org/-/media/files/irena/agency/publication/2019/oct/irena_future_of_wind_2019.pdf
B48: Page 32, 48
B50: Projecting installation cost and LCOE of solar PV and onshore wind
B51: KEEI
B52: 2020
B53: Projecting CAPEX of solar PV, and projecting LCOE of solar PV and wind (2020 est.)
B54: https://www.keei.re.kr/board.es?mid=a10101020000&bid=0001&act=view&list_no=82053&cg_code=C01&act=view&list_no=82053
B55: Page 120, 121
B57: Projecting installation cost and LCOE of offshore wind
B58: KEEI
B59: 2019
B60: Offshore wind CAPEX breakdown in 2018, and LCOE trend between 2018 and 2030 in South Korea
B61: https://signal.sedaily.com/Common/FileDownload?fileName=%EC%84%B8%EA%B3%84_%EC%9E%AC%EC%83%9D%EC%97%90%EB%84%88%EC%A7%80_%EC%9E%90%EA%B5%AD%EC%82%B0_%EB%B6%80%ED%92%88%EC%82%AC%EC%9A%A9%EC%9A%94%EA%B1%B4_%EC%A0%95%EC%B1%85%EC%97%90_%EB%8C%80%ED%95%9C_%EB%8C%80%EC%9D%91%EB%B0%A9%EC%95%88_%EC%97%B0%EA%B5%AC.pdf&fullPath=/Service/Branch/Signal/Report/2020/04/17/%EC%84%B8%EA%B3%84_%EC%9E%AC%EC%83%9D%EC%97%90%EB%84%88%EC%A7%80_%EC%9E%90%EA%B5%AD%EC%82%B0_%EB%B6%80%ED%92%88%EC%82%AC%EC%9A%A9%EC%9A%94%EA%B1%B4_%EC%A0%95%EC%B1%85%EC%97%90_%EB%8C%80%ED%95%9C_%EB%8C%80%EC%9D%91%EB%B0%A9%EC%95%88_%EC%97%B0%EA%B5%AC.pdf
B62: Page 79, 80
B64: Tax credit for investment in new and renewable energy manufacturing facilities
B65: Integrated Investment Tax Credit (Article 24)
B66: https://glaw.scourt.go.kr/wsjo/lawod/sjo192.do?lawodNm=%EC%A1%B0%EC%84%B8%ED%8A%B9%EB%A1%80%EC%A0%9C%ED%95%9C%EB%B2%95&jomunNo=24&jomunGajiNo=
A69: Notes
A70: Korea's dependence on fuel imports is 94%, so fuel production is limited.
A71: https://kosis.kr/statHtml/statHtml.do?orgId=339&tblId=DT_339001_001&conn_path=I2
A72: Most of the domestically produced fuel is anthracite coal; however, no upstream Thermal Fuel Subsidy exists for its production.
A74: As data suitable for EPS model inputs on nuclear power plant decommissioning costs in Korea was not publicly available, the value was set to 0 KRW.
A75: Subsidies paid for automatic stack monitoring equipment were allocated to BSpUEO by dividing them across anthracite and bituminous coal generation capacity.
A77: BS-BSpUECB
A78: There are errors that may occur in the subsidy for power generation facilities (BS-BSpUECB)
A79: The tax credit for domestic renewable energy facilities can be explained in two ways.
A80: 1. Tax deducted by applying a specific ratio (ex, 1, 3, 7%) to the facility investment cost.
A81: 2. Profit and loss * Tax deducted by applying a specific ratio to the tax to which corporate tax has been applied
A82: The data in the data sheet was calculated based on 1. For this reason, the subsidy received by small power generators supported by the scheme 2 may be distorted.
... A89: In addition, there is a minimum tax, so even if you receive benefits, a power company cannot pay less than the minimum tax, but the minimum tax was not applied.
A92: 2012 평균 환율 | B92: 1126.88
A93: 1MW | B93: 1000 | C93: kW

Sheet 에너지원별 발전량
A1: 통계표명: | B1: 에너지원별 발전량 현황
A2: 단위: | B2: GWh, %
C3: 계 | D3: 원자력 | E3: 석탄 | F3: 가스 | G3: 신재생 | H3: 유류 | I3: 양수 | J3: 기타
A4: 2011 | B4: 발전량 | C4: 496893 | D4: 154723 | E4: 202856 | F4: 112646 | G4: 12190 | H4: 11245 | I4: 3233 | J4: -
B5: 비중 | C5: 100 | D5: 31.1 | E5: 40.8 | F5: 22.7 | G5: 2.5 | H5: 2.3 | I5: 0.7 | J5: -
A6: 2012 | B6: 발전량 | C6: 509574 | D6: 150327 | E6: 202191 | F6: 125285 | G6: 12587 | H6: 15501 | I6: 3683 | J6: -
B7: 비중 | C7: 100 | D7: 29.5 | E7: 39.7 | F7: 24.6 | G7: 2.5 | H7: 3 | I7: 0.7 | J7: -
A8: 2013 | B8: 발전량 | C8: 517148 | D8: 138784 | E8: 204196 | F8: 139783 | G8: 14449 | H8: 15832 | I8: 4105 | J8: -
B9: 비중 | C9: 100 | D9: 26.8 | E9: 39.5 | F9: 27 | G9: 2.8 | H9: 3.1 | I9: 0.8 | J9: -
A10: 2014 | B10: 발전량 | C10: 521971 | D10: 156407 | E10: 207214 | F10: 127472 | G10: 17447 | H10: 8364 | I10: 5068 | J10: -
B11: 비중 | C11: 100 | D11: 30 | E11: 39.7 | F11: 24.4 | G11: 3.3 | H11: 1.6 | I11: 1 | J11: -
A12: 2015 | B12: 발전량 | C12: 528091 | D12: 164762 | E12: 211393 | F12: 118695 | G12: 19464 | H12: 10127 | I12: 3650 | J12: -
B13: 비중 | C13: 100 | D13: 31.2 | E13: 40 | F13: 22.5 | G13: 3.7 | H13: 1.9 | I13: 0.7 | J13: -
A14: 2016 | B14: 발전량 | C14: 540441 | D14: 161995 | E14: 213803 | F14: 121018 | G14: 25836 | H14: 14001 | I14: 3787 | J14: -
B15: 비중 | C15: 100 | D15: 30 | E15: 39.6 | F15: 22.4 | G15: 4.8 | H15: 2.6 | I15: 0.7 | J15: -
A16: 2017 | B16: 발전량 | C16: 553530 | D16: 148427 | E16: 238799 | F16: 126039 | G16: 30817 | H16: 5263 | I16: 4186 | J16: -
B17: 비중 | C17: 100 | D17: 26.8 | E17: 43.1 | F17: 22.8 | G17: 5.6 | H17: 1 | I17: 0.8 | J17: -
A18: 2018 | B18: 발전량 | C18: 570647 | D18: 133505 | E18: 238967 | F18: 152924 | G18: 35598 | H18: 5740 | I18: 3911 | J18: 0
B19: 비중 | C19: 100 | D19: 23.4 | E19: 41.9 | F19: 26.8 | G19: 6.2 | H19: 1 | I19: 0.7 | J19: 0
A20: 2019 | B20: 발전량 | C20: 563040 | D20: 145910 | E20: 227384 | F20: 144355 | G20: 36392 | H20: 3292 | I20: 3458 | J20: 2249
B21: 비중 | C21: 100 | D21: 25.9 | E21: 40.4 | F21: 25.6 | G21: 6.5 | H21: 0.6 | I21: 0.6 | J21: 0.4
A22: 2020 | B22: 발전량 | C22: 552162 | D22: 160184 | E22: 196333 | F22: 145911 | G22: 36527 | H22: 2255 | I22: 3271 | J22: 7681
B23: 비중 | C23: 100 | D23: 29 | E23: 35.6 | F23: 26.4 | G23: 6.6 | H23: 0.4 | I23: 0.6 | J23: 1.4

Sheet 발전사별 설비용량
A1: 용도및회사별(1) | B1: 용도및회사별(2) | C1: 2020
C2: 합계 | D2: 원자력 | E2: 기력 | J2: 복합화력 | M2: 내연력 | P2: 집단에너지 | U2: 양수 | V2: 신재생 | AA2: 기타
C3: 소계 | D3: 소계 | E3: 소계 | F3: 유연탄 | G3: 무연탄 | H3: 중유 | I3: LNG | J3: 소계 | K3: 경유 | L3: LNG | M3: 소계 | N3: 중유 | O3: 경유 | P3: 소계 | Q3: 유연탄 | R3: 유류 | S3: LNG | T3: 기타 | U3: 소계 | V3: 소계 | W3: 수력 | X3: 태양광 | Y3: 풍력 | Z3: 기타 | AA3: 소계
A4: 합계 | B4: 소계 | C4: 130978873 | D4: 23250000 | E4: 37950658 | F4: 34950658 | G4: 400000 | H4: 1200000 | I4: 1400000 | J4: 33012852 | K4: 612045 | L4: 32400807 | M4: 175680 | N4: 80000 | O4: 95680 | P4: 9190984 | Q4: 1502724 | R4: 259300 | S4: 7368960 | T4: 60000 | U4: 4700000 | V4: 20544895 | W4: 1805768 | X4: 14574793 | Y4: 1635802 | Z4: 2528532 | AA4: 366204
A5: 사업용발전설비 | B5: 소계 | C5: 129191273 | D5: 23250000 | E5: 37950658 | F5: 34950658 | G5: 400000 | H5: 1200000 | I5: 1400000 | J5: 33012852 | K5: 612045 | L5: 32400807 | M5: 175680 | N5: 80000 | O5: 95680 | P5: 9190984 | Q5: 1502724 | R5: 259300 | S5: 7368960 | T5: 60000 | U5: 4700000 | V5: 20544895 | W5: 1805768 | X5: 14574793 | Y5: 1635802 | Z5: 2528532 | AA5: 366204
B6: 한국전력㈜ | C6: 97103 | D6: - | E6: - | F6: - | G6: - | H6: - | I6: - | J6: - | K6: - | L6: - | M6: 95680 | N6: - | O6: 95680 | P6: - | Q6: - | R6: - | S6: - | T6: - | U6: - | V6: 1423 | W6: 700 | X6: 723 | Y6: - | Z6: - | AA6: -
B7: 한수원㈜ | C7: 28600394 | D7: 23250000 | E7: - | F7: - | G7: - | H7: - | I7: - | J7: - | K7: - | L7: - | M7: - | N7: - | O7: - | P7: - | Q7: - | R7: - | S7: - | T7: - | U7: 4700000 | V7: 650394 | W7: 606800 | X7: 42844 | Y7: 750 | Z7: - | AA7: -
B8: 남동발전㈜ | C8: 10398395 | D8: - | E8: 8988600 | F8: 8988600 | G8: - | H8: - | I8: - | J8: 922064 | K8: - | L8: 922064 | M8: - | N8: - | O8: - | P8: - | Q8: - | R8: - | S8: - | T8: - | U8: - | V8: 487731 | W8: 18599 | X8: 33922 | Y8: 58300 | Z8: 376910 | AA8: -
B9: 중부발전㈜ | C9: 10726134 | D9: - | E9: 6088058 | F9: 6088058 | G9: - | H9: - | I9: - | J9: 3779527 | K9: - | L9: 3779527 | M9: 80000 | N9: 80000 | O9: - | P9: 530441 | Q9: - | R9: - | S9: 530441 | T9: - | U9: - | V9: 238108 | W9: 12500 | X9: 15008 | Y9: 26000 | Z9: 184600 | AA9: 10000
B10: 서부발전㈜ | C10: 11361489 | D10: - | E10: 7500000 | F10: 6100000 | G10: - | H10: - | I10: 1400000 | J10: 3386900 | K10: - | L10: 3386900 | M10: - | N10: - | O10: - | P10: - | Q10: - | R10: - | S10: - | T10: - | U10: - | V10: 474589 | W10: 2200 | X10: 48099 | Y10: 16000 | Z10: 408290 | AA10: -
B11: 남부발전㈜ | C11: 11431991 | D11: - | E11: 6044000 | F11: 6044000 | G11: - | H11: - | I11: - | J11: 5060845 | K11: 146245 | L11: 4914600 | M11: - | N11: - | O11: - | P11: - | Q11: - | R11: - | S11: - | T11: - | U11: - | V11: 327146 | W11: 2810 | X11: 26116 | Y11: 39500 | Z11: 258720 | AA11: -
B12: 동서발전㈜ | C12: 11238189 | D12: - | E12: 8140000 | F12: 6540000 | G12: 400000 | H12: 1200000 | I12: - | J12: 2971900 | K12: - | L12: 2971900 | M12: - | N12: - | O12: - | P12: - | Q12: - | R12: - | S12: - | T12: - | U12: - | V12: 126289 | W12: 8198 | X12: 48811 | Y12: 3000 | Z12: 66280 | AA12: -
B13: 포스코에너지㈜ | C13: 3197669 | D13: - | E13: - | F13: - | G13: - | H13: - | I13: - | J13: 3176000 | K13: - | L13: 3176000 | M13: - | N13: - | O13: - | P13: - | Q13: - | R13: - | S13: - | T13: - | U13: - | V13: 21669 | W13: - | X13: 14469 | Y13: - | Z13: 7200 | AA13: -
B14: GS EPS㈜ | C14: 2467084 | D14: - | E14: - | F14: - | G14: - | H14: - | I14: - | J14: 2261750 | K14: - | L14: 2261750 | M14: - | N14: - | O14: - | P14: - | Q14: - | R14: - | S14: - | T14: - | U14: - | V14: 205334 | W14: - | X14: 334 | Y14: - | Z14: 205000 | AA14: -
B15: 지역난방공사 | C15: 2280523 | D15: - | E15: - | F15: - | G15: - | H15: - | I15: - | J15: - | K15: - | L15: - | M15: - | N15: - | O15: - | P15: 2220162 | Q15: - | R15: 145000 | S15: 2075162 | T15: - | U15: - | V15: 19921 | W15: - | X15: 2421 | Y15: - | Z15: 17500 | AA15: 40440
B16: 씨지앤 | C16: 1980900 | D16: - | E16: - | F16: - | G16: - | H16: - | I16: - | J16: 1855500 | K16: 465800 | L16: 1389700 | M16: - | N16: - | O16: - | P16: - | Q16: - | R16: - | S16: - | T16: - | U16: - | V16: 125400 | W16: - | X16: - | Y16: - | Z16: 125400 | AA16: -
B17: 동두천드림파워㈜ | C17: 1718662 | D17: - | E17: - | F17: - | G17: - | H17: - | I17: - | J17: 1716800 | K17: - | L17: 1716800 | M17: - | N17: - | O17: - | P17: - | Q17: - | R17: - | S17: - | T17: - | U17: - | V17: 1862 | W17: - | X17: 1862 | Y17: - | Z17: - | AA17: -
B18: 파주에너지서비스 | C18: 1715000 | D18: - | E18: - | F18: - | G18: - | H18: - | I18: - | J18: 1695200 | K18: - | L18: 1695200 | M18: - | N18: - | O18: - | P18: - | Q18: - | R18: - | S18: - | T18: - | U18: - | V18: 19800 | W18: - | X18: - | Y18: - | Z18: 19800 | AA18: -
B19: 포천파워㈜ | C19: 1450664 | D19: - | E19: - | F19: - | G19: - | H19: - | I19: - | J19: 1450000 | K19: - | L19: 1450000 | M19: - | N19: - | O19: - | P19: - | Q19: - | R19: - | S19: - | T19: - | U19: - | V19: 664 | W19: - | X19: 664 | Y19: - | Z19: - | AA19: -
B20: GS 파워㈜ | C20: 1409147 | D20: - | E20: - | F20: - | G20: - | H20: - | I20: - | J20: - | K20: - | L20: - | M20: - | N20: - | O20: - | P20: 1381690 | Q20: - | R20: - | S20: 1381690 | T20: - | U20: - | V20: 27457 | W20: 1030 | X20: 4017 | Y20: 7050 | Z20: 15360 | AA20: -
B21: 수자원공사 | C21: 1366584 | D21: - | E21: - | F21: - | G21: - | H21: - | I21: - | J21: - | K21: - | L21: - | M21: - | N21: - | O21: - | P21: - | Q21: - | R21: - | S21: - | T21: - | U21: - | V21: 1366584 | W21: 1089657 | X21: 14927 | Y21: 8000 | Z21: 254000 | AA21: -
B22: ㈜GS동해전력 | C22: 1200101 | D22: - | E22: 1190000 | F22: 1190000 | G22: - | H22: - | I22: - | J22: - | K22: - | L22: - | M22: - | N22: - | O22: - | P22: - | Q22: - | R22: - | S22: - | T22: - | U22: - | V22: 10101 | W22: 5000 | X22: 5101 | Y22: - | Z22: - | AA22: -
B23: 기타 | C23: 26551244 | D23: - | E23: - | F23: - | G23: - | H23: - | I23: - | J23: 4736366 | K23: - | L23: 4736366 | M23: - | N23: - | O23: - | P23: 5058691 | Q23: 1502724 | R23: 114300 | S23: 3381667 | T23: 60000 | U23: - | V23: 16440423 | W23: 58274 | X23: 14315474 | Y23: 1477202 | Z23: 589472 | AA23: 315764
A24: 구역전기설비 | B24: 소계 | C24: 1787600 | D24: - | E24: - | F24: - | G24: - | H24: - | I24: - | J24: - | K24: - | L24: - | M24: - | N24: - | O24: - | P24: - | Q24: - | R24: - | S24: - | T24: - | U24: - | V24: - | W24: - | X24: - | Y24: - | Z24: - | AA24: -

Sheet Subsidies Paid
A1: Model Energy Source | B1: Subsidy Name | C1: Fuel/Electricity | D1: Unit | E1: 2018 | F1: 2019 | G1: 2020 | H1: 2021 | I1: 2022 | J1: 2023 | K1: 2024 | L1: 2025 | M1: 2026 | N1: 2027 | O1: 2028 | P1: 2029 | Q1: 2030 | R1: 2031 | S1: 2032 | T1: 2033 | U1: 2034 | V1: 2035 | W1: 2036 | X1: 2037 | Y1: 2038 | Z1: 2039 | AA1: 2040 | AB1: 2041 | AC1: 2042 | AD1: 2043 | AE1: 2044 | AF1: 2045 | AG1: 2046 | AH1: 2047 | AI1: 2048 | AJ1: 2049 | AK1: 2050
A2: biomass | B2: no Subsidy | C2: Electricity | E2: 0 | F2: 0 | G2: 0 | H2: 0 | I2: 0 | J2: 0 | K2: 0 | L2: 0 | M2: 0 | N2: 0 | O2: 0 | P2: 0 | Q2: 0 | R2: 0 | S2: 0 | T2: 0 | U2: 0 | V2: 0 | W2: 0 | X2: 0 | Y2: 0 | Z2: 0 | AA2: 0 | AB2: 0 | AC2: 0 | AD2: 0 | AE2: 0 | AF2: 0 | AG2: 0 | AH2: 0 | AI2: 0 | AJ2: 0 | AK2: 0
A3: coal | B3: Amortization of air pollution control facilities | C3: Electricity | D3: $ | E3: =1070*10^6/About!$B$92*$B$27/$B$33 -> 879847.59 | F3: =19528*10^6/About!$B$92*$B$27/$B$34 -> 15996283 | G3: =F3 -> 15996283
A4: hydro | B4: no Subsidy | C4: Electricity | E4: 0 | F4: 0 | G4: 0 | H4: 0 | I4: 0 | J4: 0 | K4: 0 | L4: 0 | M4: 0 | N4: 0 | O4: 0 | P4: 0 | Q4: 0 | R4: 0 | S4: 0 | T4: 0 | U4: 0 | V4: 0 | W4: 0 | X4: 0 | Y4: 0 | Z4: 0 | AA4: 0 | AB4: 0 | AC4: 0 | AD4: 0 | AE4: 0 | AF4: 0 | AG4: 0 | AH4: 0 | AI4: 0 | AJ4: 0 | AK4: 0
A5: nuclear | B5: Special rules for nuclear decommissioning costs | C5: Electricity | D5: $
A6: solar pv | B6: no Subsidy | C6: Electricity | E6: 0 | F6: 0 | G6: 0 | H6: 0 | I6: 0 | J6: 0 | K6: 0 | L6: 0 | M6: 0 | N6: 0 | O6: 0 | P6: 0 | Q6: 0 | R6: 0 | S6: 0 | T6: 0 | U6: 0 | V6: 0 | W6: 0 | X6: 0 | Y6: 0 | Z6: 0 | AA6: 0 | AB6: 0 | AC6: 0 | AD6: 0 | AE6: 0 | AF6: 0 | AG6: 0 | AH6: 0 | AI6: 0 | AJ6: 0 | AK6: 0
A7: offshore wind | B7: no Subsidy | C7: Electricity | E7: 0 | F7: 0 | G7: 0 | H7: 0 | I7: 0 | J7: 0 | K7: 0 | L7: 0 | M7: 0 | N7: 0 | O7: 0 | P7: 0 | Q7: 0 | R7: 0 | S7: 0 | T7: 0 | U7: 0 | V7: 0 | W7: 0 | X7: 0 | Y7: 0 | Z7: 0 | AA7: 0 | AB7: 0 | AC7: 0 | AD7: 0 | AE7: 0 | AF7: 0 | AG7: 0 | AH7: 0 | AI7: 0 | AJ7: 0 | AK7: 0
A8: onshore wind | B8: no Subsidy | C8: Electricity | E8: 0 | F8: 0 | G8: 0 | H8: 0 | I8: 0 | J8: 0 | K8: 0 | L8: 0 | M8: 0 | N8: 0 | O8: 0 | P8: 0 | Q8: 0 | R8: 0 | S8: 0 | T8: 0 | U8: 0 | V8: 0 | W8: 0 | X8: 0 | Y8: 0 | Z8: 0 | AA8: 0 | AB8: 0 | AC8: 0 | AD8: 0 | AE8: 0 | AF8: 0 | AG8: 0 | AH8: 0 | AI8: 0 | AJ8: 0 | AK8: 0
A9: geothermal | B9: no Subsidy | C9: Electricity | E9: 0 | F9: 0 | G9: 0 | H9: 0 | I9: 0 | J9: 0 | K9: 0 | L9: 0 | M9: 0 | N9: 0 | O9: 0 | P9: 0 | Q9: 0 | R9: 0 | S9: 0 | T9: 0 | U9: 0 | V9: 0 | W9: 0 | X9: 0 | Y9: 0 | Z9: 0 | AA9: 0 | AB9: 0 | AC9: 0 | AD9: 0 | AE9: 0 | AF9: 0 | AG9: 0 | AH9: 0 | AI9: 0 | AJ9: 0 | AK9: 0
E10: =1070*10^6/About!$B$92 -> 949524.35 | F10: =1952*10^6/About!$B$92 -> 1732216.4
D11: 발전사별 설비용량 | G11: 설비비율
D12: 유연탄 | E12: ='발전사별 설비용량'!F5 -> 34950658 | F12: kW | G12: =E12/SUM($E$12:$E$13) -> 0.98868479
D13: 무연탄 | E13: ='발전사별 설비용량'!G5 -> 400000 | F13: kW | G13: =E13/SUM($E$12:$E$13) -> 0.011315207
D15: 무연탄, 유연탄 별 발전기여도(추정)(MWh)
D16: 구분 | E16: 2011 | F16: 2012 | G16: 2013 | H16: 2014 | I16: 2015 | J16: 2016 | K16: 2017 | L16: 2018 | M16: 2019 | N16: 2020
D17: 유연탄 | E17: {=(INDEX('에너지원별 발전량'!$E$4:$E$23,MATCH('Subsidies Paid'!E16,'에너지원별 발전량'!$A$4:$A$23,0)))*10^3-E18} -> 2.0056064e+08 | F17: {=(INDEX('에너지원별 발전량'!$E$4:$E$23,MATCH('Subsidies Paid'!F16,'에너지원별 발전량'!$A$4:$A$23,0)))*10^3-F18} -> 1.9990317e+08 | G17: {=(INDEX('에너지원별 발전량'!$E$4:$E$23,MATCH('Subsidies Paid'!G16,'에너지원별 발전량'!$A$4:$A$23,0)))*10^3-G18} -> 2.0188548e+08 | H17: {=(INDEX('에너지원별 발전량'!$E$4:$E$23,MATCH('Subsidies Paid'!H16,'에너지원별 발전량'!$A$4:$A$23,0)))*10^3-H18} -> 2.0486933e+08 | I17: {=(INDEX('에너지원별 발전량'!$E$4:$E$23,MATCH('Subsidies Paid'!I16,'에너지원별 발전량'!$A$4:$A$23,0)))*10^3-I18} -> 2.0900104e+08 | J17: {=(INDEX('에너지원별 발전량'!$E$4:$E$23,MATCH('Subsidies Paid'!J16,'에너지원별 발전량'!$A$4:$A$23,0)))*10^3-J18} -> 2.1138377e+08 | K17: {=(INDEX('에너지원별 발전량'!$E$4:$E$23,MATCH('Subsidies Paid'!K16,'에너지원별 발전량'!$A$4:$A$23,0)))*10^3-K18} -> 2.3609694e+08 | L17: {=(INDEX('에너지원별 발전량'!$E$4:$E$23,MATCH('Subsidies Paid'!L16,'에너지원별 발전량'!$A$4:$A$23,0)))*10^3-L18} -> 2.3626304e+08 | ... N17: {=(INDEX('에너지원별 발전량'!$E$4:$E$23,MATCH('Subsidies Paid'!N16,'에너지원별 발전량'!$A$4:$A$23,0)))*10^3-N18} -> 1.9411145e+08
B18: 굴뚝자동측정기기 예산, 석탄지원금으로 할당 | D18: 무연탄 | E18: {=($G$13*INDEX('에너지원별 발전량'!$E$4:$E$23,MATCH('Subsidies Paid'!E16,'에너지원별 발전량'!$A$4:$A$23,0)))*10^3} -> 2295357.6 | F18: {=($G$13*INDEX('에너지원별 발전량'!$E$4:$E$23,MATCH('Subsidies Paid'!F16,'에너지원별 발전량'!$A$4:$A$23,0)))*10^3} -> 2287832.9 | G18: {=($G$13*INDEX('에너지원별 발전량'!$E$4:$E$23,MATCH('Subsidies Paid'!G16,'에너지원별 발전량'!$A$4:$A$23,0)))*10^3} -> 2310519.9 | H18: {=($G$13*INDEX('에너지원별 발전량'!$E$4:$E$23,MATCH('Subsidies Paid'!H16,'에너지원별 발전량'!$A$4:$A$23,0)))*10^3} -> 2344669.2 | I18: {=($G$13*INDEX('에너지원별 발전량'!$E$4:$E$23,MATCH('Subsidies Paid'!I16,'에너지원별 발전량'!$A$4:$A$23,0)))*10^3} -> 2391955.5 | J18: {=($G$13*INDEX('에너지원별 발전량'!$E$4:$E$23,MATCH('Subsidies Paid'!J16,'에너지원별 발전량'!$A$4:$A$23,0)))*10^3} -> 2419225.1 | K18: {=($G$13*INDEX('에너지원별 발전량'!$E$4:$E$23,MATCH('Subsidies Paid'!K16,'에너지원별 발전량'!$A$4:$A$23,0)))*10^3} -> 2702060 | L18: {=($G$13*INDEX('에너지원별 발전량'!$E$4:$E$23,MATCH('Subsidies Paid'!L16,'에너지원별 발전량'!$A$4:$A$23,0)))*10^3} -> 2703961 | ... N18: {=($G$13*INDEX('에너지원별 발전량'!$E$4:$E$23,MATCH('Subsidies Paid'!N16,'에너지원별 발전량'!$A$4:$A$23,0)))*10^3} -> 2221548.5
A20: Notes
A21: 대기오염물질 총량관리대상 사업장은 굴뚝자동측정기기 설치가 의무 사항이고, 이를 예산을 통해 설치유도 및 운영지원을 하고 있다.
A22: 무연탄과 유연탄 발전이 합쳐진 지원 예산 현황 자료를 발전기여도를 통해 분할하였다.
A25: [참고] 소비자물가지수(CPI)
A26: 시점 | B26: 전국
A27: 2012 | B27: 91.815 | C27: =B27/$B$27 -> 1
A28: 2013 | B28: 93.01 | C28: =B28/$B$27 -> 1.0130153
A29: 2014 | B29: 94.196 | C29: =B29/$B$27 -> 1.0259326
A30: 2015 | B30: 94.861 | C30: =B30/$B$27 -> 1.0331754
A31: 2016 | B31: 95.783 | C31: =B31/$B$27 -> 1.0432173
A32: 2017 | B32: 97.645 | C32: =B32/$B$27 -> 1.0634972
A33: 2018 | B33: 99.086 | C33: =B33/$B$27 -> 1.0791919
A34: 2019 | B34: 99.466 | C34: =B34/$B$27 -> 1.0833306
A35: 2020 | B35: 100 | C35: =B35/$B$27 -> 1.0891467
A36: 2021 | B36: 102.5 | C36: =B36/$B$27 -> 1.1163753
A37: 2022 | B37: 107.72 | C37: =B37/$B$27 -> 1.1732288
A38: 2023 | B38: 111.59 | C38: =B38/$B$27 -> 1.2153788
... A40: 2025 | B40: 116.61 | C40: =B40/$B$27 -> 1.2700539

Sheet LCOE
A1: LCOE전망(won/kWh)
B2: 2020 | C2: 2030 | D2: CAGR
A3: solar pv | B3: 133.3 | C3: 106.2 | D3: =(C3/B3-1)/10 -> -0.020330083 | E3: =>태양광 CAGR만 현물가격 감소에 반영 | I3: 전원구성 전망 확인 후 offshore과 산술평균수치를 적용할지 생각중
A4: onshore wind | B4: 131.6 | C4: 122.7 | D4: =(C4/B4-1)/10 -> -0.0067629179
A5: offshore wind | B5: 215 | C5: 155 | D5: =(C5/B5-1)/10 -> -0.027906977
A7: Notes
A8: solar pv, onshore wind
A23: URL: | B23: https://home.kepco.co.kr/kepco/KR/ntcob/ntcobView.do?pageIndex=1&boardSeq=21049282&boardCd=BRD_000516&menuCd=FN3113
A25: solar pv | B25: =106*About!$B$92/1000 -> 119.44928 | C25: => 사회적 관점 선택
A26: onshore wind | B26: =105*About!$B$92/1000 -> 118.3224 | C26: => 사회적 관점 선택
A29: offshore wind

Sheet Cal-CAPEX (정리)
A1: Cal-CAPEX 계산 정리 (계산 순서대로)
A2: 원본: Cal-CAPEX 시트 기반 / 단위: $/kW (IRENA), 원/kW (한국 CAPEX)
A4: 【 STEP 1 】 IRENA 글로벌 신재생에너지 설치단가 원본 데이터 ($/kW)
A5: `
A7: 에너지원 | B7: 2010 | C7: 2011 | D7: 2012 | E7: 2013 | F7: 2014 | G7: 2015 | H7: 2016 | I7: 2017 | J7: 2018 | K7: 2019 | L7: 설명
A8: 태양광 (Solar PV) | B8: 4702.362 | C8: 3936.326 | D8: 2984.701 | E8: 2615.289 | F8: 2362.966 | G8: 1800.941 | H8: 1637.269 | I8: 1414.678 | J8: 1208.364 | K8: 994.695 | L8: 2010→2018 지속 하락
A9: 육상풍력 (Onshore Wind) | B9: 1949 | C9: 1939 | D9: 1972 | E9: 1828 | F9: 1781 | G9: 1642 | H9: 1635 | I9: 1628 | J9: 1549 | K9: 1473 | L9: 완만한 하락 추세
A10: 해상풍력 (Offshore Wind) | B10: 4650 | C10: 5326 | D10: 4741 | E10: 5738 | F10: 5245 | G10: 5260 | H10: 4280 | I10: 4683 | J10: 4245 | K10: 3800 | L10: 기준연도: 2018 ($4,245)
A11: 수력 (Hydro) | B11: 1234.26 | C11: 1210.083 | D11: 1286.921 | E11: 1517.231 | F11: 1587.465 | G11: 1452.069 | H11: 1839.237 | I11: 1768.749 | J11: 1455.857 | K11: 1709.289 | L11: 2019가격 고정 (비용상승+수요감소 상충가정)
A12: 바이오 (Bio) | B12: 2588.099 | C12: 1301.988 | D12: 1494.864 | E12: 3027.785 | F12: 2982.498 | G12: 2591.813 | H12: 2175.08 | I12: 2897.302 | J12: 1693.367 | K12: 2140.643 | L12: 2010-2019 평균가 고정 (규칙성 없음)
A14: 【 STEP 2 】 2030 / 2050년 CAPEX 목표값 가정 ($/kW)
A15: ► min/max 범위를 이용하여 IRENA 시나리오 중압값 적용 (비율 30% 위치)
A17: 에너지원 | B17: 2030 min | C17: 2030 max | D17: 2030 적용값 | E17: 2050 min | F17: 2050 max | G17: 2050 적용값 | H17: 산정공식
A18: 태양광 (Solar PV) | B18: 340 | C18: 834 | D18: =B18+(C18-B18)*0.3 -> 488.2 | E18: 165 | F18: 481 | G18: =E18+(F18-E18)*0.3 -> 259.8 | H18: = min + (max - min) xd7 30%
A19: 육상풍력 (Onshore Wind) | B19: 800 | C19: 1350 | D19: =B19+(C19-B19)*0.3 -> 965 | E19: 650 | F19: 1000 | G19: =E19+(F19-E19)*0.3 -> 755 | H19: = min + |min - max| xd7 30%
A20: 해상풍력 (Offshore Wind) | B20: 1700 | C20: 3200 | D20: =B20+(C20-B20)*0.3 -> 2150 | E20: 1400 | F20: 2800 | G20: =E20+(F20-E20)*0.3 -> 1820 | H20: = min + |min - max| xd7 30%
A22: ⚠️ 사용 비율 30%는 사용자가정. 노란 배경이 키 변수
A24: 【 STEP 3 】 CAGR (연평균성장률) 계산 - IRENA 글로벌 데이터 기반
A25: ► 실제 적용 기간: Solar PV / Onshore Wind → 2025−2050, Offshore Wind → 2018−2050
A27: 에너지원 | B27: CAGR (연평균 감소율) | C27: 적용기간 | D27: 산정공식
A28: 태양광 (Solar PV) | B28: =(G18/D18)^(1/(50-30))-1 -> -0.031048435 | C28: 2025년 이후 적용 | D28: = (2050년값 / 2025년값)^(1/연수) - 1
A29: 육상풍력 (Onshore Wind) | B29: =(G19/D19)^(1/(50-30))-1 -> -0.012195542 | C29: 2025년 이후 적용 | D29: = (2050년값 / 2025년값)^(1/연수) - 1
A30: 해상풍력 (Offshore Wind) | B30: =(G20/J10)^(1/(50-18))-1 -> -0.026118641 | C30: 2018년 이후 적용 | D30: = (2050년값 / 2018년값)^(1/연수) - 1
A32: ⚠️ 수력/바이오: CAGR 미사용 (IRENA 데이터 고정)
A34: 【 STEP 4 】 한국 신재에너지 CAPEX 연도별 추정 (원/kW)
A35: ► 파란색 셀 = 추정치(공식계산) / 흰색 셀 = 고정입력값 / 노란 배경 = 키 가정값 (2030, 2050 목표)
A36: ► 단위: 원/kW
A38: 에너지원 | B38: 2018 | C38: 2019 | D38: 2020 | E38: 2021 | F38: 2022 | G38: 2023 | H38: 2024 | I38: 2025 | J38: 2026 | K38: 2027 | L38: 2028 | M38: 2029 | N38: 2030 | O38: 2031 | P38: 2032 | Q38: 2033 | R38: 2034 | S38: 2035 | T38: 2036 | U38: 2037 | V38: 2038 | W38: 2039 | X38: 2040 | Y38: 2041 | Z38: 2042 | AA38: 2043 | AB38: 2044 | AC38: 2045 | AD38: 2046 | AE38: 2047 | AF38: 2048 | AG38: 2049 | AH38: 2050
A39: 태양광 (Solar PV) | D39: 1513.3 | E39: =_xlfn.FORECAST.LINEAR(E$38,CHOOSE({1,2},$D$39,$I$39),CHOOSE({1,2},$D$38,$I$38)) -> 1456.42 | F39: =_xlfn.FORECAST.LINEAR(F$38,CHOOSE({1,2},$D$39,$I$39),CHOOSE({1,2},$D$38,$I$38)) -> 1399.54 | G39: =_xlfn.FORECAST.LINEAR(G$38,CHOOSE({1,2},$D$39,$I$39),CHOOSE({1,2},$D$38,$I$38)) -> 1342.66 | H39: =_xlfn.FORECAST.LINEAR(H$38,CHOOSE({1,2},$D$39,$I$39),CHOOSE({1,2},$D$38,$I$38)) -> 1285.78 | I39: 1228.9 | J39: =_xlfn.FORECAST.LINEAR(J$38,CHOOSE({1,2},$I39,$N39), CHOOSE({1,2}, $I$38,$N$38)) -> 1194.14 | K39: =_xlfn.FORECAST.LINEAR(K$38,CHOOSE({1,2},$I39,$N39), CHOOSE({1,2}, $I$38,$N$38)) -> 1159.38 | L39: =_xlfn.FORECAST.LINEAR(L$38,CHOOSE({1,2},$I39,$N39), CHOOSE({1,2}, $I$38,$N$38)) -> 1124.62 | M39: =_xlfn.FORECAST.LINEAR(M$38,CHOOSE({1,2},$I39,$N39), CHOOSE({1,2}, $I$38,$N$38)) -> 1089.86 | N39: 1055.1 | O39: =N39*(1+$B$28) -> 1022.3408 | P39: =O39*(1+$B$28) -> 990.59871 | Q39: =P39*(1+$B$28) -> 959.84218 | R39: =Q39*(1+$B$28) -> 930.04058 | S39: =R39*(1+$B$28) -> 901.16427 | T39: =S39*(1+$B$28) -> 873.18453 | U39: =T39*(1+$B$28) -> 846.07352 | V39: =U39*(1+$B$28) -> 819.80426 | ... AH39: =AG39*(1+$B$28) -> 561.48091
A40: 육상풍력 (Onshore Wind) | D40: 2522.4 | E40: =_xlfn.FORECAST.LINEAR(E$38,CHOOSE({1,2},$D$40,$I$40),CHOOSE({1,2},$D$38,$I$38)) -> 2481.9 | F40: =_xlfn.FORECAST.LINEAR(F$38,CHOOSE({1,2},$D$40,$I$40),CHOOSE({1,2},$D$38,$I$38)) -> 2441.4 | G40: =_xlfn.FORECAST.LINEAR(G$38,CHOOSE({1,2},$D$40,$I$40),CHOOSE({1,2},$D$38,$I$38)) -> 2400.9 | H40: =_xlfn.FORECAST.LINEAR(H$38,CHOOSE({1,2},$D$40,$I$40),CHOOSE({1,2},$D$38,$I$38)) -> 2360.4 | I40: 2319.9 | J40: =_xlfn.FORECAST.LINEAR(J$38,CHOOSE({1,2},$I40,$N40), CHOOSE({1,2}, $I$38,$N$38)) -> 2296.4 | K40: =_xlfn.FORECAST.LINEAR(K$38,CHOOSE({1,2},$I40,$N40), CHOOSE({1,2}, $I$38,$N$38)) -> 2272.9 | L40: =_xlfn.FORECAST.LINEAR(L$38,CHOOSE({1,2},$I40,$N40), CHOOSE({1,2}, $I$38,$N$38)) -> 2249.4 | M40: =_xlfn.FORECAST.LINEAR(M$38,CHOOSE({1,2},$I40,$N40), CHOOSE({1,2}, $I$38,$N$38)) -> 2225.9 | N40: 2202.4 | O40: =N40*(1+$B$29) -> 2175.5405 | P40: =O40*(1+$B$29) -> 2149.0086 | Q40: =P40*(1+$B$29) -> 2122.8003 | R40: =Q40*(1+$B$29) -> 2096.9116 | S40: =R40*(1+$B$29) -> 2071.3386 | T40: =S40*(1+$B$29) -> 2046.0775 | U40: =T40*(1+$B$29) -> 2021.1245 | V40: =U40*(1+$B$29) -> 1996.4758 | ... AH40: =AG40*(1+$B$29) -> 1723.1212
A41: 해상풍력 (Offshore Wind) | B41: 5730 | C41: =B41*(1+$B$30) -> 5580.3402 | D41: =C41*(1+$B$30) -> 5434.5893 | E41: =D41*(1+$B$30) -> 5292.6452 | F41: =E41*(1+$B$30) -> 5154.4085 | G41: =F41*(1+$B$30) -> 5019.7823 | H41: =G41*(1+$B$30) -> 4888.6724 | I41: =H41*(1+$B$30) -> 4760.987 | J41: =I41*(1+$B$30) -> 4636.6365 | ... AH41: =AG41*(1+$B$30) -> 2456.6784
A45: ▶ 구간별 추정 방식 요약
A46: 구간 | B46: 기간 | C46: 태양광 / 육상풍력 | D46: 해상풍력
A47: 구간 1 (실적) | B47: 2020~2025 | C47: 한국 실측 CAPEX 기반 선형 보간 (5년 동안 일정 하락) | D47: 2018 기준데이터에 CAGR (−2.6%/년) 적용
A48: 구간 2 (연계) | B48: 2026~2030 | C48: IRENA 실적 기반 선형 감소 (1단계와 연계) | D48: CAGR 연속 적용
A49: 구간 3 (장기) | B49: 2031~2050 | C49: CAGR 적용 (전년 xd7 (1 + CAGR)) | D49: CAGR 연속 적용
A64: 【 STEP 5 】 한국 CAPEX USD 환산 ($/kW)
A65: ► 환산 공식: 원/kW xf7 1,000 xf7 환율(About시트 B92)
A66: ► 예시: 태양광 2020 = 1,513원/kW xf7 1,000 xf7 1,180 = 1.28 $/kW
A67: 환산 환율 (About시트) | B67: =About!$B$92 -> 1126.88
A68: 에너지원 | B68: 2020 | C68: 2021 | D68: 2022 | E68: 2023 | F68: 2024 | G68: 2025 | H68: 2026 | I68: 2027 | J68: 2028 | K68: 2029 | L68: 2030 | M68: 2031 | N68: 2032 | O68: 2033 | P68: 2034 | Q68: 2035 | R68: 2036 | S68: 2037 | T68: 2038 | U68: 2039 | V68: 2040 | W68: 2041 | X68: 2042 | Y68: 2043 | Z68: 2044 | AA68: 2045 | AB68: 2046 | AC68: 2047 | AD68: 2048 | AE68: 2049 | AF68: 2050
A69: solar PV ($/MW) | B69: =D39/$B$67*1000 -> 1342.9114 | C69: =E39/$B$67*1000 -> 1292.4358 | D69: =F39/$B$67*1000 -> 1241.9601 | E69: =G39/$B$67*1000 -> 1191.4845 | F69: =H39/$B$67*1000 -> 1141.0088 | G69: =I39/$B$67*1000 -> 1090.5332 | H69: =J39/$B$67*1000 -> 1059.6869 | I69: =K39/$B$67*1000 -> 1028.8407 | ... AF69: =AH39/$B$67*1000 -> 498.26149
A70: onshore wind ($/MW) | B70: =D40/$B$67*1000 -> 2238.3927 | C70: =E40/$B$67*1000 -> 2202.4528 | D70: =F40/$B$67*1000 -> 2166.5128 | E70: =G40/$B$67*1000 -> 2130.5729 | F70: =H40/$B$67*1000 -> 2094.633 | G70: =I40/$B$67*1000 -> 2058.693 | H70: =J40/$B$67*1000 -> 2037.839 | I70: =K40/$B$67*1000 -> 2016.9849 | ... AF70: =AH40/$B$67*1000 -> 1529.108
A71: offshore wind ($/MW) | B71: =D41/$B$67*1000 -> 4822.6868 | C71: =E41/$B$67*1000 -> 4696.7248 | D71: =F41/$B$67*1000 -> 4574.0527 | E71: =G41/$B$67*1000 -> 4454.5846 | F71: =H41/$B$67*1000 -> 4338.2369 | G71: =I41/$B$67*1000 -> 4224.9281 | H71: =J41/$B$67*1000 -> 4114.5787 | I71: =K41/$B$67*1000 -> 4007.1115 | ... AF71: =AH41/$B$67*1000 -> 2180.071
A72: hydro ($/MW) | B72: =K11 -> 1709.289 | C72: =B72 -> 1709.289 | D72: =C72 -> 1709.289 | E72: =D72 -> 1709.289 | F72: =E72 -> 1709.289 | G72: =F72 -> 1709.289 | H72: =G72 -> 1709.289 | I72: =H72 -> 1709.289 | J72: =I72 -> 1709.289 | ... AF72: =AE72 -> 1709.289 | AG72: 2019년가격 고정 (1,709 $/kW)
A73: biomass ($/MW) | B73: =AVERAGE(B12:K12) -> 2289.3439 | C73: =B73 -> 2289.3439 | D73: =C73 -> 2289.3439 | E73: =D73 -> 2289.3439 | F73: =E73 -> 2289.3439 | G73: =F73 -> 2289.3439 | H73: =G73 -> 2289.3439 | I73: =H73 -> 2289.3439 | J73: =I73 -> 2289.3439 | ... AF73: =AE73 -> 2289.3439 | AG73: 2010-2019 평균가 고정 (2,289 $/kW)
A74: 【 STEP 6 】 세액공제율 (조세특례제한법 제25조 2연)
A75: ► CAPEX에 대한 세액공제 참고용 모수 (실제 적용 시 BSpUECB 시트 활용)
A77: 기업 구분 | B77: 세액공제율
A78: 중소기업 | B78: 0.07
A79: 중견기업 | B79: 0.03
A80: 내국법인(내국인) | B80: 0.01
A83: ■ 범레
A84: 파란 텍스트 | B84: = 공식으로 계산된 추정치 (Cal-CAPEX 시트에서 직접 참조)
A85: 흰 배경 셀 | B85: = 키 입력값 (2025년 실측 기준값)
A86: 노란 배경 셀 | B86: = 2030/2050 목표값 (IRENA 시나리오 기반 가정)
A87: 노란 CAGR 비율에 근거 | B87: = 사용자가 조정 가능한 키 변수 (30%, E35 셀)
A89: ■ 계산 흐름 요약
A90: STEP 1 → IRENA 글로벌 데이터 ($/kW, 2010-2018)
A91: STEP 2 → IRENA 기반 CAGR 추정 (연평균 감소율)
A92: STEP 3 → 2030/2050 목표 CAPEX 가정 (min/max 범위 연구 기반)
A93: STEP 4 → 한국 원/kW CAPEX 2020-2050 연도별 추정 (수력/바이오는 IRENA 고정)
A94: STEP 5 → 원/kW xf7 1,000 xf7 환율 → $/kW USD 환산
A95: STEP 6 → 세액공제율 (BSpUECB 시트 활용)

Sheet Sheet1
A1: 한국 에너지 구성비(비율, 수입량, 수입의존도, 수입액) 정리
C2: page 4~
C4: 구성비 | D4: 2016 | E4: 2017 | F4: 2018
C5: 석탄(Coal) | D5: 27.7 | E5: 28.5 | F5: 28.2
C6: 석유(Petroleum) | D6: 40 | E6: 39.5 | F6: 38.5
C7: 천연가스(LNG) | D7: 15.5 | E7: 15.7 | F7: 18
C8: 수력(Hydro) | D8: 0.5 | E8: 0.5 | F8: 0.5
C9: 원자력(Nuclear) | D9: 11.6 | E9: 10.5 | F9: 9.2
C10: 신재생(Renewables) | D10: 4.6 | E10: 5.2 | F10: 5.6
F12: 1,000 ton
C13: 수입량 | D13: 2016 | E13: 2017 | F13: 2018
C14: 무연탄(Anthracite) | D14: 9424 | E14: 7003 | F14: 8126
C15: 유연탄(Bituminous) | D15: 118468 | E15: 131464 | F15: 131520
C16: 기타석탄(Others) | D16: 7038 | E16: 10210 | F16: 9450
C17: 원유(Crude Oil) | D17: 1078119 | E17: 1118167 | F17: 1116281
C18: 석유제품(Petroleum Products) | D18: 334608 | E18: 314487 | F18: 341628
C19: 천연가스(LNG) | D19: 33453 | E19: 37537 | F19: 44015
C20: 원자력 연료(Uranium) | D20: 752 | E20: 1012 | F20: 723
C22: 수출량 | D22: 2016 | E22: 2017 | F22: 2018
C23: 석유제품(Petroleum Products) | D23: 487716 | E23: 509113 | F23: 531563
F25: Million USD(CIF)
C26: 수입액 | D26: 2016 | E26: 2017 | F26: 2018
C27: 무연탄(Anthracite) | D27: 759 | E27: 933 | F27: 1199
C28: 유연탄(Bituminous) | D28: 8168 | E28: 13481 | F28: 14668
C29: 기타석탄(Others) | D29: 383 | E29: 765 | F29: 835
C30: 원유(Crude Oil) | D30: 44295 | E30: 59603 | F30: 80393
C31: 나프타(Naphtha) | D31: 8933 | E31: 10899 | F31: 15671
C32: LPG | D32: 2576 | E32: 2959 | F32: 3665
C33: 천연가스(LNG) | D33: 12170 | E33: 15616 | F33: 23189
C34: 원자력 연료(Uranium) | D34: 589 | E34: 991 | F34: 576
C36: 1차에너지 공급구조
C38: 생산 | D38: 2016 | E38: 2017 | F38: 2018
C39: 무연탄(Anthracite) | D39: 1373 | E39: 1244 | F39: 1099 | G39: 1000 ton | H39: => 무연탄 지원금을 찾아보자
C40: 천연가스(LNG) | D40: 118 | E40: 261 | F40: 234 | G40: 1000 ton
C41: 수력(Hydro) | D41: 6634 | E41: 6995 | F41: 7270 | G41: GWh
C42: 신재생(Renewables) | D42: 13575 | E42: 15848 | F42: 17119 | G42: 1000 toe
C45: 수입 | D45: 2016 | E45: 2017 | F45: 2018
C46: 석탄(Coal) | D46: 127936 | E46: 138506 | F46: 139876 | G46: 1000 ton
C47: 석유(Petroleum) | D47: 921082 | E47: 937095 | F47: 931787 | G47: 1000 bbl
C48: 원자력(Nuclear) | D48: 161995 | E48: 148427 | F48: 133505 | G48: GWh
C49: 천연가스(LNG) | D49: 34788 | E49: 36138 | F49: 42051 | G49: 1000 ton

Sheet BSpUECB_세액공제액
A1: Year | B1: 2020 | C1: 2021 | D1: 2022 | E1: 2023 | F1: 2024 | G1: 2025 | H1: 2026 | I1: 2027 | J1: 2028 | K1: 2029 | L1: 2030 | M1: 2031 | N1: 2032 | O1: 2033 | P1: 2034 | Q1: 2035 | R1: 2036 | S1: 2037 | T1: 2038 | U1: 2039 | V1: 2040 | W1: 2041 | X1: 2042 | Y1: 2043 | Z1: 2044 | AA1: 2045 | AB1: 2046 | AC1: 2047 | AD1: 2048 | AE1: 2049 | AF1: 2050
A2: hard coal ($/MW) | B2: 0 | C2: 0 | D2: 0 | E2: 0 | F2: 0 | G2: 0 | H2: 0 | I2: 0 | J2: 0 | K2: 0 | L2: 0 | M2: 0 | N2: 0 | O2: 0 | P2: 0 | Q2: 0 | R2: 0 | S2: 0 | T2: 0 | U2: 0 | V2: 0 | W2: 0 | X2: 0 | Y2: 0 | Z2: 0 | AA2: 0 | AB2: 0 | AC2: 0 | AD2: 0 | AE2: 0 | AF2: 0
A3: natural gas nonpeaker ($/MW) | B3: 0 | C3: 0 | D3: 0 | E3: 0 | F3: 0 | G3: 0 | H3: 0 | I3: 0 | J3: 0 | K3: 0 | L3: 0 | M3: 0 | N3: 0 | O3: 0 | P3: 0 | Q3: 0 | R3: 0 | S3: 0 | T3: 0 | U3: 0 | V3: 0 | W3: 0 | X3: 0 | Y3: 0 | Z3: 0 | AA3: 0 | AB3: 0 | AC3: 0 | AD3: 0 | AE3: 0 | AF3: 0
A4: nuclear ($/MW) | B4: 0 | C4: 0 | D4: 0 | E4: 0 | F4: 0 | G4: 0 | H4: 0 | I4: 0 | J4: 0 | K4: 0 | L4: 0 | M4: 0 | N4: 0 | O4: 0 | P4: 0 | Q4: 0 | R4: 0 | S4: 0 | T4: 0 | U4: 0 | V4: 0 | W4: 0 | X4: 0 | Y4: 0 | Z4: 0 | AA4: 0 | AB4: 0 | AC4: 0 | AD4: 0 | AE4: 0 | AF4: 0
A5: hydro ($/MW) | B5: =IFERROR(INDEX('Cal-CAPEX (정리)'!$B$69:$AF$73,MATCH(BSpUECB_세액공제액!$A5,'Cal-CAPEX (정리)'!$A$69:$A$73,0),MATCH(BSpUECB_세액공제액!B$1,'Cal-CAPEX (정리)'!$B$68:$AF$68,0))*About!$B$93*'Cal-CAPEX (정리)'!$B$79/10,0) -> 5127.867 | C5: =IFERROR(INDEX('Cal-CAPEX (정리)'!$B$69:$AF$73,MATCH(BSpUECB_세액공제액!$A5,'Cal-CAPEX (정리)'!$A$69:$A$73,0),MATCH(BSpUECB_세액공제액!C$1,'Cal-CAPEX (정리)'!$B$68:$AF$68,0))*About!$B$93*'Cal-CAPEX (정리)'!$B$79/10,0) -> 5127.867 | D5: =IFERROR(INDEX('Cal-CAPEX (정리)'!$B$69:$AF$73,MATCH(BSpUECB_세액공제액!$A5,'Cal-CAPEX (정리)'!$A$69:$A$73,0),MATCH(BSpUECB_세액공제액!D$1,'Cal-CAPEX (정리)'!$B$68:$AF$68,0))*About!$B$93*'Cal-CAPEX (정리)'!$B$79/10,0) -> 5127.867 | E5: =IFERROR(INDEX('Cal-CAPEX (정리)'!$B$69:$AF$73,MATCH(BSpUECB_세액공제액!$A5,'Cal-CAPEX (정리)'!$A$69:$A$73,0),MATCH(BSpUECB_세액공제액!E$1,'Cal-CAPEX (정리)'!$B$68:$AF$68,0))*About!$B$93*'Cal-CAPEX (정리)'!$B$79/10,0) -> 5127.867 | F5: =IFERROR(INDEX('Cal-CAPEX (정리)'!$B$69:$AF$73,MATCH(BSpUECB_세액공제액!$A5,'Cal-CAPEX (정리)'!$A$69:$A$73,0),MATCH(BSpUECB_세액공제액!F$1,'Cal-CAPEX (정리)'!$B$68:$AF$68,0))*About!$B$93*'Cal-CAPEX (정리)'!$B$79/10,0) -> 5127.867 | G5: =IFERROR(INDEX('Cal-CAPEX (정리)'!$B$69:$AF$73,MATCH(BSpUECB_세액공제액!$A5,'Cal-CAPEX (정리)'!$A$69:$A$73,0),MATCH(BSpUECB_세액공제액!G$1,'Cal-CAPEX (정리)'!$B$68:$AF$68,0))*About!$B$93*'Cal-CAPEX (정리)'!$B$79/10,0) -> 5127.867 | H5: =IFERROR(INDEX('Cal-CAPEX (정리)'!$B$69:$AF$73,MATCH(BSpUECB_세액공제액!$A5,'Cal-CAPEX (정리)'!$A$69:$A$73,0),MATCH(BSpUECB_세액공제액!H$1,'Cal-CAPEX (정리)'!$B$68:$AF$68,0))*About!$B$93*'Cal-CAPEX (정리)'!$B$79/10,0) -> 5127.867 | I5: =IFERROR(INDEX('Cal-CAPEX (정리)'!$B$69:$AF$73,MATCH(BSpUECB_세액공제액!$A5,'Cal-CAPEX (정리)'!$A$69:$A$73,0),MATCH(BSpUECB_세액공제액!I$1,'Cal-CAPEX (정리)'!$B$68:$AF$68,0))*About!$B$93*'Cal-CAPEX (정리)'!$B$79/10,0) -> 5127.867 | ... AF5: =IFERROR(INDEX('Cal-CAPEX (정리)'!$B$69:$AF$73,MATCH(BSpUECB_세액공제액!$A5,'Cal-CAPEX (정리)'!$A$69:$A$73,0),MATCH(BSpUECB_세액공제액!AF$1,'Cal-CAPEX (정리)'!$B$68:$AF$68,0))*About!$B$93*'Cal-CAPEX (정리)'!$B$79/10,0) -> 5127.867
A6: onshore wind ($/MW) | B6: =IFERROR(INDEX('Cal-CAPEX (정리)'!$B$69:$AF$73,MATCH(BSpUECB_세액공제액!$A6,'Cal-CAPEX (정리)'!$A$69:$A$73,0),MATCH(BSpUECB_세액공제액!B$1,'Cal-CAPEX (정리)'!$B$68:$AF$68,0))*About!$B$93*'Cal-CAPEX (정리)'!$B$79/10,0) -> 6715.1782 | C6: =IFERROR(INDEX('Cal-CAPEX (정리)'!$B$69:$AF$73,MATCH(BSpUECB_세액공제액!$A6,'Cal-CAPEX (정리)'!$A$69:$A$73,0),MATCH(BSpUECB_세액공제액!C$1,'Cal-CAPEX (정리)'!$B$68:$AF$68,0))*About!$B$93*'Cal-CAPEX (정리)'!$B$79/10,0) -> 6607.3584 | D6: =IFERROR(INDEX('Cal-CAPEX (정리)'!$B$69:$AF$73,MATCH(BSpUECB_세액공제액!$A6,'Cal-CAPEX (정리)'!$A$69:$A$73,0),MATCH(BSpUECB_세액공제액!D$1,'Cal-CAPEX (정리)'!$B$68:$AF$68,0))*About!$B$93*'Cal-CAPEX (정리)'!$B$79/10,0) -> 6499.5385 | E6: =IFERROR(INDEX('Cal-CAPEX (정리)'!$B$69:$AF$73,MATCH(BSpUECB_세액공제액!$A6,'Cal-CAPEX (정리)'!$A$69:$A$73,0),MATCH(BSpUECB_세액공제액!E$1,'Cal-CAPEX (정리)'!$B$68:$AF$68,0))*About!$B$93*'Cal-CAPEX (정리)'!$B$79/10,0) -> 6391.7187 | F6: =IFERROR(INDEX('Cal-CAPEX (정리)'!$B$69:$AF$73,MATCH(BSpUECB_세액공제액!$A6,'Cal-CAPEX (정리)'!$A$69:$A$73,0),MATCH(BSpUECB_세액공제액!F$1,'Cal-CAPEX (정리)'!$B$68:$AF$68,0))*About!$B$93*'Cal-CAPEX (정리)'!$B$79/10,0) -> 6283.8989 | G6: =IFERROR(INDEX('Cal-CAPEX (정리)'!$B$69:$AF$73,MATCH(BSpUECB_세액공제액!$A6,'Cal-CAPEX (정리)'!$A$69:$A$73,0),MATCH(BSpUECB_세액공제액!G$1,'Cal-CAPEX (정리)'!$B$68:$AF$68,0))*About!$B$93*'Cal-CAPEX (정리)'!$B$79/10,0) -> 6176.0791 | H6: =IFERROR(INDEX('Cal-CAPEX (정리)'!$B$69:$AF$73,MATCH(BSpUECB_세액공제액!$A6,'Cal-CAPEX (정리)'!$A$69:$A$73,0),MATCH(BSpUECB_세액공제액!H$1,'Cal-CAPEX (정리)'!$B$68:$AF$68,0))*About!$B$93*'Cal-CAPEX (정리)'!$B$79/10,0) -> 6113.517 | I6: =IFERROR(INDEX('Cal-CAPEX (정리)'!$B$69:$AF$73,MATCH(BSpUECB_세액공제액!$A6,'Cal-CAPEX (정리)'!$A$69:$A$73,0),MATCH(BSpUECB_세액공제액!I$1,'Cal-CAPEX (정리)'!$B$68:$AF$68,0))*About!$B$93*'Cal-CAPEX (정리)'!$B$79/10,0) -> 6050.9548 | ... AF6: =IFERROR(INDEX('Cal-CAPEX (정리)'!$B$69:$AF$73,MATCH(BSpUECB_세액공제액!$A6,'Cal-CAPEX (정리)'!$A$69:$A$73,0),MATCH(BSpUECB_세액공제액!AF$1,'Cal-CAPEX (정리)'!$B$68:$AF$68,0))*About!$B$93*'Cal-CAPEX (정리)'!$B$79/10,0) -> 4587.3241
A7: solar PV ($/MW) | B7: =IFERROR(INDEX('Cal-CAPEX (정리)'!$B$69:$AF$73,MATCH(BSpUECB_세액공제액!$A7,'Cal-CAPEX (정리)'!$A$69:$A$73,0),MATCH(BSpUECB_세액공제액!B$1,'Cal-CAPEX (정리)'!$B$68:$AF$68,0))*About!$B$93*'Cal-CAPEX (정리)'!$B$79/10,0) -> 4028.7342 | C7: =IFERROR(INDEX('Cal-CAPEX (정리)'!$B$69:$AF$73,MATCH(BSpUECB_세액공제액!$A7,'Cal-CAPEX (정리)'!$A$69:$A$73,0),MATCH(BSpUECB_세액공제액!C$1,'Cal-CAPEX (정리)'!$B$68:$AF$68,0))*About!$B$93*'Cal-CAPEX (정리)'!$B$79/10,0) -> 3877.3073 | D7: =IFERROR(INDEX('Cal-CAPEX (정리)'!$B$69:$AF$73,MATCH(BSpUECB_세액공제액!$A7,'Cal-CAPEX (정리)'!$A$69:$A$73,0),MATCH(BSpUECB_세액공제액!D$1,'Cal-CAPEX (정리)'!$B$68:$AF$68,0))*About!$B$93*'Cal-CAPEX (정리)'!$B$79/10,0) -> 3725.8803 | E7: =IFERROR(INDEX('Cal-CAPEX (정리)'!$B$69:$AF$73,MATCH(BSpUECB_세액공제액!$A7,'Cal-CAPEX (정리)'!$A$69:$A$73,0),MATCH(BSpUECB_세액공제액!E$1,'Cal-CAPEX (정리)'!$B$68:$AF$68,0))*About!$B$93*'Cal-CAPEX (정리)'!$B$79/10,0) -> 3574.4534 | F7: =IFERROR(INDEX('Cal-CAPEX (정리)'!$B$69:$AF$73,MATCH(BSpUECB_세액공제액!$A7,'Cal-CAPEX (정리)'!$A$69:$A$73,0),MATCH(BSpUECB_세액공제액!F$1,'Cal-CAPEX (정리)'!$B$68:$AF$68,0))*About!$B$93*'Cal-CAPEX (정리)'!$B$79/10,0) -> 3423.0264 | G7: =IFERROR(INDEX('Cal-CAPEX (정리)'!$B$69:$AF$73,MATCH(BSpUECB_세액공제액!$A7,'Cal-CAPEX (정리)'!$A$69:$A$73,0),MATCH(BSpUECB_세액공제액!G$1,'Cal-CAPEX (정리)'!$B$68:$AF$68,0))*About!$B$93*'Cal-CAPEX (정리)'!$B$79/10,0) -> 3271.5995 | H7: =IFERROR(INDEX('Cal-CAPEX (정리)'!$B$69:$AF$73,MATCH(BSpUECB_세액공제액!$A7,'Cal-CAPEX (정리)'!$A$69:$A$73,0),MATCH(BSpUECB_세액공제액!H$1,'Cal-CAPEX (정리)'!$B$68:$AF$68,0))*About!$B$93*'Cal-CAPEX (정리)'!$B$79/10,0) -> 3179.0608 | I7: =IFERROR(INDEX('Cal-CAPEX (정리)'!$B$69:$AF$73,MATCH(BSpUECB_세액공제액!$A7,'Cal-CAPEX (정리)'!$A$69:$A$73,0),MATCH(BSpUECB_세액공제액!I$1,'Cal-CAPEX (정리)'!$B$68:$AF$68,0))*About!$B$93*'Cal-CAPEX (정리)'!$B$79/10,0) -> 3086.5221 | ... AF7: =IFERROR(INDEX('Cal-CAPEX (정리)'!$B$69:$AF$73,MATCH(BSpUECB_세액공제액!$A7,'Cal-CAPEX (정리)'!$A$69:$A$73,0),MATCH(BSpUECB_세액공제액!AF$1,'Cal-CAPEX (정리)'!$B$68:$AF$68,0))*About!$B$93*'Cal-CAPEX (정리)'!$B$79/10,0) -> 1494.7845
A8: solar thermal ($/MW) | B8: =IFERROR(INDEX('Cal-CAPEX (정리)'!$B$69:$AF$73,MATCH(BSpUECB_세액공제액!$A8,'Cal-CAPEX (정리)'!$A$69:$A$73,0),MATCH(BSpUECB_세액공제액!B$1,'Cal-CAPEX (정리)'!$B$68:$AF$68,0))*About!$B$93*'Cal-CAPEX (정리)'!$B$79/10,0) -> 0 | C8: =IFERROR(INDEX('Cal-CAPEX (정리)'!$B$69:$AF$73,MATCH(BSpUECB_세액공제액!$A8,'Cal-CAPEX (정리)'!$A$69:$A$73,0),MATCH(BSpUECB_세액공제액!C$1,'Cal-CAPEX (정리)'!$B$68:$AF$68,0))*About!$B$93*'Cal-CAPEX (정리)'!$B$79/10,0) -> 0 | D8: =IFERROR(INDEX('Cal-CAPEX (정리)'!$B$69:$AF$73,MATCH(BSpUECB_세액공제액!$A8,'Cal-CAPEX (정리)'!$A$69:$A$73,0),MATCH(BSpUECB_세액공제액!D$1,'Cal-CAPEX (정리)'!$B$68:$AF$68,0))*About!$B$93*'Cal-CAPEX (정리)'!$B$79/10,0) -> 0 | E8: =IFERROR(INDEX('Cal-CAPEX (정리)'!$B$69:$AF$73,MATCH(BSpUECB_세액공제액!$A8,'Cal-CAPEX (정리)'!$A$69:$A$73,0),MATCH(BSpUECB_세액공제액!E$1,'Cal-CAPEX (정리)'!$B$68:$AF$68,0))*About!$B$93*'Cal-CAPEX (정리)'!$B$79/10,0) -> 0 | F8: =IFERROR(INDEX('Cal-CAPEX (정리)'!$B$69:$AF$73,MATCH(BSpUECB_세액공제액!$A8,'Cal-CAPEX (정리)'!$A$69:$A$73,0),MATCH(BSpUECB_세액공제액!F$1,'Cal-CAPEX (정리)'!$B$68:$AF$68,0))*About!$B$93*'Cal-CAPEX (정리)'!$B$79/10,0) -> 0 | G8: =IFERROR(INDEX('Cal-CAPEX (정리)'!$B$69:$AF$73,MATCH(BSpUECB_세액공제액!$A8,'Cal-CAPEX (정리)'!$A$69:$A$73,0),MATCH(BSpUECB_세액공제액!G$1,'Cal-CAPEX (정리)'!$B$68:$AF$68,0))*About!$B$93*'Cal-CAPEX (정리)'!$B$79/10,0) -> 0 | H8: =IFERROR(INDEX('Cal-CAPEX (정리)'!$B$69:$AF$73,MATCH(BSpUECB_세액공제액!$A8,'Cal-CAPEX (정리)'!$A$69:$A$73,0),MATCH(BSpUECB_세액공제액!H$1,'Cal-CAPEX (정리)'!$B$68:$AF$68,0))*About!$B$93*'Cal-CAPEX (정리)'!$B$79/10,0) -> 0 | I8: =IFERROR(INDEX('Cal-CAPEX (정리)'!$B$69:$AF$73,MATCH(BSpUECB_세액공제액!$A8,'Cal-CAPEX (정리)'!$A$69:$A$73,0),MATCH(BSpUECB_세액공제액!I$1,'Cal-CAPEX (정리)'!$B$68:$AF$68,0))*About!$B$93*'Cal-CAPEX (정리)'!$B$79/10,0) -> 0 | ... AF8: =IFERROR(INDEX('Cal-CAPEX (정리)'!$B$69:$AF$73,MATCH(BSpUECB_세액공제액!$A8,'Cal-CAPEX (정리)'!$A$69:$A$73,0),MATCH(BSpUECB_세액공제액!AF$1,'Cal-CAPEX (정리)'!$B$68:$AF$68,0))*About!$B$93*'Cal-CAPEX (정리)'!$B$79/10,0) -> 0
A9: biomass ($/MW) | B9: =IFERROR(INDEX('Cal-CAPEX (정리)'!$B$69:$AF$73,MATCH(BSpUECB_세액공제액!$A9,'Cal-CAPEX (정리)'!$A$69:$A$73,0),MATCH(BSpUECB_세액공제액!B$1,'Cal-CAPEX (정리)'!$B$68:$AF$68,0))*About!$B$93*'Cal-CAPEX (정리)'!$B$79/10,0) -> 6868.0317 | C9: =IFERROR(INDEX('Cal-CAPEX (정리)'!$B$69:$AF$73,MATCH(BSpUECB_세액공제액!$A9,'Cal-CAPEX (정리)'!$A$69:$A$73,0),MATCH(BSpUECB_세액공제액!C$1,'Cal-CAPEX (정리)'!$B$68:$AF$68,0))*About!$B$93*'Cal-CAPEX (정리)'!$B$79/10,0) -> 6868.0317 | D9: =IFERROR(INDEX('Cal-CAPEX (정리)'!$B$69:$AF$73,MATCH(BSpUECB_세액공제액!$A9,'Cal-CAPEX (정리)'!$A$69:$A$73,0),MATCH(BSpUECB_세액공제액!D$1,'Cal-CAPEX (정리)'!$B$68:$AF$68,0))*About!$B$93*'Cal-CAPEX (정리)'!$B$79/10,0) -> 6868.0317 | E9: =IFERROR(INDEX('Cal-CAPEX (정리)'!$B$69:$AF$73,MATCH(BSpUECB_세액공제액!$A9,'Cal-CAPEX (정리)'!$A$69:$A$73,0),MATCH(BSpUECB_세액공제액!E$1,'Cal-CAPEX (정리)'!$B$68:$AF$68,0))*About!$B$93*'Cal-CAPEX (정리)'!$B$79/10,0) -> 6868.0317 | F9: =IFERROR(INDEX('Cal-CAPEX (정리)'!$B$69:$AF$73,MATCH(BSpUECB_세액공제액!$A9,'Cal-CAPEX (정리)'!$A$69:$A$73,0),MATCH(BSpUECB_세액공제액!F$1,'Cal-CAPEX (정리)'!$B$68:$AF$68,0))*About!$B$93*'Cal-CAPEX (정리)'!$B$79/10,0) -> 6868.0317 | G9: =IFERROR(INDEX('Cal-CAPEX (정리)'!$B$69:$AF$73,MATCH(BSpUECB_세액공제액!$A9,'Cal-CAPEX (정리)'!$A$69:$A$73,0),MATCH(BSpUECB_세액공제액!G$1,'Cal-CAPEX (정리)'!$B$68:$AF$68,0))*About!$B$93*'Cal-CAPEX (정리)'!$B$79/10,0) -> 6868.0317 | H9: =IFERROR(INDEX('Cal-CAPEX (정리)'!$B$69:$AF$73,MATCH(BSpUECB_세액공제액!$A9,'Cal-CAPEX (정리)'!$A$69:$A$73,0),MATCH(BSpUECB_세액공제액!H$1,'Cal-CAPEX (정리)'!$B$68:$AF$68,0))*About!$B$93*'Cal-CAPEX (정리)'!$B$79/10,0) -> 6868.0317 | I9: =IFERROR(INDEX('Cal-CAPEX (정리)'!$B$69:$AF$73,MATCH(BSpUECB_세액공제액!$A9,'Cal-CAPEX (정리)'!$A$69:$A$73,0),MATCH(BSpUECB_세액공제액!I$1,'Cal-CAPEX (정리)'!$B$68:$AF$68,0))*About!$B$93*'Cal-CAPEX (정리)'!$B$79/10,0) -> 6868.0317 | ... AF9: =IFERROR(INDEX('Cal-CAPEX (정리)'!$B$69:$AF$73,MATCH(BSpUECB_세액공제액!$A9,'Cal-CAPEX (정리)'!$A$69:$A$73,0),MATCH(BSpUECB_세액공제액!AF$1,'Cal-CAPEX (정리)'!$B$68:$AF$68,0))*About!$B$93*'Cal-CAPEX (정리)'!$B$79/10,0) -> 6868.0317
A10: geothermal ($/MW) | B10: =IFERROR(INDEX('Cal-CAPEX (정리)'!$B$69:$AF$73,MATCH(BSpUECB_세액공제액!$A10,'Cal-CAPEX (정리)'!$A$69:$A$73,0),MATCH(BSpUECB_세액공제액!B$1,'Cal-CAPEX (정리)'!$B$68:$AF$68,0))*About!$B$93*'Cal-CAPEX (정리)'!$B$79/10,0) -> 0 | C10: =IFERROR(INDEX('Cal-CAPEX (정리)'!$B$69:$AF$73,MATCH(BSpUECB_세액공제액!$A10,'Cal-CAPEX (정리)'!$A$69:$A$73,0),MATCH(BSpUECB_세액공제액!C$1,'Cal-CAPEX (정리)'!$B$68:$AF$68,0))*About!$B$93*'Cal-CAPEX (정리)'!$B$79/10,0) -> 0 | D10: =IFERROR(INDEX('Cal-CAPEX (정리)'!$B$69:$AF$73,MATCH(BSpUECB_세액공제액!$A10,'Cal-CAPEX (정리)'!$A$69:$A$73,0),MATCH(BSpUECB_세액공제액!D$1,'Cal-CAPEX (정리)'!$B$68:$AF$68,0))*About!$B$93*'Cal-CAPEX (정리)'!$B$79/10,0) -> 0 | E10: =IFERROR(INDEX('Cal-CAPEX (정리)'!$B$69:$AF$73,MATCH(BSpUECB_세액공제액!$A10,'Cal-CAPEX (정리)'!$A$69:$A$73,0),MATCH(BSpUECB_세액공제액!E$1,'Cal-CAPEX (정리)'!$B$68:$AF$68,0))*About!$B$93*'Cal-CAPEX (정리)'!$B$79/10,0) -> 0 | F10: =IFERROR(INDEX('Cal-CAPEX (정리)'!$B$69:$AF$73,MATCH(BSpUECB_세액공제액!$A10,'Cal-CAPEX (정리)'!$A$69:$A$73,0),MATCH(BSpUECB_세액공제액!F$1,'Cal-CAPEX (정리)'!$B$68:$AF$68,0))*About!$B$93*'Cal-CAPEX (정리)'!$B$79/10,0) -> 0 | G10: =IFERROR(INDEX('Cal-CAPEX (정리)'!$B$69:$AF$73,MATCH(BSpUECB_세액공제액!$A10,'Cal-CAPEX (정리)'!$A$69:$A$73,0),MATCH(BSpUECB_세액공제액!G$1,'Cal-CAPEX (정리)'!$B$68:$AF$68,0))*About!$B$93*'Cal-CAPEX (정리)'!$B$79/10,0) -> 0 | H10: =IFERROR(INDEX('Cal-CAPEX (정리)'!$B$69:$AF$73,MATCH(BSpUECB_세액공제액!$A10,'Cal-CAPEX (정리)'!$A$69:$A$73,0),MATCH(BSpUECB_세액공제액!H$1,'Cal-CAPEX (정리)'!$B$68:$AF$68,0))*About!$B$93*'Cal-CAPEX (정리)'!$B$79/10,0) -> 0 | I10: =IFERROR(INDEX('Cal-CAPEX (정리)'!$B$69:$AF$73,MATCH(BSpUECB_세액공제액!$A10,'Cal-CAPEX (정리)'!$A$69:$A$73,0),MATCH(BSpUECB_세액공제액!I$1,'Cal-CAPEX (정리)'!$B$68:$AF$68,0))*About!$B$93*'Cal-CAPEX (정리)'!$B$79/10,0) -> 0 | ... AF10: =IFERROR(INDEX('Cal-CAPEX (정리)'!$B$69:$AF$73,MATCH(BSpUECB_세액공제액!$A10,'Cal-CAPEX (정리)'!$A$69:$A$73,0),MATCH(BSpUECB_세액공제액!AF$1,'Cal-CAPEX (정리)'!$B$68:$AF$68,0))*About!$B$93*'Cal-CAPEX (정리)'!$B$79/10,0) -> 0
A11: petroleum ($/MW) | B11: =IFERROR(INDEX('Cal-CAPEX (정리)'!$B$69:$AF$73,MATCH(BSpUECB_세액공제액!$A11,'Cal-CAPEX (정리)'!$A$69:$A$73,0),MATCH(BSpUECB_세액공제액!B$1,'Cal-CAPEX (정리)'!$B$68:$AF$68,0))*About!$B$93*'Cal-CAPEX (정리)'!$B$79/10,0) -> 0 | C11: =IFERROR(INDEX('Cal-CAPEX (정리)'!$B$69:$AF$73,MATCH(BSpUECB_세액공제액!$A11,'Cal-CAPEX (정리)'!$A$69:$A$73,0),MATCH(BSpUECB_세액공제액!C$1,'Cal-CAPEX (정리)'!$B$68:$AF$68,0))*About!$B$93*'Cal-CAPEX (정리)'!$B$79/10,0) -> 0 | D11: =IFERROR(INDEX('Cal-CAPEX (정리)'!$B$69:$AF$73,MATCH(BSpUECB_세액공제액!$A11,'Cal-CAPEX (정리)'!$A$69:$A$73,0),MATCH(BSpUECB_세액공제액!D$1,'Cal-CAPEX (정리)'!$B$68:$AF$68,0))*About!$B$93*'Cal-CAPEX (정리)'!$B$79/10,0) -> 0 | E11: =IFERROR(INDEX('Cal-CAPEX (정리)'!$B$69:$AF$73,MATCH(BSpUECB_세액공제액!$A11,'Cal-CAPEX (정리)'!$A$69:$A$73,0),MATCH(BSpUECB_세액공제액!E$1,'Cal-CAPEX (정리)'!$B$68:$AF$68,0))*About!$B$93*'Cal-CAPEX (정리)'!$B$79/10,0) -> 0 | F11: =IFERROR(INDEX('Cal-CAPEX (정리)'!$B$69:$AF$73,MATCH(BSpUECB_세액공제액!$A11,'Cal-CAPEX (정리)'!$A$69:$A$73,0),MATCH(BSpUECB_세액공제액!F$1,'Cal-CAPEX (정리)'!$B$68:$AF$68,0))*About!$B$93*'Cal-CAPEX (정리)'!$B$79/10,0) -> 0 | G11: =IFERROR(INDEX('Cal-CAPEX (정리)'!$B$69:$AF$73,MATCH(BSpUECB_세액공제액!$A11,'Cal-CAPEX (정리)'!$A$69:$A$73,0),MATCH(BSpUECB_세액공제액!G$1,'Cal-CAPEX (정리)'!$B$68:$AF$68,0))*About!$B$93*'Cal-CAPEX (정리)'!$B$79/10,0) -> 0 | H11: =IFERROR(INDEX('Cal-CAPEX (정리)'!$B$69:$AF$73,MATCH(BSpUECB_세액공제액!$A11,'Cal-CAPEX (정리)'!$A$69:$A$73,0),MATCH(BSpUECB_세액공제액!H$1,'Cal-CAPEX (정리)'!$B$68:$AF$68,0))*About!$B$93*'Cal-CAPEX (정리)'!$B$79/10,0) -> 0 | I11: =IFERROR(INDEX('Cal-CAPEX (정리)'!$B$69:$AF$73,MATCH(BSpUECB_세액공제액!$A11,'Cal-CAPEX (정리)'!$A$69:$A$73,0),MATCH(BSpUECB_세액공제액!I$1,'Cal-CAPEX (정리)'!$B$68:$AF$68,0))*About!$B$93*'Cal-CAPEX (정리)'!$B$79/10,0) -> 0 | ... AF11: =IFERROR(INDEX('Cal-CAPEX (정리)'!$B$69:$AF$73,MATCH(BSpUECB_세액공제액!$A11,'Cal-CAPEX (정리)'!$A$69:$A$73,0),MATCH(BSpUECB_세액공제액!AF$1,'Cal-CAPEX (정리)'!$B$68:$AF$68,0))*About!$B$93*'Cal-CAPEX (정리)'!$B$79/10,0) -> 0
A12: natural gas peaker ($/MW) | B12: =IFERROR(INDEX('Cal-CAPEX (정리)'!$B$69:$AF$73,MATCH(BSpUECB_세액공제액!$A12,'Cal-CAPEX (정리)'!$A$69:$A$73,0),MATCH(BSpUECB_세액공제액!B$1,'Cal-CAPEX (정리)'!$B$68:$AF$68,0))*About!$B$93*'Cal-CAPEX (정리)'!$B$79/10,0) -> 0 | C12: =IFERROR(INDEX('Cal-CAPEX (정리)'!$B$69:$AF$73,MATCH(BSpUECB_세액공제액!$A12,'Cal-CAPEX (정리)'!$A$69:$A$73,0),MATCH(BSpUECB_세액공제액!C$1,'Cal-CAPEX (정리)'!$B$68:$AF$68,0))*About!$B$93*'Cal-CAPEX (정리)'!$B$79/10,0) -> 0 | D12: =IFERROR(INDEX('Cal-CAPEX (정리)'!$B$69:$AF$73,MATCH(BSpUECB_세액공제액!$A12,'Cal-CAPEX (정리)'!$A$69:$A$73,0),MATCH(BSpUECB_세액공제액!D$1,'Cal-CAPEX (정리)'!$B$68:$AF$68,0))*About!$B$93*'Cal-CAPEX (정리)'!$B$79/10,0) -> 0 | E12: =IFERROR(INDEX('Cal-CAPEX (정리)'!$B$69:$AF$73,MATCH(BSpUECB_세액공제액!$A12,'Cal-CAPEX (정리)'!$A$69:$A$73,0),MATCH(BSpUECB_세액공제액!E$1,'Cal-CAPEX (정리)'!$B$68:$AF$68,0))*About!$B$93*'Cal-CAPEX (정리)'!$B$79/10,0) -> 0 | F12: =IFERROR(INDEX('Cal-CAPEX (정리)'!$B$69:$AF$73,MATCH(BSpUECB_세액공제액!$A12,'Cal-CAPEX (정리)'!$A$69:$A$73,0),MATCH(BSpUECB_세액공제액!F$1,'Cal-CAPEX (정리)'!$B$68:$AF$68,0))*About!$B$93*'Cal-CAPEX (정리)'!$B$79/10,0) -> 0 | G12: =IFERROR(INDEX('Cal-CAPEX (정리)'!$B$69:$AF$73,MATCH(BSpUECB_세액공제액!$A12,'Cal-CAPEX (정리)'!$A$69:$A$73,0),MATCH(BSpUECB_세액공제액!G$1,'Cal-CAPEX (정리)'!$B$68:$AF$68,0))*About!$B$93*'Cal-CAPEX (정리)'!$B$79/10,0) -> 0 | H12: =IFERROR(INDEX('Cal-CAPEX (정리)'!$B$69:$AF$73,MATCH(BSpUECB_세액공제액!$A12,'Cal-CAPEX (정리)'!$A$69:$A$73,0),MATCH(BSpUECB_세액공제액!H$1,'Cal-CAPEX (정리)'!$B$68:$AF$68,0))*About!$B$93*'Cal-CAPEX (정리)'!$B$79/10,0) -> 0 | I12: =IFERROR(INDEX('Cal-CAPEX (정리)'!$B$69:$AF$73,MATCH(BSpUECB_세액공제액!$A12,'Cal-CAPEX (정리)'!$A$69:$A$73,0),MATCH(BSpUECB_세액공제액!I$1,'Cal-CAPEX (정리)'!$B$68:$AF$68,0))*About!$B$93*'Cal-CAPEX (정리)'!$B$79/10,0) -> 0 | ... AF12: =IFERROR(INDEX('Cal-CAPEX (정리)'!$B$69:$AF$73,MATCH(BSpUECB_세액공제액!$A12,'Cal-CAPEX (정리)'!$A$69:$A$73,0),MATCH(BSpUECB_세액공제액!AF$1,'Cal-CAPEX (정리)'!$B$68:$AF$68,0))*About!$B$93*'Cal-CAPEX (정리)'!$B$79/10,0) -> 0
A13: lignite ($/MW) | B13: =IFERROR(INDEX('Cal-CAPEX (정리)'!$B$69:$AF$73,MATCH(BSpUECB_세액공제액!$A13,'Cal-CAPEX (정리)'!$A$69:$A$73,0),MATCH(BSpUECB_세액공제액!B$1,'Cal-CAPEX (정리)'!$B$68:$AF$68,0))*About!$B$93*'Cal-CAPEX (정리)'!$B$79/10,0) -> 0 | C13: =IFERROR(INDEX('Cal-CAPEX (정리)'!$B$69:$AF$73,MATCH(BSpUECB_세액공제액!$A13,'Cal-CAPEX (정리)'!$A$69:$A$73,0),MATCH(BSpUECB_세액공제액!C$1,'Cal-CAPEX (정리)'!$B$68:$AF$68,0))*About!$B$93*'Cal-CAPEX (정리)'!$B$79/10,0) -> 0 | D13: =IFERROR(INDEX('Cal-CAPEX (정리)'!$B$69:$AF$73,MATCH(BSpUECB_세액공제액!$A13,'Cal-CAPEX (정리)'!$A$69:$A$73,0),MATCH(BSpUECB_세액공제액!D$1,'Cal-CAPEX (정리)'!$B$68:$AF$68,0))*About!$B$93*'Cal-CAPEX (정리)'!$B$79/10,0) -> 0 | E13: =IFERROR(INDEX('Cal-CAPEX (정리)'!$B$69:$AF$73,MATCH(BSpUECB_세액공제액!$A13,'Cal-CAPEX (정리)'!$A$69:$A$73,0),MATCH(BSpUECB_세액공제액!E$1,'Cal-CAPEX (정리)'!$B$68:$AF$68,0))*About!$B$93*'Cal-CAPEX (정리)'!$B$79/10,0) -> 0 | F13: =IFERROR(INDEX('Cal-CAPEX (정리)'!$B$69:$AF$73,MATCH(BSpUECB_세액공제액!$A13,'Cal-CAPEX (정리)'!$A$69:$A$73,0),MATCH(BSpUECB_세액공제액!F$1,'Cal-CAPEX (정리)'!$B$68:$AF$68,0))*About!$B$93*'Cal-CAPEX (정리)'!$B$79/10,0) -> 0 | G13: =IFERROR(INDEX('Cal-CAPEX (정리)'!$B$69:$AF$73,MATCH(BSpUECB_세액공제액!$A13,'Cal-CAPEX (정리)'!$A$69:$A$73,0),MATCH(BSpUECB_세액공제액!G$1,'Cal-CAPEX (정리)'!$B$68:$AF$68,0))*About!$B$93*'Cal-CAPEX (정리)'!$B$79/10,0) -> 0 | H13: =IFERROR(INDEX('Cal-CAPEX (정리)'!$B$69:$AF$73,MATCH(BSpUECB_세액공제액!$A13,'Cal-CAPEX (정리)'!$A$69:$A$73,0),MATCH(BSpUECB_세액공제액!H$1,'Cal-CAPEX (정리)'!$B$68:$AF$68,0))*About!$B$93*'Cal-CAPEX (정리)'!$B$79/10,0) -> 0 | I13: =IFERROR(INDEX('Cal-CAPEX (정리)'!$B$69:$AF$73,MATCH(BSpUECB_세액공제액!$A13,'Cal-CAPEX (정리)'!$A$69:$A$73,0),MATCH(BSpUECB_세액공제액!I$1,'Cal-CAPEX (정리)'!$B$68:$AF$68,0))*About!$B$93*'Cal-CAPEX (정리)'!$B$79/10,0) -> 0 | ... AF13: =IFERROR(INDEX('Cal-CAPEX (정리)'!$B$69:$AF$73,MATCH(BSpUECB_세액공제액!$A13,'Cal-CAPEX (정리)'!$A$69:$A$73,0),MATCH(BSpUECB_세액공제액!AF$1,'Cal-CAPEX (정리)'!$B$68:$AF$68,0))*About!$B$93*'Cal-CAPEX (정리)'!$B$79/10,0) -> 0
A14: offshore wind ($/MW) | B14: =IFERROR(INDEX('Cal-CAPEX (정리)'!$B$69:$AF$73,MATCH(BSpUECB_세액공제액!$A14,'Cal-CAPEX (정리)'!$A$69:$A$73,0),MATCH(BSpUECB_세액공제액!B$1,'Cal-CAPEX (정리)'!$B$68:$AF$68,0))*About!$B$93*'Cal-CAPEX (정리)'!$B$79/10,0) -> 14468.06 | C14: =IFERROR(INDEX('Cal-CAPEX (정리)'!$B$69:$AF$73,MATCH(BSpUECB_세액공제액!$A14,'Cal-CAPEX (정리)'!$A$69:$A$73,0),MATCH(BSpUECB_세액공제액!C$1,'Cal-CAPEX (정리)'!$B$68:$AF$68,0))*About!$B$93*'Cal-CAPEX (정리)'!$B$79/10,0) -> 14090.174 | D14: =IFERROR(INDEX('Cal-CAPEX (정리)'!$B$69:$AF$73,MATCH(BSpUECB_세액공제액!$A14,'Cal-CAPEX (정리)'!$A$69:$A$73,0),MATCH(BSpUECB_세액공제액!D$1,'Cal-CAPEX (정리)'!$B$68:$AF$68,0))*About!$B$93*'Cal-CAPEX (정리)'!$B$79/10,0) -> 13722.158 | E14: =IFERROR(INDEX('Cal-CAPEX (정리)'!$B$69:$AF$73,MATCH(BSpUECB_세액공제액!$A14,'Cal-CAPEX (정리)'!$A$69:$A$73,0),MATCH(BSpUECB_세액공제액!E$1,'Cal-CAPEX (정리)'!$B$68:$AF$68,0))*About!$B$93*'Cal-CAPEX (정리)'!$B$79/10,0) -> 13363.754 | F14: =IFERROR(INDEX('Cal-CAPEX (정리)'!$B$69:$AF$73,MATCH(BSpUECB_세액공제액!$A14,'Cal-CAPEX (정리)'!$A$69:$A$73,0),MATCH(BSpUECB_세액공제액!F$1,'Cal-CAPEX (정리)'!$B$68:$AF$68,0))*About!$B$93*'Cal-CAPEX (정리)'!$B$79/10,0) -> 13014.711 | G14: =IFERROR(INDEX('Cal-CAPEX (정리)'!$B$69:$AF$73,MATCH(BSpUECB_세액공제액!$A14,'Cal-CAPEX (정리)'!$A$69:$A$73,0),MATCH(BSpUECB_세액공제액!G$1,'Cal-CAPEX (정리)'!$B$68:$AF$68,0))*About!$B$93*'Cal-CAPEX (정리)'!$B$79/10,0) -> 12674.784 | H14: =IFERROR(INDEX('Cal-CAPEX (정리)'!$B$69:$AF$73,MATCH(BSpUECB_세액공제액!$A14,'Cal-CAPEX (정리)'!$A$69:$A$73,0),MATCH(BSpUECB_세액공제액!H$1,'Cal-CAPEX (정리)'!$B$68:$AF$68,0))*About!$B$93*'Cal-CAPEX (정리)'!$B$79/10,0) -> 12343.736 | I14: =IFERROR(INDEX('Cal-CAPEX (정리)'!$B$69:$AF$73,MATCH(BSpUECB_세액공제액!$A14,'Cal-CAPEX (정리)'!$A$69:$A$73,0),MATCH(BSpUECB_세액공제액!I$1,'Cal-CAPEX (정리)'!$B$68:$AF$68,0))*About!$B$93*'Cal-CAPEX (정리)'!$B$79/10,0) -> 12021.335 | ... AF14: =IFERROR(INDEX('Cal-CAPEX (정리)'!$B$69:$AF$73,MATCH(BSpUECB_세액공제액!$A14,'Cal-CAPEX (정리)'!$A$69:$A$73,0),MATCH(BSpUECB_세액공제액!AF$1,'Cal-CAPEX (정리)'!$B$68:$AF$68,0))*About!$B$93*'Cal-CAPEX (정리)'!$B$79/10,0) -> 6540.2131
A15: crude oil ($/MWh) | B15: 0 | C15: =C11 -> 0 | D15: =D11 -> 0 | E15: =E11 -> 0 | F15: =F11 -> 0 | G15: =G11 -> 0 | H15: =H11 -> 0 | I15: =I11 -> 0 | J15: =J11 -> 0 | ... AF15: =AF11 -> 0
A16: heavy or residual fuel oil ($/MWh) | B16: 0 | C16: =C11 -> 0 | D16: =D11 -> 0 | E16: =E11 -> 0 | F16: =F11 -> 0 | G16: =G11 -> 0 | H16: =H11 -> 0 | I16: =I11 -> 0 | J16: =J11 -> 0 | ... AF16: =AF11 -> 0
A17: municipal solid waste ($/MWh) | B17: 0 | C17: 0 | D17: 0 | E17: 0 | F17: 0 | G17: 0 | H17: 0 | I17: 0 | J17: 0 | K17: 0 | L17: 0 | M17: 0 | N17: 0 | O17: 0 | P17: 0 | Q17: 0 | R17: 0 | S17: 0 | T17: 0 | U17: 0 | V17: 0 | W17: 0 | X17: 0 | Y17: 0 | Z17: 0 | AA17: 0 | AB17: 0 | AC17: 0 | AD17: 0 | AE17: 0 | AF17: 0
A19: Notes
A20: 세액공제의 이월공제기간이 10년인 것을 적용한 데이터
A23: [CAPEX($/MW)
A25: Year | B25: 2020 | C25: 2021 | D25: 2022 | E25: 2023 | F25: 2024 | G25: 2025 | H25: 2026 | I25: 2027 | J25: 2028 | K25: 2029 | L25: 2030 | M25: 2031 | N25: 2032 | O25: 2033 | P25: 2034 | Q25: 2035 | R25: 2036 | S25: 2037 | T25: 2038 | U25: 2039 | V25: 2040 | W25: 2041 | X25: 2042 | Y25: 2043 | Z25: 2044 | AA25: 2045 | AB25: 2046 | AC25: 2047 | AD25: 2048 | AE25: 2049 | AF25: 2050
A26: hard coal ($/MW)
A27: natural gas nonpeaker ($/MW)
A28: nuclear ($/MW)
A29: hydro ($/MW) | B29: =IFERROR(INDEX('Cal-CAPEX (정리)'!$B$69:$AF$73,MATCH(BSpUECB_세액공제액!$A29,'Cal-CAPEX (정리)'!$A$69:$A$73,0),MATCH(BSpUECB_세액공제액!B$25,'Cal-CAPEX (정리)'!$B$68:$AF$68,0))*About!$B$93,0) -> 1709289 | C29: =IFERROR(INDEX('Cal-CAPEX (정리)'!$B$69:$AF$73,MATCH(BSpUECB_세액공제액!$A29,'Cal-CAPEX (정리)'!$A$69:$A$73,0),MATCH(BSpUECB_세액공제액!C$25,'Cal-CAPEX (정리)'!$B$68:$AF$68,0))*About!$B$93,0) -> 1709289 | D29: =IFERROR(INDEX('Cal-CAPEX (정리)'!$B$69:$AF$73,MATCH(BSpUECB_세액공제액!$A29,'Cal-CAPEX (정리)'!$A$69:$A$73,0),MATCH(BSpUECB_세액공제액!D$25,'Cal-CAPEX (정리)'!$B$68:$AF$68,0))*About!$B$93,0) -> 1709289 | E29: =IFERROR(INDEX('Cal-CAPEX (정리)'!$B$69:$AF$73,MATCH(BSpUECB_세액공제액!$A29,'Cal-CAPEX (정리)'!$A$69:$A$73,0),MATCH(BSpUECB_세액공제액!E$25,'Cal-CAPEX (정리)'!$B$68:$AF$68,0))*About!$B$93,0) -> 1709289 | F29: =IFERROR(INDEX('Cal-CAPEX (정리)'!$B$69:$AF$73,MATCH(BSpUECB_세액공제액!$A29,'Cal-CAPEX (정리)'!$A$69:$A$73,0),MATCH(BSpUECB_세액공제액!F$25,'Cal-CAPEX (정리)'!$B$68:$AF$68,0))*About!$B$93,0) -> 1709289 | G29: =IFERROR(INDEX('Cal-CAPEX (정리)'!$B$69:$AF$73,MATCH(BSpUECB_세액공제액!$A29,'Cal-CAPEX (정리)'!$A$69:$A$73,0),MATCH(BSpUECB_세액공제액!G$25,'Cal-CAPEX (정리)'!$B$68:$AF$68,0))*About!$B$93,0) -> 1709289 | H29: =IFERROR(INDEX('Cal-CAPEX (정리)'!$B$69:$AF$73,MATCH(BSpUECB_세액공제액!$A29,'Cal-CAPEX (정리)'!$A$69:$A$73,0),MATCH(BSpUECB_세액공제액!H$25,'Cal-CAPEX (정리)'!$B$68:$AF$68,0))*About!$B$93,0) -> 1709289 | I29: =IFERROR(INDEX('Cal-CAPEX (정리)'!$B$69:$AF$73,MATCH(BSpUECB_세액공제액!$A29,'Cal-CAPEX (정리)'!$A$69:$A$73,0),MATCH(BSpUECB_세액공제액!I$25,'Cal-CAPEX (정리)'!$B$68:$AF$68,0))*About!$B$93,0) -> 1709289 | ... AF29: =IFERROR(INDEX('Cal-CAPEX (정리)'!$B$69:$AF$73,MATCH(BSpUECB_세액공제액!$A29,'Cal-CAPEX (정리)'!$A$69:$A$73,0),MATCH(BSpUECB_세액공제액!AF$25,'Cal-CAPEX (정리)'!$B$68:$AF$68,0))*About!$B$93,0) -> 1709289
A30: onshore wind ($/MW) | B30: =IFERROR(INDEX('Cal-CAPEX (정리)'!$B$69:$AF$73,MATCH(BSpUECB_세액공제액!$A30,'Cal-CAPEX (정리)'!$A$69:$A$73,0),MATCH(BSpUECB_세액공제액!B$25,'Cal-CAPEX (정리)'!$B$68:$AF$68,0))*About!$B$93,0) -> 2238392.7 | C30: =IFERROR(INDEX('Cal-CAPEX (정리)'!$B$69:$AF$73,MATCH(BSpUECB_세액공제액!$A30,'Cal-CAPEX (정리)'!$A$69:$A$73,0),MATCH(BSpUECB_세액공제액!C$25,'Cal-CAPEX (정리)'!$B$68:$AF$68,0))*About!$B$93,0) -> 2202452.8 | D30: =IFERROR(INDEX('Cal-CAPEX (정리)'!$B$69:$AF$73,MATCH(BSpUECB_세액공제액!$A30,'Cal-CAPEX (정리)'!$A$69:$A$73,0),MATCH(BSpUECB_세액공제액!D$25,'Cal-CAPEX (정리)'!$B$68:$AF$68,0))*About!$B$93,0) -> 2166512.8 | E30: =IFERROR(INDEX('Cal-CAPEX (정리)'!$B$69:$AF$73,MATCH(BSpUECB_세액공제액!$A30,'Cal-CAPEX (정리)'!$A$69:$A$73,0),MATCH(BSpUECB_세액공제액!E$25,'Cal-CAPEX (정리)'!$B$68:$AF$68,0))*About!$B$93,0) -> 2130572.9 | F30: =IFERROR(INDEX('Cal-CAPEX (정리)'!$B$69:$AF$73,MATCH(BSpUECB_세액공제액!$A30,'Cal-CAPEX (정리)'!$A$69:$A$73,0),MATCH(BSpUECB_세액공제액!F$25,'Cal-CAPEX (정리)'!$B$68:$AF$68,0))*About!$B$93,0) -> 2094633 | G30: =IFERROR(INDEX('Cal-CAPEX (정리)'!$B$69:$AF$73,MATCH(BSpUECB_세액공제액!$A30,'Cal-CAPEX (정리)'!$A$69:$A$73,0),MATCH(BSpUECB_세액공제액!G$25,'Cal-CAPEX (정리)'!$B$68:$AF$68,0))*About!$B$93,0) -> 2058693 | H30: =IFERROR(INDEX('Cal-CAPEX (정리)'!$B$69:$AF$73,MATCH(BSpUECB_세액공제액!$A30,'Cal-CAPEX (정리)'!$A$69:$A$73,0),MATCH(BSpUECB_세액공제액!H$25,'Cal-CAPEX (정리)'!$B$68:$AF$68,0))*About!$B$93,0) -> 2037839 | I30: =IFERROR(INDEX('Cal-CAPEX (정리)'!$B$69:$AF$73,MATCH(BSpUECB_세액공제액!$A30,'Cal-CAPEX (정리)'!$A$69:$A$73,0),MATCH(BSpUECB_세액공제액!I$25,'Cal-CAPEX (정리)'!$B$68:$AF$68,0))*About!$B$93,0) -> 2016984.9 | ... AF30: =IFERROR(INDEX('Cal-CAPEX (정리)'!$B$69:$AF$73,MATCH(BSpUECB_세액공제액!$A30,'Cal-CAPEX (정리)'!$A$69:$A$73,0),MATCH(BSpUECB_세액공제액!AF$25,'Cal-CAPEX (정리)'!$B$68:$AF$68,0))*About!$B$93,0) -> 1529108
A31: solar PV ($/MW) | B31: =IFERROR(INDEX('Cal-CAPEX (정리)'!$B$69:$AF$73,MATCH(BSpUECB_세액공제액!$A31,'Cal-CAPEX (정리)'!$A$69:$A$73,0),MATCH(BSpUECB_세액공제액!B$25,'Cal-CAPEX (정리)'!$B$68:$AF$68,0))*About!$B$93,0) -> 1342911.4 | C31: =IFERROR(INDEX('Cal-CAPEX (정리)'!$B$69:$AF$73,MATCH(BSpUECB_세액공제액!$A31,'Cal-CAPEX (정리)'!$A$69:$A$73,0),MATCH(BSpUECB_세액공제액!C$25,'Cal-CAPEX (정리)'!$B$68:$AF$68,0))*About!$B$93,0) -> 1292435.8 | D31: =IFERROR(INDEX('Cal-CAPEX (정리)'!$B$69:$AF$73,MATCH(BSpUECB_세액공제액!$A31,'Cal-CAPEX (정리)'!$A$69:$A$73,0),MATCH(BSpUECB_세액공제액!D$25,'Cal-CAPEX (정리)'!$B$68:$AF$68,0))*About!$B$93,0) -> 1241960.1 | E31: =IFERROR(INDEX('Cal-CAPEX (정리)'!$B$69:$AF$73,MATCH(BSpUECB_세액공제액!$A31,'Cal-CAPEX (정리)'!$A$69:$A$73,0),MATCH(BSpUECB_세액공제액!E$25,'Cal-CAPEX (정리)'!$B$68:$AF$68,0))*About!$B$93,0) -> 1191484.5 | F31: =IFERROR(INDEX('Cal-CAPEX (정리)'!$B$69:$AF$73,MATCH(BSpUECB_세액공제액!$A31,'Cal-CAPEX (정리)'!$A$69:$A$73,0),MATCH(BSpUECB_세액공제액!F$25,'Cal-CAPEX (정리)'!$B$68:$AF$68,0))*About!$B$93,0) -> 1141008.8 | G31: =IFERROR(INDEX('Cal-CAPEX (정리)'!$B$69:$AF$73,MATCH(BSpUECB_세액공제액!$A31,'Cal-CAPEX (정리)'!$A$69:$A$73,0),MATCH(BSpUECB_세액공제액!G$25,'Cal-CAPEX (정리)'!$B$68:$AF$68,0))*About!$B$93,0) -> 1090533.2 | H31: =IFERROR(INDEX('Cal-CAPEX (정리)'!$B$69:$AF$73,MATCH(BSpUECB_세액공제액!$A31,'Cal-CAPEX (정리)'!$A$69:$A$73,0),MATCH(BSpUECB_세액공제액!H$25,'Cal-CAPEX (정리)'!$B$68:$AF$68,0))*About!$B$93,0) -> 1059686.9 | I31: =IFERROR(INDEX('Cal-CAPEX (정리)'!$B$69:$AF$73,MATCH(BSpUECB_세액공제액!$A31,'Cal-CAPEX (정리)'!$A$69:$A$73,0),MATCH(BSpUECB_세액공제액!I$25,'Cal-CAPEX (정리)'!$B$68:$AF$68,0))*About!$B$93,0) -> 1028840.7 | ... AF31: =IFERROR(INDEX('Cal-CAPEX (정리)'!$B$69:$AF$73,MATCH(BSpUECB_세액공제액!$A31,'Cal-CAPEX (정리)'!$A$69:$A$73,0),MATCH(BSpUECB_세액공제액!AF$25,'Cal-CAPEX (정리)'!$B$68:$AF$68,0))*About!$B$93,0) -> 498261.49
A32: solar thermal ($/MW) | B32: =IFERROR(INDEX('Cal-CAPEX (정리)'!$B$69:$AF$73,MATCH(BSpUECB_세액공제액!$A32,'Cal-CAPEX (정리)'!$A$69:$A$73,0),MATCH(BSpUECB_세액공제액!B$25,'Cal-CAPEX (정리)'!$B$68:$AF$68,0))*About!$B$93,0) -> 0 | C32: =IFERROR(INDEX('Cal-CAPEX (정리)'!$B$69:$AF$73,MATCH(BSpUECB_세액공제액!$A32,'Cal-CAPEX (정리)'!$A$69:$A$73,0),MATCH(BSpUECB_세액공제액!C$25,'Cal-CAPEX (정리)'!$B$68:$AF$68,0))*About!$B$93,0) -> 0 | D32: =IFERROR(INDEX('Cal-CAPEX (정리)'!$B$69:$AF$73,MATCH(BSpUECB_세액공제액!$A32,'Cal-CAPEX (정리)'!$A$69:$A$73,0),MATCH(BSpUECB_세액공제액!D$25,'Cal-CAPEX (정리)'!$B$68:$AF$68,0))*About!$B$93,0) -> 0 | E32: =IFERROR(INDEX('Cal-CAPEX (정리)'!$B$69:$AF$73,MATCH(BSpUECB_세액공제액!$A32,'Cal-CAPEX (정리)'!$A$69:$A$73,0),MATCH(BSpUECB_세액공제액!E$25,'Cal-CAPEX (정리)'!$B$68:$AF$68,0))*About!$B$93,0) -> 0 | F32: =IFERROR(INDEX('Cal-CAPEX (정리)'!$B$69:$AF$73,MATCH(BSpUECB_세액공제액!$A32,'Cal-CAPEX (정리)'!$A$69:$A$73,0),MATCH(BSpUECB_세액공제액!F$25,'Cal-CAPEX (정리)'!$B$68:$AF$68,0))*About!$B$93,0) -> 0 | G32: =IFERROR(INDEX('Cal-CAPEX (정리)'!$B$69:$AF$73,MATCH(BSpUECB_세액공제액!$A32,'Cal-CAPEX (정리)'!$A$69:$A$73,0),MATCH(BSpUECB_세액공제액!G$25,'Cal-CAPEX (정리)'!$B$68:$AF$68,0))*About!$B$93,0) -> 0 | H32: =IFERROR(INDEX('Cal-CAPEX (정리)'!$B$69:$AF$73,MATCH(BSpUECB_세액공제액!$A32,'Cal-CAPEX (정리)'!$A$69:$A$73,0),MATCH(BSpUECB_세액공제액!H$25,'Cal-CAPEX (정리)'!$B$68:$AF$68,0))*About!$B$93,0) -> 0 | I32: =IFERROR(INDEX('Cal-CAPEX (정리)'!$B$69:$AF$73,MATCH(BSpUECB_세액공제액!$A32,'Cal-CAPEX (정리)'!$A$69:$A$73,0),MATCH(BSpUECB_세액공제액!I$25,'Cal-CAPEX (정리)'!$B$68:$AF$68,0))*About!$B$93,0) -> 0 | ... AF32: =IFERROR(INDEX('Cal-CAPEX (정리)'!$B$69:$AF$73,MATCH(BSpUECB_세액공제액!$A32,'Cal-CAPEX (정리)'!$A$69:$A$73,0),MATCH(BSpUECB_세액공제액!AF$25,'Cal-CAPEX (정리)'!$B$68:$AF$68,0))*About!$B$93,0) -> 0
A33: biomass ($/MW) | B33: =IFERROR(INDEX('Cal-CAPEX (정리)'!$B$69:$AF$73,MATCH(BSpUECB_세액공제액!$A33,'Cal-CAPEX (정리)'!$A$69:$A$73,0),MATCH(BSpUECB_세액공제액!B$25,'Cal-CAPEX (정리)'!$B$68:$AF$68,0))*About!$B$93,0) -> 2289343.9 | C33: =IFERROR(INDEX('Cal-CAPEX (정리)'!$B$69:$AF$73,MATCH(BSpUECB_세액공제액!$A33,'Cal-CAPEX (정리)'!$A$69:$A$73,0),MATCH(BSpUECB_세액공제액!C$25,'Cal-CAPEX (정리)'!$B$68:$AF$68,0))*About!$B$93,0) -> 2289343.9 | D33: =IFERROR(INDEX('Cal-CAPEX (정리)'!$B$69:$AF$73,MATCH(BSpUECB_세액공제액!$A33,'Cal-CAPEX (정리)'!$A$69:$A$73,0),MATCH(BSpUECB_세액공제액!D$25,'Cal-CAPEX (정리)'!$B$68:$AF$68,0))*About!$B$93,0) -> 2289343.9 | E33: =IFERROR(INDEX('Cal-CAPEX (정리)'!$B$69:$AF$73,MATCH(BSpUECB_세액공제액!$A33,'Cal-CAPEX (정리)'!$A$69:$A$73,0),MATCH(BSpUECB_세액공제액!E$25,'Cal-CAPEX (정리)'!$B$68:$AF$68,0))*About!$B$93,0) -> 2289343.9 | F33: =IFERROR(INDEX('Cal-CAPEX (정리)'!$B$69:$AF$73,MATCH(BSpUECB_세액공제액!$A33,'Cal-CAPEX (정리)'!$A$69:$A$73,0),MATCH(BSpUECB_세액공제액!F$25,'Cal-CAPEX (정리)'!$B$68:$AF$68,0))*About!$B$93,0) -> 2289343.9 | G33: =IFERROR(INDEX('Cal-CAPEX (정리)'!$B$69:$AF$73,MATCH(BSpUECB_세액공제액!$A33,'Cal-CAPEX (정리)'!$A$69:$A$73,0),MATCH(BSpUECB_세액공제액!G$25,'Cal-CAPEX (정리)'!$B$68:$AF$68,0))*About!$B$93,0) -> 2289343.9 | H33: =IFERROR(INDEX('Cal-CAPEX (정리)'!$B$69:$AF$73,MATCH(BSpUECB_세액공제액!$A33,'Cal-CAPEX (정리)'!$A$69:$A$73,0),MATCH(BSpUECB_세액공제액!H$25,'Cal-CAPEX (정리)'!$B$68:$AF$68,0))*About!$B$93,0) -> 2289343.9 | I33: =IFERROR(INDEX('Cal-CAPEX (정리)'!$B$69:$AF$73,MATCH(BSpUECB_세액공제액!$A33,'Cal-CAPEX (정리)'!$A$69:$A$73,0),MATCH(BSpUECB_세액공제액!I$25,'Cal-CAPEX (정리)'!$B$68:$AF$68,0))*About!$B$93,0) -> 2289343.9 | ... AF33: =IFERROR(INDEX('Cal-CAPEX (정리)'!$B$69:$AF$73,MATCH(BSpUECB_세액공제액!$A33,'Cal-CAPEX (정리)'!$A$69:$A$73,0),MATCH(BSpUECB_세액공제액!AF$25,'Cal-CAPEX (정리)'!$B$68:$AF$68,0))*About!$B$93,0) -> 2289343.9
A34: geothermal ($/MW) | B34: =IFERROR(INDEX('Cal-CAPEX (정리)'!$B$69:$AF$73,MATCH(BSpUECB_세액공제액!$A34,'Cal-CAPEX (정리)'!$A$69:$A$73,0),MATCH(BSpUECB_세액공제액!B$25,'Cal-CAPEX (정리)'!$B$68:$AF$68,0))*About!$B$93,0) -> 0 | C34: =IFERROR(INDEX('Cal-CAPEX (정리)'!$B$69:$AF$73,MATCH(BSpUECB_세액공제액!$A34,'Cal-CAPEX (정리)'!$A$69:$A$73,0),MATCH(BSpUECB_세액공제액!C$25,'Cal-CAPEX (정리)'!$B$68:$AF$68,0))*About!$B$93,0) -> 0 | D34: =IFERROR(INDEX('Cal-CAPEX (정리)'!$B$69:$AF$73,MATCH(BSpUECB_세액공제액!$A34,'Cal-CAPEX (정리)'!$A$69:$A$73,0),MATCH(BSpUECB_세액공제액!D$25,'Cal-CAPEX (정리)'!$B$68:$AF$68,0))*About!$B$93,0) -> 0 | E34: =IFERROR(INDEX('Cal-CAPEX (정리)'!$B$69:$AF$73,MATCH(BSpUECB_세액공제액!$A34,'Cal-CAPEX (정리)'!$A$69:$A$73,0),MATCH(BSpUECB_세액공제액!E$25,'Cal-CAPEX (정리)'!$B$68:$AF$68,0))*About!$B$93,0) -> 0 | F34: =IFERROR(INDEX('Cal-CAPEX (정리)'!$B$69:$AF$73,MATCH(BSpUECB_세액공제액!$A34,'Cal-CAPEX (정리)'!$A$69:$A$73,0),MATCH(BSpUECB_세액공제액!F$25,'Cal-CAPEX (정리)'!$B$68:$AF$68,0))*About!$B$93,0) -> 0 | G34: =IFERROR(INDEX('Cal-CAPEX (정리)'!$B$69:$AF$73,MATCH(BSpUECB_세액공제액!$A34,'Cal-CAPEX (정리)'!$A$69:$A$73,0),MATCH(BSpUECB_세액공제액!G$25,'Cal-CAPEX (정리)'!$B$68:$AF$68,0))*About!$B$93,0) -> 0 | H34: =IFERROR(INDEX('Cal-CAPEX (정리)'!$B$69:$AF$73,MATCH(BSpUECB_세액공제액!$A34,'Cal-CAPEX (정리)'!$A$69:$A$73,0),MATCH(BSpUECB_세액공제액!H$25,'Cal-CAPEX (정리)'!$B$68:$AF$68,0))*About!$B$93,0) -> 0 | I34: =IFERROR(INDEX('Cal-CAPEX (정리)'!$B$69:$AF$73,MATCH(BSpUECB_세액공제액!$A34,'Cal-CAPEX (정리)'!$A$69:$A$73,0),MATCH(BSpUECB_세액공제액!I$25,'Cal-CAPEX (정리)'!$B$68:$AF$68,0))*About!$B$93,0) -> 0 | ... AF34: =IFERROR(INDEX('Cal-CAPEX (정리)'!$B$69:$AF$73,MATCH(BSpUECB_세액공제액!$A34,'Cal-CAPEX (정리)'!$A$69:$A$73,0),MATCH(BSpUECB_세액공제액!AF$25,'Cal-CAPEX (정리)'!$B$68:$AF$68,0))*About!$B$93,0) -> 0
A35: petroleum ($/MW) | B35: =IFERROR(INDEX('Cal-CAPEX (정리)'!$B$69:$AF$73,MATCH(BSpUECB_세액공제액!$A35,'Cal-CAPEX (정리)'!$A$69:$A$73,0),MATCH(BSpUECB_세액공제액!B$25,'Cal-CAPEX (정리)'!$B$68:$AF$68,0))*About!$B$93,0) -> 0 | C35: =IFERROR(INDEX('Cal-CAPEX (정리)'!$B$69:$AF$73,MATCH(BSpUECB_세액공제액!$A35,'Cal-CAPEX (정리)'!$A$69:$A$73,0),MATCH(BSpUECB_세액공제액!C$25,'Cal-CAPEX (정리)'!$B$68:$AF$68,0))*About!$B$93,0) -> 0 | D35: =IFERROR(INDEX('Cal-CAPEX (정리)'!$B$69:$AF$73,MATCH(BSpUECB_세액공제액!$A35,'Cal-CAPEX (정리)'!$A$69:$A$73,0),MATCH(BSpUECB_세액공제액!D$25,'Cal-CAPEX (정리)'!$B$68:$AF$68,0))*About!$B$93,0) -> 0 | E35: =IFERROR(INDEX('Cal-CAPEX (정리)'!$B$69:$AF$73,MATCH(BSpUECB_세액공제액!$A35,'Cal-CAPEX (정리)'!$A$69:$A$73,0),MATCH(BSpUECB_세액공제액!E$25,'Cal-CAPEX (정리)'!$B$68:$AF$68,0))*About!$B$93,0) -> 0 | F35: =IFERROR(INDEX('Cal-CAPEX (정리)'!$B$69:$AF$73,MATCH(BSpUECB_세액공제액!$A35,'Cal-CAPEX (정리)'!$A$69:$A$73,0),MATCH(BSpUECB_세액공제액!F$25,'Cal-CAPEX (정리)'!$B$68:$AF$68,0))*About!$B$93,0) -> 0 | G35: =IFERROR(INDEX('Cal-CAPEX (정리)'!$B$69:$AF$73,MATCH(BSpUECB_세액공제액!$A35,'Cal-CAPEX (정리)'!$A$69:$A$73,0),MATCH(BSpUECB_세액공제액!G$25,'Cal-CAPEX (정리)'!$B$68:$AF$68,0))*About!$B$93,0) -> 0 | H35: =IFERROR(INDEX('Cal-CAPEX (정리)'!$B$69:$AF$73,MATCH(BSpUECB_세액공제액!$A35,'Cal-CAPEX (정리)'!$A$69:$A$73,0),MATCH(BSpUECB_세액공제액!H$25,'Cal-CAPEX (정리)'!$B$68:$AF$68,0))*About!$B$93,0) -> 0 | I35: =IFERROR(INDEX('Cal-CAPEX (정리)'!$B$69:$AF$73,MATCH(BSpUECB_세액공제액!$A35,'Cal-CAPEX (정리)'!$A$69:$A$73,0),MATCH(BSpUECB_세액공제액!I$25,'Cal-CAPEX (정리)'!$B$68:$AF$68,0))*About!$B$93,0) -> 0 | ... AF35: =IFERROR(INDEX('Cal-CAPEX (정리)'!$B$69:$AF$73,MATCH(BSpUECB_세액공제액!$A35,'Cal-CAPEX (정리)'!$A$69:$A$73,0),MATCH(BSpUECB_세액공제액!AF$25,'Cal-CAPEX (정리)'!$B$68:$AF$68,0))*About!$B$93,0) -> 0
A36: natural gas peaker ($/MW) | B36: =IFERROR(INDEX('Cal-CAPEX (정리)'!$B$69:$AF$73,MATCH(BSpUECB_세액공제액!$A36,'Cal-CAPEX (정리)'!$A$69:$A$73,0),MATCH(BSpUECB_세액공제액!B$25,'Cal-CAPEX (정리)'!$B$68:$AF$68,0))*About!$B$93,0) -> 0 | C36: =IFERROR(INDEX('Cal-CAPEX (정리)'!$B$69:$AF$73,MATCH(BSpUECB_세액공제액!$A36,'Cal-CAPEX (정리)'!$A$69:$A$73,0),MATCH(BSpUECB_세액공제액!C$25,'Cal-CAPEX (정리)'!$B$68:$AF$68,0))*About!$B$93,0) -> 0 | D36: =IFERROR(INDEX('Cal-CAPEX (정리)'!$B$69:$AF$73,MATCH(BSpUECB_세액공제액!$A36,'Cal-CAPEX (정리)'!$A$69:$A$73,0),MATCH(BSpUECB_세액공제액!D$25,'Cal-CAPEX (정리)'!$B$68:$AF$68,0))*About!$B$93,0) -> 0 | E36: =IFERROR(INDEX('Cal-CAPEX (정리)'!$B$69:$AF$73,MATCH(BSpUECB_세액공제액!$A36,'Cal-CAPEX (정리)'!$A$69:$A$73,0),MATCH(BSpUECB_세액공제액!E$25,'Cal-CAPEX (정리)'!$B$68:$AF$68,0))*About!$B$93,0) -> 0 | F36: =IFERROR(INDEX('Cal-CAPEX (정리)'!$B$69:$AF$73,MATCH(BSpUECB_세액공제액!$A36,'Cal-CAPEX (정리)'!$A$69:$A$73,0),MATCH(BSpUECB_세액공제액!F$25,'Cal-CAPEX (정리)'!$B$68:$AF$68,0))*About!$B$93,0) -> 0 | G36: =IFERROR(INDEX('Cal-CAPEX (정리)'!$B$69:$AF$73,MATCH(BSpUECB_세액공제액!$A36,'Cal-CAPEX (정리)'!$A$69:$A$73,0),MATCH(BSpUECB_세액공제액!G$25,'Cal-CAPEX (정리)'!$B$68:$AF$68,0))*About!$B$93,0) -> 0 | H36: =IFERROR(INDEX('Cal-CAPEX (정리)'!$B$69:$AF$73,MATCH(BSpUECB_세액공제액!$A36,'Cal-CAPEX (정리)'!$A$69:$A$73,0),MATCH(BSpUECB_세액공제액!H$25,'Cal-CAPEX (정리)'!$B$68:$AF$68,0))*About!$B$93,0) -> 0 | I36: =IFERROR(INDEX('Cal-CAPEX (정리)'!$B$69:$AF$73,MATCH(BSpUECB_세액공제액!$A36,'Cal-CAPEX (정리)'!$A$69:$A$73,0),MATCH(BSpUECB_세액공제액!I$25,'Cal-CAPEX (정리)'!$B$68:$AF$68,0))*About!$B$93,0) -> 0 | ... AF36: =IFERROR(INDEX('Cal-CAPEX (정리)'!$B$69:$AF$73,MATCH(BSpUECB_세액공제액!$A36,'Cal-CAPEX (정리)'!$A$69:$A$73,0),MATCH(BSpUECB_세액공제액!AF$25,'Cal-CAPEX (정리)'!$B$68:$AF$68,0))*About!$B$93,0) -> 0
A37: lignite ($/MW) | B37: =IFERROR(INDEX('Cal-CAPEX (정리)'!$B$69:$AF$73,MATCH(BSpUECB_세액공제액!$A37,'Cal-CAPEX (정리)'!$A$69:$A$73,0),MATCH(BSpUECB_세액공제액!B$25,'Cal-CAPEX (정리)'!$B$68:$AF$68,0))*About!$B$93,0) -> 0 | C37: =IFERROR(INDEX('Cal-CAPEX (정리)'!$B$69:$AF$73,MATCH(BSpUECB_세액공제액!$A37,'Cal-CAPEX (정리)'!$A$69:$A$73,0),MATCH(BSpUECB_세액공제액!C$25,'Cal-CAPEX (정리)'!$B$68:$AF$68,0))*About!$B$93,0) -> 0 | D37: =IFERROR(INDEX('Cal-CAPEX (정리)'!$B$69:$AF$73,MATCH(BSpUECB_세액공제액!$A37,'Cal-CAPEX (정리)'!$A$69:$A$73,0),MATCH(BSpUECB_세액공제액!D$25,'Cal-CAPEX (정리)'!$B$68:$AF$68,0))*About!$B$93,0) -> 0 | E37: =IFERROR(INDEX('Cal-CAPEX (정리)'!$B$69:$AF$73,MATCH(BSpUECB_세액공제액!$A37,'Cal-CAPEX (정리)'!$A$69:$A$73,0),MATCH(BSpUECB_세액공제액!E$25,'Cal-CAPEX (정리)'!$B$68:$AF$68,0))*About!$B$93,0) -> 0 | F37: =IFERROR(INDEX('Cal-CAPEX (정리)'!$B$69:$AF$73,MATCH(BSpUECB_세액공제액!$A37,'Cal-CAPEX (정리)'!$A$69:$A$73,0),MATCH(BSpUECB_세액공제액!F$25,'Cal-CAPEX (정리)'!$B$68:$AF$68,0))*About!$B$93,0) -> 0 | G37: =IFERROR(INDEX('Cal-CAPEX (정리)'!$B$69:$AF$73,MATCH(BSpUECB_세액공제액!$A37,'Cal-CAPEX (정리)'!$A$69:$A$73,0),MATCH(BSpUECB_세액공제액!G$25,'Cal-CAPEX (정리)'!$B$68:$AF$68,0))*About!$B$93,0) -> 0 | H37: =IFERROR(INDEX('Cal-CAPEX (정리)'!$B$69:$AF$73,MATCH(BSpUECB_세액공제액!$A37,'Cal-CAPEX (정리)'!$A$69:$A$73,0),MATCH(BSpUECB_세액공제액!H$25,'Cal-CAPEX (정리)'!$B$68:$AF$68,0))*About!$B$93,0) -> 0 | I37: =IFERROR(INDEX('Cal-CAPEX (정리)'!$B$69:$AF$73,MATCH(BSpUECB_세액공제액!$A37,'Cal-CAPEX (정리)'!$A$69:$A$73,0),MATCH(BSpUECB_세액공제액!I$25,'Cal-CAPEX (정리)'!$B$68:$AF$68,0))*About!$B$93,0) -> 0 | ... AF37: =IFERROR(INDEX('Cal-CAPEX (정리)'!$B$69:$AF$73,MATCH(BSpUECB_세액공제액!$A37,'Cal-CAPEX (정리)'!$A$69:$A$73,0),MATCH(BSpUECB_세액공제액!AF$25,'Cal-CAPEX (정리)'!$B$68:$AF$68,0))*About!$B$93,0) -> 0
A38: offshore wind ($/MW) | B38: =IFERROR(INDEX('Cal-CAPEX (정리)'!$B$69:$AF$73,MATCH(BSpUECB_세액공제액!$A38,'Cal-CAPEX (정리)'!$A$69:$A$73,0),MATCH(BSpUECB_세액공제액!B$25,'Cal-CAPEX (정리)'!$B$68:$AF$68,0))*About!$B$93,0) -> 4822686.8 | C38: =IFERROR(INDEX('Cal-CAPEX (정리)'!$B$69:$AF$73,MATCH(BSpUECB_세액공제액!$A38,'Cal-CAPEX (정리)'!$A$69:$A$73,0),MATCH(BSpUECB_세액공제액!C$25,'Cal-CAPEX (정리)'!$B$68:$AF$68,0))*About!$B$93,0) -> 4696724.8 | D38: =IFERROR(INDEX('Cal-CAPEX (정리)'!$B$69:$AF$73,MATCH(BSpUECB_세액공제액!$A38,'Cal-CAPEX (정리)'!$A$69:$A$73,0),MATCH(BSpUECB_세액공제액!D$25,'Cal-CAPEX (정리)'!$B$68:$AF$68,0))*About!$B$93,0) -> 4574052.7 | E38: =IFERROR(INDEX('Cal-CAPEX (정리)'!$B$69:$AF$73,MATCH(BSpUECB_세액공제액!$A38,'Cal-CAPEX (정리)'!$A$69:$A$73,0),MATCH(BSpUECB_세액공제액!E$25,'Cal-CAPEX (정리)'!$B$68:$AF$68,0))*About!$B$93,0) -> 4454584.6 | F38: =IFERROR(INDEX('Cal-CAPEX (정리)'!$B$69:$AF$73,MATCH(BSpUECB_세액공제액!$A38,'Cal-CAPEX (정리)'!$A$69:$A$73,0),MATCH(BSpUECB_세액공제액!F$25,'Cal-CAPEX (정리)'!$B$68:$AF$68,0))*About!$B$93,0) -> 4338236.9 | G38: =IFERROR(INDEX('Cal-CAPEX (정리)'!$B$69:$AF$73,MATCH(BSpUECB_세액공제액!$A38,'Cal-CAPEX (정리)'!$A$69:$A$73,0),MATCH(BSpUECB_세액공제액!G$25,'Cal-CAPEX (정리)'!$B$68:$AF$68,0))*About!$B$93,0) -> 4224928.1 | H38: =IFERROR(INDEX('Cal-CAPEX (정리)'!$B$69:$AF$73,MATCH(BSpUECB_세액공제액!$A38,'Cal-CAPEX (정리)'!$A$69:$A$73,0),MATCH(BSpUECB_세액공제액!H$25,'Cal-CAPEX (정리)'!$B$68:$AF$68,0))*About!$B$93,0) -> 4114578.7 | I38: =IFERROR(INDEX('Cal-CAPEX (정리)'!$B$69:$AF$73,MATCH(BSpUECB_세액공제액!$A38,'Cal-CAPEX (정리)'!$A$69:$A$73,0),MATCH(BSpUECB_세액공제액!I$25,'Cal-CAPEX (정리)'!$B$68:$AF$68,0))*About!$B$93,0) -> 4007111.5 | ... AF38: =IFERROR(INDEX('Cal-CAPEX (정리)'!$B$69:$AF$73,MATCH(BSpUECB_세액공제액!$A38,'Cal-CAPEX (정리)'!$A$69:$A$73,0),MATCH(BSpUECB_세액공제액!AF$25,'Cal-CAPEX (정리)'!$B$68:$AF$68,0))*About!$B$93,0) -> 2180071
A39: crude oil ($/MWh)
A40: heavy or residual fuel oil ($/MWh)
A41: municipal solid waste ($/MWh)
A44: [보조금 비율(BS-BSpUECB]
A46: Year | B46: 2020 | C46: 2021 | D46: 2022 | E46: 2023 | F46: 2024 | G46: 2025 | H46: 2026 | I46: 2027 | J46: 2028 | K46: 2029 | L46: 2030 | M46: 2031 | N46: 2032 | O46: 2033 | P46: 2034 | Q46: 2035 | R46: 2036 | S46: 2037 | T46: 2038 | U46: 2039 | V46: 2040 | W46: 2041 | X46: 2042 | Y46: 2043 | Z46: 2044 | AA46: 2045 | AB46: 2046 | AC46: 2047 | AD46: 2048 | AE46: 2049 | AF46: 2050
A47: hard coal ($/MW) | B47: =IFERROR(SUM(B2:K2)/B26,0) -> 0 | C47: =IFERROR(SUM(C2:L2)/C26,0) -> 0 | D47: =IFERROR(SUM(D2:M2)/D26,0) -> 0 | E47: =IFERROR(SUM(E2:N2)/E26,0) -> 0 | F47: =IFERROR(SUM(F2:O2)/F26,0) -> 0 | G47: =IFERROR(SUM(G2:P2)/G26,0) -> 0 | H47: =IFERROR(SUM(H2:Q2)/H26,0) -> 0 | I47: =IFERROR(SUM(I2:R2)/I26,0) -> 0 | ... W47: =IFERROR(SUM(W2:AF2)/W26,0) -> 0 | X47: =W47 -> 0 | Y47: =X47 -> 0 | Z47: =Y47 -> 0 | AA47: =Z47 -> 0 | AB47: =AA47 -> 0 | AC47: =AB47 -> 0 | AD47: =AC47 -> 0 | AE47: =AD47 -> 0 | AF47: =AE47 -> 0
A48: natural gas nonpeaker ($/MW) | B48: =IFERROR(SUM(B3:K3)/B27,0) -> 0 | C48: =IFERROR(SUM(C3:L3)/C27,0) -> 0 | D48: =IFERROR(SUM(D3:M3)/D27,0) -> 0 | E48: =IFERROR(SUM(E3:N3)/E27,0) -> 0 | F48: =IFERROR(SUM(F3:O3)/F27,0) -> 0 | G48: =IFERROR(SUM(G3:P3)/G27,0) -> 0 | H48: =IFERROR(SUM(H3:Q3)/H27,0) -> 0 | I48: =IFERROR(SUM(I3:R3)/I27,0) -> 0 | ... W48: =IFERROR(SUM(W3:AF3)/W27,0) -> 0 | X48: =W48 -> 0 | Y48: =X48 -> 0 | Z48: =Y48 -> 0 | AA48: =Z48 -> 0 | AB48: =AA48 -> 0 | AC48: =AB48 -> 0 | AD48: =AC48 -> 0 | AE48: =AD48 -> 0 | AF48: =AE48 -> 0
A49: nuclear ($/MW) | B49: =IFERROR(SUM(B4:K4)/B28,0) -> 0 | C49: =IFERROR(SUM(C4:L4)/C28,0) -> 0 | D49: =IFERROR(SUM(D4:M4)/D28,0) -> 0 | E49: =IFERROR(SUM(E4:N4)/E28,0) -> 0 | F49: =IFERROR(SUM(F4:O4)/F28,0) -> 0 | G49: =IFERROR(SUM(G4:P4)/G28,0) -> 0 | H49: =IFERROR(SUM(H4:Q4)/H28,0) -> 0 | I49: =IFERROR(SUM(I4:R4)/I28,0) -> 0 | ... W49: =IFERROR(SUM(W4:AF4)/W28,0) -> 0 | X49: =W49 -> 0 | Y49: =X49 -> 0 | Z49: =Y49 -> 0 | AA49: =Z49 -> 0 | AB49: =AA49 -> 0 | AC49: =AB49 -> 0 | AD49: =AC49 -> 0 | AE49: =AD49 -> 0 | AF49: =AE49 -> 0
A50: hydro ($/MW) | B50: =IFERROR(SUM(B5:K5)/B29,0) -> 0.03 | C50: =IFERROR(SUM(C5:L5)/C29,0) -> 0.03 | D50: =IFERROR(SUM(D5:M5)/D29,0) -> 0.03 | E50: =IFERROR(SUM(E5:N5)/E29,0) -> 0.03 | F50: =IFERROR(SUM(F5:O5)/F29,0) -> 0.03 | G50: =IFERROR(SUM(G5:P5)/G29,0) -> 0.03 | H50: =IFERROR(SUM(H5:Q5)/H29,0) -> 0.03 | I50: =IFERROR(SUM(I5:R5)/I29,0) -> 0.03 | ... W50: =IFERROR(SUM(W5:AF5)/W29,0) -> 0.03 | X50: =W50 -> 0.03 | Y50: =X50 -> 0.03 | Z50: =Y50 -> 0.03 | AA50: =Z50 -> 0.03 | AB50: =AA50 -> 0.03 | AC50: =AB50 -> 0.03 | AD50: =AC50 -> 0.03 | AE50: =AD50 -> 0.03 | AF50: =AE50 -> 0.03
A51: onshore wind ($/MW) | B51: =IFERROR(SUM(B6:K6)/B30,0) -> 0.02803461 | C51: =IFERROR(SUM(C6:L6)/C30,0) -> 0.028105282 | D51: =IFERROR(SUM(D6:M6)/D30,0) -> 0.028195061 | E51: =IFERROR(SUM(E6:N6)/E30,0) -> 0.028305322 | F51: =IFERROR(SUM(F6:O6)/F30,0) -> 0.028437531 | G51: =IFERROR(SUM(G6:P6)/G30,0) -> 0.028593251 | H51: =IFERROR(SUM(H6:Q6)/H30,0) -> 0.028561139 | I51: =IFERROR(SUM(I6:R6)/I30,0) -> 0.028526038 | ... W51: =IFERROR(SUM(W6:AF6)/W30,0) -> 0.028406019 | X51: =W51 -> 0.028406019 | Y51: =X51 -> 0.028406019 | Z51: =Y51 -> 0.028406019 | AA51: =Z51 -> 0.028406019 | AB51: =AA51 -> 0.028406019 | AC51: =AB51 -> 0.028406019 | AD51: =AC51 -> 0.028406019 | AE51: =AD51 -> 0.028406019 | AF51: =AE51 -> 0.028406019
A52: solar PV ($/MW) | B52: =IFERROR(SUM(B7:K7)/B31,0) -> 0.025364303 | C52: =IFERROR(SUM(C7:L7)/C31,0) -> 0.025411076 | D52: =IFERROR(SUM(D7:M7)/D31,0) -> 0.025513356 | E52: =IFERROR(SUM(E7:N7)/E31,0) -> 0.025680469 | F52: =IFERROR(SUM(F7:O7)/F31,0) -> 0.025923319 | G52: =IFERROR(SUM(G7:P7)/G31,0) -> 0.026254754 | H52: =IFERROR(SUM(H7:Q7)/H31,0) -> 0.026195638 | I52: =IFERROR(SUM(I7:R7)/I31,0) -> 0.026150523 | ... W52: =IFERROR(SUM(W7:AF7)/W31,0) -> 0.026137331 | X52: =W52 -> 0.026137331 | Y52: =X52 -> 0.026137331 | Z52: =Y52 -> 0.026137331 | AA52: =Z52 -> 0.026137331 | AB52: =AA52 -> 0.026137331 | AC52: =AB52 -> 0.026137331 | AD52: =AC52 -> 0.026137331 | AE52: =AD52 -> 0.026137331 | AF52: =AE52 -> 0.026137331
A53: solar thermal ($/MW) | B53: =IFERROR(SUM(B8:K8)/B32,0) -> 0 | C53: =IFERROR(SUM(C8:L8)/C32,0) -> 0 | D53: =IFERROR(SUM(D8:M8)/D32,0) -> 0 | E53: =IFERROR(SUM(E8:N8)/E32,0) -> 0 | F53: =IFERROR(SUM(F8:O8)/F32,0) -> 0 | G53: =IFERROR(SUM(G8:P8)/G32,0) -> 0 | H53: =IFERROR(SUM(H8:Q8)/H32,0) -> 0 | I53: =IFERROR(SUM(I8:R8)/I32,0) -> 0 | ... W53: =IFERROR(SUM(W8:AF8)/W32,0) -> 0 | X53: =W53 -> 0 | Y53: =X53 -> 0 | Z53: =Y53 -> 0 | AA53: =Z53 -> 0 | AB53: =AA53 -> 0 | AC53: =AB53 -> 0 | AD53: =AC53 -> 0 | AE53: =AD53 -> 0 | AF53: =AE53 -> 0
A54: biomass ($/MW) | B54: =IFERROR(SUM(B9:K9)/B33,0) -> 0.03 | C54: =IFERROR(SUM(C9:L9)/C33,0) -> 0.03 | D54: =IFERROR(SUM(D9:M9)/D33,0) -> 0.03 | E54: =IFERROR(SUM(E9:N9)/E33,0) -> 0.03 | F54: =IFERROR(SUM(F9:O9)/F33,0) -> 0.03 | G54: =IFERROR(SUM(G9:P9)/G33,0) -> 0.03 | H54: =IFERROR(SUM(H9:Q9)/H33,0) -> 0.03 | I54: =IFERROR(SUM(I9:R9)/I33,0) -> 0.03 | ... W54: =IFERROR(SUM(W9:AF9)/W33,0) -> 0.03 | X54: =W54 -> 0.03 | Y54: =X54 -> 0.03 | Z54: =Y54 -> 0.03 | AA54: =Z54 -> 0.03 | AB54: =AA54 -> 0.03 | AC54: =AB54 -> 0.03 | AD54: =AC54 -> 0.03 | AE54: =AD54 -> 0.03 | AF54: =AE54 -> 0.03
A55: geothermal ($/MW) | B55: =IFERROR(SUM(B10:K10)/B34,0) -> 0 | C55: =IFERROR(SUM(C10:L10)/C34,0) -> 0 | D55: =IFERROR(SUM(D10:M10)/D34,0) -> 0 | E55: =IFERROR(SUM(E10:N10)/E34,0) -> 0 | F55: =IFERROR(SUM(F10:O10)/F34,0) -> 0 | G55: =IFERROR(SUM(G10:P10)/G34,0) -> 0 | H55: =IFERROR(SUM(H10:Q10)/H34,0) -> 0 | I55: =IFERROR(SUM(I10:R10)/I34,0) -> 0 | ... W55: =IFERROR(SUM(W10:AF10)/W34,0) -> 0 | X55: =W55 -> 0 | Y55: =X55 -> 0 | Z55: =Y55 -> 0 | AA55: =Z55 -> 0 | AB55: =AA55 -> 0 | AC55: =AB55 -> 0 | AD55: =AC55 -> 0 | AE55: =AD55 -> 0 | AF55: =AE55 -> 0
A56: petroleum ($/MW) | B56: =IFERROR(SUM(B11:K11)/B35,0) -> 0 | C56: =IFERROR(SUM(C11:L11)/C35,0) -> 0 | D56: =IFERROR(SUM(D11:M11)/D35,0) -> 0 | E56: =IFERROR(SUM(E11:N11)/E35,0) -> 0 | F56: =IFERROR(SUM(F11:O11)/F35,0) -> 0 | G56: =IFERROR(SUM(G11:P11)/G35,0) -> 0 | H56: =IFERROR(SUM(H11:Q11)/H35,0) -> 0 | I56: =IFERROR(SUM(I11:R11)/I35,0) -> 0 | ... W56: =IFERROR(SUM(W11:AF11)/W35,0) -> 0 | X56: =W56 -> 0 | Y56: =X56 -> 0 | Z56: =Y56 -> 0 | AA56: =Z56 -> 0 | AB56: =AA56 -> 0 | AC56: =AB56 -> 0 | AD56: =AC56 -> 0 | AE56: =AD56 -> 0 | AF56: =AE56 -> 0
A57: natural gas peaker ($/MW) | B57: =IFERROR(SUM(B12:K12)/B36,0) -> 0 | C57: =IFERROR(SUM(C12:L12)/C36,0) -> 0 | D57: =IFERROR(SUM(D12:M12)/D36,0) -> 0 | E57: =IFERROR(SUM(E12:N12)/E36,0) -> 0 | F57: =IFERROR(SUM(F12:O12)/F36,0) -> 0 | G57: =IFERROR(SUM(G12:P12)/G36,0) -> 0 | H57: =IFERROR(SUM(H12:Q12)/H36,0) -> 0 | I57: =IFERROR(SUM(I12:R12)/I36,0) -> 0 | ... W57: =IFERROR(SUM(W12:AF12)/W36,0) -> 0 | X57: =W57 -> 0 | Y57: =X57 -> 0 | Z57: =Y57 -> 0 | AA57: =Z57 -> 0 | AB57: =AA57 -> 0 | AC57: =AB57 -> 0 | AD57: =AC57 -> 0 | AE57: =AD57 -> 0 | AF57: =AE57 -> 0
A58: lignite ($/MW) | B58: =IFERROR(SUM(B13:K13)/B37,0) -> 0 | C58: =IFERROR(SUM(C13:L13)/C37,0) -> 0 | D58: =IFERROR(SUM(D13:M13)/D37,0) -> 0 | E58: =IFERROR(SUM(E13:N13)/E37,0) -> 0 | F58: =IFERROR(SUM(F13:O13)/F37,0) -> 0 | G58: =IFERROR(SUM(G13:P13)/G37,0) -> 0 | H58: =IFERROR(SUM(H13:Q13)/H37,0) -> 0 | I58: =IFERROR(SUM(I13:R13)/I37,0) -> 0 | ... W58: =IFERROR(SUM(W13:AF13)/W37,0) -> 0 | X58: =W58 -> 0 | Y58: =X58 -> 0 | Z58: =Y58 -> 0 | AA58: =Z58 -> 0 | AB58: =AA58 -> 0 | AC58: =AB58 -> 0 | AD58: =AC58 -> 0 | AE58: =AD58 -> 0 | AF58: =AE58 -> 0
... A62: municipal solid waste ($/MWh) | B62: =IFERROR(SUM(B17:K17)/B41,0) -> 0 | C62: =IFERROR(SUM(C17:L17)/C41,0) -> 0 | D62: =IFERROR(SUM(D17:M17)/D41,0) -> 0 | E62: =IFERROR(SUM(E17:N17)/E41,0) -> 0 | F62: =IFERROR(SUM(F17:O17)/F41,0) -> 0 | G62: =IFERROR(SUM(G17:P17)/G41,0) -> 0 | H62: =IFERROR(SUM(H17:Q17)/H41,0) -> 0 | I62: =IFERROR(SUM(I17:R17)/I41,0) -> 0 | ... W62: =IFERROR(SUM(W17:AF17)/W41,0) -> 0 | X62: =W62 -> 0 | Y62: =X62 -> 0 | Z62: =Y62 -> 0 | AA62: =Z62 -> 0 | AB62: =AA62 -> 0 | AC62: =AB62 -> 0 | AD62: =AC62 -> 0 | AE62: =AD62 -> 0 | AF62: =AE62 -> 0
B66: d

Sheet BS-BSfTFpEUP
A1: Year | B1: 2020 | C1: 2021 | D1: 2022 | E1: 2023 | F1: 2024 | G1: 2025 | H1: 2026 | I1: 2027 | J1: 2028 | K1: 2029 | L1: 2030 | M1: 2031 | N1: 2032 | O1: 2033 | P1: 2034 | Q1: 2035 | R1: 2036 | S1: 2037 | T1: 2038 | U1: 2039 | V1: 2040 | W1: 2041 | X1: 2042 | Y1: 2043 | Z1: 2044 | AA1: 2045 | AB1: 2046 | AC1: 2047 | AD1: 2048 | AE1: 2049 | AF1: 2050
A2: electricity | B2: 0 | C2: 0 | D2: 0 | E2: 0 | F2: 0 | G2: 0 | H2: 0 | I2: 0 | J2: 0 | K2: 0 | L2: 0 | M2: 0 | N2: 0 | O2: 0 | P2: 0 | Q2: 0 | R2: 0 | S2: 0 | T2: 0 | U2: 0 | V2: 0 | W2: 0 | X2: 0 | Y2: 0 | Z2: 0 | AA2: 0 | AB2: 0 | AC2: 0 | AD2: 0 | AE2: 0 | AF2: 0
A3: hard coal ($/BTU) | B3: 0 | C3: 0 | D3: 0 | E3: 0 | F3: 0 | G3: 0 | H3: 0 | I3: 0 | J3: 0 | K3: 0 | L3: 0 | M3: 0 | N3: 0 | O3: 0 | P3: 0 | Q3: 0 | R3: 0 | S3: 0 | T3: 0 | U3: 0 | V3: 0 | W3: 0 | X3: 0 | Y3: 0 | Z3: 0 | AA3: 0 | AB3: 0 | AC3: 0 | AD3: 0 | AE3: 0 | AF3: 0
A4: natural gas ($/BTU) | B4: 0 | C4: 0 | D4: 0 | E4: 0 | F4: 0 | G4: 0 | H4: 0 | I4: 0 | J4: 0 | K4: 0 | L4: 0 | M4: 0 | N4: 0 | O4: 0 | P4: 0 | Q4: 0 | R4: 0 | S4: 0 | T4: 0 | U4: 0 | V4: 0 | W4: 0 | X4: 0 | Y4: 0 | Z4: 0 | AA4: 0 | AB4: 0 | AC4: 0 | AD4: 0 | AE4: 0 | AF4: 0
A5: nuclear | B5: 0 | C5: 0 | D5: 0 | E5: 0 | F5: 0 | G5: 0 | H5: 0 | I5: 0 | J5: 0 | K5: 0 | L5: 0 | M5: 0 | N5: 0 | O5: 0 | P5: 0 | Q5: 0 | R5: 0 | S5: 0 | T5: 0 | U5: 0 | V5: 0 | W5: 0 | X5: 0 | Y5: 0 | Z5: 0 | AA5: 0 | AB5: 0 | AC5: 0 | AD5: 0 | AE5: 0 | AF5: 0
A6: hydro | B6: 0 | C6: 0 | D6: 0 | E6: 0 | F6: 0 | G6: 0 | H6: 0 | I6: 0 | J6: 0 | K6: 0 | L6: 0 | M6: 0 | N6: 0 | O6: 0 | P6: 0 | Q6: 0 | R6: 0 | S6: 0 | T6: 0 | U6: 0 | V6: 0 | W6: 0 | X6: 0 | Y6: 0 | Z6: 0 | AA6: 0 | AB6: 0 | AC6: 0 | AD6: 0 | AE6: 0 | AF6: 0
A7: wind | B7: 0 | C7: 0 | D7: 0 | E7: 0 | F7: 0 | G7: 0 | H7: 0 | I7: 0 | J7: 0 | K7: 0 | L7: 0 | M7: 0 | N7: 0 | O7: 0 | P7: 0 | Q7: 0 | R7: 0 | S7: 0 | T7: 0 | U7: 0 | V7: 0 | W7: 0 | X7: 0 | Y7: 0 | Z7: 0 | AA7: 0 | AB7: 0 | AC7: 0 | AD7: 0 | AE7: 0 | AF7: 0
A8: solar | B8: 0 | C8: 0 | D8: 0 | E8: 0 | F8: 0 | G8: 0 | H8: 0 | I8: 0 | J8: 0 | K8: 0 | L8: 0 | M8: 0 | N8: 0 | O8: 0 | P8: 0 | Q8: 0 | R8: 0 | S8: 0 | T8: 0 | U8: 0 | V8: 0 | W8: 0 | X8: 0 | Y8: 0 | Z8: 0 | AA8: 0 | AB8: 0 | AC8: 0 | AD8: 0 | AE8: 0 | AF8: 0
A9: biomass ($/BTU) | B9: 0 | C9: 0 | D9: 0 | E9: 0 | F9: 0 | G9: 0 | H9: 0 | I9: 0 | J9: 0 | K9: 0 | L9: 0 | M9: 0 | N9: 0 | O9: 0 | P9: 0 | Q9: 0 | R9: 0 | S9: 0 | T9: 0 | U9: 0 | V9: 0 | W9: 0 | X9: 0 | Y9: 0 | Z9: 0 | AA9: 0 | AB9: 0 | AC9: 0 | AD9: 0 | AE9: 0 | AF9: 0
A10: petroleum gasoline ($/BTU) | B10: 0 | C10: 0 | D10: 0 | E10: 0 | F10: 0 | G10: 0 | H10: 0 | I10: 0 | J10: 0 | K10: 0 | L10: 0 | M10: 0 | N10: 0 | O10: 0 | P10: 0 | Q10: 0 | R10: 0 | S10: 0 | T10: 0 | U10: 0 | V10: 0 | W10: 0 | X10: 0 | Y10: 0 | Z10: 0 | AA10: 0 | AB10: 0 | AC10: 0 | AD10: 0 | AE10: 0 | AF10: 0
A11: petroleum diesel ($/BTU) | B11: 0 | C11: 0 | D11: 0 | E11: 0 | F11: 0 | G11: 0 | H11: 0 | I11: 0 | J11: 0 | K11: 0 | L11: 0 | M11: 0 | N11: 0 | O11: 0 | P11: 0 | Q11: 0 | R11: 0 | S11: 0 | T11: 0 | U11: 0 | V11: 0 | W11: 0 | X11: 0 | Y11: 0 | Z11: 0 | AA11: 0 | AB11: 0 | AC11: 0 | AD11: 0 | AE11: 0 | AF11: 0
A12: biofuel gasoline | B12: 0 | C12: 0 | D12: 0 | E12: 0 | F12: 0 | G12: 0 | H12: 0 | I12: 0 | J12: 0 | K12: 0 | L12: 0 | M12: 0 | N12: 0 | O12: 0 | P12: 0 | Q12: 0 | R12: 0 | S12: 0 | T12: 0 | U12: 0 | V12: 0 | W12: 0 | X12: 0 | Y12: 0 | Z12: 0 | AA12: 0 | AB12: 0 | AC12: 0 | AD12: 0 | AE12: 0 | AF12: 0
... A22: hydrogen | B22: 0 | C22: 0 | D22: 0 | E22: 0 | F22: 0 | G22: 0 | H22: 0 | I22: 0 | J22: 0 | K22: 0 | L22: 0 | M22: 0 | N22: 0 | O22: 0 | P22: 0 | Q22: 0 | R22: 0 | S22: 0 | T22: 0 | U22: 0 | V22: 0 | W22: 0 | X22: 0 | Y22: 0 | Z22: 0 | AA22: 0 | AB22: 0 | AC22: 0 | AD22: 0 | AE22: 0 | AF22: 0

Sheet BS-BSfTFpEUP-transportation
A1: Year | B1: 2021 | C1: 2022 | D1: 2023 | E1: 2024 | F1: 2025 | G1: 2026 | H1: 2027 | I1: 2028 | J1: 2029 | K1: 2030 | L1: 2031 | M1: 2032 | N1: 2033 | O1: 2034 | P1: 2035 | Q1: 2036 | R1: 2037 | S1: 2038 | T1: 2039 | U1: 2040 | V1: 2041 | W1: 2042 | X1: 2043 | Y1: 2044 | Z1: 2045 | AA1: 2046 | AB1: 2047 | AC1: 2048 | AD1: 2049 | AE1: 2050
A2: electricity | B2: 0 | C2: 0 | D2: 0 | E2: 0 | F2: 0 | G2: 0 | H2: 0 | I2: 0 | J2: 0 | K2: 0 | L2: 0 | M2: 0 | N2: 0 | O2: 0 | P2: 0 | Q2: 0 | R2: 0 | S2: 0 | T2: 0 | U2: 0 | V2: 0 | W2: 0 | X2: 0 | Y2: 0 | Z2: 0 | AA2: 0 | AB2: 0 | AC2: 0 | AD2: 0 | AE2: 0
A3: hard coal ($/BTU) | B3: 0 | C3: 0 | D3: 0 | E3: 0 | F3: 0 | G3: 0 | H3: 0 | I3: 0 | J3: 0 | K3: 0 | L3: 0 | M3: 0 | N3: 0 | O3: 0 | P3: 0 | Q3: 0 | R3: 0 | S3: 0 | T3: 0 | U3: 0 | V3: 0 | W3: 0 | X3: 0 | Y3: 0 | Z3: 0 | AA3: 0 | AB3: 0 | AC3: 0 | AD3: 0 | AE3: 0
A4: natural gas ($/BTU) | B4: 0 | C4: 0 | D4: 0 | E4: 0 | F4: 0 | G4: 0 | H4: 0 | I4: 0 | J4: 0 | K4: 0 | L4: 0 | M4: 0 | N4: 0 | O4: 0 | P4: 0 | Q4: 0 | R4: 0 | S4: 0 | T4: 0 | U4: 0 | V4: 0 | W4: 0 | X4: 0 | Y4: 0 | Z4: 0 | AA4: 0 | AB4: 0 | AC4: 0 | AD4: 0 | AE4: 0
A5: nuclear | B5: 0 | C5: 0 | D5: 0 | E5: 0 | F5: 0 | G5: 0 | H5: 0 | I5: 0 | J5: 0 | K5: 0 | L5: 0 | M5: 0 | N5: 0 | O5: 0 | P5: 0 | Q5: 0 | R5: 0 | S5: 0 | T5: 0 | U5: 0 | V5: 0 | W5: 0 | X5: 0 | Y5: 0 | Z5: 0 | AA5: 0 | AB5: 0 | AC5: 0 | AD5: 0 | AE5: 0
A6: hydro | B6: 0 | C6: 0 | D6: 0 | E6: 0 | F6: 0 | G6: 0 | H6: 0 | I6: 0 | J6: 0 | K6: 0 | L6: 0 | M6: 0 | N6: 0 | O6: 0 | P6: 0 | Q6: 0 | R6: 0 | S6: 0 | T6: 0 | U6: 0 | V6: 0 | W6: 0 | X6: 0 | Y6: 0 | Z6: 0 | AA6: 0 | AB6: 0 | AC6: 0 | AD6: 0 | AE6: 0
A7: wind | B7: 0 | C7: 0 | D7: 0 | E7: 0 | F7: 0 | G7: 0 | H7: 0 | I7: 0 | J7: 0 | K7: 0 | L7: 0 | M7: 0 | N7: 0 | O7: 0 | P7: 0 | Q7: 0 | R7: 0 | S7: 0 | T7: 0 | U7: 0 | V7: 0 | W7: 0 | X7: 0 | Y7: 0 | Z7: 0 | AA7: 0 | AB7: 0 | AC7: 0 | AD7: 0 | AE7: 0
A8: solar | B8: 0 | C8: 0 | D8: 0 | E8: 0 | F8: 0 | G8: 0 | H8: 0 | I8: 0 | J8: 0 | K8: 0 | L8: 0 | M8: 0 | N8: 0 | O8: 0 | P8: 0 | Q8: 0 | R8: 0 | S8: 0 | T8: 0 | U8: 0 | V8: 0 | W8: 0 | X8: 0 | Y8: 0 | Z8: 0 | AA8: 0 | AB8: 0 | AC8: 0 | AD8: 0 | AE8: 0
A9: biomass ($/BTU) | B9: 0 | C9: 0 | D9: 0 | E9: 0 | F9: 0 | G9: 0 | H9: 0 | I9: 0 | J9: 0 | K9: 0 | L9: 0 | M9: 0 | N9: 0 | O9: 0 | P9: 0 | Q9: 0 | R9: 0 | S9: 0 | T9: 0 | U9: 0 | V9: 0 | W9: 0 | X9: 0 | Y9: 0 | Z9: 0 | AA9: 0 | AB9: 0 | AC9: 0 | AD9: 0 | AE9: 0
A10: petroleum gasoline ($/BTU) | B10: 0 | C10: 0 | D10: 0 | E10: 0 | F10: 0 | G10: 0 | H10: 0 | I10: 0 | J10: 0 | K10: 0 | L10: 0 | M10: 0 | N10: 0 | O10: 0 | P10: 0 | Q10: 0 | R10: 0 | S10: 0 | T10: 0 | U10: 0 | V10: 0 | W10: 0 | X10: 0 | Y10: 0 | Z10: 0 | AA10: 0 | AB10: 0 | AC10: 0 | AD10: 0 | AE10: 0
A11: petroleum diesel ($/BTU) | B11: 0 | C11: 0 | D11: 0 | E11: 0 | F11: 0 | G11: 0 | H11: 0 | I11: 0 | J11: 0 | K11: 0 | L11: 0 | M11: 0 | N11: 0 | O11: 0 | P11: 0 | Q11: 0 | R11: 0 | S11: 0 | T11: 0 | U11: 0 | V11: 0 | W11: 0 | X11: 0 | Y11: 0 | Z11: 0 | AA11: 0 | AB11: 0 | AC11: 0 | AD11: 0 | AE11: 0
A12: biofuel gasoline | B12: 0 | C12: 0 | D12: 0 | E12: 0 | F12: 0 | G12: 0 | H12: 0 | I12: 0 | J12: 0 | K12: 0 | L12: 0 | M12: 0 | N12: 0 | O12: 0 | P12: 0 | Q12: 0 | R12: 0 | S12: 0 | T12: 0 | U12: 0 | V12: 0 | W12: 0 | X12: 0 | Y12: 0 | Z12: 0 | AA12: 0 | AB12: 0 | AC12: 0 | AD12: 0 | AE12: 0
... A22: hydrogen ($/BTU) | B22: 0 | C22: 0 | D22: 0 | E22: 0 | F22: 0 | G22: 0 | H22: 0 | I22: 0 | J22: 0 | K22: 0 | L22: 0 | M22: 0 | N22: 0 | O22: 0 | P22: 0 | Q22: 0 | R22: 0 | S22: 0 | T22: 0 | U22: 0 | V22: 0 | W22: 0 | X22: 0 | Y22: 0 | Z22: 0 | AA22: 0 | AB22: 0 | AC22: 0 | AD22: 0 | AE22: 0

Sheet BS-BSfTFpEUP-electricity
A1: Year | B1: 2021 | C1: 2022 | D1: 2023 | E1: 2024 | F1: 2025 | G1: 2026 | H1: 2027 | I1: 2028 | J1: 2029 | K1: 2030 | L1: 2031 | M1: 2032 | N1: 2033 | O1: 2034 | P1: 2035 | Q1: 2036 | R1: 2037 | S1: 2038 | T1: 2039 | U1: 2040 | V1: 2041 | W1: 2042 | X1: 2043 | Y1: 2044 | Z1: 2045 | AA1: 2046 | AB1: 2047 | AC1: 2048 | AD1: 2049 | AE1: 2050
A2: electricity | B2: 0 | C2: 0 | D2: 0 | E2: 0 | F2: 0 | G2: 0 | H2: 0 | I2: 0 | J2: 0 | K2: 0 | L2: 0 | M2: 0 | N2: 0 | O2: 0 | P2: 0 | Q2: 0 | R2: 0 | S2: 0 | T2: 0 | U2: 0 | V2: 0 | W2: 0 | X2: 0 | Y2: 0 | Z2: 0 | AA2: 0 | AB2: 0 | AC2: 0 | AD2: 0 | AE2: 0
A3: hard coal ($/BTU) | B3: 0 | C3: 0 | D3: 0 | E3: 0 | F3: 0 | G3: 0 | H3: 0 | I3: 0 | J3: 0 | K3: 0 | L3: 0 | M3: 0 | N3: 0 | O3: 0 | P3: 0 | Q3: 0 | R3: 0 | S3: 0 | T3: 0 | U3: 0 | V3: 0 | W3: 0 | X3: 0 | Y3: 0 | Z3: 0 | AA3: 0 | AB3: 0 | AC3: 0 | AD3: 0 | AE3: 0
A4: natural gas ($/BTU) | B4: 0 | C4: 0 | D4: 0 | E4: 0 | F4: 0 | G4: 0 | H4: 0 | I4: 0 | J4: 0 | K4: 0 | L4: 0 | M4: 0 | N4: 0 | O4: 0 | P4: 0 | Q4: 0 | R4: 0 | S4: 0 | T4: 0 | U4: 0 | V4: 0 | W4: 0 | X4: 0 | Y4: 0 | Z4: 0 | AA4: 0 | AB4: 0 | AC4: 0 | AD4: 0 | AE4: 0
A5: nuclear | B5: 0 | C5: 0 | D5: 0 | E5: 0 | F5: 0 | G5: 0 | H5: 0 | I5: 0 | J5: 0 | K5: 0 | L5: 0 | M5: 0 | N5: 0 | O5: 0 | P5: 0 | Q5: 0 | R5: 0 | S5: 0 | T5: 0 | U5: 0 | V5: 0 | W5: 0 | X5: 0 | Y5: 0 | Z5: 0 | AA5: 0 | AB5: 0 | AC5: 0 | AD5: 0 | AE5: 0
A6: hydro | B6: 0 | C6: 0 | D6: 0 | E6: 0 | F6: 0 | G6: 0 | H6: 0 | I6: 0 | J6: 0 | K6: 0 | L6: 0 | M6: 0 | N6: 0 | O6: 0 | P6: 0 | Q6: 0 | R6: 0 | S6: 0 | T6: 0 | U6: 0 | V6: 0 | W6: 0 | X6: 0 | Y6: 0 | Z6: 0 | AA6: 0 | AB6: 0 | AC6: 0 | AD6: 0 | AE6: 0
A7: wind | B7: 0 | C7: 0 | D7: 0 | E7: 0 | F7: 0 | G7: 0 | H7: 0 | I7: 0 | J7: 0 | K7: 0 | L7: 0 | M7: 0 | N7: 0 | O7: 0 | P7: 0 | Q7: 0 | R7: 0 | S7: 0 | T7: 0 | U7: 0 | V7: 0 | W7: 0 | X7: 0 | Y7: 0 | Z7: 0 | AA7: 0 | AB7: 0 | AC7: 0 | AD7: 0 | AE7: 0
A8: solar | B8: 0 | C8: 0 | D8: 0 | E8: 0 | F8: 0 | G8: 0 | H8: 0 | I8: 0 | J8: 0 | K8: 0 | L8: 0 | M8: 0 | N8: 0 | O8: 0 | P8: 0 | Q8: 0 | R8: 0 | S8: 0 | T8: 0 | U8: 0 | V8: 0 | W8: 0 | X8: 0 | Y8: 0 | Z8: 0 | AA8: 0 | AB8: 0 | AC8: 0 | AD8: 0 | AE8: 0
A9: biomass ($/BTU) | B9: 0 | C9: 0 | D9: 0 | E9: 0 | F9: 0 | G9: 0 | H9: 0 | I9: 0 | J9: 0 | K9: 0 | L9: 0 | M9: 0 | N9: 0 | O9: 0 | P9: 0 | Q9: 0 | R9: 0 | S9: 0 | T9: 0 | U9: 0 | V9: 0 | W9: 0 | X9: 0 | Y9: 0 | Z9: 0 | AA9: 0 | AB9: 0 | AC9: 0 | AD9: 0 | AE9: 0
A10: petroleum gasoline ($/BTU) | B10: 0 | C10: 0 | D10: 0 | E10: 0 | F10: 0 | G10: 0 | H10: 0 | I10: 0 | J10: 0 | K10: 0 | L10: 0 | M10: 0 | N10: 0 | O10: 0 | P10: 0 | Q10: 0 | R10: 0 | S10: 0 | T10: 0 | U10: 0 | V10: 0 | W10: 0 | X10: 0 | Y10: 0 | Z10: 0 | AA10: 0 | AB10: 0 | AC10: 0 | AD10: 0 | AE10: 0
A11: petroleum diesel ($/BTU) | B11: 0 | C11: 0 | D11: 0 | E11: 0 | F11: 0 | G11: 0 | H11: 0 | I11: 0 | J11: 0 | K11: 0 | L11: 0 | M11: 0 | N11: 0 | O11: 0 | P11: 0 | Q11: 0 | R11: 0 | S11: 0 | T11: 0 | U11: 0 | V11: 0 | W11: 0 | X11: 0 | Y11: 0 | Z11: 0 | AA11: 0 | AB11: 0 | AC11: 0 | AD11: 0 | AE11: 0
A12: biofuel gasoline | B12: 0 | C12: 0 | D12: 0 | E12: 0 | F12: 0 | G12: 0 | H12: 0 | I12: 0 | J12: 0 | K12: 0 | L12: 0 | M12: 0 | N12: 0 | O12: 0 | P12: 0 | Q12: 0 | R12: 0 | S12: 0 | T12: 0 | U12: 0 | V12: 0 | W12: 0 | X12: 0 | Y12: 0 | Z12: 0 | AA12: 0 | AB12: 0 | AC12: 0 | AD12: 0 | AE12: 0
... A22: hydrogen ($/BTU) | B22: 0 | C22: 0 | D22: 0 | E22: 0 | F22: 0 | G22: 0 | H22: 0 | I22: 0 | J22: 0 | K22: 0 | L22: 0 | M22: 0 | N22: 0 | O22: 0 | P22: 0 | Q22: 0 | R22: 0 | S22: 0 | T22: 0 | U22: 0 | V22: 0 | W22: 0 | X22: 0 | Y22: 0 | Z22: 0 | AA22: 0 | AB22: 0 | AC22: 0 | AD22: 0 | AE22: 0

Sheet BS-BSfTFpEUP-res-bldgs
A1: Year | B1: 2021 | C1: 2022 | D1: 2023 | E1: 2024 | F1: 2025 | G1: 2026 | H1: 2027 | I1: 2028 | J1: 2029 | K1: 2030 | L1: 2031 | M1: 2032 | N1: 2033 | O1: 2034 | P1: 2035 | Q1: 2036 | R1: 2037 | S1: 2038 | T1: 2039 | U1: 2040 | V1: 2041 | W1: 2042 | X1: 2043 | Y1: 2044 | Z1: 2045 | AA1: 2046 | AB1: 2047 | AC1: 2048 | AD1: 2049 | AE1: 2050
A2: electricity | B2: 0 | C2: 0 | D2: 0 | E2: 0 | F2: 0 | G2: 0 | H2: 0 | I2: 0 | J2: 0 | K2: 0 | L2: 0 | M2: 0 | N2: 0 | O2: 0 | P2: 0 | Q2: 0 | R2: 0 | S2: 0 | T2: 0 | U2: 0 | V2: 0 | W2: 0 | X2: 0 | Y2: 0 | Z2: 0 | AA2: 0 | AB2: 0 | AC2: 0 | AD2: 0 | AE2: 0
A3: hard coal ($/BTU) | B3: 0 | C3: 0 | D3: 0 | E3: 0 | F3: 0 | G3: 0 | H3: 0 | I3: 0 | J3: 0 | K3: 0 | L3: 0 | M3: 0 | N3: 0 | O3: 0 | P3: 0 | Q3: 0 | R3: 0 | S3: 0 | T3: 0 | U3: 0 | V3: 0 | W3: 0 | X3: 0 | Y3: 0 | Z3: 0 | AA3: 0 | AB3: 0 | AC3: 0 | AD3: 0 | AE3: 0
A4: natural gas ($/BTU) | B4: 0 | C4: 0 | D4: 0 | E4: 0 | F4: 0 | G4: 0 | H4: 0 | I4: 0 | J4: 0 | K4: 0 | L4: 0 | M4: 0 | N4: 0 | O4: 0 | P4: 0 | Q4: 0 | R4: 0 | S4: 0 | T4: 0 | U4: 0 | V4: 0 | W4: 0 | X4: 0 | Y4: 0 | Z4: 0 | AA4: 0 | AB4: 0 | AC4: 0 | AD4: 0 | AE4: 0
A5: nuclear | B5: 0 | C5: 0 | D5: 0 | E5: 0 | F5: 0 | G5: 0 | H5: 0 | I5: 0 | J5: 0 | K5: 0 | L5: 0 | M5: 0 | N5: 0 | O5: 0 | P5: 0 | Q5: 0 | R5: 0 | S5: 0 | T5: 0 | U5: 0 | V5: 0 | W5: 0 | X5: 0 | Y5: 0 | Z5: 0 | AA5: 0 | AB5: 0 | AC5: 0 | AD5: 0 | AE5: 0
A6: hydro | B6: 0 | C6: 0 | D6: 0 | E6: 0 | F6: 0 | G6: 0 | H6: 0 | I6: 0 | J6: 0 | K6: 0 | L6: 0 | M6: 0 | N6: 0 | O6: 0 | P6: 0 | Q6: 0 | R6: 0 | S6: 0 | T6: 0 | U6: 0 | V6: 0 | W6: 0 | X6: 0 | Y6: 0 | Z6: 0 | AA6: 0 | AB6: 0 | AC6: 0 | AD6: 0 | AE6: 0
A7: wind | B7: 0 | C7: 0 | D7: 0 | E7: 0 | F7: 0 | G7: 0 | H7: 0 | I7: 0 | J7: 0 | K7: 0 | L7: 0 | M7: 0 | N7: 0 | O7: 0 | P7: 0 | Q7: 0 | R7: 0 | S7: 0 | T7: 0 | U7: 0 | V7: 0 | W7: 0 | X7: 0 | Y7: 0 | Z7: 0 | AA7: 0 | AB7: 0 | AC7: 0 | AD7: 0 | AE7: 0
A8: solar | B8: 0 | C8: 0 | D8: 0 | E8: 0 | F8: 0 | G8: 0 | H8: 0 | I8: 0 | J8: 0 | K8: 0 | L8: 0 | M8: 0 | N8: 0 | O8: 0 | P8: 0 | Q8: 0 | R8: 0 | S8: 0 | T8: 0 | U8: 0 | V8: 0 | W8: 0 | X8: 0 | Y8: 0 | Z8: 0 | AA8: 0 | AB8: 0 | AC8: 0 | AD8: 0 | AE8: 0
A9: biomass ($/BTU) | B9: 0 | C9: 0 | D9: 0 | E9: 0 | F9: 0 | G9: 0 | H9: 0 | I9: 0 | J9: 0 | K9: 0 | L9: 0 | M9: 0 | N9: 0 | O9: 0 | P9: 0 | Q9: 0 | R9: 0 | S9: 0 | T9: 0 | U9: 0 | V9: 0 | W9: 0 | X9: 0 | Y9: 0 | Z9: 0 | AA9: 0 | AB9: 0 | AC9: 0 | AD9: 0 | AE9: 0
A10: petroleum gasoline ($/BTU) | B10: 0 | C10: 0 | D10: 0 | E10: 0 | F10: 0 | G10: 0 | H10: 0 | I10: 0 | J10: 0 | K10: 0 | L10: 0 | M10: 0 | N10: 0 | O10: 0 | P10: 0 | Q10: 0 | R10: 0 | S10: 0 | T10: 0 | U10: 0 | V10: 0 | W10: 0 | X10: 0 | Y10: 0 | Z10: 0 | AA10: 0 | AB10: 0 | AC10: 0 | AD10: 0 | AE10: 0
A11: petroleum diesel ($/BTU) | B11: 0 | C11: 0 | D11: 0 | E11: 0 | F11: 0 | G11: 0 | H11: 0 | I11: 0 | J11: 0 | K11: 0 | L11: 0 | M11: 0 | N11: 0 | O11: 0 | P11: 0 | Q11: 0 | R11: 0 | S11: 0 | T11: 0 | U11: 0 | V11: 0 | W11: 0 | X11: 0 | Y11: 0 | Z11: 0 | AA11: 0 | AB11: 0 | AC11: 0 | AD11: 0 | AE11: 0
A12: biofuel gasoline | B12: 0 | C12: 0 | D12: 0 | E12: 0 | F12: 0 | G12: 0 | H12: 0 | I12: 0 | J12: 0 | K12: 0 | L12: 0 | M12: 0 | N12: 0 | O12: 0 | P12: 0 | Q12: 0 | R12: 0 | S12: 0 | T12: 0 | U12: 0 | V12: 0 | W12: 0 | X12: 0 | Y12: 0 | Z12: 0 | AA12: 0 | AB12: 0 | AC12: 0 | AD12: 0 | AE12: 0
... A22: hydrogen ($/BTU) | B22: 0 | C22: 0 | D22: 0 | E22: 0 | F22: 0 | G22: 0 | H22: 0 | I22: 0 | J22: 0 | K22: 0 | L22: 0 | M22: 0 | N22: 0 | O22: 0 | P22: 0 | Q22: 0 | R22: 0 | S22: 0 | T22: 0 | U22: 0 | V22: 0 | W22: 0 | X22: 0 | Y22: 0 | Z22: 0 | AA22: 0 | AB22: 0 | AC22: 0 | AD22: 0 | AE22: 0

Sheet BS-BSfTFpEUP-com-bldgs
A1: Year | B1: 2021 | C1: 2022 | D1: 2023 | E1: 2024 | F1: 2025 | G1: 2026 | H1: 2027 | I1: 2028 | J1: 2029 | K1: 2030 | L1: 2031 | M1: 2032 | N1: 2033 | O1: 2034 | P1: 2035 | Q1: 2036 | R1: 2037 | S1: 2038 | T1: 2039 | U1: 2040 | V1: 2041 | W1: 2042 | X1: 2043 | Y1: 2044 | Z1: 2045 | AA1: 2046 | AB1: 2047 | AC1: 2048 | AD1: 2049 | AE1: 2050
A2: electricity | B2: 0 | C2: 0 | D2: 0 | E2: 0 | F2: 0 | G2: 0 | H2: 0 | I2: 0 | J2: 0 | K2: 0 | L2: 0 | M2: 0 | N2: 0 | O2: 0 | P2: 0 | Q2: 0 | R2: 0 | S2: 0 | T2: 0 | U2: 0 | V2: 0 | W2: 0 | X2: 0 | Y2: 0 | Z2: 0 | AA2: 0 | AB2: 0 | AC2: 0 | AD2: 0 | AE2: 0
A3: hard coal ($/BTU) | B3: 0 | C3: 0 | D3: 0 | E3: 0 | F3: 0 | G3: 0 | H3: 0 | I3: 0 | J3: 0 | K3: 0 | L3: 0 | M3: 0 | N3: 0 | O3: 0 | P3: 0 | Q3: 0 | R3: 0 | S3: 0 | T3: 0 | U3: 0 | V3: 0 | W3: 0 | X3: 0 | Y3: 0 | Z3: 0 | AA3: 0 | AB3: 0 | AC3: 0 | AD3: 0 | AE3: 0
A4: natural gas ($/BTU) | B4: 0 | C4: 0 | D4: 0 | E4: 0 | F4: 0 | G4: 0 | H4: 0 | I4: 0 | J4: 0 | K4: 0 | L4: 0 | M4: 0 | N4: 0 | O4: 0 | P4: 0 | Q4: 0 | R4: 0 | S4: 0 | T4: 0 | U4: 0 | V4: 0 | W4: 0 | X4: 0 | Y4: 0 | Z4: 0 | AA4: 0 | AB4: 0 | AC4: 0 | AD4: 0 | AE4: 0
A5: nuclear | B5: 0 | C5: 0 | D5: 0 | E5: 0 | F5: 0 | G5: 0 | H5: 0 | I5: 0 | J5: 0 | K5: 0 | L5: 0 | M5: 0 | N5: 0 | O5: 0 | P5: 0 | Q5: 0 | R5: 0 | S5: 0 | T5: 0 | U5: 0 | V5: 0 | W5: 0 | X5: 0 | Y5: 0 | Z5: 0 | AA5: 0 | AB5: 0 | AC5: 0 | AD5: 0 | AE5: 0
A6: hydro | B6: 0 | C6: 0 | D6: 0 | E6: 0 | F6: 0 | G6: 0 | H6: 0 | I6: 0 | J6: 0 | K6: 0 | L6: 0 | M6: 0 | N6: 0 | O6: 0 | P6: 0 | Q6: 0 | R6: 0 | S6: 0 | T6: 0 | U6: 0 | V6: 0 | W6: 0 | X6: 0 | Y6: 0 | Z6: 0 | AA6: 0 | AB6: 0 | AC6: 0 | AD6: 0 | AE6: 0
A7: wind | B7: 0 | C7: 0 | D7: 0 | E7: 0 | F7: 0 | G7: 0 | H7: 0 | I7: 0 | J7: 0 | K7: 0 | L7: 0 | M7: 0 | N7: 0 | O7: 0 | P7: 0 | Q7: 0 | R7: 0 | S7: 0 | T7: 0 | U7: 0 | V7: 0 | W7: 0 | X7: 0 | Y7: 0 | Z7: 0 | AA7: 0 | AB7: 0 | AC7: 0 | AD7: 0 | AE7: 0
A8: solar | B8: 0 | C8: 0 | D8: 0 | E8: 0 | F8: 0 | G8: 0 | H8: 0 | I8: 0 | J8: 0 | K8: 0 | L8: 0 | M8: 0 | N8: 0 | O8: 0 | P8: 0 | Q8: 0 | R8: 0 | S8: 0 | T8: 0 | U8: 0 | V8: 0 | W8: 0 | X8: 0 | Y8: 0 | Z8: 0 | AA8: 0 | AB8: 0 | AC8: 0 | AD8: 0 | AE8: 0
A9: biomass ($/BTU) | B9: 0 | C9: 0 | D9: 0 | E9: 0 | F9: 0 | G9: 0 | H9: 0 | I9: 0 | J9: 0 | K9: 0 | L9: 0 | M9: 0 | N9: 0 | O9: 0 | P9: 0 | Q9: 0 | R9: 0 | S9: 0 | T9: 0 | U9: 0 | V9: 0 | W9: 0 | X9: 0 | Y9: 0 | Z9: 0 | AA9: 0 | AB9: 0 | AC9: 0 | AD9: 0 | AE9: 0
A10: petroleum gasoline ($/BTU) | B10: 0 | C10: 0 | D10: 0 | E10: 0 | F10: 0 | G10: 0 | H10: 0 | I10: 0 | J10: 0 | K10: 0 | L10: 0 | M10: 0 | N10: 0 | O10: 0 | P10: 0 | Q10: 0 | R10: 0 | S10: 0 | T10: 0 | U10: 0 | V10: 0 | W10: 0 | X10: 0 | Y10: 0 | Z10: 0 | AA10: 0 | AB10: 0 | AC10: 0 | AD10: 0 | AE10: 0
A11: petroleum diesel ($/BTU) | B11: 0 | C11: 0 | D11: 0 | E11: 0 | F11: 0 | G11: 0 | H11: 0 | I11: 0 | J11: 0 | K11: 0 | L11: 0 | M11: 0 | N11: 0 | O11: 0 | P11: 0 | Q11: 0 | R11: 0 | S11: 0 | T11: 0 | U11: 0 | V11: 0 | W11: 0 | X11: 0 | Y11: 0 | Z11: 0 | AA11: 0 | AB11: 0 | AC11: 0 | AD11: 0 | AE11: 0
A12: biofuel gasoline | B12: 0 | C12: 0 | D12: 0 | E12: 0 | F12: 0 | G12: 0 | H12: 0 | I12: 0 | J12: 0 | K12: 0 | L12: 0 | M12: 0 | N12: 0 | O12: 0 | P12: 0 | Q12: 0 | R12: 0 | S12: 0 | T12: 0 | U12: 0 | V12: 0 | W12: 0 | X12: 0 | Y12: 0 | Z12: 0 | AA12: 0 | AB12: 0 | AC12: 0 | AD12: 0 | AE12: 0
... A22: hydrogen ($/BTU) | B22: 0 | C22: 0 | D22: 0 | E22: 0 | F22: 0 | G22: 0 | H22: 0 | I22: 0 | J22: 0 | K22: 0 | L22: 0 | M22: 0 | N22: 0 | O22: 0 | P22: 0 | Q22: 0 | R22: 0 | S22: 0 | T22: 0 | U22: 0 | V22: 0 | W22: 0 | X22: 0 | Y22: 0 | Z22: 0 | AA22: 0 | AB22: 0 | AC22: 0 | AD22: 0 | AE22: 0

Sheet BS-BSfTFpEUP-industry
A1: Year | B1: 2021 | C1: 2022 | D1: 2023 | E1: 2024 | F1: 2025 | G1: 2026 | H1: 2027 | I1: 2028 | J1: 2029 | K1: 2030 | L1: 2031 | M1: 2032 | N1: 2033 | O1: 2034 | P1: 2035 | Q1: 2036 | R1: 2037 | S1: 2038 | T1: 2039 | U1: 2040 | V1: 2041 | W1: 2042 | X1: 2043 | Y1: 2044 | Z1: 2045 | AA1: 2046 | AB1: 2047 | AC1: 2048 | AD1: 2049 | AE1: 2050
A2: electricity | B2: 0 | C2: 0 | D2: 0 | E2: 0 | F2: 0 | G2: 0 | H2: 0 | I2: 0 | J2: 0 | K2: 0 | L2: 0 | M2: 0 | N2: 0 | O2: 0 | P2: 0 | Q2: 0 | R2: 0 | S2: 0 | T2: 0 | U2: 0 | V2: 0 | W2: 0 | X2: 0 | Y2: 0 | Z2: 0 | AA2: 0 | AB2: 0 | AC2: 0 | AD2: 0 | AE2: 0
A3: hard coal ($/BTU) | B3: 0 | C3: 0 | D3: 0 | E3: 0 | F3: 0 | G3: 0 | H3: 0 | I3: 0 | J3: 0 | K3: 0 | L3: 0 | M3: 0 | N3: 0 | O3: 0 | P3: 0 | Q3: 0 | R3: 0 | S3: 0 | T3: 0 | U3: 0 | V3: 0 | W3: 0 | X3: 0 | Y3: 0 | Z3: 0 | AA3: 0 | AB3: 0 | AC3: 0 | AD3: 0 | AE3: 0
A4: natural gas ($/BTU) | B4: 0 | C4: 0 | D4: 0 | E4: 0 | F4: 0 | G4: 0 | H4: 0 | I4: 0 | J4: 0 | K4: 0 | L4: 0 | M4: 0 | N4: 0 | O4: 0 | P4: 0 | Q4: 0 | R4: 0 | S4: 0 | T4: 0 | U4: 0 | V4: 0 | W4: 0 | X4: 0 | Y4: 0 | Z4: 0 | AA4: 0 | AB4: 0 | AC4: 0 | AD4: 0 | AE4: 0
A5: nuclear | B5: 0 | C5: 0 | D5: 0 | E5: 0 | F5: 0 | G5: 0 | H5: 0 | I5: 0 | J5: 0 | K5: 0 | L5: 0 | M5: 0 | N5: 0 | O5: 0 | P5: 0 | Q5: 0 | R5: 0 | S5: 0 | T5: 0 | U5: 0 | V5: 0 | W5: 0 | X5: 0 | Y5: 0 | Z5: 0 | AA5: 0 | AB5: 0 | AC5: 0 | AD5: 0 | AE5: 0
A6: hydro | B6: 0 | C6: 0 | D6: 0 | E6: 0 | F6: 0 | G6: 0 | H6: 0 | I6: 0 | J6: 0 | K6: 0 | L6: 0 | M6: 0 | N6: 0 | O6: 0 | P6: 0 | Q6: 0 | R6: 0 | S6: 0 | T6: 0 | U6: 0 | V6: 0 | W6: 0 | X6: 0 | Y6: 0 | Z6: 0 | AA6: 0 | AB6: 0 | AC6: 0 | AD6: 0 | AE6: 0
A7: wind | B7: 0 | C7: 0 | D7: 0 | E7: 0 | F7: 0 | G7: 0 | H7: 0 | I7: 0 | J7: 0 | K7: 0 | L7: 0 | M7: 0 | N7: 0 | O7: 0 | P7: 0 | Q7: 0 | R7: 0 | S7: 0 | T7: 0 | U7: 0 | V7: 0 | W7: 0 | X7: 0 | Y7: 0 | Z7: 0 | AA7: 0 | AB7: 0 | AC7: 0 | AD7: 0 | AE7: 0
A8: solar | B8: 0 | C8: 0 | D8: 0 | E8: 0 | F8: 0 | G8: 0 | H8: 0 | I8: 0 | J8: 0 | K8: 0 | L8: 0 | M8: 0 | N8: 0 | O8: 0 | P8: 0 | Q8: 0 | R8: 0 | S8: 0 | T8: 0 | U8: 0 | V8: 0 | W8: 0 | X8: 0 | Y8: 0 | Z8: 0 | AA8: 0 | AB8: 0 | AC8: 0 | AD8: 0 | AE8: 0
A9: biomass ($/BTU) | B9: 0 | C9: 0 | D9: 0 | E9: 0 | F9: 0 | G9: 0 | H9: 0 | I9: 0 | J9: 0 | K9: 0 | L9: 0 | M9: 0 | N9: 0 | O9: 0 | P9: 0 | Q9: 0 | R9: 0 | S9: 0 | T9: 0 | U9: 0 | V9: 0 | W9: 0 | X9: 0 | Y9: 0 | Z9: 0 | AA9: 0 | AB9: 0 | AC9: 0 | AD9: 0 | AE9: 0
A10: petroleum gasoline ($/BTU) | B10: 0 | C10: 0 | D10: 0 | E10: 0 | F10: 0 | G10: 0 | H10: 0 | I10: 0 | J10: 0 | K10: 0 | L10: 0 | M10: 0 | N10: 0 | O10: 0 | P10: 0 | Q10: 0 | R10: 0 | S10: 0 | T10: 0 | U10: 0 | V10: 0 | W10: 0 | X10: 0 | Y10: 0 | Z10: 0 | AA10: 0 | AB10: 0 | AC10: 0 | AD10: 0 | AE10: 0
A11: petroleum diesel ($/BTU) | B11: 0 | C11: 0 | D11: 0 | E11: 0 | F11: 0 | G11: 0 | H11: 0 | I11: 0 | J11: 0 | K11: 0 | L11: 0 | M11: 0 | N11: 0 | O11: 0 | P11: 0 | Q11: 0 | R11: 0 | S11: 0 | T11: 0 | U11: 0 | V11: 0 | W11: 0 | X11: 0 | Y11: 0 | Z11: 0 | AA11: 0 | AB11: 0 | AC11: 0 | AD11: 0 | AE11: 0
A12: biofuel gasoline | B12: 0 | C12: 0 | D12: 0 | E12: 0 | F12: 0 | G12: 0 | H12: 0 | I12: 0 | J12: 0 | K12: 0 | L12: 0 | M12: 0 | N12: 0 | O12: 0 | P12: 0 | Q12: 0 | R12: 0 | S12: 0 | T12: 0 | U12: 0 | V12: 0 | W12: 0 | X12: 0 | Y12: 0 | Z12: 0 | AA12: 0 | AB12: 0 | AC12: 0 | AD12: 0 | AE12: 0
... A22: hydrogen ($/BTU) | B22: 0 | C22: 0 | D22: 0 | E22: 0 | F22: 0 | G22: 0 | H22: 0 | I22: 0 | J22: 0 | K22: 0 | L22: 0 | M22: 0 | N22: 0 | O22: 0 | P22: 0 | Q22: 0 | R22: 0 | S22: 0 | T22: 0 | U22: 0 | V22: 0 | W22: 0 | X22: 0 | Y22: 0 | Z22: 0 | AA22: 0 | AB22: 0 | AC22: 0 | AD22: 0 | AE22: 0

Sheet BS-BSfTFpEUP-dist-heat-hydgn
A1: Year | B1: 2021 | C1: 2022 | D1: 2023 | E1: 2024 | F1: 2025 | G1: 2026 | H1: 2027 | I1: 2028 | J1: 2029 | K1: 2030 | L1: 2031 | M1: 2032 | N1: 2033 | O1: 2034 | P1: 2035 | Q1: 2036 | R1: 2037 | S1: 2038 | T1: 2039 | U1: 2040 | V1: 2041 | W1: 2042 | X1: 2043 | Y1: 2044 | Z1: 2045 | AA1: 2046 | AB1: 2047 | AC1: 2048 | AD1: 2049 | AE1: 2050
A2: electricity | B2: 0 | C2: 0 | D2: 0 | E2: 0 | F2: 0 | G2: 0 | H2: 0 | I2: 0 | J2: 0 | K2: 0 | L2: 0 | M2: 0 | N2: 0 | O2: 0 | P2: 0 | Q2: 0 | R2: 0 | S2: 0 | T2: 0 | U2: 0 | V2: 0 | W2: 0 | X2: 0 | Y2: 0 | Z2: 0 | AA2: 0 | AB2: 0 | AC2: 0 | AD2: 0 | AE2: 0
A3: hard coal ($/BTU) | B3: 0 | C3: 0 | D3: 0 | E3: 0 | F3: 0 | G3: 0 | H3: 0 | I3: 0 | J3: 0 | K3: 0 | L3: 0 | M3: 0 | N3: 0 | O3: 0 | P3: 0 | Q3: 0 | R3: 0 | S3: 0 | T3: 0 | U3: 0 | V3: 0 | W3: 0 | X3: 0 | Y3: 0 | Z3: 0 | AA3: 0 | AB3: 0 | AC3: 0 | AD3: 0 | AE3: 0
A4: natural gas ($/BTU) | B4: 0 | C4: 0 | D4: 0 | E4: 0 | F4: 0 | G4: 0 | H4: 0 | I4: 0 | J4: 0 | K4: 0 | L4: 0 | M4: 0 | N4: 0 | O4: 0 | P4: 0 | Q4: 0 | R4: 0 | S4: 0 | T4: 0 | U4: 0 | V4: 0 | W4: 0 | X4: 0 | Y4: 0 | Z4: 0 | AA4: 0 | AB4: 0 | AC4: 0 | AD4: 0 | AE4: 0
A5: nuclear | B5: 0 | C5: 0 | D5: 0 | E5: 0 | F5: 0 | G5: 0 | H5: 0 | I5: 0 | J5: 0 | K5: 0 | L5: 0 | M5: 0 | N5: 0 | O5: 0 | P5: 0 | Q5: 0 | R5: 0 | S5: 0 | T5: 0 | U5: 0 | V5: 0 | W5: 0 | X5: 0 | Y5: 0 | Z5: 0 | AA5: 0 | AB5: 0 | AC5: 0 | AD5: 0 | AE5: 0
A6: hydro | B6: 0 | C6: 0 | D6: 0 | E6: 0 | F6: 0 | G6: 0 | H6: 0 | I6: 0 | J6: 0 | K6: 0 | L6: 0 | M6: 0 | N6: 0 | O6: 0 | P6: 0 | Q6: 0 | R6: 0 | S6: 0 | T6: 0 | U6: 0 | V6: 0 | W6: 0 | X6: 0 | Y6: 0 | Z6: 0 | AA6: 0 | AB6: 0 | AC6: 0 | AD6: 0 | AE6: 0
A7: wind | B7: 0 | C7: 0 | D7: 0 | E7: 0 | F7: 0 | G7: 0 | H7: 0 | I7: 0 | J7: 0 | K7: 0 | L7: 0 | M7: 0 | N7: 0 | O7: 0 | P7: 0 | Q7: 0 | R7: 0 | S7: 0 | T7: 0 | U7: 0 | V7: 0 | W7: 0 | X7: 0 | Y7: 0 | Z7: 0 | AA7: 0 | AB7: 0 | AC7: 0 | AD7: 0 | AE7: 0
A8: solar | B8: 0 | C8: 0 | D8: 0 | E8: 0 | F8: 0 | G8: 0 | H8: 0 | I8: 0 | J8: 0 | K8: 0 | L8: 0 | M8: 0 | N8: 0 | O8: 0 | P8: 0 | Q8: 0 | R8: 0 | S8: 0 | T8: 0 | U8: 0 | V8: 0 | W8: 0 | X8: 0 | Y8: 0 | Z8: 0 | AA8: 0 | AB8: 0 | AC8: 0 | AD8: 0 | AE8: 0
A9: biomass ($/BTU) | B9: 0 | C9: 0 | D9: 0 | E9: 0 | F9: 0 | G9: 0 | H9: 0 | I9: 0 | J9: 0 | K9: 0 | L9: 0 | M9: 0 | N9: 0 | O9: 0 | P9: 0 | Q9: 0 | R9: 0 | S9: 0 | T9: 0 | U9: 0 | V9: 0 | W9: 0 | X9: 0 | Y9: 0 | Z9: 0 | AA9: 0 | AB9: 0 | AC9: 0 | AD9: 0 | AE9: 0
A10: petroleum gasoline ($/BTU) | B10: 0 | C10: 0 | D10: 0 | E10: 0 | F10: 0 | G10: 0 | H10: 0 | I10: 0 | J10: 0 | K10: 0 | L10: 0 | M10: 0 | N10: 0 | O10: 0 | P10: 0 | Q10: 0 | R10: 0 | S10: 0 | T10: 0 | U10: 0 | V10: 0 | W10: 0 | X10: 0 | Y10: 0 | Z10: 0 | AA10: 0 | AB10: 0 | AC10: 0 | AD10: 0 | AE10: 0
A11: petroleum diesel ($/BTU) | B11: 0 | C11: 0 | D11: 0 | E11: 0 | F11: 0 | G11: 0 | H11: 0 | I11: 0 | J11: 0 | K11: 0 | L11: 0 | M11: 0 | N11: 0 | O11: 0 | P11: 0 | Q11: 0 | R11: 0 | S11: 0 | T11: 0 | U11: 0 | V11: 0 | W11: 0 | X11: 0 | Y11: 0 | Z11: 0 | AA11: 0 | AB11: 0 | AC11: 0 | AD11: 0 | AE11: 0
A12: biofuel gasoline | B12: 0 | C12: 0 | D12: 0 | E12: 0 | F12: 0 | G12: 0 | H12: 0 | I12: 0 | J12: 0 | K12: 0 | L12: 0 | M12: 0 | N12: 0 | O12: 0 | P12: 0 | Q12: 0 | R12: 0 | S12: 0 | T12: 0 | U12: 0 | V12: 0 | W12: 0 | X12: 0 | Y12: 0 | Z12: 0 | AA12: 0 | AB12: 0 | AC12: 0 | AD12: 0 | AE12: 0
... A22: hydrogen ($/BTU) | B22: 0 | C22: 0 | D22: 0 | E22: 0 | F22: 0 | G22: 0 | H22: 0 | I22: 0 | J22: 0 | K22: 0 | L22: 0 | M22: 0 | N22: 0 | O22: 0 | P22: 0 | Q22: 0 | R22: 0 | S22: 0 | T22: 0 | U22: 0 | V22: 0 | W22: 0 | X22: 0 | Y22: 0 | Z22: 0 | AA22: 0 | AB22: 0 | AC22: 0 | AD22: 0 | AE22: 0

Sheet BS-BSfTFpEUP-geoeng
A1: Year | B1: 2021 | C1: 2022 | D1: 2023 | E1: 2024 | F1: 2025 | G1: 2026 | H1: 2027 | I1: 2028 | J1: 2029 | K1: 2030 | L1: 2031 | M1: 2032 | N1: 2033 | O1: 2034 | P1: 2035 | Q1: 2036 | R1: 2037 | S1: 2038 | T1: 2039 | U1: 2040 | V1: 2041 | W1: 2042 | X1: 2043 | Y1: 2044 | Z1: 2045 | AA1: 2046 | AB1: 2047 | AC1: 2048 | AD1: 2049 | AE1: 2050
A2: electricity | B2: 0 | C2: 0 | D2: 0 | E2: 0 | F2: 0 | G2: 0 | H2: 0 | I2: 0 | J2: 0 | K2: 0 | L2: 0 | M2: 0 | N2: 0 | O2: 0 | P2: 0 | Q2: 0 | R2: 0 | S2: 0 | T2: 0 | U2: 0 | V2: 0 | W2: 0 | X2: 0 | Y2: 0 | Z2: 0 | AA2: 0 | AB2: 0 | AC2: 0 | AD2: 0 | AE2: 0
A3: hard coal ($/BTU) | B3: 0 | C3: 0 | D3: 0 | E3: 0 | F3: 0 | G3: 0 | H3: 0 | I3: 0 | J3: 0 | K3: 0 | L3: 0 | M3: 0 | N3: 0 | O3: 0 | P3: 0 | Q3: 0 | R3: 0 | S3: 0 | T3: 0 | U3: 0 | V3: 0 | W3: 0 | X3: 0 | Y3: 0 | Z3: 0 | AA3: 0 | AB3: 0 | AC3: 0 | AD3: 0 | AE3: 0
A4: natural gas ($/BTU) | B4: 0 | C4: 0 | D4: 0 | E4: 0 | F4: 0 | G4: 0 | H4: 0 | I4: 0 | J4: 0 | K4: 0 | L4: 0 | M4: 0 | N4: 0 | O4: 0 | P4: 0 | Q4: 0 | R4: 0 | S4: 0 | T4: 0 | U4: 0 | V4: 0 | W4: 0 | X4: 0 | Y4: 0 | Z4: 0 | AA4: 0 | AB4: 0 | AC4: 0 | AD4: 0 | AE4: 0
A5: nuclear | B5: 0 | C5: 0 | D5: 0 | E5: 0 | F5: 0 | G5: 0 | H5: 0 | I5: 0 | J5: 0 | K5: 0 | L5: 0 | M5: 0 | N5: 0 | O5: 0 | P5: 0 | Q5: 0 | R5: 0 | S5: 0 | T5: 0 | U5: 0 | V5: 0 | W5: 0 | X5: 0 | Y5: 0 | Z5: 0 | AA5: 0 | AB5: 0 | AC5: 0 | AD5: 0 | AE5: 0
A6: hydro | B6: 0 | C6: 0 | D6: 0 | E6: 0 | F6: 0 | G6: 0 | H6: 0 | I6: 0 | J6: 0 | K6: 0 | L6: 0 | M6: 0 | N6: 0 | O6: 0 | P6: 0 | Q6: 0 | R6: 0 | S6: 0 | T6: 0 | U6: 0 | V6: 0 | W6: 0 | X6: 0 | Y6: 0 | Z6: 0 | AA6: 0 | AB6: 0 | AC6: 0 | AD6: 0 | AE6: 0
A7: wind | B7: 0 | C7: 0 | D7: 0 | E7: 0 | F7: 0 | G7: 0 | H7: 0 | I7: 0 | J7: 0 | K7: 0 | L7: 0 | M7: 0 | N7: 0 | O7: 0 | P7: 0 | Q7: 0 | R7: 0 | S7: 0 | T7: 0 | U7: 0 | V7: 0 | W7: 0 | X7: 0 | Y7: 0 | Z7: 0 | AA7: 0 | AB7: 0 | AC7: 0 | AD7: 0 | AE7: 0
A8: solar | B8: 0 | C8: 0 | D8: 0 | E8: 0 | F8: 0 | G8: 0 | H8: 0 | I8: 0 | J8: 0 | K8: 0 | L8: 0 | M8: 0 | N8: 0 | O8: 0 | P8: 0 | Q8: 0 | R8: 0 | S8: 0 | T8: 0 | U8: 0 | V8: 0 | W8: 0 | X8: 0 | Y8: 0 | Z8: 0 | AA8: 0 | AB8: 0 | AC8: 0 | AD8: 0 | AE8: 0
A9: biomass ($/BTU) | B9: 0 | C9: 0 | D9: 0 | E9: 0 | F9: 0 | G9: 0 | H9: 0 | I9: 0 | J9: 0 | K9: 0 | L9: 0 | M9: 0 | N9: 0 | O9: 0 | P9: 0 | Q9: 0 | R9: 0 | S9: 0 | T9: 0 | U9: 0 | V9: 0 | W9: 0 | X9: 0 | Y9: 0 | Z9: 0 | AA9: 0 | AB9: 0 | AC9: 0 | AD9: 0 | AE9: 0
A10: petroleum gasoline ($/BTU) | B10: 0 | C10: 0 | D10: 0 | E10: 0 | F10: 0 | G10: 0 | H10: 0 | I10: 0 | J10: 0 | K10: 0 | L10: 0 | M10: 0 | N10: 0 | O10: 0 | P10: 0 | Q10: 0 | R10: 0 | S10: 0 | T10: 0 | U10: 0 | V10: 0 | W10: 0 | X10: 0 | Y10: 0 | Z10: 0 | AA10: 0 | AB10: 0 | AC10: 0 | AD10: 0 | AE10: 0
A11: petroleum diesel ($/BTU) | B11: 0 | C11: 0 | D11: 0 | E11: 0 | F11: 0 | G11: 0 | H11: 0 | I11: 0 | J11: 0 | K11: 0 | L11: 0 | M11: 0 | N11: 0 | O11: 0 | P11: 0 | Q11: 0 | R11: 0 | S11: 0 | T11: 0 | U11: 0 | V11: 0 | W11: 0 | X11: 0 | Y11: 0 | Z11: 0 | AA11: 0 | AB11: 0 | AC11: 0 | AD11: 0 | AE11: 0
A12: biofuel gasoline | B12: 0 | C12: 0 | D12: 0 | E12: 0 | F12: 0 | G12: 0 | H12: 0 | I12: 0 | J12: 0 | K12: 0 | L12: 0 | M12: 0 | N12: 0 | O12: 0 | P12: 0 | Q12: 0 | R12: 0 | S12: 0 | T12: 0 | U12: 0 | V12: 0 | W12: 0 | X12: 0 | Y12: 0 | Z12: 0 | AA12: 0 | AB12: 0 | AC12: 0 | AD12: 0 | AE12: 0
... A22: hydrogen ($/BTU) | B22: 0 | C22: 0 | D22: 0 | E22: 0 | F22: 0 | G22: 0 | H22: 0 | I22: 0 | J22: 0 | K22: 0 | L22: 0 | M22: 0 | N22: 0 | O22: 0 | P22: 0 | Q22: 0 | R22: 0 | S22: 0 | T22: 0 | U22: 0 | V22: 0 | W22: 0 | X22: 0 | Y22: 0 | Z22: 0 | AA22: 0 | AB22: 0 | AC22: 0 | AD22: 0 | AE22: 0

Sheet BS-BSpUEO
A1: Year | B1: 2021 | C1: 2022 | D1: 2023 | E1: 2024 | F1: 2025 | G1: 2026 | H1: 2027 | I1: 2028 | J1: 2029 | K1: 2030 | L1: 2031 | M1: 2032 | N1: 2033 | O1: 2034 | P1: 2035 | Q1: 2036 | R1: 2037 | S1: 2038 | T1: 2039 | U1: 2040 | V1: 2041 | W1: 2042 | X1: 2043 | Y1: 2044 | Z1: 2045 | AA1: 2046 | AB1: 2047 | AC1: 2048 | AD1: 2049 | AE1: 2050
A2: hard coal | B2: 0 | C2: 0 | D2: 0 | E2: 0 | F2: 0 | G2: 0 | H2: 0 | I2: 0 | J2: 0 | K2: 0 | L2: 0 | M2: 0 | N2: 0 | O2: 0 | P2: 0 | Q2: 0 | R2: 0 | S2: 0 | T2: 0 | U2: 0 | V2: 0 | W2: 0 | X2: 0 | Y2: 0 | Z2: 0 | AA2: 0 | AB2: 0 | AC2: 0 | AD2: 0 | AE2: 0
A3: natural gas steam turbine | B3: 0 | C3: 0 | D3: 0 | E3: 0 | F3: 0 | G3: 0 | H3: 0 | I3: 0 | J3: 0 | K3: 0 | L3: 0 | M3: 0 | N3: 0 | O3: 0 | P3: 0 | Q3: 0 | R3: 0 | S3: 0 | T3: 0 | U3: 0 | V3: 0 | W3: 0 | X3: 0 | Y3: 0 | Z3: 0 | AA3: 0 | AB3: 0 | AC3: 0 | AD3: 0 | AE3: 0
A4: natural gas combined cycle | B4: 0 | C4: 0 | D4: 0 | E4: 0 | F4: 0 | G4: 0 | H4: 0 | I4: 0 | J4: 0 | K4: 0 | L4: 0 | M4: 0 | N4: 0 | O4: 0 | P4: 0 | Q4: 0 | R4: 0 | S4: 0 | T4: 0 | U4: 0 | V4: 0 | W4: 0 | X4: 0 | Y4: 0 | Z4: 0 | AA4: 0 | AB4: 0 | AC4: 0 | AD4: 0 | AE4: 0
A5: nuclear | B5: 0 | C5: 0 | D5: 0 | E5: 0 | F5: 0 | G5: 0 | H5: 0 | I5: 0 | J5: 0 | K5: 0 | L5: 0 | M5: 0 | N5: 0 | O5: 0 | P5: 0 | Q5: 0 | R5: 0 | S5: 0 | T5: 0 | U5: 0 | V5: 0 | W5: 0 | X5: 0 | Y5: 0 | Z5: 0 | AA5: 0 | AB5: 0 | AC5: 0 | AD5: 0 | AE5: 0
A6: hydro | B6: 0 | C6: 0 | D6: 0 | E6: 0 | F6: 0 | G6: 0 | H6: 0 | I6: 0 | J6: 0 | K6: 0 | L6: 0 | M6: 0 | N6: 0 | O6: 0 | P6: 0 | Q6: 0 | R6: 0 | S6: 0 | T6: 0 | U6: 0 | V6: 0 | W6: 0 | X6: 0 | Y6: 0 | Z6: 0 | AA6: 0 | AB6: 0 | AC6: 0 | AD6: 0 | AE6: 0
A7: onshore wind | B7: 0 | C7: 0 | D7: 0 | E7: 0 | F7: 0 | G7: 0 | H7: 0 | I7: 0 | J7: 0 | K7: 0 | L7: 0 | M7: 0 | N7: 0 | O7: 0 | P7: 0 | Q7: 0 | R7: 0 | S7: 0 | T7: 0 | U7: 0 | V7: 0 | W7: 0 | X7: 0 | Y7: 0 | Z7: 0 | AA7: 0 | AB7: 0 | AC7: 0 | AD7: 0 | AE7: 0
A8: solar PV | B8: 0 | C8: 0 | D8: 0 | E8: 0 | F8: 0 | G8: 0 | H8: 0 | I8: 0 | J8: 0 | K8: 0 | L8: 0 | M8: 0 | N8: 0 | O8: 0 | P8: 0 | Q8: 0 | R8: 0 | S8: 0 | T8: 0 | U8: 0 | V8: 0 | W8: 0 | X8: 0 | Y8: 0 | Z8: 0 | AA8: 0 | AB8: 0 | AC8: 0 | AD8: 0 | AE8: 0
A9: solar thermal | B9: 0 | C9: 0 | D9: 0 | E9: 0 | F9: 0 | G9: 0 | H9: 0 | I9: 0 | J9: 0 | K9: 0 | L9: 0 | M9: 0 | N9: 0 | O9: 0 | P9: 0 | Q9: 0 | R9: 0 | S9: 0 | T9: 0 | U9: 0 | V9: 0 | W9: 0 | X9: 0 | Y9: 0 | Z9: 0 | AA9: 0 | AB9: 0 | AC9: 0 | AD9: 0 | AE9: 0
A10: biomass | B10: 0 | C10: 0 | D10: 0 | E10: 0 | F10: 0 | G10: 0 | H10: 0 | I10: 0 | J10: 0 | K10: 0 | L10: 0 | M10: 0 | N10: 0 | O10: 0 | P10: 0 | Q10: 0 | R10: 0 | S10: 0 | T10: 0 | U10: 0 | V10: 0 | W10: 0 | X10: 0 | Y10: 0 | Z10: 0 | AA10: 0 | AB10: 0 | AC10: 0 | AD10: 0 | AE10: 0
A11: geothermal | B11: 0 | C11: 0 | D11: 0 | E11: 0 | F11: 0 | G11: 0 | H11: 0 | I11: 0 | J11: 0 | K11: 0 | L11: 0 | M11: 0 | N11: 0 | O11: 0 | P11: 0 | Q11: 0 | R11: 0 | S11: 0 | T11: 0 | U11: 0 | V11: 0 | W11: 0 | X11: 0 | Y11: 0 | Z11: 0 | AA11: 0 | AB11: 0 | AC11: 0 | AD11: 0 | AE11: 0
A12: petroleum | B12: 0 | C12: 0 | D12: 0 | E12: 0 | F12: 0 | G12: 0 | H12: 0 | I12: 0 | J12: 0 | K12: 0 | L12: 0 | M12: 0 | N12: 0 | O12: 0 | P12: 0 | Q12: 0 | R12: 0 | S12: 0 | T12: 0 | U12: 0 | V12: 0 | W12: 0 | X12: 0 | Y12: 0 | Z12: 0 | AA12: 0 | AB12: 0 | AC12: 0 | AD12: 0 | AE12: 0
A13: natural gas peaker | B13: 0 | C13: 0 | D13: 0 | E13: 0 | F13: 0 | G13: 0 | H13: 0 | I13: 0 | J13: 0 | K13: 0 | L13: 0 | M13: 0 | N13: 0 | O13: 0 | P13: 0 | Q13: 0 | R13: 0 | S13: 0 | T13: 0 | U13: 0 | V13: 0 | W13: 0 | X13: 0 | Y13: 0 | Z13: 0 | AA13: 0 | AB13: 0 | AC13: 0 | AD13: 0 | AE13: 0
A14: lignite | B14: =B2*'Subsidies Paid'!$G$13 -> 0 | C14: =B14 -> 0 | D14: =C14 -> 0 | E14: =D14 -> 0 | F14: =E14 -> 0 | G14: =F14 -> 0 | H14: =G14 -> 0 | I14: =H14 -> 0 | J14: =I14 -> 0 | ... AE14: =AD14 -> 0
A15: offshore wind | B15: 0 | C15: 0 | D15: 0 | E15: 0 | F15: 0 | G15: 0 | H15: 0 | I15: 0 | J15: 0 | K15: 0 | L15: 0 | M15: 0 | N15: 0 | O15: 0 | P15: 0 | Q15: 0 | R15: 0 | S15: 0 | T15: 0 | U15: 0 | V15: 0 | W15: 0 | X15: 0 | Y15: 0 | Z15: 0 | AA15: 0 | AB15: 0 | AC15: 0 | AD15: 0 | AE15: 0
A16: crude oil | B16: =B12 -> 0 | C16: =C12 -> 0 | D16: =D12 -> 0 | E16: =E12 -> 0 | F16: =F12 -> 0 | G16: =G12 -> 0 | H16: =H12 -> 0 | I16: =I12 -> 0 | ... AE16: =AE12 -> 0
A17: heavy or residual fuel oil | B17: =B12 -> 0 | C17: =C12 -> 0 | D17: =D12 -> 0 | E17: =E12 -> 0 | F17: =F12 -> 0 | G17: =G12 -> 0 | H17: =H12 -> 0 | I17: =I12 -> 0 | ... AE17: =AE12 -> 0
A18: municipal solid waste | B18: 0 | C18: 0 | D18: 0 | E18: 0 | F18: 0 | G18: 0 | H18: 0 | I18: 0 | J18: 0 | K18: 0 | L18: 0 | M18: 0 | N18: 0 | O18: 0 | P18: 0 | Q18: 0 | R18: 0 | S18: 0 | T18: 0 | U18: 0 | V18: 0 | W18: 0 | X18: 0 | Y18: 0 | Z18: 0 | AA18: 0 | AB18: 0 | AC18: 0 | AD18: 0 | AE18: 0
A19: hard coal w CCS | B19: 0 | C19: 0 | D19: 0 | E19: 0 | F19: 0 | G19: 0 | H19: 0 | I19: 0 | J19: 0 | K19: 0 | L19: 0 | M19: 0 | N19: 0 | O19: 0 | P19: 0 | Q19: 0 | R19: 0 | S19: 0 | T19: 0 | U19: 0 | V19: 0 | W19: 0 | X19: 0 | Y19: 0 | Z19: 0 | AA19: 0 | AB19: 0 | AC19: 0 | AD19: 0 | AE19: 0
A20: natural gas combined cycle w CCS | B20: 0 | C20: 0 | D20: 0 | E20: 0 | F20: 0 | G20: 0 | H20: 0 | I20: 0 | J20: 0 | K20: 0 | L20: 0 | M20: 0 | N20: 0 | O20: 0 | P20: 0 | Q20: 0 | R20: 0 | S20: 0 | T20: 0 | U20: 0 | V20: 0 | W20: 0 | X20: 0 | Y20: 0 | Z20: 0 | AA20: 0 | AB20: 0 | AC20: 0 | AD20: 0 | AE20: 0
A21: biomass w CCS | B21: 0 | C21: 0 | D21: 0 | E21: 0 | F21: 0 | G21: 0 | H21: 0 | I21: 0 | J21: 0 | K21: 0 | L21: 0 | M21: 0 | N21: 0 | O21: 0 | P21: 0 | Q21: 0 | R21: 0 | S21: 0 | T21: 0 | U21: 0 | V21: 0 | W21: 0 | X21: 0 | Y21: 0 | Z21: 0 | AA21: 0 | AB21: 0 | AC21: 0 | AD21: 0 | AE21: 0
A22: lignite w CCS | B22: 0 | C22: 0 | D22: 0 | E22: 0 | F22: 0 | G22: 0 | H22: 0 | I22: 0 | J22: 0 | K22: 0 | L22: 0 | M22: 0 | N22: 0 | O22: 0 | P22: 0 | Q22: 0 | R22: 0 | S22: 0 | T22: 0 | U22: 0 | V22: 0 | W22: 0 | X22: 0 | Y22: 0 | Z22: 0 | AA22: 0 | AB22: 0 | AC22: 0 | AD22: 0 | AE22: 0
A23: small modular reactor | B23: 0 | C23: 0 | D23: 0 | E23: 0 | F23: 0 | G23: 0 | H23: 0 | I23: 0 | J23: 0 | K23: 0 | L23: 0 | M23: 0 | N23: 0 | O23: 0 | P23: 0 | Q23: 0 | R23: 0 | S23: 0 | T23: 0 | U23: 0 | V23: 0 | W23: 0 | X23: 0 | Y23: 0 | Z23: 0 | AA23: 0 | AB23: 0 | AC23: 0 | AD23: 0 | AE23: 0
A24: hydrogen combustion turbine | B24: 0 | C24: 0 | D24: 0 | E24: 0 | F24: 0 | G24: 0 | H24: 0 | I24: 0 | J24: 0 | K24: 0 | L24: 0 | M24: 0 | N24: 0 | O24: 0 | P24: 0 | Q24: 0 | R24: 0 | S24: 0 | T24: 0 | U24: 0 | V24: 0 | W24: 0 | X24: 0 | Y24: 0 | Z24: 0 | AA24: 0 | AB24: 0 | AC24: 0 | AD24: 0 | AE24: 0
A25: hydrogen combined cycle | B25: 0 | C25: 0 | D25: 0 | E25: 0 | F25: 0 | G25: 0 | H25: 0 | I25: 0 | J25: 0 | K25: 0 | L25: 0 | M25: 0 | N25: 0 | O25: 0 | P25: 0 | Q25: 0 | R25: 0 | S25: 0 | T25: 0 | U25: 0 | V25: 0 | W25: 0 | X25: 0 | Y25: 0 | Z25: 0 | AA25: 0 | AB25: 0 | AC25: 0 | AD25: 0 | AE25: 0

Sheet BS-BSpUEOfEP
A1: Year | B1: 2021 | C1: 2022 | D1: 2023 | E1: 2024 | F1: 2025 | G1: 2026 | H1: 2027 | I1: 2028 | J1: 2029 | K1: 2030 | L1: 2031 | M1: 2032 | N1: 2033 | O1: 2034 | P1: 2035 | Q1: 2036 | R1: 2037 | S1: 2038 | T1: 2039 | U1: 2040 | V1: 2041 | W1: 2042 | X1: 2043 | Y1: 2044 | Z1: 2045 | AA1: 2046 | AB1: 2047 | AC1: 2048 | AD1: 2049 | AE1: 2050
A2: hard coal | B2: ='Subsidies Paid'!G3/'Subsidies Paid'!N17 -> 0.082407725 | C2: =B2 -> 0.082407725 | D2: =C2 -> 0.082407725 | E2: =D2 -> 0.082407725 | F2: =E2 -> 0.082407725 | G2: =F2 -> 0.082407725 | H2: =G2 -> 0.082407725 | I2: =H2 -> 0.082407725 | J2: =I2 -> 0.082407725 | ... AE2: =AD2 -> 0.082407725
A3: natural gas steam turbine | B3: 0 | C3: 0 | D3: 0 | E3: 0 | F3: 0 | G3: 0 | H3: 0 | I3: 0 | J3: 0 | K3: 0 | L3: 0 | M3: 0 | N3: 0 | O3: 0 | P3: 0 | Q3: 0 | R3: 0 | S3: 0 | T3: 0 | U3: 0 | V3: 0 | W3: 0 | X3: 0 | Y3: 0 | Z3: 0 | AA3: 0 | AB3: 0 | AC3: 0 | AD3: 0 | AE3: 0
A4: natural gas combined cycle | B4: 0 | C4: 0 | D4: 0 | E4: 0 | F4: 0 | G4: 0 | H4: 0 | I4: 0 | J4: 0 | K4: 0 | L4: 0 | M4: 0 | N4: 0 | O4: 0 | P4: 0 | Q4: 0 | R4: 0 | S4: 0 | T4: 0 | U4: 0 | V4: 0 | W4: 0 | X4: 0 | Y4: 0 | Z4: 0 | AA4: 0 | AB4: 0 | AC4: 0 | AD4: 0 | AE4: 0
A5: nuclear | B5: 0 | C5: 0 | D5: 0 | E5: 0 | F5: 0 | G5: 0 | H5: 0 | I5: 0 | J5: 0 | K5: 0 | L5: 0 | M5: 0 | N5: 0 | O5: 0 | P5: 0 | Q5: 0 | R5: 0 | S5: 0 | T5: 0 | U5: 0 | V5: 0 | W5: 0 | X5: 0 | Y5: 0 | Z5: 0 | AA5: 0 | AB5: 0 | AC5: 0 | AD5: 0 | AE5: 0
A6: hydro | B6: 0 | C6: 0 | D6: 0 | E6: 0 | F6: 0 | G6: 0 | H6: 0 | I6: 0 | J6: 0 | K6: 0 | L6: 0 | M6: 0 | N6: 0 | O6: 0 | P6: 0 | Q6: 0 | R6: 0 | S6: 0 | T6: 0 | U6: 0 | V6: 0 | W6: 0 | X6: 0 | Y6: 0 | Z6: 0 | AA6: 0 | AB6: 0 | AC6: 0 | AD6: 0 | AE6: 0
A7: onshore wind | B7: 0 | C7: 0 | D7: 0 | E7: 0 | F7: 0 | G7: 0 | H7: 0 | I7: 0 | J7: 0 | K7: 0 | L7: 0 | M7: 0 | N7: 0 | O7: 0 | P7: 0 | Q7: 0 | R7: 0 | S7: 0 | T7: 0 | U7: 0 | V7: 0 | W7: 0 | X7: 0 | Y7: 0 | Z7: 0 | AA7: 0 | AB7: 0 | AC7: 0 | AD7: 0 | AE7: 0
A8: solar PV | B8: 0 | C8: 0 | D8: 0 | E8: 0 | F8: 0 | G8: 0 | H8: 0 | I8: 0 | J8: 0 | K8: 0 | L8: 0 | M8: 0 | N8: 0 | O8: 0 | P8: 0 | Q8: 0 | R8: 0 | S8: 0 | T8: 0 | U8: 0 | V8: 0 | W8: 0 | X8: 0 | Y8: 0 | Z8: 0 | AA8: 0 | AB8: 0 | AC8: 0 | AD8: 0 | AE8: 0
A9: solar thermal | B9: 0 | C9: 0 | D9: 0 | E9: 0 | F9: 0 | G9: 0 | H9: 0 | I9: 0 | J9: 0 | K9: 0 | L9: 0 | M9: 0 | N9: 0 | O9: 0 | P9: 0 | Q9: 0 | R9: 0 | S9: 0 | T9: 0 | U9: 0 | V9: 0 | W9: 0 | X9: 0 | Y9: 0 | Z9: 0 | AA9: 0 | AB9: 0 | AC9: 0 | AD9: 0 | AE9: 0
A10: biomass | B10: 0 | C10: 0 | D10: 0 | E10: 0 | F10: 0 | G10: 0 | H10: 0 | I10: 0 | J10: 0 | K10: 0 | L10: 0 | M10: 0 | N10: 0 | O10: 0 | P10: 0 | Q10: 0 | R10: 0 | S10: 0 | T10: 0 | U10: 0 | V10: 0 | W10: 0 | X10: 0 | Y10: 0 | Z10: 0 | AA10: 0 | AB10: 0 | AC10: 0 | AD10: 0 | AE10: 0
A11: geothermal | B11: 0 | C11: 0 | D11: 0 | E11: 0 | F11: 0 | G11: 0 | H11: 0 | I11: 0 | J11: 0 | K11: 0 | L11: 0 | M11: 0 | N11: 0 | O11: 0 | P11: 0 | Q11: 0 | R11: 0 | S11: 0 | T11: 0 | U11: 0 | V11: 0 | W11: 0 | X11: 0 | Y11: 0 | Z11: 0 | AA11: 0 | AB11: 0 | AC11: 0 | AD11: 0 | AE11: 0
A12: petroleum | B12: 0 | C12: 0 | D12: 0 | E12: 0 | F12: 0 | G12: 0 | H12: 0 | I12: 0 | J12: 0 | K12: 0 | L12: 0 | M12: 0 | N12: 0 | O12: 0 | P12: 0 | Q12: 0 | R12: 0 | S12: 0 | T12: 0 | U12: 0 | V12: 0 | W12: 0 | X12: 0 | Y12: 0 | Z12: 0 | AA12: 0 | AB12: 0 | AC12: 0 | AD12: 0 | AE12: 0
A13: natural gas peaker | B13: 0 | C13: 0 | D13: 0 | E13: 0 | F13: 0 | G13: 0 | H13: 0 | I13: 0 | J13: 0 | K13: 0 | L13: 0 | M13: 0 | N13: 0 | O13: 0 | P13: 0 | Q13: 0 | R13: 0 | S13: 0 | T13: 0 | U13: 0 | V13: 0 | W13: 0 | X13: 0 | Y13: 0 | Z13: 0 | AA13: 0 | AB13: 0 | AC13: 0 | AD13: 0 | AE13: 0
A14: lignite | B14: =B2 -> 0.082407725 | C14: =B14 -> 0.082407725 | D14: =C14 -> 0.082407725 | E14: =D14 -> 0.082407725 | F14: =E14 -> 0.082407725 | G14: =F14 -> 0.082407725 | H14: =G14 -> 0.082407725 | I14: =H14 -> 0.082407725 | J14: =I14 -> 0.082407725 | ... AE14: =AD14 -> 0.082407725
A15: offshore wind | B15: 0 | C15: 0 | D15: 0 | E15: 0 | F15: 0 | G15: 0 | H15: 0 | I15: 0 | J15: 0 | K15: 0 | L15: 0 | M15: 0 | N15: 0 | O15: 0 | P15: 0 | Q15: 0 | R15: 0 | S15: 0 | T15: 0 | U15: 0 | V15: 0 | W15: 0 | X15: 0 | Y15: 0 | Z15: 0 | AA15: 0 | AB15: 0 | AC15: 0 | AD15: 0 | AE15: 0
A16: crude oil | B16: =B12 -> 0 | C16: =C12 -> 0 | D16: =D12 -> 0 | E16: =E12 -> 0 | F16: =F12 -> 0 | G16: =G12 -> 0 | H16: =H12 -> 0 | I16: =I12 -> 0 | ... AE16: =AE12 -> 0
A17: heavy or residual fuel oil | B17: =B12 -> 0 | C17: =C12 -> 0 | D17: =D12 -> 0 | E17: =E12 -> 0 | F17: =F12 -> 0 | G17: =G12 -> 0 | H17: =H12 -> 0 | I17: =I12 -> 0 | ... AE17: =AE12 -> 0
A18: municipal solid waste | B18: 0 | C18: 0 | D18: 0 | E18: 0 | F18: 0 | G18: 0 | H18: 0 | I18: 0 | J18: 0 | K18: 0 | L18: 0 | M18: 0 | N18: 0 | O18: 0 | P18: 0 | Q18: 0 | R18: 0 | S18: 0 | T18: 0 | U18: 0 | V18: 0 | W18: 0 | X18: 0 | Y18: 0 | Z18: 0 | AA18: 0 | AB18: 0 | AC18: 0 | AD18: 0 | AE18: 0
A19: hard coal w CCS | B19: 0 | C19: 0 | D19: 0 | E19: 0 | F19: 0 | G19: 0 | H19: 0 | I19: 0 | J19: 0 | K19: 0 | L19: 0 | M19: 0 | N19: 0 | O19: 0 | P19: 0 | Q19: 0 | R19: 0 | S19: 0 | T19: 0 | U19: 0 | V19: 0 | W19: 0 | X19: 0 | Y19: 0 | Z19: 0 | AA19: 0 | AB19: 0 | AC19: 0 | AD19: 0 | AE19: 0
A20: natural gas combined cycle w CCS | B20: 0 | C20: 0 | D20: 0 | E20: 0 | F20: 0 | G20: 0 | H20: 0 | I20: 0 | J20: 0 | K20: 0 | L20: 0 | M20: 0 | N20: 0 | O20: 0 | P20: 0 | Q20: 0 | R20: 0 | S20: 0 | T20: 0 | U20: 0 | V20: 0 | W20: 0 | X20: 0 | Y20: 0 | Z20: 0 | AA20: 0 | AB20: 0 | AC20: 0 | AD20: 0 | AE20: 0
A21: biomass w CCS | B21: 0 | C21: 0 | D21: 0 | E21: 0 | F21: 0 | G21: 0 | H21: 0 | I21: 0 | J21: 0 | K21: 0 | L21: 0 | M21: 0 | N21: 0 | O21: 0 | P21: 0 | Q21: 0 | R21: 0 | S21: 0 | T21: 0 | U21: 0 | V21: 0 | W21: 0 | X21: 0 | Y21: 0 | Z21: 0 | AA21: 0 | AB21: 0 | AC21: 0 | AD21: 0 | AE21: 0
A22: lignite w CCS | B22: 0 | C22: 0 | D22: 0 | E22: 0 | F22: 0 | G22: 0 | H22: 0 | I22: 0 | J22: 0 | K22: 0 | L22: 0 | M22: 0 | N22: 0 | O22: 0 | P22: 0 | Q22: 0 | R22: 0 | S22: 0 | T22: 0 | U22: 0 | V22: 0 | W22: 0 | X22: 0 | Y22: 0 | Z22: 0 | AA22: 0 | AB22: 0 | AC22: 0 | AD22: 0 | AE22: 0
A23: small modular reactor | B23: 0 | C23: 0 | D23: 0 | E23: 0 | F23: 0 | G23: 0 | H23: 0 | I23: 0 | J23: 0 | K23: 0 | L23: 0 | M23: 0 | N23: 0 | O23: 0 | P23: 0 | Q23: 0 | R23: 0 | S23: 0 | T23: 0 | U23: 0 | V23: 0 | W23: 0 | X23: 0 | Y23: 0 | Z23: 0 | AA23: 0 | AB23: 0 | AC23: 0 | AD23: 0 | AE23: 0
A24: hydrogen combustion turbine | B24: 0 | C24: 0 | D24: 0 | E24: 0 | F24: 0 | G24: 0 | H24: 0 | I24: 0 | J24: 0 | K24: 0 | L24: 0 | M24: 0 | N24: 0 | O24: 0 | P24: 0 | Q24: 0 | R24: 0 | S24: 0 | T24: 0 | U24: 0 | V24: 0 | W24: 0 | X24: 0 | Y24: 0 | Z24: 0 | AA24: 0 | AB24: 0 | AC24: 0 | AD24: 0 | AE24: 0
A25: hydrogen combined cycle | B25: 0 | C25: 0 | D25: 0 | E25: 0 | F25: 0 | G25: 0 | H25: 0 | I25: 0 | J25: 0 | K25: 0 | L25: 0 | M25: 0 | N25: 0 | O25: 0 | P25: 0 | Q25: 0 | R25: 0 | S25: 0 | T25: 0 | U25: 0 | V25: 0 | W25: 0 | X25: 0 | Y25: 0 | Z25: 0 | AA25: 0 | AB25: 0 | AC25: 0 | AD25: 0 | AE25: 0

Sheet BS-BSpUECB
A1: % of capital costs | B1: 2021 | C1: 2022 | D1: 2023 | E1: 2024 | F1: 2025 | G1: 2026 | H1: 2027 | I1: 2028 | J1: 2029 | K1: 2030 | L1: 2031 | M1: 2032 | N1: 2033 | O1: 2034 | P1: 2035 | Q1: 2036 | R1: 2037 | S1: 2038 | T1: 2039 | U1: 2040 | V1: 2041 | W1: 2042 | X1: 2043 | Y1: 2044 | Z1: 2045 | AA1: 2046 | AB1: 2047 | AC1: 2048 | AD1: 2049 | AE1: 2050
A2: hard coal | B2: 0 | C2: 0 | D2: 0 | E2: 0 | F2: 0 | G2: 0 | H2: 0 | I2: 0 | J2: 0 | K2: 0 | L2: 0 | M2: 0 | N2: 0 | O2: 0 | P2: 0 | Q2: 0 | R2: 0 | S2: 0 | T2: 0 | U2: 0 | V2: 0 | W2: 0 | X2: 0 | Y2: 0 | Z2: 0 | AA2: 0 | AB2: 0 | AC2: 0 | AD2: 0 | AE2: 0
A3: natural gas steam turbine | B3: 0 | C3: 0 | D3: 0 | E3: 0 | F3: 0 | G3: 0 | H3: 0 | I3: 0 | J3: 0 | K3: 0 | L3: 0 | M3: 0 | N3: 0 | O3: 0 | P3: 0 | Q3: 0 | R3: 0 | S3: 0 | T3: 0 | U3: 0 | V3: 0 | W3: 0 | X3: 0 | Y3: 0 | Z3: 0 | AA3: 0 | AB3: 0 | AC3: 0 | AD3: 0 | AE3: 0
A4: natural gas combined cycle | B4: 0 | C4: 0 | D4: 0 | E4: 0 | F4: 0 | G4: 0 | H4: 0 | I4: 0 | J4: 0 | K4: 0 | L4: 0 | M4: 0 | N4: 0 | O4: 0 | P4: 0 | Q4: 0 | R4: 0 | S4: 0 | T4: 0 | U4: 0 | V4: 0 | W4: 0 | X4: 0 | Y4: 0 | Z4: 0 | AA4: 0 | AB4: 0 | AC4: 0 | AD4: 0 | AE4: 0
A5: nuclear | B5: 0 | C5: 0 | D5: 0 | E5: 0 | F5: 0 | G5: 0 | H5: 0 | I5: 0 | J5: 0 | K5: 0 | L5: 0 | M5: 0 | N5: 0 | O5: 0 | P5: 0 | Q5: 0 | R5: 0 | S5: 0 | T5: 0 | U5: 0 | V5: 0 | W5: 0 | X5: 0 | Y5: 0 | Z5: 0 | AA5: 0 | AB5: 0 | AC5: 0 | AD5: 0 | AE5: 0
A6: hydro | B6: =BSpUECB_세액공제액!C50 -> 0.03 | C6: =BSpUECB_세액공제액!D50 -> 0.03 | D6: =BSpUECB_세액공제액!E50 -> 0.03 | E6: =BSpUECB_세액공제액!F50 -> 0.03 | F6: =BSpUECB_세액공제액!G50 -> 0.03 | G6: =BSpUECB_세액공제액!H50 -> 0.03 | H6: =BSpUECB_세액공제액!I50 -> 0.03 | I6: =BSpUECB_세액공제액!J50 -> 0.03 | ... AE6: =BSpUECB_세액공제액!AF50 -> 0.03
A7: onshore wind | B7: =BSpUECB_세액공제액!C51 -> 0.028105282 | C7: =BSpUECB_세액공제액!D51 -> 0.028195061 | D7: =BSpUECB_세액공제액!E51 -> 0.028305322 | E7: =BSpUECB_세액공제액!F51 -> 0.028437531 | F7: =BSpUECB_세액공제액!G51 -> 0.028593251 | G7: =BSpUECB_세액공제액!H51 -> 0.028561139 | H7: =BSpUECB_세액공제액!I51 -> 0.028526038 | I7: =BSpUECB_세액공제액!J51 -> 0.028488266 | ... AE7: =BSpUECB_세액공제액!AF51 -> 0.028406019
A8: solar PV | B8: =BSpUECB_세액공제액!C52 -> 0.025411076 | C8: =BSpUECB_세액공제액!D52 -> 0.025513356 | D8: =BSpUECB_세액공제액!E52 -> 0.025680469 | E8: =BSpUECB_세액공제액!F52 -> 0.025923319 | F8: =BSpUECB_세액공제액!G52 -> 0.026254754 | G8: =BSpUECB_세액공제액!H52 -> 0.026195638 | H8: =BSpUECB_세액공제액!I52 -> 0.026150523 | I8: =BSpUECB_세액공제액!J52 -> 0.026123023 | ... AE8: =BSpUECB_세액공제액!AF52 -> 0.026137331
A9: solar thermal | B9: 0 | C9: 0 | D9: 0 | E9: 0 | F9: 0 | G9: 0 | H9: 0 | I9: 0 | J9: 0 | K9: 0 | L9: 0 | M9: 0 | N9: 0 | O9: 0 | P9: 0 | Q9: 0 | R9: 0 | S9: 0 | T9: 0 | U9: 0 | V9: 0 | W9: 0 | X9: 0 | Y9: 0 | Z9: 0 | AA9: 0 | AB9: 0 | AC9: 0 | AD9: 0 | AE9: 0
A10: biomass | B10: =BSpUECB_세액공제액!B54 -> 0.03 | C10: =BSpUECB_세액공제액!C54 -> 0.03 | D10: =BSpUECB_세액공제액!D54 -> 0.03 | E10: =BSpUECB_세액공제액!E54 -> 0.03 | F10: =BSpUECB_세액공제액!F54 -> 0.03 | G10: =BSpUECB_세액공제액!G54 -> 0.03 | H10: =BSpUECB_세액공제액!H54 -> 0.03 | I10: =BSpUECB_세액공제액!I54 -> 0.03 | ... AE10: =BSpUECB_세액공제액!AE54 -> 0.03
A11: geothermal | B11: 0 | C11: 0 | D11: 0 | E11: 0 | F11: 0 | G11: 0 | H11: 0 | I11: 0 | J11: 0 | K11: 0 | L11: 0 | M11: 0 | N11: 0 | O11: 0 | P11: 0 | Q11: 0 | R11: 0 | S11: 0 | T11: 0 | U11: 0 | V11: 0 | W11: 0 | X11: 0 | Y11: 0 | Z11: 0 | AA11: 0 | AB11: 0 | AC11: 0 | AD11: 0 | AE11: 0
A12: petroleum | B12: 0 | C12: 0 | D12: 0 | E12: 0 | F12: 0 | G12: 0 | H12: 0 | I12: 0 | J12: 0 | K12: 0 | L12: 0 | M12: 0 | N12: 0 | O12: 0 | P12: 0 | Q12: 0 | R12: 0 | S12: 0 | T12: 0 | U12: 0 | V12: 0 | W12: 0 | X12: 0 | Y12: 0 | Z12: 0 | AA12: 0 | AB12: 0 | AC12: 0 | AD12: 0 | AE12: 0
A13: natural gas peaker | B13: 0 | C13: 0 | D13: 0 | E13: 0 | F13: 0 | G13: 0 | H13: 0 | I13: 0 | J13: 0 | K13: 0 | L13: 0 | M13: 0 | N13: 0 | O13: 0 | P13: 0 | Q13: 0 | R13: 0 | S13: 0 | T13: 0 | U13: 0 | V13: 0 | W13: 0 | X13: 0 | Y13: 0 | Z13: 0 | AA13: 0 | AB13: 0 | AC13: 0 | AD13: 0 | AE13: 0
A14: lignite | B14: 0 | C14: 0 | D14: 0 | E14: 0 | F14: 0 | G14: 0 | H14: 0 | I14: 0 | J14: 0 | K14: 0 | L14: 0 | M14: 0 | N14: 0 | O14: 0 | P14: 0 | Q14: 0 | R14: 0 | S14: 0 | T14: 0 | U14: 0 | V14: 0 | W14: 0 | X14: 0 | Y14: 0 | Z14: 0 | AA14: 0 | AB14: 0 | AC14: 0 | AD14: 0 | AE14: 0
A15: offshore wind | B15: =BSpUECB_세액공제액!B59 -> 0.026708689 | C15: =BSpUECB_세액공제액!C59 -> 0.026708689 | D15: =BSpUECB_세액공제액!D59 -> 0.026708689 | E15: =BSpUECB_세액공제액!E59 -> 0.026708689 | F15: =BSpUECB_세액공제액!F59 -> 0.026708689 | G15: =BSpUECB_세액공제액!G59 -> 0.026708689 | H15: =BSpUECB_세액공제액!H59 -> 0.026708689 | I15: =BSpUECB_세액공제액!I59 -> 0.026708689 | ... AE15: =BSpUECB_세액공제액!AE59 -> 0.026708689
A16: crude oil | B16: 0 | C16: 0 | D16: 0 | E16: 0 | F16: 0 | G16: 0 | H16: 0 | I16: 0 | J16: 0 | K16: 0 | L16: 0 | M16: 0 | N16: 0 | O16: 0 | P16: 0 | Q16: 0 | R16: 0 | S16: 0 | T16: 0 | U16: 0 | V16: 0 | W16: 0 | X16: 0 | Y16: 0 | Z16: 0 | AA16: 0 | AB16: 0 | AC16: 0 | AD16: 0 | AE16: 0
A17: heavy or residual fuel oil | B17: 0 | C17: 0 | D17: 0 | E17: 0 | F17: 0 | G17: 0 | H17: 0 | I17: 0 | J17: 0 | K17: 0 | L17: 0 | M17: 0 | N17: 0 | O17: 0 | P17: 0 | Q17: 0 | R17: 0 | S17: 0 | T17: 0 | U17: 0 | V17: 0 | W17: 0 | X17: 0 | Y17: 0 | Z17: 0 | AA17: 0 | AB17: 0 | AC17: 0 | AD17: 0 | AE17: 0
A18: municipal solid waste | B18: 0 | C18: 0 | D18: 0 | E18: 0 | F18: 0 | G18: 0 | H18: 0 | I18: 0 | J18: 0 | K18: 0 | L18: 0 | M18: 0 | N18: 0 | O18: 0 | P18: 0 | Q18: 0 | R18: 0 | S18: 0 | T18: 0 | U18: 0 | V18: 0 | W18: 0 | X18: 0 | Y18: 0 | Z18: 0 | AA18: 0 | AB18: 0 | AC18: 0 | AD18: 0 | AE18: 0
A19: hard coal w CCS | B19: 0 | C19: 0 | D19: 0 | E19: 0 | F19: 0 | G19: 0 | H19: 0 | I19: 0 | J19: 0 | K19: 0 | L19: 0 | M19: 0 | N19: 0 | O19: 0 | P19: 0 | Q19: 0 | R19: 0 | S19: 0 | T19: 0 | U19: 0 | V19: 0 | W19: 0 | X19: 0 | Y19: 0 | Z19: 0 | AA19: 0 | AB19: 0 | AC19: 0 | AD19: 0 | AE19: 0
A20: natural gas combined cycle w CCS | B20: 0 | C20: 0 | D20: 0 | E20: 0 | F20: 0 | G20: 0 | H20: 0 | I20: 0 | J20: 0 | K20: 0 | L20: 0 | M20: 0 | N20: 0 | O20: 0 | P20: 0 | Q20: 0 | R20: 0 | S20: 0 | T20: 0 | U20: 0 | V20: 0 | W20: 0 | X20: 0 | Y20: 0 | Z20: 0 | AA20: 0 | AB20: 0 | AC20: 0 | AD20: 0 | AE20: 0
A21: biomass w CCS | B21: 0 | C21: 0 | D21: 0 | E21: 0 | F21: 0 | G21: 0 | H21: 0 | I21: 0 | J21: 0 | K21: 0 | L21: 0 | M21: 0 | N21: 0 | O21: 0 | P21: 0 | Q21: 0 | R21: 0 | S21: 0 | T21: 0 | U21: 0 | V21: 0 | W21: 0 | X21: 0 | Y21: 0 | Z21: 0 | AA21: 0 | AB21: 0 | AC21: 0 | AD21: 0 | AE21: 0
A22: lignite w CCS | B22: 0 | C22: 0 | D22: 0 | E22: 0 | F22: 0 | G22: 0 | H22: 0 | I22: 0 | J22: 0 | K22: 0 | L22: 0 | M22: 0 | N22: 0 | O22: 0 | P22: 0 | Q22: 0 | R22: 0 | S22: 0 | T22: 0 | U22: 0 | V22: 0 | W22: 0 | X22: 0 | Y22: 0 | Z22: 0 | AA22: 0 | AB22: 0 | AC22: 0 | AD22: 0 | AE22: 0
A23: small modular reactor | B23: 0 | C23: 0 | D23: 0 | E23: 0 | F23: 0 | G23: 0 | H23: 0 | I23: 0 | J23: 0 | K23: 0 | L23: 0 | M23: 0 | N23: 0 | O23: 0 | P23: 0 | Q23: 0 | R23: 0 | S23: 0 | T23: 0 | U23: 0 | V23: 0 | W23: 0 | X23: 0 | Y23: 0 | Z23: 0 | AA23: 0 | AB23: 0 | AC23: 0 | AD23: 0 | AE23: 0
A24: hydrogen combustion turbine | B24: 0 | C24: 0 | D24: 0 | E24: 0 | F24: 0 | G24: 0 | H24: 0 | I24: 0 | J24: 0 | K24: 0 | L24: 0 | M24: 0 | N24: 0 | O24: 0 | P24: 0 | Q24: 0 | R24: 0 | S24: 0 | T24: 0 | U24: 0 | V24: 0 | W24: 0 | X24: 0 | Y24: 0 | Z24: 0 | AA24: 0 | AB24: 0 | AC24: 0 | AD24: 0 | AE24: 0
A25: hydrogen combined cycle | B25: 0 | C25: 0 | D25: 0 | E25: 0 | F25: 0 | G25: 0 | H25: 0 | I25: 0 | J25: 0 | K25: 0 | L25: 0 | M25: 0 | N25: 0 | O25: 0 | P25: 0 | Q25: 0 | R25: 0 | S25: 0 | T25: 0 | U25: 0 | V25: 0 | W25: 0 | X25: 0 | Y25: 0 | Z25: 0 | AA25: 0 | AB25: 0 | AC25: 0 | AD25: 0 | AE25: 0

Sheet BS-DoSpUEO
A1: Year | B1: 2021 | C1: 2022 | D1: 2023 | E1: 2024 | F1: 2025 | G1: 2026 | H1: 2027 | I1: 2028 | J1: 2029 | K1: 2030 | L1: 2031 | M1: 2032 | N1: 2033 | O1: 2034 | P1: 2035 | Q1: 2036 | R1: 2037 | S1: 2038 | T1: 2039 | U1: 2040 | V1: 2041 | W1: 2042 | X1: 2043 | Y1: 2044 | Z1: 2045 | AA1: 2046 | AB1: 2047 | AC1: 2048 | AD1: 2049 | AE1: 2050
A2: hard coal | B2: 10 | C2: 10 | D2: 10 | E2: 10 | F2: 10 | G2: 10 | H2: 10 | I2: 10 | J2: 10 | K2: 10 | L2: 10 | M2: 10 | N2: 10 | O2: 10 | P2: 10 | Q2: 10 | R2: 10 | S2: 10 | T2: 10 | U2: 10 | V2: 10 | W2: 10 | X2: 10 | Y2: 10 | Z2: 10 | AA2: 10 | AB2: 10 | AC2: 10 | AD2: 10 | AE2: 10
A3: natural gas steam turbine | B3: 10 | C3: 10 | D3: 10 | E3: 10 | F3: 10 | G3: 10 | H3: 10 | I3: 10 | J3: 10 | K3: 10 | L3: 10 | M3: 10 | N3: 10 | O3: 10 | P3: 10 | Q3: 10 | R3: 10 | S3: 10 | T3: 10 | U3: 10 | V3: 10 | W3: 10 | X3: 10 | Y3: 10 | Z3: 10 | AA3: 10 | AB3: 10 | AC3: 10 | AD3: 10 | AE3: 10
A4: natural gas combined cycle | B4: 10 | C4: 10 | D4: 10 | E4: 10 | F4: 10 | G4: 10 | H4: 10 | I4: 10 | J4: 10 | K4: 10 | L4: 10 | M4: 10 | N4: 10 | O4: 10 | P4: 10 | Q4: 10 | R4: 10 | S4: 10 | T4: 10 | U4: 10 | V4: 10 | W4: 10 | X4: 10 | Y4: 10 | Z4: 10 | AA4: 10 | AB4: 10 | AC4: 10 | AD4: 10 | AE4: 10
A5: nuclear | B5: 10 | C5: 10 | D5: 10 | E5: 10 | F5: 10 | G5: 10 | H5: 10 | I5: 10 | J5: 10 | K5: 10 | L5: 10 | M5: 10 | N5: 10 | O5: 10 | P5: 10 | Q5: 10 | R5: 10 | S5: 10 | T5: 10 | U5: 10 | V5: 10 | W5: 10 | X5: 10 | Y5: 10 | Z5: 10 | AA5: 10 | AB5: 10 | AC5: 10 | AD5: 10 | AE5: 10
A6: hydro | B6: 10 | C6: 10 | D6: 10 | E6: 10 | F6: 10 | G6: 10 | H6: 10 | I6: 10 | J6: 10 | K6: 10 | L6: 10 | M6: 10 | N6: 10 | O6: 10 | P6: 10 | Q6: 10 | R6: 10 | S6: 10 | T6: 10 | U6: 10 | V6: 10 | W6: 10 | X6: 10 | Y6: 10 | Z6: 10 | AA6: 10 | AB6: 10 | AC6: 10 | AD6: 10 | AE6: 10
A7: onshore wind | B7: 10 | C7: 10 | D7: 10 | E7: 10 | F7: 10 | G7: 10 | H7: 10 | I7: 10 | J7: 10 | K7: 10 | L7: 10 | M7: 10 | N7: 10 | O7: 10 | P7: 10 | Q7: 10 | R7: 10 | S7: 10 | T7: 10 | U7: 10 | V7: 10 | W7: 10 | X7: 10 | Y7: 10 | Z7: 10 | AA7: 10 | AB7: 10 | AC7: 10 | AD7: 10 | AE7: 10
A8: solar PV | B8: 10 | C8: 10 | D8: 10 | E8: 10 | F8: 10 | G8: 10 | H8: 10 | I8: 10 | J8: 10 | K8: 10 | L8: 10 | M8: 10 | N8: 10 | O8: 10 | P8: 10 | Q8: 10 | R8: 10 | S8: 10 | T8: 10 | U8: 10 | V8: 10 | W8: 10 | X8: 10 | Y8: 10 | Z8: 10 | AA8: 10 | AB8: 10 | AC8: 10 | AD8: 10 | AE8: 10
A9: solar thermal | B9: 10 | C9: 10 | D9: 10 | E9: 10 | F9: 10 | G9: 10 | H9: 10 | I9: 10 | J9: 10 | K9: 10 | L9: 10 | M9: 10 | N9: 10 | O9: 10 | P9: 10 | Q9: 10 | R9: 10 | S9: 10 | T9: 10 | U9: 10 | V9: 10 | W9: 10 | X9: 10 | Y9: 10 | Z9: 10 | AA9: 10 | AB9: 10 | AC9: 10 | AD9: 10 | AE9: 10
A10: biomass | B10: 10 | C10: 10 | D10: 10 | E10: 10 | F10: 10 | G10: 10 | H10: 10 | I10: 10 | J10: 10 | K10: 10 | L10: 10 | M10: 10 | N10: 10 | O10: 10 | P10: 10 | Q10: 10 | R10: 10 | S10: 10 | T10: 10 | U10: 10 | V10: 10 | W10: 10 | X10: 10 | Y10: 10 | Z10: 10 | AA10: 10 | AB10: 10 | AC10: 10 | AD10: 10 | AE10: 10
A11: geothermal | B11: 10 | C11: 10 | D11: 10 | E11: 10 | F11: 10 | G11: 10 | H11: 10 | I11: 10 | J11: 10 | K11: 10 | L11: 10 | M11: 10 | N11: 10 | O11: 10 | P11: 10 | Q11: 10 | R11: 10 | S11: 10 | T11: 10 | U11: 10 | V11: 10 | W11: 10 | X11: 10 | Y11: 10 | Z11: 10 | AA11: 10 | AB11: 10 | AC11: 10 | AD11: 10 | AE11: 10
A12: petroleum | B12: 10 | C12: 10 | D12: 10 | E12: 10 | F12: 10 | G12: 10 | H12: 10 | I12: 10 | J12: 10 | K12: 10 | L12: 10 | M12: 10 | N12: 10 | O12: 10 | P12: 10 | Q12: 10 | R12: 10 | S12: 10 | T12: 10 | U12: 10 | V12: 10 | W12: 10 | X12: 10 | Y12: 10 | Z12: 10 | AA12: 10 | AB12: 10 | AC12: 10 | AD12: 10 | AE12: 10
... A25: hydrogen combined cycle | B25: 10 | C25: 10 | D25: 10 | E25: 10 | F25: 10 | G25: 10 | H25: 10 | I25: 10 | J25: 10 | K25: 10 | L25: 10 | M25: 10 | N25: 10 | O25: 10 | P25: 10 | Q25: 10 | R25: 10 | S25: 10 | T25: 10 | U25: 10 | V25: 10 | W25: 10 | X25: 10 | Y25: 10 | Z25: 10 | AA25: 10 | AB25: 10 | AC25: 10 | AD25: 10 | AE25: 10
