Workbook

Sheet About
A1: SCoC Social Cost of Carbon
A3: Source: | B3: US Environmental Protection Agency
B4: 45231
B5: Supplementary Material for the Regulatory Impact Analysis for the Supplemental Proposed Rulemaking, “Standards of Performance for New, Reconstructed, and Modified Sources and Emissions Guidelines for Existing Sources: Oil and Natural Gas Sector Climate Review”
B6: https://www.epa.gov/system/files/documents/2023-12/epa_scghg_2023_report_final.pdf
B7: Table 3.1.1
A9: Notes:
A10: When considering the Social Cost of Carbon, meant to capture the long-term economic damage caused by one
A11: ton of carbon dioxide emitted, the U.S. government typically uses the figures based on
A12: a 2% discount rate, so this is the rate we use in this model.
A13: Note that this differs from the discount rate specified in the "DR Discount Rate" variable, which is
A14: based on the Office of Management and Budget guidelines for analysis of prospective investments and policies.
A16: 2020 dollars to 2012 dollars
A17: 0.88711067
A18: See "cpi.xlsx" in the InputData folder for source information.

Sheet SourceData New
A1: Social cost of carbon
B2: 0.02
B3: Meta-Analysis
B5: 2020 dollars per metric ton of CO2
A7: 2020 | B7: 200
A8: 2030 | B8: 240
A9: 2040 | B9: 270
A10: 2050 | B10: 310
B13: annualized value (2020$/mt) | C13: 2012$/mt | D13: 2012$/g
A14: 2020 | B14: 190 | C14: =B14*About!$A$17 -> 168.55103 | D14: =C14/10^6 -> 0.00016855103
A15: 2021 | B15: =_xlfn.FORECAST.LINEAR(A15,$B$7:$B$8,$A$7:$A$8) -> 204 | C15: =B15*About!$A$17 -> 180.97058 | D15: =C15/10^6 -> 0.00018097058
A16: 2022 | B16: =_xlfn.FORECAST.LINEAR(A16,$B$7:$B$8,$A$7:$A$8) -> 208 | C16: =B16*About!$A$17 -> 184.51902 | D16: =C16/10^6 -> 0.00018451902
A17: 2023 | B17: =_xlfn.FORECAST.LINEAR(A17,$B$7:$B$8,$A$7:$A$8) -> 212 | C17: =B17*About!$A$17 -> 188.06746 | D17: =C17/10^6 -> 0.00018806746
A18: 2024 | B18: =_xlfn.FORECAST.LINEAR(A18,$B$7:$B$8,$A$7:$A$8) -> 216 | C18: =B18*About!$A$17 -> 191.61591 | D18: =C18/10^6 -> 0.00019161591
A19: 2025 | B19: =_xlfn.FORECAST.LINEAR(A19,$B$7:$B$8,$A$7:$A$8) -> 220 | C19: =B19*About!$A$17 -> 195.16435 | D19: =C19/10^6 -> 0.00019516435
A20: 2026 | B20: =_xlfn.FORECAST.LINEAR(A20,$B$7:$B$8,$A$7:$A$8) -> 224 | C20: =B20*About!$A$17 -> 198.71279 | D20: =C20/10^6 -> 0.00019871279
A21: 2027 | B21: =_xlfn.FORECAST.LINEAR(A21,$B$7:$B$8,$A$7:$A$8) -> 228 | C21: =B21*About!$A$17 -> 202.26123 | D21: =C21/10^6 -> 0.00020226123
A22: 2028 | B22: =_xlfn.FORECAST.LINEAR(A22,$B$7:$B$8,$A$7:$A$8) -> 232 | C22: =B22*About!$A$17 -> 205.80968 | D22: =C22/10^6 -> 0.00020580968
A23: 2029 | B23: =_xlfn.FORECAST.LINEAR(A23,$B$7:$B$8,$A$7:$A$8) -> 236 | C23: =B23*About!$A$17 -> 209.35812 | D23: =C23/10^6 -> 0.00020935812
A24: 2030 | B24: 230 | C24: =B24*About!$A$17 -> 204.03545 | D24: =C24/10^6 -> 0.00020403545
A25: 2031 | B25: =_xlfn.FORECAST.LINEAR(A25,$B$8:$B$9,$A$8:$A$9) -> 243 | C25: =B25*About!$A$17 -> 215.56789 | D25: =C25/10^6 -> 0.00021556789
A26: 2032 | B26: =_xlfn.FORECAST.LINEAR(A26,$B$8:$B$9,$A$8:$A$9) -> 246 | C26: =B26*About!$A$17 -> 218.22923 | D26: =C26/10^6 -> 0.00021822923
A27: 2033 | B27: =_xlfn.FORECAST.LINEAR(A27,$B$8:$B$9,$A$8:$A$9) -> 249 | C27: =B27*About!$A$17 -> 220.89056 | D27: =C27/10^6 -> 0.00022089056
A28: 2034 | B28: =_xlfn.FORECAST.LINEAR(A28,$B$8:$B$9,$A$8:$A$9) -> 252 | C28: =B28*About!$A$17 -> 223.55189 | D28: =C28/10^6 -> 0.00022355189
A29: 2035 | B29: =_xlfn.FORECAST.LINEAR(A29,$B$8:$B$9,$A$8:$A$9) -> 255 | C29: =B29*About!$A$17 -> 226.21322 | D29: =C29/10^6 -> 0.00022621322
A30: 2036 | B30: =_xlfn.FORECAST.LINEAR(A30,$B$8:$B$9,$A$8:$A$9) -> 258 | C30: =B30*About!$A$17 -> 228.87455 | D30: =C30/10^6 -> 0.00022887455
A31: 2037 | B31: =_xlfn.FORECAST.LINEAR(A31,$B$8:$B$9,$A$8:$A$9) -> 261 | C31: =B31*About!$A$17 -> 231.53589 | D31: =C31/10^6 -> 0.00023153589
A32: 2038 | B32: =_xlfn.FORECAST.LINEAR(A32,$B$8:$B$9,$A$8:$A$9) -> 264 | C32: =B32*About!$A$17 -> 234.19722 | D32: =C32/10^6 -> 0.00023419722
A33: 2039 | B33: =_xlfn.FORECAST.LINEAR(A33,$B$8:$B$9,$A$8:$A$9) -> 267 | C33: =B33*About!$A$17 -> 236.85855 | D33: =C33/10^6 -> 0.00023685855
A34: 2040 | B34: 270 | C34: =B34*About!$A$17 -> 239.51988 | D34: =C34/10^6 -> 0.00023951988
A35: 2041 | B35: =_xlfn.FORECAST.LINEAR(A35,$B$9:$B$10,$A$9:$A$10) -> 274 | C35: =B35*About!$A$17 -> 243.06832 | D35: =C35/10^6 -> 0.00024306832
A36: 2042 | B36: =_xlfn.FORECAST.LINEAR(A36,$B$9:$B$10,$A$9:$A$10) -> 278 | C36: =B36*About!$A$17 -> 246.61677 | D36: =C36/10^6 -> 0.00024661677
A37: 2043 | B37: =_xlfn.FORECAST.LINEAR(A37,$B$9:$B$10,$A$9:$A$10) -> 282 | C37: =B37*About!$A$17 -> 250.16521 | D37: =C37/10^6 -> 0.00025016521
A38: 2044 | B38: =_xlfn.FORECAST.LINEAR(A38,$B$9:$B$10,$A$9:$A$10) -> 286 | C38: =B38*About!$A$17 -> 253.71365 | D38: =C38/10^6 -> 0.00025371365
A39: 2045 | B39: =_xlfn.FORECAST.LINEAR(A39,$B$9:$B$10,$A$9:$A$10) -> 290 | C39: =B39*About!$A$17 -> 257.26209 | D39: =C39/10^6 -> 0.00025726209
A40: 2046 | B40: =_xlfn.FORECAST.LINEAR(A40,$B$9:$B$10,$A$9:$A$10) -> 294 | C40: =B40*About!$A$17 -> 260.81054 | D40: =C40/10^6 -> 0.00026081054
A41: 2047 | B41: =_xlfn.FORECAST.LINEAR(A41,$B$9:$B$10,$A$9:$A$10) -> 298 | C41: =B41*About!$A$17 -> 264.35898 | D41: =C41/10^6 -> 0.00026435898
A42: 2048 | B42: =_xlfn.FORECAST.LINEAR(A42,$B$9:$B$10,$A$9:$A$10) -> 302 | C42: =B42*About!$A$17 -> 267.90742 | D42: =C42/10^6 -> 0.00026790742
A43: 2049 | B43: =_xlfn.FORECAST.LINEAR(A43,$B$9:$B$10,$A$9:$A$10) -> 306 | C43: =B43*About!$A$17 -> 271.45587 | D43: =C43/10^6 -> 0.00027145587
A44: 2050 | B44: 310 | C44: =B44*About!$A$17 -> 275.00431 | D44: =C44/10^6 -> 0.00027500431

Sheet SCoC
A1: Year | B1: Social Cost of Carbon ($/g CO2e)
A2: 2021 | B2: ='SourceData New'!D15 -> 0.00018097058
A3: 2022 | B3: ='SourceData New'!D16 -> 0.00018451902
A4: 2023 | B4: ='SourceData New'!D17 -> 0.00018806746
A5: 2024 | B5: ='SourceData New'!D18 -> 0.00019161591
A6: 2025 | B6: ='SourceData New'!D19 -> 0.00019516435
A7: 2026 | B7: ='SourceData New'!D20 -> 0.00019871279
A8: 2027 | B8: ='SourceData New'!D21 -> 0.00020226123
A9: 2028 | B9: ='SourceData New'!D22 -> 0.00020580968
A10: 2029 | B10: ='SourceData New'!D23 -> 0.00020935812
A11: 2030 | B11: ='SourceData New'!D24 -> 0.00020403545
A12: 2031 | B12: ='SourceData New'!D25 -> 0.00021556789
A13: 2032 | B13: ='SourceData New'!D26 -> 0.00021822923
... A31: 2050 | B31: ='SourceData New'!D44 -> 0.00027500431
