Workbook
Name gal_per_barrel: [1]About!$A$63

Sheet About
A1: BPCiObIC BAU Percent Change in Output by ISIC Code
A3: Source: | B3: Future Year Projected Changes in Output by ISIC Code
B4: U.S. EIA
B5: 2023
B6: Annual Energy Outlook 2023
B7: https://www.eia.gov/outlooks/aeo/tables_ref.php
B8: Table 23: Industrial Sector Macroeconomic Indicators
B10: U.S. Bureau of Labor Statistics
B11: 2020
B12: Industry Output and Employment
B13: https://www.bls.gov/emp/tables/industry-employment-and-output.htm
B14: Table 2.7: Output and Employment by Industry
B16: GDP Projection (see BGDP)
B17: Forecasted GDP Growth
B18: OECD
B19: Last updated: January 12, 2024 at 6:54:51 AM
B20: (DF_DP_LIVE) OECD Data Archive
B21: https://data-explorer.oecd.org/vis?lc=en&df[ds]=DisseminateArchiveDMZ&df[id]=DF_DP_LIVE&df[ag]=OECD&av=true&pd=2017%2C2075&dq=KOR.GDPLTFORECAST...A&to[TIME_PERIOD]=false&vw=ov&lb=bt
B22: Real GDP long-term forecast
B24: Real GDP - Historical
B25: The World Bank
B26: GDP (constant 2015 US$)
B27: 2023
B28: https://data.worldbank.org/indicator/NY.GDP.MKTP.KD?locations=KR
A32: Notes
A34: We need a set of scaling factors to convert the I/O variables that contain static data (for one historical year)
A35: to future time series data.
A37: We base these scaling factors on the projected change in output for each ISIC code, which is readily
A38: available disaggregated by ISIC code. It is crucial for these projections to be disaggregated by ISIC code,
A39: because we need to know how industries grow or shrink relative to one-another, not just how they
A40: grow or shrink overall to fit GDP growth.
A42: For the U.S., we use projections from the BLS and EIA AEO. The BLS has growth rates for all ISIC codes,
A43: but only out to 2029. The EIA has projections for only certain ISIC codes, but out to 2050.
A44: Because energy demand projections for those ISIC codes come directly from EIA (see indst/BIFUbC),
A45: we use those growth rates directly. For all others, we use BLS and rescale the growth rates such that,
A46: when applied to Value Added quantities,
... A62: value added, employment, etc.).

Sheet BLS Table 2.7
A1: Table 2.7 Employment and Output by Industry
A2: Industry | B2: 2017 NAICS | C2: Employment | J2: Output
C3: Thousands of Jobs | F3: Change | H3: Compound Annual Rate of Change | J3: Billions of Chained 2012 Dollars | M3: Compound Annual Rate of Change
C4: 2009 | D4: 2019 | E4: 2029 | F4: 2009 - 2019 | G4: 2019 - 2029 | H4: 2009 - 2019 | I4: 2019 - 2029 | J4: 2009 | K4: 2019 | L4: 2029 | M4: 2009 - 2019 | N4: 2019 - 2029 | O4: Assigned ISIC Code
A5: Total(1)(2) | C5: 143036.4 | D5: 162795.6 | E5: 168834.7 | F5: 19759.2 | G5: 6039.1 | H5: 1.3 | I5: 0.4 | J5: 27293.3 | K5: 34049.9 | L5: 40867.6 | M5: 2.2 | N5: 1.8
A7: Nonagriculture wage and salary | B7: NA | C7: 132029.2 | D7: 151709.7 | E7: 158115.6 | F7: 19680.5 | G7: 6405.9 | H7: 1.4 | I7: 0.4 | J7: 26836.2 | K7: 33487.1 | L7: 40193.3 | M7: 2.2 | N7: 1.8
A8: Mining | B8: 21 | C8: 643.3 | D8: 684.6 | E8: 777.8 | F8: 41.3 | G8: 93.2 | H8: 0.6 | I8: 1.3 | J8: 485.8 | K8: 635.3 | L8: 835.5 | M8: 2.7 | N8: 2.8
A9: Oil and gas extraction | B9: 211 | C9: 159.8 | D9: 150.1 | E9: 129.7 | F9: -9.7 | G9: -20.4 | H9: -0.6 | I9: -1.4 | J9: 278.2 | K9: 474.3 | L9: 659.6 | M9: 5.5 | N9: 3.4 | O9: ISIC 06
A10: Mining, except oil and gas | B10: 212 | C10: 208.3 | D10: 191.4 | E10: 193.9 | F10: -16.9 | G10: 2.5 | H10: -0.8 | I10: 0.1 | J10: 124.6 | K10: 108.1 | L10: 114.2 | M10: -1.4 | N10: 0.6
A11: Coal mining | B11: 2121 | C11: 81.5 | D11: 51.9 | E11: 43.6 | F11: -29.6 | G11: -8.3 | H11: -4.4 | I11: -1.7 | J11: 50.9 | K11: 44.8 | L11: 43.8 | M11: -1.3 | N11: -0.2 | O11: ISIC 05
A12: Metal ore mining | B12: 2122 | C12: 34.8 | D12: 41.8 | E12: 48.6 | F12: 7 | G12: 6.8 | H12: 1.8 | I12: 1.5 | J12: 40.9 | K12: 36.2 | L12: 38 | M12: -1.2 | N12: 0.5 | O12: ISIC 07T08
A13: Nonmetallic mineral mining and quarrying | B13: 2123 | C13: 92 | D13: 97.7 | E13: 101.7 | F13: 5.7 | G13: 4 | H13: 0.6 | I13: 0.4 | J13: 33.4 | K13: 27.3 | L13: 32.2 | M13: -2 | N13: 1.6 | O13: ISIC 07T08
A14: Support activities for mining | B14: 213 | C14: 275.2 | D14: 343.1 | E14: 454.2 | F14: 67.9 | G14: 111.1 | H14: 2.2 | I14: 2.8 | J14: 83.5 | K14: 82.3 | L14: 109 | M14: -0.1 | N14: 2.9 | O14: ISIC 09
A15: Utilities | B15: 22 | C15: 560.1 | D15: 549 | E15: 506.7 | F15: -11.1 | G15: -42.3 | H15: -0.2 | I15: -0.8 | J15: 443.6 | K15: 458.6 | L15: 534.5 | M15: 0.3 | N15: 1.5
A16: Electric power generation, transmission and distribution | B16: 2211 | C16: 404.1 | D16: 385.5 | E16: 352 | F16: -18.6 | G16: -33.5 | H16: -0.5 | I16: -0.9 | J16: 340.5 | K16: 357 | L16: 422.3 | M16: 0.5 | N16: 1.7 | O16: ISIC 351
A17: Natural gas distribution | B17: 2212 | C17: 108.7 | D17: 110.3 | E17: 99 | F17: 1.6 | G17: -11.3 | H17: 0.1 | I17: -1.1 | J17: 88.7 | K17: 90.8 | L17: 98.8 | M17: 0.2 | N17: 0.8 | O17: ISIC 352T353
A18: Water, sewage and other systems | B18: 2213 | C18: 47.3 | D18: 53.2 | E18: 55.6 | F18: 5.9 | G18: 2.4 | H18: 1.2 | I18: 0.4 | J18: 13 | K18: 11.4 | L18: 12.8 | M18: -1.3 | N18: 1.1 | O18: ISIC 36T39
A19: Construction | B19: 23 | C19: 6016.5 | D19: 7492.2 | E19: 7792.4 | F19: 1475.7 | G19: 300.2 | H19: 2.2 | I19: 0.4 | J19: 1161.5 | K19: 1418.9 | L19: 1616.3 | M19: 2 | N19: 1.3 | O19: ISIC 41T43
A20: Manufacturing | B20: 31-33 | C20: 11847.9 | D20: 12839.5 | E20: 12394.7 | F20: 991.6 | G20: -444.8 | H20: 0.8 | I20: -0.4 | J20: 5261.6 | K20: 6384.1 | L20: 7434 | M20: 2 | N20: 1.5
A21: Food manufacturing | B21: 311 | C21: 1456.4 | D21: 1643.2 | E21: 1649.6 | F21: 186.8 | G21: 6.4 | H21: 1.2 | I21: 0 | J21: 736 | K21: 825 | L21: 972.1 | M21: 1.1 | N21: 1.7 | O21: ISIC 10T12
A22: Animal food manufacturing | B22: 3111 | C22: 51.8 | D22: 64 | E22: 74.8 | F22: 12.2 | G22: 10.8 | H22: 2.1 | I22: 1.6 | J22: 52.7 | K22: 65.7 | L22: 80.7 | M22: 2.2 | N22: 2.1
A23: Grain and oilseed milling | B23: 3112 | C23: 59.7 | D23: 60.6 | E23: 56.1 | F23: 0.9 | G23: -4.5 | H23: 0.1 | I23: -0.8 | J23: 95 | K23: 142.7 | L23: 178.5 | M23: 4.2 | N23: 2.3
A24: Sugar and confectionery product manufacturing | B24: 3113 | C24: 70.9 | D24: 78.8 | E24: 66.8 | F24: 7.9 | G24: -12 | H24: 1.1 | I24: -1.6 | J24: 33.5 | K24: 37.1 | L24: 38.6 | M24: 1 | N24: 0.4
A25: Fruit and vegetable preserving and specialty food manufacturing | B25: 3114 | C25: 172.3 | D25: 173.3 | E25: 158.7 | F25: 1 | G25: -14.6 | H25: 0.1 | I25: -0.9 | J25: 64.7 | K25: 66.6 | L25: 72.5 | M25: 0.3 | N25: 0.9
A26: Dairy product manufacturing | B26: 3115 | C26: 130.7 | D26: 155.6 | E26: 158.7 | F26: 24.9 | G26: 3.1 | H26: 1.8 | I26: 0.2 | J26: 116.8 | K26: 123.1 | L26: 149.4 | M26: 0.5 | N26: 2
A27: Animal slaughtering and processing | B27: 3116 | C27: 497.2 | D27: 531.4 | E27: 545.4 | F27: 34.2 | G27: 14 | H27: 0.7 | I27: 0.3 | J27: 213.2 | K27: 219.9 | L27: 257.9 | M27: 0.3 | N27: 1.6
A28: Seafood product preparation and packaging | B28: 3117 | C28: 38.1 | D28: 35.3 | E28: 29.3 | F28: -2.8 | G28: -6 | H28: -0.8 | I28: -1.8 | J28: 11.6 | K28: 10.9 | L28: 13 | M28: -0.6 | N28: 1.8
A29: Bakeries and tortilla manufacturing | B29: 3118 | C29: 273 | D29: 315.8 | E29: 303.1 | F29: 42.8 | G29: -12.7 | H29: 1.5 | I29: -0.4 | J29: 60.7 | K29: 66.3 | L29: 74.8 | M29: 0.9 | N29: 1.2
A30: Other food manufacturing | B30: 3119 | C30: 162.7 | D30: 228.4 | E30: 256.7 | F30: 65.7 | G30: 28.3 | H30: 3.5 | I30: 1.2 | J30: 88.4 | K30: 96.8 | L30: 115 | M30: 0.9 | N30: 1.7
A31: Beverage and tobacco product | B31: 312 | C31: 187.4 | D31: 285.8 | E31: 296.1 | F31: 98.4 | G31: 10.3 | H31: 4.3 | I31: 0.4 | J31: 167.3 | K31: 168.2 | L31: 181.3 | M31: 0.1 | N31: 0.8 | O31: ISIC 10T12
A32: Beverage manufacturing | B32: 3121 | C32: 168.7 | D32: 275 | E32: 289.4 | F32: 106.3 | G32: 14.4 | H32: 5 | I32: 0.5 | J32: 103.9 | K32: 121.8 | L32: 148.2 | M32: 1.6 | N32: 2
A33: Tobacco manufacturing | B33: 3122 | C33: 18.7 | D33: 11.3 | E33: 6.7 | F33: -7.4 | G33: -4.7 | H33: -4.9 | I33: -5.2 | J33: 63.7 | K33: 47.3 | L33: 38.3 | M33: -2.9 | N33: -2.1
A34: Textile mills and textile product mills | B34: 313,314 | C34: 250.1 | D34: 222 | E34: 198.3 | F34: -28.1 | G34: -23.7 | H34: -1.2 | I34: -1.1 | J34: 51.3 | K34: 52.8 | L34: 50.3 | M34: 0.3 | N34: -0.5 | O34: ISIC 13T15
A35: Apparel, leather and allied product manufacturing | B35: 315, 316 | C35: 196.5 | D35: 137.7 | E35: 94.2 | F35: -58.8 | G35: -43.5 | H35: -3.5 | I35: -3.7 | J35: 25.6 | K35: 19.1 | L35: 20.1 | M35: -2.8 | N35: 0.5 | O35: ISIC 13T15
A36: Wood product manufacturing | B36: 321 | C36: 360.2 | D36: 408.8 | E36: 382.3 | F36: 48.6 | G36: -26.5 | H36: 1.3 | I36: -0.7 | J36: 74.2 | K36: 94.1 | L36: 108.3 | M36: 2.4 | N36: 1.4 | O36: ISIC 16
A37: Sawmills and wood preservation | B37: 3211 | C37: 83.2 | D37: 92.3 | E37: 85.3 | F37: 9.1 | G37: -7 | H37: 1 | I37: -0.8 | J37: 21.4 | K37: 26 | L37: 30.5 | M37: 2 | N37: 1.6
A38: Veneer, plywood, and engineered wood product manufacturing | B38: 3212 | C38: 68.3 | D38: 82.1 | E38: 87 | F38: 13.8 | G38: 4.9 | H38: 1.9 | I38: 0.6 | J38: 17.6 | K38: 20.4 | L38: 23.8 | M38: 1.5 | N38: 1.6
A39: Other wood product manufacturing | B39: 3219 | C39: 208.7 | D39: 234.4 | E39: 210 | F39: 25.7 | G39: -24.4 | H39: 1.2 | I39: -1.1 | J39: 35.4 | K39: 47.9 | L39: 54.2 | M39: 3.1 | N39: 1.3
A40: Paper manufacturing | B40: 322 | C40: 407 | D40: 365.3 | E40: 340 | F40: -41.7 | G40: -25.3 | H40: -1.1 | I40: -0.7 | J40: 172.6 | K40: 176.6 | L40: 183 | M40: 0.2 | N40: 0.4 | O40: ISIC 17T18
A41: Pulp, paper, and paperboard mills | B41: 3221 | C41: 116.9 | D41: 96.4 | E41: 92.3 | F41: -20.5 | G41: -4.1 | H41: -1.9 | I41: -0.4 | J41: 79.4 | K41: 81.1 | L41: 84.4 | M41: 0.2 | N41: 0.4
A42: Converted paper product manufacturing | B42: 3222 | C42: 290.1 | D42: 268.9 | E42: 247.8 | F42: -21.2 | G42: -21.1 | H42: -0.8 | I42: -0.8 | J42: 93.2 | K42: 95.5 | L42: 98.6 | M42: 0.2 | N42: 0.3
A43: Printing and related support activities | B43: 323 | C43: 521.9 | D43: 424.6 | E43: 342.3 | F43: -97.3 | G43: -82.3 | H43: -2 | I43: -2.1 | J43: 86.1 | K43: 83.7 | L43: 89.9 | M43: -0.3 | N43: 0.7 | O43: ISIC 17T18
A44: Petroleum and coal products manufacturing | B44: 324 | C44: 115.3 | D44: 114.5 | E44: 109.1 | F44: -0.8 | G44: -5.4 | H44: -0.1 | I44: -0.5 | J44: 841 | K44: 899.8 | L44: 1132 | M44: 0.7 | N44: 2.3 | O44: ISIC 19
A45: Chemical manufacturing | B45: 325 | C45: 804.1 | D45: 849.9 | E45: 877 | F45: 45.8 | G45: 27.1 | H45: 0.6 | I45: 0.3 | J45: 743.8 | K45: 863.8 | L45: 1034.3 | M45: 1.5 | N45: 1.8
A46: Basic chemical manufacturing | B46: 3251 | C46: 145.3 | D46: 153 | E46: 160 | F46: 7.7 | G46: 7 | H46: 0.5 | I46: 0.4 | J46: 255.7 | K46: 331.5 | L46: 409.4 | M46: 2.6 | N46: 2.1 | O46: ISIC 20
A47: Resin, synthetic rubber, and artificial synthetic fibers and filaments manufacturing | B47: 3252 | C47: 92 | D47: 95.4 | E47: 94.2 | F47: 3.4 | G47: -1.2 | H47: 0.4 | I47: -0.1 | J47: 102.8 | K47: 116 | L47: 138.7 | M47: 1.2 | N47: 1.8 | O47: ISIC 20
A48: Pesticide, fertilizer, and other agricultural chemical manufacturing | B48: 3253 | C48: 36.5 | D48: 36.6 | E48: 34.7 | F48: 0.1 | G48: -1.9 | H48: 0 | I48: -0.5 | J48: 33.6 | K48: 53.6 | L48: 60.4 | M48: 4.8 | N48: 1.2 | O48: ISIC 20
A49: Pharmaceutical and medicine manufacturing | B49: 3254 | C49: 284.4 | D49: 305.9 | E49: 322.3 | F49: 21.5 | G49: 16.4 | H49: 0.7 | I49: 0.5 | J49: 201.4 | K49: 193.8 | L49: 232.3 | M49: -0.4 | N49: 1.8 | O49: ISIC 21
A50: Paint, coating, and adhesive manufacturing | B50: 3255 | C50: 57.3 | D50: 65.4 | E50: 69.4 | F50: 8.1 | G50: 4 | H50: 1.3 | I50: 0.6 | J50: 33.6 | K50: 38 | L50: 40.5 | M50: 1.2 | N50: 0.6 | O50: ISIC 20
A51: Soap, cleaning compound, and toilet preparation manufacturing | B51: 3256 | C51: 102.7 | D51: 110.2 | E51: 117 | F51: 7.5 | G51: 6.8 | H51: 0.7 | I51: 0.6 | J51: 75.3 | K51: 88.5 | L51: 110.8 | M51: 1.6 | N51: 2.3 | O51: ISIC 20
A52: Other chemical product and preparation manufacturing | B52: 3259 | C52: 85.9 | D52: 83.4 | E52: 79.3 | F52: -2.5 | G52: -4.1 | H52: -0.3 | I52: -0.5 | J52: 41.8 | K52: 47.3 | L52: 49.9 | M52: 1.2 | N52: 0.5 | O52: ISIC 20
A53: Plastics and rubber products manufacturing | B53: 326 | C53: 624.9 | D53: 737 | E53: 682.8 | F53: 112.1 | G53: -54.2 | H53: 1.7 | I53: -0.8 | J53: 188.9 | K53: 225.7 | L53: 259 | M53: 1.8 | N53: 1.4 | O53: ISIC 22
A54: Plastics product manufacturing | B54: 3261 | C54: 502.1 | D54: 599.1 | E54: 549.3 | F54: 97 | G54: -49.8 | H54: 1.8 | I54: -0.9 | J54: 150.4 | K54: 177.3 | L54: 203.1 | M54: 1.7 | N54: 1.4
A55: Rubber product manufacturing | B55: 3262 | C55: 122.8 | D55: 137.9 | E55: 133.5 | F55: 15.1 | G55: -4.4 | H55: 1.2 | I55: -0.3 | J55: 38.5 | K55: 48.5 | L55: 55.9 | M55: 2.4 | N55: 1.4
A56: Nonmetallic mineral product manufacturing | B56: 327 | C56: 394.3 | D56: 421.6 | E56: 347.9 | F56: 27.3 | G56: -73.7 | H56: 0.7 | I56: -1.9 | J56: 94 | K56: 120.6 | L56: 140.6 | M56: 2.5 | N56: 1.5
A57: Clay product and refractory manufacturing | B57: 3271 | C57: 43.6 | D57: 38.6 | E57: 29.2 | F57: -5 | G57: -9.4 | H57: -1.2 | I57: -2.8 | J57: 7.7 | K57: 10 | L57: 10.3 | M57: 2.6 | N57: 0.3 | O57: ISIC 239
A58: Glass and glass product manufacturing | B58: 3272 | C58: 83.8 | D58: 86.2 | E58: 79.3 | F58: 2.4 | G58: -6.9 | H58: 0.3 | I58: -0.8 | J58: 18.7 | K58: 28.3 | L58: 33.7 | M58: 4.3 | N58: 1.8 | O58: ISIC 231
A59: Cement and concrete product manufacturing | B59: 3273 | C59: 184.9 | D59: 199 | E59: 141.9 | F59: 14.1 | G59: -57.1 | H59: 0.7 | I59: -3.3 | J59: 42.5 | K59: 48.8 | L59: 57.3 | M59: 1.4 | N59: 1.6 | O59: ISIC 239
A60: Lime, gypsum and other nonmetallic mineral product manufacturing | B60: 3274, 3279 | C60: 82 | D60: 97.8 | E60: 97.5 | F60: 15.8 | G60: -0.3 | H60: 1.8 | I60: 0 | J60: 25 | K60: 33.6 | L60: 39.5 | M60: 3 | N60: 1.6 | O60: ISIC 239
A61: Primary metal manufacturing | B61: 331 | C61: 362.1 | D61: 385.1 | E61: 368.8 | F61: 23 | G61: -16.3 | H61: 0.6 | I61: -0.4 | J61: 203.4 | K61: 249.1 | L61: 269 | M61: 2 | N61: 0.8
A62: Iron and steel mills and ferroalloy manufacturing | B62: 3311 | C62: 85.3 | D62: 86.4 | E62: 79.3 | F62: 1.1 | G62: -7.1 | H62: 0.1 | I62: -0.8 | J62: 85.5 | K62: 102 | L62: 107.8 | M62: 1.8 | N62: 0.6 | O62: ISIC 241
A63: Steel product manufacturing from purchased steel | B63: 3312 | C63: 49.8 | D63: 57.6 | E63: 57.8 | F63: 7.8 | G63: 0.2 | H63: 1.5 | I63: 0 | J63: 17.9 | K63: 22.2 | L63: 25.2 | M63: 2.2 | N63: 1.3
A64: Alumina and aluminum production and processing | B64: 3313 | C64: 55.8 | D64: 59.8 | E64: 53.1 | F64: 4 | G64: -6.7 | H64: 0.7 | I64: -1.2 | J64: 29.4 | K64: 32 | L64: 29.3 | M64: 0.8 | N64: -0.9 | O64: ISIC 242
A65: Nonferrous metal (except aluminum) production and processing | B65: 3314 | C65: 58.2 | D65: 62 | E65: 59.5 | F65: 3.8 | G65: -2.5 | H65: 0.6 | I65: -0.4 | J65: 48 | K65: 61.8 | L65: 73.8 | M65: 2.6 | N65: 1.8 | O65: ISIC 242
A66: Foundries | B66: 3315 | C66: 113 | D66: 119.3 | E66: 119 | F66: 6.3 | G66: -0.3 | H66: 0.5 | I66: 0 | J66: 22.6 | K66: 31.2 | L66: 32.5 | M66: 3.3 | N66: 0.4
A67: Fabricated metal product manufacturing | B67: 332 | C67: 1311.8 | D67: 1491.6 | E67: 1446.2 | F67: 179.8 | G67: -45.4 | H67: 1.3 | I67: -0.3 | J67: 296.7 | K67: 385.7 | L67: 430.6 | M67: 2.7 | N67: 1.1 | O67: ISIC 25
A68: Forging and stamping | B68: 3321 | C68: 89 | D68: 101.1 | E68: 96.2 | F68: 12.1 | G68: -4.9 | H68: 1.3 | I68: -0.5 | J68: 28.4 | K68: 41.7 | L68: 46.3 | M68: 3.9 | N68: 1.1
A69: Cutlery and handtool manufacturing | B69: 3322 | C69: 42.1 | D69: 36.4 | E69: 34.5 | F69: -5.7 | G69: -1.9 | H69: -1.4 | I69: -0.5 | J69: 9.2 | K69: 11.1 | L69: 11.2 | M69: 1.9 | N69: 0.1
A70: Architectural and structural metals manufacturing | B70: 3323 | C70: 344.7 | D70: 400.5 | E70: 403.6 | F70: 55.8 | G70: 3.1 | H70: 1.5 | I70: 0.1 | J70: 74 | K70: 84.1 | L70: 96.4 | M70: 1.3 | N70: 1.4
A71: Boiler, tank, and shipping container manufacturing | B71: 3324 | C71: 88.6 | D71: 96.2 | E71: 95.2 | F71: 7.6 | G71: -1 | H71: 0.8 | I71: -0.1 | J71: 26.9 | K71: 39.3 | L71: 44 | M71: 3.9 | N71: 1.1
A72: Hardware manufacturing | B72: 3325 | C72: 24.3 | D72: 25.5 | E72: 23.9 | F72: 1.2 | G72: -1.6 | H72: 0.5 | I72: -0.7 | J72: 7.6 | K72: 7.8 | L72: 8.3 | M72: 0.2 | N72: 0.5
A73: Spring and wire product manufacturing | B73: 3326 | C73: 42.8 | D73: 43.5 | E73: 41 | F73: 0.7 | G73: -2.5 | H73: 0.2 | I73: -0.6 | J73: 7.4 | K73: 9.9 | L73: 10.4 | M73: 2.9 | N73: 0.5
A74: Machine shops; turned product; and screw, nut, and bolt manufacturing | B74: 3327 | C74: 309.1 | D74: 364.8 | E74: 377.6 | F74: 55.7 | G74: 12.8 | H74: 1.7 | I74: 0.3 | J74: 54.2 | K74: 78.5 | L74: 87.4 | M74: 3.8 | N74: 1.1
A75: Coating, engraving, heat treating, and allied activities | B75: 3328 | C75: 121 | D75: 142 | E75: 136.8 | F75: 21 | G75: -5.2 | H75: 1.6 | I75: -0.4 | J75: 23.3 | K75: 30.6 | L75: 32 | M75: 2.8 | N75: 0.4
A76: Other fabricated metal product manufacturing | B76: 3329 | C76: 250.2 | D76: 281.6 | E76: 237.4 | F76: 31.4 | G76: -44.2 | H76: 1.2 | I76: -1.7 | J76: 66 | K76: 83.2 | L76: 94.9 | M76: 2.3 | N76: 1.3
A77: Machinery manufacturing | B77: 333 | C77: 1028.7 | D77: 1126.1 | E77: 1112.3 | F77: 97.4 | G77: -13.8 | H77: 0.9 | I77: -0.1 | J77: 300 | K77: 385.3 | L77: 445.9 | M77: 2.5 | N77: 1.5 | O77: ISIC 28
A78: Agriculture, construction, and mining machinery manufacturing | B78: 3331 | C78: 213.7 | D78: 221 | E78: 218.7 | F78: 7.3 | G78: -2.3 | H78: 0.3 | I78: -0.1 | J78: 76.6 | K78: 109.9 | L78: 130.4 | M78: 3.7 | N78: 1.7
A79: Industrial machinery manufacturing | B79: 3332 | C79: 101.7 | D79: 118 | E79: 109.3 | F79: 16.3 | G79: -8.7 | H79: 1.5 | I79: -0.8 | J79: 29.6 | K79: 32.1 | L79: 37.5 | M79: 0.8 | N79: 1.6
A80: Commercial and service industry machinery manufacturing, including digital camera manufacturing | B80: 3333 | C80: 96 | D80: 94.4 | E80: 94.2 | F80: -1.6 | G80: -0.2 | H80: -0.2 | I80: 0 | J80: 22.3 | K80: 26.1 | L80: 30.5 | M80: 1.6 | N80: 1.6
A81: Ventilation, heating, air-conditioning, and commercial refrigeration equipment manufacturing | B81: 3334 | C81: 128.5 | D81: 137.8 | E81: 134.2 | F81: 9.3 | G81: -3.6 | H81: 0.7 | I81: -0.3 | J81: 34.7 | K81: 44.7 | L81: 50.1 | M81: 2.6 | N81: 1.2
A82: Metalworking machinery manufacturing | B82: 3335 | C82: 157.6 | D82: 179.7 | E82: 178.1 | F82: 22.1 | G82: -1.6 | H82: 1.3 | I82: -0.1 | J82: 23.7 | K82: 29.3 | L82: 31.4 | M82: 2.1 | N82: 0.7
A83: Engine, turbine, and power transmission equipment manufacturing | B83: 3336 | C83: 94.6 | D83: 99.6 | E83: 100.2 | F83: 5 | G83: 0.6 | H83: 0.5 | I83: 0.1 | J83: 36.9 | K83: 53.8 | L83: 62.4 | M83: 3.9 | N83: 1.5
A84: Other general purpose machinery manufacturing | B84: 3339 | C84: 236.6 | D84: 275.6 | E84: 277.7 | F84: 39 | G84: 2.1 | H84: 1.5 | I84: 0.1 | J84: 76.2 | K84: 89.7 | L84: 103.8 | M84: 1.6 | N84: 1.5
A85: Computer and electronic product manufacturing | B85: 334 | C85: 1136.9 | D85: 1080.5 | E85: 1062.1 | F85: -56.4 | G85: -18.4 | H85: -0.5 | I85: -0.2 | J85: 335.7 | K85: 404.1 | L85: 474.3 | M85: 1.9 | N85: 1.6 | O85: ISIC 26
A86: Computer and peripheral equipment manufacturing, excluding digital camera manufacturing | B86: 3341 | C86: 166.4 | D86: 163 | E86: 168.6 | F86: -3.4 | G86: 5.6 | H86: -0.2 | I86: 0.3 | J86: 44.5 | K86: 56 | L86: 72.9 | M86: 2.3 | N86: 2.7
A87: Communications equipment manufacturing | B87: 3342 | C87: 120.5 | D87: 83.5 | E87: 58 | F87: -37 | G87: -25.5 | H87: -3.6 | I87: -3.6 | J87: 57.7 | K87: 64.8 | L87: 81.5 | M87: 1.2 | N87: 2.3
A88: Audio and video equipment manufacturing | B88: 3343 | C88: 22.6 | D88: 20 | E88: 17.9 | F88: -2.6 | G88: -2.2 | H88: -1.2 | I88: -1.1 | J88: 7.7 | K88: 3.3 | L88: 3.8 | M88: -8 | N88: 1.4
A89: Semiconductor and other electronic component manufacturing | B89: 3344 | C89: 378.1 | D89: 377 | E89: 373.9 | F89: -1.1 | G89: -3.1 | H89: 0 | I89: -0.1 | J89: 91 | K89: 127.4 | L89: 129 | M89: 3.4 | N89: 0.1
A90: Navigational, measuring, electromedical, and control instruments manufacturing | B90: 3345 | C90: 421.6 | D90: 424.1 | E90: 431.4 | F90: 2.5 | G90: 7.3 | H90: 0.1 | I90: 0.2 | J90: 130.6 | K90: 151.7 | L90: 188.1 | M90: 1.5 | N90: 2.2
A91: Manufacturing and reproducing magnetic and optical media | B91: 3346 | C91: 27.7 | D91: 12.9 | E91: 12.4 | F91: -14.8 | G91: -0.5 | H91: -7.4 | I91: -0.4 | J91: 4 | K91: 4 | L91: 4.9 | M91: -0.2 | N91: 2.1
A92: Electrical equipment, appliance, and component manufacturing | B92: 335 | C92: 373.6 | D92: 405.1 | E92: 391.7 | F92: 31.5 | G92: -13.4 | H92: 0.8 | I92: -0.3 | J92: 113.9 | K92: 143 | L92: 158.4 | M92: 2.3 | N92: 1 | O92: ISIC 27
A93: Electric lighting equipment manufacturing | B93: 3351 | C93: 48.4 | D93: 46 | E93: 30.8 | F93: -2.4 | G93: -15.2 | H93: -0.5 | I93: -3.9 | J93: 11.8 | K93: 17.6 | L93: 17.8 | M93: 4 | N93: 0.2
A94: Household appliance manufacturing | B94: 3352 | C94: 59.7 | D94: 62.1 | E94: 60.5 | F94: 2.4 | G94: -1.6 | H94: 0.4 | I94: -0.3 | J94: 21 | K94: 23 | L94: 29 | M94: 0.9 | N94: 2.3
A95: Electrical equipment manufacturing | B95: 3353 | C95: 144.6 | D95: 146.9 | E95: 141.7 | F95: 2.3 | G95: -5.2 | H95: 0.2 | I95: -0.4 | J95: 35.5 | K95: 42.8 | L95: 48.8 | M95: 1.9 | N95: 1.3
A96: Other electrical equipment and component manufacturing | B96: 3359 | C96: 120.9 | D96: 150.1 | E96: 158.7 | F96: 29.2 | G96: 8.6 | H96: 2.2 | I96: 0.6 | J96: 45.6 | K96: 59.6 | L96: 62.8 | M96: 2.7 | N96: 0.5
A97: Transportation equipment manufacturing | B97: 336 | C97: 1348 | D97: 1734.2 | E97: 1715.1 | F97: 386.2 | G97: -19.1 | H97: 2.6 | I97: -0.1 | J97: 624.7 | K97: 1043.4 | L97: 1250.1 | M97: 5.3 | N97: 1.8
A98: Motor vehicle manufacturing | B98: 3361 | C98: 146.4 | D98: 237.2 | E98: 248.9 | F98: 90.8 | G98: 11.7 | H98: 4.9 | I98: 0.5 | J98: 178.6 | K98: 354.7 | L98: 452 | M98: 7.1 | N98: 2.5 | O98: ISIC 29
A99: Motor vehicle body and trailer manufacturing | B99: 3362 | C99: 104.1 | D99: 165.7 | E99: 155.4 | F99: 61.6 | G99: -10.3 | H99: 4.8 | I99: -0.6 | J99: 24.3 | K99: 45.1 | L99: 51.2 | M99: 6.4 | N99: 1.3 | O99: ISIC 29
A100: Motor vehicle parts manufacturing | B100: 3363 | C100: 413.7 | D100: 595.6 | E100: 609.9 | F100: 181.9 | G100: 14.3 | H100: 3.7 | I100: 0.2 | J100: 153.1 | K100: 324.5 | L100: 360 | M100: 7.8 | N100: 1 | O100: ISIC 29
A101: Aerospace product and parts manufacturing | B101: 3364 | C101: 492.2 | D101: 534.3 | E101: 530.5 | F101: 42.1 | G101: -3.8 | H101: 0.8 | I101: -0.1 | J101: 200 | K101: 243.6 | L101: 300.1 | M101: 2 | N101: 2.1 | O101: ISIC 30
...

Sheet AEO23 Table 23
C1: ref2023.d020623a | D1: 2022 | E1: 2023 | F1: 2024 | G1: 2025 | H1: 2026 | I1: 2027 | J1: 2028 | K1: 2029 | L1: 2030 | M1: 2031 | N1: 2032 | O1: 2033 | P1: 2034 | Q1: 2035 | R1: 2036 | S1: 2037 | T1: 2038 | U1: 2039 | V1: 2040 | W1: 2041 | X1: 2042 | Y1: 2043 | Z1: 2044 | AA1: 2045 | AB1: 2046 | AC1: 2047 | AD1: 2048 | AE1: 2049 | AF1: 2050
D3: Report | E3: Annual Energy Outlook 2023
D4: Scenario | E4: ref2023 | H4: Reference
D5: Datekey | E5: d020623a
D6: Release Date | F6: March 2023
A10: ISM000 | C10: 23. Industrial Sector Macroeconomic Indicators | AG10: Annual
AG11: Change
AG12: 2022–2050
B13: Assigned ISIC Code | C13: Indicators | D13: 2022 | E13: 2023 | F13: 2024 | G13: 2025 | H13: 2026 | I13: 2027 | J13: 2028 | K13: 2029 | L13: 2030 | M13: 2031 | N13: 2032 | O13: 2033 | P13: 2034 | Q13: 2035 | R13: 2036 | S13: 2037 | T13: 2038 | U13: 2039 | V13: 2040 | W13: 2041 | X13: 2042 | Y13: 2043 | Z13: 2044 | AA13: 2045 | AB13: 2046 | AC13: 2047 | AD13: 2048 | AE13: 2049 | AF13: 2050 | AG13: 2050
A15: ISM000:ba_GDP(billionm_ | C15: Gross Domestic Product (billion 2012 dollars) | D15: 19750.262 | E15: 19903.289 | F15: 20095.436 | G15: 20409.422 | H15: 20840.715 | I15: 21273.422 | J15: 21681.256 | K15: 22051.705 | L15: 22391.814 | M15: 22742.045 | N15: 23153.002 | O15: 23603.867 | P15: 24055.123 | Q15: 24510.957 | R15: 24995.805 | S15: 25506.922 | T15: 26032.332 | U15: 26566.107 | V15: 27148.945 | W15: 27734.088 | X15: 28324.492 | Y15: 28926.738 | Z15: 29527.414 | AA15: 30130 | AB15: 30747.568 | AC15: 31389.15 | AD15: 32039.971 | AE15: 32698.533 | AF15: 33404.984 | AG15: 0.018947
A17: ISM000:ca_NonfarmEmploy | C17: Nonfarm Employment (millions) | D17: 152.78815 | E17: 154.27263 | F17: 153.35226 | G17: 153.0864 | H17: 153.72101 | I17: 154.67316 | J17: 155.57712 | K17: 156.19121 | L17: 156.51729 | M17: 156.68424 | N17: 157.13518 | O17: 157.83719 | P17: 158.85516 | Q17: 159.68491 | R17: 160.17278 | S17: 160.75792 | T17: 161.40128 | U17: 161.96965 | V17: 162.69513 | W17: 163.29686 | X17: 163.90677 | Y17: 164.36606 | Z17: 164.78914 | AA17: 165.28934 | AB17: 165.87802 | AC17: 166.58304 | AD17: 167.2549 | AE17: 167.88226 | AF17: 168.61379 | AG17: 0.003526
C19: Value of Shipments (billion 2012 dollars)
C21: Nonmanufacturing Sector
A22: ISM000:ea_Agricultural | B22: ISIC 01T03 | C22: Agriculture/Forestry/Fishing/Hunting | D22: 545.77942 | E22: 545.04199 | F22: 550.01971 | G22: 557.38794 | H22: 565.9093 | I22: 573.4978 | J22: 580.22205 | K22: 586.10895 | L22: 591.38092 | M22: 596.96918 | N22: 602.59564 | O22: 607.97412 | P22: 612.47906 | Q22: 616.5907 | R22: 620.1156 | S22: 624.8136 | T22: 629.28332 | U22: 633.78015 | V22: 638.5282 | W22: 643.14386 | X22: 647.88428 | Y22: 652.48029 | Z22: 656.70502 | AA22: 661.02771 | AB22: 665.25879 | AC22: 669.47394 | AD22: 673.57129 | AE22: 677.73212 | AF22: 681.94012 | AG22: 0.007986
A23: ISM000:ea_Mining | B23: ISIC 05, ISIC 06, ISIC 07T08 | C23: Mining | D23: 722.17889 | E23: 701.53491 | F23: 702.08783 | G23: 704.14087 | H23: 709.14673 | I23: 706.46863 | J23: 708.54053 | K23: 706.82507 | L23: 708.71057 | M23: 711.20166 | N23: 717.27393 | O23: 723.07965 | P23: 726.81702 | Q23: 728.95288 | R23: 731.61682 | S23: 734.78876 | T23: 736.19037 | U23: 739.04053 | V23: 738.38263 | W23: 738.59168 | X23: 740.92688 | Y23: 745.11072 | Z23: 749.23816 | AA23: 749.89691 | AB23: 752.70734 | AC23: 752.01501 | AD23: 755.0564 | AE23: 759.27368 | AF23: 763.39056 | AG23: 0.001984
B24: ISIC 05 | C24: Coal Mining | D24: 26.446 | E24: 24.966 | F24: 27.292 | G24: 25.622 | H24: 23.438 | I24: 21.012 | J24: 18.858 | K24: 16.833 | L24: 15.995 | M24: 15.924 | N24: 16.039 | O24: 15.97 | P24: 15.823 | Q24: 15.942 | R24: 15.755 | S24: 15.399 | T24: 15.151 | U24: 14.791 | V24: 14.575 | W24: 14.587 | X24: 14.614 | Y24: 14.411 | Z24: 14.182 | AA24: 14.015 | AB24: 13.858 | AC24: 13.784 | AD24: 13.746 | AE24: 13.662 | AF24: 13.467 | AG24: =((AF24-D24)/D24)/(AF$13-D$13) -> -0.01752763
B25: ISIC 06 | C25: Oil & Gas Mining | D25: 623.853 | E25: 606.427 | F25: 606.26 | G25: 610.894 | H25: 619.067 | I25: 620.105 | J25: 625.143 | K25: 625.779 | L25: 628.85 | M25: 631.817 | N25: 638.005 | O25: 644.135 | P25: 648.408 | Q25: 650.536 | R25: 653.294 | S25: 656.523 | T25: 657.81 | U25: 660.437 | V25: 659.462 | W25: 659.066 | X25: 660.777 | Y25: 664.072 | Z25: 667.423 | AA25: 667.312 | AB25: 669.464 | AC25: 668.453 | AD25: 671.324 | AE25: 675.182 | AF25: 678.625 | AG25: =((AF25-D25)/D25)/(AF$13-D$13) -> 0.003135583
B26: ISIC 07T08 | C26: Metallic & Non-metallic Mining | D26: 71.88 | E26: 70.142 | F26: 68.535 | G26: 67.624 | H26: 66.642 | I26: 65.351 | J26: 64.539 | K26: 64.213 | L26: 63.865 | M26: 63.46 | N26: 63.229 | O26: 62.974 | P26: 62.587 | Q26: 62.475 | R26: 62.569 | S26: 62.866 | T26: 63.23 | U26: 63.813 | V26: 64.346 | W26: 64.939 | X26: 65.537 | Y26: 66.63 | Z26: 67.636 | AA26: 68.572 | AB26: 69.389 | AC26: 69.783 | AD26: 69.992 | AE26: 70.436 | AF26: 71.306 | AG26: =((AF26-D26)/D26)/(AF$13-D$13) -> -0.00028519755
A27: ISM000:ea_Construction | B27: ISIC 41T43 | C27: Construction | D27: 1413.1219 | E27: 1382.2755 | F27: 1372.0482 | G27: 1393.8812 | H27: 1407.6462 | I27: 1408.9215 | J27: 1419.6782 | K27: 1453.1918 | L27: 1475.3153 | M27: 1477.527 | N27: 1475.7915 | O27: 1478.0031 | P27: 1479.702 | Q27: 1486.9008 | R27: 1499.7145 | S27: 1518.985 | T27: 1541.063 | U27: 1559.6639 | V27: 1581.4187 | W27: 1606.9355 | X27: 1626.9797 | Y27: 1644.3698 | Z27: 1661.709 | AA27: 1681.6365 | AB27: 1702.3268 | AC27: 1722.4847 | AD27: 1739.5284 | AE27: 1754.6632 | AF27: 1777.882 | AG27: 0.008235
C29: Manufacturing Sector
A30: ISM000:fa_FoodandKindre | B30: ISIC 10T12 | C30: Food Products | D30: 939.78387 | E30: 954.44519 | F30: 964.02374 | G30: 972.91009 | H30: 985.45941 | I30: 999.40277 | J30: 1013.4375 | K30: 1025.6085 | L30: 1037.6696 | M30: 1051.09 | N30: 1062.7985 | O30: 1072.3557 | P30: 1082.509 | Q30: 1093.7378 | R30: 1105.5933 | S30: 1117.1162 | T30: 1128.804 | U30: 1140.9075 | V30: 1153.0015 | W30: 1164.7581 | X30: 1177.1498 | Y30: 1189.2758 | Z30: 1201.2061 | AA30: 1213.0537 | AB30: 1224.394 | AC30: 1235.8982 | AD30: 1247.5262 | AE30: 1259.2195 | AF30: 1270.8865 | AG30: 0.010838
A31: ISM000:fa_BeveragesandT | B31: ISIC 10T12 | C31: Beverages and Tobacco Products | D31: 147.62364 | E31: 145.36935 | F31: 143.5083 | G31: 142.09102 | H31: 141.56497 | I31: 141.63072 | J31: 142.03497 | K31: 142.21755 | L31: 142.01888 | M31: 141.65546 | N31: 141.51817 | O31: 141.28598 | P31: 140.65535 | Q31: 139.87833 | R31: 139.17752 | S31: 138.62692 | T31: 138.15781 | U31: 137.73245 | V31: 137.43272 | W31: 137.28285 | X31: 137.25122 | Y31: 137.28305 | Z31: 137.3369 | AA31: 137.38872 | AB31: 137.49483 | AC31: 137.73367 | AD31: 138.52859 | AE31: 139.42343 | AF31: 140.31995 | AG31: -0.001811
A32: ISM000:fa_TextileMillPr | B32: ISIC 13T15 | C32: Textile Mills and Products | D32: 66.688927 | E32: 65.669136 | F32: 65.001823 | G32: 65.029869 | H32: 66.256409 | I32: 67.770676 | J32: 68.830185 | K32: 69.285484 | L32: 69.392448 | M32: 69.699669 | N32: 70.340233 | O32: 70.872391 | P32: 71.188072 | Q32: 71.296379 | R32: 71.216957 | S32: 70.94442 | T32: 70.524757 | U32: 69.963654 | V32: 69.602867 | W32: 69.247803 | X32: 68.801804 | Y32: 68.352921 | Z32: 67.758598 | AA32: 67.12265 | AB32: 66.56498 | AC32: 66.076332 | AD32: 65.540405 | AE32: 64.960022 | AF32: 64.499519 | AG32: -0.001191
A33: ISM000:fa_LumberandWood | B33: ISIC 16 | C33: Wood Products | D33: 109.15795 | E33: 99.189583 | F33: 96.542572 | G33: 98.351212 | H33: 97.092918 | I33: 96.657242 | J33: 97.914101 | K33: 99.570168 | L33: 100.32697 | M33: 100.7081 | N33: 101.90055 | O33: 103.34675 | P33: 105.10797 | Q33: 106.07505 | R33: 105.74058 | S33: 106.26833 | T33: 106.63062 | U33: 107.17532 | V33: 108.01457 | W33: 109.21748 | X33: 110.19882 | Y33: 110.8437 | Z33: 110.92272 | AA33: 110.2698 | AB33: 109.84788 | AC33: 109.98688 | AD33: 109.76398 | AE33: 109.85477 | AF33: 111.00397 | AG33: 0.000599
A34: ISM000:fa_FurnitureandF | B34: ISIC 31T33 | C34: Furniture and Related Products | D34: 72.960655 | E34: 71.932335 | F34: 72.082062 | G34: 72.483345 | H34: 74.2827 | I34: 76.275894 | J34: 77.129929 | K34: 78.02536 | L34: 78.801346 | M34: 79.521881 | N34: 81.378906 | O34: 82.30307 | P34: 83.111809 | Q34: 84.547447 | R34: 85.96962 | S34: 87.383293 | T34: 88.995216 | U34: 90.363411 | V34: 91.695564 | W34: 93.597794 | X34: 95.362144 | Y34: 96.7351 | Z34: 97.684456 | AA34: 98.192345 | AB34: 99.417763 | AC34: 100.89883 | AD34: 101.97983 | AE34: 102.47495 | AF34: 105.48075 | AG34: 0.013252
A35: ISM000:fa_PaperandAllie | B35: ISIC 17T18 | C35: Paper Products | D35: 178.25113 | E35: 174.16162 | F35: 170.2892 | G35: 170.04311 | H35: 170.91788 | I35: 171.97682 | J35: 173.0036 | K35: 173.91675 | L35: 174.72404 | M35: 175.94983 | N35: 177.3614 | O35: 178.53641 | P35: 179.79645 | Q35: 181.1358 | R35: 182.1579 | S35: 183.31903 | T35: 184.29617 | U35: 185.34755 | V35: 186.47017 | W35: 187.5072 | X35: 188.64055 | Y35: 189.59531 | Z35: 190.21422 | AA35: 190.60817 | AB35: 191.39508 | AC35: 192.59006 | AD35: 193.08632 | AE35: 193.7601 | AF35: 195.15256 | AG35: 0.003241
A36: ISM000:fa_PrintingandPu | B36: ISIC 17T18 | C36: Printing | D36: 81.002419 | E36: 79.589355 | F36: 78.600464 | G36: 78.227867 | H36: 78.011383 | I36: 77.748795 | J36: 77.972755 | K36: 78.272659 | L36: 78.806259 | M36: 79.487358 | N36: 79.360268 | O36: 78.681564 | P36: 78.107155 | Q36: 77.655876 | R36: 77.289139 | S36: 77.00322 | T36: 76.774658 | U36: 76.536819 | V36: 76.742325 | W36: 76.605957 | X36: 76.091614 | Y36: 75.87841 | Z36: 75.894768 | AA36: 76.632271 | AB36: 77.276047 | AC36: 77.723999 | AD36: 77.96183 | AE36: 78.920258 | AF36: 79.63163 | AG36: -0.000609
A37: ISM000:fa_ChemicalandAl | B37: ISIC 20 | C37: Chemical Manufacturing | D37: 967.66296 | E37: 946.27154 | F37: 935.03003 | G37: 950.27484 | H37: 972.21118 | I37: 994.82507 | J37: 1014.7354 | K37: 1030.5259 | L37: 1043.5344 | M37: 1058.1084 | N37: 1076.729 | O37: 1095.6531 | P37: 1117.4678 | Q37: 1139.9451 | R37: 1160.9132 | S37: 1183.1794 | T37: 1205.0225 | U37: 1229.1611 | V37: 1256.4189 | W37: 1284.9854 | X37: 1315.0056 | Y37: 1345.7153 | Z37: 1374.64 | AA37: 1401.1206 | AB37: 1430.0171 | AC37: 1461.9226 | AD37: 1489.7931 | AE37: 1517.437 | AF37: 1552.1362 | AG37: 0.017018
A38: ISM000:fa_BulkChemicals | C38: Bulk Chemicals | D38: 474.04568 | E38: 452.66242 | F38: 441.20395 | G38: 453.24295 | H38: 468.34979 | I38: 480.99966 | J38: 490.77292 | K38: 497.28476 | L38: 503.20383 | M38: 511.00143 | N38: 519.99524 | O38: 527.93658 | P38: 537.20996 | Q38: 545.92432 | R38: 552.7475 | S38: 560.28912 | T38: 566.19134 | U38: 573.65039 | V38: 582.99744 | W38: 591.11865 | X38: 598.44318 | Y38: 605.70813 | Z38: 611.42059 | AA38: 616.42041 | AB38: 624.27167 | AC38: 633.37225 | AD38: 638.37659 | AE38: 645.89203 | AF38: 658.58075 | AG38: 0.011811
A39: ISM000:fa_Inorganic | C39: Inorganic | D39: 53.798809 | E39: 54.111629 | F39: 53.713581 | G39: 54.911659 | H39: 56.147316 | I39: 56.867516 | J39: 57.306702 | K39: 57.473934 | L39: 57.516285 | M39: 57.632683 | N39: 57.847565 | O39: 58.079575 | P39: 58.482449 | Q39: 58.852043 | R39: 59.066029 | S39: 59.383343 | T39: 59.432823 | U39: 59.717861 | V39: 60.181442 | W39: 60.545666 | X39: 60.773445 | Y39: 60.956928 | Z39: 61.076263 | AA39: 60.964104 | AB39: 61.165001 | AC39: 61.487888 | AD39: 61.390053 | AE39: 61.481033 | AF39: 62.171909 | AG39: 0.00518
A40: ISM000:fa_Organic | C40: Organic | D40: 248.33983 | E40: 230.08815 | F40: 219.437 | G40: 227.44753 | H40: 235.27855 | I40: 241.42763 | J40: 246.63138 | K40: 250.20329 | L40: 253.8663 | M40: 258.56909 | N40: 263.46579 | O40: 267.66647 | P40: 272.58536 | Q40: 277.16125 | R40: 280.81647 | S40: 284.98618 | T40: 288.07333 | U40: 292.60126 | V40: 298.18259 | W40: 302.85239 | X40: 307.34738 | Y40: 311.99383 | Z40: 315.71549 | AA40: 319.06912 | AB40: 324.11478 | AC40: 329.6669 | AD40: 332.79184 | AE40: 337.66672 | AF40: 345.46246 | AG40: 0.011859
A41: ISM000:fa_Resins | C41: Resin, Synthetic Rubber, and Fibers | D41: 125.4339 | E41: 122.1189 | F41: 120.86272 | G41: 122.11227 | H41: 126.20548 | I41: 130.35954 | J41: 133.31703 | K41: 135.15277 | L41: 136.57359 | M41: 138.5574 | N41: 141.15958 | O41: 143.60413 | P41: 146.3638 | Q41: 148.97583 | R41: 151.11197 | S41: 153.40373 | T41: 155.45435 | U41: 157.85867 | V41: 160.78615 | W41: 163.26277 | X41: 165.62367 | Y41: 168.16382 | Z41: 170.3674 | AA41: 172.53685 | AB41: 175.23433 | AC41: 178.26677 | AD41: 180.39847 | AE41: 182.98766 | AF41: 186.81578 | AG41: 0.014328
A42: ISM000:fa_AgriculturalC | C42: Agricultural Chemicals | D42: 46.473137 | E42: 46.343746 | F42: 47.190632 | G42: 48.771492 | H42: 50.718433 | I42: 52.345001 | J42: 53.517792 | K42: 54.454769 | L42: 55.247646 | M42: 56.242249 | N42: 57.522289 | O42: 58.586426 | P42: 59.778351 | Q42: 60.93515 | R42: 61.753002 | S42: 62.515858 | T42: 63.230846 | U42: 63.472591 | V42: 63.847294 | W42: 64.457809 | X42: 64.698669 | Y42: 64.593536 | Z42: 64.261429 | AA42: 63.850342 | AB42: 63.757587 | AC42: 63.950691 | AD42: 63.796268 | AE42: 63.756603 | AF42: 64.130592 | AG42: 0.011568
A43: ISM000:fa_OtherChemical | C43: Other Chemical Products | D43: 493.61728 | E43: 493.60913 | F43: 493.82608 | G43: 497.03189 | H43: 503.86139 | I43: 513.82538 | J43: 523.9624 | K43: 533.24115 | L43: 540.33057 | M43: 547.10693 | N43: 556.7337 | O43: 567.71655 | P43: 580.25775 | Q43: 594.02081 | R43: 608.16571 | S43: 622.89032 | T43: 638.83112 | U43: 655.51068 | V43: 673.42157 | W43: 693.8667 | X43: 716.56244 | Y43: 740.0072 | Z43: 763.21942 | AA43: 784.7002 | AB43: 805.74548 | AC43: 828.55042 | AD43: 851.4165 | AE43: 871.54504 | AF43: 893.55548 | AG43: 0.021421
A44: ISM000:fa_PetroleumandC | B44: ISIC 19 | C44: Petroleum and Coal Products | D44: 817.11469 | E44: 886.91461 | F44: 884.32819 | G44: 881.06311 | H44: 877.14594 | I44: 874.70398 | J44: 872.0647 | K44: 868.17157 | L44: 862.2085 | M44: 856.56988 | N44: 853.14038 | O44: 850.25525 | P44: 848.71527 | Q44: 846.04517 | R44: 843.56927 | S44: 841.93683 | T44: 840.54669 | U44: 840.63409 | V44: 841.8457 | W44: 843.08704 | X44: 845.15832 | Y44: 847.45727 | Z44: 850.05902 | AA44: 851.92218 | AB44: 856.05603 | AC44: 860.54694 | AD44: 862.95355 | AE44: 867.26434 | AF44: 875.4148 | AG44: 0.002464
A45: ISM000:fa_PetroleumRefi | C45: Petroleum Refineries | D45: 772.46887 | E45: 839.67993 | F45: 835.56805 | G45: 832.39215 | H45: 829.06683 | I45: 826.93988 | J45: 824.6571 | K45: 821.24591 | L45: 815.68445 | M45: 810.43555 | N45: 807.50134 | O45: 805.01221 | P45: 803.8255 | Q45: 801.60706 | R45: 799.5401 | S45: 798.39447 | T45: 797.60571 | U45: 798.13757 | V45: 799.69812 | W45: 801.39166 | X45: 803.8324 | Y45: 806.45361 | Z45: 809.37402 | AA45: 811.54797 | AB45: 815.90723 | AC45: 820.65881 | AD45: 823.51312 | AE45: 828.04889 | AF45: 836.25623 | AG45: 0.002838
A46: ISM000:fa_OtherPetroleu | C46: Other Petroleum and Coal Products | D46: 44.645794 | E46: 47.234665 | F46: 48.760155 | G46: 48.67094 | H46: 48.079117 | I46: 47.764069 | J46: 47.4076 | K46: 46.925644 | L46: 46.524067 | M46: 46.134365 | N46: 45.639008 | O46: 45.24305 | P46: 44.889744 | Q46: 44.438141 | R46: 44.029171 | S46: 43.54237 | T46: 42.940994 | U46: 42.496525 | V46: 42.147572 | W46: 41.695381 | X46: 41.325928 | Y46: 41.003651 | Z46: 40.685013 | AA46: 40.37421 | AB46: 40.148823 | AC46: 39.888149 | AD46: 39.440418 | AE46: 39.215481 | AF46: 39.158562 | AG46: -0.004673
A47: ISM000:fa_RubberandMisc | B47: ISIC 22 | C47: Plastics and Rubber Products | D47: 254.56865 | E47: 249.40262 | F47: 247.59621 | G47: 251.19984 | H47: 257.79541 | I47: 263.61346 | J47: 268.53961 | K47: 273.15314 | L47: 277.04922 | M47: 281.63605 | N47: 287.50537 | O47: 292.88174 | P47: 297.91623 | Q47: 303.86456 | R47: 309.03873 | S47: 314.23059 | T47: 319.51648 | U47: 324.26389 | V47: 329.41122 | W47: 335.37335 | X47: 341.05621 | Y47: 347.27945 | Z47: 352.69455 | AA47: 357.66486 | AB47: 363.25119 | AC47: 369.17844 | AD47: 374.38232 | AE47: 379.79688 | AF47: 387.68674 | AG47: 0.015136
A48: ISM000:fa_Stone,Clay,an | C48: Stone, Clay, and Glass Products | D48: 119.73004 | E48: 114.43849 | F48: 113.30817 | G48: 115.06697 | H48: 117.80908 | I48: 119.95847 | J48: 121.75865 | K48: 123.304 | L48: 124.48431 | M48: 125.74026 | N48: 127.29343 | O48: 128.58807 | P48: 129.51486 | Q48: 131.14478 | R48: 132.32974 | S48: 133.82094 | T48: 135.45262 | U48: 137.08142 | V48: 138.79272 | W48: 140.51498 | X48: 141.87474 | Y48: 142.38699 | Z48: 143.67725 | AA48: 145.33728 | AB48: 146.83905 | AC48: 148.28322 | AD48: 149.31998 | AE48: 150.34843 | AF48: 151.64003 | AG48: 0.008474
A49: ISM000:fa_GlassandGlass | B49: ISIC 231 | C49: Glass and Glass Products | D49: 23.835207 | E49: 22.431635 | F49: 22.050007 | G49: 22.057529 | H49: 22.68103 | I49: 23.030569 | J49: 23.301847 | K49: 23.512806 | L49: 23.634199 | M49: 23.801592 | N49: 24.003618 | O49: 24.275005 | P49: 24.565556 | Q49: 24.908245 | R49: 25.079617 | S49: 25.316305 | T49: 25.550051 | U49: 25.968063 | V49: 26.382378 | W49: 26.675877 | X49: 27.04561 | Y49: 27.1824 | Z49: 27.408552 | AA49: 27.686163 | AB49: 28.096258 | AC49: 28.340467 | AD49: 28.420309 | AE49: 28.615231 | AF49: 28.898367 | AG49: 0.006903
A50: ISM000:fa_CementandHydr | B50: ISIC 239 | C50: Cement and Lime | D50: 16.081751 | E50: 15.364241 | F50: 15.174519 | G50: 15.420744 | H50: 15.655219 | I50: 15.80765 | J50: 15.951729 | K50: 16.142639 | L50: 16.343666 | M50: 16.538471 | N50: 16.67625 | O50: 16.739433 | P50: 16.852367 | Q50: 17.106045 | R50: 17.312027 | S50: 17.484806 | T50: 17.670828 | U50: 17.814068 | V50: 18.006584 | W50: 18.220646 | X50: 18.389345 | Y50: 18.476151 | Z50: 18.683887 | AA50: 18.925755 | AB50: 19.120739 | AC50: 19.317871 | AD50: 19.466255 | AE50: 19.601412 | AF50: 19.775444 | AG50: 0.007411
A51: ISM000:fa_OtherStone,Cl | B51: ISIC 239 | C51: Other Nonmetallic Mineral Products | D51: 79.813087 | E51: 76.642616 | F51: 76.083649 | G51: 77.588699 | H51: 79.472832 | I51: 81.120255 | J51: 82.505074 | K51: 83.648552 | L51: 84.506439 | M51: 85.400192 | N51: 86.613556 | O51: 87.573631 | P51: 88.096947 | Q51: 89.130486 | R51: 89.938095 | S51: 91.019829 | T51: 92.231743 | U51: 93.299286 | V51: 94.403755 | W51: 95.618454 | X51: 96.439789 | Y51: 96.728447 | Z51: 97.584801 | AA51: 98.725357 | AB51: 99.622055 | AC51: 100.62488 | AD51: 101.4334 | AE51: 102.1318 | AF51: 102.96622 | AG51: 0.009138
A52: ISM000:ga_PrimaryMetals | C52: Primary Metals Industry | D52: 244.92064 | E52: 242.71448 | F52: 242.90793 | G52: 250.14743 | H52: 260.91779 | I52: 267.47144 | J52: 270.68414 | K52: 273.12375 | L52: 273.69507 | M52: 274.63815 | N52: 277.50684 | O52: 278.69522 | P52: 280.69861 | Q52: 283.36298 | R52: 285.98868 | S52: 290.06491 | T52: 293.63898 | U52: 296.83246 | V52: 300.25464 | W52: 304.25342 | X52: 308.32468 | Y52: 311.60855 | Z52: 314.53909 | AA52: 317.61679 | AB52: 321.32205 | AC52: 325.11304 | AD52: 327.84747 | AE52: 330.89224 | AF52: 335.56 | AG52: 0.011309
A53: ISM000:ga_BlastFurnacea | B53: ISIC 241 | C53: Iron and Steel Mills and Products | D53: 126.8552 | E53: 124.78828 | F53: 122.8615 | G53: 125.64732 | H53: 131.64795 | I53: 134.76013 | J53: 135.50011 | K53: 136.1655 | L53: 135.42818 | M53: 135.13988 | N53: 136.50102 | O53: 136.04562 | P53: 135.9646 | Q53: 136.36446 | R53: 136.71965 | S53: 138.30264 | T53: 139.27753 | U53: 139.56673 | V53: 140.15816 | W53: 141.20677 | X53: 142.31332 | Y53: 142.74843 | Z53: 142.77147 | AA53: 142.4512 | AB53: 142.66772 | AC53: 143.31915 | AD53: 143.41283 | AE53: 143.60941 | AF53: 145.06587 | AG53: 0.004802
A54: ISM000:ga_Aluminum | B54: ISIC 242 | C54: Alumina and Aluminum Products | D54: 39.489658 | E54: 39.006199 | F54: 39.241928 | G54: 40.383499 | H54: 41.714424 | I54: 42.604626 | J54: 43.222198 | K54: 43.558788 | L54: 43.667107 | M54: 43.847263 | N54: 44.095451 | O54: 44.485649 | P54: 45.056721 | Q54: 45.648441 | R54: 46.072399 | S54: 46.591618 | T54: 47.106682 | U54: 47.672859 | V54: 48.02721 | W54: 48.631012 | X54: 49.402283 | Y54: 49.964901 | Z54: 50.329197 | AA54: 50.972748 | AB54: 51.743004 | AC54: 52.397064 | AD54: 52.615349 | AE54: 53.016792 | AF54: 53.815617 | AG54: 0.011116
A55: ISM000:ga_OtherPrimaryM | B55: ISIC 242 | C55: Other Primary Metal Products | D55: 78.575775 | E55: 78.919991 | F55: 80.804497 | G55: 84.116608 | H55: 87.555405 | I55: 90.106674 | J55: 91.961853 | K55: 93.399452 | L55: 94.599777 | M55: 95.651016 | N55: 96.91037 | O55: 98.16394 | P55: 99.677277 | Q55: 101.3501 | R55: 103.19662 | S55: 105.17065 | T55: 107.25478 | U55: 109.59285 | V55: 112.06928 | W55: 114.41565 | X55: 116.60908 | Y55: 118.89523 | Z55: 121.43842 | AA55: 124.19285 | AB55: 126.91132 | AC55: 129.39682 | AD55: 131.81932 | AE55: 134.26605 | AF55: 136.67853 | AG55: 0.019967
A56: ISM000:ga_FabricatedMet | B56: ISIC 25 | C56: Fabricated Metal Products | D56: 361.08463 | E56: 354.09451 | F56: 351.4848 | G56: 357.95004 | H56: 369.75708 | I56: 379.72571 | J56: 385.55939 | K56: 390.02487 | L56: 392.79275 | M56: 396.91483 | N56: 405.37015 | O56: 412.59906 | P56: 418.59824 | Q56: 426.64352 | R56: 435.44189 | S56: 445.06946 | T56: 454.90762 | U56: 462.15436 | V56: 469.06369 | W56: 478.0939 | X56: 485.71448 | Y56: 492.09628 | Z56: 496.24027 | AA56: 498.41034 | AB56: 500.96777 | AC56: 505.22824 | AD56: 507.26755 | AE56: 507.68613 | AF56: 514.91852 | AG56: 0.012756
A57: ISM000:ga_IndustrialMac | B57: ISIC 28 | C57: Machinery | D57: 399.612 | E57: 393.56274 | F57: 393.80505 | G57: 398.59122 | H57: 413.20258 | I57: 426.06223 | J57: 431.62192 | K57: 436.47894 | L57: 441.38394 | M57: 448.8024 | N57: 460.85584 | O57: 470.08539 | P57: 477.91144 | Q57: 487.04831 | R57: 495.56311 | S57: 503.83859 | T57: 512.09668 | U57: 518.91455 | V57: 525.7898 | W57: 533.87219 | X57: 541.03369 | Y57: 546.68652 | Z57: 551.02954 | AA57: 554.63654 | AB57: 560.65308 | AC57: 567.37158 | AD57: 573.51648 | AE57: 577.69525 | AF57: 585.69397 | AG57: 0.013747
A58: ISM000:ga_Electronicand | B58: ISIC 26 | C58: Computers and Electronics | D58: 506.49094 | E58: 516.42877 | F58: 532.86395 | G58: 553.77118 | H58: 577.25574 | I58: 597.36414 | J58: 614.67828 | K58: 627.72113 | L58: 637.34918 | M58: 648.73743 | N58: 662.29175 | O58: 675.88458 | P58: 690.44891 | Q58: 704.77856 | R58: 720.01514 | S58: 736.80139 | T58: 754.86902 | U58: 773.49487 | V58: 794.91992 | W58: 816.08807 | X58: 835.0398 | Y58: 855.20026 | Z58: 874.60535 | AA58: 893.03076 | AB58: 911.92706 | AC58: 931.36383 | AD58: 950.1554 | AE58: 970.8056 | AF58: 994.11694 | AG58: 0.024376
A59: ISM000:ga_Transportatio | B59: ISIC 29, ISIC 30 | C59: Transportation Equipment | D59: 1128.2124 | E59: 1163.308 | F59: 1177.9012 | G59: 1174.4565 | H59: 1180.5706 | I59: 1202.4993 | J59: 1218.9282 | K59: 1226.8571 | L59: 1237.5537 | M59: 1256.5177 | N59: 1288.4041 | O59: 1316.1978 | P59: 1337.4108 | Q59: 1360.609 | R59: 1382.8597 | S59: 1398.0405 | T59: 1415.6758 | U59: 1429.8843 | V59: 1450.14 | W59: 1475.5818 | X59: 1500.8208 | Y59: 1522.6357 | Z59: 1540.6465 | AA59: 1558.8315 | AB59: 1582.4725 | AC59: 1608.0563 | AD59: 1631.1317 | AE59: 1653.2063 | AF59: 1681.0548 | AG59: 0.014344
A60: ISM000:ga_Instrumentsan | B60: ISIC 27 | C60: Electrical Equipment | D60: 136.71812 | E60: 136.66016 | F60: 138.18132 | G60: 141.50218 | H60: 144.87215 | I60: 147.97397 | J60: 150.72812 | K60: 153.04495 | L60: 154.97905 | M60: 156.09593 | N60: 159.33145 | O60: 163.81352 | P60: 168.14465 | Q60: 172.72577 | R60: 177.38597 | S60: 182.32001 | T60: 187.67952 | U60: 192.96304 | V60: 198.58502 | W60: 204.38623 | X60: 209.77016 | Y60: 215.49573 | Z60: 221.13318 | AA60: 226.60126 | AB60: 232.24367 | AC60: 238.18221 | AD60: 244.16103 | AE60: 250.01297 | AF60: 257.04514 | AG60: 0.022804
A61: ISM000:ga_Miscellaneous | B61: ISIC 31T33 | C61: Miscellaneous Manufacturing | D61: 166.3022 | E61: 164.43683 | F61: 164.33728 | G61: 160.20967 | H61: 158.97865 | I61: 159.3035 | J61: 160.67364 | K61: 162.23003 | L61: 163.81959 | M61: 165.47687 | N61: 168.42876 | O61: 171.3121 | P61: 174.08283 | Q61: 176.28294 | R61: 178.13245 | S61: 180.56085 | T61: 183.43233 | U61: 185.94917 | V61: 188.78363 | W61: 191.34273 | X61: 193.95433 | Y61: 196.60257 | Z61: 198.852 | AA61: 201.2506 | AB61: 203.855 | AC61: 206.75023 | AD61: 209.36388 | AE61: 211.71013 | AF61: 215.3761 | AG61: 0.009278
A63: ISM000:ha_TotalIndustri | C63: Total Industrial Value of Shipments | D63: 9378.9648 | E63: 9387.4414 | F63: 9395.9473 | G63: 9488.7803 | H63: 9626.8047 | I63: 9753.8516 | J63: 9868.7363 | K63: 9977.6572 | L63: 10065.997 | M63: 10153.048 | N63: 10277.176 | O63: 10392.405 | P63: 10500.384 | Q63: 10619.222 | R63: 10739.829 | S63: 10869.113 | T63: 11003.56 | U63: 11131.844 | V63: 11275.294 | W63: 11434.468 | X63: 11587.041 | Y63: 11733.09 | Z63: 11866.786 | AA63: 11992.253 | AB63: 12136.289 | AC63: 12286.879 | AD63: 12422.438 | AE63: 12557.138 | AF63: 12740.831 | AG63: 0.011001
C66: Note: Totals may not equal sum of components due to independent rounding.
C67: Data source: 2022: IHS Markit, Macroeconomic model, September 2022.
C68: Projections: U.S. Energy Information Administration, AEO2023 National Energy Modeling System run ref2023.d020623a.
AG162: Average

Sheet AEO22 Table 23
C1: ref2022.d011222a | D1: 2021 | E1: 2022 | F1: 2023 | G1: 2024 | H1: 2025 | I1: 2026 | J1: 2027 | K1: 2028 | L1: 2029 | M1: 2030 | N1: 2031 | O1: 2032 | P1: 2033 | Q1: 2034 | R1: 2035 | S1: 2036 | T1: 2037 | U1: 2038 | V1: 2039 | W1: 2040 | X1: 2041 | Y1: 2042 | Z1: 2043 | AA1: 2044 | AB1: 2045 | AC1: 2046 | AD1: 2047 | AE1: 2048 | AF1: 2049 | AG1: 2050
D3: Report | E3: Annual Energy Outlook 2022
D4: Scenario | E4: ref2022 | H4: Reference
D5: Datekey | E5: d011222a
D6: Release Date | F6: March 2022
A10: ISM000 | C10: 23. Industrial Sector Macroeconomic Indicators | AH10: Average
AH11: Annual
AH12: Change
C13: Indicators | D13: 2021 | E13: 2022 | F13: 2023 | G13: 2024 | H13: 2025 | I13: 2026 | J13: 2027 | K13: 2028 | L13: 2029 | M13: 2030 | N13: 2031 | O13: 2032 | P13: 2033 | Q13: 2034 | R13: 2035 | S13: 2036 | T13: 2037 | U13: 2038 | V13: 2039 | W13: 2040 | X13: 2041 | Y13: 2042 | Z13: 2043 | AA13: 2044 | AB13: 2045 | AC13: 2046 | AD13: 2047 | AE13: 2048 | AF13: 2049 | AG13: 2050 | AH13: 2021–2050
A15: ISM000:ba_GDP(billionm_ | C15: Gross Domestic Product (billion 2012 dollars) | D15: 19438.871 | E15: 20303.057 | F15: 20862.09 | G15: 21484.092 | H15: 22061.072 | I15: 22609.408 | J15: 23060.262 | K15: 23516.82 | L15: 24014.523 | M15: 24555.002 | N15: 25077.85 | O15: 25619.295 | P15: 26179.602 | Q15: 26734.855 | R15: 27278.783 | S15: 27816.73 | T15: 28383.762 | U15: 28943.43 | V15: 29525.475 | W15: 30134.961 | X15: 30703.848 | Y15: 31299.002 | Z15: 31912.465 | AA15: 32530.057 | AB15: 33192.914 | AC15: 33877.379 | AD15: 34526.266 | AE15: 35184.418 | AF15: 35901.258 | AG15: 36652.418 | AH15: 0.02211
A17: ISM000:ca_NonfarmEmploy | C17: Nonfarm Employment (millions) | D17: 147.7354 | E17: 151.96385 | F17: 154.61392 | G17: 156.59798 | H17: 158.08708 | I17: 159.09639 | J17: 159.5717 | K17: 159.86189 | L17: 160.31001 | M17: 161.08504 | N17: 161.90631 | O17: 162.76161 | P17: 163.63913 | Q17: 164.36713 | R17: 164.97369 | S17: 165.64359 | T17: 166.38374 | U17: 167.03009 | V17: 167.69005 | W17: 168.45996 | X17: 169.02303 | Y17: 169.64963 | Z17: 170.25621 | AA17: 170.88242 | AB17: 171.69136 | AC17: 172.60467 | AD17: 173.40042 | AE17: 174.12158 | AF17: 174.89842 | AG17: 175.81247 | AH17: 0.006018
C19: Value of Shipments (billion 2012 dollars)
C21: Nonmanufacturing Sector
A22: ISM000:ea_Agricultural | B22: ISIC 01T03 | C22: Agriculture/Forestry/Fishing/Hunting | D22: 545.77948 | E22: 552.14722 | F22: 560.64447 | G22: 567.55975 | H22: 573.87244 | I22: 580.91406 | J22: 586.7279 | K22: 591.82111 | L22: 596.94867 | M22: 602.08496 | N22: 607.3252 | O22: 612.60632 | P22: 618.47119 | Q22: 624.12738 | R22: 629.57202 | S22: 634.99017 | T22: 640.35761 | U22: 645.62769 | V22: 651.13117 | W22: 656.64172 | X22: 661.95502 | Y22: 667.49902 | Z22: 673.1568 | AA22: 678.7323 | AB22: 684.35681 | AC22: 689.95392 | AD22: 695.43634 | AE22: 700.97406 | AF22: 706.69727 | AG22: 712.4021 | AH22: 0.00923
A23: ISM000:ea_Mining | B23: ISIC 05, ISIC 06, ISIC 07T08 | C23: Mining | D23: 688.52893 | E23: 689.23773 | F23: 702.49676 | G23: 709.7558 | H23: 718.94476 | I23: 722.815 | J23: 722.08893 | K23: 730.04761 | L23: 731.65649 | M23: 731.26288 | N23: 732.96625 | O23: 733.21106 | P23: 736.24078 | Q23: 733.505 | R23: 731.31287 | S23: 729.72797 | T23: 728.67474 | U23: 730.38892 | V23: 733.61713 | W23: 739.07812 | X23: 743.18738 | Y23: 747.1203 | Z23: 748.44061 | AA23: 753.52881 | AB23: 758.354 | AC23: 761.52869 | AD23: 761.06799 | AE23: 761.68921 | AF23: 767.09283 | AG23: 774.31165 | AH23: 0.004057
A24: ISM000:ea_Construction | B24: ISIC 41T43 | C24: Construction | D24: 1448.7993 | E24: 1442.7209 | F24: 1437.3 | G24: 1458.236 | H24: 1477.7488 | I24: 1492.21 | J24: 1487.4272 | K24: 1483.879 | L24: 1494.762 | M24: 1510.8843 | N24: 1524.2035 | O24: 1540.861 | P24: 1562.8483 | Q24: 1583.0125 | R24: 1603.2435 | S24: 1623.929 | T24: 1649.5417 | U24: 1678.0015 | V24: 1705.311 | W24: 1732.4323 | X24: 1759.183 | Y24: 1783.3943 | Z24: 1811.0947 | AA24: 1839.1035 | AB24: 1867.8518 | AC24: 1897.6746 | AD24: 1923.6075 | AE24: 1949.1226 | AF24: 1977.4344 | AG24: 2011.7247 | AH24: 0.011384
C26: Manufacturing Sector
A27: ISM000:fa_FoodandKindre | B27: ISIC 10T12 | C27: Food Products | D27: 951.64435 | E27: 969.73547 | F27: 975.43127 | G27: 983.50012 | H27: 993.35529 | I27: 1003.6312 | J27: 1013.578 | K27: 1024.7405 | L27: 1035.0825 | M27: 1044.615 | N27: 1054.9303 | O27: 1065.0167 | P27: 1074.1035 | Q27: 1082.7581 | R27: 1091.632 | S27: 1100.9747 | T27: 1109.9 | U27: 1119.0065 | V27: 1128.4292 | W27: 1137.6937 | X27: 1146.863 | Y27: 1156.2877 | Z27: 1165.49 | AA27: 1174.729 | AB27: 1183.9547 | AC27: 1192.7638 | AD27: 1201.618 | AE27: 1210.6035 | AF27: 1219.4705 | AG27: 1228.2841 | AH27: 0.008838
A28: ISM000:fa_BeveragesandT | B28: ISIC 10T12 | C28: Beverages and Tobacco Products | D28: 150.72591 | E28: 147.2585 | F28: 144.78615 | G28: 143.32643 | H28: 142.30045 | I28: 141.96205 | J28: 142.20155 | K28: 142.80542 | L28: 143.61658 | M28: 144.21668 | N28: 144.74503 | O28: 145.869 | P28: 146.2294 | Q28: 146.5215 | R28: 147.08548 | S28: 147.69237 | T28: 148.36345 | U28: 149.07938 | V28: 149.82077 | W28: 150.58372 | X28: 151.42322 | Y28: 152.35104 | Z28: 153.35233 | AA28: 154.40097 | AB28: 155.42813 | AC28: 156.50403 | AD28: 157.64278 | AE28: 158.90268 | AF28: 160.20403 | AG28: 161.54601 | AH28: 0.002393
A29: ISM000:fa_TextileMillPr | B29: ISIC 13T15 | C29: Textile Mills and Products | D29: 66.721695 | E29: 67.593826 | F29: 68.469559 | G29: 69.033905 | H29: 69.052765 | I29: 68.939026 | J29: 68.798462 | K29: 68.594276 | L29: 68.563225 | M29: 68.533302 | N29: 68.430939 | O29: 68.233284 | P29: 67.952148 | Q29: 67.658035 | R29: 67.259186 | S29: 66.854469 | T29: 66.612335 | U29: 66.362816 | V29: 66.145142 | W29: 65.970001 | X29: 65.693214 | Y29: 65.481339 | Z29: 65.372375 | AA29: 65.213631 | AB29: 65.032646 | AC29: 64.864479 | AD29: 64.590843 | AE29: 64.266777 | AF29: 64.021324 | AG29: 63.775253 | AH29: -0.001556
A30: ISM000:fa_LumberandWood | B30: ISIC 16 | C30: Wood Products | D30: 109.86588 | E30: 106.00285 | F30: 99.745964 | G30: 100.82505 | H30: 103.02953 | I30: 101.7004 | J30: 99.70639 | K30: 98.509315 | L30: 99.302048 | M30: 100.30915 | N30: 100.32555 | O30: 100.4003 | P30: 100.47907 | Q30: 100.72337 | R30: 101.10352 | S30: 101.57725 | T30: 102.09487 | U30: 102.7057 | V30: 103.15823 | W30: 103.58488 | X30: 104.38545 | Y30: 105.33315 | Z30: 106.28017 | AA30: 107.1138 | AB30: 107.56798 | AC30: 108.25343 | AD30: 108.72565 | AE30: 108.809 | AF30: 109.43413 | AG30: 110.89915 | AH30: 0.000323
A31: ISM000:fa_FurnitureandF | B31: ISIC 31T33 | C31: Furniture and Related Products | D31: 73.106606 | E31: 75.028778 | F31: 75.784859 | G31: 76.957291 | H31: 77.742348 | I31: 78.483177 | J31: 79.329269 | K31: 79.386116 | L31: 80.388123 | M31: 81.368095 | N31: 81.871971 | O31: 83.068512 | P31: 83.768402 | Q31: 84.762726 | R31: 85.794304 | S31: 86.949249 | T31: 88.365646 | U31: 89.693413 | V31: 90.898483 | W31: 91.887215 | X31: 93.156837 | Y31: 94.80825 | Z31: 96.239616 | AA31: 97.37513 | AB31: 98.100868 | AC31: 99.55941 | AD31: 100.74035 | AE31: 101.5865 | AF31: 102.70847 | AG31: 105.44625 | AH31: 0.012711
A32: ISM000:fa_PaperandAllie | B32: ISIC 17T18 | C32: Paper Products | D32: 172.22682 | E32: 175.70012 | F32: 177.3605 | G32: 178.58215 | H32: 178.74803 | I32: 179.60713 | J32: 179.96355 | K32: 180.91734 | L32: 181.95015 | M32: 182.56682 | N32: 183.55988 | O32: 184.26218 | P32: 184.68878 | Q32: 185.0869 | R32: 185.5136 | S32: 186.00328 | T32: 186.67717 | U32: 187.50854 | V32: 188.23453 | W32: 188.80972 | X32: 189.9736 | Y32: 191.32828 | Z32: 192.54414 | AA32: 193.15605 | AB32: 193.70967 | AC32: 194.81815 | AD32: 195.5571 | AE32: 195.99753 | AF32: 196.82808 | AG32: 198.1973 | AH32: 0.004855
A33: ISM000:fa_PrintingandPu | B33: ISIC 17T18 | C33: Printing | D33: 82.234703 | E33: 81.876869 | F33: 81.840088 | G33: 81.445869 | H33: 80.929611 | I33: 80.451355 | J33: 80.031052 | K33: 80.29612 | L33: 80.499329 | M33: 80.719246 | N33: 80.959885 | O33: 81.481293 | P33: 82.232033 | Q33: 82.680382 | R33: 83.118652 | S33: 83.346397 | T33: 83.320343 | U33: 83.312767 | V33: 83.340996 | W33: 83.697945 | X33: 84.020721 | Y33: 83.936172 | Z33: 83.985703 | AA33: 84.163116 | AB33: 84.884033 | AC33: 85.389442 | AD33: 85.76915 | AE33: 86.23526 | AF33: 87.04763 | AG33: 87.409546 | AH33: 0.002107
A34: ISM000:fa_ChemicalandAl | B34: ISIC 20 | C34: Chemical Manufacturing | D34: 980.72162 | E34: 957.32135 | F34: 966.80652 | G34: 977.65759 | H34: 995.81482 | I34: 1015.5247 | J34: 1031.1311 | K34: 1046.7871 | L34: 1063.3916 | M34: 1079.6182 | N34: 1098.2726 | O34: 1119.4585 | P34: 1140.0747 | Q34: 1159.6724 | R34: 1179.4001 | S34: 1199.698 | T34: 1222.3354 | U34: 1244.856 | V34: 1266.0388 | W34: 1286.337 | X34: 1310.5225 | Y34: 1336.5942 | Z34: 1363.5806 | AA34: 1388.5498 | AB34: 1413.7634 | AC34: 1441.4657 | AD34: 1465.4834 | AE34: 1482.9764 | AF34: 1504.9686 | AG34: 1534.4824 | AH34: 0.015556
A35: ISM000:fa_BulkChemicals | C35: Bulk Chemicals | D35: 463.10675 | E35: 468.24509 | F35: 479.79095 | G35: 487.43439 | H35: 500.19367 | I35: 513.36963 | J35: 521.77905 | K35: 530.20532 | L35: 538.04102 | M35: 545.00226 | N35: 554.26514 | O35: 564.98492 | P35: 574.2337 | Q35: 581.92554 | R35: 589.4256 | S35: 597.31757 | T35: 606.92804 | U35: 615.27032 | V35: 621.87152 | W35: 628.11084 | X35: 637.29932 | Y35: 645.9115 | Z35: 654.9917 | AA35: 661.87604 | AB35: 669.14624 | AC35: 677.84235 | AD35: 682.63867 | AE35: 683.89337 | AF35: 691.96124 | AG35: 707.11926 | AH35: 0.014702
A36: ISM000:fa_Inorganic | C36: Inorganic | D36: 53.850636 | E36: 52.575943 | F36: 52.256378 | G36: 52.022209 | H36: 51.873573 | I36: 52.164024 | J36: 52.21394 | K36: 52.57375 | L36: 52.879528 | M36: 53.059776 | N36: 53.259762 | O36: 53.452988 | P36: 53.654133 | Q36: 53.825176 | R36: 54.031891 | S36: 54.32243 | T36: 54.895737 | U36: 55.440514 | V36: 55.787117 | W36: 56.099892 | X36: 56.947971 | Y36: 57.702496 | Z36: 58.261211 | AA36: 58.351322 | AB36: 58.491787 | AC36: 58.508251 | AD36: 58.358147 | AE36: 57.562294 | AF36: 57.502651 | AG36: 58 | AH36: 0.002563
A37: ISM000:fa_Organic | C37: Organic | D37: 234.04575 | E37: 233.91756 | F37: 243.59468 | G37: 249.58225 | H37: 256.79596 | I37: 263.61707 | J37: 268.50519 | K37: 274.19601 | L37: 280.12811 | M37: 285.04456 | N37: 289.97006 | O37: 294.88544 | P37: 299.7988 | Q37: 304.83197 | R37: 309.69406 | S37: 314.40494 | T37: 319.82986 | U37: 324.73733 | V37: 328.49112 | W37: 332.13684 | X37: 337.70959 | Y37: 342.51279 | Z37: 346.60788 | AA37: 349.68332 | AB37: 352.98615 | AC37: 357.61475 | AD37: 360.5083 | AE37: 361.56473 | AF37: 366.79239 | AG37: 375.53976 | AH37: 0.016439
A38: ISM000:fa_Resins | C38: Resin, Synthetic Rubber, and Fibers | D38: 130.70677 | E38: 138.19717 | F38: 138.97093 | G38: 140.1199 | H38: 145.12517 | I38: 150.24118 | J38: 152.97287 | K38: 154.59093 | L38: 155.30875 | M38: 156.46652 | N38: 159.93933 | O38: 164.80335 | P38: 168.23662 | Q38: 170.061 | R38: 171.89952 | S38: 174.29597 | T38: 177.36815 | U38: 179.80417 | V38: 182.01358 | W38: 183.9801 | X38: 186.17042 | Y38: 188.70128 | Z38: 192.6918 | AA38: 196.09195 | AB38: 199.65683 | AC38: 203.32124 | AD38: 205.16029 | AE38: 206.08197 | AF38: 208.61031 | AG38: 213.86385 | AH38: 0.017124
A39: ISM000:fa_AgriculturalC | C39: Agricultural Chemicals | D39: 44.50359 | E39: 43.554401 | F39: 44.968929 | G39: 45.710007 | H39: 46.398998 | I39: 47.34734 | J39: 48.08707 | K39: 48.844593 | L39: 49.724613 | M39: 50.431416 | N39: 51.095985 | O39: 51.843143 | P39: 52.544132 | Q39: 53.207386 | R39: 53.800083 | S39: 54.294247 | T39: 54.83427 | U39: 55.288292 | V39: 55.579697 | W39: 55.89402 | X39: 56.471321 | Y39: 56.994904 | Z39: 57.430779 | AA39: 57.749466 | AB39: 58.011463 | AC39: 58.398117 | AD39: 58.611946 | AE39: 58.684383 | AF39: 59.055882 | AG39: 59.71566 | AH39: 0.01019
A40: ISM000:fa_OtherChemical | C40: Other Chemical Products | D40: 517.61487 | E40: 489.07626 | F40: 487.01556 | G40: 490.22324 | H40: 495.62119 | I40: 502.15506 | J40: 509.35211 | K40: 516.58173 | L40: 525.35052 | M40: 534.61591 | N40: 544.00745 | O40: 554.47351 | P40: 565.84094 | Q40: 577.74683 | R40: 589.97461 | S40: 602.38049 | T40: 615.40735 | U40: 629.58557 | V40: 644.16736 | W40: 658.2262 | X40: 673.22321 | Y40: 690.68274 | Z40: 708.58887 | AA40: 726.67371 | AB40: 744.61713 | AC40: 763.62335 | AD40: 782.84473 | AE40: 799.08307 | AF40: 813.00738 | AG40: 827.36322 | AH40: 0.016304
A41: ISM000:fa_PetroleumandC | B41: ISIC 19 | C41: Petroleum and Coal Products | D41: 789.06366 | E41: 885.56708 | F41: 913.43842 | G41: 917.53394 | H41: 921.92328 | I41: 923.36243 | J41: 922.02448 | K41: 921.90979 | L41: 921.89789 | M41: 922.12647 | N41: 923.64569 | O41: 924.29199 | P41: 925.89447 | Q41: 927.1391 | R41: 927.53461 | S41: 929.30969 | T41: 932.10986 | U41: 934.19849 | V41: 937.57336 | W41: 940.02002 | X41: 943.57227 | Y41: 947.23639 | Z41: 950.93243 | AA41: 955.54675 | AB41: 960.36102 | AC41: 966.04889 | AD41: 970.07312 | AE41: 972.34815 | AF41: 978.03412 | AG41: 988.23206 | AH41: 0.007791
A42: ISM000:fa_PetroleumRefi | C42: Petroleum Refineries | D42: 746.87048 | E42: 840.716 | F42: 864.66748 | G42: 866.2876 | H42: 869.92847 | I42: 871.23602 | J42: 869.83392 | K42: 869.69403 | L42: 869.6897 | M42: 869.81574 | N42: 871.2442 | O42: 871.91681 | P42: 873.39703 | Q42: 874.50696 | R42: 874.8855 | S42: 876.52685 | T42: 879.08588 | U42: 881.02588 | V42: 884.16254 | W42: 886.38361 | X42: 889.70978 | Y42: 893.1283 | Z42: 896.59821 | AA42: 900.92377 | AB42: 905.37665 | AC42: 910.61603 | AD42: 914.26215 | AE42: 916.26386 | AF42: 921.54474 | AG42: 931.10449 | AH42: 0.007632
A43: ISM000:fa_OtherPetroleu | C43: Other Petroleum and Coal Products | D43: 42.193161 | E43: 44.851059 | F43: 48.770931 | G43: 51.246349 | H43: 51.994808 | I43: 52.126404 | J43: 52.190529 | K43: 52.215771 | L43: 52.208183 | M43: 52.310753 | N43: 52.401512 | O43: 52.375168 | P43: 52.497421 | Q43: 52.632153 | R43: 52.649117 | S43: 52.782864 | T43: 53.023979 | U43: 53.172588 | V43: 53.410816 | W43: 53.636421 | X43: 53.862469 | Y43: 54.108101 | Z43: 54.334206 | AA43: 54.622997 | AB43: 54.984352 | AC43: 55.432854 | AD43: 55.810959 | AE43: 56.084301 | AF43: 56.489395 | AG43: 57.127537 | AH43: 0.010504
A44: ISM000:fa_RubberandMisc | B44: ISIC 22 | C44: Plastics and Rubber Products | D44: 245.4554 | E44: 250.38988 | F44: 253.82719 | G44: 258.67355 | H44: 262.79642 | I44: 267.25034 | J44: 271.50519 | K44: 275.65808 | L44: 280.75714 | M44: 285.67105 | N44: 290.53449 | O44: 295.40921 | P44: 299.62936 | Q44: 303.82901 | R44: 308.64661 | S44: 313.87936 | T44: 319.60446 | U44: 325.08096 | V44: 330.44379 | W44: 335.93646 | X44: 342.10989 | Y44: 348.81363 | Z44: 356.26114 | AA44: 363.07468 | AB44: 369.68866 | AC44: 376.73611 | AD44: 383.33817 | AE44: 389.45664 | AF44: 396.51163 | AG44: 405.43817 | AH44: 0.017456
A45: ISM000:fa_Stone,Clay,an | C45: Stone, Clay, and Glass Products | D45: 113.22774 | E45: 112.25857 | F45: 112.01128 | G45: 114.50412 | H45: 116.95679 | I45: 118.96541 | J45: 120.4554 | K45: 121.80376 | L45: 123.50484 | M45: 125.09827 | N45: 126.44482 | O45: 127.82156 | P45: 129.22235 | Q45: 130.26517 | R45: 131.77515 | S45: 133.10329 | T45: 134.71251 | U45: 136.32274 | V45: 137.8826 | W45: 139.44327 | X45: 141.01437 | Y45: 142.47461 | Z45: 143.61763 | AA45: 145.37103 | AB45: 147.54275 | AC45: 149.8548 | AD45: 151.79114 | AE45: 153.38199 | AF45: 155.18726 | AG45: 157.14366 | AH45: 0.011366
A46: ISM000:fa_GlassandGlass | B46: ISIC 231 | C46: Glass and Glass Products | D46: 23.465088 | E46: 23.200544 | F46: 23.227995 | G46: 23.386314 | H46: 23.718697 | I46: 24.0749 | J46: 24.301044 | K46: 24.549915 | L46: 24.870602 | M46: 25.157772 | N46: 25.406694 | O46: 25.60154 | P46: 25.878025 | Q46: 26.171192 | R46: 26.51379 | S46: 26.748489 | T46: 27.019997 | U46: 27.321247 | V46: 27.759516 | W46: 28.109409 | X46: 28.39892 | Y46: 28.792789 | Z46: 29.014917 | AA46: 29.375418 | AB46: 29.81254 | AC46: 30.297878 | AD46: 30.63592 | AE46: 30.8899 | AF46: 31.296207 | AG46: 31.668301 | AH46: 0.010392
A47: ISM000:fa_CementandHydr | B47: ISIC 239 | C47: Cement and Lime | D47: 13.972248 | E47: 14.872414 | F47: 15.123309 | G47: 15.522886 | H47: 15.865885 | I47: 16.07589 | J47: 16.23354 | K47: 16.374475 | L47: 16.582703 | M47: 16.843021 | N47: 17.109344 | O47: 17.316126 | P47: 17.503998 | Q47: 17.716549 | R47: 17.947384 | S47: 18.121517 | T47: 18.288839 | U47: 18.46661 | V47: 18.623085 | W47: 18.825594 | X47: 19.046333 | Y47: 19.232735 | Z47: 19.416977 | AA47: 19.647312 | AB47: 19.898357 | AC47: 20.153475 | AD47: 20.391369 | AE47: 20.613503 | AF47: 20.842199 | AG47: 21.106789 | AH47: 0.014327
A48: ISM000:fa_OtherStone,Cl | B48: ISIC 239 | C48: Other Nonmetallic Mineral Products | D48: 75.790398 | E48: 74.185608 | F48: 73.659981 | G48: 75.594925 | H48: 77.372215 | I48: 78.814621 | J48: 79.920815 | K48: 80.879372 | L48: 82.051529 | M48: 83.097481 | N48: 83.92878 | O48: 84.9039 | P48: 85.840332 | Q48: 86.377434 | R48: 87.313972 | S48: 88.233276 | T48: 89.403671 | U48: 90.534882 | V48: 91.5 | W48: 92.508263 | X48: 93.56913 | Y48: 94.449089 | Z48: 95.185738 | AA48: 96.348305 | AB48: 97.831848 | AC48: 99.403442 | AD48: 100.76385 | AE48: 101.87858 | AF48: 103.04885 | AG48: 104.36858 | AH48: 0.011094
A49: ISM000:ga_PrimaryMetals | C49: Primary Metals Industry | D49: 240.15085 | E49: 247.23758 | F49: 251.7034 | G49: 255.20181 | H49: 259.51004 | I49: 263.20581 | J49: 265.11868 | K49: 266.58917 | L49: 269.7807 | M49: 271.57281 | N49: 272.75879 | O49: 274.46805 | P49: 275.49896 | Q49: 277.36249 | R49: 279.20325 | S49: 281.25568 | T49: 284.17114 | U49: 286.97736 | V49: 288.83463 | W49: 290.27048 | X49: 292.96454 | Y49: 295.85406 | Z49: 298.06482 | AA49: 299.50128 | AB49: 300.8439 | AC49: 302.61856 | AD49: 303.69708 | AE49: 303.04907 | AF49: 304.28308 | AG49: 307.40369 | AH49: 0.00855
A50: ISM000:ga_BlastFurnacea | B50: ISIC 241 | C50: Iron and Steel Mills and Products | D50: 125.35865 | E50: 126.45898 | F50: 127.35047 | G50: 127.97513 | H50: 129.97865 | I50: 131.0598 | J50: 130.98171 | K50: 130.4669 | L50: 131.59625 | M50: 131.73018 | N50: 131.49188 | O50: 132.01884 | P50: 131.81183 | Q50: 132.05624 | R50: 132.3051 | S50: 132.81302 | T50: 134.02913 | U50: 134.94963 | V50: 134.71558 | W50: 134.1055 | X50: 134.62758 | Y50: 135.2569 | Z50: 135.38115 | AA50: 134.84979 | AB50: 133.88135 | AC50: 133.40041 | AD50: 132.45042 | AE50: 130.17419 | AF50: 129.52721 | AG50: 130.4146 | AH50: 0.001364
A51: ISM000:ga_Aluminum | B51: ISIC 242 | C51: Alumina and Aluminum Products | D51: 37.984837 | E51: 40.926949 | F51: 42.201752 | G51: 43.116482 | H51: 44.108051 | I51: 45.071152 | J51: 45.787861 | K51: 46.505669 | L51: 47.184174 | M51: 47.634853 | N51: 48.024658 | O51: 48.247791 | P51: 48.53614 | Q51: 48.946041 | R51: 49.382027 | S51: 49.726952 | T51: 50.171986 | U51: 50.741581 | V51: 51.273304 | W51: 51.564491 | X51: 52.098797 | Y51: 52.80323 | Z51: 53.299732 | AA51: 53.572742 | AB51: 53.934681 | AC51: 54.287071 | AD51: 54.524368 | AE51: 54.507343 | AF51: 54.671402 | AG51: 55.205109 | AH51: 0.012975
A52: ISM000:ga_OtherPrimaryM | B52: ISIC 242 | C52: Other Primary Metal Products | D52: 76.807365 | E52: 79.851654 | F52: 82.151192 | G52: 84.110191 | H52: 85.423347 | I52: 87.074867 | J52: 88.349121 | K52: 89.616615 | L52: 91.000275 | M52: 92.207771 | N52: 93.242256 | O52: 94.201424 | P52: 95.150993 | Q52: 96.360191 | R52: 97.516129 | S52: 98.715698 | T52: 99.970024 | U52: 101.28615 | V52: 102.84575 | W52: 104.6005 | X52: 106.23815 | Y52: 107.79395 | Z52: 109.38393 | AA52: 111.07875 | AB52: 113.02788 | AC52: 114.9311 | AD52: 116.72227 | AE52: 118.36755 | AF52: 120.08447 | AG52: 121.784 | AH52: 0.016022
A53: ISM000:ga_FabricatedMet | B53: ISIC 25 | C53: Fabricated Metal Products | D53: 356.37753 | E53: 361.73721 | F53: 368.31796 | G53: 377.41559 | H53: 384.4877 | I53: 391.05005 | J53: 395.83722 | K53: 399.17871 | L53: 405.14499 | M53: 410.55728 | N53: 415.55347 | O53: 422.05597 | P53: 427.53989 | Q53: 433.46799 | R53: 439.71466 | S53: 446.85046 | T53: 455.38812 | U53: 463.0824 | V53: 469.48071 | W53: 474.8522 | X53: 481.52799 | Y53: 489.66797 | Z53: 498.85406 | AA53: 506.02576 | AB53: 512.24829 | AC53: 519.11255 | AD53: 524.125 | AE53: 526.92883 | AF53: 531.45203 | AG53: 541.60761 | AH53: 0.014537
A54: ISM000:ga_IndustrialMac | B54: ISIC 28 | C54: Machinery | D54: 388.79587 | E54: 403.9595 | F54: 407.25006 | G54: 416.22476 | H54: 424.04004 | I54: 431.49121 | J54: 439.30762 | K54: 445.39505 | L54: 455.42624 | M54: 464.19043 | N54: 472.15262 | O54: 481.50366 | P54: 489.82077 | Q54: 499.0278 | R54: 508.35712 | S54: 518.5083 | T54: 529.11951 | U54: 538.39868 | V54: 547.00848 | W54: 555.5462 | X54: 565.0968 | Y54: 575.75165 | Z54: 586.21399 | AA54: 595.4577 | AB54: 604.20325 | AC54: 614.74353 | AD54: 623.77667 | AE54: 632.38226 | AF54: 642.15369 | AG54: 654.91443 | AH54: 0.018144
A55: ISM000:ga_Electronicand | B55: ISIC 26 | C55: Computers and Electronics | D55: 481.07022 | E55: 503.04681 | F55: 519.5163 | G55: 533.74115 | H55: 546.41052 | I55: 559.15704 | J55: 572.18597 | K55: 587.9906 | L55: 603.55963 | M55: 618.55658 | N55: 634.55084 | O55: 649.11218 | P55: 663.10205 | Q55: 678.172 | R55: 693.63403 | S55: 709.75494 | T55: 727.07642 | U55: 745.45673 | V55: 764.2085 | W55: 783.63135 | X55: 803.89862 | Y55: 824.22943 | Z55: 845.34021 | AA55: 866.99811 | AB55: 888.50714 | AC55: 909.73651 | AD55: 930.98944 | AE55: 952.46637 | AF55: 975.00781 | AG55: 997.70856 | AH55: 0.025472
A56: ISM000:ga_Transportatio | B56: ISIC 29, ISIC 30 | C56: Transportation Equipment | D56: 1097.1733 | E56: 1191.6818 | F56: 1268.1002 | G56: 1261.6687 | H56: 1263.2262 | I56: 1267.3218 | J56: 1269.2875 | K56: 1281.6014 | L56: 1289.1147 | M56: 1298.8573 | N56: 1312.8805 | O56: 1330.8905 | P56: 1351.1855 | Q56: 1370.4764 | R56: 1391.126 | S56: 1413.097 | T56: 1435.7362 | U56: 1458.1305 | V56: 1479.6605 | W56: 1500.6047 | X56: 1524.334 | Y56: 1550.9268 | Z56: 1577.6047 | AA56: 1602.4122 | AB56: 1626.9358 | AC56: 1654.3722 | AD56: 1682.0417 | AE56: 1707.6345 | AF56: 1735.3103 | AG56: 1766.866 | AH56: 0.016566
A57: ISM000:ga_Instrumentsan | B57: ISIC 27 | C57: Electrical Equipment | D57: 133.00749 | E57: 138.84053 | F57: 143.80725 | G57: 147.96112 | H57: 150.88045 | I57: 153.85139 | J57: 156.61556 | K57: 159.55125 | L57: 162.86035 | M57: 166.2609 | N57: 168.4146 | O57: 171.77298 | P57: 176.09622 | Q57: 180.64563 | R57: 185.2179 | S57: 189.90358 | T57: 194.76504 | U57: 199.85715 | V57: 205.00952 | W57: 210.1633 | X57: 215.561 | Y57: 221.18793 | Z57: 226.98648 | AA57: 232.95187 | AB57: 239.31821 | AC57: 245.74962 | AD57: 252.27295 | AE57: 258.99042 | AF57: 265.57895 | AG57: 272.47015 | AH57: 0.025037
A58: ISM000:ga_Miscellaneous | B58: ISIC 31T33 | C58: Miscellaneous Manufacturing | D58: 160.34868 | E58: 160.88506 | F58: 163.25385 | G58: 168.39667 | H58: 173.6888 | I58: 178.72455 | J58: 184.49303 | K58: 190.1971 | L58: 196.61568 | M58: 202.95172 | N58: 208.66576 | O58: 214.58353 | P58: 220.77835 | Q58: 227.4921 | R58: 233.506 | S58: 239.46703 | T58: 246.26289 | U58: 253.30376 | V58: 260.98227 | W58: 268.70087 | X58: 276.09915 | Y58: 284.92816 | Z58: 293.35852 | AA58: 302.1358 | AB58: 310.90359 | AC58: 320.33691 | AD58: 328.98419 | AE58: 337.27731 | AF58: 346.36282 | AG58: 354.76004 | AH58: 0.027761
A60: ISM000:ha_TotalIndustri | C60: Total Industrial Value of Shipments | D60: 9275.0264 | E60: 9520.2275 | F60: 9691.8926 | G60: 9798.2002 | H60: 9915.46 | I60: 10020.619 | J60: 10087.813 | K60: 10177.658 | L60: 10284.823 | M60: 10392.021 | N60: 10503.195 | O60: 10626.38 | P60: 10755.857 | Q60: 10878.385 | R60: 11003.75 | S60: 11136.871 | T60: 11285.188 | U60: 11437.353 | V60: 11587.209 | W60: 11735.885 | X60: 11896.542 | Y60: 12065.203 | Z60: 12236.771 | AA60: 12405.542 | AB60: 12573.556 | AC60: 12752.085 | AD60: 12911.328 | AE60: 13055.079 | AF60: 13225.791 | AG60: 13435.021 | AH60: 0.012859
C62: Note: Totals may not equal sum of components due to independent rounding.
C63: Sources: 2021: IHS Markit, Macroeconomic model, September 2021.
C64: Projections: U.S. Energy Information Administration, AEO2022 National Energy Modeling System run ref2022.d011222a.

Sheet Data from BVAbIC
A1: Unit: USD | B1: ISIC 01T03 | C1: ISIC 05 | D1: ISIC 06 | E1: ISIC 07T08 | F1: ISIC 09 | G1: ISIC 10T12 | H1: ISIC 13T15 | I1: ISIC 16 | J1: ISIC 17T18 | K1: ISIC 19 | L1: ISIC 20 | M1: ISIC 21 | N1: ISIC 22 | O1: ISIC 231 | P1: ISIC 239 | Q1: ISIC 241 | R1: ISIC 242 | S1: ISIC 25 | T1: ISIC 26 | U1: ISIC 27 | V1: ISIC 28 | W1: ISIC 29 | X1: ISIC 30 | Y1: ISIC 31T33 | Z1: ISIC 351 | AA1: ISIC 352T353 | AB1: ISIC 36T39 | AC1: ISIC 41T43 | AD1: ISIC 45T47 | AE1: ISIC 49T53 | AF1: ISIC 55T56 | AG1: ISIC 58T60 | AH1: ISIC 61 | AI1: ISIC 62T63 | AJ1: ISIC 64T66 | AK1: ISIC 68 | AL1: ISIC 69T82 | AM1: ISIC 84 | AN1: ISIC 85 | AO1: ISIC 86T88 | AP1: ISIC 90T96 | AQ1: ISIC 97T98
A2: Value Added | B2: 2.7925734e+10 | C2: 1311397.9 | D2: 1.8090113e+08 | E2: 1.262802e+09 | F2: 11088883 | G2: 1.7735383e+10 | H2: 1.1503696e+10 | I2: 1.6322836e+09 | J2: 9.1721921e+09 | K2: 1.0038544e+10 | L2: 2.7808613e+10 | M2: 6.956367e+09 | N2: 1.9570194e+10 | O2: 3.8686567e+09 | P2: 1.1738714e+10 | Q2: 1.457761e+10 | R2: 7.1714886e+09 | S2: 2.5821042e+10 | T2: 9.2863277e+10 | U2: 2.1076951e+10 | V2: 3.2293312e+10 | W2: 2.8866581e+10 | X2: 8.1419017e+09 | Y2: 8.2692021e+09 | Z2: 1.7044384e+10 | AA2: 1.7281799e+08 | AB2: 8.8437837e+09 | AC2: 7.7112273e+10 | AD2: 1.4799153e+11 | AE2: 4.8084966e+10 | AF2: 3.2694198e+10 | AG2: 2.118234e+10 | AH2: 1.312977e+10 | AI2: 2.5177443e+10 | AJ2: 7.5716404e+10 | AK2: 1.0400778e+11 | AL2: 9.5146132e+10 | AM2: 9.3032982e+10 | AN2: 6.6938444e+10 | AO2: 6.5010309e+10 | AP2: 3.0090834e+10 | AQ2: 1.6305094e+09

Sheet GDP Forecast
B1: Value (2012 USD)
A2: 2021 | B2: 1.6434102e+12
A3: 2022 | B3: 1.6863472e+12
A4: 2023 | B4: 1.7092264e+12
A5: 2024 | B5: 1.7477784e+12
A6: 2025 | B6: 1.7850602e+12
A7: 2026 | B7: 1.8268614e+12
A8: 2027 | B8: 1.8657003e+12
A9: 2028 | B9: 1.9006139e+12
A10: 2029 | B10: 1.932921e+12
A11: 2030 | B11: 1.9640656e+12
A12: 2031 | B12: 1.9947733e+12
A13: 2032 | B13: 2.0251482e+12
... A31: 2050 | B31: 2.4298437e+12

Sheet Rescale to Fit GDP Proj
A1: Now that we have growth rates by ISIC code, we rescale all growth rates together such that BAU Value Added
A2: (summed across ISIC codes) reflects the BAU GDP projection in the final year of the model run.
C4: 2021 | D4: 2022 | E4: 2023 | F4: 2024 | G4: 2025 | H4: 2026 | I4: 2027 | J4: 2028 | K4: 2029 | L4: 2030 | M4: 2031 | N4: 2032 | O4: 2033 | P4: 2034 | Q4: 2035 | R4: 2036 | S4: 2037 | T4: 2038 | U4: 2039 | V4: 2040 | W4: 2041 | X4: 2042 | Y4: 2043 | Z4: 2044 | AA4: 2045 | AB4: 2046 | AC4: 2047 | AD4: 2048 | AE4: 2049 | AF4: 2050
A5: AEO | B5: ISIC 01T03 | C5: {=TRANSPOSE('Data from BVAbIC'!B2:AQ2)} -> 2.7925734e+10 | D5: =C5*(1+'Growth Rates'!C51) -> 2.792573e+10 | E5: =D5*(1+'Growth Rates'!D51) -> 2.7887999e+10 | F5: =E5*(1+'Growth Rates'!E51) -> 2.8142692e+10 | G5: =F5*(1+'Growth Rates'!F51) -> 2.85197e+10 | H5: =G5*(1+'Growth Rates'!G51) -> 2.895571e+10 | I5: =H5*(1+'Growth Rates'!H51) -> 2.9343989e+10 | J5: =I5*(1+'Growth Rates'!I51) -> 2.9688046e+10 | K5: =J5*(1+'Growth Rates'!J51) -> 2.9989259e+10 | ... AF5: =AE5*(1+'Growth Rates'!AE51) -> 3.4892624e+10
A6: AEO | B6: ISIC 05 | C6: 1311397.9 | D6: =C6*(1+'Growth Rates'!C52) -> 1288412.2 | E6: =D6*(1+'Growth Rates'!D52) -> 1216308.7 | F6: =E6*(1+'Growth Rates'!E52) -> 1329628.1 | G6: =F6*(1+'Growth Rates'!F52) -> 1248268.1 | H6: =G6*(1+'Growth Rates'!G52) -> 1141866.6 | I6: =H6*(1+'Growth Rates'!H52) -> 1023675.3 | J6: =I6*(1+'Growth Rates'!I52) -> 918735.44 | K6: =J6*(1+'Growth Rates'!J52) -> 820080.26 | ... AF6: =AE6*(1+'Growth Rates'!AE52) -> 656093.44
A7: AEO | B7: ISIC 06 | C7: 1.8090113e+08 | D7: =C7*(1+'Growth Rates'!C53) -> 1.8146836e+08 | E7: =D7*(1+'Growth Rates'!D53) -> 1.7639943e+08 | F7: =E7*(1+'Growth Rates'!E53) -> 1.7635086e+08 | G7: =F7*(1+'Growth Rates'!F53) -> 1.7769881e+08 | H7: =G7*(1+'Growth Rates'!G53) -> 1.800762e+08 | I7: =H7*(1+'Growth Rates'!H53) -> 1.8037813e+08 | J7: =I7*(1+'Growth Rates'!I53) -> 1.818436e+08 | K7: =J7*(1+'Growth Rates'!J53) -> 1.8202861e+08 | ... AF7: =AE7*(1+'Growth Rates'!AE53) -> 1.9740062e+08
A8: AEO | B8: ISIC 07T08 | C8: 1.262802e+09 | D8: =C8*(1+'Growth Rates'!C54) -> 1.2624419e+09 | E8: =D8*(1+'Growth Rates'!D54) -> 1.2319171e+09 | F8: =E8*(1+'Growth Rates'!E54) -> 1.203693e+09 | G8: =F8*(1+'Growth Rates'!F54) -> 1.187693e+09 | H8: =G8*(1+'Growth Rates'!G54) -> 1.1704459e+09 | I8: =H8*(1+'Growth Rates'!H54) -> 1.1477718e+09 | J8: =I8*(1+'Growth Rates'!I54) -> 1.1335105e+09 | K8: =J8*(1+'Growth Rates'!J54) -> 1.1277849e+09 | ... AF8: =AE8*(1+'Growth Rates'!AE54) -> 1.2523606e+09
B9: ISIC 09 | C9: 11088883 | D9: =C9*(1+'Growth Rates'!C55) -> 11410461 | E9: =D9*(1+'Growth Rates'!D55) -> 11741364 | F9: =E9*(1+'Growth Rates'!E55) -> 12081864 | G9: =F9*(1+'Growth Rates'!F55) -> 12432238 | H9: =G9*(1+'Growth Rates'!G55) -> 12792773 | I9: =H9*(1+'Growth Rates'!H55) -> 13163763 | J9: =I9*(1+'Growth Rates'!I55) -> 13545512 | K9: =J9*(1+'Growth Rates'!J55) -> 13938332 | ... AF9: =AE9*(1+'Growth Rates'!AE55) -> 25405847
A10: AEO | B10: ISIC 10T12 | C10: 1.7735383e+10 | D10: =C10*(1+'Growth Rates'!C56) -> 1.7514344e+10 | E10: =D10*(1+'Growth Rates'!D56) -> 1.7787581e+10 | F10: =E10*(1+'Growth Rates'!E56) -> 1.7966092e+10 | G10: =F10*(1+'Growth Rates'!F56) -> 1.8131703e+10 | H10: =G10*(1+'Growth Rates'!G56) -> 1.8365579e+10 | I10: =H10*(1+'Growth Rates'!H56) -> 1.8625436e+10 | J10: =I10*(1+'Growth Rates'!I56) -> 1.8886995e+10 | K10: =J10*(1+'Growth Rates'!J56) -> 1.9113821e+10 | ... AF10: =AE10*(1+'Growth Rates'!AE56) -> 2.368496e+10
A11: AEO | B11: ISIC 13T15 | C11: 1.1503696e+10 | D11: =C11*(1+'Growth Rates'!C57) -> 1.1498047e+10 | E11: =D11*(1+'Growth Rates'!D57) -> 1.1322221e+10 | F11: =E11*(1+'Growth Rates'!E57) -> 1.1207168e+10 | G11: =F11*(1+'Growth Rates'!F57) -> 1.1212003e+10 | H11: =G11*(1+'Growth Rates'!G57) -> 1.1423475e+10 | I11: =H11*(1+'Growth Rates'!H57) -> 1.1684554e+10 | J11: =I11*(1+'Growth Rates'!I57) -> 1.1867228e+10 | K11: =J11*(1+'Growth Rates'!J57) -> 1.1945727e+10 | ... AF11: =AE11*(1+'Growth Rates'!AE57) -> 1.1120564e+10
A12: AEO | B12: ISIC 16 | C12: 1.6322836e+09 | D12: =C12*(1+'Growth Rates'!C58) -> 1.6217658e+09 | E12: =D12*(1+'Growth Rates'!D58) -> 1.4736652e+09 | F12: =E12*(1+'Growth Rates'!E58) -> 1.4343385e+09 | G12: =F12*(1+'Growth Rates'!F58) -> 1.4612095e+09 | H12: =G12*(1+'Growth Rates'!G58) -> 1.442515e+09 | I12: =H12*(1+'Growth Rates'!H58) -> 1.4360421e+09 | J12: =I12*(1+'Growth Rates'!I58) -> 1.4547153e+09 | K12: =J12*(1+'Growth Rates'!J58) -> 1.4793196e+09 | ... AF12: =AE12*(1+'Growth Rates'!AE58) -> 1.6491923e+09
A13: AEO | B13: ISIC 17T18 | C13: 9.1721921e+09 | D13: =C13*(1+'Growth Rates'!C59) -> 9.4930254e+09 | E13: =D13*(1+'Growth Rates'!D59) -> 9.2752326e+09 | F13: =E13*(1+'Growth Rates'!E59) -> 9.0690012e+09 | G13: =F13*(1+'Growth Rates'!F59) -> 9.0558951e+09 | H13: =G13*(1+'Growth Rates'!G59) -> 9.1024823e+09 | I13: =H13*(1+'Growth Rates'!H59) -> 9.158878e+09 | J13: =I13*(1+'Growth Rates'!I59) -> 9.2135606e+09 | K13: =J13*(1+'Growth Rates'!J59) -> 9.2621916e+09 | ... AF13: =AE13*(1+'Growth Rates'!AE59) -> 1.0393136e+10
A14: AEO | B14: ISIC 19 | C14: 1.0038544e+10 | D14: =C14*(1+'Growth Rates'!C60) -> 1.0395412e+10 | E14: =D14*(1+'Growth Rates'!D60) -> 1.1283414e+10 | F14: =E14*(1+'Growth Rates'!E60) -> 1.1250509e+10 | G14: =F14*(1+'Growth Rates'!F60) -> 1.120897e+10 | H14: =G14*(1+'Growth Rates'!G60) -> 1.1159136e+10 | I14: =H14*(1+'Growth Rates'!H60) -> 1.1128069e+10 | J14: =I14*(1+'Growth Rates'!I60) -> 1.1094492e+10 | K14: =J14*(1+'Growth Rates'!J60) -> 1.1044963e+10 | ... AF14: =AE14*(1+'Growth Rates'!AE60) -> 1.1137112e+10
A15: AEO | B15: ISIC 20 | C15: 2.7808613e+10 | D15: =C15*(1+'Growth Rates'!C61) -> 2.7438332e+10 | E15: =D15*(1+'Growth Rates'!D61) -> 2.6831772e+10 | F15: =E15*(1+'Growth Rates'!E61) -> 2.6513016e+10 | G15: =F15*(1+'Growth Rates'!F61) -> 2.6945287e+10 | H15: =G15*(1+'Growth Rates'!G61) -> 2.7567297e+10 | I15: =H15*(1+'Growth Rates'!H61) -> 2.820852e+10 | J15: =I15*(1+'Growth Rates'!I61) -> 2.8773081e+10 | K15: =J15*(1+'Growth Rates'!J61) -> 2.9220826e+10 | ... AF15: =AE15*(1+'Growth Rates'!AE61) -> 4.4011221e+10
B16: ISIC 21 | C16: 6.956367e+09 | D16: =C16*(1+'Growth Rates'!C62) -> 7.0815816e+09 | E16: =D16*(1+'Growth Rates'!D62) -> 7.2090501e+09 | F16: =E16*(1+'Growth Rates'!E62) -> 7.338813e+09 | G16: =F16*(1+'Growth Rates'!F62) -> 7.4709117e+09 | H16: =G16*(1+'Growth Rates'!G62) -> 7.6053881e+09 | I16: =H16*(1+'Growth Rates'!H62) -> 7.742285e+09 | J16: =I16*(1+'Growth Rates'!I62) -> 7.8816462e+09 | K16: =J16*(1+'Growth Rates'!J62) -> 8.0235158e+09 | ... AF16: =AE16*(1+'Growth Rates'!AE62) -> 1.1669925e+10
A17: AEO | B17: ISIC 22 | C17: 1.9570194e+10 | D17: =C17*(1+'Growth Rates'!C63) -> 2.0296794e+10 | E17: =D17*(1+'Growth Rates'!D63) -> 1.9884906e+10 | F17: =E17*(1+'Growth Rates'!E63) -> 1.9740881e+10 | G17: =F17*(1+'Growth Rates'!F63) -> 2.0028199e+10 | H17: =G17*(1+'Growth Rates'!G63) -> 2.0554065e+10 | I17: =H17*(1+'Growth Rates'!H63) -> 2.1017939e+10 | J17: =I17*(1+'Growth Rates'!I63) -> 2.1410701e+10 | K17: =J17*(1+'Growth Rates'!J63) -> 2.1778538e+10 | ... AF17: =AE17*(1+'Growth Rates'!AE63) -> 3.0910318e+10
A18: AEO | B18: ISIC 231 | C18: 3.8686567e+09 | D18: =C18*(1+'Growth Rates'!C64) -> 3.9296777e+09 | E18: =D18*(1+'Growth Rates'!D64) -> 3.6982727e+09 | F18: =E18*(1+'Growth Rates'!E64) -> 3.6353542e+09 | G18: =F18*(1+'Growth Rates'!F64) -> 3.6365944e+09 | H18: =G18*(1+'Growth Rates'!G64) -> 3.7393901e+09 | I18: =H18*(1+'Growth Rates'!H64) -> 3.7970181e+09 | J18: =I18*(1+'Growth Rates'!I64) -> 3.8417434e+09 | K18: =J18*(1+'Growth Rates'!J64) -> 3.8765239e+09 | ... AF18: =AE18*(1+'Growth Rates'!AE64) -> 4.7644339e+09
A19: AEO | B19: ISIC 239 | C19: 1.1738714e+10 | D19: =C19*(1+'Growth Rates'!C65) -> 1.3511002e+10 | E19: =D19*(1+'Growth Rates'!D65) -> 1.290819e+10 | F19: =E19*(1+'Growth Rates'!E65) -> 1.2748796e+10 | G19: =F19*(1+'Growth Rates'!F65) -> 1.295566e+10 | H19: =G19*(1+'Growth Rates'!G65) -> 1.3152653e+10 | I19: =H19*(1+'Growth Rates'!H65) -> 1.3280717e+10 | J19: =I19*(1+'Growth Rates'!I65) -> 1.3401765e+10 | K19: =J19*(1+'Growth Rates'!J65) -> 1.3562157e+10 | ... AF19: =AE19*(1+'Growth Rates'!AE65) -> 1.661424e+10
A20: AEO | B20: ISIC 241 | C20: 1.457761e+10 | D20: =C20*(1+'Growth Rates'!C66) -> 1.475164e+10 | E20: =D20*(1+'Growth Rates'!D66) -> 1.4511283e+10 | F20: =E20*(1+'Growth Rates'!E66) -> 1.4287224e+10 | G20: =F20*(1+'Growth Rates'!F66) -> 1.4611179e+10 | H20: =G20*(1+'Growth Rates'!G66) -> 1.5308975e+10 | I20: =H20*(1+'Growth Rates'!H66) -> 1.5670882e+10 | J20: =I20*(1+'Growth Rates'!I66) -> 1.5756932e+10 | K20: =J20*(1+'Growth Rates'!J66) -> 1.5834308e+10 | ... AF20: =AE20*(1+'Growth Rates'!AE66) -> 1.6869308e+10
A21: AEO | B21: ISIC 242 | C21: 7.1714886e+09 | D21: =C21*(1+'Growth Rates'!C67) -> 7.4555969e+09 | E21: =D21*(1+'Growth Rates'!D67) -> 7.3643204e+09 | F21: =E21*(1+'Growth Rates'!E67) -> 7.4088257e+09 | G21: =F21*(1+'Growth Rates'!F67) -> 7.6243529e+09 | H21: =G21*(1+'Growth Rates'!G67) -> 7.8756298e+09 | I21: =H21*(1+'Growth Rates'!H67) -> 8.0436988e+09 | J21: =I21*(1+'Growth Rates'!I67) -> 8.1602956e+09 | K21: =J21*(1+'Growth Rates'!J67) -> 8.2238434e+09 | ... AF21: =AE21*(1+'Growth Rates'!AE67) -> 1.016032e+10
A22: AEO | B22: ISIC 25 | C22: 2.5821042e+10 | D22: =C22*(1+'Growth Rates'!C68) -> 2.616209e+10 | E22: =D22*(1+'Growth Rates'!D68) -> 2.5655627e+10 | F22: =E22*(1+'Growth Rates'!E68) -> 2.5466543e+10 | G22: =F22*(1+'Growth Rates'!F68) -> 2.5934977e+10 | H22: =G22*(1+'Growth Rates'!G68) -> 2.6790446e+10 | I22: =H22*(1+'Growth Rates'!H68) -> 2.7512714e+10 | J22: =I22*(1+'Growth Rates'!I68) -> 2.7935389e+10 | K22: =J22*(1+'Growth Rates'!J68) -> 2.8258932e+10 | ... AF22: =AE22*(1+'Growth Rates'!AE68) -> 3.7307999e+10
A23: AEO | B23: ISIC 26 | C23: 9.2863277e+10 | D23: =C23*(1+'Growth Rates'!C69) -> 9.7770359e+10 | E23: =D23*(1+'Growth Rates'!D69) -> 9.9688707e+10 | F23: =E23*(1+'Growth Rates'!E69) -> 1.0286127e+11 | G23: =F23*(1+'Growth Rates'!F69) -> 1.0689709e+11 | H23: =G23*(1+'Growth Rates'!G69) -> 1.1143043e+11 | I23: =H23*(1+'Growth Rates'!H69) -> 1.1531205e+11 | J23: =I23*(1+'Growth Rates'!I69) -> 1.1865428e+11 | K23: =J23*(1+'Growth Rates'!J69) -> 1.21172e+11 | ... AF23: =AE23*(1+'Growth Rates'!AE69) -> 1.9189913e+11
A24: AEO | B24: ISIC 27 | C24: 2.1076951e+10 | D24: =C24*(1+'Growth Rates'!C70) -> 2.1664954e+10 | E24: =D24*(1+'Growth Rates'!D70) -> 2.1655768e+10 | F24: =E24*(1+'Growth Rates'!E70) -> 2.1896819e+10 | G24: =F24*(1+'Growth Rates'!F70) -> 2.2423057e+10 | H24: =G24*(1+'Growth Rates'!G70) -> 2.2957076e+10 | I24: =H24*(1+'Growth Rates'!H70) -> 2.3448605e+10 | J24: =I24*(1+'Growth Rates'!I70) -> 2.388504e+10 | K24: =J24*(1+'Growth Rates'!J70) -> 2.4252175e+10 | ... AF24: =AE24*(1+'Growth Rates'!AE70) -> 4.0732501e+10
A25: AEO | B25: ISIC 28 | C25: 3.2293312e+10 | D25: =C25*(1+'Growth Rates'!C71) -> 3.3191698e+10 | E25: =D25*(1+'Growth Rates'!D71) -> 3.2689248e+10 | F25: =E25*(1+'Growth Rates'!E71) -> 3.2709374e+10 | G25: =F25*(1+'Growth Rates'!F71) -> 3.3106912e+10 | H25: =G25*(1+'Growth Rates'!G71) -> 3.4320529e+10 | I25: =H25*(1+'Growth Rates'!H71) -> 3.5388649e+10 | J25: =I25*(1+'Growth Rates'!I71) -> 3.5850436e+10 | K25: =J25*(1+'Growth Rates'!J71) -> 3.625386e+10 | ... AF25: =AE25*(1+'Growth Rates'!AE71) -> 4.8647632e+10
A26: AEO | B26: ISIC 29 | C26: 2.8866581e+10 | D26: =C26*(1+'Growth Rates'!C72) -> 2.9683218e+10 | E26: =D26*(1+'Growth Rates'!D72) -> 3.0606581e+10 | F26: =E26*(1+'Growth Rates'!E72) -> 3.0990529e+10 | G26: =F26*(1+'Growth Rates'!F72) -> 3.0899899e+10 | H26: =G26*(1+'Growth Rates'!G72) -> 3.1060758e+10 | I26: =H26*(1+'Growth Rates'!H72) -> 3.1637702e+10 | J26: =I26*(1+'Growth Rates'!I72) -> 3.2069947e+10 | K26: =J26*(1+'Growth Rates'!J72) -> 3.2278554e+10 | ... AF26: =AE26*(1+'Growth Rates'!AE72) -> 4.4228476e+10
A27: AEO | B27: ISIC 30 | C27: 8.1419017e+09 | D27: =C27*(1+'Growth Rates'!C73) -> 8.3722364e+09 | E27: =D27*(1+'Growth Rates'!D73) -> 8.6326736e+09 | F27: =E27*(1+'Growth Rates'!E73) -> 8.7409672e+09 | G27: =F27*(1+'Growth Rates'!F73) -> 8.7154048e+09 | H27: =G27*(1+'Growth Rates'!G73) -> 8.7607756e+09 | I27: =H27*(1+'Growth Rates'!H73) -> 8.9235042e+09 | J27: =I27*(1+'Growth Rates'!I73) -> 9.0454201e+09 | K27: =J27*(1+'Growth Rates'!J73) -> 9.1042584e+09 | ... AF27: =AE27*(1+'Growth Rates'!AE73) -> 1.2474768e+10
A28: AEO | B28: ISIC 31T33 | C28: 8.2692021e+09 | D28: =C28*(1+'Growth Rates'!C74) -> 8.2526934e+09 | E28: =D28*(1+'Growth Rates'!D74) -> 8.1363785e+09 | F28: =E28*(1+'Growth Rates'!E74) -> 8.1533144e+09 | G28: =F28*(1+'Growth Rates'!F74) -> 8.1987041e+09 | H28: =G28*(1+'Growth Rates'!G74) -> 8.4022319e+09 | I28: =H28*(1+'Growth Rates'!H74) -> 8.6276852e+09 | J28: =I28*(1+'Growth Rates'!I74) -> 8.7242865e+09 | K28: =J28*(1+'Growth Rates'!J74) -> 8.8255701e+09 | ... AF28: =AE28*(1+'Growth Rates'!AE74) -> 1.1931092e+10
B29: ISIC 351 | C29: 1.7044384e+10 | D29: =C29*(1+'Growth Rates'!C75) -> 1.7334138e+10 | E29: =D29*(1+'Growth Rates'!D75) -> 1.7628819e+10 | F29: =E29*(1+'Growth Rates'!E75) -> 1.7928509e+10 | G29: =F29*(1+'Growth Rates'!F75) -> 1.8233293e+10 | H29: =G29*(1+'Growth Rates'!G75) -> 1.8543259e+10 | I29: =H29*(1+'Growth Rates'!H75) -> 1.8858495e+10 | J29: =I29*(1+'Growth Rates'!I75) -> 1.9179089e+10 | K29: =J29*(1+'Growth Rates'!J75) -> 1.9505134e+10 | ... AF29: =AE29*(1+'Growth Rates'!AE75) -> 2.7790025e+10
B30: ISIC 352T353 | C30: 1.7281799e+08 | D30: =C30*(1+'Growth Rates'!C76) -> 1.7420053e+08 | E30: =D30*(1+'Growth Rates'!D76) -> 1.7559413e+08 | F30: =E30*(1+'Growth Rates'!E76) -> 1.7699889e+08 | G30: =F30*(1+'Growth Rates'!F76) -> 1.7841488e+08 | H30: =G30*(1+'Growth Rates'!G76) -> 1.798422e+08 | I30: =H30*(1+'Growth Rates'!H76) -> 1.8128093e+08 | J30: =I30*(1+'Growth Rates'!I76) -> 1.8273118e+08 | K30: =J30*(1+'Growth Rates'!J76) -> 1.8419303e+08 | ... AF30: =AE30*(1+'Growth Rates'!AE76) -> 2.1774308e+08
B31: ISIC 36T39 | C31: 8.8437837e+09 | D31: =C31*(1+'Growth Rates'!C77) -> 8.9886506e+09 | E31: =D31*(1+'Growth Rates'!D77) -> 9.1358905e+09 | F31: =E31*(1+'Growth Rates'!E77) -> 9.2855423e+09 | G31: =F31*(1+'Growth Rates'!F77) -> 9.4376454e+09 | H31: =G31*(1+'Growth Rates'!G77) -> 9.5922402e+09 | I31: =H31*(1+'Growth Rates'!H77) -> 9.7493672e+09 | J31: =I31*(1+'Growth Rates'!I77) -> 9.9090682e+09 | K31: =J31*(1+'Growth Rates'!J77) -> 1.0071385e+10 | ... AF31: =AE31*(1+'Growth Rates'!AE77) -> 1.4166851e+10
A32: AEO | B32: ISIC 41T43 | C32: 7.7112273e+10 | D32: =C32*(1+'Growth Rates'!C78) -> 7.5213346e+10 | E32: =D32*(1+'Growth Rates'!D78) -> 7.3571546e+10 | F32: =E32*(1+'Growth Rates'!E78) -> 7.3027199e+10 | G32: =F32*(1+'Growth Rates'!F78) -> 7.418926e+10 | H32: =G32*(1+'Growth Rates'!G78) -> 7.4921902e+10 | I32: =H32*(1+'Growth Rates'!H78) -> 7.4989778e+10 | J32: =I32*(1+'Growth Rates'!I78) -> 7.5562304e+10 | K32: =J32*(1+'Growth Rates'!J78) -> 7.7346061e+10 | ... AF32: =AE32*(1+'Growth Rates'!AE78) -> 9.462768e+10
B33: ISIC 45T47 | C33: 1.4799153e+11 | D33: =C33*(1+'Growth Rates'!C79) -> 1.5169446e+11 | E33: =D33*(1+'Growth Rates'!D79) -> 1.5549004e+11 | F33: =E33*(1+'Growth Rates'!E79) -> 1.5938058e+11 | G33: =F33*(1+'Growth Rates'!F79) -> 1.6336848e+11 | H33: =G33*(1+'Growth Rates'!G79) -> 1.6745616e+11 | I33: =H33*(1+'Growth Rates'!H79) -> 1.7164611e+11 | J33: =I33*(1+'Growth Rates'!I79) -> 1.7594091e+11 | K33: =J33*(1+'Growth Rates'!J79) -> 1.8034316e+11 | ... AF33: =AE33*(1+'Growth Rates'!AE79) -> 3.0303278e+11
B34: ISIC 49T53 | C34: 4.8084966e+10 | D34: =C34*(1+'Growth Rates'!C80) -> 4.8854325e+10 | E34: =D34*(1+'Growth Rates'!D80) -> 4.9635994e+10 | F34: =E34*(1+'Growth Rates'!E80) -> 5.043017e+10 | G34: =F34*(1+'Growth Rates'!F80) -> 5.1237053e+10 | H34: =G34*(1+'Growth Rates'!G80) -> 5.2056846e+10 | I34: =H34*(1+'Growth Rates'!H80) -> 5.2889755e+10 | J34: =I34*(1+'Growth Rates'!I80) -> 5.3735991e+10 | K34: =J34*(1+'Growth Rates'!J80) -> 5.4595767e+10 | ... AF34: =AE34*(1+'Growth Rates'!AE80) -> 7.6195065e+10
B35: ISIC 55T56 | C35: 3.2694198e+10 | D35: =C35*(1+'Growth Rates'!C81) -> 3.3380776e+10 | E35: =D35*(1+'Growth Rates'!D81) -> 3.4081772e+10 | F35: =E35*(1+'Growth Rates'!E81) -> 3.4797489e+10 | G35: =F35*(1+'Growth Rates'!F81) -> 3.5528237e+10 | H35: =G35*(1+'Growth Rates'!G81) -> 3.627433e+10 | I35: =H35*(1+'Growth Rates'!H81) -> 3.703609e+10 | J35: =I35*(1+'Growth Rates'!I81) -> 3.7813848e+10 | K35: =J35*(1+'Growth Rates'!J81) -> 3.8607939e+10 | ... AF35: =AE35*(1+'Growth Rates'!AE81) -> 5.9733396e+10
B36: ISIC 58T60 | C36: 2.118234e+10 | D36: =C36*(1+'Growth Rates'!C82) -> 2.1741551e+10 | E36: =D36*(1+'Growth Rates'!D82) -> 2.2315525e+10 | F36: =E36*(1+'Growth Rates'!E82) -> 2.2904652e+10 | G36: =F36*(1+'Growth Rates'!F82) -> 2.3509331e+10 | H36: =G36*(1+'Growth Rates'!G82) -> 2.4129974e+10 | I36: =H36*(1+'Growth Rates'!H82) -> 2.4767002e+10 | J36: =I36*(1+'Growth Rates'!I82) -> 2.5420848e+10 | K36: =J36*(1+'Growth Rates'!J82) -> 2.6091955e+10 | ... AF36: =AE36*(1+'Growth Rates'!AE82) -> 4.5097755e+10
B37: ISIC 61 | C37: 1.312977e+10 | D37: =C37*(1+'Growth Rates'!C83) -> 1.3392366e+10 | E37: =D37*(1+'Growth Rates'!D83) -> 1.3660213e+10 | F37: =E37*(1+'Growth Rates'!E83) -> 1.3933417e+10 | G37: =F37*(1+'Growth Rates'!F83) -> 1.4212086e+10 | H37: =G37*(1+'Growth Rates'!G83) -> 1.4496327e+10 | I37: =H37*(1+'Growth Rates'!H83) -> 1.4786254e+10 | J37: =I37*(1+'Growth Rates'!I83) -> 1.5081979e+10 | K37: =J37*(1+'Growth Rates'!J83) -> 1.5383618e+10 | ... AF37: =AE37*(1+'Growth Rates'!AE83) -> 2.3316433e+10
B38: ISIC 62T63 | C38: 2.5177443e+10 | D38: =C38*(1+'Growth Rates'!C84) -> 2.611681e+10 | E38: =D38*(1+'Growth Rates'!D84) -> 2.7091224e+10 | F38: =E38*(1+'Growth Rates'!E84) -> 2.8101994e+10 | G38: =F38*(1+'Growth Rates'!F84) -> 2.9150476e+10 | H38: =G38*(1+'Growth Rates'!G84) -> 3.0238076e+10 | I38: =H38*(1+'Growth Rates'!H84) -> 3.1366255e+10 | J38: =I38*(1+'Growth Rates'!I84) -> 3.2536525e+10 | K38: =J38*(1+'Growth Rates'!J84) -> 3.3750459e+10 | ... AF38: =AE38*(1+'Growth Rates'!AE84) -> 7.2838054e+10
B39: ISIC 64T66 | C39: 7.5716404e+10 | D39: =C39*(1+'Growth Rates'!C85) -> 7.6776434e+10 | E39: =D39*(1+'Growth Rates'!D85) -> 7.7851304e+10 | F39: =E39*(1+'Growth Rates'!E85) -> 7.8941222e+10 | G39: =F39*(1+'Growth Rates'!F85) -> 8.0046399e+10 | H39: =G39*(1+'Growth Rates'!G85) -> 8.1167049e+10 | I39: =H39*(1+'Growth Rates'!H85) -> 8.2303387e+10 | J39: =I39*(1+'Growth Rates'!I85) -> 8.3455635e+10 | K39: =J39*(1+'Growth Rates'!J85) -> 8.4624014e+10 | ... AF39: =AE39*(1+'Growth Rates'!AE85) -> 1.1331585e+11
B40: ISIC 68 | C40: 1.0400778e+11 | D40: =C40*(1+'Growth Rates'!C86) -> 1.0598393e+11 | E40: =D40*(1+'Growth Rates'!D86) -> 1.0799763e+11 | F40: =E40*(1+'Growth Rates'!E86) -> 1.1004958e+11 | G40: =F40*(1+'Growth Rates'!F86) -> 1.1214052e+11 | H40: =G40*(1+'Growth Rates'!G86) -> 1.1427119e+11 | I40: =H40*(1+'Growth Rates'!H86) -> 1.1644234e+11 | J40: =I40*(1+'Growth Rates'!I86) -> 1.1865475e+11 | K40: =J40*(1+'Growth Rates'!J86) -> 1.2090919e+11 | ... AF40: =AE40*(1+'Growth Rates'!AE86) -> 1.7952179e+11
B41: ISIC 69T82 | C41: 9.5146132e+10 | D41: =C41*(1+'Growth Rates'!C87) -> 9.7291998e+10 | E41: =D41*(1+'Growth Rates'!D87) -> 9.9486261e+10 | F41: =E41*(1+'Growth Rates'!E87) -> 1.0173001e+11 | G41: =F41*(1+'Growth Rates'!F87) -> 1.0402437e+11 | H41: =G41*(1+'Growth Rates'!G87) -> 1.0637047e+11 | I41: =H41*(1+'Growth Rates'!H87) -> 1.0876948e+11 | J41: =I41*(1+'Growth Rates'!I87) -> 1.112226e+11 | K41: =J41*(1+'Growth Rates'!J87) -> 1.1373104e+11 | ... AF41: =AE41*(1+'Growth Rates'!AE87) -> 1.8167062e+11
B42: ISIC 84 | C42: 9.3032982e+10 | D42: =C42*(1+'Growth Rates'!C88) -> 9.373518e+10 | E42: =D42*(1+'Growth Rates'!D88) -> 9.4442678e+10 | F42: =E42*(1+'Growth Rates'!E88) -> 9.5155517e+10 | G42: =F42*(1+'Growth Rates'!F88) -> 9.5873736e+10 | H42: =G42*(1+'Growth Rates'!G88) -> 9.6597376e+10 | I42: =H42*(1+'Growth Rates'!H88) -> 9.7326478e+10 | J42: =I42*(1+'Growth Rates'!I88) -> 9.8061083e+10 | K42: =J42*(1+'Growth Rates'!J88) -> 9.8801232e+10 | ... AF42: =AE42*(1+'Growth Rates'!AE88) -> 1.1570219e+11
B43: ISIC 85 | C43: 6.6938444e+10 | D43: =C43*(1+'Growth Rates'!C89) -> 6.8076397e+10 | E43: =D43*(1+'Growth Rates'!D89) -> 6.9233696e+10 | F43: =E43*(1+'Growth Rates'!E89) -> 7.0410669e+10 | G43: =F43*(1+'Growth Rates'!F89) -> 7.160765e+10 | H43: =G43*(1+'Growth Rates'!G89) -> 7.282498e+10 | I43: =H43*(1+'Growth Rates'!H89) -> 7.4063005e+10 | J43: =I43*(1+'Growth Rates'!I89) -> 7.5322076e+10 | K43: =J43*(1+'Growth Rates'!J89) -> 7.6602551e+10 | ... AF43: =AE43*(1+'Growth Rates'!AE89) -> 1.0913982e+11
B44: ISIC 86T88 | C44: 6.5010309e+10 | D44: =C44*(1+'Growth Rates'!C90) -> 6.6895608e+10 | E44: =D44*(1+'Growth Rates'!D90) -> 6.883558e+10 | F44: =E44*(1+'Growth Rates'!E90) -> 7.0831812e+10 | G44: =F44*(1+'Growth Rates'!F90) -> 7.2885935e+10 | H44: =G44*(1+'Growth Rates'!G90) -> 7.4999627e+10 | I44: =H44*(1+'Growth Rates'!H90) -> 7.7174616e+10 | J44: =I44*(1+'Growth Rates'!I90) -> 7.941268e+10 | K44: =J44*(1+'Growth Rates'!J90) -> 8.1715648e+10 | ... AF44: =AE44*(1+'Growth Rates'!AE90) -> 1.4894574e+11
... B46: ISIC 97T98 | C46: 1.6305094e+09 | D46: =C46*(1+'Growth Rates'!C92) -> 1.6582281e+09 | E46: =D46*(1+'Growth Rates'!D92) -> 1.686418e+09 | F46: =E46*(1+'Growth Rates'!E92) -> 1.7150871e+09 | G46: =F46*(1+'Growth Rates'!F92) -> 1.7442435e+09 | H46: =G46*(1+'Growth Rates'!G92) -> 1.7738957e+09 | I46: =H46*(1+'Growth Rates'!H92) -> 1.8040519e+09 | J46: =I46*(1+'Growth Rates'!I92) -> 1.8347208e+09 | K46: =J46*(1+'Growth Rates'!J92) -> 1.865911e+09 | ... AF46: =AE46*(1+'Growth Rates'!AE92) -> 2.658465e+09
B48: Total GDP | C48: =INDEX('GDP Forecast'!$B:$B,MATCH('Rescale to Fit GDP Proj'!C4,'GDP Forecast'!$A:$A,0)) -> 1.6434102e+12 | D48: =INDEX('GDP Forecast'!$B:$B,MATCH('Rescale to Fit GDP Proj'!D4,'GDP Forecast'!$A:$A,0)) -> 1.6863472e+12 | E48: =INDEX('GDP Forecast'!$B:$B,MATCH('Rescale to Fit GDP Proj'!E4,'GDP Forecast'!$A:$A,0)) -> 1.7092264e+12 | F48: =INDEX('GDP Forecast'!$B:$B,MATCH('Rescale to Fit GDP Proj'!F4,'GDP Forecast'!$A:$A,0)) -> 1.7477784e+12 | G48: =INDEX('GDP Forecast'!$B:$B,MATCH('Rescale to Fit GDP Proj'!G4,'GDP Forecast'!$A:$A,0)) -> 1.7850602e+12 | H48: =INDEX('GDP Forecast'!$B:$B,MATCH('Rescale to Fit GDP Proj'!H4,'GDP Forecast'!$A:$A,0)) -> 1.8268614e+12 | I48: =INDEX('GDP Forecast'!$B:$B,MATCH('Rescale to Fit GDP Proj'!I4,'GDP Forecast'!$A:$A,0)) -> 1.8657003e+12 | J48: =INDEX('GDP Forecast'!$B:$B,MATCH('Rescale to Fit GDP Proj'!J4,'GDP Forecast'!$A:$A,0)) -> 1.9006139e+12 | ... AF48: =INDEX('GDP Forecast'!$B:$B,MATCH('Rescale to Fit GDP Proj'!AF4,'GDP Forecast'!$A:$A,0)) -> 2.4298437e+12
B49: Toal GDP - sum of AEO projections | C49: =C48-SUMIF($A$5:$A$46,"AEO",C5:C46) -> 1.1847776e+12 | D49: =D48-SUMIF($A$5:$A$46,"AEO",D5:D46) -> 1.21876e+12 | E49: =E48-SUMIF($A$5:$A$46,"AEO",E5:E46) -> 1.2429515e+12 | F49: =F48-SUMIF($A$5:$A$46,"AEO",F5:F46) -> 1.2791471e+12 | G49: =G48-SUMIF($A$5:$A$46,"AEO",G5:G46) -> 1.3079375e+12 | H49: =H48-SUMIF($A$5:$A$46,"AEO",H5:H46) -> 1.3382186e+12 | I49: =I48-SUMIF($A$5:$A$46,"AEO",I5:I46) -> 1.3671347e+12 | J49: =J48-SUMIF($A$5:$A$46,"AEO",J5:J46) -> 1.3940209e+12 | ... AF49: =AF48-SUMIF($A$5:$A$46,"AEO",AF5:AF46) -> 1.7303366e+12
A52: Non-AEO Scaling Factor to Fit GDP Projection | D52: 0.954
A54: Difference between scaled data and GDP forecast (double check) | D54: =(SUM(AF148:AF189)-AF48)/AF48 -> -0.095007317
A56: Scaled Annual Growth Rates
C57: 2021 | D57: 2022 | E57: 2023 | F57: 2024 | G57: 2025 | H57: 2026 | I57: 2027 | J57: 2028 | K57: 2029 | L57: 2030 | M57: 2031 | N57: 2032 | O57: 2033 | P57: 2034 | Q57: 2035 | R57: 2036 | S57: 2037 | T57: 2038 | U57: 2039 | V57: 2040 | W57: 2041 | X57: 2042 | Y57: 2043 | Z57: 2044 | AA57: 2045 | AB57: 2046 | AC57: 2047 | AD57: 2048 | AE57: 2049 | AF57: 2050
A58: AEO | B58: ISIC 01T03 | C58: =IF($A58="AEO",'Growth Rates'!B51,'Growth Rates'!B51*'Rescale to Fit GDP Proj'!$D$52) -> 0 | D58: =IF($A58="AEO",'Growth Rates'!C51,'Growth Rates'!C51*'Rescale to Fit GDP Proj'!$D$52) -> -1.1176675e-07 | E58: =IF($A58="AEO",'Growth Rates'!D51,'Growth Rates'!D51*'Rescale to Fit GDP Proj'!$D$52) -> -0.0013511448 | F58: =IF($A58="AEO",'Growth Rates'!E51,'Growth Rates'!E51*'Rescale to Fit GDP Proj'!$D$52) -> 0.0091327312 | G58: =IF($A58="AEO",'Growth Rates'!F51,'Growth Rates'!F51*'Rescale to Fit GDP Proj'!$D$52) -> 0.013396293 | H58: =IF($A58="AEO",'Growth Rates'!G51,'Growth Rates'!G51*'Rescale to Fit GDP Proj'!$D$52) -> 0.015288029 | I58: =IF($A58="AEO",'Growth Rates'!H51,'Growth Rates'!H51*'Rescale to Fit GDP Proj'!$D$52) -> 0.013409394 | J58: =IF($A58="AEO",'Growth Rates'!I51,'Growth Rates'!I51*'Rescale to Fit GDP Proj'!$D$52) -> 0.011724967 | ... AF58: =IF($A58="AEO",'Growth Rates'!AE51,'Growth Rates'!AE51*'Rescale to Fit GDP Proj'!$D$52) -> 0.0062089547
A59: AEO | B59: ISIC 05 | C59: =IF($A59="AEO",'Growth Rates'!B52,'Growth Rates'!B52*'Rescale to Fit GDP Proj'!$D$52) -> 0 | D59: =IF($A59="AEO",'Growth Rates'!C52,'Growth Rates'!C52*'Rescale to Fit GDP Proj'!$D$52) -> -0.01752763 | E59: =IF($A59="AEO",'Growth Rates'!D52,'Growth Rates'!D52*'Rescale to Fit GDP Proj'!$D$52) -> -0.055963095 | F59: =IF($A59="AEO",'Growth Rates'!E52,'Growth Rates'!E52*'Rescale to Fit GDP Proj'!$D$52) -> 0.093166707 | G59: =IF($A59="AEO",'Growth Rates'!F52,'Growth Rates'!F52*'Rescale to Fit GDP Proj'!$D$52) -> -0.061190092 | H59: =IF($A59="AEO",'Growth Rates'!G52,'Growth Rates'!G52*'Rescale to Fit GDP Proj'!$D$52) -> -0.085239248 | I59: =IF($A59="AEO",'Growth Rates'!H52,'Growth Rates'!H52*'Rescale to Fit GDP Proj'!$D$52) -> -0.10350713 | J59: =IF($A59="AEO",'Growth Rates'!I52,'Growth Rates'!I52*'Rescale to Fit GDP Proj'!$D$52) -> -0.10251285 | ... AF59: =IF($A59="AEO",'Growth Rates'!AE52,'Growth Rates'!AE52*'Rescale to Fit GDP Proj'!$D$52) -> -0.014273166
A60: AEO | B60: ISIC 06 | C60: =IF($A60="AEO",'Growth Rates'!B53,'Growth Rates'!B53*'Rescale to Fit GDP Proj'!$D$52) -> 0 | D60: =IF($A60="AEO",'Growth Rates'!C53,'Growth Rates'!C53*'Rescale to Fit GDP Proj'!$D$52) -> 0.003135583 | E60: =IF($A60="AEO",'Growth Rates'!D53,'Growth Rates'!D53*'Rescale to Fit GDP Proj'!$D$52) -> -0.027932862 | F60: =IF($A60="AEO",'Growth Rates'!E53,'Growth Rates'!E53*'Rescale to Fit GDP Proj'!$D$52) -> -0.00027538352 | G60: =IF($A60="AEO",'Growth Rates'!F53,'Growth Rates'!F53*'Rescale to Fit GDP Proj'!$D$52) -> 0.0076435853 | H60: =IF($A60="AEO",'Growth Rates'!G53,'Growth Rates'!G53*'Rescale to Fit GDP Proj'!$D$52) -> 0.013378753 | I60: =IF($A60="AEO",'Growth Rates'!H53,'Growth Rates'!H53*'Rescale to Fit GDP Proj'!$D$52) -> 0.0016767167 | J60: =IF($A60="AEO",'Growth Rates'!I53,'Growth Rates'!I53*'Rescale to Fit GDP Proj'!$D$52) -> 0.0081244305 | ... AF60: =IF($A60="AEO",'Growth Rates'!AE53,'Growth Rates'!AE53*'Rescale to Fit GDP Proj'!$D$52) -> 0.0050993658
A61: AEO | B61: ISIC 07T08 | C61: =IF($A61="AEO",'Growth Rates'!B54,'Growth Rates'!B54*'Rescale to Fit GDP Proj'!$D$52) -> 0 | D61: =IF($A61="AEO",'Growth Rates'!C54,'Growth Rates'!C54*'Rescale to Fit GDP Proj'!$D$52) -> -0.00028519755 | E61: =IF($A61="AEO",'Growth Rates'!D54,'Growth Rates'!D54*'Rescale to Fit GDP Proj'!$D$52) -> -0.024179188 | F61: =IF($A61="AEO",'Growth Rates'!E54,'Growth Rates'!E54*'Rescale to Fit GDP Proj'!$D$52) -> -0.022910667 | G61: =IF($A61="AEO",'Growth Rates'!F54,'Growth Rates'!F54*'Rescale to Fit GDP Proj'!$D$52) -> -0.013292478 | H61: =IF($A61="AEO",'Growth Rates'!G54,'Growth Rates'!G54*'Rescale to Fit GDP Proj'!$D$52) -> -0.014521472 | I61: =IF($A61="AEO",'Growth Rates'!H54,'Growth Rates'!H54*'Rescale to Fit GDP Proj'!$D$52) -> -0.019372168 | J61: =IF($A61="AEO",'Growth Rates'!I54,'Growth Rates'!I54*'Rescale to Fit GDP Proj'!$D$52) -> -0.012425212 | ... AF61: =IF($A61="AEO",'Growth Rates'!AE54,'Growth Rates'!AE54*'Rescale to Fit GDP Proj'!$D$52) -> 0.012351638
B62: ISIC 09 | C62: =IF($A62="AEO",'Growth Rates'!B55,'Growth Rates'!B55*'Rescale to Fit GDP Proj'!$D$52) -> 0 | D62: =IF($A62="AEO",'Growth Rates'!C55,'Growth Rates'!C55*'Rescale to Fit GDP Proj'!$D$52) -> 0.027666 | E62: =IF($A62="AEO",'Growth Rates'!D55,'Growth Rates'!D55*'Rescale to Fit GDP Proj'!$D$52) -> 0.027666 | F62: =IF($A62="AEO",'Growth Rates'!E55,'Growth Rates'!E55*'Rescale to Fit GDP Proj'!$D$52) -> 0.027666 | G62: =IF($A62="AEO",'Growth Rates'!F55,'Growth Rates'!F55*'Rescale to Fit GDP Proj'!$D$52) -> 0.027666 | H62: =IF($A62="AEO",'Growth Rates'!G55,'Growth Rates'!G55*'Rescale to Fit GDP Proj'!$D$52) -> 0.027666 | I62: =IF($A62="AEO",'Growth Rates'!H55,'Growth Rates'!H55*'Rescale to Fit GDP Proj'!$D$52) -> 0.027666 | J62: =IF($A62="AEO",'Growth Rates'!I55,'Growth Rates'!I55*'Rescale to Fit GDP Proj'!$D$52) -> 0.027666 | ... AF62: =IF($A62="AEO",'Growth Rates'!AE55,'Growth Rates'!AE55*'Rescale to Fit GDP Proj'!$D$52) -> 0.027666
A63: AEO | B63: ISIC 10T12 | C63: =IF($A63="AEO",'Growth Rates'!B56,'Growth Rates'!B56*'Rescale to Fit GDP Proj'!$D$52) -> 0 | D63: =IF($A63="AEO",'Growth Rates'!C56,'Growth Rates'!C56*'Rescale to Fit GDP Proj'!$D$52) -> -0.012463136 | E63: =IF($A63="AEO",'Growth Rates'!D56,'Growth Rates'!D56*'Rescale to Fit GDP Proj'!$D$52) -> 0.015600731 | F63: =IF($A63="AEO",'Growth Rates'!E56,'Growth Rates'!E56*'Rescale to Fit GDP Proj'!$D$52) -> 0.010035729 | G63: =IF($A63="AEO",'Growth Rates'!F56,'Growth Rates'!F56*'Rescale to Fit GDP Proj'!$D$52) -> 0.0092179804 | H63: =IF($A63="AEO",'Growth Rates'!G56,'Growth Rates'!G56*'Rescale to Fit GDP Proj'!$D$52) -> 0.012898743 | I63: =IF($A63="AEO",'Growth Rates'!H56,'Growth Rates'!H56*'Rescale to Fit GDP Proj'!$D$52) -> 0.014149095 | J63: =IF($A63="AEO",'Growth Rates'!I56,'Growth Rates'!I56*'Rescale to Fit GDP Proj'!$D$52) -> 0.014043116 | ... AF63: =IF($A63="AEO",'Growth Rates'!AE56,'Growth Rates'!AE56*'Rescale to Fit GDP Proj'!$D$52) -> 0.0092652577
A64: AEO | B64: ISIC 13T15 | C64: =IF($A64="AEO",'Growth Rates'!B57,'Growth Rates'!B57*'Rescale to Fit GDP Proj'!$D$52) -> 0 | D64: =IF($A64="AEO",'Growth Rates'!C57,'Growth Rates'!C57*'Rescale to Fit GDP Proj'!$D$52) -> -0.00049111462 | E64: =IF($A64="AEO",'Growth Rates'!D57,'Growth Rates'!D57*'Rescale to Fit GDP Proj'!$D$52) -> -0.015291759 | F64: =IF($A64="AEO",'Growth Rates'!E57,'Growth Rates'!E57*'Rescale to Fit GDP Proj'!$D$52) -> -0.010161745 | G64: =IF($A64="AEO",'Growth Rates'!F57,'Growth Rates'!F57*'Rescale to Fit GDP Proj'!$D$52) -> 0.00043146482 | H64: =IF($A64="AEO",'Growth Rates'!G57,'Growth Rates'!G57*'Rescale to Fit GDP Proj'!$D$52) -> 0.018861179 | I64: =IF($A64="AEO",'Growth Rates'!H57,'Growth Rates'!H57*'Rescale to Fit GDP Proj'!$D$52) -> 0.022854649 | J64: =IF($A64="AEO",'Growth Rates'!I57,'Growth Rates'!I57*'Rescale to Fit GDP Proj'!$D$52) -> 0.015633738 | ... AF64: =IF($A64="AEO",'Growth Rates'!AE57,'Growth Rates'!AE57*'Rescale to Fit GDP Proj'!$D$52) -> -0.0070890216
A65: AEO | B65: ISIC 16 | C65: =IF($A65="AEO",'Growth Rates'!B58,'Growth Rates'!B58*'Rescale to Fit GDP Proj'!$D$52) -> 0 | D65: =IF($A65="AEO",'Growth Rates'!C58,'Growth Rates'!C58*'Rescale to Fit GDP Proj'!$D$52) -> -0.0064436018 | E65: =IF($A65="AEO",'Growth Rates'!D58,'Growth Rates'!D58*'Rescale to Fit GDP Proj'!$D$52) -> -0.091320586 | F65: =IF($A65="AEO",'Growth Rates'!E58,'Growth Rates'!E58*'Rescale to Fit GDP Proj'!$D$52) -> -0.026686381 | G65: =IF($A65="AEO",'Growth Rates'!F58,'Growth Rates'!F58*'Rescale to Fit GDP Proj'!$D$52) -> 0.018734119 | H65: =IF($A65="AEO",'Growth Rates'!G58,'Growth Rates'!G58*'Rescale to Fit GDP Proj'!$D$52) -> -0.012793884 | I65: =IF($A65="AEO",'Growth Rates'!H58,'Growth Rates'!H58*'Rescale to Fit GDP Proj'!$D$52) -> -0.0044872068 | J65: =IF($A65="AEO",'Growth Rates'!I58,'Growth Rates'!I58*'Rescale to Fit GDP Proj'!$D$52) -> 0.013003257 | ... AF65: =IF($A65="AEO",'Growth Rates'!AE58,'Growth Rates'!AE58*'Rescale to Fit GDP Proj'!$D$52) -> 0.010461093
A66: AEO | B66: ISIC 17T18 | C66: =IF($A66="AEO",'Growth Rates'!B59,'Growth Rates'!B59*'Rescale to Fit GDP Proj'!$D$52) -> 0 | D66: =IF($A66="AEO",'Growth Rates'!C59,'Growth Rates'!C59*'Rescale to Fit GDP Proj'!$D$52) -> 0.034978913 | E66: =IF($A66="AEO",'Growth Rates'!D59,'Growth Rates'!D59*'Rescale to Fit GDP Proj'!$D$52) -> -0.022942396 | F66: =IF($A66="AEO",'Growth Rates'!E59,'Growth Rates'!E59*'Rescale to Fit GDP Proj'!$D$52) -> -0.02223464 | G66: =IF($A66="AEO",'Growth Rates'!F59,'Growth Rates'!F59*'Rescale to Fit GDP Proj'!$D$52) -> -0.0014451533 | H66: =IF($A66="AEO",'Growth Rates'!G59,'Growth Rates'!G59*'Rescale to Fit GDP Proj'!$D$52) -> 0.0051444073 | I66: =IF($A66="AEO",'Growth Rates'!H59,'Growth Rates'!H59*'Rescale to Fit GDP Proj'!$D$52) -> 0.0061956363 | J66: =IF($A66="AEO",'Growth Rates'!I59,'Growth Rates'!I59*'Rescale to Fit GDP Proj'!$D$52) -> 0.0059704499 | ... AF66: =IF($A66="AEO",'Growth Rates'!AE59,'Growth Rates'!AE59*'Rescale to Fit GDP Proj'!$D$52) -> 0.007186495
A67: AEO | B67: ISIC 19 | C67: =IF($A67="AEO",'Growth Rates'!B60,'Growth Rates'!B60*'Rescale to Fit GDP Proj'!$D$52) -> 0 | D67: =IF($A67="AEO",'Growth Rates'!C60,'Growth Rates'!C60*'Rescale to Fit GDP Proj'!$D$52) -> 0.035549762 | E67: =IF($A67="AEO",'Growth Rates'!D60,'Growth Rates'!D60*'Rescale to Fit GDP Proj'!$D$52) -> 0.085422436 | F67: =IF($A67="AEO",'Growth Rates'!E60,'Growth Rates'!E60*'Rescale to Fit GDP Proj'!$D$52) -> -0.0029162063 | G67: =IF($A67="AEO",'Growth Rates'!F60,'Growth Rates'!F60*'Rescale to Fit GDP Proj'!$D$52) -> -0.0036921542 | H67: =IF($A67="AEO",'Growth Rates'!G60,'Growth Rates'!G60*'Rescale to Fit GDP Proj'!$D$52) -> -0.0044459641 | I67: =IF($A67="AEO",'Growth Rates'!H60,'Growth Rates'!H60*'Rescale to Fit GDP Proj'!$D$52) -> -0.0027839792 | J67: =IF($A67="AEO",'Growth Rates'!I60,'Growth Rates'!I60*'Rescale to Fit GDP Proj'!$D$52) -> -0.0030173431 | ... AF67: =IF($A67="AEO",'Growth Rates'!AE60,'Growth Rates'!AE60*'Rescale to Fit GDP Proj'!$D$52) -> 0.0093978867
A68: AEO | B68: ISIC 20 | C68: =IF($A68="AEO",'Growth Rates'!B61,'Growth Rates'!B61*'Rescale to Fit GDP Proj'!$D$52) -> 0 | D68: =IF($A68="AEO",'Growth Rates'!C61,'Growth Rates'!C61*'Rescale to Fit GDP Proj'!$D$52) -> -0.013315353 | E68: =IF($A68="AEO",'Growth Rates'!D61,'Growth Rates'!D61*'Rescale to Fit GDP Proj'!$D$52) -> -0.02210627 | F68: =IF($A68="AEO",'Growth Rates'!E61,'Growth Rates'!E61*'Rescale to Fit GDP Proj'!$D$52) -> -0.011879799 | G68: =IF($A68="AEO",'Growth Rates'!F61,'Growth Rates'!F61*'Rescale to Fit GDP Proj'!$D$52) -> 0.016304088 | H68: =IF($A68="AEO",'Growth Rates'!G61,'Growth Rates'!G61*'Rescale to Fit GDP Proj'!$D$52) -> 0.023084207 | I68: =IF($A68="AEO",'Growth Rates'!H61,'Growth Rates'!H61*'Rescale to Fit GDP Proj'!$D$52) -> 0.023260266 | J68: =IF($A68="AEO",'Growth Rates'!I61,'Growth Rates'!I61*'Rescale to Fit GDP Proj'!$D$52) -> 0.020013849 | ... AF68: =IF($A68="AEO",'Growth Rates'!AE61,'Growth Rates'!AE61*'Rescale to Fit GDP Proj'!$D$52) -> 0.022866991
B69: ISIC 21 | C69: =IF($A69="AEO",'Growth Rates'!B62,'Growth Rates'!B62*'Rescale to Fit GDP Proj'!$D$52) -> 0 | D69: =IF($A69="AEO",'Growth Rates'!C62,'Growth Rates'!C62*'Rescale to Fit GDP Proj'!$D$52) -> 0.017172 | E69: =IF($A69="AEO",'Growth Rates'!D62,'Growth Rates'!D62*'Rescale to Fit GDP Proj'!$D$52) -> 0.017172 | F69: =IF($A69="AEO",'Growth Rates'!E62,'Growth Rates'!E62*'Rescale to Fit GDP Proj'!$D$52) -> 0.017172 | G69: =IF($A69="AEO",'Growth Rates'!F62,'Growth Rates'!F62*'Rescale to Fit GDP Proj'!$D$52) -> 0.017172 | H69: =IF($A69="AEO",'Growth Rates'!G62,'Growth Rates'!G62*'Rescale to Fit GDP Proj'!$D$52) -> 0.017172 | I69: =IF($A69="AEO",'Growth Rates'!H62,'Growth Rates'!H62*'Rescale to Fit GDP Proj'!$D$52) -> 0.017172 | J69: =IF($A69="AEO",'Growth Rates'!I62,'Growth Rates'!I62*'Rescale to Fit GDP Proj'!$D$52) -> 0.017172 | ... AF69: =IF($A69="AEO",'Growth Rates'!AE62,'Growth Rates'!AE62*'Rescale to Fit GDP Proj'!$D$52) -> 0.017172
A70: AEO | B70: ISIC 22 | C70: =IF($A70="AEO",'Growth Rates'!B63,'Growth Rates'!B63*'Rescale to Fit GDP Proj'!$D$52) -> 0 | D70: =IF($A70="AEO",'Growth Rates'!C63,'Growth Rates'!C63*'Rescale to Fit GDP Proj'!$D$52) -> 0.037127926 | E70: =IF($A70="AEO",'Growth Rates'!D63,'Growth Rates'!D63*'Rescale to Fit GDP Proj'!$D$52) -> -0.020293273 | F70: =IF($A70="AEO",'Growth Rates'!E63,'Growth Rates'!E63*'Rescale to Fit GDP Proj'!$D$52) -> -0.0072429512 | G70: =IF($A70="AEO",'Growth Rates'!F63,'Growth Rates'!F63*'Rescale to Fit GDP Proj'!$D$52) -> 0.014554492 | H70: =IF($A70="AEO",'Growth Rates'!G63,'Growth Rates'!G63*'Rescale to Fit GDP Proj'!$D$52) -> 0.02625625 | I70: =IF($A70="AEO",'Growth Rates'!H63,'Growth Rates'!H63*'Rescale to Fit GDP Proj'!$D$52) -> 0.022568493 | J70: =IF($A70="AEO",'Growth Rates'!I63,'Growth Rates'!I63*'Rescale to Fit GDP Proj'!$D$52) -> 0.018687012 | ... AF70: =IF($A70="AEO",'Growth Rates'!AE63,'Growth Rates'!AE63*'Rescale to Fit GDP Proj'!$D$52) -> 0.020773899
A71: AEO | B71: ISIC 231 | C71: =IF($A71="AEO",'Growth Rates'!B64,'Growth Rates'!B64*'Rescale to Fit GDP Proj'!$D$52) -> 0 | D71: =IF($A71="AEO",'Growth Rates'!C64,'Growth Rates'!C64*'Rescale to Fit GDP Proj'!$D$52) -> 0.015773178 | E71: =IF($A71="AEO",'Growth Rates'!D64,'Growth Rates'!D64*'Rescale to Fit GDP Proj'!$D$52) -> -0.058886503 | F71: =IF($A71="AEO",'Growth Rates'!E64,'Growth Rates'!E64*'Rescale to Fit GDP Proj'!$D$52) -> -0.017012937 | G71: =IF($A71="AEO",'Growth Rates'!F64,'Growth Rates'!F64*'Rescale to Fit GDP Proj'!$D$52) -> 0.00034113368 | H71: =IF($A71="AEO",'Growth Rates'!G64,'Growth Rates'!G64*'Rescale to Fit GDP Proj'!$D$52) -> 0.028267038 | I71: =IF($A71="AEO",'Growth Rates'!H64,'Growth Rates'!H64*'Rescale to Fit GDP Proj'!$D$52) -> 0.015411073 | J71: =IF($A71="AEO",'Growth Rates'!I64,'Growth Rates'!I64*'Rescale to Fit GDP Proj'!$D$52) -> 0.01177904 | ... AF71: =IF($A71="AEO",'Growth Rates'!AE64,'Growth Rates'!AE64*'Rescale to Fit GDP Proj'!$D$52) -> 0.0098945908
A72: AEO | B72: ISIC 239 | C72: =IF($A72="AEO",'Growth Rates'!B65,'Growth Rates'!B65*'Rescale to Fit GDP Proj'!$D$52) -> 0 | D72: =IF($A72="AEO",'Growth Rates'!C65,'Growth Rates'!C65*'Rescale to Fit GDP Proj'!$D$52) -> 0.15097807 | E72: =IF($A72="AEO",'Growth Rates'!D65,'Growth Rates'!D65*'Rescale to Fit GDP Proj'!$D$52) -> -0.04461641 | F72: =IF($A72="AEO",'Growth Rates'!E65,'Growth Rates'!E65*'Rescale to Fit GDP Proj'!$D$52) -> -0.012348283 | G72: =IF($A72="AEO",'Growth Rates'!F65,'Growth Rates'!F65*'Rescale to Fit GDP Proj'!$D$52) -> 0.016226214 | H72: =IF($A72="AEO",'Growth Rates'!G65,'Growth Rates'!G65*'Rescale to Fit GDP Proj'!$D$52) -> 0.015205168 | I72: =IF($A72="AEO",'Growth Rates'!H65,'Growth Rates'!H65*'Rescale to Fit GDP Proj'!$D$52) -> 0.009736753 | J72: =IF($A72="AEO",'Growth Rates'!I65,'Growth Rates'!I65*'Rescale to Fit GDP Proj'!$D$52) -> 0.009114511 | ... AF72: =IF($A72="AEO",'Growth Rates'!AE65,'Growth Rates'!AE65*'Rescale to Fit GDP Proj'!$D$52) -> 0.0088785441
A73: AEO | B73: ISIC 241 | C73: =IF($A73="AEO",'Growth Rates'!B66,'Growth Rates'!B66*'Rescale to Fit GDP Proj'!$D$52) -> 0 | D73: =IF($A73="AEO",'Growth Rates'!C66,'Growth Rates'!C66*'Rescale to Fit GDP Proj'!$D$52) -> 0.011938163 | E73: =IF($A73="AEO",'Growth Rates'!D66,'Growth Rates'!D66*'Rescale to Fit GDP Proj'!$D$52) -> -0.016293577 | F73: =IF($A73="AEO",'Growth Rates'!E66,'Growth Rates'!E66*'Rescale to Fit GDP Proj'!$D$52) -> -0.015440337 | G73: =IF($A73="AEO",'Growth Rates'!F66,'Growth Rates'!F66*'Rescale to Fit GDP Proj'!$D$52) -> 0.022674474 | H73: =IF($A73="AEO",'Growth Rates'!G66,'Growth Rates'!G66*'Rescale to Fit GDP Proj'!$D$52) -> 0.047757682 | I73: =IF($A73="AEO",'Growth Rates'!H66,'Growth Rates'!H66*'Rescale to Fit GDP Proj'!$D$52) -> 0.023640194 | J73: =IF($A73="AEO",'Growth Rates'!I66,'Growth Rates'!I66*'Rescale to Fit GDP Proj'!$D$52) -> 0.0054910528 | ... AF73: =IF($A73="AEO",'Growth Rates'!AE66,'Growth Rates'!AE66*'Rescale to Fit GDP Proj'!$D$52) -> 0.010141857
A74: AEO | B74: ISIC 242 | C74: =IF($A74="AEO",'Growth Rates'!B67,'Growth Rates'!B67*'Rescale to Fit GDP Proj'!$D$52) -> 0 | D74: =IF($A74="AEO",'Growth Rates'!C67,'Growth Rates'!C67*'Rescale to Fit GDP Proj'!$D$52) -> 0.039616361 | E74: =IF($A74="AEO",'Growth Rates'!D67,'Growth Rates'!D67*'Rescale to Fit GDP Proj'!$D$52) -> -0.012242674 | F74: =IF($A74="AEO",'Growth Rates'!E67,'Growth Rates'!E67*'Rescale to Fit GDP Proj'!$D$52) -> 0.0060433727 | G74: =IF($A74="AEO",'Growth Rates'!F67,'Growth Rates'!F67*'Rescale to Fit GDP Proj'!$D$52) -> 0.029090594 | H74: =IF($A74="AEO",'Growth Rates'!G67,'Growth Rates'!G67*'Rescale to Fit GDP Proj'!$D$52) -> 0.032957149 | I74: =IF($A74="AEO",'Growth Rates'!H67,'Growth Rates'!H67*'Rescale to Fit GDP Proj'!$D$52) -> 0.021340388 | J74: =IF($A74="AEO",'Growth Rates'!I67,'Growth Rates'!I67*'Rescale to Fit GDP Proj'!$D$52) -> 0.014495421 | ... AF74: =IF($A74="AEO",'Growth Rates'!AE67,'Growth Rates'!AE67*'Rescale to Fit GDP Proj'!$D$52) -> 0.015067396
A75: AEO | B75: ISIC 25 | C75: =IF($A75="AEO",'Growth Rates'!B68,'Growth Rates'!B68*'Rescale to Fit GDP Proj'!$D$52) -> 0 | D75: =IF($A75="AEO",'Growth Rates'!C68,'Growth Rates'!C68*'Rescale to Fit GDP Proj'!$D$52) -> 0.013208161 | E75: =IF($A75="AEO",'Growth Rates'!D68,'Growth Rates'!D68*'Rescale to Fit GDP Proj'!$D$52) -> -0.019358653 | F75: =IF($A75="AEO",'Growth Rates'!E68,'Growth Rates'!E68*'Rescale to Fit GDP Proj'!$D$52) -> -0.0073700973 | G75: =IF($A75="AEO",'Growth Rates'!F68,'Growth Rates'!F68*'Rescale to Fit GDP Proj'!$D$52) -> 0.018394084 | H75: =IF($A75="AEO",'Growth Rates'!G68,'Growth Rates'!G68*'Rescale to Fit GDP Proj'!$D$52) -> 0.032985153 | I75: =IF($A75="AEO",'Growth Rates'!H68,'Growth Rates'!H68*'Rescale to Fit GDP Proj'!$D$52) -> 0.026959938 | J75: =IF($A75="AEO",'Growth Rates'!I68,'Growth Rates'!I68*'Rescale to Fit GDP Proj'!$D$52) -> 0.015362876 | ... AF75: =IF($A75="AEO",'Growth Rates'!AE68,'Growth Rates'!AE68*'Rescale to Fit GDP Proj'!$D$52) -> 0.014245792
A76: AEO | B76: ISIC 26 | C76: =IF($A76="AEO",'Growth Rates'!B69,'Growth Rates'!B69*'Rescale to Fit GDP Proj'!$D$52) -> 0 | D76: =IF($A76="AEO",'Growth Rates'!C69,'Growth Rates'!C69*'Rescale to Fit GDP Proj'!$D$52) -> 0.052842005 | E76: =IF($A76="AEO",'Growth Rates'!D69,'Growth Rates'!D69*'Rescale to Fit GDP Proj'!$D$52) -> 0.019620955 | F76: =IF($A76="AEO",'Growth Rates'!E69,'Growth Rates'!E69*'Rescale to Fit GDP Proj'!$D$52) -> 0.031824681 | G76: =IF($A76="AEO",'Growth Rates'!F69,'Growth Rates'!F69*'Rescale to Fit GDP Proj'!$D$52) -> 0.03923558 | H76: =IF($A76="AEO",'Growth Rates'!G69,'Growth Rates'!G69*'Rescale to Fit GDP Proj'!$D$52) -> 0.042408415 | I76: =IF($A76="AEO",'Growth Rates'!H69,'Growth Rates'!H69*'Rescale to Fit GDP Proj'!$D$52) -> 0.034834472 | J76: =IF($A76="AEO",'Growth Rates'!I69,'Growth Rates'!I69*'Rescale to Fit GDP Proj'!$D$52) -> 0.028984244 | ... AF76: =IF($A76="AEO",'Growth Rates'!AE69,'Growth Rates'!AE69*'Rescale to Fit GDP Proj'!$D$52) -> 0.024012367
A77: AEO | B77: ISIC 27 | C77: =IF($A77="AEO",'Growth Rates'!B70,'Growth Rates'!B70*'Rescale to Fit GDP Proj'!$D$52) -> 0 | D77: =IF($A77="AEO",'Growth Rates'!C70,'Growth Rates'!C70*'Rescale to Fit GDP Proj'!$D$52) -> 0.027897917 | E77: =IF($A77="AEO",'Growth Rates'!D70,'Growth Rates'!D70*'Rescale to Fit GDP Proj'!$D$52) -> -0.00042399646 | F77: =IF($A77="AEO",'Growth Rates'!E70,'Growth Rates'!E70*'Rescale to Fit GDP Proj'!$D$52) -> 0.011130999 | G77: =IF($A77="AEO",'Growth Rates'!F70,'Growth Rates'!F70*'Rescale to Fit GDP Proj'!$D$52) -> 0.024032641 | H77: =IF($A77="AEO",'Growth Rates'!G70,'Growth Rates'!G70*'Rescale to Fit GDP Proj'!$D$52) -> 0.02381564 | I77: =IF($A77="AEO",'Growth Rates'!H70,'Growth Rates'!H70*'Rescale to Fit GDP Proj'!$D$52) -> 0.021410755 | J77: =IF($A77="AEO",'Growth Rates'!I70,'Growth Rates'!I70*'Rescale to Fit GDP Proj'!$D$52) -> 0.018612395 | ... AF77: =IF($A77="AEO",'Growth Rates'!AE70,'Growth Rates'!AE70*'Rescale to Fit GDP Proj'!$D$52) -> 0.028127201
A78: AEO | B78: ISIC 28 | C78: =IF($A78="AEO",'Growth Rates'!B71,'Growth Rates'!B71*'Rescale to Fit GDP Proj'!$D$52) -> 0 | D78: =IF($A78="AEO",'Growth Rates'!C71,'Growth Rates'!C71*'Rescale to Fit GDP Proj'!$D$52) -> 0.027819565 | E78: =IF($A78="AEO",'Growth Rates'!D71,'Growth Rates'!D71*'Rescale to Fit GDP Proj'!$D$52) -> -0.015137824 | F78: =IF($A78="AEO",'Growth Rates'!E71,'Growth Rates'!E71*'Rescale to Fit GDP Proj'!$D$52) -> 0.00061568328 | G78: =IF($A78="AEO",'Growth Rates'!F71,'Growth Rates'!F71*'Rescale to Fit GDP Proj'!$D$52) -> 0.012153635 | H78: =IF($A78="AEO",'Growth Rates'!G71,'Growth Rates'!G71*'Rescale to Fit GDP Proj'!$D$52) -> 0.036657504 | I78: =IF($A78="AEO",'Growth Rates'!H71,'Growth Rates'!H71*'Rescale to Fit GDP Proj'!$D$52) -> 0.031121899 | J78: =IF($A78="AEO",'Growth Rates'!I71,'Growth Rates'!I71*'Rescale to Fit GDP Proj'!$D$52) -> 0.013049016 | ... AF78: =IF($A78="AEO",'Growth Rates'!AE71,'Growth Rates'!AE71*'Rescale to Fit GDP Proj'!$D$52) -> 0.013845914
A79: AEO | B79: ISIC 29 | C79: =IF($A79="AEO",'Growth Rates'!B72,'Growth Rates'!B72*'Rescale to Fit GDP Proj'!$D$52) -> 0 | D79: =IF($A79="AEO",'Growth Rates'!C72,'Growth Rates'!C72*'Rescale to Fit GDP Proj'!$D$52) -> 0.028290026 | E79: =IF($A79="AEO",'Growth Rates'!D72,'Growth Rates'!D72*'Rescale to Fit GDP Proj'!$D$52) -> 0.031107246 | F79: =IF($A79="AEO",'Growth Rates'!E72,'Growth Rates'!E72*'Rescale to Fit GDP Proj'!$D$52) -> 0.012544625 | G79: =IF($A79="AEO",'Growth Rates'!F72,'Growth Rates'!F72*'Rescale to Fit GDP Proj'!$D$52) -> -0.0029244404 | H79: =IF($A79="AEO",'Growth Rates'!G72,'Growth Rates'!G72*'Rescale to Fit GDP Proj'!$D$52) -> 0.005205824 | I79: =IF($A79="AEO",'Growth Rates'!H72,'Growth Rates'!H72*'Rescale to Fit GDP Proj'!$D$52) -> 0.018574672 | J79: =IF($A79="AEO",'Growth Rates'!I72,'Growth Rates'!I72*'Rescale to Fit GDP Proj'!$D$52) -> 0.013662341 | ... AF79: =IF($A79="AEO",'Growth Rates'!AE72,'Growth Rates'!AE72*'Rescale to Fit GDP Proj'!$D$52) -> 0.016845152
A80: AEO | B80: ISIC 30 | C80: =IF($A80="AEO",'Growth Rates'!B73,'Growth Rates'!B73*'Rescale to Fit GDP Proj'!$D$52) -> 0 | D80: =IF($A80="AEO",'Growth Rates'!C73,'Growth Rates'!C73*'Rescale to Fit GDP Proj'!$D$52) -> 0.028290026 | E80: =IF($A80="AEO",'Growth Rates'!D73,'Growth Rates'!D73*'Rescale to Fit GDP Proj'!$D$52) -> 0.031107246 | F80: =IF($A80="AEO",'Growth Rates'!E73,'Growth Rates'!E73*'Rescale to Fit GDP Proj'!$D$52) -> 0.012544625 | G80: =IF($A80="AEO",'Growth Rates'!F73,'Growth Rates'!F73*'Rescale to Fit GDP Proj'!$D$52) -> -0.0029244404 | H80: =IF($A80="AEO",'Growth Rates'!G73,'Growth Rates'!G73*'Rescale to Fit GDP Proj'!$D$52) -> 0.005205824 | I80: =IF($A80="AEO",'Growth Rates'!H73,'Growth Rates'!H73*'Rescale to Fit GDP Proj'!$D$52) -> 0.018574672 | J80: =IF($A80="AEO",'Growth Rates'!I73,'Growth Rates'!I73*'Rescale to Fit GDP Proj'!$D$52) -> 0.013662341 | ... AF80: =IF($A80="AEO",'Growth Rates'!AE73,'Growth Rates'!AE73*'Rescale to Fit GDP Proj'!$D$52) -> 0.016845152
A81: AEO | B81: ISIC 31T33 | C81: =IF($A81="AEO",'Growth Rates'!B74,'Growth Rates'!B74*'Rescale to Fit GDP Proj'!$D$52) -> 0 | D81: =IF($A81="AEO",'Growth Rates'!C74,'Growth Rates'!C74*'Rescale to Fit GDP Proj'!$D$52) -> -0.0019964133 | E81: =IF($A81="AEO",'Growth Rates'!D74,'Growth Rates'!D74*'Rescale to Fit GDP Proj'!$D$52) -> -0.014094172 | F81: =IF($A81="AEO",'Growth Rates'!E74,'Growth Rates'!E74*'Rescale to Fit GDP Proj'!$D$52) -> 0.0020814978 | G81: =IF($A81="AEO",'Growth Rates'!F74,'Growth Rates'!F74*'Rescale to Fit GDP Proj'!$D$52) -> 0.00556703 | H81: =IF($A81="AEO",'Growth Rates'!G74,'Growth Rates'!G74*'Rescale to Fit GDP Proj'!$D$52) -> 0.024824392 | I81: =IF($A81="AEO",'Growth Rates'!H74,'Growth Rates'!H74*'Rescale to Fit GDP Proj'!$D$52) -> 0.026832546 | J81: =IF($A81="AEO",'Growth Rates'!I74,'Growth Rates'!I74*'Rescale to Fit GDP Proj'!$D$52) -> 0.011196657 | ... AF81: =IF($A81="AEO",'Growth Rates'!AE74,'Growth Rates'!AE74*'Rescale to Fit GDP Proj'!$D$52) -> 0.029332026
B82: ISIC 351 | C82: =IF($A82="AEO",'Growth Rates'!B75,'Growth Rates'!B75*'Rescale to Fit GDP Proj'!$D$52) -> 0 | D82: =IF($A82="AEO",'Growth Rates'!C75,'Growth Rates'!C75*'Rescale to Fit GDP Proj'!$D$52) -> 0.016218 | E82: =IF($A82="AEO",'Growth Rates'!D75,'Growth Rates'!D75*'Rescale to Fit GDP Proj'!$D$52) -> 0.016218 | F82: =IF($A82="AEO",'Growth Rates'!E75,'Growth Rates'!E75*'Rescale to Fit GDP Proj'!$D$52) -> 0.016218 | G82: =IF($A82="AEO",'Growth Rates'!F75,'Growth Rates'!F75*'Rescale to Fit GDP Proj'!$D$52) -> 0.016218 | H82: =IF($A82="AEO",'Growth Rates'!G75,'Growth Rates'!G75*'Rescale to Fit GDP Proj'!$D$52) -> 0.016218 | I82: =IF($A82="AEO",'Growth Rates'!H75,'Growth Rates'!H75*'Rescale to Fit GDP Proj'!$D$52) -> 0.016218 | J82: =IF($A82="AEO",'Growth Rates'!I75,'Growth Rates'!I75*'Rescale to Fit GDP Proj'!$D$52) -> 0.016218 | ... AF82: =IF($A82="AEO",'Growth Rates'!AE75,'Growth Rates'!AE75*'Rescale to Fit GDP Proj'!$D$52) -> 0.016218
B83: ISIC 352T353 | C83: =IF($A83="AEO",'Growth Rates'!B76,'Growth Rates'!B76*'Rescale to Fit GDP Proj'!$D$52) -> 0 | D83: =IF($A83="AEO",'Growth Rates'!C76,'Growth Rates'!C76*'Rescale to Fit GDP Proj'!$D$52) -> 0.007632 | E83: =IF($A83="AEO",'Growth Rates'!D76,'Growth Rates'!D76*'Rescale to Fit GDP Proj'!$D$52) -> 0.007632 | F83: =IF($A83="AEO",'Growth Rates'!E76,'Growth Rates'!E76*'Rescale to Fit GDP Proj'!$D$52) -> 0.007632 | G83: =IF($A83="AEO",'Growth Rates'!F76,'Growth Rates'!F76*'Rescale to Fit GDP Proj'!$D$52) -> 0.007632 | H83: =IF($A83="AEO",'Growth Rates'!G76,'Growth Rates'!G76*'Rescale to Fit GDP Proj'!$D$52) -> 0.007632 | I83: =IF($A83="AEO",'Growth Rates'!H76,'Growth Rates'!H76*'Rescale to Fit GDP Proj'!$D$52) -> 0.007632 | J83: =IF($A83="AEO",'Growth Rates'!I76,'Growth Rates'!I76*'Rescale to Fit GDP Proj'!$D$52) -> 0.007632 | ... AF83: =IF($A83="AEO",'Growth Rates'!AE76,'Growth Rates'!AE76*'Rescale to Fit GDP Proj'!$D$52) -> 0.007632
B84: ISIC 36T39 | C84: =IF($A84="AEO",'Growth Rates'!B77,'Growth Rates'!B77*'Rescale to Fit GDP Proj'!$D$52) -> 0 | D84: =IF($A84="AEO",'Growth Rates'!C77,'Growth Rates'!C77*'Rescale to Fit GDP Proj'!$D$52) -> 0.015627135 | E84: =IF($A84="AEO",'Growth Rates'!D77,'Growth Rates'!D77*'Rescale to Fit GDP Proj'!$D$52) -> 0.015627135 | F84: =IF($A84="AEO",'Growth Rates'!E77,'Growth Rates'!E77*'Rescale to Fit GDP Proj'!$D$52) -> 0.015627135 | G84: =IF($A84="AEO",'Growth Rates'!F77,'Growth Rates'!F77*'Rescale to Fit GDP Proj'!$D$52) -> 0.015627135 | H84: =IF($A84="AEO",'Growth Rates'!G77,'Growth Rates'!G77*'Rescale to Fit GDP Proj'!$D$52) -> 0.015627135 | I84: =IF($A84="AEO",'Growth Rates'!H77,'Growth Rates'!H77*'Rescale to Fit GDP Proj'!$D$52) -> 0.015627135 | J84: =IF($A84="AEO",'Growth Rates'!I77,'Growth Rates'!I77*'Rescale to Fit GDP Proj'!$D$52) -> 0.015627135 | ... AF84: =IF($A84="AEO",'Growth Rates'!AE77,'Growth Rates'!AE77*'Rescale to Fit GDP Proj'!$D$52) -> 0.015627135
A85: AEO | B85: ISIC 41T43 | C85: =IF($A85="AEO",'Growth Rates'!B78,'Growth Rates'!B78*'Rescale to Fit GDP Proj'!$D$52) -> 0 | D85: =IF($A85="AEO",'Growth Rates'!C78,'Growth Rates'!C78*'Rescale to Fit GDP Proj'!$D$52) -> -0.024625473 | E85: =IF($A85="AEO",'Growth Rates'!D78,'Growth Rates'!D78*'Rescale to Fit GDP Proj'!$D$52) -> -0.021828573 | F85: =IF($A85="AEO",'Growth Rates'!E78,'Growth Rates'!E78*'Rescale to Fit GDP Proj'!$D$52) -> -0.0073988831 | G85: =IF($A85="AEO",'Growth Rates'!F78,'Growth Rates'!F78*'Rescale to Fit GDP Proj'!$D$52) -> 0.015912712 | H85: =IF($A85="AEO",'Growth Rates'!G78,'Growth Rates'!G78*'Rescale to Fit GDP Proj'!$D$52) -> 0.0098753134 | I85: =IF($A85="AEO",'Growth Rates'!H78,'Growth Rates'!H78*'Rescale to Fit GDP Proj'!$D$52) -> 0.00090595845 | J85: =IF($A85="AEO",'Growth Rates'!I78,'Growth Rates'!I78*'Rescale to Fit GDP Proj'!$D$52) -> 0.0076347149 | ... AF85: =IF($A85="AEO",'Growth Rates'!AE78,'Growth Rates'!AE78*'Rescale to Fit GDP Proj'!$D$52) -> 0.013232596
B86: ISIC 45T47 | C86: =IF($A86="AEO",'Growth Rates'!B79,'Growth Rates'!B79*'Rescale to Fit GDP Proj'!$D$52) -> 0 | D86: =IF($A86="AEO",'Growth Rates'!C79,'Growth Rates'!C79*'Rescale to Fit GDP Proj'!$D$52) -> 0.023870238 | E86: =IF($A86="AEO",'Growth Rates'!D79,'Growth Rates'!D79*'Rescale to Fit GDP Proj'!$D$52) -> 0.023870238 | F86: =IF($A86="AEO",'Growth Rates'!E79,'Growth Rates'!E79*'Rescale to Fit GDP Proj'!$D$52) -> 0.023870238 | G86: =IF($A86="AEO",'Growth Rates'!F79,'Growth Rates'!F79*'Rescale to Fit GDP Proj'!$D$52) -> 0.023870238 | H86: =IF($A86="AEO",'Growth Rates'!G79,'Growth Rates'!G79*'Rescale to Fit GDP Proj'!$D$52) -> 0.023870238 | I86: =IF($A86="AEO",'Growth Rates'!H79,'Growth Rates'!H79*'Rescale to Fit GDP Proj'!$D$52) -> 0.023870238 | J86: =IF($A86="AEO",'Growth Rates'!I79,'Growth Rates'!I79*'Rescale to Fit GDP Proj'!$D$52) -> 0.023870238 | ... AF86: =IF($A86="AEO",'Growth Rates'!AE79,'Growth Rates'!AE79*'Rescale to Fit GDP Proj'!$D$52) -> 0.023870238
B87: ISIC 49T53 | C87: =IF($A87="AEO",'Growth Rates'!B80,'Growth Rates'!B80*'Rescale to Fit GDP Proj'!$D$52) -> 0 | D87: =IF($A87="AEO",'Growth Rates'!C80,'Growth Rates'!C80*'Rescale to Fit GDP Proj'!$D$52) -> 0.015264 | E87: =IF($A87="AEO",'Growth Rates'!D80,'Growth Rates'!D80*'Rescale to Fit GDP Proj'!$D$52) -> 0.015264 | F87: =IF($A87="AEO",'Growth Rates'!E80,'Growth Rates'!E80*'Rescale to Fit GDP Proj'!$D$52) -> 0.015264 | G87: =IF($A87="AEO",'Growth Rates'!F80,'Growth Rates'!F80*'Rescale to Fit GDP Proj'!$D$52) -> 0.015264 | H87: =IF($A87="AEO",'Growth Rates'!G80,'Growth Rates'!G80*'Rescale to Fit GDP Proj'!$D$52) -> 0.015264 | I87: =IF($A87="AEO",'Growth Rates'!H80,'Growth Rates'!H80*'Rescale to Fit GDP Proj'!$D$52) -> 0.015264 | J87: =IF($A87="AEO",'Growth Rates'!I80,'Growth Rates'!I80*'Rescale to Fit GDP Proj'!$D$52) -> 0.015264 | ... AF87: =IF($A87="AEO",'Growth Rates'!AE80,'Growth Rates'!AE80*'Rescale to Fit GDP Proj'!$D$52) -> 0.015264
B88: ISIC 55T56 | C88: =IF($A88="AEO",'Growth Rates'!B81,'Growth Rates'!B81*'Rescale to Fit GDP Proj'!$D$52) -> 0 | D88: =IF($A88="AEO",'Growth Rates'!C81,'Growth Rates'!C81*'Rescale to Fit GDP Proj'!$D$52) -> 0.020034 | E88: =IF($A88="AEO",'Growth Rates'!D81,'Growth Rates'!D81*'Rescale to Fit GDP Proj'!$D$52) -> 0.020034 | F88: =IF($A88="AEO",'Growth Rates'!E81,'Growth Rates'!E81*'Rescale to Fit GDP Proj'!$D$52) -> 0.020034 | G88: =IF($A88="AEO",'Growth Rates'!F81,'Growth Rates'!F81*'Rescale to Fit GDP Proj'!$D$52) -> 0.020034 | H88: =IF($A88="AEO",'Growth Rates'!G81,'Growth Rates'!G81*'Rescale to Fit GDP Proj'!$D$52) -> 0.020034 | I88: =IF($A88="AEO",'Growth Rates'!H81,'Growth Rates'!H81*'Rescale to Fit GDP Proj'!$D$52) -> 0.020034 | J88: =IF($A88="AEO",'Growth Rates'!I81,'Growth Rates'!I81*'Rescale to Fit GDP Proj'!$D$52) -> 0.020034 | ... AF88: =IF($A88="AEO",'Growth Rates'!AE81,'Growth Rates'!AE81*'Rescale to Fit GDP Proj'!$D$52) -> 0.020034
B89: ISIC 58T60 | C89: =IF($A89="AEO",'Growth Rates'!B82,'Growth Rates'!B82*'Rescale to Fit GDP Proj'!$D$52) -> 0 | D89: =IF($A89="AEO",'Growth Rates'!C82,'Growth Rates'!C82*'Rescale to Fit GDP Proj'!$D$52) -> 0.02518547 | E89: =IF($A89="AEO",'Growth Rates'!D82,'Growth Rates'!D82*'Rescale to Fit GDP Proj'!$D$52) -> 0.02518547 | F89: =IF($A89="AEO",'Growth Rates'!E82,'Growth Rates'!E82*'Rescale to Fit GDP Proj'!$D$52) -> 0.02518547 | G89: =IF($A89="AEO",'Growth Rates'!F82,'Growth Rates'!F82*'Rescale to Fit GDP Proj'!$D$52) -> 0.02518547 | H89: =IF($A89="AEO",'Growth Rates'!G82,'Growth Rates'!G82*'Rescale to Fit GDP Proj'!$D$52) -> 0.02518547 | I89: =IF($A89="AEO",'Growth Rates'!H82,'Growth Rates'!H82*'Rescale to Fit GDP Proj'!$D$52) -> 0.02518547 | J89: =IF($A89="AEO",'Growth Rates'!I82,'Growth Rates'!I82*'Rescale to Fit GDP Proj'!$D$52) -> 0.02518547 | ... AF89: =IF($A89="AEO",'Growth Rates'!AE82,'Growth Rates'!AE82*'Rescale to Fit GDP Proj'!$D$52) -> 0.02518547
B90: ISIC 61 | C90: =IF($A90="AEO",'Growth Rates'!B83,'Growth Rates'!B83*'Rescale to Fit GDP Proj'!$D$52) -> 0 | D90: =IF($A90="AEO",'Growth Rates'!C83,'Growth Rates'!C83*'Rescale to Fit GDP Proj'!$D$52) -> 0.01908 | E90: =IF($A90="AEO",'Growth Rates'!D83,'Growth Rates'!D83*'Rescale to Fit GDP Proj'!$D$52) -> 0.01908 | F90: =IF($A90="AEO",'Growth Rates'!E83,'Growth Rates'!E83*'Rescale to Fit GDP Proj'!$D$52) -> 0.01908 | G90: =IF($A90="AEO",'Growth Rates'!F83,'Growth Rates'!F83*'Rescale to Fit GDP Proj'!$D$52) -> 0.01908 | H90: =IF($A90="AEO",'Growth Rates'!G83,'Growth Rates'!G83*'Rescale to Fit GDP Proj'!$D$52) -> 0.01908 | I90: =IF($A90="AEO",'Growth Rates'!H83,'Growth Rates'!H83*'Rescale to Fit GDP Proj'!$D$52) -> 0.01908 | J90: =IF($A90="AEO",'Growth Rates'!I83,'Growth Rates'!I83*'Rescale to Fit GDP Proj'!$D$52) -> 0.01908 | ... AF90: =IF($A90="AEO",'Growth Rates'!AE83,'Growth Rates'!AE83*'Rescale to Fit GDP Proj'!$D$52) -> 0.01908
B91: ISIC 62T63 | C91: =IF($A91="AEO",'Growth Rates'!B84,'Growth Rates'!B84*'Rescale to Fit GDP Proj'!$D$52) -> 0 | D91: =IF($A91="AEO",'Growth Rates'!C84,'Growth Rates'!C84*'Rescale to Fit GDP Proj'!$D$52) -> 0.03559361 | E91: =IF($A91="AEO",'Growth Rates'!D84,'Growth Rates'!D84*'Rescale to Fit GDP Proj'!$D$52) -> 0.03559361 | F91: =IF($A91="AEO",'Growth Rates'!E84,'Growth Rates'!E84*'Rescale to Fit GDP Proj'!$D$52) -> 0.03559361 | G91: =IF($A91="AEO",'Growth Rates'!F84,'Growth Rates'!F84*'Rescale to Fit GDP Proj'!$D$52) -> 0.03559361 | H91: =IF($A91="AEO",'Growth Rates'!G84,'Growth Rates'!G84*'Rescale to Fit GDP Proj'!$D$52) -> 0.03559361 | I91: =IF($A91="AEO",'Growth Rates'!H84,'Growth Rates'!H84*'Rescale to Fit GDP Proj'!$D$52) -> 0.03559361 | J91: =IF($A91="AEO",'Growth Rates'!I84,'Growth Rates'!I84*'Rescale to Fit GDP Proj'!$D$52) -> 0.03559361 | ... AF91: =IF($A91="AEO",'Growth Rates'!AE84,'Growth Rates'!AE84*'Rescale to Fit GDP Proj'!$D$52) -> 0.03559361
B92: ISIC 64T66 | C92: =IF($A92="AEO",'Growth Rates'!B85,'Growth Rates'!B85*'Rescale to Fit GDP Proj'!$D$52) -> 0 | D92: =IF($A92="AEO",'Growth Rates'!C85,'Growth Rates'!C85*'Rescale to Fit GDP Proj'!$D$52) -> 0.013356 | E92: =IF($A92="AEO",'Growth Rates'!D85,'Growth Rates'!D85*'Rescale to Fit GDP Proj'!$D$52) -> 0.013356 | F92: =IF($A92="AEO",'Growth Rates'!E85,'Growth Rates'!E85*'Rescale to Fit GDP Proj'!$D$52) -> 0.013356 | G92: =IF($A92="AEO",'Growth Rates'!F85,'Growth Rates'!F85*'Rescale to Fit GDP Proj'!$D$52) -> 0.013356 | H92: =IF($A92="AEO",'Growth Rates'!G85,'Growth Rates'!G85*'Rescale to Fit GDP Proj'!$D$52) -> 0.013356 | I92: =IF($A92="AEO",'Growth Rates'!H85,'Growth Rates'!H85*'Rescale to Fit GDP Proj'!$D$52) -> 0.013356 | J92: =IF($A92="AEO",'Growth Rates'!I85,'Growth Rates'!I85*'Rescale to Fit GDP Proj'!$D$52) -> 0.013356 | ... AF92: =IF($A92="AEO",'Growth Rates'!AE85,'Growth Rates'!AE85*'Rescale to Fit GDP Proj'!$D$52) -> 0.013356
B93: ISIC 68 | C93: =IF($A93="AEO",'Growth Rates'!B86,'Growth Rates'!B86*'Rescale to Fit GDP Proj'!$D$52) -> 0 | D93: =IF($A93="AEO",'Growth Rates'!C86,'Growth Rates'!C86*'Rescale to Fit GDP Proj'!$D$52) -> 0.018126 | E93: =IF($A93="AEO",'Growth Rates'!D86,'Growth Rates'!D86*'Rescale to Fit GDP Proj'!$D$52) -> 0.018126 | F93: =IF($A93="AEO",'Growth Rates'!E86,'Growth Rates'!E86*'Rescale to Fit GDP Proj'!$D$52) -> 0.018126 | G93: =IF($A93="AEO",'Growth Rates'!F86,'Growth Rates'!F86*'Rescale to Fit GDP Proj'!$D$52) -> 0.018126 | H93: =IF($A93="AEO",'Growth Rates'!G86,'Growth Rates'!G86*'Rescale to Fit GDP Proj'!$D$52) -> 0.018126 | I93: =IF($A93="AEO",'Growth Rates'!H86,'Growth Rates'!H86*'Rescale to Fit GDP Proj'!$D$52) -> 0.018126 | J93: =IF($A93="AEO",'Growth Rates'!I86,'Growth Rates'!I86*'Rescale to Fit GDP Proj'!$D$52) -> 0.018126 | ... AF93: =IF($A93="AEO",'Growth Rates'!AE86,'Growth Rates'!AE86*'Rescale to Fit GDP Proj'!$D$52) -> 0.018126
B94: ISIC 69T82 | C94: =IF($A94="AEO",'Growth Rates'!B87,'Growth Rates'!B87*'Rescale to Fit GDP Proj'!$D$52) -> 0 | D94: =IF($A94="AEO",'Growth Rates'!C87,'Growth Rates'!C87*'Rescale to Fit GDP Proj'!$D$52) -> 0.021515917 | E94: =IF($A94="AEO",'Growth Rates'!D87,'Growth Rates'!D87*'Rescale to Fit GDP Proj'!$D$52) -> 0.021515917 | F94: =IF($A94="AEO",'Growth Rates'!E87,'Growth Rates'!E87*'Rescale to Fit GDP Proj'!$D$52) -> 0.021515917 | G94: =IF($A94="AEO",'Growth Rates'!F87,'Growth Rates'!F87*'Rescale to Fit GDP Proj'!$D$52) -> 0.021515917 | H94: =IF($A94="AEO",'Growth Rates'!G87,'Growth Rates'!G87*'Rescale to Fit GDP Proj'!$D$52) -> 0.021515917 | I94: =IF($A94="AEO",'Growth Rates'!H87,'Growth Rates'!H87*'Rescale to Fit GDP Proj'!$D$52) -> 0.021515917 | J94: =IF($A94="AEO",'Growth Rates'!I87,'Growth Rates'!I87*'Rescale to Fit GDP Proj'!$D$52) -> 0.021515917 | ... AF94: =IF($A94="AEO",'Growth Rates'!AE87,'Growth Rates'!AE87*'Rescale to Fit GDP Proj'!$D$52) -> 0.021515917
B95: ISIC 84 | C95: =IF($A95="AEO",'Growth Rates'!B88,'Growth Rates'!B88*'Rescale to Fit GDP Proj'!$D$52) -> 0 | D95: =IF($A95="AEO",'Growth Rates'!C88,'Growth Rates'!C88*'Rescale to Fit GDP Proj'!$D$52) -> 0.0072006424 | E95: =IF($A95="AEO",'Growth Rates'!D88,'Growth Rates'!D88*'Rescale to Fit GDP Proj'!$D$52) -> 0.0072006424 | F95: =IF($A95="AEO",'Growth Rates'!E88,'Growth Rates'!E88*'Rescale to Fit GDP Proj'!$D$52) -> 0.0072006424 | G95: =IF($A95="AEO",'Growth Rates'!F88,'Growth Rates'!F88*'Rescale to Fit GDP Proj'!$D$52) -> 0.0072006424 | H95: =IF($A95="AEO",'Growth Rates'!G88,'Growth Rates'!G88*'Rescale to Fit GDP Proj'!$D$52) -> 0.0072006424 | I95: =IF($A95="AEO",'Growth Rates'!H88,'Growth Rates'!H88*'Rescale to Fit GDP Proj'!$D$52) -> 0.0072006424 | J95: =IF($A95="AEO",'Growth Rates'!I88,'Growth Rates'!I88*'Rescale to Fit GDP Proj'!$D$52) -> 0.0072006424 | ... AF95: =IF($A95="AEO",'Growth Rates'!AE88,'Growth Rates'!AE88*'Rescale to Fit GDP Proj'!$D$52) -> 0.0072006424
B96: ISIC 85 | C96: =IF($A96="AEO",'Growth Rates'!B89,'Growth Rates'!B89*'Rescale to Fit GDP Proj'!$D$52) -> 0 | D96: =IF($A96="AEO",'Growth Rates'!C89,'Growth Rates'!C89*'Rescale to Fit GDP Proj'!$D$52) -> 0.016218 | E96: =IF($A96="AEO",'Growth Rates'!D89,'Growth Rates'!D89*'Rescale to Fit GDP Proj'!$D$52) -> 0.016218 | F96: =IF($A96="AEO",'Growth Rates'!E89,'Growth Rates'!E89*'Rescale to Fit GDP Proj'!$D$52) -> 0.016218 | G96: =IF($A96="AEO",'Growth Rates'!F89,'Growth Rates'!F89*'Rescale to Fit GDP Proj'!$D$52) -> 0.016218 | H96: =IF($A96="AEO",'Growth Rates'!G89,'Growth Rates'!G89*'Rescale to Fit GDP Proj'!$D$52) -> 0.016218 | I96: =IF($A96="AEO",'Growth Rates'!H89,'Growth Rates'!H89*'Rescale to Fit GDP Proj'!$D$52) -> 0.016218 | J96: =IF($A96="AEO",'Growth Rates'!I89,'Growth Rates'!I89*'Rescale to Fit GDP Proj'!$D$52) -> 0.016218 | ... AF96: =IF($A96="AEO",'Growth Rates'!AE89,'Growth Rates'!AE89*'Rescale to Fit GDP Proj'!$D$52) -> 0.016218
B97: ISIC 86T88 | C97: =IF($A97="AEO",'Growth Rates'!B90,'Growth Rates'!B90*'Rescale to Fit GDP Proj'!$D$52) -> 0 | D97: =IF($A97="AEO",'Growth Rates'!C90,'Growth Rates'!C90*'Rescale to Fit GDP Proj'!$D$52) -> 0.027666 | E97: =IF($A97="AEO",'Growth Rates'!D90,'Growth Rates'!D90*'Rescale to Fit GDP Proj'!$D$52) -> 0.027666 | F97: =IF($A97="AEO",'Growth Rates'!E90,'Growth Rates'!E90*'Rescale to Fit GDP Proj'!$D$52) -> 0.027666 | G97: =IF($A97="AEO",'Growth Rates'!F90,'Growth Rates'!F90*'Rescale to Fit GDP Proj'!$D$52) -> 0.027666 | H97: =IF($A97="AEO",'Growth Rates'!G90,'Growth Rates'!G90*'Rescale to Fit GDP Proj'!$D$52) -> 0.027666 | I97: =IF($A97="AEO",'Growth Rates'!H90,'Growth Rates'!H90*'Rescale to Fit GDP Proj'!$D$52) -> 0.027666 | J97: =IF($A97="AEO",'Growth Rates'!I90,'Growth Rates'!I90*'Rescale to Fit GDP Proj'!$D$52) -> 0.027666 | ... AF97: =IF($A97="AEO",'Growth Rates'!AE90,'Growth Rates'!AE90*'Rescale to Fit GDP Proj'!$D$52) -> 0.027666
... B99: ISIC 97T98 | C99: =IF($A99="AEO",'Growth Rates'!B92,'Growth Rates'!B92*'Rescale to Fit GDP Proj'!$D$52) -> 0 | D99: =IF($A99="AEO",'Growth Rates'!C92,'Growth Rates'!C92*'Rescale to Fit GDP Proj'!$D$52) -> 0.016218 | E99: =IF($A99="AEO",'Growth Rates'!D92,'Growth Rates'!D92*'Rescale to Fit GDP Proj'!$D$52) -> 0.016218 | F99: =IF($A99="AEO",'Growth Rates'!E92,'Growth Rates'!E92*'Rescale to Fit GDP Proj'!$D$52) -> 0.016218 | G99: =IF($A99="AEO",'Growth Rates'!F92,'Growth Rates'!F92*'Rescale to Fit GDP Proj'!$D$52) -> 0.016218 | H99: =IF($A99="AEO",'Growth Rates'!G92,'Growth Rates'!G92*'Rescale to Fit GDP Proj'!$D$52) -> 0.016218 | I99: =IF($A99="AEO",'Growth Rates'!H92,'Growth Rates'!H92*'Rescale to Fit GDP Proj'!$D$52) -> 0.016218 | J99: =IF($A99="AEO",'Growth Rates'!I92,'Growth Rates'!I92*'Rescale to Fit GDP Proj'!$D$52) -> 0.016218 | ... AF99: =IF($A99="AEO",'Growth Rates'!AE92,'Growth Rates'!AE92*'Rescale to Fit GDP Proj'!$D$52) -> 0.016218
A101: Scaled Compounded Growth Relative to Start Year Data
C102: 2021 | D102: 2022 | E102: 2023 | F102: 2024 | G102: 2025 | H102: 2026 | I102: 2027 | J102: 2028 | K102: 2029 | L102: 2030 | M102: 2031 | N102: 2032 | O102: 2033 | P102: 2034 | Q102: 2035 | R102: 2036 | S102: 2037 | T102: 2038 | U102: 2039 | V102: 2040 | W102: 2041 | X102: 2042 | Y102: 2043 | Z102: 2044 | AA102: 2045 | AB102: 2046 | AC102: 2047 | AD102: 2048 | AE102: 2049 | AF102: 2050
A103: AEO | B103: ISIC 01T03 | C103: =IF($A103="AEO",'Growth Rates'!B96,'Growth Rates'!B96*'Rescale to Fit GDP Proj'!$D$52) -> 0 | D103: =D58 -> -1.1176675e-07 | E103: =(1+D103)*(1+E58)-1 -> -0.0013512564 | F103: =(1+E103)*(1+F58)-1 -> 0.0077691342 | G103: =(1+F103)*(1+G58)-1 -> 0.021269504 | H103: =(1+G103)*(1+H58)-1 -> 0.036882702 | I103: =(1+H103)*(1+I58)-1 -> 0.050786671 | J103: =(1+I103)*(1+J58)-1 -> 0.063107111 | K103: =(1+J103)*(1+K58)-1 -> 0.073893339 | L103: =(1+K103)*(1+L58)-1 -> 0.083552866 | ... AF103: =(1+AE103)*(1+AF58)-1 -> 0.24947923
A104: AEO | B104: ISIC 05 | C104: =IF($A104="AEO",'Growth Rates'!B97,'Growth Rates'!B97*'Rescale to Fit GDP Proj'!$D$52) -> 0 | D104: =D59 -> -0.01752763 | E104: =(1+D104)*(1+E59)-1 -> -0.072509825 | F104: =(1+E104)*(1+F59)-1 -> 0.013901381 | G104: =(1+F104)*(1+G59)-1 -> -0.048139339 | H104: =(1+G104)*(1+H59)-1 -> -0.12927523 | I104: =(1+H104)*(1+I59)-1 -> -0.21940144 | J104: =(1+I104)*(1+J59)-1 -> -0.29942283 | K104: =(1+J104)*(1+K59)-1 -> -0.37465184 | L104: =(1+K104)*(1+L59)-1 -> -0.40578365 | ... AF104: =(1+AE104)*(1+AF59)-1 -> -0.49969918
A105: AEO | B105: ISIC 06 | C105: =IF($A105="AEO",'Growth Rates'!B98,'Growth Rates'!B98*'Rescale to Fit GDP Proj'!$D$52) -> 0 | D105: =D60 -> 0.003135583 | E105: =(1+D105)*(1+E60)-1 -> -0.024884865 | F105: =(1+E105)*(1+F60)-1 -> -0.025153396 | G105: =(1+F105)*(1+G60)-1 -> -0.017702073 | H105: =(1+G105)*(1+H60)-1 -> -0.0045601513 | I105: =(1+H105)*(1+I60)-1 -> -0.0028910806 | J105: =(1+I105)*(1+J60)-1 -> 0.0052098616 | K105: =(1+J105)*(1+K60)-1 -> 0.0062325291 | L105: =(1+K105)*(1+L60)-1 -> 0.011170598 | ... AF105: =(1+AE105)*(1+AF60)-1 -> 0.091207199
A106: AEO | B106: ISIC 07T08 | C106: =IF($A106="AEO",'Growth Rates'!B99,'Growth Rates'!B99*'Rescale to Fit GDP Proj'!$D$52) -> 0 | D106: =D61 -> -0.00028519755 | E106: =(1+D106)*(1+E61)-1 -> -0.024457489 | F106: =(1+E106)*(1+F61)-1 -> -0.046807819 | G106: =(1+F106)*(1+G61)-1 -> -0.059478105 | H106: =(1+G106)*(1+H61)-1 -> -0.073135867 | I106: =(1+H106)*(1+I61)-1 -> -0.091091235 | J106: =(1+I106)*(1+J61)-1 -> -0.10238462 | K106: =(1+J106)*(1+K61)-1 -> -0.10691866 | L106: =(1+K106)*(1+L61)-1 -> -0.11175868 | ... AF106: =(1+AE106)*(1+AF61)-1 -> -0.0082684515
B107: ISIC 09 | C107: =IF($A107="AEO",'Growth Rates'!B100,'Growth Rates'!B100*'Rescale to Fit GDP Proj'!$D$52) -> 0 | D107: =D62 -> 0.027666 | E107: =(1+D107)*(1+E62)-1 -> 0.056097408 | F107: =(1+E107)*(1+F62)-1 -> 0.085315398 | G107: =(1+F107)*(1+G62)-1 -> 0.11534173 | H107: =(1+G107)*(1+H62)-1 -> 0.14619878 | I107: =(1+H107)*(1+I62)-1 -> 0.17790951 | J107: =(1+I107)*(1+J62)-1 -> 0.21049756 | K107: =(1+J107)*(1+K62)-1 -> 0.24398718 | L107: =(1+K107)*(1+L62)-1 -> 0.27840333 | ... AF107: =(1+AE107)*(1+AF62)-1 -> 1.2065189
A108: AEO | B108: ISIC 10T12 | C108: =IF($A108="AEO",'Growth Rates'!B101,'Growth Rates'!B101*'Rescale to Fit GDP Proj'!$D$52) -> 0 | D108: =D63 -> -0.012463136 | E108: =(1+D108)*(1+E63)-1 -> 0.0029431604 | F108: =(1+E108)*(1+F63)-1 -> 0.013008426 | G108: =(1+F108)*(1+G63)-1 -> 0.022346318 | H108: =(1+G108)*(1+H63)-1 -> 0.0355333 | I108: =(1+H108)*(1+I63)-1 -> 0.050185159 | J108: =(1+I108)*(1+J63)-1 -> 0.064933031 | K108: =(1+J108)*(1+K63)-1 -> 0.077722495 | L108: =(1+K108)*(1+L63)-1 -> 0.090396384 | ... AF108: =(1+AE108)*(1+AF63)-1 -> 0.33546369
A109: AEO | B109: ISIC 13T15 | C109: =IF($A109="AEO",'Growth Rates'!B102,'Growth Rates'!B102*'Rescale to Fit GDP Proj'!$D$52) -> 0 | D109: =D64 -> -0.00049111462 | E109: =(1+D109)*(1+E64)-1 -> -0.015775364 | F109: =(1+E109)*(1+F64)-1 -> -0.025776803 | G109: =(1+F109)*(1+G64)-1 -> -0.02535646 | H109: =(1+G109)*(1+H64)-1 -> -0.0069735339 | I109: =(1+H109)*(1+I64)-1 -> 0.015721738 | J109: =(1+I109)*(1+J64)-1 -> 0.031601266 | K109: =(1+J109)*(1+K64)-1 -> 0.038425118 | L109: =(1+K109)*(1+L64)-1 -> 0.040028255 | ... AF109: =(1+AE109)*(1+AF64)-1 -> -0.033305149
...

Sheet Growth Rates
A1: BLS Data | F1: EIA AEO Data | G1: 3 | H1: 4 | I1: 5 | J1: 6 | K1: 7 | L1: 8 | M1: 9 | N1: 10 | O1: 11 | P1: 12 | Q1: 13 | R1: 14 | S1: 15 | T1: 16 | U1: 17 | V1: 18 | W1: 19 | X1: 20 | Y1: 21 | Z1: 22 | AA1: 23 | AB1: 24 | AC1: 25 | AD1: 26 | AE1: 27 | AF1: 28 | AG1: 29 | AH1: 30 | AI1: 31
B2: Compound Growth Rate (output-weighted average of components of each ISIC code)
B3: 2019-2029 | F3: 2022-2050 | G3: 2022 | H3: 2023 | I3: 2024 | J3: 2025 | K3: 2026 | L3: 2027 | M3: 2028 | N3: 2029 | O3: 2030 | P3: 2031 | Q3: 2032 | R3: 2033 | S3: 2034 | T3: 2035 | U3: 2036 | V3: 2037 | W3: 2038 | X3: 2039 | Y3: 2040 | Z3: 2041 | AA3: 2042 | AB3: 2043 | AC3: 2044 | AD3: 2045 | AE3: 2046 | AF3: 2047 | AG3: 2048 | AH3: 2049 | AI3: 2050
A4: ISIC 01T03 | B4: {=SUMPRODUCT(--('BLS Table 2.7'!$O:$O=$A4),'BLS Table 2.7'!L:L,'BLS Table 2.7'!N:N)/SUMIFS('BLS Table 2.7'!L:L,'BLS Table 2.7'!$O:$O,$A4)/100} -> 0.018 | E4: ISIC 01T03 | F4: =IFERROR(INDEX('AEO23 Table 23'!$AG$22:$AG$61,MATCH($E4,'AEO23 Table 23'!$B$22:$B$61,0),1),"") -> 0.007986 | G4: =(INDEX('AEO23 Table 23'!$D$22:$D$61,MATCH('Growth Rates'!E4,'AEO23 Table 23'!$B$22:$B$61,0))-INDEX('AEO22 Table 23'!$D$22:$D$58,MATCH('Growth Rates'!E4,'AEO22 Table 23'!$B$22:$B$58,0)))/INDEX('AEO22 Table 23'!$D$22:$D$58,MATCH('Growth Rates'!E4,'AEO22 Table 23'!$B$22:$B$58,0)) -> -1.1176675e-07 | H4: =IFERROR((VLOOKUP($E4,'AEO23 Table 23'!$B$13:$AF$61,H$1,FALSE)-(VLOOKUP($E4,'AEO23 Table 23'!$B$13:$AF$61,G$1,FALSE)))/VLOOKUP($E4,'AEO23 Table 23'!$B$13:$AF$61,G$1,FALSE),"") -> -0.0013511448 | I4: =IFERROR((VLOOKUP($E4,'AEO23 Table 23'!$B$13:$AF$61,I$1,FALSE)-(VLOOKUP($E4,'AEO23 Table 23'!$B$13:$AF$61,H$1,FALSE)))/VLOOKUP($E4,'AEO23 Table 23'!$B$13:$AF$61,H$1,FALSE),"") -> 0.0091327312 | J4: =IFERROR((VLOOKUP($E4,'AEO23 Table 23'!$B$13:$AF$61,J$1,FALSE)-(VLOOKUP($E4,'AEO23 Table 23'!$B$13:$AF$61,I$1,FALSE)))/VLOOKUP($E4,'AEO23 Table 23'!$B$13:$AF$61,I$1,FALSE),"") -> 0.013396293 | K4: =IFERROR((VLOOKUP($E4,'AEO23 Table 23'!$B$13:$AF$61,K$1,FALSE)-(VLOOKUP($E4,'AEO23 Table 23'!$B$13:$AF$61,J$1,FALSE)))/VLOOKUP($E4,'AEO23 Table 23'!$B$13:$AF$61,J$1,FALSE),"") -> 0.015288029 | L4: =IFERROR((VLOOKUP($E4,'AEO23 Table 23'!$B$13:$AF$61,L$1,FALSE)-(VLOOKUP($E4,'AEO23 Table 23'!$B$13:$AF$61,K$1,FALSE)))/VLOOKUP($E4,'AEO23 Table 23'!$B$13:$AF$61,K$1,FALSE),"") -> 0.013409394 | M4: =IFERROR((VLOOKUP($E4,'AEO23 Table 23'!$B$13:$AF$61,M$1,FALSE)-(VLOOKUP($E4,'AEO23 Table 23'!$B$13:$AF$61,L$1,FALSE)))/VLOOKUP($E4,'AEO23 Table 23'!$B$13:$AF$61,L$1,FALSE),"") -> 0.011724967 | N4: =IFERROR((VLOOKUP($E4,'AEO23 Table 23'!$B$13:$AF$61,N$1,FALSE)-(VLOOKUP($E4,'AEO23 Table 23'!$B$13:$AF$61,M$1,FALSE)))/VLOOKUP($E4,'AEO23 Table 23'!$B$13:$AF$61,M$1,FALSE),"") -> 0.010145947 | O4: =IFERROR((VLOOKUP($E4,'AEO23 Table 23'!$B$13:$AF$61,O$1,FALSE)-(VLOOKUP($E4,'AEO23 Table 23'!$B$13:$AF$61,N$1,FALSE)))/VLOOKUP($E4,'AEO23 Table 23'!$B$13:$AF$61,N$1,FALSE),"") -> 0.0089948669 | ... AI4: =IFERROR((VLOOKUP($E4,'AEO23 Table 23'!$B$13:$AF$61,AI$1,FALSE)-(VLOOKUP($E4,'AEO23 Table 23'!$B$13:$AF$61,AH$1,FALSE)))/VLOOKUP($E4,'AEO23 Table 23'!$B$13:$AF$61,AH$1,FALSE),"") -> 0.0062089547
A5: ISIC 05 | B5: {=SUMPRODUCT(--('BLS Table 2.7'!$O:$O=$A5),'BLS Table 2.7'!L:L,'BLS Table 2.7'!N:N)/SUMIFS('BLS Table 2.7'!L:L,'BLS Table 2.7'!$O:$O,$A5)/100} -> -0.002 | E5: ISIC 05 | F5: =IFERROR(INDEX('AEO23 Table 23'!$AG$22:$AG$61,MATCH($E5,'AEO23 Table 23'!$B$22:$B$61,0)),"") -> -0.01752763 | G5: =F5 -> -0.01752763 | H5: =IFERROR((VLOOKUP($E5,'AEO23 Table 23'!$B$13:$AF$61,H$1,FALSE)-(VLOOKUP($E5,'AEO23 Table 23'!$B$13:$AF$61,G$1,FALSE)))/VLOOKUP($E5,'AEO23 Table 23'!$B$13:$AF$61,G$1,FALSE),"") -> -0.055963095 | I5: =IFERROR((VLOOKUP($E5,'AEO23 Table 23'!$B$13:$AF$61,I$1,FALSE)-(VLOOKUP($E5,'AEO23 Table 23'!$B$13:$AF$61,H$1,FALSE)))/VLOOKUP($E5,'AEO23 Table 23'!$B$13:$AF$61,H$1,FALSE),"") -> 0.093166707 | J5: =IFERROR((VLOOKUP($E5,'AEO23 Table 23'!$B$13:$AF$61,J$1,FALSE)-(VLOOKUP($E5,'AEO23 Table 23'!$B$13:$AF$61,I$1,FALSE)))/VLOOKUP($E5,'AEO23 Table 23'!$B$13:$AF$61,I$1,FALSE),"") -> -0.061190092 | K5: =IFERROR((VLOOKUP($E5,'AEO23 Table 23'!$B$13:$AF$61,K$1,FALSE)-(VLOOKUP($E5,'AEO23 Table 23'!$B$13:$AF$61,J$1,FALSE)))/VLOOKUP($E5,'AEO23 Table 23'!$B$13:$AF$61,J$1,FALSE),"") -> -0.085239248 | L5: =IFERROR((VLOOKUP($E5,'AEO23 Table 23'!$B$13:$AF$61,L$1,FALSE)-(VLOOKUP($E5,'AEO23 Table 23'!$B$13:$AF$61,K$1,FALSE)))/VLOOKUP($E5,'AEO23 Table 23'!$B$13:$AF$61,K$1,FALSE),"") -> -0.10350713 | M5: =IFERROR((VLOOKUP($E5,'AEO23 Table 23'!$B$13:$AF$61,M$1,FALSE)-(VLOOKUP($E5,'AEO23 Table 23'!$B$13:$AF$61,L$1,FALSE)))/VLOOKUP($E5,'AEO23 Table 23'!$B$13:$AF$61,L$1,FALSE),"") -> -0.10251285 | N5: =IFERROR((VLOOKUP($E5,'AEO23 Table 23'!$B$13:$AF$61,N$1,FALSE)-(VLOOKUP($E5,'AEO23 Table 23'!$B$13:$AF$61,M$1,FALSE)))/VLOOKUP($E5,'AEO23 Table 23'!$B$13:$AF$61,M$1,FALSE),"") -> -0.10738148 | O5: =IFERROR((VLOOKUP($E5,'AEO23 Table 23'!$B$13:$AF$61,O$1,FALSE)-(VLOOKUP($E5,'AEO23 Table 23'!$B$13:$AF$61,N$1,FALSE)))/VLOOKUP($E5,'AEO23 Table 23'!$B$13:$AF$61,N$1,FALSE),"") -> -0.049783164 | ... AI5: =IFERROR((VLOOKUP($E5,'AEO23 Table 23'!$B$13:$AF$61,AI$1,FALSE)-(VLOOKUP($E5,'AEO23 Table 23'!$B$13:$AF$61,AH$1,FALSE)))/VLOOKUP($E5,'AEO23 Table 23'!$B$13:$AF$61,AH$1,FALSE),"") -> -0.014273166
A6: ISIC 06 | B6: {=SUMPRODUCT(--('BLS Table 2.7'!$O:$O=$A6),'BLS Table 2.7'!L:L,'BLS Table 2.7'!N:N)/SUMIFS('BLS Table 2.7'!L:L,'BLS Table 2.7'!$O:$O,$A6)/100} -> 0.034 | E6: ISIC 06 | F6: =IFERROR(INDEX('AEO23 Table 23'!$AG$22:$AG$61,MATCH($E6,'AEO23 Table 23'!$B$22:$B$61,0)),"") -> 0.003135583 | G6: =F6 -> 0.003135583 | H6: =IFERROR((VLOOKUP($E6,'AEO23 Table 23'!$B$13:$AF$61,H$1,FALSE)-(VLOOKUP($E6,'AEO23 Table 23'!$B$13:$AF$61,G$1,FALSE)))/VLOOKUP($E6,'AEO23 Table 23'!$B$13:$AF$61,G$1,FALSE),"") -> -0.027932862 | I6: =IFERROR((VLOOKUP($E6,'AEO23 Table 23'!$B$13:$AF$61,I$1,FALSE)-(VLOOKUP($E6,'AEO23 Table 23'!$B$13:$AF$61,H$1,FALSE)))/VLOOKUP($E6,'AEO23 Table 23'!$B$13:$AF$61,H$1,FALSE),"") -> -0.00027538352 | J6: =IFERROR((VLOOKUP($E6,'AEO23 Table 23'!$B$13:$AF$61,J$1,FALSE)-(VLOOKUP($E6,'AEO23 Table 23'!$B$13:$AF$61,I$1,FALSE)))/VLOOKUP($E6,'AEO23 Table 23'!$B$13:$AF$61,I$1,FALSE),"") -> 0.0076435853 | K6: =IFERROR((VLOOKUP($E6,'AEO23 Table 23'!$B$13:$AF$61,K$1,FALSE)-(VLOOKUP($E6,'AEO23 Table 23'!$B$13:$AF$61,J$1,FALSE)))/VLOOKUP($E6,'AEO23 Table 23'!$B$13:$AF$61,J$1,FALSE),"") -> 0.013378753 | L6: =IFERROR((VLOOKUP($E6,'AEO23 Table 23'!$B$13:$AF$61,L$1,FALSE)-(VLOOKUP($E6,'AEO23 Table 23'!$B$13:$AF$61,K$1,FALSE)))/VLOOKUP($E6,'AEO23 Table 23'!$B$13:$AF$61,K$1,FALSE),"") -> 0.0016767167 | M6: =IFERROR((VLOOKUP($E6,'AEO23 Table 23'!$B$13:$AF$61,M$1,FALSE)-(VLOOKUP($E6,'AEO23 Table 23'!$B$13:$AF$61,L$1,FALSE)))/VLOOKUP($E6,'AEO23 Table 23'!$B$13:$AF$61,L$1,FALSE),"") -> 0.0081244305 | N6: =IFERROR((VLOOKUP($E6,'AEO23 Table 23'!$B$13:$AF$61,N$1,FALSE)-(VLOOKUP($E6,'AEO23 Table 23'!$B$13:$AF$61,M$1,FALSE)))/VLOOKUP($E6,'AEO23 Table 23'!$B$13:$AF$61,M$1,FALSE),"") -> 0.0010173672 | O6: =IFERROR((VLOOKUP($E6,'AEO23 Table 23'!$B$13:$AF$61,O$1,FALSE)-(VLOOKUP($E6,'AEO23 Table 23'!$B$13:$AF$61,N$1,FALSE)))/VLOOKUP($E6,'AEO23 Table 23'!$B$13:$AF$61,N$1,FALSE),"") -> 0.0049074833 | ... AI6: =IFERROR((VLOOKUP($E6,'AEO23 Table 23'!$B$13:$AF$61,AI$1,FALSE)-(VLOOKUP($E6,'AEO23 Table 23'!$B$13:$AF$61,AH$1,FALSE)))/VLOOKUP($E6,'AEO23 Table 23'!$B$13:$AF$61,AH$1,FALSE),"") -> 0.0050993658
A7: ISIC 07T08 | B7: {=SUMPRODUCT(--('BLS Table 2.7'!$O:$O=$A7),'BLS Table 2.7'!L:L,'BLS Table 2.7'!N:N)/SUMIFS('BLS Table 2.7'!L:L,'BLS Table 2.7'!$O:$O,$A7)/100} -> 0.010045584 | E7: ISIC 07T08 | F7: =IFERROR(INDEX('AEO23 Table 23'!$AG$22:$AG$61,MATCH($E7,'AEO23 Table 23'!$B$22:$B$61,0)),"") -> -0.00028519755 | G7: =F7 -> -0.00028519755 | H7: =IFERROR((VLOOKUP($E7,'AEO23 Table 23'!$B$13:$AF$61,H$1,FALSE)-(VLOOKUP($E7,'AEO23 Table 23'!$B$13:$AF$61,G$1,FALSE)))/VLOOKUP($E7,'AEO23 Table 23'!$B$13:$AF$61,G$1,FALSE),"") -> -0.024179188 | I7: =IFERROR((VLOOKUP($E7,'AEO23 Table 23'!$B$13:$AF$61,I$1,FALSE)-(VLOOKUP($E7,'AEO23 Table 23'!$B$13:$AF$61,H$1,FALSE)))/VLOOKUP($E7,'AEO23 Table 23'!$B$13:$AF$61,H$1,FALSE),"") -> -0.022910667 | J7: =IFERROR((VLOOKUP($E7,'AEO23 Table 23'!$B$13:$AF$61,J$1,FALSE)-(VLOOKUP($E7,'AEO23 Table 23'!$B$13:$AF$61,I$1,FALSE)))/VLOOKUP($E7,'AEO23 Table 23'!$B$13:$AF$61,I$1,FALSE),"") -> -0.013292478 | K7: =IFERROR((VLOOKUP($E7,'AEO23 Table 23'!$B$13:$AF$61,K$1,FALSE)-(VLOOKUP($E7,'AEO23 Table 23'!$B$13:$AF$61,J$1,FALSE)))/VLOOKUP($E7,'AEO23 Table 23'!$B$13:$AF$61,J$1,FALSE),"") -> -0.014521472 | L7: =IFERROR((VLOOKUP($E7,'AEO23 Table 23'!$B$13:$AF$61,L$1,FALSE)-(VLOOKUP($E7,'AEO23 Table 23'!$B$13:$AF$61,K$1,FALSE)))/VLOOKUP($E7,'AEO23 Table 23'!$B$13:$AF$61,K$1,FALSE),"") -> -0.019372168 | M7: =IFERROR((VLOOKUP($E7,'AEO23 Table 23'!$B$13:$AF$61,M$1,FALSE)-(VLOOKUP($E7,'AEO23 Table 23'!$B$13:$AF$61,L$1,FALSE)))/VLOOKUP($E7,'AEO23 Table 23'!$B$13:$AF$61,L$1,FALSE),"") -> -0.012425212 | N7: =IFERROR((VLOOKUP($E7,'AEO23 Table 23'!$B$13:$AF$61,N$1,FALSE)-(VLOOKUP($E7,'AEO23 Table 23'!$B$13:$AF$61,M$1,FALSE)))/VLOOKUP($E7,'AEO23 Table 23'!$B$13:$AF$61,M$1,FALSE),"") -> -0.0050512093 | O7: =IFERROR((VLOOKUP($E7,'AEO23 Table 23'!$B$13:$AF$61,O$1,FALSE)-(VLOOKUP($E7,'AEO23 Table 23'!$B$13:$AF$61,N$1,FALSE)))/VLOOKUP($E7,'AEO23 Table 23'!$B$13:$AF$61,N$1,FALSE),"") -> -0.0054194633 | ... AI7: =IFERROR((VLOOKUP($E7,'AEO23 Table 23'!$B$13:$AF$61,AI$1,FALSE)-(VLOOKUP($E7,'AEO23 Table 23'!$B$13:$AF$61,AH$1,FALSE)))/VLOOKUP($E7,'AEO23 Table 23'!$B$13:$AF$61,AH$1,FALSE),"") -> 0.012351638
A8: ISIC 09 | B8: {=SUMPRODUCT(--('BLS Table 2.7'!$O:$O=$A8),'BLS Table 2.7'!L:L,'BLS Table 2.7'!N:N)/SUMIFS('BLS Table 2.7'!L:L,'BLS Table 2.7'!$O:$O,$A8)/100} -> 0.029 | E8: ISIC 09 | F8: =IFERROR(INDEX('AEO23 Table 23'!$AG$22:$AG$61,MATCH($E8,'AEO23 Table 23'!$B$22:$B$61,0)),"") | H8: =IFERROR((VLOOKUP($E8,'AEO23 Table 23'!$B$13:$AF$61,H$1,FALSE)-(VLOOKUP($E8,'AEO23 Table 23'!$B$13:$AF$61,G$1,FALSE)))/VLOOKUP($E8,'AEO23 Table 23'!$B$13:$AF$61,G$1,FALSE),"") | I8: =IFERROR((VLOOKUP($E8,'AEO23 Table 23'!$B$13:$AF$61,I$1,FALSE)-(VLOOKUP($E8,'AEO23 Table 23'!$B$13:$AF$61,H$1,FALSE)))/VLOOKUP($E8,'AEO23 Table 23'!$B$13:$AF$61,H$1,FALSE),"") | J8: =IFERROR((VLOOKUP($E8,'AEO23 Table 23'!$B$13:$AF$61,J$1,FALSE)-(VLOOKUP($E8,'AEO23 Table 23'!$B$13:$AF$61,I$1,FALSE)))/VLOOKUP($E8,'AEO23 Table 23'!$B$13:$AF$61,I$1,FALSE),"") | K8: =IFERROR((VLOOKUP($E8,'AEO23 Table 23'!$B$13:$AF$61,K$1,FALSE)-(VLOOKUP($E8,'AEO23 Table 23'!$B$13:$AF$61,J$1,FALSE)))/VLOOKUP($E8,'AEO23 Table 23'!$B$13:$AF$61,J$1,FALSE),"") | L8: =IFERROR((VLOOKUP($E8,'AEO23 Table 23'!$B$13:$AF$61,L$1,FALSE)-(VLOOKUP($E8,'AEO23 Table 23'!$B$13:$AF$61,K$1,FALSE)))/VLOOKUP($E8,'AEO23 Table 23'!$B$13:$AF$61,K$1,FALSE),"") | M8: =IFERROR((VLOOKUP($E8,'AEO23 Table 23'!$B$13:$AF$61,M$1,FALSE)-(VLOOKUP($E8,'AEO23 Table 23'!$B$13:$AF$61,L$1,FALSE)))/VLOOKUP($E8,'AEO23 Table 23'!$B$13:$AF$61,L$1,FALSE),"") | N8: =IFERROR((VLOOKUP($E8,'AEO23 Table 23'!$B$13:$AF$61,N$1,FALSE)-(VLOOKUP($E8,'AEO23 Table 23'!$B$13:$AF$61,M$1,FALSE)))/VLOOKUP($E8,'AEO23 Table 23'!$B$13:$AF$61,M$1,FALSE),"") | O8: =IFERROR((VLOOKUP($E8,'AEO23 Table 23'!$B$13:$AF$61,O$1,FALSE)-(VLOOKUP($E8,'AEO23 Table 23'!$B$13:$AF$61,N$1,FALSE)))/VLOOKUP($E8,'AEO23 Table 23'!$B$13:$AF$61,N$1,FALSE),"") | ... AI8: =IFERROR((VLOOKUP($E8,'AEO23 Table 23'!$B$13:$AF$61,AI$1,FALSE)-(VLOOKUP($E8,'AEO23 Table 23'!$B$13:$AF$61,AH$1,FALSE)))/VLOOKUP($E8,'AEO23 Table 23'!$B$13:$AF$61,AH$1,FALSE),"")
A9: ISIC 10T12 | B9: {=SUMPRODUCT(--('BLS Table 2.7'!$O:$O=$A9),'BLS Table 2.7'!L:L,'BLS Table 2.7'!N:N)/SUMIFS('BLS Table 2.7'!L:L,'BLS Table 2.7'!$O:$O,$A9)/100} -> 0.015585313 | E9: ISIC 10T12 | F9: =IFERROR(INDEX('AEO23 Table 23'!$AG$22:$AG$61,MATCH($E9,'AEO23 Table 23'!$B$22:$B$61,0)),"") -> 0.010838 | G9: =(INDEX('AEO23 Table 23'!$D$22:$D$61,MATCH('Growth Rates'!E9,'AEO23 Table 23'!$B$22:$B$61,0))-INDEX('AEO22 Table 23'!$D$22:$D$58,MATCH('Growth Rates'!E9,'AEO22 Table 23'!$B$22:$B$58,0)))/INDEX('AEO22 Table 23'!$D$22:$D$58,MATCH('Growth Rates'!E9,'AEO22 Table 23'!$B$22:$B$58,0)) -> -0.012463136 | H9: =IFERROR((VLOOKUP($E9,'AEO23 Table 23'!$B$13:$AF$61,H$1,FALSE)-(VLOOKUP($E9,'AEO23 Table 23'!$B$13:$AF$61,G$1,FALSE)))/VLOOKUP($E9,'AEO23 Table 23'!$B$13:$AF$61,G$1,FALSE),"") -> 0.015600731 | I9: =IFERROR((VLOOKUP($E9,'AEO23 Table 23'!$B$13:$AF$61,I$1,FALSE)-(VLOOKUP($E9,'AEO23 Table 23'!$B$13:$AF$61,H$1,FALSE)))/VLOOKUP($E9,'AEO23 Table 23'!$B$13:$AF$61,H$1,FALSE),"") -> 0.010035729 | J9: =IFERROR((VLOOKUP($E9,'AEO23 Table 23'!$B$13:$AF$61,J$1,FALSE)-(VLOOKUP($E9,'AEO23 Table 23'!$B$13:$AF$61,I$1,FALSE)))/VLOOKUP($E9,'AEO23 Table 23'!$B$13:$AF$61,I$1,FALSE),"") -> 0.0092179804 | K9: =IFERROR((VLOOKUP($E9,'AEO23 Table 23'!$B$13:$AF$61,K$1,FALSE)-(VLOOKUP($E9,'AEO23 Table 23'!$B$13:$AF$61,J$1,FALSE)))/VLOOKUP($E9,'AEO23 Table 23'!$B$13:$AF$61,J$1,FALSE),"") -> 0.012898743 | L9: =IFERROR((VLOOKUP($E9,'AEO23 Table 23'!$B$13:$AF$61,L$1,FALSE)-(VLOOKUP($E9,'AEO23 Table 23'!$B$13:$AF$61,K$1,FALSE)))/VLOOKUP($E9,'AEO23 Table 23'!$B$13:$AF$61,K$1,FALSE),"") -> 0.014149095 | M9: =IFERROR((VLOOKUP($E9,'AEO23 Table 23'!$B$13:$AF$61,M$1,FALSE)-(VLOOKUP($E9,'AEO23 Table 23'!$B$13:$AF$61,L$1,FALSE)))/VLOOKUP($E9,'AEO23 Table 23'!$B$13:$AF$61,L$1,FALSE),"") -> 0.014043116 | N9: =IFERROR((VLOOKUP($E9,'AEO23 Table 23'!$B$13:$AF$61,N$1,FALSE)-(VLOOKUP($E9,'AEO23 Table 23'!$B$13:$AF$61,M$1,FALSE)))/VLOOKUP($E9,'AEO23 Table 23'!$B$13:$AF$61,M$1,FALSE),"") -> 0.012009641 | O9: =IFERROR((VLOOKUP($E9,'AEO23 Table 23'!$B$13:$AF$61,O$1,FALSE)-(VLOOKUP($E9,'AEO23 Table 23'!$B$13:$AF$61,N$1,FALSE)))/VLOOKUP($E9,'AEO23 Table 23'!$B$13:$AF$61,N$1,FALSE),"") -> 0.011759882 | ... AI9: =IFERROR((VLOOKUP($E9,'AEO23 Table 23'!$B$13:$AF$61,AI$1,FALSE)-(VLOOKUP($E9,'AEO23 Table 23'!$B$13:$AF$61,AH$1,FALSE)))/VLOOKUP($E9,'AEO23 Table 23'!$B$13:$AF$61,AH$1,FALSE),"") -> 0.0092652577
A10: ISIC 13T15 | B10: {=SUMPRODUCT(--('BLS Table 2.7'!$O:$O=$A10),'BLS Table 2.7'!L:L,'BLS Table 2.7'!N:N)/SUMIFS('BLS Table 2.7'!L:L,'BLS Table 2.7'!$O:$O,$A10)/100} -> -0.0021448864 | E10: ISIC 13T15 | F10: =IFERROR(INDEX('AEO23 Table 23'!$AG$22:$AG$61,MATCH($E10,'AEO23 Table 23'!$B$22:$B$61,0)),"") -> -0.001191 | G10: =(INDEX('AEO23 Table 23'!$D$22:$D$61,MATCH('Growth Rates'!E10,'AEO23 Table 23'!$B$22:$B$61,0))-INDEX('AEO22 Table 23'!$D$22:$D$58,MATCH('Growth Rates'!E10,'AEO22 Table 23'!$B$22:$B$58,0)))/INDEX('AEO22 Table 23'!$D$22:$D$58,MATCH('Growth Rates'!E10,'AEO22 Table 23'!$B$22:$B$58,0)) -> -0.00049111462 | H10: =IFERROR((VLOOKUP($E10,'AEO23 Table 23'!$B$13:$AF$61,H$1,FALSE)-(VLOOKUP($E10,'AEO23 Table 23'!$B$13:$AF$61,G$1,FALSE)))/VLOOKUP($E10,'AEO23 Table 23'!$B$13:$AF$61,G$1,FALSE),"") -> -0.015291759 | I10: =IFERROR((VLOOKUP($E10,'AEO23 Table 23'!$B$13:$AF$61,I$1,FALSE)-(VLOOKUP($E10,'AEO23 Table 23'!$B$13:$AF$61,H$1,FALSE)))/VLOOKUP($E10,'AEO23 Table 23'!$B$13:$AF$61,H$1,FALSE),"") -> -0.010161745 | J10: =IFERROR((VLOOKUP($E10,'AEO23 Table 23'!$B$13:$AF$61,J$1,FALSE)-(VLOOKUP($E10,'AEO23 Table 23'!$B$13:$AF$61,I$1,FALSE)))/VLOOKUP($E10,'AEO23 Table 23'!$B$13:$AF$61,I$1,FALSE),"") -> 0.00043146482 | K10: =IFERROR((VLOOKUP($E10,'AEO23 Table 23'!$B$13:$AF$61,K$1,FALSE)-(VLOOKUP($E10,'AEO23 Table 23'!$B$13:$AF$61,J$1,FALSE)))/VLOOKUP($E10,'AEO23 Table 23'!$B$13:$AF$61,J$1,FALSE),"") -> 0.018861179 | L10: =IFERROR((VLOOKUP($E10,'AEO23 Table 23'!$B$13:$AF$61,L$1,FALSE)-(VLOOKUP($E10,'AEO23 Table 23'!$B$13:$AF$61,K$1,FALSE)))/VLOOKUP($E10,'AEO23 Table 23'!$B$13:$AF$61,K$1,FALSE),"") -> 0.022854649 | M10: =IFERROR((VLOOKUP($E10,'AEO23 Table 23'!$B$13:$AF$61,M$1,FALSE)-(VLOOKUP($E10,'AEO23 Table 23'!$B$13:$AF$61,L$1,FALSE)))/VLOOKUP($E10,'AEO23 Table 23'!$B$13:$AF$61,L$1,FALSE),"") -> 0.015633738 | N10: =IFERROR((VLOOKUP($E10,'AEO23 Table 23'!$B$13:$AF$61,N$1,FALSE)-(VLOOKUP($E10,'AEO23 Table 23'!$B$13:$AF$61,M$1,FALSE)))/VLOOKUP($E10,'AEO23 Table 23'!$B$13:$AF$61,M$1,FALSE),"") -> 0.0066148159 | O10: =IFERROR((VLOOKUP($E10,'AEO23 Table 23'!$B$13:$AF$61,O$1,FALSE)-(VLOOKUP($E10,'AEO23 Table 23'!$B$13:$AF$61,N$1,FALSE)))/VLOOKUP($E10,'AEO23 Table 23'!$B$13:$AF$61,N$1,FALSE),"") -> 0.0015438154 | ... AI10: =IFERROR((VLOOKUP($E10,'AEO23 Table 23'!$B$13:$AF$61,AI$1,FALSE)-(VLOOKUP($E10,'AEO23 Table 23'!$B$13:$AF$61,AH$1,FALSE)))/VLOOKUP($E10,'AEO23 Table 23'!$B$13:$AF$61,AH$1,FALSE),"") -> -0.0070890216
A11: ISIC 16 | B11: {=SUMPRODUCT(--('BLS Table 2.7'!$O:$O=$A11),'BLS Table 2.7'!L:L,'BLS Table 2.7'!N:N)/SUMIFS('BLS Table 2.7'!L:L,'BLS Table 2.7'!$O:$O,$A11)/100} -> 0.014 | E11: ISIC 16 | F11: =IFERROR(INDEX('AEO23 Table 23'!$AG$22:$AG$61,MATCH($E11,'AEO23 Table 23'!$B$22:$B$61,0)),"") -> 0.000599 | G11: =(INDEX('AEO23 Table 23'!$D$22:$D$61,MATCH('Growth Rates'!E11,'AEO23 Table 23'!$B$22:$B$61,0))-INDEX('AEO22 Table 23'!$D$22:$D$58,MATCH('Growth Rates'!E11,'AEO22 Table 23'!$B$22:$B$58,0)))/INDEX('AEO22 Table 23'!$D$22:$D$58,MATCH('Growth Rates'!E11,'AEO22 Table 23'!$B$22:$B$58,0)) -> -0.0064436018 | H11: =IFERROR((VLOOKUP($E11,'AEO23 Table 23'!$B$13:$AF$61,H$1,FALSE)-(VLOOKUP($E11,'AEO23 Table 23'!$B$13:$AF$61,G$1,FALSE)))/VLOOKUP($E11,'AEO23 Table 23'!$B$13:$AF$61,G$1,FALSE),"") -> -0.091320586 | I11: =IFERROR((VLOOKUP($E11,'AEO23 Table 23'!$B$13:$AF$61,I$1,FALSE)-(VLOOKUP($E11,'AEO23 Table 23'!$B$13:$AF$61,H$1,FALSE)))/VLOOKUP($E11,'AEO23 Table 23'!$B$13:$AF$61,H$1,FALSE),"") -> -0.026686381 | J11: =IFERROR((VLOOKUP($E11,'AEO23 Table 23'!$B$13:$AF$61,J$1,FALSE)-(VLOOKUP($E11,'AEO23 Table 23'!$B$13:$AF$61,I$1,FALSE)))/VLOOKUP($E11,'AEO23 Table 23'!$B$13:$AF$61,I$1,FALSE),"") -> 0.018734119 | K11: =IFERROR((VLOOKUP($E11,'AEO23 Table 23'!$B$13:$AF$61,K$1,FALSE)-(VLOOKUP($E11,'AEO23 Table 23'!$B$13:$AF$61,J$1,FALSE)))/VLOOKUP($E11,'AEO23 Table 23'!$B$13:$AF$61,J$1,FALSE),"") -> -0.012793884 | L11: =IFERROR((VLOOKUP($E11,'AEO23 Table 23'!$B$13:$AF$61,L$1,FALSE)-(VLOOKUP($E11,'AEO23 Table 23'!$B$13:$AF$61,K$1,FALSE)))/VLOOKUP($E11,'AEO23 Table 23'!$B$13:$AF$61,K$1,FALSE),"") -> -0.0044872068 | M11: =IFERROR((VLOOKUP($E11,'AEO23 Table 23'!$B$13:$AF$61,M$1,FALSE)-(VLOOKUP($E11,'AEO23 Table 23'!$B$13:$AF$61,L$1,FALSE)))/VLOOKUP($E11,'AEO23 Table 23'!$B$13:$AF$61,L$1,FALSE),"") -> 0.013003257 | N11: =IFERROR((VLOOKUP($E11,'AEO23 Table 23'!$B$13:$AF$61,N$1,FALSE)-(VLOOKUP($E11,'AEO23 Table 23'!$B$13:$AF$61,M$1,FALSE)))/VLOOKUP($E11,'AEO23 Table 23'!$B$13:$AF$61,M$1,FALSE),"") -> 0.016913468 | O11: =IFERROR((VLOOKUP($E11,'AEO23 Table 23'!$B$13:$AF$61,O$1,FALSE)-(VLOOKUP($E11,'AEO23 Table 23'!$B$13:$AF$61,N$1,FALSE)))/VLOOKUP($E11,'AEO23 Table 23'!$B$13:$AF$61,N$1,FALSE),"") -> 0.0076007203 | ... AI11: =IFERROR((VLOOKUP($E11,'AEO23 Table 23'!$B$13:$AF$61,AI$1,FALSE)-(VLOOKUP($E11,'AEO23 Table 23'!$B$13:$AF$61,AH$1,FALSE)))/VLOOKUP($E11,'AEO23 Table 23'!$B$13:$AF$61,AH$1,FALSE),"") -> 0.010461093
A12: ISIC 17T18 | B12: {=SUMPRODUCT(--('BLS Table 2.7'!$O:$O=$A12),'BLS Table 2.7'!L:L,'BLS Table 2.7'!N:N)/SUMIFS('BLS Table 2.7'!L:L,'BLS Table 2.7'!$O:$O,$A12)/100} -> 0.0049882741 | E12: ISIC 17T18 | F12: =IFERROR(INDEX('AEO23 Table 23'!$AG$22:$AG$61,MATCH($E12,'AEO23 Table 23'!$B$22:$B$61,0)),"") -> 0.003241 | G12: =(INDEX('AEO23 Table 23'!$D$22:$D$61,MATCH('Growth Rates'!E12,'AEO23 Table 23'!$B$22:$B$61,0))-INDEX('AEO22 Table 23'!$D$22:$D$58,MATCH('Growth Rates'!E12,'AEO22 Table 23'!$B$22:$B$58,0)))/INDEX('AEO22 Table 23'!$D$22:$D$58,MATCH('Growth Rates'!E12,'AEO22 Table 23'!$B$22:$B$58,0)) -> 0.034978913 | H12: =IFERROR((VLOOKUP($E12,'AEO23 Table 23'!$B$13:$AF$61,H$1,FALSE)-(VLOOKUP($E12,'AEO23 Table 23'!$B$13:$AF$61,G$1,FALSE)))/VLOOKUP($E12,'AEO23 Table 23'!$B$13:$AF$61,G$1,FALSE),"") -> -0.022942396 | I12: =IFERROR((VLOOKUP($E12,'AEO23 Table 23'!$B$13:$AF$61,I$1,FALSE)-(VLOOKUP($E12,'AEO23 Table 23'!$B$13:$AF$61,H$1,FALSE)))/VLOOKUP($E12,'AEO23 Table 23'!$B$13:$AF$61,H$1,FALSE),"") -> -0.02223464 | J12: =IFERROR((VLOOKUP($E12,'AEO23 Table 23'!$B$13:$AF$61,J$1,FALSE)-(VLOOKUP($E12,'AEO23 Table 23'!$B$13:$AF$61,I$1,FALSE)))/VLOOKUP($E12,'AEO23 Table 23'!$B$13:$AF$61,I$1,FALSE),"") -> -0.0014451533 | K12: =IFERROR((VLOOKUP($E12,'AEO23 Table 23'!$B$13:$AF$61,K$1,FALSE)-(VLOOKUP($E12,'AEO23 Table 23'!$B$13:$AF$61,J$1,FALSE)))/VLOOKUP($E12,'AEO23 Table 23'!$B$13:$AF$61,J$1,FALSE),"") -> 0.0051444073 | L12: =IFERROR((VLOOKUP($E12,'AEO23 Table 23'!$B$13:$AF$61,L$1,FALSE)-(VLOOKUP($E12,'AEO23 Table 23'!$B$13:$AF$61,K$1,FALSE)))/VLOOKUP($E12,'AEO23 Table 23'!$B$13:$AF$61,K$1,FALSE),"") -> 0.0061956363 | M12: =IFERROR((VLOOKUP($E12,'AEO23 Table 23'!$B$13:$AF$61,M$1,FALSE)-(VLOOKUP($E12,'AEO23 Table 23'!$B$13:$AF$61,L$1,FALSE)))/VLOOKUP($E12,'AEO23 Table 23'!$B$13:$AF$61,L$1,FALSE),"") -> 0.0059704499 | N12: =IFERROR((VLOOKUP($E12,'AEO23 Table 23'!$B$13:$AF$61,N$1,FALSE)-(VLOOKUP($E12,'AEO23 Table 23'!$B$13:$AF$61,M$1,FALSE)))/VLOOKUP($E12,'AEO23 Table 23'!$B$13:$AF$61,M$1,FALSE),"") -> 0.0052781965 | O12: =IFERROR((VLOOKUP($E12,'AEO23 Table 23'!$B$13:$AF$61,O$1,FALSE)-(VLOOKUP($E12,'AEO23 Table 23'!$B$13:$AF$61,N$1,FALSE)))/VLOOKUP($E12,'AEO23 Table 23'!$B$13:$AF$61,N$1,FALSE),"") -> 0.0046418589 | ... AI12: =IFERROR((VLOOKUP($E12,'AEO23 Table 23'!$B$13:$AF$61,AI$1,FALSE)-(VLOOKUP($E12,'AEO23 Table 23'!$B$13:$AF$61,AH$1,FALSE)))/VLOOKUP($E12,'AEO23 Table 23'!$B$13:$AF$61,AH$1,FALSE),"") -> 0.007186495
A13: ISIC 19 | B13: {=SUMPRODUCT(--('BLS Table 2.7'!$O:$O=$A13),'BLS Table 2.7'!L:L,'BLS Table 2.7'!N:N)/SUMIFS('BLS Table 2.7'!L:L,'BLS Table 2.7'!$O:$O,$A13)/100} -> 0.023 | E13: ISIC 19 | F13: =IFERROR(INDEX('AEO23 Table 23'!$AG$22:$AG$61,MATCH($E13,'AEO23 Table 23'!$B$22:$B$61,0)),"") -> 0.002464 | G13: =(INDEX('AEO23 Table 23'!$D$22:$D$61,MATCH('Growth Rates'!E13,'AEO23 Table 23'!$B$22:$B$61,0))-INDEX('AEO22 Table 23'!$D$22:$D$58,MATCH('Growth Rates'!E13,'AEO22 Table 23'!$B$22:$B$58,0)))/INDEX('AEO22 Table 23'!$D$22:$D$58,MATCH('Growth Rates'!E13,'AEO22 Table 23'!$B$22:$B$58,0)) -> 0.035549762 | H13: =IFERROR((VLOOKUP($E13,'AEO23 Table 23'!$B$13:$AF$61,H$1,FALSE)-(VLOOKUP($E13,'AEO23 Table 23'!$B$13:$AF$61,G$1,FALSE)))/VLOOKUP($E13,'AEO23 Table 23'!$B$13:$AF$61,G$1,FALSE),"") -> 0.085422436 | I13: =IFERROR((VLOOKUP($E13,'AEO23 Table 23'!$B$13:$AF$61,I$1,FALSE)-(VLOOKUP($E13,'AEO23 Table 23'!$B$13:$AF$61,H$1,FALSE)))/VLOOKUP($E13,'AEO23 Table 23'!$B$13:$AF$61,H$1,FALSE),"") -> -0.0029162063 | J13: =IFERROR((VLOOKUP($E13,'AEO23 Table 23'!$B$13:$AF$61,J$1,FALSE)-(VLOOKUP($E13,'AEO23 Table 23'!$B$13:$AF$61,I$1,FALSE)))/VLOOKUP($E13,'AEO23 Table 23'!$B$13:$AF$61,I$1,FALSE),"") -> -0.0036921542 | K13: =IFERROR((VLOOKUP($E13,'AEO23 Table 23'!$B$13:$AF$61,K$1,FALSE)-(VLOOKUP($E13,'AEO23 Table 23'!$B$13:$AF$61,J$1,FALSE)))/VLOOKUP($E13,'AEO23 Table 23'!$B$13:$AF$61,J$1,FALSE),"") -> -0.0044459641 | L13: =IFERROR((VLOOKUP($E13,'AEO23 Table 23'!$B$13:$AF$61,L$1,FALSE)-(VLOOKUP($E13,'AEO23 Table 23'!$B$13:$AF$61,K$1,FALSE)))/VLOOKUP($E13,'AEO23 Table 23'!$B$13:$AF$61,K$1,FALSE),"") -> -0.0027839792 | M13: =IFERROR((VLOOKUP($E13,'AEO23 Table 23'!$B$13:$AF$61,M$1,FALSE)-(VLOOKUP($E13,'AEO23 Table 23'!$B$13:$AF$61,L$1,FALSE)))/VLOOKUP($E13,'AEO23 Table 23'!$B$13:$AF$61,L$1,FALSE),"") -> -0.0030173431 | N13: =IFERROR((VLOOKUP($E13,'AEO23 Table 23'!$B$13:$AF$61,N$1,FALSE)-(VLOOKUP($E13,'AEO23 Table 23'!$B$13:$AF$61,M$1,FALSE)))/VLOOKUP($E13,'AEO23 Table 23'!$B$13:$AF$61,M$1,FALSE),"") -> -0.004464264 | O13: =IFERROR((VLOOKUP($E13,'AEO23 Table 23'!$B$13:$AF$61,O$1,FALSE)-(VLOOKUP($E13,'AEO23 Table 23'!$B$13:$AF$61,N$1,FALSE)))/VLOOKUP($E13,'AEO23 Table 23'!$B$13:$AF$61,N$1,FALSE),"") -> -0.0068685433 | ... AI13: =IFERROR((VLOOKUP($E13,'AEO23 Table 23'!$B$13:$AF$61,AI$1,FALSE)-(VLOOKUP($E13,'AEO23 Table 23'!$B$13:$AF$61,AH$1,FALSE)))/VLOOKUP($E13,'AEO23 Table 23'!$B$13:$AF$61,AH$1,FALSE),"") -> 0.0093978867
A14: ISIC 20 | B14: {=SUMPRODUCT(--('BLS Table 2.7'!$O:$O=$A14),'BLS Table 2.7'!L:L,'BLS Table 2.7'!N:N)/SUMIFS('BLS Table 2.7'!L:L,'BLS Table 2.7'!$O:$O,$A14)/100} -> 0.018352106 | E14: ISIC 20 | F14: =IFERROR(INDEX('AEO23 Table 23'!$AG$22:$AG$61,MATCH($E14,'AEO23 Table 23'!$B$22:$B$61,0)),"") -> 0.017018 | G14: =(INDEX('AEO23 Table 23'!$D$22:$D$61,MATCH('Growth Rates'!E14,'AEO23 Table 23'!$B$22:$B$61,0))-INDEX('AEO22 Table 23'!$D$22:$D$58,MATCH('Growth Rates'!E14,'AEO22 Table 23'!$B$22:$B$58,0)))/INDEX('AEO22 Table 23'!$D$22:$D$58,MATCH('Growth Rates'!E14,'AEO22 Table 23'!$B$22:$B$58,0)) -> -0.013315353 | H14: =IFERROR((VLOOKUP($E14,'AEO23 Table 23'!$B$13:$AF$61,H$1,FALSE)-(VLOOKUP($E14,'AEO23 Table 23'!$B$13:$AF$61,G$1,FALSE)))/VLOOKUP($E14,'AEO23 Table 23'!$B$13:$AF$61,G$1,FALSE),"") -> -0.02210627 | I14: =IFERROR((VLOOKUP($E14,'AEO23 Table 23'!$B$13:$AF$61,I$1,FALSE)-(VLOOKUP($E14,'AEO23 Table 23'!$B$13:$AF$61,H$1,FALSE)))/VLOOKUP($E14,'AEO23 Table 23'!$B$13:$AF$61,H$1,FALSE),"") -> -0.011879799 | J14: =IFERROR((VLOOKUP($E14,'AEO23 Table 23'!$B$13:$AF$61,J$1,FALSE)-(VLOOKUP($E14,'AEO23 Table 23'!$B$13:$AF$61,I$1,FALSE)))/VLOOKUP($E14,'AEO23 Table 23'!$B$13:$AF$61,I$1,FALSE),"") -> 0.016304088 | K14: =IFERROR((VLOOKUP($E14,'AEO23 Table 23'!$B$13:$AF$61,K$1,FALSE)-(VLOOKUP($E14,'AEO23 Table 23'!$B$13:$AF$61,J$1,FALSE)))/VLOOKUP($E14,'AEO23 Table 23'!$B$13:$AF$61,J$1,FALSE),"") -> 0.023084207 | L14: =IFERROR((VLOOKUP($E14,'AEO23 Table 23'!$B$13:$AF$61,L$1,FALSE)-(VLOOKUP($E14,'AEO23 Table 23'!$B$13:$AF$61,K$1,FALSE)))/VLOOKUP($E14,'AEO23 Table 23'!$B$13:$AF$61,K$1,FALSE),"") -> 0.023260266 | M14: =IFERROR((VLOOKUP($E14,'AEO23 Table 23'!$B$13:$AF$61,M$1,FALSE)-(VLOOKUP($E14,'AEO23 Table 23'!$B$13:$AF$61,L$1,FALSE)))/VLOOKUP($E14,'AEO23 Table 23'!$B$13:$AF$61,L$1,FALSE),"") -> 0.020013849 | N14: =IFERROR((VLOOKUP($E14,'AEO23 Table 23'!$B$13:$AF$61,N$1,FALSE)-(VLOOKUP($E14,'AEO23 Table 23'!$B$13:$AF$61,M$1,FALSE)))/VLOOKUP($E14,'AEO23 Table 23'!$B$13:$AF$61,M$1,FALSE),"") -> 0.015561227 | O14: =IFERROR((VLOOKUP($E14,'AEO23 Table 23'!$B$13:$AF$61,O$1,FALSE)-(VLOOKUP($E14,'AEO23 Table 23'!$B$13:$AF$61,N$1,FALSE)))/VLOOKUP($E14,'AEO23 Table 23'!$B$13:$AF$61,N$1,FALSE),"") -> 0.01262321 | ... AI14: =IFERROR((VLOOKUP($E14,'AEO23 Table 23'!$B$13:$AF$61,AI$1,FALSE)-(VLOOKUP($E14,'AEO23 Table 23'!$B$13:$AF$61,AH$1,FALSE)))/VLOOKUP($E14,'AEO23 Table 23'!$B$13:$AF$61,AH$1,FALSE),"") -> 0.022866991
A15: ISIC 21 | B15: {=SUMPRODUCT(--('BLS Table 2.7'!$O:$O=$A15),'BLS Table 2.7'!L:L,'BLS Table 2.7'!N:N)/SUMIFS('BLS Table 2.7'!L:L,'BLS Table 2.7'!$O:$O,$A15)/100} -> 0.018 | E15: ISIC 21 | F15: =IFERROR(INDEX('AEO23 Table 23'!$AG$22:$AG$61,MATCH($E15,'AEO23 Table 23'!$B$22:$B$61,0)),"") | H15: =IFERROR((VLOOKUP($E15,'AEO23 Table 23'!$B$13:$AF$61,H$1,FALSE)-(VLOOKUP($E15,'AEO23 Table 23'!$B$13:$AF$61,G$1,FALSE)))/VLOOKUP($E15,'AEO23 Table 23'!$B$13:$AF$61,G$1,FALSE),"") | I15: =IFERROR((VLOOKUP($E15,'AEO23 Table 23'!$B$13:$AF$61,I$1,FALSE)-(VLOOKUP($E15,'AEO23 Table 23'!$B$13:$AF$61,H$1,FALSE)))/VLOOKUP($E15,'AEO23 Table 23'!$B$13:$AF$61,H$1,FALSE),"") | J15: =IFERROR((VLOOKUP($E15,'AEO23 Table 23'!$B$13:$AF$61,J$1,FALSE)-(VLOOKUP($E15,'AEO23 Table 23'!$B$13:$AF$61,I$1,FALSE)))/VLOOKUP($E15,'AEO23 Table 23'!$B$13:$AF$61,I$1,FALSE),"") | K15: =IFERROR((VLOOKUP($E15,'AEO23 Table 23'!$B$13:$AF$61,K$1,FALSE)-(VLOOKUP($E15,'AEO23 Table 23'!$B$13:$AF$61,J$1,FALSE)))/VLOOKUP($E15,'AEO23 Table 23'!$B$13:$AF$61,J$1,FALSE),"") | L15: =IFERROR((VLOOKUP($E15,'AEO23 Table 23'!$B$13:$AF$61,L$1,FALSE)-(VLOOKUP($E15,'AEO23 Table 23'!$B$13:$AF$61,K$1,FALSE)))/VLOOKUP($E15,'AEO23 Table 23'!$B$13:$AF$61,K$1,FALSE),"") | M15: =IFERROR((VLOOKUP($E15,'AEO23 Table 23'!$B$13:$AF$61,M$1,FALSE)-(VLOOKUP($E15,'AEO23 Table 23'!$B$13:$AF$61,L$1,FALSE)))/VLOOKUP($E15,'AEO23 Table 23'!$B$13:$AF$61,L$1,FALSE),"") | N15: =IFERROR((VLOOKUP($E15,'AEO23 Table 23'!$B$13:$AF$61,N$1,FALSE)-(VLOOKUP($E15,'AEO23 Table 23'!$B$13:$AF$61,M$1,FALSE)))/VLOOKUP($E15,'AEO23 Table 23'!$B$13:$AF$61,M$1,FALSE),"") | O15: =IFERROR((VLOOKUP($E15,'AEO23 Table 23'!$B$13:$AF$61,O$1,FALSE)-(VLOOKUP($E15,'AEO23 Table 23'!$B$13:$AF$61,N$1,FALSE)))/VLOOKUP($E15,'AEO23 Table 23'!$B$13:$AF$61,N$1,FALSE),"") | ... AI15: =IFERROR((VLOOKUP($E15,'AEO23 Table 23'!$B$13:$AF$61,AI$1,FALSE)-(VLOOKUP($E15,'AEO23 Table 23'!$B$13:$AF$61,AH$1,FALSE)))/VLOOKUP($E15,'AEO23 Table 23'!$B$13:$AF$61,AH$1,FALSE),"")
A16: ISIC 22 | B16: {=SUMPRODUCT(--('BLS Table 2.7'!$O:$O=$A16),'BLS Table 2.7'!L:L,'BLS Table 2.7'!N:N)/SUMIFS('BLS Table 2.7'!L:L,'BLS Table 2.7'!$O:$O,$A16)/100} -> 0.014 | E16: ISIC 22 | F16: =IFERROR(INDEX('AEO23 Table 23'!$AG$22:$AG$61,MATCH($E16,'AEO23 Table 23'!$B$22:$B$61,0)),"") -> 0.015136 | G16: =(INDEX('AEO23 Table 23'!$D$22:$D$61,MATCH('Growth Rates'!E16,'AEO23 Table 23'!$B$22:$B$61,0))-INDEX('AEO22 Table 23'!$D$22:$D$58,MATCH('Growth Rates'!E16,'AEO22 Table 23'!$B$22:$B$58,0)))/INDEX('AEO22 Table 23'!$D$22:$D$58,MATCH('Growth Rates'!E16,'AEO22 Table 23'!$B$22:$B$58,0)) -> 0.037127926 | H16: =IFERROR((VLOOKUP($E16,'AEO23 Table 23'!$B$13:$AF$61,H$1,FALSE)-(VLOOKUP($E16,'AEO23 Table 23'!$B$13:$AF$61,G$1,FALSE)))/VLOOKUP($E16,'AEO23 Table 23'!$B$13:$AF$61,G$1,FALSE),"") -> -0.020293273 | I16: =IFERROR((VLOOKUP($E16,'AEO23 Table 23'!$B$13:$AF$61,I$1,FALSE)-(VLOOKUP($E16,'AEO23 Table 23'!$B$13:$AF$61,H$1,FALSE)))/VLOOKUP($E16,'AEO23 Table 23'!$B$13:$AF$61,H$1,FALSE),"") -> -0.0072429512 | J16: =IFERROR((VLOOKUP($E16,'AEO23 Table 23'!$B$13:$AF$61,J$1,FALSE)-(VLOOKUP($E16,'AEO23 Table 23'!$B$13:$AF$61,I$1,FALSE)))/VLOOKUP($E16,'AEO23 Table 23'!$B$13:$AF$61,I$1,FALSE),"") -> 0.014554492 | K16: =IFERROR((VLOOKUP($E16,'AEO23 Table 23'!$B$13:$AF$61,K$1,FALSE)-(VLOOKUP($E16,'AEO23 Table 23'!$B$13:$AF$61,J$1,FALSE)))/VLOOKUP($E16,'AEO23 Table 23'!$B$13:$AF$61,J$1,FALSE),"") -> 0.02625625 | L16: =IFERROR((VLOOKUP($E16,'AEO23 Table 23'!$B$13:$AF$61,L$1,FALSE)-(VLOOKUP($E16,'AEO23 Table 23'!$B$13:$AF$61,K$1,FALSE)))/VLOOKUP($E16,'AEO23 Table 23'!$B$13:$AF$61,K$1,FALSE),"") -> 0.022568493 | M16: =IFERROR((VLOOKUP($E16,'AEO23 Table 23'!$B$13:$AF$61,M$1,FALSE)-(VLOOKUP($E16,'AEO23 Table 23'!$B$13:$AF$61,L$1,FALSE)))/VLOOKUP($E16,'AEO23 Table 23'!$B$13:$AF$61,L$1,FALSE),"") -> 0.018687012 | N16: =IFERROR((VLOOKUP($E16,'AEO23 Table 23'!$B$13:$AF$61,N$1,FALSE)-(VLOOKUP($E16,'AEO23 Table 23'!$B$13:$AF$61,M$1,FALSE)))/VLOOKUP($E16,'AEO23 Table 23'!$B$13:$AF$61,M$1,FALSE),"") -> 0.017180054 | O16: =IFERROR((VLOOKUP($E16,'AEO23 Table 23'!$B$13:$AF$61,O$1,FALSE)-(VLOOKUP($E16,'AEO23 Table 23'!$B$13:$AF$61,N$1,FALSE)))/VLOOKUP($E16,'AEO23 Table 23'!$B$13:$AF$61,N$1,FALSE),"") -> 0.014263384 | ... AI16: =IFERROR((VLOOKUP($E16,'AEO23 Table 23'!$B$13:$AF$61,AI$1,FALSE)-(VLOOKUP($E16,'AEO23 Table 23'!$B$13:$AF$61,AH$1,FALSE)))/VLOOKUP($E16,'AEO23 Table 23'!$B$13:$AF$61,AH$1,FALSE),"") -> 0.020773899
A17: ISIC 231 | B17: {=SUMPRODUCT(--('BLS Table 2.7'!$O:$O=$A17),'BLS Table 2.7'!L:L,'BLS Table 2.7'!N:N)/SUMIFS('BLS Table 2.7'!L:L,'BLS Table 2.7'!$O:$O,$A17)/100} -> 0.018 | E17: ISIC 231 | F17: =IFERROR(INDEX('AEO23 Table 23'!$AG$22:$AG$61,MATCH($E17,'AEO23 Table 23'!$B$22:$B$61,0)),"") -> 0.006903 | G17: =(INDEX('AEO23 Table 23'!$D$22:$D$61,MATCH('Growth Rates'!E17,'AEO23 Table 23'!$B$22:$B$61,0))-INDEX('AEO22 Table 23'!$D$22:$D$58,MATCH('Growth Rates'!E17,'AEO22 Table 23'!$B$22:$B$58,0)))/INDEX('AEO22 Table 23'!$D$22:$D$58,MATCH('Growth Rates'!E17,'AEO22 Table 23'!$B$22:$B$58,0)) -> 0.015773178 | H17: =IFERROR((VLOOKUP($E17,'AEO23 Table 23'!$B$13:$AF$61,H$1,FALSE)-(VLOOKUP($E17,'AEO23 Table 23'!$B$13:$AF$61,G$1,FALSE)))/VLOOKUP($E17,'AEO23 Table 23'!$B$13:$AF$61,G$1,FALSE),"") -> -0.058886503 | I17: =IFERROR((VLOOKUP($E17,'AEO23 Table 23'!$B$13:$AF$61,I$1,FALSE)-(VLOOKUP($E17,'AEO23 Table 23'!$B$13:$AF$61,H$1,FALSE)))/VLOOKUP($E17,'AEO23 Table 23'!$B$13:$AF$61,H$1,FALSE),"") -> -0.017012937 | J17: =IFERROR((VLOOKUP($E17,'AEO23 Table 23'!$B$13:$AF$61,J$1,FALSE)-(VLOOKUP($E17,'AEO23 Table 23'!$B$13:$AF$61,I$1,FALSE)))/VLOOKUP($E17,'AEO23 Table 23'!$B$13:$AF$61,I$1,FALSE),"") -> 0.00034113368 | K17: =IFERROR((VLOOKUP($E17,'AEO23 Table 23'!$B$13:$AF$61,K$1,FALSE)-(VLOOKUP($E17,'AEO23 Table 23'!$B$13:$AF$61,J$1,FALSE)))/VLOOKUP($E17,'AEO23 Table 23'!$B$13:$AF$61,J$1,FALSE),"") -> 0.028267038 | L17: =IFERROR((VLOOKUP($E17,'AEO23 Table 23'!$B$13:$AF$61,L$1,FALSE)-(VLOOKUP($E17,'AEO23 Table 23'!$B$13:$AF$61,K$1,FALSE)))/VLOOKUP($E17,'AEO23 Table 23'!$B$13:$AF$61,K$1,FALSE),"") -> 0.015411073 | M17: =IFERROR((VLOOKUP($E17,'AEO23 Table 23'!$B$13:$AF$61,M$1,FALSE)-(VLOOKUP($E17,'AEO23 Table 23'!$B$13:$AF$61,L$1,FALSE)))/VLOOKUP($E17,'AEO23 Table 23'!$B$13:$AF$61,L$1,FALSE),"") -> 0.01177904 | N17: =IFERROR((VLOOKUP($E17,'AEO23 Table 23'!$B$13:$AF$61,N$1,FALSE)-(VLOOKUP($E17,'AEO23 Table 23'!$B$13:$AF$61,M$1,FALSE)))/VLOOKUP($E17,'AEO23 Table 23'!$B$13:$AF$61,M$1,FALSE),"") -> 0.0090533167 | O17: =IFERROR((VLOOKUP($E17,'AEO23 Table 23'!$B$13:$AF$61,O$1,FALSE)-(VLOOKUP($E17,'AEO23 Table 23'!$B$13:$AF$61,N$1,FALSE)))/VLOOKUP($E17,'AEO23 Table 23'!$B$13:$AF$61,N$1,FALSE),"") -> 0.0051628462 | ... AI17: =IFERROR((VLOOKUP($E17,'AEO23 Table 23'!$B$13:$AF$61,AI$1,FALSE)-(VLOOKUP($E17,'AEO23 Table 23'!$B$13:$AF$61,AH$1,FALSE)))/VLOOKUP($E17,'AEO23 Table 23'!$B$13:$AF$61,AH$1,FALSE),"") -> 0.0098945908
A18: ISIC 239 | B18: {=SUMPRODUCT(--('BLS Table 2.7'!$O:$O=$A18),'BLS Table 2.7'!L:L,'BLS Table 2.7'!N:N)/SUMIFS('BLS Table 2.7'!L:L,'BLS Table 2.7'!$O:$O,$A18)/100} -> 0.014749767 | E18: ISIC 239 | F18: =IFERROR(INDEX('AEO23 Table 23'!$AG$22:$AG$61,MATCH($E18,'AEO23 Table 23'!$B$22:$B$61,0)),"") -> 0.007411 | G18: =(INDEX('AEO23 Table 23'!$D$22:$D$61,MATCH('Growth Rates'!E18,'AEO23 Table 23'!$B$22:$B$61,0))-INDEX('AEO22 Table 23'!$D$22:$D$58,MATCH('Growth Rates'!E18,'AEO22 Table 23'!$B$22:$B$58,0)))/INDEX('AEO22 Table 23'!$D$22:$D$58,MATCH('Growth Rates'!E18,'AEO22 Table 23'!$B$22:$B$58,0)) -> 0.15097807 | H18: =IFERROR((VLOOKUP($E18,'AEO23 Table 23'!$B$13:$AF$61,H$1,FALSE)-(VLOOKUP($E18,'AEO23 Table 23'!$B$13:$AF$61,G$1,FALSE)))/VLOOKUP($E18,'AEO23 Table 23'!$B$13:$AF$61,G$1,FALSE),"") -> -0.04461641 | I18: =IFERROR((VLOOKUP($E18,'AEO23 Table 23'!$B$13:$AF$61,I$1,FALSE)-(VLOOKUP($E18,'AEO23 Table 23'!$B$13:$AF$61,H$1,FALSE)))/VLOOKUP($E18,'AEO23 Table 23'!$B$13:$AF$61,H$1,FALSE),"") -> -0.012348283 | J18: =IFERROR((VLOOKUP($E18,'AEO23 Table 23'!$B$13:$AF$61,J$1,FALSE)-(VLOOKUP($E18,'AEO23 Table 23'!$B$13:$AF$61,I$1,FALSE)))/VLOOKUP($E18,'AEO23 Table 23'!$B$13:$AF$61,I$1,FALSE),"") -> 0.016226214 | K18: =IFERROR((VLOOKUP($E18,'AEO23 Table 23'!$B$13:$AF$61,K$1,FALSE)-(VLOOKUP($E18,'AEO23 Table 23'!$B$13:$AF$61,J$1,FALSE)))/VLOOKUP($E18,'AEO23 Table 23'!$B$13:$AF$61,J$1,FALSE),"") -> 0.015205168 | L18: =IFERROR((VLOOKUP($E18,'AEO23 Table 23'!$B$13:$AF$61,L$1,FALSE)-(VLOOKUP($E18,'AEO23 Table 23'!$B$13:$AF$61,K$1,FALSE)))/VLOOKUP($E18,'AEO23 Table 23'!$B$13:$AF$61,K$1,FALSE),"") -> 0.009736753 | M18: =IFERROR((VLOOKUP($E18,'AEO23 Table 23'!$B$13:$AF$61,M$1,FALSE)-(VLOOKUP($E18,'AEO23 Table 23'!$B$13:$AF$61,L$1,FALSE)))/VLOOKUP($E18,'AEO23 Table 23'!$B$13:$AF$61,L$1,FALSE),"") -> 0.009114511 | N18: =IFERROR((VLOOKUP($E18,'AEO23 Table 23'!$B$13:$AF$61,N$1,FALSE)-(VLOOKUP($E18,'AEO23 Table 23'!$B$13:$AF$61,M$1,FALSE)))/VLOOKUP($E18,'AEO23 Table 23'!$B$13:$AF$61,M$1,FALSE),"") -> 0.011967982 | O18: =IFERROR((VLOOKUP($E18,'AEO23 Table 23'!$B$13:$AF$61,O$1,FALSE)-(VLOOKUP($E18,'AEO23 Table 23'!$B$13:$AF$61,N$1,FALSE)))/VLOOKUP($E18,'AEO23 Table 23'!$B$13:$AF$61,N$1,FALSE),"") -> 0.012453168 | ... AI18: =IFERROR((VLOOKUP($E18,'AEO23 Table 23'!$B$13:$AF$61,AI$1,FALSE)-(VLOOKUP($E18,'AEO23 Table 23'!$B$13:$AF$61,AH$1,FALSE)))/VLOOKUP($E18,'AEO23 Table 23'!$B$13:$AF$61,AH$1,FALSE),"") -> 0.0088785441
A19: ISIC 241 | B19: {=SUMPRODUCT(--('BLS Table 2.7'!$O:$O=$A19),'BLS Table 2.7'!L:L,'BLS Table 2.7'!N:N)/SUMIFS('BLS Table 2.7'!L:L,'BLS Table 2.7'!$O:$O,$A19)/100} -> 0.006 | E19: ISIC 241 | F19: =IFERROR(INDEX('AEO23 Table 23'!$AG$22:$AG$61,MATCH($E19,'AEO23 Table 23'!$B$22:$B$61,0)),"") -> 0.004802 | G19: =(INDEX('AEO23 Table 23'!$D$22:$D$61,MATCH('Growth Rates'!E19,'AEO23 Table 23'!$B$22:$B$61,0))-INDEX('AEO22 Table 23'!$D$22:$D$58,MATCH('Growth Rates'!E19,'AEO22 Table 23'!$B$22:$B$58,0)))/INDEX('AEO22 Table 23'!$D$22:$D$58,MATCH('Growth Rates'!E19,'AEO22 Table 23'!$B$22:$B$58,0)) -> 0.011938163 | H19: =IFERROR((VLOOKUP($E19,'AEO23 Table 23'!$B$13:$AF$61,H$1,FALSE)-(VLOOKUP($E19,'AEO23 Table 23'!$B$13:$AF$61,G$1,FALSE)))/VLOOKUP($E19,'AEO23 Table 23'!$B$13:$AF$61,G$1,FALSE),"") -> -0.016293577 | I19: =IFERROR((VLOOKUP($E19,'AEO23 Table 23'!$B$13:$AF$61,I$1,FALSE)-(VLOOKUP($E19,'AEO23 Table 23'!$B$13:$AF$61,H$1,FALSE)))/VLOOKUP($E19,'AEO23 Table 23'!$B$13:$AF$61,H$1,FALSE),"") -> -0.015440337 | J19: =IFERROR((VLOOKUP($E19,'AEO23 Table 23'!$B$13:$AF$61,J$1,FALSE)-(VLOOKUP($E19,'AEO23 Table 23'!$B$13:$AF$61,I$1,FALSE)))/VLOOKUP($E19,'AEO23 Table 23'!$B$13:$AF$61,I$1,FALSE),"") -> 0.022674474 | K19: =IFERROR((VLOOKUP($E19,'AEO23 Table 23'!$B$13:$AF$61,K$1,FALSE)-(VLOOKUP($E19,'AEO23 Table 23'!$B$13:$AF$61,J$1,FALSE)))/VLOOKUP($E19,'AEO23 Table 23'!$B$13:$AF$61,J$1,FALSE),"") -> 0.047757682 | L19: =IFERROR((VLOOKUP($E19,'AEO23 Table 23'!$B$13:$AF$61,L$1,FALSE)-(VLOOKUP($E19,'AEO23 Table 23'!$B$13:$AF$61,K$1,FALSE)))/VLOOKUP($E19,'AEO23 Table 23'!$B$13:$AF$61,K$1,FALSE),"") -> 0.023640194 | M19: =IFERROR((VLOOKUP($E19,'AEO23 Table 23'!$B$13:$AF$61,M$1,FALSE)-(VLOOKUP($E19,'AEO23 Table 23'!$B$13:$AF$61,L$1,FALSE)))/VLOOKUP($E19,'AEO23 Table 23'!$B$13:$AF$61,L$1,FALSE),"") -> 0.0054910528 | N19: =IFERROR((VLOOKUP($E19,'AEO23 Table 23'!$B$13:$AF$61,N$1,FALSE)-(VLOOKUP($E19,'AEO23 Table 23'!$B$13:$AF$61,M$1,FALSE)))/VLOOKUP($E19,'AEO23 Table 23'!$B$13:$AF$61,M$1,FALSE),"") -> 0.0049106234 | O19: =IFERROR((VLOOKUP($E19,'AEO23 Table 23'!$B$13:$AF$61,O$1,FALSE)-(VLOOKUP($E19,'AEO23 Table 23'!$B$13:$AF$61,N$1,FALSE)))/VLOOKUP($E19,'AEO23 Table 23'!$B$13:$AF$61,N$1,FALSE),"") -> -0.0054148813 | ... AI19: =IFERROR((VLOOKUP($E19,'AEO23 Table 23'!$B$13:$AF$61,AI$1,FALSE)-(VLOOKUP($E19,'AEO23 Table 23'!$B$13:$AF$61,AH$1,FALSE)))/VLOOKUP($E19,'AEO23 Table 23'!$B$13:$AF$61,AH$1,FALSE),"") -> 0.010141857
A20: ISIC 242 | B20: {=SUMPRODUCT(--('BLS Table 2.7'!$O:$O=$A20),'BLS Table 2.7'!L:L,'BLS Table 2.7'!N:N)/SUMIFS('BLS Table 2.7'!L:L,'BLS Table 2.7'!$O:$O,$A20)/100} -> 0.010326867 | E20: ISIC 242 | F20: =IFERROR(INDEX('AEO23 Table 23'!$AG$22:$AG$61,MATCH($E20,'AEO23 Table 23'!$B$22:$B$61,0)),"") -> 0.011116 | G20: =(INDEX('AEO23 Table 23'!$D$22:$D$61,MATCH('Growth Rates'!E20,'AEO23 Table 23'!$B$22:$B$61,0))-INDEX('AEO22 Table 23'!$D$22:$D$58,MATCH('Growth Rates'!E20,'AEO22 Table 23'!$B$22:$B$58,0)))/INDEX('AEO22 Table 23'!$D$22:$D$58,MATCH('Growth Rates'!E20,'AEO22 Table 23'!$B$22:$B$58,0)) -> 0.039616361 | H20: =IFERROR((VLOOKUP($E20,'AEO23 Table 23'!$B$13:$AF$61,H$1,FALSE)-(VLOOKUP($E20,'AEO23 Table 23'!$B$13:$AF$61,G$1,FALSE)))/VLOOKUP($E20,'AEO23 Table 23'!$B$13:$AF$61,G$1,FALSE),"") -> -0.012242674 | I20: =IFERROR((VLOOKUP($E20,'AEO23 Table 23'!$B$13:$AF$61,I$1,FALSE)-(VLOOKUP($E20,'AEO23 Table 23'!$B$13:$AF$61,H$1,FALSE)))/VLOOKUP($E20,'AEO23 Table 23'!$B$13:$AF$61,H$1,FALSE),"") -> 0.0060433727 | J20: =IFERROR((VLOOKUP($E20,'AEO23 Table 23'!$B$13:$AF$61,J$1,FALSE)-(VLOOKUP($E20,'AEO23 Table 23'!$B$13:$AF$61,I$1,FALSE)))/VLOOKUP($E20,'AEO23 Table 23'!$B$13:$AF$61,I$1,FALSE),"") -> 0.029090594 | K20: =IFERROR((VLOOKUP($E20,'AEO23 Table 23'!$B$13:$AF$61,K$1,FALSE)-(VLOOKUP($E20,'AEO23 Table 23'!$B$13:$AF$61,J$1,FALSE)))/VLOOKUP($E20,'AEO23 Table 23'!$B$13:$AF$61,J$1,FALSE),"") -> 0.032957149 | L20: =IFERROR((VLOOKUP($E20,'AEO23 Table 23'!$B$13:$AF$61,L$1,FALSE)-(VLOOKUP($E20,'AEO23 Table 23'!$B$13:$AF$61,K$1,FALSE)))/VLOOKUP($E20,'AEO23 Table 23'!$B$13:$AF$61,K$1,FALSE),"") -> 0.021340388 | M20: =IFERROR((VLOOKUP($E20,'AEO23 Table 23'!$B$13:$AF$61,M$1,FALSE)-(VLOOKUP($E20,'AEO23 Table 23'!$B$13:$AF$61,L$1,FALSE)))/VLOOKUP($E20,'AEO23 Table 23'!$B$13:$AF$61,L$1,FALSE),"") -> 0.014495421 | N20: =IFERROR((VLOOKUP($E20,'AEO23 Table 23'!$B$13:$AF$61,N$1,FALSE)-(VLOOKUP($E20,'AEO23 Table 23'!$B$13:$AF$61,M$1,FALSE)))/VLOOKUP($E20,'AEO23 Table 23'!$B$13:$AF$61,M$1,FALSE),"") -> 0.0077874337 | O20: =IFERROR((VLOOKUP($E20,'AEO23 Table 23'!$B$13:$AF$61,O$1,FALSE)-(VLOOKUP($E20,'AEO23 Table 23'!$B$13:$AF$61,N$1,FALSE)))/VLOOKUP($E20,'AEO23 Table 23'!$B$13:$AF$61,N$1,FALSE),"") -> 0.0024867313 | ... AI20: =IFERROR((VLOOKUP($E20,'AEO23 Table 23'!$B$13:$AF$61,AI$1,FALSE)-(VLOOKUP($E20,'AEO23 Table 23'!$B$13:$AF$61,AH$1,FALSE)))/VLOOKUP($E20,'AEO23 Table 23'!$B$13:$AF$61,AH$1,FALSE),"") -> 0.015067396
A21: ISIC 25 | B21: {=SUMPRODUCT(--('BLS Table 2.7'!$O:$O=$A21),'BLS Table 2.7'!L:L,'BLS Table 2.7'!N:N)/SUMIFS('BLS Table 2.7'!L:L,'BLS Table 2.7'!$O:$O,$A21)/100} -> 0.011 | E21: ISIC 25 | F21: =IFERROR(INDEX('AEO23 Table 23'!$AG$22:$AG$61,MATCH($E21,'AEO23 Table 23'!$B$22:$B$61,0)),"") -> 0.012756 | G21: =(INDEX('AEO23 Table 23'!$D$22:$D$61,MATCH('Growth Rates'!E21,'AEO23 Table 23'!$B$22:$B$61,0))-INDEX('AEO22 Table 23'!$D$22:$D$58,MATCH('Growth Rates'!E21,'AEO22 Table 23'!$B$22:$B$58,0)))/INDEX('AEO22 Table 23'!$D$22:$D$58,MATCH('Growth Rates'!E21,'AEO22 Table 23'!$B$22:$B$58,0)) -> 0.013208161 | H21: =IFERROR((VLOOKUP($E21,'AEO23 Table 23'!$B$13:$AF$61,H$1,FALSE)-(VLOOKUP($E21,'AEO23 Table 23'!$B$13:$AF$61,G$1,FALSE)))/VLOOKUP($E21,'AEO23 Table 23'!$B$13:$AF$61,G$1,FALSE),"") -> -0.019358653 | I21: =IFERROR((VLOOKUP($E21,'AEO23 Table 23'!$B$13:$AF$61,I$1,FALSE)-(VLOOKUP($E21,'AEO23 Table 23'!$B$13:$AF$61,H$1,FALSE)))/VLOOKUP($E21,'AEO23 Table 23'!$B$13:$AF$61,H$1,FALSE),"") -> -0.0073700973 | J21: =IFERROR((VLOOKUP($E21,'AEO23 Table 23'!$B$13:$AF$61,J$1,FALSE)-(VLOOKUP($E21,'AEO23 Table 23'!$B$13:$AF$61,I$1,FALSE)))/VLOOKUP($E21,'AEO23 Table 23'!$B$13:$AF$61,I$1,FALSE),"") -> 0.018394084 | K21: =IFERROR((VLOOKUP($E21,'AEO23 Table 23'!$B$13:$AF$61,K$1,FALSE)-(VLOOKUP($E21,'AEO23 Table 23'!$B$13:$AF$61,J$1,FALSE)))/VLOOKUP($E21,'AEO23 Table 23'!$B$13:$AF$61,J$1,FALSE),"") -> 0.032985153 | L21: =IFERROR((VLOOKUP($E21,'AEO23 Table 23'!$B$13:$AF$61,L$1,FALSE)-(VLOOKUP($E21,'AEO23 Table 23'!$B$13:$AF$61,K$1,FALSE)))/VLOOKUP($E21,'AEO23 Table 23'!$B$13:$AF$61,K$1,FALSE),"") -> 0.026959938 | M21: =IFERROR((VLOOKUP($E21,'AEO23 Table 23'!$B$13:$AF$61,M$1,FALSE)-(VLOOKUP($E21,'AEO23 Table 23'!$B$13:$AF$61,L$1,FALSE)))/VLOOKUP($E21,'AEO23 Table 23'!$B$13:$AF$61,L$1,FALSE),"") -> 0.015362876 | N21: =IFERROR((VLOOKUP($E21,'AEO23 Table 23'!$B$13:$AF$61,N$1,FALSE)-(VLOOKUP($E21,'AEO23 Table 23'!$B$13:$AF$61,M$1,FALSE)))/VLOOKUP($E21,'AEO23 Table 23'!$B$13:$AF$61,M$1,FALSE),"") -> 0.011581834 | O21: =IFERROR((VLOOKUP($E21,'AEO23 Table 23'!$B$13:$AF$61,O$1,FALSE)-(VLOOKUP($E21,'AEO23 Table 23'!$B$13:$AF$61,N$1,FALSE)))/VLOOKUP($E21,'AEO23 Table 23'!$B$13:$AF$61,N$1,FALSE),"") -> 0.0070966833 | ... AI21: =IFERROR((VLOOKUP($E21,'AEO23 Table 23'!$B$13:$AF$61,AI$1,FALSE)-(VLOOKUP($E21,'AEO23 Table 23'!$B$13:$AF$61,AH$1,FALSE)))/VLOOKUP($E21,'AEO23 Table 23'!$B$13:$AF$61,AH$1,FALSE),"") -> 0.014245792
A22: ISIC 26 | B22: {=SUMPRODUCT(--('BLS Table 2.7'!$O:$O=$A22),'BLS Table 2.7'!L:L,'BLS Table 2.7'!N:N)/SUMIFS('BLS Table 2.7'!L:L,'BLS Table 2.7'!$O:$O,$A22)/100} -> 0.016 | E22: ISIC 26 | F22: =IFERROR(INDEX('AEO23 Table 23'!$AG$22:$AG$61,MATCH($E22,'AEO23 Table 23'!$B$22:$B$61,0)),"") -> 0.024376 | G22: =(INDEX('AEO23 Table 23'!$D$22:$D$61,MATCH('Growth Rates'!E22,'AEO23 Table 23'!$B$22:$B$61,0))-INDEX('AEO22 Table 23'!$D$22:$D$58,MATCH('Growth Rates'!E22,'AEO22 Table 23'!$B$22:$B$58,0)))/INDEX('AEO22 Table 23'!$D$22:$D$58,MATCH('Growth Rates'!E22,'AEO22 Table 23'!$B$22:$B$58,0)) -> 0.052842005 | H22: =IFERROR((VLOOKUP($E22,'AEO23 Table 23'!$B$13:$AF$61,H$1,FALSE)-(VLOOKUP($E22,'AEO23 Table 23'!$B$13:$AF$61,G$1,FALSE)))/VLOOKUP($E22,'AEO23 Table 23'!$B$13:$AF$61,G$1,FALSE),"") -> 0.019620955 | I22: =IFERROR((VLOOKUP($E22,'AEO23 Table 23'!$B$13:$AF$61,I$1,FALSE)-(VLOOKUP($E22,'AEO23 Table 23'!$B$13:$AF$61,H$1,FALSE)))/VLOOKUP($E22,'AEO23 Table 23'!$B$13:$AF$61,H$1,FALSE),"") -> 0.031824681 | J22: =IFERROR((VLOOKUP($E22,'AEO23 Table 23'!$B$13:$AF$61,J$1,FALSE)-(VLOOKUP($E22,'AEO23 Table 23'!$B$13:$AF$61,I$1,FALSE)))/VLOOKUP($E22,'AEO23 Table 23'!$B$13:$AF$61,I$1,FALSE),"") -> 0.03923558 | K22: =IFERROR((VLOOKUP($E22,'AEO23 Table 23'!$B$13:$AF$61,K$1,FALSE)-(VLOOKUP($E22,'AEO23 Table 23'!$B$13:$AF$61,J$1,FALSE)))/VLOOKUP($E22,'AEO23 Table 23'!$B$13:$AF$61,J$1,FALSE),"") -> 0.042408415 | L22: =IFERROR((VLOOKUP($E22,'AEO23 Table 23'!$B$13:$AF$61,L$1,FALSE)-(VLOOKUP($E22,'AEO23 Table 23'!$B$13:$AF$61,K$1,FALSE)))/VLOOKUP($E22,'AEO23 Table 23'!$B$13:$AF$61,K$1,FALSE),"") -> 0.034834472 | M22: =IFERROR((VLOOKUP($E22,'AEO23 Table 23'!$B$13:$AF$61,M$1,FALSE)-(VLOOKUP($E22,'AEO23 Table 23'!$B$13:$AF$61,L$1,FALSE)))/VLOOKUP($E22,'AEO23 Table 23'!$B$13:$AF$61,L$1,FALSE),"") -> 0.028984244 | N22: =IFERROR((VLOOKUP($E22,'AEO23 Table 23'!$B$13:$AF$61,N$1,FALSE)-(VLOOKUP($E22,'AEO23 Table 23'!$B$13:$AF$61,M$1,FALSE)))/VLOOKUP($E22,'AEO23 Table 23'!$B$13:$AF$61,M$1,FALSE),"") -> 0.02121898 | O22: =IFERROR((VLOOKUP($E22,'AEO23 Table 23'!$B$13:$AF$61,O$1,FALSE)-(VLOOKUP($E22,'AEO23 Table 23'!$B$13:$AF$61,N$1,FALSE)))/VLOOKUP($E22,'AEO23 Table 23'!$B$13:$AF$61,N$1,FALSE),"") -> 0.015338104 | ... AI22: =IFERROR((VLOOKUP($E22,'AEO23 Table 23'!$B$13:$AF$61,AI$1,FALSE)-(VLOOKUP($E22,'AEO23 Table 23'!$B$13:$AF$61,AH$1,FALSE)))/VLOOKUP($E22,'AEO23 Table 23'!$B$13:$AF$61,AH$1,FALSE),"") -> 0.024012367
A23: ISIC 27 | B23: {=SUMPRODUCT(--('BLS Table 2.7'!$O:$O=$A23),'BLS Table 2.7'!L:L,'BLS Table 2.7'!N:N)/SUMIFS('BLS Table 2.7'!L:L,'BLS Table 2.7'!$O:$O,$A23)/100} -> 0.01 | E23: ISIC 27 | F23: =IFERROR(INDEX('AEO23 Table 23'!$AG$22:$AG$61,MATCH($E23,'AEO23 Table 23'!$B$22:$B$61,0)),"") -> 0.022804 | G23: =(INDEX('AEO23 Table 23'!$D$22:$D$61,MATCH('Growth Rates'!E23,'AEO23 Table 23'!$B$22:$B$61,0))-INDEX('AEO22 Table 23'!$D$22:$D$58,MATCH('Growth Rates'!E23,'AEO22 Table 23'!$B$22:$B$58,0)))/INDEX('AEO22 Table 23'!$D$22:$D$58,MATCH('Growth Rates'!E23,'AEO22 Table 23'!$B$22:$B$58,0)) -> 0.027897917 | H23: =IFERROR((VLOOKUP($E23,'AEO23 Table 23'!$B$13:$AF$61,H$1,FALSE)-(VLOOKUP($E23,'AEO23 Table 23'!$B$13:$AF$61,G$1,FALSE)))/VLOOKUP($E23,'AEO23 Table 23'!$B$13:$AF$61,G$1,FALSE),"") -> -0.00042399646 | I23: =IFERROR((VLOOKUP($E23,'AEO23 Table 23'!$B$13:$AF$61,I$1,FALSE)-(VLOOKUP($E23,'AEO23 Table 23'!$B$13:$AF$61,H$1,FALSE)))/VLOOKUP($E23,'AEO23 Table 23'!$B$13:$AF$61,H$1,FALSE),"") -> 0.011130999 | J23: =IFERROR((VLOOKUP($E23,'AEO23 Table 23'!$B$13:$AF$61,J$1,FALSE)-(VLOOKUP($E23,'AEO23 Table 23'!$B$13:$AF$61,I$1,FALSE)))/VLOOKUP($E23,'AEO23 Table 23'!$B$13:$AF$61,I$1,FALSE),"") -> 0.024032641 | K23: =IFERROR((VLOOKUP($E23,'AEO23 Table 23'!$B$13:$AF$61,K$1,FALSE)-(VLOOKUP($E23,'AEO23 Table 23'!$B$13:$AF$61,J$1,FALSE)))/VLOOKUP($E23,'AEO23 Table 23'!$B$13:$AF$61,J$1,FALSE),"") -> 0.02381564 | L23: =IFERROR((VLOOKUP($E23,'AEO23 Table 23'!$B$13:$AF$61,L$1,FALSE)-(VLOOKUP($E23,'AEO23 Table 23'!$B$13:$AF$61,K$1,FALSE)))/VLOOKUP($E23,'AEO23 Table 23'!$B$13:$AF$61,K$1,FALSE),"") -> 0.021410755 | M23: =IFERROR((VLOOKUP($E23,'AEO23 Table 23'!$B$13:$AF$61,M$1,FALSE)-(VLOOKUP($E23,'AEO23 Table 23'!$B$13:$AF$61,L$1,FALSE)))/VLOOKUP($E23,'AEO23 Table 23'!$B$13:$AF$61,L$1,FALSE),"") -> 0.018612395 | N23: =IFERROR((VLOOKUP($E23,'AEO23 Table 23'!$B$13:$AF$61,N$1,FALSE)-(VLOOKUP($E23,'AEO23 Table 23'!$B$13:$AF$61,M$1,FALSE)))/VLOOKUP($E23,'AEO23 Table 23'!$B$13:$AF$61,M$1,FALSE),"") -> 0.015370941 | O23: =IFERROR((VLOOKUP($E23,'AEO23 Table 23'!$B$13:$AF$61,O$1,FALSE)-(VLOOKUP($E23,'AEO23 Table 23'!$B$13:$AF$61,N$1,FALSE)))/VLOOKUP($E23,'AEO23 Table 23'!$B$13:$AF$61,N$1,FALSE),"") -> 0.01263745 | ... AI23: =IFERROR((VLOOKUP($E23,'AEO23 Table 23'!$B$13:$AF$61,AI$1,FALSE)-(VLOOKUP($E23,'AEO23 Table 23'!$B$13:$AF$61,AH$1,FALSE)))/VLOOKUP($E23,'AEO23 Table 23'!$B$13:$AF$61,AH$1,FALSE),"") -> 0.028127201
A24: ISIC 28 | B24: {=SUMPRODUCT(--('BLS Table 2.7'!$O:$O=$A24),'BLS Table 2.7'!L:L,'BLS Table 2.7'!N:N)/SUMIFS('BLS Table 2.7'!L:L,'BLS Table 2.7'!$O:$O,$A24)/100} -> 0.015 | E24: ISIC 28 | F24: =IFERROR(INDEX('AEO23 Table 23'!$AG$22:$AG$61,MATCH($E24,'AEO23 Table 23'!$B$22:$B$61,0)),"") -> 0.013747 | G24: =(INDEX('AEO23 Table 23'!$D$22:$D$61,MATCH('Growth Rates'!E24,'AEO23 Table 23'!$B$22:$B$61,0))-INDEX('AEO22 Table 23'!$D$22:$D$58,MATCH('Growth Rates'!E24,'AEO22 Table 23'!$B$22:$B$58,0)))/INDEX('AEO22 Table 23'!$D$22:$D$58,MATCH('Growth Rates'!E24,'AEO22 Table 23'!$B$22:$B$58,0)) -> 0.027819565 | H24: =IFERROR((VLOOKUP($E24,'AEO23 Table 23'!$B$13:$AF$61,H$1,FALSE)-(VLOOKUP($E24,'AEO23 Table 23'!$B$13:$AF$61,G$1,FALSE)))/VLOOKUP($E24,'AEO23 Table 23'!$B$13:$AF$61,G$1,FALSE),"") -> -0.015137824 | I24: =IFERROR((VLOOKUP($E24,'AEO23 Table 23'!$B$13:$AF$61,I$1,FALSE)-(VLOOKUP($E24,'AEO23 Table 23'!$B$13:$AF$61,H$1,FALSE)))/VLOOKUP($E24,'AEO23 Table 23'!$B$13:$AF$61,H$1,FALSE),"") -> 0.00061568328 | J24: =IFERROR((VLOOKUP($E24,'AEO23 Table 23'!$B$13:$AF$61,J$1,FALSE)-(VLOOKUP($E24,'AEO23 Table 23'!$B$13:$AF$61,I$1,FALSE)))/VLOOKUP($E24,'AEO23 Table 23'!$B$13:$AF$61,I$1,FALSE),"") -> 0.012153635 | K24: =IFERROR((VLOOKUP($E24,'AEO23 Table 23'!$B$13:$AF$61,K$1,FALSE)-(VLOOKUP($E24,'AEO23 Table 23'!$B$13:$AF$61,J$1,FALSE)))/VLOOKUP($E24,'AEO23 Table 23'!$B$13:$AF$61,J$1,FALSE),"") -> 0.036657504 | L24: =IFERROR((VLOOKUP($E24,'AEO23 Table 23'!$B$13:$AF$61,L$1,FALSE)-(VLOOKUP($E24,'AEO23 Table 23'!$B$13:$AF$61,K$1,FALSE)))/VLOOKUP($E24,'AEO23 Table 23'!$B$13:$AF$61,K$1,FALSE),"") -> 0.031121899 | M24: =IFERROR((VLOOKUP($E24,'AEO23 Table 23'!$B$13:$AF$61,M$1,FALSE)-(VLOOKUP($E24,'AEO23 Table 23'!$B$13:$AF$61,L$1,FALSE)))/VLOOKUP($E24,'AEO23 Table 23'!$B$13:$AF$61,L$1,FALSE),"") -> 0.013049016 | N24: =IFERROR((VLOOKUP($E24,'AEO23 Table 23'!$B$13:$AF$61,N$1,FALSE)-(VLOOKUP($E24,'AEO23 Table 23'!$B$13:$AF$61,M$1,FALSE)))/VLOOKUP($E24,'AEO23 Table 23'!$B$13:$AF$61,M$1,FALSE),"") -> 0.011252962 | O24: =IFERROR((VLOOKUP($E24,'AEO23 Table 23'!$B$13:$AF$61,O$1,FALSE)-(VLOOKUP($E24,'AEO23 Table 23'!$B$13:$AF$61,N$1,FALSE)))/VLOOKUP($E24,'AEO23 Table 23'!$B$13:$AF$61,N$1,FALSE),"") -> 0.011237653 | ... AI24: =IFERROR((VLOOKUP($E24,'AEO23 Table 23'!$B$13:$AF$61,AI$1,FALSE)-(VLOOKUP($E24,'AEO23 Table 23'!$B$13:$AF$61,AH$1,FALSE)))/VLOOKUP($E24,'AEO23 Table 23'!$B$13:$AF$61,AH$1,FALSE),"") -> 0.013845914
A25: ISIC 29 | B25: {=SUMPRODUCT(--('BLS Table 2.7'!$O:$O=$A25),'BLS Table 2.7'!L:L,'BLS Table 2.7'!N:N)/SUMIFS('BLS Table 2.7'!L:L,'BLS Table 2.7'!$O:$O,$A25)/100} -> 0.018032437 | E25: ISIC 29, ISIC 30 | F25: =IFERROR(INDEX('AEO23 Table 23'!$AG$22:$AG$61,MATCH($E25,'AEO23 Table 23'!$B$22:$B$61,0)),"") -> 0.014344 | G25: =(INDEX('AEO23 Table 23'!$D$22:$D$61,MATCH('Growth Rates'!E25,'AEO23 Table 23'!$B$22:$B$61,0))-INDEX('AEO22 Table 23'!$D$22:$D$58,MATCH('Growth Rates'!E25,'AEO22 Table 23'!$B$22:$B$58,0)))/INDEX('AEO22 Table 23'!$D$22:$D$58,MATCH('Growth Rates'!E25,'AEO22 Table 23'!$B$22:$B$58,0)) -> 0.028290026 | H25: =IFERROR((VLOOKUP($E25,'AEO23 Table 23'!$B$13:$AF$61,H$1,FALSE)-(VLOOKUP($E25,'AEO23 Table 23'!$B$13:$AF$61,G$1,FALSE)))/VLOOKUP($E25,'AEO23 Table 23'!$B$13:$AF$61,G$1,FALSE),"") -> 0.031107246 | I25: =IFERROR((VLOOKUP($E25,'AEO23 Table 23'!$B$13:$AF$61,I$1,FALSE)-(VLOOKUP($E25,'AEO23 Table 23'!$B$13:$AF$61,H$1,FALSE)))/VLOOKUP($E25,'AEO23 Table 23'!$B$13:$AF$61,H$1,FALSE),"") -> 0.012544625 | J25: =IFERROR((VLOOKUP($E25,'AEO23 Table 23'!$B$13:$AF$61,J$1,FALSE)-(VLOOKUP($E25,'AEO23 Table 23'!$B$13:$AF$61,I$1,FALSE)))/VLOOKUP($E25,'AEO23 Table 23'!$B$13:$AF$61,I$1,FALSE),"") -> -0.0029244404 | K25: =IFERROR((VLOOKUP($E25,'AEO23 Table 23'!$B$13:$AF$61,K$1,FALSE)-(VLOOKUP($E25,'AEO23 Table 23'!$B$13:$AF$61,J$1,FALSE)))/VLOOKUP($E25,'AEO23 Table 23'!$B$13:$AF$61,J$1,FALSE),"") -> 0.005205824 | L25: =IFERROR((VLOOKUP($E25,'AEO23 Table 23'!$B$13:$AF$61,L$1,FALSE)-(VLOOKUP($E25,'AEO23 Table 23'!$B$13:$AF$61,K$1,FALSE)))/VLOOKUP($E25,'AEO23 Table 23'!$B$13:$AF$61,K$1,FALSE),"") -> 0.018574672 | M25: =IFERROR((VLOOKUP($E25,'AEO23 Table 23'!$B$13:$AF$61,M$1,FALSE)-(VLOOKUP($E25,'AEO23 Table 23'!$B$13:$AF$61,L$1,FALSE)))/VLOOKUP($E25,'AEO23 Table 23'!$B$13:$AF$61,L$1,FALSE),"") -> 0.013662341 | N25: =IFERROR((VLOOKUP($E25,'AEO23 Table 23'!$B$13:$AF$61,N$1,FALSE)-(VLOOKUP($E25,'AEO23 Table 23'!$B$13:$AF$61,M$1,FALSE)))/VLOOKUP($E25,'AEO23 Table 23'!$B$13:$AF$61,M$1,FALSE),"") -> 0.0065047579 | O25: =IFERROR((VLOOKUP($E25,'AEO23 Table 23'!$B$13:$AF$61,O$1,FALSE)-(VLOOKUP($E25,'AEO23 Table 23'!$B$13:$AF$61,N$1,FALSE)))/VLOOKUP($E25,'AEO23 Table 23'!$B$13:$AF$61,N$1,FALSE),"") -> 0.008718746 | ... AI25: =IFERROR((VLOOKUP($E25,'AEO23 Table 23'!$B$13:$AF$61,AI$1,FALSE)-(VLOOKUP($E25,'AEO23 Table 23'!$B$13:$AF$61,AH$1,FALSE)))/VLOOKUP($E25,'AEO23 Table 23'!$B$13:$AF$61,AH$1,FALSE),"") -> 0.016845152
A26: ISIC 30 | B26: {=SUMPRODUCT(--('BLS Table 2.7'!$O:$O=$A26),'BLS Table 2.7'!L:L,'BLS Table 2.7'!N:N)/SUMIFS('BLS Table 2.7'!L:L,'BLS Table 2.7'!$O:$O,$A26)/100} -> 0.019602007 | E26: ISIC 29, ISIC 30 | F26: =IFERROR(INDEX('AEO23 Table 23'!$AG$22:$AG$61,MATCH($E26,'AEO23 Table 23'!$B$22:$B$61,0)),"") -> 0.014344 | G26: =(INDEX('AEO23 Table 23'!$D$22:$D$61,MATCH('Growth Rates'!E26,'AEO23 Table 23'!$B$22:$B$61,0))-INDEX('AEO22 Table 23'!$D$22:$D$58,MATCH('Growth Rates'!E26,'AEO22 Table 23'!$B$22:$B$58,0)))/INDEX('AEO22 Table 23'!$D$22:$D$58,MATCH('Growth Rates'!E26,'AEO22 Table 23'!$B$22:$B$58,0)) -> 0.028290026 | H26: =IFERROR((VLOOKUP($E26,'AEO23 Table 23'!$B$13:$AF$61,H$1,FALSE)-(VLOOKUP($E26,'AEO23 Table 23'!$B$13:$AF$61,G$1,FALSE)))/VLOOKUP($E26,'AEO23 Table 23'!$B$13:$AF$61,G$1,FALSE),"") -> 0.031107246 | I26: =IFERROR((VLOOKUP($E26,'AEO23 Table 23'!$B$13:$AF$61,I$1,FALSE)-(VLOOKUP($E26,'AEO23 Table 23'!$B$13:$AF$61,H$1,FALSE)))/VLOOKUP($E26,'AEO23 Table 23'!$B$13:$AF$61,H$1,FALSE),"") -> 0.012544625 | J26: =IFERROR((VLOOKUP($E26,'AEO23 Table 23'!$B$13:$AF$61,J$1,FALSE)-(VLOOKUP($E26,'AEO23 Table 23'!$B$13:$AF$61,I$1,FALSE)))/VLOOKUP($E26,'AEO23 Table 23'!$B$13:$AF$61,I$1,FALSE),"") -> -0.0029244404 | K26: =IFERROR((VLOOKUP($E26,'AEO23 Table 23'!$B$13:$AF$61,K$1,FALSE)-(VLOOKUP($E26,'AEO23 Table 23'!$B$13:$AF$61,J$1,FALSE)))/VLOOKUP($E26,'AEO23 Table 23'!$B$13:$AF$61,J$1,FALSE),"") -> 0.005205824 | L26: =IFERROR((VLOOKUP($E26,'AEO23 Table 23'!$B$13:$AF$61,L$1,FALSE)-(VLOOKUP($E26,'AEO23 Table 23'!$B$13:$AF$61,K$1,FALSE)))/VLOOKUP($E26,'AEO23 Table 23'!$B$13:$AF$61,K$1,FALSE),"") -> 0.018574672 | M26: =IFERROR((VLOOKUP($E26,'AEO23 Table 23'!$B$13:$AF$61,M$1,FALSE)-(VLOOKUP($E26,'AEO23 Table 23'!$B$13:$AF$61,L$1,FALSE)))/VLOOKUP($E26,'AEO23 Table 23'!$B$13:$AF$61,L$1,FALSE),"") -> 0.013662341 | N26: =IFERROR((VLOOKUP($E26,'AEO23 Table 23'!$B$13:$AF$61,N$1,FALSE)-(VLOOKUP($E26,'AEO23 Table 23'!$B$13:$AF$61,M$1,FALSE)))/VLOOKUP($E26,'AEO23 Table 23'!$B$13:$AF$61,M$1,FALSE),"") -> 0.0065047579 | O26: =IFERROR((VLOOKUP($E26,'AEO23 Table 23'!$B$13:$AF$61,O$1,FALSE)-(VLOOKUP($E26,'AEO23 Table 23'!$B$13:$AF$61,N$1,FALSE)))/VLOOKUP($E26,'AEO23 Table 23'!$B$13:$AF$61,N$1,FALSE),"") -> 0.008718746 | ... AI26: =IFERROR((VLOOKUP($E26,'AEO23 Table 23'!$B$13:$AF$61,AI$1,FALSE)-(VLOOKUP($E26,'AEO23 Table 23'!$B$13:$AF$61,AH$1,FALSE)))/VLOOKUP($E26,'AEO23 Table 23'!$B$13:$AF$61,AH$1,FALSE),"") -> 0.016845152
A27: ISIC 31T33 | B27: {=SUMPRODUCT(--('BLS Table 2.7'!$O:$O=$A27),'BLS Table 2.7'!L:L,'BLS Table 2.7'!N:N)/SUMIFS('BLS Table 2.7'!L:L,'BLS Table 2.7'!$O:$O,$A27)/100} -> 0.014107993 | E27: ISIC 31T33 | F27: =IFERROR(INDEX('AEO23 Table 23'!$AG$22:$AG$61,MATCH($E27,'AEO23 Table 23'!$B$22:$B$61,0)),"") -> 0.013252 | G27: =(INDEX('AEO23 Table 23'!$D$22:$D$61,MATCH('Growth Rates'!E27,'AEO23 Table 23'!$B$22:$B$61,0))-INDEX('AEO22 Table 23'!$D$22:$D$58,MATCH('Growth Rates'!E27,'AEO22 Table 23'!$B$22:$B$58,0)))/INDEX('AEO22 Table 23'!$D$22:$D$58,MATCH('Growth Rates'!E27,'AEO22 Table 23'!$B$22:$B$58,0)) -> -0.0019964133 | H27: =IFERROR((VLOOKUP($E27,'AEO23 Table 23'!$B$13:$AF$61,H$1,FALSE)-(VLOOKUP($E27,'AEO23 Table 23'!$B$13:$AF$61,G$1,FALSE)))/VLOOKUP($E27,'AEO23 Table 23'!$B$13:$AF$61,G$1,FALSE),"") -> -0.014094172 | I27: =IFERROR((VLOOKUP($E27,'AEO23 Table 23'!$B$13:$AF$61,I$1,FALSE)-(VLOOKUP($E27,'AEO23 Table 23'!$B$13:$AF$61,H$1,FALSE)))/VLOOKUP($E27,'AEO23 Table 23'!$B$13:$AF$61,H$1,FALSE),"") -> 0.0020814978 | J27: =IFERROR((VLOOKUP($E27,'AEO23 Table 23'!$B$13:$AF$61,J$1,FALSE)-(VLOOKUP($E27,'AEO23 Table 23'!$B$13:$AF$61,I$1,FALSE)))/VLOOKUP($E27,'AEO23 Table 23'!$B$13:$AF$61,I$1,FALSE),"") -> 0.00556703 | K27: =IFERROR((VLOOKUP($E27,'AEO23 Table 23'!$B$13:$AF$61,K$1,FALSE)-(VLOOKUP($E27,'AEO23 Table 23'!$B$13:$AF$61,J$1,FALSE)))/VLOOKUP($E27,'AEO23 Table 23'!$B$13:$AF$61,J$1,FALSE),"") -> 0.024824392 | L27: =IFERROR((VLOOKUP($E27,'AEO23 Table 23'!$B$13:$AF$61,L$1,FALSE)-(VLOOKUP($E27,'AEO23 Table 23'!$B$13:$AF$61,K$1,FALSE)))/VLOOKUP($E27,'AEO23 Table 23'!$B$13:$AF$61,K$1,FALSE),"") -> 0.026832546 | M27: =IFERROR((VLOOKUP($E27,'AEO23 Table 23'!$B$13:$AF$61,M$1,FALSE)-(VLOOKUP($E27,'AEO23 Table 23'!$B$13:$AF$61,L$1,FALSE)))/VLOOKUP($E27,'AEO23 Table 23'!$B$13:$AF$61,L$1,FALSE),"") -> 0.011196657 | N27: =IFERROR((VLOOKUP($E27,'AEO23 Table 23'!$B$13:$AF$61,N$1,FALSE)-(VLOOKUP($E27,'AEO23 Table 23'!$B$13:$AF$61,M$1,FALSE)))/VLOOKUP($E27,'AEO23 Table 23'!$B$13:$AF$61,M$1,FALSE),"") -> 0.011609384 | O27: =IFERROR((VLOOKUP($E27,'AEO23 Table 23'!$B$13:$AF$61,O$1,FALSE)-(VLOOKUP($E27,'AEO23 Table 23'!$B$13:$AF$61,N$1,FALSE)))/VLOOKUP($E27,'AEO23 Table 23'!$B$13:$AF$61,N$1,FALSE),"") -> 0.009945305 | ... AI27: =IFERROR((VLOOKUP($E27,'AEO23 Table 23'!$B$13:$AF$61,AI$1,FALSE)-(VLOOKUP($E27,'AEO23 Table 23'!$B$13:$AF$61,AH$1,FALSE)))/VLOOKUP($E27,'AEO23 Table 23'!$B$13:$AF$61,AH$1,FALSE),"") -> 0.029332026
